{
  "type": "Feature",
  "properties": {
    "gn:admin1_code":"30.0",
    "gn:asciiname":"Mlayon",
    "gn:country_code":"ID",
    "gn:dem":27,
    "gn:feature_class":"P",
    "gn:feature_code":"PPL",
    "gn:name":"Mlayon",
    "gn:population":0,
    "gn:timezone":"Asia/Jakarta",
    "iso:country":"ID",
    "name:ind_x_preferred":[
        "Mlayon"
    ],
    "wof:name":"Mlayon",
    "wof:placetype":"locality"
},
  "geometry": {"coordinates":[108.44556,-6.72083],"type":"Point"}
}