{
  "type": "Feature",
  "properties": {
    "gn:admin1_code":"17",
    "gn:asciiname":"Embungsempait Bat",
    "gn:country_code":"ID",
    "gn:dem":183,
    "gn:feature_class":"P",
    "gn:feature_code":"PPL",
    "gn:name":"Embungsempait Bat",
    "gn:population":0,
    "gn:timezone":"Asia/Makassar",
    "iso:country":"ID",
    "name:ind_x_preferred":[
        "Embungsempait Bat"
    ],
    "wof:name":"Embungsempait Bat",
    "wof:placetype":"locality"
},
  "geometry": {"coordinates":[116.4992,-8.6764],"type":"Point"}
}