{
  "type": "Feature",
  "properties": {
    "gn:admin1_code":"22",
    "gn:asciiname":"Puulemo",
    "gn:country_code":"ID",
    "gn:dem":14,
    "gn:feature_class":"P",
    "gn:feature_code":"PPL",
    "gn:name":"Puulemo",
    "gn:population":0,
    "gn:timezone":"Asia/Makassar",
    "iso:country":"ID",
    "name:ind_x_preferred":[
        "Puulemo"
    ],
    "wof:name":"Puulemo",
    "wof:placetype":"locality"
},
  "geometry": {"coordinates":[122.7715,-4.1572],"type":"Point"}
}