{
  "type": "Feature",
  "properties": {
    "gn:admin1_code":"08",
    "gn:asciiname":"Lebak",
    "gn:country_code":"ID",
    "gn:dem":7,
    "gn:feature_class":"P",
    "gn:feature_code":"PPL",
    "gn:name":"Lebak",
    "gn:population":0,
    "gn:timezone":"Asia/Jakarta",
    "iso:country":"ID",
    "name:ceb_x_preferred":[
        "Lebak"
    ],
    "name:fra_x_preferred":[
        "Lebak"
    ],
    "name:ind_x_preferred":[
        "Lebak"
    ],
    "name:ita_x_preferred":[
        "Lebak"
    ],
    "name:nld_x_preferred":[
        "Lebak"
    ],
    "name:sun_x_preferred":[
        "Lebak"
    ],
    "name:swe_x_preferred":[
        "Lebak"
    ],
    "name:und_x_variant":[
        "Lebak 2",
        "Lebak Dua"
    ],
    "wof:lang_x_official":[
        "ind"
    ],
    "wof:lang_x_spoken":[
        "ind",
        "eng"
    ],
    "wof:name":"Lebak",
    "wof:placetype":"locality"
},
  "geometry": {"coordinates":[112.58920000000001,-7.0483],"type":"Point"}
}