{
  "type": "Feature",
  "properties": {
    "gn:admin1_code":"7.0",
    "gn:asciiname":"Batan",
    "gn:country_code":"ID",
    "gn:dem":581,
    "gn:feature_class":"P",
    "gn:feature_code":"PPL",
    "gn:name":"Batan",
    "gn:population":0,
    "gn:timezone":"Asia/Jakarta",
    "iso:country":"ID",
    "name:ceb_x_preferred":[
        "Batan"
    ],
    "name:deu_x_preferred":[
        "Batan"
    ],
    "name:fra_x_preferred":[
        "Batan"
    ],
    "name:ilo_x_preferred":[
        "Batan"
    ],
    "name:ita_x_preferred":[
        "Batan"
    ],
    "name:nld_x_preferred":[
        "Batan"
    ],
    "name:pol_x_preferred":[
        "Batan"
    ],
    "name:rus_x_preferred":[
        "\u0411\u0430\u0442\u0430\u043d"
    ],
    "name:spa_x_preferred":[
        "Bat\u00e1n"
    ],
    "name:swe_x_preferred":[
        "Batan"
    ],
    "name:ukr_x_preferred":[
        "\u0411\u0430\u0442\u0430\u043d"
    ],
    "wof:lang_x_official":[
        "ind"
    ],
    "wof:lang_x_spoken":[
        "ind",
        "eng"
    ],
    "wof:name":"Batan",
    "wof:placetype":"locality"
},
  "geometry": {"coordinates":[110.18000000000001,-7.31278],"type":"Point"}
}