{
  "type": "Feature",
  "properties": {
    "gn:admin1_code":"2",
    "gn:asciiname":"Banjar Tempekkelahan",
    "gn:country_code":"ID",
    "gn:dem":972,
    "gn:feature_class":"P",
    "gn:feature_code":"PPL",
    "gn:name":"Banjar Tempekkelahan",
    "gn:population":0,
    "gn:timezone":"Asia/Makassar",
    "iso:country":"ID",
    "name:ind_x_preferred":[
        "Banjar Tempekkelahan"
    ],
    "wof:name":"Banjar Tempekkelahan",
    "wof:placetype":"locality"
},
  "geometry": {"coordinates":[115.3194,-8.329],"type":"Point"}
}