{
  "type": "Feature",
  "properties": {
    "gn:admin1_code":"15.0",
    "gn:asciiname":"Tanjungbaru",
    "gn:country_code":"ID",
    "gn:dem":703,
    "gn:feature_class":"P",
    "gn:feature_code":"PPL",
    "gn:name":"Tanjungbaru",
    "gn:population":0,
    "gn:timezone":"Asia/Jakarta",
    "iso:country":"ID",
    "name:ind_x_preferred":[
        "Tanjungbaru"
    ],
    "wof:name":"Tanjungbaru",
    "wof:placetype":"locality"
},
  "geometry": {"coordinates":[104.63137999999999,-5.27959],"type":"Point"}
}