{
  "type": "Feature",
  "properties": {
    "gn:admin1_code":"0.0",
    "gn:asciiname":"Girijati",
    "gn:cc2":"ID",
    "gn:country_code":"ID",
    "gn:dem":104,
    "gn:feature_class":"P",
    "gn:feature_code":"PPL",
    "gn:name":"Girijati",
    "gn:population":0,
    "gn:timezone":"Asia/Jakarta",
    "iso:country":"ID",
    "name:und_x_variant":[
        "Giridjati",
        "Girijati"
    ],
    "wof:lang_x_official":[
        "ind"
    ],
    "wof:lang_x_spoken":[
        "ind",
        "eng"
    ],
    "wof:name":"Girijati",
    "wof:placetype":"locality"
},
  "geometry": {"coordinates":[110.33333,-8.01667],"type":"Point"}
}