{
  "type": "Feature",
  "properties": {
    "gn:country":"ID",
    "gn:fcode":"PPL",
    "gn:pop":0,
    "iso:country":"ID",
    "name:ind_x_preferred":[
        "Bintang"
    ],
    "name:unk_x_variant":[
        "Binbang"
    ],
    "qs:name":"Bintang",
    "qs:name_adm0":"Indonesia",
    "qs:name_adm1":"Nanggroe Aceh Darussalam",
    "qs:photos_9k":1,
    "qs:photos_9r":2,
    "qs:photos_all":65,
    "qs:photos_sr":0,
    "qs:placetype":"Town",
    "qs:pop_sr":"0",
    "wof:lang_x_official":[
        "ind"
    ],
    "wof:lang_x_spoken":[
        "ind",
        "eng"
    ],
    "wof:name":"Bintang",
    "wof:placetype":"locality",
    "wof:population":0
},
  "geometry": {"coordinates":[97.00490000000001,4.5856],"type":"Point"}
}