{
  "type": "Feature",
  "properties": {
    "gn:admin1_code":"39.0",
    "gn:asciiname":"Rome",
    "gn:country_code":"ID",
    "gn:dem":-9999,
    "gn:feature_class":"P",
    "gn:feature_code":"PPL",
    "gn:name":"Rome",
    "gn:population":0,
    "gn:timezone":"Asia/Jayapura",
    "iso:country":"ID",
    "name:und_x_variant":[
        "Oerarom",
        "Utarom",
        "Urarom"
    ],
    "wof:name":"Rome",
    "wof:placetype":"locality"
},
  "geometry": {"coordinates":[133.68389999999999,-3.6326],"type":"Point"}
}