{
  "type": "Feature",
  "properties": {
    "gn:admin1_code":"7",
    "gn:asciiname":"Watesalit Tengah",
    "gn:country_code":"ID",
    "gn:dem":8,
    "gn:feature_class":"P",
    "gn:feature_code":"PPL",
    "gn:name":"Watesalit Tengah",
    "gn:population":0,
    "gn:timezone":"Asia/Jakarta",
    "iso:country":"ID",
    "name:ind_x_preferred":[
        "Watesalit Tengah"
    ],
    "wof:name":"Watesalit Tengah",
    "wof:placetype":"locality"
},
  "geometry": {"coordinates":[109.71841000000001,-6.90984],"type":"Point"}
}