{
  "type": "Feature",
  "properties": {
    "gn:admin1_code":"7",
    "gn:asciiname":"Sonorejo",
    "gn:country_code":"ID",
    "gn:dem":78,
    "gn:feature_class":"P",
    "gn:feature_code":"PPL",
    "gn:name":"Sonorejo",
    "gn:population":0,
    "gn:timezone":"Asia/Jakarta",
    "iso:country":"ID",
    "name:ind_x_preferred":[
        "Sonorejo"
    ],
    "wof:name":"Sonorejo",
    "wof:placetype":"locality"
},
  "geometry": {"coordinates":[111.09917,-7.37778],"type":"Point"}
}