{
  "type": "Feature",
  "properties": {
    "gn:admin1_code":"7.0",
    "gn:asciiname":"Pohijo",
    "gn:country_code":"ID",
    "gn:dem":14,
    "gn:feature_class":"P",
    "gn:feature_code":"PPLA4",
    "gn:name":"Pohijo",
    "gn:population":0,
    "gn:timezone":"Asia/Jakarta",
    "iso:country":"ID",
    "name:ind_x_preferred":[
        "Pohijo"
    ],
    "wof:name":"Pohijo",
    "wof:placetype":"locality"
},
  "geometry": {"coordinates":[111.07170000000001,-6.6266],"type":"Point"}
}