{
  "type": "Feature",
  "properties": {
    "gn:admin1_code":"21",
    "gn:asciiname":"Uwepolo",
    "gn:country_code":"ID",
    "gn:dem":15,
    "gn:feature_class":"P",
    "gn:feature_code":"PPL",
    "gn:name":"Uwepolo",
    "gn:population":0,
    "gn:timezone":"Asia/Makassar",
    "iso:country":"ID",
    "name:ind_x_preferred":[
        "Uwepolo"
    ],
    "wof:name":"Uwepolo",
    "wof:placetype":"locality"
},
  "geometry": {"coordinates":[120.0581,-0.6322],"type":"Point"}
}