{
  "type": "Feature",
  "properties": {
    "gn:admin1_code":"30.0",
    "gn:asciiname":"Cileles",
    "gn:country_code":"ID",
    "gn:dem":265,
    "gn:feature_class":"P",
    "gn:feature_code":"PPL",
    "gn:name":"Cileles",
    "gn:population":0,
    "gn:timezone":"Asia/Jakarta",
    "iso:country":"ID",
    "name:ind_x_preferred":[
        "Cileles"
    ],
    "name:und_x_variant":[
        "Tjileles"
    ],
    "wof:name":"Cileles",
    "wof:placetype":"locality"
},
  "geometry": {"coordinates":[108.55159999999999,-7.1861],"type":"Point"}
}