{
  "type": "Feature",
  "properties": {
    "gn:admin1_code":"26.0",
    "gn:asciiname":"Sosorgodang Satu",
    "gn:country_code":"ID",
    "gn:dem":1386,
    "gn:feature_class":"P",
    "gn:feature_code":"PPL",
    "gn:name":"Sosorgodang Satu",
    "gn:population":0,
    "gn:timezone":"Asia/Jakarta",
    "iso:country":"ID",
    "name:ind_x_preferred":[
        "Sosorgodang Satu"
    ],
    "name:und_x_variant":[
        "Sosorgodang 1"
    ],
    "wof:lang_x_official":[
        "ind"
    ],
    "wof:lang_x_spoken":[
        "ind",
        "eng"
    ],
    "wof:name":"Sosorgodang Satu",
    "wof:placetype":"locality"
},
  "geometry": {"coordinates":[98.6806,2.1936],"type":"Point"}
}