{
  "type": "Feature",
  "properties": {
    "gn:admin1_code":"8.0",
    "gn:asciiname":"Kalisangkrah Lor",
    "gn:country_code":"ID",
    "gn:dem":427,
    "gn:feature_class":"P",
    "gn:feature_code":"PPLA4",
    "gn:name":"Kalisangkrah Lor",
    "gn:population":0,
    "gn:timezone":"Asia/Jakarta",
    "iso:country":"ID",
    "name:ind_x_preferred":[
        "Kalisangkrah Lor"
    ],
    "wof:name":"Kalisangkrah Lor",
    "wof:placetype":"locality"
},
  "geometry": {"coordinates":[112.38849999999999,-8.2852],"type":"Point"}
}