{
  "type": "Feature",
  "properties": {
    "gn:admin1_code":"26",
    "gn:asciiname":"Pulau Agas",
    "gn:country_code":"ID",
    "gn:dem":8,
    "gn:feature_class":"P",
    "gn:feature_code":"PPL",
    "gn:name":"Pulau Agas",
    "gn:population":0,
    "gn:timezone":"Asia/Jakarta",
    "iso:country":"ID",
    "name:ind_x_preferred":[
        "Pulau Agas"
    ],
    "wof:name":"Pulau Agas",
    "wof:placetype":"locality"
},
  "geometry": {"coordinates":[98.60339999999999,3.7117],"type":"Point"}
}