{
  "type": "Feature",
  "properties": {
    "gn:admin1_code":"8.0",
    "gn:asciiname":"Karanganom",
    "gn:country_code":"ID",
    "gn:dem":78,
    "gn:feature_class":"P",
    "gn:feature_code":"PPL",
    "gn:name":"Karanganom",
    "gn:population":0,
    "gn:timezone":"Asia/Jakarta",
    "iso:country":"ID",
    "name:ceb_x_preferred":[
        "Karanganom"
    ],
    "name:ind_x_preferred":[
        "Karanganom"
    ],
    "name:jav_x_preferred":[
        "Karanganom"
    ],
    "name:mlg_x_preferred":[
        "Karanganom"
    ],
    "name:nld_x_preferred":[
        "Karanganom"
    ],
    "wof:lang_x_official":[
        "ind"
    ],
    "wof:lang_x_spoken":[
        "ind",
        "eng"
    ],
    "wof:name":"Karanganom",
    "wof:placetype":"locality"
},
  "geometry": {"coordinates":[113.45650000000001,-7.0985],"type":"Point"}
}