{
  "type": "Feature",
  "properties": {
    "gn:admin1_code":"26",
    "gn:asciiname":"Batuanggan",
    "gn:country_code":"ID",
    "gn:dem":966,
    "gn:feature_class":"P",
    "gn:feature_code":"PPL",
    "gn:name":"Batuanggan",
    "gn:population":0,
    "gn:timezone":"Asia/Jakarta",
    "iso:country":"ID",
    "name:ind_x_preferred":[
        "Batuanggan"
    ],
    "wof:name":"Batuanggan",
    "wof:placetype":"locality"
},
  "geometry": {"coordinates":[98.37,2.7821],"type":"Point"}
}