{
  "type": "Feature",
  "properties": {
    "gn:admin1_code":"1.0",
    "gn:asciiname":"Kampung Lot",
    "gn:country_code":"ID",
    "gn:dem":411,
    "gn:feature_class":"P",
    "gn:feature_code":"PPL",
    "gn:name":"Kampung Lot",
    "gn:population":0,
    "gn:timezone":"Asia/Jakarta",
    "iso:country":"ID",
    "name:ind_x_preferred":[
        "Kampung Lot"
    ],
    "wof:name":"Kampung Lot",
    "wof:placetype":"locality"
},
  "geometry": {"coordinates":[97.19333,4.3975],"type":"Point"}
}