{
  "type": "Feature",
  "properties": {
    "gn:admin1_code":"26",
    "gn:asciiname":"Hutapangorian",
    "gn:country_code":"ID",
    "gn:dem":929,
    "gn:feature_class":"P",
    "gn:feature_code":"PPL",
    "gn:name":"Hutapangorian",
    "gn:population":0,
    "gn:timezone":"Asia/Jakarta",
    "iso:country":"ID",
    "name:ind_x_preferred":[
        "Hutapangorian"
    ],
    "wof:name":"Hutapangorian",
    "wof:placetype":"locality"
},
  "geometry": {"coordinates":[99.28319999999999,1.9628],"type":"Point"}
}