{
  "type": "Feature",
  "properties": {
    "gn:admin1_code":"1",
    "gn:asciiname":"Lampoh Rayeuen",
    "gn:country_code":"ID",
    "gn:dem":12,
    "gn:feature_class":"P",
    "gn:feature_code":"PPL",
    "gn:name":"Lampoh Rayeuen",
    "gn:population":0,
    "gn:timezone":"Asia/Jakarta",
    "iso:country":"ID",
    "name:ind_x_preferred":[
        "Lampoh Rayeuen"
    ],
    "wof:name":"Lampoh Rayeuen",
    "wof:placetype":"locality"
},
  "geometry": {"coordinates":[96.7788,5.2433],"type":"Point"}
}