{
  "type": "Feature",
  "properties": {
    "gn:admin1_code":"30.0",
    "gn:asciiname":"Cipulus",
    "gn:country_code":"ID",
    "gn:dem":114,
    "gn:feature_class":"P",
    "gn:feature_code":"PPL",
    "gn:name":"Cipulus",
    "gn:population":0,
    "gn:timezone":"Asia/Jakarta",
    "iso:country":"ID",
    "name:ind_x_preferred":[
        "Cipulus"
    ],
    "wof:name":"Cipulus",
    "wof:placetype":"locality"
},
  "geometry": {"coordinates":[106.9083,-7.3312],"type":"Point"}
}