{
  "type": "Feature",
  "properties": {
    "gn:admin1_code":"7.0",
    "gn:asciiname":"Bodong",
    "gn:country_code":"ID",
    "gn:dem":168,
    "gn:feature_class":"P",
    "gn:feature_code":"PPL",
    "gn:name":"Bodong",
    "gn:population":0,
    "gn:timezone":"Asia/Jakarta",
    "iso:country":"ID",
    "name:ind_x_preferred":[
        "Bodong"
    ],
    "wof:name":"Bodong",
    "wof:placetype":"locality"
},
  "geometry": {"coordinates":[109.57277999999999,-7.46556],"type":"Point"}
}