{
  "type": "Feature",
  "properties": {
    "gn:admin1_code":"7.0",
    "gn:asciiname":"Keciples",
    "gn:country_code":"ID",
    "gn:dem":32,
    "gn:feature_class":"P",
    "gn:feature_code":"PPL",
    "gn:name":"Keciples",
    "gn:population":0,
    "gn:timezone":"Asia/Jakarta",
    "iso:country":"ID",
    "name:ind_x_preferred":[
        "Keciples"
    ],
    "wof:name":"Keciples",
    "wof:placetype":"locality"
},
  "geometry": {"coordinates":[109.36388999999998,-7.60889],"type":"Point"}
}