{
  "type": "Feature",
  "properties": {
    "gn:admin1_code":"8.0",
    "gn:asciiname":"Krayen",
    "gn:country_code":"ID",
    "gn:dem":137,
    "gn:feature_class":"P",
    "gn:feature_code":"PPLA4",
    "gn:name":"Krayen",
    "gn:population":0,
    "gn:timezone":"Asia/Jakarta",
    "iso:country":"ID",
    "name:ind_x_preferred":[
        "Krayen"
    ],
    "wof:lang_x_official":[
        "ind"
    ],
    "wof:lang_x_spoken":[
        "ind",
        "eng"
    ],
    "wof:name":"Krayen",
    "wof:placetype":"locality"
},
  "geometry": {"coordinates":[111.6426,-8.0871],"type":"Point"}
}