{
  "type": "Feature",
  "properties": {
    "gn:admin1_code":"17.0",
    "gn:asciiname":"Woro",
    "gn:country_code":"ID",
    "gn:dem":78,
    "gn:feature_class":"P",
    "gn:feature_code":"PPLA4",
    "gn:name":"Woro",
    "gn:population":0,
    "gn:timezone":"Asia/Makassar",
    "iso:country":"ID",
    "name:ind_x_preferred":[
        "Woro"
    ],
    "wof:name":"Woro",
    "wof:placetype":"locality"
},
  "geometry": {"coordinates":[118.5437,-8.573],"type":"Point"}
}