{
  "type": "Feature",
  "properties": {
    "gn:admin1_code":"39.0",
    "gn:asciiname":"Wertra",
    "gn:country_code":"ID",
    "gn:dem":202,
    "gn:feature_class":"P",
    "gn:feature_code":"PPL",
    "gn:name":"Wertra",
    "gn:population":0,
    "gn:timezone":"Asia/Jayapura",
    "iso:country":"ID",
    "name:ind_x_preferred":[
        "Wertra"
    ],
    "name:und_x_variant":[
        "Werfera",
        "Werfra"
    ],
    "wof:lang_x_official":[
        "ind"
    ],
    "wof:lang_x_spoken":[
        "ind",
        "eng"
    ],
    "wof:name":"Wertra",
    "wof:placetype":"locality"
},
  "geometry": {"coordinates":[132.00389999999999,-2.7682],"type":"Point"}
}