{
  "type": "Feature",
  "properties": {
    "gn:admin1_code":"8",
    "gn:asciiname":"Pangloros",
    "gn:country_code":"ID",
    "gn:dem":51,
    "gn:feature_class":"P",
    "gn:feature_code":"PPL",
    "gn:name":"Pangloros",
    "gn:population":0,
    "gn:timezone":"Asia/Jakarta",
    "iso:country":"ID",
    "name:ind_x_preferred":[
        "Pangloros"
    ],
    "wof:name":"Pangloros",
    "wof:placetype":"locality"
},
  "geometry": {"coordinates":[113.07850000000001,-7.0817],"type":"Point"}
}