{
  "type": "Feature",
  "properties": {
    "gn:admin1_code":"0.0",
    "gn:asciiname":"Batusirah",
    "gn:country_code":"ID",
    "gn:dem":17,
    "gn:feature_class":"P",
    "gn:feature_code":"PPL",
    "gn:name":"Batusirah",
    "gn:population":0,
    "gn:timezone":"Asia/Jakarta",
    "iso:country":"ID",
    "name:ind_x_preferred":[
        "Batusirah"
    ],
    "wof:name":"Batusirah",
    "wof:placetype":"locality"
},
  "geometry": {"coordinates":[99.03428,0.78821],"type":"Point"}
}