{
  "type": "Feature",
  "properties": {
    "gn:admin1_code":"30.0",
    "gn:asciiname":"Cigunungherang",
    "gn:country_code":"ID",
    "gn:dem":509,
    "gn:feature_class":"P",
    "gn:feature_code":"PPL",
    "gn:name":"Cigunungherang",
    "gn:population":0,
    "gn:timezone":"Asia/Jakarta",
    "iso:country":"ID",
    "name:ind_x_preferred":[
        "Cigunungherang"
    ],
    "name:und_x_variant":[
        "Tjigoenoengherang"
    ],
    "wof:name":"Cigunungherang",
    "wof:placetype":"locality"
},
  "geometry": {"coordinates":[106.7444,-7.1413],"type":"Point"}
}