{
  "type": "Feature",
  "properties": {
    "gn:admin1_code":"36.0",
    "gn:asciiname":"Bahor",
    "gn:country_code":"ID",
    "gn:dem":8,
    "gn:feature_class":"P",
    "gn:feature_code":"PPL",
    "gn:name":"Bahor",
    "gn:population":0,
    "gn:timezone":"Asia/Jayapura",
    "iso:country":"ID",
    "name:ckb_x_preferred":[
        "\u0628\u06d5\u06be\u0627\u0631"
    ],
    "name:fas_x_preferred":[
        "\u0628\u0647\u0627\u0631"
    ],
    "name:ind_x_preferred":[
        "Bahor"
    ],
    "wof:lang_x_official":[
        "ind"
    ],
    "wof:lang_x_spoken":[
        "ind",
        "eng"
    ],
    "wof:name":"Bahor",
    "wof:placetype":"locality"
},
  "geometry": {"coordinates":[140.30456000000001,-8.43734],"type":"Point"}
}