{
  "type": "Feature",
  "properties": {
    "gn:admin1_code":"36.0",
    "gn:asciiname":"Bahor",
    "gn:country_code":"ID",
    "gn:dem":8,
    "gn:feature_class":"P",
    "gn:feature_code":"PPL",
    "gn:name":"Bahor",
    "gn:population":0,
    "gn:timezone":"Asia/Jayapura",
    "iso:country":"ID",
    "name:ind_x_preferred":[
        "Bahor"
    ],
    "wof:name":"Bahor",
    "wof:placetype":"locality"
},
  "geometry": {"coordinates":[140.30456000000001,-8.43734],"type":"Point"}
}