{
  "type": "Feature",
  "properties": {
    "gn:admin1_code":"30",
    "gn:asciiname":"Kalurahan",
    "gn:country_code":"ID",
    "gn:dem":230,
    "gn:feature_class":"P",
    "gn:feature_code":"PPL",
    "gn:name":"Kalurahan",
    "gn:population":0,
    "gn:timezone":"Asia/Jakarta",
    "iso:country":"ID",
    "name:ind_x_preferred":[
        "Kalurahan"
    ],
    "wof:name":"Kalurahan",
    "wof:placetype":"locality"
},
  "geometry": {"coordinates":[106.67444,-6.57917],"type":"Point"}
}