{
  "type": "Feature",
  "properties": {
    "gn:admin1_code":"15.0",
    "gn:asciiname":"Umbulan Wewangtakal",
    "gn:country_code":"ID",
    "gn:dem":32,
    "gn:feature_class":"P",
    "gn:feature_code":"PPL",
    "gn:name":"Umbulan Wewangtakal",
    "gn:population":0,
    "gn:timezone":"Asia/Jakarta",
    "iso:country":"ID",
    "name:ind_x_preferred":[
        "Umbulan Wewangtakal"
    ],
    "name:und_x_variant":[
        "Umbulanwewangtakal"
    ],
    "wof:name":"Umbulan Wewangtakal",
    "wof:placetype":"locality"
},
  "geometry": {"coordinates":[104.87396,-4.81145],"type":"Point"}
}