{
  "type": "Feature",
  "properties": {
    "gn:admin1_code":"17",
    "gn:asciiname":"Keselet Timur",
    "gn:country_code":"ID",
    "gn:dem":186,
    "gn:feature_class":"P",
    "gn:feature_code":"PPL",
    "gn:name":"Keselet Timur",
    "gn:population":0,
    "gn:timezone":"Asia/Makassar",
    "iso:country":"ID",
    "name:ind_x_preferred":[
        "Keselet Timur"
    ],
    "wof:name":"Keselet Timur",
    "wof:placetype":"locality"
},
  "geometry": {"coordinates":[116.4948,-8.6591],"type":"Point"}
}