{
  "type": "Feature",
  "properties": {
    "gn:admin1_code":"30.0",
    "gn:asciiname":"Cinangor",
    "gn:country_code":"ID",
    "gn:dem":722,
    "gn:feature_class":"P",
    "gn:feature_code":"PPL",
    "gn:name":"Cinangor",
    "gn:population":0,
    "gn:timezone":"Asia/Jakarta",
    "iso:country":"ID",
    "name:ind_x_preferred":[
        "Cinangor"
    ],
    "name:und_x_variant":[
        "Tjnangor"
    ],
    "wof:name":"Cinangor",
    "wof:placetype":"locality"
},
  "geometry": {"coordinates":[107.96259999999999,-7.0112],"type":"Point"}
}