{
  "type": "Feature",
  "properties": {
    "gn:admin1_code":"8",
    "gn:asciiname":"Anyer",
    "gn:country_code":"ID",
    "gn:dem":27,
    "gn:feature_class":"P",
    "gn:feature_code":"PPL",
    "gn:name":"Anyer",
    "gn:population":0,
    "gn:timezone":"Asia/Jakarta",
    "iso:country":"ID",
    "name:deu_x_preferred":[
        "Anyer"
    ],
    "name:fra_x_preferred":[
        "Anyer"
    ],
    "name:fry_x_preferred":[
        "Anjer"
    ],
    "name:ind_x_preferred":[
        "Anyer"
    ],
    "name:ind_x_variant":[
        "Anyar"
    ],
    "name:jav_x_preferred":[
        "Anyar"
    ],
    "name:msa_x_preferred":[
        "Anyar"
    ],
    "name:nld_x_preferred":[
        "Anyer"
    ],
    "name:por_x_preferred":[
        "Anyer"
    ],
    "name:sun_x_preferred":[
        "Anyar"
    ],
    "wof:lang_x_official":[
        "ind"
    ],
    "wof:lang_x_spoken":[
        "ind",
        "eng"
    ],
    "wof:name":"Anyer",
    "wof:placetype":"locality"
},
  "geometry": {"coordinates":[113.1919,-7.1812],"type":"Point"}
}