{
  "type": "Feature",
  "properties": {
    "gn:admin1_code":"0.0",
    "gn:asciiname":"Tsyohtayoh",
    "gn:cc2":"ID",
    "gn:country_code":"ID",
    "gn:dem":37,
    "gn:feature_class":"P",
    "gn:feature_code":"PPL",
    "gn:name":"Tsyohtayoh",
    "gn:population":0,
    "gn:timezone":"Asia/Jayapura",
    "iso:country":"ID",
    "name:und_x_variant":[
        "Tsjohtojoh",
        "Tsjohtajoh",
        "Tsyohtayoh"
    ],
    "wof:lang_x_official":[
        "ind"
    ],
    "wof:lang_x_spoken":[
        "ind",
        "eng"
    ],
    "wof:name":"Tsyohtayoh",
    "wof:placetype":"locality"
},
  "geometry": {"coordinates":[140.01667,-5.91667],"type":"Point"}
}