{
  "type": "Feature",
  "properties": {
    "gn:admin1_code":"7.0",
    "gn:asciiname":"Kedungwaru",
    "gn:country_code":"ID",
    "gn:dem":62,
    "gn:feature_class":"P",
    "gn:feature_code":"PPL",
    "gn:name":"Kedungwaru",
    "gn:population":0,
    "gn:timezone":"Asia/Jakarta",
    "iso:country":"ID",
    "name:ind_x_preferred":[
        "Kedungwaru"
    ],
    "wof:name":"Kedungwaru",
    "wof:placetype":"locality"
},
  "geometry": {"coordinates":[111.19459999999999,-7.1231],"type":"Point"}
}