{
  "type": "Feature",
  "properties": {
    "gn:admin1_code":"12",
    "gn:asciiname":"Jaro",
    "gn:country_code":"ID",
    "gn:dem":76,
    "gn:feature_class":"P",
    "gn:feature_code":"PPL",
    "gn:name":"Jaro",
    "gn:population":0,
    "gn:timezone":"Asia/Makassar",
    "iso:country":"ID",
    "name:ceb_x_preferred":[
        "Jaro"
    ],
    "name:ces_x_preferred":[
        "Jaro"
    ],
    "name:deu_x_preferred":[
        "Jaro"
    ],
    "name:fra_x_preferred":[
        "Jaro"
    ],
    "name:ind_x_preferred":[
        "Jaro"
    ],
    "name:ita_x_preferred":[
        "Jaro"
    ],
    "name:nld_x_preferred":[
        "Jaro"
    ],
    "name:pol_x_preferred":[
        "Jaro"
    ],
    "name:spa_x_preferred":[
        "Jaro"
    ],
    "name:swe_x_preferred":[
        "Jaro"
    ],
    "name:ukr_x_preferred":[
        "\u042f\u0440\u043e"
    ],
    "wof:lang_x_official":[
        "ind"
    ],
    "wof:lang_x_spoken":[
        "ind",
        "eng"
    ],
    "wof:name":"Jaro",
    "wof:placetype":"locality"
},
  "geometry": {"coordinates":[115.63509999999999,-1.8381],"type":"Point"}
}