{
  "type": "Feature",
  "properties": {
    "gn:admin1_code":"07",
    "gn:asciiname":"Klumpit",
    "gn:country_code":"ID",
    "gn:dem":734,
    "gn:feature_class":"P",
    "gn:feature_code":"PPL",
    "gn:name":"Klumpit",
    "gn:population":0,
    "gn:timezone":"Asia/Jakarta",
    "iso:country":"ID",
    "name:und_x_variant":[
        "Kumprit",
        "Klumpit"
    ],
    "wof:name":"Klumpit",
    "wof:placetype":"locality"
},
  "geometry": {"coordinates":[110.28055999999999,-7.3175],"type":"Point"}
}