{
  "type": "Feature",
  "properties": {
    "gn:admin1_code":"07",
    "gn:asciiname":"Ngerjoso",
    "gn:cc2":"ID",
    "gn:country_code":"ID",
    "gn:dem":513,
    "gn:feature_class":"P",
    "gn:feature_code":"PPL",
    "gn:name":"Ngerjoso",
    "gn:population":0,
    "gn:timezone":"Asia/Jakarta",
    "iso:country":"ID",
    "name:und_x_variant":[
        "Ngerdjoso",
        "Ngerjoso"
    ],
    "wof:lang_x_official":[
        "ind"
    ],
    "wof:lang_x_spoken":[
        "ind",
        "eng"
    ],
    "wof:name":"Ngerjoso",
    "wof:placetype":"locality"
},
  "geometry": {"coordinates":[110.58972,-7.40806],"type":"Point"}
}