{
  "type": "Feature",
  "properties": {
    "gn:admin1_code":"18",
    "gn:asciiname":"Lakokur",
    "gn:country_code":"ID",
    "gn:dem":656,
    "gn:feature_class":"P",
    "gn:feature_code":"PPL",
    "gn:name":"Lakokur",
    "gn:population":0,
    "gn:timezone":"Asia/Makassar",
    "iso:country":"ID",
    "name:ind_x_preferred":[
        "Lakokur"
    ],
    "wof:lang_x_official":[
        "ind"
    ],
    "wof:lang_x_spoken":[
        "ind",
        "eng"
    ],
    "wof:name":"Lakokur",
    "wof:placetype":"locality"
},
  "geometry": {"coordinates":[120.1066,-9.6973],"type":"Point"}
}