{
  "type": "Feature",
  "properties": {
    "gn:admin1_code":"30.0",
    "gn:asciiname":"Sukasenang",
    "gn:country_code":"ID",
    "gn:dem":161,
    "gn:feature_class":"P",
    "gn:feature_code":"PPLA4",
    "gn:name":"Sukasenang",
    "gn:population":0,
    "gn:timezone":"Asia/Jakarta",
    "iso:country":"ID",
    "name:ind_x_preferred":[
        "Sukasenang"
    ],
    "wof:name":"Sukasenang",
    "wof:placetype":"locality"
},
  "geometry": {"coordinates":[108.19370000000001,-7.5099],"type":"Point"}
}