{
  "type": "Feature",
  "properties": {
    "gn:admin1_code":"15.0",
    "gn:asciiname":"Penggawalimaulu",
    "gn:country_code":"ID",
    "gn:dem":11,
    "gn:feature_class":"P",
    "gn:feature_code":"PPL",
    "gn:name":"Penggawalimaulu",
    "gn:population":0,
    "gn:timezone":"Asia/Jakarta",
    "iso:country":"ID",
    "name:ind_x_preferred":[
        "Penggawalimaulu"
    ],
    "name:und_x_variant":[
        "Negeri"
    ],
    "wof:name":"Penggawalimaulu",
    "wof:placetype":"locality"
},
  "geometry": {"coordinates":[103.92907,-5.13724],"type":"Point"}
}