{
  "type": "Feature",
  "properties": {
    "gn:admin1_code":"15.0",
    "gn:asciiname":"Umbulan Bolong Bolong",
    "gn:country_code":"ID",
    "gn:dem":20,
    "gn:feature_class":"P",
    "gn:feature_code":"PPL",
    "gn:name":"Umbulan Bolong Bolong",
    "gn:population":0,
    "gn:timezone":"Asia/Jakarta",
    "iso:country":"ID",
    "name:ind_x_preferred":[
        "Umbulan Bolong Bolong"
    ],
    "name:ind_x_variant":[
        "Umbulanbolongbolong"
    ],
    "wof:name":"Umbulan Bolong Bolong",
    "wof:placetype":"locality"
},
  "geometry": {"coordinates":[105.24211,-4.31155],"type":"Point"}
}