{
  "type": "Feature",
  "properties": {
    "gn:admin1_code":"07",
    "gn:asciiname":"Sribit",
    "gn:country_code":"ID",
    "gn:dem":188,
    "gn:feature_class":"P",
    "gn:feature_code":"PPL",
    "gn:name":"Sribit",
    "gn:population":0,
    "gn:timezone":"Asia/Jakarta",
    "iso:country":"ID",
    "wof:name":"Sribit",
    "wof:placetype":"locality"
},
  "geometry": {"coordinates":[110.64943999999998,-7.63611],"type":"Point"}
}