{
  "type": "Feature",
  "properties": {
    "gn:admin1_code":"30.0",
    "gn:asciiname":"Cinunuk Girang",
    "gn:country_code":"ID",
    "gn:dem":714,
    "gn:feature_class":"P",
    "gn:feature_code":"PPLA4",
    "gn:name":"Cinunuk Girang",
    "gn:population":0,
    "gn:timezone":"Asia/Jakarta",
    "iso:country":"ID",
    "name:ind_x_preferred":[
        "Cinunuk Girang"
    ],
    "name:und_x_variant":[
        "Tjinoenoenk Girang"
    ],
    "wof:lang_x_official":[
        "ind"
    ],
    "wof:lang_x_spoken":[
        "ind",
        "eng"
    ],
    "wof:name":"Cinunuk Girang",
    "wof:placetype":"locality"
},
  "geometry": {"coordinates":[107.9751,-7.1787],"type":"Point"}
}