{
  "type": "Feature",
  "properties": {
    "gn:admin1_code":"7.0",
    "gn:asciiname":"Depok",
    "gn:country_code":"ID",
    "gn:dem":448,
    "gn:feature_class":"P",
    "gn:feature_code":"PPL",
    "gn:name":"Depok",
    "gn:population":0,
    "gn:timezone":"Asia/Jakarta",
    "iso:country":"ID",
    "wof:name":"Depok",
    "wof:placetype":"locality"
},
  "geometry": {"coordinates":[110.30611,-7.56028],"type":"Point"}
}