{
  "type": "Feature",
  "properties": {
    "gn:admin1_code":"38",
    "gn:asciiname":"Beru",
    "gn:country_code":"ID",
    "gn:dem":14,
    "gn:feature_class":"P",
    "gn:feature_code":"PPL",
    "gn:name":"Beru",
    "gn:population":0,
    "gn:timezone":"Asia/Makassar",
    "iso:country":"ID",
    "name:ceb_x_preferred":[
        "Beru"
    ],
    "name:deu_x_preferred":[
        "Beru"
    ],
    "name:ind_x_preferred":[
        "Beru"
    ],
    "name:nld_x_preferred":[
        "Beru"
    ],
    "name:rus_x_preferred":[
        "\u0411\u0435\u0440\u0443"
    ],
    "name:swe_x_preferred":[
        "Beru"
    ],
    "wof:lang_x_official":[
        "ind"
    ],
    "wof:lang_x_spoken":[
        "ind",
        "eng"
    ],
    "wof:name":"Beru",
    "wof:placetype":"locality"
},
  "geometry": {"coordinates":[119.5787,-5.6468],"type":"Point"}
}