{
  "type": "Feature",
  "properties": {
    "gn:admin1_code":"41",
    "gn:asciiname":"Keppe",
    "gn:country_code":"ID",
    "gn:dem":750,
    "gn:feature_class":"P",
    "gn:feature_code":"PPL",
    "gn:name":"Keppe",
    "gn:population":0,
    "gn:timezone":"Asia/Makassar",
    "iso:country":"ID",
    "name:ind_x_preferred":[
        "Keppe"
    ],
    "name:und_x_variant":[
        "Kepe"
    ],
    "wof:name":"Keppe",
    "wof:placetype":"locality"
},
  "geometry": {"coordinates":[119.1836,-2.971],"type":"Point"}
}