{
  "type": "Feature",
  "properties": {
    "gn:admin1_code":"7.0",
    "gn:asciiname":"Kedompon",
    "gn:country_code":"ID",
    "gn:dem":22,
    "gn:feature_class":"P",
    "gn:feature_code":"PPL",
    "gn:name":"Kedompon",
    "gn:population":0,
    "gn:timezone":"Asia/Jakarta",
    "iso:country":"ID",
    "name:ind_x_preferred":[
        "Kedompon"
    ],
    "wof:name":"Kedompon",
    "wof:placetype":"locality"
},
  "geometry": {"coordinates":[109.52943999999999,-7.62861],"type":"Point"}
}