{
  "type": "Feature",
  "properties": {
    "gn:admin1_code":"26",
    "gn:asciiname":"Pondok Satu",
    "gn:country_code":"ID",
    "gn:dem":29,
    "gn:feature_class":"P",
    "gn:feature_code":"PPL",
    "gn:name":"Pondok Satu",
    "gn:population":0,
    "gn:timezone":"Asia/Jakarta",
    "iso:country":"ID",
    "name:ind_x_preferred":[
        "Pondok Satu"
    ],
    "name:und_x_variant":[
        "Pondok I"
    ],
    "wof:name":"Pondok Satu",
    "wof:placetype":"locality"
},
  "geometry": {"coordinates":[99.1228,3.3219],"type":"Point"}
}