{
  "type": "Feature",
  "properties": {
    "gn:admin1_code":"18.0",
    "gn:asciiname":"Sawah",
    "gn:country_code":"ID",
    "gn:dem":43,
    "gn:feature_class":"P",
    "gn:feature_code":"PPL",
    "gn:name":"Sawah",
    "gn:population":0,
    "gn:timezone":"Asia/Makassar",
    "iso:country":"ID",
    "name:ara_x_preferred":[
        "\u0633\u0648\u0627\u062d"
    ],
    "name:arz_x_preferred":[
        "\u0633\u0648\u0627\u062d"
    ],
    "name:bul_x_preferred":[
        "\u0425\u0430\u0431\u0438\u0431\u0438"
    ],
    "name:ind_x_preferred":[
        "Sawah"
    ],
    "wof:name":"Sawah",
    "wof:placetype":"locality"
},
  "geometry": {"coordinates":[123.21850000000001,-8.2545],"type":"Point"}
}