{
  "type": "Feature",
  "properties": {
    "gn:admin1_code":"26",
    "gn:asciiname":"Pembangunan",
    "gn:country_code":"ID",
    "gn:dem":126,
    "gn:feature_class":"P",
    "gn:feature_code":"PPL",
    "gn:name":"Pembangunan",
    "gn:population":0,
    "gn:timezone":"Asia/Jakarta",
    "iso:country":"ID",
    "name:ind_x_preferred":[
        "Pembangunan"
    ],
    "wof:name":"Pembangunan",
    "wof:placetype":"locality"
},
  "geometry": {"coordinates":[99.53973000000001,1.45041],"type":"Point"}
}