{
  "type": "Feature",
  "properties": {
    "gn:admin1_code":"30.0",
    "gn:asciiname":"Pancalan",
    "gn:country_code":"ID",
    "gn:dem":777,
    "gn:feature_class":"P",
    "gn:feature_code":"PPLA4",
    "gn:name":"Pancalan",
    "gn:population":0,
    "gn:timezone":"Asia/Jakarta",
    "iso:country":"ID",
    "name:ind_x_preferred":[
        "Pancalan"
    ],
    "wof:name":"Pancalan",
    "wof:placetype":"locality"
},
  "geometry": {"coordinates":[107.3138,-7.3159],"type":"Point"}
}