{
  "type": "Feature",
  "properties": {
    "gn:admin1_code":"30",
    "gn:asciiname":"Nurulhuda",
    "gn:country_code":"ID",
    "gn:dem":1043,
    "gn:feature_class":"P",
    "gn:feature_code":"PPL",
    "gn:name":"Nurulhuda",
    "gn:population":0,
    "gn:timezone":"Asia/Jakarta",
    "iso:country":"ID",
    "name:ind_x_preferred":[
        "Nurulhuda"
    ],
    "wof:name":"Nurulhuda",
    "wof:placetype":"locality"
},
  "geometry": {"coordinates":[107.8035,-7.2367],"type":"Point"}
}