{
  "type": "Feature",
  "properties": {
    "gn:admin1_code":"38",
    "gn:asciiname":"Peniroan",
    "gn:country_code":"ID",
    "gn:dem":1085,
    "gn:feature_class":"P",
    "gn:feature_code":"PPL",
    "gn:name":"Peniroan",
    "gn:population":0,
    "gn:timezone":"Asia/Makassar",
    "iso:country":"ID",
    "name:ind_x_preferred":[
        "Peniroan"
    ],
    "wof:name":"Peniroan",
    "wof:placetype":"locality"
},
  "geometry": {"coordinates":[119.8721,-3.242],"type":"Point"}
}