{
  "type": "Feature",
  "properties": {
    "gn:admin1_code":"8",
    "gn:asciiname":"Potok",
    "gn:country_code":"ID",
    "gn:dem":452,
    "gn:feature_class":"P",
    "gn:feature_code":"PPL",
    "gn:name":"Potok",
    "gn:population":0,
    "gn:timezone":"Asia/Jakarta",
    "iso:country":"ID",
    "name:bos_x_preferred":[
        "Potok"
    ],
    "name:ceb_x_preferred":[
        "Potok"
    ],
    "name:deu_x_preferred":[
        "Potok"
    ],
    "name:epo_x_preferred":[
        "Potok"
    ],
    "name:fra_x_preferred":[
        "Potok"
    ],
    "name:hrv_x_preferred":[
        "Potok"
    ],
    "name:hun_x_preferred":[
        "Potok"
    ],
    "name:ind_x_preferred":[
        "Potok"
    ],
    "name:ita_x_preferred":[
        "Potok"
    ],
    "name:nld_x_preferred":[
        "Potok"
    ],
    "name:pol_x_preferred":[
        "Potok"
    ],
    "name:rue_x_preferred":[
        "\u041f\u043e\u0442\u043e\u043a"
    ],
    "name:sco_x_preferred":[
        "Potok"
    ],
    "name:slk_x_preferred":[
        "Potok"
    ],
    "name:slv_x_preferred":[
        "Potok"
    ],
    "name:swe_x_preferred":[
        "Potok"
    ],
    "name:ukr_x_preferred":[
        "\u041f\u043e\u0442\u043e\u043a"
    ],
    "wof:lang_x_official":[
        "ind"
    ],
    "wof:lang_x_spoken":[
        "ind",
        "eng"
    ],
    "wof:name":"Potok",
    "wof:placetype":"locality"
},
  "geometry": {"coordinates":[113.68640000000001,-7.826],"type":"Point"}
}