{
  "type": "Feature",
  "properties": {
    "gn:admin1_code":"8",
    "gn:asciiname":"Potok",
    "gn:country_code":"ID",
    "gn:dem":452,
    "gn:feature_class":"P",
    "gn:feature_code":"PPL",
    "gn:name":"Potok",
    "gn:population":0,
    "gn:timezone":"Asia/Jakarta",
    "iso:country":"ID",
    "name:ind_x_preferred":[
        "Potok"
    ],
    "wof:name":"Potok",
    "wof:placetype":"locality"
},
  "geometry": {"coordinates":[113.68640000000001,-7.826],"type":"Point"}
}