{
  "type": "Feature",
  "properties": {
    "gn:admin1_code":"15.0",
    "gn:asciiname":"Umbulanbakem Dua",
    "gn:country_code":"ID",
    "gn:dem":8,
    "gn:feature_class":"P",
    "gn:feature_code":"PPL",
    "gn:name":"Umbulanbakem Dua",
    "gn:population":0,
    "gn:timezone":"Asia/Jakarta",
    "iso:country":"ID",
    "name:ind_x_preferred":[
        "Umbulanbakem Dua"
    ],
    "name:ind_x_variant":[
        "Umbulanbakem 2"
    ],
    "wof:lang_x_official":[
        "ind"
    ],
    "wof:lang_x_spoken":[
        "ind",
        "eng"
    ],
    "wof:name":"Umbulanbakem Dua",
    "wof:placetype":"locality"
},
  "geometry": {"coordinates":[105.16625000000001,-4.45413],"type":"Point"}
}