{
  "type": "Feature",
  "properties": {
    "gn:admin1_code":"18.0",
    "gn:asciiname":"Leteturano",
    "gn:country_code":"ID",
    "gn:dem":490,
    "gn:feature_class":"P",
    "gn:feature_code":"PPL",
    "gn:name":"Leteturano",
    "gn:population":0,
    "gn:timezone":"Asia/Makassar",
    "iso:country":"ID",
    "name:ind_x_preferred":[
        "Leteturano"
    ],
    "wof:name":"Leteturano",
    "wof:placetype":"locality"
},
  "geometry": {"coordinates":[119.32040000000001,-9.566],"type":"Point"}
}