{
  "type": "Feature",
  "properties": {
    "gn:admin1_code":"8.0",
    "gn:asciiname":"Badas",
    "gn:country_code":"ID",
    "gn:dem":15,
    "gn:feature_class":"P",
    "gn:feature_code":"PPL",
    "gn:name":"Badas",
    "gn:population":0,
    "gn:timezone":"Asia/Jakarta",
    "iso:country":"ID",
    "name:ceb_x_preferred":[
        "Badas"
    ],
    "name:ind_x_preferred":[
        "Badas"
    ],
    "name:nld_x_preferred":[
        "Badas"
    ],
    "name:swe_x_preferred":[
        "Badas"
    ],
    "wof:name":"Badas",
    "wof:placetype":"locality"
},
  "geometry": {"coordinates":[112.6088,-7.3709],"type":"Point"}
}