{
  "type": "Feature",
  "properties": {
    "gn:admin1_code":"26",
    "gn:asciiname":"Parlambean",
    "gn:country_code":"ID",
    "gn:dem":202,
    "gn:feature_class":"P",
    "gn:feature_code":"PPL",
    "gn:name":"Parlambean",
    "gn:population":0,
    "gn:timezone":"Asia/Jakarta",
    "iso:country":"ID",
    "name:ind_x_preferred":[
        "Parlambean"
    ],
    "wof:name":"Parlambean",
    "wof:placetype":"locality"
},
  "geometry": {"coordinates":[99.03440000000001,3.0981],"type":"Point"}
}