{
  "type": "Feature",
  "properties": {
    "gn:admin1_code":"26.0",
    "gn:asciiname":"Sibolga",
    "gn:country_code":"ID",
    "gn:dem":1014,
    "gn:feature_class":"P",
    "gn:feature_code":"PPL",
    "gn:name":"Sibolga",
    "gn:population":0,
    "gn:timezone":"Asia/Jakarta",
    "iso:country":"ID",
    "name:ind_x_preferred":[
        "Sibolga"
    ],
    "wof:name":"Sibolga",
    "wof:placetype":"locality"
},
  "geometry": {"coordinates":[98.6078,2.1378],"type":"Point"}
}