{
  "type": "Feature",
  "properties": {
    "gn:admin1_code":"26.0",
    "gn:asciiname":"Sibolga",
    "gn:country_code":"ID",
    "gn:dem":1014,
    "gn:feature_class":"P",
    "gn:feature_code":"PPL",
    "gn:name":"Sibolga",
    "gn:population":0,
    "gn:timezone":"Asia/Jakarta",
    "iso:country":"ID",
    "name:ace_x_preferred":[
        "Sibolga"
    ],
    "name:afr_x_preferred":[
        "Sibolga"
    ],
    "name:ara_x_preferred":[
        "\u0633\u064a\u0628\u0648\u0644\u063a\u0627"
    ],
    "name:ben_x_preferred":[
        "\u09b8\u09bf\u09ac\u09cb\u09b2\u0997\u09be"
    ],
    "name:ceb_x_preferred":[
        "Sibolga"
    ],
    "name:deu_x_preferred":[
        "Sibolga"
    ],
    "name:ell_x_preferred":[
        "\u03a3\u03b9\u03bc\u03c0\u03cc\u03bb\u03b3\u03ba\u03b1"
    ],
    "name:fin_x_preferred":[
        "Sibolga"
    ],
    "name:fra_x_preferred":[
        "Sibolga"
    ],
    "name:fry_x_preferred":[
        "Sibolga"
    ],
    "name:heb_x_preferred":[
        "\u05e1\u05d9\u05d1\u05d5\u05dc\u05d2\u05d4"
    ],
    "name:hin_x_preferred":[
        "\u0938\u093f\u092c\u094b\u0932\u094d\u0917\u093e"
    ],
    "name:hun_x_preferred":[
        "Sibolga"
    ],
    "name:ind_x_preferred":[
        "Sibolga"
    ],
    "name:ind_x_variant":[
        "Kota Sibolga"
    ],
    "name:ita_x_preferred":[
        "Sibolga"
    ],
    "name:jav_x_preferred":[
        "Kota Sibolga"
    ],
    "name:kor_x_preferred":[
        "\uc2dc\ubcfc\uac00"
    ],
    "name:lit_x_preferred":[
        "Sibolga"
    ],
    "name:min_x_preferred":[
        "Kota Sibolga"
    ],
    "name:mlg_x_preferred":[
        "Kota Sibolga"
    ],
    "name:msa_x_preferred":[
        "Sibolga"
    ],
    "name:nld_x_preferred":[
        "Sibolga"
    ],
    "name:pol_x_preferred":[
        "Sibolga"
    ],
    "name:por_x_preferred":[
        "Sibolga"
    ],
    "name:ron_x_preferred":[
        "Sibolga"
    ],
    "name:rus_x_preferred":[
        "\u0421\u0438\u0431\u043e\u043b\u0433\u0430"
    ],
    "name:swe_x_preferred":[
        "Sibolga"
    ],
    "name:tur_x_preferred":[
        "Sibolga"
    ],
    "name:urd_x_preferred":[
        "\u0633\u06cc\u0628\u0648\u0644\u06af\u0627"
    ],
    "name:vie_x_preferred":[
        "Sibolga"
    ],
    "name:war_x_preferred":[
        "Sibolga"
    ],
    "name:zho_x_preferred":[
        "\u5b9e\u6b66\u7259"
    ],
    "wof:lang_x_official":[
        "ind"
    ],
    "wof:lang_x_spoken":[
        "ind",
        "eng"
    ],
    "wof:name":"Sibolga",
    "wof:placetype":"locality"
},
  "geometry": {"coordinates":[98.6078,2.1378],"type":"Point"}
}