{
  "type": "Feature",
  "properties": {
    "gn:admin1_code":"7.0",
    "gn:asciiname":"Perumahan Angkatan Bersenjata Republik Indonesia",
    "gn:country_code":"ID",
    "gn:dem":20,
    "gn:feature_class":"P",
    "gn:feature_code":"PPL",
    "gn:name":"Perumahan Angkatan Bersenjata Republik Indonesia",
    "gn:population":0,
    "gn:timezone":"Asia/Jakarta",
    "iso:country":"ID",
    "name:ind_x_preferred":[
        "Perumahan Angkatan Bersenjata Republik Indonesia"
    ],
    "name:und_x_variant":[
        "Perumahan ABRI"
    ],
    "wof:name":"Perumahan Angkatan Bersenjata Republik Indonesia",
    "wof:placetype":"locality"
},
  "geometry": {"coordinates":[111.3421,-6.7197],"type":"Point"}
}