{
  "type": "Feature",
  "properties": {
    "gn:admin1_code":"7.0",
    "gn:asciiname":"Wageair",
    "gn:country_code":"ID",
    "gn:dem":45,
    "gn:feature_class":"P",
    "gn:feature_code":"PPL",
    "gn:name":"Wageair",
    "gn:population":0,
    "gn:timezone":"Asia/Jakarta",
    "iso:country":"ID",
    "name:ind_x_preferred":[
        "Wageair"
    ],
    "wof:name":"Wageair",
    "wof:placetype":"locality"
},
  "geometry": {"coordinates":[109.45471999999999,-7.60528],"type":"Point"}
}