{
  "type": "Feature",
  "properties": {
    "gn:admin1_code":"7.0",
    "gn:asciiname":"Gembleb",
    "gn:country_code":"ID",
    "gn:dem":644,
    "gn:feature_class":"P",
    "gn:feature_code":"PPL",
    "gn:name":"Gembleb",
    "gn:population":0,
    "gn:timezone":"Asia/Jakarta",
    "iso:country":"ID",
    "wof:name":"Gembleb",
    "wof:placetype":"locality"
},
  "geometry": {"coordinates":[110.23721999999999,-7.27444],"type":"Point"}
}