{
  "type": "Feature",
  "properties": {
    "gn:admin1_code":"26.0",
    "gn:asciiname":"Pondok Serbangan",
    "gn:country_code":"ID",
    "gn:dem":14,
    "gn:feature_class":"P",
    "gn:feature_code":"PPL",
    "gn:name":"Pondok Serbangan",
    "gn:population":0,
    "gn:timezone":"Asia/Jakarta",
    "iso:country":"ID",
    "name:ind_x_preferred":[
        "Pondok Serbangan"
    ],
    "name:und_x_variant":[
        "Serbangan"
    ],
    "wof:name":"Pondok Serbangan",
    "wof:placetype":"locality"
},
  "geometry": {"coordinates":[99.6583,3.0245],"type":"Point"}
}