{
  "type": "Feature",
  "properties": {
    "gn:admin1_code":"30.0",
    "gn:asciiname":"Tegalsadang",
    "gn:country_code":"ID",
    "gn:dem":520,
    "gn:feature_class":"P",
    "gn:feature_code":"PPL",
    "gn:name":"Tegalsadang",
    "gn:population":0,
    "gn:timezone":"Asia/Jakarta",
    "iso:country":"ID",
    "name:ind_x_preferred":[
        "Tegalsadang"
    ],
    "wof:name":"Tegalsadang",
    "wof:placetype":"locality"
},
  "geometry": {"coordinates":[106.76649999999999,-7.1635],"type":"Point"}
}