{
  "type": "Feature",
  "properties": {
    "gn:admin1_code":"1",
    "gn:asciiname":"Iemameh",
    "gn:country_code":"ID",
    "gn:dem":9,
    "gn:feature_class":"P",
    "gn:feature_code":"PPL",
    "gn:name":"Iemameh",
    "gn:population":0,
    "gn:timezone":"Asia/Jakarta",
    "iso:country":"ID",
    "name:ind_x_preferred":[
        "Iemameh"
    ],
    "wof:name":"Iemameh",
    "wof:placetype":"locality"
},
  "geometry": {"coordinates":[96.7794,3.7614],"type":"Point"}
}