{
  "type": "Feature",
  "properties": {
    "gn:admin1_code":"30",
    "gn:asciiname":"Calincingsindangsaluyu",
    "gn:country_code":"ID",
    "gn:dem":245,
    "gn:feature_class":"P",
    "gn:feature_code":"PPL",
    "gn:name":"Calincingsindangsaluyu",
    "gn:population":0,
    "gn:timezone":"Asia/Jakarta",
    "iso:country":"ID",
    "name:ind_x_preferred":[
        "Calincingsindangsaluyu"
    ],
    "wof:name":"Calincingsindangsaluyu",
    "wof:placetype":"locality"
},
  "geometry": {"coordinates":[107.27249999999999,-6.77083],"type":"Point"}
}