{
  "type": "Feature",
  "properties": {
    "gn:admin1_code":"10",
    "gn:asciiname":"Sanggrahan Satu",
    "gn:country_code":"ID",
    "gn:dem":371,
    "gn:feature_class":"P",
    "gn:feature_code":"PPL",
    "gn:name":"Sanggrahan Satu",
    "gn:population":0,
    "gn:timezone":"Asia/Jakarta",
    "iso:country":"ID",
    "wof:name":"Sanggrahan Satu",
    "wof:placetype":"locality"
},
  "geometry": {"coordinates":[110.45,-7.90583],"type":"Point"}
}