{
  "type": "Feature",
  "properties": {
    "gn:admin1_code":"8.0",
    "gn:asciiname":"Bates",
    "gn:country_code":"ID",
    "gn:dem":19,
    "gn:feature_class":"P",
    "gn:feature_code":"PPL",
    "gn:name":"Bates",
    "gn:population":0,
    "gn:timezone":"Asia/Jakarta",
    "iso:country":"ID",
    "name:ces_x_preferred":[
        "Bates"
    ],
    "name:deu_x_preferred":[
        "Bates"
    ],
    "name:ind_x_preferred":[
        "Bates"
    ],
    "name:rus_x_preferred":[
        "\u0411\u0435\u0439\u0442\u0441"
    ],
    "wof:lang_x_official":[
        "ind"
    ],
    "wof:lang_x_spoken":[
        "ind",
        "eng"
    ],
    "wof:name":"Bates",
    "wof:placetype":"locality"
},
  "geometry": {"coordinates":[113.58369,-7.12819],"type":"Point"}
}