{
  "type": "Feature",
  "properties": {
    "gn:admin1_code":"26",
    "gn:asciiname":"Togijita",
    "gn:country_code":"ID",
    "gn:dem":329,
    "gn:feature_class":"P",
    "gn:feature_code":"PPL",
    "gn:name":"Togijita",
    "gn:population":0,
    "gn:timezone":"Asia/Jakarta",
    "iso:country":"ID",
    "name:ind_x_preferred":[
        "Togijita"
    ],
    "name:und_x_variant":[
        "Togidjita"
    ],
    "wof:name":"Togijita",
    "wof:placetype":"locality"
},
  "geometry": {"coordinates":[97.6007,1.0311],"type":"Point"}
}