{
  "type": "Feature",
  "properties": {
    "gn:admin1_code":"41.0",
    "gn:asciiname":"Taupe",
    "gn:country_code":"ID",
    "gn:dem":1329,
    "gn:feature_class":"P",
    "gn:feature_code":"PPL",
    "gn:name":"Taupe",
    "gn:population":0,
    "gn:timezone":"Asia/Makassar",
    "iso:country":"ID",
    "name:afr_x_preferred":[
        "Taupe"
    ],
    "name:cat_x_preferred":[
        "Taup"
    ],
    "name:deu_x_preferred":[
        "Taupe"
    ],
    "name:hin_x_preferred":[
        "\u091f\u093e\u0909\u092a"
    ],
    "name:ind_x_preferred":[
        "Taupe"
    ],
    "name:ita_x_preferred":[
        "Talpa"
    ],
    "name:msa_x_preferred":[
        "Kelabu kecoklatan"
    ],
    "name:nld_x_preferred":[
        "Taupe"
    ],
    "wof:name":"Taupe",
    "wof:placetype":"locality"
},
  "geometry": {"coordinates":[119.35120000000001,-2.9281],"type":"Point"}
}