{
  "type": "Feature",
  "properties": {
    "gn:country":"ID",
    "gn:fcode":"PPL",
    "gn:pop":0,
    "iso:country":"ID",
    "name:ind_x_preferred":[
        "Girian"
    ],
    "qs:name":"Girian",
    "qs:name_adm0":"Indonesia",
    "qs:name_adm1":"Sulawesi Utara",
    "qs:photos_9k":1,
    "qs:photos_9r":2,
    "qs:photos_all":26,
    "qs:photos_sr":0,
    "qs:placetype":"Town",
    "qs:pop_sr":"0",
    "wof:lang_x_official":[
        "ind"
    ],
    "wof:lang_x_spoken":[
        "ind",
        "eng"
    ],
    "wof:name":"Girian",
    "wof:placetype":"locality",
    "wof:population":0
},
  "geometry": {"coordinates":[125.1384,1.4394],"type":"Point"}
}