{
  "type": "Feature",
  "properties": {
    "gn:admin1_code":"0.0",
    "gn:asciiname":"Pebedilan-kulon",
    "gn:cc2":"ID",
    "gn:country_code":"ID",
    "gn:dem":8,
    "gn:feature_class":"P",
    "gn:feature_code":"PPL",
    "gn:name":"Pebedilan-kulon",
    "gn:population":0,
    "gn:timezone":"Asia/Jakarta",
    "iso:country":"ID",
    "name:und_x_variant":[
        "Pebedilan-koelon",
        "Pebedilan-kulon"
    ],
    "wof:name":"Pebedilan-kulon",
    "wof:placetype":"locality"
},
  "geometry": {"coordinates":[108.75,-6.86667],"type":"Point"}
}