{
  "type": "Feature",
  "properties": {
    "gn:admin1_code":"22.0",
    "gn:asciiname":"Unauna",
    "gn:country_code":"ID",
    "gn:dem":13,
    "gn:feature_class":"P",
    "gn:feature_code":"PPL",
    "gn:name":"Unauna",
    "gn:population":0,
    "gn:timezone":"Asia/Makassar",
    "iso:country":"ID",
    "name:ind_x_preferred":[
        "Unauna"
    ],
    "wof:name":"Unauna",
    "wof:placetype":"locality"
},
  "geometry": {"coordinates":[121.06829999999999,-3.1823],"type":"Point"}
}