{
  "type": "Feature",
  "properties": {
    "gn:admin1_code":"30",
    "gn:asciiname":"Margaluyu",
    "gn:country_code":"ID",
    "gn:dem":490,
    "gn:feature_class":"P",
    "gn:feature_code":"PPL",
    "gn:name":"Margaluyu",
    "gn:population":0,
    "gn:timezone":"Asia/Jakarta",
    "iso:country":"ID",
    "name:ind_x_preferred":[
        "Margaluyu"
    ],
    "wof:name":"Margaluyu",
    "wof:placetype":"locality"
},
  "geometry": {"coordinates":[107.93861,-6.82944],"type":"Point"}
}