{
  "type": "Feature",
  "properties": {
    "gn:admin1_code":"18",
    "gn:asciiname":"Patab",
    "gn:country_code":"ID",
    "gn:dem":505,
    "gn:feature_class":"P",
    "gn:feature_code":"PPL",
    "gn:name":"Patab",
    "gn:population":0,
    "gn:timezone":"Asia/Makassar",
    "iso:country":"ID",
    "wof:name":"Patab",
    "wof:placetype":"locality"
},
  "geometry": {"coordinates":[124.75306,-9.68389],"type":"Point"}
}