{
  "type": "Feature",
  "properties": {
    "gn:admin1_code":"34.0",
    "gn:asciiname":"Bunoyo Tengah",
    "gn:country_code":"ID",
    "gn:dem":19,
    "gn:feature_class":"P",
    "gn:feature_code":"PPL",
    "gn:name":"Bunoyo Tengah",
    "gn:population":0,
    "gn:timezone":"Asia/Makassar",
    "iso:country":"ID",
    "name:ind_x_preferred":[
        "Bunoyo Tengah"
    ],
    "wof:name":"Bunoyo Tengah",
    "wof:placetype":"locality"
},
  "geometry": {"coordinates":[122.0754,0.4993],"type":"Point"}
}