{
  "type": "Feature",
  "properties": {
    "gn:admin1_code":"21",
    "gn:asciiname":"Tang",
    "gn:country_code":"ID",
    "gn:dem":12,
    "gn:feature_class":"P",
    "gn:feature_code":"PPL",
    "gn:name":"Tang",
    "gn:population":0,
    "gn:timezone":"Asia/Makassar",
    "iso:country":"ID",
    "name:ceb_x_preferred":[
        "Tang"
    ],
    "name:dan_x_preferred":[
        "Tang"
    ],
    "name:deu_x_preferred":[
        "Tang"
    ],
    "name:est_x_preferred":[
        "Tang"
    ],
    "name:fin_x_preferred":[
        "Tang"
    ],
    "name:fra_x_preferred":[
        "Tang"
    ],
    "name:hun_x_preferred":[
        "Tang"
    ],
    "name:ind_x_preferred":[
        "Tang"
    ],
    "name:nld_x_preferred":[
        "Tang"
    ],
    "name:nor_x_preferred":[
        "Tang"
    ],
    "name:pol_x_preferred":[
        "Tang"
    ],
    "name:rus_x_preferred":[
        "\u0422\u0430\u043d\u0433"
    ],
    "name:spa_x_preferred":[
        "Tang"
    ],
    "name:swe_x_preferred":[
        "Tang"
    ],
    "name:ukr_x_preferred":[
        "\u0422\u0430\u043d\u0433"
    ],
    "wof:name":"Tang",
    "wof:placetype":"locality"
},
  "geometry": {"coordinates":[121.7169,1.0756],"type":"Point"}
}