{
  "type": "Feature",
  "properties": {
    "gn:admin1_code":"38.0",
    "gn:asciiname":"Poakpoak",
    "gn:country_code":"ID",
    "gn:dem":1263,
    "gn:feature_class":"P",
    "gn:feature_code":"PPL",
    "gn:name":"Poakpoak",
    "gn:population":0,
    "gn:timezone":"Asia/Makassar",
    "iso:country":"ID",
    "name:ind_x_preferred":[
        "Poakpoak"
    ],
    "wof:name":"Poakpoak",
    "wof:placetype":"locality"
},
  "geometry": {"coordinates":[119.752,-2.3521],"type":"Point"}
}