{
  "type": "Feature",
  "properties": {
    "gn:admin1_code":"15.0",
    "gn:asciiname":"Umbulan Royaliu",
    "gn:country_code":"ID",
    "gn:dem":25,
    "gn:feature_class":"P",
    "gn:feature_code":"PPL",
    "gn:name":"Umbulan Royaliu",
    "gn:population":0,
    "gn:timezone":"Asia/Jakarta",
    "iso:country":"ID",
    "name:ind_x_preferred":[
        "Umbulan Royaliu"
    ],
    "name:ind_x_variant":[
        "Oemboelan Rojalioe",
        "Umbulan Rojalu",
        "Umbulanrayaliu"
    ],
    "wof:lang_x_official":[
        "ind"
    ],
    "wof:lang_x_spoken":[
        "ind",
        "eng"
    ],
    "wof:name":"Umbulan Royaliu",
    "wof:placetype":"locality"
},
  "geometry": {"coordinates":[105.3725,-4.68],"type":"Point"}
}