{
  "type": "Feature",
  "properties": {
    "gn:admin1_code":"37",
    "gn:asciiname":"Pulauhalangbelakang",
    "gn:country_code":"ID",
    "gn:dem":0,
    "gn:feature_class":"P",
    "gn:feature_code":"PPL",
    "gn:name":"Pulauhalangbelakang",
    "gn:population":0,
    "gn:timezone":"Asia/Pontianak",
    "iso:country":"ID",
    "name:ind_x_preferred":[
        "Pulauhalangbelakang"
    ],
    "wof:name":"Pulauhalangbelakang",
    "wof:placetype":"locality"
},
  "geometry": {"coordinates":[100.64278,2.18665],"type":"Point"}
}