{
  "type": "Feature",
  "properties": {
    "gn:admin1_code":"2.0",
    "gn:asciiname":"Tunglangan",
    "gn:country_code":"ID",
    "gn:dem":333,
    "gn:feature_class":"P",
    "gn:feature_code":"PPL",
    "gn:name":"Tunglangan",
    "gn:population":0,
    "gn:timezone":"Asia/Makassar",
    "iso:country":"ID",
    "name:ind_x_preferred":[
        "Tunglangan"
    ],
    "wof:name":"Tunglangan",
    "wof:placetype":"locality"
},
  "geometry": {"coordinates":[115.1634,-8.4497],"type":"Point"}
}