{
  "type": "Feature",
  "properties": {
    "gn:admin1_code":"1",
    "gn:asciiname":"Hagu",
    "gn:country_code":"ID",
    "gn:dem":17,
    "gn:feature_class":"P",
    "gn:feature_code":"PPL",
    "gn:name":"Hagu",
    "gn:population":0,
    "gn:timezone":"Asia/Jakarta",
    "iso:country":"ID",
    "name:ind_x_preferred":[
        "Hagu"
    ],
    "name:und_x_variant":[
        "Pantehagu"
    ],
    "wof:name":"Hagu",
    "wof:placetype":"locality"
},
  "geometry": {"coordinates":[96.58499999999999,5.1756],"type":"Point"}
}