{
  "type": "Feature",
  "properties": {
    "gn:admin1_code":"30",
    "gn:asciiname":"Bakom Kulon",
    "gn:country_code":"ID",
    "gn:dem":254,
    "gn:feature_class":"P",
    "gn:feature_code":"PPL",
    "gn:name":"Bakom Kulon",
    "gn:population":0,
    "gn:timezone":"Asia/Jakarta",
    "iso:country":"ID",
    "name:ind_x_preferred":[
        "Bakom Kulon"
    ],
    "wof:name":"Bakom Kulon",
    "wof:placetype":"locality"
},
  "geometry": {"coordinates":[107.23806,-6.75861],"type":"Point"}
}