{
  "type": "Feature",
  "properties": {
    "gn:admin1_code":"8",
    "gn:asciiname":"Mangirejo",
    "gn:country_code":"ID",
    "gn:dem":118,
    "gn:feature_class":"P",
    "gn:feature_code":"PPL",
    "gn:name":"Mangirejo",
    "gn:population":0,
    "gn:timezone":"Asia/Jakarta",
    "iso:country":"ID",
    "name:ind_x_preferred":[
        "Mangirejo"
    ],
    "wof:name":"Mangirejo",
    "wof:placetype":"locality"
},
  "geometry": {"coordinates":[111.7371,-7.5452],"type":"Point"}
}