{
  "type": "Feature",
  "properties": {
    "gn:admin1_code":"21.0",
    "gn:asciiname":"Peley",
    "gn:country_code":"ID",
    "gn:dem":38,
    "gn:feature_class":"P",
    "gn:feature_code":"PPL",
    "gn:name":"Peley",
    "gn:population":0,
    "gn:timezone":"Asia/Makassar",
    "iso:country":"ID",
    "name:ind_x_preferred":[
        "Peley"
    ],
    "name:und_x_variant":[
        "Pelei"
    ],
    "wof:name":"Peley",
    "wof:placetype":"locality"
},
  "geometry": {"coordinates":[123.4709,-1.4601],"type":"Point"}
}