{
  "type": "Feature",
  "properties": {
    "gn:admin1_code":"07",
    "gn:asciiname":"Bojo",
    "gn:country_code":"ID",
    "gn:dem":174,
    "gn:feature_class":"P",
    "gn:feature_code":"PPL",
    "gn:name":"Bojo",
    "gn:population":0,
    "gn:timezone":"Asia/Jakarta",
    "iso:country":"ID",
    "name:und_x_variant":[
        "Bodjo",
        "Bojo"
    ],
    "wof:name":"Bojo",
    "wof:placetype":"locality"
},
  "geometry": {"coordinates":[110.70056,-7.25139],"type":"Point"}
}