{
  "type": "Feature",
  "properties": {
    "gn:admin1_code":"7",
    "gn:asciiname":"Pucung",
    "gn:country_code":"ID",
    "gn:dem":63,
    "gn:feature_class":"P",
    "gn:feature_code":"PPL",
    "gn:name":"Pucung",
    "gn:population":0,
    "gn:timezone":"Asia/Jakarta",
    "iso:country":"ID",
    "name:ind_x_preferred":[
        "Pucung"
    ],
    "wof:name":"Pucung",
    "wof:placetype":"locality"
},
  "geometry": {"coordinates":[111.00278,-7.20667],"type":"Point"}
}