{
  "type": "Feature",
  "properties": {
    "gn:admin1_code":"28.0",
    "gn:asciiname":"Wangura Fennabu",
    "gn:country_code":"ID",
    "gn:dem":223,
    "gn:feature_class":"P",
    "gn:feature_code":"PPL",
    "gn:name":"Wangura Fennabu",
    "gn:population":0,
    "gn:timezone":"Asia/Jayapura",
    "iso:country":"ID",
    "name:ind_x_preferred":[
        "Wangura Fennabu"
    ],
    "name:und_x_variant":[
        "Wa Ngoera Fen \u2019Nabo\u00e9"
    ],
    "wof:lang_x_official":[
        "ind"
    ],
    "wof:lang_x_spoken":[
        "ind",
        "eng"
    ],
    "wof:name":"Wangura Fennabu",
    "wof:placetype":"locality"
},
  "geometry": {"coordinates":[126.84629,-3.37025],"type":"Point"}
}