{
  "type": "Feature",
  "properties": {
    "gn:admin1_code":"7.0",
    "gn:asciiname":"Ngiri",
    "gn:country_code":"ID",
    "gn:dem":121,
    "gn:feature_class":"P",
    "gn:feature_code":"PPL",
    "gn:name":"Ngiri",
    "gn:population":0,
    "gn:timezone":"Asia/Jakarta",
    "iso:country":"ID",
    "name:ceb_x_preferred":[
        "Ngiri"
    ],
    "name:fra_x_preferred":[
        "Ngiri"
    ],
    "name:swe_x_preferred":[
        "Ngiri"
    ],
    "wof:lang_x_official":[
        "ind"
    ],
    "wof:lang_x_spoken":[
        "ind",
        "eng"
    ],
    "wof:name":"Ngiri",
    "wof:placetype":"locality"
},
  "geometry": {"coordinates":[110.90971999999999,-7.58694],"type":"Point"}
}