{
  "type": "Feature",
  "properties": {
    "gn:admin1_code":"37",
    "gn:asciiname":"Tualang",
    "gn:country_code":"ID",
    "gn:dem":52,
    "gn:feature_class":"P",
    "gn:feature_code":"PPL",
    "gn:name":"Tualang",
    "gn:population":0,
    "gn:timezone":"Asia/Jakarta",
    "iso:country":"ID",
    "name:ind_x_preferred":[
        "Tualang 2"
    ],
    "name:ind_x_variant":[
        "Tualang"
    ],
    "name:und_x_variant":[
        "Tualang Dua"
    ],
    "wof:name":"Tualang",
    "wof:placetype":"locality"
},
  "geometry": {"coordinates":[101.68989999999999,0.4929],"type":"Point"}
}