{
  "type": "Feature",
  "properties": {
    "gn:admin1_code":"7",
    "gn:asciiname":"Andong",
    "gn:country_code":"ID",
    "gn:dem":18,
    "gn:feature_class":"P",
    "gn:feature_code":"PPL",
    "gn:name":"Andong",
    "gn:population":0,
    "gn:timezone":"Asia/Jakarta",
    "iso:country":"ID",
    "name:ara_x_preferred":[
        "\u0622\u0646\u062f\u0648\u0646\u063a"
    ],
    "name:cat_x_preferred":[
        "Andong"
    ],
    "name:ceb_x_preferred":[
        "Andong"
    ],
    "name:ces_x_preferred":[
        "Andong"
    ],
    "name:deu_x_preferred":[
        "Andong"
    ],
    "name:epo_x_preferred":[
        "Andon"
    ],
    "name:est_x_preferred":[
        "Andong"
    ],
    "name:fas_x_preferred":[
        "\u0622\u0646\u062f\u0648\u0646\u06af"
    ],
    "name:fin_x_preferred":[
        "Andong"
    ],
    "name:fra_x_preferred":[
        "Andong"
    ],
    "name:hun_x_preferred":[
        "Andong"
    ],
    "name:hye_x_preferred":[
        "\u0531\u0576\u0564\u0578\u0576\u0563"
    ],
    "name:ind_x_preferred":[
        "Andong"
    ],
    "name:ita_x_preferred":[
        "Andong"
    ],
    "name:jpn_x_preferred":[
        "\u5b89\u6771\u5e02"
    ],
    "name:kat_x_preferred":[
        "\u10d0\u10dc\u10d3\u10dd\u10dc\u10d8"
    ],
    "name:kor_x_preferred":[
        "\uc548\ub3d9\uc2dc"
    ],
    "name:lit_x_preferred":[
        "Andongas"
    ],
    "name:lmo_x_preferred":[
        "Andong"
    ],
    "name:mon_x_preferred":[
        "\u0410\u043d\u044c\u0434\u0443\u043d"
    ],
    "name:msa_x_preferred":[
        "Andong"
    ],
    "name:nld_x_preferred":[
        "Andong"
    ],
    "name:nor_x_preferred":[
        "Andong"
    ],
    "name:pol_x_preferred":[
        "Andong"
    ],
    "name:por_x_preferred":[
        "Andong"
    ],
    "name:ron_x_preferred":[
        "Andong"
    ],
    "name:rus_x_preferred":[
        "\u0410\u043d\u0434\u043e\u043d"
    ],
    "name:spa_x_preferred":[
        "Andong"
    ],
    "name:swe_x_preferred":[
        "Andong"
    ],
    "name:tgl_x_preferred":[
        "Andong"
    ],
    "name:tha_x_preferred":[
        "\u0e2d\u0e31\u0e19\u0e14\u0e07"
    ],
    "name:tur_x_preferred":[
        "Andong"
    ],
    "name:ukr_x_preferred":[
        "\u0410\u043d\u0434\u043e\u043d"
    ],
    "name:urd_x_preferred":[
        "\u0627\u0646\u0688\u0648\u0646\u06af"
    ],
    "name:vie_x_preferred":[
        "Andong"
    ],
    "name:war_x_preferred":[
        "Andong"
    ],
    "name:wuu_x_preferred":[
        "\u5b89\u4e1c\u5e02"
    ],
    "name:zho_x_preferred":[
        "\u5b89\u4e1c\u5e02"
    ],
    "wof:lang_x_official":[
        "ind"
    ],
    "wof:lang_x_spoken":[
        "ind",
        "eng"
    ],
    "wof:name":"Andong",
    "wof:placetype":"locality"
},
  "geometry": {"coordinates":[110.1019,-6.9752],"type":"Point"}
}