{
  "type": "Feature",
  "properties": {
    "gn:admin1_code":"33.0",
    "gn:asciiname":"Tarikolot",
    "gn:country_code":"ID",
    "gn:dem":169,
    "gn:feature_class":"P",
    "gn:feature_code":"PPLA4",
    "gn:name":"Tarikolot",
    "gn:population":0,
    "gn:timezone":"Asia/Jakarta",
    "iso:country":"ID",
    "name:ind_x_preferred":[
        "Tarikolot"
    ],
    "wof:lang_x_official":[
        "ind"
    ],
    "wof:lang_x_spoken":[
        "ind",
        "eng"
    ],
    "wof:name":"Tarikolot",
    "wof:placetype":"locality"
},
  "geometry": {"coordinates":[106.01739999999999,-6.363],"type":"Point"}
}