{
  "type": "Feature",
  "properties": {
    "gn:admin1_code":"30",
    "gn:asciiname":"Kuta",
    "gn:country_code":"ID",
    "gn:dem":517,
    "gn:feature_class":"P",
    "gn:feature_code":"PPL",
    "gn:name":"Kuta",
    "gn:population":0,
    "gn:timezone":"Asia/Jakarta",
    "iso:country":"ID",
    "name:ind_x_preferred":[
        "Kuta"
    ],
    "wof:name":"Kuta",
    "wof:placetype":"locality"
},
  "geometry": {"coordinates":[106.75667,-6.79056],"type":"Point"}
}