{
  "type": "Feature",
  "properties": {
    "gn:admin1_code":"18.0",
    "gn:asciiname":"Prekahembi",
    "gn:country_code":"ID",
    "gn:dem":19,
    "gn:feature_class":"P",
    "gn:feature_code":"PPL",
    "gn:name":"Prekahembi",
    "gn:population":0,
    "gn:timezone":"Asia/Makassar",
    "iso:country":"ID",
    "name:ind_x_preferred":[
        "Prekahembi"
    ],
    "name:und_x_variant":[
        "Kahembi"
    ],
    "wof:name":"Prekahembi",
    "wof:placetype":"locality"
},
  "geometry": {"coordinates":[120.67004,-9.94303],"type":"Point"}
}