{
  "type": "Feature",
  "properties": {
    "gn:admin1_code":"18",
    "gn:asciiname":"Bilas",
    "gn:country_code":"ID",
    "gn:dem":1084,
    "gn:feature_class":"P",
    "gn:feature_code":"PPL",
    "gn:name":"Bilas",
    "gn:population":0,
    "gn:timezone":"Asia/Makassar",
    "iso:country":"ID",
    "name:ind_x_preferred":[
        "Bilas"
    ],
    "name:ukr_x_preferred":[
        "\u0411\u0456\u043b\u0430\u0441"
    ],
    "wof:lang_x_official":[
        "ind"
    ],
    "wof:lang_x_spoken":[
        "ind",
        "eng"
    ],
    "wof:name":"Bilas",
    "wof:placetype":"locality"
},
  "geometry": {"coordinates":[120.45,-8.5826],"type":"Point"}
}