{
  "type": "Feature",
  "properties": {
    "gn:admin1_code":"29.0",
    "gn:asciiname":"Umaoya",
    "gn:country_code":"ID",
    "gn:dem":16,
    "gn:feature_class":"P",
    "gn:feature_code":"PPL",
    "gn:name":"Umaoya",
    "gn:population":0,
    "gn:timezone":"Asia/Jayapura",
    "iso:country":"ID",
    "name:ind_x_preferred":[
        "Umaoya"
    ],
    "name:und_x_variant":[
        "Oema\u2019oja",
        "Umaoja",
        "Umaoya"
    ],
    "wof:lang_x_official":[
        "ind"
    ],
    "wof:lang_x_spoken":[
        "ind",
        "eng"
    ],
    "wof:name":"Umaoya",
    "wof:placetype":"locality"
},
  "geometry": {"coordinates":[125.96214000000001,-2.10746],"type":"Point"}
}