{
  "type": "Feature",
  "properties": {
    "gn:admin1_code":"8.0",
    "gn:asciiname":"Codo Timursawah",
    "gn:country_code":"ID",
    "gn:dem":495,
    "gn:feature_class":"P",
    "gn:feature_code":"PPL",
    "gn:name":"Codo Timursawah",
    "gn:population":0,
    "gn:timezone":"Asia/Jakarta",
    "iso:country":"ID",
    "name:ind_x_preferred":[
        "Codo Timursawah"
    ],
    "wof:name":"Codo Timursawah",
    "wof:placetype":"locality"
},
  "geometry": {"coordinates":[112.74393000000001,-8.12608],"type":"Point"}
}