{
  "type": "Feature",
  "properties": {
    "gn:admin1_code":"38.0",
    "gn:asciiname":"Ranoang",
    "gn:country_code":"ID",
    "gn:dem":725,
    "gn:feature_class":"P",
    "gn:feature_code":"PPL",
    "gn:name":"Ranoang",
    "gn:population":0,
    "gn:timezone":"Asia/Makassar",
    "iso:country":"ID",
    "name:ind_x_preferred":[
        "Ranoang"
    ],
    "name:und_x_variant":[
        "Ranoeang",
        "Ranuang"
    ],
    "wof:name":"Ranoang",
    "wof:placetype":"locality"
},
  "geometry": {"coordinates":[119.62949999999999,-3.0459],"type":"Point"}
}