{
  "type": "Feature",
  "properties": {
    "gn:admin1_code":"35",
    "gn:asciiname":"Tuit",
    "gn:country_code":"ID",
    "gn:dem":32,
    "gn:feature_class":"P",
    "gn:feature_code":"PPL",
    "gn:name":"Tuit",
    "gn:population":0,
    "gn:timezone":"Asia/Jakarta",
    "iso:country":"ID",
    "name:ind_x_preferred":[
        "Tuit"
    ],
    "wof:name":"Tuit",
    "wof:placetype":"locality"
},
  "geometry": {"coordinates":[105.69018,-1.8391],"type":"Point"}
}