{
  "type": "Feature",
  "properties": {
    "gn:admin1_code":"24.0",
    "gn:asciiname":"Lubukasam",
    "gn:country_code":"ID",
    "gn:dem":87,
    "gn:feature_class":"P",
    "gn:feature_code":"PPL",
    "gn:name":"Lubukasam",
    "gn:population":0,
    "gn:timezone":"Asia/Jakarta",
    "iso:country":"ID",
    "name:ind_x_preferred":[
        "Lubukasam"
    ],
    "wof:name":"Lubukasam",
    "wof:placetype":"locality"
},
  "geometry": {"coordinates":[101.6915,-1.1294],"type":"Point"}
}