{
  "type": "Feature",
  "properties": {
    "gn:admin1_code":"15.0",
    "gn:asciiname":"Rajabasalama Tiga",
    "gn:country_code":"ID",
    "gn:dem":35,
    "gn:feature_class":"P",
    "gn:feature_code":"PPL",
    "gn:name":"Rajabasalama Tiga",
    "gn:population":0,
    "gn:timezone":"Asia/Jakarta",
    "iso:country":"ID",
    "name:ind_x_preferred":[
        "Rajabasalama Tiga"
    ],
    "name:und_x_variant":[
        "Rajabasalama 3"
    ],
    "wof:name":"Rajabasalama Tiga",
    "wof:placetype":"locality"
},
  "geometry": {"coordinates":[105.66297,-5.09032],"type":"Point"}
}