{
  "type": "Feature",
  "properties": {
    "gn:admin1_code":"33",
    "gn:asciiname":"Cimanggu Baru",
    "gn:country_code":"ID",
    "gn:dem":44,
    "gn:feature_class":"P",
    "gn:feature_code":"PPL",
    "gn:name":"Cimanggu Baru",
    "gn:population":0,
    "gn:timezone":"Asia/Jakarta",
    "iso:country":"ID",
    "name:ind_x_preferred":[
        "Cimanggu Baru"
    ],
    "name:und_x_variant":[
        "Cimangmaggu Baru"
    ],
    "wof:name":"Cimanggu Baru",
    "wof:placetype":"locality"
},
  "geometry": {"coordinates":[106.26949999999999,-6.3738],"type":"Point"}
}