{
  "type": "Feature",
  "properties": {
    "gn:admin1_code":"32.0",
    "gn:asciiname":"Talang Grincingmas",
    "gn:country_code":"ID",
    "gn:dem":238,
    "gn:feature_class":"P",
    "gn:feature_code":"PPL",
    "gn:name":"Talang Grincingmas",
    "gn:population":0,
    "gn:timezone":"Asia/Jakarta",
    "iso:country":"ID",
    "name:ind_x_preferred":[
        "Talang Grincingmas"
    ],
    "name:und_x_variant":[
        "Talanggrintjingmas",
        "Talanggrincingmas"
    ],
    "wof:lang_x_official":[
        "ind"
    ],
    "wof:lang_x_spoken":[
        "ind",
        "eng"
    ],
    "wof:name":"Talang Grincingmas",
    "wof:placetype":"locality"
},
  "geometry": {"coordinates":[103.90459,-3.95221],"type":"Point"}
}