{
  "type": "Feature",
  "properties": {
    "gn:admin1_code":"21.0",
    "gn:asciiname":"Ujuna",
    "gn:country_code":"ID",
    "gn:dem":7,
    "gn:feature_class":"P",
    "gn:feature_code":"PPL",
    "gn:name":"Ujuna",
    "gn:population":0,
    "gn:timezone":"Asia/Makassar",
    "iso:country":"ID",
    "name:ind_x_preferred":[
        "Ujuna"
    ],
    "wof:name":"Ujuna",
    "wof:placetype":"locality"
},
  "geometry": {"coordinates":[119.8133,-0.2052],"type":"Point"}
}