{
  "type": "Feature",
  "properties": {
    "gn:admin1_code":"30.0",
    "gn:asciiname":"Caringin",
    "gn:country_code":"ID",
    "gn:dem":1238,
    "gn:feature_class":"P",
    "gn:feature_code":"PPL",
    "gn:name":"Caringin",
    "gn:population":0,
    "gn:timezone":"Asia/Jakarta",
    "iso:country":"ID",
    "name:ind_x_preferred":[
        "Caringin"
    ],
    "name:und_x_variant":[
        "Tjaringin"
    ],
    "wof:lang_x_official":[
        "ind"
    ],
    "wof:lang_x_spoken":[
        "ind",
        "eng"
    ],
    "wof:name":"Caringin",
    "wof:placetype":"locality"
},
  "geometry": {"coordinates":[107.79640000000001,-7.3245],"type":"Point"}
}