{
  "type": "Feature",
  "properties": {
    "gn:admin1_code":"7",
    "gn:asciiname":"Pekeongan Kidul",
    "gn:country_code":"ID",
    "gn:dem":10,
    "gn:feature_class":"P",
    "gn:feature_code":"PPL",
    "gn:name":"Pekeongan Kidul",
    "gn:population":0,
    "gn:timezone":"Asia/Jakarta",
    "iso:country":"ID",
    "name:ind_x_preferred":[
        "Pekeongan Kidul"
    ],
    "wof:name":"Pekeongan Kidul",
    "wof:placetype":"locality"
},
  "geometry": {"coordinates":[110.14709999999999,-6.9358],"type":"Point"}
}