{
  "type": "Feature",
  "properties": {
    "gn:admin1_code":"18.0",
    "gn:asciiname":"Tondongkampas",
    "gn:country_code":"ID",
    "gn:dem":125,
    "gn:feature_class":"P",
    "gn:feature_code":"PPL",
    "gn:name":"Tondongkampas",
    "gn:population":0,
    "gn:timezone":"Asia/Makassar",
    "iso:country":"ID",
    "name:ind_x_preferred":[
        "Tondongkampas"
    ],
    "wof:name":"Tondongkampas",
    "wof:placetype":"locality"
},
  "geometry": {"coordinates":[120.1426,-8.6877],"type":"Point"}
}