{
  "type": "Feature",
  "properties": {
    "gn:admin1_code":"30.0",
    "gn:asciiname":"Cikukuk",
    "gn:country_code":"ID",
    "gn:dem":827,
    "gn:feature_class":"P",
    "gn:feature_code":"PPL",
    "gn:name":"Cikukuk",
    "gn:population":0,
    "gn:timezone":"Asia/Jakarta",
    "iso:country":"ID",
    "name:ind_x_preferred":[
        "Cikukuk"
    ],
    "name:und_x_variant":[
        "Tjikoekoek"
    ],
    "wof:name":"Cikukuk",
    "wof:placetype":"locality"
},
  "geometry": {"coordinates":[108.3233,-7.1005],"type":"Point"}
}