{
  "type": "Feature",
  "properties": {
    "gn:admin1_code":"12.0",
    "gn:asciiname":"Manggajaya",
    "gn:country_code":"ID",
    "gn:dem":337,
    "gn:feature_class":"P",
    "gn:feature_code":"PPL",
    "gn:name":"Manggajaya",
    "gn:population":0,
    "gn:timezone":"Asia/Makassar",
    "iso:country":"ID",
    "name:ind_x_preferred":[
        "Manggajaya"
    ],
    "name:und_x_variant":[
        "Mangandjaja",
        "Manganajaja",
        "Manganjaya"
    ],
    "wof:lang_x_official":[
        "ind"
    ],
    "wof:lang_x_spoken":[
        "ind",
        "eng"
    ],
    "wof:name":"Manggajaya",
    "wof:placetype":"locality"
},
  "geometry": {"coordinates":[115.80500000000001,-2.5936],"type":"Point"}
}