{
  "type": "Feature",
  "properties": {
    "gn:admin1_code":"18.0",
    "gn:asciiname":"Lariwane",
    "gn:country_code":"ID",
    "gn:dem":144,
    "gn:feature_class":"P",
    "gn:feature_code":"PPL",
    "gn:name":"Lariwane",
    "gn:population":0,
    "gn:timezone":"Asia/Makassar",
    "iso:country":"ID",
    "name:ind_x_preferred":[
        "Lariwane"
    ],
    "wof:name":"Lariwane",
    "wof:placetype":"locality"
},
  "geometry": {"coordinates":[121.887,-10.5712],"type":"Point"}
}