{
  "type": "Feature",
  "properties": {
    "gn:admin1_code":"37",
    "gn:asciiname":"Bekasab",
    "gn:country_code":"ID",
    "gn:dem":58,
    "gn:feature_class":"P",
    "gn:feature_code":"PPL",
    "gn:name":"Bekasab",
    "gn:population":0,
    "gn:timezone":"Asia/Jakarta",
    "iso:country":"ID",
    "name:ind_x_preferred":[
        "Bekasab"
    ],
    "wof:name":"Bekasab",
    "wof:placetype":"locality"
},
  "geometry": {"coordinates":[101.20522,1.25059],"type":"Point"}
}