{
  "type": "Feature",
  "properties": {
    "gn:admin1_code":"26",
    "gn:asciiname":"Lumban Siantar",
    "gn:country_code":"ID",
    "gn:dem":969,
    "gn:feature_class":"P",
    "gn:feature_code":"PPL",
    "gn:name":"Lumban Siantar",
    "gn:population":0,
    "gn:timezone":"Asia/Jakarta",
    "iso:country":"ID",
    "name:ind_x_preferred":[
        "Lumban Siantar"
    ],
    "wof:name":"Lumban Siantar",
    "wof:placetype":"locality"
},
  "geometry": {"coordinates":[98.9263,2.3344],"type":"Point"}
}