{
  "type": "Feature",
  "properties": {
    "gn:admin1_code":"30.0",
    "gn:asciiname":"Bojongsalam",
    "gn:country_code":"ID",
    "gn:dem":33,
    "gn:feature_class":"P",
    "gn:feature_code":"PPL",
    "gn:name":"Bojongsalam",
    "gn:population":0,
    "gn:timezone":"Asia/Jakarta",
    "iso:country":"ID",
    "name:ind_x_preferred":[
        "Bojongsalam"
    ],
    "wof:name":"Bojongsalam",
    "wof:placetype":"locality"
},
  "geometry": {"coordinates":[107.76631999999999,-7.64334],"type":"Point"}
}