{
  "type": "Feature",
  "properties": {
    "gn:admin1_code":"8.0",
    "gn:asciiname":"Suci",
    "gn:country_code":"ID",
    "gn:dem":23,
    "gn:feature_class":"P",
    "gn:feature_code":"PPL",
    "gn:name":"Suci",
    "gn:population":0,
    "gn:timezone":"Asia/Jakarta",
    "iso:country":"ID",
    "name:ell_x_preferred":[
        "\u03a3\u03bf\u03cd\u03ba\u03bf\u03b9"
    ],
    "name:ind_x_preferred":[
        "Suci"
    ],
    "name:nld_x_preferred":[
        "Suci"
    ],
    "name:ron_x_preferred":[
        "Suci"
    ],
    "wof:name":"Suci",
    "wof:placetype":"locality"
},
  "geometry": {"coordinates":[112.1609,-6.9396],"type":"Point"}
}