{
  "type": "Feature",
  "properties": {
    "gn:admin1_code":"33.0",
    "gn:asciiname":"Karangsari",
    "gn:country_code":"ID",
    "gn:dem":175,
    "gn:feature_class":"P",
    "gn:feature_code":"PPL",
    "gn:name":"Karangsari",
    "gn:population":0,
    "gn:timezone":"Asia/Jakarta",
    "iso:country":"ID",
    "name:ind_x_preferred":[
        "Karangsari"
    ],
    "wof:name":"Karangsari",
    "wof:placetype":"locality"
},
  "geometry": {"coordinates":[106.1703,-6.8595],"type":"Point"}
}