{
  "type": "Feature",
  "properties": {
    "gn:admin1_code":"30",
    "gn:asciiname":"Cinangka",
    "gn:country_code":"ID",
    "gn:dem":1161,
    "gn:feature_class":"P",
    "gn:feature_code":"PPL",
    "gn:name":"Cinangka",
    "gn:population":0,
    "gn:timezone":"Asia/Jakarta",
    "iso:country":"ID",
    "wof:name":"Cinangka",
    "wof:placetype":"locality"
},
  "geometry": {"coordinates":[107.54722,-7.13889],"type":"Point"}
}