{
  "type": "Feature",
  "properties": {
    "gn:admin1_code":"41.0",
    "gn:asciiname":"Penanian",
    "gn:country_code":"ID",
    "gn:dem":1284,
    "gn:feature_class":"P",
    "gn:feature_code":"PPL",
    "gn:name":"Penanian",
    "gn:population":0,
    "gn:timezone":"Asia/Makassar",
    "iso:country":"ID",
    "name:ind_x_preferred":[
        "Penanian"
    ],
    "wof:name":"Penanian",
    "wof:placetype":"locality"
},
  "geometry": {"coordinates":[119.4293,-2.9101],"type":"Point"}
}