{
  "type": "Feature",
  "properties": {
    "gn:admin1_code":"33",
    "gn:asciiname":"Panimbangan Hilir",
    "gn:country_code":"ID",
    "gn:dem":30,
    "gn:feature_class":"P",
    "gn:feature_code":"PPL",
    "gn:name":"Panimbangan Hilir",
    "gn:population":0,
    "gn:timezone":"Asia/Jakarta",
    "iso:country":"ID",
    "name:ind_x_preferred":[
        "Panimbangan Hilir"
    ],
    "wof:name":"Panimbangan Hilir",
    "wof:placetype":"locality"
},
  "geometry": {"coordinates":[105.88930000000001,-6.096],"type":"Point"}
}