{
  "type": "Feature",
  "properties": {
    "gn:admin1_code":"30.0",
    "gn:asciiname":"Ciparaja",
    "gn:country_code":"ID",
    "gn:dem":155,
    "gn:feature_class":"P",
    "gn:feature_code":"PPL",
    "gn:name":"Ciparaja",
    "gn:population":0,
    "gn:timezone":"Asia/Jakarta",
    "iso:country":"ID",
    "name:ind_x_preferred":[
        "Ciparaja"
    ],
    "wof:name":"Ciparaja",
    "wof:placetype":"locality"
},
  "geometry": {"coordinates":[107.1429,-7.3705],"type":"Point"}
}