{
  "type": "Feature",
  "properties": {
    "gn:admin1_code":"8",
    "gn:asciiname":"Gunongsatogel",
    "gn:country_code":"ID",
    "gn:dem":118,
    "gn:feature_class":"P",
    "gn:feature_code":"PPL",
    "gn:name":"Gunongsatogel",
    "gn:population":0,
    "gn:timezone":"Asia/Jakarta",
    "iso:country":"ID",
    "name:ind_x_preferred":[
        "Gunongsatogel"
    ],
    "wof:name":"Gunongsatogel",
    "wof:placetype":"locality"
},
  "geometry": {"coordinates":[113.224,-7.0039],"type":"Point"}
}