{
  "type": "Feature",
  "properties": {
    "gn:admin1_code":"7",
    "gn:asciiname":"Karangrejo",
    "gn:country_code":"ID",
    "gn:dem":166,
    "gn:feature_class":"P",
    "gn:feature_code":"PPL",
    "gn:name":"Karangrejo",
    "gn:population":0,
    "gn:timezone":"Asia/Jakarta",
    "iso:country":"ID",
    "name:ind_x_preferred":[
        "Karangrejo"
    ],
    "wof:name":"Karangrejo",
    "wof:placetype":"locality"
},
  "geometry": {"coordinates":[109.6409,-7.0677],"type":"Point"}
}