{
  "type": "Feature",
  "properties": {
    "gn:admin1_code":"0.0",
    "gn:asciiname":"Asur",
    "gn:cc2":"ID",
    "gn:country_code":"ID",
    "gn:dem":31,
    "gn:feature_class":"P",
    "gn:feature_code":"PPL",
    "gn:name":"Asur",
    "gn:population":0,
    "gn:timezone":"Asia/Jayapura",
    "iso:country":"ID",
    "name:deu_x_preferred":[
        "Asur"
    ],
    "name:eus_x_preferred":[
        "Asur"
    ],
    "name:und_x_variant":[
        "Asoer",
        "Asur"
    ],
    "wof:lang_x_official":[
        "ind"
    ],
    "wof:lang_x_spoken":[
        "ind",
        "eng"
    ],
    "wof:name":"Asur",
    "wof:placetype":"locality"
},
  "geometry": {"coordinates":[140.86667,-6.86667],"type":"Point"}
}