{
  "type": "Feature",
  "properties": {
    "gn:admin1_code":"2.0",
    "gn:asciiname":"Banjar Rangdu",
    "gn:country_code":"ID",
    "gn:dem":48,
    "gn:feature_class":"P",
    "gn:feature_code":"PPL",
    "gn:name":"Banjar Rangdu",
    "gn:population":0,
    "gn:timezone":"Asia/Makassar",
    "iso:country":"ID",
    "name:ind_x_preferred":[
        "Banjar Rangdu"
    ],
    "wof:name":"Banjar Rangdu",
    "wof:placetype":"locality"
},
  "geometry": {"coordinates":[114.68170000000001,-8.3564],"type":"Point"}
}