{
  "type": "Feature",
  "properties": {
    "gn:admin1_code":"26.0",
    "gn:asciiname":"Lumban Holang-holang",
    "gn:country_code":"ID",
    "gn:dem":1121,
    "gn:feature_class":"P",
    "gn:feature_code":"PPL",
    "gn:name":"Lumban Holang-holang",
    "gn:population":0,
    "gn:timezone":"Asia/Jakarta",
    "iso:country":"ID",
    "name:ind_x_preferred":[
        "Lumban Holang-holang"
    ],
    "wof:name":"Lumban Holang-holang",
    "wof:placetype":"locality"
},
  "geometry": {"coordinates":[98.73099999999999,2.578],"type":"Point"}
}