{
  "type": "Feature",
  "properties": {
    "gn:admin1_code":"8",
    "gn:asciiname":"Gendu",
    "gn:country_code":"ID",
    "gn:dem":441,
    "gn:feature_class":"P",
    "gn:feature_code":"PPL",
    "gn:name":"Gendu",
    "gn:population":0,
    "gn:timezone":"Asia/Jakarta",
    "iso:country":"ID",
    "name:ind_x_preferred":[
        "Gendu"
    ],
    "wof:name":"Gendu",
    "wof:placetype":"locality"
},
  "geometry": {"coordinates":[111.6091,-7.8295],"type":"Point"}
}