{
  "type": "Feature",
  "properties": {
    "gn:admin1_code":"37.0",
    "gn:asciiname":"Sarosa",
    "gn:country_code":"ID",
    "gn:dem":120,
    "gn:feature_class":"P",
    "gn:feature_code":"PPL",
    "gn:name":"Sarosa",
    "gn:population":0,
    "gn:timezone":"Asia/Jakarta",
    "iso:country":"ID",
    "name:ceb_x_preferred":[
        "Sarosa"
    ],
    "name:ind_x_preferred":[
        "Sarosa"
    ],
    "name:ron_x_preferred":[
        "Sarosa"
    ],
    "name:swe_x_preferred":[
        "Sarosa"
    ],
    "name:war_x_preferred":[
        "Sarosa"
    ],
    "wof:lang_x_official":[
        "ind"
    ],
    "wof:lang_x_spoken":[
        "ind",
        "eng"
    ],
    "wof:name":"Sarosa",
    "wof:placetype":"locality"
},
  "geometry": {"coordinates":[101.4027,-0.5252],"type":"Point"}
}