{
  "type": "Feature",
  "properties": {
    "gn:admin1_code":"7.0",
    "gn:asciiname":"Watulurung",
    "gn:country_code":"ID",
    "gn:dem":143,
    "gn:feature_class":"P",
    "gn:feature_code":"PPL",
    "gn:name":"Watulurung",
    "gn:population":0,
    "gn:timezone":"Asia/Jakarta",
    "iso:country":"ID",
    "name:ind_x_preferred":[
        "Watulurung"
    ],
    "wof:name":"Watulurung",
    "wof:placetype":"locality"
},
  "geometry": {"coordinates":[111.36920000000001,-6.9037],"type":"Point"}
}