{
  "type": "Feature",
  "properties": {
    "gn:admin1_code":"8.0",
    "gn:asciiname":"Bandung",
    "gn:country_code":"ID",
    "gn:dem":299,
    "gn:feature_class":"P",
    "gn:feature_code":"PPLA4",
    "gn:name":"Bandung",
    "gn:population":0,
    "gn:timezone":"Asia/Jakarta",
    "iso:country":"ID",
    "name:ind_x_preferred":[
        "Bandung"
    ],
    "wof:name":"Bandung",
    "wof:placetype":"locality"
},
  "geometry": {"coordinates":[112.4618,-8.1586],"type":"Point"}
}