{
  "type": "Feature",
  "properties": {
    "gn:admin1_code":"30",
    "gn:asciiname":"Cilengkrang Lebak",
    "gn:country_code":"ID",
    "gn:dem":1078,
    "gn:feature_class":"P",
    "gn:feature_code":"PPL",
    "gn:name":"Cilengkrang Lebak",
    "gn:population":0,
    "gn:timezone":"Asia/Jakarta",
    "iso:country":"ID",
    "name:ind_x_preferred":[
        "Cilengkrang Lebak"
    ],
    "name:und_x_variant":[
        "Tjilengkrang",
        "Cilengkrang"
    ],
    "wof:name":"Cilengkrang Lebak",
    "wof:placetype":"locality"
},
  "geometry": {"coordinates":[107.53833,-6.82528],"type":"Point"}
}