{
  "type": "Feature",
  "properties": {
    "gn:admin1_code":"15.0",
    "gn:asciiname":"Brajakencana",
    "gn:country_code":"ID",
    "gn:dem":20,
    "gn:feature_class":"P",
    "gn:feature_code":"PPL",
    "gn:name":"Brajakencana",
    "gn:population":0,
    "gn:timezone":"Asia/Jakarta",
    "iso:country":"ID",
    "name:ind_x_preferred":[
        "Brajakencana"
    ],
    "wof:name":"Brajakencana",
    "wof:placetype":"locality"
},
  "geometry": {"coordinates":[105.78315000000001,-5.20623],"type":"Point"}
}