{
  "type": "Feature",
  "properties": {
    "gn:admin1_code":"30",
    "gn:asciiname":"Sicangkir",
    "gn:country_code":"ID",
    "gn:dem":15,
    "gn:feature_class":"P",
    "gn:feature_code":"PPL",
    "gn:name":"Sicangkir",
    "gn:population":0,
    "gn:timezone":"Asia/Jakarta",
    "iso:country":"ID",
    "name:ind_x_preferred":[
        "Sicangkir"
    ],
    "wof:name":"Sicangkir",
    "wof:placetype":"locality"
},
  "geometry": {"coordinates":[108.5827,-6.7838],"type":"Point"}
}