{
  "type": "Feature",
  "properties": {
    "gn:admin1_code":"30",
    "gn:asciiname":"Ciranggon Timur",
    "gn:country_code":"ID",
    "gn:dem":14,
    "gn:feature_class":"P",
    "gn:feature_code":"PPL",
    "gn:name":"Ciranggon Timur",
    "gn:population":0,
    "gn:timezone":"Asia/Jakarta",
    "iso:country":"ID",
    "name:ind_x_preferred":[
        "Ciranggon Timur"
    ],
    "wof:name":"Ciranggon Timur",
    "wof:placetype":"locality"
},
  "geometry": {"coordinates":[107.36722,-6.28528],"type":"Point"}
}