{
  "type": "Feature",
  "properties": {
    "gn:admin1_code":"30",
    "gn:asciiname":"Cihuni",
    "gn:country_code":"ID",
    "gn:dem":115,
    "gn:feature_class":"P",
    "gn:feature_code":"PPL",
    "gn:name":"Cihuni",
    "gn:population":0,
    "gn:timezone":"Asia/Jakarta",
    "iso:country":"ID",
    "name:ind_x_preferred":[
        "Cihuni"
    ],
    "wof:name":"Cihuni",
    "wof:placetype":"locality"
},
  "geometry": {"coordinates":[107.29194,-6.50639],"type":"Point"}
}