{
  "type": "Feature",
  "properties": {
    "gn:admin1_code":"7",
    "gn:asciiname":"Laren",
    "gn:country_code":"ID",
    "gn:dem":792,
    "gn:feature_class":"P",
    "gn:feature_code":"PPL",
    "gn:name":"Laren",
    "gn:population":0,
    "gn:timezone":"Asia/Jakarta",
    "iso:country":"ID",
    "name:ind_x_preferred":[
        "Laren"
    ],
    "wof:name":"Laren",
    "wof:placetype":"locality"
},
  "geometry": {"coordinates":[109.59389,-7.12917],"type":"Point"}
}