{
  "type": "Feature",
  "properties": {
    "gn:admin1_code":"30.0",
    "gn:asciiname":"Kampungbaru",
    "gn:cc2":"ID",
    "gn:country_code":"ID",
    "gn:dem":0,
    "gn:feature_class":"P",
    "gn:feature_code":"PPL",
    "gn:name":"Kampungbaru",
    "gn:population":0,
    "gn:timezone":"Asia/Jakarta",
    "iso:country":"ID",
    "name:und_x_variant":[
        "Kampoengbaroe",
        "Kampungbaru"
    ],
    "wof:name":"Kampungbaru",
    "wof:placetype":"locality"
},
  "geometry": {"coordinates":[107.02333,-5.99806],"type":"Point"}
}