{
  "type": "Feature",
  "properties": {
    "gn:admin1_code":"15.0",
    "gn:asciiname":"Umbulan Kuyurepung",
    "gn:country_code":"ID",
    "gn:dem":67,
    "gn:feature_class":"P",
    "gn:feature_code":"PPL",
    "gn:name":"Umbulan Kuyurepung",
    "gn:population":0,
    "gn:timezone":"Asia/Jakarta",
    "iso:country":"ID",
    "name:ind_x_preferred":[
        "Umbulan Kuyurepung"
    ],
    "name:und_x_variant":[
        "Umbulan Kayurepung"
    ],
    "wof:name":"Umbulan Kuyurepung",
    "wof:placetype":"locality"
},
  "geometry": {"coordinates":[104.71459,-4.4236],"type":"Point"}
}