{
  "type": "Feature",
  "properties": {
    "gn:admin1_code":"8.0",
    "gn:asciiname":"Barisan",
    "gn:country_code":"ID",
    "gn:dem":291,
    "gn:feature_class":"P",
    "gn:feature_code":"PPLA4",
    "gn:name":"Barisan",
    "gn:population":0,
    "gn:timezone":"Asia/Jakarta",
    "iso:country":"ID",
    "name:ind_x_preferred":[
        "Barisan"
    ],
    "wof:name":"Barisan",
    "wof:placetype":"locality"
},
  "geometry": {"coordinates":[112.4251,-8.1841],"type":"Point"}
}