{
  "type": "Feature",
  "properties": {
    "gn:admin1_code":"24.0",
    "gn:asciiname":"Binjai",
    "gn:country_code":"ID",
    "gn:dem":30,
    "gn:feature_class":"P",
    "gn:feature_code":"PPL",
    "gn:name":"Binjai",
    "gn:population":0,
    "gn:timezone":"Asia/Jakarta",
    "iso:country":"ID",
    "name:ind_x_preferred":[
        "Binjai"
    ],
    "wof:name":"Binjai",
    "wof:placetype":"locality"
},
  "geometry": {"coordinates":[101.0973,-2.1406],"type":"Point"}
}