{
  "type": "Feature",
  "properties": {
    "gn:admin1_code":"24.0",
    "gn:asciiname":"Binjai",
    "gn:country_code":"ID",
    "gn:dem":30,
    "gn:feature_class":"P",
    "gn:feature_code":"PPL",
    "gn:name":"Binjai",
    "gn:population":0,
    "gn:timezone":"Asia/Jakarta",
    "iso:country":"ID",
    "name:ace_x_preferred":[
        "Binjai"
    ],
    "name:afr_x_preferred":[
        "Binjai"
    ],
    "name:ara_x_preferred":[
        "\u0628\u0646\u062c\u0627\u064a"
    ],
    "name:azb_x_preferred":[
        "\u0628\u06cc\u0646\u062c\u0627\u06cc\u06cc"
    ],
    "name:ceb_x_preferred":[
        "Binjai"
    ],
    "name:fas_x_preferred":[
        "\u0628\u06cc\u0646\u062c\u0627\u06cc"
    ],
    "name:fin_x_preferred":[
        "Binjai"
    ],
    "name:fra_x_preferred":[
        "Binjai"
    ],
    "name:heb_x_preferred":[
        "\u05d1\u05d9\u05e0\u05d2'\u05d0\u05d9"
    ],
    "name:hun_x_preferred":[
        "Binjai"
    ],
    "name:ind_x_preferred":[
        "Binjai"
    ],
    "name:ind_x_variant":[
        "Kota Binjai"
    ],
    "name:ita_x_preferred":[
        "Binjai"
    ],
    "name:jav_x_preferred":[
        "Kutha Binjai"
    ],
    "name:jpn_x_preferred":[
        "\u30d3\u30f3\u30b8\u30e3\u30a4"
    ],
    "name:kor_x_preferred":[
        "\ube48\uc790\uc774"
    ],
    "name:lit_x_preferred":[
        "Bind\u017eajas"
    ],
    "name:mal_x_preferred":[
        "\u0d2c\u0d3f\u0d1e\u0d4d\u0d1a\u0d3e\u0d2f\u0d3f"
    ],
    "name:mlg_x_preferred":[
        "Kota Binjai"
    ],
    "name:msa_x_preferred":[
        "Binjai"
    ],
    "name:nld_x_preferred":[
        "Binjai"
    ],
    "name:nor_x_preferred":[
        "Binjai"
    ],
    "name:pol_x_preferred":[
        "Binjai"
    ],
    "name:rus_x_preferred":[
        "\u0411\u0438\u043d\u0434\u0436\u0430\u0439"
    ],
    "name:swe_x_preferred":[
        "Binjai"
    ],
    "name:tur_x_preferred":[
        "Binjai"
    ],
    "name:urd_x_preferred":[
        "\u0628\u0646\u062c\u0627\u0626\u06cc"
    ],
    "name:vie_x_preferred":[
        "Binjai"
    ],
    "wof:lang_x_official":[
        "ind"
    ],
    "wof:lang_x_spoken":[
        "ind",
        "eng"
    ],
    "wof:name":"Binjai",
    "wof:placetype":"locality"
},
  "geometry": {"coordinates":[101.0973,-2.1406],"type":"Point"}
}