{
  "type": "Feature",
  "properties": {
    "gn:admin1_code":"30",
    "gn:asciiname":"Babakan Bandung",
    "gn:country_code":"ID",
    "gn:dem":800,
    "gn:feature_class":"P",
    "gn:feature_code":"PPL",
    "gn:name":"Babakan Bandung",
    "gn:population":0,
    "gn:timezone":"Asia/Jakarta",
    "iso:country":"ID",
    "name:ind_x_preferred":[
        "Babakan Bandung"
    ],
    "wof:name":"Babakan Bandung",
    "wof:placetype":"locality"
},
  "geometry": {"coordinates":[107.79028,-6.91917],"type":"Point"}
}