{
  "type": "Feature",
  "properties": {
    "gn:admin1_code":"38",
    "gn:asciiname":"Pabaengbaeng",
    "gn:country_code":"ID",
    "gn:dem":21,
    "gn:feature_class":"P",
    "gn:feature_code":"PPL",
    "gn:name":"Pabaengbaeng",
    "gn:population":0,
    "gn:timezone":"Asia/Makassar",
    "iso:country":"ID",
    "name:ind_x_preferred":[
        "Pabaengbaeng"
    ],
    "wof:name":"Pabaengbaeng",
    "wof:placetype":"locality"
},
  "geometry": {"coordinates":[119.613,-5.6122],"type":"Point"}
}