{
  "type": "Feature",
  "properties": {
    "gn:admin1_code":"8.0",
    "gn:asciiname":"Bulurejo",
    "gn:country_code":"ID",
    "gn:dem":420,
    "gn:feature_class":"P",
    "gn:feature_code":"PPL",
    "gn:name":"Bulurejo",
    "gn:population":0,
    "gn:timezone":"Asia/Jakarta",
    "iso:country":"ID",
    "name:ind_x_preferred":[
        "Bulurejo"
    ],
    "wof:name":"Bulurejo",
    "wof:placetype":"locality"
},
  "geometry": {"coordinates":[111.81010000000001,-7.7165],"type":"Point"}
}