{
  "type": "Feature",
  "properties": {
    "gn:admin1_code":"1",
    "gn:asciiname":"Kedaipaya",
    "gn:country_code":"ID",
    "gn:dem":14,
    "gn:feature_class":"P",
    "gn:feature_code":"PPL",
    "gn:name":"Kedaipaya",
    "gn:population":0,
    "gn:timezone":"Asia/Jakarta",
    "iso:country":"ID",
    "name:ind_x_preferred":[
        "Kedaipaya"
    ],
    "wof:name":"Kedaipaya",
    "wof:placetype":"locality"
},
  "geometry": {"coordinates":[96.8481,3.7331],"type":"Point"}
}