{
  "type": "Feature",
  "properties": {
    "gn:admin1_code":"10",
    "gn:asciiname":"Jambe",
    "gn:country_code":"ID",
    "gn:dem":292,
    "gn:feature_class":"P",
    "gn:feature_code":"PPL",
    "gn:name":"Jambe",
    "gn:population":0,
    "gn:timezone":"Asia/Jakarta",
    "iso:country":"ID",
    "name:ind_x_preferred":[
        "Jambe"
    ],
    "name:urd_x_preferred":[
        "\u062c\u0645\u0628\u06d2"
    ],
    "wof:lang_x_official":[
        "ind"
    ],
    "wof:lang_x_spoken":[
        "ind",
        "eng"
    ],
    "wof:name":"Jambe",
    "wof:placetype":"locality"
},
  "geometry": {"coordinates":[110.42222,-8.04056],"type":"Point"}
}