{
  "type": "Feature",
  "properties": {
    "gn:admin1_code":"8.0",
    "gn:asciiname":"Sumberkates",
    "gn:country_code":"ID",
    "gn:dem":370,
    "gn:feature_class":"P",
    "gn:feature_code":"PPL",
    "gn:name":"Sumberkates",
    "gn:population":0,
    "gn:timezone":"Asia/Jakarta",
    "iso:country":"ID",
    "name:ind_x_preferred":[
        "Sumberkates"
    ],
    "wof:name":"Sumberkates",
    "wof:placetype":"locality"
},
  "geometry": {"coordinates":[112.4359,-8.1042],"type":"Point"}
}