{
  "type": "Feature",
  "properties": {
    "gn:country":"ID",
    "gn:fcode":"PPL",
    "gn:pop":0,
    "iso:country":"ID",
    "name:ban_x_preferred":[
        "Cibodas"
    ],
    "name:deu_x_preferred":[
        "Cibodas"
    ],
    "name:eng_x_preferred":[
        "Cibodas"
    ],
    "name:fra_x_preferred":[
        "Cibodas"
    ],
    "name:ind_x_preferred":[
        "Cibodas"
    ],
    "name:jav_x_preferred":[
        "Cibodas"
    ],
    "name:msa_x_preferred":[
        "Cibodas"
    ],
    "name:nld_x_preferred":[
        "Cibodas"
    ],
    "name:sun_x_preferred":[
        "Cibodas"
    ],
    "name:unk_x_variant":[
        "Tjibodas"
    ],
    "qs:name":"Cibodas",
    "qs:name_adm0":"Indonesia",
    "qs:name_adm1":"Jawa Barat",
    "qs:photos":229,
    "qs:photos_1k":46,
    "qs:photos_9k":1,
    "qs:photos_9r":4,
    "qs:photos_all":229,
    "qs:photos_sr":4,
    "qs:placetype":"Town",
    "qs:pop_sr":"0",
    "wd:wordcount":12,
    "wof:lang_x_official":[
        "ind"
    ],
    "wof:lang_x_spoken":[
        "ind",
        "eng"
    ],
    "wof:name":"Cibodas",
    "wof:placetype":"locality",
    "wof:population":0
},
  "geometry": {"coordinates":[107.0675,-6.73028],"type":"Point"}
}