{
  "type": "Feature",
  "properties": {
    "gn:admin1_code":"7.0",
    "gn:asciiname":"Tarub",
    "gn:country_code":"ID",
    "gn:dem":50,
    "gn:feature_class":"P",
    "gn:feature_code":"PPL",
    "gn:name":"Tarub",
    "gn:population":0,
    "gn:timezone":"Asia/Jakarta",
    "iso:country":"ID",
    "name:ind_x_preferred":[
        "Tarub"
    ],
    "wof:name":"Tarub",
    "wof:placetype":"locality"
},
  "geometry": {"coordinates":[111.01430000000001,-7.0593],"type":"Point"}
}