{
  "type": "Feature",
  "properties": {
    "gn:admin1_code":"33.0",
    "gn:asciiname":"Babakannagamukti",
    "gn:country_code":"ID",
    "gn:dem":652,
    "gn:feature_class":"P",
    "gn:feature_code":"PPLA4",
    "gn:name":"Babakannagamukti",
    "gn:population":0,
    "gn:timezone":"Asia/Jakarta",
    "iso:country":"ID",
    "name:ind_x_preferred":[
        "Babakannagamukti"
    ],
    "wof:name":"Babakannagamukti",
    "wof:placetype":"locality"
},
  "geometry": {"coordinates":[106.33434,-6.69865],"type":"Point"}
}