{
  "type": "Feature",
  "properties": {
    "gn:admin1_code":"8",
    "gn:asciiname":"Simon",
    "gn:country_code":"ID",
    "gn:dem":80,
    "gn:feature_class":"P",
    "gn:feature_code":"PPL",
    "gn:name":"Simon",
    "gn:population":0,
    "gn:timezone":"Asia/Jakarta",
    "iso:country":"ID",
    "name:ara_x_preferred":[
        "\u0633\u064a\u0645\u0648\u0646"
    ],
    "name:ceb_x_preferred":[
        "Simon"
    ],
    "name:ces_x_preferred":[
        "Simon"
    ],
    "name:deu_x_preferred":[
        "Simon"
    ],
    "name:eus_x_preferred":[
        "Simon"
    ],
    "name:fas_x_preferred":[
        "\u0633\u06cc\u0645\u0648\u0646"
    ],
    "name:fin_x_preferred":[
        "Simon"
    ],
    "name:fra_x_preferred":[
        "Simon"
    ],
    "name:heb_x_preferred":[
        "\u05e1\u05d9\u05d9\u05de\u05d5\u05df"
    ],
    "name:ind_x_preferred":[
        "Simon"
    ],
    "name:ita_x_preferred":[
        "Simon"
    ],
    "name:jpn_x_preferred":[
        "\u30b5\u30a4\u30e2\u30f3"
    ],
    "name:lav_x_preferred":[
        "Simon"
    ],
    "name:mkd_x_preferred":[
        "\u0428\u0438\u043c\u043e\u043d"
    ],
    "name:nld_x_preferred":[
        "Simon"
    ],
    "name:rus_x_preferred":[
        "Simon"
    ],
    "name:slk_x_preferred":[
        "Simon"
    ],
    "name:spa_x_preferred":[
        "Simon"
    ],
    "name:srp_x_preferred":[
        "\u0428\u0438\u043c\u043e\u043d"
    ],
    "name:swe_x_preferred":[
        "Simon"
    ],
    "wof:lang_x_official":[
        "ind"
    ],
    "wof:lang_x_spoken":[
        "ind",
        "eng"
    ],
    "wof:name":"Simon",
    "wof:placetype":"locality"
},
  "geometry": {"coordinates":[111.5098,-7.6954],"type":"Point"}
}