{
  "type": "Feature",
  "properties": {
    "gn:admin1_code":"18.0",
    "gn:asciiname":"Niku",
    "gn:country_code":"ID",
    "gn:dem":503,
    "gn:feature_class":"P",
    "gn:feature_code":"PPL",
    "gn:name":"Niku",
    "gn:population":0,
    "gn:timezone":"Asia/Makassar",
    "iso:country":"ID",
    "name:ind_x_preferred":[
        "Niku"
    ],
    "wof:name":"Niku",
    "wof:placetype":"locality"
},
  "geometry": {"coordinates":[124.63120000000001,-9.9348],"type":"Point"}
}