{
  "type": "Feature",
  "properties": {
    "gn:admin1_code":"26",
    "gn:asciiname":"Pondok Bah Balua",
    "gn:country_code":"ID",
    "gn:dem":177,
    "gn:feature_class":"P",
    "gn:feature_code":"PPL",
    "gn:name":"Pondok Bah Balua",
    "gn:population":0,
    "gn:timezone":"Asia/Jakarta",
    "iso:country":"ID",
    "name:ind_x_preferred":[
        "Pondok Bah Balua"
    ],
    "wof:name":"Pondok Bah Balua",
    "wof:placetype":"locality"
},
  "geometry": {"coordinates":[98.7958,3.3245],"type":"Point"}
}