{
  "type": "Feature",
  "properties": {
    "gn:admin1_code":"8",
    "gn:asciiname":"Garahan Jati",
    "gn:country_code":"ID",
    "gn:dem":486,
    "gn:feature_class":"P",
    "gn:feature_code":"PPL",
    "gn:name":"Garahan Jati",
    "gn:population":0,
    "gn:timezone":"Asia/Jakarta",
    "iso:country":"ID",
    "name:ind_x_preferred":[
        "Garahan Jati"
    ],
    "wof:name":"Garahan Jati",
    "wof:placetype":"locality"
},
  "geometry": {"coordinates":[113.89360000000001,-8.2011],"type":"Point"}
}