{
  "type": "Feature",
  "properties": {
    "gn:admin1_code":"30.0",
    "gn:asciiname":"Lamajang",
    "gn:cc2":"ID",
    "gn:country_code":"ID",
    "gn:dem":947,
    "gn:feature_class":"P",
    "gn:feature_code":"PPL",
    "gn:name":"Lamajang",
    "gn:population":0,
    "gn:timezone":"Asia/Jakarta",
    "iso:country":"ID",
    "name:und_x_variant":[
        "Lamadjang",
        "Lamadjan",
        "Lamajang"
    ],
    "wof:lang_x_official":[
        "ind"
    ],
    "wof:lang_x_spoken":[
        "ind",
        "eng"
    ],
    "wof:name":"Lamajang",
    "wof:placetype":"locality"
},
  "geometry": {"coordinates":[107.54722,-7.12028],"type":"Point"}
}