{
  "type": "Feature",
  "properties": {
    "gn:admin1_code":"7.0",
    "gn:asciiname":"Citelaga",
    "gn:country_code":"ID",
    "gn:dem":98,
    "gn:feature_class":"P",
    "gn:feature_code":"PPL",
    "gn:name":"Citelaga",
    "gn:population":0,
    "gn:timezone":"Asia/Jakarta",
    "iso:country":"ID",
    "name:ind_x_preferred":[
        "Citelaga"
    ],
    "wof:name":"Citelaga",
    "wof:placetype":"locality"
},
  "geometry": {"coordinates":[108.8075,-7.2944],"type":"Point"}
}