{
  "type": "Feature",
  "properties": {
    "gn:admin1_code":"1.0",
    "gn:asciiname":"Serawai",
    "gn:country_code":"ID",
    "gn:dem":6,
    "gn:feature_class":"P",
    "gn:feature_code":"PPLA3",
    "gn:name":"Serawai",
    "gn:population":0,
    "gn:timezone":"Asia/Jakarta",
    "iso:country":"ID",
    "name:ind_x_preferred":[
        "Serawai"
    ],
    "name:und_x_variant":[
        "Seroewai",
        "Seruwai",
        "Peukan Seruway"
    ],
    "wof:lang_x_official":[
        "ind"
    ],
    "wof:lang_x_spoken":[
        "ind",
        "eng"
    ],
    "wof:name":"Serawai",
    "wof:placetype":"locality"
},
  "geometry": {"coordinates":[98.18680000000001,4.3542],"type":"Point"}
}