{
  "type": "Feature",
  "properties": {
    "gn:admin1_code":"18.0",
    "gn:asciiname":"Tuapene",
    "gn:country_code":"ID",
    "gn:dem":409,
    "gn:feature_class":"P",
    "gn:feature_code":"PPL",
    "gn:name":"Tuapene",
    "gn:population":0,
    "gn:timezone":"Asia/Makassar",
    "iso:country":"ID",
    "name:ind_x_preferred":[
        "Tuapene"
    ],
    "wof:name":"Tuapene",
    "wof:placetype":"locality"
},
  "geometry": {"coordinates":[124.18680000000001,-9.8415],"type":"Point"}
}