{
  "type": "Feature",
  "properties": {
    "gn:admin1_code":"21",
    "gn:asciiname":"Unauna",
    "gn:country_code":"ID",
    "gn:dem":5,
    "gn:feature_class":"P",
    "gn:feature_code":"PPL",
    "gn:name":"Unauna",
    "gn:population":0,
    "gn:timezone":"Asia/Makassar",
    "iso:country":"ID",
    "name:ind_x_preferred":[
        "Unauna"
    ],
    "name:und_x_variant":[
        "Unauana"
    ],
    "wof:name":"Unauna",
    "wof:placetype":"locality"
},
  "geometry": {"coordinates":[121.857,-0.4198],"type":"Point"}
}