{
  "type": "Feature",
  "properties": {
    "gn:admin1_code":"7",
    "gn:asciiname":"Pangle",
    "gn:country_code":"ID",
    "gn:dem":77,
    "gn:feature_class":"P",
    "gn:feature_code":"PPL",
    "gn:name":"Pangle",
    "gn:population":0,
    "gn:timezone":"Asia/Jakarta",
    "iso:country":"ID",
    "name:ind_x_preferred":[
        "Pangle"
    ],
    "wof:name":"Pangle",
    "wof:placetype":"locality"
},
  "geometry": {"coordinates":[111.10722,-7.35306],"type":"Point"}
}