{
  "type": "Feature",
  "properties": {
    "gn:admin1_code":"41.0",
    "gn:asciiname":"Timbugading",
    "gn:country_code":"ID",
    "gn:dem":322,
    "gn:feature_class":"P",
    "gn:feature_code":"PPL",
    "gn:name":"Timbugading",
    "gn:population":0,
    "gn:timezone":"Asia/Makassar",
    "iso:country":"ID",
    "name:ind_x_preferred":[
        "Timbugading"
    ],
    "wof:name":"Timbugading",
    "wof:placetype":"locality"
},
  "geometry": {"coordinates":[118.9121,-3.4737],"type":"Point"}
}