{
  "type": "Feature",
  "properties": {
    "gn:admin1_code":"17",
    "gn:asciiname":"Labuantereng",
    "gn:country_code":"ID",
    "gn:dem":10,
    "gn:feature_class":"P",
    "gn:feature_code":"PPL",
    "gn:name":"Labuantereng",
    "gn:population":0,
    "gn:timezone":"Asia/Makassar",
    "iso:country":"ID",
    "name:ind_x_preferred":[
        "Labuantereng"
    ],
    "wof:name":"Labuantereng",
    "wof:placetype":"locality"
},
  "geometry": {"coordinates":[116.07680000000001,-8.7348],"type":"Point"}
}