{
  "type": "Feature",
  "properties": {
    "gn:admin1_code":"7.0",
    "gn:asciiname":"Dagan",
    "gn:country_code":"ID",
    "gn:dem":1021,
    "gn:feature_class":"P",
    "gn:feature_code":"PPL",
    "gn:name":"Dagan",
    "gn:population":0,
    "gn:timezone":"Asia/Jakarta",
    "iso:country":"ID",
    "name:deu_x_preferred":[
        "Dagan"
    ],
    "name:fra_x_preferred":[
        "Dagan"
    ],
    "name:heb_x_preferred":[
        "\u05d3\u05d2\u05df"
    ],
    "name:ind_x_preferred":[
        "Dagan"
    ],
    "wof:lang_x_official":[
        "ind"
    ],
    "wof:lang_x_spoken":[
        "ind",
        "eng"
    ],
    "wof:name":"Dagan",
    "wof:placetype":"locality"
},
  "geometry": {"coordinates":[109.71944000000001,-7.29583],"type":"Point"}
}