{
  "type": "Feature",
  "properties": {
    "gn:admin1_code":"8",
    "gn:asciiname":"Tamanbali",
    "gn:country_code":"ID",
    "gn:dem":1006,
    "gn:feature_class":"P",
    "gn:feature_code":"PPL",
    "gn:name":"Tamanbali",
    "gn:population":0,
    "gn:timezone":"Asia/Jakarta",
    "iso:country":"ID",
    "name:ind_x_preferred":[
        "Tamanbali"
    ],
    "wof:name":"Tamanbali",
    "wof:placetype":"locality"
},
  "geometry": {"coordinates":[112.8622,-8.1616],"type":"Point"}
}