{
  "type": "Feature",
  "properties": {
    "gn:admin1_code":"7.0",
    "gn:asciiname":"Margosari",
    "gn:country_code":"ID",
    "gn:dem":14,
    "gn:feature_class":"P",
    "gn:feature_code":"PPL",
    "gn:name":"Margosari",
    "gn:population":0,
    "gn:timezone":"Asia/Jakarta",
    "iso:country":"ID",
    "name:ind_x_preferred":[
        "Margosari"
    ],
    "wof:name":"Margosari",
    "wof:placetype":"locality"
},
  "geometry": {"coordinates":[108.6871,-7.3614],"type":"Point"}
}