{
  "type": "Feature",
  "properties": {
    "gn:admin1_code":"8.0",
    "gn:asciiname":"Sidorejo",
    "gn:country_code":"ID",
    "gn:dem":6,
    "gn:feature_class":"P",
    "gn:feature_code":"PPL",
    "gn:name":"Sidorejo",
    "gn:population":0,
    "gn:timezone":"Asia/Jakarta",
    "iso:country":"ID",
    "name:ind_x_preferred":[
        "Sidorejo"
    ],
    "wof:name":"Sidorejo",
    "wof:placetype":"locality"
},
  "geometry": {"coordinates":[111.08499999999999,-8.21556],"type":"Point"}
}