{
  "type": "Feature",
  "properties": {
    "gn:admin1_code":"2",
    "gn:asciiname":"Banjar Karipan Kelod",
    "gn:country_code":"ID",
    "gn:dem":118,
    "gn:feature_class":"P",
    "gn:feature_code":"PPL",
    "gn:name":"Banjar Karipan Kelod",
    "gn:population":0,
    "gn:timezone":"Asia/Makassar",
    "iso:country":"ID",
    "name:ind_x_preferred":[
        "Banjar Karipan Kelod"
    ],
    "wof:name":"Banjar Karipan Kelod",
    "wof:placetype":"locality"
},
  "geometry": {"coordinates":[115.14579999999999,-8.5527],"type":"Point"}
}