{
  "type": "Feature",
  "properties": {
    "gn:admin1_code":"30",
    "gn:asciiname":"Cipurut",
    "gn:country_code":"ID",
    "gn:dem":901,
    "gn:feature_class":"P",
    "gn:feature_code":"PPL",
    "gn:name":"Cipurut",
    "gn:population":0,
    "gn:timezone":"Asia/Jakarta",
    "iso:country":"ID",
    "wof:name":"Cipurut",
    "wof:placetype":"locality"
},
  "geometry": {"coordinates":[107.63028,-7.05833],"type":"Point"}
}