{
  "type": "Feature",
  "properties": {
    "gn:admin1_code":"30",
    "gn:asciiname":"Vilamas",
    "gn:country_code":"ID",
    "gn:dem":805,
    "gn:feature_class":"P",
    "gn:feature_code":"PPL",
    "gn:name":"Vilamas",
    "gn:population":0,
    "gn:timezone":"Asia/Jakarta",
    "iso:country":"ID",
    "name:ind_x_preferred":[
        "Vilamas"
    ],
    "wof:name":"Vilamas",
    "wof:placetype":"locality"
},
  "geometry": {"coordinates":[107.65083,-6.88194],"type":"Point"}
}