{
  "type": "Feature",
  "properties": {
    "gn:admin1_code":"30",
    "gn:asciiname":"Leboknangka",
    "gn:country_code":"ID",
    "gn:dem":412,
    "gn:feature_class":"P",
    "gn:feature_code":"PPL",
    "gn:name":"Leboknangka",
    "gn:population":0,
    "gn:timezone":"Asia/Jakarta",
    "iso:country":"ID",
    "name:ind_x_preferred":[
        "Leboknangka"
    ],
    "wof:name":"Leboknangka",
    "wof:placetype":"locality"
},
  "geometry": {"coordinates":[107.19972,-6.68361],"type":"Point"}
}