{
  "type": "Feature",
  "properties": {
    "gn:admin1_code":"22",
    "gn:asciiname":"Penanggosi",
    "gn:country_code":"ID",
    "gn:dem":56,
    "gn:feature_class":"P",
    "gn:feature_code":"PPL",
    "gn:name":"Penanggosi",
    "gn:population":0,
    "gn:timezone":"Asia/Makassar",
    "iso:country":"ID",
    "name:ind_x_preferred":[
        "Penanggosi"
    ],
    "wof:name":"Penanggosi",
    "wof:placetype":"locality"
},
  "geometry": {"coordinates":[121.9075,-4.31],"type":"Point"}
}