{
  "type": "Feature",
  "properties": {
    "gn:admin1_code":"24.0",
    "gn:asciiname":"Sikabaluan",
    "gn:country_code":"ID",
    "gn:dem":11,
    "gn:feature_class":"P",
    "gn:feature_code":"PPLA3",
    "gn:name":"Sikabaluan",
    "gn:population":0,
    "gn:timezone":"Asia/Jakarta",
    "iso:country":"ID",
    "name:ind_x_preferred":[
        "Sikabaluan"
    ],
    "name:und_x_variant":[
        "Moearasikabaloean",
        "Muarasikabaluan"
    ],
    "wof:lang_x_official":[
        "ind"
    ],
    "wof:lang_x_spoken":[
        "ind",
        "eng"
    ],
    "wof:name":"Sikabaluan",
    "wof:placetype":"locality"
},
  "geometry": {"coordinates":[98.99217,-1.11961],"type":"Point"}
}