{
  "type": "Feature",
  "properties": {
    "gn:admin1_code":"33.0",
    "gn:asciiname":"Cikuya Hilir",
    "gn:country_code":"ID",
    "gn:dem":150,
    "gn:feature_class":"P",
    "gn:feature_code":"PPL",
    "gn:name":"Cikuya Hilir",
    "gn:population":0,
    "gn:timezone":"Asia/Jakarta",
    "iso:country":"ID",
    "name:ind_x_preferred":[
        "Cikuya Hilir"
    ],
    "wof:name":"Cikuya Hilir",
    "wof:placetype":"locality"
},
  "geometry": {"coordinates":[106.09690000000001,-6.3458],"type":"Point"}
}