{
  "type": "Feature",
  "properties": {
    "gn:admin1_code":"8.0",
    "gn:asciiname":"Jatijajar",
    "gn:country_code":"ID",
    "gn:dem":101,
    "gn:feature_class":"P",
    "gn:feature_code":"PPL",
    "gn:name":"Jatijajar",
    "gn:population":0,
    "gn:timezone":"Asia/Jakarta",
    "iso:country":"ID",
    "name:ind_x_preferred":[
        "Jatijajar"
    ],
    "wof:name":"Jatijajar",
    "wof:placetype":"locality"
},
  "geometry": {"coordinates":[113.3998,-7.0462],"type":"Point"}
}