{
  "type": "Feature",
  "properties": {
    "gn:admin1_code":"0.0",
    "gn:asciiname":"Mohapi",
    "gn:country_code":"ID",
    "gn:dem":1564,
    "gn:feature_class":"P",
    "gn:feature_code":"PPL",
    "gn:name":"Mohapi",
    "gn:population":0,
    "gn:timezone":"Asia/Makassar",
    "iso:country":"ID",
    "wof:name":"Mohapi",
    "wof:placetype":"locality"
},
  "geometry": {"coordinates":[119.96666999999999,-1.76667],"type":"Point"}
}