{
  "type": "Feature",
  "properties": {
    "gn:admin1_code":"31",
    "gn:asciiname":"Pangi",
    "gn:country_code":"ID",
    "gn:dem":51,
    "gn:feature_class":"P",
    "gn:feature_code":"PPL",
    "gn:name":"Pangi",
    "gn:population":0,
    "gn:timezone":"Asia/Makassar",
    "iso:country":"ID",
    "name:ind_x_preferred":[
        "Pangi"
    ],
    "wof:name":"Pangi",
    "wof:placetype":"locality"
},
  "geometry": {"coordinates":[123.93559999999999,0.8301],"type":"Point"}
}