{
  "type": "Feature",
  "properties": {
    "gn:admin1_code":"7.0",
    "gn:asciiname":"Dipan",
    "gn:country_code":"ID",
    "gn:dem":150,
    "gn:feature_class":"P",
    "gn:feature_code":"PPL",
    "gn:name":"Dipan",
    "gn:population":0,
    "gn:timezone":"Asia/Jakarta",
    "iso:country":"ID",
    "wof:name":"Dipan",
    "wof:placetype":"locality"
},
  "geometry": {"coordinates":[110.69750000000001,-7.56194],"type":"Point"}
}