{
  "type": "Feature",
  "properties": {
    "gn:admin1_code":"7.0",
    "gn:asciiname":"Bradag",
    "gn:country_code":"ID",
    "gn:dem":93,
    "gn:feature_class":"P",
    "gn:feature_code":"PPLA4",
    "gn:name":"Bradag",
    "gn:population":0,
    "gn:timezone":"Asia/Jakarta",
    "iso:country":"ID",
    "name:ind_x_preferred":[
        "Bradag"
    ],
    "wof:lang_x_official":[
        "ind"
    ],
    "wof:lang_x_spoken":[
        "ind",
        "eng"
    ],
    "wof:name":"Bradag",
    "wof:placetype":"locality"
},
  "geometry": {"coordinates":[111.2953,-6.9933],"type":"Point"}
}