{
  "type": "Feature",
  "properties": {
    "gn:admin1_code":"30.0",
    "gn:asciiname":"Lancarmanah",
    "gn:country_code":"ID",
    "gn:dem":283,
    "gn:feature_class":"P",
    "gn:feature_code":"PPL",
    "gn:name":"Lancarmanah",
    "gn:population":0,
    "gn:timezone":"Asia/Jakarta",
    "iso:country":"ID",
    "name:ind_x_preferred":[
        "Lancarmanah"
    ],
    "wof:name":"Lancarmanah",
    "wof:placetype":"locality"
},
  "geometry": {"coordinates":[108.13590000000001,-7.4994],"type":"Point"}
}