{
  "type": "Feature",
  "properties": {
    "gn:admin1_code":"18.0",
    "gn:asciiname":"Anamanggut",
    "gn:country_code":"ID",
    "gn:dem":105,
    "gn:feature_class":"P",
    "gn:feature_code":"PPL",
    "gn:name":"Anamanggut",
    "gn:population":0,
    "gn:timezone":"Asia/Makassar",
    "iso:country":"ID",
    "name:ind_x_preferred":[
        "Anamanggut"
    ],
    "wof:name":"Anamanggut",
    "wof:placetype":"locality"
},
  "geometry": {"coordinates":[119.66719999999999,-9.3908],"type":"Point"}
}