{
  "type": "Feature",
  "properties": {
    "gn:admin1_code":"28",
    "gn:asciiname":"Bagi",
    "gn:country_code":"ID",
    "gn:dem":14,
    "gn:feature_class":"P",
    "gn:feature_code":"PPL",
    "gn:name":"Bagi",
    "gn:population":0,
    "gn:timezone":"Asia/Jayapura",
    "iso:country":"ID",
    "name:ceb_x_preferred":[
        "Bagi"
    ],
    "name:deu_x_preferred":[
        "Bagi"
    ],
    "name:ind_x_preferred":[
        "Bagi"
    ],
    "name:swe_x_preferred":[
        "Bagi"
    ],
    "wof:lang_x_official":[
        "ind"
    ],
    "wof:lang_x_spoken":[
        "ind",
        "eng"
    ],
    "wof:name":"Bagi",
    "wof:placetype":"locality"
},
  "geometry": {"coordinates":[130.81129999999999,-3.8267],"type":"Point"}
}