{
  "type": "Feature",
  "properties": {
    "gn:admin1_code":"41.0",
    "gn:asciiname":"Maroa",
    "gn:country_code":"ID",
    "gn:dem":823,
    "gn:feature_class":"P",
    "gn:feature_code":"PPL",
    "gn:name":"Maroa",
    "gn:population":0,
    "gn:timezone":"Asia/Makassar",
    "iso:country":"ID",
    "name:ceb_x_preferred":[
        "Maroa"
    ],
    "name:deu_x_preferred":[
        "Maroa"
    ],
    "name:fra_x_preferred":[
        "Maroa"
    ],
    "name:ind_x_preferred":[
        "Maroa"
    ],
    "name:ita_x_preferred":[
        "Maroa"
    ],
    "name:nld_x_preferred":[
        "Maroa"
    ],
    "name:pol_x_preferred":[
        "Maroa"
    ],
    "name:por_x_preferred":[
        "Maroa"
    ],
    "name:slk_x_preferred":[
        "Maroa"
    ],
    "name:spa_x_preferred":[
        "Maroa"
    ],
    "name:swe_x_preferred":[
        "Maroa"
    ],
    "wof:name":"Maroa",
    "wof:placetype":"locality"
},
  "geometry": {"coordinates":[119.1863,-2.765],"type":"Point"}
}