{
  "type": "Feature",
  "properties": {
    "gn:admin1_code":"8.0",
    "gn:asciiname":"Karangtengah",
    "gn:country_code":"ID",
    "gn:dem":117,
    "gn:feature_class":"P",
    "gn:feature_code":"PPL",
    "gn:name":"Karangtengah",
    "gn:population":0,
    "gn:timezone":"Asia/Jakarta",
    "iso:country":"ID",
    "name:fra_x_preferred":[
        "Karang Tengah"
    ],
    "name:ind_x_preferred":[
        "Karangtengah"
    ],
    "name:jav_x_preferred":[
        "Karangtengah"
    ],
    "name:msa_x_preferred":[
        "Karangtengah"
    ],
    "name:sun_x_preferred":[
        "Karangtengah"
    ],
    "wof:lang_x_official":[
        "ind"
    ],
    "wof:lang_x_spoken":[
        "ind",
        "eng"
    ],
    "wof:name":"Karangtengah",
    "wof:placetype":"locality"
},
  "geometry": {"coordinates":[113.27849999999999,-7.8716],"type":"Point"}
}