{
  "type": "Feature",
  "properties": {
    "gn:admin1_code":"38",
    "gn:asciiname":"Sapakeke",
    "gn:country_code":"ID",
    "gn:dem":325,
    "gn:feature_class":"P",
    "gn:feature_code":"PPL",
    "gn:name":"Sapakeke",
    "gn:population":0,
    "gn:timezone":"Asia/Makassar",
    "iso:country":"ID",
    "name:ind_x_preferred":[
        "Sapakeke"
    ],
    "wof:name":"Sapakeke",
    "wof:placetype":"locality"
},
  "geometry": {"coordinates":[119.69580000000001,-5.3592],"type":"Point"}
}