{
  "type": "Feature",
  "properties": {
    "gn:admin1_code":"17",
    "gn:asciiname":"Rempungbarat Selatan",
    "gn:country_code":"ID",
    "gn:dem":250,
    "gn:feature_class":"P",
    "gn:feature_code":"PPL",
    "gn:name":"Rempungbarat Selatan",
    "gn:population":0,
    "gn:timezone":"Asia/Makassar",
    "iso:country":"ID",
    "name:ind_x_preferred":[
        "Rempungbarat Selatan"
    ],
    "wof:name":"Rempungbarat Selatan",
    "wof:placetype":"locality"
},
  "geometry": {"coordinates":[116.4954,-8.6158],"type":"Point"}
}