{
  "type": "Feature",
  "properties": {
    "gn:admin1_code":"08",
    "gn:asciiname":"Jatirajah",
    "gn:country_code":"ID",
    "gn:dem":48,
    "gn:feature_class":"P",
    "gn:feature_code":"PPL",
    "gn:name":"Jatirajah",
    "gn:population":0,
    "gn:timezone":"Asia/Jakarta",
    "iso:country":"ID",
    "name:ind_x_preferred":[
        "Jatirajah"
    ],
    "name:und_x_variant":[
        "Djatiradjek",
        "Jatirajek"
    ],
    "wof:lang_x_official":[
        "ind"
    ],
    "wof:lang_x_spoken":[
        "ind",
        "eng"
    ],
    "wof:name":"Jatirajah",
    "wof:placetype":"locality"
},
  "geometry": {"coordinates":[112.7543,-7.1035],"type":"Point"}
}