{
  "type": "Feature",
  "properties": {
    "gn:admin1_code":"33.0",
    "gn:asciiname":"Sukajadi",
    "gn:country_code":"ID",
    "gn:dem":366,
    "gn:feature_class":"P",
    "gn:feature_code":"PPL",
    "gn:name":"Sukajadi",
    "gn:population":0,
    "gn:timezone":"Asia/Jakarta",
    "iso:country":"ID",
    "name:ind_x_preferred":[
        "Sukajadi"
    ],
    "wof:name":"Sukajadi",
    "wof:placetype":"locality"
},
  "geometry": {"coordinates":[106.0771,-6.2301],"type":"Point"}
}