{
  "type": "Feature",
  "properties": {
    "gn:admin1_code":"38.0",
    "gn:asciiname":"Amani",
    "gn:country_code":"ID",
    "gn:dem":2,
    "gn:feature_class":"P",
    "gn:feature_code":"PPL",
    "gn:name":"Amani",
    "gn:population":0,
    "gn:timezone":"Asia/Makassar",
    "iso:country":"ID",
    "name:ang_x_preferred":[
        "Amani"
    ],
    "name:deu_x_preferred":[
        "Amani"
    ],
    "name:fra_x_preferred":[
        "Amani"
    ],
    "name:ita_x_preferred":[
        "Amani"
    ],
    "wof:lang_x_official":[
        "ind"
    ],
    "wof:lang_x_spoken":[
        "ind",
        "eng"
    ],
    "wof:name":"Amani",
    "wof:placetype":"locality"
},
  "geometry": {"coordinates":[119.48417000000001,-3.76667],"type":"Point"}
}