{
  "type": "Feature",
  "properties": {
    "gn:admin1_code":"08",
    "gn:asciiname":"Parangas Tiga",
    "gn:cc2":"ID",
    "gn:country_code":"ID",
    "gn:dem":453,
    "gn:feature_class":"P",
    "gn:feature_code":"PPL",
    "gn:name":"Parangas Tiga",
    "gn:population":0,
    "gn:timezone":"Asia/Jakarta",
    "iso:country":"ID",
    "name:und_x_variant":[
        "Parangas 3",
        "Parangas Tiga"
    ],
    "wof:lang_x_official":[
        "ind"
    ],
    "wof:lang_x_spoken":[
        "ind",
        "eng"
    ],
    "wof:name":"Parangas Tiga",
    "wof:placetype":"locality"
},
  "geometry": {"coordinates":[112.7175,-8.25028],"type":"Point"}
}