{
  "type": "Feature",
  "properties": {
    "gn:admin1_code":"38",
    "gn:asciiname":"Pabuntang",
    "gn:country_code":"ID",
    "gn:dem":71,
    "gn:feature_class":"P",
    "gn:feature_code":"PPL",
    "gn:name":"Pabuntang",
    "gn:population":0,
    "gn:timezone":"Asia/Makassar",
    "iso:country":"ID",
    "name:ind_x_preferred":[
        "Pabuntang"
    ],
    "wof:name":"Pabuntang",
    "wof:placetype":"locality"
},
  "geometry": {"coordinates":[120.12690000000001,-2.8442],"type":"Point"}
}