{
  "type": "Feature",
  "properties": {
    "gn:admin1_code":"26",
    "gn:asciiname":"Lumbantobing",
    "gn:country_code":"ID",
    "gn:dem":1240,
    "gn:feature_class":"P",
    "gn:feature_code":"PPL",
    "gn:name":"Lumbantobing",
    "gn:population":0,
    "gn:timezone":"Asia/Jakarta",
    "iso:country":"ID",
    "name:ind_x_preferred":[
        "Lumbantobing"
    ],
    "wof:name":"Lumbantobing",
    "wof:placetype":"locality"
},
  "geometry": {"coordinates":[99.0979,1.965],"type":"Point"}
}