{
  "type": "Feature",
  "properties": {
    "gn:admin1_code":"15.0",
    "gn:asciiname":"Bedeng",
    "gn:country_code":"ID",
    "gn:dem":169,
    "gn:feature_class":"P",
    "gn:feature_code":"PPL",
    "gn:name":"Bedeng",
    "gn:population":0,
    "gn:timezone":"Asia/Jakarta",
    "iso:country":"ID",
    "name:ind_x_preferred":[
        "Bedeng"
    ],
    "wof:name":"Bedeng",
    "wof:placetype":"locality"
},
  "geometry": {"coordinates":[104.53823,-4.71694],"type":"Point"}
}