{
  "type": "Feature",
  "properties": {
    "gn:admin1_code":"38",
    "gn:asciiname":"Tondok",
    "gn:country_code":"ID",
    "gn:dem":814,
    "gn:feature_class":"P",
    "gn:feature_code":"PPL",
    "gn:name":"Tondok",
    "gn:population":0,
    "gn:timezone":"Asia/Makassar",
    "iso:country":"ID",
    "name:ind_x_preferred":[
        "Tondok"
    ],
    "wof:name":"Tondok",
    "wof:placetype":"locality"
},
  "geometry": {"coordinates":[119.85250000000001,-3.0646],"type":"Point"}
}