{
  "type": "Feature",
  "properties": {
    "gn:admin1_code":"7.0",
    "gn:asciiname":"Jambesewu",
    "gn:country_code":"ID",
    "gn:dem":27,
    "gn:feature_class":"P",
    "gn:feature_code":"PPL",
    "gn:name":"Jambesewu",
    "gn:population":0,
    "gn:timezone":"Asia/Jakarta",
    "iso:country":"ID",
    "name:ind_x_preferred":[
        "Jambesewu"
    ],
    "wof:name":"Jambesewu",
    "wof:placetype":"locality"
},
  "geometry": {"coordinates":[108.7854,-7.3143],"type":"Point"}
}