{
  "type": "Feature",
  "properties": {
    "gn:admin1_code":"8.0",
    "gn:asciiname":"Kedunggajul",
    "gn:country_code":"ID",
    "gn:dem":96,
    "gn:feature_class":"P",
    "gn:feature_code":"PPLA4",
    "gn:name":"Kedunggajul",
    "gn:population":0,
    "gn:timezone":"Asia/Jakarta",
    "iso:country":"ID",
    "name:ind_x_preferred":[
        "Kedunggajul"
    ],
    "wof:name":"Kedunggajul",
    "wof:placetype":"locality"
},
  "geometry": {"coordinates":[112.0763,-8.2852],"type":"Point"}
}