{
  "type": "Feature",
  "properties": {
    "gn:admin1_code":"31",
    "gn:asciiname":"Perkamil",
    "gn:country_code":"ID",
    "gn:dem":19,
    "gn:feature_class":"P",
    "gn:feature_code":"PPL",
    "gn:name":"Perkamil",
    "gn:population":0,
    "gn:timezone":"Asia/Makassar",
    "iso:country":"ID",
    "name:ind_x_preferred":[
        "Perkamil"
    ],
    "wof:name":"Perkamil",
    "wof:placetype":"locality"
},
  "geometry": {"coordinates":[124.87690000000001,1.4664],"type":"Point"}
}