{
  "type": "Feature",
  "properties": {
    "gn:admin1_code":"33",
    "gn:asciiname":"Singamerta",
    "gn:country_code":"ID",
    "gn:dem":14,
    "gn:feature_class":"P",
    "gn:feature_code":"PPL",
    "gn:name":"Singamerta",
    "gn:population":0,
    "gn:timezone":"Asia/Jakarta",
    "iso:country":"ID",
    "name:ind_x_preferred":[
        "Singamerta"
    ],
    "wof:name":"Singamerta",
    "wof:placetype":"locality"
},
  "geometry": {"coordinates":[106.24290000000001,-6.1222],"type":"Point"}
}