{
  "type": "Feature",
  "properties": {
    "gn:admin1_code":"24",
    "gn:asciiname":"Alahanpanjang",
    "gn:country_code":"ID",
    "gn:dem":92,
    "gn:feature_class":"P",
    "gn:feature_code":"PPL",
    "gn:name":"Alahanpanjang",
    "gn:population":0,
    "gn:timezone":"Asia/Jakarta",
    "iso:country":"ID",
    "name:ind_x_preferred":[
        "Alahanpanjang"
    ],
    "wof:name":"Alahanpanjang",
    "wof:placetype":"locality"
},
  "geometry": {"coordinates":[100.07544,-0.47953],"type":"Point"}
}