{
  "type": "Feature",
  "properties": {
    "gn:admin1_code":"15.0",
    "gn:asciiname":"Tanjungkurung",
    "gn:country_code":"ID",
    "gn:dem":220,
    "gn:feature_class":"P",
    "gn:feature_code":"PPL",
    "gn:name":"Tanjungkurung",
    "gn:population":0,
    "gn:timezone":"Asia/Jakarta",
    "iso:country":"ID",
    "name:und_x_variant":[
        "Tandjungkurung",
        "Tandjoengkoeroeng",
        "Tanjungkurung"
    ],
    "wof:name":"Tanjungkurung",
    "wof:placetype":"locality"
},
  "geometry": {"coordinates":[104.39395,-4.69423],"type":"Point"}
}