{
  "type": "Feature",
  "properties": {
    "gn:admin1_code":"35.0",
    "gn:asciiname":"Bedar",
    "gn:country_code":"ID",
    "gn:dem":7,
    "gn:feature_class":"P",
    "gn:feature_code":"PPL",
    "gn:name":"Bedar",
    "gn:population":0,
    "gn:timezone":"Asia/Jakarta",
    "iso:country":"ID",
    "name:ceb_x_preferred":[
        "Bedar"
    ],
    "name:ind_x_preferred":[
        "Bedar"
    ],
    "name:swe_x_preferred":[
        "Bedar"
    ],
    "wof:name":"Bedar",
    "wof:placetype":"locality"
},
  "geometry": {"coordinates":[106.08344,-2.47013],"type":"Point"}
}