{
  "type": "Feature",
  "properties": {
    "gn:admin1_code":"30",
    "gn:asciiname":"Malati",
    "gn:country_code":"ID",
    "gn:dem":1028,
    "gn:feature_class":"P",
    "gn:feature_code":"PPL",
    "gn:name":"Malati",
    "gn:population":0,
    "gn:timezone":"Asia/Jakarta",
    "iso:country":"ID",
    "name:ind_x_preferred":[
        "Malati"
    ],
    "wof:name":"Malati",
    "wof:placetype":"locality"
},
  "geometry": {"coordinates":[107.81100000000001,-7.2198],"type":"Point"}
}