{
  "type": "Feature",
  "properties": {
    "gn:admin1_code":"7.0",
    "gn:asciiname":"Trahan Kulon",
    "gn:country_code":"ID",
    "gn:dem":18,
    "gn:feature_class":"P",
    "gn:feature_code":"PPL",
    "gn:name":"Trahan Kulon",
    "gn:population":0,
    "gn:timezone":"Asia/Jakarta",
    "iso:country":"ID",
    "name:ind_x_preferred":[
        "Trahan Kulon"
    ],
    "wof:name":"Trahan Kulon",
    "wof:placetype":"locality"
},
  "geometry": {"coordinates":[111.4807,-6.639],"type":"Point"}
}