{
  "type": "Feature",
  "properties": {
    "gn:admin1_code":"18.0",
    "gn:asciiname":"Betmanu",
    "gn:country_code":"ID",
    "gn:dem":533,
    "gn:feature_class":"P",
    "gn:feature_code":"PPL",
    "gn:name":"Betmanu",
    "gn:population":0,
    "gn:timezone":"Asia/Makassar",
    "iso:country":"ID",
    "name:ind_x_preferred":[
        "Betmanu"
    ],
    "wof:name":"Betmanu",
    "wof:placetype":"locality"
},
  "geometry": {"coordinates":[123.8794,-9.9889],"type":"Point"}
}