{
  "type": "Feature",
  "properties": {
    "gn:admin1_code":"3.0",
    "gn:asciiname":"Batuhaji",
    "gn:country_code":"ID",
    "gn:dem":178,
    "gn:feature_class":"P",
    "gn:feature_code":"PPL",
    "gn:name":"Batuhaji",
    "gn:population":0,
    "gn:timezone":"Asia/Jakarta",
    "iso:country":"ID",
    "name:ind_x_preferred":[
        "Batuhaji"
    ],
    "name:ind_x_variant":[
        "Batuaji"
    ],
    "wof:lang_x_official":[
        "ind"
    ],
    "wof:lang_x_spoken":[
        "ind",
        "eng"
    ],
    "wof:name":"Batuhaji",
    "wof:placetype":"locality"
},
  "geometry": {"coordinates":[102.99252,-4.26216],"type":"Point"}
}