{
  "type": "Feature",
  "properties": {
    "gn:admin1_code":"8.0",
    "gn:asciiname":"Sambikerep",
    "gn:country_code":"ID",
    "gn:dem":29,
    "gn:feature_class":"P",
    "gn:feature_code":"PPL",
    "gn:name":"Sambikerep",
    "gn:population":0,
    "gn:timezone":"Asia/Jakarta",
    "iso:country":"ID",
    "name:ind_x_preferred":[
        "Sambikerep"
    ],
    "wof:name":"Sambikerep",
    "wof:placetype":"locality"
},
  "geometry": {"coordinates":[111.97866,-7.21734],"type":"Point"}
}