{
  "type": "Feature",
  "properties": {
    "gn:admin1_code":"18.0",
    "gn:asciiname":"Weekamura",
    "gn:country_code":"ID",
    "gn:dem":578,
    "gn:feature_class":"P",
    "gn:feature_code":"PPL",
    "gn:name":"Weekamura",
    "gn:population":0,
    "gn:timezone":"Asia/Makassar",
    "iso:country":"ID",
    "name:ind_x_preferred":[
        "Weekamura"
    ],
    "wof:name":"Weekamura",
    "wof:placetype":"locality"
},
  "geometry": {"coordinates":[119.2543,-9.5735],"type":"Point"}
}