{
  "type": "Feature",
  "properties": {
    "gn:admin1_code":"8.0",
    "gn:asciiname":"Nginokrajan",
    "gn:country_code":"ID",
    "gn:dem":87,
    "gn:feature_class":"P",
    "gn:feature_code":"PPLA4",
    "gn:name":"Nginokrajan",
    "gn:population":0,
    "gn:timezone":"Asia/Jakarta",
    "iso:country":"ID",
    "name:ind_x_preferred":[
        "Nginokrajan"
    ],
    "name:und_x_variant":[
        "Ngina",
        "Ngino"
    ],
    "wof:name":"Nginokrajan",
    "wof:placetype":"locality"
},
  "geometry": {"coordinates":[112.0647,-6.9936],"type":"Point"}
}