{
  "type": "Feature",
  "properties": {
    "gn:admin1_code":"8.0",
    "gn:asciiname":"Lepelle",
    "gn:country_code":"ID",
    "gn:dem":61,
    "gn:feature_class":"P",
    "gn:feature_code":"PPL",
    "gn:name":"Lepelle",
    "gn:population":0,
    "gn:timezone":"Asia/Jakarta",
    "iso:country":"ID",
    "name:ind_x_preferred":[
        "Lepelle"
    ],
    "wof:name":"Lepelle",
    "wof:placetype":"locality"
},
  "geometry": {"coordinates":[113.33240000000001,-6.8992],"type":"Point"}
}