{
  "type": "Feature",
  "properties": {
    "gn:admin1_code":"30",
    "gn:asciiname":"Wage",
    "gn:country_code":"ID",
    "gn:dem":13,
    "gn:feature_class":"P",
    "gn:feature_code":"PPL",
    "gn:name":"Wage",
    "gn:population":0,
    "gn:timezone":"Asia/Jakarta",
    "iso:country":"ID",
    "name:ara_x_preferred":[
        "\u0623\u062c\u0631"
    ],
    "name:bel_x_preferred":[
        "\u0417\u0430\u0440\u0430\u0431\u043e\u0442\u043d\u0430\u044f \u043f\u043b\u0430\u0442\u0430"
    ],
    "name:bul_x_preferred":[
        "\u0417\u0430\u043f\u043b\u0430\u0442\u0430"
    ],
    "name:ces_x_preferred":[
        "Mzda"
    ],
    "name:ckb_x_preferred":[
        "\u06a9\u0631\u06ce"
    ],
    "name:cym_x_preferred":[
        "Cyflog"
    ],
    "name:deu_x_preferred":[
        "Zeitlohn"
    ],
    "name:est_x_preferred":[
        "T\u00f6\u00f6tasu"
    ],
    "name:fas_x_preferred":[
        "\u062f\u0633\u062a\u0645\u0632\u062f"
    ],
    "name:hin_x_preferred":[
        "\u092e\u091c\u0926\u0942\u0930\u0940"
    ],
    "name:ind_x_preferred":[
        "Wage"
    ],
    "name:ind_x_variant":[
        "Upah"
    ],
    "name:kan_x_preferred":[
        "\u0c95\u0cc2\u0cb2\u0cbf"
    ],
    "name:kaz_x_preferred":[
        "\u0415\u04a3\u0431\u0435\u043a\u0430\u049b\u044b"
    ],
    "name:kor_x_preferred":[
        "\uc784\uae08"
    ],
    "name:msa_x_preferred":[
        "Upah"
    ],
    "name:nep_x_preferred":[
        "\u091c\u094d\u092f\u093e\u0932\u093e"
    ],
    "name:pan_x_preferred":[
        "\u0a09\u0a1c\u0a30\u0a24"
    ],
    "name:rus_x_preferred":[
        "\u0417\u0430\u0440\u0430\u0431\u043e\u0442\u043d\u0430\u044f \u043f\u043b\u0430\u0442\u0430"
    ],
    "name:slk_x_preferred":[
        "Mzda"
    ],
    "name:tam_x_preferred":[
        "\u0b95\u0bc2\u0bb2\u0bbf"
    ],
    "name:tat_x_preferred":[
        "\u0425\u0435\u0437\u043c\u04d9\u0442 \u0445\u0430\u043a\u044b"
    ],
    "name:tur_x_preferred":[
        "Maa\u015f"
    ],
    "name:ukr_x_preferred":[
        "\u0417\u0430\u0440\u043e\u0431\u0456\u0442\u043d\u0430 \u043f\u043b\u0430\u0442\u0430"
    ],
    "name:uzb_x_preferred":[
        "Ish haqi"
    ],
    "name:vie_x_preferred":[
        "Ti\u1ec1n c\u00f4ng"
    ],
    "wof:lang_x_official":[
        "ind"
    ],
    "wof:lang_x_spoken":[
        "ind",
        "eng"
    ],
    "wof:name":"Wage",
    "wof:placetype":"locality"
},
  "geometry": {"coordinates":[108.7953,-6.8705],"type":"Point"}
}