{
  "type": "Feature",
  "properties": {
    "gn:admin1_code":"08",
    "gn:asciiname":"Karangpundut",
    "gn:country_code":"ID",
    "gn:dem":17,
    "gn:feature_class":"P",
    "gn:feature_code":"PPL",
    "gn:name":"Karangpundut",
    "gn:population":0,
    "gn:timezone":"Asia/Jakarta",
    "iso:country":"ID",
    "name:ind_x_preferred":[
        "Karangpundut"
    ],
    "wof:name":"Karangpundut",
    "wof:placetype":"locality"
},
  "geometry": {"coordinates":[112.508,-7.2084],"type":"Point"}
}