{
  "type": "Feature",
  "properties": {
    "gn:admin1_code":"33",
    "gn:asciiname":"Tambalungsasak",
    "gn:country_code":"ID",
    "gn:dem":20,
    "gn:feature_class":"P",
    "gn:feature_code":"PPL",
    "gn:name":"Tambalungsasak",
    "gn:population":0,
    "gn:timezone":"Asia/Jakarta",
    "iso:country":"ID",
    "name:ind_x_preferred":[
        "Tambalungsasak"
    ],
    "name:und_x_variant":[
        "Tjisangu",
        "Cisangu"
    ],
    "wof:lang_x_official":[
        "ind"
    ],
    "wof:lang_x_spoken":[
        "ind",
        "eng"
    ],
    "wof:name":"Tambalungsasak",
    "wof:placetype":"locality"
},
  "geometry": {"coordinates":[106.2569,-6.2894],"type":"Point"}
}