{
  "type": "Feature",
  "properties": {
    "gn:admin1_code":"15.0",
    "gn:asciiname":"Padangnegeri",
    "gn:country_code":"ID",
    "gn:dem":7,
    "gn:feature_class":"P",
    "gn:feature_code":"PPL",
    "gn:name":"Padangnegeri",
    "gn:population":0,
    "gn:timezone":"Asia/Jakarta",
    "iso:country":"ID",
    "name:ind_x_preferred":[
        "Padangnegeri"
    ],
    "wof:name":"Padangnegeri",
    "wof:placetype":"locality"
},
  "geometry": {"coordinates":[103.91808,-5.22873],"type":"Point"}
}