{
  "type": "Feature",
  "properties": {
    "gn:admin1_code":"32.0",
    "gn:asciiname":"Umbulan Lebuai",
    "gn:country_code":"ID",
    "gn:dem":61,
    "gn:feature_class":"P",
    "gn:feature_code":"PPL",
    "gn:name":"Umbulan Lebuai",
    "gn:population":0,
    "gn:timezone":"Asia/Jakarta",
    "iso:country":"ID",
    "name:ind_x_preferred":[
        "Umbulan Lebuai"
    ],
    "wof:name":"Umbulan Lebuai",
    "wof:placetype":"locality"
},
  "geometry": {"coordinates":[104.6649,-3.9145],"type":"Point"}
}