{
  "type": "Feature",
  "properties": {
    "gn:admin1_code":"26",
    "gn:asciiname":"Parrongitan",
    "gn:country_code":"ID",
    "gn:dem":1154,
    "gn:feature_class":"P",
    "gn:feature_code":"PPL",
    "gn:name":"Parrongitan",
    "gn:population":0,
    "gn:timezone":"Asia/Jakarta",
    "iso:country":"ID",
    "name:ind_x_preferred":[
        "Parrongitan"
    ],
    "wof:name":"Parrongitan",
    "wof:placetype":"locality"
},
  "geometry": {"coordinates":[99.0042,2.1053],"type":"Point"}
}