{
  "type": "Feature",
  "properties": {
    "gn:admin1_code":"26",
    "gn:asciiname":"Sitabotabo",
    "gn:country_code":"ID",
    "gn:dem":1194,
    "gn:feature_class":"P",
    "gn:feature_code":"PPL",
    "gn:name":"Sitabotabo",
    "gn:population":0,
    "gn:timezone":"Asia/Jakarta",
    "iso:country":"ID",
    "name:ind_x_preferred":[
        "Sitabotabo"
    ],
    "wof:name":"Sitabotabo",
    "wof:placetype":"locality"
},
  "geometry": {"coordinates":[98.98820000000001,2.1715],"type":"Point"}
}