{
  "type": "Feature",
  "properties": {
    "gn:admin1_code":"33.0",
    "gn:asciiname":"Cigalimbang",
    "gn:country_code":"ID",
    "gn:dem":336,
    "gn:feature_class":"P",
    "gn:feature_code":"PPL",
    "gn:name":"Cigalimbang",
    "gn:population":0,
    "gn:timezone":"Asia/Jakarta",
    "iso:country":"ID",
    "name:ind_x_preferred":[
        "Cigalimbang"
    ],
    "wof:name":"Cigalimbang",
    "wof:placetype":"locality"
},
  "geometry": {"coordinates":[106.114,-6.6772],"type":"Point"}
}