{
  "type": "Feature",
  "properties": {
    "gn:admin1_code":"7.0",
    "gn:asciiname":"Sukayasa",
    "gn:country_code":"ID",
    "gn:dem":364,
    "gn:feature_class":"P",
    "gn:feature_code":"PPL",
    "gn:name":"Sukayasa",
    "gn:population":0,
    "gn:timezone":"Asia/Jakarta",
    "iso:country":"ID",
    "name:ind_x_preferred":[
        "Sukayasa"
    ],
    "wof:name":"Sukayasa",
    "wof:placetype":"locality"
},
  "geometry": {"coordinates":[109.72417,-7.40583],"type":"Point"}
}