{
  "type": "Feature",
  "properties": {
    "gn:admin1_code":"7.0",
    "gn:asciiname":"Muncar",
    "gn:country_code":"ID",
    "gn:dem":395,
    "gn:feature_class":"P",
    "gn:feature_code":"PPL",
    "gn:name":"Muncar",
    "gn:population":0,
    "gn:timezone":"Asia/Jakarta",
    "iso:country":"ID",
    "wof:name":"Muncar",
    "wof:placetype":"locality"
},
  "geometry": {"coordinates":[110.61694,-7.37556],"type":"Point"}
}