{
  "type": "Feature",
  "properties": {
    "gn:admin1_code":"30",
    "gn:asciiname":"Naringgul",
    "gn:country_code":"ID",
    "gn:dem":730,
    "gn:feature_class":"P",
    "gn:feature_code":"PPL",
    "gn:name":"Naringgul",
    "gn:population":0,
    "gn:timezone":"Asia/Jakarta",
    "iso:country":"ID",
    "name:ind_x_preferred":[
        "Naringgul"
    ],
    "wof:name":"Naringgul",
    "wof:placetype":"locality"
},
  "geometry": {"coordinates":[107.80500000000001,-6.94861],"type":"Point"}
}