{
  "type": "Feature",
  "properties": {
    "gn:admin1_code":"30",
    "gn:asciiname":"Bojongloa",
    "gn:cc2":"ID",
    "gn:country_code":"ID",
    "gn:dem":699,
    "gn:feature_class":"P",
    "gn:feature_code":"PPL",
    "gn:name":"Bojongloa",
    "gn:population":0,
    "gn:timezone":"Asia/Jakarta",
    "iso:country":"ID",
    "name:ind_x_preferred":[
        "Bojongloa"
    ],
    "name:und_x_variant":[
        "Bodjongloa 1",
        "Bojongloa Satu"
    ],
    "wof:name":"Bojongloa",
    "wof:placetype":"locality"
},
  "geometry": {"coordinates":[107.51806000000001,-6.99972],"type":"Point"}
}