{
  "type": "Feature",
  "properties": {
    "gn:admin1_code":"22",
    "gn:asciiname":"Teppoe",
    "gn:country_code":"ID",
    "gn:dem":8,
    "gn:feature_class":"P",
    "gn:feature_code":"PPL",
    "gn:name":"Teppoe",
    "gn:population":0,
    "gn:timezone":"Asia/Makassar",
    "iso:country":"ID",
    "name:ind_x_preferred":[
        "Teppoe"
    ],
    "name:und_x_variant":[
        "Tppoe"
    ],
    "wof:name":"Teppoe",
    "wof:placetype":"locality"
},
  "geometry": {"coordinates":[121.76990000000001,-4.8237],"type":"Point"}
}