{
  "type": "Feature",
  "properties": {
    "gn:admin1_code":"7.0",
    "gn:asciiname":"Jambuer",
    "gn:country_code":"ID",
    "gn:dem":1106,
    "gn:feature_class":"P",
    "gn:feature_code":"PPL",
    "gn:name":"Jambuer",
    "gn:population":0,
    "gn:timezone":"Asia/Jakarta",
    "iso:country":"ID",
    "name:ind_x_preferred":[
        "Jambuer"
    ],
    "wof:name":"Jambuer",
    "wof:placetype":"locality"
},
  "geometry": {"coordinates":[109.78082999999999,-7.25333],"type":"Point"}
}