{
  "type": "Feature",
  "properties": {
    "gn:admin1_code":"30.0",
    "gn:asciiname":"Majalaya",
    "gn:country_code":"ID",
    "gn:dem":56,
    "gn:feature_class":"P",
    "gn:feature_code":"PPL",
    "gn:name":"Majalaya",
    "gn:population":0,
    "gn:timezone":"Asia/Jakarta",
    "iso:country":"ID",
    "name:ind_x_preferred":[
        "Majalaya"
    ],
    "name:und_x_variant":[
        "Madjalaja"
    ],
    "wof:name":"Majalaya",
    "wof:placetype":"locality"
},
  "geometry": {"coordinates":[108.75920000000001,-7.0281],"type":"Point"}
}