{
  "type": "Feature",
  "properties": {
    "gn:admin1_code":"30.0",
    "gn:asciiname":"Barengkok",
    "gn:country_code":"ID",
    "gn:dem":10,
    "gn:feature_class":"P",
    "gn:feature_code":"PPL",
    "gn:name":"Barengkok",
    "gn:population":0,
    "gn:timezone":"Asia/Jakarta",
    "iso:country":"ID",
    "name:ind_x_preferred":[
        "Barengkok"
    ],
    "name:und_x_variant":[
        "Tjibarengkok"
    ],
    "wof:name":"Barengkok",
    "wof:placetype":"locality"
},
  "geometry": {"coordinates":[108.4726,-7.7315],"type":"Point"}
}