{
  "type": "Feature",
  "properties": {
    "gn:admin1_code":"30.0",
    "gn:asciiname":"Cilangir",
    "gn:country_code":"ID",
    "gn:dem":575,
    "gn:feature_class":"P",
    "gn:feature_code":"PPL",
    "gn:name":"Cilangir",
    "gn:population":0,
    "gn:timezone":"Asia/Jakarta",
    "iso:country":"ID",
    "name:ind_x_preferred":[
        "Cilangir"
    ],
    "name:und_x_variant":[
        "Pasirlanggir"
    ],
    "wof:name":"Cilangir",
    "wof:placetype":"locality"
},
  "geometry": {"coordinates":[107.95059999999999,-7.0442],"type":"Point"}
}