{
  "type": "Feature",
  "properties": {
    "gn:admin1_code":"30",
    "gn:asciiname":"Gembor",
    "gn:country_code":"ID",
    "gn:dem":726,
    "gn:feature_class":"P",
    "gn:feature_code":"PPL",
    "gn:name":"Gembor",
    "gn:population":0,
    "gn:timezone":"Asia/Jakarta",
    "iso:country":"ID",
    "wof:name":"Gembor",
    "wof:placetype":"locality"
},
  "geometry": {"coordinates":[107.60028,-7.05889],"type":"Point"}
}