{
  "type": "Feature",
  "properties": {
    "gn:admin1_code":"18.0",
    "gn:asciiname":"Kurupoke",
    "gn:country_code":"ID",
    "gn:dem":924,
    "gn:feature_class":"P",
    "gn:feature_code":"PPL",
    "gn:name":"Kurupoke",
    "gn:population":0,
    "gn:timezone":"Asia/Makassar",
    "iso:country":"ID",
    "name:ind_x_preferred":[
        "Kurupoke"
    ],
    "wof:name":"Kurupoke",
    "wof:placetype":"locality"
},
  "geometry": {"coordinates":[121.8314,-8.6251],"type":"Point"}
}