{
  "type": "Feature",
  "properties": {
    "gn:admin1_code":"30",
    "gn:asciiname":"Haursereh",
    "gn:country_code":"ID",
    "gn:dem":1015,
    "gn:feature_class":"P",
    "gn:feature_code":"PPL",
    "gn:name":"Haursereh",
    "gn:population":0,
    "gn:timezone":"Asia/Jakarta",
    "iso:country":"ID",
    "name:ind_x_preferred":[
        "Haursereh"
    ],
    "name:und_x_variant":[
        "Haurseah"
    ],
    "wof:lang_x_official":[
        "ind"
    ],
    "wof:lang_x_spoken":[
        "ind",
        "eng"
    ],
    "wof:name":"Haursereh",
    "wof:placetype":"locality"
},
  "geometry": {"coordinates":[107.479,-7.007],"type":"Point"}
}