{
  "type": "Feature",
  "properties": {
    "gn:admin1_code":"21.0",
    "gn:asciiname":"Komba",
    "gn:country_code":"ID",
    "gn:dem":162,
    "gn:feature_class":"P",
    "gn:feature_code":"PPL",
    "gn:name":"Komba",
    "gn:population":0,
    "gn:timezone":"Asia/Makassar",
    "iso:country":"ID",
    "name:ind_x_preferred":[
        "Komba"
    ],
    "wof:name":"Komba",
    "wof:placetype":"locality"
},
  "geometry": {"coordinates":[119.9145,-0.7309],"type":"Point"}
}