{
  "type": "Feature",
  "properties": {
    "gn:admin1_code":"30",
    "gn:asciiname":"Awitali",
    "gn:country_code":"ID",
    "gn:dem":440,
    "gn:feature_class":"P",
    "gn:feature_code":"PPL",
    "gn:name":"Awitali",
    "gn:population":0,
    "gn:timezone":"Asia/Jakarta",
    "iso:country":"ID",
    "name:ind_x_preferred":[
        "Awitali"
    ],
    "wof:name":"Awitali",
    "wof:placetype":"locality"
},
  "geometry": {"coordinates":[107.89306000000001,-6.78694],"type":"Point"}
}