{
  "type": "Feature",
  "properties": {
    "gn:admin1_code":"1",
    "gn:asciiname":"Tanjung Parit",
    "gn:country_code":"ID",
    "gn:dem":15,
    "gn:feature_class":"P",
    "gn:feature_code":"PPL",
    "gn:name":"Tanjung Parit",
    "gn:population":0,
    "gn:timezone":"Asia/Jakarta",
    "iso:country":"ID",
    "name:ind_x_preferred":[
        "Tanjung Parit"
    ],
    "name:und_x_variant":[
        "Tandjungparit"
    ],
    "wof:name":"Tanjung Parit",
    "wof:placetype":"locality"
},
  "geometry": {"coordinates":[98.1439,4.3716],"type":"Point"}
}