{
  "type": "Feature",
  "properties": {
    "gn:admin1_code":"7",
    "gn:asciiname":"Ngargosari",
    "gn:country_code":"ID",
    "gn:dem":1088,
    "gn:feature_class":"P",
    "gn:feature_code":"PPL",
    "gn:name":"Ngargosari",
    "gn:population":0,
    "gn:timezone":"Asia/Jakarta",
    "iso:country":"ID",
    "name:ind_x_preferred":[
        "Ngargosari"
    ],
    "wof:name":"Ngargosari",
    "wof:placetype":"locality"
},
  "geometry": {"coordinates":[109.99556,-7.16222],"type":"Point"}
}