{
  "type": "Feature",
  "properties": {
    "gn:admin1_code":"17.0",
    "gn:asciiname":"Batucangku",
    "gn:country_code":"ID",
    "gn:dem":524,
    "gn:feature_class":"P",
    "gn:feature_code":"PPL",
    "gn:name":"Batucangku",
    "gn:population":0,
    "gn:timezone":"Asia/Makassar",
    "iso:country":"ID",
    "name:ind_x_preferred":[
        "Batucangku"
    ],
    "wof:name":"Batucangku",
    "wof:placetype":"locality"
},
  "geometry": {"coordinates":[116.56570000000001,-8.498],"type":"Point"}
}