{
  "type": "Feature",
  "properties": {
    "gn:admin1_code":"7.0",
    "gn:asciiname":"Telukawur",
    "gn:country_code":"ID",
    "gn:dem":8,
    "gn:feature_class":"P",
    "gn:feature_code":"PPL",
    "gn:name":"Telukawur",
    "gn:population":0,
    "gn:timezone":"Asia/Jakarta",
    "iso:country":"ID",
    "name:ind_x_preferred":[
        "Telukawur"
    ],
    "wof:name":"Telukawur",
    "wof:placetype":"locality"
},
  "geometry": {"coordinates":[110.64100000000001,-6.6247],"type":"Point"}
}