{
  "type": "Feature",
  "properties": {
    "gn:admin1_code":"30.0",
    "gn:asciiname":"Cireundang",
    "gn:country_code":"ID",
    "gn:dem":774,
    "gn:feature_class":"P",
    "gn:feature_code":"PPLA4",
    "gn:name":"Cireundang",
    "gn:population":0,
    "gn:timezone":"Asia/Jakarta",
    "iso:country":"ID",
    "name:ind_x_preferred":[
        "Cireundang"
    ],
    "name:und_x_variant":[
        "Tjirendang"
    ],
    "wof:lang_x_official":[
        "ind"
    ],
    "wof:lang_x_spoken":[
        "ind",
        "eng"
    ],
    "wof:name":"Cireundang",
    "wof:placetype":"locality"
},
  "geometry": {"coordinates":[107.87819,-7.20021],"type":"Point"}
}