{
  "type": "Feature",
  "properties": {
    "gn:admin1_code":"18.0",
    "gn:asciiname":"Halat",
    "gn:country_code":"ID",
    "gn:dem":281,
    "gn:feature_class":"P",
    "gn:feature_code":"PPLA4",
    "gn:name":"Halat",
    "gn:population":0,
    "gn:timezone":"Asia/Makassar",
    "iso:country":"ID",
    "name:ceb_x_preferred":[
        "Halat"
    ],
    "name:ind_x_preferred":[
        "Halat"
    ],
    "name:swe_x_preferred":[
        "Halat"
    ],
    "wof:name":"Halat",
    "wof:placetype":"locality"
},
  "geometry": {"coordinates":[122.2073,-8.6832],"type":"Point"}
}