{
  "type": "Feature",
  "properties": {
    "gn:admin1_code":"30",
    "gn:asciiname":"Watubiting",
    "gn:country_code":"ID",
    "gn:dem":301,
    "gn:feature_class":"P",
    "gn:feature_code":"PPL",
    "gn:name":"Watubiting",
    "gn:population":0,
    "gn:timezone":"Asia/Jakarta",
    "iso:country":"ID",
    "name:ind_x_preferred":[
        "Watubiting"
    ],
    "wof:name":"Watubiting",
    "wof:placetype":"locality"
},
  "geometry": {"coordinates":[112.9564,-7.7847],"type":"Point"}
}