{
  "type": "Feature",
  "properties": {
    "gn:admin1_code":"40",
    "gn:asciiname":"Kandis",
    "gn:country_code":"ID",
    "gn:dem":6,
    "gn:feature_class":"P",
    "gn:feature_code":"PPL",
    "gn:name":"Kandis",
    "gn:population":0,
    "gn:timezone":"Asia/Jakarta",
    "iso:country":"ID",
    "name:ceb_x_preferred":[
        "Kandis"
    ],
    "name:dan_x_preferred":[
        "Kandis"
    ],
    "name:deu_x_preferred":[
        "Kandis"
    ],
    "name:ind_x_preferred":[
        "Kandis"
    ],
    "name:lit_x_preferred":[
        "Kandis"
    ],
    "name:nld_x_preferred":[
        "Kandis"
    ],
    "name:swe_x_preferred":[
        "Kandis"
    ],
    "wof:lang_x_official":[
        "ind"
    ],
    "wof:lang_x_spoken":[
        "ind",
        "eng"
    ],
    "wof:name":"Kandis",
    "wof:placetype":"locality"
},
  "geometry": {"coordinates":[103.48545,0.89961],"type":"Point"}
}