{
  "type": "Feature",
  "properties": {
    "gn:admin1_code":"30",
    "gn:asciiname":"Neglasari",
    "gn:country_code":"ID",
    "gn:dem":531,
    "gn:feature_class":"P",
    "gn:feature_code":"PPL",
    "gn:name":"Neglasari",
    "gn:population":0,
    "gn:timezone":"Asia/Jakarta",
    "iso:country":"ID",
    "name:ind_x_preferred":[
        "Neglasari"
    ],
    "name:jav_x_preferred":[
        "Neglasari"
    ],
    "name:msa_x_preferred":[
        "Neglasari"
    ],
    "name:sun_x_preferred":[
        "N\u00e9glasari"
    ],
    "wof:name":"Neglasari",
    "wof:placetype":"locality"
},
  "geometry": {"coordinates":[108.26611,-6.94167],"type":"Point"}
}