{
  "type": "Feature",
  "properties": {
    "gn:admin1_code":"33.0",
    "gn:asciiname":"Janaka",
    "gn:country_code":"ID",
    "gn:dem":187,
    "gn:feature_class":"P",
    "gn:feature_code":"PPLA4",
    "gn:name":"Janaka",
    "gn:population":0,
    "gn:timezone":"Asia/Jakarta",
    "iso:country":"ID",
    "name:ben_x_preferred":[
        "\u099c\u09a8\u0995"
    ],
    "name:deu_x_preferred":[
        "Janaka"
    ],
    "name:dty_x_preferred":[
        "\u091c\u0928\u0915"
    ],
    "name:fra_x_preferred":[
        "Janaka"
    ],
    "name:guj_x_preferred":[
        "\u0a9c\u0aa8\u0a95"
    ],
    "name:hin_x_preferred":[
        "\u091c\u0928\u0915"
    ],
    "name:ind_x_preferred":[
        "Janaka"
    ],
    "name:jpn_x_preferred":[
        "\u30b8\u30e3\u30ca\u30ab"
    ],
    "name:kan_x_preferred":[
        "\u0c9c\u0ca8\u0c95"
    ],
    "name:mai_x_preferred":[
        "\u091c\u0928\u0915"
    ],
    "name:mal_x_preferred":[
        "\u0d1c\u0d28\u0d15\u0d7b"
    ],
    "name:mar_x_preferred":[
        "\u091c\u0928\u0915"
    ],
    "name:nep_x_preferred":[
        "\u091c\u0928\u0915"
    ],
    "name:pan_x_preferred":[
        "\u0a1c\u0a28\u0a15"
    ],
    "name:pnb_x_preferred":[
        "\u062c\u0646\u06a9"
    ],
    "name:por_x_preferred":[
        "Janaka"
    ],
    "name:rus_x_preferred":[
        "\u0414\u0436\u0430\u043d\u0430\u043a\u0430"
    ],
    "name:san_x_preferred":[
        "\u091c\u0928\u0915\u0903"
    ],
    "name:tam_x_preferred":[
        "\u0b9a\u0ba9\u0b95\u0ba9\u0bcd"
    ],
    "name:tel_x_preferred":[
        "\u0c1c\u0c28\u0c15\u0c41\u0c21\u0c41"
    ],
    "name:tha_x_preferred":[
        "\u0e0a\u0e19\u0e01"
    ],
    "name:und_x_variant":[
        "Djanaka",
        "Janaka"
    ],
    "name:zho_x_preferred":[
        "\u906e\u90a3\u7aed"
    ],
    "wof:lang_x_official":[
        "ind"
    ],
    "wof:lang_x_spoken":[
        "ind",
        "eng"
    ],
    "wof:name":"Janaka",
    "wof:placetype":"locality"
},
  "geometry": {"coordinates":[105.88137,-6.31671],"type":"Point"}
}