{
  "type": "Feature",
  "properties": {
    "gn:admin1_code":"07",
    "gn:asciiname":"Kalitengah",
    "gn:country_code":"ID",
    "gn:dem":1228,
    "gn:feature_class":"P",
    "gn:feature_code":"PPL",
    "gn:name":"Kalitengah",
    "gn:population":0,
    "gn:timezone":"Asia/Jakarta",
    "iso:country":"ID",
    "name:und_x_variant":[
        "Kalitengah Satu",
        "Kalitengah 1",
        "Kalitengah"
    ],
    "wof:name":"Kalitengah",
    "wof:placetype":"locality"
},
  "geometry": {"coordinates":[110.44138999999998,-7.39028],"type":"Point"}
}