{
  "type": "Feature",
  "properties": {
    "gn:admin1_code":"30",
    "gn:asciiname":"Cilimpung",
    "gn:country_code":"ID",
    "gn:dem":55,
    "gn:feature_class":"P",
    "gn:feature_code":"PPL",
    "gn:name":"Cilimpung",
    "gn:population":0,
    "gn:timezone":"Asia/Jakarta",
    "iso:country":"ID",
    "name:ind_x_preferred":[
        "Cilimpung"
    ],
    "wof:name":"Cilimpung",
    "wof:placetype":"locality"
},
  "geometry": {"coordinates":[107.84417000000001,-6.53361],"type":"Point"}
}