{
  "type": "Feature",
  "properties": {
    "gn:admin1_code":"33.0",
    "gn:asciiname":"Pakalongan",
    "gn:country_code":"ID",
    "gn:dem":164,
    "gn:feature_class":"P",
    "gn:feature_code":"PPL",
    "gn:name":"Pakalongan",
    "gn:population":0,
    "gn:timezone":"Asia/Jakarta",
    "iso:country":"ID",
    "name:heb_x_preferred":[
        "\u05e4\u05e7\u05dc\u05d5\u05e0\u05d2\u05df"
    ],
    "name:ind_x_preferred":[
        "Pakalongan"
    ],
    "wof:lang_x_official":[
        "ind"
    ],
    "wof:lang_x_spoken":[
        "ind",
        "eng"
    ],
    "wof:name":"Pakalongan",
    "wof:placetype":"locality"
},
  "geometry": {"coordinates":[106.1087,-6.3309],"type":"Point"}
}