{
  "type": "Feature",
  "properties": {
    "gn:admin1_code":"7.0",
    "gn:asciiname":"Kamal",
    "gn:country_code":"ID",
    "gn:dem":88,
    "gn:feature_class":"P",
    "gn:feature_code":"PPL",
    "gn:name":"Kamal",
    "gn:population":0,
    "gn:timezone":"Asia/Jakarta",
    "iso:country":"ID",
    "name:ind_x_preferred":[
        "Kamal"
    ],
    "wof:name":"Kamal",
    "wof:placetype":"locality"
},
  "geometry": {"coordinates":[109.48417000000001,-7.49583],"type":"Point"}
}