{
  "type": "Feature",
  "properties": {
    "gn:admin1_code":"15.0",
    "gn:asciiname":"Sukamenanti Tiga",
    "gn:country_code":"ID",
    "gn:dem":230,
    "gn:feature_class":"P",
    "gn:feature_code":"PPL",
    "gn:name":"Sukamenanti Tiga",
    "gn:population":0,
    "gn:timezone":"Asia/Jakarta",
    "iso:country":"ID",
    "name:ind_x_preferred":[
        "Sukamenanti Tiga"
    ],
    "name:und_x_variant":[
        "Sukamenanti 3"
    ],
    "wof:name":"Sukamenanti Tiga",
    "wof:placetype":"locality"
},
  "geometry": {"coordinates":[104.60186,-4.87827],"type":"Point"}
}