{
  "type": "Feature",
  "properties": {
    "gn:admin1_code":"15.0",
    "gn:asciiname":"Yatma",
    "gn:country_code":"ID",
    "gn:dem":42,
    "gn:feature_class":"P",
    "gn:feature_code":"PPL",
    "gn:name":"Yatma",
    "gn:population":0,
    "gn:timezone":"Asia/Jakarta",
    "iso:country":"ID",
    "name:ara_x_preferred":[
        "\u064a\u062a\u0645\u0627"
    ],
    "name:cat_x_preferred":[
        "Yatma"
    ],
    "name:ceb_x_preferred":[
        "Yatm\u0101"
    ],
    "name:ind_x_preferred":[
        "Yatma"
    ],
    "wof:lang_x_official":[
        "ind"
    ],
    "wof:lang_x_spoken":[
        "ind",
        "eng"
    ],
    "wof:name":"Yatma",
    "wof:placetype":"locality"
},
  "geometry": {"coordinates":[105.55531000000001,-5.62855],"type":"Point"}
}