{
  "type": "Feature",
  "properties": {
    "gn:admin1_code":"32.0",
    "gn:asciiname":"Jambatmayan",
    "gn:country_code":"ID",
    "gn:dem":737,
    "gn:feature_class":"P",
    "gn:feature_code":"PPL",
    "gn:name":"Jambatmayan",
    "gn:population":0,
    "gn:timezone":"Asia/Jakarta",
    "iso:country":"ID",
    "name:und_x_variant":[
        "Djambatmajan",
        "Jambatmayan"
    ],
    "wof:name":"Jambatmayan",
    "wof:placetype":"locality"
},
  "geometry": {"coordinates":[103.15682,-3.91],"type":"Point"}
}