{
  "type": "Feature",
  "properties": {
    "gn:admin1_code":"8",
    "gn:asciiname":"Penangan",
    "gn:country_code":"ID",
    "gn:dem":29,
    "gn:feature_class":"P",
    "gn:feature_code":"PPL",
    "gn:name":"Penangan",
    "gn:population":0,
    "gn:timezone":"Asia/Jakarta",
    "iso:country":"ID",
    "name:ind_x_preferred":[
        "Penangan"
    ],
    "wof:name":"Penangan",
    "wof:placetype":"locality"
},
  "geometry": {"coordinates":[113.10429999999999,-7.0768],"type":"Point"}
}