{
  "type": "Feature",
  "properties": {
    "gn:admin1_code":"26",
    "gn:asciiname":"Pondok Afdeling Tujuh",
    "gn:country_code":"ID",
    "gn:dem":166,
    "gn:feature_class":"P",
    "gn:feature_code":"PPL",
    "gn:name":"Pondok Afdeling Tujuh",
    "gn:population":0,
    "gn:timezone":"Asia/Jakarta",
    "iso:country":"ID",
    "name:ind_x_preferred":[
        "Pondok Afdeling Tujuh"
    ],
    "name:und_x_variant":[
        "Pondok Afdeling 7"
    ],
    "wof:name":"Pondok Afdeling Tujuh",
    "wof:placetype":"locality"
},
  "geometry": {"coordinates":[99.1977,3.0211],"type":"Point"}
}