{
  "type": "Feature",
  "properties": {
    "gn:admin1_code":"8.0",
    "gn:asciiname":"Pucangan",
    "gn:country_code":"ID",
    "gn:dem":453,
    "gn:feature_class":"P",
    "gn:feature_code":"PPL",
    "gn:name":"Pucangan",
    "gn:population":0,
    "gn:timezone":"Asia/Jakarta",
    "iso:country":"ID",
    "name:ind_x_preferred":[
        "Pucangan"
    ],
    "wof:name":"Pucangan",
    "wof:placetype":"locality"
},
  "geometry": {"coordinates":[111.762,-8.0034],"type":"Point"}
}