{
  "type": "Feature",
  "properties": {
    "gn:admin1_code":"26",
    "gn:asciiname":"Afdeling Dua Puluh Empat/Enam",
    "gn:country_code":"ID",
    "gn:dem":86,
    "gn:feature_class":"P",
    "gn:feature_code":"PPL",
    "gn:name":"Afdeling Dua Puluh Empat/Enam",
    "gn:population":0,
    "gn:timezone":"Asia/Jakarta",
    "iso:country":"ID",
    "name:ind_x_preferred":[
        "Afdeling Dua Puluh Empat/Enam"
    ],
    "name:und_x_variant":[
        "Afdeling 24/6"
    ],
    "wof:lang_x_official":[
        "ind"
    ],
    "wof:lang_x_spoken":[
        "ind",
        "eng"
    ],
    "wof:name":"Afdeling Dua Puluh Empat/Enam",
    "wof:placetype":"locality"
},
  "geometry": {"coordinates":[99.1678,3.1985],"type":"Point"}
}