{
  "type": "Feature",
  "properties": {
    "gn:admin1_code":"0.0",
    "gn:asciiname":"Salurang",
    "gn:cc2":"ID",
    "gn:country_code":"ID",
    "gn:dem":62,
    "gn:feature_class":"P",
    "gn:feature_code":"PPL",
    "gn:name":"Salurang",
    "gn:population":0,
    "gn:timezone":"Asia/Makassar",
    "iso:country":"ID",
    "name:und_x_variant":[
        "Moade",
        "Saluran",
        "Saloerang",
        "Salurang"
    ],
    "wof:name":"Salurang",
    "wof:placetype":"locality"
},
  "geometry": {"coordinates":[125.65000000000001,3.46667],"type":"Point"}
}