{
  "type": "Feature",
  "properties": {
    "gn:admin1_code":"26",
    "gn:asciiname":"Sumberejo Dua",
    "gn:country_code":"ID",
    "gn:dem":16,
    "gn:feature_class":"P",
    "gn:feature_code":"PPL",
    "gn:name":"Sumberejo Dua",
    "gn:population":0,
    "gn:timezone":"Asia/Jakarta",
    "iso:country":"ID",
    "name:ind_x_preferred":[
        "Sumberejo Dua"
    ],
    "name:und_x_variant":[
        "Sumberejo 2"
    ],
    "wof:name":"Sumberejo Dua",
    "wof:placetype":"locality"
},
  "geometry": {"coordinates":[98.91719999999999,3.5578],"type":"Point"}
}