{
  "type": "Feature",
  "properties": {
    "gn:admin1_code":"24",
    "gn:asciiname":"Kotobaru",
    "gn:country_code":"ID",
    "gn:dem":160,
    "gn:feature_class":"P",
    "gn:feature_code":"PPL",
    "gn:name":"Kotobaru",
    "gn:population":0,
    "gn:timezone":"Asia/Jakarta",
    "iso:country":"ID",
    "name:ind_x_preferred":[
        "Kotobaru"
    ],
    "wof:name":"Kotobaru",
    "wof:placetype":"locality"
},
  "geometry": {"coordinates":[100.5265,0.157],"type":"Point"}
}