{
  "type": "Feature",
  "properties": {
    "gn:admin1_code":"30.0",
    "gn:asciiname":"Ciseuti",
    "gn:country_code":"ID",
    "gn:dem":294,
    "gn:feature_class":"P",
    "gn:feature_code":"PPL",
    "gn:name":"Ciseuti",
    "gn:population":0,
    "gn:timezone":"Asia/Jakarta",
    "iso:country":"ID",
    "name:ind_x_preferred":[
        "Ciseuti"
    ],
    "wof:name":"Ciseuti",
    "wof:placetype":"locality"
},
  "geometry": {"coordinates":[107.0633,-7.3133],"type":"Point"}
}