{
  "type": "Feature",
  "properties": {
    "gn:admin1_code":"29.0",
    "gn:asciiname":"Paniti",
    "gn:country_code":"ID",
    "gn:dem":7,
    "gn:feature_class":"P",
    "gn:feature_code":"PPL",
    "gn:name":"Paniti",
    "gn:population":0,
    "gn:timezone":"Asia/Jayapura",
    "iso:country":"ID",
    "name:und_x_variant":[
        "Peniti",
        "Paniti"
    ],
    "wof:name":"Paniti",
    "wof:placetype":"locality"
},
  "geometry": {"coordinates":[128.68256,0.39683],"type":"Point"}
}