{
  "type": "Feature",
  "properties": {
    "gn:admin1_code":"39.0",
    "gn:asciiname":"Saukris",
    "gn:country_code":"ID",
    "gn:dem":16,
    "gn:feature_class":"P",
    "gn:feature_code":"PPL",
    "gn:name":"Saukris",
    "gn:population":0,
    "gn:timezone":"Asia/Jayapura",
    "iso:country":"ID",
    "name:und_x_variant":[
        "Saoekris",
        "Saukris"
    ],
    "wof:name":"Saukris",
    "wof:placetype":"locality"
},
  "geometry": {"coordinates":[132.96029999999999,-0.46711],"type":"Point"}
}