{
  "type": "Feature",
  "properties": {
    "gn:admin1_code":"38",
    "gn:asciiname":"Gatareng",
    "gn:country_code":"ID",
    "gn:dem":760,
    "gn:feature_class":"P",
    "gn:feature_code":"PPL",
    "gn:name":"Gatareng",
    "gn:population":0,
    "gn:timezone":"Asia/Makassar",
    "iso:country":"ID",
    "name:ind_x_preferred":[
        "Gatareng"
    ],
    "wof:name":"Gatareng",
    "wof:placetype":"locality"
},
  "geometry": {"coordinates":[119.7936,-4.7051],"type":"Point"}
}