{
  "type": "Feature",
  "properties": {
    "gn:admin1_code":"8.0",
    "gn:asciiname":"Senden",
    "gn:country_code":"ID",
    "gn:dem":124,
    "gn:feature_class":"P",
    "gn:feature_code":"PPLA4",
    "gn:name":"Senden",
    "gn:population":0,
    "gn:timezone":"Asia/Jakarta",
    "iso:country":"ID",
    "name:ind_x_preferred":[
        "Senden"
    ],
    "wof:name":"Senden",
    "wof:placetype":"locality"
},
  "geometry": {"coordinates":[111.6742,-8.1859],"type":"Point"}
}