{
  "type": "Feature",
  "properties": {
    "gn:admin1_code":"8.0",
    "gn:asciiname":"Senden",
    "gn:country_code":"ID",
    "gn:dem":124,
    "gn:feature_class":"P",
    "gn:feature_code":"PPLA4",
    "gn:name":"Senden",
    "gn:population":0,
    "gn:timezone":"Asia/Jakarta",
    "iso:country":"ID",
    "name:als_x_preferred":[
        "Senden"
    ],
    "name:ara_x_preferred":[
        "\u0632\u0646\u062f\u0646"
    ],
    "name:azb_x_preferred":[
        "\u0632\u0646\u062f\u0646"
    ],
    "name:ceb_x_preferred":[
        "Senden"
    ],
    "name:dan_x_preferred":[
        "Senden"
    ],
    "name:deu_x_preferred":[
        "Senden"
    ],
    "name:epo_x_preferred":[
        "Senden"
    ],
    "name:eus_x_preferred":[
        "Senden"
    ],
    "name:fas_x_preferred":[
        "\u0632\u0646\u062f\u0646"
    ],
    "name:fra_x_preferred":[
        "Senden"
    ],
    "name:hun_x_preferred":[
        "Senden"
    ],
    "name:hye_x_preferred":[
        "\u0536\u0565\u0576\u0564\u0565\u0576"
    ],
    "name:ind_x_preferred":[
        "Senden"
    ],
    "name:ita_x_preferred":[
        "Senden"
    ],
    "name:kaz_x_preferred":[
        "\u0417\u0435\u043d\u0434\u0435\u043d"
    ],
    "name:kir_x_preferred":[
        "\u0417\u0435\u043d\u0434\u0435\u043d"
    ],
    "name:lmo_x_preferred":[
        "Senden"
    ],
    "name:msa_x_preferred":[
        "Senden"
    ],
    "name:nld_x_preferred":[
        "Senden"
    ],
    "name:pol_x_preferred":[
        "Senden"
    ],
    "name:por_x_preferred":[
        "Senden"
    ],
    "name:ron_x_preferred":[
        "Senden"
    ],
    "name:rus_x_preferred":[
        "\u0417\u0435\u043d\u0434\u0435\u043d"
    ],
    "name:spa_x_preferred":[
        "Senden"
    ],
    "name:srp_x_preferred":[
        "\u0417\u0435\u043d\u0434\u0435\u043d"
    ],
    "name:swe_x_preferred":[
        "Senden"
    ],
    "name:tur_x_preferred":[
        "Senden"
    ],
    "name:ukr_x_preferred":[
        "\u0417\u0435\u043d\u0434\u0435\u043d"
    ],
    "name:uzb_x_preferred":[
        "Senden"
    ],
    "name:vie_x_preferred":[
        "Senden"
    ],
    "name:vol_x_preferred":[
        "Senden"
    ],
    "name:war_x_preferred":[
        "Senden"
    ],
    "wof:lang_x_official":[
        "ind"
    ],
    "wof:lang_x_spoken":[
        "ind",
        "eng"
    ],
    "wof:name":"Senden",
    "wof:placetype":"locality"
},
  "geometry": {"coordinates":[111.6742,-8.1859],"type":"Point"}
}