{
  "type": "Feature",
  "properties": {
    "gn:admin1_code":"8.0",
    "gn:asciiname":"Sambiroto",
    "gn:country_code":"ID",
    "gn:dem":74,
    "gn:feature_class":"P",
    "gn:feature_code":"PPL",
    "gn:name":"Sambiroto",
    "gn:population":0,
    "gn:timezone":"Asia/Jakarta",
    "iso:country":"ID",
    "name:ind_x_preferred":[
        "Sambiroto"
    ],
    "wof:name":"Sambiroto",
    "wof:placetype":"locality"
},
  "geometry": {"coordinates":[112.5371,-7.5431],"type":"Point"}
}