{
  "type": "Feature",
  "properties": {
    "gn:admin1_code":"30.0",
    "gn:asciiname":"Simpang",
    "gn:country_code":"ID",
    "gn:dem":16,
    "gn:feature_class":"P",
    "gn:feature_code":"PPLA4",
    "gn:name":"Simpang",
    "gn:population":0,
    "gn:timezone":"Asia/Jakarta",
    "iso:country":"ID",
    "name:ind_x_preferred":[
        "Simpang"
    ],
    "name:und_x_variant":[
        "Simpang Dua"
    ],
    "wof:name":"Simpang",
    "wof:placetype":"locality"
},
  "geometry": {"coordinates":[107.1592,-7.4188],"type":"Point"}
}