{
  "type": "Feature",
  "properties": {
    "gn:admin1_code":"15.0",
    "gn:asciiname":"Umbulan Tulungkenbung",
    "gn:country_code":"ID",
    "gn:dem":48,
    "gn:feature_class":"P",
    "gn:feature_code":"PPL",
    "gn:name":"Umbulan Tulungkenbung",
    "gn:population":0,
    "gn:timezone":"Asia/Jakarta",
    "iso:country":"ID",
    "name:ind_x_preferred":[
        "Umbulan Tulungkenbung"
    ],
    "wof:name":"Umbulan Tulungkenbung",
    "wof:placetype":"locality"
},
  "geometry": {"coordinates":[104.88994,-4.87478],"type":"Point"}
}