{
  "type": "Feature",
  "properties": {
    "gn:admin1_code":"30",
    "gn:asciiname":"Cibadak Dua",
    "gn:country_code":"ID",
    "gn:dem":436,
    "gn:feature_class":"P",
    "gn:feature_code":"PPL",
    "gn:name":"Cibadak Dua",
    "gn:population":0,
    "gn:timezone":"Asia/Jakarta",
    "iso:country":"ID",
    "name:ind_x_preferred":[
        "Cibadak Dua"
    ],
    "wof:name":"Cibadak Dua",
    "wof:placetype":"locality"
},
  "geometry": {"coordinates":[106.9575,-6.57167],"type":"Point"}
}