{
  "type": "Feature",
  "properties": {
    "gn:admin1_code":"08",
    "gn:asciiname":"Duhalas",
    "gn:country_code":"ID",
    "gn:dem":63,
    "gn:feature_class":"P",
    "gn:feature_code":"PPL",
    "gn:name":"Duhalas",
    "gn:population":0,
    "gn:timezone":"Asia/Jakarta",
    "iso:country":"ID",
    "name:ind_x_preferred":[
        "Duhalas"
    ],
    "name:und_x_variant":[
        "Dukalas 2",
        "Dukalas Dua"
    ],
    "wof:lang_x_official":[
        "ind"
    ],
    "wof:lang_x_spoken":[
        "ind",
        "eng"
    ],
    "wof:name":"Duhalas",
    "wof:placetype":"locality"
},
  "geometry": {"coordinates":[112.9953,-7.0238],"type":"Point"}
}