{
  "type": "Feature",
  "properties": {
    "gn:admin1_code":"30",
    "gn:asciiname":"Cicariu",
    "gn:country_code":"ID",
    "gn:dem":1030,
    "gn:feature_class":"P",
    "gn:feature_code":"PPL",
    "gn:name":"Cicariu",
    "gn:population":0,
    "gn:timezone":"Asia/Jakarta",
    "iso:country":"ID",
    "name:ind_x_preferred":[
        "Cicariu"
    ],
    "name:und_x_variant":[
        "Tjitjariu"
    ],
    "wof:lang_x_official":[
        "ind"
    ],
    "wof:lang_x_spoken":[
        "ind",
        "eng"
    ],
    "wof:name":"Cicariu",
    "wof:placetype":"locality"
},
  "geometry": {"coordinates":[107.3014,-7.0242],"type":"Point"}
}