{
  "type": "Feature",
  "properties": {
    "gn:admin1_code":"7.0",
    "gn:asciiname":"Ciptosari",
    "gn:country_code":"ID",
    "gn:dem":22,
    "gn:feature_class":"P",
    "gn:feature_code":"PPL",
    "gn:name":"Ciptosari",
    "gn:population":0,
    "gn:timezone":"Asia/Jakarta",
    "iso:country":"ID",
    "name:ind_x_preferred":[
        "Ciptosari"
    ],
    "wof:name":"Ciptosari",
    "wof:placetype":"locality"
},
  "geometry": {"coordinates":[109.00082999999999,-7.62722],"type":"Point"}
}