{
  "type": "Feature",
  "properties": {
    "gn:admin1_code":"30.0",
    "gn:asciiname":"Nangkarea",
    "gn:country_code":"ID",
    "gn:dem":1007,
    "gn:feature_class":"P",
    "gn:feature_code":"PPL",
    "gn:name":"Nangkarea",
    "gn:population":0,
    "gn:timezone":"Asia/Jakarta",
    "iso:country":"ID",
    "name:ind_x_preferred":[
        "Nangkarea"
    ],
    "name:und_x_variant":[
        "Babakan Nangkareja",
        "Nangkareya"
    ],
    "wof:lang_x_official":[
        "ind"
    ],
    "wof:lang_x_spoken":[
        "ind",
        "eng"
    ],
    "wof:name":"Nangkarea",
    "wof:placetype":"locality"
},
  "geometry": {"coordinates":[108.1741,-7.0295],"type":"Point"}
}