{
  "type": "Feature",
  "properties": {
    "gn:admin1_code":"26",
    "gn:asciiname":"Sadakata",
    "gn:country_code":"ID",
    "gn:dem":33,
    "gn:feature_class":"P",
    "gn:feature_code":"PPL",
    "gn:name":"Sadakata",
    "gn:population":0,
    "gn:timezone":"Asia/Jakarta",
    "iso:country":"ID",
    "name:ind_x_preferred":[
        "Sadakata"
    ],
    "wof:name":"Sadakata",
    "wof:placetype":"locality"
},
  "geometry": {"coordinates":[98.5859,3.5748],"type":"Point"}
}