{
  "type": "Feature",
  "properties": {
    "gn:admin1_code":"30",
    "gn:asciiname":"Pasirmakam Leutik",
    "gn:country_code":"ID",
    "gn:dem":55,
    "gn:feature_class":"P",
    "gn:feature_code":"PPL",
    "gn:name":"Pasirmakam Leutik",
    "gn:population":0,
    "gn:timezone":"Asia/Jakarta",
    "iso:country":"ID",
    "wof:name":"Pasirmakam Leutik",
    "wof:placetype":"locality"
},
  "geometry": {"coordinates":[106.35361,-6.38889],"type":"Point"}
}