{
  "type": "Feature",
  "properties": {
    "gn:admin1_code":"26",
    "gn:asciiname":"Sianipar Dua",
    "gn:country_code":"ID",
    "gn:dem":992,
    "gn:feature_class":"P",
    "gn:feature_code":"PPL",
    "gn:name":"Sianipar Dua",
    "gn:population":0,
    "gn:timezone":"Asia/Jakarta",
    "iso:country":"ID",
    "name:ind_x_preferred":[
        "Sianipar Dua"
    ],
    "name:und_x_variant":[
        "Sianipar 2"
    ],
    "wof:lang_x_official":[
        "ind"
    ],
    "wof:lang_x_spoken":[
        "ind",
        "eng"
    ],
    "wof:name":"Sianipar Dua",
    "wof:placetype":"locality"
},
  "geometry": {"coordinates":[99.1949,2.3357],"type":"Point"}
}