{
  "type": "Feature",
  "properties": {
    "gn:admin1_code":"7.0",
    "gn:asciiname":"Kolan",
    "gn:country_code":"ID",
    "gn:dem":12,
    "gn:feature_class":"P",
    "gn:feature_code":"PPL",
    "gn:name":"Kolan",
    "gn:population":0,
    "gn:timezone":"Asia/Jakarta",
    "iso:country":"ID",
    "name:bos_x_preferred":[
        "Kolan"
    ],
    "name:deu_x_preferred":[
        "Kolan"
    ],
    "name:hrv_x_preferred":[
        "Kolan"
    ],
    "name:hun_x_preferred":[
        "Kolan"
    ],
    "name:ind_x_preferred":[
        "Kolan"
    ],
    "name:ita_x_preferred":[
        "Colane"
    ],
    "name:nld_x_preferred":[
        "Kolan"
    ],
    "name:pol_x_preferred":[
        "Gmina Kolan"
    ],
    "name:ron_x_preferred":[
        "Comuna Kolan"
    ],
    "name:slv_x_preferred":[
        "Kolan"
    ],
    "name:srp_x_preferred":[
        "\u041a\u043e\u043b\u0430\u043d"
    ],
    "name:ukr_x_preferred":[
        "\u041a\u043e\u043b\u0430\u043d"
    ],
    "wof:lang_x_official":[
        "ind"
    ],
    "wof:lang_x_spoken":[
        "ind",
        "eng"
    ],
    "wof:name":"Kolan",
    "wof:placetype":"locality"
},
  "geometry": {"coordinates":[111.081,-6.7049],"type":"Point"}
}