{
  "type": "Feature",
  "properties": {
    "gn:admin1_code":"7.0",
    "gn:asciiname":"Selorejo",
    "gn:country_code":"ID",
    "gn:dem":48,
    "gn:feature_class":"P",
    "gn:feature_code":"PPL",
    "gn:name":"Selorejo",
    "gn:population":0,
    "gn:timezone":"Asia/Jakarta",
    "iso:country":"ID",
    "name:ind_x_preferred":[
        "Selorejo"
    ],
    "wof:name":"Selorejo",
    "wof:placetype":"locality"
},
  "geometry": {"coordinates":[110.40089999999999,-7.0254],"type":"Point"}
}