{
  "type": "Feature",
  "properties": {
    "gn:admin1_code":"38",
    "gn:asciiname":"Bontopunre",
    "gn:country_code":"ID",
    "gn:dem":28,
    "gn:feature_class":"P",
    "gn:feature_code":"PPL",
    "gn:name":"Bontopunre",
    "gn:population":0,
    "gn:timezone":"Asia/Makassar",
    "iso:country":"ID",
    "name:ind_x_preferred":[
        "Bontopunre"
    ],
    "wof:name":"Bontopunre",
    "wof:placetype":"locality"
},
  "geometry": {"coordinates":[120.3865,-5.34],"type":"Point"}
}