{
  "type": "Feature",
  "properties": {
    "gn:admin1_code":"1",
    "gn:asciiname":"Meunasah Tuha",
    "gn:country_code":"ID",
    "gn:dem":13,
    "gn:feature_class":"P",
    "gn:feature_code":"PPL",
    "gn:name":"Meunasah Tuha",
    "gn:population":0,
    "gn:timezone":"Asia/Jakarta",
    "iso:country":"ID",
    "name:ind_x_preferred":[
        "Meunasah Tuha"
    ],
    "wof:name":"Meunasah Tuha",
    "wof:placetype":"locality"
},
  "geometry": {"coordinates":[97.32989999999999,5.005],"type":"Point"}
}