{
  "type": "Feature",
  "properties": {
    "gn:admin1_code":"24.0",
    "gn:asciiname":"Labajau",
    "gn:country_code":"ID",
    "gn:dem":13,
    "gn:feature_class":"P",
    "gn:feature_code":"PPL",
    "gn:name":"Labajau",
    "gn:population":0,
    "gn:timezone":"Asia/Jakarta",
    "iso:country":"ID",
    "name:und_x_variant":[
        "Labadjau",
        "Labajau"
    ],
    "wof:name":"Labajau",
    "wof:placetype":"locality"
},
  "geometry": {"coordinates":[100.4406,-3.0619],"type":"Point"}
}