{
  "type": "Feature",
  "properties": {
    "gn:admin1_code":"8.0",
    "gn:asciiname":"Suket",
    "gn:country_code":"ID",
    "gn:dem":121,
    "gn:feature_class":"P",
    "gn:feature_code":"PPL",
    "gn:name":"Suket",
    "gn:population":0,
    "gn:timezone":"Asia/Jakarta",
    "iso:country":"ID",
    "name:ben_x_preferred":[
        "\u09b8\u09c1\u0995\u09c7\u09a4"
    ],
    "name:bpy_x_preferred":[
        "\u09b8\u09c1\u0995\u09c7\u09a4"
    ],
    "name:ceb_x_preferred":[
        "Suket"
    ],
    "name:hin_x_preferred":[
        "\u0938\u0941\u0915\u0947\u0924"
    ],
    "name:ind_x_preferred":[
        "Suket"
    ],
    "name:ita_x_preferred":[
        "Suket"
    ],
    "name:msa_x_preferred":[
        "Suket"
    ],
    "name:nld_x_preferred":[
        "Suket"
    ],
    "name:por_x_preferred":[
        "Suket"
    ],
    "name:vie_x_preferred":[
        "Suket"
    ],
    "name:zho_x_preferred":[
        "\u82cf\u51ef\u7279"
    ],
    "wof:name":"Suket",
    "wof:placetype":"locality"
},
  "geometry": {"coordinates":[112.7127,-7.6363],"type":"Point"}
}