{
  "type": "Feature",
  "properties": {
    "gn:admin1_code":"30.0",
    "gn:asciiname":"Cilampahan",
    "gn:country_code":"ID",
    "gn:dem":27,
    "gn:feature_class":"P",
    "gn:feature_code":"PPL",
    "gn:name":"Cilampahan",
    "gn:population":0,
    "gn:timezone":"Asia/Jakarta",
    "iso:country":"ID",
    "name:ind_x_preferred":[
        "Cilampahan"
    ],
    "wof:name":"Cilampahan",
    "wof:placetype":"locality"
},
  "geometry": {"coordinates":[106.8329,-7.3763],"type":"Point"}
}