{
  "type": "Feature",
  "properties": {
    "gn:admin1_code":"32.0",
    "gn:asciiname":"Talang Saka-kecil",
    "gn:country_code":"ID",
    "gn:dem":57,
    "gn:feature_class":"P",
    "gn:feature_code":"PPL",
    "gn:name":"Talang Saka-kecil",
    "gn:population":0,
    "gn:timezone":"Asia/Jakarta",
    "iso:country":"ID",
    "name:ind_x_preferred":[
        "Talang Saka-kecil"
    ],
    "wof:name":"Talang Saka-kecil",
    "wof:placetype":"locality"
},
  "geometry": {"coordinates":[103.6358,-3.1038],"type":"Point"}
}