{
  "type": "Feature",
  "properties": {
    "gn:admin1_code":"33.0",
    "gn:asciiname":"Cibinong",
    "gn:country_code":"ID",
    "gn:dem":441,
    "gn:feature_class":"P",
    "gn:feature_code":"PPL",
    "gn:name":"Cibinong",
    "gn:population":0,
    "gn:timezone":"Asia/Jakarta",
    "iso:country":"ID",
    "name:ind_x_preferred":[
        "Cibinong"
    ],
    "wof:name":"Cibinong",
    "wof:placetype":"locality"
},
  "geometry": {"coordinates":[105.9619,-6.2691],"type":"Point"}
}