{
  "type": "Feature",
  "properties": {
    "gn:admin1_code":"26",
    "gn:asciiname":"Paribuanjahean",
    "gn:country_code":"ID",
    "gn:dem":1235,
    "gn:feature_class":"P",
    "gn:feature_code":"PPL",
    "gn:name":"Paribuanjahean",
    "gn:population":0,
    "gn:timezone":"Asia/Jakarta",
    "iso:country":"ID",
    "name:ind_x_preferred":[
        "Paribuanjahean"
    ],
    "wof:lang_x_official":[
        "ind"
    ],
    "wof:lang_x_spoken":[
        "ind",
        "eng"
    ],
    "wof:name":"Paribuanjahean",
    "wof:placetype":"locality"
},
  "geometry": {"coordinates":[98.6559,3.0228],"type":"Point"}
}