{
  "type": "Feature",
  "properties": {
    "gn:admin1_code":"18",
    "gn:asciiname":"Wolobalu",
    "gn:country_code":"ID",
    "gn:dem":851,
    "gn:feature_class":"P",
    "gn:feature_code":"PPL",
    "gn:name":"Wolobalu",
    "gn:population":0,
    "gn:timezone":"Asia/Makassar",
    "iso:country":"ID",
    "name:ind_x_preferred":[
        "Wolobalu"
    ],
    "wof:name":"Wolobalu",
    "wof:placetype":"locality"
},
  "geometry": {"coordinates":[121.83069999999999,-8.5837],"type":"Point"}
}