{
  "type": "Feature",
  "properties": {
    "gn:admin1_code":"30",
    "gn:asciiname":"Galunggung",
    "gn:country_code":"ID",
    "gn:dem":693,
    "gn:feature_class":"P",
    "gn:feature_code":"PPL",
    "gn:name":"Galunggung",
    "gn:population":0,
    "gn:timezone":"Asia/Jakarta",
    "iso:country":"ID",
    "name:ara_x_preferred":[
        "\u062c\u0627\u0644\u0648\u0646\u062c\u0648\u0646\u062c"
    ],
    "name:ast_x_preferred":[
        "Galunggung"
    ],
    "name:cat_x_preferred":[
        "Galunggung"
    ],
    "name:ceb_x_preferred":[
        "Gunung Galunggung"
    ],
    "name:ces_x_preferred":[
        "Galunggung"
    ],
    "name:deu_x_preferred":[
        "Galunggung"
    ],
    "name:est_x_preferred":[
        "Galunggung"
    ],
    "name:eus_x_preferred":[
        "Galunggung"
    ],
    "name:fin_x_preferred":[
        "Galunggung"
    ],
    "name:fra_x_preferred":[
        "Galunggung"
    ],
    "name:ind_x_preferred":[
        "Galunggung"
    ],
    "name:ind_x_variant":[
        "Gunung Galunggung"
    ],
    "name:ita_x_preferred":[
        "Galunggung"
    ],
    "name:jav_x_preferred":[
        "Gunung Galunggung"
    ],
    "name:jpn_x_preferred":[
        "\u30ac\u30eb\u30f3\u30b0\u30f3\u5c71"
    ],
    "name:kor_x_preferred":[
        "\uac08\ub8fd\uad81\uc0b0"
    ],
    "name:msa_x_preferred":[
        "Gunung Galunggung"
    ],
    "name:nld_x_preferred":[
        "Galunggung"
    ],
    "name:nor_x_preferred":[
        "Galunggung"
    ],
    "name:pol_x_preferred":[
        "Galunggung"
    ],
    "name:por_x_preferred":[
        "Galunggung"
    ],
    "name:rus_x_preferred":[
        "\u0413\u0430\u043b\u0443\u043d\u0433\u0433\u0443\u043d\u0433"
    ],
    "name:slk_x_preferred":[
        "Galunggung"
    ],
    "name:spa_x_preferred":[
        "Galunggung"
    ],
    "name:sun_x_preferred":[
        "Gunung Galunggung"
    ],
    "name:swe_x_preferred":[
        "Gunung Galunggung"
    ],
    "name:wuu_x_preferred":[
        "\u52a0\u9686\u8d21\u706b\u5c71"
    ],
    "name:zho_x_preferred":[
        "\u52a0\u9686\u8ca2\u706b\u5c71"
    ],
    "wof:lang_x_official":[
        "ind"
    ],
    "wof:lang_x_spoken":[
        "ind",
        "eng"
    ],
    "wof:name":"Galunggung",
    "wof:placetype":"locality"
},
  "geometry": {"coordinates":[107.62555999999999,-6.92583],"type":"Point"}
}