{
  "type": "Feature",
  "properties": {
    "gn:admin1_code":"30",
    "gn:asciiname":"Cicakrawang",
    "gn:country_code":"ID",
    "gn:dem":34,
    "gn:feature_class":"P",
    "gn:feature_code":"PPL",
    "gn:name":"Cicakrawang",
    "gn:population":0,
    "gn:timezone":"Asia/Jakarta",
    "iso:country":"ID",
    "name:ind_x_preferred":[
        "Cicakrawang"
    ],
    "wof:name":"Cicakrawang",
    "wof:placetype":"locality"
},
  "geometry": {"coordinates":[107.40861,-6.50306],"type":"Point"}
}