{
  "type": "Feature",
  "properties": {
    "gn:admin1_code":"18",
    "gn:asciiname":"Haor",
    "gn:country_code":"ID",
    "gn:dem":962,
    "gn:feature_class":"P",
    "gn:feature_code":"PPL",
    "gn:name":"Haor",
    "gn:population":0,
    "gn:timezone":"Asia/Makassar",
    "iso:country":"ID",
    "name:ben_x_preferred":[
        "\u09b9\u09be\u0993\u09b0"
    ],
    "name:bih_x_preferred":[
        "\u0939\u093e\u0909\u0930"
    ],
    "name:hin_x_preferred":[
        "\u0939\u093e\u0909\u0930"
    ],
    "name:ind_x_preferred":[
        "Haor"
    ],
    "wof:lang_x_official":[
        "ind"
    ],
    "wof:lang_x_spoken":[
        "ind",
        "eng"
    ],
    "wof:name":"Haor",
    "wof:placetype":"locality"
},
  "geometry": {"coordinates":[120.4876,-8.5199],"type":"Point"}
}