{
  "type": "Feature",
  "properties": {
    "gn:admin1_code":"7.0",
    "gn:asciiname":"Ngasinan",
    "gn:country_code":"ID",
    "gn:dem":9,
    "gn:feature_class":"P",
    "gn:feature_code":"PPL",
    "gn:name":"Ngasinan",
    "gn:population":0,
    "gn:timezone":"Asia/Jakarta",
    "iso:country":"ID",
    "name:ind_x_preferred":[
        "Ngasinan"
    ],
    "wof:name":"Ngasinan",
    "wof:placetype":"locality"
},
  "geometry": {"coordinates":[111.0919,-6.7625],"type":"Point"}
}