{
  "type": "Feature",
  "properties": {
    "gn:admin1_code":"18",
    "gn:asciiname":"Lancang",
    "gn:country_code":"ID",
    "gn:dem":579,
    "gn:feature_class":"P",
    "gn:feature_code":"PPL",
    "gn:name":"Lancang",
    "gn:population":0,
    "gn:timezone":"Asia/Makassar",
    "iso:country":"ID",
    "name:fra_x_preferred":[
        "Lancang"
    ],
    "name:ind_x_preferred":[
        "Lancang"
    ],
    "name:nld_x_preferred":[
        "Lancang"
    ],
    "name:nor_x_preferred":[
        "Lancang"
    ],
    "wof:name":"Lancang",
    "wof:placetype":"locality"
},
  "geometry": {"coordinates":[120.37390000000001,-8.7484],"type":"Point"}
}