{
  "type": "Feature",
  "properties": {
    "gn:admin1_code":"30.0",
    "gn:asciiname":"Pasirpeundeuy",
    "gn:country_code":"ID",
    "gn:dem":124,
    "gn:feature_class":"P",
    "gn:feature_code":"PPL",
    "gn:name":"Pasirpeundeuy",
    "gn:population":0,
    "gn:timezone":"Asia/Jakarta",
    "iso:country":"ID",
    "name:ind_x_preferred":[
        "Pasirpeundeuy"
    ],
    "wof:name":"Pasirpeundeuy",
    "wof:placetype":"locality"
},
  "geometry": {"coordinates":[108.76739999999999,-7.6768],"type":"Point"}
}