{
  "type": "Feature",
  "properties": {
    "gn:admin1_code":"18.0",
    "gn:asciiname":"Ndalir",
    "gn:country_code":"ID",
    "gn:dem":613,
    "gn:feature_class":"P",
    "gn:feature_code":"PPL",
    "gn:name":"Ndalir",
    "gn:population":0,
    "gn:timezone":"Asia/Makassar",
    "iso:country":"ID",
    "name:ind_x_preferred":[
        "Ndalir"
    ],
    "wof:name":"Ndalir",
    "wof:placetype":"locality"
},
  "geometry": {"coordinates":[120.69,-8.7333],"type":"Point"}
}