{
  "type": "Feature",
  "properties": {
    "gn:admin1_code":"0.0",
    "gn:asciiname":"Bendoyo",
    "gn:cc2":"ID",
    "gn:country_code":"ID",
    "gn:dem":229,
    "gn:feature_class":"P",
    "gn:feature_code":"PPL",
    "gn:name":"Bendoyo",
    "gn:population":0,
    "gn:timezone":"Asia/Makassar",
    "iso:country":"ID",
    "name:und_x_variant":[
        "Bendojo",
        "Bendoyo"
    ],
    "wof:lang_x_official":[
        "ind"
    ],
    "wof:lang_x_spoken":[
        "ind",
        "eng"
    ],
    "wof:name":"Bendoyo",
    "wof:placetype":"locality"
},
  "geometry": {"coordinates":[120.15000000000001,0.23333],"type":"Point"}
}