{
  "type": "Feature",
  "properties": {
    "gn:admin1_code":"07",
    "gn:asciiname":"Kadirejo",
    "gn:country_code":"ID",
    "gn:dem":875,
    "gn:feature_class":"P",
    "gn:feature_code":"PPL",
    "gn:name":"Kadirejo",
    "gn:population":0,
    "gn:timezone":"Asia/Jakarta",
    "iso:country":"ID",
    "wof:name":"Kadirejo",
    "wof:placetype":"locality"
},
  "geometry": {"coordinates":[110.50861,-7.57167],"type":"Point"}
}