{
  "type": "Feature",
  "properties": {
    "gn:admin1_code":"21",
    "gn:asciiname":"Tambun",
    "gn:country_code":"ID",
    "gn:dem":11,
    "gn:feature_class":"P",
    "gn:feature_code":"PPL",
    "gn:name":"Tambun",
    "gn:population":0,
    "gn:timezone":"Asia/Makassar",
    "iso:country":"ID",
    "name:epo_x_preferred":[
        "Tambun"
    ],
    "name:fra_x_preferred":[
        "Tambun"
    ],
    "name:ind_x_preferred":[
        "Tambun"
    ],
    "name:msa_x_preferred":[
        "Tambun"
    ],
    "name:nld_x_preferred":[
        "Tambun"
    ],
    "name:tam_x_preferred":[
        "\u0ba4\u0bae\u0bcd\u0baa\u0bc2\u0ba9\u0bcd"
    ],
    "wof:name":"Tambun",
    "wof:placetype":"locality"
},
  "geometry": {"coordinates":[120.7835,1.0057],"type":"Point"}
}