{
  "type": "Feature",
  "properties": {
    "gn:admin1_code":"38",
    "gn:asciiname":"Barubaru",
    "gn:country_code":"ID",
    "gn:dem":2,
    "gn:feature_class":"P",
    "gn:feature_code":"PPL",
    "gn:name":"Barubaru",
    "gn:population":0,
    "gn:timezone":"Asia/Makassar",
    "iso:country":"ID",
    "name:ind_x_preferred":[
        "Barubaru"
    ],
    "wof:name":"Barubaru",
    "wof:placetype":"locality"
},
  "geometry": {"coordinates":[119.5605,-4.9925],"type":"Point"}
}