{
  "type": "Feature",
  "properties": {
    "gn:admin1_code":"04",
    "gn:asciiname":"Salembaoluntas",
    "gn:country_code":"ID",
    "gn:dem":13,
    "gn:feature_class":"P",
    "gn:feature_code":"PPL",
    "gn:name":"Salembaoluntas",
    "gn:population":0,
    "gn:timezone":"Asia/Jakarta",
    "iso:country":"ID",
    "wof:name":"Salembaoluntas",
    "wof:placetype":"locality"
},
  "geometry": {"coordinates":[106.86139,-6.19583],"type":"Point"}
}