{
  "type": "Feature",
  "properties": {
    "gn:admin1_code":"21.0",
    "gn:asciiname":"Lero",
    "gn:country_code":"ID",
    "gn:dem":23,
    "gn:feature_class":"P",
    "gn:feature_code":"PPL",
    "gn:name":"Lero",
    "gn:population":0,
    "gn:timezone":"Asia/Makassar",
    "iso:country":"ID",
    "name:glg_x_preferred":[
        "Lero"
    ],
    "name:heb_x_preferred":[
        "\u05dc\u05e8\u05d5 \u05d5\u05dc\u05e8\u05d9\u05e0\u05d4"
    ],
    "name:ind_x_preferred":[
        "Lero"
    ],
    "name:por_x_preferred":[
        "Lero"
    ],
    "name:und_x_variant":[
        "Lera"
    ],
    "wof:lang_x_official":[
        "ind"
    ],
    "wof:lang_x_spoken":[
        "ind",
        "eng"
    ],
    "wof:name":"Lero",
    "wof:placetype":"locality"
},
  "geometry": {"coordinates":[119.81229999999999,-0.633],"type":"Point"}
}