{
  "type": "Feature",
  "properties": {
    "gn:admin1_code":"8.0",
    "gn:asciiname":"Pesantren",
    "gn:country_code":"ID",
    "gn:dem":9,
    "gn:feature_class":"P",
    "gn:feature_code":"PPLA4",
    "gn:name":"Pesantren",
    "gn:population":0,
    "gn:timezone":"Asia/Jakarta",
    "iso:country":"ID",
    "name:ind_x_preferred":[
        "Pesantren"
    ],
    "wof:name":"Pesantren",
    "wof:placetype":"locality"
},
  "geometry": {"coordinates":[111.8443,-6.8148],"type":"Point"}
}