{
  "type": "Feature",
  "properties": {
    "gn:admin1_code":"26",
    "gn:asciiname":"Rajaberneh",
    "gn:country_code":"ID",
    "gn:dem":464,
    "gn:feature_class":"P",
    "gn:feature_code":"PPL",
    "gn:name":"Rajaberneh",
    "gn:population":0,
    "gn:timezone":"Asia/Jakarta",
    "iso:country":"ID",
    "name:ind_x_preferred":[
        "Rajaberneh"
    ],
    "wof:name":"Rajaberneh",
    "wof:placetype":"locality"
},
  "geometry": {"coordinates":[98.5633,3.3218],"type":"Point"}
}