{
  "type": "Feature",
  "properties": {
    "gn:admin1_code":"38",
    "gn:asciiname":"Bongorena",
    "gn:country_code":"ID",
    "gn:dem":154,
    "gn:feature_class":"P",
    "gn:feature_code":"PPL",
    "gn:name":"Bongorena",
    "gn:population":0,
    "gn:timezone":"Asia/Makassar",
    "iso:country":"ID",
    "name:ind_x_preferred":[
        "Bongorena"
    ],
    "wof:name":"Bongorena",
    "wof:placetype":"locality"
},
  "geometry": {"coordinates":[120.2561,-5.2511],"type":"Point"}
}