{
  "type": "Feature",
  "properties": {
    "gn:admin1_code":"30",
    "gn:asciiname":"Karangmakam",
    "gn:country_code":"ID",
    "gn:dem":179,
    "gn:feature_class":"P",
    "gn:feature_code":"PPL",
    "gn:name":"Karangmakam",
    "gn:population":0,
    "gn:timezone":"Asia/Jakarta",
    "iso:country":"ID",
    "name:ind_x_preferred":[
        "Karangmakam"
    ],
    "wof:name":"Karangmakam",
    "wof:placetype":"locality"
},
  "geometry": {"coordinates":[112.9538,-7.7769],"type":"Point"}
}