{
  "type": "Feature",
  "properties": {
    "gn:admin1_code":"7",
    "gn:asciiname":"Gondangbaru",
    "gn:country_code":"ID",
    "gn:dem":90,
    "gn:feature_class":"P",
    "gn:feature_code":"PPL",
    "gn:name":"Gondangbaru",
    "gn:population":0,
    "gn:timezone":"Asia/Jakarta",
    "iso:country":"ID",
    "name:ind_x_preferred":[
        "Gondangbaru"
    ],
    "wof:name":"Gondangbaru",
    "wof:placetype":"locality"
},
  "geometry": {"coordinates":[111.11306,-7.40583],"type":"Point"}
}