{
  "type": "Feature",
  "properties": {
    "gn:admin1_code":"7.0",
    "gn:asciiname":"Kapulogo Kulon",
    "gn:country_code":"ID",
    "gn:dem":612,
    "gn:feature_class":"P",
    "gn:feature_code":"PPL",
    "gn:name":"Kapulogo Kulon",
    "gn:population":0,
    "gn:timezone":"Asia/Jakarta",
    "iso:country":"ID",
    "wof:name":"Kapulogo Kulon",
    "wof:placetype":"locality"
},
  "geometry": {"coordinates":[110.01000000000001,-7.49944],"type":"Point"}
}