{
  "type": "Feature",
  "properties": {
    "gn:gn_country":"ID",
    "gn:gn_fcode":"ADMD",
    "gn:gn_pop":0,
    "iso:country":"ID",
    "name:unk_x_variant":[
        "Daerah Tingkat II Pasaman"
    ],
    "qs_pg:aaroncc":"ID",
    "qs_pg:gn_country":"ID",
    "qs_pg:gn_fcode":"ADMD",
    "qs_pg:gn_pop":0,
    "qs_pg:name":"Kabupaten Pasaman",
    "qs_pg:photos_9r":0,
    "qs_pg:photos_sr":0,
    "qs_pg:pop_sr":0,
    "qs_pg:qs_pg_placetype":"localadmin",
    "wof:name":"Kabupaten Pasaman",
    "wof:placetype":"localadmin"
},
  "geometry": {"coordinates":[99.75,0.33333],"type":"Point"}
}