{
  "type": "Feature",
  "properties": {
    "gn:admin1_code":"18.0",
    "gn:asciiname":"Komna",
    "gn:country_code":"ID",
    "gn:dem":465,
    "gn:feature_class":"P",
    "gn:feature_code":"PPL",
    "gn:name":"Komna",
    "gn:population":0,
    "gn:timezone":"Asia/Makassar",
    "iso:country":"ID",
    "name:ind_x_preferred":[
        "Komna"
    ],
    "name:pol_x_preferred":[
        "Komna"
    ],
    "wof:name":"Komna",
    "wof:placetype":"locality"
},
  "geometry": {"coordinates":[124.5304,-9.9883],"type":"Point"}
}