{
  "type": "Feature",
  "properties": {
    "gn:admin1_code":"18",
    "gn:asciiname":"Puunga",
    "gn:country_code":"ID",
    "gn:dem":389,
    "gn:feature_class":"P",
    "gn:feature_code":"PPL",
    "gn:name":"Puunga",
    "gn:population":0,
    "gn:timezone":"Asia/Makassar",
    "iso:country":"ID",
    "name:ind_x_preferred":[
        "Puunga"
    ],
    "wof:name":"Puunga",
    "wof:placetype":"locality"
},
  "geometry": {"coordinates":[119.1519,-9.4865],"type":"Point"}
}