{
  "type": "Feature",
  "properties": {
    "gn:admin1_code":"7",
    "gn:asciiname":"Jiwo",
    "gn:country_code":"ID",
    "gn:dem":434,
    "gn:feature_class":"P",
    "gn:feature_code":"PPL",
    "gn:name":"Jiwo",
    "gn:population":0,
    "gn:timezone":"Asia/Jakarta",
    "iso:country":"ID",
    "name:ind_x_preferred":[
        "Jiwo"
    ],
    "wof:name":"Jiwo",
    "wof:placetype":"locality"
},
  "geometry": {"coordinates":[110.9397,-6.5743],"type":"Point"}
}