{
  "type": "Feature",
  "properties": {
    "gn:admin1_code":"7.0",
    "gn:asciiname":"Bengkah",
    "gn:country_code":"ID",
    "gn:dem":468,
    "gn:feature_class":"P",
    "gn:feature_code":"PPL",
    "gn:name":"Bengkah",
    "gn:population":0,
    "gn:timezone":"Asia/Jakarta",
    "iso:country":"ID",
    "wof:name":"Bengkah",
    "wof:placetype":"locality"
},
  "geometry": {"coordinates":[110.54528000000001,-7.61861],"type":"Point"}
}