{
  "type": "Feature",
  "properties": {
    "gn:admin1_code":"30.0",
    "gn:asciiname":"Lemahneundeut Kaler",
    "gn:country_code":"ID",
    "gn:dem":1365,
    "gn:feature_class":"P",
    "gn:feature_code":"PPL",
    "gn:name":"Lemahneundeut Kaler",
    "gn:population":0,
    "gn:timezone":"Asia/Jakarta",
    "iso:country":"ID",
    "name:ind_x_preferred":[
        "Lemahneundeut Kaler"
    ],
    "wof:name":"Lemahneundeut Kaler",
    "wof:placetype":"locality"
},
  "geometry": {"coordinates":[107.7771,-7.3116],"type":"Point"}
}