{
  "type": "Feature",
  "properties": {
    "gn:admin1_code":"30",
    "gn:asciiname":"Balonggubug Wetan",
    "gn:country_code":"ID",
    "gn:dem":6,
    "gn:feature_class":"P",
    "gn:feature_code":"PPL",
    "gn:name":"Balonggubug Wetan",
    "gn:population":0,
    "gn:timezone":"Asia/Jakarta",
    "iso:country":"ID",
    "name:ind_x_preferred":[
        "Balonggubug Wetan"
    ],
    "name:und_x_variant":[
        "Balonggubug"
    ],
    "wof:lang_x_official":[
        "ind"
    ],
    "wof:lang_x_spoken":[
        "ind",
        "eng"
    ],
    "wof:name":"Balonggubug Wetan",
    "wof:placetype":"locality"
},
  "geometry": {"coordinates":[107.15389,-6.16139],"type":"Point"}
}