{
  "type": "Feature",
  "properties": {
    "gn:admin1_code":"17",
    "gn:asciiname":"Tababan Timur",
    "gn:country_code":"ID",
    "gn:dem":199,
    "gn:feature_class":"P",
    "gn:feature_code":"PPL",
    "gn:name":"Tababan Timur",
    "gn:population":0,
    "gn:timezone":"Asia/Makassar",
    "iso:country":"ID",
    "name:ind_x_preferred":[
        "Tababan Timur"
    ],
    "wof:name":"Tababan Timur",
    "wof:placetype":"locality"
},
  "geometry": {"coordinates":[116.5239,-8.6208],"type":"Point"}
}