{
  "type": "Feature",
  "properties": {
    "gn:admin1_code":"15.0",
    "gn:asciiname":"Banjarejo",
    "gn:country_code":"ID",
    "gn:dem":122,
    "gn:feature_class":"P",
    "gn:feature_code":"PPL",
    "gn:name":"Banjarejo",
    "gn:population":0,
    "gn:timezone":"Asia/Jakarta",
    "iso:country":"ID",
    "name:ind_x_preferred":[
        "Banjarejo"
    ],
    "wof:name":"Banjarejo",
    "wof:placetype":"locality"
},
  "geometry": {"coordinates":[105.05385,-5.33248],"type":"Point"}
}