{
  "type": "Feature",
  "properties": {
    "gn:country":"ID",
    "gn:fcode":"ADM4",
    "gn:pop":0,
    "iso:country":"ID",
    "name:ind_x_preferred":[
        "Desa Kacongan"
    ],
    "name:unk_x_variant":[
        "Kacongan"
    ],
    "qs:name":"Desa Kacongan",
    "qs:photos_9r":0,
    "qs:photos_sr":0,
    "qs:pop_sr":"0",
    "wof:name":"Desa Kacongan",
    "wof:placetype":"localadmin",
    "wof:population":0
},
  "geometry": {"coordinates":[113.8826,-7.0138],"type":"Point"}
}