{
  "type": "Feature",
  "properties": {
    "gn:admin1_code":"30.0",
    "gn:asciiname":"Nyangkowek",
    "gn:country_code":"ID",
    "gn:dem":475,
    "gn:feature_class":"P",
    "gn:feature_code":"PPL",
    "gn:name":"Nyangkowek",
    "gn:population":0,
    "gn:timezone":"Asia/Jakarta",
    "iso:country":"ID",
    "name:ind_x_preferred":[
        "Nyangkowek"
    ],
    "name:und_x_variant":[
        "Njangkowek"
    ],
    "wof:name":"Nyangkowek",
    "wof:placetype":"locality"
},
  "geometry": {"coordinates":[106.77722,-6.79083],"type":"Point"}
}