{
  "type": "Feature",
  "properties": {
    "gn:admin1_code":"8.0",
    "gn:asciiname":"Karangdalam",
    "gn:country_code":"ID",
    "gn:dem":14,
    "gn:feature_class":"P",
    "gn:feature_code":"PPLA4",
    "gn:name":"Karangdalam",
    "gn:population":0,
    "gn:timezone":"Asia/Jakarta",
    "iso:country":"ID",
    "name:ind_x_preferred":[
        "Karangdalam"
    ],
    "wof:name":"Karangdalam",
    "wof:placetype":"locality"
},
  "geometry": {"coordinates":[113.51245,-7.18877],"type":"Point"}
}