{
  "type": "Feature",
  "properties": {
    "gn:admin1_code":"7",
    "gn:asciiname":"Nglahar",
    "gn:country_code":"ID",
    "gn:dem":64,
    "gn:feature_class":"P",
    "gn:feature_code":"PPL",
    "gn:name":"Nglahar",
    "gn:population":0,
    "gn:timezone":"Asia/Jakarta",
    "iso:country":"ID",
    "name:ind_x_preferred":[
        "Nglahar"
    ],
    "wof:name":"Nglahar",
    "wof:placetype":"locality"
},
  "geometry": {"coordinates":[111.2748,-7.0771],"type":"Point"}
}