{
  "type": "Feature",
  "properties": {
    "gn:admin1_code":"18.0",
    "gn:asciiname":"Komerda Empat",
    "gn:country_code":"ID",
    "gn:dem":406,
    "gn:feature_class":"P",
    "gn:feature_code":"PPL",
    "gn:name":"Komerda Empat",
    "gn:population":0,
    "gn:timezone":"Asia/Makassar",
    "iso:country":"ID",
    "name:ind_x_preferred":[
        "Komerda Empat"
    ],
    "name:und_x_variant":[
        "Komerda 4"
    ],
    "wof:lang_x_official":[
        "ind"
    ],
    "wof:lang_x_spoken":[
        "ind",
        "eng"
    ],
    "wof:name":"Komerda Empat",
    "wof:placetype":"locality"
},
  "geometry": {"coordinates":[119.4061,-9.6283],"type":"Point"}
}