{
  "type": "Feature",
  "properties": {
    "gn:country":"ID",
    "gn:fcode":"ADM4",
    "gn:pop":0,
    "iso:country":"ID",
    "name:ind_x_preferred":[
        "Desa Sindangkerta"
    ],
    "name:unk_x_variant":[
        "Sindangkerta"
    ],
    "qs:name":"Desa Sindangkerta",
    "qs:photos_9r":0,
    "qs:photos_sr":0,
    "qs:pop_sr":"0",
    "wd:wordcount":1319,
    "wof:name":"Desa Sindangkerta",
    "wof:placetype":"localadmin",
    "wof:population":0
},
  "geometry": {"coordinates":[108.28888999999999,-6.86944],"type":"Point"}
}