{
  "type": "Feature",
  "properties": {
    "gn:admin1_code":"30",
    "gn:asciiname":"Banyuresmi",
    "gn:country_code":"ID",
    "gn:dem":206,
    "gn:feature_class":"P",
    "gn:feature_code":"PPL",
    "gn:name":"Banyuresmi",
    "gn:population":0,
    "gn:timezone":"Asia/Jakarta",
    "iso:country":"ID",
    "name:ind_x_preferred":[
        "Banyuresmi"
    ],
    "wof:name":"Banyuresmi",
    "wof:placetype":"locality"
},
  "geometry": {"coordinates":[106.63778000000001,-6.58],"type":"Point"}
}