{
  "type": "Feature",
  "properties": {
    "gn:admin1_code":"8",
    "gn:asciiname":"Misih",
    "gn:country_code":"ID",
    "gn:dem":530,
    "gn:feature_class":"P",
    "gn:feature_code":"PPL",
    "gn:name":"Misih",
    "gn:population":0,
    "gn:timezone":"Asia/Jakarta",
    "iso:country":"ID",
    "name:ind_x_preferred":[
        "Misih"
    ],
    "wof:name":"Misih",
    "wof:placetype":"locality"
},
  "geometry": {"coordinates":[111.29528000000001,-7.67889],"type":"Point"}
}