{
  "type": "Feature",
  "properties": {
    "gn:admin1_code":"18.0",
    "gn:asciiname":"Nifukiu",
    "gn:country_code":"ID",
    "gn:dem":243,
    "gn:feature_class":"P",
    "gn:feature_code":"PPL",
    "gn:name":"Nifukiu",
    "gn:population":0,
    "gn:timezone":"Asia/Makassar",
    "iso:country":"ID",
    "name:ind_x_preferred":[
        "Nifukiu"
    ],
    "wof:name":"Nifukiu",
    "wof:placetype":"locality"
},
  "geometry": {"coordinates":[124.2903,-10.0475],"type":"Point"}
}