{
  "type": "Feature",
  "properties": {
    "gn:admin1_code":"1.0",
    "gn:asciiname":"Dayahmeunara",
    "gn:country_code":"ID",
    "gn:dem":20,
    "gn:feature_class":"P",
    "gn:feature_code":"PPL",
    "gn:name":"Dayahmeunara",
    "gn:population":0,
    "gn:timezone":"Asia/Jakarta",
    "iso:country":"ID",
    "name:ind_x_preferred":[
        "Dayahmeunara"
    ],
    "wof:name":"Dayahmeunara",
    "wof:placetype":"locality"
},
  "geometry": {"coordinates":[96.62779999999999,5.1777],"type":"Point"}
}