{
  "type": "Feature",
  "properties": {
    "gn:admin1_code":"26.0",
    "gn:asciiname":"Siatas Dua",
    "gn:country_code":"ID",
    "gn:dem":1103,
    "gn:feature_class":"P",
    "gn:feature_code":"PPL",
    "gn:name":"Siatas Dua",
    "gn:population":0,
    "gn:timezone":"Asia/Jakarta",
    "iso:country":"ID",
    "name:ind_x_preferred":[
        "Siatas Dua"
    ],
    "name:und_x_variant":[
        "Siatas 2"
    ],
    "wof:name":"Siatas Dua",
    "wof:placetype":"locality"
},
  "geometry": {"coordinates":[98.61669999999999,2.1577],"type":"Point"}
}