{
  "type": "Feature",
  "properties": {
    "gn:admin1_code":"7.0",
    "gn:asciiname":"Pakis",
    "gn:country_code":"ID",
    "gn:dem":358,
    "gn:feature_class":"P",
    "gn:feature_code":"PPLA4",
    "gn:name":"Pakis",
    "gn:population":0,
    "gn:timezone":"Asia/Jakarta",
    "iso:country":"ID",
    "wof:name":"Pakis",
    "wof:placetype":"locality"
},
  "geometry": {"coordinates":[111.50933000000001,-6.82439],"type":"Point"}
}