{
  "type": "Feature",
  "properties": {
    "gn:admin1_code":"7",
    "gn:asciiname":"Dapurno",
    "gn:country_code":"ID",
    "gn:dem":535,
    "gn:feature_class":"P",
    "gn:feature_code":"PPL",
    "gn:name":"Dapurno",
    "gn:population":0,
    "gn:timezone":"Asia/Jakarta",
    "iso:country":"ID",
    "name:ind_x_preferred":[
        "Dapurno"
    ],
    "wof:name":"Dapurno",
    "wof:placetype":"locality"
},
  "geometry": {"coordinates":[109.89055999999999,-7.56333],"type":"Point"}
}