{
  "type": "Feature",
  "properties": {
    "gn:admin1_code":"10.0",
    "gn:asciiname":"Tanjung",
    "gn:cc2":"ID",
    "gn:country_code":"ID",
    "gn:dem":228,
    "gn:feature_class":"P",
    "gn:feature_code":"PPL",
    "gn:name":"Tanjung",
    "gn:population":0,
    "gn:timezone":"Asia/Jakarta",
    "iso:country":"ID",
    "name:und_x_variant":[
        "Tandjung",
        "Tanjung"
    ],
    "wof:name":"Tanjung",
    "wof:placetype":"locality"
},
  "geometry": {"coordinates":[110.47417,-7.92167],"type":"Point"}
}