{
  "type": "Feature",
  "properties": {
    "gn:admin1_code":"38.0",
    "gn:asciiname":"Bajumata",
    "gn:country_code":"ID",
    "gn:dem":190,
    "gn:feature_class":"P",
    "gn:feature_code":"PPL",
    "gn:name":"Bajumata",
    "gn:population":0,
    "gn:timezone":"Asia/Makassar",
    "iso:country":"ID",
    "name:ind_x_preferred":[
        "Bajumata"
    ],
    "wof:name":"Bajumata",
    "wof:placetype":"locality"
},
  "geometry": {"coordinates":[119.7473,-3.4805],"type":"Point"}
}