{
  "type": "Feature",
  "properties": {
    "gn:admin1_code":"2.0",
    "gn:asciiname":"Tenggang",
    "gn:country_code":"ID",
    "gn:dem":114,
    "gn:feature_class":"P",
    "gn:feature_code":"PPL",
    "gn:name":"Tenggang",
    "gn:population":0,
    "gn:timezone":"Asia/Makassar",
    "iso:country":"ID",
    "name:ind_x_preferred":[
        "Tenggang"
    ],
    "wof:name":"Tenggang",
    "wof:placetype":"locality"
},
  "geometry": {"coordinates":[115.65260000000001,-8.4428],"type":"Point"}
}