{
  "type": "Feature",
  "properties": {
    "gn:admin1_code":"30.0",
    "gn:asciiname":"Kendal",
    "gn:country_code":"ID",
    "gn:dem":435,
    "gn:feature_class":"P",
    "gn:feature_code":"PPL",
    "gn:name":"Kendal",
    "gn:population":0,
    "gn:timezone":"Asia/Jakarta",
    "iso:country":"ID",
    "name:ind_x_preferred":[
        "Kendal"
    ],
    "wof:name":"Kendal",
    "wof:placetype":"locality"
},
  "geometry": {"coordinates":[108.1991,-7.2637],"type":"Point"}
}