{
  "type": "Feature",
  "properties": {
    "gn:admin1_code":"30",
    "gn:asciiname":"Rajasuka",
    "gn:country_code":"ID",
    "gn:dem":627,
    "gn:feature_class":"P",
    "gn:feature_code":"PPL",
    "gn:name":"Rajasuka",
    "gn:population":0,
    "gn:timezone":"Asia/Jakarta",
    "iso:country":"ID",
    "name:ind_x_preferred":[
        "Rajasuka"
    ],
    "wof:name":"Rajasuka",
    "wof:placetype":"locality"
},
  "geometry": {"coordinates":[107.70611,-6.73472],"type":"Point"}
}