{
  "type": "Feature",
  "properties": {
    "gn:admin1_code":"17",
    "gn:asciiname":"Lekonggunung",
    "gn:country_code":"ID",
    "gn:dem":434,
    "gn:feature_class":"P",
    "gn:feature_code":"PPL",
    "gn:name":"Lekonggunung",
    "gn:population":0,
    "gn:timezone":"Asia/Makassar",
    "iso:country":"ID",
    "name:ind_x_preferred":[
        "Lekonggunung"
    ],
    "wof:name":"Lekonggunung",
    "wof:placetype":"locality"
},
  "geometry": {"coordinates":[116.3916,-8.5963],"type":"Point"}
}