{
  "type": "Feature",
  "properties": {
    "gn:admin1_code":"30",
    "gn:asciiname":"Parakanjengkol",
    "gn:country_code":"ID",
    "gn:dem":330,
    "gn:feature_class":"P",
    "gn:feature_code":"PPL",
    "gn:name":"Parakanjengkol",
    "gn:population":0,
    "gn:timezone":"Asia/Jakarta",
    "iso:country":"ID",
    "name:ind_x_preferred":[
        "Parakanjengkol"
    ],
    "wof:name":"Parakanjengkol",
    "wof:placetype":"locality"
},
  "geometry": {"coordinates":[106.62,-6.89361],"type":"Point"}
}