{
  "type": "Feature",
  "properties": {
    "gn:admin1_code":"30.0",
    "gn:asciiname":"Jolokreungas",
    "gn:country_code":"ID",
    "gn:dem":696,
    "gn:feature_class":"P",
    "gn:feature_code":"PPL",
    "gn:name":"Jolokreungas",
    "gn:population":0,
    "gn:timezone":"Asia/Jakarta",
    "iso:country":"ID",
    "name:ind_x_preferred":[
        "Jolokreungas"
    ],
    "name:und_x_variant":[
        "Djolokreungas"
    ],
    "wof:name":"Jolokreungas",
    "wof:placetype":"locality"
},
  "geometry": {"coordinates":[107.93770000000001,-7.1683],"type":"Point"}
}