{
  "type": "Feature",
  "properties": {
    "gn:admin1_code":"7.0",
    "gn:asciiname":"Petuguran",
    "gn:country_code":"ID",
    "gn:dem":355,
    "gn:feature_class":"P",
    "gn:feature_code":"PPL",
    "gn:name":"Petuguran",
    "gn:population":0,
    "gn:timezone":"Asia/Jakarta",
    "iso:country":"ID",
    "name:ind_x_preferred":[
        "Petuguran"
    ],
    "name:und_x_variant":[
        "Patuguran 1",
        "Patoegoeran 1",
        "Patuguran"
    ],
    "wof:lang_x_official":[
        "ind"
    ],
    "wof:lang_x_spoken":[
        "ind",
        "eng"
    ],
    "wof:name":"Petuguran",
    "wof:placetype":"locality"
},
  "geometry": {"coordinates":[109.06167000000001,-7.32778],"type":"Point"}
}