{
  "type": "Feature",
  "properties": {
    "gn:admin1_code":"15.0",
    "gn:asciiname":"Olokradang",
    "gn:country_code":"ID",
    "gn:dem":92,
    "gn:feature_class":"P",
    "gn:feature_code":"PPL",
    "gn:name":"Olokradang",
    "gn:population":0,
    "gn:timezone":"Asia/Jakarta",
    "iso:country":"ID",
    "name:ind_x_preferred":[
        "Olokradang"
    ],
    "wof:name":"Olokradang",
    "wof:placetype":"locality"
},
  "geometry": {"coordinates":[104.63890000000001,-5.8352],"type":"Point"}
}