{
  "type": "Feature",
  "properties": {
    "gn:admin1_code":"38.0",
    "gn:asciiname":"Galung",
    "gn:country_code":"ID",
    "gn:dem":710,
    "gn:feature_class":"P",
    "gn:feature_code":"PPL",
    "gn:name":"Galung",
    "gn:population":0,
    "gn:timezone":"Asia/Makassar",
    "iso:country":"ID",
    "name:ind_x_preferred":[
        "Galung"
    ],
    "wof:name":"Galung",
    "wof:placetype":"locality"
},
  "geometry": {"coordinates":[120.11709999999999,-3.6559],"type":"Point"}
}