{
  "type": "Feature",
  "properties": {
    "gn:admin1_code":"7.0",
    "gn:asciiname":"Geneng",
    "gn:country_code":"ID",
    "gn:dem":17,
    "gn:feature_class":"P",
    "gn:feature_code":"PPL",
    "gn:name":"Geneng",
    "gn:population":0,
    "gn:timezone":"Asia/Jakarta",
    "iso:country":"ID",
    "name:ind_x_preferred":[
        "Geneng"
    ],
    "wof:name":"Geneng",
    "wof:placetype":"locality"
},
  "geometry": {"coordinates":[111.2409,-6.7305],"type":"Point"}
}