{
  "type": "Feature",
  "properties": {
    "gn:admin1_code":"30",
    "gn:asciiname":"Malingping",
    "gn:country_code":"ID",
    "gn:dem":573,
    "gn:feature_class":"P",
    "gn:feature_code":"PPL",
    "gn:name":"Malingping",
    "gn:population":0,
    "gn:timezone":"Asia/Jakarta",
    "iso:country":"ID",
    "name:ind_x_preferred":[
        "Malingping"
    ],
    "wof:name":"Malingping",
    "wof:placetype":"locality"
},
  "geometry": {"coordinates":[107.69611,-6.7025],"type":"Point"}
}