{
  "type": "Feature",
  "properties": {
    "gn:admin1_code":"33.0",
    "gn:asciiname":"Ciambon",
    "gn:country_code":"ID",
    "gn:dem":228,
    "gn:feature_class":"P",
    "gn:feature_code":"PPL",
    "gn:name":"Ciambon",
    "gn:population":0,
    "gn:timezone":"Asia/Jakarta",
    "iso:country":"ID",
    "name:ind_x_preferred":[
        "Ciambon"
    ],
    "wof:name":"Ciambon",
    "wof:placetype":"locality"
},
  "geometry": {"coordinates":[106.0249,-6.3509],"type":"Point"}
}