{
  "type": "Feature",
  "properties": {
    "gn:admin1_code":"32.0",
    "gn:asciiname":"Bayat",
    "gn:country_code":"ID",
    "gn:dem":18,
    "gn:feature_class":"P",
    "gn:feature_code":"PPL",
    "gn:name":"Bayat",
    "gn:population":0,
    "gn:timezone":"Asia/Jakarta",
    "iso:country":"ID",
    "name:und_x_variant":[
        "Bajat",
        "Bayat"
    ],
    "wof:name":"Bayat",
    "wof:placetype":"locality"
},
  "geometry": {"coordinates":[103.6238,-2.1219],"type":"Point"}
}