{
  "type": "Feature",
  "properties": {
    "gn:admin1_code":"32.0",
    "gn:asciiname":"Bayat",
    "gn:country_code":"ID",
    "gn:dem":18,
    "gn:feature_class":"P",
    "gn:feature_code":"PPL",
    "gn:name":"Bayat",
    "gn:population":0,
    "gn:timezone":"Asia/Jakarta",
    "iso:country":"ID",
    "name:ara_x_preferred":[
        "\u0628\u064a\u0627\u062a"
    ],
    "name:aze_x_preferred":[
        "Bayat"
    ],
    "name:deu_x_preferred":[
        "Bayat"
    ],
    "name:eus_x_preferred":[
        "Bayat"
    ],
    "name:fas_x_preferred":[
        "\u0628\u06cc\u0627\u062a"
    ],
    "name:fra_x_preferred":[
        "Bayat"
    ],
    "name:ita_x_preferred":[
        "Bayat"
    ],
    "name:nld_x_preferred":[
        "Bayat"
    ],
    "name:rus_x_preferred":[
        "\u0411\u0430\u044f\u0442\u044b"
    ],
    "name:tur_x_preferred":[
        "Bayat"
    ],
    "name:und_x_variant":[
        "Bajat",
        "Bayat"
    ],
    "name:vie_x_preferred":[
        "Bayat"
    ],
    "wof:name":"Bayat",
    "wof:placetype":"locality"
},
  "geometry": {"coordinates":[103.6238,-2.1219],"type":"Point"}
}