{
  "type": "Feature",
  "properties": {
    "gn:admin1_code":"31.0",
    "gn:asciiname":"Sendangan",
    "gn:country_code":"ID",
    "gn:dem":743,
    "gn:feature_class":"P",
    "gn:feature_code":"PPL",
    "gn:name":"Sendangan",
    "gn:population":0,
    "gn:timezone":"Asia/Makassar",
    "iso:country":"ID",
    "name:ind_x_preferred":[
        "Sendangan"
    ],
    "wof:lang_x_official":[
        "ind"
    ],
    "wof:lang_x_spoken":[
        "ind",
        "eng"
    ],
    "wof:name":"Sendangan",
    "wof:placetype":"locality"
},
  "geometry": {"coordinates":[124.78830000000001,1.1986],"type":"Point"}
}