{
  "type": "Feature",
  "properties": {
    "gn:admin1_code":"18.0",
    "gn:asciiname":"Pota",
    "gn:country_code":"ID",
    "gn:dem":10,
    "gn:feature_class":"P",
    "gn:feature_code":"PPLA3",
    "gn:name":"Pota",
    "gn:population":0,
    "gn:timezone":"Asia/Makassar",
    "iso:country":"ID",
    "name:und_x_variant":[
        "Potah",
        "Pota"
    ],
    "wof:name":"Pota",
    "wof:placetype":"locality"
},
  "geometry": {"coordinates":[120.7607,-8.3414],"type":"Point"}
}