{
  "type": "Feature",
  "properties": {
    "gn:admin1_code":"30.0",
    "gn:asciiname":"Sideurangdatar",
    "gn:country_code":"ID",
    "gn:dem":1232,
    "gn:feature_class":"P",
    "gn:feature_code":"PPL",
    "gn:name":"Sideurangdatar",
    "gn:population":0,
    "gn:timezone":"Asia/Jakarta",
    "iso:country":"ID",
    "name:ind_x_preferred":[
        "Sideurangdatar"
    ],
    "wof:name":"Sideurangdatar",
    "wof:placetype":"locality"
},
  "geometry": {"coordinates":[107.821,-7.298],"type":"Point"}
}