{
  "type": "Feature",
  "properties": {
    "gn:admin1_code":"2.0",
    "gn:asciiname":"Banjar Asahduren",
    "gn:country_code":"ID",
    "gn:dem":253,
    "gn:feature_class":"P",
    "gn:feature_code":"PPLA4",
    "gn:name":"Banjar Asahduren",
    "gn:population":0,
    "gn:timezone":"Asia/Makassar",
    "iso:country":"ID",
    "name:ind_x_preferred":[
        "Banjar Asahduren"
    ],
    "wof:name":"Banjar Asahduren",
    "wof:placetype":"locality"
},
  "geometry": {"coordinates":[114.85250000000001,-8.3981],"type":"Point"}
}