{
  "type": "Feature",
  "properties": {
    "gn:admin1_code":"28.0",
    "gn:asciiname":"Ngursi",
    "gn:country_code":"ID",
    "gn:dem":7,
    "gn:feature_class":"P",
    "gn:feature_code":"PPL",
    "gn:name":"Ngursi",
    "gn:population":0,
    "gn:timezone":"Asia/Jayapura",
    "iso:country":"ID",
    "name:und_x_variant":[
        "Ngoersit",
        "Ngursi"
    ],
    "wof:name":"Ngursi",
    "wof:placetype":"locality"
},
  "geometry": {"coordinates":[132.67487,-5.75979],"type":"Point"}
}