{
  "type": "Feature",
  "properties": {
    "gn:admin1_code":"07",
    "gn:asciiname":"Kaliwungu",
    "gn:country_code":"ID",
    "gn:dem":340,
    "gn:feature_class":"P",
    "gn:feature_code":"PPL",
    "gn:name":"Kaliwungu",
    "gn:population":0,
    "gn:timezone":"Asia/Jakarta",
    "iso:country":"ID",
    "name:und_x_variant":[
        "Kaliwungo Dua",
        "Kaliwungo 2",
        "Kaliwungu"
    ],
    "wof:name":"Kaliwungu",
    "wof:placetype":"locality"
},
  "geometry": {"coordinates":[110.66417,-7.40639],"type":"Point"}
}