{
  "type": "Feature",
  "properties": {
    "gn:admin1_code":"30",
    "gn:asciiname":"Pasirkiara",
    "gn:cc2":"ID",
    "gn:country_code":"ID",
    "gn:dem":685,
    "gn:feature_class":"P",
    "gn:feature_code":"PPL",
    "gn:name":"Pasirkiara",
    "gn:population":0,
    "gn:timezone":"Asia/Jakarta",
    "iso:country":"ID",
    "name:und_x_variant":[
        "Pasirklara",
        "Pasirkiara"
    ],
    "wof:lang_x_official":[
        "ind"
    ],
    "wof:lang_x_spoken":[
        "ind",
        "eng"
    ],
    "wof:name":"Pasirkiara",
    "wof:placetype":"locality"
},
  "geometry": {"coordinates":[107.74917000000001,-7.05833],"type":"Point"}
}