{
  "type": "Feature",
  "properties": {
    "gn:admin1_code":"18.0",
    "gn:asciiname":"Loborae",
    "gn:country_code":"ID",
    "gn:dem":102,
    "gn:feature_class":"P",
    "gn:feature_code":"PPL",
    "gn:name":"Loborae",
    "gn:population":0,
    "gn:timezone":"Asia/Makassar",
    "iso:country":"ID",
    "name:ind_x_preferred":[
        "Loborae"
    ],
    "wof:name":"Loborae",
    "wof:placetype":"locality"
},
  "geometry": {"coordinates":[121.97069999999999,-10.4755],"type":"Point"}
}