{
  "type": "Feature",
  "properties": {
    "gn:admin1_code":"37",
    "gn:asciiname":"Parittigabelas",
    "gn:country_code":"ID",
    "gn:dem":2,
    "gn:feature_class":"P",
    "gn:feature_code":"PPL",
    "gn:name":"Parittigabelas",
    "gn:population":0,
    "gn:timezone":"Asia/Jakarta",
    "iso:country":"ID",
    "name:ind_x_preferred":[
        "Parittigabelas"
    ],
    "wof:name":"Parittigabelas",
    "wof:placetype":"locality"
},
  "geometry": {"coordinates":[103.29976000000001,-0.27877],"type":"Point"}
}