{
  "type": "Feature",
  "properties": {
    "gn:admin1_code":"1.0",
    "gn:asciiname":"Bayu",
    "gn:country_code":"ID",
    "gn:dem":180,
    "gn:feature_class":"P",
    "gn:feature_code":"PPL",
    "gn:name":"Bayu",
    "gn:population":0,
    "gn:timezone":"Asia/Jakarta",
    "iso:country":"ID",
    "name:ind_x_preferred":[
        "Bayu"
    ],
    "name:jav_x_preferred":[
        "Bayu"
    ],
    "name:nld_x_preferred":[
        "Bayu"
    ],
    "name:und_x_variant":[
        "Baju"
    ],
    "wof:name":"Bayu",
    "wof:placetype":"locality"
},
  "geometry": {"coordinates":[95.5972,5.3937],"type":"Point"}
}