{
  "type": "Feature",
  "properties": {
    "gn:admin1_code":"38.0",
    "gn:asciiname":"Rarukan",
    "gn:country_code":"ID",
    "gn:dem":356,
    "gn:feature_class":"P",
    "gn:feature_code":"PPL",
    "gn:name":"Rarukan",
    "gn:population":0,
    "gn:timezone":"Asia/Makassar",
    "iso:country":"ID",
    "name:ind_x_preferred":[
        "Rarukan"
    ],
    "wof:name":"Rarukan",
    "wof:placetype":"locality"
},
  "geometry": {"coordinates":[120.05670000000001,-3.2173],"type":"Point"}
}