{
  "type": "Feature",
  "properties": {
    "gn:admin1_code":"26",
    "gn:asciiname":"Lawe Bekung Gabungan",
    "gn:country_code":"ID",
    "gn:dem":250,
    "gn:feature_class":"P",
    "gn:feature_code":"PPL",
    "gn:name":"Lawe Bekung Gabungan",
    "gn:population":0,
    "gn:timezone":"Asia/Jakarta",
    "iso:country":"ID",
    "name:ind_x_preferred":[
        "Lawe Bekung Gabungan"
    ],
    "wof:name":"Lawe Bekung Gabungan",
    "wof:placetype":"locality"
},
  "geometry": {"coordinates":[97.8049,3.5259],"type":"Point"}
}