{
  "type": "Feature",
  "properties": {
    "gn:admin1_code":"7.0",
    "gn:asciiname":"Karanggintung",
    "gn:country_code":"ID",
    "gn:dem":105,
    "gn:feature_class":"P",
    "gn:feature_code":"PPLA4",
    "gn:name":"Karanggintung",
    "gn:population":0,
    "gn:timezone":"Asia/Jakarta",
    "iso:country":"ID",
    "name:ind_x_preferred":[
        "Karanggintung"
    ],
    "name:und_x_variant":[
        "Karanggintoeng"
    ],
    "wof:lang_x_official":[
        "ind"
    ],
    "wof:lang_x_spoken":[
        "ind",
        "eng"
    ],
    "wof:name":"Karanggintung",
    "wof:placetype":"locality"
},
  "geometry": {"coordinates":[108.85899999999999,-7.4579],"type":"Point"}
}