{
  "type": "Feature",
  "properties": {
    "gn:admin1_code":"10.0",
    "gn:asciiname":"Songbanyu Dua",
    "gn:country_code":"ID",
    "gn:dem":219,
    "gn:feature_class":"P",
    "gn:feature_code":"PPL",
    "gn:name":"Songbanyu Dua",
    "gn:population":0,
    "gn:timezone":"Asia/Jakarta",
    "iso:country":"ID",
    "name:ind_x_preferred":[
        "Songbanyu Dua"
    ],
    "wof:name":"Songbanyu Dua",
    "wof:placetype":"locality"
},
  "geometry": {"coordinates":[110.81583000000001,-8.14667],"type":"Point"}
}