{
  "type": "Feature",
  "properties": {
    "gn:admin1_code":"8.0",
    "gn:asciiname":"Sumberurip Lor",
    "gn:country_code":"ID",
    "gn:dem":592,
    "gn:feature_class":"P",
    "gn:feature_code":"PPL",
    "gn:name":"Sumberurip Lor",
    "gn:population":0,
    "gn:timezone":"Asia/Jakarta",
    "iso:country":"ID",
    "name:ind_x_preferred":[
        "Sumberurip Lor"
    ],
    "wof:name":"Sumberurip Lor",
    "wof:placetype":"locality"
},
  "geometry": {"coordinates":[112.3969,-8.0284],"type":"Point"}
}