{
  "type": "Feature",
  "properties": {
    "gn:admin1_code":"15.0",
    "gn:asciiname":"Talang Pengeringan",
    "gn:country_code":"ID",
    "gn:dem":140,
    "gn:feature_class":"P",
    "gn:feature_code":"PPL",
    "gn:name":"Talang Pengeringan",
    "gn:population":0,
    "gn:timezone":"Asia/Jakarta",
    "iso:country":"ID",
    "name:ind_x_preferred":[
        "Talang Pengeringan"
    ],
    "wof:name":"Talang Pengeringan",
    "wof:placetype":"locality"
},
  "geometry": {"coordinates":[104.40939,-4.60323],"type":"Point"}
}