{
  "type": "Feature",
  "properties": {
    "gn:admin1_code":"8.0",
    "gn:asciiname":"Krajan Tambakrejo",
    "gn:country_code":"ID",
    "gn:dem":27,
    "gn:feature_class":"P",
    "gn:feature_code":"PPLA4",
    "gn:name":"Krajan Tambakrejo",
    "gn:population":0,
    "gn:timezone":"Asia/Jakarta",
    "iso:country":"ID",
    "name:ind_x_preferred":[
        "Krajan Tambakrejo"
    ],
    "name:ind_x_variant":[
        "Tambakredja"
    ],
    "name:und_x_variant":[
        "Tambakredjo",
        "Tambakrejo"
    ],
    "wof:lang_x_official":[
        "ind"
    ],
    "wof:lang_x_spoken":[
        "ind",
        "eng"
    ],
    "wof:name":"Krajan Tambakrejo",
    "wof:placetype":"locality"
},
  "geometry": {"coordinates":[112.7145,-8.4028],"type":"Point"}
}