{
  "type": "Feature",
  "properties": {
    "gn:admin1_code":"37.0",
    "gn:asciiname":"Tanahputih",
    "gn:country_code":"ID",
    "gn:dem":23,
    "gn:feature_class":"P",
    "gn:feature_code":"PPL",
    "gn:name":"Tanahputih",
    "gn:population":0,
    "gn:timezone":"Asia/Jakarta",
    "iso:country":"ID",
    "name:und_x_variant":[
        "Tanahpoetih",
        "Tanahputi",
        "Tanahputih"
    ],
    "wof:name":"Tanahputih",
    "wof:placetype":"locality"
},
  "geometry": {"coordinates":[101.05713,1.68245],"type":"Point"}
}