{
  "type": "Feature",
  "properties": {
    "gn:admin1_code":"11",
    "gn:asciiname":"Sebabas",
    "gn:country_code":"ID",
    "gn:dem":87,
    "gn:feature_class":"P",
    "gn:feature_code":"PPL",
    "gn:name":"Sebabas",
    "gn:population":0,
    "gn:timezone":"Asia/Pontianak",
    "iso:country":"ID",
    "name:ind_x_preferred":[
        "Sebabas"
    ],
    "wof:name":"Sebabas",
    "wof:placetype":"locality"
},
  "geometry": {"coordinates":[110.81228,-0.44095],"type":"Point"}
}