{
  "type": "Feature",
  "properties": {
    "gn:admin1_code":"8.0",
    "gn:asciiname":"Budu",
    "gn:country_code":"ID",
    "gn:dem":117,
    "gn:feature_class":"P",
    "gn:feature_code":"PPL",
    "gn:name":"Budu",
    "gn:population":0,
    "gn:timezone":"Asia/Jakarta",
    "iso:country":"ID",
    "name:ceb_x_preferred":[
        "Budu"
    ],
    "name:deu_x_preferred":[
        "Budu"
    ],
    "name:fra_x_preferred":[
        "Budu"
    ],
    "name:ind_x_preferred":[
        "Budu"
    ],
    "name:swe_x_preferred":[
        "Budu"
    ],
    "name:tgl_x_preferred":[
        "Budu"
    ],
    "wof:lang_x_official":[
        "ind"
    ],
    "wof:lang_x_spoken":[
        "ind",
        "eng"
    ],
    "wof:name":"Budu",
    "wof:placetype":"locality"
},
  "geometry": {"coordinates":[111.4389,-7.9874],"type":"Point"}
}