{
  "type": "Feature",
  "properties": {
    "gn:admin1_code":"35",
    "gn:asciiname":"Manggarau",
    "gn:country_code":"ID",
    "gn:dem":34,
    "gn:feature_class":"P",
    "gn:feature_code":"PPL",
    "gn:name":"Manggarau",
    "gn:population":0,
    "gn:timezone":"Asia/Jakarta",
    "iso:country":"ID",
    "name:ind_x_preferred":[
        "Manggarau"
    ],
    "wof:name":"Manggarau",
    "wof:placetype":"locality"
},
  "geometry": {"coordinates":[105.88137999999999,-2.25072],"type":"Point"}
}