{
  "type": "Feature",
  "properties": {
    "gn:admin1_code":"15.0",
    "gn:asciiname":"Cibalong",
    "gn:country_code":"ID",
    "gn:dem":221,
    "gn:feature_class":"P",
    "gn:feature_code":"PPL",
    "gn:name":"Cibalong",
    "gn:population":0,
    "gn:timezone":"Asia/Jakarta",
    "iso:country":"ID",
    "name:ind_x_preferred":[
        "Cibalong"
    ],
    "wof:name":"Cibalong",
    "wof:placetype":"locality"
},
  "geometry": {"coordinates":[105.08471000000002,-5.58779],"type":"Point"}
}