{
  "type": "Feature",
  "properties": {
    "gn:admin1_code":"38",
    "gn:asciiname":"Patiroang",
    "gn:country_code":"ID",
    "gn:dem":8,
    "gn:feature_class":"P",
    "gn:feature_code":"PPL",
    "gn:name":"Patiroang",
    "gn:population":0,
    "gn:timezone":"Asia/Makassar",
    "iso:country":"ID",
    "name:ind_x_preferred":[
        "Patiroang"
    ],
    "wof:name":"Patiroang",
    "wof:placetype":"locality"
},
  "geometry": {"coordinates":[119.6748,-5.6364],"type":"Point"}
}