{
  "type": "Feature",
  "properties": {
    "gn:admin1_code":"26",
    "gn:asciiname":"Tanopan",
    "gn:country_code":"ID",
    "gn:dem":130,
    "gn:feature_class":"P",
    "gn:feature_code":"PPL",
    "gn:name":"Tanopan",
    "gn:population":0,
    "gn:timezone":"Asia/Jakarta",
    "iso:country":"ID",
    "name:ind_x_preferred":[
        "Tanopan"
    ],
    "wof:name":"Tanopan",
    "wof:placetype":"locality"
},
  "geometry": {"coordinates":[99.73685999999999,1.09532],"type":"Point"}
}