{
  "type": "Feature",
  "properties": {
    "gn:admin1_code":"15.0",
    "gn:asciiname":"Kotakarang",
    "gn:country_code":"ID",
    "gn:dem":12,
    "gn:feature_class":"P",
    "gn:feature_code":"PPL",
    "gn:name":"Kotakarang",
    "gn:population":0,
    "gn:timezone":"Asia/Jakarta",
    "iso:country":"ID",
    "name:ind_x_preferred":[
        "Kotakarang"
    ],
    "name:und_x_variant":[
        "Koetakarang"
    ],
    "wof:name":"Kotakarang",
    "wof:placetype":"locality"
},
  "geometry": {"coordinates":[103.80622,-5.04714],"type":"Point"}
}