{
  "type": "Feature",
  "properties": {
    "gn:admin1_code":"17",
    "gn:asciiname":"Tapon Timur",
    "gn:country_code":"ID",
    "gn:dem":81,
    "gn:feature_class":"P",
    "gn:feature_code":"PPL",
    "gn:name":"Tapon Timur",
    "gn:population":0,
    "gn:timezone":"Asia/Makassar",
    "iso:country":"ID",
    "name:ind_x_preferred":[
        "Tapon Timur"
    ],
    "wof:name":"Tapon Timur",
    "wof:placetype":"locality"
},
  "geometry": {"coordinates":[116.1853,-8.621],"type":"Point"}
}