{
  "type": "Feature",
  "properties": {
    "gn:admin1_code":"10",
    "gn:asciiname":"Sepat",
    "gn:country_code":"ID",
    "gn:dem":361,
    "gn:feature_class":"P",
    "gn:feature_code":"PPL",
    "gn:name":"Sepat",
    "gn:population":0,
    "gn:timezone":"Asia/Jakarta",
    "iso:country":"ID",
    "name:ind_x_preferred":[
        "Sepat"
    ],
    "wof:name":"Sepat",
    "wof:placetype":"locality"
},
  "geometry": {"coordinates":[110.53306000000001,-7.83417],"type":"Point"}
}