{
  "type": "Feature",
  "properties": {
    "gn:admin1_code":"1",
    "gn:asciiname":"Shintob",
    "gn:country_code":"ID",
    "gn:dem":33,
    "gn:feature_class":"P",
    "gn:feature_code":"PPL",
    "gn:name":"Shintob",
    "gn:population":0,
    "gn:timezone":"Asia/Jakarta",
    "iso:country":"ID",
    "name:ind_x_preferred":[
        "Shintob"
    ],
    "name:und_x_variant":[
        "Sintob"
    ],
    "wof:name":"Shintob",
    "wof:placetype":"locality"
},
  "geometry": {"coordinates":[95.91249999999999,5.2893],"type":"Point"}
}