{
  "type": "Feature",
  "properties": {
    "gn:admin1_code":"30.0",
    "gn:asciiname":"Cibeureum",
    "gn:country_code":"ID",
    "gn:dem":711,
    "gn:feature_class":"P",
    "gn:feature_code":"PPLA4",
    "gn:name":"Cibeureum",
    "gn:population":0,
    "gn:timezone":"Asia/Jakarta",
    "iso:country":"ID",
    "name:ind_x_preferred":[
        "Cibeureum"
    ],
    "name:und_x_variant":[
        "Tjibeureumtoea"
    ],
    "wof:name":"Cibeureum",
    "wof:placetype":"locality"
},
  "geometry": {"coordinates":[107.9933,-7.1597],"type":"Point"}
}