{
  "type": "Feature",
  "properties": {
    "gn:admin1_code":"30.0",
    "gn:asciiname":"Cibogo",
    "gn:country_code":"ID",
    "gn:dem":461,
    "gn:feature_class":"P",
    "gn:feature_code":"PPL",
    "gn:name":"Cibogo",
    "gn:population":0,
    "gn:timezone":"Asia/Jakarta",
    "iso:country":"ID",
    "name:ind_x_preferred":[
        "Cibogo"
    ],
    "wof:name":"Cibogo",
    "wof:placetype":"locality"
},
  "geometry": {"coordinates":[106.7336,-7.0489],"type":"Point"}
}