{
  "type": "Feature",
  "properties": {
    "gn:admin1_code":"30",
    "gn:asciiname":"Cimanggu Dua",
    "gn:country_code":"ID",
    "gn:dem":224,
    "gn:feature_class":"P",
    "gn:feature_code":"PPL",
    "gn:name":"Cimanggu Dua",
    "gn:population":0,
    "gn:timezone":"Asia/Jakarta",
    "iso:country":"ID",
    "name:ind_x_preferred":[
        "Cimanggu Dua"
    ],
    "name:und_x_variant":[
        "Cimanggu 2"
    ],
    "wof:lang_x_official":[
        "ind"
    ],
    "wof:lang_x_spoken":[
        "ind",
        "eng"
    ],
    "wof:name":"Cimanggu Dua",
    "wof:placetype":"locality"
},
  "geometry": {"coordinates":[106.66417,-6.57389],"type":"Point"}
}