{
  "type": "Feature",
  "properties": {
    "gn:admin1_code":"15.0",
    "gn:asciiname":"Piabung",
    "gn:country_code":"ID",
    "gn:dem":6,
    "gn:feature_class":"P",
    "gn:feature_code":"PPL",
    "gn:name":"Piabung",
    "gn:population":0,
    "gn:timezone":"Asia/Jakarta",
    "iso:country":"ID",
    "name:ind_x_preferred":[
        "Piabung"
    ],
    "name:und_x_variant":[
        "Piaboeng"
    ],
    "wof:name":"Piabung",
    "wof:placetype":"locality"
},
  "geometry": {"coordinates":[105.17194000000001,-5.61193],"type":"Point"}
}