{
  "type": "Feature",
  "properties": {
    "gn:country":"ID",
    "gn:fcode":"ADM4",
    "gn:pop":0,
    "iso:country":"ID",
    "name:ind_x_preferred":[
        "Desa Tugu Utara"
    ],
    "name:unk_x_variant":[
        "Tugu Utara"
    ],
    "qs:name":"Desa Tugu Utara",
    "qs:photos_9r":0,
    "qs:photos_sr":0,
    "qs:pop_sr":"0",
    "wof:name":"Desa Tugu Utara",
    "wof:placetype":"localadmin",
    "wof:population":0
},
  "geometry": {"coordinates":[106.97583,-6.68444],"type":"Point"}
}