{
  "type": "Feature",
  "properties": {
    "gn:admin1_code":"30",
    "gn:asciiname":"Pasirhaur",
    "gn:country_code":"ID",
    "gn:dem":407,
    "gn:feature_class":"P",
    "gn:feature_code":"PPL",
    "gn:name":"Pasirhaur",
    "gn:population":0,
    "gn:timezone":"Asia/Jakarta",
    "iso:country":"ID",
    "name:ind_x_preferred":[
        "Pasirhaur"
    ],
    "wof:name":"Pasirhaur",
    "wof:placetype":"locality"
},
  "geometry": {"coordinates":[107.16861000000002,-6.88472],"type":"Point"}
}