{
  "type": "Feature",
  "properties": {
    "gn:admin1_code":"38.0",
    "gn:asciiname":"Rada",
    "gn:country_code":"ID",
    "gn:dem":934,
    "gn:feature_class":"P",
    "gn:feature_code":"PPL",
    "gn:name":"Rada",
    "gn:population":0,
    "gn:timezone":"Asia/Makassar",
    "iso:country":"ID",
    "name:ind_x_preferred":[
        "Rada"
    ],
    "wof:name":"Rada",
    "wof:placetype":"locality"
},
  "geometry": {"coordinates":[119.7436,-3.0328],"type":"Point"}
}