{
  "type": "Feature",
  "properties": {
    "gn:admin1_code":"8.0",
    "gn:asciiname":"Konang Daja",
    "gn:country_code":"ID",
    "gn:dem":22,
    "gn:feature_class":"P",
    "gn:feature_code":"PPL",
    "gn:name":"Konang Daja",
    "gn:population":0,
    "gn:timezone":"Asia/Jakarta",
    "iso:country":"ID",
    "name:ind_x_preferred":[
        "Konang Daja"
    ],
    "wof:name":"Konang Daja",
    "wof:placetype":"locality"
},
  "geometry": {"coordinates":[113.53448,-7.14736],"type":"Point"}
}