{
  "type": "Feature",
  "properties": {
    "gn:admin1_code":"37.0",
    "gn:asciiname":"Sungaipuyuh",
    "gn:country_code":"ID",
    "gn:dem":8,
    "gn:feature_class":"P",
    "gn:feature_code":"PPL",
    "gn:name":"Sungaipuyuh",
    "gn:population":0,
    "gn:timezone":"Asia/Jakarta",
    "iso:country":"ID",
    "name:und_x_variant":[
        "Soengaipoejoeh",
        "Sungaipujuh",
        "Sungaipuyuh"
    ],
    "wof:name":"Sungaipuyuh",
    "wof:placetype":"locality"
},
  "geometry": {"coordinates":[102.16667,1.16667],"type":"Point"}
}