{
  "type": "Feature",
  "properties": {
    "gn:admin1_code":"30",
    "gn:asciiname":"Hargem Girang",
    "gn:country_code":"ID",
    "gn:dem":1051,
    "gn:feature_class":"P",
    "gn:feature_code":"PPL",
    "gn:name":"Hargem Girang",
    "gn:population":0,
    "gn:timezone":"Asia/Jakarta",
    "iso:country":"ID",
    "name:ind_x_preferred":[
        "Hargem Girang"
    ],
    "name:und_x_variant":[
        "Heregam 1"
    ],
    "wof:name":"Hargem Girang",
    "wof:placetype":"locality"
},
  "geometry": {"coordinates":[107.05083,-6.78472],"type":"Point"}
}