{
  "type": "Feature",
  "properties": {
    "gn:admin1_code":"18",
    "gn:asciiname":"Punggowacu",
    "gn:country_code":"ID",
    "gn:dem":596,
    "gn:feature_class":"P",
    "gn:feature_code":"PPL",
    "gn:name":"Punggowacu",
    "gn:population":0,
    "gn:timezone":"Asia/Makassar",
    "iso:country":"ID",
    "name:ind_x_preferred":[
        "Punggowacu"
    ],
    "wof:name":"Punggowacu",
    "wof:placetype":"locality"
},
  "geometry": {"coordinates":[119.7877,-9.6318],"type":"Point"}
}