{
  "type": "Feature",
  "properties": {
    "gn:admin1_code":"30",
    "gn:asciiname":"Tegalpanjang",
    "gn:country_code":"ID",
    "gn:dem":308,
    "gn:feature_class":"P",
    "gn:feature_code":"PPL",
    "gn:name":"Tegalpanjang",
    "gn:population":0,
    "gn:timezone":"Asia/Jakarta",
    "iso:country":"ID",
    "name:ind_x_preferred":[
        "Tegalpanjang"
    ],
    "wof:name":"Tegalpanjang",
    "wof:placetype":"locality"
},
  "geometry": {"coordinates":[106.76888999999998,-6.99278],"type":"Point"}
}