{
  "type": "Feature",
  "properties": {
    "gn:admin1_code":"35",
    "gn:asciiname":"Telukpanyemen",
    "gn:country_code":"ID",
    "gn:dem":18,
    "gn:feature_class":"P",
    "gn:feature_code":"PPL",
    "gn:name":"Telukpanyemen",
    "gn:population":0,
    "gn:timezone":"Asia/Jakarta",
    "iso:country":"ID",
    "name:ind_x_preferred":[
        "Telukpanyemen"
    ],
    "wof:name":"Telukpanyemen",
    "wof:placetype":"locality"
},
  "geometry": {"coordinates":[106.43137,-2.88373],"type":"Point"}
}