{
  "type": "Feature",
  "properties": {
    "gn:admin1_code":"2.0",
    "gn:asciiname":"Batang",
    "gn:country_code":"ID",
    "gn:dem":99,
    "gn:feature_class":"P",
    "gn:feature_code":"PPL",
    "gn:name":"Batang",
    "gn:population":0,
    "gn:timezone":"Asia/Makassar",
    "iso:country":"ID",
    "name:ceb_x_preferred":[
        "Batang"
    ],
    "name:deu_x_preferred":[
        "Batang"
    ],
    "name:fra_x_preferred":[
        "Batang"
    ],
    "name:ind_x_preferred":[
        "Batang"
    ],
    "name:jpn_x_preferred":[
        "\u30d0\u30bf\u30f3"
    ],
    "name:mlg_x_preferred":[
        "Batang"
    ],
    "name:nld_x_preferred":[
        "Batang"
    ],
    "name:nor_x_preferred":[
        "Batang"
    ],
    "name:sun_x_preferred":[
        "Batang"
    ],
    "name:swe_x_preferred":[
        "Batang"
    ],
    "wof:lang_x_official":[
        "ind"
    ],
    "wof:lang_x_spoken":[
        "ind",
        "eng"
    ],
    "wof:name":"Batang",
    "wof:placetype":"locality"
},
  "geometry": {"coordinates":[115.61190000000001,-8.3341],"type":"Point"}
}