{
  "type": "Feature",
  "properties": {
    "gn:admin1_code":"8",
    "gn:asciiname":"Ploso",
    "gn:country_code":"ID",
    "gn:dem":57,
    "gn:feature_class":"P",
    "gn:feature_code":"PPL",
    "gn:name":"Ploso",
    "gn:population":0,
    "gn:timezone":"Asia/Jakarta",
    "iso:country":"ID",
    "name:ind_x_preferred":[
        "Ploso"
    ],
    "wof:name":"Ploso",
    "wof:placetype":"locality"
},
  "geometry": {"coordinates":[112.10769999999999,-7.6692],"type":"Point"}
}