{
  "type": "Feature",
  "properties": {
    "gn:admin1_code":"0.0",
    "gn:asciiname":"Cisurupan",
    "gn:cc2":"ID",
    "gn:country_code":"ID",
    "gn:dem":1319,
    "gn:feature_class":"P",
    "gn:feature_code":"PPL",
    "gn:name":"Cisurupan",
    "gn:population":0,
    "gn:timezone":"Asia/Jakarta",
    "iso:country":"ID",
    "name:und_x_variant":[
        "Tjisoeroepan",
        "Tjisurupan",
        "Cisurupan"
    ],
    "wof:name":"Cisurupan",
    "wof:placetype":"locality"
},
  "geometry": {"coordinates":[107.78333000000001,-7.31667],"type":"Point"}
}