{
  "type": "Feature",
  "properties": {
    "gn:admin1_code":"8.0",
    "gn:asciiname":"Glendoh",
    "gn:country_code":"ID",
    "gn:dem":109,
    "gn:feature_class":"P",
    "gn:feature_code":"PPL",
    "gn:name":"Glendoh",
    "gn:population":0,
    "gn:timezone":"Asia/Jakarta",
    "iso:country":"ID",
    "name:ind_x_preferred":[
        "Glendoh"
    ],
    "wof:name":"Glendoh",
    "wof:placetype":"locality"
},
  "geometry": {"coordinates":[111.4721,-7.9597],"type":"Point"}
}