{
  "type": "Feature",
  "properties": {
    "gn:admin1_code":"8.0",
    "gn:asciiname":"Parasgowang",
    "gn:country_code":"ID",
    "gn:dem":35,
    "gn:feature_class":"P",
    "gn:feature_code":"PPL",
    "gn:name":"Parasgowang",
    "gn:population":0,
    "gn:timezone":"Asia/Jakarta",
    "iso:country":"ID",
    "name:ind_x_preferred":[
        "Parasgowang"
    ],
    "wof:name":"Parasgowang",
    "wof:placetype":"locality"
},
  "geometry": {"coordinates":[113.18340000000001,-8.2563],"type":"Point"}
}