{
  "type": "Feature",
  "properties": {
    "gn:admin1_code":"30",
    "gn:asciiname":"Gununghalu",
    "gn:country_code":"ID",
    "gn:dem":272,
    "gn:feature_class":"P",
    "gn:feature_code":"PPL",
    "gn:name":"Gununghalu",
    "gn:population":0,
    "gn:timezone":"Asia/Jakarta",
    "iso:country":"ID",
    "name:ind_x_preferred":[
        "Gununghalu"
    ],
    "wof:name":"Gununghalu",
    "wof:placetype":"locality"
},
  "geometry": {"coordinates":[107.26806000000001,-6.80861],"type":"Point"}
}