{
  "type": "Feature",
  "properties": {
    "gn:admin1_code":"8.0",
    "gn:asciiname":"Tembalang",
    "gn:country_code":"ID",
    "gn:dem":320,
    "gn:feature_class":"P",
    "gn:feature_code":"PPLA4",
    "gn:name":"Tembalang",
    "gn:population":0,
    "gn:timezone":"Asia/Jakarta",
    "iso:country":"ID",
    "name:ind_x_preferred":[
        "Tembalang"
    ],
    "wof:name":"Tembalang",
    "wof:placetype":"locality"
},
  "geometry": {"coordinates":[112.33499999999999,-8.0701],"type":"Point"}
}