{
  "type": "Feature",
  "properties": {
    "gn:admin1_code":"0.0",
    "gn:asciiname":"Tukarkendah",
    "gn:cc2":"ID",
    "gn:country_code":"ID",
    "gn:dem":380,
    "gn:feature_class":"P",
    "gn:feature_code":"PPL",
    "gn:name":"Tukarkendah",
    "gn:population":0,
    "gn:timezone":"Asia/Jayapura",
    "iso:country":"ID",
    "name:und_x_variant":[
        "Toekarkendah",
        "Tukarkendah"
    ],
    "wof:name":"Tukarkendah",
    "wof:placetype":"locality"
},
  "geometry": {"coordinates":[132.23333,-2.86667],"type":"Point"}
}