{
  "type": "Feature",
  "properties": {
    "gn:admin1_code":"18.0",
    "gn:asciiname":"Baudale",
    "gn:country_code":"ID",
    "gn:dem":37,
    "gn:feature_class":"P",
    "gn:feature_code":"PPL",
    "gn:name":"Baudale",
    "gn:population":0,
    "gn:timezone":"Asia/Makassar",
    "iso:country":"ID",
    "name:ind_x_preferred":[
        "Baudale"
    ],
    "wof:name":"Baudale",
    "wof:placetype":"locality"
},
  "geometry": {"coordinates":[123.0774,-10.6987],"type":"Point"}
}