{
  "type": "Feature",
  "properties": {
    "gn:admin1_code":"22.0",
    "gn:asciiname":"Awo",
    "gn:country_code":"ID",
    "gn:dem":4,
    "gn:feature_class":"P",
    "gn:feature_code":"PPL",
    "gn:name":"Awo",
    "gn:population":0,
    "gn:timezone":"Asia/Makassar",
    "iso:country":"ID",
    "name:ceb_x_preferred":[
        "Awo"
    ],
    "name:ind_x_preferred":[
        "Awo"
    ],
    "name:swe_x_preferred":[
        "Awo"
    ],
    "wof:lang_x_official":[
        "ind"
    ],
    "wof:lang_x_spoken":[
        "ind",
        "eng"
    ],
    "wof:name":"Awo",
    "wof:placetype":"locality"
},
  "geometry": {"coordinates":[120.9006,-3.3825],"type":"Point"}
}