{
  "type": "Feature",
  "properties": {
    "gn:admin1_code":"30",
    "gn:asciiname":"Pekalongan",
    "gn:country_code":"ID",
    "gn:dem":1224,
    "gn:feature_class":"P",
    "gn:feature_code":"PPL",
    "gn:name":"Pekalongan",
    "gn:population":0,
    "gn:timezone":"Asia/Jakarta",
    "iso:country":"ID",
    "name:ind_x_preferred":[
        "Pekalongan"
    ],
    "wof:name":"Pekalongan",
    "wof:placetype":"locality"
},
  "geometry": {"coordinates":[107.02472,-6.73722],"type":"Point"}
}