{
  "type": "Feature",
  "properties": {
    "gn:admin1_code":"37",
    "gn:asciiname":"Pangkalansiminai",
    "gn:country_code":"ID",
    "gn:dem":18,
    "gn:feature_class":"P",
    "gn:feature_code":"PPL",
    "gn:name":"Pangkalansiminai",
    "gn:population":0,
    "gn:timezone":"Asia/Jakarta",
    "iso:country":"ID",
    "name:ind_x_preferred":[
        "Pangkalansiminai"
    ],
    "wof:name":"Pangkalansiminai",
    "wof:placetype":"locality"
},
  "geometry": {"coordinates":[101.7906,0.3848],"type":"Point"}
}