{
  "type": "Feature",
  "properties": {
    "gn:admin1_code":"30",
    "gn:asciiname":"Cijamur",
    "gn:country_code":"ID",
    "gn:dem":386,
    "gn:feature_class":"P",
    "gn:feature_code":"PPL",
    "gn:name":"Cijamur",
    "gn:population":0,
    "gn:timezone":"Asia/Jakarta",
    "iso:country":"ID",
    "name:ind_x_preferred":[
        "Cijamur"
    ],
    "wof:name":"Cijamur",
    "wof:placetype":"locality"
},
  "geometry": {"coordinates":[107.39888999999999,-6.70222],"type":"Point"}
}