{
  "type": "Feature",
  "properties": {
    "gn:admin1_code":"1",
    "gn:asciiname":"Lubok Pingping",
    "gn:country_code":"ID",
    "gn:dem":14,
    "gn:feature_class":"P",
    "gn:feature_code":"PPL",
    "gn:name":"Lubok Pingping",
    "gn:population":0,
    "gn:timezone":"Asia/Jakarta",
    "iso:country":"ID",
    "name:ind_x_preferred":[
        "Lubok Pingping"
    ],
    "name:und_x_variant":[
        "Lubokpengpeng"
    ],
    "wof:name":"Lubok Pingping",
    "wof:placetype":"locality"
},
  "geometry": {"coordinates":[97.81359999999999,4.771],"type":"Point"}
}