{
  "type": "Feature",
  "properties": {
    "gn:admin1_code":"8",
    "gn:asciiname":"Jambu",
    "gn:country_code":"ID",
    "gn:dem":29,
    "gn:feature_class":"P",
    "gn:feature_code":"PPL",
    "gn:name":"Jambu",
    "gn:population":0,
    "gn:timezone":"Asia/Jakarta",
    "iso:country":"ID",
    "name:ceb_x_preferred":[
        "Jambu"
    ],
    "name:deu_x_preferred":[
        "Jambu"
    ],
    "name:ind_x_preferred":[
        "Jambu"
    ],
    "name:nld_x_preferred":[
        "Jambu"
    ],
    "name:swe_x_preferred":[
        "Jambu"
    ],
    "wof:lang_x_official":[
        "ind"
    ],
    "wof:lang_x_spoken":[
        "ind",
        "eng"
    ],
    "wof:name":"Jambu",
    "wof:placetype":"locality"
},
  "geometry": {"coordinates":[112.8438,-7.6655],"type":"Point"}
}