{
  "type": "Feature",
  "properties": {
    "gn:admin1_code":"30.0",
    "gn:asciiname":"Linggajaya",
    "gn:country_code":"ID",
    "gn:dem":266,
    "gn:feature_class":"P",
    "gn:feature_code":"PPL",
    "gn:name":"Linggajaya",
    "gn:population":0,
    "gn:timezone":"Asia/Jakarta",
    "iso:country":"ID",
    "name:ind_x_preferred":[
        "Linggajaya"
    ],
    "name:und_x_variant":[
        "Linggadjaja"
    ],
    "wof:name":"Linggajaya",
    "wof:placetype":"locality"
},
  "geometry": {"coordinates":[106.8398,-7.3069],"type":"Point"}
}