{
  "type": "Feature",
  "properties": {
    "gn:admin1_code":"8.0",
    "gn:asciiname":"Gondang Kidul",
    "gn:country_code":"ID",
    "gn:dem":23,
    "gn:feature_class":"P",
    "gn:feature_code":"PPL",
    "gn:name":"Gondang Kidul",
    "gn:population":0,
    "gn:timezone":"Asia/Jakarta",
    "iso:country":"ID",
    "name:ind_x_preferred":[
        "Gondang Kidul"
    ],
    "wof:name":"Gondang Kidul",
    "wof:placetype":"locality"
},
  "geometry": {"coordinates":[112.94459999999999,-7.7438],"type":"Point"}
}