{
  "type": "Feature",
  "properties": {
    "gn:admin1_code":"18",
    "gn:asciiname":"Kanganara",
    "gn:country_code":"ID",
    "gn:dem":747,
    "gn:feature_class":"P",
    "gn:feature_code":"PPLA4",
    "gn:name":"Kanganara",
    "gn:population":0,
    "gn:timezone":"Asia/Makassar",
    "iso:country":"ID",
    "name:ind_x_preferred":[
        "Kanganara"
    ],
    "wof:lang_x_official":[
        "ind"
    ],
    "wof:lang_x_spoken":[
        "ind",
        "eng"
    ],
    "wof:name":"Kanganara",
    "wof:placetype":"locality"
},
  "geometry": {"coordinates":[121.8411,-8.6237],"type":"Point"}
}