{
  "type": "Feature",
  "properties": {
    "gn:admin1_code":"18.0",
    "gn:asciiname":"Waling",
    "gn:country_code":"ID",
    "gn:dem":1208,
    "gn:feature_class":"P",
    "gn:feature_code":"PPLA4",
    "gn:name":"Waling",
    "gn:population":0,
    "gn:timezone":"Asia/Makassar",
    "iso:country":"ID",
    "name:ind_x_preferred":[
        "Waling"
    ],
    "wof:name":"Waling",
    "wof:placetype":"locality"
},
  "geometry": {"coordinates":[120.6378,-8.6466],"type":"Point"}
}