{
  "type": "Feature",
  "properties": {
    "gn:admin1_code":"18.0",
    "gn:asciiname":"Waling",
    "gn:country_code":"ID",
    "gn:dem":1208,
    "gn:feature_class":"P",
    "gn:feature_code":"PPLA4",
    "gn:name":"Waling",
    "gn:population":0,
    "gn:timezone":"Asia/Makassar",
    "iso:country":"ID",
    "name:deu_x_preferred":[
        "Waling"
    ],
    "name:hin_x_preferred":[
        "\u0935\u093e\u0932\u093f\u0919 \u0928\u0917\u0930\u092a\u093e\u0932\u093f\u0915\u093e"
    ],
    "name:ind_x_preferred":[
        "Waling"
    ],
    "name:mai_x_preferred":[
        "\u0935\u093e\u0932\u093f\u0919 \u0928\u0917\u0930\u092a\u093e\u0932\u093f\u0915\u093e"
    ],
    "name:msa_x_preferred":[
        "Waling"
    ],
    "name:nep_x_preferred":[
        "\u0935\u093e\u0932\u093f\u0919 \u0928\u0917\u0930\u092a\u093e\u0932\u093f\u0915\u093e"
    ],
    "name:new_x_preferred":[
        "\u0935\u093e\u0932\u093f\u0919 \u0928\u0917\u0930\u092a\u093e\u0932\u093f\u0915\u093e"
    ],
    "name:pol_x_preferred":[
        "Waling"
    ],
    "name:urd_x_preferred":[
        "\u0648\u0627\u0644\u0646\u06af"
    ],
    "name:zho_x_preferred":[
        "\u6c83\u6797\u683c"
    ],
    "wof:lang_x_official":[
        "ind"
    ],
    "wof:lang_x_spoken":[
        "ind",
        "eng"
    ],
    "wof:name":"Waling",
    "wof:placetype":"locality"
},
  "geometry": {"coordinates":[120.6378,-8.6466],"type":"Point"}
}