{
  "type": "Feature",
  "properties": {
    "gn:admin1_code":"5.0",
    "gn:asciiname":"Pondoklintang",
    "gn:country_code":"ID",
    "gn:dem":1519,
    "gn:feature_class":"P",
    "gn:feature_code":"PPL",
    "gn:name":"Pondoklintang",
    "gn:population":0,
    "gn:timezone":"Asia/Jakarta",
    "iso:country":"ID",
    "name:ind_x_preferred":[
        "Pondoklintang"
    ],
    "wof:name":"Pondoklintang",
    "wof:placetype":"locality"
},
  "geometry": {"coordinates":[101.2667,-1.7937],"type":"Point"}
}