{
  "type": "Feature",
  "properties": {
    "gn:admin1_code":"30.0",
    "gn:asciiname":"Cipipisan",
    "gn:country_code":"ID",
    "gn:dem":788,
    "gn:feature_class":"P",
    "gn:feature_code":"PPL",
    "gn:name":"Cipipisan",
    "gn:population":0,
    "gn:timezone":"Asia/Jakarta",
    "iso:country":"ID",
    "name:ind_x_preferred":[
        "Cipipisan"
    ],
    "name:und_x_variant":[
        "Tjipipisan"
    ],
    "wof:lang_x_official":[
        "ind"
    ],
    "wof:lang_x_spoken":[
        "ind",
        "eng"
    ],
    "wof:name":"Cipipisan",
    "wof:placetype":"locality"
},
  "geometry": {"coordinates":[108.4131,-7.0583],"type":"Point"}
}