{
  "type": "Feature",
  "properties": {
    "gn:admin1_code":"30.0",
    "gn:asciiname":"Sindangrasa",
    "gn:country_code":"ID",
    "gn:dem":286,
    "gn:feature_class":"P",
    "gn:feature_code":"PPL",
    "gn:name":"Sindangrasa",
    "gn:population":0,
    "gn:timezone":"Asia/Jakarta",
    "iso:country":"ID",
    "name:ind_x_preferred":[
        "Sindangrasa"
    ],
    "wof:name":"Sindangrasa",
    "wof:placetype":"locality"
},
  "geometry": {"coordinates":[108.1091,-7.5991],"type":"Point"}
}