{
  "type": "Feature",
  "properties": {
    "gn:admin1_code":"24.0",
    "gn:asciiname":"Pinang",
    "gn:country_code":"ID",
    "gn:dem":176,
    "gn:feature_class":"P",
    "gn:feature_code":"PPL",
    "gn:name":"Pinang",
    "gn:population":0,
    "gn:timezone":"Asia/Jakarta",
    "iso:country":"ID",
    "name:ceb_x_preferred":[
        "Pinang"
    ],
    "name:ind_x_preferred":[
        "Pinang"
    ],
    "name:msa_x_preferred":[
        "Pinang"
    ],
    "name:swe_x_preferred":[
        "Pinang"
    ],
    "wof:lang_x_official":[
        "ind"
    ],
    "wof:lang_x_spoken":[
        "ind",
        "eng"
    ],
    "wof:name":"Pinang",
    "wof:placetype":"locality"
},
  "geometry": {"coordinates":[101.03879999999999,-0.552],"type":"Point"}
}