{
  "type": "Feature",
  "properties": {
    "gn:admin1_code":"8.0",
    "gn:asciiname":"Menangas Wetan",
    "gn:country_code":"ID",
    "gn:dem":22,
    "gn:feature_class":"P",
    "gn:feature_code":"PPL",
    "gn:name":"Menangas Wetan",
    "gn:population":0,
    "gn:timezone":"Asia/Jakarta",
    "iso:country":"ID",
    "name:ind_x_preferred":[
        "Menangas Wetan"
    ],
    "wof:name":"Menangas Wetan",
    "wof:placetype":"locality"
},
  "geometry": {"coordinates":[112.977,-7.7379],"type":"Point"}
}