{
  "type": "Feature",
  "properties": {
    "gn:admin1_code":"11",
    "gn:asciiname":"Permata Dua",
    "gn:country_code":"ID",
    "gn:dem":1,
    "gn:feature_class":"P",
    "gn:feature_code":"PPL",
    "gn:name":"Permata Dua",
    "gn:population":0,
    "gn:timezone":"Asia/Pontianak",
    "iso:country":"ID",
    "name:ind_x_preferred":[
        "Permata Dua"
    ],
    "wof:name":"Permata Dua",
    "wof:placetype":"locality"
},
  "geometry": {"coordinates":[109.63249999999999,-0.37285],"type":"Point"}
}