{
  "type": "Feature",
  "properties": {
    "gn:admin1_code":"30.0",
    "gn:asciiname":"Barurapei",
    "gn:country_code":"ID",
    "gn:dem":873,
    "gn:feature_class":"P",
    "gn:feature_code":"PPL",
    "gn:name":"Barurapei",
    "gn:population":0,
    "gn:timezone":"Asia/Jakarta",
    "iso:country":"ID",
    "name:ind_x_preferred":[
        "Barurapei"
    ],
    "wof:name":"Barurapei",
    "wof:placetype":"locality"
},
  "geometry": {"coordinates":[107.09139999999999,-7.1035],"type":"Point"}
}