{
  "type": "Feature",
  "properties": {
    "gn:admin1_code":"7.0",
    "gn:asciiname":"Dadapan",
    "gn:country_code":"ID",
    "gn:dem":1303,
    "gn:feature_class":"P",
    "gn:feature_code":"PPL",
    "gn:name":"Dadapan",
    "gn:population":0,
    "gn:timezone":"Asia/Jakarta",
    "iso:country":"ID",
    "wof:name":"Dadapan",
    "wof:placetype":"locality"
},
  "geometry": {"coordinates":[110.10778000000001,-7.41694],"type":"Point"}
}