{
  "type": "Feature",
  "properties": {
    "gn:admin1_code":"17",
    "gn:asciiname":"Seraya",
    "gn:country_code":"ID",
    "gn:dem":300,
    "gn:feature_class":"P",
    "gn:feature_code":"PPL",
    "gn:name":"Seraya",
    "gn:population":0,
    "gn:timezone":"Asia/Makassar",
    "iso:country":"ID",
    "name:ara_x_preferred":[
        "\u0633\u064a\u0631\u0627\u064a\u0627"
    ],
    "name:ara_x_variant":[
        "\u0633\u0631\u0627\u064a\u0627 \u0627\u0644\u0646\u0627\u0635\u0631\u0629"
    ],
    "name:ben_x_preferred":[
        "\u09b8\u09c7\u09b0\u09be\u09af\u09bc\u09be"
    ],
    "name:deu_x_preferred":[
        "Seraya"
    ],
    "name:ell_x_preferred":[
        "\u03a3\u03b5\u03c1\u03ac\u03b3\u03b9\u03b1"
    ],
    "name:eng_x_preferred":[
        "Mount Seraya"
    ],
    "name:fas_x_preferred":[
        "\u0633\u0631\u0627\u06cc\u0627"
    ],
    "name:fra_x_preferred":[
        "Seraya"
    ],
    "name:heb_x_preferred":[
        "\u05e1\u05e8\u05d0\u05d9\u05d4"
    ],
    "name:hin_x_preferred":[
        "\u0938\u0947\u0930\u093e\u092f\u093e"
    ],
    "name:hun_x_preferred":[
        "Seraya"
    ],
    "name:ind_x_preferred":[
        "Seraya"
    ],
    "name:ita_x_preferred":[
        "Seraya"
    ],
    "name:jpn_x_preferred":[
        "\u30bb\u30e9\u30e4"
    ],
    "name:kor_x_preferred":[
        "\uc138\ub77c\uc57c"
    ],
    "name:nld_x_preferred":[
        "Seno Otway"
    ],
    "name:pol_x_preferred":[
        "Seraya"
    ],
    "name:por_x_preferred":[
        "Seraya"
    ],
    "name:rus_x_preferred":[
        "\u0433\u043e\u0440\u0430 \u0421\u0435\u0440\u0430\u044f"
    ],
    "name:spa_x_preferred":[
        "Seraya"
    ],
    "name:swe_x_preferred":[
        "Seraya"
    ],
    "name:tur_x_preferred":[
        "Seraya"
    ],
    "name:ukr_x_preferred":[
        "\u0421\u0435\u0440\u0430\u044f"
    ],
    "name:urd_x_preferred":[
        "\u0633\u06cc\u0631\u0627\u06cc\u0627"
    ],
    "name:vie_x_preferred":[
        "N\u00fai Seraya"
    ],
    "name:zho_cn_x_preferred":[
        "\u585e\u62c9\u4e9a\u5c71"
    ],
    "name:zho_tw_x_preferred":[
        "\u585e\u62c9\u4e9e\u5c71"
    ],
    "wof:lang_x_official":[
        "ind"
    ],
    "wof:lang_x_spoken":[
        "ind",
        "eng"
    ],
    "wof:name":"Seraya",
    "wof:placetype":"locality"
},
  "geometry": {"coordinates":[116.1636,-8.526],"type":"Point"}
}