{
  "type": "Feature",
  "properties": {
    "gn:admin1_code":"17",
    "gn:asciiname":"Seraya",
    "gn:country_code":"ID",
    "gn:dem":300,
    "gn:feature_class":"P",
    "gn:feature_code":"PPL",
    "gn:name":"Seraya",
    "gn:population":0,
    "gn:timezone":"Asia/Makassar",
    "iso:country":"ID",
    "name:ara_x_preferred":[
        "\u0633\u0631\u0627\u064a\u0627 \u0627\u0644\u0646\u0627\u0635\u0631\u0629"
    ],
    "name:ind_x_preferred":[
        "Seraya"
    ],
    "wof:lang_x_official":[
        "ind"
    ],
    "wof:lang_x_spoken":[
        "ind",
        "eng"
    ],
    "wof:name":"Seraya",
    "wof:placetype":"locality"
},
  "geometry": {"coordinates":[116.1636,-8.526],"type":"Point"}
}