{
  "type": "Feature",
  "properties": {
    "gn:admin1_code":"1.0",
    "gn:asciiname":"Linggi",
    "gn:country_code":"ID",
    "gn:dem":3,
    "gn:feature_class":"P",
    "gn:feature_code":"PPL",
    "gn:name":"Linggi",
    "gn:population":0,
    "gn:timezone":"Asia/Jakarta",
    "iso:country":"ID",
    "name:epo_x_preferred":[
        "Linggi"
    ],
    "name:ind_x_preferred":[
        "Linggi"
    ],
    "name:msa_x_preferred":[
        "Linggi"
    ],
    "wof:name":"Linggi",
    "wof:placetype":"locality"
},
  "geometry": {"coordinates":[96.3464,2.5169],"type":"Point"}
}