{
  "type": "Feature",
  "properties": {
    "gn:admin1_code":"22.0",
    "gn:asciiname":"Lemboea Dua",
    "gn:country_code":"ID",
    "gn:dem":7,
    "gn:feature_class":"P",
    "gn:feature_code":"PPL",
    "gn:name":"Lemboea Dua",
    "gn:population":0,
    "gn:timezone":"Asia/Makassar",
    "iso:country":"ID",
    "name:ind_x_preferred":[
        "Lemboea Dua"
    ],
    "name:und_x_variant":[
        "Lemboea 2"
    ],
    "wof:lang_x_official":[
        "ind"
    ],
    "wof:lang_x_spoken":[
        "ind",
        "eng"
    ],
    "wof:name":"Lemboea Dua",
    "wof:placetype":"locality"
},
  "geometry": {"coordinates":[121.7822,-4.7902],"type":"Point"}
}