{
  "type": "Feature",
  "properties": {
    "gn:admin1_code":"3.0",
    "gn:asciiname":"Padanggulaktanjung",
    "gn:country_code":"ID",
    "gn:dem":143,
    "gn:feature_class":"P",
    "gn:feature_code":"PPL",
    "gn:name":"Padanggulaktanjung",
    "gn:population":0,
    "gn:timezone":"Asia/Jakarta",
    "iso:country":"ID",
    "name:ind_x_preferred":[
        "Padanggulaktanjung"
    ],
    "wof:name":"Padanggulaktanjung",
    "wof:placetype":"locality"
},
  "geometry": {"coordinates":[102.41630000000001,-3.8486],"type":"Point"}
}