{
  "type": "Feature",
  "properties": {
    "gn:country":"ID",
    "gn:fcode":"PPLA3",
    "gn:pop":0,
    "iso:country":"ID",
    "name:ind_x_preferred":[
        "Cibeureum"
    ],
    "name:unk_x_variant":[
        "Tjibeureum"
    ],
    "qs:name":"Cibeureum",
    "qs:photos_9r":0,
    "qs:photos_sr":0,
    "qs:pop_sr":"0",
    "wof:name":"Cibeureum",
    "wof:placetype":"locality",
    "wof:population":0
},
  "geometry": {"coordinates":[108.2693,-7.3552],"type":"Point"}
}