{
  "type": "Feature",
  "properties": {
    "gn:admin1_code":"38",
    "gn:asciiname":"Ballacamba",
    "gn:country_code":"ID",
    "gn:dem":576,
    "gn:feature_class":"P",
    "gn:feature_code":"PPL",
    "gn:name":"Ballacamba",
    "gn:population":0,
    "gn:timezone":"Asia/Makassar",
    "iso:country":"ID",
    "name:ind_x_preferred":[
        "Ballacamba"
    ],
    "wof:name":"Ballacamba",
    "wof:placetype":"locality"
},
  "geometry": {"coordinates":[119.8456,-5.2243],"type":"Point"}
}