{
  "type": "Feature",
  "properties": {
    "gn:admin1_code":"8",
    "gn:asciiname":"Jetak",
    "gn:country_code":"ID",
    "gn:dem":916,
    "gn:feature_class":"P",
    "gn:feature_code":"PPL",
    "gn:name":"Jetak",
    "gn:population":0,
    "gn:timezone":"Asia/Jakarta",
    "iso:country":"ID",
    "name:ind_x_preferred":[
        "Jetak"
    ],
    "wof:name":"Jetak",
    "wof:placetype":"locality"
},
  "geometry": {"coordinates":[111.13333,-7.99778],"type":"Point"}
}