{
  "type": "Feature",
  "properties": {
    "gn:admin1_code":"1.0",
    "gn:asciiname":"Lawe Parbunga",
    "gn:country_code":"ID",
    "gn:dem":227,
    "gn:feature_class":"P",
    "gn:feature_code":"PPL",
    "gn:name":"Lawe Parbunga",
    "gn:population":0,
    "gn:timezone":"Asia/Jakarta",
    "iso:country":"ID",
    "name:ind_x_preferred":[
        "Lawe Parbunga"
    ],
    "wof:name":"Lawe Parbunga",
    "wof:placetype":"locality"
},
  "geometry": {"coordinates":[97.95451,3.31778],"type":"Point"}
}