{
  "type": "Feature",
  "properties": {
    "gn:admin1_code":"30.0",
    "gn:asciiname":"Kalapanunggal",
    "gn:country_code":"ID",
    "gn:dem":347,
    "gn:feature_class":"P",
    "gn:feature_code":"PPLA4",
    "gn:name":"Kalapanunggal",
    "gn:population":0,
    "gn:timezone":"Asia/Jakarta",
    "iso:country":"ID",
    "name:ind_x_preferred":[
        "Kalapanunggal"
    ],
    "wof:lang_x_official":[
        "ind"
    ],
    "wof:lang_x_spoken":[
        "ind",
        "eng"
    ],
    "wof:name":"Kalapanunggal",
    "wof:placetype":"locality"
},
  "geometry": {"coordinates":[107.0047,-7.2146],"type":"Point"}
}