{
  "type": "Feature",
  "properties": {
    "gn:admin1_code":"2",
    "gn:asciiname":"Banjar Babakan",
    "gn:country_code":"ID",
    "gn:dem":141,
    "gn:feature_class":"P",
    "gn:feature_code":"PPL",
    "gn:name":"Banjar Babakan",
    "gn:population":0,
    "gn:timezone":"Asia/Makassar",
    "iso:country":"ID",
    "name:ind_x_preferred":[
        "Banjar Babakan"
    ],
    "name:und_x_variant":[
        "Babakan"
    ],
    "wof:name":"Banjar Babakan",
    "wof:placetype":"locality"
},
  "geometry": {"coordinates":[115.04300000000001,-8.4981],"type":"Point"}
}