{
  "type": "Feature",
  "properties": {
    "gn:admin1_code":"8",
    "gn:asciiname":"Ciliwung",
    "gn:country_code":"ID",
    "gn:dem":458,
    "gn:feature_class":"P",
    "gn:feature_code":"PPL",
    "gn:name":"Ciliwung",
    "gn:population":0,
    "gn:timezone":"Asia/Jakarta",
    "iso:country":"ID",
    "name:deu_x_preferred":[
        "Ciliwung"
    ],
    "name:fin_x_preferred":[
        "Ciliwung"
    ],
    "name:fra_x_preferred":[
        "Ciliwung"
    ],
    "name:ind_x_preferred":[
        "Ciliwung"
    ],
    "name:ind_x_variant":[
        "Ci Liwung"
    ],
    "name:jav_x_preferred":[
        "Kali Ciliwung"
    ],
    "name:khm_x_preferred":[
        "\u179f\u17d2\u1791\u17b9\u1784\u179f\u17ca\u17b8\u179b\u17b8\u179c\u17bc\u1784"
    ],
    "name:msa_x_preferred":[
        "Sungai Ciliwung"
    ],
    "name:nld_x_preferred":[
        "Ciliwung"
    ],
    "name:nor_x_preferred":[
        "Ciliwung"
    ],
    "name:pol_x_preferred":[
        "Ciliwung"
    ],
    "name:rus_x_preferred":[
        "\u0427\u0438\u043b\u0438\u0432\u0443\u043d\u0433"
    ],
    "name:sun_x_preferred":[
        "Walungan Ciliwung"
    ],
    "name:ukr_x_preferred":[
        "\u0427\u0438\u043b\u0456\u0432\u0443\u043d\u0433"
    ],
    "name:vie_x_preferred":[
        "S\u00f4ng Ciliwung"
    ],
    "name:zho_x_preferred":[
        "\u829d\u5229\u7fc1\u6cb3"
    ],
    "wof:lang_x_official":[
        "ind"
    ],
    "wof:lang_x_spoken":[
        "ind",
        "eng"
    ],
    "wof:name":"Ciliwung",
    "wof:placetype":"locality"
},
  "geometry": {"coordinates":[112.6414,-7.9547],"type":"Point"}
}