{
  "type": "Feature",
  "properties": {
    "gn:admin1_code":"7",
    "gn:asciiname":"Mbakmati",
    "gn:country_code":"ID",
    "gn:dem":4,
    "gn:feature_class":"P",
    "gn:feature_code":"PPL",
    "gn:name":"Mbakmati",
    "gn:population":0,
    "gn:timezone":"Asia/Jakarta",
    "iso:country":"ID",
    "name:ind_x_preferred":[
        "Mbakmati"
    ],
    "wof:name":"Mbakmati",
    "wof:placetype":"locality"
},
  "geometry": {"coordinates":[110.7145,-6.4686],"type":"Point"}
}