{
  "type": "Feature",
  "properties": {
    "gn:admin1_code":"8.0",
    "gn:asciiname":"Gringging Lor",
    "gn:country_code":"ID",
    "gn:dem":77,
    "gn:feature_class":"P",
    "gn:feature_code":"PPL",
    "gn:name":"Gringging Lor",
    "gn:population":0,
    "gn:timezone":"Asia/Jakarta",
    "iso:country":"ID",
    "name:ind_x_preferred":[
        "Gringging Lor"
    ],
    "wof:name":"Gringging Lor",
    "wof:placetype":"locality"
},
  "geometry": {"coordinates":[111.9614,-7.7435],"type":"Point"}
}