{
  "type": "Feature",
  "properties": {
    "gn:admin1_code":"30.0",
    "gn:asciiname":"Tegallega",
    "gn:country_code":"ID",
    "gn:dem":1021,
    "gn:feature_class":"P",
    "gn:feature_code":"PPL",
    "gn:name":"Tegallega",
    "gn:population":0,
    "gn:timezone":"Asia/Jakarta",
    "iso:country":"ID",
    "name:ind_x_preferred":[
        "Tegallega"
    ],
    "name:und_x_variant":[
        "Tegallega Dua"
    ],
    "wof:lang_x_official":[
        "ind"
    ],
    "wof:lang_x_spoken":[
        "ind",
        "eng"
    ],
    "wof:name":"Tegallega",
    "wof:placetype":"locality"
},
  "geometry": {"coordinates":[107.2109,-7.0739],"type":"Point"}
}