{
  "type": "Feature",
  "properties": {
    "gn:admin1_code":"8",
    "gn:asciiname":"Bere Jalan",
    "gn:country_code":"ID",
    "gn:dem":469,
    "gn:feature_class":"P",
    "gn:feature_code":"PPL",
    "gn:name":"Bere Jalan",
    "gn:population":0,
    "gn:timezone":"Asia/Jakarta",
    "iso:country":"ID",
    "name:ind_x_preferred":[
        "Bere Jalan"
    ],
    "wof:name":"Bere Jalan",
    "wof:placetype":"locality"
},
  "geometry": {"coordinates":[113.7432,-7.8391],"type":"Point"}
}