{
  "type": "Feature",
  "properties": {
    "gn:admin1_code":"38",
    "gn:asciiname":"Lamaniang",
    "gn:country_code":"ID",
    "gn:dem":246,
    "gn:feature_class":"P",
    "gn:feature_code":"PPL",
    "gn:name":"Lamaniang",
    "gn:population":0,
    "gn:timezone":"Asia/Makassar",
    "iso:country":"ID",
    "name:ind_x_preferred":[
        "Lamaniang"
    ],
    "wof:name":"Lamaniang",
    "wof:placetype":"locality"
},
  "geometry": {"coordinates":[119.71339999999999,-4.2874],"type":"Point"}
}