{
  "type": "Feature",
  "properties": {
    "gn:admin1_code":"7",
    "gn:asciiname":"Suwang",
    "gn:country_code":"ID",
    "gn:dem":171,
    "gn:feature_class":"P",
    "gn:feature_code":"PPL",
    "gn:name":"Suwang",
    "gn:population":0,
    "gn:timezone":"Asia/Jakarta",
    "iso:country":"ID",
    "name:ind_x_preferred":[
        "Suwang"
    ],
    "wof:name":"Suwang",
    "wof:placetype":"locality"
},
  "geometry": {"coordinates":[110.7774,-6.6562],"type":"Point"}
}