{
  "type": "Feature",
  "properties": {
    "gn:admin1_code":"38",
    "gn:asciiname":"Puderebbae",
    "gn:country_code":"ID",
    "gn:dem":180,
    "gn:feature_class":"P",
    "gn:feature_code":"PPL",
    "gn:name":"Puderebbae",
    "gn:population":0,
    "gn:timezone":"Asia/Makassar",
    "iso:country":"ID",
    "name:ind_x_preferred":[
        "Puderebbae"
    ],
    "wof:lang_x_official":[
        "ind"
    ],
    "wof:lang_x_spoken":[
        "ind",
        "eng"
    ],
    "wof:name":"Puderebbae",
    "wof:placetype":"locality"
},
  "geometry": {"coordinates":[120.1396,-4.4343],"type":"Point"}
}