{
  "type": "Feature",
  "properties": {
    "gn:admin1_code":"30.0",
    "gn:asciiname":"Cimanggu",
    "gn:country_code":"ID",
    "gn:dem":535,
    "gn:feature_class":"P",
    "gn:feature_code":"PPL",
    "gn:name":"Cimanggu",
    "gn:population":0,
    "gn:timezone":"Asia/Jakarta",
    "iso:country":"ID",
    "name:ind_x_preferred":[
        "Cimanggu"
    ],
    "wof:name":"Cimanggu",
    "wof:placetype":"locality"
},
  "geometry": {"coordinates":[107.23999999999999,-7.352],"type":"Point"}
}