{
  "type": "Feature",
  "properties": {
    "gn:admin1_code":"15.0",
    "gn:asciiname":"Margajaya Dua",
    "gn:country_code":"ID",
    "gn:dem":397,
    "gn:feature_class":"P",
    "gn:feature_code":"PPL",
    "gn:name":"Margajaya Dua",
    "gn:population":0,
    "gn:timezone":"Asia/Jakarta",
    "iso:country":"ID",
    "name:ind_x_preferred":[
        "Margajaya Dua"
    ],
    "name:und_x_variant":[
        "Margajaya 2"
    ],
    "wof:name":"Margajaya Dua",
    "wof:placetype":"locality"
},
  "geometry": {"coordinates":[104.70592000000001,-5.08045],"type":"Point"}
}