{
  "type": "Feature",
  "properties": {
    "gn:admin1_code":"8.0",
    "gn:asciiname":"Gununglawang",
    "gn:country_code":"ID",
    "gn:dem":240,
    "gn:feature_class":"P",
    "gn:feature_code":"PPL",
    "gn:name":"Gununglawang",
    "gn:population":0,
    "gn:timezone":"Asia/Jakarta",
    "iso:country":"ID",
    "name:ind_x_preferred":[
        "Gununglawang"
    ],
    "wof:name":"Gununglawang",
    "wof:placetype":"locality"
},
  "geometry": {"coordinates":[113.2589,-7.9743],"type":"Point"}
}