{
  "type": "Feature",
  "properties": {
    "gn:admin1_code":"1",
    "gn:asciiname":"Mane",
    "gn:country_code":"ID",
    "gn:dem":17,
    "gn:feature_class":"P",
    "gn:feature_code":"PPL",
    "gn:name":"Mane",
    "gn:population":0,
    "gn:timezone":"Asia/Jakarta",
    "iso:country":"ID",
    "name:bel_x_preferred":[
        "\u041c\u0430\u043d"
    ],
    "name:bul_x_preferred":[
        "\u041c\u0430\u043d"
    ],
    "name:ceb_x_preferred":[
        "Mane"
    ],
    "name:deu_x_preferred":[
        "Mane"
    ],
    "name:fra_x_preferred":[
        "Mane"
    ],
    "name:glg_x_preferred":[
        "Mane"
    ],
    "name:ind_x_preferred":[
        "Mane"
    ],
    "name:ita_x_preferred":[
        "Mane"
    ],
    "name:nds_x_preferred":[
        "Mane"
    ],
    "name:nld_x_preferred":[
        "Mane"
    ],
    "name:pol_x_preferred":[
        "Mane"
    ],
    "name:rus_x_preferred":[
        "\u041c\u0430\u043d"
    ],
    "name:slk_x_preferred":[
        "Mane"
    ],
    "name:spa_x_preferred":[
        "Mane"
    ],
    "name:srp_x_preferred":[
        "\u041c\u0430\u043d"
    ],
    "name:swe_x_preferred":[
        "Mane"
    ],
    "name:ukr_x_preferred":[
        "\u041c\u0430\u043d"
    ],
    "name:urd_x_preferred":[
        "\u0627\u06cc\u0627\u0644"
    ],
    "wof:name":"Mane",
    "wof:placetype":"locality"
},
  "geometry": {"coordinates":[95.33110000000001,5.4801],"type":"Point"}
}