{
  "type": "Feature",
  "properties": {
    "gn:admin1_code":"1",
    "gn:asciiname":"Tani",
    "gn:country_code":"ID",
    "gn:dem":28,
    "gn:feature_class":"P",
    "gn:feature_code":"PPL",
    "gn:name":"Tani",
    "gn:population":0,
    "gn:timezone":"Asia/Jakarta",
    "iso:country":"ID",
    "name:ceb_x_preferred":[
        "Tani"
    ],
    "name:deu_x_preferred":[
        "Tani"
    ],
    "name:fin_x_preferred":[
        "Tani"
    ],
    "name:fra_x_preferred":[
        "Tani"
    ],
    "name:ind_x_preferred":[
        "Tani"
    ],
    "name:ita_x_preferred":[
        "Tani"
    ],
    "name:por_x_preferred":[
        "Tani"
    ],
    "name:swe_x_preferred":[
        "Tani"
    ],
    "wof:lang_x_official":[
        "ind"
    ],
    "wof:lang_x_spoken":[
        "ind",
        "eng"
    ],
    "wof:name":"Tani",
    "wof:placetype":"locality"
},
  "geometry": {"coordinates":[97.7727,4.8304],"type":"Point"}
}