{
  "type": "Feature",
  "properties": {
    "gn:admin1_code":"8.0",
    "gn:asciiname":"Pasar",
    "gn:country_code":"ID",
    "gn:dem":45,
    "gn:feature_class":"P",
    "gn:feature_code":"PPL",
    "gn:name":"Pasar",
    "gn:population":0,
    "gn:timezone":"Asia/Jakarta",
    "iso:country":"ID",
    "name:ceb_x_preferred":[
        "P\u0101s\u0101r"
    ],
    "name:fas_x_preferred":[
        "\u067e\u0627\u0633\u0627\u0631"
    ],
    "name:ind_x_preferred":[
        "Pasar"
    ],
    "wof:name":"Pasar",
    "wof:placetype":"locality"
},
  "geometry": {"coordinates":[113.7433,-6.905],"type":"Point"}
}