{
  "type": "Feature",
  "properties": {
    "gn:admin1_code":"7.0",
    "gn:asciiname":"Macangaeng",
    "gn:country_code":"ID",
    "gn:dem":7,
    "gn:feature_class":"P",
    "gn:feature_code":"PPL",
    "gn:name":"Macangaeng",
    "gn:population":0,
    "gn:timezone":"Asia/Jakarta",
    "iso:country":"ID",
    "name:ind_x_preferred":[
        "Macangaeng"
    ],
    "wof:name":"Macangaeng",
    "wof:placetype":"locality"
},
  "geometry": {"coordinates":[109.02249999999999,-7.70944],"type":"Point"}
}