{
  "type": "Feature",
  "properties": {
    "gn:admin1_code":"8.0",
    "gn:asciiname":"Gedangsewu Wetan",
    "gn:country_code":"ID",
    "gn:dem":153,
    "gn:feature_class":"P",
    "gn:feature_code":"PPL",
    "gn:name":"Gedangsewu Wetan",
    "gn:population":0,
    "gn:timezone":"Asia/Jakarta",
    "iso:country":"ID",
    "name:ind_x_preferred":[
        "Gedangsewu Wetan"
    ],
    "wof:name":"Gedangsewu Wetan",
    "wof:placetype":"locality"
},
  "geometry": {"coordinates":[112.19540000000001,-7.7812],"type":"Point"}
}