{
  "type": "Feature",
  "properties": {
    "gn:admin1_code":"1",
    "gn:asciiname":"Cerakceue",
    "gn:country_code":"ID",
    "gn:dem":25,
    "gn:feature_class":"P",
    "gn:feature_code":"PPL",
    "gn:name":"Cerakceue",
    "gn:population":0,
    "gn:timezone":"Asia/Jakarta",
    "iso:country":"ID",
    "name:ind_x_preferred":[
        "Cerakceue"
    ],
    "name:und_x_variant":[
        "Tjeraktjeue"
    ],
    "wof:name":"Cerakceue",
    "wof:placetype":"locality"
},
  "geometry": {"coordinates":[95.8819,4.5496],"type":"Point"}
}