{
  "type": "Feature",
  "properties": {
    "gn:admin1_code":"2",
    "gn:asciiname":"Banjar Basangalas Kawan",
    "gn:country_code":"ID",
    "gn:dem":252,
    "gn:feature_class":"P",
    "gn:feature_code":"PPL",
    "gn:name":"Banjar Basangalas Kawan",
    "gn:population":0,
    "gn:timezone":"Asia/Makassar",
    "iso:country":"ID",
    "name:ind_x_preferred":[
        "Banjar Basangalas Kawan"
    ],
    "wof:name":"Banjar Basangalas Kawan",
    "wof:placetype":"locality"
},
  "geometry": {"coordinates":[115.6204,-8.4037],"type":"Point"}
}