{
  "type": "Feature",
  "properties": {
    "gn:admin1_code":"30.0",
    "gn:asciiname":"Sirnabaru",
    "gn:country_code":"ID",
    "gn:dem":401,
    "gn:feature_class":"P",
    "gn:feature_code":"PPL",
    "gn:name":"Sirnabaru",
    "gn:population":0,
    "gn:timezone":"Asia/Jakarta",
    "iso:country":"ID",
    "name:ind_x_preferred":[
        "Sirnabaru"
    ],
    "wof:name":"Sirnabaru",
    "wof:placetype":"locality"
},
  "geometry": {"coordinates":[106.9725,-7.1938],"type":"Point"}
}