{
  "type": "Feature",
  "properties": {
    "gn:admin1_code":"30",
    "gn:asciiname":"Mekarsari",
    "gn:country_code":"ID",
    "gn:dem":856,
    "gn:feature_class":"P",
    "gn:feature_code":"PPL",
    "gn:name":"Mekarsari",
    "gn:population":0,
    "gn:timezone":"Asia/Jakarta",
    "iso:country":"ID",
    "wof:name":"Mekarsari",
    "wof:placetype":"locality"
},
  "geometry": {"coordinates":[107.66278,-7.04889],"type":"Point"}
}