{
  "type": "Feature",
  "properties": {
    "gn:admin1_code":"28.0",
    "gn:asciiname":"Wamnebu",
    "gn:country_code":"ID",
    "gn:dem":14,
    "gn:feature_class":"P",
    "gn:feature_code":"PPL",
    "gn:name":"Wamnebu",
    "gn:population":0,
    "gn:timezone":"Asia/Jayapura",
    "iso:country":"ID",
    "name:ind_x_preferred":[
        "Wamnebu"
    ],
    "name:und_x_variant":[
        "Wa \u2019Mn\u00e9boe"
    ],
    "wof:name":"Wamnebu",
    "wof:placetype":"locality"
},
  "geometry": {"coordinates":[126.59632000000001,-3.06691],"type":"Point"}
}