{
  "type": "Feature",
  "properties": {
    "gn:admin1_code":"26.0",
    "gn:asciiname":"Lumban Sahot",
    "gn:country_code":"ID",
    "gn:dem":1374,
    "gn:feature_class":"P",
    "gn:feature_code":"PPL",
    "gn:name":"Lumban Sahot",
    "gn:population":0,
    "gn:timezone":"Asia/Jakarta",
    "iso:country":"ID",
    "name:ind_x_preferred":[
        "Lumban Sahot"
    ],
    "wof:name":"Lumban Sahot",
    "wof:placetype":"locality"
},
  "geometry": {"coordinates":[98.9177,2.5283],"type":"Point"}
}