{
  "type": "Feature",
  "properties": {
    "gn:admin1_code":"7",
    "gn:asciiname":"Klampok",
    "gn:country_code":"ID",
    "gn:dem":48,
    "gn:feature_class":"P",
    "gn:feature_code":"PPL",
    "gn:name":"Klampok",
    "gn:population":0,
    "gn:timezone":"Asia/Jakarta",
    "iso:country":"ID",
    "name:ind_x_preferred":[
        "Klampok"
    ],
    "wof:name":"Klampok",
    "wof:placetype":"locality"
},
  "geometry": {"coordinates":[110.9756,-7.0075],"type":"Point"}
}