{
  "type": "Feature",
  "properties": {
    "gn:admin1_code":"30.0",
    "gn:asciiname":"Parung",
    "gn:country_code":"ID",
    "gn:dem":749,
    "gn:feature_class":"P",
    "gn:feature_code":"PPLA4",
    "gn:name":"Parung",
    "gn:population":0,
    "gn:timezone":"Asia/Jakarta",
    "iso:country":"ID",
    "name:ind_x_preferred":[
        "Parung"
    ],
    "name:und_x_variant":[
        "Paroeng"
    ],
    "wof:name":"Parung",
    "wof:placetype":"locality"
},
  "geometry": {"coordinates":[108.3984,-7.0045],"type":"Point"}
}