{
  "type": "Feature",
  "properties": {
    "gn:admin1_code":"30.0",
    "gn:asciiname":"Nyalindung",
    "gn:country_code":"ID",
    "gn:dem":910,
    "gn:feature_class":"P",
    "gn:feature_code":"PPL",
    "gn:name":"Nyalindung",
    "gn:population":0,
    "gn:timezone":"Asia/Jakarta",
    "iso:country":"ID",
    "name:ind_x_preferred":[
        "Nyalindung"
    ],
    "name:und_x_variant":[
        "Njalindung"
    ],
    "wof:name":"Nyalindung",
    "wof:placetype":"locality"
},
  "geometry": {"coordinates":[107.06111,-6.795],"type":"Point"}
}