{
  "type": "Feature",
  "properties": {
    "gn:admin1_code":"18.0",
    "gn:asciiname":"Wanobou",
    "gn:country_code":"ID",
    "gn:dem":674,
    "gn:feature_class":"P",
    "gn:feature_code":"PPL",
    "gn:name":"Wanobou",
    "gn:population":0,
    "gn:timezone":"Asia/Makassar",
    "iso:country":"ID",
    "name:ind_x_preferred":[
        "Wanobou"
    ],
    "wof:name":"Wanobou",
    "wof:placetype":"locality"
},
  "geometry": {"coordinates":[119.4032,-9.5554],"type":"Point"}
}