{
  "type": "Feature",
  "properties": {
    "gn:admin1_code":"30",
    "gn:asciiname":"Sukaati",
    "gn:country_code":"ID",
    "gn:dem":34,
    "gn:feature_class":"P",
    "gn:feature_code":"PPL",
    "gn:name":"Sukaati",
    "gn:population":0,
    "gn:timezone":"Asia/Jakarta",
    "iso:country":"ID",
    "name:ind_x_preferred":[
        "Sukaati"
    ],
    "wof:name":"Sukaati",
    "wof:placetype":"locality"
},
  "geometry": {"coordinates":[107.52139,-6.38278],"type":"Point"}
}