{
  "type": "Feature",
  "properties": {
    "gn:admin1_code":"30",
    "gn:asciiname":"Perusahaan Umum Pengarian",
    "gn:country_code":"ID",
    "gn:dem":19,
    "gn:feature_class":"P",
    "gn:feature_code":"PPL",
    "gn:name":"Perusahaan Umum Pengarian",
    "gn:population":0,
    "gn:timezone":"Asia/Jakarta",
    "iso:country":"ID",
    "name:ind_x_preferred":[
        "Perusahaan Umum Pengarian"
    ],
    "name:und_x_variant":[
        "Perumpengairan"
    ],
    "wof:name":"Perusahaan Umum Pengarian",
    "wof:placetype":"locality"
},
  "geometry": {"coordinates":[107.01944,-6.25222],"type":"Point"}
}