{
  "type": "Feature",
  "properties": {
    "gn:admin1_code":"1",
    "gn:asciiname":"Kompung Baro",
    "gn:country_code":"ID",
    "gn:dem":4,
    "gn:feature_class":"P",
    "gn:feature_code":"PPL",
    "gn:name":"Kompung Baro",
    "gn:population":0,
    "gn:timezone":"Asia/Jakarta",
    "iso:country":"ID",
    "name:ind_x_preferred":[
        "Kompung Baro"
    ],
    "wof:name":"Kompung Baro",
    "wof:placetype":"locality"
},
  "geometry": {"coordinates":[97.5282,5.0967],"type":"Point"}
}