{
  "type": "Feature",
  "properties": {
    "gn:admin1_code":"38",
    "gn:asciiname":"Balombong",
    "gn:country_code":"ID",
    "gn:dem":910,
    "gn:feature_class":"P",
    "gn:feature_code":"PPL",
    "gn:name":"Balombong",
    "gn:population":0,
    "gn:timezone":"Asia/Makassar",
    "iso:country":"ID",
    "name:ind_x_preferred":[
        "Balombong"
    ],
    "wof:name":"Balombong",
    "wof:placetype":"locality"
},
  "geometry": {"coordinates":[119.8755,-3.253],"type":"Point"}
}