{
  "type": "Feature",
  "properties": {
    "gn:admin1_code":"32.0",
    "gn:asciiname":"Telanai",
    "gn:country_code":"ID",
    "gn:dem":503,
    "gn:feature_class":"P",
    "gn:feature_code":"PPL",
    "gn:name":"Telanai",
    "gn:population":0,
    "gn:timezone":"Asia/Jakarta",
    "iso:country":"ID",
    "name:ind_x_preferred":[
        "Telanai"
    ],
    "name:und_x_variant":[
        "Talang Telanai"
    ],
    "wof:name":"Telanai",
    "wof:placetype":"locality"
},
  "geometry": {"coordinates":[103.86365000000001,-4.74614],"type":"Point"}
}