{
  "type": "Feature",
  "properties": {
    "gn:admin1_code":"7.0",
    "gn:asciiname":"Dukuhwulung",
    "gn:country_code":"ID",
    "gn:dem":101,
    "gn:feature_class":"P",
    "gn:feature_code":"PPL",
    "gn:name":"Dukuhwulung",
    "gn:population":0,
    "gn:timezone":"Asia/Jakarta",
    "iso:country":"ID",
    "name:ind_x_preferred":[
        "Dukuhwulung"
    ],
    "wof:name":"Dukuhwulung",
    "wof:placetype":"locality"
},
  "geometry": {"coordinates":[109.26806000000001,-7.40556],"type":"Point"}
}