{
  "type": "Feature",
  "properties": {
    "gn:admin1_code":"22.0",
    "gn:asciiname":"Tapupua",
    "gn:country_code":"ID",
    "gn:dem":-9999,
    "gn:feature_class":"P",
    "gn:feature_code":"PPL",
    "gn:name":"Tapupua",
    "gn:population":0,
    "gn:timezone":"Asia/Makassar",
    "iso:country":"ID",
    "name:ind_x_preferred":[
        "Tapupua"
    ],
    "wof:name":"Tapupua",
    "wof:placetype":"locality"
},
  "geometry": {"coordinates":[122.27916999999999,-3.51819],"type":"Point"}
}