{
  "type": "Feature",
  "properties": {
    "gn:admin1_code":"26.0",
    "gn:asciiname":"Sibolangit",
    "gn:country_code":"ID",
    "gn:dem":690,
    "gn:feature_class":"P",
    "gn:feature_code":"PPL",
    "gn:name":"Sibolangit",
    "gn:population":0,
    "gn:timezone":"Asia/Jakarta",
    "iso:country":"ID",
    "name:cat_x_preferred":[
        "Serdang"
    ],
    "name:ind_x_preferred":[
        "Sibolangit"
    ],
    "name:jav_x_preferred":[
        "Sibolangit"
    ],
    "name:min_x_preferred":[
        "Sibolangit"
    ],
    "name:msa_x_preferred":[
        "Sibolangit"
    ],
    "wof:lang_x_official":[
        "ind"
    ],
    "wof:lang_x_spoken":[
        "ind",
        "eng"
    ],
    "wof:name":"Sibolangit",
    "wof:placetype":"locality"
},
  "geometry": {"coordinates":[98.9676,2.8917],"type":"Point"}
}