{
  "type": "Feature",
  "properties": {
    "gn:admin1_code":"30.0",
    "gn:asciiname":"Karyanyata",
    "gn:country_code":"ID",
    "gn:dem":210,
    "gn:feature_class":"P",
    "gn:feature_code":"PPL",
    "gn:name":"Karyanyata",
    "gn:population":0,
    "gn:timezone":"Asia/Jakarta",
    "iso:country":"ID",
    "name:ind_x_preferred":[
        "Karyanyata"
    ],
    "wof:name":"Karyanyata",
    "wof:placetype":"locality"
},
  "geometry": {"coordinates":[107.0059,-7.2331],"type":"Point"}
}