{
  "type": "Feature",
  "properties": {
    "gn:admin1_code":"24",
    "gn:asciiname":"Logan Dua",
    "gn:country_code":"ID",
    "gn:dem":7,
    "gn:feature_class":"P",
    "gn:feature_code":"PPL",
    "gn:name":"Logan Dua",
    "gn:population":0,
    "gn:timezone":"Asia/Jakarta",
    "iso:country":"ID",
    "name:ind_x_preferred":[
        "Logan Dua"
    ],
    "name:und_x_variant":[
        "Logan 2"
    ],
    "wof:name":"Logan Dua",
    "wof:placetype":"locality"
},
  "geometry": {"coordinates":[100.10168,-0.55427],"type":"Point"}
}