{
  "type": "Feature",
  "properties": {
    "gn:admin1_code":"1.0",
    "gn:asciiname":"Cure",
    "gn:country_code":"ID",
    "gn:dem":8,
    "gn:feature_class":"P",
    "gn:feature_code":"PPL",
    "gn:name":"Cure",
    "gn:population":0,
    "gn:timezone":"Asia/Jakarta",
    "iso:country":"ID",
    "name:ara_x_preferred":[
        "\u0647\u062f\u0623\u0629"
    ],
    "name:deu_x_preferred":[
        "Heilmittel"
    ],
    "name:ind_x_preferred":[
        "Cure"
    ],
    "name:scn_x_preferred":[
        "Rimediu"
    ],
    "name:spa_x_preferred":[
        "Remedio"
    ],
    "name:und_x_variant":[
        "Tjure"
    ],
    "name:urd_x_preferred":[
        "\u0634\u0641\u0627"
    ],
    "wof:lang_x_official":[
        "ind"
    ],
    "wof:lang_x_spoken":[
        "ind",
        "eng"
    ],
    "wof:name":"Cure",
    "wof:placetype":"locality"
},
  "geometry": {"coordinates":[95.8366,5.508],"type":"Point"}
}