{
  "type": "Feature",
  "properties": {
    "gn:admin1_code":"2",
    "gn:asciiname":"Pangkungkunyit",
    "gn:country_code":"ID",
    "gn:dem":677,
    "gn:feature_class":"P",
    "gn:feature_code":"PPL",
    "gn:name":"Pangkungkunyit",
    "gn:population":0,
    "gn:timezone":"Asia/Makassar",
    "iso:country":"ID",
    "name:ind_x_preferred":[
        "Pangkungkunyit"
    ],
    "wof:name":"Pangkungkunyit",
    "wof:placetype":"locality"
},
  "geometry": {"coordinates":[114.94329999999999,-8.3474],"type":"Point"}
}