{
  "type": "Feature",
  "properties": {
    "gn:admin1_code":"7.0",
    "gn:asciiname":"Ngemplak",
    "gn:country_code":"ID",
    "gn:dem":366,
    "gn:feature_class":"P",
    "gn:feature_code":"PPL",
    "gn:name":"Ngemplak",
    "gn:population":0,
    "gn:timezone":"Asia/Jakarta",
    "iso:country":"ID",
    "name:und_x_variant":[
        "Emplak",
        "Ngemplak"
    ],
    "wof:name":"Ngemplak",
    "wof:placetype":"locality"
},
  "geometry": {"coordinates":[110.11611000000001,-7.5925],"type":"Point"}
}