{
  "type": "Feature",
  "properties": {
    "gn:admin1_code":"30",
    "gn:asciiname":"Cisaranten",
    "gn:country_code":"ID",
    "gn:dem":679,
    "gn:feature_class":"P",
    "gn:feature_code":"PPL",
    "gn:name":"Cisaranten",
    "gn:population":0,
    "gn:timezone":"Asia/Jakarta",
    "iso:country":"ID",
    "name:ind_x_preferred":[
        "Cisaranten"
    ],
    "name:und_x_variant":[
        "Tjisarenten",
        "Cisarenten"
    ],
    "wof:name":"Cisaranten",
    "wof:placetype":"locality"
},
  "geometry": {"coordinates":[107.68444,-6.91917],"type":"Point"}
}