{
  "type": "Feature",
  "properties": {
    "gn:admin1_code":"22.0",
    "gn:asciiname":"Langgonawe",
    "gn:country_code":"ID",
    "gn:dem":30,
    "gn:feature_class":"P",
    "gn:feature_code":"PPL",
    "gn:name":"Langgonawe",
    "gn:population":0,
    "gn:timezone":"Asia/Makassar",
    "iso:country":"ID",
    "name:ind_x_preferred":[
        "Langgonawe"
    ],
    "wof:name":"Langgonawe",
    "wof:placetype":"locality"
},
  "geometry": {"coordinates":[122.1885,-3.9441],"type":"Point"}
}