{
  "type": "Feature",
  "properties": {
    "gn:admin1_code":"0.0",
    "gn:asciiname":"Kirasai",
    "gn:country_code":"ID",
    "gn:dem":17,
    "gn:feature_class":"P",
    "gn:feature_code":"PPL",
    "gn:name":"Kirasai",
    "gn:population":0,
    "gn:timezone":"Asia/Jayapura",
    "iso:country":"ID",
    "wof:name":"Kirasai",
    "wof:placetype":"locality"
},
  "geometry": {"coordinates":[133.84999999999999,-2.06667],"type":"Point"}
}