{
  "type": "Feature",
  "properties": {
    "gn:admin1_code":"33",
    "gn:asciiname":"Pasirbuyut",
    "gn:country_code":"ID",
    "gn:dem":23,
    "gn:feature_class":"P",
    "gn:feature_code":"PPL",
    "gn:name":"Pasirbuyut",
    "gn:population":0,
    "gn:timezone":"Asia/Jakarta",
    "iso:country":"ID",
    "name:ind_x_preferred":[
        "Pasirbuyut"
    ],
    "wof:name":"Pasirbuyut",
    "wof:placetype":"locality"
},
  "geometry": {"coordinates":[106.367,-6.2814],"type":"Point"}
}