{
  "type": "Feature",
  "properties": {
    "gn:admin1_code":"10.0",
    "gn:asciiname":"Koroulon Kidul",
    "gn:country_code":"ID",
    "gn:dem":274,
    "gn:feature_class":"P",
    "gn:feature_code":"PPL",
    "gn:name":"Koroulon Kidul",
    "gn:population":0,
    "gn:timezone":"Asia/Jakarta",
    "iso:country":"ID",
    "wof:name":"Koroulon Kidul",
    "wof:placetype":"locality"
},
  "geometry": {"coordinates":[110.46528000000001,-7.69944],"type":"Point"}
}