{
  "type": "Feature",
  "properties": {
    "gn:admin1_code":"8.0",
    "gn:asciiname":"Kecubung Timur",
    "gn:country_code":"ID",
    "gn:dem":61,
    "gn:feature_class":"P",
    "gn:feature_code":"PPL",
    "gn:name":"Kecubung Timur",
    "gn:population":0,
    "gn:timezone":"Asia/Jakarta",
    "iso:country":"ID",
    "name:ind_x_preferred":[
        "Kecubung Timur"
    ],
    "wof:name":"Kecubung Timur",
    "wof:placetype":"locality"
},
  "geometry": {"coordinates":[111.9332,-7.6543],"type":"Point"}
}