{
  "type": "Feature",
  "properties": {
    "gn:admin1_code":"7.0",
    "gn:asciiname":"Karangjengkol",
    "gn:country_code":"ID",
    "gn:dem":72,
    "gn:feature_class":"P",
    "gn:feature_code":"PPL",
    "gn:name":"Karangjengkol",
    "gn:population":0,
    "gn:timezone":"Asia/Jakarta",
    "iso:country":"ID",
    "name:ind_x_preferred":[
        "Karangjengkol"
    ],
    "wof:name":"Karangjengkol",
    "wof:placetype":"locality"
},
  "geometry": {"coordinates":[109.60111000000001,-7.58639],"type":"Point"}
}