{
  "type": "Feature",
  "properties": {
    "gn:admin1_code":"36.0",
    "gn:asciiname":"Merajop",
    "gn:country_code":"ID",
    "gn:dem":96,
    "gn:feature_class":"P",
    "gn:feature_code":"PPL",
    "gn:name":"Merajop",
    "gn:population":0,
    "gn:timezone":"Asia/Jayapura",
    "iso:country":"ID",
    "name:ind_x_preferred":[
        "Merajop"
    ],
    "wof:name":"Merajop",
    "wof:placetype":"locality"
},
  "geometry": {"coordinates":[140.59371999999999,-5.64328],"type":"Point"}
}