{
  "type": "Feature",
  "properties": {
    "gn:admin1_code":"17",
    "gn:asciiname":"Mengiuh",
    "gn:country_code":"ID",
    "gn:dem":48,
    "gn:feature_class":"P",
    "gn:feature_code":"PPL",
    "gn:name":"Mengiuh",
    "gn:population":0,
    "gn:timezone":"Asia/Makassar",
    "iso:country":"ID",
    "name:ind_x_preferred":[
        "Mengiuh"
    ],
    "wof:name":"Mengiuh",
    "wof:placetype":"locality"
},
  "geometry": {"coordinates":[116.4378,-8.8087],"type":"Point"}
}