{
  "type": "Feature",
  "properties": {
    "gn:admin1_code":"30",
    "gn:asciiname":"Kamurang",
    "gn:country_code":"ID",
    "gn:dem":14,
    "gn:feature_class":"P",
    "gn:feature_code":"PPL",
    "gn:name":"Kamurang",
    "gn:population":0,
    "gn:timezone":"Asia/Jakarta",
    "iso:country":"ID",
    "name:ind_x_preferred":[
        "Kamurang"
    ],
    "wof:name":"Kamurang",
    "wof:placetype":"locality"
},
  "geometry": {"coordinates":[107.34417000000001,-6.26639],"type":"Point"}
}