{
  "type": "Feature",
  "properties": {
    "gn:admin1_code":"30",
    "gn:asciiname":"Karekhel",
    "gn:cc2":"ID",
    "gn:country_code":"ID",
    "gn:dem":73,
    "gn:feature_class":"P",
    "gn:feature_code":"PPL",
    "gn:name":"Karekhel",
    "gn:population":0,
    "gn:timezone":"Asia/Jakarta",
    "iso:country":"ID",
    "name:und_x_variant":[
        "Krikil",
        "Karekhel"
    ],
    "wof:lang_x_official":[
        "ind"
    ],
    "wof:lang_x_spoken":[
        "ind",
        "eng"
    ],
    "wof:name":"Karekhel",
    "wof:placetype":"locality"
},
  "geometry": {"coordinates":[106.60056,-6.39833],"type":"Point"}
}