{
  "type": "Feature",
  "properties": {
    "gn:admin1_code":"8.0",
    "gn:asciiname":"Prangkas",
    "gn:country_code":"ID",
    "gn:dem":662,
    "gn:feature_class":"P",
    "gn:feature_code":"PPL",
    "gn:name":"Prangkas",
    "gn:population":0,
    "gn:timezone":"Asia/Jakarta",
    "iso:country":"ID",
    "name:ind_x_preferred":[
        "Prangkas"
    ],
    "wof:name":"Prangkas",
    "wof:placetype":"locality"
},
  "geometry": {"coordinates":[112.7222,-8.2606],"type":"Point"}
}