{
  "type": "Feature",
  "properties": {
    "gn:admin1_code":"26.0",
    "gn:asciiname":"Padangmandeling",
    "gn:country_code":"ID",
    "gn:dem":854,
    "gn:feature_class":"P",
    "gn:feature_code":"PPL",
    "gn:name":"Padangmandeling",
    "gn:population":0,
    "gn:timezone":"Asia/Jakarta",
    "iso:country":"ID",
    "name:ind_x_preferred":[
        "Padangmandeling"
    ],
    "name:ind_x_variant":[
        "Padang Mandailing"
    ],
    "wof:lang_x_official":[
        "ind"
    ],
    "wof:lang_x_spoken":[
        "ind",
        "eng"
    ],
    "wof:name":"Padangmandeling",
    "wof:placetype":"locality"
},
  "geometry": {"coordinates":[99.2612,1.81627],"type":"Point"}
}