{
  "type": "Feature",
  "properties": {
    "gn:admin1_code":"26",
    "gn:asciiname":"Imana",
    "gn:country_code":"ID",
    "gn:dem":0,
    "gn:feature_class":"P",
    "gn:feature_code":"PPL",
    "gn:name":"Imana",
    "gn:population":0,
    "gn:timezone":"Asia/Jakarta",
    "iso:country":"ID",
    "name:fra_x_preferred":[
        "Imana"
    ],
    "name:ind_x_preferred":[
        "Imana"
    ],
    "name:ita_x_preferred":[
        "Imana"
    ],
    "wof:lang_x_official":[
        "ind"
    ],
    "wof:lang_x_spoken":[
        "ind",
        "eng"
    ],
    "wof:name":"Imana",
    "wof:placetype":"locality"
},
  "geometry": {"coordinates":[97.331,0.8508],"type":"Point"}
}