{
  "type": "Feature",
  "properties": {
    "gn:admin1_code":"37",
    "gn:asciiname":"Labuhanbilik",
    "gn:country_code":"ID",
    "gn:dem":10,
    "gn:feature_class":"P",
    "gn:feature_code":"PPL",
    "gn:name":"Labuhanbilik",
    "gn:population":0,
    "gn:timezone":"Asia/Jakarta",
    "iso:country":"ID",
    "name:ind_x_preferred":[
        "Labuhanbilik"
    ],
    "wof:name":"Labuhanbilik",
    "wof:placetype":"locality"
},
  "geometry": {"coordinates":[103.15761000000001,0.40384],"type":"Point"}
}