{
  "type": "Feature",
  "properties": {
    "gn:admin1_code":"30.0",
    "gn:asciiname":"Pari",
    "gn:country_code":"ID",
    "gn:dem":681,
    "gn:feature_class":"P",
    "gn:feature_code":"PPL",
    "gn:name":"Pari",
    "gn:population":0,
    "gn:timezone":"Asia/Jakarta",
    "iso:country":"ID",
    "name:ceb_x_preferred":[
        "Pari"
    ],
    "name:deu_x_preferred":[
        "Pari"
    ],
    "name:fin_x_preferred":[
        "Pari"
    ],
    "name:fra_x_preferred":[
        "Pari"
    ],
    "name:hye_x_preferred":[
        "\u0533\u0580\u0561\u0566"
    ],
    "name:ind_x_preferred":[
        "Pari"
    ],
    "name:ita_x_preferred":[
        "Pari"
    ],
    "name:rus_x_preferred":[
        "\u041f\u0430\u0440\u0438"
    ],
    "name:sco_x_preferred":[
        "Pari"
    ],
    "name:swe_x_preferred":[
        "Pari"
    ],
    "name:tgl_x_preferred":[
        "Pari"
    ],
    "name:ukr_x_preferred":[
        "\u041f\u0430\u0440\u0456"
    ],
    "wof:lang_x_official":[
        "ind"
    ],
    "wof:lang_x_spoken":[
        "ind",
        "eng"
    ],
    "wof:name":"Pari",
    "wof:placetype":"locality"
},
  "geometry": {"coordinates":[106.5702,-7.1011],"type":"Point"}
}