{
  "type": "Feature",
  "properties": {
    "gn:admin1_code":"38",
    "gn:asciiname":"Salolampe",
    "gn:country_code":"ID",
    "gn:dem":13,
    "gn:feature_class":"P",
    "gn:feature_code":"PPL",
    "gn:name":"Salolampe",
    "gn:population":0,
    "gn:timezone":"Asia/Makassar",
    "iso:country":"ID",
    "name:ind_x_preferred":[
        "Salolampe"
    ],
    "wof:name":"Salolampe",
    "wof:placetype":"locality"
},
  "geometry": {"coordinates":[119.5728,-4.7164],"type":"Point"}
}