{
  "type": "Feature",
  "properties": {
    "gn:admin1_code":"3.0",
    "gn:asciiname":"Batusiding",
    "gn:country_code":"ID",
    "gn:dem":117,
    "gn:feature_class":"P",
    "gn:feature_code":"PPL",
    "gn:name":"Batusiding",
    "gn:population":0,
    "gn:timezone":"Asia/Jakarta",
    "iso:country":"ID",
    "name:ind_x_preferred":[
        "Batusiding"
    ],
    "name:ind_x_variant":[
        "Batuniding"
    ],
    "wof:name":"Batusiding",
    "wof:placetype":"locality"
},
  "geometry": {"coordinates":[102.95742,-4.36181],"type":"Point"}
}