{
  "type": "Feature",
  "properties": {
    "gn:admin1_code":"30",
    "gn:asciiname":"Carangpulang Kaler",
    "gn:country_code":"ID",
    "gn:dem":159,
    "gn:feature_class":"P",
    "gn:feature_code":"PPL",
    "gn:name":"Carangpulang Kaler",
    "gn:population":0,
    "gn:timezone":"Asia/Jakarta",
    "iso:country":"ID",
    "name:ind_x_preferred":[
        "Carangpulang Kaler"
    ],
    "wof:name":"Carangpulang Kaler",
    "wof:placetype":"locality"
},
  "geometry": {"coordinates":[106.72499999999999,-6.54139],"type":"Point"}
}