{
  "type": "Feature",
  "properties": {
    "gn:country":"ID",
    "gn:fcode":"PPL",
    "gn:pop":154234,
    "iso:country":"ID",
    "name:unk_x_variant":[
        "Pasarkemis"
    ],
    "qs:name":"Pasar Kemis",
    "qs:name_adm0":"Indonesia",
    "qs:name_adm1":"Banten",
    "qs:photos_9r":0,
    "qs:photos_sr":0,
    "qs:placetype":"Town",
    "qs:pop_sr":"9",
    "wof:name":"Pasar Kemis",
    "wof:placetype":"locality",
    "wof:population":154234
},
  "geometry": {"coordinates":[106.53028,-6.17028],"type":"Point"}
}