{
  "type": "Feature",
  "properties": {
    "gn:admin1_code":"17",
    "gn:asciiname":"Gili Air",
    "gn:country_code":"ID",
    "gn:dem":11,
    "gn:feature_class":"P",
    "gn:feature_code":"PPL",
    "gn:name":"Gili Air",
    "gn:population":1800,
    "gn:timezone":"Asia/Makassar",
    "iso:country":"ID",
    "name:fra_x_preferred":[
        "Gili Air"
    ],
    "name:rus_x_preferred":[
        "\u0413\u0438\u043b\u0438 \u042d\u0439\u0440"
    ],
    "name:und_x_variant":[
        "gili air"
    ],
    "wof:name":"Gili Air",
    "wof:placetype":"locality",
    "wof:population":1800
},
  "geometry": {"coordinates":[116.08240000000001,-8.35783],"type":"Point"}
}