{
  "type": "Feature",
  "properties": {
    "gn:admin1_code":"7",
    "gn:asciiname":"Bayanan",
    "gn:country_code":"ID",
    "gn:dem":271,
    "gn:feature_class":"P",
    "gn:feature_code":"PPL",
    "gn:name":"Bayanan",
    "gn:population":0,
    "gn:timezone":"Asia/Jakarta",
    "iso:country":"ID",
    "name:ind_x_preferred":[
        "Bayanan"
    ],
    "name:por_x_preferred":[
        "Bayanan"
    ],
    "wof:name":"Bayanan",
    "wof:placetype":"locality"
},
  "geometry": {"coordinates":[111.12111000000002,-7.50667],"type":"Point"}
}