{
  "type": "Feature",
  "properties": {
    "gn:admin1_code":"18",
    "gn:asciiname":"Numbabesar",
    "gn:country_code":"ID",
    "gn:dem":20,
    "gn:feature_class":"P",
    "gn:feature_code":"PPL",
    "gn:name":"Numbabesar",
    "gn:population":0,
    "gn:timezone":"Asia/Makassar",
    "iso:country":"ID",
    "name:ind_x_preferred":[
        "Numbabesar"
    ],
    "wof:name":"Numbabesar",
    "wof:placetype":"locality"
},
  "geometry": {"coordinates":[121.53230000000001,-8.8067],"type":"Point"}
}