{
  "type": "Feature",
  "properties": {
    "gn:admin1_code":"30.0",
    "gn:asciiname":"Jayaraga Kaler",
    "gn:country_code":"ID",
    "gn:dem":713,
    "gn:feature_class":"P",
    "gn:feature_code":"PPLA4",
    "gn:name":"Jayaraga Kaler",
    "gn:population":0,
    "gn:timezone":"Asia/Jakarta",
    "iso:country":"ID",
    "name:ind_x_preferred":[
        "Jayaraga Kaler"
    ],
    "wof:lang_x_official":[
        "ind"
    ],
    "wof:lang_x_spoken":[
        "ind",
        "eng"
    ],
    "wof:name":"Jayaraga Kaler",
    "wof:placetype":"locality"
},
  "geometry": {"coordinates":[107.9004,-7.2043],"type":"Point"}
}