{
  "type": "Feature",
  "properties": {
    "gn:admin1_code":"30.0",
    "gn:asciiname":"Cibitung",
    "gn:country_code":"ID",
    "gn:dem":744,
    "gn:feature_class":"P",
    "gn:feature_code":"PPL",
    "gn:name":"Cibitung",
    "gn:population":0,
    "gn:timezone":"Asia/Jakarta",
    "iso:country":"ID",
    "name:ind_x_preferred":[
        "Cibitung"
    ],
    "name:und_x_variant":[
        "Tjibitoeng 4"
    ],
    "wof:name":"Cibitung",
    "wof:placetype":"locality"
},
  "geometry": {"coordinates":[108.06189999999999,-7.0728],"type":"Point"}
}