{
  "type": "Feature",
  "properties": {
    "gn:admin1_code":"07",
    "gn:asciiname":"Seloggring",
    "gn:country_code":"ID",
    "gn:dem":298,
    "gn:feature_class":"P",
    "gn:feature_code":"PPL",
    "gn:name":"Seloggring",
    "gn:population":0,
    "gn:timezone":"Asia/Jakarta",
    "iso:country":"ID",
    "wof:name":"Seloggring",
    "wof:placetype":"locality"
},
  "geometry": {"coordinates":[110.61888999999999,-7.5925],"type":"Point"}
}