{
  "type": "Feature",
  "properties": {
    "gn:admin1_code":"7",
    "gn:asciiname":"Kendilwesi",
    "gn:country_code":"ID",
    "gn:dem":861,
    "gn:feature_class":"P",
    "gn:feature_code":"PPL",
    "gn:name":"Kendilwesi",
    "gn:population":0,
    "gn:timezone":"Asia/Jakarta",
    "iso:country":"ID",
    "name:ind_x_preferred":[
        "Kendilwesi"
    ],
    "wof:name":"Kendilwesi",
    "wof:placetype":"locality"
},
  "geometry": {"coordinates":[109.565,-7.23528],"type":"Point"}
}