{
  "type": "Feature",
  "properties": {
    "gn:admin1_code":"15.0",
    "gn:asciiname":"Semancung",
    "gn:country_code":"ID",
    "gn:dem":174,
    "gn:feature_class":"P",
    "gn:feature_code":"PPL",
    "gn:name":"Semancung",
    "gn:population":0,
    "gn:timezone":"Asia/Jakarta",
    "iso:country":"ID",
    "name:ind_x_preferred":[
        "Semancung"
    ],
    "wof:name":"Semancung",
    "wof:placetype":"locality"
},
  "geometry": {"coordinates":[104.59923000000001,-4.75648],"type":"Point"}
}