{
  "type": "Feature",
  "properties": {
    "gn:admin1_code":"7.0",
    "gn:asciiname":"Wareng",
    "gn:country_code":"ID",
    "gn:dem":288,
    "gn:feature_class":"P",
    "gn:feature_code":"PPL",
    "gn:name":"Wareng",
    "gn:population":0,
    "gn:timezone":"Asia/Jakarta",
    "iso:country":"ID",
    "wof:name":"Wareng",
    "wof:placetype":"locality"
},
  "geometry": {"coordinates":[110.17361,-7.55222],"type":"Point"}
}