{
  "type": "Feature",
  "properties": {
    "gn:admin1_code":"7.0",
    "gn:asciiname":"Cirebonan",
    "gn:country_code":"ID",
    "gn:dem":323,
    "gn:feature_class":"P",
    "gn:feature_code":"PPL",
    "gn:name":"Cirebonan",
    "gn:population":0,
    "gn:timezone":"Asia/Jakarta",
    "iso:country":"ID",
    "name:ind_x_preferred":[
        "Cirebonan"
    ],
    "wof:name":"Cirebonan",
    "wof:placetype":"locality"
},
  "geometry": {"coordinates":[110.41160000000001,-7.1151],"type":"Point"}
}