{
  "type": "Feature",
  "properties": {
    "gn:admin1_code":"5.0",
    "gn:asciiname":"Sungaipageh",
    "gn:country_code":"ID",
    "gn:dem":873,
    "gn:feature_class":"P",
    "gn:feature_code":"PPL",
    "gn:name":"Sungaipageh",
    "gn:population":0,
    "gn:timezone":"Asia/Jakarta",
    "iso:country":"ID",
    "name:ind_x_preferred":[
        "Sungaipageh"
    ],
    "wof:name":"Sungaipageh",
    "wof:placetype":"locality"
},
  "geometry": {"coordinates":[101.3275,-1.9403],"type":"Point"}
}