{
  "type": "Feature",
  "properties": {
    "gn:admin1_code":"18",
    "gn:asciiname":"Lenggaji",
    "gn:country_code":"ID",
    "gn:dem":546,
    "gn:feature_class":"P",
    "gn:feature_code":"PPL",
    "gn:name":"Lenggaji",
    "gn:population":0,
    "gn:timezone":"Asia/Makassar",
    "iso:country":"ID",
    "name:ind_x_preferred":[
        "Lenggaji"
    ],
    "wof:name":"Lenggaji",
    "wof:placetype":"locality"
},
  "geometry": {"coordinates":[119.8942,-9.7079],"type":"Point"}
}