{
  "type": "Feature",
  "properties": {
    "gn:admin1_code":"7",
    "gn:asciiname":"Pagedangan",
    "gn:country_code":"ID",
    "gn:dem":217,
    "gn:feature_class":"P",
    "gn:feature_code":"PPL",
    "gn:name":"Pagedangan",
    "gn:population":0,
    "gn:timezone":"Asia/Jakarta",
    "iso:country":"ID",
    "name:ind_x_preferred":[
        "Pagedangan"
    ],
    "name:jav_x_preferred":[
        "Pagedangan"
    ],
    "name:msa_x_preferred":[
        "Pagedangan"
    ],
    "wof:lang_x_official":[
        "ind"
    ],
    "wof:lang_x_spoken":[
        "ind",
        "eng"
    ],
    "wof:name":"Pagedangan",
    "wof:placetype":"locality"
},
  "geometry": {"coordinates":[109.9468,-6.9719],"type":"Point"}
}