{
  "type": "Feature",
  "properties": {
    "gn:admin1_code":"30",
    "gn:asciiname":"Babakansewi",
    "gn:country_code":"ID",
    "gn:dem":31,
    "gn:feature_class":"P",
    "gn:feature_code":"PPL",
    "gn:name":"Babakansewi",
    "gn:population":0,
    "gn:timezone":"Asia/Jakarta",
    "iso:country":"ID",
    "name:ind_x_preferred":[
        "Babakansewi"
    ],
    "wof:name":"Babakansewi",
    "wof:placetype":"locality"
},
  "geometry": {"coordinates":[107.52583,-6.37556],"type":"Point"}
}