{
  "type": "Feature",
  "properties": {
    "gn:admin1_code":"30",
    "gn:asciiname":"Babakancirumput",
    "gn:country_code":"ID",
    "gn:dem":589,
    "gn:feature_class":"P",
    "gn:feature_code":"PPL",
    "gn:name":"Babakancirumput",
    "gn:population":0,
    "gn:timezone":"Asia/Jakarta",
    "iso:country":"ID",
    "name:ind_x_preferred":[
        "Babakancirumput"
    ],
    "wof:name":"Babakancirumput",
    "wof:placetype":"locality"
},
  "geometry": {"coordinates":[106.98917,-6.9375],"type":"Point"}
}