{
  "type": "Feature",
  "properties": {
    "gn:admin1_code":"18.0",
    "gn:asciiname":"Tawiana",
    "gn:country_code":"ID",
    "gn:dem":462,
    "gn:feature_class":"P",
    "gn:feature_code":"PPL",
    "gn:name":"Tawiana",
    "gn:population":0,
    "gn:timezone":"Asia/Makassar",
    "iso:country":"ID",
    "name:ind_x_preferred":[
        "Tawiana"
    ],
    "wof:name":"Tawiana",
    "wof:placetype":"locality"
},
  "geometry": {"coordinates":[119.3869,-9.6153],"type":"Point"}
}