{
  "type": "Feature",
  "properties": {
    "gn:admin1_code":"30",
    "gn:asciiname":"Cikurba",
    "gn:country_code":"ID",
    "gn:dem":54,
    "gn:feature_class":"P",
    "gn:feature_code":"PPL",
    "gn:name":"Cikurba",
    "gn:population":0,
    "gn:timezone":"Asia/Jakarta",
    "iso:country":"ID",
    "name:ind_x_preferred":[
        "Cikurba"
    ],
    "wof:name":"Cikurba",
    "wof:placetype":"locality"
},
  "geometry": {"coordinates":[107.16667,-6.48278],"type":"Point"}
}