{
  "type": "Feature",
  "properties": {
    "gn:admin1_code":"1",
    "gn:asciiname":"Suka Ramai Satu",
    "gn:country_code":"ID",
    "gn:dem":42,
    "gn:feature_class":"P",
    "gn:feature_code":"PPL",
    "gn:name":"Suka Ramai Satu",
    "gn:population":0,
    "gn:timezone":"Asia/Jakarta",
    "iso:country":"ID",
    "name:ind_x_preferred":[
        "Suka Ramai Satu"
    ],
    "name:und_x_variant":[
        "Sukaramai 1"
    ],
    "wof:name":"Suka Ramai Satu",
    "wof:placetype":"locality"
},
  "geometry": {"coordinates":[98.148,4.297],"type":"Point"}
}