{
  "type": "Feature",
  "properties": {
    "gn:admin1_code":"30",
    "gn:asciiname":"Sarimukti",
    "gn:country_code":"ID",
    "gn:dem":1353,
    "gn:feature_class":"P",
    "gn:feature_code":"PPL",
    "gn:name":"Sarimukti",
    "gn:population":0,
    "gn:timezone":"Asia/Jakarta",
    "iso:country":"ID",
    "name:ind_x_preferred":[
        "Sarimukti"
    ],
    "wof:lang_x_official":[
        "ind"
    ],
    "wof:lang_x_spoken":[
        "ind",
        "eng"
    ],
    "wof:name":"Sarimukti",
    "wof:placetype":"locality"
},
  "geometry": {"coordinates":[107.76519999999999,-7.2277],"type":"Point"}
}