{
  "type": "Feature",
  "properties": {
    "gn:admin1_code":"38",
    "gn:asciiname":"Limpua",
    "gn:country_code":"ID",
    "gn:dem":9,
    "gn:feature_class":"P",
    "gn:feature_code":"PPL",
    "gn:name":"Limpua",
    "gn:population":0,
    "gn:timezone":"Asia/Makassar",
    "iso:country":"ID",
    "name:ind_x_preferred":[
        "Limpua"
    ],
    "wof:name":"Limpua",
    "wof:placetype":"locality"
},
  "geometry": {"coordinates":[120.0829,-4.1354],"type":"Point"}
}