{
  "type": "Feature",
  "properties": {
    "gn:admin1_code":"30",
    "gn:asciiname":"Cinangka",
    "gn:country_code":"ID",
    "gn:dem":854,
    "gn:feature_class":"P",
    "gn:feature_code":"PPL",
    "gn:name":"Cinangka",
    "gn:population":0,
    "gn:timezone":"Asia/Jakarta",
    "iso:country":"ID",
    "name:ind_x_preferred":[
        "Cinangka"
    ],
    "name:jav_x_preferred":[
        "Cinangka"
    ],
    "name:msa_x_preferred":[
        "Cinangka"
    ],
    "name:nld_x_preferred":[
        "Cinangka"
    ],
    "name:sun_x_preferred":[
        "Cinangka"
    ],
    "wof:lang_x_official":[
        "ind"
    ],
    "wof:lang_x_spoken":[
        "ind",
        "eng"
    ],
    "wof:name":"Cinangka",
    "wof:placetype":"locality"
},
  "geometry": {"coordinates":[107.08499999999999,-6.70583],"type":"Point"}
}