{
  "type": "Feature",
  "properties": {
    "gn:admin1_code":"10",
    "gn:asciiname":"Pagerjurang",
    "gn:country_code":"ID",
    "gn:dem":250,
    "gn:feature_class":"P",
    "gn:feature_code":"PPL",
    "gn:name":"Pagerjurang",
    "gn:population":0,
    "gn:timezone":"Asia/Jakarta",
    "iso:country":"ID",
    "wof:name":"Pagerjurang",
    "wof:placetype":"locality"
},
  "geometry": {"coordinates":[110.68778,-7.8225],"type":"Point"}
}