{
  "type": "Feature",
  "properties": {
    "gn:admin1_code":"1",
    "gn:asciiname":"Lawe Serky",
    "gn:country_code":"ID",
    "gn:dem":126,
    "gn:feature_class":"P",
    "gn:feature_code":"PPL",
    "gn:name":"Lawe Serky",
    "gn:population":0,
    "gn:timezone":"Asia/Jakarta",
    "iso:country":"ID",
    "name:ind_x_preferred":[
        "Lawe Serky"
    ],
    "wof:name":"Lawe Serky",
    "wof:placetype":"locality"
},
  "geometry": {"coordinates":[97.8882,3.3604],"type":"Point"}
}