{
  "type": "Feature",
  "properties": {
    "gn:admin1_code":"0.0",
    "gn:asciiname":"Wendi",
    "gn:country_code":"ID",
    "gn:dem":163,
    "gn:feature_class":"P",
    "gn:feature_code":"PPL",
    "gn:name":"Wendi",
    "gn:population":0,
    "gn:timezone":"Asia/Jayapura",
    "iso:country":"ID",
    "name:deu_x_preferred":[
        "Wendi"
    ],
    "name:fra_x_preferred":[
        "Wendi"
    ],
    "name:ita_x_preferred":[
        "Wendi"
    ],
    "name:pol_x_preferred":[
        "Wendi"
    ],
    "wof:lang_x_official":[
        "ind"
    ],
    "wof:lang_x_spoken":[
        "ind",
        "eng"
    ],
    "wof:name":"Wendi",
    "wof:placetype":"locality"
},
  "geometry": {"coordinates":[124.65000000000001,-1.96667],"type":"Point"}
}