{
  "type": "Feature",
  "properties": {
    "gn:admin1_code":"30",
    "gn:asciiname":"Bonang",
    "gn:country_code":"ID",
    "gn:dem":1071,
    "gn:feature_class":"P",
    "gn:feature_code":"PPL",
    "gn:name":"Bonang",
    "gn:population":0,
    "gn:timezone":"Asia/Jakarta",
    "iso:country":"ID",
    "name:ind_x_preferred":[
        "Bonang"
    ],
    "wof:name":"Bonang",
    "wof:placetype":"locality"
},
  "geometry": {"coordinates":[107.8035,-7.1998],"type":"Point"}
}