{
  "type": "Feature",
  "properties": {
    "gn:admin1_code":"8",
    "gn:asciiname":"Pandak",
    "gn:country_code":"ID",
    "gn:dem":424,
    "gn:feature_class":"P",
    "gn:feature_code":"PPL",
    "gn:name":"Pandak",
    "gn:population":0,
    "gn:timezone":"Asia/Jakarta",
    "iso:country":"ID",
    "name:ceb_x_preferred":[
        "Pandak"
    ],
    "name:ind_x_preferred":[
        "Pandak"
    ],
    "name:nld_x_preferred":[
        "Pandak"
    ],
    "name:swe_x_preferred":[
        "Pandak"
    ],
    "wof:lang_x_official":[
        "ind"
    ],
    "wof:lang_x_spoken":[
        "ind",
        "eng"
    ],
    "wof:name":"Pandak",
    "wof:placetype":"locality"
},
  "geometry": {"coordinates":[111.3075,-7.635],"type":"Point"}
}