{
  "type": "Feature",
  "properties": {
    "gn:admin1_code":"26",
    "gn:asciiname":"Pemenangan",
    "gn:country_code":"ID",
    "gn:dem":667,
    "gn:feature_class":"P",
    "gn:feature_code":"PPL",
    "gn:name":"Pemenangan",
    "gn:population":0,
    "gn:timezone":"Asia/Jakarta",
    "iso:country":"ID",
    "name:ind_x_preferred":[
        "Pemenangan"
    ],
    "wof:name":"Pemenangan",
    "wof:placetype":"locality"
},
  "geometry": {"coordinates":[99.0078,2.8422],"type":"Point"}
}