{
  "type": "Feature",
  "properties": {
    "gn:admin1_code":"8.0",
    "gn:asciiname":"Baton",
    "gn:country_code":"ID",
    "gn:dem":13,
    "gn:feature_class":"P",
    "gn:feature_code":"PPL",
    "gn:name":"Baton",
    "gn:population":0,
    "gn:timezone":"Asia/Jakarta",
    "iso:country":"ID",
    "name:ceb_x_preferred":[
        "Baton"
    ],
    "name:deu_x_preferred":[
        "Baton"
    ],
    "name:hun_x_preferred":[
        "Baton"
    ],
    "name:ind_x_preferred":[
        "Baton"
    ],
    "name:jpn_x_preferred":[
        "\u30d0\u30c8\u30f3"
    ],
    "name:nld_x_preferred":[
        "Baton"
    ],
    "name:pol_x_preferred":[
        "Baton"
    ],
    "name:por_x_preferred":[
        "Batom"
    ],
    "name:swe_x_preferred":[
        "Baton"
    ],
    "wof:lang_x_official":[
        "ind"
    ],
    "wof:lang_x_spoken":[
        "ind",
        "eng"
    ],
    "wof:name":"Baton",
    "wof:placetype":"locality"
},
  "geometry": {"coordinates":[113.0235,-7.2077],"type":"Point"}
}