{
  "type": "Feature",
  "properties": {
    "gn:admin1_code":"7",
    "gn:asciiname":"Bulaktunggak",
    "gn:country_code":"ID",
    "gn:dem":12,
    "gn:feature_class":"P",
    "gn:feature_code":"PPL",
    "gn:name":"Bulaktunggak",
    "gn:population":0,
    "gn:timezone":"Asia/Jakarta",
    "iso:country":"ID",
    "name:ind_x_preferred":[
        "Bulaktunggak"
    ],
    "wof:name":"Bulaktunggak",
    "wof:placetype":"locality"
},
  "geometry": {"coordinates":[109.5639,-6.9366],"type":"Point"}
}