{
  "type": "Feature",
  "properties": {
    "gn:admin1_code":"1.0",
    "gn:asciiname":"Alue Baroh",
    "gn:country_code":"ID",
    "gn:dem":8,
    "gn:feature_class":"P",
    "gn:feature_code":"PPL",
    "gn:name":"Alue Baroh",
    "gn:population":0,
    "gn:timezone":"Asia/Jakarta",
    "iso:country":"ID",
    "name:ind_x_preferred":[
        "Alue Baroh"
    ],
    "wof:name":"Alue Baroh",
    "wof:placetype":"locality"
},
  "geometry": {"coordinates":[97.423,5.1641],"type":"Point"}
}