{
  "type": "Feature",
  "properties": {
    "gn:admin1_code":"1",
    "gn:asciiname":"Ramiti",
    "gn:country_code":"ID",
    "gn:dem":39,
    "gn:feature_class":"P",
    "gn:feature_code":"PPL",
    "gn:name":"Ramiti",
    "gn:population":0,
    "gn:timezone":"Asia/Jakarta",
    "iso:country":"ID",
    "name:ind_x_preferred":[
        "Ramiti"
    ],
    "wof:name":"Ramiti",
    "wof:placetype":"locality"
},
  "geometry": {"coordinates":[96.03400000000001,4.5211],"type":"Point"}
}