{
  "type": "Feature",
  "properties": {
    "gn:admin1_code":"18.0",
    "gn:asciiname":"Sawahbenlaweng",
    "gn:country_code":"ID",
    "gn:dem":30,
    "gn:feature_class":"P",
    "gn:feature_code":"PPL",
    "gn:name":"Sawahbenlaweng",
    "gn:population":0,
    "gn:timezone":"Asia/Makassar",
    "iso:country":"ID",
    "name:ind_x_preferred":[
        "Sawahbenlaweng"
    ],
    "wof:name":"Sawahbenlaweng",
    "wof:placetype":"locality"
},
  "geometry": {"coordinates":[124.5823,-8.2053],"type":"Point"}
}