{
  "type": "Feature",
  "properties": {
    "gn:admin1_code":"26",
    "gn:asciiname":"Komplek Afdeling Satu",
    "gn:country_code":"ID",
    "gn:dem":24,
    "gn:feature_class":"P",
    "gn:feature_code":"PPL",
    "gn:name":"Komplek Afdeling Satu",
    "gn:population":0,
    "gn:timezone":"Asia/Jakarta",
    "iso:country":"ID",
    "name:ind_x_preferred":[
        "Komplek Afdeling Satu"
    ],
    "name:und_x_variant":[
        "Komplek Afdeling 1"
    ],
    "wof:lang_x_official":[
        "ind"
    ],
    "wof:lang_x_spoken":[
        "ind",
        "eng"
    ],
    "wof:name":"Komplek Afdeling Satu",
    "wof:placetype":"locality"
},
  "geometry": {"coordinates":[99.6857,2.5376],"type":"Point"}
}