{
  "type": "Feature",
  "properties": {
    "gn:admin1_code":"28.0",
    "gn:asciiname":"Wadule",
    "gn:country_code":"ID",
    "gn:dem":176,
    "gn:feature_class":"P",
    "gn:feature_code":"PPL",
    "gn:name":"Wadule",
    "gn:population":0,
    "gn:timezone":"Asia/Jayapura",
    "iso:country":"ID",
    "name:ind_x_preferred":[
        "Wadule"
    ],
    "name:und_x_variant":[
        "Wa Doel\u00e9"
    ],
    "wof:name":"Wadule",
    "wof:placetype":"locality"
},
  "geometry": {"coordinates":[126.73811000000001,-3.27867],"type":"Point"}
}