{
  "type": "Feature",
  "properties": {
    "gn:admin1_code":"7.0",
    "gn:asciiname":"Wani",
    "gn:country_code":"ID",
    "gn:dem":344,
    "gn:feature_class":"P",
    "gn:feature_code":"PPL",
    "gn:name":"Wani",
    "gn:population":0,
    "gn:timezone":"Asia/Jakarta",
    "iso:country":"ID",
    "name:ceb_x_preferred":[
        "Wani"
    ],
    "name:deu_x_preferred":[
        "Wani"
    ],
    "name:kat_x_preferred":[
        "\u10d5\u10d0\u10dc\u10d8"
    ],
    "name:pol_x_preferred":[
        "Wani"
    ],
    "name:swe_x_preferred":[
        "Wani"
    ],
    "name:xmf_x_preferred":[
        "\u10d5\u10d0\u10dc\u10d8"
    ],
    "wof:name":"Wani",
    "wof:placetype":"locality"
},
  "geometry": {"coordinates":[110.31583000000001,-7.63611],"type":"Point"}
}