{
  "type": "Feature",
  "properties": {
    "gn:admin1_code":"1",
    "gn:asciiname":"Grot",
    "gn:country_code":"ID",
    "gn:dem":17,
    "gn:feature_class":"P",
    "gn:feature_code":"PPL",
    "gn:name":"Grot",
    "gn:population":0,
    "gn:timezone":"Asia/Jakarta",
    "iso:country":"ID",
    "name:ceb_x_preferred":[
        "Grot"
    ],
    "name:deu_x_preferred":[
        "Grot"
    ],
    "name:ind_x_preferred":[
        "Grot"
    ],
    "name:pol_x_preferred":[
        "Grot"
    ],
    "name:rus_x_preferred":[
        "\u0413\u0440\u043e\u0442"
    ],
    "name:swe_x_preferred":[
        "Grot"
    ],
    "name:ukr_x_preferred":[
        "\u0413\u0440\u043e\u0442"
    ],
    "wof:lang_x_official":[
        "ind"
    ],
    "wof:lang_x_spoken":[
        "ind",
        "eng"
    ],
    "wof:name":"Grot",
    "wof:placetype":"locality"
},
  "geometry": {"coordinates":[95.3248,5.4875],"type":"Point"}
}