{
  "type": "Feature",
  "properties": {
    "gn:admin1_code":"30",
    "gn:asciiname":"Banyusrep",
    "gn:country_code":"ID",
    "gn:dem":5,
    "gn:feature_class":"P",
    "gn:feature_code":"PPL",
    "gn:name":"Banyusrep",
    "gn:population":0,
    "gn:timezone":"Asia/Jakarta",
    "iso:country":"ID",
    "name:ind_x_preferred":[
        "Banyusrep"
    ],
    "wof:name":"Banyusrep",
    "wof:placetype":"locality"
},
  "geometry": {"coordinates":[108.5839,-6.759],"type":"Point"}
}