{
  "type": "Feature",
  "properties": {
    "gn:admin1_code":"0.0",
    "gn:asciiname":"Klandasan-besar",
    "gn:country_code":"ID",
    "gn:dem":1,
    "gn:feature_class":"P",
    "gn:feature_code":"PPL",
    "gn:name":"Klandasan-besar",
    "gn:population":0,
    "gn:timezone":"Asia/Makassar",
    "iso:country":"ID",
    "wof:name":"Klandasan-besar",
    "wof:placetype":"locality"
},
  "geometry": {"coordinates":[116.81667,-1.28333],"type":"Point"}
}