{
  "type": "Feature",
  "properties": {
    "gn:admin1_code":"38",
    "gn:asciiname":"Panyura",
    "gn:country_code":"ID",
    "gn:dem":592,
    "gn:feature_class":"P",
    "gn:feature_code":"PPL",
    "gn:name":"Panyura",
    "gn:population":0,
    "gn:timezone":"Asia/Makassar",
    "iso:country":"ID",
    "name:ind_x_preferred":[
        "Panyura"
    ],
    "wof:name":"Panyura",
    "wof:placetype":"locality"
},
  "geometry": {"coordinates":[119.87739999999999,-3.4225],"type":"Point"}
}