{
  "type": "Feature",
  "properties": {
    "gn:admin1_code":"41.0",
    "gn:asciiname":"Bulobulo",
    "gn:country_code":"ID",
    "gn:dem":677,
    "gn:feature_class":"P",
    "gn:feature_code":"PPL",
    "gn:name":"Bulobulo",
    "gn:population":0,
    "gn:timezone":"Asia/Makassar",
    "iso:country":"ID",
    "name:ind_x_preferred":[
        "Bulobulo"
    ],
    "name:und_x_variant":[
        "Boeloboelo",
        "Boeloeboeloe"
    ],
    "wof:lang_x_official":[
        "ind"
    ],
    "wof:lang_x_spoken":[
        "ind",
        "eng"
    ],
    "wof:name":"Bulobulo",
    "wof:placetype":"locality"
},
  "geometry": {"coordinates":[118.92230000000001,-3.2192],"type":"Point"}
}