{
  "type": "Feature",
  "properties": {
    "gn:admin1_code":"37",
    "gn:asciiname":"Lubuksiam",
    "gn:country_code":"ID",
    "gn:dem":14,
    "gn:feature_class":"P",
    "gn:feature_code":"PPL",
    "gn:name":"Lubuksiam",
    "gn:population":0,
    "gn:timezone":"Asia/Jakarta",
    "iso:country":"ID",
    "name:ind_x_preferred":[
        "Lubuksiam"
    ],
    "wof:name":"Lubuksiam",
    "wof:placetype":"locality"
},
  "geometry": {"coordinates":[101.4825,0.3701],"type":"Point"}
}