{
  "type": "Feature",
  "properties": {
    "gn:admin1_code":"22",
    "gn:asciiname":"Kessie",
    "gn:country_code":"ID",
    "gn:dem":25,
    "gn:feature_class":"P",
    "gn:feature_code":"PPL",
    "gn:name":"Kessie",
    "gn:population":0,
    "gn:timezone":"Asia/Makassar",
    "iso:country":"ID",
    "name:ind_x_preferred":[
        "Kessie"
    ],
    "wof:name":"Kessie",
    "wof:placetype":"locality"
},
  "geometry": {"coordinates":[121.5175,-4.7221],"type":"Point"}
}