{
  "type": "Feature",
  "properties": {
    "gn:admin1_code":"7",
    "gn:asciiname":"Tempel",
    "gn:country_code":"ID",
    "gn:dem":161,
    "gn:feature_class":"P",
    "gn:feature_code":"PPL",
    "gn:name":"Tempel",
    "gn:population":0,
    "gn:timezone":"Asia/Jakarta",
    "iso:country":"ID",
    "name:ceb_x_preferred":[
        "Tempel"
    ],
    "name:deu_x_preferred":[
        "Tempel"
    ],
    "name:fra_x_preferred":[
        "Tempel"
    ],
    "name:ind_x_preferred":[
        "Tempel"
    ],
    "name:jpn_x_preferred":[
        "\u30c6\u30f3\u30da\u30eb"
    ],
    "name:lav_x_preferred":[
        "Tempels"
    ],
    "name:nds_x_preferred":[
        "Tempel"
    ],
    "name:nld_x_preferred":[
        "Tempel"
    ],
    "name:pol_x_preferred":[
        "Tempel"
    ],
    "name:slk_x_preferred":[
        "Tempel"
    ],
    "name:swe_x_preferred":[
        "Tempel"
    ],
    "wof:name":"Tempel",
    "wof:placetype":"locality"
},
  "geometry": {"coordinates":[111.01111000000002,-7.49222],"type":"Point"}
}