{
  "type": "Feature",
  "properties": {
    "gn:admin1_code":"8.0",
    "gn:asciiname":"Dadap Wetan",
    "gn:country_code":"ID",
    "gn:dem":1060,
    "gn:feature_class":"P",
    "gn:feature_code":"PPL",
    "gn:name":"Dadap Wetan",
    "gn:population":0,
    "gn:timezone":"Asia/Jakarta",
    "iso:country":"ID",
    "name:ind_x_preferred":[
        "Dadap Wetan"
    ],
    "wof:name":"Dadap Wetan",
    "wof:placetype":"locality"
},
  "geometry": {"coordinates":[112.42910000000001,-7.8761],"type":"Point"}
}