{
  "type": "Feature",
  "properties": {
    "gn:admin1_code":"30.0",
    "gn:asciiname":"Cireang",
    "gn:country_code":"ID",
    "gn:dem":177,
    "gn:feature_class":"P",
    "gn:feature_code":"PPL",
    "gn:name":"Cireang",
    "gn:population":0,
    "gn:timezone":"Asia/Jakarta",
    "iso:country":"ID",
    "name:ind_x_preferred":[
        "Cireang"
    ],
    "wof:name":"Cireang",
    "wof:placetype":"locality"
},
  "geometry": {"coordinates":[106.9294,-7.3501],"type":"Point"}
}