{
  "type": "Feature",
  "properties": {
    "gn:admin1_code":"8",
    "gn:asciiname":"Laoksungai",
    "gn:country_code":"ID",
    "gn:dem":68,
    "gn:feature_class":"P",
    "gn:feature_code":"PPL",
    "gn:name":"Laoksungai",
    "gn:population":0,
    "gn:timezone":"Asia/Jakarta",
    "iso:country":"ID",
    "name:ind_x_preferred":[
        "Laoksungai"
    ],
    "wof:name":"Laoksungai",
    "wof:placetype":"locality"
},
  "geometry": {"coordinates":[112.90006,-7.09656],"type":"Point"}
}