{
  "type": "Feature",
  "properties": {
    "gn:admin1_code":"30.0",
    "gn:asciiname":"Pangsor",
    "gn:country_code":"ID",
    "gn:dem":276,
    "gn:feature_class":"P",
    "gn:feature_code":"PPL",
    "gn:name":"Pangsor",
    "gn:population":0,
    "gn:timezone":"Asia/Jakarta",
    "iso:country":"ID",
    "name:ind_x_preferred":[
        "Pangsor"
    ],
    "wof:name":"Pangsor",
    "wof:placetype":"locality"
},
  "geometry": {"coordinates":[108.38209999999999,-7.2415],"type":"Point"}
}