{
  "type": "Feature",
  "properties": {
    "gn:admin1_code":"12",
    "gn:asciiname":"Mangkalapi",
    "gn:country_code":"ID",
    "gn:dem":35,
    "gn:feature_class":"P",
    "gn:feature_code":"PPL",
    "gn:name":"Mangkalapi",
    "gn:population":0,
    "gn:timezone":"Asia/Makassar",
    "iso:country":"ID",
    "name:ind_x_preferred":[
        "Mangkalapi"
    ],
    "wof:name":"Mangkalapi",
    "wof:placetype":"locality"
},
  "geometry": {"coordinates":[115.6249,-3.4475],"type":"Point"}
}