{
  "type": "Feature",
  "properties": {
    "gn:admin1_code":"37.0",
    "gn:asciiname":"Simpang",
    "gn:country_code":"ID",
    "gn:dem":7,
    "gn:feature_class":"P",
    "gn:feature_code":"PPL",
    "gn:name":"Simpang",
    "gn:population":0,
    "gn:timezone":"Asia/Jakarta",
    "iso:country":"ID",
    "name:mlg_x_preferred":[
        "Simpang"
    ],
    "name:und_x_variant":[
        "Simipang",
        "Simpang"
    ],
    "wof:name":"Simpang",
    "wof:placetype":"locality"
},
  "geometry": {"coordinates":[103.1028,-0.0976],"type":"Point"}
}