{
  "type": "Feature",
  "properties": {
    "gn:admin1_code":"30.0",
    "gn:asciiname":"Pamalayan",
    "gn:country_code":"ID",
    "gn:dem":297,
    "gn:feature_class":"P",
    "gn:feature_code":"PPL",
    "gn:name":"Pamalayan",
    "gn:population":0,
    "gn:timezone":"Asia/Jakarta",
    "iso:country":"ID",
    "name:ind_x_preferred":[
        "Pamalayan"
    ],
    "name:und_x_variant":[
        "Pamalajan"
    ],
    "wof:name":"Pamalayan",
    "wof:placetype":"locality"
},
  "geometry": {"coordinates":[108.2919,-7.3494],"type":"Point"}
}