{
  "type": "Feature",
  "properties": {
    "gn:country":"ID",
    "gn:fcode":"PPL",
    "gn:pop":0,
    "iso:country":"ID",
    "name:ban_x_preferred":[
        "Kecamatan lan kelurahan ring Lampung"
    ],
    "name:eng_x_preferred":[
        "Districts of Lampung"
    ],
    "name:ind_x_preferred":[
        "Teluk Betung"
    ],
    "qs:name":"Teluk Betung Utara",
    "qs:name_adm0":"Indonesia",
    "qs:name_adm1":"Lampung",
    "qs:photos_9k":1,
    "qs:photos_9r":1,
    "qs:photos_all":19,
    "qs:photos_sr":0,
    "qs:placetype":"Town",
    "qs:pop_sr":"0",
    "wd:wordcount":669,
    "wof:lang_x_official":[
        "ind"
    ],
    "wof:lang_x_spoken":[
        "ind",
        "eng"
    ],
    "wof:name":"Teluk Betung Utara",
    "wof:placetype":"locality",
    "wof:population":0
},
  "geometry": {"coordinates":[105.36812,-5.48166],"type":"Point"}
}