{
  "type": "Feature",
  "properties": {
    "gn:admin1_code":"1",
    "gn:asciiname":"Peureulak Baru",
    "gn:country_code":"ID",
    "gn:dem":35,
    "gn:feature_class":"P",
    "gn:feature_code":"PPL",
    "gn:name":"Peureulak Baru",
    "gn:population":0,
    "gn:timezone":"Asia/Jakarta",
    "iso:country":"ID",
    "name:ind_x_preferred":[
        "Peureulak Baru"
    ],
    "wof:name":"Peureulak Baru",
    "wof:placetype":"locality"
},
  "geometry": {"coordinates":[95.9532,5.2556],"type":"Point"}
}