{
  "type": "Feature",
  "properties": {
    "gn:admin1_code":"18",
    "gn:asciiname":"Waekoe",
    "gn:country_code":"ID",
    "gn:dem":19,
    "gn:feature_class":"P",
    "gn:feature_code":"PPL",
    "gn:name":"Waekoe",
    "gn:population":0,
    "gn:timezone":"Asia/Makassar",
    "iso:country":"ID",
    "name:ind_x_preferred":[
        "Waekoe"
    ],
    "wof:name":"Waekoe",
    "wof:placetype":"locality"
},
  "geometry": {"coordinates":[121.0184,-8.9532],"type":"Point"}
}