{
  "type": "Feature",
  "properties": {
    "gn:admin1_code":"30.0",
    "gn:asciiname":"Cipancur",
    "gn:country_code":"ID",
    "gn:dem":159,
    "gn:feature_class":"P",
    "gn:feature_code":"PPL",
    "gn:name":"Cipancur",
    "gn:population":0,
    "gn:timezone":"Asia/Jakarta",
    "iso:country":"ID",
    "name:ind_x_preferred":[
        "Cipancur"
    ],
    "wof:name":"Cipancur",
    "wof:placetype":"locality"
},
  "geometry": {"coordinates":[108.24509999999999,-7.6331],"type":"Point"}
}