{
  "type": "Feature",
  "properties": {
    "gn:admin1_code":"18.0",
    "gn:asciiname":"Wajo",
    "gn:country_code":"ID",
    "gn:dem":54,
    "gn:feature_class":"P",
    "gn:feature_code":"PPL",
    "gn:name":"Wajo",
    "gn:population":0,
    "gn:timezone":"Asia/Makassar",
    "iso:country":"ID",
    "name:ceb_x_preferred":[
        "Wajo"
    ],
    "name:fra_x_preferred":[
        "Wajo"
    ],
    "name:ind_x_preferred":[
        "Wajo"
    ],
    "name:swe_x_preferred":[
        "Wajo"
    ],
    "wof:lang_x_official":[
        "ind"
    ],
    "wof:lang_x_spoken":[
        "ind",
        "eng"
    ],
    "wof:name":"Wajo",
    "wof:placetype":"locality"
},
  "geometry": {"coordinates":[122.0699,-8.7505],"type":"Point"}
}