{
  "type": "Feature",
  "properties": {
    "gn:admin1_code":"40.0",
    "gn:asciiname":"Kelume",
    "gn:country_code":"ID",
    "gn:dem":114,
    "gn:feature_class":"P",
    "gn:feature_code":"PPL",
    "gn:name":"Kelume",
    "gn:population":0,
    "gn:timezone":"Asia/Jakarta",
    "iso:country":"ID",
    "name:und_x_variant":[
        "Keloeme",
        "Kelume"
    ],
    "wof:name":"Kelume",
    "wof:placetype":"locality"
},
  "geometry": {"coordinates":[104.49584,-0.23615],"type":"Point"}
}