{
  "type": "Feature",
  "properties": {
    "gn:admin1_code":"7.0",
    "gn:asciiname":"Ngontoonto",
    "gn:country_code":"ID",
    "gn:dem":616,
    "gn:feature_class":"P",
    "gn:feature_code":"PPL",
    "gn:name":"Ngontoonto",
    "gn:population":0,
    "gn:timezone":"Asia/Jakarta",
    "iso:country":"ID",
    "wof:name":"Ngontoonto",
    "wof:placetype":"locality"
},
  "geometry": {"coordinates":[110.30444,-7.47194],"type":"Point"}
}