{
  "type": "Feature",
  "properties": {
    "gn:admin1_code":"17",
    "gn:asciiname":"Karangpenunjak",
    "gn:country_code":"ID",
    "gn:dem":21,
    "gn:feature_class":"P",
    "gn:feature_code":"PPL",
    "gn:name":"Karangpenunjak",
    "gn:population":0,
    "gn:timezone":"Asia/Makassar",
    "iso:country":"ID",
    "name:ind_x_preferred":[
        "Karangpenunjak"
    ],
    "wof:name":"Karangpenunjak",
    "wof:placetype":"locality"
},
  "geometry": {"coordinates":[116.1019,-8.6718],"type":"Point"}
}