{
  "type": "Feature",
  "properties": {
    "gn:admin1_code":"30.0",
    "gn:asciiname":"Ciseupan",
    "gn:country_code":"ID",
    "gn:dem":343,
    "gn:feature_class":"P",
    "gn:feature_code":"PPL",
    "gn:name":"Ciseupan",
    "gn:population":0,
    "gn:timezone":"Asia/Jakarta",
    "iso:country":"ID",
    "name:ind_x_preferred":[
        "Ciseupan"
    ],
    "wof:name":"Ciseupan",
    "wof:placetype":"locality"
},
  "geometry": {"coordinates":[106.8536,-7.2674],"type":"Point"}
}