{
  "type": "Feature",
  "properties": {
    "gn:admin1_code":"38.0",
    "gn:asciiname":"Takke",
    "gn:country_code":"ID",
    "gn:dem":1218,
    "gn:feature_class":"P",
    "gn:feature_code":"PPL",
    "gn:name":"Takke",
    "gn:population":0,
    "gn:timezone":"Asia/Makassar",
    "iso:country":"ID",
    "name:ind_x_preferred":[
        "Takke"
    ],
    "wof:name":"Takke",
    "wof:placetype":"locality"
},
  "geometry": {"coordinates":[119.8338,-2.9647],"type":"Point"}
}