{
  "type": "Feature",
  "properties": {
    "gn:admin1_code":"10",
    "gn:asciiname":"Genting",
    "gn:country_code":"ID",
    "gn:dem":77,
    "gn:feature_class":"P",
    "gn:feature_code":"PPL",
    "gn:name":"Genting",
    "gn:population":0,
    "gn:timezone":"Asia/Jakarta",
    "iso:country":"ID",
    "name:ceb_x_preferred":[
        "Genting"
    ],
    "name:ind_x_preferred":[
        "Genting"
    ],
    "name:msa_x_preferred":[
        "Genting"
    ],
    "name:nld_x_preferred":[
        "Genting"
    ],
    "name:swe_x_preferred":[
        "Genting"
    ],
    "wof:lang_x_official":[
        "ind"
    ],
    "wof:lang_x_spoken":[
        "ind",
        "eng"
    ],
    "wof:name":"Genting",
    "wof:placetype":"locality"
},
  "geometry": {"coordinates":[110.43472,-7.85583],"type":"Point"}
}