{
  "type": "Feature",
  "properties": {
    "gn:admin1_code":"30",
    "gn:asciiname":"Penyusuhan",
    "gn:country_code":"ID",
    "gn:dem":529,
    "gn:feature_class":"P",
    "gn:feature_code":"PPL",
    "gn:name":"Penyusuhan",
    "gn:population":0,
    "gn:timezone":"Asia/Jakarta",
    "iso:country":"ID",
    "name:ind_x_preferred":[
        "Penyusuhan"
    ],
    "wof:name":"Penyusuhan",
    "wof:placetype":"locality"
},
  "geometry": {"coordinates":[106.8175,-6.82528],"type":"Point"}
}