{
  "type": "Feature",
  "properties": {
    "gn:admin1_code":"7.0",
    "gn:asciiname":"Paso",
    "gn:country_code":"ID",
    "gn:dem":32,
    "gn:feature_class":"P",
    "gn:feature_code":"PPL",
    "gn:name":"Paso",
    "gn:population":0,
    "gn:timezone":"Asia/Jakarta",
    "iso:country":"ID",
    "name:ceb_x_preferred":[
        "Paso"
    ],
    "name:deu_x_preferred":[
        "Paso"
    ],
    "name:fra_x_preferred":[
        "Paso"
    ],
    "name:glg_x_preferred":[
        "Paso"
    ],
    "name:ind_x_preferred":[
        "Paso"
    ],
    "name:rus_x_preferred":[
        "\u041f\u0430\u0441\u043e"
    ],
    "name:spa_x_preferred":[
        "Paso"
    ],
    "name:swe_x_preferred":[
        "Paso"
    ],
    "wof:lang_x_official":[
        "ind"
    ],
    "wof:lang_x_spoken":[
        "ind",
        "eng"
    ],
    "wof:name":"Paso",
    "wof:placetype":"locality"
},
  "geometry": {"coordinates":[111.0874,-6.8626],"type":"Point"}
}