{
  "type": "Feature",
  "properties": {
    "gn:admin1_code":"7",
    "gn:asciiname":"Tretep",
    "gn:country_code":"ID",
    "gn:dem":730,
    "gn:feature_class":"P",
    "gn:feature_code":"PPL",
    "gn:name":"Tretep",
    "gn:population":0,
    "gn:timezone":"Asia/Jakarta",
    "iso:country":"ID",
    "name:ind_x_preferred":[
        "Tretep"
    ],
    "wof:name":"Tretep",
    "wof:placetype":"locality"
},
  "geometry": {"coordinates":[109.24222,-7.1525],"type":"Point"}
}