{
  "type": "Feature",
  "properties": {
    "gn:admin1_code":"7.0",
    "gn:asciiname":"Lampeng",
    "gn:country_code":"ID",
    "gn:dem":749,
    "gn:feature_class":"P",
    "gn:feature_code":"PPL",
    "gn:name":"Lampeng",
    "gn:population":0,
    "gn:timezone":"Asia/Jakarta",
    "iso:country":"ID",
    "name:ind_x_preferred":[
        "Lampeng"
    ],
    "wof:name":"Lampeng",
    "wof:placetype":"locality"
},
  "geometry": {"coordinates":[109.60889,-7.25028],"type":"Point"}
}