{
  "type": "Feature",
  "properties": {
    "gn:admin1_code":"1.0",
    "gn:asciiname":"Gajahmeuntah",
    "gn:country_code":"ID",
    "gn:dem":14,
    "gn:feature_class":"P",
    "gn:feature_code":"PPL",
    "gn:name":"Gajahmeuntah",
    "gn:population":0,
    "gn:timezone":"Asia/Jakarta",
    "iso:country":"ID",
    "name:ind_x_preferred":[
        "Gajahmeuntah"
    ],
    "name:und_x_variant":[
        "Gadjahmeuentah",
        "Gajahmeuentah",
        "Gajahmentah"
    ],
    "wof:name":"Gajahmeuntah",
    "wof:placetype":"locality"
},
  "geometry": {"coordinates":[97.8693,4.6475],"type":"Point"}
}