{
  "type": "Feature",
  "properties": {
    "gn:admin1_code":"26",
    "gn:asciiname":"Namokedai",
    "gn:country_code":"ID",
    "gn:dem":59,
    "gn:feature_class":"P",
    "gn:feature_code":"PPL",
    "gn:name":"Namokedai",
    "gn:population":0,
    "gn:timezone":"Asia/Jakarta",
    "iso:country":"ID",
    "name:ind_x_preferred":[
        "Namokedai"
    ],
    "name:und_x_variant":[
        "Namukedah"
    ],
    "wof:name":"Namokedai",
    "wof:placetype":"locality"
},
  "geometry": {"coordinates":[98.1742,3.6734],"type":"Point"}
}