{
  "type": "Feature",
  "properties": {
    "gn:admin1_code":"26",
    "gn:asciiname":"Labujelok",
    "gn:country_code":"ID",
    "gn:dem":619,
    "gn:feature_class":"P",
    "gn:feature_code":"PPL",
    "gn:name":"Labujelok",
    "gn:population":0,
    "gn:timezone":"Asia/Jakarta",
    "iso:country":"ID",
    "name:ind_x_preferred":[
        "Labujelok"
    ],
    "wof:name":"Labujelok",
    "wof:placetype":"locality"
},
  "geometry": {"coordinates":[99.18470000000001,1.4176],"type":"Point"}
}