{
  "type": "Feature",
  "properties": {
    "gn:admin1_code":"8.0",
    "gn:asciiname":"Padanan Barat",
    "gn:country_code":"ID",
    "gn:dem":81,
    "gn:feature_class":"P",
    "gn:feature_code":"PPL",
    "gn:name":"Padanan Barat",
    "gn:population":0,
    "gn:timezone":"Asia/Jakarta",
    "iso:country":"ID",
    "name:ind_x_preferred":[
        "Padanan Barat"
    ],
    "wof:name":"Padanan Barat",
    "wof:placetype":"locality"
},
  "geometry": {"coordinates":[113.7217,-7.0301],"type":"Point"}
}