{
  "type": "Feature",
  "properties": {
    "gn:admin1_code":"38",
    "gn:asciiname":"Kombong",
    "gn:country_code":"ID",
    "gn:dem":830,
    "gn:feature_class":"P",
    "gn:feature_code":"PPL",
    "gn:name":"Kombong",
    "gn:population":0,
    "gn:timezone":"Asia/Makassar",
    "iso:country":"ID",
    "name:ind_x_preferred":[
        "Kombong"
    ],
    "name:und_x_variant":[
        "Kambong"
    ],
    "wof:name":"Kombong",
    "wof:placetype":"locality"
},
  "geometry": {"coordinates":[119.9237,-2.9183],"type":"Point"}
}