{
  "type": "Feature",
  "properties": {
    "gn:country":"ID",
    "gn:fcode":"PPLA4",
    "gn:pop":0,
    "iso:country":"ID",
    "name:ind_x_preferred":[
        "Sukasukur"
    ],
    "name:unk_x_variant":[
        "Soekasoekoer"
    ],
    "qs:name":"Sukasukur",
    "qs:photos_9r":0,
    "qs:photos_sr":0,
    "qs:pop_sr":"0",
    "wof:name":"Sukasukur",
    "wof:placetype":"locality",
    "wof:population":0
},
  "geometry": {"coordinates":[108.0753,-7.3737],"type":"Point"}
}