{
  "type": "Feature",
  "properties": {
    "gn:admin1_code":"38",
    "gn:asciiname":"Bolapattappuloe",
    "gn:country_code":"ID",
    "gn:dem":13,
    "gn:feature_class":"P",
    "gn:feature_code":"PPL",
    "gn:name":"Bolapattappuloe",
    "gn:population":0,
    "gn:timezone":"Asia/Makassar",
    "iso:country":"ID",
    "name:ind_x_preferred":[
        "Bolapattappuloe"
    ],
    "name:und_x_variant":[
        "Bolapattapuloe"
    ],
    "wof:name":"Bolapattappuloe",
    "wof:placetype":"locality"
},
  "geometry": {"coordinates":[119.6079,-3.81],"type":"Point"}
}