{
  "type": "Feature",
  "properties": {
    "gn:admin1_code":"30.0",
    "gn:asciiname":"Cikulina",
    "gn:country_code":"ID",
    "gn:dem":221,
    "gn:feature_class":"P",
    "gn:feature_code":"PPLA4",
    "gn:name":"Cikulina",
    "gn:population":0,
    "gn:timezone":"Asia/Jakarta",
    "iso:country":"ID",
    "name:ind_x_preferred":[
        "Cikulina"
    ],
    "wof:lang_x_official":[
        "ind"
    ],
    "wof:lang_x_spoken":[
        "ind",
        "eng"
    ],
    "wof:name":"Cikulina",
    "wof:placetype":"locality"
},
  "geometry": {"coordinates":[106.98560000000001,-7.229],"type":"Point"}
}