{
  "type": "Feature",
  "properties": {
    "gn:admin1_code":"2",
    "gn:asciiname":"Banjar Sanggem",
    "gn:country_code":"ID",
    "gn:dem":480,
    "gn:feature_class":"P",
    "gn:feature_code":"PPL",
    "gn:name":"Banjar Sanggem",
    "gn:population":0,
    "gn:timezone":"Asia/Makassar",
    "iso:country":"ID",
    "name:ind_x_preferred":[
        "Banjar Sanggem"
    ],
    "wof:name":"Banjar Sanggem",
    "wof:placetype":"locality"
},
  "geometry": {"coordinates":[115.43680000000001,-8.4538],"type":"Point"}
}