{
  "type": "Feature",
  "properties": {
    "gn:admin1_code":"30",
    "gn:asciiname":"Ciater Satu",
    "gn:cc2":"ID",
    "gn:country_code":"ID",
    "gn:dem":50,
    "gn:feature_class":"P",
    "gn:feature_code":"PPL",
    "gn:name":"Ciater Satu",
    "gn:population":0,
    "gn:timezone":"Asia/Jakarta",
    "iso:country":"ID",
    "name:und_x_variant":[
        "Ciater 1",
        "Ciater Satu"
    ],
    "wof:lang_x_official":[
        "ind"
    ],
    "wof:lang_x_spoken":[
        "ind",
        "eng"
    ],
    "wof:name":"Ciater Satu",
    "wof:placetype":"locality"
},
  "geometry": {"coordinates":[106.68861,-6.31194],"type":"Point"}
}