{
  "type": "Feature",
  "properties": {
    "gn:admin1_code":"8.0",
    "gn:asciiname":"Wolungewu",
    "gn:country_code":"ID",
    "gn:dem":728,
    "gn:feature_class":"P",
    "gn:feature_code":"PPL",
    "gn:name":"Wolungewu",
    "gn:population":0,
    "gn:timezone":"Asia/Jakarta",
    "iso:country":"ID",
    "name:ind_x_preferred":[
        "Wolungewu"
    ],
    "wof:name":"Wolungewu",
    "wof:placetype":"locality"
},
  "geometry": {"coordinates":[112.3792,-7.9661],"type":"Point"}
}