{
  "type": "Feature",
  "properties": {
    "gn:admin1_code":"15.0",
    "gn:asciiname":"Belimbing",
    "gn:country_code":"ID",
    "gn:dem":69,
    "gn:feature_class":"P",
    "gn:feature_code":"PPL",
    "gn:name":"Belimbing",
    "gn:population":0,
    "gn:timezone":"Asia/Jakarta",
    "iso:country":"ID",
    "name:ind_x_preferred":[
        "Belimbing"
    ],
    "name:msa_x_preferred":[
        "Belimbing"
    ],
    "wof:name":"Belimbing",
    "wof:placetype":"locality"
},
  "geometry": {"coordinates":[105.57940000000001,-5.07985],"type":"Point"}
}