{
  "type": "Feature",
  "properties": {
    "gn:admin1_code":"34.0",
    "gn:asciiname":"Dungalio Utara",
    "gn:country_code":"ID",
    "gn:dem":8,
    "gn:feature_class":"P",
    "gn:feature_code":"PPL",
    "gn:name":"Dungalio Utara",
    "gn:population":0,
    "gn:timezone":"Asia/Makassar",
    "iso:country":"ID",
    "name:ind_x_preferred":[
        "Dungalio Utara"
    ],
    "wof:name":"Dungalio Utara",
    "wof:placetype":"locality"
},
  "geometry": {"coordinates":[122.9179,0.8342],"type":"Point"}
}