{
  "type": "Feature",
  "properties": {
    "gn:admin1_code":"26",
    "gn:asciiname":"Hiliotaluwa",
    "gn:country_code":"ID",
    "gn:dem":42,
    "gn:feature_class":"P",
    "gn:feature_code":"PPL",
    "gn:name":"Hiliotaluwa",
    "gn:population":0,
    "gn:timezone":"Asia/Jakarta",
    "iso:country":"ID",
    "name:ind_x_preferred":[
        "Hiliotaluwa"
    ],
    "wof:name":"Hiliotaluwa",
    "wof:placetype":"locality"
},
  "geometry": {"coordinates":[97.5699,0.9265],"type":"Point"}
}