{
  "type": "Feature",
  "properties": {
    "gn:admin1_code":"33.0",
    "gn:asciiname":"Kadujulang",
    "gn:country_code":"ID",
    "gn:dem":69,
    "gn:feature_class":"P",
    "gn:feature_code":"PPL",
    "gn:name":"Kadujulang",
    "gn:population":0,
    "gn:timezone":"Asia/Jakarta",
    "iso:country":"ID",
    "name:ind_x_preferred":[
        "Kadujulang"
    ],
    "name:und_x_variant":[
        "Kadudjulang",
        "Kadujulang"
    ],
    "wof:name":"Kadujulang",
    "wof:placetype":"locality"
},
  "geometry": {"coordinates":[105.8703,-6.185],"type":"Point"}
}