{
  "type": "Feature",
  "properties": {
    "gn:admin1_code":"24",
    "gn:asciiname":"Balaisati",
    "gn:country_code":"ID",
    "gn:dem":40,
    "gn:feature_class":"P",
    "gn:feature_code":"PPL",
    "gn:name":"Balaisati",
    "gn:population":0,
    "gn:timezone":"Asia/Jakarta",
    "iso:country":"ID",
    "name:ind_x_preferred":[
        "Balaisati"
    ],
    "wof:name":"Balaisati",
    "wof:placetype":"locality"
},
  "geometry": {"coordinates":[100.21145,-0.59606],"type":"Point"}
}