{
  "type": "Feature",
  "properties": {
    "gn:admin1_code":"0.0",
    "gn:asciiname":"Ogar",
    "gn:cc2":"ID",
    "gn:country_code":"ID",
    "gn:dem":-9999,
    "gn:feature_class":"P",
    "gn:feature_code":"PPL",
    "gn:name":"Ogar",
    "gn:population":0,
    "gn:timezone":"Asia/Jayapura",
    "iso:country":"ID",
    "name:ceb_x_preferred":[
        "Ogar"
    ],
    "name:epo_x_preferred":[
        "Ogar"
    ],
    "name:fra_x_preferred":[
        "Ogar"
    ],
    "name:hrv_x_preferred":[
        "Ogar"
    ],
    "name:hun_x_preferred":[
        "Ogar"
    ],
    "name:msa_x_preferred":[
        "Ogar"
    ],
    "name:slv_x_preferred":[
        "Ogar"
    ],
    "name:srp_x_preferred":[
        "\u041e\u0433\u0430\u0440"
    ],
    "name:und_x_variant":[
        "Ogasmoeni",
        "Ogar"
    ],
    "wof:lang_x_official":[
        "ind"
    ],
    "wof:lang_x_spoken":[
        "ind",
        "eng"
    ],
    "wof:name":"Ogar",
    "wof:placetype":"locality"
},
  "geometry": {"coordinates":[132.43333000000001,-2.63333],"type":"Point"}
}