{
  "type": "Feature",
  "properties": {
    "gn:admin1_code":"0.0",
    "gn:asciiname":"Ogar",
    "gn:cc2":"ID",
    "gn:country_code":"ID",
    "gn:dem":-9999,
    "gn:feature_class":"P",
    "gn:feature_code":"PPL",
    "gn:name":"Ogar",
    "gn:population":0,
    "gn:timezone":"Asia/Jayapura",
    "iso:country":"ID",
    "name:und_x_variant":[
        "Ogasmoeni",
        "Ogar"
    ],
    "wof:name":"Ogar",
    "wof:placetype":"locality"
},
  "geometry": {"coordinates":[132.43333000000001,-2.63333],"type":"Point"}
}