{
  "type": "Feature",
  "properties": {
    "gn:admin1_code":"30",
    "gn:asciiname":"Warnasari",
    "gn:country_code":"ID",
    "gn:dem":88,
    "gn:feature_class":"P",
    "gn:feature_code":"PPL",
    "gn:name":"Warnasari",
    "gn:population":0,
    "gn:timezone":"Asia/Jakarta",
    "iso:country":"ID",
    "name:ind_x_preferred":[
        "Warnasari"
    ],
    "wof:name":"Warnasari",
    "wof:placetype":"locality"
},
  "geometry": {"coordinates":[107.44861000000002,-6.52167],"type":"Point"}
}