{
  "type": "Feature",
  "properties": {
    "gn:admin1_code":"30.0",
    "gn:asciiname":"Datarwangi",
    "gn:country_code":"ID",
    "gn:dem":179,
    "gn:feature_class":"P",
    "gn:feature_code":"PPL",
    "gn:name":"Datarwangi",
    "gn:population":0,
    "gn:timezone":"Asia/Jakarta",
    "iso:country":"ID",
    "name:ind_x_preferred":[
        "Datarwangi"
    ],
    "wof:name":"Datarwangi",
    "wof:placetype":"locality"
},
  "geometry": {"coordinates":[107.4117,-7.4666],"type":"Point"}
}