{
  "type": "Feature",
  "properties": {
    "gn:admin1_code":"26",
    "gn:asciiname":"Sukarama",
    "gn:country_code":"ID",
    "gn:dem":813,
    "gn:feature_class":"P",
    "gn:feature_code":"PPLA3",
    "gn:name":"Sukarama",
    "gn:population":0,
    "gn:timezone":"Asia/Jakarta",
    "iso:country":"ID",
    "name:ind_x_preferred":[
        "Sukarama"
    ],
    "wof:lang_x_official":[
        "ind"
    ],
    "wof:lang_x_spoken":[
        "ind",
        "eng"
    ],
    "wof:name":"Sukarama",
    "wof:placetype":"locality"
},
  "geometry": {"coordinates":[98.3015,2.6465],"type":"Point"}
}