{
  "type": "Feature",
  "properties": {
    "gn:admin1_code":"8.0",
    "gn:asciiname":"Krajan Balung Kidul",
    "gn:country_code":"ID",
    "gn:dem":26,
    "gn:feature_class":"P",
    "gn:feature_code":"PPL",
    "gn:name":"Krajan Balung Kidul",
    "gn:population":0,
    "gn:timezone":"Asia/Jakarta",
    "iso:country":"ID",
    "name:ind_x_preferred":[
        "Krajan Balung Kidul"
    ],
    "wof:name":"Krajan Balung Kidul",
    "wof:placetype":"locality"
},
  "geometry": {"coordinates":[113.5394,-8.285],"type":"Point"}
}