{
  "type": "Feature",
  "properties": {
    "gn:country":"ID",
    "gn:fcode":"PPLA3",
    "gn:pop":0,
    "iso:country":"ID",
    "name:ind_x_preferred":[
        "Bayongbong"
    ],
    "name:unk_x_variant":[
        "Bajongbong"
    ],
    "qs:name":"Bayongbong",
    "qs:photos_9r":0,
    "qs:photos_sr":0,
    "qs:pop_sr":"0",
    "wof:name":"Bayongbong",
    "wof:placetype":"locality",
    "wof:population":0
},
  "geometry": {"coordinates":[107.8197,-7.2716],"type":"Point"}
}