{
  "type": "Feature",
  "properties": {
    "gn:admin1_code":"33.0",
    "gn:asciiname":"Cibeureum Dua",
    "gn:country_code":"ID",
    "gn:dem":100,
    "gn:feature_class":"P",
    "gn:feature_code":"PPL",
    "gn:name":"Cibeureum Dua",
    "gn:population":0,
    "gn:timezone":"Asia/Jakarta",
    "iso:country":"ID",
    "name:ind_x_preferred":[
        "Cibeureum Dua"
    ],
    "wof:name":"Cibeureum Dua",
    "wof:placetype":"locality"
},
  "geometry": {"coordinates":[106.10550000000001,-6.407],"type":"Point"}
}