{
  "type": "Feature",
  "properties": {
    "gn:admin1_code":"7.0",
    "gn:asciiname":"Jompo",
    "gn:country_code":"ID",
    "gn:dem":36,
    "gn:feature_class":"P",
    "gn:feature_code":"PPL",
    "gn:name":"Jompo",
    "gn:population":0,
    "gn:timezone":"Asia/Jakarta",
    "iso:country":"ID",
    "name:ind_x_preferred":[
        "Jompo"
    ],
    "wof:name":"Jompo",
    "wof:placetype":"locality"
},
  "geometry": {"coordinates":[109.33693999999998,-7.43778],"type":"Point"}
}