{
  "type": "Feature",
  "properties": {
    "iso:country":"ID",
    "name:ceb_x_preferred":[
        "Kubu"
    ],
    "name:ind_x_preferred":[
        "Kubu"
    ],
    "name:msa_x_preferred":[
        "Kubu"
    ],
    "name:nld_x_preferred":[
        "Kubu"
    ],
    "name:rus_x_preferred":[
        "\u041a\u0443\u0431\u0443"
    ],
    "name:swe_x_preferred":[
        "Kubu"
    ],
    "qs:name":"Kubu",
    "qs:name_adm0":"Indonesia",
    "qs:name_adm1":"Bali",
    "qs:photos":33,
    "qs:photos_1k":7,
    "qs:photos_9k":1,
    "qs:photos_9r":2,
    "qs:photos_all":33,
    "qs:photos_sr":2,
    "qs:placetype":"Town",
    "qs:pop_sr":"0",
    "wd:wordcount":101,
    "wof:lang_x_official":[
        "ind"
    ],
    "wof:lang_x_spoken":[
        "ind",
        "eng"
    ],
    "wof:name":"Kubu",
    "wof:placetype":"locality"
},
  "geometry": {"coordinates":[115.522682,-8.216247],"type":"Point"}
}