{
  "type": "Feature",
  "properties": {
    "gn:admin1_code":"34",
    "gn:asciiname":"Helemohengu",
    "gn:country_code":"ID",
    "gn:dem":78,
    "gn:feature_class":"P",
    "gn:feature_code":"PPL",
    "gn:name":"Helemohengu",
    "gn:population":0,
    "gn:timezone":"Asia/Makassar",
    "iso:country":"ID",
    "name:ind_x_preferred":[
        "Helemohengu"
    ],
    "wof:name":"Helemohengu",
    "wof:placetype":"locality"
},
  "geometry": {"coordinates":[122.7801,0.6612],"type":"Point"}
}