{
  "type": "Feature",
  "properties": {
    "gn:admin1_code":"8",
    "gn:asciiname":"Pandanrejo",
    "gn:country_code":"ID",
    "gn:dem":734,
    "gn:feature_class":"P",
    "gn:feature_code":"PPL",
    "gn:name":"Pandanrejo",
    "gn:population":0,
    "gn:timezone":"Asia/Jakarta",
    "iso:country":"ID",
    "name:ind_x_preferred":[
        "Pandanrejo"
    ],
    "wof:name":"Pandanrejo",
    "wof:placetype":"locality"
},
  "geometry": {"coordinates":[112.7915,-7.98],"type":"Point"}
}