{
  "type": "Feature",
  "properties": {
    "gn:admin1_code":"10.0",
    "gn:asciiname":"Pomahan",
    "gn:country_code":"ID",
    "gn:dem":291,
    "gn:feature_class":"P",
    "gn:feature_code":"PPL",
    "gn:name":"Pomahan",
    "gn:population":0,
    "gn:timezone":"Asia/Jakarta",
    "iso:country":"ID",
    "name:ind_x_preferred":[
        "Pomahan"
    ],
    "wof:name":"Pomahan",
    "wof:placetype":"locality"
},
  "geometry": {"coordinates":[110.70028000000001,-8.0575],"type":"Point"}
}