{
  "type": "Feature",
  "properties": {
    "gn:admin1_code":"7.0",
    "gn:asciiname":"Nglandeyan",
    "gn:country_code":"ID",
    "gn:dem":64,
    "gn:feature_class":"P",
    "gn:feature_code":"PPL",
    "gn:name":"Nglandeyan",
    "gn:population":0,
    "gn:timezone":"Asia/Jakarta",
    "iso:country":"ID",
    "name:ind_x_preferred":[
        "Nglandeyan"
    ],
    "wof:name":"Nglandeyan",
    "wof:placetype":"locality"
},
  "geometry": {"coordinates":[111.5365,-7.1614],"type":"Point"}
}