{
  "type": "Feature",
  "properties": {
    "gn:admin1_code":"8.0",
    "gn:asciiname":"Sambongrejo",
    "gn:country_code":"ID",
    "gn:dem":170,
    "gn:feature_class":"P",
    "gn:feature_code":"PPL",
    "gn:name":"Sambongrejo",
    "gn:population":0,
    "gn:timezone":"Asia/Jakarta",
    "iso:country":"ID",
    "name:ind_x_preferred":[
        "Sambongrejo"
    ],
    "name:und_x_variant":[
        "Sambungredjo",
        "Sambungrejo"
    ],
    "wof:lang_x_official":[
        "ind"
    ],
    "wof:lang_x_spoken":[
        "ind",
        "eng"
    ],
    "wof:name":"Sambongrejo",
    "wof:placetype":"locality"
},
  "geometry": {"coordinates":[111.8373,-7.4182],"type":"Point"}
}