{
  "type": "Feature",
  "properties": {
    "gn:admin1_code":"26.0",
    "gn:asciiname":"Huta Bagas",
    "gn:country_code":"ID",
    "gn:dem":1034,
    "gn:feature_class":"P",
    "gn:feature_code":"PPL",
    "gn:name":"Huta Bagas",
    "gn:population":0,
    "gn:timezone":"Asia/Jakarta",
    "iso:country":"ID",
    "name:ind_x_preferred":[
        "Huta Bagas"
    ],
    "wof:name":"Huta Bagas",
    "wof:placetype":"locality"
},
  "geometry": {"coordinates":[98.6332,2.6219],"type":"Point"}
}