{
  "type": "Feature",
  "properties": {
    "gn:admin1_code":"38.0",
    "gn:asciiname":"Bontoborusu",
    "gn:country_code":"ID",
    "gn:dem":17,
    "gn:feature_class":"P",
    "gn:feature_code":"PPL",
    "gn:name":"Bontoborusu",
    "gn:population":0,
    "gn:timezone":"Asia/Makassar",
    "iso:country":"ID",
    "name:ind_x_preferred":[
        "Bontoborusu"
    ],
    "name:und_x_variant":[
        "Bonto-baroe",
        "Bonto-barusu"
    ],
    "wof:lang_x_official":[
        "ind"
    ],
    "wof:lang_x_spoken":[
        "ind",
        "eng"
    ],
    "wof:name":"Bontoborusu",
    "wof:placetype":"locality"
},
  "geometry": {"coordinates":[120.4766,-6.3204],"type":"Point"}
}