{
  "type": "Feature",
  "properties": {
    "gn:admin1_code":"1",
    "gn:asciiname":"Matang Menye",
    "gn:country_code":"ID",
    "gn:dem":13,
    "gn:feature_class":"P",
    "gn:feature_code":"PPL",
    "gn:name":"Matang Menye",
    "gn:population":0,
    "gn:timezone":"Asia/Jakarta",
    "iso:country":"ID",
    "name:ind_x_preferred":[
        "Matang Menye"
    ],
    "name:und_x_variant":[
        "Matangmenje"
    ],
    "wof:name":"Matang Menye",
    "wof:placetype":"locality"
},
  "geometry": {"coordinates":[97.3039,5.0369],"type":"Point"}
}