{
  "type": "Feature",
  "properties": {
    "gn:admin1_code":"0.0",
    "gn:asciiname":"Sungainamang",
    "gn:cc2":"ID",
    "gn:country_code":"ID",
    "gn:dem":4,
    "gn:feature_class":"P",
    "gn:feature_code":"PPL",
    "gn:name":"Sungainamang",
    "gn:population":0,
    "gn:timezone":"Asia/Makassar",
    "iso:country":"ID",
    "name:ind_x_preferred":[
        "Sungaipanangah"
    ],
    "name:und_x_variant":[
        "Soengainamang",
        "Sungainamang"
    ],
    "wof:name":"Sungainamang",
    "wof:placetype":"locality"
},
  "geometry": {"coordinates":[115.11667,-2.46667],"type":"Point"}
}