{
  "type": "Feature",
  "properties": {
    "gn:admin1_code":"22.0",
    "gn:asciiname":"Talabente",
    "gn:country_code":"ID",
    "gn:dem":7,
    "gn:feature_class":"P",
    "gn:feature_code":"PPL",
    "gn:name":"Talabente",
    "gn:population":0,
    "gn:timezone":"Asia/Makassar",
    "iso:country":"ID",
    "name:ind_x_preferred":[
        "Talabente"
    ],
    "wof:name":"Talabente",
    "wof:placetype":"locality"
},
  "geometry": {"coordinates":[122.02249999999999,-4.7555],"type":"Point"}
}