{
  "type": "Feature",
  "properties": {
    "gn:admin1_code":"0.0",
    "gn:asciiname":"Wabar",
    "gn:cc2":"ID",
    "gn:country_code":"ID",
    "gn:dem":-9999,
    "gn:feature_class":"P",
    "gn:feature_code":"PPL",
    "gn:name":"Wabar",
    "gn:population":0,
    "gn:timezone":"Asia/Jayapura",
    "iso:country":"ID",
    "name:und_x_variant":[
        "Krore",
        "Wambar",
        "Wabar"
    ],
    "wof:name":"Wabar",
    "wof:placetype":"locality"
},
  "geometry": {"coordinates":[132.46666999999999,-3.05],"type":"Point"}
}