{
  "type": "Feature",
  "properties": {
    "gn:admin1_code":"21.0",
    "gn:asciiname":"Rano",
    "gn:country_code":"ID",
    "gn:dem":80,
    "gn:feature_class":"P",
    "gn:feature_code":"PPL",
    "gn:name":"Rano",
    "gn:population":0,
    "gn:timezone":"Asia/Makassar",
    "iso:country":"ID",
    "name:ceb_x_preferred":[
        "Rano"
    ],
    "name:fra_x_preferred":[
        "Rano"
    ],
    "name:hau_x_preferred":[
        "Rano"
    ],
    "name:ind_x_preferred":[
        "Rano"
    ],
    "name:ita_x_preferred":[
        "Rano"
    ],
    "name:por_x_preferred":[
        "Rano"
    ],
    "name:spa_x_preferred":[
        "Rano"
    ],
    "wof:lang_x_official":[
        "ind"
    ],
    "wof:lang_x_spoken":[
        "ind",
        "eng"
    ],
    "wof:name":"Rano",
    "wof:placetype":"locality"
},
  "geometry": {"coordinates":[119.77160000000001,-0.4313],"type":"Point"}
}