{
  "type": "Feature",
  "properties": {
    "gn:admin1_code":"31.0",
    "gn:asciiname":"Tokin",
    "gn:country_code":"ID",
    "gn:dem":492,
    "gn:feature_class":"P",
    "gn:feature_code":"PPL",
    "gn:name":"Tokin",
    "gn:population":0,
    "gn:timezone":"Asia/Makassar",
    "iso:country":"ID",
    "name:ind_x_preferred":[
        "Tokin"
    ],
    "name:srp_x_preferred":[
        "\u0422\u043e\u043a\u0438\u043d"
    ],
    "wof:name":"Tokin",
    "wof:placetype":"locality"
},
  "geometry": {"coordinates":[124.52330000000001,1.0814],"type":"Point"}
}