{
  "type": "Feature",
  "properties": {
    "gn:admin1_code":"7",
    "gn:asciiname":"Ngasem Satu",
    "gn:country_code":"ID",
    "gn:dem":6,
    "gn:feature_class":"P",
    "gn:feature_code":"PPL",
    "gn:name":"Ngasem Satu",
    "gn:population":0,
    "gn:timezone":"Asia/Jakarta",
    "iso:country":"ID",
    "name:ind_x_preferred":[
        "Ngasem Satu"
    ],
    "wof:name":"Ngasem Satu",
    "wof:placetype":"locality"
},
  "geometry": {"coordinates":[110.5877,-6.8884],"type":"Point"}
}