{
  "type": "Feature",
  "properties": {
    "gn:admin1_code":"15.0",
    "gn:asciiname":"Dusunbaru",
    "gn:country_code":"ID",
    "gn:dem":916,
    "gn:feature_class":"P",
    "gn:feature_code":"PPL",
    "gn:name":"Dusunbaru",
    "gn:population":0,
    "gn:timezone":"Asia/Jakarta",
    "iso:country":"ID",
    "name:und_x_variant":[
        "Doesoenbaroe",
        "Dusunbaru"
    ],
    "wof:name":"Dusunbaru",
    "wof:placetype":"locality"
},
  "geometry": {"coordinates":[104.2236,-4.99458],"type":"Point"}
}