{
  "type": "Feature",
  "properties": {
    "gn:admin1_code":"17",
    "gn:asciiname":"Lekongsiwak",
    "gn:country_code":"ID",
    "gn:dem":140,
    "gn:feature_class":"P",
    "gn:feature_code":"PPL",
    "gn:name":"Lekongsiwak",
    "gn:population":0,
    "gn:timezone":"Asia/Makassar",
    "iso:country":"ID",
    "name:ind_x_preferred":[
        "Lekongsiwak"
    ],
    "wof:name":"Lekongsiwak",
    "wof:placetype":"locality"
},
  "geometry": {"coordinates":[116.217,-8.6014],"type":"Point"}
}