{
  "type": "Feature",
  "properties": {
    "gn:admin1_code":"8",
    "gn:asciiname":"Jaddih Tehgah Dua",
    "gn:country_code":"ID",
    "gn:dem":22,
    "gn:feature_class":"P",
    "gn:feature_code":"PPL",
    "gn:name":"Jaddih Tehgah Dua",
    "gn:population":0,
    "gn:timezone":"Asia/Jakarta",
    "iso:country":"ID",
    "name:ind_x_preferred":[
        "Jaddih Tehgah Dua"
    ],
    "name:und_x_variant":[
        "Jadih Tehgah Dua"
    ],
    "wof:name":"Jaddih Tehgah Dua",
    "wof:placetype":"locality"
},
  "geometry": {"coordinates":[112.7473,-7.0859],"type":"Point"}
}