{
  "type": "Feature",
  "properties": {
    "gn:admin1_code":"22",
    "gn:asciiname":"Majapahit",
    "gn:country_code":"ID",
    "gn:dem":19,
    "gn:feature_class":"P",
    "gn:feature_code":"PPL",
    "gn:name":"Majapahit",
    "gn:population":0,
    "gn:timezone":"Asia/Makassar",
    "iso:country":"ID",
    "name:ind_x_preferred":[
        "Majapahit"
    ],
    "wof:name":"Majapahit",
    "wof:placetype":"locality"
},
  "geometry": {"coordinates":[121.07989999999999,-3.1561],"type":"Point"}
}