{
  "type": "Feature",
  "properties": {
    "gn:admin1_code":"7",
    "gn:asciiname":"Sobokerto",
    "gn:country_code":"ID",
    "gn:dem":584,
    "gn:feature_class":"P",
    "gn:feature_code":"PPL",
    "gn:name":"Sobokerto",
    "gn:population":0,
    "gn:timezone":"Asia/Jakarta",
    "iso:country":"ID",
    "name:ind_x_preferred":[
        "Sobokerto"
    ],
    "wof:name":"Sobokerto",
    "wof:placetype":"locality"
},
  "geometry": {"coordinates":[111.08444,-7.75889],"type":"Point"}
}