{
  "type": "Feature",
  "properties": {
    "gn:admin1_code":"30",
    "gn:asciiname":"Cipayung Empat",
    "gn:cc2":"ID",
    "gn:country_code":"ID",
    "gn:dem":131,
    "gn:feature_class":"P",
    "gn:feature_code":"PPL",
    "gn:name":"Cipayung Empat",
    "gn:population":0,
    "gn:timezone":"Asia/Jakarta",
    "iso:country":"ID",
    "name:und_x_variant":[
        "Tjipajung Empat",
        "Tjipajung 4",
        "Cipayung Empat"
    ],
    "wof:lang_x_official":[
        "ind"
    ],
    "wof:lang_x_spoken":[
        "ind",
        "eng"
    ],
    "wof:name":"Cipayung Empat",
    "wof:placetype":"locality"
},
  "geometry": {"coordinates":[106.82944000000001,-6.4825],"type":"Point"}
}