{
  "type": "Feature",
  "properties": {
    "gn:country":"ID",
    "gn:fcode":"ADM4",
    "gn:pop":0,
    "iso:country":"ID",
    "name:ind_x_preferred":[
        "Kelurahan Pati Lor"
    ],
    "name:unk_x_variant":[
        "Pati Lor"
    ],
    "qs:name":"Kelurahan Pati Lor",
    "qs:photos_9r":0,
    "qs:photos_sr":0,
    "qs:pop_sr":"0",
    "wof:name":"Kelurahan Pati Lor",
    "wof:placetype":"localadmin",
    "wof:population":0
},
  "geometry": {"coordinates":[111.0381,-6.7453],"type":"Point"}
}