{
  "type": "Feature",
  "properties": {
    "gn:admin1_code":"8.0",
    "gn:asciiname":"Taman",
    "gn:country_code":"ID",
    "gn:dem":36,
    "gn:feature_class":"P",
    "gn:feature_code":"PPL",
    "gn:name":"Taman",
    "gn:population":0,
    "gn:timezone":"Asia/Jakarta",
    "iso:country":"ID",
    "name:ceb_x_preferred":[
        "Taman"
    ],
    "name:deu_x_preferred":[
        "Taman"
    ],
    "name:fra_x_preferred":[
        "Taman"
    ],
    "name:heb_x_preferred":[
        "\u05d8\u05d0\u05de\u05d0\u05df"
    ],
    "name:ind_x_preferred":[
        "Taman"
    ],
    "name:jpn_x_preferred":[
        "\u30bf\u30de\u30f3"
    ],
    "name:nld_x_preferred":[
        "Taman"
    ],
    "name:nor_x_preferred":[
        "Taman"
    ],
    "name:por_x_preferred":[
        "Taman"
    ],
    "name:swe_x_preferred":[
        "Taman"
    ],
    "name:zho_x_preferred":[
        "Taman"
    ],
    "wof:lang_x_official":[
        "ind"
    ],
    "wof:lang_x_spoken":[
        "ind",
        "eng"
    ],
    "wof:name":"Taman",
    "wof:placetype":"locality"
},
  "geometry": {"coordinates":[115.3164,-6.8621],"type":"Point"}
}