{
  "type": "Feature",
  "properties": {
    "gn:admin1_code":"07",
    "gn:asciiname":"Urutsewu",
    "gn:country_code":"ID",
    "gn:dem":726,
    "gn:feature_class":"P",
    "gn:feature_code":"PPL",
    "gn:name":"Urutsewu",
    "gn:population":0,
    "gn:timezone":"Asia/Jakarta",
    "iso:country":"ID",
    "wof:name":"Urutsewu",
    "wof:placetype":"locality"
},
  "geometry": {"coordinates":[110.53639,-7.43944],"type":"Point"}
}