{
  "type": "Feature",
  "properties": {
    "gn:admin1_code":"30.0",
    "gn:asciiname":"Bebedahan Kidul",
    "gn:country_code":"ID",
    "gn:dem":797,
    "gn:feature_class":"P",
    "gn:feature_code":"PPL",
    "gn:name":"Bebedahan Kidul",
    "gn:population":0,
    "gn:timezone":"Asia/Jakarta",
    "iso:country":"ID",
    "name:ind_x_preferred":[
        "Bebedahan Kidul"
    ],
    "wof:name":"Bebedahan Kidul",
    "wof:placetype":"locality"
},
  "geometry": {"coordinates":[108.012,-7.1703],"type":"Point"}
}