{
  "type": "Feature",
  "properties": {
    "gn:admin1_code":"1",
    "gn:asciiname":"Tenembak Juhar Dua",
    "gn:country_code":"ID",
    "gn:dem":203,
    "gn:feature_class":"P",
    "gn:feature_code":"PPL",
    "gn:name":"Tenembak Juhar Dua",
    "gn:population":0,
    "gn:timezone":"Asia/Jakarta",
    "iso:country":"ID",
    "name:ind_x_preferred":[
        "Tenembak Juhar Dua"
    ],
    "name:und_x_variant":[
        "Tenembak Juhar 2"
    ],
    "wof:lang_x_official":[
        "ind"
    ],
    "wof:lang_x_spoken":[
        "ind",
        "eng"
    ],
    "wof:name":"Tenembak Juhar Dua",
    "wof:placetype":"locality"
},
  "geometry": {"coordinates":[97.8515,3.4855],"type":"Point"}
}