{
  "type": "Feature",
  "properties": {
    "gn:admin1_code":"33",
    "gn:asciiname":"Garawano",
    "gn:country_code":"ID",
    "gn:dem":119,
    "gn:feature_class":"P",
    "gn:feature_code":"PPL",
    "gn:name":"Garawano",
    "gn:population":0,
    "gn:timezone":"Asia/Jakarta",
    "iso:country":"ID",
    "name:ind_x_preferred":[
        "Garawano"
    ],
    "wof:name":"Garawano",
    "wof:placetype":"locality"
},
  "geometry": {"coordinates":[106.1687,-6.2639],"type":"Point"}
}