{
  "type": "Feature",
  "properties": {
    "gn:admin1_code":"18.0",
    "gn:asciiname":"Neponono",
    "gn:country_code":"ID",
    "gn:dem":1007,
    "gn:feature_class":"P",
    "gn:feature_code":"PPL",
    "gn:name":"Neponono",
    "gn:population":0,
    "gn:timezone":"Asia/Makassar",
    "iso:country":"ID",
    "name:ind_x_preferred":[
        "Neponono"
    ],
    "wof:name":"Neponono",
    "wof:placetype":"locality"
},
  "geometry": {"coordinates":[124.28100000000001,-9.7833],"type":"Point"}
}