{
  "type": "Feature",
  "properties": {
    "gn:admin1_code":"30.0",
    "gn:asciiname":"Garasi",
    "gn:country_code":"ID",
    "gn:dem":72,
    "gn:feature_class":"P",
    "gn:feature_code":"PPL",
    "gn:name":"Garasi",
    "gn:population":0,
    "gn:timezone":"Asia/Jakarta",
    "iso:country":"ID",
    "name:ind_x_preferred":[
        "Garasi"
    ],
    "wof:name":"Garasi",
    "wof:placetype":"locality"
},
  "geometry": {"coordinates":[106.54300000000001,-7.3557],"type":"Point"}
}