{
  "type": "Feature",
  "properties": {
    "gn:admin1_code":"38",
    "gn:asciiname":"Pandoso",
    "gn:country_code":"ID",
    "gn:dem":76,
    "gn:feature_class":"P",
    "gn:feature_code":"PPL",
    "gn:name":"Pandoso",
    "gn:population":0,
    "gn:timezone":"Asia/Makassar",
    "iso:country":"ID",
    "name:ind_x_preferred":[
        "Pandoso"
    ],
    "wof:name":"Pandoso",
    "wof:placetype":"locality"
},
  "geometry": {"coordinates":[120.3082,-3.4037],"type":"Point"}
}