{
  "type": "Feature",
  "properties": {
    "gn:admin1_code":"30.0",
    "gn:asciiname":"Pataregan",
    "gn:country_code":"ID",
    "gn:dem":180,
    "gn:feature_class":"P",
    "gn:feature_code":"PPL",
    "gn:name":"Pataregan",
    "gn:population":0,
    "gn:timezone":"Asia/Jakarta",
    "iso:country":"ID",
    "name:ind_x_preferred":[
        "Pataregan"
    ],
    "name:und_x_variant":[
        "Pateregan"
    ],
    "wof:name":"Pataregan",
    "wof:placetype":"locality"
},
  "geometry": {"coordinates":[108.5676,-7.0147],"type":"Point"}
}