{
  "type": "Feature",
  "properties": {
    "gn:admin1_code":"26",
    "gn:asciiname":"Partimelayu",
    "gn:country_code":"ID",
    "gn:dem":422,
    "gn:feature_class":"P",
    "gn:feature_code":"PPL",
    "gn:name":"Partimelayu",
    "gn:population":0,
    "gn:timezone":"Asia/Jakarta",
    "iso:country":"ID",
    "name:ind_x_preferred":[
        "Partimelayu"
    ],
    "name:und_x_variant":[
        "Pertimelaju"
    ],
    "wof:lang_x_official":[
        "ind"
    ],
    "wof:lang_x_spoken":[
        "ind",
        "eng"
    ],
    "wof:name":"Partimelayu",
    "wof:placetype":"locality"
},
  "geometry": {"coordinates":[98.8086,3.1104],"type":"Point"}
}