{
  "type": "Feature",
  "properties": {
    "gn:admin1_code":"30",
    "gn:asciiname":"Cibodas",
    "gn:country_code":"ID",
    "gn:dem":10,
    "gn:feature_class":"P",
    "gn:feature_code":"PPL",
    "gn:name":"Cibodas",
    "gn:population":0,
    "gn:timezone":"Asia/Jakarta",
    "iso:country":"ID",
    "name:ind_x_preferred":[
        "Cibodas"
    ],
    "name:jav_x_preferred":[
        "Cibodas"
    ],
    "name:msa_x_preferred":[
        "Cibodas"
    ],
    "name:sun_x_preferred":[
        "Cibodas"
    ],
    "wof:name":"Cibodas",
    "wof:placetype":"locality"
},
  "geometry": {"coordinates":[106.325,-6.04222],"type":"Point"}
}