{
  "type": "Feature",
  "properties": {
    "gn:admin1_code":"41.0",
    "gn:asciiname":"Pao",
    "gn:country_code":"ID",
    "gn:dem":1321,
    "gn:feature_class":"P",
    "gn:feature_code":"PPL",
    "gn:name":"Pao",
    "gn:population":0,
    "gn:timezone":"Asia/Makassar",
    "iso:country":"ID",
    "name:ind_x_preferred":[
        "Pao"
    ],
    "wof:name":"Pao",
    "wof:placetype":"locality"
},
  "geometry": {"coordinates":[119.37130000000001,-2.9165],"type":"Point"}
}