{
  "type": "Feature",
  "properties": {
    "gn:admin1_code":"18.0",
    "gn:asciiname":"Habigahar",
    "gn:country_code":"ID",
    "gn:dem":80,
    "gn:feature_class":"P",
    "gn:feature_code":"PPL",
    "gn:name":"Habigahar",
    "gn:population":0,
    "gn:timezone":"Asia/Makassar",
    "iso:country":"ID",
    "name:ind_x_preferred":[
        "Habigahar"
    ],
    "wof:name":"Habigahar",
    "wof:placetype":"locality"
},
  "geometry": {"coordinates":[122.2487,-8.6561],"type":"Point"}
}