{
  "type": "Feature",
  "properties": {
    "gn:admin1_code":"26",
    "gn:asciiname":"Adian Nangka",
    "gn:country_code":"ID",
    "gn:dem":655,
    "gn:feature_class":"P",
    "gn:feature_code":"PPL",
    "gn:name":"Adian Nangka",
    "gn:population":0,
    "gn:timezone":"Asia/Jakarta",
    "iso:country":"ID",
    "name:ind_x_preferred":[
        "Adian Nangka"
    ],
    "wof:name":"Adian Nangka",
    "wof:placetype":"locality"
},
  "geometry": {"coordinates":[98.1908,2.8233],"type":"Point"}
}