{
  "type": "Feature",
  "properties": {
    "gn:admin1_code":"11.0",
    "gn:asciiname":"Kerandjian",
    "gn:country_code":"ID",
    "gn:dem":11,
    "gn:feature_class":"P",
    "gn:feature_code":"PPL",
    "gn:name":"Kerandjian",
    "gn:population":0,
    "gn:timezone":"Asia/Pontianak",
    "iso:country":"ID",
    "name:ind_x_preferred":[
        "Kerandjian"
    ],
    "wof:name":"Kerandjian",
    "wof:placetype":"locality"
},
  "geometry": {"coordinates":[110.21448999999998,-1.75427],"type":"Point"}
}