{
  "type": "Feature",
  "properties": {
    "gn:admin1_code":"7.0",
    "gn:asciiname":"Turen",
    "gn:country_code":"ID",
    "gn:dem":98,
    "gn:feature_class":"P",
    "gn:feature_code":"PPL",
    "gn:name":"Turen",
    "gn:population":0,
    "gn:timezone":"Asia/Jakarta",
    "iso:country":"ID",
    "wof:name":"Turen",
    "wof:placetype":"locality"
},
  "geometry": {"coordinates":[110.79971999999999,-7.66778],"type":"Point"}
}