{
  "type": "Feature",
  "properties": {
    "gn:admin1_code":"17.0",
    "gn:asciiname":"Terbis",
    "gn:country_code":"ID",
    "gn:dem":167,
    "gn:feature_class":"P",
    "gn:feature_code":"PPL",
    "gn:name":"Terbis",
    "gn:population":0,
    "gn:timezone":"Asia/Makassar",
    "iso:country":"ID",
    "name:ind_x_preferred":[
        "Terbis"
    ],
    "wof:name":"Terbis",
    "wof:placetype":"locality"
},
  "geometry": {"coordinates":[116.36660000000001,-8.2548],"type":"Point"}
}