{
  "type": "Feature",
  "properties": {
    "gn:admin1_code":"30.0",
    "gn:asciiname":"Negla",
    "gn:country_code":"ID",
    "gn:dem":939,
    "gn:feature_class":"P",
    "gn:feature_code":"PPL",
    "gn:name":"Negla",
    "gn:population":0,
    "gn:timezone":"Asia/Jakarta",
    "iso:country":"ID",
    "name:ind_x_preferred":[
        "Negla"
    ],
    "wof:name":"Negla",
    "wof:placetype":"locality"
},
  "geometry": {"coordinates":[107.52978,-7.33584],"type":"Point"}
}