{
  "type": "Feature",
  "properties": {
    "gn:admin1_code":"18",
    "gn:asciiname":"Perumahanlangkasdamai",
    "gn:country_code":"ID",
    "gn:dem":1062,
    "gn:feature_class":"P",
    "gn:feature_code":"PPL",
    "gn:name":"Perumahanlangkasdamai",
    "gn:population":0,
    "gn:timezone":"Asia/Makassar",
    "iso:country":"ID",
    "name:ind_x_preferred":[
        "Perumahanlangkasdamai"
    ],
    "wof:name":"Perumahanlangkasdamai",
    "wof:placetype":"locality"
},
  "geometry": {"coordinates":[120.4402,-8.5907],"type":"Point"}
}