{
  "type": "Feature",
  "properties": {
    "gn:admin1_code":"7",
    "gn:asciiname":"Sempulawang",
    "gn:country_code":"ID",
    "gn:dem":326,
    "gn:feature_class":"P",
    "gn:feature_code":"PPL",
    "gn:name":"Sempulawang",
    "gn:population":0,
    "gn:timezone":"Asia/Jakarta",
    "iso:country":"ID",
    "name:ind_x_preferred":[
        "Sempulawang"
    ],
    "wof:name":"Sempulawang",
    "wof:placetype":"locality"
},
  "geometry": {"coordinates":[110.0523,-7.0057],"type":"Point"}
}