{
  "type": "Feature",
  "properties": {
    "gn:admin1_code":"30",
    "gn:asciiname":"Galumpit",
    "gn:country_code":"ID",
    "gn:dem":820,
    "gn:feature_class":"P",
    "gn:feature_code":"PPL",
    "gn:name":"Galumpit",
    "gn:population":0,
    "gn:timezone":"Asia/Jakarta",
    "iso:country":"ID",
    "name:ind_x_preferred":[
        "Galumpit"
    ],
    "wof:name":"Galumpit",
    "wof:placetype":"locality"
},
  "geometry": {"coordinates":[107.8681,-7.0935],"type":"Point"}
}