{
  "type": "Feature",
  "properties": {
    "gn:admin1_code":"7",
    "gn:asciiname":"Klitik",
    "gn:country_code":"ID",
    "gn:dem":373,
    "gn:feature_class":"P",
    "gn:feature_code":"PPL",
    "gn:name":"Klitik",
    "gn:population":0,
    "gn:timezone":"Asia/Jakarta",
    "iso:country":"ID",
    "name:ind_x_preferred":[
        "Klitik"
    ],
    "wof:name":"Klitik",
    "wof:placetype":"locality"
},
  "geometry": {"coordinates":[111.03861000000001,-7.57972],"type":"Point"}
}