{
  "type": "Feature",
  "properties": {
    "gn:admin1_code":"22",
    "gn:asciiname":"Wolulu",
    "gn:country_code":"ID",
    "gn:dem":4,
    "gn:feature_class":"P",
    "gn:feature_code":"PPL",
    "gn:name":"Wolulu",
    "gn:population":0,
    "gn:timezone":"Asia/Makassar",
    "iso:country":"ID",
    "name:ind_x_preferred":[
        "Wolulu"
    ],
    "wof:name":"Wolulu",
    "wof:placetype":"locality"
},
  "geometry": {"coordinates":[121.5198,-4.4386],"type":"Point"}
}