{
  "type": "Feature",
  "properties": {
    "gn:admin1_code":"38.0",
    "gn:asciiname":"Pengga",
    "gn:country_code":"ID",
    "gn:dem":33,
    "gn:feature_class":"P",
    "gn:feature_code":"PPL",
    "gn:name":"Pengga",
    "gn:population":0,
    "gn:timezone":"Asia/Makassar",
    "iso:country":"ID",
    "name:ind_x_preferred":[
        "Pengga"
    ],
    "name:und_x_variant":[
        "Poengga"
    ],
    "wof:name":"Pengga",
    "wof:placetype":"locality"
},
  "geometry": {"coordinates":[120.508,-5.839],"type":"Point"}
}