{
  "type": "Feature",
  "properties": {
    "gn:admin1_code":"8.0",
    "gn:asciiname":"Pengincengan",
    "gn:country_code":"ID",
    "gn:dem":103,
    "gn:feature_class":"P",
    "gn:feature_code":"PPL",
    "gn:name":"Pengincengan",
    "gn:population":0,
    "gn:timezone":"Asia/Jakarta",
    "iso:country":"ID",
    "name:ind_x_preferred":[
        "Pengincengan"
    ],
    "wof:name":"Pengincengan",
    "wof:placetype":"locality"
},
  "geometry": {"coordinates":[111.9632,-7.8647],"type":"Point"}
}