{
  "type": "Feature",
  "properties": {
    "gn:admin1_code":"0.0",
    "gn:asciiname":"Bajoog",
    "gn:cc2":"ID",
    "gn:country_code":"ID",
    "gn:dem":41,
    "gn:feature_class":"P",
    "gn:feature_code":"PPL",
    "gn:name":"Bajoog",
    "gn:population":0,
    "gn:timezone":"Asia/Pontianak",
    "iso:country":"ID",
    "name:und_x_variant":[
        "Badjoog",
        "Bajoog"
    ],
    "wof:name":"Bajoog",
    "wof:placetype":"locality"
},
  "geometry": {"coordinates":[114.23333,-1.23333],"type":"Point"}
}