{
  "type": "Feature",
  "properties": {
    "gn:admin1_code":"38",
    "gn:asciiname":"Bentengpancasila",
    "gn:country_code":"ID",
    "gn:dem":309,
    "gn:feature_class":"P",
    "gn:feature_code":"PPL",
    "gn:name":"Bentengpancasila",
    "gn:population":0,
    "gn:timezone":"Asia/Makassar",
    "iso:country":"ID",
    "name:ind_x_preferred":[
        "Bentengpancasila"
    ],
    "name:und_x_variant":[
        "Bontobero",
        "Bontob\u00e9roe"
    ],
    "wof:lang_x_official":[
        "ind"
    ],
    "wof:lang_x_spoken":[
        "ind",
        "eng"
    ],
    "wof:name":"Bentengpancasila",
    "wof:placetype":"locality"
},
  "geometry": {"coordinates":[120.5132,-5.9024],"type":"Point"}
}