{
  "type": "Feature",
  "properties": {
    "gn:admin1_code":"8.0",
    "gn:asciiname":"Krajan Satu Putukrejo",
    "gn:country_code":"ID",
    "gn:dem":531,
    "gn:feature_class":"P",
    "gn:feature_code":"PPL",
    "gn:name":"Krajan Satu Putukrejo",
    "gn:population":0,
    "gn:timezone":"Asia/Jakarta",
    "iso:country":"ID",
    "name:ind_x_preferred":[
        "Krajan Satu Putukrejo"
    ],
    "wof:name":"Krajan Satu Putukrejo",
    "wof:placetype":"locality"
},
  "geometry": {"coordinates":[112.4503,-8.2383],"type":"Point"}
}