{
  "type": "Feature",
  "properties": {
    "gn:admin1_code":"30",
    "gn:asciiname":"Cikarang Satu",
    "gn:country_code":"ID",
    "gn:dem":62,
    "gn:feature_class":"P",
    "gn:feature_code":"PPL",
    "gn:name":"Cikarang Satu",
    "gn:population":0,
    "gn:timezone":"Asia/Jakarta",
    "iso:country":"ID",
    "name:ind_x_preferred":[
        "Cikarang Satu"
    ],
    "wof:name":"Cikarang Satu",
    "wof:placetype":"locality"
},
  "geometry": {"coordinates":[107.06111,-6.40722],"type":"Point"}
}