{
  "type": "Feature",
  "properties": {
    "gn:admin1_code":"17",
    "gn:asciiname":"Kelawuulan",
    "gn:country_code":"ID",
    "gn:dem":16,
    "gn:feature_class":"P",
    "gn:feature_code":"PPL",
    "gn:name":"Kelawuulan",
    "gn:population":0,
    "gn:timezone":"Asia/Makassar",
    "iso:country":"ID",
    "name:ind_x_preferred":[
        "Kelawuulan"
    ],
    "wof:name":"Kelawuulan",
    "wof:placetype":"locality"
},
  "geometry": {"coordinates":[116.4391,-8.9111],"type":"Point"}
}