{
  "type": "Feature",
  "properties": {
    "gn:admin1_code":"15.0",
    "gn:asciiname":"Sukomargo",
    "gn:country_code":"ID",
    "gn:dem":930,
    "gn:feature_class":"P",
    "gn:feature_code":"PPL",
    "gn:name":"Sukomargo",
    "gn:population":0,
    "gn:timezone":"Asia/Jakarta",
    "iso:country":"ID",
    "name:ind_x_preferred":[
        "Sukomargo"
    ],
    "name:und_x_variant":[
        "Soek\u014fmargo"
    ],
    "wof:lang_x_official":[
        "ind"
    ],
    "wof:lang_x_spoken":[
        "ind",
        "eng"
    ],
    "wof:name":"Sukomargo",
    "wof:placetype":"locality"
},
  "geometry": {"coordinates":[104.02713,-5.00328],"type":"Point"}
}