{
  "type": "Feature",
  "properties": {
    "gn:admin1_code":"38.0",
    "gn:asciiname":"Parada",
    "gn:country_code":"ID",
    "gn:dem":993,
    "gn:feature_class":"P",
    "gn:feature_code":"PPL",
    "gn:name":"Parada",
    "gn:population":0,
    "gn:timezone":"Asia/Makassar",
    "iso:country":"ID",
    "name:ind_x_preferred":[
        "Parada"
    ],
    "wof:name":"Parada",
    "wof:placetype":"locality"
},
  "geometry": {"coordinates":[120.0856,-3.0942],"type":"Point"}
}