{
  "type": "Feature",
  "properties": {
    "gn:admin1_code":"8",
    "gn:asciiname":"Jatian Lor",
    "gn:country_code":"ID",
    "gn:dem":186,
    "gn:feature_class":"P",
    "gn:feature_code":"PPL",
    "gn:name":"Jatian Lor",
    "gn:population":0,
    "gn:timezone":"Asia/Jakarta",
    "iso:country":"ID",
    "name:ind_x_preferred":[
        "Jatian Lor"
    ],
    "wof:name":"Jatian Lor",
    "wof:placetype":"locality"
},
  "geometry": {"coordinates":[113.77249999999999,-8.152],"type":"Point"}
}