{
  "type": "Feature",
  "properties": {
    "gn:admin1_code":"17",
    "gn:asciiname":"Tiwugalih",
    "gn:country_code":"ID",
    "gn:dem":111,
    "gn:feature_class":"P",
    "gn:feature_code":"PPL",
    "gn:name":"Tiwugalih",
    "gn:population":0,
    "gn:timezone":"Asia/Makassar",
    "iso:country":"ID",
    "name:ind_x_preferred":[
        "Tiwugalih"
    ],
    "wof:name":"Tiwugalih",
    "wof:placetype":"locality"
},
  "geometry": {"coordinates":[116.28660000000001,-8.7115],"type":"Point"}
}