{
  "type": "Feature",
  "properties": {
    "gn:admin1_code":"30.0",
    "gn:asciiname":"Panenjoan",
    "gn:country_code":"ID",
    "gn:dem":887,
    "gn:feature_class":"P",
    "gn:feature_code":"PPL",
    "gn:name":"Panenjoan",
    "gn:population":0,
    "gn:timezone":"Asia/Jakarta",
    "iso:country":"ID",
    "name:ind_x_preferred":[
        "Panenjoan"
    ],
    "wof:name":"Panenjoan",
    "wof:placetype":"locality"
},
  "geometry": {"coordinates":[107.9486,-7.3655],"type":"Point"}
}