{
  "type": "Feature",
  "properties": {
    "gn:admin1_code":"30",
    "gn:asciiname":"Solokondang",
    "gn:country_code":"ID",
    "gn:dem":706,
    "gn:feature_class":"P",
    "gn:feature_code":"PPL",
    "gn:name":"Solokondang",
    "gn:population":0,
    "gn:timezone":"Asia/Jakarta",
    "iso:country":"ID",
    "name:ind_x_preferred":[
        "Solokondang"
    ],
    "wof:name":"Solokondang",
    "wof:placetype":"locality"
},
  "geometry": {"coordinates":[107.38388999999999,-6.98],"type":"Point"}
}