{
  "type": "Feature",
  "properties": {
    "gn:admin1_code":"26.0",
    "gn:asciiname":"Tanjung Slamat",
    "gn:country_code":"ID",
    "gn:dem":14,
    "gn:feature_class":"P",
    "gn:feature_code":"PPL",
    "gn:name":"Tanjung Slamat",
    "gn:population":0,
    "gn:timezone":"Asia/Jakarta",
    "iso:country":"ID",
    "name:ind_x_preferred":[
        "Tanjung Slamat"
    ],
    "name:und_x_variant":[
        "Tandjungslamat",
        "Tandjungselamat",
        "Tandjoengslamat"
    ],
    "wof:lang_x_official":[
        "ind"
    ],
    "wof:lang_x_spoken":[
        "ind",
        "eng"
    ],
    "wof:name":"Tanjung Slamat",
    "wof:placetype":"locality"
},
  "geometry": {"coordinates":[98.3297,3.8316],"type":"Point"}
}