{
  "type": "Feature",
  "properties": {
    "gn:admin1_code":"8.0",
    "gn:asciiname":"Mindahan",
    "gn:country_code":"ID",
    "gn:dem":72,
    "gn:feature_class":"P",
    "gn:feature_code":"PPL",
    "gn:name":"Mindahan",
    "gn:population":0,
    "gn:timezone":"Asia/Jakarta",
    "iso:country":"ID",
    "name:ind_x_preferred":[
        "Mindahan"
    ],
    "wof:name":"Mindahan",
    "wof:placetype":"locality"
},
  "geometry": {"coordinates":[112.3133,-7.2828],"type":"Point"}
}