{
  "type": "Feature",
  "properties": {
    "gn:admin1_code":"8.0",
    "gn:asciiname":"Krajan Harjokuncaran",
    "gn:country_code":"ID",
    "gn:dem":629,
    "gn:feature_class":"P",
    "gn:feature_code":"PPLA4",
    "gn:name":"Krajan Harjokuncaran",
    "gn:population":0,
    "gn:timezone":"Asia/Jakarta",
    "iso:country":"ID",
    "name:ind_x_preferred":[
        "Krajan Harjokuncaran"
    ],
    "wof:name":"Krajan Harjokuncaran",
    "wof:placetype":"locality"
},
  "geometry": {"coordinates":[112.70350000000001,-8.2639],"type":"Point"}
}