{
  "type": "Feature",
  "properties": {
    "gn:admin1_code":"15.0",
    "gn:asciiname":"Umbulan Tumijajar",
    "gn:country_code":"ID",
    "gn:dem":37,
    "gn:feature_class":"P",
    "gn:feature_code":"PPL",
    "gn:name":"Umbulan Tumijajar",
    "gn:population":0,
    "gn:timezone":"Asia/Jakarta",
    "iso:country":"ID",
    "name:ind_x_preferred":[
        "Umbulan Tumijajar"
    ],
    "name:ind_x_variant":[
        "Umbulantumijajar",
        "Oemboelan Toemidjadjar Satoe"
    ],
    "wof:lang_x_official":[
        "ind"
    ],
    "wof:lang_x_spoken":[
        "ind",
        "eng"
    ],
    "wof:name":"Umbulan Tumijajar",
    "wof:placetype":"locality"
},
  "geometry": {"coordinates":[105.09362,-4.64741],"type":"Point"}
}