{
  "type": "Feature",
  "properties": {
    "gn:admin1_code":"26",
    "gn:asciiname":"Bandar",
    "gn:country_code":"ID",
    "gn:dem":185,
    "gn:feature_class":"P",
    "gn:feature_code":"PPL",
    "gn:name":"Bandar",
    "gn:population":0,
    "gn:timezone":"Asia/Jakarta",
    "iso:country":"ID",
    "name:cat_x_preferred":[
        "Bandar"
    ],
    "name:ceb_x_preferred":[
        "Bandar"
    ],
    "name:deu_x_preferred":[
        "Bandar"
    ],
    "name:ind_x_preferred":[
        "Bandar"
    ],
    "name:mkd_x_preferred":[
        "\u0411\u0430\u043d\u0434\u0430\u0440"
    ],
    "name:mlg_x_preferred":[
        "Bandar"
    ],
    "name:nld_x_preferred":[
        "Bandar"
    ],
    "name:swe_x_preferred":[
        "Bandar"
    ],
    "name:uzb_x_preferred":[
        "Bandar"
    ],
    "wof:name":"Bandar",
    "wof:placetype":"locality"
},
  "geometry": {"coordinates":[98.9425,3.1741],"type":"Point"}
}