{
  "type": "Feature",
  "properties": {
    "gn:country":"ID",
    "gn:fcode":"PPLA3",
    "gn:pop":0,
    "iso:country":"ID",
    "name:ind_x_preferred":[
        "Kambang"
    ],
    "qs:name":"Kambang",
    "qs:photos_9r":0,
    "qs:photos_sr":0,
    "qs:pop_sr":"0",
    "wof:name":"Kambang",
    "wof:placetype":"locality",
    "wof:population":0
},
  "geometry": {"coordinates":[100.7209,-1.6904],"type":"Point"}
}