{
  "type": "Feature",
  "properties": {
    "gn:admin1_code":"7",
    "gn:asciiname":"Karangmalang",
    "gn:country_code":"ID",
    "gn:dem":36,
    "gn:feature_class":"P",
    "gn:feature_code":"PPL",
    "gn:name":"Karangmalang",
    "gn:population":0,
    "gn:timezone":"Asia/Jakarta",
    "iso:country":"ID",
    "name:ind_x_preferred":[
        "Karangmalang"
    ],
    "wof:name":"Karangmalang",
    "wof:placetype":"locality"
},
  "geometry": {"coordinates":[110.97709999999999,-7.0942],"type":"Point"}
}