{
  "type": "Feature",
  "properties": {
    "gn:admin1_code":"07",
    "gn:asciiname":"Canden",
    "gn:country_code":"ID",
    "gn:dem":729,
    "gn:feature_class":"P",
    "gn:feature_code":"PPL",
    "gn:name":"Canden",
    "gn:population":0,
    "gn:timezone":"Asia/Jakarta",
    "iso:country":"ID",
    "wof:name":"Canden",
    "wof:placetype":"locality"
},
  "geometry": {"coordinates":[110.54472,-7.52917],"type":"Point"}
}