{
  "type": "Feature",
  "properties": {
    "gn:admin1_code":"26.0",
    "gn:asciiname":"Talunkota",
    "gn:country_code":"ID",
    "gn:dem":1154,
    "gn:feature_class":"P",
    "gn:feature_code":"PPL",
    "gn:name":"Talunkota",
    "gn:population":0,
    "gn:timezone":"Asia/Jakarta",
    "iso:country":"ID",
    "name:ind_x_preferred":[
        "Talunkota"
    ],
    "wof:name":"Talunkota",
    "wof:placetype":"locality"
},
  "geometry": {"coordinates":[98.43049999999999,3.0292],"type":"Point"}
}