{
  "type": "Feature",
  "properties": {
    "gn:admin1_code":"17",
    "gn:asciiname":"Mispauh",
    "gn:country_code":"ID",
    "gn:dem":101,
    "gn:feature_class":"P",
    "gn:feature_code":"PPL",
    "gn:name":"Mispauh",
    "gn:population":0,
    "gn:timezone":"Asia/Makassar",
    "iso:country":"ID",
    "name:ind_x_preferred":[
        "Mispauh"
    ],
    "wof:name":"Mispauh",
    "wof:placetype":"locality"
},
  "geometry": {"coordinates":[116.2649,-8.7071],"type":"Point"}
}