{
  "type": "Feature",
  "properties": {
    "gn:admin1_code":"26",
    "gn:asciiname":"Aras Kabu Lima",
    "gn:country_code":"ID",
    "gn:dem":6,
    "gn:feature_class":"P",
    "gn:feature_code":"PPL",
    "gn:name":"Aras Kabu Lima",
    "gn:population":0,
    "gn:timezone":"Asia/Jakarta",
    "iso:country":"ID",
    "name:ind_x_preferred":[
        "Aras Kabu Lima"
    ],
    "name:und_x_variant":[
        "Araskabu 5"
    ],
    "wof:lang_x_official":[
        "ind"
    ],
    "wof:lang_x_spoken":[
        "ind",
        "eng"
    ],
    "wof:name":"Aras Kabu Lima",
    "wof:placetype":"locality"
},
  "geometry": {"coordinates":[98.8451,3.6293],"type":"Point"}
}