{
  "type": "Feature",
  "properties": {
    "gn:admin1_code":"7",
    "gn:asciiname":"Daleman",
    "gn:country_code":"ID",
    "gn:dem":59,
    "gn:feature_class":"P",
    "gn:feature_code":"PPL",
    "gn:name":"Daleman",
    "gn:population":0,
    "gn:timezone":"Asia/Jakarta",
    "iso:country":"ID",
    "name:ind_x_preferred":[
        "Daleman"
    ],
    "wof:name":"Daleman",
    "wof:placetype":"locality"
},
  "geometry": {"coordinates":[109.98611,-7.72389],"type":"Point"}
}