{
  "type": "Feature",
  "properties": {
    "gn:admin1_code":"7.0",
    "gn:asciiname":"Karangbenda",
    "gn:country_code":"ID",
    "gn:dem":152,
    "gn:feature_class":"P",
    "gn:feature_code":"PPL",
    "gn:name":"Karangbenda",
    "gn:population":0,
    "gn:timezone":"Asia/Jakarta",
    "iso:country":"ID",
    "name:ind_x_preferred":[
        "Karangbenda"
    ],
    "wof:name":"Karangbenda",
    "wof:placetype":"locality"
},
  "geometry": {"coordinates":[109.42,-7.35861],"type":"Point"}
}