{
  "type": "Feature",
  "properties": {
    "gn:admin1_code":"30.0",
    "gn:asciiname":"Puncakbaru",
    "gn:country_code":"ID",
    "gn:dem":1034,
    "gn:feature_class":"P",
    "gn:feature_code":"PPLA4",
    "gn:name":"Puncakbaru",
    "gn:population":0,
    "gn:timezone":"Asia/Jakarta",
    "iso:country":"ID",
    "name:ind_x_preferred":[
        "Puncakbaru"
    ],
    "wof:lang_x_official":[
        "ind"
    ],
    "wof:lang_x_spoken":[
        "ind",
        "eng"
    ],
    "wof:name":"Puncakbaru",
    "wof:placetype":"locality"
},
  "geometry": {"coordinates":[107.4481,-7.3348],"type":"Point"}
}