{
  "type": "Feature",
  "properties": {
    "gn:admin1_code":"7.0",
    "gn:asciiname":"Gramang",
    "gn:country_code":"ID",
    "gn:dem":156,
    "gn:feature_class":"P",
    "gn:feature_code":"PPL",
    "gn:name":"Gramang",
    "gn:population":0,
    "gn:timezone":"Asia/Jakarta",
    "iso:country":"ID",
    "name:ind_x_preferred":[
        "Gramang"
    ],
    "wof:name":"Gramang",
    "wof:placetype":"locality"
},
  "geometry": {"coordinates":[109.48472,-7.54],"type":"Point"}
}