{
  "type": "Feature",
  "properties": {
    "gn:admin1_code":"30",
    "gn:asciiname":"Paratag",
    "gn:country_code":"ID",
    "gn:dem":785,
    "gn:feature_class":"P",
    "gn:feature_code":"PPL",
    "gn:name":"Paratag",
    "gn:population":0,
    "gn:timezone":"Asia/Jakarta",
    "iso:country":"ID",
    "name:ind_x_preferred":[
        "Paratag"
    ],
    "wof:name":"Paratag",
    "wof:placetype":"locality"
},
  "geometry": {"coordinates":[107.49889,-6.71333],"type":"Point"}
}