{
  "type": "Feature",
  "properties": {
    "gn:admin1_code":"30",
    "gn:asciiname":"Citenong",
    "gn:country_code":"ID",
    "gn:dem":1002,
    "gn:feature_class":"P",
    "gn:feature_code":"PPL",
    "gn:name":"Citenong",
    "gn:population":0,
    "gn:timezone":"Asia/Jakarta",
    "iso:country":"ID",
    "name:ind_x_preferred":[
        "Citenong"
    ],
    "name:und_x_variant":[
        "Tjilemong",
        "Cilemong"
    ],
    "wof:lang_x_official":[
        "ind"
    ],
    "wof:lang_x_spoken":[
        "ind",
        "eng"
    ],
    "wof:name":"Citenong",
    "wof:placetype":"locality"
},
  "geometry": {"coordinates":[107.2727,-7.0144],"type":"Point"}
}