{
  "type": "Feature",
  "properties": {
    "gn:admin1_code":"8",
    "gn:asciiname":"Tinggen",
    "gn:country_code":"ID",
    "gn:dem":556,
    "gn:feature_class":"P",
    "gn:feature_code":"PPL",
    "gn:name":"Tinggen",
    "gn:population":0,
    "gn:timezone":"Asia/Jakarta",
    "iso:country":"ID",
    "name:ind_x_preferred":[
        "Tinggen"
    ],
    "wof:name":"Tinggen",
    "wof:placetype":"locality"
},
  "geometry": {"coordinates":[111.28972,-7.64944],"type":"Point"}
}