{
  "type": "Feature",
  "properties": {
    "gn:admin1_code":"22.0",
    "gn:asciiname":"Mololaloanodahu",
    "gn:country_code":"ID",
    "gn:dem":51,
    "gn:feature_class":"P",
    "gn:feature_code":"PPL",
    "gn:name":"Mololaloanodahu",
    "gn:population":0,
    "gn:timezone":"Asia/Makassar",
    "iso:country":"ID",
    "name:ind_x_preferred":[
        "Mololaloanodahu"
    ],
    "wof:name":"Mololaloanodahu",
    "wof:placetype":"locality"
},
  "geometry": {"coordinates":[121.92149999999999,-4.0426],"type":"Point"}
}