{
  "type": "Feature",
  "properties": {
    "gn:admin1_code":"30",
    "gn:asciiname":"Balungtunggal",
    "gn:country_code":"ID",
    "gn:dem":398,
    "gn:feature_class":"P",
    "gn:feature_code":"PPL",
    "gn:name":"Balungtunggal",
    "gn:population":0,
    "gn:timezone":"Asia/Jakarta",
    "iso:country":"ID",
    "name:ind_x_preferred":[
        "Balungtunggal"
    ],
    "wof:name":"Balungtunggal",
    "wof:placetype":"locality"
},
  "geometry": {"coordinates":[107.15416999999999,-6.84111],"type":"Point"}
}