{
  "type": "Feature",
  "properties": {
    "gn:admin1_code":"7.0",
    "gn:asciiname":"Limbangan",
    "gn:country_code":"ID",
    "gn:dem":481,
    "gn:feature_class":"P",
    "gn:feature_code":"PPL",
    "gn:name":"Limbangan",
    "gn:population":0,
    "gn:timezone":"Asia/Jakarta",
    "iso:country":"ID",
    "wof:name":"Limbangan",
    "wof:placetype":"locality"
},
  "geometry": {"coordinates":[110.02694,-7.58667],"type":"Point"}
}