{
  "type": "Feature",
  "properties": {
    "gn:admin1_code":"7.0",
    "gn:asciiname":"Wringinanom",
    "gn:country_code":"ID",
    "gn:dem":381,
    "gn:feature_class":"P",
    "gn:feature_code":"PPL",
    "gn:name":"Wringinanom",
    "gn:population":0,
    "gn:timezone":"Asia/Jakarta",
    "iso:country":"ID",
    "wof:name":"Wringinanom",
    "wof:placetype":"locality"
},
  "geometry": {"coordinates":[110.22194,-7.45],"type":"Point"}
}