{
  "type": "Feature",
  "properties": {
    "gn:admin1_code":"26",
    "gn:asciiname":"Sitirangga",
    "gn:country_code":"ID",
    "gn:dem":324,
    "gn:feature_class":"P",
    "gn:feature_code":"PPL",
    "gn:name":"Sitirangga",
    "gn:population":0,
    "gn:timezone":"Asia/Jakarta",
    "iso:country":"ID",
    "name:ind_x_preferred":[
        "Sitirangga"
    ],
    "wof:name":"Sitirangga",
    "wof:placetype":"locality"
},
  "geometry": {"coordinates":[98.9384,1.6308],"type":"Point"}
}