{
  "type": "Feature",
  "properties": {
    "gn:admin1_code":"33.0",
    "gn:asciiname":"Sukaliuh",
    "gn:country_code":"ID",
    "gn:dem":30,
    "gn:feature_class":"P",
    "gn:feature_code":"PPL",
    "gn:name":"Sukaliuh",
    "gn:population":0,
    "gn:timezone":"Asia/Jakarta",
    "iso:country":"ID",
    "name:ind_x_preferred":[
        "Sukaliuh"
    ],
    "wof:name":"Sukaliuh",
    "wof:placetype":"locality"
},
  "geometry": {"coordinates":[105.8336,-6.5768],"type":"Point"}
}