{
  "type": "Feature",
  "properties": {
    "gn:admin1_code":"30",
    "gn:asciiname":"Kamiran",
    "gn:country_code":"ID",
    "gn:dem":287,
    "gn:feature_class":"P",
    "gn:feature_code":"PPL",
    "gn:name":"Kamiran",
    "gn:population":0,
    "gn:timezone":"Asia/Jakarta",
    "iso:country":"ID",
    "name:ind_x_preferred":[
        "Kamiran"
    ],
    "wof:name":"Kamiran",
    "wof:placetype":"locality"
},
  "geometry": {"coordinates":[107.21917000000001,-6.81194],"type":"Point"}
}