{
  "type": "Feature",
  "properties": {
    "gn:admin1_code":"8",
    "gn:asciiname":"Sanan",
    "gn:country_code":"ID",
    "gn:dem":138,
    "gn:feature_class":"P",
    "gn:feature_code":"PPL",
    "gn:name":"Sanan",
    "gn:population":0,
    "gn:timezone":"Asia/Jakarta",
    "iso:country":"ID",
    "name:ind_x_preferred":[
        "Sanan"
    ],
    "wof:name":"Sanan",
    "wof:placetype":"locality"
},
  "geometry": {"coordinates":[111.52679999999999,-7.9803],"type":"Point"}
}