{
  "type": "Feature",
  "properties": {
    "gn:admin1_code":"18.0",
    "gn:asciiname":"Edo",
    "gn:country_code":"ID",
    "gn:dem":328,
    "gn:feature_class":"P",
    "gn:feature_code":"PPL",
    "gn:name":"Edo",
    "gn:population":0,
    "gn:timezone":"Asia/Makassar",
    "iso:country":"ID",
    "name:ara_x_preferred":[
        "\u0625\u064a\u062f\u0648"
    ],
    "name:bel_x_preferred":[
        "\u042d\u0434\u0430"
    ],
    "name:ben_x_preferred":[
        "\u098f\u09a6\u09cb"
    ],
    "name:bos_x_preferred":[
        "Edo"
    ],
    "name:bre_x_preferred":[
        "Edo"
    ],
    "name:cat_x_preferred":[
        "Edo"
    ],
    "name:ces_x_preferred":[
        "Edo"
    ],
    "name:cym_x_preferred":[
        "Edo"
    ],
    "name:dan_x_preferred":[
        "Edo"
    ],
    "name:deu_x_preferred":[
        "Edo"
    ],
    "name:ell_x_preferred":[
        "\u0388\u03bd\u03c4\u03bf"
    ],
    "name:epo_x_preferred":[
        "Edo"
    ],
    "name:est_x_preferred":[
        "Edo"
    ],
    "name:eus_x_preferred":[
        "Edo"
    ],
    "name:fas_x_preferred":[
        "\u0627\u062f\u0648"
    ],
    "name:fra_x_preferred":[
        "Edo"
    ],
    "name:heb_x_preferred":[
        "\u05d0\u05d3\u05d5"
    ],
    "name:hrv_x_preferred":[
        "Edo"
    ],
    "name:hun_x_preferred":[
        "Edo"
    ],
    "name:ind_x_preferred":[
        "Edo"
    ],
    "name:ita_x_preferred":[
        "Edo"
    ],
    "name:lit_x_preferred":[
        "Edas"
    ],
    "name:mal_x_preferred":[
        "\u0d0f\u0d21\u0d4b"
    ],
    "name:mon_x_preferred":[
        "\u042d\u0434\u043e"
    ],
    "name:msa_x_preferred":[
        "Edo"
    ],
    "name:nld_x_preferred":[
        "Edo"
    ],
    "name:nor_x_preferred":[
        "Edo"
    ],
    "name:pol_x_preferred":[
        "Edo"
    ],
    "name:por_x_preferred":[
        "Edo"
    ],
    "name:rus_x_preferred":[
        "\u042d\u0434\u043e"
    ],
    "name:spa_x_preferred":[
        "Edo"
    ],
    "name:swe_x_preferred":[
        "Edo"
    ],
    "name:tur_x_preferred":[
        "Edo"
    ],
    "name:ukr_x_preferred":[
        "\u0415\u0434\u043e"
    ],
    "name:urd_x_preferred":[
        "\u0627\u062f\u0648"
    ],
    "name:vie_x_preferred":[
        "Edo"
    ],
    "wof:lang_x_official":[
        "ind"
    ],
    "wof:lang_x_spoken":[
        "ind",
        "eng"
    ],
    "wof:name":"Edo",
    "wof:placetype":"locality"
},
  "geometry": {"coordinates":[122.2801,-8.6956],"type":"Point"}
}