{
  "type": "Feature",
  "properties": {
    "gn:admin1_code":"18.0",
    "gn:asciiname":"Edo",
    "gn:country_code":"ID",
    "gn:dem":328,
    "gn:feature_class":"P",
    "gn:feature_code":"PPL",
    "gn:name":"Edo",
    "gn:population":0,
    "gn:timezone":"Asia/Makassar",
    "iso:country":"ID",
    "name:ind_x_preferred":[
        "Edo"
    ],
    "wof:name":"Edo",
    "wof:placetype":"locality"
},
  "geometry": {"coordinates":[122.2801,-8.6956],"type":"Point"}
}