{
  "type": "Feature",
  "properties": {
    "gn:admin1_code":"30.0",
    "gn:asciiname":"Ikar",
    "gn:country_code":"ID",
    "gn:dem":578,
    "gn:feature_class":"P",
    "gn:feature_code":"PPLA4",
    "gn:name":"Ikar",
    "gn:population":0,
    "gn:timezone":"Asia/Jakarta",
    "iso:country":"ID",
    "name:ind_x_preferred":[
        "Ikar"
    ],
    "wof:name":"Ikar",
    "wof:placetype":"locality"
},
  "geometry": {"coordinates":[107.9735,-7.0204],"type":"Point"}
}