{
  "type": "Feature",
  "properties": {
    "gn:admin1_code":"15.0",
    "gn:asciiname":"Umbulan Tungbasung",
    "gn:country_code":"ID",
    "gn:dem":41,
    "gn:feature_class":"P",
    "gn:feature_code":"PPL",
    "gn:name":"Umbulan Tungbasung",
    "gn:population":0,
    "gn:timezone":"Asia/Jakarta",
    "iso:country":"ID",
    "name:ind_x_preferred":[
        "Umbulan Tungbasung"
    ],
    "name:ind_x_variant":[
        "Umbulantungbatung",
        "Oemboelan Toengbasoeng"
    ],
    "wof:name":"Umbulan Tungbasung",
    "wof:placetype":"locality"
},
  "geometry": {"coordinates":[105.2516,-4.3582],"type":"Point"}
}