{
  "type": "Feature",
  "properties": {
    "gn:admin1_code":"07",
    "gn:asciiname":"Tomo",
    "gn:country_code":"ID",
    "gn:dem":838,
    "gn:feature_class":"P",
    "gn:feature_code":"PPL",
    "gn:name":"Tomo",
    "gn:population":0,
    "gn:timezone":"Asia/Jakarta",
    "iso:country":"ID",
    "name:ceb_x_preferred":[
        "Tomo"
    ],
    "name:ita_x_preferred":[
        "Tomo"
    ],
    "name:nld_x_preferred":[
        "Tomo"
    ],
    "name:spa_x_preferred":[
        "Tomo"
    ],
    "name:swe_x_preferred":[
        "Tomo"
    ],
    "name:tgl_x_preferred":[
        "Tomo"
    ],
    "wof:name":"Tomo",
    "wof:placetype":"locality"
},
  "geometry": {"coordinates":[110.49444,-7.415],"type":"Point"}
}