{
  "type": "Feature",
  "properties": {
    "gn:admin1_code":"30.0",
    "gn:asciiname":"Cikadu",
    "gn:country_code":"ID",
    "gn:dem":181,
    "gn:feature_class":"P",
    "gn:feature_code":"PPL",
    "gn:name":"Cikadu",
    "gn:population":0,
    "gn:timezone":"Asia/Jakarta",
    "iso:country":"ID",
    "name:ind_x_preferred":[
        "Cikadu"
    ],
    "name:und_x_variant":[
        "Tjikadu",
        "Cikadu"
    ],
    "wof:lang_x_official":[
        "ind"
    ],
    "wof:lang_x_spoken":[
        "ind",
        "eng"
    ],
    "wof:name":"Cikadu",
    "wof:placetype":"locality"
},
  "geometry": {"coordinates":[106.6631,-7.3211],"type":"Point"}
}