{
  "type": "Feature",
  "properties": {
    "gn:admin1_code":"26",
    "gn:asciiname":"Afdeling Satu",
    "gn:country_code":"ID",
    "gn:dem":161,
    "gn:feature_class":"P",
    "gn:feature_code":"PPL",
    "gn:name":"Afdeling Satu",
    "gn:population":0,
    "gn:timezone":"Asia/Jakarta",
    "iso:country":"ID",
    "name:ind_x_preferred":[
        "Afdeling Satu"
    ],
    "name:und_x_variant":[
        "AFD 1"
    ],
    "wof:lang_x_official":[
        "ind"
    ],
    "wof:lang_x_spoken":[
        "ind",
        "eng"
    ],
    "wof:name":"Afdeling Satu",
    "wof:placetype":"locality"
},
  "geometry": {"coordinates":[99.3605,2.7605],"type":"Point"}
}