{
  "type": "Feature",
  "properties": {
    "gn:admin1_code":"1",
    "gn:asciiname":"Ietare Dua",
    "gn:country_code":"ID",
    "gn:dem":14,
    "gn:feature_class":"P",
    "gn:feature_code":"PPL",
    "gn:name":"Ietare Dua",
    "gn:population":0,
    "gn:timezone":"Asia/Jakarta",
    "iso:country":"ID",
    "name:ind_x_preferred":[
        "Ietare Dua"
    ],
    "name:und_x_variant":[
        "Ie Tare 2"
    ],
    "wof:name":"Ietare Dua",
    "wof:placetype":"locality"
},
  "geometry": {"coordinates":[97.1101,5.0932],"type":"Point"}
}