{
  "type": "Feature",
  "properties": {
    "gn:admin1_code":"07",
    "gn:asciiname":"Kepatran",
    "gn:country_code":"ID",
    "gn:dem":712,
    "gn:feature_class":"P",
    "gn:feature_code":"PPL",
    "gn:name":"Kepatran",
    "gn:population":0,
    "gn:timezone":"Asia/Jakarta",
    "iso:country":"ID",
    "name:und_x_variant":[
        "Kepakran",
        "Kepatran"
    ],
    "wof:name":"Kepatran",
    "wof:placetype":"locality"
},
  "geometry": {"coordinates":[110.34417000000001,-7.33556],"type":"Point"}
}