{
  "type": "Feature",
  "properties": {
    "gn:admin1_code":"18.0",
    "gn:asciiname":"Fukatbat",
    "gn:country_code":"ID",
    "gn:dem":368,
    "gn:feature_class":"P",
    "gn:feature_code":"PPL",
    "gn:name":"Fukatbat",
    "gn:population":0,
    "gn:timezone":"Asia/Makassar",
    "iso:country":"ID",
    "name:ind_x_preferred":[
        "Fukatbat"
    ],
    "wof:name":"Fukatbat",
    "wof:placetype":"locality"
},
  "geometry": {"coordinates":[124.2577,-9.9194],"type":"Point"}
}