{
  "type": "Feature",
  "properties": {
    "gn:admin1_code":"26",
    "gn:asciiname":"Negeri Tongah",
    "gn:country_code":"ID",
    "gn:dem":265,
    "gn:feature_class":"P",
    "gn:feature_code":"PPL",
    "gn:name":"Negeri Tongah",
    "gn:population":0,
    "gn:timezone":"Asia/Jakarta",
    "iso:country":"ID",
    "name:ind_x_preferred":[
        "Negeri Tongah"
    ],
    "wof:name":"Negeri Tongah",
    "wof:placetype":"locality"
},
  "geometry": {"coordinates":[98.8523,3.1701],"type":"Point"}
}