{
  "type": "Feature",
  "properties": {
    "gn:admin1_code":"08",
    "gn:asciiname":"Karangsari Dua",
    "gn:cc2":"ID",
    "gn:country_code":"ID",
    "gn:dem":318,
    "gn:feature_class":"P",
    "gn:feature_code":"PPL",
    "gn:name":"Karangsari Dua",
    "gn:population":0,
    "gn:timezone":"Asia/Jakarta",
    "iso:country":"ID",
    "name:und_x_variant":[
        "Karangsari 2",
        "Karangsari Dua"
    ],
    "wof:name":"Karangsari Dua",
    "wof:placetype":"locality"
},
  "geometry": {"coordinates":[112.57306,-8.21889],"type":"Point"}
}