{
  "type": "Feature",
  "properties": {
    "gn:admin1_code":"15.0",
    "gn:asciiname":"Trenggalok",
    "gn:country_code":"ID",
    "gn:dem":104,
    "gn:feature_class":"P",
    "gn:feature_code":"PPL",
    "gn:name":"Trenggalok",
    "gn:population":0,
    "gn:timezone":"Asia/Jakarta",
    "iso:country":"ID",
    "name:ind_x_preferred":[
        "Trenggalok"
    ],
    "wof:name":"Trenggalok",
    "wof:placetype":"locality"
},
  "geometry": {"coordinates":[104.84428,-5.08335],"type":"Point"}
}