{
  "type": "Feature",
  "properties": {
    "gn:admin1_code":"30.0",
    "gn:asciiname":"Pasirangin Dua",
    "gn:country_code":"ID",
    "gn:dem":1047,
    "gn:feature_class":"P",
    "gn:feature_code":"PPL",
    "gn:name":"Pasirangin Dua",
    "gn:population":0,
    "gn:timezone":"Asia/Jakarta",
    "iso:country":"ID",
    "name:ind_x_preferred":[
        "Pasirangin Dua"
    ],
    "wof:name":"Pasirangin Dua",
    "wof:placetype":"locality"
},
  "geometry": {"coordinates":[107.5509,-7.2796],"type":"Point"}
}