{
  "type": "Feature",
  "properties": {
    "gn:admin1_code":"17",
    "gn:asciiname":"Sebowok",
    "gn:country_code":"ID",
    "gn:dem":31,
    "gn:feature_class":"P",
    "gn:feature_code":"PPL",
    "gn:name":"Sebowok",
    "gn:population":0,
    "gn:timezone":"Asia/Makassar",
    "iso:country":"ID",
    "name:ind_x_preferred":[
        "Sebowok"
    ],
    "wof:name":"Sebowok",
    "wof:placetype":"locality"
},
  "geometry": {"coordinates":[116.3481,-8.895],"type":"Point"}
}