{
  "type": "Feature",
  "properties": {
    "gn:admin1_code":"31.0",
    "gn:asciiname":"Woloan Dua",
    "gn:country_code":"ID",
    "gn:dem":741,
    "gn:feature_class":"P",
    "gn:feature_code":"PPL",
    "gn:name":"Woloan Dua",
    "gn:population":0,
    "gn:timezone":"Asia/Makassar",
    "iso:country":"ID",
    "name:ind_x_preferred":[
        "Woloan Dua"
    ],
    "name:und_x_variant":[
        "Wotoan",
        "Woloan",
        "Woloan 2"
    ],
    "wof:lang_x_official":[
        "ind"
    ],
    "wof:lang_x_spoken":[
        "ind",
        "eng"
    ],
    "wof:name":"Woloan Dua",
    "wof:placetype":"locality"
},
  "geometry": {"coordinates":[124.8075,1.3171],"type":"Point"}
}