{
  "type": "Feature",
  "properties": {
    "gn:admin1_code":"30.0",
    "gn:asciiname":"Ciketug",
    "gn:country_code":"ID",
    "gn:dem":364,
    "gn:feature_class":"P",
    "gn:feature_code":"PPL",
    "gn:name":"Ciketug",
    "gn:population":0,
    "gn:timezone":"Asia/Jakarta",
    "iso:country":"ID",
    "name:ind_x_preferred":[
        "Ciketug"
    ],
    "name:und_x_variant":[
        "Tjiketoek"
    ],
    "wof:name":"Ciketug",
    "wof:placetype":"locality"
},
  "geometry": {"coordinates":[108.53749999999999,-7.152],"type":"Point"}
}