{
  "type": "Feature",
  "properties": {
    "gn:admin1_code":"7.0",
    "gn:asciiname":"Purwodadi",
    "gn:country_code":"ID",
    "gn:dem":19,
    "gn:feature_class":"P",
    "gn:feature_code":"PPL",
    "gn:name":"Purwodadi",
    "gn:population":0,
    "gn:timezone":"Asia/Jakarta",
    "iso:country":"ID",
    "name:ind_x_preferred":[
        "Purwodadi"
    ],
    "name:und_x_variant":[
        "Poerwodadi",
        "Purwadadi"
    ],
    "wof:name":"Purwodadi",
    "wof:placetype":"locality"
},
  "geometry": {"coordinates":[109.42444,-7.6075],"type":"Point"}
}