{
  "type": "Feature",
  "properties": {
    "gn:admin1_code":"30.0",
    "gn:asciiname":"Cibeet",
    "gn:country_code":"ID",
    "gn:dem":261,
    "gn:feature_class":"P",
    "gn:feature_code":"PPL",
    "gn:name":"Cibeet",
    "gn:population":0,
    "gn:timezone":"Asia/Jakarta",
    "iso:country":"ID",
    "name:ind_x_preferred":[
        "Cibeet"
    ],
    "wof:name":"Cibeet",
    "wof:placetype":"locality"
},
  "geometry": {"coordinates":[107.3579,-7.4192],"type":"Point"}
}