{
  "type": "Feature",
  "properties": {
    "gn:admin1_code":"8.0",
    "gn:asciiname":"Dusun Tengah",
    "gn:country_code":"ID",
    "gn:dem":116,
    "gn:feature_class":"P",
    "gn:feature_code":"PPL",
    "gn:name":"Dusun Tengah",
    "gn:population":0,
    "gn:timezone":"Asia/Jakarta",
    "iso:country":"ID",
    "name:ind_x_preferred":[
        "Dusun Tengah"
    ],
    "wof:name":"Dusun Tengah",
    "wof:placetype":"locality"
},
  "geometry": {"coordinates":[111.3995,-7.914],"type":"Point"}
}