{
  "type": "Feature",
  "properties": {
    "gn:admin1_code":"18",
    "gn:asciiname":"Lago",
    "gn:country_code":"ID",
    "gn:dem":841,
    "gn:feature_class":"P",
    "gn:feature_code":"PPL",
    "gn:name":"Lago",
    "gn:population":0,
    "gn:timezone":"Asia/Makassar",
    "iso:country":"ID",
    "name:ceb_x_preferred":[
        "Lago"
    ],
    "name:deu_x_preferred":[
        "Lago"
    ],
    "name:fra_x_preferred":[
        "Lago"
    ],
    "name:glg_x_preferred":[
        "Lago"
    ],
    "name:ind_x_preferred":[
        "Lago"
    ],
    "name:ita_x_preferred":[
        "Lago"
    ],
    "name:nld_x_preferred":[
        "Lago"
    ],
    "name:pap_x_preferred":[
        "Lago"
    ],
    "name:por_x_preferred":[
        "Lago"
    ],
    "name:rus_x_preferred":[
        "\u041b\u0430\u0433\u043e"
    ],
    "name:sco_x_preferred":[
        "Lago"
    ],
    "name:spa_x_preferred":[
        "Lago"
    ],
    "name:srp_x_preferred":[
        "\u041b\u0430\u0433\u043e"
    ],
    "name:swe_x_preferred":[
        "Lago"
    ],
    "name:vol_x_preferred":[
        "Lago"
    ],
    "wof:lang_x_official":[
        "ind"
    ],
    "wof:lang_x_spoken":[
        "ind",
        "eng"
    ],
    "wof:name":"Lago",
    "wof:placetype":"locality"
},
  "geometry": {"coordinates":[120.6803,-8.5037],"type":"Point"}
}