{
  "type": "Feature",
  "properties": {
    "gn:admin1_code":"30",
    "gn:asciiname":"Sindangsari",
    "gn:country_code":"ID",
    "gn:dem":182,
    "gn:feature_class":"P",
    "gn:feature_code":"PPL",
    "gn:name":"Sindangsari",
    "gn:population":0,
    "gn:timezone":"Asia/Jakarta",
    "iso:country":"ID",
    "name:ind_x_preferred":[
        "Sindangsari"
    ],
    "wof:name":"Sindangsari",
    "wof:placetype":"locality"
},
  "geometry": {"coordinates":[106.82389000000001,-6.55778],"type":"Point"}
}