{
  "type": "Feature",
  "properties": {
    "gn:admin1_code":"8.0",
    "gn:asciiname":"Kambata",
    "gn:country_code":"ID",
    "gn:dem":6,
    "gn:feature_class":"P",
    "gn:feature_code":"PPL",
    "gn:name":"Kambata",
    "gn:population":0,
    "gn:timezone":"Asia/Jakarta",
    "iso:country":"ID",
    "name:ind_x_preferred":[
        "Kambata"
    ],
    "wof:name":"Kambata",
    "wof:placetype":"locality"
},
  "geometry": {"coordinates":[115.53091000000001,-6.89352],"type":"Point"}
}