{
  "type": "Feature",
  "properties": {
    "gn:admin1_code":"30",
    "gn:asciiname":"Citapen",
    "gn:country_code":"ID",
    "gn:dem":712,
    "gn:feature_class":"P",
    "gn:feature_code":"PPL",
    "gn:name":"Citapen",
    "gn:population":0,
    "gn:timezone":"Asia/Jakarta",
    "iso:country":"ID",
    "name:ind_x_preferred":[
        "Citapen"
    ],
    "wof:name":"Citapen",
    "wof:placetype":"locality"
},
  "geometry": {"coordinates":[108.035,-6.96917],"type":"Point"}
}