{
  "type": "Feature",
  "properties": {
    "gn:admin1_code":"30",
    "gn:asciiname":"Rancabuaya Satu",
    "gn:cc2":"ID",
    "gn:country_code":"ID",
    "gn:dem":38,
    "gn:feature_class":"P",
    "gn:feature_code":"PPL",
    "gn:name":"Rancabuaya Satu",
    "gn:population":0,
    "gn:timezone":"Asia/Jakarta",
    "iso:country":"ID",
    "name:und_x_variant":[
        "Rancabuaya",
        "Rantjabuaja",
        "Rancabuaya Satu"
    ],
    "wof:lang_x_official":[
        "ind"
    ],
    "wof:lang_x_spoken":[
        "ind",
        "eng"
    ],
    "wof:name":"Rancabuaya Satu",
    "wof:placetype":"locality"
},
  "geometry": {"coordinates":[106.50639,-6.31639],"type":"Point"}
}