{
  "type": "Feature",
  "properties": {
    "gn:admin1_code":"18",
    "gn:asciiname":"Mburukullu",
    "gn:country_code":"ID",
    "gn:dem":96,
    "gn:feature_class":"P",
    "gn:feature_code":"PPLA4",
    "gn:name":"Mburukullu",
    "gn:population":0,
    "gn:timezone":"Asia/Makassar",
    "iso:country":"ID",
    "name:ind_x_preferred":[
        "Mburukullu"
    ],
    "wof:lang_x_official":[
        "ind"
    ],
    "wof:lang_x_spoken":[
        "ind",
        "eng"
    ],
    "wof:name":"Mburukullu",
    "wof:placetype":"locality"
},
  "geometry": {"coordinates":[120.7569,-10.0776],"type":"Point"}
}