{
  "type": "Feature",
  "properties": {
    "gn:admin1_code":"26",
    "gn:asciiname":"Binanga",
    "gn:country_code":"ID",
    "gn:dem":390,
    "gn:feature_class":"P",
    "gn:feature_code":"PPL",
    "gn:name":"Binanga",
    "gn:population":0,
    "gn:timezone":"Asia/Jakarta",
    "iso:country":"ID",
    "name:ind_x_preferred":[
        "Binanga"
    ],
    "wof:name":"Binanga",
    "wof:placetype":"locality"
},
  "geometry": {"coordinates":[99.37773,1.49231],"type":"Point"}
}