{
  "type": "Feature",
  "properties": {
    "gn:country":"ID",
    "gn:fcode":"ADM3",
    "gn:pop":0,
    "iso:country":"ID",
    "name:ind_x_preferred":[
        "Kecamatan Pineleng"
    ],
    "name:unk_x_variant":[
        "Pineleng"
    ],
    "qs:name":"Kecamatan Pineleng",
    "qs:photos_9r":0,
    "qs:photos_sr":0,
    "qs:pop_sr":"0",
    "wd:wordcount":423,
    "wof:name":"Kecamatan Pineleng",
    "wof:placetype":"localadmin",
    "wof:population":0
},
  "geometry": {"coordinates":[124.82129999999999,1.4167],"type":"Point"}
}