{
  "type": "Feature",
  "properties": {
    "gn:admin1_code":"30.0",
    "gn:asciiname":"Padarek",
    "gn:country_code":"ID",
    "gn:dem":423,
    "gn:feature_class":"P",
    "gn:feature_code":"PPL",
    "gn:name":"Padarek",
    "gn:population":0,
    "gn:timezone":"Asia/Jakarta",
    "iso:country":"ID",
    "name:ind_x_preferred":[
        "Padarek"
    ],
    "wof:name":"Padarek",
    "wof:placetype":"locality"
},
  "geometry": {"coordinates":[108.0853,-7.3621],"type":"Point"}
}