{
  "type": "Feature",
  "properties": {
    "gn:admin1_code":"30",
    "gn:asciiname":"Kenda",
    "gn:country_code":"ID",
    "gn:dem":4,
    "gn:feature_class":"P",
    "gn:feature_code":"PPL",
    "gn:name":"Kenda",
    "gn:population":0,
    "gn:timezone":"Asia/Jakarta",
    "iso:country":"ID",
    "name:ben_x_preferred":[
        "\u0995\u09c7\u09a8\u09cd\u09a6\u09be"
    ],
    "name:bpy_x_preferred":[
        "\u0995\u09c7\u09a8\u09cd\u09a6\u09be"
    ],
    "name:ceb_x_preferred":[
        "Kenda"
    ],
    "name:ind_x_preferred":[
        "Kenda"
    ],
    "name:ita_x_preferred":[
        "Kenda"
    ],
    "name:mlg_x_preferred":[
        "Kenda"
    ],
    "name:msa_x_preferred":[
        "Kenda"
    ],
    "name:new_x_preferred":[
        "\u0915\u0947\u0928\u094d\u0926\u093e"
    ],
    "name:nld_x_preferred":[
        "Kenda"
    ],
    "name:por_x_preferred":[
        "Kenda"
    ],
    "name:swe_x_preferred":[
        "Kenda"
    ],
    "name:vie_x_preferred":[
        "Kenda"
    ],
    "wof:lang_x_official":[
        "ind"
    ],
    "wof:lang_x_spoken":[
        "ind",
        "eng"
    ],
    "wof:name":"Kenda",
    "wof:placetype":"locality"
},
  "geometry": {"coordinates":[108.41417,-6.39694],"type":"Point"}
}