{
  "type": "Feature",
  "properties": {
    "gn:admin1_code":"30",
    "gn:asciiname":"Cimpaeum Dua",
    "gn:cc2":"ID",
    "gn:country_code":"ID",
    "gn:dem":120,
    "gn:feature_class":"P",
    "gn:feature_code":"PPL",
    "gn:name":"Cimpaeum Dua",
    "gn:population":0,
    "gn:timezone":"Asia/Jakarta",
    "iso:country":"ID",
    "name:und_x_variant":[
        "Tjimpaeum Dua",
        "Tjimpaeum 2",
        "Cimpaeum Dua"
    ],
    "wof:lang_x_official":[
        "ind"
    ],
    "wof:lang_x_spoken":[
        "ind",
        "eng"
    ],
    "wof:name":"Cimpaeum Dua",
    "wof:placetype":"locality"
},
  "geometry": {"coordinates":[106.86360999999999,-6.45028],"type":"Point"}
}