{
  "type": "Feature",
  "properties": {
    "gn:admin1_code":"30.0",
    "gn:asciiname":"Kampungdesakolot",
    "gn:country_code":"ID",
    "gn:dem":23,
    "gn:feature_class":"P",
    "gn:feature_code":"PPL",
    "gn:name":"Kampungdesakolot",
    "gn:population":0,
    "gn:timezone":"Asia/Jakarta",
    "iso:country":"ID",
    "name:ind_x_preferred":[
        "Kampungdesakolot"
    ],
    "name:und_x_variant":[
        "Desakolot 2"
    ],
    "wof:lang_x_official":[
        "ind"
    ],
    "wof:lang_x_spoken":[
        "ind",
        "eng"
    ],
    "wof:name":"Kampungdesakolot",
    "wof:placetype":"locality"
},
  "geometry": {"coordinates":[108.16889999999999,-7.7653],"type":"Point"}
}