{
  "type": "Feature",
  "properties": {
    "gn:admin1_code":"7.0",
    "gn:asciiname":"Kalijaya",
    "gn:country_code":"ID",
    "gn:dem":39,
    "gn:feature_class":"P",
    "gn:feature_code":"PPL",
    "gn:name":"Kalijaya",
    "gn:population":0,
    "gn:timezone":"Asia/Jakarta",
    "iso:country":"ID",
    "name:ind_x_preferred":[
        "Kalijaya"
    ],
    "wof:name":"Kalijaya",
    "wof:placetype":"locality"
},
  "geometry": {"coordinates":[109.68889,-7.62028],"type":"Point"}
}