{
  "type": "Feature",
  "properties": {
    "gn:admin1_code":"30.0",
    "gn:asciiname":"Ciupas",
    "gn:country_code":"ID",
    "gn:dem":495,
    "gn:feature_class":"P",
    "gn:feature_code":"PPL",
    "gn:name":"Ciupas",
    "gn:population":0,
    "gn:timezone":"Asia/Jakarta",
    "iso:country":"ID",
    "name:ind_x_preferred":[
        "Ciupas"
    ],
    "name:und_x_variant":[
        "Tjiupas",
        "Ciupas",
        "Tjioepas"
    ],
    "wof:lang_x_official":[
        "ind"
    ],
    "wof:lang_x_spoken":[
        "ind",
        "eng"
    ],
    "wof:name":"Ciupas",
    "wof:placetype":"locality"
},
  "geometry": {"coordinates":[107.9704,-7.6151],"type":"Point"}
}