{
  "type": "Feature",
  "properties": {
    "gn:admin1_code":"07",
    "gn:asciiname":"Kajangan",
    "gn:country_code":"ID",
    "gn:dem":389,
    "gn:feature_class":"P",
    "gn:feature_code":"PPL",
    "gn:name":"Kajangan",
    "gn:population":0,
    "gn:timezone":"Asia/Jakarta",
    "iso:country":"ID",
    "name:ind_x_preferred":[
        "Kajangan"
    ],
    "name:und_x_variant":[
        "Kadjangan"
    ],
    "wof:name":"Kajangan",
    "wof:placetype":"locality"
},
  "geometry": {"coordinates":[110.43222,-7.13917],"type":"Point"}
}