{
  "type": "Feature",
  "properties": {
    "gn:admin1_code":"30",
    "gn:asciiname":"Pasirbukur",
    "gn:country_code":"ID",
    "gn:dem":321,
    "gn:feature_class":"P",
    "gn:feature_code":"PPL",
    "gn:name":"Pasirbukur",
    "gn:population":0,
    "gn:timezone":"Asia/Jakarta",
    "iso:country":"ID",
    "name:ind_x_preferred":[
        "Pasirbukur"
    ],
    "wof:name":"Pasirbukur",
    "wof:placetype":"locality"
},
  "geometry": {"coordinates":[107.20471999999999,-6.84],"type":"Point"}
}