{
  "type": "Feature",
  "properties": {
    "gn:admin1_code":"8.0",
    "gn:asciiname":"Perumahan Puncakburingindah",
    "gn:country_code":"ID",
    "gn:dem":446,
    "gn:feature_class":"P",
    "gn:feature_code":"PPL",
    "gn:name":"Perumahan Puncakburingindah",
    "gn:population":0,
    "gn:timezone":"Asia/Jakarta",
    "iso:country":"ID",
    "name:ind_x_preferred":[
        "Perumahan Puncakburingindah"
    ],
    "wof:name":"Perumahan Puncakburingindah",
    "wof:placetype":"locality"
},
  "geometry": {"coordinates":[112.6489,-8.0113],"type":"Point"}
}