{
  "type": "Feature",
  "properties": {
    "gn:admin1_code":"32.0",
    "gn:asciiname":"Umbulan Kerinyik",
    "gn:country_code":"ID",
    "gn:dem":46,
    "gn:feature_class":"P",
    "gn:feature_code":"PPL",
    "gn:name":"Umbulan Kerinyik",
    "gn:population":0,
    "gn:timezone":"Asia/Jakarta",
    "iso:country":"ID",
    "name:ind_x_preferred":[
        "Umbulan Kerinyik"
    ],
    "name:und_x_variant":[
        "Umbulan Kerinuik"
    ],
    "wof:name":"Umbulan Kerinyik",
    "wof:placetype":"locality"
},
  "geometry": {"coordinates":[104.71192000000001,-4.05279],"type":"Point"}
}