{
  "type": "Feature",
  "properties": {
    "gn:admin1_code":"26",
    "gn:asciiname":"Silautongah",
    "gn:country_code":"ID",
    "gn:dem":854,
    "gn:feature_class":"P",
    "gn:feature_code":"PPL",
    "gn:name":"Silautongah",
    "gn:population":0,
    "gn:timezone":"Asia/Jakarta",
    "iso:country":"ID",
    "name:ind_x_preferred":[
        "Silautongah"
    ],
    "wof:name":"Silautongah",
    "wof:placetype":"locality"
},
  "geometry": {"coordinates":[98.80800000000001,3.0127],"type":"Point"}
}