{
  "type": "Feature",
  "properties": {
    "gn:admin1_code":"30.0",
    "gn:asciiname":"Pangawinan",
    "gn:cc2":"ID",
    "gn:country_code":"ID",
    "gn:dem":29,
    "gn:feature_class":"P",
    "gn:feature_code":"PPL",
    "gn:name":"Pangawinan",
    "gn:population":0,
    "gn:timezone":"Asia/Jakarta",
    "iso:country":"ID",
    "name:und_x_variant":[
        "Pangawinan 1",
        "Pangawinan 2",
        "Pangawinan Dua",
        "Pangawinan Satu",
        "Pangawinan"
    ],
    "wof:lang_x_official":[
        "ind"
    ],
    "wof:lang_x_spoken":[
        "ind",
        "eng"
    ],
    "wof:name":"Pangawinan",
    "wof:placetype":"locality"
},
  "geometry": {"coordinates":[106.30556,-6.24583],"type":"Point"}
}