{
  "type": "Feature",
  "properties": {
    "gn:admin1_code":"36.0",
    "gn:asciiname":"Kaptiau",
    "gn:country_code":"ID",
    "gn:dem":8,
    "gn:feature_class":"P",
    "gn:feature_code":"PPL",
    "gn:name":"Kaptiau",
    "gn:population":0,
    "gn:timezone":"Asia/Jayapura",
    "iso:country":"ID",
    "name:und_x_variant":[
        "Kaptiaoe",
        "Kaptiau"
    ],
    "wof:name":"Kaptiau",
    "wof:placetype":"locality"
},
  "geometry": {"coordinates":[139.84530000000001,-2.3755],"type":"Point"}
}