{
  "type": "Feature",
  "properties": {
    "gn:admin1_code":"7.0",
    "gn:asciiname":"Kibon",
    "gn:country_code":"ID",
    "gn:dem":29,
    "gn:feature_class":"P",
    "gn:feature_code":"PPL",
    "gn:name":"Kibon",
    "gn:population":0,
    "gn:timezone":"Asia/Jakarta",
    "iso:country":"ID",
    "name:deu_x_preferred":[
        "Langnese"
    ],
    "name:por_x_preferred":[
        "Kibon"
    ],
    "name:tur_x_preferred":[
        "Kibon"
    ],
    "wof:name":"Kibon",
    "wof:placetype":"locality"
},
  "geometry": {"coordinates":[110.02222,-7.77139],"type":"Point"}
}