{
  "type": "Feature",
  "properties": {
    "gn:admin1_code":"38.0",
    "gn:asciiname":"Kattaro",
    "gn:country_code":"ID",
    "gn:dem":320,
    "gn:feature_class":"P",
    "gn:feature_code":"PPL",
    "gn:name":"Kattaro",
    "gn:population":0,
    "gn:timezone":"Asia/Makassar",
    "iso:country":"ID",
    "name:ind_x_preferred":[
        "Kattaro"
    ],
    "wof:name":"Kattaro",
    "wof:placetype":"locality"
},
  "geometry": {"coordinates":[120.07389999999999,-3.244],"type":"Point"}
}