{
  "type": "Feature",
  "properties": {
    "gn:admin1_code":"8.0",
    "gn:asciiname":"Congol",
    "gn:country_code":"ID",
    "gn:dem":347,
    "gn:feature_class":"P",
    "gn:feature_code":"PPL",
    "gn:name":"Congol",
    "gn:population":0,
    "gn:timezone":"Asia/Jakarta",
    "iso:country":"ID",
    "name:ind_x_preferred":[
        "Congol"
    ],
    "wof:name":"Congol",
    "wof:placetype":"locality"
},
  "geometry": {"coordinates":[111.87050000000001,-7.7256],"type":"Point"}
}