{
  "type": "Feature",
  "properties": {
    "gn:admin1_code":"30.0",
    "gn:asciiname":"Kubangeceng",
    "gn:country_code":"ID",
    "gn:dem":505,
    "gn:feature_class":"P",
    "gn:feature_code":"PPLA4",
    "gn:name":"Kubangeceng",
    "gn:population":0,
    "gn:timezone":"Asia/Jakarta",
    "iso:country":"ID",
    "name:ind_x_preferred":[
        "Kubangeceng"
    ],
    "name:und_x_variant":[
        "Koebangetjeng"
    ],
    "wof:name":"Kubangeceng",
    "wof:placetype":"locality"
},
  "geometry": {"coordinates":[108.1264,-7.2966],"type":"Point"}
}