{
  "type": "Feature",
  "properties": {
    "gn:country":"ID",
    "gn:fcode":"PPL",
    "gn:pop":0,
    "iso:country":"ID",
    "name:ind_x_preferred":[
        "Lintong Nihuta"
    ],
    "qs:name":"Lintong Nihuta",
    "qs:name_adm0":"Indonesia",
    "qs:name_adm1":"Sumatera Utara",
    "qs:photos_9r":0,
    "qs:photos_sr":0,
    "qs:placetype":"Town",
    "qs:pop_sr":"0",
    "wof:name":"Lintong Nihuta",
    "wof:placetype":"locality",
    "wof:population":0
},
  "geometry": {"coordinates":[99.0234,2.1437],"type":"Point"}
}