{
  "type": "Feature",
  "properties": {
    "gn:admin1_code":"21.0",
    "gn:asciiname":"Mongo",
    "gn:country_code":"ID",
    "gn:dem":72,
    "gn:feature_class":"P",
    "gn:feature_code":"PPL",
    "gn:name":"Mongo",
    "gn:population":0,
    "gn:timezone":"Asia/Makassar",
    "iso:country":"ID",
    "name:ind_x_preferred":[
        "Mongo"
    ],
    "wof:name":"Mongo",
    "wof:placetype":"locality"
},
  "geometry": {"coordinates":[119.71729999999999,-0.7733],"type":"Point"}
}