{
  "type": "Feature",
  "properties": {
    "gn:admin1_code":"21.0",
    "gn:asciiname":"Mongo",
    "gn:country_code":"ID",
    "gn:dem":72,
    "gn:feature_class":"P",
    "gn:feature_code":"PPL",
    "gn:name":"Mongo",
    "gn:population":0,
    "gn:timezone":"Asia/Makassar",
    "iso:country":"ID",
    "name:ceb_x_preferred":[
        "Mongo"
    ],
    "name:deu_x_preferred":[
        "Mongo"
    ],
    "name:fin_x_preferred":[
        "Mongo"
    ],
    "name:fra_x_preferred":[
        "Mongo"
    ],
    "name:hun_x_preferred":[
        "Mongo"
    ],
    "name:ind_x_preferred":[
        "Mongo"
    ],
    "name:ita_x_preferred":[
        "Mongo"
    ],
    "name:kor_x_preferred":[
        "\ubabd\uace0"
    ],
    "name:msa_x_preferred":[
        "Mongo"
    ],
    "name:nld_x_preferred":[
        "Mongo"
    ],
    "name:nor_x_preferred":[
        "Mongo"
    ],
    "name:pol_x_preferred":[
        "Mongo"
    ],
    "name:por_x_preferred":[
        "Mongo"
    ],
    "name:ron_x_preferred":[
        "Mongo"
    ],
    "name:rus_x_preferred":[
        "\u041c\u043e\u043d\u0433\u043e"
    ],
    "name:spa_x_preferred":[
        "Mongo"
    ],
    "name:swe_x_preferred":[
        "Mongo"
    ],
    "name:ukr_x_preferred":[
        "\u041c\u043e\u043d\u0433\u043e"
    ],
    "wof:lang_x_official":[
        "ind"
    ],
    "wof:lang_x_spoken":[
        "ind",
        "eng"
    ],
    "wof:name":"Mongo",
    "wof:placetype":"locality"
},
  "geometry": {"coordinates":[119.71729999999999,-0.7733],"type":"Point"}
}