{
  "type": "Feature",
  "properties": {
    "gn:admin1_code":"18.0",
    "gn:asciiname":"Pukaniki",
    "gn:country_code":"ID",
    "gn:dem":360,
    "gn:feature_class":"P",
    "gn:feature_code":"PPL",
    "gn:name":"Pukaniki",
    "gn:population":0,
    "gn:timezone":"Asia/Makassar",
    "iso:country":"ID",
    "name:ind_x_preferred":[
        "Pukaniki"
    ],
    "wof:name":"Pukaniki",
    "wof:placetype":"locality"
},
  "geometry": {"coordinates":[119.3613,-9.5199],"type":"Point"}
}