{
  "type": "Feature",
  "properties": {
    "gn:admin1_code":"7.0",
    "gn:asciiname":"Kemendungan",
    "gn:country_code":"ID",
    "gn:dem":642,
    "gn:feature_class":"P",
    "gn:feature_code":"PPL",
    "gn:name":"Kemendungan",
    "gn:population":0,
    "gn:timezone":"Asia/Jakarta",
    "iso:country":"ID",
    "wof:name":"Kemendungan",
    "wof:placetype":"locality"
},
  "geometry": {"coordinates":[110.16194,-7.28],"type":"Point"}
}