{
  "type": "Feature",
  "properties": {
    "gn:admin1_code":"8.0",
    "gn:asciiname":"Nangka",
    "gn:country_code":"ID",
    "gn:dem":75,
    "gn:feature_class":"P",
    "gn:feature_code":"PPL",
    "gn:name":"Nangka",
    "gn:population":0,
    "gn:timezone":"Asia/Jakarta",
    "iso:country":"ID",
    "name:ceb_x_preferred":[
        "Nangka"
    ],
    "name:ind_x_preferred":[
        "Nangka"
    ],
    "name:msa_x_preferred":[
        "Nangka"
    ],
    "name:swe_x_preferred":[
        "Nangka"
    ],
    "wof:lang_x_official":[
        "ind"
    ],
    "wof:lang_x_spoken":[
        "ind",
        "eng"
    ],
    "wof:name":"Nangka",
    "wof:placetype":"locality"
},
  "geometry": {"coordinates":[113.193,-7.8536],"type":"Point"}
}