{
  "type": "Feature",
  "properties": {
    "gn:admin1_code":"30",
    "gn:asciiname":"Tritik",
    "gn:cc2":"ID",
    "gn:country_code":"ID",
    "gn:dem":13,
    "gn:feature_class":"P",
    "gn:feature_code":"PPL",
    "gn:name":"Tritik",
    "gn:population":0,
    "gn:timezone":"Asia/Jakarta",
    "iso:country":"ID",
    "name:und_x_variant":[
        "Tritih",
        "Tritik"
    ],
    "wof:name":"Tritik",
    "wof:placetype":"locality"
},
  "geometry": {"coordinates":[106.31610999999999,-6.14722],"type":"Point"}
}