{
  "type": "Feature",
  "properties": {
    "gn:admin1_code":"30",
    "gn:asciiname":"Bojong",
    "gn:country_code":"ID",
    "gn:dem":332,
    "gn:feature_class":"P",
    "gn:feature_code":"PPL",
    "gn:name":"Bojong",
    "gn:population":0,
    "gn:timezone":"Asia/Jakarta",
    "iso:country":"ID",
    "name:ind_x_preferred":[
        "Bojong"
    ],
    "wof:name":"Bojong",
    "wof:placetype":"locality"
},
  "geometry": {"coordinates":[107.96167,-6.70333],"type":"Point"}
}