{
  "type": "Feature",
  "properties": {
    "gn:admin1_code":"26",
    "gn:asciiname":"Simpang Persaoran",
    "gn:country_code":"ID",
    "gn:dem":716,
    "gn:feature_class":"P",
    "gn:feature_code":"PPL",
    "gn:name":"Simpang Persaoran",
    "gn:population":0,
    "gn:timezone":"Asia/Jakarta",
    "iso:country":"ID",
    "name:ind_x_preferred":[
        "Simpang Persaoran"
    ],
    "wof:name":"Simpang Persaoran",
    "wof:placetype":"locality"
},
  "geometry": {"coordinates":[99.03530000000001,2.8089],"type":"Point"}
}