{
  "type": "Feature",
  "properties": {
    "gn:country":"ID",
    "gn:fcode":"PPL",
    "gn:pop":0,
    "iso:country":"ID",
    "name:ind_x_preferred":[
        "Labuhanhaji"
    ],
    "name:unk_x_variant":[
        "Labuhanhadji"
    ],
    "qs:name":"Labuhanhaji",
    "qs:name_adm0":"Indonesia",
    "qs:name_adm1":"Nanggroe Aceh Darussalam",
    "qs:photos_9r":0,
    "qs:photos_sr":0,
    "qs:placetype":"Town",
    "qs:pop_sr":"5",
    "wof:name":"Labuhanhaji",
    "wof:placetype":"locality",
    "wof:population":0
},
  "geometry": {"coordinates":[96.9945,3.5593],"type":"Point"}
}