{
  "type": "Feature",
  "properties": {
    "gn:admin1_code":"33.0",
    "gn:asciiname":"Eunyay",
    "gn:country_code":"ID",
    "gn:dem":94,
    "gn:feature_class":"P",
    "gn:feature_code":"PPL",
    "gn:name":"Eunyay",
    "gn:population":0,
    "gn:timezone":"Asia/Jakarta",
    "iso:country":"ID",
    "name:ind_x_preferred":[
        "Eunyay"
    ],
    "wof:name":"Eunyay",
    "wof:placetype":"locality"
},
  "geometry": {"coordinates":[106.267,-6.5206],"type":"Point"}
}