{
  "type": "Feature",
  "properties": {
    "gn:admin1_code":"31.0",
    "gn:asciiname":"Ibolian",
    "gn:country_code":"ID",
    "gn:dem":142,
    "gn:feature_class":"P",
    "gn:feature_code":"PPL",
    "gn:name":"Ibolian",
    "gn:population":0,
    "gn:timezone":"Asia/Makassar",
    "iso:country":"ID",
    "name:ind_x_preferred":[
        "Ibolian"
    ],
    "wof:name":"Ibolian",
    "wof:placetype":"locality"
},
  "geometry": {"coordinates":[124.0248,0.5586],"type":"Point"}
}