{
  "type": "Feature",
  "properties": {
    "gn:admin1_code":"30.0",
    "gn:asciiname":"Cikati",
    "gn:country_code":"ID",
    "gn:dem":1350,
    "gn:feature_class":"P",
    "gn:feature_code":"PPL",
    "gn:name":"Cikati",
    "gn:population":0,
    "gn:timezone":"Asia/Jakarta",
    "iso:country":"ID",
    "name:ind_x_preferred":[
        "Cikati"
    ],
    "wof:name":"Cikati",
    "wof:placetype":"locality"
},
  "geometry": {"coordinates":[107.7706,-7.283],"type":"Point"}
}