{
  "type": "Feature",
  "properties": {
    "gn:admin1_code":"26",
    "gn:asciiname":"Gupa Lama",
    "gn:country_code":"ID",
    "gn:dem":689,
    "gn:feature_class":"P",
    "gn:feature_code":"PPL",
    "gn:name":"Gupa Lama",
    "gn:population":0,
    "gn:timezone":"Asia/Jakarta",
    "iso:country":"ID",
    "name:ind_x_preferred":[
        "Gupa Lama"
    ],
    "wof:name":"Gupa Lama",
    "wof:placetype":"locality"
},
  "geometry": {"coordinates":[98.16800000000001,2.8062],"type":"Point"}
}