{
  "type": "Feature",
  "properties": {
    "gn:admin1_code":"7.0",
    "gn:asciiname":"Baturledok",
    "gn:country_code":"ID",
    "gn:dem":23,
    "gn:feature_class":"P",
    "gn:feature_code":"PPL",
    "gn:name":"Baturledok",
    "gn:population":0,
    "gn:timezone":"Asia/Jakarta",
    "iso:country":"ID",
    "name:ind_x_preferred":[
        "Baturledok"
    ],
    "wof:name":"Baturledok",
    "wof:placetype":"locality"
},
  "geometry": {"coordinates":[111.6452,-6.7696],"type":"Point"}
}