{
  "type": "Feature",
  "properties": {
    "gn:admin1_code":"18",
    "gn:asciiname":"Nuageru",
    "gn:country_code":"ID",
    "gn:dem":472,
    "gn:feature_class":"P",
    "gn:feature_code":"PPL",
    "gn:name":"Nuageru",
    "gn:population":0,
    "gn:timezone":"Asia/Makassar",
    "iso:country":"ID",
    "name:ind_x_preferred":[
        "Nuageru"
    ],
    "wof:name":"Nuageru",
    "wof:placetype":"locality"
},
  "geometry": {"coordinates":[121.6347,-8.807],"type":"Point"}
}