{
  "type": "Feature",
  "properties": {
    "gn:admin1_code":"8.0",
    "gn:asciiname":"Pandansari",
    "gn:country_code":"ID",
    "gn:dem":17,
    "gn:feature_class":"P",
    "gn:feature_code":"PPL",
    "gn:name":"Pandansari",
    "gn:population":0,
    "gn:timezone":"Asia/Jakarta",
    "iso:country":"ID",
    "name:ind_x_preferred":[
        "Pandansari"
    ],
    "wof:name":"Pandansari",
    "wof:placetype":"locality"
},
  "geometry": {"coordinates":[113.22669999999999,-8.2525],"type":"Point"}
}