{
  "type": "Feature",
  "properties": {
    "gn:admin1_code":"8.0",
    "gn:asciiname":"Ramaram",
    "gn:country_code":"ID",
    "gn:dem":17,
    "gn:feature_class":"P",
    "gn:feature_code":"PPL",
    "gn:name":"Ramaram",
    "gn:population":0,
    "gn:timezone":"Asia/Jakarta",
    "iso:country":"ID",
    "name:ind_x_preferred":[
        "Ramaram"
    ],
    "wof:name":"Ramaram",
    "wof:placetype":"locality"
},
  "geometry": {"coordinates":[113.7099,-6.8899],"type":"Point"}
}