{
  "type": "Feature",
  "properties": {
    "gn:admin1_code":"7.0",
    "gn:asciiname":"Blagung Kulon",
    "gn:country_code":"ID",
    "gn:dem":175,
    "gn:feature_class":"P",
    "gn:feature_code":"PPL",
    "gn:name":"Blagung Kulon",
    "gn:population":0,
    "gn:timezone":"Asia/Jakarta",
    "iso:country":"ID",
    "wof:name":"Blagung Kulon",
    "wof:placetype":"locality"
},
  "geometry": {"coordinates":[110.69693999999998,-7.42722],"type":"Point"}
}