{
  "type": "Feature",
  "properties": {
    "gn:admin1_code":"18",
    "gn:asciiname":"Paka",
    "gn:country_code":"ID",
    "gn:dem":847,
    "gn:feature_class":"P",
    "gn:feature_code":"PPL",
    "gn:name":"Paka",
    "gn:population":0,
    "gn:timezone":"Asia/Makassar",
    "iso:country":"ID",
    "name:bos_x_preferred":[
        "Paka"
    ],
    "name:ceb_x_preferred":[
        "Paka"
    ],
    "name:fra_x_preferred":[
        "Paka"
    ],
    "name:hrv_x_preferred":[
        "Paka"
    ],
    "name:hun_x_preferred":[
        "Paka"
    ],
    "name:ind_x_preferred":[
        "Paka"
    ],
    "name:nld_x_preferred":[
        "Paka"
    ],
    "name:pol_x_preferred":[
        "Paka"
    ],
    "name:slv_x_preferred":[
        "Paka"
    ],
    "name:srp_x_preferred":[
        "\u041f\u0430\u043a\u0430"
    ],
    "name:swa_x_preferred":[
        "Paka"
    ],
    "wof:lang_x_official":[
        "ind"
    ],
    "wof:lang_x_spoken":[
        "ind",
        "eng"
    ],
    "wof:name":"Paka",
    "wof:placetype":"locality"
},
  "geometry": {"coordinates":[120.35599999999999,-8.6836],"type":"Point"}
}