{
  "type": "Feature",
  "properties": {
    "gn:admin1_code":"18",
    "gn:asciiname":"Paka",
    "gn:country_code":"ID",
    "gn:dem":847,
    "gn:feature_class":"P",
    "gn:feature_code":"PPL",
    "gn:name":"Paka",
    "gn:population":0,
    "gn:timezone":"Asia/Makassar",
    "iso:country":"ID",
    "name:ind_x_preferred":[
        "Paka"
    ],
    "wof:name":"Paka",
    "wof:placetype":"locality"
},
  "geometry": {"coordinates":[120.35599999999999,-8.6836],"type":"Point"}
}