{
  "type": "Feature",
  "properties": {
    "gn:admin1_code":"8.0",
    "gn:asciiname":"Balongrejo",
    "gn:country_code":"ID",
    "gn:dem":31,
    "gn:feature_class":"P",
    "gn:feature_code":"PPL",
    "gn:name":"Balongrejo",
    "gn:population":0,
    "gn:timezone":"Asia/Jakarta",
    "iso:country":"ID",
    "name:ind_x_preferred":[
        "Balongrejo"
    ],
    "wof:name":"Balongrejo",
    "wof:placetype":"locality"
},
  "geometry": {"coordinates":[112.3107,-7.5282],"type":"Point"}
}