{
  "type": "Feature",
  "properties": {
    "gn:admin1_code":"08",
    "gn:asciiname":"Jaddih Tehgah Satu",
    "gn:country_code":"ID",
    "gn:dem":30,
    "gn:feature_class":"P",
    "gn:feature_code":"PPL",
    "gn:name":"Jaddih Tehgah Satu",
    "gn:population":0,
    "gn:timezone":"Asia/Jakarta",
    "iso:country":"ID",
    "name:ind_x_preferred":[
        "Jaddih Tehgah Satu"
    ],
    "name:und_x_variant":[
        "Djadih",
        "Jadih"
    ],
    "wof:lang_x_official":[
        "ind"
    ],
    "wof:lang_x_spoken":[
        "ind",
        "eng"
    ],
    "wof:name":"Jaddih Tehgah Satu",
    "wof:placetype":"locality"
},
  "geometry": {"coordinates":[112.74120000000001,-7.083],"type":"Point"}
}