{
  "type": "Feature",
  "properties": {
    "gn:admin1_code":"8.0",
    "gn:asciiname":"Ngampel Kidul",
    "gn:country_code":"ID",
    "gn:dem":491,
    "gn:feature_class":"P",
    "gn:feature_code":"PPL",
    "gn:name":"Ngampel Kidul",
    "gn:population":0,
    "gn:timezone":"Asia/Jakarta",
    "iso:country":"ID",
    "name:ind_x_preferred":[
        "Ngampel Kidul"
    ],
    "wof:name":"Ngampel Kidul",
    "wof:placetype":"locality"
},
  "geometry": {"coordinates":[113.1671,-8.0283],"type":"Point"}
}