{
  "type": "Feature",
  "properties": {
    "gn:admin1_code":"26",
    "gn:asciiname":"Lumban Tampubolon",
    "gn:country_code":"ID",
    "gn:dem":1405,
    "gn:feature_class":"P",
    "gn:feature_code":"PPL",
    "gn:name":"Lumban Tampubolon",
    "gn:population":0,
    "gn:timezone":"Asia/Jakarta",
    "iso:country":"ID",
    "name:ind_x_preferred":[
        "Lumban Tampubolon"
    ],
    "wof:name":"Lumban Tampubolon",
    "wof:placetype":"locality"
},
  "geometry": {"coordinates":[98.9061,2.258],"type":"Point"}
}