{
  "type": "Feature",
  "properties": {
    "gn:admin1_code":"26",
    "gn:asciiname":"Pondok Afdeling Dua",
    "gn:country_code":"ID",
    "gn:dem":75,
    "gn:feature_class":"P",
    "gn:feature_code":"PPL",
    "gn:name":"Pondok Afdeling Dua",
    "gn:population":0,
    "gn:timezone":"Asia/Jakarta",
    "iso:country":"ID",
    "name:ind_x_preferred":[
        "Pondok Afdeling Dua"
    ],
    "name:und_x_variant":[
        "Pondok Afdeling II"
    ],
    "wof:name":"Pondok Afdeling Dua",
    "wof:placetype":"locality"
},
  "geometry": {"coordinates":[98.2303,3.8185],"type":"Point"}
}