{
  "type": "Feature",
  "properties": {
    "gn:admin1_code":"39.0",
    "gn:asciiname":"Mur",
    "gn:country_code":"ID",
    "gn:dem":105,
    "gn:feature_class":"P",
    "gn:feature_code":"PPL",
    "gn:name":"Mur",
    "gn:population":0,
    "gn:timezone":"Asia/Jayapura",
    "iso:country":"ID",
    "name:ind_x_preferred":[
        "Mur"
    ],
    "wof:name":"Mur",
    "wof:placetype":"locality"
},
  "geometry": {"coordinates":[134.42955000000001,-3.89774],"type":"Point"}
}