{
  "type": "Feature",
  "properties": {
    "gn:admin1_code":"39.0",
    "gn:asciiname":"Mur",
    "gn:country_code":"ID",
    "gn:dem":105,
    "gn:feature_class":"P",
    "gn:feature_code":"PPL",
    "gn:name":"Mur",
    "gn:population":0,
    "gn:timezone":"Asia/Jayapura",
    "iso:country":"ID",
    "name:ara_x_preferred":[
        "\u0645\u0648\u0631"
    ],
    "name:bel_x_preferred":[
        "\u041c\u0443\u0440"
    ],
    "name:ben_x_preferred":[
        "\u09ae\u09c1\u09b0"
    ],
    "name:bre_x_preferred":[
        "Mur"
    ],
    "name:bul_x_preferred":[
        "\u041c\u0443\u0440"
    ],
    "name:cat_x_preferred":[
        "Mur"
    ],
    "name:ceb_x_preferred":[
        "Mur"
    ],
    "name:dan_x_preferred":[
        "Mur"
    ],
    "name:deu_x_preferred":[
        "Mur"
    ],
    "name:eus_x_preferred":[
        "Mur"
    ],
    "name:fra_x_preferred":[
        "Mur"
    ],
    "name:heb_x_preferred":[
        "\u05de\u05d5\u05e8"
    ],
    "name:hin_x_preferred":[
        "\u092e\u0941\u0930"
    ],
    "name:hun_x_preferred":[
        "Mur"
    ],
    "name:ind_x_preferred":[
        "Mur"
    ],
    "name:nld_x_preferred":[
        "Mur"
    ],
    "name:nor_x_preferred":[
        "Mur"
    ],
    "name:pol_x_preferred":[
        "Mur"
    ],
    "name:por_x_preferred":[
        "Mur"
    ],
    "name:ron_x_preferred":[
        "Mur"
    ],
    "name:rus_x_preferred":[
        "\u041c\u0443\u0440"
    ],
    "name:srp_x_preferred":[
        "\u041c\u0443\u0440"
    ],
    "name:ukr_x_preferred":[
        "\u041c\u0443\u0440"
    ],
    "name:urd_x_preferred":[
        "\u0645\u0631"
    ],
    "name:vie_x_preferred":[
        "S\u00f4ng Mur"
    ],
    "wof:lang_x_official":[
        "ind"
    ],
    "wof:lang_x_spoken":[
        "ind",
        "eng"
    ],
    "wof:name":"Mur",
    "wof:placetype":"locality"
},
  "geometry": {"coordinates":[134.42955000000001,-3.89774],"type":"Point"}
}