{
  "type": "Feature",
  "properties": {
    "gn:admin1_code":"21",
    "gn:asciiname":"Kasinggoli",
    "gn:country_code":"ID",
    "gn:dem":426,
    "gn:feature_class":"P",
    "gn:feature_code":"PPL",
    "gn:name":"Kasinggoli",
    "gn:population":0,
    "gn:timezone":"Asia/Makassar",
    "iso:country":"ID",
    "name:ind_x_preferred":[
        "Kasinggoli"
    ],
    "name:und_x_variant":[
        "Kasinggali"
    ],
    "wof:lang_x_official":[
        "ind"
    ],
    "wof:lang_x_spoken":[
        "ind",
        "eng"
    ],
    "wof:name":"Kasinggoli",
    "wof:placetype":"locality"
},
  "geometry": {"coordinates":[120.90430000000001,-2.0601],"type":"Point"}
}