{
  "type": "Feature",
  "properties": {
    "gn:admin1_code":"7",
    "gn:asciiname":"Dukuhan",
    "gn:country_code":"ID",
    "gn:dem":85,
    "gn:feature_class":"P",
    "gn:feature_code":"PPL",
    "gn:name":"Dukuhan",
    "gn:population":0,
    "gn:timezone":"Asia/Jakarta",
    "iso:country":"ID",
    "name:ind_x_preferred":[
        "Dukuhan"
    ],
    "wof:name":"Dukuhan",
    "wof:placetype":"locality"
},
  "geometry": {"coordinates":[110.94278,-7.21444],"type":"Point"}
}