{
  "type": "Feature",
  "properties": {
    "gn:admin1_code":"8",
    "gn:asciiname":"Banjar",
    "gn:country_code":"ID",
    "gn:dem":513,
    "gn:feature_class":"P",
    "gn:feature_code":"PPL",
    "gn:name":"Banjar",
    "gn:population":0,
    "gn:timezone":"Asia/Jakarta",
    "iso:country":"ID",
    "name:ara_x_preferred":[
        "\u0628\u0646\u062c\u0631"
    ],
    "name:ben_x_preferred":[
        "\u09ac\u09be\u09a8\u099c\u09be\u09b0"
    ],
    "name:bjn_x_preferred":[
        "Banjar"
    ],
    "name:bpy_x_preferred":[
        "\u09ac\u09be\u09a8\u099c\u09be\u09b0"
    ],
    "name:bul_x_preferred":[
        "\u0411\u0430\u043d\u0434\u0436\u0430\u0440"
    ],
    "name:ceb_x_preferred":[
        "Banjar"
    ],
    "name:deu_x_preferred":[
        "Banjar"
    ],
    "name:fin_x_preferred":[
        "Banjar"
    ],
    "name:fra_x_preferred":[
        "Banjar"
    ],
    "name:ind_x_preferred":[
        "Banjar"
    ],
    "name:jav_x_preferred":[
        "Banjar"
    ],
    "name:mlg_x_preferred":[
        "Banjar"
    ],
    "name:msa_x_preferred":[
        "Banjar"
    ],
    "name:new_x_preferred":[
        "\u092c\u0902\u091c\u0930"
    ],
    "name:nld_x_preferred":[
        "Banjar"
    ],
    "name:pol_x_preferred":[
        "Banjar"
    ],
    "name:swe_x_preferred":[
        "Banjar"
    ],
    "wof:lang_x_official":[
        "ind"
    ],
    "wof:lang_x_spoken":[
        "ind",
        "eng"
    ],
    "wof:name":"Banjar",
    "wof:placetype":"locality"
},
  "geometry": {"coordinates":[111.30417,-7.71472],"type":"Point"}
}