{
  "type": "Feature",
  "properties": {
    "gn:admin1_code":"8.0",
    "gn:asciiname":"Sukorejo Satu",
    "gn:country_code":"ID",
    "gn:dem":102,
    "gn:feature_class":"P",
    "gn:feature_code":"PPL",
    "gn:name":"Sukorejo Satu",
    "gn:population":0,
    "gn:timezone":"Asia/Jakarta",
    "iso:country":"ID",
    "name:ind_x_preferred":[
        "Sukorejo Satu"
    ],
    "name:und_x_variant":[
        "Sukorejo 1"
    ],
    "wof:name":"Sukorejo Satu",
    "wof:placetype":"locality"
},
  "geometry": {"coordinates":[112.1024,-7.3501],"type":"Point"}
}