{
  "type": "Feature",
  "properties": {
    "gn:admin1_code":"8",
    "gn:asciiname":"Krajanputuk",
    "gn:country_code":"ID",
    "gn:dem":144,
    "gn:feature_class":"P",
    "gn:feature_code":"PPLA4",
    "gn:name":"Krajanputuk",
    "gn:population":0,
    "gn:timezone":"Asia/Jakarta",
    "iso:country":"ID",
    "name:ind_x_preferred":[
        "Krajanputuk"
    ],
    "wof:lang_x_official":[
        "ind"
    ],
    "wof:lang_x_spoken":[
        "ind",
        "eng"
    ],
    "wof:name":"Krajanputuk",
    "wof:placetype":"locality"
},
  "geometry": {"coordinates":[114.3365,-8.189],"type":"Point"}
}