{
  "type": "Feature",
  "properties": {
    "gn:admin1_code":"30.0",
    "gn:asciiname":"Alhuda",
    "gn:country_code":"ID",
    "gn:dem":993,
    "gn:feature_class":"P",
    "gn:feature_code":"PPL",
    "gn:name":"Alhuda",
    "gn:population":0,
    "gn:timezone":"Asia/Jakarta",
    "iso:country":"ID",
    "name:ind_x_preferred":[
        "Alhuda"
    ],
    "wof:name":"Alhuda",
    "wof:placetype":"locality"
},
  "geometry": {"coordinates":[107.19580000000001,-7.0846],"type":"Point"}
}