{
  "type": "Feature",
  "properties": {
    "gn:admin1_code":"24",
    "gn:asciiname":"Angus",
    "gn:country_code":"ID",
    "gn:dem":211,
    "gn:feature_class":"P",
    "gn:feature_code":"PPL",
    "gn:name":"Angus",
    "gn:population":0,
    "gn:timezone":"Asia/Jakarta",
    "iso:country":"ID",
    "name:ind_x_preferred":[
        "Angus"
    ],
    "wof:name":"Angus",
    "wof:placetype":"locality"
},
  "geometry": {"coordinates":[100.18962999999999,-0.04111],"type":"Point"}
}