{
  "type": "Feature",
  "properties": {
    "gn:admin1_code":"24",
    "gn:asciiname":"Angus",
    "gn:country_code":"ID",
    "gn:dem":211,
    "gn:feature_class":"P",
    "gn:feature_code":"PPL",
    "gn:name":"Angus",
    "gn:population":0,
    "gn:timezone":"Asia/Jakarta",
    "iso:country":"ID",
    "name:ara_x_preferred":[
        "\u0623\u0646\u063a\u0648\u0633"
    ],
    "name:bre_x_preferred":[
        "Angus"
    ],
    "name:ceb_x_preferred":[
        "Angus"
    ],
    "name:ces_x_preferred":[
        "Angus"
    ],
    "name:deu_x_preferred":[
        "Angus"
    ],
    "name:fra_x_preferred":[
        "Angus"
    ],
    "name:glv_x_preferred":[
        "Aonghas"
    ],
    "name:hin_x_preferred":[
        "\u090f\u0902\u0917\u0938"
    ],
    "name:hun_x_preferred":[
        "Angus"
    ],
    "name:ind_x_preferred":[
        "Angus"
    ],
    "name:ita_x_preferred":[
        "Angus"
    ],
    "name:jpn_x_preferred":[
        "\u30a2\u30f3\u30ac\u30b9"
    ],
    "name:kor_x_preferred":[
        "\uc575\uac70\uc2a4"
    ],
    "name:nld_x_preferred":[
        "Angus"
    ],
    "name:pol_x_preferred":[
        "Angus"
    ],
    "name:por_x_preferred":[
        "Angus"
    ],
    "name:rus_x_preferred":[
        "\u0410\u043d\u0433\u0443\u0441"
    ],
    "name:spa_x_preferred":[
        "Angus"
    ],
    "name:srp_x_preferred":[
        "\u0410\u043d\u0433\u0443\u0441"
    ],
    "name:swe_x_preferred":[
        "Angus"
    ],
    "name:ukr_x_preferred":[
        "\u0410\u043d\u0433\u0443\u0441"
    ],
    "name:vie_x_preferred":[
        "Angus"
    ],
    "wof:lang_x_official":[
        "ind"
    ],
    "wof:lang_x_spoken":[
        "ind",
        "eng"
    ],
    "wof:name":"Angus",
    "wof:placetype":"locality"
},
  "geometry": {"coordinates":[100.18962999999999,-0.04111],"type":"Point"}
}