{
  "type": "Feature",
  "properties": {
    "gn:admin1_code":"36.0",
    "gn:asciiname":"Lokasi Transmigrasi Dua Numbokrang",
    "gn:country_code":"ID",
    "gn:dem":32,
    "gn:feature_class":"P",
    "gn:feature_code":"PPL",
    "gn:name":"Lokasi Transmigrasi Dua Numbokrang",
    "gn:population":0,
    "gn:timezone":"Asia/Jayapura",
    "iso:country":"ID",
    "name:ind_x_preferred":[
        "Lokasi Transmigrasi Dua Numbokrang"
    ],
    "name:und_x_variant":[
        "Lokasi Trans II Numbokrang"
    ],
    "wof:name":"Lokasi Transmigrasi Dua Numbokrang",
    "wof:placetype":"locality"
},
  "geometry": {"coordinates":[140.13249999999999,-2.5458],"type":"Point"}
}