{
  "type": "Feature",
  "properties": {
    "gn:admin1_code":"8",
    "gn:asciiname":"Kebunsari",
    "gn:country_code":"ID",
    "gn:dem":77,
    "gn:feature_class":"P",
    "gn:feature_code":"PPL",
    "gn:name":"Kebunsari",
    "gn:population":0,
    "gn:timezone":"Asia/Jakarta",
    "iso:country":"ID",
    "name:ind_x_preferred":[
        "Kebunsari"
    ],
    "wof:name":"Kebunsari",
    "wof:placetype":"locality"
},
  "geometry": {"coordinates":[114.2324,-8.4267],"type":"Point"}
}