{
  "type": "Feature",
  "properties": {
    "gn:admin1_code":"8",
    "gn:asciiname":"Benem Lor",
    "gn:country_code":"ID",
    "gn:dem":6,
    "gn:feature_class":"P",
    "gn:feature_code":"PPL",
    "gn:name":"Benem Lor",
    "gn:population":0,
    "gn:timezone":"Asia/Jakarta",
    "iso:country":"ID",
    "name:ind_x_preferred":[
        "Benem Lor"
    ],
    "wof:name":"Benem Lor",
    "wof:placetype":"locality"
},
  "geometry": {"coordinates":[112.5219,-7.1432],"type":"Point"}
}