{
  "type": "Feature",
  "properties": {
    "gn:admin1_code":"8",
    "gn:asciiname":"Cempokoan",
    "gn:country_code":"ID",
    "gn:dem":163,
    "gn:feature_class":"P",
    "gn:feature_code":"PPL",
    "gn:name":"Cempokoan",
    "gn:population":0,
    "gn:timezone":"Asia/Jakarta",
    "iso:country":"ID",
    "name:ind_x_preferred":[
        "Cempokoan"
    ],
    "wof:lang_x_official":[
        "ind"
    ],
    "wof:lang_x_spoken":[
        "ind",
        "eng"
    ],
    "wof:name":"Cempokoan",
    "wof:placetype":"locality"
},
  "geometry": {"coordinates":[113.65940000000001,-8.1516],"type":"Point"}
}