{
  "type": "Feature",
  "properties": {
    "gn:admin1_code":"42.0",
    "gn:asciiname":"Long Uru",
    "gn:country_code":"ID",
    "gn:dem":669,
    "gn:feature_class":"P",
    "gn:feature_code":"PPL",
    "gn:name":"Long Uru",
    "gn:population":0,
    "gn:timezone":"Asia/Makassar",
    "iso:country":"ID",
    "name:ind_x_preferred":[
        "Long Uru"
    ],
    "name:ind_x_variant":[
        "Long Oeroe",
        "Long Oero"
    ],
    "name:und_x_variant":[
        "Longuron",
        "Longoero",
        "Longuro"
    ],
    "wof:lang_x_official":[
        "ind"
    ],
    "wof:lang_x_spoken":[
        "ind",
        "eng"
    ],
    "wof:name":"Long Uru",
    "wof:placetype":"locality"
},
  "geometry": {"coordinates":[114.99826,1.68131],"type":"Point"}
}