{
  "type": "Feature",
  "properties": {
    "gn:country":"ID",
    "gn:fcode":"PPL",
    "gn:pop":0,
    "iso:country":"ID",
    "qs:name":"Tanahlot",
    "qs:name_adm0":"Indonesia",
    "qs:name_adm1":"Bali",
    "qs:photos":941,
    "qs:photos_1k":191,
    "qs:photos_9k":4,
    "qs:photos_9r":6,
    "qs:photos_all":941,
    "qs:photos_sr":10,
    "qs:placetype":"Town",
    "qs:pop_sr":"0",
    "wd:wordcount":636,
    "wof:name":"Tanahlot",
    "wof:placetype":"locality",
    "wof:population":0
},
  "geometry": {"coordinates":[115.08756,-8.61747],"type":"Point"}
}