{
  "type": "Feature",
  "properties": {
    "gn:country":"ID",
    "gn:fcode":"PPL",
    "gn:pop":0,
    "iso:country":"ID",
    "name:ara_x_preferred":[
        "\u062a\u0627\u0646\u0627\u0647 \u0644\u0648\u0637"
    ],
    "name:arz_x_preferred":[
        "\u062a\u0627\u0646\u0627\u0647 \u0644\u0648\u0637"
    ],
    "name:ban_x_preferred":[
        "Tanah Lot"
    ],
    "name:bul_x_preferred":[
        "\u0422\u0430\u043d\u0430\u0445 \u041b\u043e\u0442"
    ],
    "name:eng_x_preferred":[
        "Tanah Lot"
    ],
    "name:fra_x_preferred":[
        "Tanah Lot"
    ],
    "name:hin_x_preferred":[
        "\u0924\u0928\u093e\u0939 \u0932\u094b\u0924"
    ],
    "name:hye_x_preferred":[
        "\u0539\u0561\u0576\u0561 \u053c\u0578\u0569"
    ],
    "name:ind_x_preferred":[
        "Tanah Lot"
    ],
    "name:jav_x_preferred":[
        "Tanah Lot"
    ],
    "name:jpn_x_preferred":[
        "\u30bf\u30ca\u30ed\u30c3\u30c8\u5bfa\u9662"
    ],
    "name:kor_x_preferred":[
        "\ud0c0\ub098\ub86f"
    ],
    "name:msa_x_preferred":[
        "Tanah Lot"
    ],
    "name:pol_x_preferred":[
        "Tanah Lot"
    ],
    "name:por_x_preferred":[
        "Tanah Lot"
    ],
    "name:tam_x_preferred":[
        "\u0ba4\u0ba9\u0bbe \u0bb2\u0bbe\u0b9f\u0bcd"
    ],
    "name:tgl_x_preferred":[
        "Tanah Lot"
    ],
    "name:tha_x_preferred":[
        "\u0e15\u0e32\u0e19\u0e30\u0e2e\u0e4c\u0e25\u0e15"
    ],
    "name:zho_x_preferred":[
        "\u6d77\u795e\u5edf"
    ],
    "qs:name":"Tanahlot",
    "qs:name_adm0":"Indonesia",
    "qs:name_adm1":"Bali",
    "qs:photos":941,
    "qs:photos_1k":191,
    "qs:photos_9k":4,
    "qs:photos_9r":6,
    "qs:photos_all":941,
    "qs:photos_sr":10,
    "qs:placetype":"Town",
    "qs:pop_sr":"0",
    "wd:wordcount":636,
    "wof:lang_x_official":[
        "ind"
    ],
    "wof:lang_x_spoken":[
        "ind",
        "eng"
    ],
    "wof:name":"Tanahlot",
    "wof:placetype":"locality",
    "wof:population":0
},
  "geometry": {"coordinates":[115.08756,-8.61747],"type":"Point"}
}