{
  "type": "Feature",
  "properties": {
    "gn:admin1_code":"18.0",
    "gn:asciiname":"Oefau",
    "gn:country_code":"ID",
    "gn:dem":833,
    "gn:feature_class":"P",
    "gn:feature_code":"PPL",
    "gn:name":"Oefau",
    "gn:population":0,
    "gn:timezone":"Asia/Makassar",
    "iso:country":"ID",
    "name:ind_x_preferred":[
        "Oefau"
    ],
    "wof:name":"Oefau",
    "wof:placetype":"locality"
},
  "geometry": {"coordinates":[124.48135000000001,-9.87235],"type":"Point"}
}