{
  "type": "Feature",
  "properties": {
    "gn:admin1_code":"15.0",
    "gn:asciiname":"Lengkungdaun",
    "gn:country_code":"ID",
    "gn:dem":218,
    "gn:feature_class":"P",
    "gn:feature_code":"PPL",
    "gn:name":"Lengkungdaun",
    "gn:population":0,
    "gn:timezone":"Asia/Jakarta",
    "iso:country":"ID",
    "name:ind_x_preferred":[
        "Lengkungdaun"
    ],
    "wof:name":"Lengkungdaun",
    "wof:placetype":"locality"
},
  "geometry": {"coordinates":[104.77800000000001,-5.24231],"type":"Point"}
}