{
  "type": "Feature",
  "properties": {
    "gn:admin1_code":"0.0",
    "gn:asciiname":"Labuhan",
    "gn:cc2":"ID",
    "gn:country_code":"ID",
    "gn:dem":335,
    "gn:feature_class":"P",
    "gn:feature_code":"PPL",
    "gn:name":"Labuhan",
    "gn:population":0,
    "gn:timezone":"Asia/Makassar",
    "iso:country":"ID",
    "name:und_x_variant":[
        "Laboehan",
        "Laboean",
        "Labuhan"
    ],
    "wof:lang_x_official":[
        "ind"
    ],
    "wof:lang_x_spoken":[
        "ind",
        "eng"
    ],
    "wof:name":"Labuhan",
    "wof:placetype":"locality"
},
  "geometry": {"coordinates":[119.96666999999999,-0.23333],"type":"Point"}
}