{
  "type": "Feature",
  "properties": {
    "gn:admin1_code":"30",
    "gn:asciiname":"Ceuri",
    "gn:country_code":"ID",
    "gn:dem":359,
    "gn:feature_class":"P",
    "gn:feature_code":"PPL",
    "gn:name":"Ceuri",
    "gn:population":0,
    "gn:timezone":"Asia/Jakarta",
    "iso:country":"ID",
    "name:ind_x_preferred":[
        "Ceuri"
    ],
    "wof:name":"Ceuri",
    "wof:placetype":"locality"
},
  "geometry": {"coordinates":[107.89806000000002,-6.73556],"type":"Point"}
}