{
  "type": "Feature",
  "properties": {
    "gn:admin1_code":"32.0",
    "gn:asciiname":"Muarakeong",
    "gn:country_code":"ID",
    "gn:dem":31,
    "gn:feature_class":"P",
    "gn:feature_code":"PPL",
    "gn:name":"Muarakeong",
    "gn:population":0,
    "gn:timezone":"Asia/Jakarta",
    "iso:country":"ID",
    "name:ind_x_preferred":[
        "Muarakeong"
    ],
    "wof:name":"Muarakeong",
    "wof:placetype":"locality"
},
  "geometry": {"coordinates":[104.56789999999999,-3.6461],"type":"Point"}
}