{
  "type": "Feature",
  "properties": {
    "gn:admin1_code":"30",
    "gn:asciiname":"Cisegel",
    "gn:country_code":"ID",
    "gn:dem":537,
    "gn:feature_class":"P",
    "gn:feature_code":"PPL",
    "gn:name":"Cisegel",
    "gn:population":0,
    "gn:timezone":"Asia/Jakarta",
    "iso:country":"ID",
    "name:ind_x_preferred":[
        "Cisegel"
    ],
    "wof:name":"Cisegel",
    "wof:placetype":"locality"
},
  "geometry": {"coordinates":[107.78749999999999,-6.75417],"type":"Point"}
}