{
  "type": "Feature",
  "properties": {
    "gn:admin1_code":"1.0",
    "gn:asciiname":"Keudeudu",
    "gn:country_code":"ID",
    "gn:dem":11,
    "gn:feature_class":"P",
    "gn:feature_code":"PPL",
    "gn:name":"Keudeudu",
    "gn:population":0,
    "gn:timezone":"Asia/Jakarta",
    "iso:country":"ID",
    "name:ind_x_preferred":[
        "Keudeudu"
    ],
    "name:und_x_variant":[
        "Keud\u00e8 Pant\u00e9 Radja",
        "Keudeudoe\u00eb",
        "Keudeudue"
    ],
    "wof:name":"Keudeudu",
    "wof:placetype":"locality"
},
  "geometry": {"coordinates":[96.1408,5.2569],"type":"Point"}
}