{
  "type": "Feature",
  "properties": {
    "gn:admin1_code":"15.0",
    "gn:asciiname":"Sukatenang",
    "gn:country_code":"ID",
    "gn:dem":60,
    "gn:feature_class":"P",
    "gn:feature_code":"PPL",
    "gn:name":"Sukatenang",
    "gn:population":0,
    "gn:timezone":"Asia/Jakarta",
    "iso:country":"ID",
    "name:ind_x_preferred":[
        "Sukatenang"
    ],
    "wof:name":"Sukatenang",
    "wof:placetype":"locality"
},
  "geometry": {"coordinates":[104.85839,-4.88752],"type":"Point"}
}