{
  "type": "Feature",
  "properties": {
    "gn:admin1_code":"38",
    "gn:asciiname":"Pollo",
    "gn:country_code":"ID",
    "gn:dem":961,
    "gn:feature_class":"P",
    "gn:feature_code":"PPL",
    "gn:name":"Pollo",
    "gn:population":0,
    "gn:timezone":"Asia/Makassar",
    "iso:country":"ID",
    "name:ind_x_preferred":[
        "Pollo"
    ],
    "name:rus_x_preferred":[
        "\u041f\u043e\u043b\u044c\u043e"
    ],
    "name:spa_x_preferred":[
        "Pollo"
    ],
    "name:tgk_x_preferred":[
        "\u041f\u043e\u043b\u043e"
    ],
    "wof:lang_x_official":[
        "ind"
    ],
    "wof:lang_x_spoken":[
        "ind",
        "eng"
    ],
    "wof:name":"Pollo",
    "wof:placetype":"locality"
},
  "geometry": {"coordinates":[119.58759999999999,-2.9544],"type":"Point"}
}