{
  "type": "Feature",
  "properties": {
    "gn:admin1_code":"38",
    "gn:asciiname":"Pollo",
    "gn:country_code":"ID",
    "gn:dem":961,
    "gn:feature_class":"P",
    "gn:feature_code":"PPL",
    "gn:name":"Pollo",
    "gn:population":0,
    "gn:timezone":"Asia/Makassar",
    "iso:country":"ID",
    "name:ind_x_preferred":[
        "Pollo"
    ],
    "wof:name":"Pollo",
    "wof:placetype":"locality"
},
  "geometry": {"coordinates":[119.58759999999999,-2.9544],"type":"Point"}
}