{
  "type": "Feature",
  "properties": {
    "gn:gn_country":"ID",
    "gn:gn_fcode":"ADM4",
    "gn:gn_pop":0,
    "iso:country":"ID",
    "name:ind_x_preferred":[
        "Desa Serongga"
    ],
    "name:unk_x_variant":[
        "Serongga"
    ],
    "qs_pg:aaroncc":"ID",
    "qs_pg:gn_country":"ID",
    "qs_pg:gn_fcode":"ADM4",
    "qs_pg:gn_pop":0,
    "qs_pg:name":"Desa Serongga",
    "qs_pg:photos_9r":0,
    "qs_pg:photos_sr":0,
    "qs_pg:pop_sr":0,
    "qs_pg:qs_pg_placetype":"localadmin",
    "wof:name":"Desa Serongga",
    "wof:placetype":"localadmin"
},
  "geometry": {"coordinates":[115.33759999999999,-8.5671],"type":"Point"}
}