{
  "type": "Feature",
  "properties": {
    "gn:admin1_code":"41.0",
    "gn:asciiname":"Pumbalanu",
    "gn:country_code":"ID",
    "gn:dem":61,
    "gn:feature_class":"P",
    "gn:feature_code":"PPL",
    "gn:name":"Pumbalanu",
    "gn:population":0,
    "gn:timezone":"Asia/Makassar",
    "iso:country":"ID",
    "name:ind_x_preferred":[
        "Pumbalanu"
    ],
    "wof:name":"Pumbalanu",
    "wof:placetype":"locality"
},
  "geometry": {"coordinates":[118.94840000000001,-3.4317],"type":"Point"}
}