{
  "type": "Feature",
  "properties": {
    "gn:admin1_code":"30",
    "gn:asciiname":"Tegalnangka",
    "gn:country_code":"ID",
    "gn:dem":77,
    "gn:feature_class":"P",
    "gn:feature_code":"PPL",
    "gn:name":"Tegalnangka",
    "gn:population":0,
    "gn:timezone":"Asia/Jakarta",
    "iso:country":"ID",
    "name:ind_x_preferred":[
        "Tegalnangka"
    ],
    "wof:name":"Tegalnangka",
    "wof:placetype":"locality"
},
  "geometry": {"coordinates":[107.19306,-6.5225],"type":"Point"}
}