{
  "type": "Feature",
  "properties": {
    "gn:admin1_code":"42.0",
    "gn:asciiname":"Long Lejuh",
    "gn:country_code":"ID",
    "gn:dem":53,
    "gn:feature_class":"P",
    "gn:feature_code":"PPL",
    "gn:name":"Long Lejuh",
    "gn:population":0,
    "gn:timezone":"Asia/Makassar",
    "iso:country":"ID",
    "name:ind_x_preferred":[
        "Long Lejuh"
    ],
    "name:ind_x_variant":[
        "Long Ledjoe",
        "Long Lejo"
    ],
    "name:und_x_variant":[
        "Longledjon",
        "Longledju",
        "Longledjoe",
        "Long Ledjo",
        "Longleju"
    ],
    "wof:name":"Long Lejuh",
    "wof:placetype":"locality"
},
  "geometry": {"coordinates":[116.68167,2.8208],"type":"Point"}
}