{
  "type": "Feature",
  "properties": {
    "gn:admin1_code":"21.0",
    "gn:asciiname":"Lanona",
    "gn:country_code":"ID",
    "gn:dem":10,
    "gn:feature_class":"P",
    "gn:feature_code":"PPL",
    "gn:name":"Lanona",
    "gn:population":0,
    "gn:timezone":"Asia/Makassar",
    "iso:country":"ID",
    "name:ind_x_preferred":[
        "Lanona"
    ],
    "name:und_x_variant":[
        "Lanana"
    ],
    "wof:name":"Lanona",
    "wof:placetype":"locality"
},
  "geometry": {"coordinates":[121.89360000000001,-2.4244],"type":"Point"}
}