{
  "type": "Feature",
  "properties": {
    "gn:admin1_code":"38.0",
    "gn:asciiname":"Podon",
    "gn:country_code":"ID",
    "gn:dem":1303,
    "gn:feature_class":"P",
    "gn:feature_code":"PPL",
    "gn:name":"Podon",
    "gn:population":0,
    "gn:timezone":"Asia/Makassar",
    "iso:country":"ID",
    "name:ind_x_preferred":[
        "Podon"
    ],
    "wof:name":"Podon",
    "wof:placetype":"locality"
},
  "geometry": {"coordinates":[119.8351,-2.9549],"type":"Point"}
}