{
  "type": "Feature",
  "properties": {
    "gn:admin1_code":"0.0",
    "gn:asciiname":"Tanjungbakung",
    "gn:cc2":"ID",
    "gn:country_code":"ID",
    "gn:dem":5,
    "gn:feature_class":"P",
    "gn:feature_code":"PPL",
    "gn:name":"Tanjungbakung",
    "gn:population":0,
    "gn:timezone":"Asia/Pontianak",
    "iso:country":"ID",
    "name:und_x_variant":[
        "Tandjungbakung",
        "Tandjoengbakoeng",
        "Tanjungbakung"
    ],
    "wof:lang_x_official":[
        "ind"
    ],
    "wof:lang_x_spoken":[
        "ind",
        "eng"
    ],
    "wof:name":"Tanjungbakung",
    "wof:placetype":"locality"
},
  "geometry": {"coordinates":[109.46666999999999,-0.38333],"type":"Point"}
}