{
  "type": "Feature",
  "properties": {
    "gn:admin1_code":"33",
    "gn:asciiname":"Pasirkacapi",
    "gn:country_code":"ID",
    "gn:dem":130,
    "gn:feature_class":"P",
    "gn:feature_code":"PPL",
    "gn:name":"Pasirkacapi",
    "gn:population":0,
    "gn:timezone":"Asia/Jakarta",
    "iso:country":"ID",
    "name:ind_x_preferred":[
        "Pasirkacapi"
    ],
    "wof:name":"Pasirkacapi",
    "wof:placetype":"locality"
},
  "geometry": {"coordinates":[106.1322,-6.3522],"type":"Point"}
}