{
  "type": "Feature",
  "properties": {
    "gn:admin1_code":"18.0",
    "gn:asciiname":"Kiufana",
    "gn:country_code":"ID",
    "gn:dem":181,
    "gn:feature_class":"P",
    "gn:feature_code":"PPL",
    "gn:name":"Kiufana",
    "gn:population":0,
    "gn:timezone":"Asia/Makassar",
    "iso:country":"ID",
    "name:ind_x_preferred":[
        "Kiufana"
    ],
    "wof:name":"Kiufana",
    "wof:placetype":"locality"
},
  "geometry": {"coordinates":[124.4622,-10.0942],"type":"Point"}
}