{
  "type": "Feature",
  "properties": {
    "gn:admin1_code":"30.0",
    "gn:asciiname":"Cigorowong",
    "gn:country_code":"ID",
    "gn:dem":799,
    "gn:feature_class":"P",
    "gn:feature_code":"PPL",
    "gn:name":"Cigorowong",
    "gn:population":0,
    "gn:timezone":"Asia/Jakarta",
    "iso:country":"ID",
    "name:ind_x_preferred":[
        "Cigorowong"
    ],
    "name:und_x_variant":[
        "Tjigorowong",
        "Cigorowong"
    ],
    "wof:lang_x_official":[
        "ind"
    ],
    "wof:lang_x_spoken":[
        "ind",
        "eng"
    ],
    "wof:name":"Cigorowong",
    "wof:placetype":"locality"
},
  "geometry": {"coordinates":[108.12990000000001,-7.2292],"type":"Point"}
}