{
  "type": "Feature",
  "properties": {
    "gn:admin1_code":"7",
    "gn:asciiname":"Tanggel",
    "gn:country_code":"ID",
    "gn:dem":78,
    "gn:feature_class":"P",
    "gn:feature_code":"PPL",
    "gn:name":"Tanggel",
    "gn:population":0,
    "gn:timezone":"Asia/Jakarta",
    "iso:country":"ID",
    "name:ind_x_preferred":[
        "Tanggel"
    ],
    "wof:name":"Tanggel",
    "wof:placetype":"locality"
},
  "geometry": {"coordinates":[111.36528,-7.14278],"type":"Point"}
}