{
  "type": "Feature",
  "properties": {
    "gn:admin1_code":"18.0",
    "gn:asciiname":"Nangablo",
    "gn:country_code":"ID",
    "gn:dem":157,
    "gn:feature_class":"P",
    "gn:feature_code":"PPL",
    "gn:name":"Nangablo",
    "gn:population":0,
    "gn:timezone":"Asia/Makassar",
    "iso:country":"ID",
    "name:ind_x_preferred":[
        "Nangablo"
    ],
    "wof:name":"Nangablo",
    "wof:placetype":"locality"
},
  "geometry": {"coordinates":[122.1048,-8.7024],"type":"Point"}
}