{
  "type": "Feature",
  "properties": {
    "gn:admin1_code":"15.0",
    "gn:asciiname":"Karangmulyo",
    "gn:country_code":"ID",
    "gn:dem":54,
    "gn:feature_class":"P",
    "gn:feature_code":"PPL",
    "gn:name":"Karangmulyo",
    "gn:population":0,
    "gn:timezone":"Asia/Jakarta",
    "iso:country":"ID",
    "name:ind_x_preferred":[
        "Karangmulyo"
    ],
    "wof:name":"Karangmulyo",
    "wof:placetype":"locality"
},
  "geometry": {"coordinates":[104.97315,-4.94336],"type":"Point"}
}