{
  "type": "Feature",
  "properties": {
    "gn:admin1_code":"8.0",
    "gn:asciiname":"Sumberpayung",
    "gn:country_code":"ID",
    "gn:dem":100,
    "gn:feature_class":"P",
    "gn:feature_code":"PPL",
    "gn:name":"Sumberpayung",
    "gn:population":0,
    "gn:timezone":"Asia/Jakarta",
    "iso:country":"ID",
    "name:ind_x_preferred":[
        "Sumberpayung"
    ],
    "wof:name":"Sumberpayung",
    "wof:placetype":"locality"
},
  "geometry": {"coordinates":[113.6905,-7.0541],"type":"Point"}
}