{
  "type": "Feature",
  "properties": {
    "gn:admin1_code":"7.0",
    "gn:asciiname":"Banjarmanggu",
    "gn:country_code":"ID",
    "gn:dem":326,
    "gn:feature_class":"P",
    "gn:feature_code":"PPL",
    "gn:name":"Banjarmanggu",
    "gn:population":0,
    "gn:timezone":"Asia/Jakarta",
    "iso:country":"ID",
    "name:ind_x_preferred":[
        "Banjarmanggu"
    ],
    "name:und_x_variant":[
        "Bandjarmangoe",
        "Bandjarmangu",
        "Banjarmangu"
    ],
    "wof:name":"Banjarmanggu",
    "wof:placetype":"locality"
},
  "geometry": {"coordinates":[109.6875,-7.36111],"type":"Point"}
}