{
  "type": "Feature",
  "properties": {
    "gn:admin1_code":"33",
    "gn:asciiname":"Cikubang Lima",
    "gn:country_code":"ID",
    "gn:dem":12,
    "gn:feature_class":"P",
    "gn:feature_code":"PPL",
    "gn:name":"Cikubang Lima",
    "gn:population":0,
    "gn:timezone":"Asia/Jakarta",
    "iso:country":"ID",
    "name:ind_x_preferred":[
        "Cikubang Lima"
    ],
    "wof:name":"Cikubang Lima",
    "wof:placetype":"locality"
},
  "geometry": {"coordinates":[106.1002,-5.9479],"type":"Point"}
}