{
  "type": "Feature",
  "properties": {
    "gn:admin1_code":"7",
    "gn:asciiname":"Petung",
    "gn:country_code":"ID",
    "gn:dem":597,
    "gn:feature_class":"P",
    "gn:feature_code":"PPL",
    "gn:name":"Petung",
    "gn:population":0,
    "gn:timezone":"Asia/Jakarta",
    "iso:country":"ID",
    "name:ind_x_preferred":[
        "Petung"
    ],
    "wof:name":"Petung",
    "wof:placetype":"locality"
},
  "geometry": {"coordinates":[110.89239999999999,-6.5957],"type":"Point"}
}