{
  "type": "Feature",
  "properties": {
    "gn:admin1_code":"35",
    "gn:asciiname":"Kelogong",
    "gn:country_code":"ID",
    "gn:dem":5,
    "gn:feature_class":"P",
    "gn:feature_code":"PPL",
    "gn:name":"Kelogong",
    "gn:population":0,
    "gn:timezone":"Asia/Jakarta",
    "iso:country":"ID",
    "name:ind_x_preferred":[
        "Kelogong"
    ],
    "wof:name":"Kelogong",
    "wof:placetype":"locality"
},
  "geometry": {"coordinates":[107.62059000000001,-3.15936],"type":"Point"}
}