{
  "type": "Feature",
  "properties": {
    "gn:admin1_code":"38",
    "gn:asciiname":"Mario",
    "gn:country_code":"ID",
    "gn:dem":490,
    "gn:feature_class":"P",
    "gn:feature_code":"PPL",
    "gn:name":"Mario",
    "gn:population":0,
    "gn:timezone":"Asia/Makassar",
    "iso:country":"ID",
    "name:ind_x_preferred":[
        "Mario"
    ],
    "name:und_x_variant":[
        "Murio"
    ],
    "wof:name":"Mario",
    "wof:placetype":"locality"
},
  "geometry": {"coordinates":[119.7988,-4.8325],"type":"Point"}
}