{
  "type": "Feature",
  "properties": {
    "gn:admin1_code":"15.0",
    "gn:asciiname":"Umbulan Bawangbeter",
    "gn:country_code":"ID",
    "gn:dem":7,
    "gn:feature_class":"P",
    "gn:feature_code":"PPL",
    "gn:name":"Umbulan Bawangbeter",
    "gn:population":0,
    "gn:timezone":"Asia/Jakarta",
    "iso:country":"ID",
    "name:ind_x_preferred":[
        "Umbulan Bawangbeter"
    ],
    "name:ind_x_variant":[
        "Umbulanbawangbeter",
        "Oemboelan Bawangb\u0115t\u0115r"
    ],
    "wof:lang_x_official":[
        "ind"
    ],
    "wof:lang_x_spoken":[
        "ind",
        "eng"
    ],
    "wof:name":"Umbulan Bawangbeter",
    "wof:placetype":"locality"
},
  "geometry": {"coordinates":[105.22215,-4.50333],"type":"Point"}
}