{
  "type": "Feature",
  "properties": {
    "gn:admin1_code":"7.0",
    "gn:asciiname":"Putihan",
    "gn:country_code":"ID",
    "gn:dem":22,
    "gn:feature_class":"P",
    "gn:feature_code":"PPL",
    "gn:name":"Putihan",
    "gn:population":0,
    "gn:timezone":"Asia/Jakarta",
    "iso:country":"ID",
    "name:ind_x_preferred":[
        "Putihan"
    ],
    "wof:name":"Putihan",
    "wof:placetype":"locality"
},
  "geometry": {"coordinates":[109.68778,-7.68389],"type":"Point"}
}