{
  "type": "Feature",
  "properties": {
    "gn:admin1_code":"38",
    "gn:asciiname":"Lembang",
    "gn:country_code":"ID",
    "gn:dem":307,
    "gn:feature_class":"P",
    "gn:feature_code":"PPL",
    "gn:name":"Lembang",
    "gn:population":0,
    "gn:timezone":"Asia/Makassar",
    "iso:country":"ID",
    "name:ind_x_preferred":[
        "Lembang"
    ],
    "wof:name":"Lembang",
    "wof:placetype":"locality"
},
  "geometry": {"coordinates":[120.09829999999999,-5.4533],"type":"Point"}
}