{
  "type": "Feature",
  "properties": {
    "gn:admin1_code":"8.0",
    "gn:asciiname":"Palangan",
    "gn:country_code":"ID",
    "gn:dem":43,
    "gn:feature_class":"P",
    "gn:feature_code":"PPL",
    "gn:name":"Palangan",
    "gn:population":0,
    "gn:timezone":"Asia/Jakarta",
    "iso:country":"ID",
    "name:ceb_x_preferred":[
        "Palangan"
    ],
    "name:fas_x_preferred":[
        "\u067e\u0644\u0646\u06af\u0627\u0646"
    ],
    "name:ind_x_preferred":[
        "Palangan"
    ],
    "name:nld_x_preferred":[
        "Palangan"
    ],
    "name:swe_x_preferred":[
        "Palangan"
    ],
    "wof:lang_x_official":[
        "ind"
    ],
    "wof:lang_x_spoken":[
        "ind",
        "eng"
    ],
    "wof:name":"Palangan",
    "wof:placetype":"locality"
},
  "geometry": {"coordinates":[111.6413,-7.1428],"type":"Point"}
}