{
  "type": "Feature",
  "properties": {
    "gn:admin1_code":"30",
    "gn:asciiname":"Cihaliwung",
    "gn:country_code":"ID",
    "gn:dem":700,
    "gn:feature_class":"P",
    "gn:feature_code":"PPL",
    "gn:name":"Cihaliwung",
    "gn:population":0,
    "gn:timezone":"Asia/Jakarta",
    "iso:country":"ID",
    "name:ind_x_preferred":[
        "Cihaliwung"
    ],
    "name:und_x_variant":[
        "Tjihahwung",
        "Cihahwung"
    ],
    "wof:lang_x_official":[
        "ind"
    ],
    "wof:lang_x_spoken":[
        "ind",
        "eng"
    ],
    "wof:name":"Cihaliwung",
    "wof:placetype":"locality"
},
  "geometry": {"coordinates":[107.48972000000001,-6.83778],"type":"Point"}
}