{
  "type": "Feature",
  "properties": {
    "gn:admin1_code":"30",
    "gn:asciiname":"Lango",
    "gn:country_code":"ID",
    "gn:dem":756,
    "gn:feature_class":"P",
    "gn:feature_code":"PPL",
    "gn:name":"Lango",
    "gn:population":0,
    "gn:timezone":"Asia/Jakarta",
    "iso:country":"ID",
    "name:ind_x_preferred":[
        "Lango"
    ],
    "wof:name":"Lango",
    "wof:placetype":"locality"
},
  "geometry": {"coordinates":[107.4875,-6.73778],"type":"Point"}
}