{
  "type": "Feature",
  "properties": {
    "gn:admin1_code":"30",
    "gn:asciiname":"Bojong Wetan",
    "gn:country_code":"ID",
    "gn:dem":882,
    "gn:feature_class":"P",
    "gn:feature_code":"PPL",
    "gn:name":"Bojong Wetan",
    "gn:population":0,
    "gn:timezone":"Asia/Jakarta",
    "iso:country":"ID",
    "name:ind_x_preferred":[
        "Bojong Wetan"
    ],
    "wof:name":"Bojong Wetan",
    "wof:placetype":"locality"
},
  "geometry": {"coordinates":[107.06,-6.72333],"type":"Point"}
}