{
  "type": "Feature",
  "properties": {
    "gn:admin1_code":"17.0",
    "gn:asciiname":"Lanci Tiga",
    "gn:country_code":"ID",
    "gn:dem":139,
    "gn:feature_class":"P",
    "gn:feature_code":"PPL",
    "gn:name":"Lanci Tiga",
    "gn:population":0,
    "gn:timezone":"Asia/Makassar",
    "iso:country":"ID",
    "name:ind_x_preferred":[
        "Lanci Tiga"
    ],
    "name:und_x_variant":[
        "Lanci 3"
    ],
    "wof:name":"Lanci Tiga",
    "wof:placetype":"locality"
},
  "geometry": {"coordinates":[118.33629999999999,-8.4703],"type":"Point"}
}