{
  "type": "Feature",
  "properties": {
    "gn:admin1_code":"7.0",
    "gn:asciiname":"Ngadiprono",
    "gn:country_code":"ID",
    "gn:dem":618,
    "gn:feature_class":"P",
    "gn:feature_code":"PPL",
    "gn:name":"Ngadiprono",
    "gn:population":0,
    "gn:timezone":"Asia/Jakarta",
    "iso:country":"ID",
    "wof:name":"Ngadiprono",
    "wof:placetype":"locality"
},
  "geometry": {"coordinates":[110.16417,-7.26222],"type":"Point"}
}