{
  "type": "Feature",
  "properties": {
    "gn:admin1_code":"42.0",
    "gn:asciiname":"Tanjung Selor",
    "gn:country_code":"ID",
    "gn:dem":9,
    "gn:feature_class":"P",
    "gn:feature_code":"PPLA",
    "gn:name":"Tanjung Selor",
    "gn:population":0,
    "gn:timezone":"Asia/Makassar",
    "iso:country":"ID",
    "name:ace_x_preferred":[
        "Tanjung Selor"
    ],
    "name:bjn_x_preferred":[
        "Tanjung Selor"
    ],
    "name:ceb_x_preferred":[
        "Tanjung Selor"
    ],
    "name:deu_x_preferred":[
        "Tanjung Selor"
    ],
    "name:epo_x_preferred":[
        "Tanjung Selor"
    ],
    "name:eus_x_preferred":[
        "Tanjung Selor"
    ],
    "name:fra_x_preferred":[
        "Tanjung Selor"
    ],
    "name:gor_x_preferred":[
        "Kota Tanjung Selor"
    ],
    "name:ind_x_preferred":[
        "Tanjung Selor"
    ],
    "name:jpn_x_preferred":[
        "\u30bf\u30f3\u30b8\u30e5\u30f3\u30fb\u30bb\u30ed\u30eb"
    ],
    "name:kor_x_preferred":[
        "\ud0c4\uc911\uc2ac\ub85c\ub974"
    ],
    "name:nld_x_preferred":[
        "Tanjung Selor"
    ],
    "name:pol_x_preferred":[
        "Tanjung Selor"
    ],
    "name:rus_x_preferred":[
        "\u0422\u0430\u043d\u0434\u0436\u0443\u043d\u0433\u0441\u0435\u043b\u043e\u0440"
    ],
    "name:und_x_variant":[
        "Tandjungselor",
        "Tandjoengseloe",
        "Tandjoengselor",
        "Tandjoeng Seilor",
        "Tanjongselor",
        "Tanjungselor"
    ],
    "name:urd_x_preferred":[
        "\u062a\u0627\u0646\u062c\u0648\u0646\u06af \u0633\u06cc\u0644\u0648\u0631"
    ],
    "name:zho_x_preferred":[
        "\u4e39\u620e\u65bd\u6a02"
    ],
    "wof:lang_x_official":[
        "ind"
    ],
    "wof:lang_x_spoken":[
        "ind",
        "eng"
    ],
    "wof:name":"Tanjung Selor",
    "wof:placetype":"locality"
},
  "geometry": {"coordinates":[117.36528,2.8375],"type":"Point"}
}