{
  "type": "Feature",
  "properties": {
    "gn:admin1_code":"42.0",
    "gn:asciiname":"Tanjung Selor",
    "gn:country_code":"ID",
    "gn:dem":9,
    "gn:feature_class":"P",
    "gn:feature_code":"PPLA",
    "gn:name":"Tanjung Selor",
    "gn:population":0,
    "gn:timezone":"Asia/Makassar",
    "iso:country":"ID",
    "name:ind_x_preferred":[
        "Tanjung Selor"
    ],
    "name:und_x_variant":[
        "Tandjungselor",
        "Tandjoengseloe",
        "Tandjoengselor",
        "Tandjoeng Seilor",
        "Tanjongselor",
        "Tanjungselor"
    ],
    "wof:name":"Tanjung Selor",
    "wof:placetype":"locality"
},
  "geometry": {"coordinates":[117.36528,2.8375],"type":"Point"}
}