{
  "type": "Feature",
  "properties": {
    "gn:admin1_code":"30.0",
    "gn:asciiname":"Playangan",
    "gn:country_code":"ID",
    "gn:dem":5,
    "gn:feature_class":"P",
    "gn:feature_code":"PPL",
    "gn:name":"Playangan",
    "gn:population":0,
    "gn:timezone":"Asia/Jakarta",
    "iso:country":"ID",
    "name:ind_x_preferred":[
        "Playangan"
    ],
    "name:und_x_variant":[
        "Plajangan",
        "Pelajangan",
        "Pelayangan"
    ],
    "wof:lang_x_official":[
        "ind"
    ],
    "wof:lang_x_spoken":[
        "ind",
        "eng"
    ],
    "wof:name":"Playangan",
    "wof:placetype":"locality"
},
  "geometry": {"coordinates":[108.76009999999999,-6.828],"type":"Point"}
}