{
  "type": "Feature",
  "properties": {
    "gn:admin1_code":"18",
    "gn:asciiname":"Lapalidi",
    "gn:country_code":"ID",
    "gn:dem":292,
    "gn:feature_class":"P",
    "gn:feature_code":"PPL",
    "gn:name":"Lapalidi",
    "gn:population":0,
    "gn:timezone":"Asia/Makassar",
    "iso:country":"ID",
    "name:ind_x_preferred":[
        "Lapalidi"
    ],
    "wof:name":"Lapalidi",
    "wof:placetype":"locality"
},
  "geometry": {"coordinates":[120.96080000000001,-8.4224],"type":"Point"}
}