{
  "type": "Feature",
  "properties": {
    "gn:admin1_code":"26.0",
    "gn:asciiname":"Sibagindar",
    "gn:country_code":"ID",
    "gn:dem":312,
    "gn:feature_class":"P",
    "gn:feature_code":"PPL",
    "gn:name":"Sibagindar",
    "gn:population":0,
    "gn:timezone":"Asia/Jakarta",
    "iso:country":"ID",
    "name:ind_x_preferred":[
        "Sibagindar"
    ],
    "wof:name":"Sibagindar",
    "wof:placetype":"locality"
},
  "geometry": {"coordinates":[98.1998,2.4881],"type":"Point"}
}