{
  "type": "Feature",
  "properties": {
    "gn:admin1_code":"30",
    "gn:asciiname":"Singkil",
    "gn:country_code":"ID",
    "gn:dem":5,
    "gn:feature_class":"P",
    "gn:feature_code":"PPL",
    "gn:name":"Singkil",
    "gn:population":0,
    "gn:timezone":"Asia/Jakarta",
    "iso:country":"ID",
    "name:ind_x_preferred":[
        "Singkil"
    ],
    "name:mlg_x_preferred":[
        "Singkil"
    ],
    "name:tgl_x_preferred":[
        "Singkil"
    ],
    "wof:name":"Singkil",
    "wof:placetype":"locality"
},
  "geometry": {"coordinates":[108.37166999999999,-6.34444],"type":"Point"}
}