{
  "type": "Feature",
  "properties": {
    "gn:admin1_code":"30",
    "gn:asciiname":"Leuwiliang",
    "gn:cc2":"ID",
    "gn:country_code":"ID",
    "gn:dem":1143,
    "gn:feature_class":"P",
    "gn:feature_code":"PPL",
    "gn:name":"Leuwiliang",
    "gn:population":0,
    "gn:timezone":"Asia/Jakarta",
    "iso:country":"ID",
    "name:und_x_variant":[
        "Leuwiliang Dua",
        "Leuwiliang 2",
        "Leuwiliang"
    ],
    "wof:name":"Leuwiliang",
    "wof:placetype":"locality"
},
  "geometry": {"coordinates":[107.50194,-7.11694],"type":"Point"}
}