{
  "type": "Feature",
  "properties": {
    "iso:country":"ID",
    "name:eng_x_preferred":[
        "Districts of East Java"
    ],
    "qs:name":"Kalibaru Wetan",
    "qs:name_adm0":"Indonesia",
    "qs:name_adm1":"Jawa Timur",
    "qs:photos":317,
    "qs:photos_1k":64,
    "qs:photos_9k":1,
    "qs:photos_9r":5,
    "qs:photos_all":317,
    "qs:photos_sr":5,
    "qs:placetype":"Town",
    "qs:pop_sr":"0",
    "wd:wordcount":1363,
    "wof:lang_x_official":[
        "ind"
    ],
    "wof:lang_x_spoken":[
        "ind",
        "eng"
    ],
    "wof:name":"Kalibaru Wetan",
    "wof:placetype":"locality"
},
  "geometry": {"coordinates":[114.02451499999999,-8.299942],"type":"Point"}
}