{
  "type": "Feature",
  "properties": {
    "gn:admin1_code":"07",
    "gn:asciiname":"Kaligintung",
    "gn:country_code":"ID",
    "gn:dem":673,
    "gn:feature_class":"P",
    "gn:feature_code":"PPL",
    "gn:name":"Kaligintung",
    "gn:population":0,
    "gn:timezone":"Asia/Jakarta",
    "iso:country":"ID",
    "wof:name":"Kaligintung",
    "wof:placetype":"locality"
},
  "geometry": {"coordinates":[110.32693999999999,-7.36306],"type":"Point"}
}