{
  "type": "Feature",
  "properties": {
    "gn:admin1_code":"22.0",
    "gn:asciiname":"Pongkowulu",
    "gn:country_code":"ID",
    "gn:dem":40,
    "gn:feature_class":"P",
    "gn:feature_code":"PPL",
    "gn:name":"Pongkowulu",
    "gn:population":0,
    "gn:timezone":"Asia/Makassar",
    "iso:country":"ID",
    "name:ind_x_preferred":[
        "Pongkowulu"
    ],
    "wof:name":"Pongkowulu",
    "wof:placetype":"locality"
},
  "geometry": {"coordinates":[122.9689,-5.0728],"type":"Point"}
}