{
  "type": "Feature",
  "properties": {
    "gn:admin1_code":"7",
    "gn:asciiname":"Kuwut",
    "gn:country_code":"ID",
    "gn:dem":345,
    "gn:feature_class":"P",
    "gn:feature_code":"PPL",
    "gn:name":"Kuwut",
    "gn:population":0,
    "gn:timezone":"Asia/Jakarta",
    "iso:country":"ID",
    "name:ind_x_preferred":[
        "Kuwut"
    ],
    "wof:name":"Kuwut",
    "wof:placetype":"locality"
},
  "geometry": {"coordinates":[111.10250000000001,-7.52222],"type":"Point"}
}