{
  "type": "Feature",
  "properties": {
    "gn:admin1_code":"30",
    "gn:asciiname":"Kalapa",
    "gn:country_code":"ID",
    "gn:dem":93,
    "gn:feature_class":"P",
    "gn:feature_code":"PPL",
    "gn:name":"Kalapa",
    "gn:population":0,
    "gn:timezone":"Asia/Jakarta",
    "iso:country":"ID",
    "name:ast_x_preferred":[
        "Kal\u0101pa"
    ],
    "name:fra_x_preferred":[
        "Kalapa"
    ],
    "name:ind_x_preferred":[
        "Kalapa"
    ],
    "name:spa_x_preferred":[
        "Kalapa"
    ],
    "wof:name":"Kalapa",
    "wof:placetype":"locality"
},
  "geometry": {"coordinates":[107.75861,-6.56417],"type":"Point"}
}