{
  "type": "Feature",
  "properties": {
    "gn:admin1_code":"17",
    "gn:asciiname":"Total",
    "gn:country_code":"ID",
    "gn:dem":42,
    "gn:feature_class":"P",
    "gn:feature_code":"PPL",
    "gn:name":"Total",
    "gn:population":0,
    "gn:timezone":"Asia/Makassar",
    "iso:country":"ID",
    "name:ceb_x_preferred":[
        "Total"
    ],
    "name:dan_x_preferred":[
        "Total"
    ],
    "name:deu_x_preferred":[
        "Total"
    ],
    "name:fra_x_preferred":[
        "Total"
    ],
    "name:ind_x_preferred":[
        "Total"
    ],
    "name:ita_x_preferred":[
        "Total"
    ],
    "name:nld_x_preferred":[
        "Total"
    ],
    "name:nor_x_preferred":[
        "Total"
    ],
    "name:por_x_preferred":[
        "Total"
    ],
    "name:ron_x_preferred":[
        "Total"
    ],
    "name:rus_x_preferred":[
        "Total"
    ],
    "name:spa_x_preferred":[
        "Total"
    ],
    "name:swe_x_preferred":[
        "Total"
    ],
    "wof:lang_x_official":[
        "ind"
    ],
    "wof:lang_x_spoken":[
        "ind",
        "eng"
    ],
    "wof:name":"Total",
    "wof:placetype":"locality"
},
  "geometry": {"coordinates":[116.1621,-8.7176],"type":"Point"}
}