{
  "type": "Feature",
  "properties": {
    "gn:admin1_code":"33.0",
    "gn:asciiname":"Kaduhejo",
    "gn:country_code":"ID",
    "gn:dem":267,
    "gn:feature_class":"P",
    "gn:feature_code":"PPL",
    "gn:name":"Kaduhejo",
    "gn:population":0,
    "gn:timezone":"Asia/Jakarta",
    "iso:country":"ID",
    "name:ind_x_preferred":[
        "Kaduhejo"
    ],
    "wof:name":"Kaduhejo",
    "wof:placetype":"locality"
},
  "geometry": {"coordinates":[105.94840000000001,-6.3509],"type":"Point"}
}