{
  "type": "Feature",
  "properties": {
    "gn:admin1_code":"8.0",
    "gn:asciiname":"Panebalan",
    "gn:country_code":"ID",
    "gn:dem":17,
    "gn:feature_class":"P",
    "gn:feature_code":"PPL",
    "gn:name":"Panebalan",
    "gn:population":0,
    "gn:timezone":"Asia/Jakarta",
    "iso:country":"ID",
    "name:ind_x_preferred":[
        "Panebalan"
    ],
    "wof:name":"Panebalan",
    "wof:placetype":"locality"
},
  "geometry": {"coordinates":[115.35590000000001,-6.9028],"type":"Point"}
}