{
  "type": "Feature",
  "properties": {
    "gn:admin1_code":"10",
    "gn:asciiname":"Sentul",
    "gn:country_code":"ID",
    "gn:dem":145,
    "gn:feature_class":"P",
    "gn:feature_code":"PPL",
    "gn:name":"Sentul",
    "gn:population":0,
    "gn:timezone":"Asia/Jakarta",
    "iso:country":"ID",
    "name:ceb_x_preferred":[
        "Sentul"
    ],
    "name:ind_x_preferred":[
        "Sentul"
    ],
    "name:nld_x_preferred":[
        "Sentul"
    ],
    "name:swe_x_preferred":[
        "Sentul"
    ],
    "wof:name":"Sentul",
    "wof:placetype":"locality"
},
  "geometry": {"coordinates":[110.48556000000001,-8.09278],"type":"Point"}
}