{
  "type": "Feature",
  "properties": {
    "gn:admin1_code":"34",
    "gn:asciiname":"Olumongo",
    "gn:country_code":"ID",
    "gn:dem":23,
    "gn:feature_class":"P",
    "gn:feature_code":"PPL",
    "gn:name":"Olumongo",
    "gn:population":0,
    "gn:timezone":"Asia/Makassar",
    "iso:country":"ID",
    "name:ind_x_preferred":[
        "Olumongo"
    ],
    "wof:name":"Olumongo",
    "wof:placetype":"locality"
},
  "geometry": {"coordinates":[122.8959,0.6025],"type":"Point"}
}