{
  "type": "Feature",
  "properties": {
    "gn:admin1_code":"31",
    "gn:asciiname":"Baru",
    "gn:country_code":"ID",
    "gn:dem":46,
    "gn:feature_class":"P",
    "gn:feature_code":"PPL",
    "gn:name":"Baru",
    "gn:population":0,
    "gn:timezone":"Asia/Makassar",
    "iso:country":"ID",
    "name:ces_x_preferred":[
        "Baru"
    ],
    "name:nld_x_preferred":[
        "Baru"
    ],
    "name:spa_x_preferred":[
        "Baru"
    ],
    "wof:lang_x_official":[
        "ind"
    ],
    "wof:lang_x_spoken":[
        "ind",
        "eng"
    ],
    "wof:name":"Baru",
    "wof:placetype":"locality"
},
  "geometry": {"coordinates":[124.83722,1.535],"type":"Point"}
}