{
  "type": "Feature",
  "properties": {
    "gn:country":"ID",
    "gn:fcode":"PPL",
    "gn:pop":0,
    "iso:country":"ID",
    "name:ceb_x_preferred":[
        "Paya"
    ],
    "name:deu_x_preferred":[
        "Paya"
    ],
    "name:fra_x_preferred":[
        "Paya"
    ],
    "name:mar_x_preferred":[
        "\u092a\u092f\u093e"
    ],
    "name:nld_x_preferred":[
        "Paya"
    ],
    "name:spa_x_preferred":[
        "Paya"
    ],
    "name:swe_x_preferred":[
        "Paya"
    ],
    "name:unk_x_variant":[
        "Paja"
    ],
    "qs:name":"Paya",
    "qs:name_adm0":"Indonesia",
    "qs:name_adm1":"Nanggroe Aceh Darussalam",
    "qs:photos":13,
    "qs:photos_1k":3,
    "qs:photos_9k":1,
    "qs:photos_9r":1,
    "qs:photos_all":13,
    "qs:photos_sr":1,
    "qs:placetype":"Town",
    "qs:pop_sr":"0",
    "wof:name":"Paya",
    "wof:placetype":"locality",
    "wof:population":0
},
  "geometry": {"coordinates":[95.30722,5.77972],"type":"Point"}
}