{
  "type": "Feature",
  "properties": {
    "gn:admin1_code":"2.0",
    "gn:asciiname":"Sekargunung Kelod",
    "gn:country_code":"ID",
    "gn:dem":245,
    "gn:feature_class":"P",
    "gn:feature_code":"PPL",
    "gn:name":"Sekargunung Kelod",
    "gn:population":0,
    "gn:timezone":"Asia/Makassar",
    "iso:country":"ID",
    "name:ind_x_preferred":[
        "Sekargunung Kelod"
    ],
    "wof:name":"Sekargunung Kelod",
    "wof:placetype":"locality"
},
  "geometry": {"coordinates":[115.6307,-8.4173],"type":"Point"}
}