{
  "type": "Feature",
  "properties": {
    "gn:admin1_code":"8.0",
    "gn:asciiname":"Sumbermas",
    "gn:country_code":"ID",
    "gn:dem":262,
    "gn:feature_class":"P",
    "gn:feature_code":"PPL",
    "gn:name":"Sumbermas",
    "gn:population":0,
    "gn:timezone":"Asia/Jakarta",
    "iso:country":"ID",
    "name:ind_x_preferred":[
        "Soembermas"
    ],
    "wof:name":"Sumbermas",
    "wof:placetype":"locality"
},
  "geometry": {"coordinates":[112.70050000000001,-8.3491],"type":"Point"}
}