{
  "type": "Feature",
  "properties": {
    "gn:admin1_code":"12",
    "gn:asciiname":"Tanjungmahkota",
    "gn:country_code":"ID",
    "gn:dem":7,
    "gn:feature_class":"P",
    "gn:feature_code":"PPL",
    "gn:name":"Tanjungmahkota",
    "gn:population":0,
    "gn:timezone":"Asia/Makassar",
    "iso:country":"ID",
    "name:ind_x_preferred":[
        "Tanjungmahkota"
    ],
    "wof:name":"Tanjungmahkota",
    "wof:placetype":"locality"
},
  "geometry": {"coordinates":[116.355,-2.847],"type":"Point"}
}