{
  "type": "Feature",
  "properties": {
    "gn:admin1_code":"22",
    "gn:asciiname":"Duriaasi",
    "gn:country_code":"ID",
    "gn:dem":30,
    "gn:feature_class":"P",
    "gn:feature_code":"PPL",
    "gn:name":"Duriaasi",
    "gn:population":0,
    "gn:timezone":"Asia/Makassar",
    "iso:country":"ID",
    "name:ind_x_preferred":[
        "Duriaasi"
    ],
    "wof:name":"Duriaasi",
    "wof:placetype":"locality"
},
  "geometry": {"coordinates":[122.1585,-3.9563],"type":"Point"}
}