{
  "type": "Feature",
  "properties": {
    "gn:admin1_code":"12.0",
    "gn:asciiname":"Telukkemuning",
    "gn:country_code":"ID",
    "gn:dem":85,
    "gn:feature_class":"P",
    "gn:feature_code":"PPL",
    "gn:name":"Telukkemuning",
    "gn:population":0,
    "gn:timezone":"Asia/Makassar",
    "iso:country":"ID",
    "name:ind_x_preferred":[
        "Telukkemuning"
    ],
    "wof:name":"Telukkemuning",
    "wof:placetype":"locality"
},
  "geometry": {"coordinates":[116.13748,-4.03019],"type":"Point"}
}