{
  "type": "Feature",
  "properties": {
    "gn:admin1_code":"30",
    "gn:asciiname":"Pasirkebon",
    "gn:country_code":"ID",
    "gn:dem":1087,
    "gn:feature_class":"P",
    "gn:feature_code":"PPL",
    "gn:name":"Pasirkebon",
    "gn:population":0,
    "gn:timezone":"Asia/Jakarta",
    "iso:country":"ID",
    "name:ind_x_preferred":[
        "Pasirkebon"
    ],
    "wof:name":"Pasirkebon",
    "wof:placetype":"locality"
},
  "geometry": {"coordinates":[107.79940000000001,-7.2296],"type":"Point"}
}