{
  "type": "Feature",
  "properties": {
    "gn:admin1_code":"26.0",
    "gn:asciiname":"Tanjung Saribu",
    "gn:country_code":"ID",
    "gn:dem":1240,
    "gn:feature_class":"P",
    "gn:feature_code":"PPL",
    "gn:name":"Tanjung Saribu",
    "gn:population":0,
    "gn:timezone":"Asia/Jakarta",
    "iso:country":"ID",
    "name:ind_x_preferred":[
        "Tanjung Saribu"
    ],
    "name:und_x_variant":[
        "Tandjoeng Sariboe"
    ],
    "wof:name":"Tanjung Saribu",
    "wof:placetype":"locality"
},
  "geometry": {"coordinates":[98.7851,2.8552],"type":"Point"}
}