{
  "type": "Feature",
  "properties": {
    "gn:admin1_code":"21",
    "gn:asciiname":"Kilo",
    "gn:country_code":"ID",
    "gn:dem":879,
    "gn:feature_class":"P",
    "gn:feature_code":"PPL",
    "gn:name":"Kilo",
    "gn:population":0,
    "gn:timezone":"Asia/Makassar",
    "iso:country":"ID",
    "name:ceb_x_preferred":[
        "Kilo"
    ],
    "name:deu_x_preferred":[
        "Kilo"
    ],
    "name:ell_x_preferred":[
        "\u039a\u03b9\u03bb\u03cc"
    ],
    "name:epo_x_preferred":[
        "Kilo"
    ],
    "name:eus_x_preferred":[
        "Kilo"
    ],
    "name:fin_x_preferred":[
        "Kilo"
    ],
    "name:glg_x_preferred":[
        "Kilo"
    ],
    "name:heb_x_preferred":[
        "\u05e7\u05d9\u05dc\u05d5"
    ],
    "name:ind_x_preferred":[
        "Kilo"
    ],
    "name:ita_x_preferred":[
        "Kilo"
    ],
    "name:kor_x_preferred":[
        "\ud0ac\ub85c"
    ],
    "name:lim_x_preferred":[
        "Kilo"
    ],
    "name:nds_x_preferred":[
        "Kilo"
    ],
    "name:nld_x_preferred":[
        "Kilo"
    ],
    "name:por_x_preferred":[
        "Quilo"
    ],
    "name:spa_x_preferred":[
        "Kilo"
    ],
    "name:swe_x_preferred":[
        "Kilo"
    ],
    "name:ukr_x_preferred":[
        "\u041a\u0456\u043b\u043e"
    ],
    "name:urd_x_preferred":[
        "\u06a9\u0644\u0648"
    ],
    "wof:lang_x_official":[
        "ind"
    ],
    "wof:lang_x_spoken":[
        "ind",
        "eng"
    ],
    "wof:name":"Kilo",
    "wof:placetype":"locality"
},
  "geometry": {"coordinates":[119.9087,-1.6802],"type":"Point"}
}