{
  "type": "Feature",
  "properties": {
    "gn:admin1_code":"21",
    "gn:asciiname":"Keuno",
    "gn:country_code":"ID",
    "gn:dem":51,
    "gn:feature_class":"P",
    "gn:feature_code":"PPL",
    "gn:name":"Keuno",
    "gn:population":0,
    "gn:timezone":"Asia/Makassar",
    "iso:country":"ID",
    "name:ind_x_preferred":[
        "Keuno"
    ],
    "wof:name":"Keuno",
    "wof:placetype":"locality"
},
  "geometry": {"coordinates":[121.5029,-2.165],"type":"Point"}
}