{
  "type": "Feature",
  "properties": {
    "gn:admin1_code":"30",
    "gn:asciiname":"Selong",
    "gn:country_code":"ID",
    "gn:dem":2,
    "gn:feature_class":"P",
    "gn:feature_code":"PPL",
    "gn:name":"Selong",
    "gn:population":0,
    "gn:timezone":"Asia/Jakarta",
    "iso:country":"ID",
    "name:ind_x_preferred":[
        "Selong"
    ],
    "name:jav_x_preferred":[
        "Selong"
    ],
    "name:msa_x_preferred":[
        "Selong"
    ],
    "name:ukr_x_preferred":[
        "\u0421\u0435\u043b\u043e\u043d\u0433"
    ],
    "wof:lang_x_official":[
        "ind"
    ],
    "wof:lang_x_spoken":[
        "ind",
        "eng"
    ],
    "wof:name":"Selong",
    "wof:placetype":"locality"
},
  "geometry": {"coordinates":[107.38249999999999,-6.02],"type":"Point"}
}