{
  "type": "Feature",
  "properties": {
    "gn:admin1_code":"42.0",
    "gn:asciiname":"Ambalat",
    "gn:country_code":"ID",
    "gn:dem":44,
    "gn:feature_class":"P",
    "gn:feature_code":"PPL",
    "gn:name":"Ambalat",
    "gn:population":0,
    "gn:timezone":"Asia/Makassar",
    "iso:country":"ID",
    "name:fas_x_preferred":[
        "\u0627\u0645\u0628\u0627\u0644\u0627\u062a"
    ],
    "name:ind_x_preferred":[
        "Ambalat"
    ],
    "name:jav_x_preferred":[
        "Ambalat"
    ],
    "name:msa_x_preferred":[
        "Ambalat"
    ],
    "wof:name":"Ambalat",
    "wof:placetype":"locality"
},
  "geometry": {"coordinates":[117.12705,3.24447],"type":"Point"}
}