{
  "type": "Feature",
  "properties": {
    "gn:admin1_code":"7",
    "gn:asciiname":"Leter Lor",
    "gn:country_code":"ID",
    "gn:dem":14,
    "gn:feature_class":"P",
    "gn:feature_code":"PPL",
    "gn:name":"Leter Lor",
    "gn:population":0,
    "gn:timezone":"Asia/Jakarta",
    "iso:country":"ID",
    "name:ind_x_preferred":[
        "Leter Lor"
    ],
    "wof:name":"Leter Lor",
    "wof:placetype":"locality"
},
  "geometry": {"coordinates":[109.75611000000001,-7.74222],"type":"Point"}
}