{
  "type": "Feature",
  "properties": {
    "gn:admin1_code":"18.0",
    "gn:asciiname":"Weepoda",
    "gn:country_code":"ID",
    "gn:dem":425,
    "gn:feature_class":"P",
    "gn:feature_code":"PPL",
    "gn:name":"Weepoda",
    "gn:population":0,
    "gn:timezone":"Asia/Makassar",
    "iso:country":"ID",
    "name:ind_x_preferred":[
        "Weepoda"
    ],
    "wof:name":"Weepoda",
    "wof:placetype":"locality"
},
  "geometry": {"coordinates":[119.3796,-9.6255],"type":"Point"}
}