{
  "type": "Feature",
  "properties": {
    "gn:admin1_code":"26.0",
    "gn:asciiname":"Silau Malihat",
    "gn:country_code":"ID",
    "gn:dem":1093,
    "gn:feature_class":"P",
    "gn:feature_code":"PPL",
    "gn:name":"Silau Malihat",
    "gn:population":0,
    "gn:timezone":"Asia/Jakarta",
    "iso:country":"ID",
    "name:ind_x_preferred":[
        "Silau Malihat"
    ],
    "name:und_x_variant":[
        "Silau Marihat"
    ],
    "wof:lang_x_official":[
        "ind"
    ],
    "wof:lang_x_spoken":[
        "ind",
        "eng"
    ],
    "wof:name":"Silau Malihat",
    "wof:placetype":"locality"
},
  "geometry": {"coordinates":[98.8078,2.893],"type":"Point"}
}