{
  "type": "Feature",
  "properties": {
    "gn:admin1_code":"30",
    "gn:asciiname":"Cigadung",
    "gn:cc2":"ID",
    "gn:country_code":"ID",
    "gn:dem":1141,
    "gn:feature_class":"P",
    "gn:feature_code":"PPL",
    "gn:name":"Cigadung",
    "gn:population":0,
    "gn:timezone":"Asia/Jakarta",
    "iso:country":"ID",
    "name:und_x_variant":[
        "Tjigadung",
        "Cigadung"
    ],
    "wof:name":"Cigadung",
    "wof:placetype":"locality"
},
  "geometry": {"coordinates":[107.50472000000001,-7.08833],"type":"Point"}
}