{
  "type": "Feature",
  "properties": {
    "gn:admin1_code":"7",
    "gn:asciiname":"Pagonan",
    "gn:country_code":"ID",
    "gn:dem":595,
    "gn:feature_class":"P",
    "gn:feature_code":"PPL",
    "gn:name":"Pagonan",
    "gn:population":0,
    "gn:timezone":"Asia/Jakarta",
    "iso:country":"ID",
    "name:ind_x_preferred":[
        "Pagonan"
    ],
    "wof:name":"Pagonan",
    "wof:placetype":"locality"
},
  "geometry": {"coordinates":[110.9483,-6.6225],"type":"Point"}
}