{
  "type": "Feature",
  "properties": {
    "gn:admin1_code":"32.0",
    "gn:asciiname":"Pagar Jati",
    "gn:country_code":"ID",
    "gn:dem":165,
    "gn:feature_class":"P",
    "gn:feature_code":"PPL",
    "gn:name":"Pagar Jati",
    "gn:population":0,
    "gn:timezone":"Asia/Jakarta",
    "iso:country":"ID",
    "name:ind_x_preferred":[
        "Pagar Jati"
    ],
    "name:und_x_variant":[
        "Pagerdjati",
        "Djati",
        "Pagerdjatl",
        "Jati"
    ],
    "wof:name":"Pagar Jati",
    "wof:placetype":"locality"
},
  "geometry": {"coordinates":[103.25147,-3.74856],"type":"Point"}
}