{
  "type": "Feature",
  "properties": {
    "gn:admin1_code":"30.0",
    "gn:asciiname":"Pogorsari",
    "gn:country_code":"ID",
    "gn:dem":392,
    "gn:feature_class":"P",
    "gn:feature_code":"PPL",
    "gn:name":"Pogorsari",
    "gn:population":0,
    "gn:timezone":"Asia/Jakarta",
    "iso:country":"ID",
    "name:ind_x_preferred":[
        "Pogorsari"
    ],
    "wof:name":"Pogorsari",
    "wof:placetype":"locality"
},
  "geometry": {"coordinates":[108.3642,-7.1867],"type":"Point"}
}