{
  "type": "Feature",
  "properties": {
    "gn:admin1_code":"7.0",
    "gn:asciiname":"Gajahmungkur",
    "gn:country_code":"ID",
    "gn:dem":83,
    "gn:feature_class":"P",
    "gn:feature_code":"PPL",
    "gn:name":"Gajahmungkur",
    "gn:population":0,
    "gn:timezone":"Asia/Jakarta",
    "iso:country":"ID",
    "name:ind_x_preferred":[
        "Gajahmungkur"
    ],
    "wof:name":"Gajahmungkur",
    "wof:placetype":"locality"
},
  "geometry": {"coordinates":[110.41240000000001,-7.0078],"type":"Point"}
}