{
  "type": "Feature",
  "properties": {
    "gn:admin1_code":"7",
    "gn:asciiname":"Muteran",
    "gn:country_code":"ID",
    "gn:dem":279,
    "gn:feature_class":"P",
    "gn:feature_code":"PPL",
    "gn:name":"Muteran",
    "gn:population":0,
    "gn:timezone":"Asia/Jakarta",
    "iso:country":"ID",
    "name:ind_x_preferred":[
        "Muteran"
    ],
    "wof:name":"Muteran",
    "wof:placetype":"locality"
},
  "geometry": {"coordinates":[110.2456,-7.0466],"type":"Point"}
}