{
  "type": "Feature",
  "properties": {
    "gn:admin1_code":"30",
    "gn:asciiname":"Tamannuansamajasem",
    "gn:country_code":"ID",
    "gn:dem":27,
    "gn:feature_class":"P",
    "gn:feature_code":"PPL",
    "gn:name":"Tamannuansamajasem",
    "gn:population":0,
    "gn:timezone":"Asia/Jakarta",
    "iso:country":"ID",
    "name:ind_x_preferred":[
        "Tamannuansamajasem"
    ],
    "wof:name":"Tamannuansamajasem",
    "wof:placetype":"locality"
},
  "geometry": {"coordinates":[108.5243,-6.7379],"type":"Point"}
}