{
  "type": "Feature",
  "properties": {
    "gn:admin1_code":"07",
    "gn:asciiname":"Jambon",
    "gn:country_code":"ID",
    "gn:dem":953,
    "gn:feature_class":"P",
    "gn:feature_code":"PPL",
    "gn:name":"Jambon",
    "gn:population":0,
    "gn:timezone":"Asia/Jakarta",
    "iso:country":"ID",
    "name:ind_x_preferred":[
        "Jambon"
    ],
    "name:und_x_variant":[
        "Djambon"
    ],
    "wof:name":"Jambon",
    "wof:placetype":"locality"
},
  "geometry": {"coordinates":[110.32138999999999,-7.24056],"type":"Point"}
}