{
  "type": "Feature",
  "properties": {
    "gn:admin1_code":"7",
    "gn:asciiname":"Karangmojo",
    "gn:country_code":"ID",
    "gn:dem":71,
    "gn:feature_class":"P",
    "gn:feature_code":"PPL",
    "gn:name":"Karangmojo",
    "gn:population":0,
    "gn:timezone":"Asia/Jakarta",
    "iso:country":"ID",
    "name:ind_x_preferred":[
        "Karangmojo"
    ],
    "wof:name":"Karangmojo",
    "wof:placetype":"locality"
},
  "geometry": {"coordinates":[111.32277999999999,-7.18833],"type":"Point"}
}