{
  "type": "Feature",
  "properties": {
    "gn:admin1_code":"8",
    "gn:asciiname":"Rejeng Wetan",
    "gn:country_code":"ID",
    "gn:dem":329,
    "gn:feature_class":"P",
    "gn:feature_code":"PPL",
    "gn:name":"Rejeng Wetan",
    "gn:population":0,
    "gn:timezone":"Asia/Jakarta",
    "iso:country":"ID",
    "name:ind_x_preferred":[
        "Rejeng Wetan"
    ],
    "wof:name":"Rejeng Wetan",
    "wof:placetype":"locality"
},
  "geometry": {"coordinates":[114.19499999999999,-8.2496],"type":"Point"}
}