{
  "type": "Feature",
  "properties": {
    "gn:admin1_code":"33.0",
    "gn:asciiname":"Cepakbinglu",
    "gn:country_code":"ID",
    "gn:dem":417,
    "gn:feature_class":"P",
    "gn:feature_code":"PPL",
    "gn:name":"Cepakbinglu",
    "gn:population":0,
    "gn:timezone":"Asia/Jakarta",
    "iso:country":"ID",
    "name:ind_x_preferred":[
        "Cepakbinglu"
    ],
    "wof:name":"Cepakbinglu",
    "wof:placetype":"locality"
},
  "geometry": {"coordinates":[106.1992,-6.6569],"type":"Point"}
}