{
  "type": "Feature",
  "properties": {
    "gn:admin1_code":"18.0",
    "gn:asciiname":"Kadaka",
    "gn:country_code":"ID",
    "gn:dem":732,
    "gn:feature_class":"P",
    "gn:feature_code":"PPL",
    "gn:name":"Kadaka",
    "gn:population":0,
    "gn:timezone":"Asia/Makassar",
    "iso:country":"ID",
    "name:ces_x_preferred":[
        "Kadaka"
    ],
    "name:est_x_preferred":[
        "Kadaka"
    ],
    "name:fra_x_preferred":[
        "Kadaka"
    ],
    "name:ind_x_preferred":[
        "Kadaka"
    ],
    "name:nld_x_preferred":[
        "Kadaka"
    ],
    "name:pol_x_preferred":[
        "Kadaka"
    ],
    "name:sco_x_preferred":[
        "Kadaka"
    ],
    "name:ukr_x_preferred":[
        "\u041a\u0430\u0434\u0430\u043a\u0430"
    ],
    "name:vol_x_preferred":[
        "Kadaka"
    ],
    "wof:lang_x_official":[
        "ind"
    ],
    "wof:lang_x_spoken":[
        "ind",
        "eng"
    ],
    "wof:name":"Kadaka",
    "wof:placetype":"locality"
},
  "geometry": {"coordinates":[124.736,-8.3376],"type":"Point"}
}