{
  "type": "Feature",
  "properties": {
    "gn:admin1_code":"05",
    "gn:asciiname":"Buntumahang",
    "gn:country_code":"ID",
    "gn:dem":22,
    "gn:feature_class":"P",
    "gn:feature_code":"PPL",
    "gn:name":"Buntumahang",
    "gn:population":0,
    "gn:timezone":"Asia/Jakarta",
    "iso:country":"ID",
    "name:ind_x_preferred":[
        "Buntumahang"
    ],
    "wof:name":"Buntumahang",
    "wof:placetype":"locality"
},
  "geometry": {"coordinates":[103.37390000000001,-1.1075],"type":"Point"}
}