{
  "type": "Feature",
  "properties": {
    "gn:admin1_code":"2.0",
    "gn:asciiname":"Lumbungsari",
    "gn:country_code":"ID",
    "gn:dem":45,
    "gn:feature_class":"P",
    "gn:feature_code":"PPL",
    "gn:name":"Lumbungsari",
    "gn:population":0,
    "gn:timezone":"Asia/Makassar",
    "iso:country":"ID",
    "name:ind_x_preferred":[
        "Lumbungsari"
    ],
    "wof:name":"Lumbungsari",
    "wof:placetype":"locality"
},
  "geometry": {"coordinates":[115.22190000000001,-8.6381],"type":"Point"}
}