{
  "type": "Feature",
  "properties": {
    "gn:admin1_code":"8.0",
    "gn:asciiname":"Durbugan",
    "gn:country_code":"ID",
    "gn:dem":58,
    "gn:feature_class":"P",
    "gn:feature_code":"PPL",
    "gn:name":"Durbugan",
    "gn:population":0,
    "gn:timezone":"Asia/Jakarta",
    "iso:country":"ID",
    "name:ind_x_preferred":[
        "Durbugan"
    ],
    "wof:name":"Durbugan",
    "wof:placetype":"locality"
},
  "geometry": {"coordinates":[113.3596,-7.1746],"type":"Point"}
}