{
  "type": "Feature",
  "properties": {
    "gn:admin1_code":"30.0",
    "gn:asciiname":"Pinggirsari",
    "gn:country_code":"ID",
    "gn:dem":1245,
    "gn:feature_class":"P",
    "gn:feature_code":"PPL",
    "gn:name":"Pinggirsari",
    "gn:population":0,
    "gn:timezone":"Asia/Jakarta",
    "iso:country":"ID",
    "name:ind_x_preferred":[
        "Pinggirsari"
    ],
    "wof:name":"Pinggirsari",
    "wof:placetype":"locality"
},
  "geometry": {"coordinates":[107.78879999999999,-7.3497],"type":"Point"}
}