{
  "type": "Feature",
  "properties": {
    "gn:admin1_code":"29.0",
    "gn:asciiname":"Samada",
    "gn:country_code":"ID",
    "gn:dem":13,
    "gn:feature_class":"P",
    "gn:feature_code":"PPL",
    "gn:name":"Samada",
    "gn:population":0,
    "gn:timezone":"Asia/Jayapura",
    "iso:country":"ID",
    "name:ind_x_preferred":[
        "Samada"
    ],
    "name:msa_x_preferred":[
        "Samada"
    ],
    "name:zho_x_preferred":[
        "\u8428\u739b\u8fbe\u4e61"
    ],
    "wof:lang_x_official":[
        "ind"
    ],
    "wof:lang_x_spoken":[
        "ind",
        "eng"
    ],
    "wof:name":"Samada",
    "wof:placetype":"locality"
},
  "geometry": {"coordinates":[124.49644000000001,-1.66117],"type":"Point"}
}