{
  "type": "Feature",
  "properties": {
    "gn:country":"ID",
    "gn:fcode":"PPL",
    "gn:pop":0,
    "iso:country":"ID",
    "name:unk_x_variant":[
        "Dalaindah"
    ],
    "qs:name":"Bale Endah",
    "qs:name_adm0":"Indonesia",
    "qs:name_adm1":"Jawa Barat",
    "qs:photos_9r":0,
    "qs:photos_sr":0,
    "qs:placetype":"Town",
    "qs:pop_sr":"0",
    "wof:name":"Bale Endah",
    "wof:placetype":"locality",
    "wof:population":0
},
  "geometry": {"coordinates":[107.62778,-7.01167],"type":"Point"}
}