{
  "type": "Feature",
  "properties": {
    "gn:admin1_code":"30",
    "gn:asciiname":"Rawalele",
    "gn:country_code":"ID",
    "gn:dem":92,
    "gn:feature_class":"P",
    "gn:feature_code":"PPL",
    "gn:name":"Rawalele",
    "gn:population":0,
    "gn:timezone":"Asia/Jakarta",
    "iso:country":"ID",
    "name:ind_x_preferred":[
        "Rawalele"
    ],
    "wof:name":"Rawalele",
    "wof:placetype":"locality"
},
  "geometry": {"coordinates":[107.715,-6.54167],"type":"Point"}
}