{
  "type": "Feature",
  "properties": {
    "gn:admin1_code":"8",
    "gn:asciiname":"Sumberagung",
    "gn:country_code":"ID",
    "gn:dem":92,
    "gn:feature_class":"P",
    "gn:feature_code":"PPL",
    "gn:name":"Sumberagung",
    "gn:population":0,
    "gn:timezone":"Asia/Jakarta",
    "iso:country":"ID",
    "name:ind_x_preferred":[
        "Sumberagung"
    ],
    "wof:name":"Sumberagung",
    "wof:placetype":"locality"
},
  "geometry": {"coordinates":[111.6953,-7.5022],"type":"Point"}
}