{
  "type": "Feature",
  "properties": {
    "gn:admin1_code":"8.0",
    "gn:asciiname":"Sumberingin",
    "gn:country_code":"ID",
    "gn:dem":741,
    "gn:feature_class":"P",
    "gn:feature_code":"PPLA4",
    "gn:name":"Sumberingin",
    "gn:population":0,
    "gn:timezone":"Asia/Jakarta",
    "iso:country":"ID",
    "name:ind_x_preferred":[
        "Sumberingin"
    ],
    "wof:lang_x_official":[
        "ind"
    ],
    "wof:lang_x_spoken":[
        "ind",
        "eng"
    ],
    "wof:name":"Sumberingin",
    "wof:placetype":"locality"
},
  "geometry": {"coordinates":[112.465,-8.0428],"type":"Point"}
}