{
  "type": "Feature",
  "properties": {
    "gn:admin1_code":"36.0",
    "gn:asciiname":"Atsy",
    "gn:country_code":"ID",
    "gn:dem":5,
    "gn:feature_class":"P",
    "gn:feature_code":"PPL",
    "gn:name":"Atsy",
    "gn:population":0,
    "gn:timezone":"Asia/Jayapura",
    "iso:country":"ID",
    "name:ind_x_preferred":[
        "Atsy"
    ],
    "name:und_x_variant":[
        "Atsj"
    ],
    "wof:name":"Atsy",
    "wof:placetype":"locality"
},
  "geometry": {"coordinates":[138.38345000000001,-5.73512],"type":"Point"}
}