{
  "type": "Feature",
  "properties": {
    "gn:admin1_code":"17.0",
    "gn:asciiname":"Pagutan",
    "gn:country_code":"ID",
    "gn:dem":360,
    "gn:feature_class":"P",
    "gn:feature_code":"PPL",
    "gn:name":"Pagutan",
    "gn:population":0,
    "gn:timezone":"Asia/Makassar",
    "iso:country":"ID",
    "name:ind_x_preferred":[
        "Pagutan"
    ],
    "wof:name":"Pagutan",
    "wof:placetype":"locality"
},
  "geometry": {"coordinates":[116.2945,-8.5649],"type":"Point"}
}