{
  "type": "Feature",
  "properties": {
    "gn:admin1_code":"7",
    "gn:asciiname":"Ngawen",
    "gn:country_code":"ID",
    "gn:dem":169,
    "gn:feature_class":"P",
    "gn:feature_code":"PPL",
    "gn:name":"Ngawen",
    "gn:population":0,
    "gn:timezone":"Asia/Jakarta",
    "iso:country":"ID",
    "name:ind_x_preferred":[
        "Ngawen"
    ],
    "wof:name":"Ngawen",
    "wof:placetype":"locality"
},
  "geometry": {"coordinates":[110.9654,-6.5356],"type":"Point"}
}