{
  "type": "Feature",
  "properties": {
    "gn:admin1_code":"26",
    "gn:asciiname":"Tanjung Morawa B Sepuluh",
    "gn:country_code":"ID",
    "gn:dem":21,
    "gn:feature_class":"P",
    "gn:feature_code":"PPL",
    "gn:name":"Tanjung Morawa B Sepuluh",
    "gn:population":0,
    "gn:timezone":"Asia/Jakarta",
    "iso:country":"ID",
    "name:ind_x_preferred":[
        "Tanjung Morawa B Sepuluh"
    ],
    "name:und_x_variant":[
        "Tanjungmorawa B 10"
    ],
    "wof:name":"Tanjung Morawa B Sepuluh",
    "wof:placetype":"locality"
},
  "geometry": {"coordinates":[98.8146,3.5396],"type":"Point"}
}