{
  "type": "Feature",
  "properties": {
    "gn:admin1_code":"18.0",
    "gn:asciiname":"Okanjara",
    "gn:country_code":"ID",
    "gn:dem":116,
    "gn:feature_class":"P",
    "gn:feature_code":"PPL",
    "gn:name":"Okanjara",
    "gn:population":0,
    "gn:timezone":"Asia/Makassar",
    "iso:country":"ID",
    "name:ind_x_preferred":[
        "Okanjara"
    ],
    "wof:name":"Okanjara",
    "wof:placetype":"locality"
},
  "geometry": {"coordinates":[120.6181,-10.2022],"type":"Point"}
}