{
  "type": "Feature",
  "properties": {
    "gn:admin1_code":"31.0",
    "gn:asciiname":"Lumahado",
    "gn:country_code":"ID",
    "gn:dem":243,
    "gn:feature_class":"P",
    "gn:feature_code":"PPL",
    "gn:name":"Lumahado",
    "gn:population":0,
    "gn:timezone":"Asia/Makassar",
    "iso:country":"ID",
    "name:ind_x_preferred":[
        "Lumahado"
    ],
    "wof:name":"Lumahado",
    "wof:placetype":"locality"
},
  "geometry": {"coordinates":[125.51909999999999,3.4521],"type":"Point"}
}