{
  "type": "Feature",
  "properties": {
    "gn:admin1_code":"30.0",
    "gn:asciiname":"Cibelangbeng",
    "gn:country_code":"ID",
    "gn:dem":273,
    "gn:feature_class":"P",
    "gn:feature_code":"PPL",
    "gn:name":"Cibelangbeng",
    "gn:population":0,
    "gn:timezone":"Asia/Jakarta",
    "iso:country":"ID",
    "name:ind_x_preferred":[
        "Cibelangbeng"
    ],
    "wof:name":"Cibelangbeng",
    "wof:placetype":"locality"
},
  "geometry": {"coordinates":[106.53879999999999,-7.2689],"type":"Point"}
}