{
  "type": "Feature",
  "properties": {
    "gn:admin1_code":"7",
    "gn:asciiname":"Gesik",
    "gn:country_code":"ID",
    "gn:dem":77,
    "gn:feature_class":"P",
    "gn:feature_code":"PPLA4",
    "gn:name":"Gesik",
    "gn:population":0,
    "gn:timezone":"Asia/Jakarta",
    "iso:country":"ID",
    "name:ind_x_preferred":[
        "Gesik"
    ],
    "wof:name":"Gesik",
    "wof:placetype":"locality"
},
  "geometry": {"coordinates":[111.3336,-7.0464],"type":"Point"}
}