{
  "type": "Feature",
  "properties": {
    "gn:admin1_code":"7.0",
    "gn:asciiname":"Cerak",
    "gn:country_code":"ID",
    "gn:dem":150,
    "gn:feature_class":"P",
    "gn:feature_code":"PPL",
    "gn:name":"Cerak",
    "gn:population":0,
    "gn:timezone":"Asia/Jakarta",
    "iso:country":"ID",
    "name:fra_x_preferred":[
        "Cerak"
    ],
    "name:ind_x_preferred":[
        "Cerak"
    ],
    "name:srp_x_preferred":[
        "\u0426\u0435\u0440\u0430\u043a"
    ],
    "wof:lang_x_official":[
        "ind"
    ],
    "wof:lang_x_spoken":[
        "ind",
        "eng"
    ],
    "wof:name":"Cerak",
    "wof:placetype":"locality"
},
  "geometry": {"coordinates":[109.65167,-7.53222],"type":"Point"}
}