{
  "type": "Feature",
  "properties": {
    "gn:admin1_code":"1.0",
    "gn:asciiname":"Bunta",
    "gn:country_code":"ID",
    "gn:dem":19,
    "gn:feature_class":"P",
    "gn:feature_code":"PPL",
    "gn:name":"Bunta",
    "gn:population":0,
    "gn:timezone":"Asia/Jakarta",
    "iso:country":"ID",
    "name:epo_x_preferred":[
        "Bunto"
    ],
    "name:fra_x_preferred":[
        "Bunta"
    ],
    "name:ind_x_preferred":[
        "Bunta"
    ],
    "name:pol_x_preferred":[
        "Bunta"
    ],
    "name:und_x_variant":[
        "Boenta",
        "Buntha"
    ],
    "wof:lang_x_official":[
        "ind"
    ],
    "wof:lang_x_spoken":[
        "ind",
        "eng"
    ],
    "wof:name":"Bunta",
    "wof:placetype":"locality"
},
  "geometry": {"coordinates":[95.6653,4.6594],"type":"Point"}
}