{
  "type": "Feature",
  "properties": {
    "gn:admin1_code":"30.0",
    "gn:asciiname":"Pamimpiran",
    "gn:country_code":"ID",
    "gn:dem":455,
    "gn:feature_class":"P",
    "gn:feature_code":"PPL",
    "gn:name":"Pamimpiran",
    "gn:population":0,
    "gn:timezone":"Asia/Jakarta",
    "iso:country":"ID",
    "name:ind_x_preferred":[
        "Pamimpiran"
    ],
    "wof:name":"Pamimpiran",
    "wof:placetype":"locality"
},
  "geometry": {"coordinates":[106.7816,-7.1477],"type":"Point"}
}