{
  "type": "Feature",
  "properties": {
    "gn:admin1_code":"7.0",
    "gn:asciiname":"Tukangawitan",
    "gn:country_code":"ID",
    "gn:dem":358,
    "gn:feature_class":"P",
    "gn:feature_code":"PPL",
    "gn:name":"Tukangawitan",
    "gn:population":0,
    "gn:timezone":"Asia/Jakarta",
    "iso:country":"ID",
    "wof:name":"Tukangawitan",
    "wof:placetype":"locality"
},
  "geometry": {"coordinates":[110.22889000000001,-7.4825],"type":"Point"}
}