{
  "type": "Feature",
  "properties": {
    "gn:admin1_code":"26.0",
    "gn:asciiname":"Simangapu",
    "gn:country_code":"ID",
    "gn:dem":1102,
    "gn:feature_class":"P",
    "gn:feature_code":"PPL",
    "gn:name":"Simangapu",
    "gn:population":0,
    "gn:timezone":"Asia/Jakarta",
    "iso:country":"ID",
    "name:ind_x_preferred":[
        "Simangapu"
    ],
    "wof:name":"Simangapu",
    "wof:placetype":"locality"
},
  "geometry": {"coordinates":[98.7992,2.9274],"type":"Point"}
}