{
  "type": "Feature",
  "properties": {
    "gn:admin1_code":"37.0",
    "gn:asciiname":"Airkuning",
    "gn:country_code":"ID",
    "gn:dem":17,
    "gn:feature_class":"P",
    "gn:feature_code":"PPL",
    "gn:name":"Airkuning",
    "gn:population":0,
    "gn:timezone":"Asia/Jakarta",
    "iso:country":"ID",
    "name:ind_x_preferred":[
        "Airkuning"
    ],
    "wof:name":"Airkuning",
    "wof:placetype":"locality"
},
  "geometry": {"coordinates":[101.6446,0.5461],"type":"Point"}
}