{
  "type": "Feature",
  "properties": {
    "gn:admin1_code":"0.0",
    "gn:asciiname":"Duri-kecil",
    "gn:cc2":"ID",
    "gn:country_code":"ID",
    "gn:dem":4,
    "gn:feature_class":"P",
    "gn:feature_code":"PPL",
    "gn:name":"Duri-kecil",
    "gn:population":0,
    "gn:timezone":"Asia/Jakarta",
    "iso:country":"ID",
    "name:und_x_variant":[
        "Dur-ketjil",
        "Duri-ketjil",
        "Doeri-ketjil",
        "Duri-kecil"
    ],
    "wof:lang_x_official":[
        "ind"
    ],
    "wof:lang_x_spoken":[
        "ind",
        "eng"
    ],
    "wof:name":"Duri-kecil",
    "wof:placetype":"locality"
},
  "geometry": {"coordinates":[106.72444,-6.15806],"type":"Point"}
}