{
  "type": "Feature",
  "properties": {
    "gn:admin1_code":"30.0",
    "gn:asciiname":"Kunciran",
    "gn:cc2":"ID",
    "gn:country_code":"ID",
    "gn:dem":21,
    "gn:feature_class":"P",
    "gn:feature_code":"PPL",
    "gn:name":"Kunciran",
    "gn:population":0,
    "gn:timezone":"Asia/Jakarta",
    "iso:country":"ID",
    "name:und_x_variant":[
        "Koentjiran 1",
        "Kuntjiran",
        "Kuntjiran 1",
        "Kunciran"
    ],
    "wof:lang_x_official":[
        "ind"
    ],
    "wof:lang_x_spoken":[
        "ind",
        "eng"
    ],
    "wof:name":"Kunciran",
    "wof:placetype":"locality"
},
  "geometry": {"coordinates":[106.66777999999999,-6.21944],"type":"Point"}
}