{
  "type": "Feature",
  "properties": {
    "gn:admin1_code":"8.0",
    "gn:asciiname":"Genting",
    "gn:country_code":"ID",
    "gn:dem":403,
    "gn:feature_class":"P",
    "gn:feature_code":"PPL",
    "gn:name":"Genting",
    "gn:population":0,
    "gn:timezone":"Asia/Jakarta",
    "iso:country":"ID",
    "name:ind_x_preferred":[
        "Genting"
    ],
    "wof:name":"Genting",
    "wof:placetype":"locality"
},
  "geometry": {"coordinates":[112.6657,-7.6871],"type":"Point"}
}