{
  "type": "Feature",
  "properties": {
    "gn:admin1_code":"7",
    "gn:asciiname":"Ketanggi",
    "gn:country_code":"ID",
    "gn:dem":79,
    "gn:feature_class":"P",
    "gn:feature_code":"PPLA4",
    "gn:name":"Ketanggi",
    "gn:population":0,
    "gn:timezone":"Asia/Jakarta",
    "iso:country":"ID",
    "name:ind_x_preferred":[
        "Ketanggi"
    ],
    "wof:name":"Ketanggi",
    "wof:placetype":"locality"
},
  "geometry": {"coordinates":[111.31619999999999,-7.0156],"type":"Point"}
}