{
  "type": "Feature",
  "properties": {
    "gn:admin1_code":"0.0",
    "gn:asciiname":"Manami",
    "gn:cc2":"ID",
    "gn:country_code":"ID",
    "gn:dem":213,
    "gn:feature_class":"P",
    "gn:feature_code":"PPL",
    "gn:name":"Manami",
    "gn:population":0,
    "gn:timezone":"Asia/Jayapura",
    "iso:country":"ID",
    "name:und_x_variant":[
        "Manum",
        "Manam",
        "Manami"
    ],
    "wof:name":"Manami",
    "wof:placetype":"locality"
},
  "geometry": {"coordinates":[135.01667,-3.88333],"type":"Point"}
}