{
  "type": "Feature",
  "properties": {
    "gn:admin1_code":"1",
    "gn:asciiname":"Teungoh",
    "gn:country_code":"ID",
    "gn:dem":18,
    "gn:feature_class":"P",
    "gn:feature_code":"PPL",
    "gn:name":"Teungoh",
    "gn:population":0,
    "gn:timezone":"Asia/Jakarta",
    "iso:country":"ID",
    "name:ind_x_preferred":[
        "Teungoh"
    ],
    "wof:name":"Teungoh",
    "wof:placetype":"locality"
},
  "geometry": {"coordinates":[97.27070000000001,5.0133],"type":"Point"}
}