{
  "type": "Feature",
  "properties": {
    "gn:admin1_code":"33.0",
    "gn:asciiname":"Pasartundun",
    "gn:country_code":"ID",
    "gn:dem":122,
    "gn:feature_class":"P",
    "gn:feature_code":"PPL",
    "gn:name":"Pasartundun",
    "gn:population":0,
    "gn:timezone":"Asia/Jakarta",
    "iso:country":"ID",
    "name:ind_x_preferred":[
        "Pasartundun"
    ],
    "wof:name":"Pasartundun",
    "wof:placetype":"locality"
},
  "geometry": {"coordinates":[106.1053,-6.3637],"type":"Point"}
}