{
  "type": "Feature",
  "properties": {
    "gn:admin1_code":"30.0",
    "gn:asciiname":"Kudu",
    "gn:country_code":"ID",
    "gn:dem":43,
    "gn:feature_class":"P",
    "gn:feature_code":"PPL",
    "gn:name":"Kudu",
    "gn:population":0,
    "gn:timezone":"Asia/Jakarta",
    "iso:country":"ID",
    "name:ces_x_preferred":[
        "Kudu"
    ],
    "name:fas_x_preferred":[
        "\u06a9\u0648\u062f\u0648"
    ],
    "name:fra_x_preferred":[
        "Koudou"
    ],
    "name:ind_x_preferred":[
        "Kudu"
    ],
    "name:kaz_x_preferred":[
        "\u041a\u0443\u0434\u0443"
    ],
    "name:lez_x_preferred":[
        "\u041a\u0443\u0434\u0443"
    ],
    "name:msa_x_preferred":[
        "Kudu"
    ],
    "name:por_x_preferred":[
        "Cudo"
    ],
    "wof:lang_x_official":[
        "ind"
    ],
    "wof:lang_x_spoken":[
        "ind",
        "eng"
    ],
    "wof:name":"Kudu",
    "wof:placetype":"locality"
},
  "geometry": {"coordinates":[111.4614,-7.3447],"type":"Point"}
}