{
  "type": "Feature",
  "properties": {
    "gn:admin1_code":"8.0",
    "gn:asciiname":"Bapelem",
    "gn:country_code":"ID",
    "gn:dem":63,
    "gn:feature_class":"P",
    "gn:feature_code":"PPL",
    "gn:name":"Bapelem",
    "gn:population":0,
    "gn:timezone":"Asia/Jakarta",
    "iso:country":"ID",
    "name:ind_x_preferred":[
        "Bapelem"
    ],
    "wof:name":"Bapelem",
    "wof:placetype":"locality"
},
  "geometry": {"coordinates":[113.83540000000001,-6.9813],"type":"Point"}
}