{
  "type": "Feature",
  "properties": {
    "gn:admin1_code":"33.0",
    "gn:asciiname":"Pamatangkawung",
    "gn:country_code":"ID",
    "gn:dem":6,
    "gn:feature_class":"P",
    "gn:feature_code":"PPL",
    "gn:name":"Pamatangkawung",
    "gn:population":0,
    "gn:timezone":"Asia/Jakarta",
    "iso:country":"ID",
    "name:ind_x_preferred":[
        "Pamatangkawung"
    ],
    "wof:name":"Pamatangkawung",
    "wof:placetype":"locality"
},
  "geometry": {"coordinates":[105.80929999999999,-6.511],"type":"Point"}
}