{
  "type": "Feature",
  "properties": {
    "gn:admin1_code":"7.0",
    "gn:asciiname":"Dukuhbanjaran",
    "gn:country_code":"ID",
    "gn:dem":264,
    "gn:feature_class":"P",
    "gn:feature_code":"PPL",
    "gn:name":"Dukuhbanjaran",
    "gn:population":0,
    "gn:timezone":"Asia/Jakarta",
    "iso:country":"ID",
    "name:ind_x_preferred":[
        "Dukuhbanjaran"
    ],
    "wof:name":"Dukuhbanjaran",
    "wof:placetype":"locality"
},
  "geometry": {"coordinates":[109.36,-7.57778],"type":"Point"}
}