{
  "type": "Feature",
  "properties": {
    "gn:country":"ID",
    "gn:fcode":"PPL",
    "gn:pop":0,
    "iso:country":"ID",
    "name:unk_x_variant":[
        "Pedurenan Dua"
    ],
    "qs:name":"Pedurenan",
    "qs:name_adm0":"Indonesia",
    "qs:name_adm1":"Banten",
    "qs:photos_9r":0,
    "qs:photos_sr":0,
    "qs:placetype":"Town",
    "qs:pop_sr":"0",
    "wof:lang_x_official":[
        "ind"
    ],
    "wof:lang_x_spoken":[
        "ind",
        "eng"
    ],
    "wof:name":"Pedurenan",
    "wof:placetype":"locality",
    "wof:population":0
},
  "geometry": {"coordinates":[106.82306,-6.22611],"type":"Point"}
}