{
  "type": "Feature",
  "properties": {
    "gn:admin1_code":"21.0",
    "gn:asciiname":"Bonebaru",
    "gn:country_code":"ID",
    "gn:dem":1,
    "gn:feature_class":"P",
    "gn:feature_code":"PPL",
    "gn:name":"Bonebaru",
    "gn:population":0,
    "gn:timezone":"Asia/Makassar",
    "iso:country":"ID",
    "name:ind_x_preferred":[
        "Bonebaru"
    ],
    "wof:name":"Bonebaru",
    "wof:placetype":"locality"
},
  "geometry": {"coordinates":[123.4923,-1.5326],"type":"Point"}
}