{
  "type": "Feature",
  "properties": {
    "gn:admin1_code":"30",
    "gn:asciiname":"Munjuljayapermai",
    "gn:country_code":"ID",
    "gn:dem":99,
    "gn:feature_class":"P",
    "gn:feature_code":"PPL",
    "gn:name":"Munjuljayapermai",
    "gn:population":0,
    "gn:timezone":"Asia/Jakarta",
    "iso:country":"ID",
    "name:ind_x_preferred":[
        "Munjuljayapermai"
    ],
    "wof:name":"Munjuljayapermai",
    "wof:placetype":"locality"
},
  "geometry": {"coordinates":[107.45556000000001,-6.53472],"type":"Point"}
}