{
  "type": "Feature",
  "properties": {
    "gn:admin1_code":"7.0",
    "gn:asciiname":"Kragilan",
    "gn:country_code":"ID",
    "gn:dem":282,
    "gn:feature_class":"P",
    "gn:feature_code":"PPL",
    "gn:name":"Kragilan",
    "gn:population":0,
    "gn:timezone":"Asia/Jakarta",
    "iso:country":"ID",
    "wof:name":"Kragilan",
    "wof:placetype":"locality"
},
  "geometry": {"coordinates":[110.20556000000001,-7.56],"type":"Point"}
}