{
  "type": "Feature",
  "properties": {
    "gn:admin1_code":"26",
    "gn:asciiname":"Najalow",
    "gn:country_code":"ID",
    "gn:dem":243,
    "gn:feature_class":"P",
    "gn:feature_code":"PPL",
    "gn:name":"Najalow",
    "gn:population":0,
    "gn:timezone":"Asia/Jakarta",
    "iso:country":"ID",
    "name:ind_x_preferred":[
        "Najalow"
    ],
    "name:und_x_variant":[
        "Nadjalow"
    ],
    "wof:name":"Najalow",
    "wof:placetype":"locality"
},
  "geometry": {"coordinates":[97.5534,1.2994],"type":"Point"}
}