{
  "type": "Feature",
  "properties": {
    "gn:admin1_code":"7.0",
    "gn:asciiname":"Sinanggul Timur",
    "gn:country_code":"ID",
    "gn:dem":46,
    "gn:feature_class":"P",
    "gn:feature_code":"PPL",
    "gn:name":"Sinanggul Timur",
    "gn:population":0,
    "gn:timezone":"Asia/Jakarta",
    "iso:country":"ID",
    "name:ind_x_preferred":[
        "Sinanggul Timur"
    ],
    "wof:name":"Sinanggul Timur",
    "wof:placetype":"locality"
},
  "geometry": {"coordinates":[110.7159,-6.5451],"type":"Point"}
}