{
  "type": "Feature",
  "properties": {
    "gn:admin1_code":"8",
    "gn:asciiname":"Batok",
    "gn:country_code":"ID",
    "gn:dem":511,
    "gn:feature_class":"P",
    "gn:feature_code":"PPL",
    "gn:name":"Batok",
    "gn:population":0,
    "gn:timezone":"Asia/Jakarta",
    "iso:country":"ID",
    "name:ind_x_preferred":[
        "Batok"
    ],
    "wof:name":"Batok",
    "wof:placetype":"locality"
},
  "geometry": {"coordinates":[111.71639999999999,-7.6991],"type":"Point"}
}