{
  "type": "Feature",
  "properties": {
    "gn:admin1_code":"18.0",
    "gn:asciiname":"Sabu Dua",
    "gn:country_code":"ID",
    "gn:dem":772,
    "gn:feature_class":"P",
    "gn:feature_code":"PPL",
    "gn:name":"Sabu Dua",
    "gn:population":0,
    "gn:timezone":"Asia/Makassar",
    "iso:country":"ID",
    "name:ind_x_preferred":[
        "Sabu Dua"
    ],
    "wof:lang_x_official":[
        "ind"
    ],
    "wof:lang_x_spoken":[
        "ind",
        "eng"
    ],
    "wof:name":"Sabu Dua",
    "wof:placetype":"locality"
},
  "geometry": {"coordinates":[124.27549999999999,-9.8707],"type":"Point"}
}