{
  "type": "Feature",
  "properties": {
    "gn:admin1_code":"18.0",
    "gn:asciiname":"Nanga",
    "gn:country_code":"ID",
    "gn:dem":25,
    "gn:feature_class":"P",
    "gn:feature_code":"PPL",
    "gn:name":"Nanga",
    "gn:population":0,
    "gn:timezone":"Asia/Makassar",
    "iso:country":"ID",
    "name:ceb_x_preferred":[
        "Nanga"
    ],
    "name:fra_x_preferred":[
        "Nanga"
    ],
    "name:ind_x_preferred":[
        "Nanga"
    ],
    "name:swe_x_preferred":[
        "Nanga"
    ],
    "wof:name":"Nanga",
    "wof:placetype":"locality"
},
  "geometry": {"coordinates":[122.12820000000001,-8.7221],"type":"Point"}
}