{
  "type": "Feature",
  "properties": {
    "gn:admin1_code":"31.0",
    "gn:asciiname":"Lelepu",
    "gn:country_code":"ID",
    "gn:dem":173,
    "gn:feature_class":"P",
    "gn:feature_code":"PPL",
    "gn:name":"Lelepu",
    "gn:population":0,
    "gn:timezone":"Asia/Makassar",
    "iso:country":"ID",
    "name:ind_x_preferred":[
        "Lelepu"
    ],
    "wof:name":"Lelepu",
    "wof:placetype":"locality"
},
  "geometry": {"coordinates":[125.4819,3.634],"type":"Point"}
}