{
  "type": "Feature",
  "properties": {
    "gn:admin1_code":"26",
    "gn:asciiname":"Pondok Tangsi",
    "gn:country_code":"ID",
    "gn:dem":120,
    "gn:feature_class":"P",
    "gn:feature_code":"PPL",
    "gn:name":"Pondok Tangsi",
    "gn:population":0,
    "gn:timezone":"Asia/Jakarta",
    "iso:country":"ID",
    "name:ind_x_preferred":[
        "Pondok Tangsi"
    ],
    "wof:name":"Pondok Tangsi",
    "wof:placetype":"locality"
},
  "geometry": {"coordinates":[99.10720000000001,3.1645],"type":"Point"}
}