{
  "type": "Feature",
  "properties": {
    "gn:admin1_code":"07",
    "gn:asciiname":"Seno",
    "gn:country_code":"ID",
    "gn:dem":855,
    "gn:feature_class":"P",
    "gn:feature_code":"PPL",
    "gn:name":"Seno",
    "gn:population":0,
    "gn:timezone":"Asia/Jakarta",
    "iso:country":"ID",
    "name:ceb_x_preferred":[
        "Seno"
    ],
    "name:deu_x_preferred":[
        "Seno"
    ],
    "name:fra_x_preferred":[
        "Seno"
    ],
    "name:ita_x_preferred":[
        "Seno"
    ],
    "name:por_x_preferred":[
        "Seno"
    ],
    "name:rus_x_preferred":[
        "\u0421\u0435\u043d\u043e"
    ],
    "name:spa_x_preferred":[
        "Seno"
    ],
    "name:swe_x_preferred":[
        "Seno"
    ],
    "name:ukr_x_preferred":[
        "\u0421\u0435\u043d\u043e"
    ],
    "name:und_x_variant":[
        "Sono",
        "Seno"
    ],
    "wof:name":"Seno",
    "wof:placetype":"locality"
},
  "geometry": {"coordinates":[110.34361,-7.47],"type":"Point"}
}