{
  "type": "Feature",
  "properties": {
    "gn:admin1_code":"34",
    "gn:asciiname":"Pantai",
    "gn:country_code":"ID",
    "gn:dem":1,
    "gn:feature_class":"P",
    "gn:feature_code":"PPL",
    "gn:name":"Pantai",
    "gn:population":0,
    "gn:timezone":"Asia/Makassar",
    "iso:country":"ID",
    "name:epo_x_preferred":[
        "Pantai"
    ],
    "name:ind_x_preferred":[
        "Pantai"
    ],
    "name:msa_x_preferred":[
        "Pantai"
    ],
    "wof:lang_x_official":[
        "ind"
    ],
    "wof:lang_x_spoken":[
        "ind",
        "eng"
    ],
    "wof:name":"Pantai",
    "wof:placetype":"locality"
},
  "geometry": {"coordinates":[122.304,0.4901],"type":"Point"}
}