{
  "type": "Feature",
  "properties": {
    "gn:admin1_code":"7",
    "gn:asciiname":"Mojoreno Kidul",
    "gn:country_code":"ID",
    "gn:dem":248,
    "gn:feature_class":"P",
    "gn:feature_code":"PPL",
    "gn:name":"Mojoreno Kidul",
    "gn:population":0,
    "gn:timezone":"Asia/Jakarta",
    "iso:country":"ID",
    "name:ind_x_preferred":[
        "Mojoreno Kidul"
    ],
    "wof:name":"Mojoreno Kidul",
    "wof:placetype":"locality"
},
  "geometry": {"coordinates":[111.05916999999999,-7.85889],"type":"Point"}
}