{
  "type": "Feature",
  "properties": {
    "gn:admin1_code":"18.0",
    "gn:asciiname":"Nus",
    "gn:country_code":"ID",
    "gn:dem":465,
    "gn:feature_class":"P",
    "gn:feature_code":"PPL",
    "gn:name":"Nus",
    "gn:population":0,
    "gn:timezone":"Asia/Makassar",
    "iso:country":"ID",
    "name:als_x_preferred":[
        "Nus"
    ],
    "name:azb_x_preferred":[
        "\u0646\u0648\u0633"
    ],
    "name:bel_x_preferred":[
        "\u041d\u044e\u0441"
    ],
    "name:bul_x_preferred":[
        "\u041d\u044e\u0441"
    ],
    "name:cat_x_preferred":[
        "Nus"
    ],
    "name:ceb_x_preferred":[
        "Nus"
    ],
    "name:deu_x_preferred":[
        "Nus"
    ],
    "name:epo_x_preferred":[
        "Nus"
    ],
    "name:eus_x_preferred":[
        "Nus"
    ],
    "name:fas_x_preferred":[
        "\u0646\u0648\u0633"
    ],
    "name:fra_x_preferred":[
        "Nus"
    ],
    "name:hun_x_preferred":[
        "Nus"
    ],
    "name:hye_x_preferred":[
        "\u0546\u0575\u0578\u0582\u057d"
    ],
    "name:ina_x_preferred":[
        "Nus"
    ],
    "name:ind_x_preferred":[
        "Nus"
    ],
    "name:ita_x_preferred":[
        "Nus"
    ],
    "name:jpn_x_preferred":[
        "\u30cb\u30e5\u30b9"
    ],
    "name:kaz_x_preferred":[
        "\u041d\u044e\u0441"
    ],
    "name:lat_x_preferred":[
        "Nucetum"
    ],
    "name:lmo_x_preferred":[
        "Nus"
    ],
    "name:msa_x_preferred":[
        "Nus"
    ],
    "name:nap_x_preferred":[
        "Nus"
    ],
    "name:nld_x_preferred":[
        "Nus"
    ],
    "name:pms_x_preferred":[
        "Nus"
    ],
    "name:pol_x_preferred":[
        "Nus"
    ],
    "name:ron_x_preferred":[
        "Nus"
    ],
    "name:rus_x_preferred":[
        "\u041d\u044e\u0441"
    ],
    "name:scn_x_preferred":[
        "Nus"
    ],
    "name:spa_x_preferred":[
        "Nus"
    ],
    "name:srp_x_preferred":[
        "\u041d\u0443\u0437"
    ],
    "name:swe_x_preferred":[
        "Nus"
    ],
    "name:tgl_x_preferred":[
        "Nus"
    ],
    "name:ukr_x_preferred":[
        "\u041d\u044e\u0441"
    ],
    "name:uzb_x_preferred":[
        "Nus"
    ],
    "name:vie_x_preferred":[
        "Nus"
    ],
    "name:vol_x_preferred":[
        "Nus"
    ],
    "name:war_x_preferred":[
        "Nus"
    ],
    "wof:lang_x_official":[
        "ind"
    ],
    "wof:lang_x_spoken":[
        "ind",
        "eng"
    ],
    "wof:name":"Nus",
    "wof:placetype":"locality"
},
  "geometry": {"coordinates":[124.3794,-10.0577],"type":"Point"}
}