{
  "type": "Feature",
  "properties": {
    "gn:admin1_code":"38.0",
    "gn:asciiname":"Langda",
    "gn:country_code":"ID",
    "gn:dem":461,
    "gn:feature_class":"P",
    "gn:feature_code":"PPL",
    "gn:name":"Langda",
    "gn:population":0,
    "gn:timezone":"Asia/Makassar",
    "iso:country":"ID",
    "name:ind_x_preferred":[
        "Langda"
    ],
    "wof:name":"Langda",
    "wof:placetype":"locality"
},
  "geometry": {"coordinates":[119.7139,-3.1919],"type":"Point"}
}