{
  "type": "Feature",
  "properties": {
    "gn:admin1_code":"8.0",
    "gn:asciiname":"Ringinanom Satu",
    "gn:country_code":"ID",
    "gn:dem":363,
    "gn:feature_class":"P",
    "gn:feature_code":"PPL",
    "gn:name":"Ringinanom Satu",
    "gn:population":0,
    "gn:timezone":"Asia/Jakarta",
    "iso:country":"ID",
    "name:ind_x_preferred":[
        "Ringinanom Satu"
    ],
    "wof:name":"Ringinanom Satu",
    "wof:placetype":"locality"
},
  "geometry": {"coordinates":[112.3412,-8.2666],"type":"Point"}
}