{
  "type": "Feature",
  "properties": {
    "gn:admin1_code":"26.0",
    "gn:asciiname":"Sibargar",
    "gn:country_code":"ID",
    "gn:dem":649,
    "gn:feature_class":"P",
    "gn:feature_code":"PPL",
    "gn:name":"Sibargar",
    "gn:population":0,
    "gn:timezone":"Asia/Jakarta",
    "iso:country":"ID",
    "name:ind_x_preferred":[
        "Sibargar"
    ],
    "wof:name":"Sibargar",
    "wof:placetype":"locality"
},
  "geometry": {"coordinates":[98.5342,2.0366],"type":"Point"}
}