{
  "type": "Feature",
  "properties": {
    "gn:admin1_code":"30.0",
    "gn:asciiname":"Tegallaja Tiga",
    "gn:country_code":"ID",
    "gn:dem":268,
    "gn:feature_class":"P",
    "gn:feature_code":"PPL",
    "gn:name":"Tegallaja Tiga",
    "gn:population":0,
    "gn:timezone":"Asia/Jakarta",
    "iso:country":"ID",
    "name:ind_x_preferred":[
        "Tegallaja Tiga"
    ],
    "wof:name":"Tegallaja Tiga",
    "wof:placetype":"locality"
},
  "geometry": {"coordinates":[107.6069,-7.4816],"type":"Point"}
}