{
  "type": "Feature",
  "properties": {
    "gn:admin1_code":"30.0",
    "gn:asciiname":"Bitung",
    "gn:country_code":"ID",
    "gn:dem":786,
    "gn:feature_class":"P",
    "gn:feature_code":"PPL",
    "gn:name":"Bitung",
    "gn:population":0,
    "gn:timezone":"Asia/Jakarta",
    "iso:country":"ID",
    "name:ind_x_preferred":[
        "Bitung"
    ],
    "wof:name":"Bitung",
    "wof:placetype":"locality"
},
  "geometry": {"coordinates":[108.023,-7.4936],"type":"Point"}
}