{
  "type": "Feature",
  "properties": {
    "gn:admin1_code":"30.0",
    "gn:asciiname":"Bitung",
    "gn:country_code":"ID",
    "gn:dem":786,
    "gn:feature_class":"P",
    "gn:feature_code":"PPL",
    "gn:name":"Bitung",
    "gn:population":0,
    "gn:timezone":"Asia/Jakarta",
    "iso:country":"ID",
    "name:ara_x_preferred":[
        "\u0628\u064a\u062a\u0648\u0646\u063a"
    ],
    "name:ceb_x_preferred":[
        "Bitung"
    ],
    "name:deu_x_preferred":[
        "Bitung"
    ],
    "name:fas_x_preferred":[
        "\u0628\u06cc\u062a\u0648\u0646\u06af"
    ],
    "name:fra_x_preferred":[
        "Bitung"
    ],
    "name:gor_x_preferred":[
        "Kota Bitung"
    ],
    "name:ind_x_preferred":[
        "Bitung"
    ],
    "name:ind_x_variant":[
        "Kota Bitung"
    ],
    "name:ita_x_preferred":[
        "Bitung"
    ],
    "name:jav_x_preferred":[
        "Kutha Bitung"
    ],
    "name:jpn_x_preferred":[
        "\u30d3\u30c4\u30f3"
    ],
    "name:mlg_x_preferred":[
        "Kota Bitung"
    ],
    "name:msa_x_preferred":[
        "Bandar Bitung"
    ],
    "name:nld_x_preferred":[
        "Bitung"
    ],
    "name:nor_x_preferred":[
        "Bitung"
    ],
    "name:pfl_x_preferred":[
        "Bitung"
    ],
    "name:pol_x_preferred":[
        "Bitung"
    ],
    "name:rus_x_preferred":[
        "\u0411\u0438\u0442\u0443\u043d\u0433"
    ],
    "name:swe_x_preferred":[
        "Bitung"
    ],
    "name:tur_x_preferred":[
        "Bitung"
    ],
    "name:urd_x_preferred":[
        "\u0628\u06cc\u062a\u0648\u0646\u06af"
    ],
    "wof:name":"Bitung",
    "wof:placetype":"locality"
},
  "geometry": {"coordinates":[108.023,-7.4936],"type":"Point"}
}