{
  "type": "Feature",
  "properties": {
    "gn:admin1_code":"30",
    "gn:asciiname":"Bojongmenteng",
    "gn:country_code":"ID",
    "gn:dem":239,
    "gn:feature_class":"P",
    "gn:feature_code":"PPL",
    "gn:name":"Bojongmenteng",
    "gn:population":0,
    "gn:timezone":"Asia/Jakarta",
    "iso:country":"ID",
    "name:ind_x_preferred":[
        "Bojongmenteng"
    ],
    "wof:name":"Bojongmenteng",
    "wof:placetype":"locality"
},
  "geometry": {"coordinates":[106.77222,-6.60194],"type":"Point"}
}