{
  "type": "Feature",
  "properties": {
    "gn:admin1_code":"7",
    "gn:asciiname":"Pedak",
    "gn:country_code":"ID",
    "gn:dem":47,
    "gn:feature_class":"P",
    "gn:feature_code":"PPL",
    "gn:name":"Pedak",
    "gn:population":0,
    "gn:timezone":"Asia/Jakarta",
    "iso:country":"ID",
    "name:ind_x_preferred":[
        "Pedak"
    ],
    "wof:name":"Pedak",
    "wof:placetype":"locality"
},
  "geometry": {"coordinates":[110.8227,-6.7709],"type":"Point"}
}