{
  "type": "Feature",
  "properties": {
    "gn:admin1_code":"30.0",
    "gn:asciiname":"Lamijaya",
    "gn:country_code":"ID",
    "gn:dem":208,
    "gn:feature_class":"P",
    "gn:feature_code":"PPL",
    "gn:name":"Lamijaya",
    "gn:population":0,
    "gn:timezone":"Asia/Jakarta",
    "iso:country":"ID",
    "name:ind_x_preferred":[
        "Lamijaya"
    ],
    "wof:name":"Lamijaya",
    "wof:placetype":"locality"
},
  "geometry": {"coordinates":[106.9969,-7.3432],"type":"Point"}
}