{
  "type": "Feature",
  "properties": {
    "gn:admin1_code":"7",
    "gn:asciiname":"Polowono Ngisor",
    "gn:country_code":"ID",
    "gn:dem":444,
    "gn:feature_class":"P",
    "gn:feature_code":"PPL",
    "gn:name":"Polowono Ngisor",
    "gn:population":0,
    "gn:timezone":"Asia/Jakarta",
    "iso:country":"ID",
    "name:ind_x_preferred":[
        "Polowono Ngisor"
    ],
    "wof:name":"Polowono Ngisor",
    "wof:placetype":"locality"
},
  "geometry": {"coordinates":[109.99167,-7.5325],"type":"Point"}
}