{
  "type": "Feature",
  "properties": {
    "gn:admin1_code":"7.0",
    "gn:admin2_code":"3312",
    "gn:asciiname":"Jrakah",
    "gn:country_code":"ID",
    "gn:dem":484,
    "gn:feature_class":"P",
    "gn:feature_code":"PPL",
    "gn:name":"Jrakah",
    "gn:population":0,
    "gn:timezone":"Asia/Jakarta",
    "iso:country":"ID",
    "wof:lang_x_official":[
        "ind"
    ],
    "wof:lang_x_spoken":[
        "ind",
        "eng"
    ],
    "wof:name":"Jrakah",
    "wof:placetype":"locality"
},
  "geometry": {"coordinates":[111.02472,-8.01083],"type":"Point"}
}