{
  "type": "Feature",
  "properties": {
    "gn:admin1_code":"30.0",
    "gn:asciiname":"Kubangsari",
    "gn:country_code":"ID",
    "gn:dem":588,
    "gn:feature_class":"P",
    "gn:feature_code":"PPL",
    "gn:name":"Kubangsari",
    "gn:population":0,
    "gn:timezone":"Asia/Jakarta",
    "iso:country":"ID",
    "name:ind_x_preferred":[
        "Kubangsari"
    ],
    "wof:name":"Kubangsari",
    "wof:placetype":"locality"
},
  "geometry": {"coordinates":[107.9204,-7.5288],"type":"Point"}
}