{
  "type": "Feature",
  "properties": {
    "gn:admin1_code":"30.0",
    "gn:asciiname":"Garutan",
    "gn:country_code":"ID",
    "gn:dem":93,
    "gn:feature_class":"P",
    "gn:feature_code":"PPL",
    "gn:name":"Garutan",
    "gn:population":0,
    "gn:timezone":"Asia/Jakarta",
    "iso:country":"ID",
    "name:ind_x_preferred":[
        "Garutan"
    ],
    "wof:name":"Garutan",
    "wof:placetype":"locality"
},
  "geometry": {"coordinates":[111.4945,-7.3912],"type":"Point"}
}