{
  "type": "Feature",
  "properties": {
    "gn:admin1_code":"30.0",
    "gn:asciiname":"Cipari",
    "gn:country_code":"ID",
    "gn:dem":14,
    "gn:feature_class":"P",
    "gn:feature_code":"PPL",
    "gn:name":"Cipari",
    "gn:population":0,
    "gn:timezone":"Asia/Jakarta",
    "iso:country":"ID",
    "name:ind_x_preferred":[
        "Cipari"
    ],
    "name:und_x_variant":[
        "Tjipari",
        "Cipari"
    ],
    "wof:name":"Cipari",
    "wof:placetype":"locality"
},
  "geometry": {"coordinates":[107.95440000000001,-7.7203],"type":"Point"}
}