{
  "type": "Feature",
  "properties": {
    "gn:admin1_code":"41.0",
    "gn:asciiname":"Salubanua",
    "gn:country_code":"ID",
    "gn:dem":800,
    "gn:feature_class":"P",
    "gn:feature_code":"PPL",
    "gn:name":"Salubanua",
    "gn:population":0,
    "gn:timezone":"Asia/Makassar",
    "iso:country":"ID",
    "name:ind_x_preferred":[
        "Salubanua"
    ],
    "wof:name":"Salubanua",
    "wof:placetype":"locality"
},
  "geometry": {"coordinates":[119.1387,-2.9981],"type":"Point"}
}