{
  "type": "Feature",
  "properties": {
    "gn:admin1_code":"5.0",
    "gn:asciiname":"Kampungdalam",
    "gn:country_code":"ID",
    "gn:dem":127,
    "gn:feature_class":"P",
    "gn:feature_code":"PPL",
    "gn:name":"Kampungdalam",
    "gn:population":0,
    "gn:timezone":"Asia/Jakarta",
    "iso:country":"ID",
    "name:ind_x_preferred":[
        "Kampungdalam"
    ],
    "wof:name":"Kampungdalam",
    "wof:placetype":"locality"
},
  "geometry": {"coordinates":[102.3263,-2.4635],"type":"Point"}
}