{
  "type": "Feature",
  "properties": {
    "gn:admin1_code":"8.0",
    "gn:asciiname":"Tenggong",
    "gn:country_code":"ID",
    "gn:dem":110,
    "gn:feature_class":"P",
    "gn:feature_code":"PPL",
    "gn:name":"Tenggong",
    "gn:population":0,
    "gn:timezone":"Asia/Jakarta",
    "iso:country":"ID",
    "name:ind_x_preferred":[
        "Tenggong"
    ],
    "wof:name":"Tenggong",
    "wof:placetype":"locality"
},
  "geometry": {"coordinates":[111.75069999999999,-8.1698],"type":"Point"}
}