{
  "type": "Feature",
  "properties": {
    "gn:admin1_code":"7.0",
    "gn:asciiname":"Gambarsari",
    "gn:country_code":"ID",
    "gn:dem":33,
    "gn:feature_class":"P",
    "gn:feature_code":"PPL",
    "gn:name":"Gambarsari",
    "gn:population":0,
    "gn:timezone":"Asia/Jakarta",
    "iso:country":"ID",
    "name:ind_x_preferred":[
        "Gambarsari"
    ],
    "wof:name":"Gambarsari",
    "wof:placetype":"locality"
},
  "geometry": {"coordinates":[109.36360999999999,-7.4325],"type":"Point"}
}