{
  "type": "Feature",
  "properties": {
    "gn:admin1_code":"32.0",
    "gn:asciiname":"Seteria",
    "gn:country_code":"ID",
    "gn:dem":16,
    "gn:feature_class":"P",
    "gn:feature_code":"PPL",
    "gn:name":"Seteria",
    "gn:population":0,
    "gn:timezone":"Asia/Jakarta",
    "iso:country":"ID",
    "name:ind_x_preferred":[
        "Seteria"
    ],
    "wof:name":"Seteria",
    "wof:placetype":"locality"
},
  "geometry": {"coordinates":[104.3818,-2.8692],"type":"Point"}
}