{
  "type": "Feature",
  "properties": {
    "gn:gn_country":"ID",
    "gn:gn_fcode":"PPL",
    "gn:gn_pop":0,
    "iso:country":"ID",
    "name:unk_x_variant":[
        "Jorong"
    ],
    "qs_pg:aaroncc":"ID",
    "qs_pg:gn_country":"ID",
    "qs_pg:gn_fcode":"PPL",
    "qs_pg:gn_pop":0,
    "qs_pg:name":"Djorong",
    "qs_pg:name_adm0":"Indonesia",
    "qs_pg:name_adm1":"Kalimantan Selatan",
    "qs_pg:photos_9r":0,
    "qs_pg:photos_sr":0,
    "qs_pg:pop_sr":4,
    "qs_pg:qs_pg_placetype":"locality",
    "qs_pg:qs_pg_placetype_gp":"Town",
    "qs_pg:woe_adm0":23424846,
    "woe:adm0_id":23424846,
    "woe:name_adm0":"Indonesia",
    "woe:name_adm1":"Kalimantan Selatan",
    "woe:placetype":"Town",
    "wof:lang_x_official":[
        "ind"
    ],
    "wof:lang_x_spoken":[
        "ind",
        "eng"
    ],
    "wof:name":"Djorong",
    "wof:placetype":"locality"
},
  "geometry": {"coordinates":[114.93333,-3.96667],"type":"Point"}
}