{
  "type": "Feature",
  "properties": {
    "gn:admin1_code":"8.0",
    "gn:asciiname":"Luksongo Satu",
    "gn:country_code":"ID",
    "gn:dem":392,
    "gn:feature_class":"P",
    "gn:feature_code":"PPL",
    "gn:name":"Luksongo Satu",
    "gn:population":0,
    "gn:timezone":"Asia/Jakarta",
    "iso:country":"ID",
    "name:ind_x_preferred":[
        "Luksongo Satu"
    ],
    "wof:name":"Luksongo Satu",
    "wof:placetype":"locality"
},
  "geometry": {"coordinates":[112.3527,-8.0432],"type":"Point"}
}