{
  "type": "Feature",
  "properties": {
    "gn:admin1_code":"21.0",
    "gn:asciiname":"Uebone",
    "gn:country_code":"ID",
    "gn:dem":25,
    "gn:feature_class":"P",
    "gn:feature_code":"PPL",
    "gn:name":"Uebone",
    "gn:population":0,
    "gn:timezone":"Asia/Makassar",
    "iso:country":"ID",
    "name:ind_x_preferred":[
        "Uebone"
    ],
    "name:und_x_variant":[
        "Oe\u00ebbonti",
        "Uebonti",
        "Oebonti",
        "Ueboni"
    ],
    "wof:lang_x_official":[
        "ind"
    ],
    "wof:lang_x_spoken":[
        "ind",
        "eng"
    ],
    "wof:name":"Uebone",
    "wof:placetype":"locality"
},
  "geometry": {"coordinates":[121.6605,-0.9165],"type":"Point"}
}