{
  "type": "Feature",
  "properties": {
    "gn:admin1_code":"1",
    "gn:asciiname":"Seuneubok Gunci",
    "gn:country_code":"ID",
    "gn:dem":44,
    "gn:feature_class":"P",
    "gn:feature_code":"PPL",
    "gn:name":"Seuneubok Gunci",
    "gn:population":0,
    "gn:timezone":"Asia/Jakarta",
    "iso:country":"ID",
    "name:ind_x_preferred":[
        "Seuneubok Gunci"
    ],
    "wof:name":"Seuneubok Gunci",
    "wof:placetype":"locality"
},
  "geometry": {"coordinates":[96.7201,5.1551],"type":"Point"}
}