{
  "type": "Feature",
  "properties": {
    "gn:admin1_code":"18.0",
    "gn:asciiname":"Ruanfeno",
    "gn:country_code":"ID",
    "gn:dem":304,
    "gn:feature_class":"P",
    "gn:feature_code":"PPL",
    "gn:name":"Ruanfeno",
    "gn:population":0,
    "gn:timezone":"Asia/Makassar",
    "iso:country":"ID",
    "name:ind_x_preferred":[
        "Ruanfeno"
    ],
    "wof:name":"Ruanfeno",
    "wof:placetype":"locality"
},
  "geometry": {"coordinates":[123.71212,-10.31401],"type":"Point"}
}