{
  "type": "Feature",
  "properties": {
    "gn:admin1_code":"26",
    "gn:asciiname":"Sambirejo Timur Delapan",
    "gn:country_code":"ID",
    "gn:dem":17,
    "gn:feature_class":"P",
    "gn:feature_code":"PPL",
    "gn:name":"Sambirejo Timur Delapan",
    "gn:population":0,
    "gn:timezone":"Asia/Jakarta",
    "iso:country":"ID",
    "name:ind_x_preferred":[
        "Sambirejo Timur Delapan"
    ],
    "name:und_x_variant":[
        "Sambirejo Timur 8"
    ],
    "wof:name":"Sambirejo Timur Delapan",
    "wof:placetype":"locality"
},
  "geometry": {"coordinates":[98.7714,3.5869],"type":"Point"}
}