{
  "type": "Feature",
  "properties": {
    "gn:admin1_code":"8",
    "gn:asciiname":"Sapulante Tengah",
    "gn:country_code":"ID",
    "gn:dem":322,
    "gn:feature_class":"P",
    "gn:feature_code":"PPL",
    "gn:name":"Sapulante Tengah",
    "gn:population":0,
    "gn:timezone":"Asia/Jakarta",
    "iso:country":"ID",
    "name:ind_x_preferred":[
        "Sapulante Tengah"
    ],
    "wof:name":"Sapulante Tengah",
    "wof:placetype":"locality"
},
  "geometry": {"coordinates":[112.8184,-7.7852],"type":"Point"}
}