{
  "type": "Feature",
  "properties": {
    "gn:admin1_code":"38",
    "gn:asciiname":"Badoah",
    "gn:country_code":"ID",
    "gn:dem":75,
    "gn:feature_class":"P",
    "gn:feature_code":"PPL",
    "gn:name":"Badoah",
    "gn:population":0,
    "gn:timezone":"Asia/Makassar",
    "iso:country":"ID",
    "name:ind_x_preferred":[
        "Badoah"
    ],
    "wof:name":"Badoah",
    "wof:placetype":"locality"
},
  "geometry": {"coordinates":[120.31570000000001,-5.3996],"type":"Point"}
}