{
  "type": "Feature",
  "properties": {
    "gn:admin1_code":"30",
    "gn:asciiname":"Ciwaru",
    "gn:cc2":"ID",
    "gn:country_code":"ID",
    "gn:dem":945,
    "gn:feature_class":"P",
    "gn:feature_code":"PPL",
    "gn:name":"Ciwaru",
    "gn:population":0,
    "gn:timezone":"Asia/Jakarta",
    "iso:country":"ID",
    "name:und_x_variant":[
        "Tjiwaru 2",
        "Ciwaru Dua",
        "Ciwaru"
    ],
    "wof:name":"Ciwaru",
    "wof:placetype":"locality"
},
  "geometry": {"coordinates":[107.63833,-7.06306],"type":"Point"}
}