{
  "type": "Feature",
  "properties": {
    "gn:admin1_code":"29.0",
    "gn:asciiname":"Tubo",
    "gn:country_code":"ID",
    "gn:dem":78,
    "gn:feature_class":"P",
    "gn:feature_code":"PPL",
    "gn:name":"Tubo",
    "gn:population":0,
    "gn:timezone":"Asia/Jayapura",
    "iso:country":"ID",
    "name:und_x_variant":[
        "Toebo",
        "Tubo"
    ],
    "wof:name":"Tubo",
    "wof:placetype":"locality"
},
  "geometry": {"coordinates":[127.37796000000002,0.82427],"type":"Point"}
}