{
  "type": "Feature",
  "properties": {
    "gn:admin1_code":"29.0",
    "gn:asciiname":"Tubo",
    "gn:country_code":"ID",
    "gn:dem":78,
    "gn:feature_class":"P",
    "gn:feature_code":"PPL",
    "gn:name":"Tubo",
    "gn:population":0,
    "gn:timezone":"Asia/Jayapura",
    "iso:country":"ID",
    "name:ceb_x_preferred":[
        "Tubo"
    ],
    "name:glg_x_preferred":[
        "Tubo"
    ],
    "name:ita_x_preferred":[
        "Tubo"
    ],
    "name:nld_x_preferred":[
        "Tubo"
    ],
    "name:spa_x_preferred":[
        "Tubo"
    ],
    "name:swe_x_preferred":[
        "Tubo"
    ],
    "name:tgl_x_preferred":[
        "Tubo"
    ],
    "name:und_x_variant":[
        "Toebo",
        "Tubo"
    ],
    "name:war_x_preferred":[
        "Tubo"
    ],
    "wof:lang_x_official":[
        "ind"
    ],
    "wof:lang_x_spoken":[
        "ind",
        "eng"
    ],
    "wof:name":"Tubo",
    "wof:placetype":"locality"
},
  "geometry": {"coordinates":[127.37796,0.82427],"type":"Point"}
}