{
  "type": "Feature",
  "properties": {
    "gn:admin1_code":"8",
    "gn:asciiname":"Sekarputih",
    "gn:country_code":"ID",
    "gn:dem":25,
    "gn:feature_class":"P",
    "gn:feature_code":"PPL",
    "gn:name":"Sekarputih",
    "gn:population":0,
    "gn:timezone":"Asia/Jakarta",
    "iso:country":"ID",
    "name:ind_x_preferred":[
        "Sekarputih"
    ],
    "wof:name":"Sekarputih",
    "wof:placetype":"locality"
},
  "geometry": {"coordinates":[112.44199999999999,-7.3024],"type":"Point"}
}