{
  "type": "Feature",
  "properties": {
    "gn:admin1_code":"07",
    "gn:asciiname":"Dampit Satu",
    "gn:cc2":"ID",
    "gn:country_code":"ID",
    "gn:dem":749,
    "gn:feature_class":"P",
    "gn:feature_code":"PPL",
    "gn:name":"Dampit Satu",
    "gn:population":0,
    "gn:timezone":"Asia/Jakarta",
    "iso:country":"ID",
    "name:und_x_variant":[
        "Dampit 1",
        "Dampit Satu"
    ],
    "wof:lang_x_official":[
        "ind"
    ],
    "wof:lang_x_spoken":[
        "ind",
        "eng"
    ],
    "wof:name":"Dampit Satu",
    "wof:placetype":"locality"
},
  "geometry": {"coordinates":[110.51721999999999,-7.40972],"type":"Point"}
}