{
  "type": "Feature",
  "properties": {
    "gn:admin1_code":"18.0",
    "gn:asciiname":"Hoka",
    "gn:country_code":"ID",
    "gn:dem":23,
    "gn:feature_class":"P",
    "gn:feature_code":"PPL",
    "gn:name":"Hoka",
    "gn:population":0,
    "gn:timezone":"Asia/Makassar",
    "iso:country":"ID",
    "name:ind_x_preferred":[
        "Hoka"
    ],
    "wof:name":"Hoka",
    "wof:placetype":"locality"
},
  "geometry": {"coordinates":[121.72709999999999,-8.3004],"type":"Point"}
}