{
  "type": "Feature",
  "properties": {
    "gn:admin1_code":"30",
    "gn:asciiname":"Gang Pesama",
    "gn:country_code":"ID",
    "gn:dem":224,
    "gn:feature_class":"P",
    "gn:feature_code":"PPL",
    "gn:name":"Gang Pesama",
    "gn:population":0,
    "gn:timezone":"Asia/Jakarta",
    "iso:country":"ID",
    "name:ind_x_preferred":[
        "Gang Pesama"
    ],
    "wof:name":"Gang Pesama",
    "wof:placetype":"locality"
},
  "geometry": {"coordinates":[106.79000000000001,-6.57417],"type":"Point"}
}