{
  "type": "Feature",
  "properties": {
    "gn:admin1_code":"32.0",
    "gn:asciiname":"Pangkalan",
    "gn:country_code":"ID",
    "gn:dem":85,
    "gn:feature_class":"P",
    "gn:feature_code":"PPL",
    "gn:name":"Pangkalan",
    "gn:population":0,
    "gn:timezone":"Asia/Jakarta",
    "iso:country":"ID",
    "name:ceb_x_preferred":[
        "Pangkalan"
    ],
    "name:ind_x_preferred":[
        "Pangkalan"
    ],
    "name:nld_x_preferred":[
        "Pangkalan"
    ],
    "name:swe_x_preferred":[
        "Pangkalan"
    ],
    "wof:name":"Pangkalan",
    "wof:placetype":"locality"
},
  "geometry": {"coordinates":[102.64019999999999,-2.6678],"type":"Point"}
}