{
  "type": "Feature",
  "properties": {
    "gn:admin1_code":"30",
    "gn:asciiname":"Parigi Lor",
    "gn:cc2":"ID",
    "gn:country_code":"ID",
    "gn:dem":71,
    "gn:feature_class":"P",
    "gn:feature_code":"PPL",
    "gn:name":"Parigi Lor",
    "gn:population":0,
    "gn:timezone":"Asia/Jakarta",
    "iso:country":"ID",
    "name:und_x_variant":[
        "Parigi",
        "Parigi Lor"
    ],
    "wof:name":"Parigi Lor",
    "wof:placetype":"locality"
},
  "geometry": {"coordinates":[106.61028,-6.37111],"type":"Point"}
}