{
  "type": "Feature",
  "properties": {
    "gn:admin1_code":"8.0",
    "gn:asciiname":"Bendo Kidul",
    "gn:country_code":"ID",
    "gn:dem":150,
    "gn:feature_class":"P",
    "gn:feature_code":"PPL",
    "gn:name":"Bendo Kidul",
    "gn:population":0,
    "gn:timezone":"Asia/Jakarta",
    "iso:country":"ID",
    "name:ind_x_preferred":[
        "Bendo Kidul"
    ],
    "wof:name":"Bendo Kidul",
    "wof:placetype":"locality"
},
  "geometry": {"coordinates":[111.37730000000001,-7.9643],"type":"Point"}
}