{
  "type": "Feature",
  "properties": {
    "gn:country":"ID",
    "gn:fcode":"PPLA4",
    "gn:pop":0,
    "iso:country":"ID",
    "name:ind_x_preferred":[
        "Tempelan"
    ],
    "qs:name":"Tempelan",
    "qs:photos_9r":0,
    "qs:photos_sr":0,
    "qs:pop_sr":"0",
    "wof:name":"Tempelan",
    "wof:placetype":"locality",
    "wof:population":0
},
  "geometry": {"coordinates":[111.4156,-6.9656],"type":"Point"}
}