{
  "type": "Feature",
  "properties": {
    "gn:admin1_code":"7",
    "gn:asciiname":"Rembundukuh",
    "gn:country_code":"ID",
    "gn:dem":6,
    "gn:feature_class":"P",
    "gn:feature_code":"PPL",
    "gn:name":"Rembundukuh",
    "gn:population":0,
    "gn:timezone":"Asia/Jakarta",
    "iso:country":"ID",
    "name:ind_x_preferred":[
        "Rembundukuh"
    ],
    "wof:name":"Rembundukuh",
    "wof:placetype":"locality"
},
  "geometry": {"coordinates":[109.5737,-6.9029],"type":"Point"}
}