{
  "type": "Feature",
  "properties": {
    "gn:admin1_code":"30.0",
    "gn:asciiname":"Nusalaksana",
    "gn:country_code":"ID",
    "gn:dem":257,
    "gn:feature_class":"P",
    "gn:feature_code":"PPL",
    "gn:name":"Nusalaksana",
    "gn:population":0,
    "gn:timezone":"Asia/Jakarta",
    "iso:country":"ID",
    "name:ind_x_preferred":[
        "Nusalaksana"
    ],
    "wof:name":"Nusalaksana",
    "wof:placetype":"locality"
},
  "geometry": {"coordinates":[108.1876,-7.4144],"type":"Point"}
}