{
  "type": "Feature",
  "properties": {
    "gn:admin1_code":"30",
    "gn:asciiname":"Legoknyenang",
    "gn:cc2":"ID",
    "gn:country_code":"ID",
    "gn:dem":682,
    "gn:feature_class":"P",
    "gn:feature_code":"PPL",
    "gn:name":"Legoknyenang",
    "gn:population":0,
    "gn:timezone":"Asia/Jakarta",
    "iso:country":"ID",
    "name:und_x_variant":[
        "Legoknjenang",
        "Legoknyenang"
    ],
    "wof:lang_x_official":[
        "ind"
    ],
    "wof:lang_x_spoken":[
        "ind",
        "eng"
    ],
    "wof:name":"Legoknyenang",
    "wof:placetype":"locality"
},
  "geometry": {"coordinates":[107.51861,-6.99222],"type":"Point"}
}