{
  "type": "Feature",
  "properties": {
    "gn:admin1_code":"26",
    "gn:asciiname":"Simbertong",
    "gn:country_code":"ID",
    "gn:dem":165,
    "gn:feature_class":"P",
    "gn:feature_code":"PPL",
    "gn:name":"Simbertong",
    "gn:population":0,
    "gn:timezone":"Asia/Jakarta",
    "iso:country":"ID",
    "name:ind_x_preferred":[
        "Simbertong"
    ],
    "wof:name":"Simbertong",
    "wof:placetype":"locality"
},
  "geometry": {"coordinates":[98.7791,3.3258],"type":"Point"}
}