{
  "type": "Feature",
  "properties": {
    "gn:admin1_code":"7.0",
    "gn:asciiname":"Pepabri",
    "gn:country_code":"ID",
    "gn:dem":29,
    "gn:feature_class":"P",
    "gn:feature_code":"PPL",
    "gn:name":"Pepabri",
    "gn:population":0,
    "gn:timezone":"Asia/Jakarta",
    "iso:country":"ID",
    "name:ind_x_preferred":[
        "Pepabri"
    ],
    "wof:name":"Pepabri",
    "wof:placetype":"locality"
},
  "geometry": {"coordinates":[109.66500000000001,-7.64694],"type":"Point"}
}