{
  "type": "Feature",
  "properties": {
    "gn:admin1_code":"37",
    "gn:asciiname":"Pulaupandang",
    "gn:country_code":"ID",
    "gn:dem":11,
    "gn:feature_class":"P",
    "gn:feature_code":"PPL",
    "gn:name":"Pulaupandang",
    "gn:population":0,
    "gn:timezone":"Asia/Jakarta",
    "iso:country":"ID",
    "name:ind_x_preferred":[
        "Pulaupandang"
    ],
    "wof:name":"Pulaupandang",
    "wof:placetype":"locality"
},
  "geometry": {"coordinates":[101.6109,0.2994],"type":"Point"}
}