{
  "type": "Feature",
  "properties": {
    "gn:admin1_code":"8.0",
    "gn:asciiname":"Kalibening",
    "gn:country_code":"ID",
    "gn:dem":41,
    "gn:feature_class":"P",
    "gn:feature_code":"PPL",
    "gn:name":"Kalibening",
    "gn:population":0,
    "gn:timezone":"Asia/Jakarta",
    "iso:country":"ID",
    "name:ind_x_preferred":[
        "Kalibening"
    ],
    "wof:name":"Kalibening",
    "wof:placetype":"locality"
},
  "geometry": {"coordinates":[112.36279999999999,-7.5813],"type":"Point"}
}