{
  "type": "Feature",
  "properties": {
    "gn:admin1_code":"8",
    "gn:asciiname":"Bulakgempol",
    "gn:country_code":"ID",
    "gn:dem":212,
    "gn:feature_class":"P",
    "gn:feature_code":"PPL",
    "gn:name":"Bulakgempol",
    "gn:population":0,
    "gn:timezone":"Asia/Jakarta",
    "iso:country":"ID",
    "name:ind_x_preferred":[
        "Bulakgempol"
    ],
    "wof:name":"Bulakgempol",
    "wof:placetype":"locality"
},
  "geometry": {"coordinates":[113.11620000000001,-8.177],"type":"Point"}
}