{
  "type": "Feature",
  "properties": {
    "gn:admin1_code":"18.0",
    "gn:asciiname":"Gopo",
    "gn:country_code":"ID",
    "gn:dem":25,
    "gn:feature_class":"P",
    "gn:feature_code":"PPL",
    "gn:name":"Gopo",
    "gn:population":0,
    "gn:timezone":"Asia/Makassar",
    "iso:country":"ID",
    "name:ceb_x_preferred":[
        "Gopo"
    ],
    "name:ind_x_preferred":[
        "Gopo"
    ],
    "name:swe_x_preferred":[
        "Gopo"
    ],
    "wof:name":"Gopo",
    "wof:placetype":"locality"
},
  "geometry": {"coordinates":[121.8824,-10.5947],"type":"Point"}
}