{
  "type": "Feature",
  "properties": {
    "gn:admin1_code":"30",
    "gn:asciiname":"Kedungringin Tengah",
    "gn:country_code":"ID",
    "gn:dem":5,
    "gn:feature_class":"P",
    "gn:feature_code":"PPL",
    "gn:name":"Kedungringin Tengah",
    "gn:population":0,
    "gn:timezone":"Asia/Jakarta",
    "iso:country":"ID",
    "name:ind_x_preferred":[
        "Kedungringin Tengah"
    ],
    "wof:name":"Kedungringin Tengah",
    "wof:placetype":"locality"
},
  "geometry": {"coordinates":[107.08499999999999,-6.08778],"type":"Point"}
}