{
  "type": "Feature",
  "properties": {
    "gn:admin1_code":"30",
    "gn:asciiname":"Paledran",
    "gn:country_code":"ID",
    "gn:dem":1431,
    "gn:feature_class":"P",
    "gn:feature_code":"PPL",
    "gn:name":"Paledran",
    "gn:population":0,
    "gn:timezone":"Asia/Jakarta",
    "iso:country":"ID",
    "wof:name":"Paledran",
    "wof:placetype":"locality"
},
  "geometry": {"coordinates":[107.58389,-7.18194],"type":"Point"}
}