{
  "type": "Feature",
  "properties": {
    "gn:admin1_code":"08",
    "gn:asciiname":"Balonggabus",
    "gn:country_code":"ID",
    "gn:dem":20,
    "gn:feature_class":"P",
    "gn:feature_code":"PPL",
    "gn:name":"Balonggabus",
    "gn:population":0,
    "gn:timezone":"Asia/Jakarta",
    "iso:country":"ID",
    "name:ind_x_preferred":[
        "Balonggabus"
    ],
    "wof:name":"Balonggabus",
    "wof:placetype":"locality"
},
  "geometry": {"coordinates":[112.5176,-7.4524],"type":"Point"}
}