{
  "type": "Feature",
  "properties": {
    "gn:admin1_code":"35.0",
    "gn:asciiname":"Pangkalraya",
    "gn:country_code":"ID",
    "gn:dem":30,
    "gn:feature_class":"P",
    "gn:feature_code":"PPL",
    "gn:name":"Pangkalraya",
    "gn:population":0,
    "gn:timezone":"Asia/Jakarta",
    "iso:country":"ID",
    "name:ind_x_preferred":[
        "Pangkal Raja"
    ],
    "name:ind_x_variant":[
        "Pangkalraya"
    ],
    "wof:name":"Pangkalraya",
    "wof:placetype":"locality"
},
  "geometry": {"coordinates":[105.95077000000001,-2.42456],"type":"Point"}
}