{
  "type": "Feature",
  "properties": {
    "gn:admin1_code":"30.0",
    "gn:asciiname":"Pasirkembang",
    "gn:country_code":"ID",
    "gn:dem":1277,
    "gn:feature_class":"P",
    "gn:feature_code":"PPL",
    "gn:name":"Pasirkembang",
    "gn:population":0,
    "gn:timezone":"Asia/Jakarta",
    "iso:country":"ID",
    "name:ind_x_preferred":[
        "Pasirkembang"
    ],
    "wof:lang_x_official":[
        "ind"
    ],
    "wof:lang_x_spoken":[
        "ind",
        "eng"
    ],
    "wof:name":"Pasirkembang",
    "wof:placetype":"locality"
},
  "geometry": {"coordinates":[107.82980000000001,-7.3798],"type":"Point"}
}