{
  "type": "Feature",
  "properties": {
    "gn:admin1_code":"30",
    "gn:asciiname":"Nagrak",
    "gn:country_code":"ID",
    "gn:dem":358,
    "gn:feature_class":"P",
    "gn:feature_code":"PPL",
    "gn:name":"Nagrak",
    "gn:population":0,
    "gn:timezone":"Asia/Jakarta",
    "iso:country":"ID",
    "name:ind_x_preferred":[
        "Nagrak"
    ],
    "wof:name":"Nagrak",
    "wof:placetype":"locality"
},
  "geometry": {"coordinates":[107.37389,-6.73333],"type":"Point"}
}