{
  "type": "Feature",
  "properties": {
    "iso:country":"ID",
    "qs:name":"Danau/waduk",
    "qs:name_adm0":"Indonesia",
    "qs:name_adm1":"Bali",
    "qs:photos":1508,
    "qs:photos_1k":306,
    "qs:photos_9k":7,
    "qs:photos_9r":8,
    "qs:photos_all":1508,
    "qs:photos_sr":13,
    "qs:placetype":"Town",
    "qs:pop_sr":"0",
    "wof:lang_x_official":[
        "ind"
    ],
    "wof:lang_x_spoken":[
        "ind",
        "eng"
    ],
    "wof:name":"Danau/waduk",
    "wof:placetype":"locality"
},
  "geometry": {"coordinates":[115.165952,-8.274662],"type":"Point"}
}