{
  "type": "Feature",
  "properties": {
    "gn:admin1_code":"30",
    "gn:asciiname":"Jatimulya",
    "gn:country_code":"ID",
    "gn:dem":26,
    "gn:feature_class":"P",
    "gn:feature_code":"PPL",
    "gn:name":"Jatimulya",
    "gn:population":0,
    "gn:timezone":"Asia/Jakarta",
    "iso:country":"ID",
    "name:ind_x_preferred":[
        "Jatimulya"
    ],
    "wof:name":"Jatimulya",
    "wof:placetype":"locality"
},
  "geometry": {"coordinates":[107.35693999999999,-6.33833],"type":"Point"}
}