{
  "type": "Feature",
  "properties": {
    "gn:admin1_code":"38",
    "gn:asciiname":"Saukeng",
    "gn:country_code":"ID",
    "gn:dem":161,
    "gn:feature_class":"P",
    "gn:feature_code":"PPL",
    "gn:name":"Saukeng",
    "gn:population":0,
    "gn:timezone":"Asia/Makassar",
    "iso:country":"ID",
    "name:ind_x_preferred":[
        "Saukeng"
    ],
    "wof:name":"Saukeng",
    "wof:placetype":"locality"
},
  "geometry": {"coordinates":[120.3877,-5.3975],"type":"Point"}
}