{
  "type": "Feature",
  "properties": {
    "gn:country":"ID",
    "gn:fcode":"PPL",
    "gn:pop":0,
    "iso:country":"ID",
    "name:ind_x_preferred":[
        "Mandiraja Kulon"
    ],
    "name:unk_x_variant":[
        "Mandiredja"
    ],
    "qs:name":"Mandiraja Kulon",
    "qs:name_adm0":"Indonesia",
    "qs:name_adm1":"Provinsi Jawa Tengah",
    "qs:photos_9k":1,
    "qs:photos_9r":1,
    "qs:photos_all":1,
    "qs:photos_sr":0,
    "qs:placetype":"Town",
    "qs:pop_sr":"0",
    "wof:lang_x_official":[
        "ind"
    ],
    "wof:lang_x_spoken":[
        "ind",
        "eng"
    ],
    "wof:name":"Mandiraja Kulon",
    "wof:placetype":"locality",
    "wof:population":0
},
  "geometry": {"coordinates":[109.52278,-7.45333],"type":"Point"}
}