{
  "type": "Feature",
  "properties": {
    "gn:admin1_code":"8",
    "gn:asciiname":"Kampungrejo",
    "gn:country_code":"ID",
    "gn:dem":477,
    "gn:feature_class":"P",
    "gn:feature_code":"PPL",
    "gn:name":"Kampungrejo",
    "gn:population":0,
    "gn:timezone":"Asia/Jakarta",
    "iso:country":"ID",
    "name:ind_x_preferred":[
        "Kampungrejo"
    ],
    "wof:name":"Kampungrejo",
    "wof:placetype":"locality"
},
  "geometry": {"coordinates":[112.6455,-7.9306],"type":"Point"}
}