{
  "type": "Feature",
  "properties": {
    "gn:admin1_code":"30.0",
    "gn:asciiname":"Nyangkokot",
    "gn:country_code":"ID",
    "gn:dem":207,
    "gn:feature_class":"P",
    "gn:feature_code":"PPL",
    "gn:name":"Nyangkokot",
    "gn:population":0,
    "gn:timezone":"Asia/Jakarta",
    "iso:country":"ID",
    "name:ind_x_preferred":[
        "Nyangkokot"
    ],
    "name:und_x_variant":[
        "Njangkokot"
    ],
    "wof:name":"Nyangkokot",
    "wof:placetype":"locality"
},
  "geometry": {"coordinates":[108.52419999999999,-7.0174],"type":"Point"}
}