{
  "type": "Feature",
  "properties": {
    "gn:admin1_code":"8.0",
    "gn:asciiname":"Krajan Curahcotok",
    "gn:country_code":"ID",
    "gn:dem":24,
    "gn:feature_class":"P",
    "gn:feature_code":"PPLA4",
    "gn:name":"Krajan Curahcotok",
    "gn:population":0,
    "gn:timezone":"Asia/Jakarta",
    "iso:country":"ID",
    "name:ind_x_preferred":[
        "Krajan Curahcotok"
    ],
    "name:ind_x_variant":[
        "Krajan"
    ],
    "wof:name":"Krajan Curahcotok",
    "wof:placetype":"locality"
},
  "geometry": {"coordinates":[114.0643,-7.7169],"type":"Point"}
}