{
  "type": "Feature",
  "properties": {
    "gn:admin1_code":"30.0",
    "gn:asciiname":"Cikadongdong",
    "gn:country_code":"ID",
    "gn:dem":631,
    "gn:feature_class":"P",
    "gn:feature_code":"PPL",
    "gn:name":"Cikadongdong",
    "gn:population":0,
    "gn:timezone":"Asia/Jakarta",
    "iso:country":"ID",
    "name:ind_x_preferred":[
        "Cikadongdong"
    ],
    "wof:name":"Cikadongdong",
    "wof:placetype":"locality"
},
  "geometry": {"coordinates":[107.9528,-7.1192],"type":"Point"}
}