{
  "type": "Feature",
  "properties": {
    "gn:admin1_code":"1",
    "gn:asciiname":"Teungku Dilaweueng",
    "gn:country_code":"ID",
    "gn:dem":10,
    "gn:feature_class":"P",
    "gn:feature_code":"PPL",
    "gn:name":"Teungku Dilaweueng",
    "gn:population":0,
    "gn:timezone":"Asia/Jakarta",
    "iso:country":"ID",
    "name:ind_x_preferred":[
        "Teungku Dilaweueng"
    ],
    "wof:name":"Teungku Dilaweueng",
    "wof:placetype":"locality"
},
  "geometry": {"coordinates":[95.8653,5.5131],"type":"Point"}
}