{
  "type": "Feature",
  "properties": {
    "gn:admin1_code":"30.0",
    "gn:asciiname":"Pasirsongket Dua",
    "gn:country_code":"ID",
    "gn:dem":200,
    "gn:feature_class":"P",
    "gn:feature_code":"PPLA4",
    "gn:name":"Pasirsongket Dua",
    "gn:population":0,
    "gn:timezone":"Asia/Jakarta",
    "iso:country":"ID",
    "name:ind_x_preferred":[
        "Pasirsongket Dua"
    ],
    "wof:name":"Pasirsongket Dua",
    "wof:placetype":"locality"
},
  "geometry": {"coordinates":[106.5946,-7.3106],"type":"Point"}
}