{
  "type": "Feature",
  "properties": {
    "gn:admin1_code":"18.0",
    "gn:asciiname":"Kailututun",
    "gn:country_code":"ID",
    "gn:dem":14,
    "gn:feature_class":"P",
    "gn:feature_code":"PPL",
    "gn:name":"Kailututun",
    "gn:population":0,
    "gn:timezone":"Asia/Makassar",
    "iso:country":"ID",
    "name:ind_x_preferred":[
        "Kailututun"
    ],
    "wof:name":"Kailututun",
    "wof:placetype":"locality"
},
  "geometry": {"coordinates":[123.35429999999999,-10.6797],"type":"Point"}
}