{
  "type": "Feature",
  "properties": {
    "gn:admin1_code":"38",
    "gn:asciiname":"Bosang Dua",
    "gn:country_code":"ID",
    "gn:dem":235,
    "gn:feature_class":"P",
    "gn:feature_code":"PPL",
    "gn:name":"Bosang Dua",
    "gn:population":0,
    "gn:timezone":"Asia/Makassar",
    "iso:country":"ID",
    "name:ind_x_preferred":[
        "Bosang Dua"
    ],
    "name:und_x_variant":[
        "Bosang 2"
    ],
    "wof:name":"Bosang Dua",
    "wof:placetype":"locality"
},
  "geometry": {"coordinates":[120.10469999999999,-5.1913],"type":"Point"}
}