{
  "type": "Feature",
  "properties": {
    "gn:admin1_code":"18.0",
    "gn:asciiname":"Denarumakapa",
    "gn:country_code":"ID",
    "gn:dem":250,
    "gn:feature_class":"P",
    "gn:feature_code":"PPL",
    "gn:name":"Denarumakapa",
    "gn:population":0,
    "gn:timezone":"Asia/Makassar",
    "iso:country":"ID",
    "name:ind_x_preferred":[
        "Denarumakapa"
    ],
    "wof:name":"Denarumakapa",
    "wof:placetype":"locality"
},
  "geometry": {"coordinates":[121.2111,-8.6517],"type":"Point"}
}