{
  "type": "Feature",
  "properties": {
    "gn:admin1_code":"34.0",
    "gn:asciiname":"Tuladenggi",
    "gn:country_code":"ID",
    "gn:dem":11,
    "gn:feature_class":"P",
    "gn:feature_code":"PPL",
    "gn:name":"Tuladenggi",
    "gn:population":0,
    "gn:timezone":"Asia/Makassar",
    "iso:country":"ID",
    "name:ind_x_preferred":[
        "Tuladenggi"
    ],
    "wof:name":"Tuladenggi",
    "wof:placetype":"locality"
},
  "geometry": {"coordinates":[123.0269,0.5577],"type":"Point"}
}