{
  "type": "Feature",
  "properties": {
    "gn:admin1_code":"37",
    "gn:asciiname":"Ukai",
    "gn:country_code":"ID",
    "gn:dem":14,
    "gn:feature_class":"P",
    "gn:feature_code":"PPL",
    "gn:name":"Ukai",
    "gn:population":0,
    "gn:timezone":"Asia/Jakarta",
    "iso:country":"ID",
    "name:eng_x_preferred":[
        "Ukai"
    ],
    "wof:name":"Ukai",
    "wof:placetype":"locality"
},
  "geometry": {"coordinates":[101.52630000000001,0.6022],"type":"Point"}
}