{
  "type": "Feature",
  "properties": {
    "gn:admin1_code":"37",
    "gn:asciiname":"Ukai",
    "gn:country_code":"ID",
    "gn:dem":14,
    "gn:feature_class":"P",
    "gn:feature_code":"PPL",
    "gn:name":"Ukai",
    "gn:population":0,
    "gn:timezone":"Asia/Jakarta",
    "iso:country":"ID",
    "name:bpy_x_preferred":[
        "\u0989\u0995\u09be\u0987"
    ],
    "name:eng_x_preferred":[
        "Ukai"
    ],
    "name:guj_x_preferred":[
        "\u0a89\u0a95\u0abe\u0a87"
    ],
    "name:ita_x_preferred":[
        "Ukai"
    ],
    "name:msa_x_preferred":[
        "Ukai"
    ],
    "name:nld_x_preferred":[
        "Ukai"
    ],
    "name:por_x_preferred":[
        "Ukai"
    ],
    "name:vie_x_preferred":[
        "Ukai"
    ],
    "wof:lang_x_official":[
        "ind"
    ],
    "wof:lang_x_spoken":[
        "ind",
        "eng"
    ],
    "wof:name":"Ukai",
    "wof:placetype":"locality"
},
  "geometry": {"coordinates":[101.52630000000001,0.6022],"type":"Point"}
}