{
  "type": "Feature",
  "properties": {
    "gn:admin1_code":"38",
    "gn:asciiname":"Palatae",
    "gn:country_code":"ID",
    "gn:dem":8,
    "gn:feature_class":"P",
    "gn:feature_code":"PPL",
    "gn:name":"Palatae",
    "gn:population":0,
    "gn:timezone":"Asia/Makassar",
    "iso:country":"ID",
    "name:ind_x_preferred":[
        "Palatae"
    ],
    "wof:name":"Palatae",
    "wof:placetype":"locality"
},
  "geometry": {"coordinates":[120.19222000000001,-5.56192],"type":"Point"}
}