{
  "type": "Feature",
  "properties": {
    "gn:admin1_code":"18.0",
    "gn:asciiname":"Bukapiting",
    "gn:country_code":"ID",
    "gn:dem":59,
    "gn:feature_class":"P",
    "gn:feature_code":"PPLA4",
    "gn:name":"Bukapiting",
    "gn:population":0,
    "gn:timezone":"Asia/Makassar",
    "iso:country":"ID",
    "name:ind_x_preferred":[
        "Bukapiting"
    ],
    "wof:name":"Bukapiting",
    "wof:placetype":"locality"
},
  "geometry": {"coordinates":[124.7606,-8.1812],"type":"Point"}
}