{
  "type": "Feature",
  "properties": {
    "gn:admin1_code":"2",
    "gn:asciiname":"Kebon Kaja",
    "gn:country_code":"ID",
    "gn:dem":646,
    "gn:feature_class":"P",
    "gn:feature_code":"PPL",
    "gn:name":"Kebon Kaja",
    "gn:population":0,
    "gn:timezone":"Asia/Makassar",
    "iso:country":"ID",
    "name:ind_x_preferred":[
        "Kebon Kaja"
    ],
    "wof:name":"Kebon Kaja",
    "wof:placetype":"locality"
},
  "geometry": {"coordinates":[115.00230000000001,-8.3702],"type":"Point"}
}