{
  "type": "Feature",
  "properties": {
    "gn:admin1_code":"05",
    "gn:asciiname":"Kedaton",
    "gn:country_code":"ID",
    "gn:dem":13,
    "gn:feature_class":"P",
    "gn:feature_code":"PPL",
    "gn:name":"Kedaton",
    "gn:population":0,
    "gn:timezone":"Asia/Jakarta",
    "iso:country":"ID",
    "name:ind_x_preferred":[
        "Kedaton"
    ],
    "wof:name":"Kedaton",
    "wof:placetype":"locality"
},
  "geometry": {"coordinates":[103.52030999999999,-1.53012],"type":"Point"}
}