{
  "type": "Feature",
  "properties": {
    "gn:admin1_code":"7",
    "gn:asciiname":"Ero Kulon",
    "gn:country_code":"ID",
    "gn:dem":30,
    "gn:feature_class":"P",
    "gn:feature_code":"PPL",
    "gn:name":"Ero Kulon",
    "gn:population":0,
    "gn:timezone":"Asia/Jakarta",
    "iso:country":"ID",
    "name:ind_x_preferred":[
        "Ero Kulon"
    ],
    "wof:name":"Ero Kulon",
    "wof:placetype":"locality"
},
  "geometry": {"coordinates":[109.81556,-7.6575],"type":"Point"}
}