{
  "type": "Feature",
  "properties": {
    "gn:admin1_code":"8.0",
    "gn:asciiname":"Sumberklampok",
    "gn:country_code":"ID",
    "gn:dem":404,
    "gn:feature_class":"P",
    "gn:feature_code":"PPL",
    "gn:name":"Sumberklampok",
    "gn:population":0,
    "gn:timezone":"Asia/Jakarta",
    "iso:country":"ID",
    "name:ind_x_preferred":[
        "Sumberklampok"
    ],
    "wof:name":"Sumberklampok",
    "wof:placetype":"locality"
},
  "geometry": {"coordinates":[111.8807,-7.7427],"type":"Point"}
}