{
  "type": "Feature",
  "properties": {
    "gn:admin1_code":"7.0",
    "gn:asciiname":"Kramattalok",
    "gn:country_code":"ID",
    "gn:dem":180,
    "gn:feature_class":"P",
    "gn:feature_code":"PPL",
    "gn:name":"Kramattalok",
    "gn:population":0,
    "gn:timezone":"Asia/Jakarta",
    "iso:country":"ID",
    "name:ind_x_preferred":[
        "Kramattalok"
    ],
    "wof:name":"Kramattalok",
    "wof:placetype":"locality"
},
  "geometry": {"coordinates":[109.00611000000001,-7.24611],"type":"Point"}
}