{
  "type": "Feature",
  "properties": {
    "gn:admin1_code":"15.0",
    "gn:asciiname":"Talang Babakan",
    "gn:country_code":"ID",
    "gn:dem":324,
    "gn:feature_class":"P",
    "gn:feature_code":"PPL",
    "gn:name":"Talang Babakan",
    "gn:population":0,
    "gn:timezone":"Asia/Jakarta",
    "iso:country":"ID",
    "name:ind_x_preferred":[
        "Talang Babakan"
    ],
    "wof:lang_x_official":[
        "ind"
    ],
    "wof:lang_x_spoken":[
        "ind",
        "eng"
    ],
    "wof:name":"Talang Babakan",
    "wof:placetype":"locality"
},
  "geometry": {"coordinates":[104.83396999999999,-5.46847],"type":"Point"}
}