{
  "type": "Feature",
  "properties": {
    "gn:admin1_code":"24.0",
    "gn:asciiname":"Lubukjaring",
    "gn:country_code":"ID",
    "gn:dem":468,
    "gn:feature_class":"P",
    "gn:feature_code":"PPL",
    "gn:name":"Lubukjaring",
    "gn:population":0,
    "gn:timezone":"Asia/Jakarta",
    "iso:country":"ID",
    "name:ind_x_preferred":[
        "Lubukjaring"
    ],
    "wof:name":"Lubukjaring",
    "wof:placetype":"locality"
},
  "geometry": {"coordinates":[101.0843,-1.5143],"type":"Point"}
}