{
  "type": "Feature",
  "properties": {
    "gn:admin1_code":"7",
    "gn:asciiname":"Bakal",
    "gn:country_code":"ID",
    "gn:dem":1836,
    "gn:feature_class":"P",
    "gn:feature_code":"PPL",
    "gn:name":"Bakal",
    "gn:population":0,
    "gn:timezone":"Asia/Jakarta",
    "iso:country":"ID",
    "name:ceb_x_preferred":[
        "Bakal"
    ],
    "name:ind_x_preferred":[
        "Bakal"
    ],
    "name:spa_x_preferred":[
        "Bakal"
    ],
    "name:swe_x_preferred":[
        "Bakal"
    ],
    "name:tgl_x_preferred":[
        "Bakal"
    ],
    "wof:name":"Bakal",
    "wof:placetype":"locality"
},
  "geometry": {"coordinates":[109.87806,-7.22028],"type":"Point"}
}