{
  "type": "Feature",
  "properties": {
    "gn:admin1_code":"15.0",
    "gn:asciiname":"Umbulan Tawan Satu",
    "gn:country_code":"ID",
    "gn:dem":93,
    "gn:feature_class":"P",
    "gn:feature_code":"PPL",
    "gn:name":"Umbulan Tawan Satu",
    "gn:population":0,
    "gn:timezone":"Asia/Jakarta",
    "iso:country":"ID",
    "name:ind_x_preferred":[
        "Umbulan Tawan Satu"
    ],
    "name:und_x_variant":[
        "Umbulan Tawan 1"
    ],
    "wof:name":"Umbulan Tawan Satu",
    "wof:placetype":"locality"
},
  "geometry": {"coordinates":[105.56397,-5.23201],"type":"Point"}
}