{
  "type": "Feature",
  "properties": {
    "gn:admin1_code":"30",
    "gn:asciiname":"Jigud",
    "gn:cc2":"ID",
    "gn:country_code":"ID",
    "gn:dem":1114,
    "gn:feature_class":"P",
    "gn:feature_code":"PPL",
    "gn:name":"Jigud",
    "gn:population":0,
    "gn:timezone":"Asia/Jakarta",
    "iso:country":"ID",
    "name:und_x_variant":[
        "Djegud",
        "Jegud",
        "Jigud"
    ],
    "wof:lang_x_official":[
        "ind"
    ],
    "wof:lang_x_spoken":[
        "ind",
        "eng"
    ],
    "wof:name":"Jigud",
    "wof:placetype":"locality"
},
  "geometry": {"coordinates":[107.58778,-7.11361],"type":"Point"}
}