{
  "type": "Feature",
  "properties": {
    "gn:admin1_code":"28.0",
    "gn:asciiname":"Manglusi",
    "gn:country_code":"ID",
    "gn:dem":22,
    "gn:feature_class":"P",
    "gn:feature_code":"PPL",
    "gn:name":"Manglusi",
    "gn:population":0,
    "gn:timezone":"Asia/Jayapura",
    "iso:country":"ID",
    "name:und_x_variant":[
        "Mangloesi",
        "Mangloessi",
        "Manglusi"
    ],
    "wof:name":"Manglusi",
    "wof:placetype":"locality"
},
  "geometry": {"coordinates":[131.66828000000001,-7.48057],"type":"Point"}
}