{
  "type": "Feature",
  "properties": {
    "gn:admin1_code":"41.0",
    "gn:asciiname":"Malolo",
    "gn:country_code":"ID",
    "gn:dem":12,
    "gn:feature_class":"P",
    "gn:feature_code":"PPL",
    "gn:name":"Malolo",
    "gn:population":0,
    "gn:timezone":"Asia/Makassar",
    "iso:country":"ID",
    "name:fij_x_preferred":[
        "Malolo"
    ],
    "name:hif_x_preferred":[
        "Malolo"
    ],
    "name:ind_x_preferred":[
        "Malolo"
    ],
    "name:ita_x_preferred":[
        "Malolo"
    ],
    "name:rus_x_preferred":[
        "\u041c\u0430\u043b\u043e\u043b\u043e"
    ],
    "wof:name":"Malolo",
    "wof:placetype":"locality"
},
  "geometry": {"coordinates":[119.0416,-2.5262],"type":"Point"}
}