{
  "type": "Feature",
  "properties": {
    "gn:admin1_code":"38",
    "gn:asciiname":"Malakaya",
    "gn:country_code":"ID",
    "gn:dem":12,
    "gn:feature_class":"P",
    "gn:feature_code":"PPL",
    "gn:name":"Malakaya",
    "gn:population":0,
    "gn:timezone":"Asia/Makassar",
    "iso:country":"ID",
    "name:ind_x_preferred":[
        "Malakaya"
    ],
    "wof:name":"Malakaya",
    "wof:placetype":"locality"
},
  "geometry": {"coordinates":[119.3937,-5.2724],"type":"Point"}
}