{
  "type": "Feature",
  "properties": {
    "gn:admin1_code":"30.0",
    "gn:asciiname":"Alangkecil",
    "gn:cc2":"ID",
    "gn:country_code":"ID",
    "gn:dem":6,
    "gn:feature_class":"P",
    "gn:feature_code":"PPL",
    "gn:name":"Alangkecil",
    "gn:population":0,
    "gn:timezone":"Asia/Jakarta",
    "iso:country":"ID",
    "name:und_x_variant":[
        "Alang-ketjil",
        "Alangkecil"
    ],
    "wof:name":"Alangkecil",
    "wof:placetype":"locality"
},
  "geometry": {"coordinates":[106.65833000000001,-6.09028],"type":"Point"}
}