{
  "type": "Feature",
  "properties": {
    "gn:admin1_code":"18.0",
    "gn:asciiname":"Gebak",
    "gn:country_code":"ID",
    "gn:dem":147,
    "gn:feature_class":"P",
    "gn:feature_code":"PPL",
    "gn:name":"Gebak",
    "gn:population":0,
    "gn:timezone":"Asia/Makassar",
    "iso:country":"ID",
    "name:ind_x_preferred":[
        "Gebak"
    ],
    "wof:name":"Gebak",
    "wof:placetype":"locality"
},
  "geometry": {"coordinates":[123.49392,-8.24544],"type":"Point"}
}