{
  "type": "Feature",
  "properties": {
    "gn:admin1_code":"10",
    "gn:asciiname":"Babur",
    "gn:country_code":"ID",
    "gn:dem":303,
    "gn:feature_class":"P",
    "gn:feature_code":"PPL",
    "gn:name":"Babur",
    "gn:population":0,
    "gn:timezone":"Asia/Jakarta",
    "iso:country":"ID",
    "name:ind_x_preferred":[
        "Babur"
    ],
    "wof:name":"Babur",
    "wof:placetype":"locality"
},
  "geometry": {"coordinates":[110.4575,-8.02917],"type":"Point"}
}