{
  "type": "Feature",
  "properties": {
    "gn:admin1_code":"28.0",
    "gn:asciiname":"Wasehut",
    "gn:country_code":"ID",
    "gn:dem":454,
    "gn:feature_class":"P",
    "gn:feature_code":"PPL",
    "gn:name":"Wasehut",
    "gn:population":0,
    "gn:timezone":"Asia/Jayapura",
    "iso:country":"ID",
    "name:ind_x_preferred":[
        "Wasehul"
    ],
    "name:ind_x_variant":[
        "Wasehut"
    ],
    "name:und_x_variant":[
        "Wa S\u00e9hoel"
    ],
    "wof:lang_x_official":[
        "ind"
    ],
    "wof:lang_x_spoken":[
        "ind",
        "eng"
    ],
    "wof:name":"Wasehut",
    "wof:placetype":"locality"
},
  "geometry": {"coordinates":[126.71821,-3.37536],"type":"Point"}
}