{
  "type": "Feature",
  "properties": {
    "gn:admin1_code":"26",
    "gn:asciiname":"Gundaling Satu",
    "gn:country_code":"ID",
    "gn:dem":498,
    "gn:feature_class":"P",
    "gn:feature_code":"PPL",
    "gn:name":"Gundaling Satu",
    "gn:population":0,
    "gn:timezone":"Asia/Jakarta",
    "iso:country":"ID",
    "name:ind_x_preferred":[
        "Gundaling Satu"
    ],
    "name:und_x_variant":[
        "Gundaling 1"
    ],
    "wof:name":"Gundaling Satu",
    "wof:placetype":"locality"
},
  "geometry": {"coordinates":[98.145,2.9515],"type":"Point"}
}