{
  "type": "Feature",
  "properties": {
    "gn:admin1_code":"3.0",
    "gn:asciiname":"Sukapindah",
    "gn:country_code":"ID",
    "gn:dem":30,
    "gn:feature_class":"P",
    "gn:feature_code":"PPL",
    "gn:name":"Sukapindah",
    "gn:population":0,
    "gn:timezone":"Asia/Jakarta",
    "iso:country":"ID",
    "name:ind_x_preferred":[
        "Sukapindah"
    ],
    "wof:name":"Sukapindah",
    "wof:placetype":"locality"
},
  "geometry": {"coordinates":[101.1841,-2.4245],"type":"Point"}
}