{
  "type": "Feature",
  "properties": {
    "gn:admin1_code":"8.0",
    "gn:asciiname":"Tanahmerah",
    "gn:country_code":"ID",
    "gn:dem":426,
    "gn:feature_class":"P",
    "gn:feature_code":"PPL",
    "gn:name":"Tanahmerah",
    "gn:population":0,
    "gn:timezone":"Asia/Jakarta",
    "iso:country":"ID",
    "name:ind_x_preferred":[
        "Tanahmerah"
    ],
    "name:ind_x_variant":[
        "Tanah Merah"
    ],
    "name:jpn_x_preferred":[
        "\u30bf\u30ca\u30e1\u30e9"
    ],
    "name:nld_x_preferred":[
        "Tanahmerah"
    ],
    "name:rus_x_preferred":[
        "\u0422\u0430\u043d\u0430\u0445\u043c\u0435\u0440\u0430\u0445"
    ],
    "name:zho_x_preferred":[
        "\u5854\u7eb3\u9ed8\u62c9"
    ],
    "wof:lang_x_official":[
        "ind"
    ],
    "wof:lang_x_spoken":[
        "ind",
        "eng"
    ],
    "wof:name":"Tanahmerah",
    "wof:placetype":"locality"
},
  "geometry": {"coordinates":[114.1374,-7.8546],"type":"Point"}
}