{
  "type": "Feature",
  "properties": {
    "gn:admin1_code":"30.0",
    "gn:asciiname":"Batukarut",
    "gn:country_code":"ID",
    "gn:dem":327,
    "gn:feature_class":"P",
    "gn:feature_code":"PPLA4",
    "gn:name":"Batukarut",
    "gn:population":0,
    "gn:timezone":"Asia/Jakarta",
    "iso:country":"ID",
    "name:ind_x_preferred":[
        "Batukarut"
    ],
    "name:und_x_variant":[
        "Batoekaroet"
    ],
    "wof:lang_x_official":[
        "ind"
    ],
    "wof:lang_x_spoken":[
        "ind",
        "eng"
    ],
    "wof:name":"Batukarut",
    "wof:placetype":"locality"
},
  "geometry": {"coordinates":[107.01434999999999,-7.29152],"type":"Point"}
}