{
  "type": "Feature",
  "properties": {
    "gn:admin1_code":"40.0",
    "gn:asciiname":"Senayang",
    "gn:country_code":"ID",
    "gn:dem":4,
    "gn:feature_class":"P",
    "gn:feature_code":"PPL",
    "gn:name":"Senayang",
    "gn:population":0,
    "gn:timezone":"Asia/Jakarta",
    "iso:country":"ID",
    "wof:lang_x_official":[
        "ind"
    ],
    "wof:lang_x_spoken":[
        "ind",
        "eng"
    ],
    "wof:name":"Senayang",
    "wof:placetype":"locality"
},
  "geometry": {"coordinates":[104.64333000000001,-0.07556],"type":"Point"}
}