{
  "type": "Feature",
  "properties": {
    "gn:admin1_code":"8",
    "gn:asciiname":"Wonosari",
    "gn:country_code":"ID",
    "gn:dem":355,
    "gn:feature_class":"P",
    "gn:feature_code":"PPL",
    "gn:name":"Wonosari",
    "gn:population":0,
    "gn:timezone":"Asia/Jakarta",
    "iso:country":"ID",
    "name:ceb_x_preferred":[
        "Kecamatan Wonosari"
    ],
    "name:ind_x_preferred":[
        "Wonosari"
    ],
    "name:jav_x_preferred":[
        "Wanasari"
    ],
    "name:msa_x_preferred":[
        "Wonosari"
    ],
    "name:sun_x_preferred":[
        "Wonosari"
    ],
    "name:szl_x_preferred":[
        "Wonosari"
    ],
    "wof:lang_x_official":[
        "ind"
    ],
    "wof:lang_x_spoken":[
        "ind",
        "eng"
    ],
    "wof:name":"Wonosari",
    "wof:placetype":"locality"
},
  "geometry": {"coordinates":[114.2923,-8.1886],"type":"Point"}
}