{
  "type": "Feature",
  "properties": {
    "gn:admin1_code":"38",
    "gn:asciiname":"Barua",
    "gn:country_code":"ID",
    "gn:dem":938,
    "gn:feature_class":"P",
    "gn:feature_code":"PPL",
    "gn:name":"Barua",
    "gn:population":0,
    "gn:timezone":"Asia/Makassar",
    "iso:country":"ID",
    "name:deu_x_preferred":[
        "Barua"
    ],
    "name:fra_x_preferred":[
        "Barua"
    ],
    "name:ind_x_preferred":[
        "Barua"
    ],
    "name:zho_x_preferred":[
        "\u5df4\u9b6f\u963f"
    ],
    "wof:name":"Barua",
    "wof:placetype":"locality"
},
  "geometry": {"coordinates":[119.9269,-3.1661],"type":"Point"}
}