{
  "type": "Feature",
  "properties": {
    "gn:admin1_code":"5.0",
    "gn:asciiname":"Kumantankecil",
    "gn:country_code":"ID",
    "gn:dem":796,
    "gn:feature_class":"P",
    "gn:feature_code":"PPL",
    "gn:name":"Kumantankecil",
    "gn:population":0,
    "gn:timezone":"Asia/Jakarta",
    "iso:country":"ID",
    "name:ind_x_preferred":[
        "Kumantankecil"
    ],
    "wof:name":"Kumantankecil",
    "wof:placetype":"locality"
},
  "geometry": {"coordinates":[101.4555,-2.0634],"type":"Point"}
}