{
  "type": "Feature",
  "properties": {
    "gn:admin1_code":"30",
    "gn:asciiname":"Bunar",
    "gn:country_code":"ID",
    "gn:dem":284,
    "gn:feature_class":"P",
    "gn:feature_code":"PPL",
    "gn:name":"Bunar",
    "gn:population":0,
    "gn:timezone":"Asia/Jakarta",
    "iso:country":"ID",
    "name:ceb_x_preferred":[
        "Bunar"
    ],
    "name:fra_x_preferred":[
        "Bunar"
    ],
    "name:ind_x_preferred":[
        "Bunar"
    ],
    "name:msa_x_preferred":[
        "Bunar"
    ],
    "name:nld_x_preferred":[
        "Bunar"
    ],
    "name:por_x_preferred":[
        "Bunar"
    ],
    "name:slv_x_preferred":[
        "Bunar"
    ],
    "name:srp_x_preferred":[
        "\u0411\u0443\u043d\u0430\u0440"
    ],
    "wof:lang_x_official":[
        "ind"
    ],
    "wof:lang_x_spoken":[
        "ind",
        "eng"
    ],
    "wof:name":"Bunar",
    "wof:placetype":"locality"
},
  "geometry": {"coordinates":[107.27556,-6.83583],"type":"Point"}
}