{
  "type": "Feature",
  "properties": {
    "gn:admin1_code":"1",
    "gn:asciiname":"Punti",
    "gn:country_code":"ID",
    "gn:dem":11,
    "gn:feature_class":"P",
    "gn:feature_code":"PPL",
    "gn:name":"Punti",
    "gn:population":0,
    "gn:timezone":"Asia/Jakarta",
    "iso:country":"ID",
    "name:ind_x_preferred":[
        "Punti"
    ],
    "name:nld_x_preferred":[
        "Wai t'auw"
    ],
    "name:zho_x_preferred":[
        "\u570d\u982d\u4eba"
    ],
    "wof:lang_x_official":[
        "ind"
    ],
    "wof:lang_x_spoken":[
        "ind",
        "eng"
    ],
    "wof:name":"Punti",
    "wof:placetype":"locality"
},
  "geometry": {"coordinates":[97.8728,4.8007],"type":"Point"}
}