{
  "type": "Feature",
  "properties": {
    "gn:admin1_code":"8.0",
    "gn:asciiname":"Calan",
    "gn:country_code":"ID",
    "gn:dem":5,
    "gn:feature_class":"P",
    "gn:feature_code":"PPLA4",
    "gn:name":"Calan",
    "gn:population":0,
    "gn:timezone":"Asia/Jakarta",
    "iso:country":"ID",
    "name:ceb_x_preferred":[
        "Calan"
    ],
    "name:cym_x_preferred":[
        "Calan"
    ],
    "name:epo_x_preferred":[
        "Calan"
    ],
    "name:fra_x_preferred":[
        "Calan"
    ],
    "name:ind_x_preferred":[
        "Calan"
    ],
    "name:nld_x_preferred":[
        "Calan"
    ],
    "name:por_x_preferred":[
        "Calan"
    ],
    "name:spa_x_preferred":[
        "Calan"
    ],
    "wof:name":"Calan",
    "wof:placetype":"locality"
},
  "geometry": {"coordinates":[112.4646,-7.0483],"type":"Point"}
}