{
  "type": "Feature",
  "properties": {
    "gn:admin1_code":"18.0",
    "gn:asciiname":"Kangalilombo",
    "gn:country_code":"ID",
    "gn:dem":447,
    "gn:feature_class":"P",
    "gn:feature_code":"PPL",
    "gn:name":"Kangalilombo",
    "gn:population":0,
    "gn:timezone":"Asia/Makassar",
    "iso:country":"ID",
    "name:ind_x_preferred":[
        "Kangalilombo"
    ],
    "wof:name":"Kangalilombo",
    "wof:placetype":"locality"
},
  "geometry": {"coordinates":[119.2774,-9.4826],"type":"Point"}
}