{
  "type": "Feature",
  "properties": {
    "gn:admin1_code":"26.0",
    "gn:asciiname":"Sosor Pasir",
    "gn:country_code":"ID",
    "gn:dem":920,
    "gn:feature_class":"P",
    "gn:feature_code":"PPL",
    "gn:name":"Sosor Pasir",
    "gn:population":0,
    "gn:timezone":"Asia/Jakarta",
    "iso:country":"ID",
    "name:ind_x_preferred":[
        "Sosor Pasir"
    ],
    "wof:name":"Sosor Pasir",
    "wof:placetype":"locality"
},
  "geometry": {"coordinates":[98.9913,2.5504],"type":"Point"}
}