{
  "type": "Feature",
  "properties": {
    "gn:admin1_code":"8",
    "gn:asciiname":"Karyabakti",
    "gn:country_code":"ID",
    "gn:dem":39,
    "gn:feature_class":"P",
    "gn:feature_code":"PPL",
    "gn:name":"Karyabakti",
    "gn:population":0,
    "gn:timezone":"Asia/Jakarta",
    "iso:country":"ID",
    "name:ind_x_preferred":[
        "Karyabakti"
    ],
    "wof:name":"Karyabakti",
    "wof:placetype":"locality"
},
  "geometry": {"coordinates":[112.84739999999999,-7.6932],"type":"Point"}
}