{
  "type": "Feature",
  "properties": {
    "gn:admin1_code":"18.0",
    "gn:asciiname":"Oekamusa",
    "gn:country_code":"ID",
    "gn:dem":789,
    "gn:feature_class":"P",
    "gn:feature_code":"PPLA3",
    "gn:name":"Oekamusa",
    "gn:population":0,
    "gn:timezone":"Asia/Makassar",
    "iso:country":"ID",
    "name:ind_x_preferred":[
        "Oekamusa"
    ],
    "wof:name":"Oekamusa",
    "wof:placetype":"locality"
},
  "geometry": {"coordinates":[124.3064,-9.8747],"type":"Point"}
}