{
  "type": "Feature",
  "properties": {
    "gn:admin1_code":"30",
    "gn:asciiname":"Serang",
    "gn:country_code":"ID",
    "gn:dem":43,
    "gn:feature_class":"P",
    "gn:feature_code":"PPL",
    "gn:name":"Serang",
    "gn:population":0,
    "gn:timezone":"Asia/Jakarta",
    "iso:country":"ID",
    "name:ind_x_preferred":[
        "Serang"
    ],
    "wof:name":"Serang",
    "wof:placetype":"locality"
},
  "geometry": {"coordinates":[107.39082999999999,-6.39222],"type":"Point"}
}