{
  "type": "Feature",
  "properties": {
    "gn:admin1_code":"1.0",
    "gn:asciiname":"Krueng Mane",
    "gn:country_code":"ID",
    "gn:dem":8,
    "gn:feature_class":"P",
    "gn:feature_code":"PPL",
    "gn:name":"Krueng Mane",
    "gn:population":0,
    "gn:timezone":"Asia/Jakarta",
    "iso:country":"ID",
    "name:ind_x_preferred":[
        "Krueng Mane"
    ],
    "name:und_x_variant":[
        "Keudemane",
        "Kroe\u00ebngmane"
    ],
    "wof:lang_x_official":[
        "ind"
    ],
    "wof:lang_x_spoken":[
        "ind",
        "eng"
    ],
    "wof:name":"Krueng Mane",
    "wof:placetype":"locality"
},
  "geometry": {"coordinates":[96.9178,5.2461],"type":"Point"}
}