{
  "type": "Feature",
  "properties": {
    "gn:admin1_code":"30.0",
    "gn:asciiname":"Nengtet",
    "gn:country_code":"ID",
    "gn:dem":261,
    "gn:feature_class":"P",
    "gn:feature_code":"PPL",
    "gn:name":"Nengtet",
    "gn:population":0,
    "gn:timezone":"Asia/Jakarta",
    "iso:country":"ID",
    "name:ind_x_preferred":[
        "Nengtet"
    ],
    "wof:name":"Nengtet",
    "wof:placetype":"locality"
},
  "geometry": {"coordinates":[108.0911,-7.4574],"type":"Point"}
}