{
  "type": "Feature",
  "properties": {
    "gn:admin1_code":"7",
    "gn:asciiname":"Sawanganronggo",
    "gn:country_code":"ID",
    "gn:dem":699,
    "gn:feature_class":"P",
    "gn:feature_code":"PPL",
    "gn:name":"Sawanganronggo",
    "gn:population":0,
    "gn:timezone":"Asia/Jakarta",
    "iso:country":"ID",
    "name:ind_x_preferred":[
        "Sawanganronggo"
    ],
    "wof:name":"Sawanganronggo",
    "wof:placetype":"locality"
},
  "geometry": {"coordinates":[109.69278,-7.13417],"type":"Point"}
}