{
  "type": "Feature",
  "properties": {
    "gn:admin1_code":"26",
    "gn:asciiname":"Kampung Jawa",
    "gn:country_code":"ID",
    "gn:dem":256,
    "gn:feature_class":"P",
    "gn:feature_code":"PPL",
    "gn:name":"Kampung Jawa",
    "gn:population":0,
    "gn:timezone":"Asia/Jakarta",
    "iso:country":"ID",
    "name:ind_x_preferred":[
        "Kampung Jawa"
    ],
    "wof:name":"Kampung Jawa",
    "wof:placetype":"locality"
},
  "geometry": {"coordinates":[99.1824,2.8768],"type":"Point"}
}