{
  "type": "Feature",
  "properties": {
    "gn:admin1_code":"30.0",
    "gn:asciiname":"Ciburial",
    "gn:country_code":"ID",
    "gn:dem":298,
    "gn:feature_class":"P",
    "gn:feature_code":"PPL",
    "gn:name":"Ciburial",
    "gn:population":0,
    "gn:timezone":"Asia/Jakarta",
    "iso:country":"ID",
    "name:ind_x_preferred":[
        "Ciburial"
    ],
    "name:und_x_variant":[
        "Tjiburia",
        "Ciburia"
    ],
    "wof:name":"Ciburial",
    "wof:placetype":"locality"
},
  "geometry": {"coordinates":[106.69722,-6.60472],"type":"Point"}
}