{
  "type": "Feature",
  "properties": {
    "gn:admin1_code":"30",
    "gn:asciiname":"Cukanggenteng Satu",
    "gn:cc2":"ID",
    "gn:country_code":"ID",
    "gn:dem":1000,
    "gn:feature_class":"P",
    "gn:feature_code":"PPL",
    "gn:name":"Cukanggenteng Satu",
    "gn:population":0,
    "gn:timezone":"Asia/Jakarta",
    "iso:country":"ID",
    "name:und_x_variant":[
        "Tjukanggenteng 1",
        "Cukanggenteng Satu"
    ],
    "wof:lang_x_official":[
        "ind"
    ],
    "wof:lang_x_spoken":[
        "ind",
        "eng"
    ],
    "wof:name":"Cukanggenteng Satu",
    "wof:placetype":"locality"
},
  "geometry": {"coordinates":[107.48417000000001,-7.08278],"type":"Point"}
}