{
  "type": "Feature",
  "properties": {
    "gn:admin1_code":"30",
    "gn:asciiname":"Kopo",
    "gn:country_code":"ID",
    "gn:dem":688,
    "gn:feature_class":"P",
    "gn:feature_code":"PPL",
    "gn:name":"Kopo",
    "gn:population":0,
    "gn:timezone":"Asia/Jakarta",
    "iso:country":"ID",
    "name:ind_x_preferred":[
        "Kopo"
    ],
    "wof:name":"Kopo",
    "wof:placetype":"locality"
},
  "geometry": {"coordinates":[106.91472,-6.65861],"type":"Point"}
}