{
  "type": "Feature",
  "properties": {
    "gn:admin1_code":"30.0",
    "gn:asciiname":"Sukamajuhilir",
    "gn:country_code":"ID",
    "gn:dem":517,
    "gn:feature_class":"P",
    "gn:feature_code":"PPL",
    "gn:name":"Sukamajuhilir",
    "gn:population":0,
    "gn:timezone":"Asia/Jakarta",
    "iso:country":"ID",
    "name:ind_x_preferred":[
        "Sukamajuhilir"
    ],
    "wof:name":"Sukamajuhilir",
    "wof:placetype":"locality"
},
  "geometry": {"coordinates":[108.21769999999999,-7.251],"type":"Point"}
}