{
  "type": "Feature",
  "properties": {
    "gn:admin1_code":"8.0",
    "gn:asciiname":"Kapasan",
    "gn:country_code":"ID",
    "gn:dem":18,
    "gn:feature_class":"P",
    "gn:feature_code":"PPLA4",
    "gn:name":"Kapasan",
    "gn:population":0,
    "gn:timezone":"Asia/Jakarta",
    "iso:country":"ID",
    "name:ind_x_preferred":[
        "Kapasan"
    ],
    "wof:name":"Kapasan",
    "wof:placetype":"locality"
},
  "geometry": {"coordinates":[113.18600000000001,-6.8996],"type":"Point"}
}