{
  "type": "Feature",
  "properties": {
    "gn:admin1_code":"8.0",
    "gn:asciiname":"Kapasan",
    "gn:country_code":"ID",
    "gn:dem":18,
    "gn:feature_class":"P",
    "gn:feature_code":"PPLA4",
    "gn:name":"Kapasan",
    "gn:population":0,
    "gn:timezone":"Asia/Jakarta",
    "iso:country":"ID",
    "name:ben_x_preferred":[
        "\u0995\u09be\u09aa\u09be\u09b8\u09be\u09a8"
    ],
    "name:bpy_x_preferred":[
        "\u0995\u09be\u09aa\u09be\u09b8\u09be\u09a8"
    ],
    "name:cat_x_preferred":[
        "Kapasan"
    ],
    "name:ceb_x_preferred":[
        "Kapasan"
    ],
    "name:hin_x_preferred":[
        "\u0915\u092a\u093e\u0938\u0928"
    ],
    "name:ind_x_preferred":[
        "Kapasan"
    ],
    "name:ita_x_preferred":[
        "Kapasan"
    ],
    "name:mlg_x_preferred":[
        "Kapasan"
    ],
    "name:msa_x_preferred":[
        "Kapasan"
    ],
    "name:new_x_preferred":[
        "\u0915\u092a\u093e\u0938\u0928"
    ],
    "name:por_x_preferred":[
        "Kapasan"
    ],
    "name:vie_x_preferred":[
        "Kapasan"
    ],
    "name:zho_x_preferred":[
        "\u5361\u5e15\u6851"
    ],
    "wof:lang_x_official":[
        "ind"
    ],
    "wof:lang_x_spoken":[
        "ind",
        "eng"
    ],
    "wof:name":"Kapasan",
    "wof:placetype":"locality"
},
  "geometry": {"coordinates":[113.18600000000001,-6.8996],"type":"Point"}
}