{
  "type": "Feature",
  "properties": {
    "gn:admin1_code":"7",
    "gn:asciiname":"Kranding Wetan",
    "gn:country_code":"ID",
    "gn:dem":272,
    "gn:feature_class":"P",
    "gn:feature_code":"PPL",
    "gn:name":"Kranding Wetan",
    "gn:population":0,
    "gn:timezone":"Asia/Jakarta",
    "iso:country":"ID",
    "name:ind_x_preferred":[
        "Kranding Wetan"
    ],
    "wof:name":"Kranding Wetan",
    "wof:placetype":"locality"
},
  "geometry": {"coordinates":[109.2897,-7.0778],"type":"Point"}
}