{
  "type": "Feature",
  "properties": {
    "gn:admin1_code":"21",
    "gn:asciiname":"Kali",
    "gn:country_code":"ID",
    "gn:dem":9,
    "gn:feature_class":"P",
    "gn:feature_code":"PPLA3",
    "gn:name":"Kali",
    "gn:population":0,
    "gn:timezone":"Asia/Makassar",
    "iso:country":"ID",
    "name:ind_x_preferred":[
        "Kali"
    ],
    "wof:name":"Kali",
    "wof:placetype":"locality"
},
  "geometry": {"coordinates":[121.4278,1.1627],"type":"Point"}
}