{
  "type": "Feature",
  "properties": {
    "gn:admin1_code":"2",
    "gn:asciiname":"Ketapang",
    "gn:country_code":"ID",
    "gn:dem":9,
    "gn:feature_class":"P",
    "gn:feature_code":"PPL",
    "gn:name":"Ketapang",
    "gn:population":0,
    "gn:timezone":"Asia/Makassar",
    "iso:country":"ID",
    "name:ind_x_preferred":[
        "Ketapang"
    ],
    "wof:name":"Ketapang",
    "wof:placetype":"locality"
},
  "geometry": {"coordinates":[114.6168,-8.3624],"type":"Point"}
}