{
  "type": "Feature",
  "properties": {
    "gn:admin1_code":"11.0",
    "gn:asciiname":"Serang",
    "gn:country_code":"ID",
    "gn:dem":330,
    "gn:feature_class":"P",
    "gn:feature_code":"PPL",
    "gn:name":"Serang",
    "gn:population":0,
    "gn:timezone":"Asia/Pontianak",
    "iso:country":"ID",
    "wof:name":"Serang",
    "wof:placetype":"locality"
},
  "geometry": {"coordinates":[112.28333000000001,0.01667],"type":"Point"}
}