{
  "type": "Feature",
  "properties": {
    "gn:admin1_code":"38",
    "gn:asciiname":"Karawang",
    "gn:country_code":"ID",
    "gn:dem":40,
    "gn:feature_class":"P",
    "gn:feature_code":"PPL",
    "gn:name":"Karawang",
    "gn:population":0,
    "gn:timezone":"Asia/Makassar",
    "iso:country":"ID",
    "name:ara_x_preferred":[
        "\u0643\u0631\u0627\u0648\u0627\u0646\u063a"
    ],
    "name:ceb_x_preferred":[
        "Kecamatan Karawang"
    ],
    "name:fra_x_preferred":[
        "Karawang"
    ],
    "name:ind_x_preferred":[
        "Karawang"
    ],
    "name:jpn_x_preferred":[
        "\u30ab\u30e9\u30ef\u30f3"
    ],
    "name:nld_x_preferred":[
        "Karawang"
    ],
    "name:nor_x_preferred":[
        "Karawang"
    ],
    "name:pol_x_preferred":[
        "Karawang"
    ],
    "name:sun_x_preferred":[
        "Karawang"
    ],
    "name:swe_x_preferred":[
        "Kecamatan Karawang"
    ],
    "wof:lang_x_official":[
        "ind"
    ],
    "wof:lang_x_spoken":[
        "ind",
        "eng"
    ],
    "wof:name":"Karawang",
    "wof:placetype":"locality"
},
  "geometry": {"coordinates":[120.2949,-4.6657],"type":"Point"}
}