{
  "type": "Feature",
  "properties": {
    "gn:admin1_code":"38.0",
    "gn:asciiname":"Senga",
    "gn:country_code":"ID",
    "gn:dem":19,
    "gn:feature_class":"P",
    "gn:feature_code":"PPL",
    "gn:name":"Senga",
    "gn:population":0,
    "gn:timezone":"Asia/Makassar",
    "iso:country":"ID",
    "name:ceb_x_preferred":[
        "Senga"
    ],
    "name:ind_x_preferred":[
        "Senga"
    ],
    "name:ita_x_preferred":[
        "Senga"
    ],
    "name:swa_x_preferred":[
        "Senga"
    ],
    "name:swe_x_preferred":[
        "Senga"
    ],
    "wof:lang_x_official":[
        "ind"
    ],
    "wof:lang_x_spoken":[
        "ind",
        "eng"
    ],
    "wof:name":"Senga",
    "wof:placetype":"locality"
},
  "geometry": {"coordinates":[120.3693,-3.3991],"type":"Point"}
}