{
  "type": "Feature",
  "properties": {
    "gn:admin1_code":"2",
    "gn:asciiname":"Banjar Pejengan",
    "gn:country_code":"ID",
    "gn:dem":406,
    "gn:feature_class":"P",
    "gn:feature_code":"PPL",
    "gn:name":"Banjar Pejengan",
    "gn:population":0,
    "gn:timezone":"Asia/Makassar",
    "iso:country":"ID",
    "name:ind_x_preferred":[
        "Banjar Pejengan"
    ],
    "wof:name":"Banjar Pejengan",
    "wof:placetype":"locality"
},
  "geometry": {"coordinates":[115.27760000000001,-8.4474],"type":"Point"}
}