{
  "type": "Feature",
  "properties": {
    "gn:admin1_code":"8",
    "gn:asciiname":"Anggrungan",
    "gn:country_code":"ID",
    "gn:dem":340,
    "gn:feature_class":"P",
    "gn:feature_code":"PPL",
    "gn:name":"Anggrungan",
    "gn:population":0,
    "gn:timezone":"Asia/Jakarta",
    "iso:country":"ID",
    "name:ind_x_preferred":[
        "Anggrungan"
    ],
    "wof:name":"Anggrungan",
    "wof:placetype":"locality"
},
  "geometry": {"coordinates":[112.5558,-8.12968],"type":"Point"}
}