{
  "type": "Feature",
  "properties": {
    "gn:admin1_code":"18.0",
    "gn:asciiname":"Kabondok",
    "gn:country_code":"ID",
    "gn:dem":445,
    "gn:feature_class":"P",
    "gn:feature_code":"PPLA4",
    "gn:name":"Kabondok",
    "gn:population":0,
    "gn:timezone":"Asia/Makassar",
    "iso:country":"ID",
    "name:ind_x_preferred":[
        "Kabondok"
    ],
    "name:und_x_variant":[
        "Kabunduk"
    ],
    "wof:name":"Kabondok",
    "wof:placetype":"locality"
},
  "geometry": {"coordinates":[119.572,-9.5994],"type":"Point"}
}