{
  "type": "Feature",
  "properties": {
    "gn:admin1_code":"1",
    "gn:asciiname":"Dasan",
    "gn:country_code":"ID",
    "gn:dem":104,
    "gn:feature_class":"P",
    "gn:feature_code":"PPL",
    "gn:name":"Dasan",
    "gn:population":0,
    "gn:timezone":"Asia/Jakarta",
    "iso:country":"ID",
    "name:ind_x_preferred":[
        "Dasan"
    ],
    "wof:name":"Dasan",
    "wof:placetype":"locality"
},
  "geometry": {"coordinates":[97.9464,2.9131],"type":"Point"}
}