{
  "type": "Feature",
  "properties": {
    "gn:admin1_code":"18.0",
    "gn:asciiname":"Koli",
    "gn:country_code":"ID",
    "gn:dem":145,
    "gn:feature_class":"P",
    "gn:feature_code":"PPL",
    "gn:name":"Koli",
    "gn:population":0,
    "gn:timezone":"Asia/Makassar",
    "iso:country":"ID",
    "name:ceb_x_preferred":[
        "Koli"
    ],
    "name:deu_x_preferred":[
        "Koli"
    ],
    "name:fin_x_preferred":[
        "Koli"
    ],
    "name:ind_x_preferred":[
        "Koli"
    ],
    "name:isl_x_preferred":[
        "Koli"
    ],
    "name:swe_x_preferred":[
        "Koli"
    ],
    "name:tgl_x_preferred":[
        "Koli"
    ],
    "wof:lang_x_official":[
        "ind"
    ],
    "wof:lang_x_spoken":[
        "ind",
        "eng"
    ],
    "wof:name":"Koli",
    "wof:placetype":"locality"
},
  "geometry": {"coordinates":[123.0196,-10.7953],"type":"Point"}
}