{
  "type": "Feature",
  "properties": {
    "gn:admin1_code":"30",
    "gn:asciiname":"Grahapuri",
    "gn:country_code":"ID",
    "gn:dem":19,
    "gn:feature_class":"P",
    "gn:feature_code":"PPL",
    "gn:name":"Grahapuri",
    "gn:population":0,
    "gn:timezone":"Asia/Jakarta",
    "iso:country":"ID",
    "name:ind_x_preferred":[
        "Grahapuri"
    ],
    "wof:name":"Grahapuri",
    "wof:placetype":"locality"
},
  "geometry": {"coordinates":[107.08444,-6.25417],"type":"Point"}
}