{
  "type": "Feature",
  "properties": {
    "gn:admin1_code":"38.0",
    "gn:asciiname":"Kamanre",
    "gn:country_code":"ID",
    "gn:dem":24,
    "gn:feature_class":"P",
    "gn:feature_code":"PPL",
    "gn:name":"Kamanre",
    "gn:population":0,
    "gn:timezone":"Asia/Makassar",
    "iso:country":"ID",
    "name:ind_x_preferred":[
        "Kamanre"
    ],
    "wof:name":"Kamanre",
    "wof:placetype":"locality"
},
  "geometry": {"coordinates":[120.3284,-3.3179],"type":"Point"}
}