{
  "type": "Feature",
  "properties": {
    "gn:admin1_code":"30",
    "gn:asciiname":"Lebakhuni",
    "gn:country_code":"ID",
    "gn:dem":935,
    "gn:feature_class":"P",
    "gn:feature_code":"PPL",
    "gn:name":"Lebakhuni",
    "gn:population":0,
    "gn:timezone":"Asia/Jakarta",
    "iso:country":"ID",
    "name:ind_x_preferred":[
        "Lebakhuni"
    ],
    "wof:name":"Lebakhuni",
    "wof:placetype":"locality"
},
  "geometry": {"coordinates":[107.81638999999998,-6.87472],"type":"Point"}
}