{
  "type": "Feature",
  "properties": {
    "gn:admin1_code":"38",
    "gn:asciiname":"Romantangnga",
    "gn:country_code":"ID",
    "gn:dem":599,
    "gn:feature_class":"P",
    "gn:feature_code":"PPL",
    "gn:name":"Romantangnga",
    "gn:population":0,
    "gn:timezone":"Asia/Makassar",
    "iso:country":"ID",
    "name:ind_x_preferred":[
        "Romantangnga"
    ],
    "wof:name":"Romantangnga",
    "wof:placetype":"locality"
},
  "geometry": {"coordinates":[119.714,-5.3137],"type":"Point"}
}