{
  "type": "Feature",
  "properties": {
    "gn:admin1_code":"17",
    "gn:asciiname":"Embungduduk",
    "gn:country_code":"ID",
    "gn:dem":66,
    "gn:feature_class":"P",
    "gn:feature_code":"PPL",
    "gn:name":"Embungduduk",
    "gn:population":0,
    "gn:timezone":"Asia/Makassar",
    "iso:country":"ID",
    "name:ind_x_preferred":[
        "Embungduduk"
    ],
    "wof:name":"Embungduduk",
    "wof:placetype":"locality"
},
  "geometry": {"coordinates":[116.18980000000001,-8.6477],"type":"Point"}
}