{
  "type": "Feature",
  "properties": {
    "gn:admin1_code":"12.0",
    "gn:asciiname":"Sungaipasir",
    "gn:country_code":"ID",
    "gn:dem":50,
    "gn:feature_class":"P",
    "gn:feature_code":"PPL",
    "gn:name":"Sungaipasir",
    "gn:population":0,
    "gn:timezone":"Asia/Makassar",
    "iso:country":"ID",
    "name:und_x_variant":[
        "Soengaipasir",
        "Sungaipasir"
    ],
    "wof:name":"Sungaipasir",
    "wof:placetype":"locality"
},
  "geometry": {"coordinates":[116.0521,-3.5889],"type":"Point"}
}