{
  "type": "Feature",
  "properties": {
    "gn:admin1_code":"5.0",
    "gn:asciiname":"Pulau",
    "gn:country_code":"ID",
    "gn:dem":56,
    "gn:feature_class":"P",
    "gn:feature_code":"PPL",
    "gn:name":"Pulau",
    "gn:population":0,
    "gn:timezone":"Asia/Jakarta",
    "iso:country":"ID",
    "name:deu_x_preferred":[
        "Pulau"
    ],
    "name:fra_x_preferred":[
        "Pulau"
    ],
    "name:ind_x_preferred":[
        "Pulau"
    ],
    "name:nld_x_preferred":[
        "Pulau"
    ],
    "wof:name":"Pulau",
    "wof:placetype":"locality"
},
  "geometry": {"coordinates":[102.4983,-2.2654],"type":"Point"}
}