{
  "type": "Feature",
  "properties": {
    "gn:admin1_code":"15.0",
    "gn:asciiname":"Saptorenggo",
    "gn:country_code":"ID",
    "gn:dem":69,
    "gn:feature_class":"P",
    "gn:feature_code":"PPL",
    "gn:name":"Saptorenggo",
    "gn:population":0,
    "gn:timezone":"Asia/Jakarta",
    "iso:country":"ID",
    "name:ind_x_preferred":[
        "Saptorenggo"
    ],
    "wof:name":"Saptorenggo",
    "wof:placetype":"locality"
},
  "geometry": {"coordinates":[104.64193,-4.24851],"type":"Point"}
}