{
  "type": "Feature",
  "properties": {
    "gn:admin1_code":"30.0",
    "gn:asciiname":"Cisempur",
    "gn:country_code":"ID",
    "gn:dem":827,
    "gn:feature_class":"P",
    "gn:feature_code":"PPL",
    "gn:name":"Cisempur",
    "gn:population":0,
    "gn:timezone":"Asia/Jakarta",
    "iso:country":"ID",
    "name:ind_x_preferred":[
        "Cisempur"
    ],
    "wof:name":"Cisempur",
    "wof:placetype":"locality"
},
  "geometry": {"coordinates":[108.0988,-7.019],"type":"Point"}
}