{
  "type": "Feature",
  "properties": {
    "gn:admin1_code":"37",
    "gn:asciiname":"Sungaiberbari",
    "gn:country_code":"ID",
    "gn:dem":8,
    "gn:feature_class":"P",
    "gn:feature_code":"PPL",
    "gn:name":"Sungaiberbari",
    "gn:population":0,
    "gn:timezone":"Asia/Jakarta",
    "iso:country":"ID",
    "name:ind_x_preferred":[
        "Sungaiberbari"
    ],
    "wof:name":"Sungaiberbari",
    "wof:placetype":"locality"
},
  "geometry": {"coordinates":[102.0543,0.91249],"type":"Point"}
}