{
  "type": "Feature",
  "properties": {
    "gn:admin1_code":"30",
    "gn:asciiname":"Ciawigede",
    "gn:country_code":"ID",
    "gn:dem":834,
    "gn:feature_class":"P",
    "gn:feature_code":"PPL",
    "gn:name":"Ciawigede",
    "gn:population":0,
    "gn:timezone":"Asia/Jakarta",
    "iso:country":"ID",
    "wof:name":"Ciawigede",
    "wof:placetype":"locality"
},
  "geometry": {"coordinates":[107.67194000000001,-7.06167],"type":"Point"}
}