{
  "type": "Feature",
  "properties": {
    "gn:admin1_code":"28.0",
    "gn:asciiname":"Atubul",
    "gn:country_code":"ID",
    "gn:dem":10,
    "gn:feature_class":"P",
    "gn:feature_code":"PPL",
    "gn:name":"Atubul",
    "gn:population":0,
    "gn:timezone":"Asia/Jayapura",
    "iso:country":"ID",
    "name:ind_x_preferred":[
        "Atubul"
    ],
    "name:und_x_variant":[
        "Atoeboel"
    ],
    "wof:name":"Atubul",
    "wof:placetype":"locality"
},
  "geometry": {"coordinates":[131.10844,-7.95623],"type":"Point"}
}