{
  "type": "Feature",
  "properties": {
    "gn:admin1_code":"26.0",
    "gn:asciiname":"Siparapat Dugul",
    "gn:country_code":"ID",
    "gn:dem":1027,
    "gn:feature_class":"P",
    "gn:feature_code":"PPL",
    "gn:name":"Siparapat Dugul",
    "gn:population":0,
    "gn:timezone":"Asia/Jakarta",
    "iso:country":"ID",
    "name:ind_x_preferred":[
        "Siparapat Dugul"
    ],
    "wof:name":"Siparapat Dugul",
    "wof:placetype":"locality"
},
  "geometry": {"coordinates":[98.7338,2.7392],"type":"Point"}
}