{
  "type": "Feature",
  "properties": {
    "gn:admin1_code":"1.0",
    "gn:asciiname":"Bukit Pulau",
    "gn:country_code":"ID",
    "gn:dem":16,
    "gn:feature_class":"P",
    "gn:feature_code":"PPL",
    "gn:name":"Bukit Pulau",
    "gn:population":0,
    "gn:timezone":"Asia/Jakarta",
    "iso:country":"ID",
    "name:ind_x_preferred":[
        "Bukit Pulau"
    ],
    "wof:name":"Bukit Pulau",
    "wof:placetype":"locality"
},
  "geometry": {"coordinates":[97.99679999999999,4.4354],"type":"Point"}
}