{
  "type": "Feature",
  "properties": {
    "gn:admin1_code":"7.0",
    "gn:asciiname":"Ciloning",
    "gn:country_code":"ID",
    "gn:dem":30,
    "gn:feature_class":"P",
    "gn:feature_code":"PPLA4",
    "gn:name":"Ciloning",
    "gn:population":0,
    "gn:timezone":"Asia/Jakarta",
    "iso:country":"ID",
    "name:ind_x_preferred":[
        "Ciloning"
    ],
    "wof:name":"Ciloning",
    "wof:placetype":"locality"
},
  "geometry": {"coordinates":[108.85169999999999,-7.4746],"type":"Point"}
}