{
  "type": "Feature",
  "properties": {
    "gn:admin1_code":"38.0",
    "gn:asciiname":"Tondokbakaru",
    "gn:country_code":"ID",
    "gn:dem":1036,
    "gn:feature_class":"P",
    "gn:feature_code":"PPL",
    "gn:name":"Tondokbakaru",
    "gn:population":0,
    "gn:timezone":"Asia/Makassar",
    "iso:country":"ID",
    "name:ind_x_preferred":[
        "Tondokbakaru"
    ],
    "wof:name":"Tondokbakaru",
    "wof:placetype":"locality"
},
  "geometry": {"coordinates":[119.5706,-3.0758],"type":"Point"}
}