{
  "type": "Feature",
  "properties": {
    "gn:admin1_code":"18.0",
    "gn:asciiname":"Bondowero Dua",
    "gn:country_code":"ID",
    "gn:dem":572,
    "gn:feature_class":"P",
    "gn:feature_code":"PPL",
    "gn:name":"Bondowero Dua",
    "gn:population":0,
    "gn:timezone":"Asia/Makassar",
    "iso:country":"ID",
    "name:ind_x_preferred":[
        "Bondowero Dua"
    ],
    "name:und_x_variant":[
        "Bondowero 2"
    ],
    "wof:lang_x_official":[
        "ind"
    ],
    "wof:lang_x_spoken":[
        "ind",
        "eng"
    ],
    "wof:name":"Bondowero Dua",
    "wof:placetype":"locality"
},
  "geometry": {"coordinates":[119.4289,-9.5333],"type":"Point"}
}