{
  "type": "Feature",
  "properties": {
    "gn:admin1_code":"8",
    "gn:asciiname":"Bangeran",
    "gn:country_code":"ID",
    "gn:dem":58,
    "gn:feature_class":"P",
    "gn:feature_code":"PPL",
    "gn:name":"Bangeran",
    "gn:population":0,
    "gn:timezone":"Asia/Jakarta",
    "iso:country":"ID",
    "name:ind_x_preferred":[
        "Bangeran"
    ],
    "wof:name":"Bangeran",
    "wof:placetype":"locality"
},
  "geometry": {"coordinates":[112.4387,-7.3681],"type":"Point"}
}