{
  "type": "Feature",
  "properties": {
    "gn:admin1_code":"26",
    "gn:asciiname":"Tanjung Kuala",
    "gn:country_code":"ID",
    "gn:dem":213,
    "gn:feature_class":"P",
    "gn:feature_code":"PPL",
    "gn:name":"Tanjung Kuala",
    "gn:population":0,
    "gn:timezone":"Asia/Jakarta",
    "iso:country":"ID",
    "name:ind_x_preferred":[
        "Tanjung Kuala"
    ],
    "name:und_x_variant":[
        "Tandjungkuala"
    ],
    "wof:name":"Tanjung Kuala",
    "wof:placetype":"locality"
},
  "geometry": {"coordinates":[98.4669,3.4123],"type":"Point"}
}