{
  "type": "Feature",
  "properties": {
    "gn:admin1_code":"18.0",
    "gn:asciiname":"Tulun Satu",
    "gn:country_code":"ID",
    "gn:dem":571,
    "gn:feature_class":"P",
    "gn:feature_code":"PPL",
    "gn:name":"Tulun Satu",
    "gn:population":0,
    "gn:timezone":"Asia/Makassar",
    "iso:country":"ID",
    "name:ind_x_preferred":[
        "Tulun Satu"
    ],
    "wof:name":"Tulun Satu",
    "wof:placetype":"locality"
},
  "geometry": {"coordinates":[124.52030000000001,-9.7728],"type":"Point"}
}