{
  "type": "Feature",
  "properties": {
    "gn:admin1_code":"0.0",
    "gn:asciiname":"Jemuat",
    "gn:cc2":"ID",
    "gn:country_code":"ID",
    "gn:dem":213,
    "gn:feature_class":"P",
    "gn:feature_code":"PPL",
    "gn:name":"Jemuat",
    "gn:population":0,
    "gn:timezone":"Asia/Pontianak",
    "iso:country":"ID",
    "name:ind_x_preferred":[
        "Djemuwat"
    ],
    "name:und_x_variant":[
        "Djemuat",
        "Djemoewat",
        "Dj\u0115moeat",
        "Jemuat"
    ],
    "wof:lang_x_official":[
        "ind"
    ],
    "wof:lang_x_spoken":[
        "ind",
        "eng"
    ],
    "wof:name":"Jemuat",
    "wof:placetype":"locality"
},
  "geometry": {"coordinates":[111.13333,-1.48333],"type":"Point"}
}