{
  "type": "Feature",
  "properties": {
    "gn:admin1_code":"7.0",
    "gn:asciiname":"Slirap",
    "gn:country_code":"ID",
    "gn:dem":143,
    "gn:feature_class":"P",
    "gn:feature_code":"PPL",
    "gn:name":"Slirap",
    "gn:population":0,
    "gn:timezone":"Asia/Jakarta",
    "iso:country":"ID",
    "name:ind_x_preferred":[
        "Slirap"
    ],
    "wof:name":"Slirap",
    "wof:placetype":"locality"
},
  "geometry": {"coordinates":[109.43832999999999,-7.58583],"type":"Point"}
}