{
  "type": "Feature",
  "properties": {
    "gn:admin1_code":"8",
    "gn:asciiname":"Curahpalung",
    "gn:country_code":"ID",
    "gn:dem":64,
    "gn:feature_class":"P",
    "gn:feature_code":"PPL",
    "gn:name":"Curahpalung",
    "gn:population":0,
    "gn:timezone":"Asia/Jakarta",
    "iso:country":"ID",
    "name:ind_x_preferred":[
        "Curahpalung"
    ],
    "wof:name":"Curahpalung",
    "wof:placetype":"locality"
},
  "geometry": {"coordinates":[114.2209,-8.4687],"type":"Point"}
}