{
  "type": "Feature",
  "properties": {
    "gn:admin1_code":"30",
    "gn:asciiname":"Lapang",
    "gn:country_code":"ID",
    "gn:dem":840,
    "gn:feature_class":"P",
    "gn:feature_code":"PPL",
    "gn:name":"Lapang",
    "gn:population":0,
    "gn:timezone":"Asia/Jakarta",
    "iso:country":"ID",
    "name:ind_x_preferred":[
        "Lapang"
    ],
    "wof:name":"Lapang",
    "wof:placetype":"locality"
},
  "geometry": {"coordinates":[107.04000000000001,-6.86333],"type":"Point"}
}