{
  "type": "Feature",
  "properties": {
    "gn:admin1_code":"8.0",
    "gn:asciiname":"Gempolan",
    "gn:country_code":"ID",
    "gn:dem":78,
    "gn:feature_class":"P",
    "gn:feature_code":"PPL",
    "gn:name":"Gempolan",
    "gn:population":0,
    "gn:timezone":"Asia/Jakarta",
    "iso:country":"ID",
    "name:ind_x_preferred":[
        "Gempolan"
    ],
    "wof:name":"Gempolan",
    "wof:placetype":"locality"
},
  "geometry": {"coordinates":[112.9212,-8.3042],"type":"Point"}
}