{
  "type": "Feature",
  "properties": {
    "gn:admin1_code":"30.0",
    "gn:asciiname":"Cikiwul Dua",
    "gn:country_code":"ID",
    "gn:dem":566,
    "gn:feature_class":"P",
    "gn:feature_code":"PPL",
    "gn:name":"Cikiwul Dua",
    "gn:population":0,
    "gn:timezone":"Asia/Jakarta",
    "iso:country":"ID",
    "name:ind_x_preferred":[
        "Cikiwul Dua"
    ],
    "wof:name":"Cikiwul Dua",
    "wof:placetype":"locality"
},
  "geometry": {"coordinates":[106.80880000000001,-7.0723],"type":"Point"}
}