{
  "type": "Feature",
  "properties": {
    "gn:admin1_code":"28.0",
    "gn:asciiname":"Kabutteah",
    "gn:country_code":"ID",
    "gn:dem":791,
    "gn:feature_class":"P",
    "gn:feature_code":"PPL",
    "gn:name":"Kabutteah",
    "gn:population":0,
    "gn:timezone":"Asia/Jayapura",
    "iso:country":"ID",
    "name:ind_x_preferred":[
        "Kabutteah"
    ],
    "name:und_x_variant":[
        "Kaboett\u00e9ah"
    ],
    "wof:lang_x_official":[
        "ind"
    ],
    "wof:lang_x_spoken":[
        "ind",
        "eng"
    ],
    "wof:name":"Kabutteah",
    "wof:placetype":"locality"
},
  "geometry": {"coordinates":[126.4923,-3.4293],"type":"Point"}
}