{
  "type": "Feature",
  "properties": {
    "gn:admin1_code":"26",
    "gn:asciiname":"Lhokreudeueb",
    "gn:country_code":"ID",
    "gn:dem":12,
    "gn:feature_class":"P",
    "gn:feature_code":"PPL",
    "gn:name":"Lhokreudeueb",
    "gn:population":0,
    "gn:timezone":"Asia/Jakarta",
    "iso:country":"ID",
    "name:ind_x_preferred":[
        "Lhokreudeueb"
    ],
    "wof:name":"Lhokreudeueb",
    "wof:placetype":"locality"
},
  "geometry": {"coordinates":[97.67440000000001,2.7379],"type":"Point"}
}