{
  "type": "Feature",
  "properties": {
    "gn:admin1_code":"30",
    "gn:asciiname":"Babakantegal",
    "gn:country_code":"ID",
    "gn:dem":34,
    "gn:feature_class":"P",
    "gn:feature_code":"PPL",
    "gn:name":"Babakantegal",
    "gn:population":0,
    "gn:timezone":"Asia/Jakarta",
    "iso:country":"ID",
    "name:ind_x_preferred":[
        "Babakantegal"
    ],
    "wof:name":"Babakantegal",
    "wof:placetype":"locality"
},
  "geometry": {"coordinates":[108.06222,-6.55111],"type":"Point"}
}