{
  "type": "Feature",
  "properties": {
    "gn:country":"ID",
    "gn:fcode":"PPL",
    "gn:pop":0,
    "iso:country":"ID",
    "name:ind_x_preferred":[
        "Ketapang"
    ],
    "qs:name":"Ketapang",
    "qs:name_adm0":"Indonesia",
    "qs:name_adm1":"Jawa Timur",
    "qs:photos_9k":1,
    "qs:photos_9r":1,
    "qs:photos_all":1,
    "qs:photos_sr":0,
    "qs:placetype":"Town",
    "qs:pop_sr":"4",
    "wof:name":"Ketapang",
    "wof:placetype":"locality",
    "wof:population":0
},
  "geometry": {"coordinates":[112.70229999999999,-7.3742],"type":"Point"}
}