{
  "type": "Feature",
  "properties": {
    "gn:country":"ID",
    "gn:fcode":"PPL",
    "gn:pop":0,
    "iso:country":"ID",
    "name:ara_x_preferred":[
        "\u0643\u064a\u062a\u0627\u0628\u0627\u0646\u063a"
    ],
    "name:fas_x_preferred":[
        "\u06a9\u062a\u0627\u067e\u0646\u06af"
    ],
    "name:fra_x_preferred":[
        "Ketapang"
    ],
    "name:ind_x_preferred":[
        "Ketapang"
    ],
    "name:lit_x_preferred":[
        "Ketapangas"
    ],
    "name:nor_x_preferred":[
        "Ketapang"
    ],
    "name:rus_x_preferred":[
        "\u041a\u0435\u0442\u0430\u043f\u0430\u043d\u0433"
    ],
    "name:vie_x_preferred":[
        "Ketapang"
    ],
    "qs:name":"Ketapang",
    "qs:name_adm0":"Indonesia",
    "qs:name_adm1":"Jawa Timur",
    "qs:photos_9k":1,
    "qs:photos_9r":1,
    "qs:photos_all":1,
    "qs:photos_sr":0,
    "qs:placetype":"Town",
    "qs:pop_sr":"4",
    "wof:lang_x_official":[
        "ind"
    ],
    "wof:lang_x_spoken":[
        "ind",
        "eng"
    ],
    "wof:name":"Ketapang",
    "wof:placetype":"locality",
    "wof:population":0
},
  "geometry": {"coordinates":[112.70229999999999,-7.3742],"type":"Point"}
}