{
  "type": "Feature",
  "properties": {
    "gn:admin1_code":"26",
    "gn:asciiname":"Tanjung Merahe",
    "gn:country_code":"ID",
    "gn:dem":809,
    "gn:feature_class":"P",
    "gn:feature_code":"PPL",
    "gn:name":"Tanjung Merahe",
    "gn:population":0,
    "gn:timezone":"Asia/Jakarta",
    "iso:country":"ID",
    "name:ind_x_preferred":[
        "Tanjung Merahe"
    ],
    "name:und_x_variant":[
        "Tandjungmerahe"
    ],
    "wof:lang_x_official":[
        "ind"
    ],
    "wof:lang_x_spoken":[
        "ind",
        "eng"
    ],
    "wof:name":"Tanjung Merahe",
    "wof:placetype":"locality"
},
  "geometry": {"coordinates":[98.179,3.2067],"type":"Point"}
}