{
  "type": "Feature",
  "properties": {
    "gn:admin1_code":"8.0",
    "gn:asciiname":"Sumbergayam",
    "gn:country_code":"ID",
    "gn:dem":51,
    "gn:feature_class":"P",
    "gn:feature_code":"PPL",
    "gn:name":"Sumbergayam",
    "gn:population":0,
    "gn:timezone":"Asia/Jakarta",
    "iso:country":"ID",
    "name:ind_x_preferred":[
        "Sumbergayam"
    ],
    "wof:name":"Sumbergayam",
    "wof:placetype":"locality"
},
  "geometry": {"coordinates":[112.3561,-7.3826],"type":"Point"}
}