{
  "type": "Feature",
  "properties": {
    "gn:admin1_code":"8.0",
    "gn:asciiname":"Latsari",
    "gn:country_code":"ID",
    "gn:dem":19,
    "gn:feature_class":"P",
    "gn:feature_code":"PPLA4",
    "gn:name":"Latsari",
    "gn:population":0,
    "gn:timezone":"Asia/Jakarta",
    "iso:country":"ID",
    "name:ind_x_preferred":[
        "Latsari"
    ],
    "wof:name":"Latsari",
    "wof:placetype":"locality"
},
  "geometry": {"coordinates":[111.6918,-6.7785],"type":"Point"}
}