{
  "type": "Feature",
  "properties": {
    "gn:admin1_code":"30.0",
    "gn:asciiname":"Cigarungsang",
    "gn:country_code":"ID",
    "gn:dem":969,
    "gn:feature_class":"P",
    "gn:feature_code":"PPLA4",
    "gn:name":"Cigarungsang",
    "gn:population":0,
    "gn:timezone":"Asia/Jakarta",
    "iso:country":"ID",
    "name:ind_x_preferred":[
        "Cigarungsang"
    ],
    "wof:lang_x_official":[
        "ind"
    ],
    "wof:lang_x_spoken":[
        "ind",
        "eng"
    ],
    "wof:name":"Cigarungsang",
    "wof:placetype":"locality"
},
  "geometry": {"coordinates":[107.92359999999999,-7.2973],"type":"Point"}
}