{
  "type": "Feature",
  "properties": {
    "gn:admin1_code":"26.0",
    "gn:asciiname":"Sitio-tio",
    "gn:country_code":"ID",
    "gn:dem":1411,
    "gn:feature_class":"P",
    "gn:feature_code":"PPL",
    "gn:name":"Sitio-tio",
    "gn:population":0,
    "gn:timezone":"Asia/Jakarta",
    "iso:country":"ID",
    "name:ind_x_preferred":[
        "Sitio-tio"
    ],
    "wof:name":"Sitio-tio",
    "wof:placetype":"locality"
},
  "geometry": {"coordinates":[98.89830000000001,2.522],"type":"Point"}
}