{
  "type": "Feature",
  "properties": {
    "gn:admin1_code":"34.0",
    "gn:asciiname":"Iloheluma",
    "gn:country_code":"ID",
    "gn:dem":23,
    "gn:feature_class":"P",
    "gn:feature_code":"PPL",
    "gn:name":"Iloheluma",
    "gn:population":0,
    "gn:timezone":"Asia/Makassar",
    "iso:country":"ID",
    "name:ind_x_preferred":[
        "Iloheluma"
    ],
    "name:und_x_variant":[
        "Modelomo"
    ],
    "wof:name":"Iloheluma",
    "wof:placetype":"locality"
},
  "geometry": {"coordinates":[122.33280000000001,0.5407],"type":"Point"}
}