{
  "type": "Feature",
  "properties": {
    "gn:admin1_code":"30.0",
    "gn:asciiname":"Cibeureum",
    "gn:country_code":"ID",
    "gn:dem":486,
    "gn:feature_class":"P",
    "gn:feature_code":"PPL",
    "gn:name":"Cibeureum",
    "gn:population":0,
    "gn:timezone":"Asia/Jakarta",
    "iso:country":"ID",
    "name:ind_x_preferred":[
        "Cibeureum"
    ],
    "name:und_x_variant":[
        "Tjibeureum"
    ],
    "wof:lang_x_official":[
        "ind"
    ],
    "wof:lang_x_spoken":[
        "ind",
        "eng"
    ],
    "wof:name":"Cibeureum",
    "wof:placetype":"locality"
},
  "geometry": {"coordinates":[107.19833,-6.60722],"type":"Point"}
}