{
  "type": "Feature",
  "properties": {
    "gn:admin1_code":"18.0",
    "gn:asciiname":"Wanopoi",
    "gn:country_code":"ID",
    "gn:dem":433,
    "gn:feature_class":"P",
    "gn:feature_code":"PPL",
    "gn:name":"Wanopoi",
    "gn:population":0,
    "gn:timezone":"Asia/Makassar",
    "iso:country":"ID",
    "name:ind_x_preferred":[
        "Wanopoi"
    ],
    "wof:name":"Wanopoi",
    "wof:placetype":"locality"
},
  "geometry": {"coordinates":[119.1835,-9.5166],"type":"Point"}
}