{
  "type": "Feature",
  "properties": {
    "gn:admin1_code":"18",
    "gn:asciiname":"Kolanoan",
    "gn:country_code":"ID",
    "gn:dem":355,
    "gn:feature_class":"P",
    "gn:feature_code":"PPL",
    "gn:name":"Kolanoan",
    "gn:population":0,
    "gn:timezone":"Asia/Makassar",
    "iso:country":"ID",
    "wof:name":"Kolanoan",
    "wof:placetype":"locality"
},
  "geometry": {"coordinates":[124.845,-9.29417],"type":"Point"}
}