{
  "type": "Feature",
  "properties": {
    "gn:admin1_code":"8.0",
    "gn:asciiname":"Kedekan",
    "gn:country_code":"ID",
    "gn:dem":113,
    "gn:feature_class":"P",
    "gn:feature_code":"PPL",
    "gn:name":"Kedekan",
    "gn:population":0,
    "gn:timezone":"Asia/Jakarta",
    "iso:country":"ID",
    "name:ind_x_preferred":[
        "Kedekan"
    ],
    "wof:name":"Kedekan",
    "wof:placetype":"locality"
},
  "geometry": {"coordinates":[111.69370000000001,-8.1141],"type":"Point"}
}