{
  "type": "Feature",
  "properties": {
    "gn:admin1_code":"17.0",
    "gn:asciiname":"Samangawah",
    "gn:country_code":"ID",
    "gn:dem":123,
    "gn:feature_class":"P",
    "gn:feature_code":"PPLA4",
    "gn:name":"Samangawah",
    "gn:population":0,
    "gn:timezone":"Asia/Makassar",
    "iso:country":"ID",
    "name:ind_x_preferred":[
        "Samangawah"
    ],
    "wof:lang_x_official":[
        "ind"
    ],
    "wof:lang_x_spoken":[
        "ind",
        "eng"
    ],
    "wof:name":"Samangawah",
    "wof:placetype":"locality"
},
  "geometry": {"coordinates":[118.2991,-8.4955],"type":"Point"}
}