{
  "type": "Feature",
  "properties": {
    "gn:country":"ID",
    "gn:fcode":"ADM3",
    "gn:pop":0,
    "iso:country":"ID",
    "name:eng_x_preferred":[
        "Districts of North Sulawesi"
    ],
    "name:ind_x_preferred":[
        "Kecamatan Mapanget"
    ],
    "name:unk_x_variant":[
        "Mapanget"
    ],
    "qs:name":"Kecamatan Mapanget",
    "qs:photos_9r":0,
    "qs:photos_sr":0,
    "qs:pop_sr":"0",
    "wd:wordcount":423,
    "wof:lang_x_official":[
        "ind"
    ],
    "wof:lang_x_spoken":[
        "ind",
        "eng"
    ],
    "wof:name":"Kecamatan Mapanget",
    "wof:placetype":"localadmin",
    "wof:population":0
},
  "geometry": {"coordinates":[124.8909,1.493],"type":"Point"}
}