{
  "type": "Feature",
  "properties": {
    "gn:admin1_code":"0.0",
    "gn:asciiname":"Kalau",
    "gn:cc2":"ID",
    "gn:country_code":"ID",
    "gn:dem":37,
    "gn:feature_class":"P",
    "gn:feature_code":"PPL",
    "gn:name":"Kalau",
    "gn:population":0,
    "gn:timezone":"Asia/Pontianak",
    "iso:country":"ID",
    "name:und_x_variant":[
        "Keloi",
        "Kalau"
    ],
    "wof:lang_x_official":[
        "ind"
    ],
    "wof:lang_x_spoken":[
        "ind",
        "eng"
    ],
    "wof:name":"Kalau",
    "wof:placetype":"locality"
},
  "geometry": {"coordinates":[111.91667,-0.03333],"type":"Point"}
}