{
  "type": "Feature",
  "properties": {
    "gn:admin1_code":"30",
    "gn:asciiname":"Bojong Tengah",
    "gn:country_code":"ID",
    "gn:dem":325,
    "gn:feature_class":"P",
    "gn:feature_code":"PPL",
    "gn:name":"Bojong Tengah",
    "gn:population":0,
    "gn:timezone":"Asia/Jakarta",
    "iso:country":"ID",
    "name:ind_x_preferred":[
        "Bojong Tengah"
    ],
    "wof:lang_x_official":[
        "ind"
    ],
    "wof:lang_x_spoken":[
        "ind",
        "eng"
    ],
    "wof:name":"Bojong Tengah",
    "wof:placetype":"locality"
},
  "geometry": {"coordinates":[107.36333,-6.75139],"type":"Point"}
}