{
  "type": "Feature",
  "properties": {
    "gn:admin1_code":"18.0",
    "gn:asciiname":"Puuredapa",
    "gn:country_code":"ID",
    "gn:dem":519,
    "gn:feature_class":"P",
    "gn:feature_code":"PPL",
    "gn:name":"Puuredapa",
    "gn:population":0,
    "gn:timezone":"Asia/Makassar",
    "iso:country":"ID",
    "name:ind_x_preferred":[
        "Puuredapa"
    ],
    "wof:name":"Puuredapa",
    "wof:placetype":"locality"
},
  "geometry": {"coordinates":[119.292,-9.5406],"type":"Point"}
}