{
  "type": "Feature",
  "properties": {
    "gn:admin1_code":"8.0",
    "gn:asciiname":"Kulon",
    "gn:country_code":"ID",
    "gn:dem":324,
    "gn:feature_class":"P",
    "gn:feature_code":"PPL",
    "gn:name":"Kulon",
    "gn:population":0,
    "gn:timezone":"Asia/Jakarta",
    "iso:country":"ID",
    "name:ind_x_preferred":[
        "Kulon"
    ],
    "wof:name":"Kulon",
    "wof:placetype":"locality"
},
  "geometry": {"coordinates":[113.836,-8.1198],"type":"Point"}
}