{
  "type": "Feature",
  "properties": {
    "gn:admin1_code":"30",
    "gn:asciiname":"Babakancikole",
    "gn:country_code":"ID",
    "gn:dem":1035,
    "gn:feature_class":"P",
    "gn:feature_code":"PPL",
    "gn:name":"Babakancikole",
    "gn:population":0,
    "gn:timezone":"Asia/Jakarta",
    "iso:country":"ID",
    "name:ind_x_preferred":[
        "Babakancikole"
    ],
    "wof:name":"Babakancikole",
    "wof:placetype":"locality"
},
  "geometry": {"coordinates":[107.03028,-6.70111],"type":"Point"}
}