{
  "type": "Feature",
  "properties": {
    "gn:admin1_code":"18",
    "gn:asciiname":"Tibakisa",
    "gn:country_code":"ID",
    "gn:dem":593,
    "gn:feature_class":"P",
    "gn:feature_code":"PPLA4",
    "gn:name":"Tibakisa",
    "gn:population":0,
    "gn:timezone":"Asia/Makassar",
    "iso:country":"ID",
    "name:ind_x_preferred":[
        "Tibakisa"
    ],
    "wof:lang_x_official":[
        "ind"
    ],
    "wof:lang_x_spoken":[
        "ind",
        "eng"
    ],
    "wof:name":"Tibakisa",
    "wof:placetype":"locality"
},
  "geometry": {"coordinates":[121.30540000000001,-8.7393],"type":"Point"}
}