{
  "type": "Feature",
  "properties": {
    "gn:admin1_code":"15.0",
    "gn:asciiname":"Majapahit",
    "gn:country_code":"ID",
    "gn:dem":149,
    "gn:feature_class":"P",
    "gn:feature_code":"PPL",
    "gn:name":"Majapahit",
    "gn:population":0,
    "gn:timezone":"Asia/Jakarta",
    "iso:country":"ID",
    "name:ind_x_preferred":[
        "Majapahit"
    ],
    "wof:name":"Majapahit",
    "wof:placetype":"locality"
},
  "geometry": {"coordinates":[105.66305,-5.35973],"type":"Point"}
}