{
  "type": "Feature",
  "properties": {
    "gn:admin1_code":"42",
    "gn:asciiname":"Pa Mering",
    "gn:country_code":"ID",
    "gn:dem":946,
    "gn:feature_class":"P",
    "gn:feature_code":"PPL",
    "gn:name":"Pa Mering",
    "gn:population":0,
    "gn:timezone":"Asia/Makassar",
    "iso:country":"ID",
    "name:msa_x_preferred":[
        "Pa Mering"
    ],
    "wof:lang_x_official":[
        "ind"
    ],
    "wof:lang_x_spoken":[
        "ind",
        "eng"
    ],
    "wof:name":"Pa Mering",
    "wof:placetype":"locality"
},
  "geometry": {"coordinates":[115.66486999999999,3.88686],"type":"Point"}
}