{
  "type": "Feature",
  "properties": {
    "gn:admin1_code":"1",
    "gn:asciiname":"Lae Tonong",
    "gn:country_code":"ID",
    "gn:dem":21,
    "gn:feature_class":"P",
    "gn:feature_code":"PPL",
    "gn:name":"Lae Tonong",
    "gn:population":0,
    "gn:timezone":"Asia/Jakarta",
    "iso:country":"ID",
    "name:ind_x_preferred":[
        "Lae Tonong"
    ],
    "wof:name":"Lae Tonong",
    "wof:placetype":"locality"
},
  "geometry": {"coordinates":[97.82259999999999,2.7572],"type":"Point"}
}