{
  "type": "Feature",
  "properties": {
    "gn:admin1_code":"18.0",
    "gn:asciiname":"Muni",
    "gn:country_code":"ID",
    "gn:dem":492,
    "gn:feature_class":"P",
    "gn:feature_code":"PPL",
    "gn:name":"Muni",
    "gn:population":0,
    "gn:timezone":"Asia/Makassar",
    "iso:country":"ID",
    "name:ind_x_preferred":[
        "Muni"
    ],
    "wof:name":"Muni",
    "wof:placetype":"locality"
},
  "geometry": {"coordinates":[124.5896,-9.9668],"type":"Point"}
}