{
  "type": "Feature",
  "properties": {
    "gn:admin1_code":"18.0",
    "gn:asciiname":"Muni",
    "gn:country_code":"ID",
    "gn:dem":492,
    "gn:feature_class":"P",
    "gn:feature_code":"PPL",
    "gn:name":"Muni",
    "gn:population":0,
    "gn:timezone":"Asia/Makassar",
    "iso:country":"ID",
    "name:ceb_x_preferred":[
        "Muni"
    ],
    "name:ces_x_preferred":[
        "Muni"
    ],
    "name:deu_x_preferred":[
        "Muni"
    ],
    "name:fra_x_preferred":[
        "Muni"
    ],
    "name:ind_x_preferred":[
        "Muni"
    ],
    "name:nld_x_preferred":[
        "Muni"
    ],
    "name:por_x_preferred":[
        "Muni"
    ],
    "name:spa_x_preferred":[
        "Muni"
    ],
    "name:swe_x_preferred":[
        "Muni"
    ],
    "name:tam_x_preferred":[
        "\u0bae\u0bc1\u0ba9\u0bbf"
    ],
    "wof:name":"Muni",
    "wof:placetype":"locality"
},
  "geometry": {"coordinates":[124.5896,-9.9668],"type":"Point"}
}