{
  "type": "Feature",
  "properties": {
    "gn:admin1_code":"8",
    "gn:asciiname":"Gunungmalang Dua",
    "gn:country_code":"ID",
    "gn:dem":558,
    "gn:feature_class":"P",
    "gn:feature_code":"PPL",
    "gn:name":"Gunungmalang Dua",
    "gn:population":0,
    "gn:timezone":"Asia/Jakarta",
    "iso:country":"ID",
    "name:ind_x_preferred":[
        "Gunungmalang Dua"
    ],
    "wof:name":"Gunungmalang Dua",
    "wof:placetype":"locality"
},
  "geometry": {"coordinates":[113.91079999999999,-8.0843],"type":"Point"}
}