{
  "type": "Feature",
  "properties": {
    "gn:admin1_code":"7.0",
    "gn:asciiname":"Jebrug",
    "gn:country_code":"ID",
    "gn:dem":205,
    "gn:feature_class":"P",
    "gn:feature_code":"PPL",
    "gn:name":"Jebrug",
    "gn:population":0,
    "gn:timezone":"Asia/Jakarta",
    "iso:country":"ID",
    "name:ind_x_preferred":[
        "Jebrug"
    ],
    "wof:name":"Jebrug",
    "wof:placetype":"locality"
},
  "geometry": {"coordinates":[109.345,-7.31389],"type":"Point"}
}