{
  "type": "Feature",
  "properties": {
    "gn:admin1_code":"36.0",
    "gn:asciiname":"Otsjonep",
    "gn:country_code":"ID",
    "gn:dem":16,
    "gn:feature_class":"P",
    "gn:feature_code":"PPL",
    "gn:name":"Otsjonep",
    "gn:population":0,
    "gn:timezone":"Asia/Jayapura",
    "iso:country":"ID",
    "name:ind_x_preferred":[
        "Otsjonep"
    ],
    "name:und_x_variant":[
        "Otsjanep"
    ],
    "wof:name":"Otsjonep",
    "wof:placetype":"locality"
},
  "geometry": {"coordinates":[138.35979,-5.97261],"type":"Point"}
}