{
  "type": "Feature",
  "properties": {
    "gn:admin1_code":"8.0",
    "gn:asciiname":"Sumberkembang Kidul",
    "gn:country_code":"ID",
    "gn:dem":504,
    "gn:feature_class":"P",
    "gn:feature_code":"PPL",
    "gn:name":"Sumberkembang Kidul",
    "gn:population":0,
    "gn:timezone":"Asia/Jakarta",
    "iso:country":"ID",
    "name:ind_x_preferred":[
        "Sumberkembang Kidul"
    ],
    "wof:name":"Sumberkembang Kidul",
    "wof:placetype":"locality"
},
  "geometry": {"coordinates":[112.7576,-8.3392],"type":"Point"}
}