{
  "type": "Feature",
  "properties": {
    "gn:admin1_code":"21.0",
    "gn:asciiname":"Laemanta",
    "gn:country_code":"ID",
    "gn:dem":13,
    "gn:feature_class":"P",
    "gn:feature_code":"PPL",
    "gn:name":"Laemanta",
    "gn:population":0,
    "gn:timezone":"Asia/Makassar",
    "iso:country":"ID",
    "name:ind_x_preferred":[
        "Laemanta"
    ],
    "wof:name":"Laemanta",
    "wof:placetype":"locality"
},
  "geometry": {"coordinates":[120.00839999999999,-0.1741],"type":"Point"}
}