{
  "type": "Feature",
  "properties": {
    "gn:admin1_code":"30",
    "gn:asciiname":"Ibun",
    "gn:country_code":"ID",
    "gn:dem":901,
    "gn:feature_class":"P",
    "gn:feature_code":"PPL",
    "gn:name":"Ibun",
    "gn:population":0,
    "gn:timezone":"Asia/Jakarta",
    "iso:country":"ID",
    "name:ind_x_preferred":[
        "Ibun"
    ],
    "wof:name":"Ibun",
    "wof:placetype":"locality"
},
  "geometry": {"coordinates":[107.7637,-7.0982],"type":"Point"}
}