{
  "type": "Feature",
  "properties": {
    "gn:admin1_code":"32.0",
    "gn:asciiname":"Tanjung Batu",
    "gn:country_code":"ID",
    "gn:dem":25,
    "gn:feature_class":"P",
    "gn:feature_code":"PPL",
    "gn:name":"Tanjung Batu",
    "gn:population":0,
    "gn:timezone":"Asia/Jakarta",
    "iso:country":"ID",
    "name:ceb_x_preferred":[
        "Tanjung Batu"
    ],
    "name:ind_x_preferred":[
        "Tanjung Batu"
    ],
    "name:nld_x_preferred":[
        "Tanjung Batu"
    ],
    "name:swe_x_preferred":[
        "Tanjung Batu"
    ],
    "name:und_x_variant":[
        "Tandjungbatu",
        "Tandjoengbatoe",
        "Tanjungbatu"
    ],
    "wof:name":"Tanjung Batu",
    "wof:placetype":"locality"
},
  "geometry": {"coordinates":[104.61945,-3.35761],"type":"Point"}
}