{
  "type": "Feature",
  "properties": {
    "gn:admin1_code":"30.0",
    "gn:asciiname":"Cipeundeuy",
    "gn:country_code":"ID",
    "gn:dem":757,
    "gn:feature_class":"P",
    "gn:feature_code":"PPLA4",
    "gn:name":"Cipeundeuy",
    "gn:population":0,
    "gn:timezone":"Asia/Jakarta",
    "iso:country":"ID",
    "name:ind_x_preferred":[
        "Cipeundeuy"
    ],
    "name:und_x_variant":[
        "Tjipeundeuj"
    ],
    "wof:name":"Cipeundeuy",
    "wof:placetype":"locality"
},
  "geometry": {"coordinates":[106.50111,-6.65694],"type":"Point"}
}