{
  "type": "Feature",
  "properties": {
    "gn:admin1_code":"30",
    "gn:asciiname":"Babakanempang",
    "gn:country_code":"ID",
    "gn:dem":49,
    "gn:feature_class":"P",
    "gn:feature_code":"PPL",
    "gn:name":"Babakanempang",
    "gn:population":0,
    "gn:timezone":"Asia/Jakarta",
    "iso:country":"ID",
    "name:ind_x_preferred":[
        "Babakanempang"
    ],
    "wof:name":"Babakanempang",
    "wof:placetype":"locality"
},
  "geometry": {"coordinates":[107.46889,-6.40722],"type":"Point"}
}