{
  "type": "Feature",
  "properties": {
    "gn:admin1_code":"7.0",
    "gn:asciiname":"Klahang",
    "gn:country_code":"ID",
    "gn:dem":37,
    "gn:feature_class":"P",
    "gn:feature_code":"PPL",
    "gn:name":"Klahang",
    "gn:population":0,
    "gn:timezone":"Asia/Jakarta",
    "iso:country":"ID",
    "name:ind_x_preferred":[
        "Klahang"
    ],
    "wof:name":"Klahang",
    "wof:placetype":"locality"
},
  "geometry": {"coordinates":[109.31471999999999,-7.44361],"type":"Point"}
}