{
  "type": "Feature",
  "properties": {
    "gn:admin1_code":"30",
    "gn:asciiname":"Rohong Hilir",
    "gn:cc2":"ID",
    "gn:country_code":"ID",
    "gn:dem":195,
    "gn:feature_class":"P",
    "gn:feature_code":"PPL",
    "gn:name":"Rohong Hilir",
    "gn:population":0,
    "gn:timezone":"Asia/Jakarta",
    "iso:country":"ID",
    "name:und_x_variant":[
        "Rahong-hilir",
        "Rohong Hilir"
    ],
    "wof:lang_x_official":[
        "ind"
    ],
    "wof:lang_x_spoken":[
        "ind",
        "eng"
    ],
    "wof:name":"Rohong Hilir",
    "wof:placetype":"locality"
},
  "geometry": {"coordinates":[106.58638999999999,-6.46389],"type":"Point"}
}