{
  "type": "Feature",
  "properties": {
    "gn:admin1_code":"15.0",
    "gn:asciiname":"Jejawi",
    "gn:country_code":"ID",
    "gn:dem":898,
    "gn:feature_class":"P",
    "gn:feature_code":"PPL",
    "gn:name":"Jejawi",
    "gn:population":0,
    "gn:timezone":"Asia/Jakarta",
    "iso:country":"ID",
    "name:epo_x_preferred":[
        "Jejawi"
    ],
    "name:ind_x_preferred":[
        "Jejawi"
    ],
    "name:msa_x_preferred":[
        "Jejawi"
    ],
    "name:und_x_variant":[
        "Umbulan Jejawi"
    ],
    "wof:name":"Jejawi",
    "wof:placetype":"locality"
},
  "geometry": {"coordinates":[104.11297999999999,-4.96769],"type":"Point"}
}