{
  "type": "Feature",
  "properties": {
    "gn:admin1_code":"8.0",
    "gn:asciiname":"Nambak Tengah",
    "gn:country_code":"ID",
    "gn:dem":133,
    "gn:feature_class":"P",
    "gn:feature_code":"PPLA4",
    "gn:name":"Nambak Tengah",
    "gn:population":0,
    "gn:timezone":"Asia/Jakarta",
    "iso:country":"ID",
    "name:ind_x_preferred":[
        "Nambak Tengah"
    ],
    "wof:name":"Nambak Tengah",
    "wof:placetype":"locality"
},
  "geometry": {"coordinates":[111.4462,-8.009],"type":"Point"}
}