{
  "type": "Feature",
  "properties": {
    "gn:admin1_code":"35",
    "gn:asciiname":"Airkeranji",
    "gn:country_code":"ID",
    "gn:dem":6,
    "gn:feature_class":"P",
    "gn:feature_code":"PPL",
    "gn:name":"Airkeranji",
    "gn:population":0,
    "gn:timezone":"Asia/Jakarta",
    "iso:country":"ID",
    "name:ind_x_preferred":[
        "Airkeranji"
    ],
    "wof:name":"Airkeranji",
    "wof:placetype":"locality"
},
  "geometry": {"coordinates":[105.25902000000001,-1.89822],"type":"Point"}
}