{
  "type": "Feature",
  "properties": {
    "gn:admin1_code":"18.0",
    "gn:asciiname":"Papilawe",
    "gn:country_code":"ID",
    "gn:dem":576,
    "gn:feature_class":"P",
    "gn:feature_code":"PPLA4",
    "gn:name":"Papilawe",
    "gn:population":0,
    "gn:timezone":"Asia/Makassar",
    "iso:country":"ID",
    "name:ind_x_preferred":[
        "Papilawe"
    ],
    "name:und_x_variant":[
        "Papelawe"
    ],
    "wof:lang_x_official":[
        "ind"
    ],
    "wof:lang_x_spoken":[
        "ind",
        "eng"
    ],
    "wof:name":"Papilawe",
    "wof:placetype":"locality"
},
  "geometry": {"coordinates":[123.1609,-8.3153],"type":"Point"}
}