{
  "type": "Feature",
  "properties": {
    "gn:admin1_code":"1",
    "gn:asciiname":"Meunasah Ceberik",
    "gn:country_code":"ID",
    "gn:dem":11,
    "gn:feature_class":"P",
    "gn:feature_code":"PPL",
    "gn:name":"Meunasah Ceberik",
    "gn:population":0,
    "gn:timezone":"Asia/Jakarta",
    "iso:country":"ID",
    "name:ind_x_preferred":[
        "Meunasah Ceberik"
    ],
    "wof:name":"Meunasah Ceberik",
    "wof:placetype":"locality"
},
  "geometry": {"coordinates":[97.289,5.148],"type":"Point"}
}