{
  "type": "Feature",
  "properties": {
    "gn:admin1_code":"12.0",
    "gn:asciiname":"Semaras",
    "gn:country_code":"ID",
    "gn:dem":17,
    "gn:feature_class":"P",
    "gn:feature_code":"PPL",
    "gn:name":"Semaras",
    "gn:population":0,
    "gn:timezone":"Asia/Makassar",
    "iso:country":"ID",
    "name:und_x_variant":[
        "Semara",
        "Semaras"
    ],
    "wof:name":"Semaras",
    "wof:placetype":"locality"
},
  "geometry": {"coordinates":[116.08110000000001,-3.7967],"type":"Point"}
}