{
  "type": "Feature",
  "properties": {
    "gn:admin1_code":"0.0",
    "gn:asciiname":"Sungai Seluang",
    "gn:cc2":"ID",
    "gn:country_code":"ID",
    "gn:dem":10,
    "gn:feature_class":"P",
    "gn:feature_code":"PPL",
    "gn:name":"Sungai Seluang",
    "gn:population":0,
    "gn:timezone":"Asia/Makassar",
    "iso:country":"ID",
    "name:und_x_variant":[
        "Soengai Seloeang",
        "Sungai Seluang"
    ],
    "wof:name":"Sungai Seluang",
    "wof:placetype":"locality"
},
  "geometry": {"coordinates":[114.56667,-3.15],"type":"Point"}
}