{
  "type": "Feature",
  "properties": {
    "gn:admin1_code":"34",
    "gn:asciiname":"Tanjungharapan",
    "gn:country_code":"ID",
    "gn:dem":27,
    "gn:feature_class":"P",
    "gn:feature_code":"PPL",
    "gn:name":"Tanjungharapan",
    "gn:population":0,
    "gn:timezone":"Asia/Makassar",
    "iso:country":"ID",
    "name:ind_x_preferred":[
        "Tanjungharapan"
    ],
    "wof:name":"Tanjungharapan",
    "wof:placetype":"locality"
},
  "geometry": {"coordinates":[122.5462,0.6791],"type":"Point"}
}