{
  "type": "Feature",
  "properties": {
    "gn:admin1_code":"7",
    "gn:asciiname":"Gimik",
    "gn:country_code":"ID",
    "gn:dem":723,
    "gn:feature_class":"P",
    "gn:feature_code":"PPL",
    "gn:name":"Gimik",
    "gn:population":0,
    "gn:timezone":"Asia/Jakarta",
    "iso:country":"ID",
    "name:ind_x_preferred":[
        "Gimik"
    ],
    "wof:name":"Gimik",
    "wof:placetype":"locality"
},
  "geometry": {"coordinates":[110.22528,-7.24],"type":"Point"}
}