{
  "type": "Feature",
  "properties": {
    "gn:admin1_code":"8",
    "gn:asciiname":"Gambir",
    "gn:country_code":"ID",
    "gn:dem":89,
    "gn:feature_class":"P",
    "gn:feature_code":"PPL",
    "gn:name":"Gambir",
    "gn:population":0,
    "gn:timezone":"Asia/Jakarta",
    "iso:country":"ID",
    "name:ceb_x_preferred":[
        "Gambir"
    ],
    "name:ind_x_preferred":[
        "Gambir"
    ],
    "name:nld_x_preferred":[
        "Gambir"
    ],
    "name:swe_x_preferred":[
        "Gambir"
    ],
    "wof:name":"Gambir",
    "wof:placetype":"locality"
},
  "geometry": {"coordinates":[111.90130000000001,-7.0671],"type":"Point"}
}