{
  "type": "Feature",
  "properties": {
    "gn:admin1_code":"18",
    "gn:asciiname":"Laramate",
    "gn:country_code":"ID",
    "gn:dem":180,
    "gn:feature_class":"P",
    "gn:feature_code":"PPL",
    "gn:name":"Laramate",
    "gn:population":0,
    "gn:timezone":"Asia/Makassar",
    "iso:country":"ID",
    "name:ind_x_preferred":[
        "Laramate"
    ],
    "wof:name":"Laramate",
    "wof:placetype":"locality"
},
  "geometry": {"coordinates":[119.21934,-9.46587],"type":"Point"}
}