{
  "type": "Feature",
  "properties": {
    "gn:country":"ID",
    "gn:fcode":"ADMD",
    "gn:pop":0,
    "iso:country":"ID",
    "name:unk_x_variant":[
        "Daerah Tingkat II Tanah Datar"
    ],
    "qs:name":"Kabupaten Tanah Datar",
    "qs:photos_9r":0,
    "qs:photos_sr":0,
    "qs:pop_sr":"0",
    "wof:name":"Kabupaten Tanah Datar",
    "wof:placetype":"localadmin",
    "wof:population":0
},
  "geometry": {"coordinates":[100.44199999999999,-0.41708],"type":"Point"}
}