{
  "type": "Feature",
  "properties": {
    "gn:admin1_code":"41",
    "gn:asciiname":"Patotong",
    "gn:country_code":"ID",
    "gn:dem":763,
    "gn:feature_class":"P",
    "gn:feature_code":"PPL",
    "gn:name":"Patotong",
    "gn:population":0,
    "gn:timezone":"Asia/Makassar",
    "iso:country":"ID",
    "name:ind_x_preferred":[
        "Patotong"
    ],
    "wof:name":"Patotong",
    "wof:placetype":"locality"
},
  "geometry": {"coordinates":[119.5543,-2.974],"type":"Point"}
}