{
  "type": "Feature",
  "properties": {
    "gn:admin1_code":"08",
    "gn:asciiname":"Bedugbaru",
    "gn:country_code":"ID",
    "gn:dem":7,
    "gn:feature_class":"P",
    "gn:feature_code":"PPL",
    "gn:name":"Bedugbaru",
    "gn:population":0,
    "gn:timezone":"Asia/Jakarta",
    "iso:country":"ID",
    "name:ind_x_preferred":[
        "Bedugbaru"
    ],
    "name:und_x_variant":[
        "Durungbedug"
    ],
    "wof:lang_x_official":[
        "ind"
    ],
    "wof:lang_x_spoken":[
        "ind",
        "eng"
    ],
    "wof:name":"Bedugbaru",
    "wof:placetype":"locality"
},
  "geometry": {"coordinates":[112.6671,-7.465],"type":"Point"}
}