{
  "type": "Feature",
  "properties": {
    "gn:admin1_code":"08",
    "gn:asciiname":"Kencar",
    "gn:country_code":"ID",
    "gn:dem":6,
    "gn:feature_class":"P",
    "gn:feature_code":"PPL",
    "gn:name":"Kencar",
    "gn:population":0,
    "gn:timezone":"Asia/Jakarta",
    "iso:country":"ID",
    "name:ind_x_preferred":[
        "Kencar"
    ],
    "name:und_x_variant":[
        "Kentjat",
        "Kencat"
    ],
    "wof:name":"Kencar",
    "wof:placetype":"locality"
},
  "geometry": {"coordinates":[112.7692,-7.0139],"type":"Point"}
}