{
  "type": "Feature",
  "properties": {
    "gn:admin1_code":"22.0",
    "gn:asciiname":"Tasahea",
    "gn:country_code":"ID",
    "gn:dem":63,
    "gn:feature_class":"P",
    "gn:feature_code":"PPL",
    "gn:name":"Tasahea",
    "gn:population":0,
    "gn:timezone":"Asia/Makassar",
    "iso:country":"ID",
    "name:ind_x_preferred":[
        "Tasahea"
    ],
    "wof:name":"Tasahea",
    "wof:placetype":"locality"
},
  "geometry": {"coordinates":[121.8882,-4.0586],"type":"Point"}
}