{
  "type": "Feature",
  "properties": {
    "gn:admin1_code":"33",
    "gn:asciiname":"Kaduodeng",
    "gn:country_code":"ID",
    "gn:dem":144,
    "gn:feature_class":"P",
    "gn:feature_code":"PPL",
    "gn:name":"Kaduodeng",
    "gn:population":0,
    "gn:timezone":"Asia/Jakarta",
    "iso:country":"ID",
    "name:ind_x_preferred":[
        "Kaduodeng"
    ],
    "wof:name":"Kaduodeng",
    "wof:placetype":"locality"
},
  "geometry": {"coordinates":[105.956,-6.0862],"type":"Point"}
}