{
  "type": "Feature",
  "properties": {
    "gn:country":"ID",
    "gn:fcode":"ADM4",
    "gn:pop":0,
    "iso:country":"ID",
    "name:eng_x_preferred":[
        "Districts of West Java"
    ],
    "name:ind_x_preferred":[
        "Desa Telukjambe"
    ],
    "name:unk_x_variant":[
        "Telukjambe"
    ],
    "qs:name":"Desa Telukjambe",
    "qs:photos_9r":0,
    "qs:photos_sr":0,
    "qs:pop_sr":"0",
    "wd:wordcount":1319,
    "wof:name":"Desa Telukjambe",
    "wof:placetype":"localadmin",
    "wof:population":0
},
  "geometry": {"coordinates":[107.32138999999999,-6.33833],"type":"Point"}
}