{
  "type": "Feature",
  "properties": {
    "gn:admin1_code":"17",
    "gn:asciiname":"Monte",
    "gn:country_code":"ID",
    "gn:dem":186,
    "gn:feature_class":"P",
    "gn:feature_code":"PPL",
    "gn:name":"Monte",
    "gn:population":0,
    "gn:timezone":"Asia/Makassar",
    "iso:country":"ID",
    "name:aze_x_preferred":[
        "Monte"
    ],
    "name:bre_x_preferred":[
        "Monte"
    ],
    "name:bul_x_preferred":[
        "\u041c\u043e\u043d\u0442\u0435"
    ],
    "name:ceb_x_preferred":[
        "Monte"
    ],
    "name:deu_x_preferred":[
        "Monte"
    ],
    "name:fas_x_preferred":[
        "\u0645\u0648\u0646\u062a\u0647"
    ],
    "name:fra_x_preferred":[
        "Monte"
    ],
    "name:glg_x_preferred":[
        "Monte"
    ],
    "name:hun_x_preferred":[
        "Monte"
    ],
    "name:ind_x_preferred":[
        "Monte"
    ],
    "name:ita_x_preferred":[
        "Monte"
    ],
    "name:jpn_x_preferred":[
        "\u30e2\u30f3\u30c6"
    ],
    "name:nld_x_preferred":[
        "Monte"
    ],
    "name:pol_x_preferred":[
        "Monte"
    ],
    "name:por_x_preferred":[
        "Monte"
    ],
    "name:rus_x_preferred":[
        "\u041c\u043e\u043d\u0442\u0435"
    ],
    "name:slk_x_preferred":[
        "Monte"
    ],
    "name:spa_x_preferred":[
        "Monte"
    ],
    "name:srp_x_preferred":[
        "Monte"
    ],
    "name:swe_x_preferred":[
        "Monte"
    ],
    "name:tur_x_preferred":[
        "Monte"
    ],
    "name:ukr_x_preferred":[
        "\u041c\u043e\u043d\u0442\u0435"
    ],
    "wof:lang_x_official":[
        "ind"
    ],
    "wof:lang_x_spoken":[
        "ind",
        "eng"
    ],
    "wof:name":"Monte",
    "wof:placetype":"locality"
},
  "geometry": {"coordinates":[116.2624,-8.8499],"type":"Point"}
}