{
  "type": "Feature",
  "properties": {
    "gn:admin1_code":"7.0",
    "gn:asciiname":"Kedungdalem",
    "gn:country_code":"ID",
    "gn:dem":35,
    "gn:feature_class":"P",
    "gn:feature_code":"PPL",
    "gn:name":"Kedungdalem",
    "gn:population":0,
    "gn:timezone":"Asia/Jakarta",
    "iso:country":"ID",
    "name:ind_x_preferred":[
        "Kedungdalem"
    ],
    "wof:name":"Kedungdalem",
    "wof:placetype":"locality"
},
  "geometry": {"coordinates":[109.70917,-7.64083],"type":"Point"}
}