{
  "type": "Feature",
  "properties": {
    "gn:admin1_code":"07",
    "gn:asciiname":"Wonorejo",
    "gn:country_code":"ID",
    "gn:dem":103,
    "gn:feature_class":"P",
    "gn:feature_code":"PPL",
    "gn:name":"Wonorejo",
    "gn:population":0,
    "gn:timezone":"Asia/Jakarta",
    "iso:country":"ID",
    "wof:name":"Wonorejo",
    "wof:placetype":"locality"
},
  "geometry": {"coordinates":[110.70917,-7.72361],"type":"Point"}
}