{
  "type": "Feature",
  "properties": {
    "gn:admin1_code":"21",
    "gn:asciiname":"Mokupo",
    "gn:country_code":"ID",
    "gn:dem":33,
    "gn:feature_class":"P",
    "gn:feature_code":"PPL",
    "gn:name":"Mokupo",
    "gn:population":0,
    "gn:timezone":"Asia/Makassar",
    "iso:country":"ID",
    "name:ind_x_preferred":[
        "Mokupo"
    ],
    "name:und_x_variant":[
        "Makupo"
    ],
    "wof:name":"Mokupo",
    "wof:placetype":"locality"
},
  "geometry": {"coordinates":[121.4096,1.255],"type":"Point"}
}