{
  "type": "Feature",
  "properties": {
    "gn:admin1_code":"8.0",
    "gn:asciiname":"Krandon Wetan",
    "gn:country_code":"ID",
    "gn:dem":15,
    "gn:feature_class":"P",
    "gn:feature_code":"PPL",
    "gn:name":"Krandon Wetan",
    "gn:population":0,
    "gn:timezone":"Asia/Jakarta",
    "iso:country":"ID",
    "name:ind_x_preferred":[
        "Krandon Wetan"
    ],
    "wof:name":"Krandon Wetan",
    "wof:placetype":"locality"
},
  "geometry": {"coordinates":[113.3556,-7.7875],"type":"Point"}
}