{
  "type": "Feature",
  "properties": {
    "gn:admin1_code":"26",
    "gn:asciiname":"Hatinggian",
    "gn:country_code":"ID",
    "gn:dem":1095,
    "gn:feature_class":"P",
    "gn:feature_code":"PPL",
    "gn:name":"Hatinggian",
    "gn:population":0,
    "gn:timezone":"Asia/Jakarta",
    "iso:country":"ID",
    "name:ind_x_preferred":[
        "Hatinggian"
    ],
    "wof:name":"Hatinggian",
    "wof:placetype":"locality"
},
  "geometry": {"coordinates":[99.0397,2.5347],"type":"Point"}
}