{
  "type": "Feature",
  "properties": {
    "gn:admin1_code":"30",
    "gn:asciiname":"Kedep Utara",
    "gn:cc2":"ID",
    "gn:country_code":"ID",
    "gn:dem":97,
    "gn:feature_class":"P",
    "gn:feature_code":"PPL",
    "gn:name":"Kedep Utara",
    "gn:population":0,
    "gn:timezone":"Asia/Jakarta",
    "iso:country":"ID",
    "name:und_x_variant":[
        "Kedep Dua",
        "Kedep 2",
        "Kedep Utara"
    ],
    "wof:name":"Kedep Utara",
    "wof:placetype":"locality"
},
  "geometry": {"coordinates":[106.92528,-6.44361],"type":"Point"}
}