{
  "type": "Feature",
  "properties": {
    "gn:admin1_code":"21.0",
    "gn:asciiname":"Pososlalongo",
    "gn:country_code":"ID",
    "gn:dem":101,
    "gn:feature_class":"P",
    "gn:feature_code":"PPL",
    "gn:name":"Pososlalongo",
    "gn:population":0,
    "gn:timezone":"Asia/Makassar",
    "iso:country":"ID",
    "name:ind_x_preferred":[
        "Pososlalongo"
    ],
    "wof:name":"Pososlalongo",
    "wof:placetype":"locality"
},
  "geometry": {"coordinates":[123.4847,-1.66],"type":"Point"}
}