{
  "type": "Feature",
  "properties": {
    "gn:admin1_code":"30",
    "gn:asciiname":"Bunipasir",
    "gn:country_code":"ID",
    "gn:dem":636,
    "gn:feature_class":"P",
    "gn:feature_code":"PPL",
    "gn:name":"Bunipasir",
    "gn:population":0,
    "gn:timezone":"Asia/Jakarta",
    "iso:country":"ID",
    "name:ind_x_preferred":[
        "Bunipasir"
    ],
    "wof:name":"Bunipasir",
    "wof:placetype":"locality"
},
  "geometry": {"coordinates":[107.12027999999999,-6.7825],"type":"Point"}
}