{
  "type": "Feature",
  "properties": {
    "gn:admin1_code":"8.0",
    "gn:asciiname":"Jabon",
    "gn:country_code":"ID",
    "gn:dem":8,
    "gn:feature_class":"P",
    "gn:feature_code":"PPL",
    "gn:name":"Jabon",
    "gn:population":0,
    "gn:timezone":"Asia/Jakarta",
    "iso:country":"ID",
    "name:ind_x_preferred":[
        "Jabon"
    ],
    "name:und_x_variant":[
        "Djabon"
    ],
    "wof:name":"Jabon",
    "wof:placetype":"locality"
},
  "geometry": {"coordinates":[112.70489999999999,-7.5425],"type":"Point"}
}