{
  "type": "Feature",
  "properties": {
    "gn:admin1_code":"17",
    "gn:asciiname":"Suwangi Selatan",
    "gn:country_code":"ID",
    "gn:dem":242,
    "gn:feature_class":"P",
    "gn:feature_code":"PPL",
    "gn:name":"Suwangi Selatan",
    "gn:population":0,
    "gn:timezone":"Asia/Makassar",
    "iso:country":"ID",
    "name:ind_x_preferred":[
        "Suwangi Selatan"
    ],
    "wof:name":"Suwangi Selatan",
    "wof:placetype":"locality"
},
  "geometry": {"coordinates":[116.44540000000001,-8.6944],"type":"Point"}
}