{
  "type": "Feature",
  "properties": {
    "gn:admin1_code":"31.0",
    "gn:asciiname":"Lingkungan Dua",
    "gn:country_code":"ID",
    "gn:dem":300,
    "gn:feature_class":"P",
    "gn:feature_code":"PPL",
    "gn:name":"Lingkungan Dua",
    "gn:population":0,
    "gn:timezone":"Asia/Makassar",
    "iso:country":"ID",
    "name:ind_x_preferred":[
        "Lingkungan Dua"
    ],
    "name:und_x_variant":[
        "Lingkungan 2"
    ],
    "wof:lang_x_official":[
        "ind"
    ],
    "wof:lang_x_spoken":[
        "ind",
        "eng"
    ],
    "wof:name":"Lingkungan Dua",
    "wof:placetype":"locality"
},
  "geometry": {"coordinates":[124.3117,0.7541],"type":"Point"}
}