{
  "type": "Feature",
  "properties": {
    "gn:admin1_code":"18.0",
    "gn:asciiname":"Manus",
    "gn:country_code":"ID",
    "gn:dem":1037,
    "gn:feature_class":"P",
    "gn:feature_code":"PPL",
    "gn:name":"Manus",
    "gn:population":0,
    "gn:timezone":"Asia/Makassar",
    "iso:country":"ID",
    "name:ind_x_preferred":[
        "Manus"
    ],
    "name:und_x_variant":[
        "Manoes",
        "Mandoes",
        "Manus"
    ],
    "wof:name":"Manus",
    "wof:placetype":"locality"
},
  "geometry": {"coordinates":[120.7021,-8.6575],"type":"Point"}
}