{
  "type": "Feature",
  "properties": {
    "gn:admin1_code":"18.0",
    "gn:asciiname":"Manus",
    "gn:country_code":"ID",
    "gn:dem":1037,
    "gn:feature_class":"P",
    "gn:feature_code":"PPL",
    "gn:name":"Manus",
    "gn:population":0,
    "gn:timezone":"Asia/Makassar",
    "iso:country":"ID",
    "name:ceb_x_preferred":[
        "Manus"
    ],
    "name:ces_x_preferred":[
        "Manus"
    ],
    "name:deu_x_preferred":[
        "Manus"
    ],
    "name:est_x_preferred":[
        "Manus"
    ],
    "name:fra_x_preferred":[
        "Manus"
    ],
    "name:hrv_x_preferred":[
        "Manus"
    ],
    "name:ind_x_preferred":[
        "Manus"
    ],
    "name:nld_x_preferred":[
        "Manus"
    ],
    "name:pol_x_preferred":[
        "Manus"
    ],
    "name:por_x_preferred":[
        "Manus"
    ],
    "name:rus_x_preferred":[
        "\u041c\u0430\u043d\u0443\u0441"
    ],
    "name:swe_x_preferred":[
        "Manus"
    ],
    "name:tur_x_preferred":[
        "Manus"
    ],
    "name:und_x_variant":[
        "Manoes",
        "Mandoes",
        "Manus"
    ],
    "wof:lang_x_official":[
        "ind"
    ],
    "wof:lang_x_spoken":[
        "ind",
        "eng"
    ],
    "wof:name":"Manus",
    "wof:placetype":"locality"
},
  "geometry": {"coordinates":[120.7021,-8.6575],"type":"Point"}
}