{
  "type": "Feature",
  "properties": {
    "gn:admin1_code":"18.0",
    "gn:asciiname":"Manus",
    "gn:country_code":"ID",
    "gn:dem":1037,
    "gn:feature_class":"P",
    "gn:feature_code":"PPL",
    "gn:name":"Manus",
    "gn:population":0,
    "gn:timezone":"Asia/Makassar",
    "iso:country":"ID",
    "name:ara_x_preferred":[
        "\u0645\u0627\u0646\u0648\u0633"
    ],
    "name:ben_x_preferred":[
        "\u09ae\u09be\u09a8\u09c1\u09b8"
    ],
    "name:ceb_x_preferred":[
        "Manus"
    ],
    "name:ces_x_preferred":[
        "Manus"
    ],
    "name:deu_x_preferred":[
        "Manus"
    ],
    "name:ell_x_preferred":[
        "\u039c\u03ac\u03bd\u03bf\u03c5\u03c2"
    ],
    "name:est_x_preferred":[
        "Manus"
    ],
    "name:fra_x_preferred":[
        "Manus"
    ],
    "name:heb_x_preferred":[
        "\u05de\u05d0\u05e0\u05d5\u05e1"
    ],
    "name:hin_x_preferred":[
        "\u092e\u093e\u0928\u0941\u0938"
    ],
    "name:hrv_x_preferred":[
        "Manus"
    ],
    "name:hun_x_preferred":[
        "Manus"
    ],
    "name:ind_x_preferred":[
        "Manus"
    ],
    "name:nld_x_preferred":[
        "Manus"
    ],
    "name:pol_x_preferred":[
        "Manus"
    ],
    "name:por_x_preferred":[
        "Manus"
    ],
    "name:rus_x_preferred":[
        "\u041c\u0430\u043d\u0443\u0441"
    ],
    "name:swe_x_preferred":[
        "Manus"
    ],
    "name:tur_x_preferred":[
        "Manus"
    ],
    "name:ukr_x_preferred":[
        "\u041c\u0430\u043d\u0443\u0441"
    ],
    "name:und_x_variant":[
        "Manoes",
        "Mandoes",
        "Manus"
    ],
    "wof:lang_x_official":[
        "ind"
    ],
    "wof:lang_x_spoken":[
        "ind",
        "eng"
    ],
    "wof:name":"Manus",
    "wof:placetype":"locality"
},
  "geometry": {"coordinates":[120.7021,-8.6575],"type":"Point"}
}