{
  "type": "Feature",
  "properties": {
    "gn:admin1_code":"7",
    "gn:asciiname":"Ngrandu",
    "gn:country_code":"ID",
    "gn:dem":538,
    "gn:feature_class":"P",
    "gn:feature_code":"PPL",
    "gn:name":"Ngrandu",
    "gn:population":0,
    "gn:timezone":"Asia/Jakarta",
    "iso:country":"ID",
    "name:ind_x_preferred":[
        "Ngrandu"
    ],
    "wof:name":"Ngrandu",
    "wof:placetype":"locality"
},
  "geometry": {"coordinates":[111.22693999999998,-7.80833],"type":"Point"}
}