{
  "type": "Feature",
  "properties": {
    "gn:admin1_code":"26.0",
    "gn:asciiname":"Permahanan",
    "gn:country_code":"ID",
    "gn:dem":1065,
    "gn:feature_class":"P",
    "gn:feature_code":"PPL",
    "gn:name":"Permahanan",
    "gn:population":0,
    "gn:timezone":"Asia/Jakarta",
    "iso:country":"ID",
    "name:ind_x_preferred":[
        "Permahanan"
    ],
    "wof:name":"Permahanan",
    "wof:placetype":"locality"
},
  "geometry": {"coordinates":[98.8683,2.8355],"type":"Point"}
}