{
  "type": "Feature",
  "properties": {
    "gn:admin1_code":"17",
    "gn:asciiname":"Nyangkat",
    "gn:country_code":"ID",
    "gn:dem":113,
    "gn:feature_class":"P",
    "gn:feature_code":"PPL",
    "gn:name":"Nyangkat",
    "gn:population":0,
    "gn:timezone":"Asia/Makassar",
    "iso:country":"ID",
    "name:ind_x_preferred":[
        "Nyangkat"
    ],
    "wof:name":"Nyangkat",
    "wof:placetype":"locality"
},
  "geometry": {"coordinates":[116.3946,-8.7745],"type":"Point"}
}