{
  "type": "Feature",
  "properties": {
    "gn:admin1_code":"18.0",
    "gn:asciiname":"Iungsinu",
    "gn:country_code":"ID",
    "gn:dem":22,
    "gn:feature_class":"P",
    "gn:feature_code":"PPL",
    "gn:name":"Iungsinu",
    "gn:population":0,
    "gn:timezone":"Asia/Makassar",
    "iso:country":"ID",
    "name:ind_x_preferred":[
        "Iungsinu"
    ],
    "name:und_x_variant":[
        "Besdale 2",
        "Besdale"
    ],
    "wof:lang_x_official":[
        "ind"
    ],
    "wof:lang_x_spoken":[
        "ind",
        "eng"
    ],
    "wof:name":"Iungsinu",
    "wof:placetype":"locality"
},
  "geometry": {"coordinates":[123.3231,-10.2757],"type":"Point"}
}