{
  "type": "Feature",
  "properties": {
    "gn:admin1_code":"30.0",
    "gn:asciiname":"Datarkoang",
    "gn:country_code":"ID",
    "gn:dem":30,
    "gn:feature_class":"P",
    "gn:feature_code":"PPL",
    "gn:name":"Datarkoang",
    "gn:population":0,
    "gn:timezone":"Asia/Jakarta",
    "iso:country":"ID",
    "name:ind_x_preferred":[
        "Datarkoang"
    ],
    "wof:name":"Datarkoang",
    "wof:placetype":"locality"
},
  "geometry": {"coordinates":[107.48,-7.5254],"type":"Point"}
}