{
  "type": "Feature",
  "properties": {
    "gn:admin1_code":"8",
    "gn:asciiname":"Kulonbukit",
    "gn:country_code":"ID",
    "gn:dem":122,
    "gn:feature_class":"P",
    "gn:feature_code":"PPL",
    "gn:name":"Kulonbukit",
    "gn:population":0,
    "gn:timezone":"Asia/Jakarta",
    "iso:country":"ID",
    "name:ind_x_preferred":[
        "Kulonbukit"
    ],
    "wof:name":"Kulonbukit",
    "wof:placetype":"locality"
},
  "geometry": {"coordinates":[113.74930000000001,-8.2042],"type":"Point"}
}