{
  "type": "Feature",
  "properties": {
    "gn:admin1_code":"30",
    "gn:asciiname":"Cigondol",
    "gn:country_code":"ID",
    "gn:dem":879,
    "gn:feature_class":"P",
    "gn:feature_code":"PPL",
    "gn:name":"Cigondol",
    "gn:population":0,
    "gn:timezone":"Asia/Jakarta",
    "iso:country":"ID",
    "name:ind_x_preferred":[
        "Cigondol"
    ],
    "wof:name":"Cigondol",
    "wof:placetype":"locality"
},
  "geometry": {"coordinates":[107.48139,-6.77917],"type":"Point"}
}