{
  "type": "Feature",
  "properties": {
    "gn:admin1_code":"33.0",
    "gn:asciiname":"Cibuni",
    "gn:country_code":"ID",
    "gn:dem":440,
    "gn:feature_class":"P",
    "gn:feature_code":"PPL",
    "gn:name":"Cibuni",
    "gn:population":0,
    "gn:timezone":"Asia/Jakarta",
    "iso:country":"ID",
    "name:ind_x_preferred":[
        "Cibuni"
    ],
    "wof:name":"Cibuni",
    "wof:placetype":"locality"
},
  "geometry": {"coordinates":[106.1806,-6.6347],"type":"Point"}
}