{
  "type": "Feature",
  "properties": {
    "gn:admin1_code":"17.0",
    "gn:asciiname":"Pepao Timur",
    "gn:country_code":"ID",
    "gn:dem":166,
    "gn:feature_class":"P",
    "gn:feature_code":"PPL",
    "gn:name":"Pepao Timur",
    "gn:population":0,
    "gn:timezone":"Asia/Makassar",
    "iso:country":"ID",
    "name:ind_x_preferred":[
        "Pepao Timur"
    ],
    "wof:name":"Pepao Timur",
    "wof:placetype":"locality"
},
  "geometry": {"coordinates":[116.44199999999999,-8.7254],"type":"Point"}
}