{
  "type": "Feature",
  "properties": {
    "gn:admin1_code":"26",
    "gn:asciiname":"Hajoranjae",
    "gn:country_code":"ID",
    "gn:dem":42,
    "gn:feature_class":"P",
    "gn:feature_code":"PPL",
    "gn:name":"Hajoranjae",
    "gn:population":0,
    "gn:timezone":"Asia/Jakarta",
    "iso:country":"ID",
    "name:ind_x_preferred":[
        "Hajoranjae"
    ],
    "name:ind_x_variant":[
        "Havoranjae"
    ],
    "wof:name":"Hajoranjae",
    "wof:placetype":"locality"
},
  "geometry": {"coordinates":[99.91837,1.74535],"type":"Point"}
}