{
  "type": "Feature",
  "properties": {
    "gn:admin1_code":"8.0",
    "gn:asciiname":"Turi",
    "gn:country_code":"ID",
    "gn:dem":894,
    "gn:feature_class":"P",
    "gn:feature_code":"PPL",
    "gn:name":"Turi",
    "gn:population":0,
    "gn:timezone":"Asia/Jakarta",
    "iso:country":"ID",
    "name:ind_x_preferred":[
        "Turi"
    ],
    "wof:name":"Turi",
    "wof:placetype":"locality"
},
  "geometry": {"coordinates":[111.789,-7.9147],"type":"Point"}
}