{
  "type": "Feature",
  "properties": {
    "gn:admin1_code":"37",
    "gn:asciiname":"Paritsatu",
    "gn:country_code":"ID",
    "gn:dem":14,
    "gn:feature_class":"P",
    "gn:feature_code":"PPL",
    "gn:name":"Paritsatu",
    "gn:population":0,
    "gn:timezone":"Asia/Jakarta",
    "iso:country":"ID",
    "name:ind_x_preferred":[
        "Paritsatu"
    ],
    "wof:name":"Paritsatu",
    "wof:placetype":"locality"
},
  "geometry": {"coordinates":[103.29255000000001,0.49575],"type":"Point"}
}