{
  "type": "Feature",
  "properties": {
    "gn:admin1_code":"2",
    "gn:asciiname":"Banjar Lumajang",
    "gn:country_code":"ID",
    "gn:dem":123,
    "gn:feature_class":"P",
    "gn:feature_code":"PPL",
    "gn:name":"Banjar Lumajang",
    "gn:population":0,
    "gn:timezone":"Asia/Makassar",
    "iso:country":"ID",
    "name:ind_x_preferred":[
        "Banjar Lumajang"
    ],
    "wof:name":"Banjar Lumajang",
    "wof:placetype":"locality"
},
  "geometry": {"coordinates":[115.1003,-8.5241],"type":"Point"}
}