{
  "type": "Feature",
  "properties": {
    "gn:admin1_code":"30",
    "gn:asciiname":"Areng Tengah",
    "gn:country_code":"ID",
    "gn:dem":1122,
    "gn:feature_class":"P",
    "gn:feature_code":"PPL",
    "gn:name":"Areng Tengah",
    "gn:population":0,
    "gn:timezone":"Asia/Jakarta",
    "iso:country":"ID",
    "name:ind_x_preferred":[
        "Areng Tengah"
    ],
    "wof:name":"Areng Tengah",
    "wof:placetype":"locality"
},
  "geometry": {"coordinates":[107.61499999999999,-6.83611],"type":"Point"}
}