{
  "type": "Feature",
  "properties": {
    "gn:admin1_code":"30.0",
    "gn:asciiname":"Cihanyir",
    "gn:country_code":"ID",
    "gn:dem":756,
    "gn:feature_class":"P",
    "gn:feature_code":"PPL",
    "gn:name":"Cihanyir",
    "gn:population":0,
    "gn:timezone":"Asia/Jakarta",
    "iso:country":"ID",
    "name:ind_x_preferred":[
        "Cihanyir"
    ],
    "name:und_x_variant":[
        "Tjihanjir"
    ],
    "wof:name":"Cihanyir",
    "wof:placetype":"locality"
},
  "geometry": {"coordinates":[108.1404,-7.209],"type":"Point"}
}