{
  "type": "Feature",
  "properties": {
    "gn:admin1_code":"26",
    "gn:asciiname":"Sisangkil",
    "gn:country_code":"ID",
    "gn:dem":125,
    "gn:feature_class":"P",
    "gn:feature_code":"PPL",
    "gn:name":"Sisangkil",
    "gn:population":0,
    "gn:timezone":"Asia/Jakarta",
    "iso:country":"ID",
    "name:ind_x_preferred":[
        "Sisangkil"
    ],
    "wof:name":"Sisangkil",
    "wof:placetype":"locality"
},
  "geometry": {"coordinates":[99.20926,1.3014],"type":"Point"}
}