{
  "type": "Feature",
  "properties": {
    "gn:admin1_code":"7.0",
    "gn:asciiname":"Jaten Kulon",
    "gn:country_code":"ID",
    "gn:dem":171,
    "gn:feature_class":"P",
    "gn:feature_code":"PPL",
    "gn:name":"Jaten Kulon",
    "gn:population":0,
    "gn:timezone":"Asia/Jakarta",
    "iso:country":"ID",
    "wof:name":"Jaten Kulon",
    "wof:placetype":"locality"
},
  "geometry": {"coordinates":[110.75639,-7.38417],"type":"Point"}
}