{
  "type": "Feature",
  "properties": {
    "gn:admin1_code":"28.0",
    "gn:asciiname":"Ngurwalek",
    "gn:country_code":"ID",
    "gn:dem":55,
    "gn:feature_class":"P",
    "gn:feature_code":"PPL",
    "gn:name":"Ngurwalek",
    "gn:population":0,
    "gn:timezone":"Asia/Jayapura",
    "iso:country":"ID",
    "name:und_x_variant":[
        "Ngoerwalek",
        "Ngurwalek"
    ],
    "wof:name":"Ngurwalek",
    "wof:placetype":"locality"
},
  "geometry": {"coordinates":[133.04570000000001,-5.5111],"type":"Point"}
}