{
  "type": "Feature",
  "properties": {
    "gn:admin1_code":"30",
    "gn:asciiname":"Mekarasih",
    "gn:country_code":"ID",
    "gn:dem":283,
    "gn:feature_class":"P",
    "gn:feature_code":"PPL",
    "gn:name":"Mekarasih",
    "gn:population":0,
    "gn:timezone":"Asia/Jakarta",
    "iso:country":"ID",
    "name:ind_x_preferred":[
        "Mekarasih"
    ],
    "wof:name":"Mekarasih",
    "wof:placetype":"locality"
},
  "geometry": {"coordinates":[108.53279999999999,-6.8228],"type":"Point"}
}