{
  "type": "Feature",
  "properties": {
    "gn:admin1_code":"30.0",
    "gn:asciiname":"Pangkalan Barat",
    "gn:country_code":"ID",
    "gn:dem":9,
    "gn:feature_class":"P",
    "gn:feature_code":"PPL",
    "gn:name":"Pangkalan Barat",
    "gn:population":0,
    "gn:timezone":"Asia/Jakarta",
    "iso:country":"ID",
    "name:ind_x_preferred":[
        "Pangkalan Barat"
    ],
    "name:und_x_variant":[
        "Pangkalan"
    ],
    "wof:name":"Pangkalan Barat",
    "wof:placetype":"locality"
},
  "geometry": {"coordinates":[108.49639000000001,-6.66139],"type":"Point"}
}