{
  "type": "Feature",
  "properties": {
    "gn:admin1_code":"7.0",
    "gn:asciiname":"Dlimas",
    "gn:country_code":"ID",
    "gn:dem":772,
    "gn:feature_class":"P",
    "gn:feature_code":"PPL",
    "gn:name":"Dlimas",
    "gn:population":0,
    "gn:timezone":"Asia/Jakarta",
    "iso:country":"ID",
    "wof:name":"Dlimas",
    "wof:placetype":"locality"
},
  "geometry": {"coordinates":[110.41388999999999,-7.31722],"type":"Point"}
}