{
  "type": "Feature",
  "properties": {
    "gn:admin1_code":"18.0",
    "gn:asciiname":"Parada",
    "gn:country_code":"ID",
    "gn:dem":53,
    "gn:feature_class":"P",
    "gn:feature_code":"PPL",
    "gn:name":"Parada",
    "gn:population":0,
    "gn:timezone":"Asia/Makassar",
    "iso:country":"ID",
    "name:ind_x_preferred":[
        "Parada"
    ],
    "wof:name":"Parada",
    "wof:placetype":"locality"
},
  "geometry": {"coordinates":[118.97669999999999,-9.5231],"type":"Point"}
}