{
  "type": "Feature",
  "properties": {
    "gn:admin1_code":"18.0",
    "gn:asciiname":"Parada",
    "gn:country_code":"ID",
    "gn:dem":53,
    "gn:feature_class":"P",
    "gn:feature_code":"PPL",
    "gn:name":"Parada",
    "gn:population":0,
    "gn:timezone":"Asia/Makassar",
    "iso:country":"ID",
    "name:cat_x_preferred":[
        "Parada"
    ],
    "name:ceb_x_preferred":[
        "Parada"
    ],
    "name:deu_x_preferred":[
        "Parada"
    ],
    "name:eus_x_preferred":[
        "Parada"
    ],
    "name:fra_x_preferred":[
        "Parada"
    ],
    "name:glg_x_preferred":[
        "Parada"
    ],
    "name:ind_x_preferred":[
        "Parada"
    ],
    "name:nld_x_preferred":[
        "Parada"
    ],
    "name:pol_x_preferred":[
        "Parada"
    ],
    "name:por_x_preferred":[
        "Parada"
    ],
    "name:rus_x_preferred":[
        "\u041f\u0430\u0440\u0430\u0434\u0430"
    ],
    "name:slv_x_preferred":[
        "Parada"
    ],
    "name:spa_x_preferred":[
        "Parada"
    ],
    "name:srp_x_preferred":[
        "\u041f\u0430\u0440\u0430\u0434\u0430"
    ],
    "name:swe_x_preferred":[
        "Parada"
    ],
    "wof:name":"Parada",
    "wof:placetype":"locality"
},
  "geometry": {"coordinates":[118.97669999999999,-9.5231],"type":"Point"}
}