{
  "type": "Feature",
  "properties": {
    "gn:admin1_code":"8",
    "gn:asciiname":"Sumberkardi",
    "gn:country_code":"ID",
    "gn:dem":145,
    "gn:feature_class":"P",
    "gn:feature_code":"PPLA4",
    "gn:name":"Sumberkardi",
    "gn:population":0,
    "gn:timezone":"Asia/Jakarta",
    "iso:country":"ID",
    "name:ind_x_preferred":[
        "Sumberkardi"
    ],
    "wof:name":"Sumberkardi",
    "wof:placetype":"locality"
},
  "geometry": {"coordinates":[113.1027,-8.2287],"type":"Point"}
}