{
  "type": "Feature",
  "properties": {
    "gn:admin1_code":"7.0",
    "gn:asciiname":"Donggalan",
    "gn:country_code":"ID",
    "gn:dem":119,
    "gn:feature_class":"P",
    "gn:feature_code":"PPL",
    "gn:name":"Donggalan",
    "gn:population":0,
    "gn:timezone":"Asia/Jakarta",
    "iso:country":"ID",
    "wof:name":"Donggalan",
    "wof:placetype":"locality"
},
  "geometry": {"coordinates":[110.74306,-7.57917],"type":"Point"}
}