{
  "type": "Feature",
  "properties": {
    "gn:admin1_code":"18.0",
    "gn:asciiname":"Sewowoto",
    "gn:country_code":"ID",
    "gn:dem":127,
    "gn:feature_class":"P",
    "gn:feature_code":"PPL",
    "gn:name":"Sewowoto",
    "gn:population":0,
    "gn:timezone":"Asia/Makassar",
    "iso:country":"ID",
    "name:ind_x_preferred":[
        "Sewowoto"
    ],
    "wof:name":"Sewowoto",
    "wof:placetype":"locality"
},
  "geometry": {"coordinates":[120.99120000000001,-8.9468],"type":"Point"}
}