{
  "type": "Feature",
  "properties": {
    "gn:admin1_code":"11.0",
    "gn:asciiname":"Tempah",
    "gn:country_code":"ID",
    "gn:dem":179,
    "gn:feature_class":"P",
    "gn:feature_code":"PPL",
    "gn:name":"Tempah",
    "gn:population":0,
    "gn:timezone":"Asia/Pontianak",
    "iso:country":"ID",
    "name:und_x_variant":[
        "Toempah",
        "Tempah"
    ],
    "wof:name":"Tempah",
    "wof:placetype":"locality"
},
  "geometry": {"coordinates":[112.31667,-0.01667],"type":"Point"}
}