{
  "type": "Feature",
  "properties": {
    "gn:country":"ID",
    "gn:fcode":"ADM3",
    "gn:pop":0,
    "iso:country":"ID",
    "name:eng_x_preferred":[
        "Districts of West Sumatra"
    ],
    "name:fra_x_preferred":[
        "Districts of West Sumatra"
    ],
    "name:ind_x_preferred":[
        "Kecamatan Bayang"
    ],
    "name:nld_x_preferred":[
        "Districts of West Sumatra"
    ],
    "name:unk_x_variant":[
        "Bayang"
    ],
    "qs:name":"Kecamatan Bayang",
    "qs:photos_9r":0,
    "qs:photos_sr":0,
    "qs:pop_sr":"0",
    "wd:wordcount":626,
    "wof:name":"Kecamatan Bayang",
    "wof:placetype":"localadmin",
    "wof:population":0
},
  "geometry": {"coordinates":[100.56777,-1.1572],"type":"Point"}
}