{
  "type": "Feature",
  "properties": {
    "gn:admin1_code":"15.0",
    "gn:asciiname":"Geremleba Tiga",
    "gn:country_code":"ID",
    "gn:dem":98,
    "gn:feature_class":"P",
    "gn:feature_code":"PPL",
    "gn:name":"Geremleba Tiga",
    "gn:population":0,
    "gn:timezone":"Asia/Jakarta",
    "iso:country":"ID",
    "name:ind_x_preferred":[
        "Geremleba Tiga"
    ],
    "name:und_x_variant":[
        "Geremleba 3"
    ],
    "wof:name":"Geremleba Tiga",
    "wof:placetype":"locality"
},
  "geometry": {"coordinates":[105.56833,-5.18842],"type":"Point"}
}