{
  "type": "Feature",
  "properties": {
    "gn:admin1_code":"0.0",
    "gn:asciiname":"Ciramaeuwah-girang",
    "gn:cc2":"ID",
    "gn:country_code":"ID",
    "gn:dem":302,
    "gn:feature_class":"P",
    "gn:feature_code":"PPL",
    "gn:name":"Ciramaeuwah-girang",
    "gn:population":0,
    "gn:timezone":"Asia/Jakarta",
    "iso:country":"ID",
    "name:und_x_variant":[
        "Tjiramaeuwah",
        "Tjiramaeuwah-girang",
        "Ciramaeuwah-girang"
    ],
    "wof:lang_x_official":[
        "ind"
    ],
    "wof:lang_x_spoken":[
        "ind",
        "eng"
    ],
    "wof:name":"Ciramaeuwah-girang",
    "wof:placetype":"locality"
},
  "geometry": {"coordinates":[107.25,-6.68333],"type":"Point"}
}