{
  "type": "Feature",
  "properties": {
    "gn:admin1_code":"26",
    "gn:asciiname":"Raya Dolok",
    "gn:country_code":"ID",
    "gn:dem":176,
    "gn:feature_class":"P",
    "gn:feature_code":"PPL",
    "gn:name":"Raya Dolok",
    "gn:population":0,
    "gn:timezone":"Asia/Jakarta",
    "iso:country":"ID",
    "name:ind_x_preferred":[
        "Raya Dolok"
    ],
    "wof:name":"Raya Dolok",
    "wof:placetype":"locality"
},
  "geometry": {"coordinates":[99.3242,2.8603],"type":"Point"}
}