{
  "type": "Feature",
  "properties": {
    "gn:admin1_code":"26",
    "gn:asciiname":"Pasir Tinggi",
    "gn:country_code":"ID",
    "gn:dem":15,
    "gn:feature_class":"P",
    "gn:feature_code":"PPL",
    "gn:name":"Pasir Tinggi",
    "gn:population":0,
    "gn:timezone":"Asia/Jakarta",
    "iso:country":"ID",
    "name:ind_x_preferred":[
        "Pasir Tinggi"
    ],
    "wof:name":"Pasir Tinggi",
    "wof:placetype":"locality"
},
  "geometry": {"coordinates":[99.05074,1.03167],"type":"Point"}
}