{
  "type": "Feature",
  "properties": {
    "gn:admin1_code":"30.0",
    "gn:asciiname":"Sukawinangun",
    "gn:country_code":"ID",
    "gn:dem":478,
    "gn:feature_class":"P",
    "gn:feature_code":"PPL",
    "gn:name":"Sukawinangun",
    "gn:population":0,
    "gn:timezone":"Asia/Jakarta",
    "iso:country":"ID",
    "name:ind_x_preferred":[
        "Sukawinangun"
    ],
    "name:und_x_variant":[
        "Soekawinangoen"
    ],
    "wof:name":"Sukawinangun",
    "wof:placetype":"locality"
},
  "geometry": {"coordinates":[108.1493,-7.142],"type":"Point"}
}