{
  "type": "Feature",
  "properties": {
    "gn:admin1_code":"30.0",
    "gn:asciiname":"Bengkok",
    "gn:country_code":"ID",
    "gn:dem":113,
    "gn:feature_class":"P",
    "gn:feature_code":"PPL",
    "gn:name":"Bengkok",
    "gn:population":0,
    "gn:timezone":"Asia/Jakarta",
    "iso:country":"ID",
    "name:ind_x_preferred":[
        "Bengkok"
    ],
    "wof:name":"Bengkok",
    "wof:placetype":"locality"
},
  "geometry": {"coordinates":[108.4992,-7.6623],"type":"Point"}
}