{
  "type": "Feature",
  "properties": {
    "gn:admin1_code":"31",
    "gn:asciiname":"Tetetempeng",
    "gn:country_code":"ID",
    "gn:dem":50,
    "gn:feature_class":"P",
    "gn:feature_code":"PPL",
    "gn:name":"Tetetempeng",
    "gn:population":0,
    "gn:timezone":"Asia/Makassar",
    "iso:country":"ID",
    "wof:name":"Tetetempeng",
    "wof:placetype":"locality"
},
  "geometry": {"coordinates":[124.97667,1.70667],"type":"Point"}
}