{
  "type": "Feature",
  "properties": {
    "gn:admin1_code":"30",
    "gn:asciiname":"Timbarigrawa",
    "gn:country_code":"ID",
    "gn:dem":36,
    "gn:feature_class":"P",
    "gn:feature_code":"PPL",
    "gn:name":"Timbarigrawa",
    "gn:population":0,
    "gn:timezone":"Asia/Jakarta",
    "iso:country":"ID",
    "wof:name":"Timbarigrawa",
    "wof:placetype":"locality"
},
  "geometry": {"coordinates":[107.69528,-6.4225],"type":"Point"}
}