{
  "type": "Feature",
  "properties": {
    "gn:admin1_code":"38",
    "gn:asciiname":"Pangaparang",
    "gn:country_code":"ID",
    "gn:dem":13,
    "gn:feature_class":"P",
    "gn:feature_code":"PPL",
    "gn:name":"Pangaparang",
    "gn:population":0,
    "gn:timezone":"Asia/Makassar",
    "iso:country":"ID",
    "name:ind_x_preferred":[
        "Pangaparang"
    ],
    "wof:name":"Pangaparang",
    "wof:placetype":"locality"
},
  "geometry": {"coordinates":[119.48779999999999,-3.4894],"type":"Point"}
}