{
  "type": "Feature",
  "properties": {
    "gn:admin1_code":"7",
    "gn:asciiname":"Sudan Kidul",
    "gn:country_code":"ID",
    "gn:dem":29,
    "gn:feature_class":"P",
    "gn:feature_code":"PPL",
    "gn:name":"Sudan Kidul",
    "gn:population":0,
    "gn:timezone":"Asia/Jakarta",
    "iso:country":"ID",
    "name:ind_x_preferred":[
        "Sudan Kidul"
    ],
    "wof:name":"Sudan Kidul",
    "wof:placetype":"locality"
},
  "geometry": {"coordinates":[109.70292000000001,-6.96061],"type":"Point"}
}