{
  "type": "Feature",
  "properties": {
    "gn:admin1_code":"14",
    "gn:asciiname":"Sukamaju",
    "gn:country_code":"ID",
    "gn:dem":25,
    "gn:feature_class":"P",
    "gn:feature_code":"PPL",
    "gn:name":"Sukamaju",
    "gn:population":0,
    "gn:timezone":"Asia/Makassar",
    "iso:country":"ID",
    "name:ind_x_preferred":[
        "Sukamaju"
    ],
    "wof:name":"Sukamaju",
    "wof:placetype":"locality"
},
  "geometry": {"coordinates":[117.0801,-0.2242],"type":"Point"}
}