{
  "type": "Feature",
  "properties": {
    "gn:admin1_code":"41.0",
    "gn:asciiname":"Salanase",
    "gn:country_code":"ID",
    "gn:dem":16,
    "gn:feature_class":"P",
    "gn:feature_code":"PPL",
    "gn:name":"Salanase",
    "gn:population":0,
    "gn:timezone":"Asia/Makassar",
    "iso:country":"ID",
    "name:ind_x_preferred":[
        "Salanase"
    ],
    "wof:name":"Salanase",
    "wof:placetype":"locality"
},
  "geometry": {"coordinates":[118.7903,-2.8557],"type":"Point"}
}