{
  "type": "Feature",
  "properties": {
    "gn:admin1_code":"7",
    "gn:asciiname":"Ngrao",
    "gn:country_code":"ID",
    "gn:dem":28,
    "gn:feature_class":"P",
    "gn:feature_code":"PPL",
    "gn:name":"Ngrao",
    "gn:population":0,
    "gn:timezone":"Asia/Jakarta",
    "iso:country":"ID",
    "name:ind_x_preferred":[
        "Ngrao"
    ],
    "wof:name":"Ngrao",
    "wof:placetype":"locality"
},
  "geometry": {"coordinates":[110.0164,-6.9705],"type":"Point"}
}