{
  "type": "Feature",
  "properties": {
    "gn:admin1_code":"30.0",
    "gn:asciiname":"Rawagede Satu",
    "gn:country_code":"ID",
    "gn:dem":11,
    "gn:feature_class":"P",
    "gn:feature_code":"PPL",
    "gn:name":"Rawagede Satu",
    "gn:population":0,
    "gn:timezone":"Asia/Jakarta",
    "iso:country":"ID",
    "name:ind_x_preferred":[
        "Rawagede Satu"
    ],
    "name:und_x_variant":[
        "Rawagede",
        "Rawagede 1"
    ],
    "wof:lang_x_official":[
        "ind"
    ],
    "wof:lang_x_spoken":[
        "ind",
        "eng"
    ],
    "wof:name":"Rawagede Satu",
    "wof:placetype":"locality"
},
  "geometry": {"coordinates":[107.32666999999999,-6.24028],"type":"Point"}
}