{
  "type": "Feature",
  "properties": {
    "gn:admin1_code":"7.0",
    "gn:asciiname":"Kwagean",
    "gn:country_code":"ID",
    "gn:dem":992,
    "gn:feature_class":"P",
    "gn:feature_code":"PPL",
    "gn:name":"Kwagean",
    "gn:population":0,
    "gn:timezone":"Asia/Jakarta",
    "iso:country":"ID",
    "wof:name":"Kwagean",
    "wof:placetype":"locality"
},
  "geometry": {"coordinates":[110.06610999999999,-7.28667],"type":"Point"}
}