{
  "type": "Feature",
  "properties": {
    "gn:admin1_code":"18.0",
    "gn:asciiname":"Oka",
    "gn:country_code":"ID",
    "gn:dem":13,
    "gn:feature_class":"P",
    "gn:feature_code":"PPL",
    "gn:name":"Oka",
    "gn:population":0,
    "gn:timezone":"Asia/Makassar",
    "iso:country":"ID",
    "name:ara_x_preferred":[
        "\u0623\u0648\u0643\u0627"
    ],
    "name:aze_x_preferred":[
        "Oka"
    ],
    "name:bel_x_preferred":[
        "\u0410\u043a\u0430"
    ],
    "name:ben_x_preferred":[
        "\u0993\u0995\u09be"
    ],
    "name:bul_x_preferred":[
        "\u041e\u043a\u0430"
    ],
    "name:ceb_x_preferred":[
        "Oka"
    ],
    "name:ces_x_preferred":[
        "Oka"
    ],
    "name:dan_x_preferred":[
        "Oka"
    ],
    "name:deu_x_preferred":[
        "Oka"
    ],
    "name:ell_x_preferred":[
        "\u038c\u03ba\u03b1"
    ],
    "name:eus_x_preferred":[
        "Oka"
    ],
    "name:fas_x_preferred":[
        "\u0627\u0648\u06a9\u0627"
    ],
    "name:fin_x_preferred":[
        "Oka"
    ],
    "name:fra_x_preferred":[
        "Oka"
    ],
    "name:fry_x_preferred":[
        "Oka"
    ],
    "name:glg_x_preferred":[
        "Oka"
    ],
    "name:heb_x_preferred":[
        "\u05d0\u05d5\u05e7\u05d4"
    ],
    "name:hin_x_preferred":[
        "\u0913\u0915\u093e"
    ],
    "name:hrv_x_preferred":[
        "Oka"
    ],
    "name:hun_x_preferred":[
        "Oka"
    ],
    "name:hye_x_preferred":[
        "\u0555\u056f\u0561"
    ],
    "name:ind_x_preferred":[
        "Oka"
    ],
    "name:nld_x_preferred":[
        "Oka"
    ],
    "name:oss_x_preferred":[
        "\u041e\u043a\u0430"
    ],
    "name:pol_x_preferred":[
        "Oka"
    ],
    "name:por_x_preferred":[
        "Oca"
    ],
    "name:ron_x_preferred":[
        "Oka"
    ],
    "name:rus_x_preferred":[
        "\u041e\u043a\u0430"
    ],
    "name:slk_x_preferred":[
        "Oka"
    ],
    "name:slv_x_preferred":[
        "Oka"
    ],
    "name:spa_x_preferred":[
        "Oka"
    ],
    "name:srp_x_preferred":[
        "\u041e\u043a\u0430"
    ],
    "name:swe_x_preferred":[
        "Oka"
    ],
    "name:tur_x_preferred":[
        "Oka"
    ],
    "name:ukr_x_preferred":[
        "\u041e\u043a\u0430"
    ],
    "name:und_x_variant":[
        "Lewotala",
        "Okka",
        "Oka"
    ],
    "name:urd_x_preferred":[
        "\u0627\u0648\u06a9\u0627"
    ],
    "name:vie_x_preferred":[
        "S\u00f4ng Oka"
    ],
    "wof:lang_x_official":[
        "ind"
    ],
    "wof:lang_x_spoken":[
        "ind",
        "eng"
    ],
    "wof:name":"Oka",
    "wof:placetype":"locality"
},
  "geometry": {"coordinates":[122.9265,-8.3269],"type":"Point"}
}