{
  "type": "Feature",
  "properties": {
    "gn:admin1_code":"18.0",
    "gn:asciiname":"Oka",
    "gn:country_code":"ID",
    "gn:dem":13,
    "gn:feature_class":"P",
    "gn:feature_code":"PPL",
    "gn:name":"Oka",
    "gn:population":0,
    "gn:timezone":"Asia/Makassar",
    "iso:country":"ID",
    "name:und_x_variant":[
        "Lewotala",
        "Okka",
        "Oka"
    ],
    "wof:name":"Oka",
    "wof:placetype":"locality"
},
  "geometry": {"coordinates":[122.9265,-8.3269],"type":"Point"}
}