{
  "type": "Feature",
  "properties": {
    "gn:admin1_code":"22",
    "gn:asciiname":"Oloa",
    "gn:country_code":"ID",
    "gn:dem":14,
    "gn:feature_class":"P",
    "gn:feature_code":"PPL",
    "gn:name":"Oloa",
    "gn:population":0,
    "gn:timezone":"Asia/Makassar",
    "iso:country":"ID",
    "name:ind_x_preferred":[
        "Oloa"
    ],
    "name:und_x_variant":[
        "Ojoa"
    ],
    "wof:name":"Oloa",
    "wof:placetype":"locality"
},
  "geometry": {"coordinates":[122.896,-4.3709],"type":"Point"}
}