{
  "type": "Feature",
  "properties": {
    "gn:admin1_code":"18.0",
    "gn:asciiname":"Leunapo",
    "gn:country_code":"ID",
    "gn:dem":28,
    "gn:feature_class":"P",
    "gn:feature_code":"PPL",
    "gn:name":"Leunapo",
    "gn:population":0,
    "gn:timezone":"Asia/Makassar",
    "iso:country":"ID",
    "name:ind_x_preferred":[
        "Leunapo"
    ],
    "wof:name":"Leunapo",
    "wof:placetype":"locality"
},
  "geometry": {"coordinates":[123.7555,-8.1852],"type":"Point"}
}