{
  "type": "Feature",
  "properties": {
    "gn:admin1_code":"7",
    "gn:asciiname":"Gilisari",
    "gn:country_code":"ID",
    "gn:dem":12,
    "gn:feature_class":"P",
    "gn:feature_code":"PPL",
    "gn:name":"Gilisari",
    "gn:population":0,
    "gn:timezone":"Asia/Jakarta",
    "iso:country":"ID",
    "name:ind_x_preferred":[
        "Gilisari"
    ],
    "wof:name":"Gilisari",
    "wof:placetype":"locality"
},
  "geometry": {"coordinates":[110.0714,-6.9306],"type":"Point"}
}