{
  "type": "Feature",
  "properties": {
    "gn:admin1_code":"30.0",
    "gn:asciiname":"Nyomplong",
    "gn:country_code":"ID",
    "gn:dem":341,
    "gn:feature_class":"P",
    "gn:feature_code":"PPL",
    "gn:name":"Nyomplong",
    "gn:population":0,
    "gn:timezone":"Asia/Jakarta",
    "iso:country":"ID",
    "name:ind_x_preferred":[
        "Nyomplong"
    ],
    "name:und_x_variant":[
        "Njomplong"
    ],
    "wof:lang_x_official":[
        "ind"
    ],
    "wof:lang_x_spoken":[
        "ind",
        "eng"
    ],
    "wof:name":"Nyomplong",
    "wof:placetype":"locality"
},
  "geometry": {"coordinates":[108.5061,-7.4784],"type":"Point"}
}