{
  "type": "Feature",
  "properties": {
    "gn:admin1_code":"18.0",
    "gn:asciiname":"Kaleb",
    "gn:country_code":"ID",
    "gn:dem":794,
    "gn:feature_class":"P",
    "gn:feature_code":"PPL",
    "gn:name":"Kaleb",
    "gn:population":0,
    "gn:timezone":"Asia/Makassar",
    "iso:country":"ID",
    "name:ind_x_preferred":[
        "Kaleb"
    ],
    "wof:name":"Kaleb",
    "wof:placetype":"locality"
},
  "geometry": {"coordinates":[124.7033,-8.2773],"type":"Point"}
}