{
  "type": "Feature",
  "properties": {
    "gn:admin1_code":"28.0",
    "gn:asciiname":"Kulor",
    "gn:country_code":"ID",
    "gn:dem":4,
    "gn:feature_class":"P",
    "gn:feature_code":"PPL",
    "gn:name":"Kulor",
    "gn:population":0,
    "gn:timezone":"Asia/Jayapura",
    "iso:country":"ID",
    "name:ceb_x_preferred":[
        "K\u016blor"
    ],
    "name:fas_x_preferred":[
        "\u06a9\u0648\u0644\u0631"
    ],
    "name:ind_x_preferred":[
        "Kulor"
    ],
    "name:swe_x_preferred":[
        "K\u016blor"
    ],
    "wof:lang_x_official":[
        "ind"
    ],
    "wof:lang_x_spoken":[
        "ind",
        "eng"
    ],
    "wof:name":"Kulor",
    "wof:placetype":"locality"
},
  "geometry": {"coordinates":[128.56451999999999,-3.50348],"type":"Point"}
}