{
  "type": "Feature",
  "properties": {
    "gn:admin1_code":"28.0",
    "gn:asciiname":"Kulor",
    "gn:country_code":"ID",
    "gn:dem":4,
    "gn:feature_class":"P",
    "gn:feature_code":"PPL",
    "gn:name":"Kulor",
    "gn:population":0,
    "gn:timezone":"Asia/Jayapura",
    "iso:country":"ID",
    "name:ind_x_preferred":[
        "Kulor"
    ],
    "wof:name":"Kulor",
    "wof:placetype":"locality"
},
  "geometry": {"coordinates":[128.56451999999999,-3.50348],"type":"Point"}
}