{
  "type": "Feature",
  "properties": {
    "gn:admin1_code":"28.0",
    "gn:asciiname":"Eglisu",
    "gn:country_code":"ID",
    "gn:dem":639,
    "gn:feature_class":"P",
    "gn:feature_code":"PPL",
    "gn:name":"Eglisu",
    "gn:population":0,
    "gn:timezone":"Asia/Jayapura",
    "iso:country":"ID",
    "name:ind_x_preferred":[
        "Eglisu"
    ],
    "name:und_x_variant":[
        "Eglisoe",
        "Eglisu"
    ],
    "wof:lang_x_official":[
        "ind"
    ],
    "wof:lang_x_spoken":[
        "ind",
        "eng"
    ],
    "wof:name":"Eglisu",
    "wof:placetype":"locality"
},
  "geometry": {"coordinates":[126.6601,-3.5377],"type":"Point"}
}