{
  "type": "Feature",
  "properties": {
    "gn:admin1_code":"24.0",
    "gn:asciiname":"Simpanglolo",
    "gn:country_code":"ID",
    "gn:dem":736,
    "gn:feature_class":"P",
    "gn:feature_code":"PPL",
    "gn:name":"Simpanglolo",
    "gn:population":0,
    "gn:timezone":"Asia/Jakarta",
    "iso:country":"ID",
    "name:ind_x_preferred":[
        "Simpanglolo"
    ],
    "wof:name":"Simpanglolo",
    "wof:placetype":"locality"
},
  "geometry": {"coordinates":[99.7377,0.4298],"type":"Point"}
}