{
  "type": "Feature",
  "properties": {
    "gn:admin1_code":"8.0",
    "gn:asciiname":"Bakalan",
    "gn:country_code":"ID",
    "gn:dem":738,
    "gn:feature_class":"P",
    "gn:feature_code":"PPL",
    "gn:name":"Bakalan",
    "gn:population":0,
    "gn:timezone":"Asia/Jakarta",
    "iso:country":"ID",
    "name:ind_x_preferred":[
        "Bakalan"
    ],
    "wof:name":"Bakalan",
    "wof:placetype":"locality"
},
  "geometry": {"coordinates":[111.53,-8.138],"type":"Point"}
}