{
  "type": "Feature",
  "properties": {
    "gn:admin1_code":"38.0",
    "gn:asciiname":"Tedeboe",
    "gn:country_code":"ID",
    "gn:dem":1230,
    "gn:feature_class":"P",
    "gn:feature_code":"PPL",
    "gn:name":"Tedeboe",
    "gn:population":0,
    "gn:timezone":"Asia/Makassar",
    "iso:country":"ID",
    "name:ind_x_preferred":[
        "Tedeboe"
    ],
    "name:ind_x_variant":[
        "Telebo"
    ],
    "name:und_x_variant":[
        "Rampi",
        "Tedeboi"
    ],
    "wof:lang_x_official":[
        "ind"
    ],
    "wof:lang_x_spoken":[
        "ind",
        "eng"
    ],
    "wof:name":"Tedeboe",
    "wof:placetype":"locality"
},
  "geometry": {"coordinates":[120.1639,-2.1066],"type":"Point"}
}