{
  "type": "Feature",
  "properties": {
    "gn:admin1_code":"7",
    "gn:asciiname":"Dukuhbadag",
    "gn:country_code":"ID",
    "gn:dem":25,
    "gn:feature_class":"P",
    "gn:feature_code":"PPL",
    "gn:name":"Dukuhbadag",
    "gn:population":0,
    "gn:timezone":"Asia/Jakarta",
    "iso:country":"ID",
    "name:ind_x_preferred":[
        "Dukuhbadag"
    ],
    "wof:name":"Dukuhbadag",
    "wof:placetype":"locality"
},
  "geometry": {"coordinates":[108.8725,-6.9495],"type":"Point"}
}