{
  "type": "Feature",
  "properties": {
    "gn:admin1_code":"8.0",
    "gn:asciiname":"Alastengah",
    "gn:country_code":"ID",
    "gn:dem":655,
    "gn:feature_class":"P",
    "gn:feature_code":"PPL",
    "gn:name":"Alastengah",
    "gn:population":0,
    "gn:timezone":"Asia/Jakarta",
    "iso:country":"ID",
    "name:ind_x_preferred":[
        "Alastengah"
    ],
    "wof:name":"Alastengah",
    "wof:placetype":"locality"
},
  "geometry": {"coordinates":[114.0138,-8.2426],"type":"Point"}
}