{
  "type": "Feature",
  "properties": {
    "gn:admin1_code":"8",
    "gn:asciiname":"Tegalmanik",
    "gn:country_code":"ID",
    "gn:dem":86,
    "gn:feature_class":"P",
    "gn:feature_code":"PPL",
    "gn:name":"Tegalmanik",
    "gn:population":0,
    "gn:timezone":"Asia/Jakarta",
    "iso:country":"ID",
    "name:ind_x_preferred":[
        "Tegalmanik"
    ],
    "wof:name":"Tegalmanik",
    "wof:placetype":"locality"
},
  "geometry": {"coordinates":[113.7354,-7.7761],"type":"Point"}
}