{
  "type": "Feature",
  "properties": {
    "gn:admin1_code":"38.0",
    "gn:asciiname":"Botto",
    "gn:country_code":"ID",
    "gn:dem":16,
    "gn:feature_class":"P",
    "gn:feature_code":"PPL",
    "gn:name":"Botto",
    "gn:population":0,
    "gn:timezone":"Asia/Makassar",
    "iso:country":"ID",
    "name:deu_x_preferred":[
        "Botto"
    ],
    "name:fra_x_preferred":[
        "Botto"
    ],
    "name:ind_x_preferred":[
        "Botto"
    ],
    "name:ita_x_preferred":[
        "Botto"
    ],
    "name:pol_x_preferred":[
        "Botto"
    ],
    "name:por_x_preferred":[
        "Botto"
    ],
    "name:rus_x_preferred":[
        "\u0411\u043e\u0442\u0442\u043e"
    ],
    "name:slk_x_preferred":[
        "Botto"
    ],
    "name:spa_x_preferred":[
        "Botto"
    ],
    "name:srp_x_preferred":[
        "Botto"
    ],
    "wof:name":"Botto",
    "wof:placetype":"locality"
},
  "geometry": {"coordinates":[119.4953,-3.4776],"type":"Point"}
}