{
  "type": "Feature",
  "properties": {
    "gn:admin1_code":"8",
    "gn:asciiname":"User",
    "gn:country_code":"ID",
    "gn:dem":340,
    "gn:feature_class":"P",
    "gn:feature_code":"PPL",
    "gn:name":"User",
    "gn:population":0,
    "gn:timezone":"Asia/Jakarta",
    "iso:country":"ID",
    "name:ind_x_preferred":[
        "User"
    ],
    "wof:name":"User",
    "wof:placetype":"locality"
},
  "geometry": {"coordinates":[111.9862,-7.0253],"type":"Point"}
}