{
  "type": "Feature",
  "properties": {
    "gn:admin1_code":"8",
    "gn:asciiname":"User",
    "gn:country_code":"ID",
    "gn:dem":340,
    "gn:feature_class":"P",
    "gn:feature_code":"PPL",
    "gn:name":"User",
    "gn:population":0,
    "gn:timezone":"Asia/Jakarta",
    "iso:country":"ID",
    "name:bar_x_preferred":[
        "Nutza"
    ],
    "name:ces_x_preferred":[
        "U\u017eivatel"
    ],
    "name:dan_x_preferred":[
        "Bruger"
    ],
    "name:deu_x_preferred":[
        "User"
    ],
    "name:fra_x_preferred":[
        "Utilisateur"
    ],
    "name:hun_x_preferred":[
        "Felhaszn\u00e1l\u00f3"
    ],
    "name:ind_x_preferred":[
        "User"
    ],
    "name:jpn_x_preferred":[
        "\u30e6\u30fc\u30b6\u30fc"
    ],
    "name:kor_x_preferred":[
        "\uc0ac\uc6a9\uc790"
    ],
    "name:lat_x_preferred":[
        "Usor"
    ],
    "name:msa_x_preferred":[
        "Pengguna"
    ],
    "name:pol_x_preferred":[
        "U\u017cytkownik"
    ],
    "name:por_x_preferred":[
        "Usu\u00e1rio"
    ],
    "name:pus_x_preferred":[
        "\u06a9\u0627\u0631\u0646"
    ],
    "name:ron_x_preferred":[
        "Utilizator"
    ],
    "name:slk_x_preferred":[
        "Pou\u017e\u00edvate\u013e"
    ],
    "name:tha_x_preferred":[
        "\u0e1c\u0e39\u0e49\u0e43\u0e0a\u0e49"
    ],
    "wof:lang_x_official":[
        "ind"
    ],
    "wof:lang_x_spoken":[
        "ind",
        "eng"
    ],
    "wof:name":"User",
    "wof:placetype":"locality"
},
  "geometry": {"coordinates":[111.9862,-7.0253],"type":"Point"}
}