{
  "type": "Feature",
  "properties": {
    "gn:admin1_code":"26",
    "gn:asciiname":"Afdeling Pondok Ullu",
    "gn:country_code":"ID",
    "gn:dem":42,
    "gn:feature_class":"P",
    "gn:feature_code":"PPL",
    "gn:name":"Afdeling Pondok Ullu",
    "gn:population":0,
    "gn:timezone":"Asia/Jakarta",
    "iso:country":"ID",
    "name:ind_x_preferred":[
        "Afdeling Pondok Ullu"
    ],
    "wof:name":"Afdeling Pondok Ullu",
    "wof:placetype":"locality"
},
  "geometry": {"coordinates":[99.4162,3.1353],"type":"Point"}
}