{
  "type": "Feature",
  "properties": {
    "gn:admin1_code":"8",
    "gn:asciiname":"Tamansarikrajan",
    "gn:country_code":"ID",
    "gn:dem":138,
    "gn:feature_class":"P",
    "gn:feature_code":"PPL",
    "gn:name":"Tamansarikrajan",
    "gn:population":0,
    "gn:timezone":"Asia/Jakarta",
    "iso:country":"ID",
    "name:ind_x_preferred":[
        "Tamansarikrajan"
    ],
    "wof:name":"Tamansarikrajan",
    "wof:placetype":"locality"
},
  "geometry": {"coordinates":[112.77209999999999,-7.7245],"type":"Point"}
}