{
  "type": "Feature",
  "properties": {
    "gn:admin1_code":"39.0",
    "gn:asciiname":"Sewarre",
    "gn:country_code":"ID",
    "gn:dem":110,
    "gn:feature_class":"P",
    "gn:feature_code":"PPL",
    "gn:name":"Sewarre",
    "gn:population":0,
    "gn:timezone":"Asia/Jayapura",
    "iso:country":"ID",
    "name:ind_x_preferred":[
        "Sewarre"
    ],
    "wof:name":"Sewarre",
    "wof:placetype":"locality"
},
  "geometry": {"coordinates":[133.3742,-3.1224],"type":"Point"}
}