{
  "type": "Feature",
  "properties": {
    "gn:admin1_code":"8.0",
    "gn:asciiname":"Sentul Utara",
    "gn:country_code":"ID",
    "gn:dem":6,
    "gn:feature_class":"P",
    "gn:feature_code":"PPL",
    "gn:name":"Sentul Utara",
    "gn:population":0,
    "gn:timezone":"Asia/Jakarta",
    "iso:country":"ID",
    "name:ind_x_preferred":[
        "Sentul Utara"
    ],
    "wof:name":"Sentul Utara",
    "wof:placetype":"locality"
},
  "geometry": {"coordinates":[112.73699999999999,-7.524],"type":"Point"}
}