{
  "type": "Feature",
  "properties": {
    "gn:admin1_code":"17",
    "gn:asciiname":"Montonglekong",
    "gn:country_code":"ID",
    "gn:dem":339,
    "gn:feature_class":"P",
    "gn:feature_code":"PPL",
    "gn:name":"Montonglekong",
    "gn:population":0,
    "gn:timezone":"Asia/Makassar",
    "iso:country":"ID",
    "name:ind_x_preferred":[
        "Montonglekong"
    ],
    "wof:name":"Montonglekong",
    "wof:placetype":"locality"
},
  "geometry": {"coordinates":[116.36750000000001,-8.6616],"type":"Point"}
}