{
  "type": "Feature",
  "properties": {
    "gn:admin1_code":"8",
    "gn:asciiname":"Kebonrejo",
    "gn:country_code":"ID",
    "gn:dem":84,
    "gn:feature_class":"P",
    "gn:feature_code":"PPL",
    "gn:name":"Kebonrejo",
    "gn:population":0,
    "gn:timezone":"Asia/Jakarta",
    "iso:country":"ID",
    "name:ind_x_preferred":[
        "Kebonrejo"
    ],
    "wof:name":"Kebonrejo",
    "wof:placetype":"locality"
},
  "geometry": {"coordinates":[114.1323,-8.4847],"type":"Point"}
}