{
  "type": "Feature",
  "properties": {
    "gn:admin1_code":"36.0",
    "gn:asciiname":"Kumopa",
    "gn:country_code":"ID",
    "gn:dem":2450,
    "gn:feature_class":"P",
    "gn:feature_code":"PPLA3",
    "gn:name":"Kumopa",
    "gn:population":0,
    "gn:timezone":"Asia/Jayapura",
    "iso:country":"ID",
    "name:ind_x_preferred":[
        "Kumopa"
    ],
    "wof:name":"Kumopa",
    "wof:placetype":"locality"
},
  "geometry": {"coordinates":[136.50919999999999,-3.8216],"type":"Point"}
}