{
  "type": "Feature",
  "properties": {
    "gn:country":"ID",
    "gn:fcode":"PPL",
    "gn:pop":93420,
    "iso:country":"ID",
    "name:ast_x_preferred":[
        "Cibenda"
    ],
    "name:ban_x_preferred":[
        "Sumber"
    ],
    "name:ceb_x_preferred":[
        "Kecamatan Sumber"
    ],
    "name:deu_x_preferred":[
        "Sumber"
    ],
    "name:eng_x_preferred":[
        "Sumber"
    ],
    "name:fas_x_preferred":[
        "\u0633\u0648\u0645\u0628\u0631"
    ],
    "name:fra_x_preferred":[
        "Sumber"
    ],
    "name:ind_x_preferred":[
        "Sumber"
    ],
    "name:jav_x_preferred":[
        "Sumber"
    ],
    "name:jpn_x_preferred":[
        "\u30b9\u30f3\u30d0\u30fc"
    ],
    "name:mlg_x_preferred":[
        "Sumber"
    ],
    "name:nan_x_preferred":[
        "Sumber"
    ],
    "name:nld_x_preferred":[
        "Sumber"
    ],
    "name:sun_x_preferred":[
        "Sumber"
    ],
    "name:swe_x_preferred":[
        "Kecamatan Sumber"
    ],
    "name:unk_x_variant":[
        "Soember"
    ],
    "qs:name":"Sumber",
    "qs:name_adm0":"Indonesia",
    "qs:name_adm1":"Jawa Barat",
    "qs:photos_9r":0,
    "qs:photos_sr":0,
    "qs:placetype":"Town",
    "qs:pop_sr":"8",
    "wd:wordcount":18,
    "wof:lang_x_official":[
        "ind"
    ],
    "wof:lang_x_spoken":[
        "ind",
        "eng"
    ],
    "wof:name":"Sumber",
    "wof:placetype":"locality",
    "wof:population":93420
},
  "geometry": {"coordinates":[108.48305999999999,-6.76028],"type":"Point"}
}