{
  "type": "Feature",
  "properties": {
    "gn:admin1_code":"8",
    "gn:asciiname":"Keron",
    "gn:country_code":"ID",
    "gn:dem":461,
    "gn:feature_class":"P",
    "gn:feature_code":"PPL",
    "gn:name":"Keron",
    "gn:population":0,
    "gn:timezone":"Asia/Jakarta",
    "iso:country":"ID",
    "name:ind_x_preferred":[
        "Keron"
    ],
    "name:pol_x_preferred":[
        "Keroun"
    ],
    "wof:lang_x_official":[
        "ind"
    ],
    "wof:lang_x_spoken":[
        "ind",
        "eng"
    ],
    "wof:name":"Keron",
    "wof:placetype":"locality"
},
  "geometry": {"coordinates":[111.62309999999999,-7.8622],"type":"Point"}
}