{
  "type": "Feature",
  "properties": {
    "gn:admin1_code":"8.0",
    "gn:asciiname":"Karangrejan",
    "gn:country_code":"ID",
    "gn:dem":231,
    "gn:feature_class":"P",
    "gn:feature_code":"PPL",
    "gn:name":"Karangrejan",
    "gn:population":0,
    "gn:timezone":"Asia/Jakarta",
    "iso:country":"ID",
    "name:ind_x_preferred":[
        "Karangrejan"
    ],
    "wof:name":"Karangrejan",
    "wof:placetype":"locality"
},
  "geometry": {"coordinates":[112.12690000000001,-7.9198],"type":"Point"}
}