{
  "type": "Feature",
  "properties": {
    "gn:admin1_code":"26.0",
    "gn:asciiname":"Makancar Godang",
    "gn:country_code":"ID",
    "gn:dem":594,
    "gn:feature_class":"P",
    "gn:feature_code":"PPL",
    "gn:name":"Makancar Godang",
    "gn:population":0,
    "gn:timezone":"Asia/Jakarta",
    "iso:country":"ID",
    "name:ind_x_preferred":[
        "Makancar Godang"
    ],
    "name:und_x_variant":[
        "Marantjar",
        "Marancar"
    ],
    "wof:lang_x_official":[
        "ind"
    ],
    "wof:lang_x_spoken":[
        "ind",
        "eng"
    ],
    "wof:name":"Makancar Godang",
    "wof:placetype":"locality"
},
  "geometry": {"coordinates":[99.16842,1.5189],"type":"Point"}
}