{
  "type": "Feature",
  "properties": {
    "gn:admin1_code":"8.0",
    "gn:asciiname":"Jurak Lao'",
    "gn:country_code":"ID",
    "gn:dem":133,
    "gn:feature_class":"P",
    "gn:feature_code":"PPLA4",
    "gn:name":"Jurak Lao\u2019",
    "gn:population":0,
    "gn:timezone":"Asia/Jakarta",
    "iso:country":"ID",
    "name:ind_x_preferred":[
        "Jurak Lao\u2019"
    ],
    "wof:name":"Jurak Lao'",
    "wof:placetype":"locality"
},
  "geometry": {"coordinates":[113.9572,-6.907],"type":"Point"}
}