{
  "type": "Feature",
  "properties": {
    "gn:admin1_code":"1",
    "gn:asciiname":"Lhee",
    "gn:country_code":"ID",
    "gn:dem":17,
    "gn:feature_class":"P",
    "gn:feature_code":"PPL",
    "gn:name":"Lhee",
    "gn:population":0,
    "gn:timezone":"Asia/Jakarta",
    "iso:country":"ID",
    "name:fra_x_preferred":[
        "Lhee"
    ],
    "name:ind_x_preferred":[
        "Lhee"
    ],
    "name:nld_x_preferred":[
        "Lhee"
    ],
    "name:por_x_preferred":[
        "Lhee"
    ],
    "wof:lang_x_official":[
        "ind"
    ],
    "wof:lang_x_spoken":[
        "ind",
        "eng"
    ],
    "wof:name":"Lhee",
    "wof:placetype":"locality"
},
  "geometry": {"coordinates":[95.9171,5.3388],"type":"Point"}
}