{
  "type": "Feature",
  "properties": {
    "gn:admin1_code":"7",
    "gn:asciiname":"Wotglinggang Kulon",
    "gn:country_code":"ID",
    "gn:dem":387,
    "gn:feature_class":"P",
    "gn:feature_code":"PPL",
    "gn:name":"Wotglinggang Kulon",
    "gn:population":0,
    "gn:timezone":"Asia/Jakarta",
    "iso:country":"ID",
    "name:ind_x_preferred":[
        "Wotglinggang Kulon"
    ],
    "wof:name":"Wotglinggang Kulon",
    "wof:placetype":"locality"
},
  "geometry": {"coordinates":[111.23,-7.84],"type":"Point"}
}