{
  "type": "Feature",
  "properties": {
    "gn:admin1_code":"0.0",
    "gn:asciiname":"Kepalacurup",
    "gn:cc2":"ID",
    "gn:country_code":"ID",
    "gn:dem":565,
    "gn:feature_class":"P",
    "gn:feature_code":"PPL",
    "gn:name":"Kepalacurup",
    "gn:population":0,
    "gn:timezone":"Asia/Jakarta",
    "iso:country":"ID",
    "name:und_x_variant":[
        "Kapalatjoeroep",
        "Kepalatjoeroep",
        "Kepalatjurup",
        "Kepalacurup"
    ],
    "wof:lang_x_official":[
        "ind"
    ],
    "wof:lang_x_spoken":[
        "ind",
        "eng"
    ],
    "wof:name":"Kepalacurup",
    "wof:placetype":"locality"
},
  "geometry": {"coordinates":[102.73333,-3.45],"type":"Point"}
}