{
  "type": "Feature",
  "properties": {
    "gn:admin1_code":"30",
    "gn:asciiname":"Sukaasih",
    "gn:country_code":"ID",
    "gn:dem":308,
    "gn:feature_class":"P",
    "gn:feature_code":"PPL",
    "gn:name":"Sukaasih",
    "gn:population":0,
    "gn:timezone":"Asia/Jakarta",
    "iso:country":"ID",
    "name:ind_x_preferred":[
        "Sukaasih"
    ],
    "wof:name":"Sukaasih",
    "wof:placetype":"locality"
},
  "geometry": {"coordinates":[108.02722,-6.76111],"type":"Point"}
}