{
  "type": "Feature",
  "properties": {
    "gn:admin1_code":"22.0",
    "gn:asciiname":"Batumea",
    "gn:country_code":"ID",
    "gn:dem":21,
    "gn:feature_class":"P",
    "gn:feature_code":"PPL",
    "gn:name":"Batumea",
    "gn:population":0,
    "gn:timezone":"Asia/Makassar",
    "iso:country":"ID",
    "name:ind_x_preferred":[
        "Batumea"
    ],
    "name:und_x_variant":[
        "Watoenea",
        "Batoemea",
        "Watunea",
        "Watoemea"
    ],
    "wof:name":"Batumea",
    "wof:placetype":"locality"
},
  "geometry": {"coordinates":[122.94289999999999,-4.0759],"type":"Point"}
}