{
  "type": "Feature",
  "properties": {
    "gn:admin1_code":"15.0",
    "gn:asciiname":"Batukebayan Dua",
    "gn:country_code":"ID",
    "gn:dem":929,
    "gn:feature_class":"P",
    "gn:feature_code":"PPL",
    "gn:name":"Batukebayan Dua",
    "gn:population":0,
    "gn:timezone":"Asia/Jakarta",
    "iso:country":"ID",
    "name:ind_x_preferred":[
        "Batukebayan Dua"
    ],
    "name:und_x_variant":[
        "Batukebayan 2"
    ],
    "wof:lang_x_official":[
        "ind"
    ],
    "wof:lang_x_spoken":[
        "ind",
        "eng"
    ],
    "wof:name":"Batukebayan Dua",
    "wof:placetype":"locality"
},
  "geometry": {"coordinates":[104.23416,-5.02599],"type":"Point"}
}