{
  "type": "Feature",
  "properties": {
    "gn:admin1_code":"7",
    "gn:asciiname":"Wonokambang",
    "gn:country_code":"ID",
    "gn:dem":716,
    "gn:feature_class":"P",
    "gn:feature_code":"PPL",
    "gn:name":"Wonokambang",
    "gn:population":0,
    "gn:timezone":"Asia/Jakarta",
    "iso:country":"ID",
    "name:ind_x_preferred":[
        "Wonokambang"
    ],
    "wof:name":"Wonokambang",
    "wof:placetype":"locality"
},
  "geometry": {"coordinates":[109.96810000000001,-7.0993],"type":"Point"}
}