{
  "type": "Feature",
  "properties": {
    "gn:admin1_code":"7.0",
    "gn:asciiname":"Dowakan",
    "gn:country_code":"ID",
    "gn:dem":421,
    "gn:feature_class":"P",
    "gn:feature_code":"PPL",
    "gn:name":"Dowakan",
    "gn:population":0,
    "gn:timezone":"Asia/Jakarta",
    "iso:country":"ID",
    "wof:name":"Dowakan",
    "wof:placetype":"locality"
},
  "geometry": {"coordinates":[110.31471999999999,-7.60028],"type":"Point"}
}