{
  "type": "Feature",
  "properties": {
    "gn:admin1_code":"34",
    "gn:asciiname":"Hutabohu Tengah",
    "gn:country_code":"ID",
    "gn:dem":15,
    "gn:feature_class":"P",
    "gn:feature_code":"PPL",
    "gn:name":"Hutabohu Tengah",
    "gn:population":0,
    "gn:timezone":"Asia/Makassar",
    "iso:country":"ID",
    "name:ind_x_preferred":[
        "Hutabohu Tengah"
    ],
    "wof:name":"Hutabohu Tengah",
    "wof:placetype":"locality"
},
  "geometry": {"coordinates":[122.91419999999999,0.6237],"type":"Point"}
}