{
  "type": "Feature",
  "properties": {
    "gn:admin1_code":"2",
    "gn:asciiname":"Banjar Bangkilesan",
    "gn:country_code":"ID",
    "gn:dem":141,
    "gn:feature_class":"P",
    "gn:feature_code":"PPL",
    "gn:name":"Banjar Bangkilesan",
    "gn:population":0,
    "gn:timezone":"Asia/Makassar",
    "iso:country":"ID",
    "name:ind_x_preferred":[
        "Banjar Bangkilesan"
    ],
    "wof:name":"Banjar Bangkilesan",
    "wof:placetype":"locality"
},
  "geometry": {"coordinates":[115.26779999999999,-8.5476],"type":"Point"}
}