{
  "type": "Feature",
  "properties": {
    "gn:admin1_code":"26",
    "gn:asciiname":"Tiram",
    "gn:country_code":"ID",
    "gn:dem":11,
    "gn:feature_class":"P",
    "gn:feature_code":"PPL",
    "gn:name":"Tiram",
    "gn:population":0,
    "gn:timezone":"Asia/Jakarta",
    "iso:country":"ID",
    "name:ind_x_preferred":[
        "Tiram"
    ],
    "name:mai_x_preferred":[
        "\u0924\u093f\u0930\u093e\u092e"
    ],
    "name:msa_x_preferred":[
        "Tiram"
    ],
    "name:nep_x_preferred":[
        "\u0924\u093f\u0930\u093e\u092e"
    ],
    "name:new_x_preferred":[
        "\u0924\u093f\u0930\u093e\u092e"
    ],
    "name:pol_x_preferred":[
        "Tiram"
    ],
    "wof:lang_x_official":[
        "ind"
    ],
    "wof:lang_x_spoken":[
        "ind",
        "eng"
    ],
    "wof:name":"Tiram",
    "wof:placetype":"locality"
},
  "geometry": {"coordinates":[98.1925,4.1022],"type":"Point"}
}