{
  "type": "Feature",
  "properties": {
    "gn:admin1_code":"8.0",
    "gn:asciiname":"Polay Barat",
    "gn:country_code":"ID",
    "gn:dem":139,
    "gn:feature_class":"P",
    "gn:feature_code":"PPL",
    "gn:name":"Polay Barat",
    "gn:population":0,
    "gn:timezone":"Asia/Jakarta",
    "iso:country":"ID",
    "name:ind_x_preferred":[
        "Polay Barat"
    ],
    "wof:name":"Polay Barat",
    "wof:placetype":"locality"
},
  "geometry": {"coordinates":[113.7132,-7.0135],"type":"Point"}
}