{
  "type": "Feature",
  "properties": {
    "gn:admin1_code":"28.0",
    "gn:asciiname":"Pika",
    "gn:country_code":"ID",
    "gn:dem":13,
    "gn:feature_class":"P",
    "gn:feature_code":"PPL",
    "gn:name":"Pika",
    "gn:population":0,
    "gn:timezone":"Asia/Jayapura",
    "iso:country":"ID",
    "name:ara_x_preferred":[
        "\u0628\u064a\u0643\u0627"
    ],
    "name:ast_x_preferred":[
        "Ochotona"
    ],
    "name:bod_x_preferred":[
        "\u0f68\u0f0b\u0f56\u0fb2\u0f0b\u0f61\u0f44\u0f0b\u0f53\u0f0b\u0f68\u0f56\u0f0b\u0f62\u0f0d"
    ],
    "name:bre_x_preferred":[
        "Pika"
    ],
    "name:bul_x_preferred":[
        "\u0421\u0435\u043d\u043e\u0441\u044a\u0431\u0438\u0440\u0430\u0447\u0438"
    ],
    "name:cat_x_preferred":[
        "Pica"
    ],
    "name:ceb_x_preferred":[
        "Ochotona"
    ],
    "name:cym_x_preferred":[
        "Pica"
    ],
    "name:dan_x_preferred":[
        "Pibeharer"
    ],
    "name:deu_x_preferred":[
        "Pfeifhasen"
    ],
    "name:fas_x_preferred":[
        "\u062e\u0631\u06af\u0648\u0634 \u0628\u06cc\u200c\u062f\u0645"
    ],
    "name:fra_x_preferred":[
        "Ochotona"
    ],
    "name:glg_x_preferred":[
        "Ochotona"
    ],
    "name:heb_x_preferred":[
        "\u05e4\u05d9\u05e7\u05ea\u05d9\u05d9\u05dd"
    ],
    "name:hrv_x_preferred":[
        "Zvi\u017edari"
    ],
    "name:ind_x_preferred":[
        "Pika"
    ],
    "name:isl_x_preferred":[
        "M\u00fash\u00e9ri"
    ],
    "name:ita_x_preferred":[
        "Ochotona"
    ],
    "name:jpn_x_preferred":[
        "\u30ca\u30ad\u30a6\u30b5\u30ae"
    ],
    "name:kab_x_preferred":[
        "Pika"
    ],
    "name:kaz_x_preferred":[
        "\u0428\u0430\u049b\u044b\u043b\u0434\u0430\u049b\u0442\u0430\u0440"
    ],
    "name:kor_x_preferred":[
        "\uc6b0\ub294\ud1a0\ub07c\uacfc"
    ],
    "name:lav_x_preferred":[
        "Svilp\u0113jza\u0137i"
    ],
    "name:lit_x_preferred":[
        "Ki\u0161k\u0117nai"
    ],
    "name:mkd_x_preferred":[
        "\u041f\u0438\u043a\u0430"
    ],
    "name:mlt_x_preferred":[
        "Pika"
    ],
    "name:msa_x_preferred":[
        "Pika"
    ],
    "name:nav_x_preferred":[
        "Ts\u00e9tah gah"
    ],
    "name:nld_x_preferred":[
        "Fluithazen"
    ],
    "name:nor_x_preferred":[
        "Pipeharer"
    ],
    "name:pnb_x_preferred":[
        "\u067e\u0627\u0626\u06cc\u06a9\u0627"
    ],
    "name:pol_x_preferred":[
        "Szczekuszkowate"
    ],
    "name:por_x_preferred":[
        "Ochotona"
    ],
    "name:ron_x_preferred":[
        "Ursui"
    ],
    "name:rus_x_preferred":[
        "\u041f\u0438\u0449\u0443\u0445\u0438"
    ],
    "name:slv_x_preferred":[
        "\u017dvi\u017ega\u010di"
    ],
    "name:spa_x_preferred":[
        "Ochotona"
    ],
    "name:srp_x_preferred":[
        "\u041f\u0438\u043a\u0435"
    ],
    "name:swe_x_preferred":[
        "Pipharar"
    ],
    "name:tat_x_preferred":[
        "\u0427\u044b\u0435\u043b\u0434\u044b\u043a\u043b\u0430\u0440"
    ],
    "name:tgl_x_preferred":[
        "Pika"
    ],
    "name:tha_x_preferred":[
        "\u0e44\u0e1e\u0e01\u0e32"
    ],
    "name:tur_x_preferred":[
        "Isl\u0131kl\u0131 tav\u015fangiller"
    ],
    "name:ukr_x_preferred":[
        "\u041f\u0438\u0441\u043a\u0443\u0445\u0430"
    ],
    "name:vie_x_preferred":[
        "Ochotona"
    ],
    "name:war_x_preferred":[
        "Ochotona"
    ],
    "name:wln_x_preferred":[
        "Live xhufleu"
    ],
    "wof:lang_x_official":[
        "ind"
    ],
    "wof:lang_x_spoken":[
        "ind",
        "eng"
    ],
    "wof:name":"Pika",
    "wof:placetype":"locality"
},
  "geometry": {"coordinates":[127.94276000000001,-3.53591],"type":"Point"}
}