{
  "type": "Feature",
  "properties": {
    "gn:admin1_code":"28.0",
    "gn:asciiname":"Pika",
    "gn:country_code":"ID",
    "gn:dem":13,
    "gn:feature_class":"P",
    "gn:feature_code":"PPL",
    "gn:name":"Pika",
    "gn:population":0,
    "gn:timezone":"Asia/Jayapura",
    "iso:country":"ID",
    "name:ind_x_preferred":[
        "Pika"
    ],
    "wof:name":"Pika",
    "wof:placetype":"locality"
},
  "geometry": {"coordinates":[127.94276000000001,-3.53591],"type":"Point"}
}