{
  "type": "Feature",
  "properties": {
    "gn:admin1_code":"8.0",
    "gn:asciiname":"Mulyosari",
    "gn:country_code":"ID",
    "gn:dem":409,
    "gn:feature_class":"P",
    "gn:feature_code":"PPL",
    "gn:name":"Mulyosari",
    "gn:population":0,
    "gn:timezone":"Asia/Jakarta",
    "iso:country":"ID",
    "name:ind_x_preferred":[
        "Mulyosari"
    ],
    "wof:name":"Mulyosari",
    "wof:placetype":"locality"
},
  "geometry": {"coordinates":[111.8047,-7.987],"type":"Point"}
}