{
  "type": "Feature",
  "properties": {
    "gn:admin1_code":"7",
    "gn:asciiname":"Bancak Kulon",
    "gn:country_code":"ID",
    "gn:dem":160,
    "gn:feature_class":"P",
    "gn:feature_code":"PPL",
    "gn:name":"Bancak Kulon",
    "gn:population":0,
    "gn:timezone":"Asia/Jakarta",
    "iso:country":"ID",
    "name:ind_x_preferred":[
        "Bancak Kulon"
    ],
    "wof:name":"Bancak Kulon",
    "wof:placetype":"locality"
},
  "geometry": {"coordinates":[110.9783,-6.5592],"type":"Point"}
}