{
  "type": "Feature",
  "properties": {
    "gn:admin1_code":"30",
    "gn:asciiname":"Tenggelar",
    "gn:country_code":"ID",
    "gn:dem":3,
    "gn:feature_class":"P",
    "gn:feature_code":"PPL",
    "gn:name":"Tenggelar",
    "gn:population":0,
    "gn:timezone":"Asia/Jakarta",
    "iso:country":"ID",
    "name:ind_x_preferred":[
        "Tenggelar"
    ],
    "wof:name":"Tenggelar",
    "wof:placetype":"locality"
},
  "geometry": {"coordinates":[108.5842,-6.7551],"type":"Point"}
}