{
  "type": "Feature",
  "properties": {
    "gn:admin1_code":"26",
    "gn:asciiname":"Alamentonor",
    "gn:country_code":"ID",
    "gn:dem":52,
    "gn:feature_class":"P",
    "gn:feature_code":"PPL",
    "gn:name":"Alamentonor",
    "gn:population":0,
    "gn:timezone":"Asia/Jakarta",
    "iso:country":"ID",
    "name:ind_x_preferred":[
        "Alamentonor"
    ],
    "wof:name":"Alamentonor",
    "wof:placetype":"locality"
},
  "geometry": {"coordinates":[99.06708999999999,1.42388],"type":"Point"}
}