{
  "type": "Feature",
  "properties": {
    "gn:admin1_code":"7.0",
    "gn:asciiname":"Sawangan",
    "gn:country_code":"ID",
    "gn:dem":45,
    "gn:feature_class":"P",
    "gn:feature_code":"PPL",
    "gn:name":"Sawangan",
    "gn:population":0,
    "gn:timezone":"Asia/Jakarta",
    "iso:country":"ID",
    "name:bjn_x_preferred":[
        "Sawangan"
    ],
    "name:fas_x_preferred":[
        "\u0633\u0627\u0648\u0646\u06af\u0646"
    ],
    "name:ind_x_preferred":[
        "Sawangan"
    ],
    "name:jav_x_preferred":[
        "Sawangan"
    ],
    "name:mlg_x_preferred":[
        "Sawangan"
    ],
    "name:sun_x_preferred":[
        "Sawangan"
    ],
    "wof:name":"Sawangan",
    "wof:placetype":"locality"
},
  "geometry": {"coordinates":[108.798,-7.4471],"type":"Point"}
}