{
  "type": "Feature",
  "properties": {
    "gn:admin1_code":"7.0",
    "gn:asciiname":"Gasing",
    "gn:country_code":"ID",
    "gn:dem":25,
    "gn:feature_class":"P",
    "gn:feature_code":"PPL",
    "gn:name":"Gasing",
    "gn:population":0,
    "gn:timezone":"Asia/Jakarta",
    "iso:country":"ID",
    "name:ind_x_preferred":[
        "Gasing"
    ],
    "wof:name":"Gasing",
    "wof:placetype":"locality"
},
  "geometry": {"coordinates":[111.05929999999999,-6.629],"type":"Point"}
}