{
  "type": "Feature",
  "properties": {
    "gn:admin1_code":"2",
    "gn:asciiname":"Tangguwisia",
    "gn:country_code":"ID",
    "gn:dem":28,
    "gn:feature_class":"P",
    "gn:feature_code":"PPLA4",
    "gn:name":"Tangguwisia",
    "gn:population":0,
    "gn:timezone":"Asia/Makassar",
    "iso:country":"ID",
    "name:ind_x_preferred":[
        "Tangguwisia"
    ],
    "wof:name":"Tangguwisia",
    "wof:placetype":"locality"
},
  "geometry": {"coordinates":[114.9466,-8.1976],"type":"Point"}
}