{
  "type": "Feature",
  "properties": {
    "gn:admin1_code":"34",
    "gn:asciiname":"Teladan",
    "gn:country_code":"ID",
    "gn:dem":30,
    "gn:feature_class":"P",
    "gn:feature_code":"PPL",
    "gn:name":"Teladan",
    "gn:population":0,
    "gn:timezone":"Asia/Makassar",
    "iso:country":"ID",
    "name:ind_x_preferred":[
        "Teladan"
    ],
    "wof:name":"Teladan",
    "wof:placetype":"locality"
},
  "geometry": {"coordinates":[122.8738,0.6458],"type":"Point"}
}