{
  "type": "Feature",
  "properties": {
    "gn:admin1_code":"42.0",
    "gn:asciiname":"Naulik",
    "gn:country_code":"ID",
    "gn:dem":287,
    "gn:feature_class":"P",
    "gn:feature_code":"PPL",
    "gn:name":"Naulik",
    "gn:population":0,
    "gn:timezone":"Asia/Makassar",
    "iso:country":"ID",
    "name:und_x_variant":[
        "Naoelik",
        "Naulik"
    ],
    "wof:name":"Naulik",
    "wof:placetype":"locality"
},
  "geometry": {"coordinates":[115.93317,2.51582],"type":"Point"}
}