{
  "type": "Feature",
  "properties": {
    "gn:admin1_code":"7.0",
    "gn:asciiname":"Tulak",
    "gn:country_code":"ID",
    "gn:dem":234,
    "gn:feature_class":"P",
    "gn:feature_code":"PPL",
    "gn:name":"Tulak",
    "gn:population":0,
    "gn:timezone":"Asia/Jakarta",
    "iso:country":"ID",
    "name:fra_x_preferred":[
        "Toulak"
    ],
    "name:ind_x_preferred":[
        "Tulak"
    ],
    "wof:lang_x_official":[
        "ind"
    ],
    "wof:lang_x_spoken":[
        "ind",
        "eng"
    ],
    "wof:name":"Tulak",
    "wof:placetype":"locality"
},
  "geometry": {"coordinates":[109.41667,-7.58278],"type":"Point"}
}