{
  "type": "Feature",
  "properties": {
    "gn:admin1_code":"7.0",
    "gn:asciiname":"Bokor",
    "gn:country_code":"ID",
    "gn:dem":156,
    "gn:feature_class":"P",
    "gn:feature_code":"PPL",
    "gn:name":"Bokor",
    "gn:population":0,
    "gn:timezone":"Asia/Jakarta",
    "iso:country":"ID",
    "name:fra_x_preferred":[
        "Bokor"
    ],
    "name:hat_x_preferred":[
        "B\u00f2k\u00f2"
    ],
    "name:ita_x_preferred":[
        "Bokor"
    ],
    "name:lit_x_preferred":[
        "Bokoras"
    ],
    "name:por_x_preferred":[
        "Bokor"
    ],
    "name:ron_x_preferred":[
        "Bokor"
    ],
    "wof:name":"Bokor",
    "wof:placetype":"locality"
},
  "geometry": {"coordinates":[110.95860999999999,-7.56028],"type":"Point"}
}