{
  "type": "Feature",
  "properties": {
    "gn:admin1_code":"8",
    "gn:asciiname":"Mlaten",
    "gn:country_code":"ID",
    "gn:dem":491,
    "gn:feature_class":"P",
    "gn:feature_code":"PPL",
    "gn:name":"Mlaten",
    "gn:population":0,
    "gn:timezone":"Asia/Jakarta",
    "iso:country":"ID",
    "name:ind_x_preferred":[
        "Mlaten"
    ],
    "wof:name":"Mlaten",
    "wof:placetype":"locality"
},
  "geometry": {"coordinates":[111.6071,-7.9551],"type":"Point"}
}