{
  "type": "Feature",
  "properties": {
    "gn:admin1_code":"29.0",
    "gn:asciiname":"Kolanotombagga",
    "gn:country_code":"ID",
    "gn:dem":607,
    "gn:feature_class":"P",
    "gn:feature_code":"PPL",
    "gn:name":"Kolanotombagga",
    "gn:population":0,
    "gn:timezone":"Asia/Jayapura",
    "iso:country":"ID",
    "name:und_x_variant":[
        "Kolano-Tombanga",
        "Kolanotombagga"
    ],
    "wof:lang_x_official":[
        "ind"
    ],
    "wof:lang_x_spoken":[
        "ind",
        "eng"
    ],
    "wof:name":"Kolanotombagga",
    "wof:placetype":"locality"
},
  "geometry": {"coordinates":[127.38617000000001,0.66991],"type":"Point"}
}