{
  "type": "Feature",
  "properties": {
    "gn:admin1_code":"8.0",
    "gn:asciiname":"Bulung",
    "gn:country_code":"ID",
    "gn:dem":69,
    "gn:feature_class":"P",
    "gn:feature_code":"PPL",
    "gn:name":"Bulung",
    "gn:population":0,
    "gn:timezone":"Asia/Jakarta",
    "iso:country":"ID",
    "name:bih_x_preferred":[
        "\u092c\u0941\u0932\u0941\u0919"
    ],
    "name:ceb_x_preferred":[
        "Bulung"
    ],
    "name:ind_x_preferred":[
        "Bulung"
    ],
    "name:mai_x_preferred":[
        "\u092c\u0941\u0932\u0941\u0919"
    ],
    "name:msa_x_preferred":[
        "Bulung"
    ],
    "name:nep_x_preferred":[
        "\u092c\u0941\u0932\u0941\u0919"
    ],
    "name:new_x_preferred":[
        "\u092c\u0941\u0932\u0941\u0919\u094d\u0917"
    ],
    "name:pol_x_preferred":[
        "Bulung"
    ],
    "wof:lang_x_official":[
        "ind"
    ],
    "wof:lang_x_spoken":[
        "ind",
        "eng"
    ],
    "wof:name":"Bulung",
    "wof:placetype":"locality"
},
  "geometry": {"coordinates":[111.8516,-7.5914],"type":"Point"}
}