{
  "type": "Feature",
  "properties": {
    "gn:admin1_code":"26",
    "gn:asciiname":"Namobelang",
    "gn:country_code":"ID",
    "gn:dem":110,
    "gn:feature_class":"P",
    "gn:feature_code":"PPL",
    "gn:name":"Namobelang",
    "gn:population":0,
    "gn:timezone":"Asia/Jakarta",
    "iso:country":"ID",
    "name:ind_x_preferred":[
        "Namobelang"
    ],
    "wof:name":"Namobelang",
    "wof:placetype":"locality"
},
  "geometry": {"coordinates":[98.3202,3.4483],"type":"Point"}
}