{
  "type": "Feature",
  "properties": {
    "gn:admin1_code":"38",
    "gn:asciiname":"Baku",
    "gn:country_code":"ID",
    "gn:dem":836,
    "gn:feature_class":"P",
    "gn:feature_code":"PPL",
    "gn:name":"Baku",
    "gn:population":0,
    "gn:timezone":"Asia/Makassar",
    "iso:country":"ID",
    "name:ind_x_preferred":[
        "Baku"
    ],
    "wof:name":"Baku",
    "wof:placetype":"locality"
},
  "geometry": {"coordinates":[119.79900000000001,-3.0274],"type":"Point"}
}