{
  "type": "Feature",
  "properties": {
    "gn:admin1_code":"31.0",
    "gn:asciiname":"Nonapan Satu",
    "gn:country_code":"ID",
    "gn:dem":5,
    "gn:feature_class":"P",
    "gn:feature_code":"PPL",
    "gn:name":"Nonapan Satu",
    "gn:population":0,
    "gn:timezone":"Asia/Makassar",
    "iso:country":"ID",
    "name:ind_x_preferred":[
        "Nonapan Satu"
    ],
    "name:und_x_variant":[
        "Nonapan",
        "Nonopan",
        "Nonapan 1"
    ],
    "wof:lang_x_official":[
        "ind"
    ],
    "wof:lang_x_spoken":[
        "ind",
        "eng"
    ],
    "wof:name":"Nonapan Satu",
    "wof:placetype":"locality"
},
  "geometry": {"coordinates":[124.24687,0.9838],"type":"Point"}
}