{
  "type": "Feature",
  "properties": {
    "gn:admin1_code":"30",
    "gn:asciiname":"Sadarayna",
    "gn:country_code":"ID",
    "gn:dem":749,
    "gn:feature_class":"P",
    "gn:feature_code":"PPL",
    "gn:name":"Sadarayna",
    "gn:population":0,
    "gn:timezone":"Asia/Jakarta",
    "iso:country":"ID",
    "name:ind_x_preferred":[
        "Sadarayna"
    ],
    "wof:name":"Sadarayna",
    "wof:placetype":"locality"
},
  "geometry": {"coordinates":[107.98361,-6.90667],"type":"Point"}
}