{
  "type": "Feature",
  "properties": {
    "gn:admin1_code":"30",
    "gn:asciiname":"Cibuntu",
    "gn:country_code":"ID",
    "gn:dem":332,
    "gn:feature_class":"P",
    "gn:feature_code":"PPL",
    "gn:name":"Cibuntu",
    "gn:population":0,
    "gn:timezone":"Asia/Jakarta",
    "iso:country":"ID",
    "name:ind_x_preferred":[
        "Cibuntu"
    ],
    "name:und_x_variant":[
        "Tjibuntu"
    ],
    "wof:name":"Cibuntu",
    "wof:placetype":"locality"
},
  "geometry": {"coordinates":[107.32083,-6.86806],"type":"Point"}
}