{
  "type": "Feature",
  "properties": {
    "gn:admin1_code":"30.0",
    "gn:asciiname":"Tipar",
    "gn:country_code":"ID",
    "gn:dem":533,
    "gn:feature_class":"P",
    "gn:feature_code":"PPL",
    "gn:name":"Tipar",
    "gn:population":0,
    "gn:timezone":"Asia/Jakarta",
    "iso:country":"ID",
    "name:ind_x_preferred":[
        "Tipar"
    ],
    "wof:name":"Tipar",
    "wof:placetype":"locality"
},
  "geometry": {"coordinates":[107.4716,-7.342],"type":"Point"}
}