{
  "type": "Feature",
  "properties": {
    "gn:admin1_code":"15.0",
    "gn:asciiname":"Talang Kayuhujan",
    "gn:country_code":"ID",
    "gn:dem":156,
    "gn:feature_class":"P",
    "gn:feature_code":"PPL",
    "gn:name":"Talang Kayuhujan",
    "gn:population":0,
    "gn:timezone":"Asia/Jakarta",
    "iso:country":"ID",
    "name:ind_x_preferred":[
        "Talang Kayuhujan"
    ],
    "wof:name":"Talang Kayuhujan",
    "wof:placetype":"locality"
},
  "geometry": {"coordinates":[104.48641000000001,-4.6685],"type":"Point"}
}