{
  "type": "Feature",
  "properties": {
    "gn:admin1_code":"1",
    "gn:asciiname":"Cot Mesjid",
    "gn:country_code":"ID",
    "gn:dem":10,
    "gn:feature_class":"P",
    "gn:feature_code":"PPL",
    "gn:name":"Cot Mesjid",
    "gn:population":0,
    "gn:timezone":"Asia/Jakarta",
    "iso:country":"ID",
    "name:ind_x_preferred":[
        "Cot Mesjid"
    ],
    "wof:name":"Cot Mesjid",
    "wof:placetype":"locality"
},
  "geometry": {"coordinates":[95.33759999999999,5.5344],"type":"Point"}
}