{
  "type": "Feature",
  "properties": {
    "gn:admin1_code":"18.0",
    "gn:asciiname":"Watungiung",
    "gn:country_code":"ID",
    "gn:dem":572,
    "gn:feature_class":"P",
    "gn:feature_code":"PPL",
    "gn:name":"Watungiung",
    "gn:population":0,
    "gn:timezone":"Asia/Makassar",
    "iso:country":"ID",
    "name:ind_x_preferred":[
        "Watungiung"
    ],
    "wof:name":"Watungiung",
    "wof:placetype":"locality"
},
  "geometry": {"coordinates":[120.6617,-8.7402],"type":"Point"}
}