{
  "type": "Feature",
  "properties": {
    "gn:admin1_code":"15.0",
    "gn:asciiname":"Banjarbaru",
    "gn:country_code":"ID",
    "gn:dem":184,
    "gn:feature_class":"P",
    "gn:feature_code":"PPL",
    "gn:name":"Banjarbaru",
    "gn:population":0,
    "gn:timezone":"Asia/Jakarta",
    "iso:country":"ID",
    "name:afr_x_preferred":[
        "Banjarbaru"
    ],
    "name:ara_x_preferred":[
        "\u0628\u0646\u062c\u0627\u0631\u0628\u0627\u0631\u0648"
    ],
    "name:bjn_x_preferred":[
        "Kuta Banjarbaru"
    ],
    "name:bug_x_preferred":[
        "Banjarbaru"
    ],
    "name:fra_x_preferred":[
        "Banjarbaru"
    ],
    "name:ind_x_preferred":[
        "Banjarbaru"
    ],
    "name:ind_x_variant":[
        "Kota Banjarbaru"
    ],
    "name:ita_x_preferred":[
        "Banjarbaru"
    ],
    "name:jav_x_preferred":[
        "Kutha Banjarbaru"
    ],
    "name:kat_x_preferred":[
        "\u10d1\u10d0\u10dc\u10ef\u10d0\u10e0\u10d1\u10d0\u10e0\u10e3"
    ],
    "name:mlg_x_preferred":[
        "Kota Banjarbaru"
    ],
    "name:msa_x_preferred":[
        "Kota Banjarbaru"
    ],
    "name:nld_x_preferred":[
        "Benjarbaru"
    ],
    "name:pol_x_preferred":[
        "Banjarbaru"
    ],
    "name:rus_x_preferred":[
        "\u0411\u0430\u043d\u0434\u0436\u0430\u0440\u0431\u0430\u0440\u0443"
    ],
    "name:swe_x_preferred":[
        "Banjarbaru"
    ],
    "name:tur_x_preferred":[
        "Banjarbaru"
    ],
    "name:urd_x_preferred":[
        "\u0628\u0627\u0646\u062c\u0627\u0631\u0628\u0627\u0631\u0648"
    ],
    "name:zho_x_preferred":[
        "\u73ed\u8d3e\u5c14\u5df4\u9c81"
    ],
    "wof:lang_x_official":[
        "ind"
    ],
    "wof:lang_x_spoken":[
        "ind",
        "eng"
    ],
    "wof:name":"Banjarbaru",
    "wof:placetype":"locality"
},
  "geometry": {"coordinates":[104.53233,-4.77171],"type":"Point"}
}