{
  "type": "Feature",
  "properties": {
    "gn:admin1_code":"15.0",
    "gn:asciiname":"Banjarbaru",
    "gn:country_code":"ID",
    "gn:dem":184,
    "gn:feature_class":"P",
    "gn:feature_code":"PPL",
    "gn:name":"Banjarbaru",
    "gn:population":0,
    "gn:timezone":"Asia/Jakarta",
    "iso:country":"ID",
    "name:ind_x_preferred":[
        "Banjarbaru"
    ],
    "wof:name":"Banjarbaru",
    "wof:placetype":"locality"
},
  "geometry": {"coordinates":[104.53233,-4.77171],"type":"Point"}
}