{
  "type": "Feature",
  "properties": {
    "gn:admin1_code":"7.0",
    "gn:asciiname":"Jengglong Lor",
    "gn:country_code":"ID",
    "gn:dem":138,
    "gn:feature_class":"P",
    "gn:feature_code":"PPL",
    "gn:name":"Jengglong Lor",
    "gn:population":0,
    "gn:timezone":"Asia/Jakarta",
    "iso:country":"ID",
    "wof:name":"Jengglong Lor",
    "wof:placetype":"locality"
},
  "geometry": {"coordinates":[110.87667,-7.32333],"type":"Point"}
}