{
  "type": "Feature",
  "properties": {
    "gn:admin1_code":"15.0",
    "gn:asciiname":"Umbulan Betawi",
    "gn:country_code":"ID",
    "gn:dem":64,
    "gn:feature_class":"P",
    "gn:feature_code":"PPL",
    "gn:name":"Umbulan Betawi",
    "gn:population":0,
    "gn:timezone":"Asia/Jakarta",
    "iso:country":"ID",
    "name:ind_x_preferred":[
        "Umbulan Betawi"
    ],
    "wof:name":"Umbulan Betawi",
    "wof:placetype":"locality"
},
  "geometry": {"coordinates":[105.57908999999999,-5.11861],"type":"Point"}
}