{
  "type": "Feature",
  "properties": {
    "gn:admin1_code":"17.0",
    "gn:asciiname":"Jongat",
    "gn:country_code":"ID",
    "gn:dem":112,
    "gn:feature_class":"P",
    "gn:feature_code":"PPL",
    "gn:name":"Jongat",
    "gn:population":0,
    "gn:timezone":"Asia/Makassar",
    "iso:country":"ID",
    "name:ind_x_preferred":[
        "Jongat"
    ],
    "name:und_x_variant":[
        "Djonggat",
        "Jonggat"
    ],
    "wof:name":"Jongat",
    "wof:placetype":"locality"
},
  "geometry": {"coordinates":[116.2118,-8.6427],"type":"Point"}
}