{
  "type": "Feature",
  "properties": {
    "gn:admin1_code":"7.0",
    "gn:asciiname":"Tangkisan",
    "gn:country_code":"ID",
    "gn:dem":541,
    "gn:feature_class":"P",
    "gn:feature_code":"PPL",
    "gn:name":"Tangkisan",
    "gn:population":0,
    "gn:timezone":"Asia/Jakarta",
    "iso:country":"ID",
    "name:ind_x_preferred":[
        "Tangkisan"
    ],
    "wof:name":"Tangkisan",
    "wof:placetype":"locality"
},
  "geometry": {"coordinates":[109.62888999999998,-7.32778],"type":"Point"}
}