{
  "type": "Feature",
  "properties": {
    "gn:admin1_code":"8.0",
    "gn:asciiname":"Geger",
    "gn:country_code":"ID",
    "gn:dem":67,
    "gn:feature_class":"P",
    "gn:feature_code":"PPL",
    "gn:name":"Geger",
    "gn:population":0,
    "gn:timezone":"Asia/Jakarta",
    "iso:country":"ID",
    "name:ind_x_preferred":[
        "Geger"
    ],
    "name:spa_x_preferred":[
        "Geger"
    ],
    "wof:name":"Geger",
    "wof:placetype":"locality"
},
  "geometry": {"coordinates":[111.503,-7.4055],"type":"Point"}
}