{
  "type": "Feature",
  "properties": {
    "gn:admin1_code":"30",
    "gn:asciiname":"Lampegan",
    "gn:country_code":"ID",
    "gn:dem":822,
    "gn:feature_class":"P",
    "gn:feature_code":"PPL",
    "gn:name":"Lampegan",
    "gn:population":0,
    "gn:timezone":"Asia/Jakarta",
    "iso:country":"ID",
    "name:ind_x_preferred":[
        "Lampegan"
    ],
    "name:und_x_variant":[
        "Lampogan"
    ],
    "wof:lang_x_official":[
        "ind"
    ],
    "wof:lang_x_spoken":[
        "ind",
        "eng"
    ],
    "wof:name":"Lampegan",
    "wof:placetype":"locality"
},
  "geometry": {"coordinates":[107.44777999999999,-6.83694],"type":"Point"}
}