{
  "type": "Feature",
  "properties": {
    "gn:admin1_code":"07",
    "gn:asciiname":"Belo",
    "gn:country_code":"ID",
    "gn:dem":157,
    "gn:feature_class":"P",
    "gn:feature_code":"PPL",
    "gn:name":"Belo",
    "gn:population":0,
    "gn:timezone":"Asia/Jakarta",
    "iso:country":"ID",
    "name:deu_x_preferred":[
        "Belo"
    ],
    "name:ind_x_preferred":[
        "Belo"
    ],
    "name:ita_x_preferred":[
        "Belo"
    ],
    "name:swe_x_preferred":[
        "Belo"
    ],
    "name:und_x_variant":[
        "Belon 1",
        "Belon Satu"
    ],
    "wof:lang_x_official":[
        "ind"
    ],
    "wof:lang_x_spoken":[
        "ind",
        "eng"
    ],
    "wof:name":"Belo",
    "wof:placetype":"locality"
},
  "geometry": {"coordinates":[110.53778,-7.21778],"type":"Point"}
}