{
  "type": "Feature",
  "properties": {
    "gn:admin1_code":"30",
    "gn:asciiname":"Lebaknangka Kulon",
    "gn:country_code":"ID",
    "gn:dem":496,
    "gn:feature_class":"P",
    "gn:feature_code":"PPL",
    "gn:name":"Lebaknangka Kulon",
    "gn:population":0,
    "gn:timezone":"Asia/Jakarta",
    "iso:country":"ID",
    "name:ind_x_preferred":[
        "Lebaknangka Kulon"
    ],
    "wof:name":"Lebaknangka Kulon",
    "wof:placetype":"locality"
},
  "geometry": {"coordinates":[106.75055999999999,-6.89028],"type":"Point"}
}