{
  "type": "Feature",
  "properties": {
    "gn:admin1_code":"7.0",
    "gn:asciiname":"Gempalan",
    "gn:country_code":"ID",
    "gn:dem":433,
    "gn:feature_class":"P",
    "gn:feature_code":"PPL",
    "gn:name":"Gempalan",
    "gn:population":0,
    "gn:timezone":"Asia/Jakarta",
    "iso:country":"ID",
    "name:ind_x_preferred":[
        "Gempalan"
    ],
    "name:und_x_variant":[
        "Gegempalan"
    ],
    "wof:lang_x_official":[
        "ind"
    ],
    "wof:lang_x_spoken":[
        "ind",
        "eng"
    ],
    "wof:name":"Gempalan",
    "wof:placetype":"locality"
},
  "geometry": {"coordinates":[108.72790000000001,-7.2554],"type":"Point"}
}