{
  "type": "Feature",
  "properties": {
    "gn:admin1_code":"32.0",
    "gn:asciiname":"Ulokbuntar",
    "gn:country_code":"ID",
    "gn:dem":44,
    "gn:feature_class":"P",
    "gn:feature_code":"PPL",
    "gn:name":"Ulokbuntar",
    "gn:population":0,
    "gn:timezone":"Asia/Jakarta",
    "iso:country":"ID",
    "name:ind_x_preferred":[
        "Ulokbuntar"
    ],
    "name:und_x_variant":[
        "Oelakboentar",
        "Ulakbuntar"
    ],
    "wof:lang_x_official":[
        "ind"
    ],
    "wof:lang_x_spoken":[
        "ind",
        "eng"
    ],
    "wof:name":"Ulokbuntar",
    "wof:placetype":"locality"
},
  "geometry": {"coordinates":[104.73813,-4.04145],"type":"Point"}
}