{
  "type": "Feature",
  "properties": {
    "gn:admin1_code":"07",
    "gn:asciiname":"Baben",
    "gn:country_code":"ID",
    "gn:dem":160,
    "gn:feature_class":"P",
    "gn:feature_code":"PPL",
    "gn:name":"Baben",
    "gn:population":0,
    "gn:timezone":"Asia/Jakarta",
    "iso:country":"ID",
    "name:bak_x_preferred":[
        "\u0411\u0430\u0431\u0435\u043d"
    ],
    "name:ceb_x_preferred":[
        "Baben"
    ],
    "name:deu_x_preferred":[
        "Baben"
    ],
    "name:epo_x_preferred":[
        "Baben"
    ],
    "name:fas_x_preferred":[
        "\u0628\u0627\u0628\u0646"
    ],
    "name:ita_x_preferred":[
        "Baben"
    ],
    "name:kaz_x_preferred":[
        "\u0411\u0430\u0431\u0435\u043d"
    ],
    "name:kir_x_preferred":[
        "\u0411\u0430\u0431\u0435\u043d"
    ],
    "name:nld_x_preferred":[
        "Baben"
    ],
    "name:ron_x_preferred":[
        "Baben"
    ],
    "name:rus_x_preferred":[
        "\u0411\u0430\u0431\u0435\u043d"
    ],
    "name:uzb_x_preferred":[
        "Baben"
    ],
    "name:vie_x_preferred":[
        "Baben"
    ],
    "name:vol_x_preferred":[
        "Baben"
    ],
    "wof:lang_x_official":[
        "ind"
    ],
    "wof:lang_x_spoken":[
        "ind",
        "eng"
    ],
    "wof:name":"Baben",
    "wof:placetype":"locality"
},
  "geometry": {"coordinates":[110.60917000000001,-7.70444],"type":"Point"}
}