{
  "type": "Feature",
  "properties": {
    "gn:admin1_code":"8.0",
    "gn:asciiname":"Kawal",
    "gn:country_code":"ID",
    "gn:dem":26,
    "gn:feature_class":"P",
    "gn:feature_code":"PPL",
    "gn:name":"Kawal",
    "gn:population":0,
    "gn:timezone":"Asia/Jakarta",
    "iso:country":"ID",
    "name:ind_x_preferred":[
        "Kawal"
    ],
    "name:tam_x_preferred":[
        "\u0b95\u0bb5\u0bbe\u0bb2\u0bcd \u0b95\u0bbf\u0bb0\u0bbe\u0bae\u0bae\u0bcd"
    ],
    "wof:name":"Kawal",
    "wof:placetype":"locality"
},
  "geometry": {"coordinates":[112.6961,-7.2875],"type":"Point"}
}