{
  "type": "Feature",
  "properties": {
    "gn:admin1_code":"26",
    "gn:asciiname":"Limaumungkur Dua",
    "gn:country_code":"ID",
    "gn:dem":6,
    "gn:feature_class":"P",
    "gn:feature_code":"PPL",
    "gn:name":"Limaumungkur Dua",
    "gn:population":0,
    "gn:timezone":"Asia/Jakarta",
    "iso:country":"ID",
    "name:ind_x_preferred":[
        "Limaumungkur Dua"
    ],
    "name:und_x_variant":[
        "Limaumungkur 2"
    ],
    "wof:name":"Limaumungkur Dua",
    "wof:placetype":"locality"
},
  "geometry": {"coordinates":[98.17659999999999,4.2352],"type":"Point"}
}