{
  "type": "Feature",
  "properties": {
    "gn:admin1_code":"26",
    "gn:asciiname":"Helvetia",
    "gn:country_code":"ID",
    "gn:dem":21,
    "gn:feature_class":"P",
    "gn:feature_code":"PPL",
    "gn:name":"Helvetia",
    "gn:population":0,
    "gn:timezone":"Asia/Jakarta",
    "iso:country":"ID",
    "name:als_x_preferred":[
        "Helvetia"
    ],
    "name:ara_x_preferred":[
        "\u0647\u064a\u0644\u0641\u064a\u062a\u064a\u0627"
    ],
    "name:cat_x_preferred":[
        "Helv\u00e8cia"
    ],
    "name:deu_x_preferred":[
        "Helvetia"
    ],
    "name:fin_x_preferred":[
        "Helvetia"
    ],
    "name:fra_x_preferred":[
        "Helvetia"
    ],
    "name:hun_x_preferred":[
        "Helvetia"
    ],
    "name:ind_x_preferred":[
        "Helvetia"
    ],
    "name:ita_x_preferred":[
        "Helvetia"
    ],
    "name:jpn_x_preferred":[
        "\u30d8\u30eb\u30f4\u30a7\u30c6\u30a3\u30a2"
    ],
    "name:kat_x_preferred":[
        "\u10f0\u10d4\u10da\u10d5\u10d4\u10ea\u10d8\u10d0"
    ],
    "name:nld_x_preferred":[
        "Helvetia"
    ],
    "name:nor_x_preferred":[
        "Helvetia"
    ],
    "name:por_x_preferred":[
        "Helv\u00e9cia"
    ],
    "name:rus_x_preferred":[
        "\u0413\u0435\u043b\u044c\u0432\u0435\u0446\u0438\u044f"
    ],
    "name:spa_x_preferred":[
        "Helvetia"
    ],
    "name:swe_x_preferred":[
        "Helvetia"
    ],
    "name:tur_x_preferred":[
        "Helvetia"
    ],
    "name:vie_x_preferred":[
        "Helvetia"
    ],
    "name:zho_x_preferred":[
        "\u8d6b\u5c14\u7ef4\u8482\u5a05"
    ],
    "wof:lang_x_official":[
        "ind"
    ],
    "wof:lang_x_spoken":[
        "ind",
        "eng"
    ],
    "wof:name":"Helvetia",
    "wof:placetype":"locality"
},
  "geometry": {"coordinates":[98.63500000000001,3.6071],"type":"Point"}
}