{
  "type": "Feature",
  "properties": {
    "gn:admin1_code":"26",
    "gn:asciiname":"Helvetia",
    "gn:country_code":"ID",
    "gn:dem":21,
    "gn:feature_class":"P",
    "gn:feature_code":"PPL",
    "gn:name":"Helvetia",
    "gn:population":0,
    "gn:timezone":"Asia/Jakarta",
    "iso:country":"ID",
    "name:ind_x_preferred":[
        "Helvetia"
    ],
    "wof:name":"Helvetia",
    "wof:placetype":"locality"
},
  "geometry": {"coordinates":[98.63500000000001,3.6071],"type":"Point"}
}