{
  "type": "Feature",
  "properties": {
    "gn:admin1_code":"4.0",
    "gn:asciiname":"Rawabunga",
    "gn:country_code":"ID",
    "gn:dem":16,
    "gn:feature_class":"P",
    "gn:feature_code":"PPL",
    "gn:name":"Rawabunga",
    "gn:population":0,
    "gn:timezone":"Asia/Jakarta",
    "iso:country":"ID",
    "name:ind_x_preferred":[
        "Rawabunga"
    ],
    "name:und_x_variant":[
        "Rawabangke"
    ],
    "wof:name":"Rawabunga",
    "wof:placetype":"locality"
},
  "geometry": {"coordinates":[106.87260000000001,-6.2212],"type":"Point"}
}