{
  "type": "Feature",
  "properties": {
    "gn:admin1_code":"33.0",
    "gn:asciiname":"Panacaran",
    "gn:country_code":"ID",
    "gn:dem":69,
    "gn:feature_class":"P",
    "gn:feature_code":"PPLA4",
    "gn:name":"Panacaran",
    "gn:population":0,
    "gn:timezone":"Asia/Jakarta",
    "iso:country":"ID",
    "name:ind_x_preferred":[
        "Panacaran"
    ],
    "name:und_x_variant":[
        "Panatjaran",
        "Panacaran"
    ],
    "wof:lang_x_official":[
        "ind"
    ],
    "wof:lang_x_spoken":[
        "ind",
        "eng"
    ],
    "wof:name":"Panacaran",
    "wof:placetype":"locality"
},
  "geometry": {"coordinates":[105.92400000000001,-6.6606],"type":"Point"}
}