{
  "type": "Feature",
  "properties": {
    "gn:admin1_code":"8",
    "gn:asciiname":"Gunting Lor",
    "gn:country_code":"ID",
    "gn:dem":498,
    "gn:feature_class":"P",
    "gn:feature_code":"PPL",
    "gn:name":"Gunting Lor",
    "gn:population":0,
    "gn:timezone":"Asia/Jakarta",
    "iso:country":"ID",
    "name:ind_x_preferred":[
        "Gunting Lor"
    ],
    "wof:name":"Gunting Lor",
    "wof:placetype":"locality"
},
  "geometry": {"coordinates":[112.7042,-7.8102],"type":"Point"}
}