{
  "type": "Feature",
  "properties": {
    "gn:admin1_code":"7.0",
    "gn:asciiname":"Cilaku",
    "gn:country_code":"ID",
    "gn:dem":84,
    "gn:feature_class":"P",
    "gn:feature_code":"PPL",
    "gn:name":"Cilaku",
    "gn:population":0,
    "gn:timezone":"Asia/Jakarta",
    "iso:country":"ID",
    "name:ind_x_preferred":[
        "Cilaku"
    ],
    "wof:name":"Cilaku",
    "wof:placetype":"locality"
},
  "geometry": {"coordinates":[109.17861000000001,-7.47278],"type":"Point"}
}