{
  "type": "Feature",
  "properties": {
    "gn:admin1_code":"30",
    "gn:asciiname":"Pulotimaha Satu",
    "gn:cc2":"ID",
    "gn:country_code":"ID",
    "gn:dem":11,
    "gn:feature_class":"P",
    "gn:feature_code":"PPL",
    "gn:name":"Pulotimaha Satu",
    "gn:population":0,
    "gn:timezone":"Asia/Jakarta",
    "iso:country":"ID",
    "name:und_x_variant":[
        "Pulotimaha 1",
        "Pulotimaha Satu"
    ],
    "wof:name":"Pulotimaha Satu",
    "wof:placetype":"locality"
},
  "geometry": {"coordinates":[107.1925,-6.20472],"type":"Point"}
}