{
  "type": "Feature",
  "properties": {
    "gn:admin1_code":"40.0",
    "gn:asciiname":"Labuangurab",
    "gn:country_code":"ID",
    "gn:dem":12,
    "gn:feature_class":"P",
    "gn:feature_code":"PPL",
    "gn:name":"Labuangurab",
    "gn:population":0,
    "gn:timezone":"Asia/Jakarta",
    "iso:country":"ID",
    "name:ind_x_preferred":[
        "Labuangurab"
    ],
    "name:und_x_variant":[
        "Labuangurap",
        "Labuangkurab",
        "Laboeangoerab"
    ],
    "wof:lang_x_official":[
        "ind"
    ],
    "wof:lang_x_spoken":[
        "ind",
        "eng"
    ],
    "wof:name":"Labuangurab",
    "wof:placetype":"locality"
},
  "geometry": {"coordinates":[104.14049,1.14654],"type":"Point"}
}