{
  "type": "Feature",
  "properties": {
    "gn:admin1_code":"8.0",
    "gn:asciiname":"Singorejo",
    "gn:country_code":"ID",
    "gn:dem":11,
    "gn:feature_class":"P",
    "gn:feature_code":"PPL",
    "gn:name":"Singorejo",
    "gn:population":0,
    "gn:timezone":"Asia/Jakarta",
    "iso:country":"ID",
    "name:ind_x_preferred":[
        "Singorejo"
    ],
    "name:und_x_variant":[
        "Singapadoe",
        "Singopadoe",
        "Singopadu"
    ],
    "wof:name":"Singorejo",
    "wof:placetype":"locality"
},
  "geometry": {"coordinates":[112.59780000000001,-7.1655],"type":"Point"}
}