{
  "type": "Feature",
  "properties": {
    "gn:admin1_code":"1.0",
    "gn:asciiname":"Pepajungeun",
    "gn:country_code":"ID",
    "gn:dem":962,
    "gn:feature_class":"P",
    "gn:feature_code":"PPL",
    "gn:name":"Pepajungeun",
    "gn:population":0,
    "gn:timezone":"Asia/Jakarta",
    "iso:country":"ID",
    "name:ind_x_preferred":[
        "Pepajungeun"
    ],
    "name:und_x_variant":[
        "Pepajoengiun",
        "Pepajoengeun",
        "P\u0115paj\u014dng\u00f6n",
        "Pepayungeun"
    ],
    "wof:name":"Pepajungeun",
    "wof:placetype":"locality"
},
  "geometry": {"coordinates":[96.7145,4.6327],"type":"Point"}
}