{
  "type": "Feature",
  "properties": {
    "gn:admin1_code":"18.0",
    "gn:asciiname":"Uluwolo",
    "gn:country_code":"ID",
    "gn:dem":41,
    "gn:feature_class":"P",
    "gn:feature_code":"PPLA4",
    "gn:name":"Uluwolo",
    "gn:population":0,
    "gn:timezone":"Asia/Makassar",
    "iso:country":"ID",
    "name:ind_x_preferred":[
        "Uluwolo"
    ],
    "name:und_x_variant":[
        "Oeloe Wolo",
        "Uluwolo"
    ],
    "wof:lang_x_official":[
        "ind"
    ],
    "wof:lang_x_spoken":[
        "ind",
        "eng"
    ],
    "wof:name":"Uluwolo",
    "wof:placetype":"locality"
},
  "geometry": {"coordinates":[121.2908,-8.5753],"type":"Point"}
}