{
  "type": "Feature",
  "properties": {
    "gn:admin1_code":"33.0",
    "gn:asciiname":"Pasirkamarang",
    "gn:country_code":"ID",
    "gn:dem":101,
    "gn:feature_class":"P",
    "gn:feature_code":"PPL",
    "gn:name":"Pasirkamarang",
    "gn:population":0,
    "gn:timezone":"Asia/Jakarta",
    "iso:country":"ID",
    "name:ind_x_preferred":[
        "Pasirkamarang"
    ],
    "wof:name":"Pasirkamarang",
    "wof:placetype":"locality"
},
  "geometry": {"coordinates":[105.9807,-6.4303],"type":"Point"}
}