{
  "type": "Feature",
  "properties": {
    "gn:admin1_code":"1",
    "gn:asciiname":"Tungkogajah",
    "gn:country_code":"ID",
    "gn:dem":12,
    "gn:feature_class":"P",
    "gn:feature_code":"PPL",
    "gn:name":"Tungkogajah",
    "gn:population":0,
    "gn:timezone":"Asia/Jakarta",
    "iso:country":"ID",
    "name:ind_x_preferred":[
        "Tungkogajah"
    ],
    "name:und_x_variant":[
        "Tungkogadjah"
    ],
    "wof:name":"Tungkogajah",
    "wof:placetype":"locality"
},
  "geometry": {"coordinates":[97.8533,4.8475],"type":"Point"}
}