{
  "type": "Feature",
  "properties": {
    "gn:admin1_code":"30",
    "gn:asciiname":"Situhiang",
    "gn:country_code":"ID",
    "gn:dem":1113,
    "gn:feature_class":"P",
    "gn:feature_code":"PPL",
    "gn:name":"Situhiang",
    "gn:population":0,
    "gn:timezone":"Asia/Jakarta",
    "iso:country":"ID",
    "name:ind_x_preferred":[
        "Situhiang"
    ],
    "wof:name":"Situhiang",
    "wof:placetype":"locality"
},
  "geometry": {"coordinates":[107.87778,-6.95639],"type":"Point"}
}