{
  "type": "Feature",
  "properties": {
    "gn:admin1_code":"30",
    "gn:asciiname":"Putraco",
    "gn:country_code":"ID",
    "gn:dem":736,
    "gn:feature_class":"P",
    "gn:feature_code":"PPL",
    "gn:name":"Putraco",
    "gn:population":0,
    "gn:timezone":"Asia/Jakarta",
    "iso:country":"ID",
    "name:ind_x_preferred":[
        "Putraco"
    ],
    "wof:name":"Putraco",
    "wof:placetype":"locality"
},
  "geometry": {"coordinates":[107.8325,-6.95556],"type":"Point"}
}