{
  "type": "Feature",
  "properties": {
    "gn:admin1_code":"21",
    "gn:asciiname":"Tampabatu",
    "gn:country_code":"ID",
    "gn:dem":9,
    "gn:feature_class":"P",
    "gn:feature_code":"PPL",
    "gn:name":"Tampabatu",
    "gn:population":0,
    "gn:timezone":"Asia/Makassar",
    "iso:country":"ID",
    "name:ind_x_preferred":[
        "Tampabatu"
    ],
    "wof:name":"Tampabatu",
    "wof:placetype":"locality"
},
  "geometry": {"coordinates":[121.79179999999999,-0.9652],"type":"Point"}
}