{
  "type": "Feature",
  "properties": {
    "gn:admin1_code":"34.0",
    "gn:asciiname":"Teratai",
    "gn:country_code":"ID",
    "gn:dem":10,
    "gn:feature_class":"P",
    "gn:feature_code":"PPL",
    "gn:name":"Teratai",
    "gn:population":0,
    "gn:timezone":"Asia/Makassar",
    "iso:country":"ID",
    "name:ind_x_preferred":[
        "Teratai"
    ],
    "wof:name":"Teratai",
    "wof:placetype":"locality"
},
  "geometry": {"coordinates":[121.93600000000001,0.4628],"type":"Point"}
}