{
  "type": "Feature",
  "properties": {
    "gn:admin1_code":"30.0",
    "gn:asciiname":"Ciputat",
    "gn:cc2":"ID",
    "gn:country_code":"ID",
    "gn:dem":50,
    "gn:feature_class":"P",
    "gn:feature_code":"PPL",
    "gn:name":"Ciputat",
    "gn:population":0,
    "gn:timezone":"Asia/Jakarta",
    "iso:country":"ID",
    "name:und_x_variant":[
        "Tjiputat",
        "Ciputa",
        "Tjipoetat 1",
        "Ciputat"
    ],
    "wof:name":"Ciputat",
    "wof:placetype":"locality"
},
  "geometry": {"coordinates":[106.7475,-6.31111],"type":"Point"}
}