{
  "type": "Feature",
  "properties": {
    "gn:admin1_code":"41",
    "gn:asciiname":"Magelang",
    "gn:country_code":"ID",
    "gn:dem":12,
    "gn:feature_class":"P",
    "gn:feature_code":"PPL",
    "gn:name":"Magelang",
    "gn:population":0,
    "gn:timezone":"Asia/Makassar",
    "iso:country":"ID",
    "name:ind_x_preferred":[
        "Magelang"
    ],
    "wof:name":"Magelang",
    "wof:placetype":"locality"
},
  "geometry": {"coordinates":[119.2058,-3.4211],"type":"Point"}
}