{
  "type": "Feature",
  "properties": {
    "gn:admin1_code":"41",
    "gn:asciiname":"Magelang",
    "gn:country_code":"ID",
    "gn:dem":12,
    "gn:feature_class":"P",
    "gn:feature_code":"PPL",
    "gn:name":"Magelang",
    "gn:population":0,
    "gn:timezone":"Asia/Makassar",
    "iso:country":"ID",
    "name:afr_x_preferred":[
        "Magelang"
    ],
    "name:ara_x_preferred":[
        "\u0645\u062c\u0644\u0627\u0646\u063a"
    ],
    "name:ceb_x_preferred":[
        "Magelang"
    ],
    "name:ces_x_preferred":[
        "Magelang"
    ],
    "name:deu_x_preferred":[
        "Magelang"
    ],
    "name:fas_x_preferred":[
        "\u0645\u0627\u06af\u0644\u0627\u0646\u06af"
    ],
    "name:fra_x_preferred":[
        "Magelang"
    ],
    "name:hun_x_preferred":[
        "Magelang"
    ],
    "name:ind_x_preferred":[
        "Magelang"
    ],
    "name:ind_x_variant":[
        "Kota Magelang"
    ],
    "name:ita_x_preferred":[
        "Magelang"
    ],
    "name:jav_x_preferred":[
        "Kutha Magelang"
    ],
    "name:jpn_x_preferred":[
        "\u30de\u30b2\u30e9\u30f3"
    ],
    "name:kat_x_preferred":[
        "\u10db\u10d0\u10d2\u10d4\u10da\u10d0\u10dc\u10d2\u10d8"
    ],
    "name:kor_x_preferred":[
        "\ub9c8\uac94\ub791"
    ],
    "name:mlg_x_preferred":[
        "Kota Magelang"
    ],
    "name:nld_x_preferred":[
        "Magelang"
    ],
    "name:nor_x_preferred":[
        "Magelang"
    ],
    "name:pol_x_preferred":[
        "Magelang"
    ],
    "name:por_x_preferred":[
        "Magelang"
    ],
    "name:ron_x_preferred":[
        "Magelang"
    ],
    "name:rus_x_preferred":[
        "\u041c\u0430\u0433\u0435\u043b\u0430\u043d\u0433"
    ],
    "name:spa_x_preferred":[
        "Magelang"
    ],
    "name:sun_x_preferred":[
        "Kota Magelang"
    ],
    "name:swe_x_preferred":[
        "Magelang"
    ],
    "name:tam_x_preferred":[
        "\u0bae\u0b95\u0bb2\u0bbe\u0b99\u0bcd"
    ],
    "name:tha_x_preferred":[
        "\u0e21\u0e32\u0e40\u0e01\u0e2d\u0e25\u0e31\u0e07"
    ],
    "name:tur_x_preferred":[
        "Magelang"
    ],
    "name:urd_x_preferred":[
        "\u0645\u0627\u06af\u06cc\u0644\u0627\u0646\u06af"
    ],
    "name:vie_x_preferred":[
        "Magelang"
    ],
    "name:war_x_preferred":[
        "Magelang"
    ],
    "name:zho_x_preferred":[
        "\u99ac\u683c\u6717"
    ],
    "wof:lang_x_official":[
        "ind"
    ],
    "wof:lang_x_spoken":[
        "ind",
        "eng"
    ],
    "wof:name":"Magelang",
    "wof:placetype":"locality"
},
  "geometry": {"coordinates":[119.2058,-3.4211],"type":"Point"}
}