{
  "type": "Feature",
  "properties": {
    "gn:admin1_code":"1",
    "gn:asciiname":"Drien Coleus",
    "gn:country_code":"ID",
    "gn:dem":15,
    "gn:feature_class":"P",
    "gn:feature_code":"PPL",
    "gn:name":"Drien Coleus",
    "gn:population":0,
    "gn:timezone":"Asia/Jakarta",
    "iso:country":"ID",
    "name:ind_x_preferred":[
        "Drien Coleus"
    ],
    "name:und_x_variant":[
        "Drientjaleu"
    ],
    "wof:name":"Drien Coleus",
    "wof:placetype":"locality"
},
  "geometry": {"coordinates":[96.2299,4.311],"type":"Point"}
}