{
  "type": "Feature",
  "properties": {
    "gn:admin1_code":"1.0",
    "gn:asciiname":"Matang Keulayu",
    "gn:country_code":"ID",
    "gn:dem":5,
    "gn:feature_class":"P",
    "gn:feature_code":"PPL",
    "gn:name":"Matang Keulayu",
    "gn:population":0,
    "gn:timezone":"Asia/Jakarta",
    "iso:country":"ID",
    "name:ind_x_preferred":[
        "Matang Keulayu"
    ],
    "name:und_x_variant":[
        "Matangkeulaju"
    ],
    "wof:name":"Matang Keulayu",
    "wof:placetype":"locality"
},
  "geometry": {"coordinates":[97.3982,5.1662],"type":"Point"}
}