{
  "type": "Feature",
  "properties": {
    "gn:admin1_code":"8",
    "gn:asciiname":"Tambakrejo",
    "gn:country_code":"ID",
    "gn:dem":248,
    "gn:feature_class":"P",
    "gn:feature_code":"PPL",
    "gn:name":"Tambakrejo",
    "gn:population":0,
    "gn:timezone":"Asia/Jakarta",
    "iso:country":"ID",
    "name:ind_x_preferred":[
        "Tambakrejo"
    ],
    "wof:name":"Tambakrejo",
    "wof:placetype":"locality"
},
  "geometry": {"coordinates":[112.3746,-8.1897],"type":"Point"}
}