{
  "type": "Feature",
  "properties": {
    "gn:admin1_code":"17",
    "gn:asciiname":"Mentorok",
    "gn:country_code":"ID",
    "gn:dem":100,
    "gn:feature_class":"P",
    "gn:feature_code":"PPL",
    "gn:name":"Mentorok",
    "gn:population":0,
    "gn:timezone":"Asia/Makassar",
    "iso:country":"ID",
    "name:ind_x_preferred":[
        "Mentorok"
    ],
    "wof:name":"Mentorok",
    "wof:placetype":"locality"
},
  "geometry": {"coordinates":[116.2383,-8.8344],"type":"Point"}
}