{
  "type": "Feature",
  "properties": {
    "gn:admin1_code":"7",
    "gn:asciiname":"Sidokangen",
    "gn:country_code":"ID",
    "gn:dem":1071,
    "gn:feature_class":"P",
    "gn:feature_code":"PPL",
    "gn:name":"Sidokangen",
    "gn:population":0,
    "gn:timezone":"Asia/Jakarta",
    "iso:country":"ID",
    "name:ind_x_preferred":[
        "Sidokangen"
    ],
    "wof:name":"Sidokangen",
    "wof:placetype":"locality"
},
  "geometry": {"coordinates":[109.65472,-7.21806],"type":"Point"}
}