{
  "type": "Feature",
  "properties": {
    "gn:admin1_code":"18.0",
    "gn:asciiname":"Cere",
    "gn:country_code":"ID",
    "gn:dem":217,
    "gn:feature_class":"P",
    "gn:feature_code":"PPL",
    "gn:name":"Cere",
    "gn:population":0,
    "gn:timezone":"Asia/Makassar",
    "iso:country":"ID",
    "name:ces_x_preferred":[
        "Ozob\u00ed"
    ],
    "name:deu_x_preferred":[
        "Wachshaut"
    ],
    "name:epo_x_preferred":[
        "Vaksa\u0135o"
    ],
    "name:fin_x_preferred":[
        "Vahanahka"
    ],
    "name:fra_x_preferred":[
        "Cire"
    ],
    "name:ind_x_preferred":[
        "Cere"
    ],
    "name:pol_x_preferred":[
        "Wosk\u00f3wka"
    ],
    "name:spa_x_preferred":[
        "Cera"
    ],
    "name:swe_x_preferred":[
        "N\u00e4bb#Vaxhud"
    ],
    "wof:lang_x_official":[
        "ind"
    ],
    "wof:lang_x_spoken":[
        "ind",
        "eng"
    ],
    "wof:name":"Cere",
    "wof:placetype":"locality"
},
  "geometry": {"coordinates":[121.6844,-8.3368],"type":"Point"}
}