{
  "type": "Feature",
  "properties": {
    "gn:country":"ID",
    "gn:fcode":"ADM3",
    "gn:pop":0,
    "iso:country":"ID",
    "name:eng_x_preferred":[
        "Districts of South Sulawesi"
    ],
    "name:eng_x_variant":[
        "districts of South Sulawesi"
    ],
    "name:ind_x_preferred":[
        "Kecamatan Wara Utara"
    ],
    "name:unk_x_variant":[
        "Wara Utara"
    ],
    "qs:name":"Kecamatan Wara Utara",
    "qs:photos_9r":0,
    "qs:photos_sr":0,
    "qs:pop_sr":"0",
    "wd:wordcount":717,
    "wof:lang_x_official":[
        "ind"
    ],
    "wof:lang_x_spoken":[
        "ind",
        "eng"
    ],
    "wof:name":"Kecamatan Wara Utara",
    "wof:placetype":"localadmin",
    "wof:population":0
},
  "geometry": {"coordinates":[120.1343,-2.9425],"type":"Point"}
}