{
  "type": "Feature",
  "properties": {
    "gn:admin1_code":"33.0",
    "gn:asciiname":"Cipacungmesjid",
    "gn:country_code":"ID",
    "gn:dem":29,
    "gn:feature_class":"P",
    "gn:feature_code":"PPL",
    "gn:name":"Cipacungmesjid",
    "gn:population":0,
    "gn:timezone":"Asia/Jakarta",
    "iso:country":"ID",
    "name:ind_x_preferred":[
        "Cipacungmesjid"
    ],
    "wof:name":"Cipacungmesjid",
    "wof:placetype":"locality"
},
  "geometry": {"coordinates":[105.85120000000001,-6.1775],"type":"Point"}
}