{
  "type": "Feature",
  "properties": {
    "gn:admin1_code":"30",
    "gn:asciiname":"Situleutik",
    "gn:country_code":"ID",
    "gn:dem":1210,
    "gn:feature_class":"P",
    "gn:feature_code":"PPL",
    "gn:name":"Situleutik",
    "gn:population":0,
    "gn:timezone":"Asia/Jakarta",
    "iso:country":"ID",
    "name:ind_x_preferred":[
        "Situleutik"
    ],
    "wof:name":"Situleutik",
    "wof:placetype":"locality"
},
  "geometry": {"coordinates":[107.4646,-7.1182],"type":"Point"}
}