{
  "type": "Feature",
  "properties": {
    "gn:admin1_code":"7",
    "gn:asciiname":"Guwo",
    "gn:country_code":"ID",
    "gn:dem":184,
    "gn:feature_class":"P",
    "gn:feature_code":"PPL",
    "gn:name":"Guwo",
    "gn:population":0,
    "gn:timezone":"Asia/Jakarta",
    "iso:country":"ID",
    "name:ind_x_preferred":[
        "Guwo"
    ],
    "wof:name":"Guwo",
    "wof:placetype":"locality"
},
  "geometry": {"coordinates":[110.9811,-6.6814],"type":"Point"}
}