{
  "type": "Feature",
  "properties": {
    "gn:admin1_code":"8",
    "gn:asciiname":"Nangpenang",
    "gn:country_code":"ID",
    "gn:dem":8,
    "gn:feature_class":"P",
    "gn:feature_code":"PPL",
    "gn:name":"Nangpenang",
    "gn:population":0,
    "gn:timezone":"Asia/Jakarta",
    "iso:country":"ID",
    "name:ind_x_preferred":[
        "Nangpenang"
    ],
    "wof:name":"Nangpenang",
    "wof:placetype":"locality"
},
  "geometry": {"coordinates":[112.904,-7.1703],"type":"Point"}
}