{
  "type": "Feature",
  "properties": {
    "gn:admin1_code":"0.0",
    "gn:asciiname":"Oni",
    "gn:cc2":"ID",
    "gn:country_code":"ID",
    "gn:dem":273,
    "gn:feature_class":"P",
    "gn:feature_code":"PPL",
    "gn:name":"Oni",
    "gn:population":0,
    "gn:timezone":"Asia/Jayapura",
    "iso:country":"ID",
    "name:und_x_variant":[
        "Omi",
        "Oni"
    ],
    "wof:name":"Oni",
    "wof:placetype":"locality"
},
  "geometry": {"coordinates":[134.09999999999999,-1.18333],"type":"Point"}
}