{
  "type": "Feature",
  "properties": {
    "gn:admin1_code":"7.0",
    "gn:asciiname":"Mutih Wetan",
    "gn:country_code":"ID",
    "gn:dem":4,
    "gn:feature_class":"P",
    "gn:feature_code":"PPL",
    "gn:name":"Mutih Wetan",
    "gn:population":0,
    "gn:timezone":"Asia/Jakarta",
    "iso:country":"ID",
    "name:ind_x_preferred":[
        "Mutih Wetan"
    ],
    "name:und_x_variant":[
        "Mutih"
    ],
    "wof:name":"Mutih Wetan",
    "wof:placetype":"locality"
},
  "geometry": {"coordinates":[110.6674,-6.7448],"type":"Point"}
}