{
  "type": "Feature",
  "properties": {
    "gn:admin1_code":"1",
    "gn:asciiname":"Paya Pingan",
    "gn:country_code":"ID",
    "gn:dem":25,
    "gn:feature_class":"P",
    "gn:feature_code":"PPL",
    "gn:name":"Paya Pingan",
    "gn:population":0,
    "gn:timezone":"Asia/Jakarta",
    "iso:country":"ID",
    "name:ind_x_preferred":[
        "Paya Pingan"
    ],
    "name:und_x_variant":[
        "Pajapingan"
    ],
    "wof:name":"Paya Pingan",
    "wof:placetype":"locality"
},
  "geometry": {"coordinates":[97.2093,4.9621],"type":"Point"}
}