{
  "type": "Feature",
  "properties": {
    "gn:admin1_code":"18.0",
    "gn:asciiname":"Noetaimisa",
    "gn:country_code":"ID",
    "gn:dem":93,
    "gn:feature_class":"P",
    "gn:feature_code":"PPL",
    "gn:name":"Noetaimisa",
    "gn:population":0,
    "gn:timezone":"Asia/Makassar",
    "iso:country":"ID",
    "name:ind_x_preferred":[
        "Noetaimisa"
    ],
    "wof:name":"Noetaimisa",
    "wof:placetype":"locality"
},
  "geometry": {"coordinates":[124.3496,-10.0621],"type":"Point"}
}