{
  "type": "Feature",
  "properties": {
    "gn:admin1_code":"26",
    "gn:asciiname":"Sukamandi Hulu Tiga",
    "gn:country_code":"ID",
    "gn:dem":18,
    "gn:feature_class":"P",
    "gn:feature_code":"PPL",
    "gn:name":"Sukamandi Hulu Tiga",
    "gn:population":0,
    "gn:timezone":"Asia/Jakarta",
    "iso:country":"ID",
    "name:ind_x_preferred":[
        "Sukamandi Hulu Tiga"
    ],
    "name:und_x_variant":[
        "Sukamandihulu 3"
    ],
    "wof:lang_x_official":[
        "ind"
    ],
    "wof:lang_x_spoken":[
        "ind",
        "eng"
    ],
    "wof:name":"Sukamandi Hulu Tiga",
    "wof:placetype":"locality"
},
  "geometry": {"coordinates":[98.92742,3.55487],"type":"Point"}
}