{
  "type": "Feature",
  "properties": {
    "gn:admin1_code":"22.0",
    "gn:asciiname":"Onembute",
    "gn:country_code":"ID",
    "gn:dem":79,
    "gn:feature_class":"P",
    "gn:feature_code":"PPL",
    "gn:name":"Onembute",
    "gn:population":0,
    "gn:timezone":"Asia/Makassar",
    "iso:country":"ID",
    "name:ind_x_preferred":[
        "Onembute"
    ],
    "name:ind_x_variant":[
        "Onebute"
    ],
    "name:und_x_variant":[
        "Onemboete",
        "Oneboete"
    ],
    "wof:name":"Onembute",
    "wof:placetype":"locality"
},
  "geometry": {"coordinates":[122.3241,-3.9585],"type":"Point"}
}