{
  "type": "Feature",
  "properties": {
    "gn:admin1_code":"18.0",
    "gn:asciiname":"Lereng",
    "gn:country_code":"ID",
    "gn:dem":608,
    "gn:feature_class":"P",
    "gn:feature_code":"PPL",
    "gn:name":"Lereng",
    "gn:population":0,
    "gn:timezone":"Asia/Makassar",
    "iso:country":"ID",
    "name:ind_x_preferred":[
        "Lereng"
    ],
    "wof:name":"Lereng",
    "wof:placetype":"locality"
},
  "geometry": {"coordinates":[120.7383,-8.7011],"type":"Point"}
}