{
  "type": "Feature",
  "properties": {
    "gn:admin1_code":"30",
    "gn:asciiname":"Buana",
    "gn:country_code":"ID",
    "gn:dem":520,
    "gn:feature_class":"P",
    "gn:feature_code":"PPL",
    "gn:name":"Buana",
    "gn:population":0,
    "gn:timezone":"Asia/Jakarta",
    "iso:country":"ID",
    "name:ind_x_preferred":[
        "Buana"
    ],
    "wof:name":"Buana",
    "wof:placetype":"locality"
},
  "geometry": {"coordinates":[108.49194,-6.96944],"type":"Point"}
}