{
  "type": "Feature",
  "properties": {
    "gn:admin1_code":"26",
    "gn:asciiname":"Medan Krio Tiga",
    "gn:country_code":"ID",
    "gn:dem":31,
    "gn:feature_class":"P",
    "gn:feature_code":"PPL",
    "gn:name":"Medan Krio Tiga",
    "gn:population":0,
    "gn:timezone":"Asia/Jakarta",
    "iso:country":"ID",
    "name:ind_x_preferred":[
        "Medan Krio Tiga"
    ],
    "name:und_x_variant":[
        "Medankrio 3"
    ],
    "wof:name":"Medan Krio Tiga",
    "wof:placetype":"locality"
},
  "geometry": {"coordinates":[98.5939,3.5818],"type":"Point"}
}