{
  "type": "Feature",
  "properties": {
    "gn:admin1_code":"17",
    "gn:asciiname":"Tubakpancor",
    "gn:country_code":"ID",
    "gn:dem":131,
    "gn:feature_class":"P",
    "gn:feature_code":"PPL",
    "gn:name":"Tubakpancor",
    "gn:population":0,
    "gn:timezone":"Asia/Makassar",
    "iso:country":"ID",
    "name:ind_x_preferred":[
        "Tubakpancor"
    ],
    "wof:name":"Tubakpancor",
    "wof:placetype":"locality"
},
  "geometry": {"coordinates":[116.0724,-8.7487],"type":"Point"}
}