{
  "type": "Feature",
  "properties": {
    "gn:admin1_code":"37.0",
    "gn:asciiname":"Sungailimau",
    "gn:country_code":"ID",
    "gn:dem":32,
    "gn:feature_class":"P",
    "gn:feature_code":"PPL",
    "gn:name":"Sungailimau",
    "gn:population":0,
    "gn:timezone":"Asia/Jakarta",
    "iso:country":"ID",
    "name:und_x_variant":[
        "Soengailimau",
        "Sungailimau"
    ],
    "wof:name":"Sungailimau",
    "wof:placetype":"locality"
},
  "geometry": {"coordinates":[102.2406,-0.5396],"type":"Point"}
}