{
  "type": "Feature",
  "properties": {
    "gn:admin1_code":"30.0",
    "gn:asciiname":"Nanggung",
    "gn:country_code":"ID",
    "gn:dem":53,
    "gn:feature_class":"P",
    "gn:feature_code":"PPL",
    "gn:name":"Nanggung",
    "gn:population":0,
    "gn:timezone":"Asia/Jakarta",
    "iso:country":"ID",
    "name:ind_x_preferred":[
        "Nanggung"
    ],
    "name:und_x_variant":[
        "Nanggung 2",
        "Nanggung Dua",
        "Nanggung Satu",
        "Nanggung 1"
    ],
    "wof:name":"Nanggung",
    "wof:placetype":"locality"
},
  "geometry": {"coordinates":[106.47472,-6.34806],"type":"Point"}
}