{
  "type": "Feature",
  "properties": {
    "gn:admin1_code":"17",
    "gn:asciiname":"Dasankedondong",
    "gn:country_code":"ID",
    "gn:dem":73,
    "gn:feature_class":"P",
    "gn:feature_code":"PPL",
    "gn:name":"Dasankedondong",
    "gn:population":0,
    "gn:timezone":"Asia/Makassar",
    "iso:country":"ID",
    "name:ind_x_preferred":[
        "Dasankedondong"
    ],
    "wof:name":"Dasankedondong",
    "wof:placetype":"locality"
},
  "geometry": {"coordinates":[116.596,-8.6014],"type":"Point"}
}