{
  "type": "Feature",
  "properties": {
    "gn:admin1_code":"21",
    "gn:asciiname":"Losung",
    "gn:country_code":"ID",
    "gn:dem":58,
    "gn:feature_class":"P",
    "gn:feature_code":"PPL",
    "gn:name":"Losung",
    "gn:population":0,
    "gn:timezone":"Asia/Makassar",
    "iso:country":"ID",
    "name:ind_x_preferred":[
        "Losung"
    ],
    "wof:name":"Losung",
    "wof:placetype":"locality"
},
  "geometry": {"coordinates":[120.03959999999999,0.6084],"type":"Point"}
}