{
  "type": "Feature",
  "properties": {
    "gn:admin1_code":"30.0",
    "gn:asciiname":"Taringgul",
    "gn:country_code":"ID",
    "gn:dem":1025,
    "gn:feature_class":"P",
    "gn:feature_code":"PPL",
    "gn:name":"Taringgul",
    "gn:population":0,
    "gn:timezone":"Asia/Jakarta",
    "iso:country":"ID",
    "name:ind_x_preferred":[
        "Taringgul"
    ],
    "name:und_x_variant":[
        "Taringgoel"
    ],
    "wof:name":"Taringgul",
    "wof:placetype":"locality"
},
  "geometry": {"coordinates":[107.93770000000001,-7.2689],"type":"Point"}
}