{
  "type": "Feature",
  "properties": {
    "gn:admin1_code":"8",
    "gn:asciiname":"Prodo",
    "gn:country_code":"ID",
    "gn:dem":358,
    "gn:feature_class":"P",
    "gn:feature_code":"PPL",
    "gn:name":"Prodo",
    "gn:population":0,
    "gn:timezone":"Asia/Jakarta",
    "iso:country":"ID",
    "name:ind_x_preferred":[
        "Prodo"
    ],
    "wof:name":"Prodo",
    "wof:placetype":"locality"
},
  "geometry": {"coordinates":[112.8349,-7.7953],"type":"Point"}
}