{
  "type": "Feature",
  "properties": {
    "gn:admin1_code":"30.0",
    "gn:asciiname":"Nangkasari",
    "gn:country_code":"ID",
    "gn:dem":803,
    "gn:feature_class":"P",
    "gn:feature_code":"PPLA4",
    "gn:name":"Nangkasari",
    "gn:population":0,
    "gn:timezone":"Asia/Jakarta",
    "iso:country":"ID",
    "name:ind_x_preferred":[
        "Nangkasari"
    ],
    "wof:lang_x_official":[
        "ind"
    ],
    "wof:lang_x_spoken":[
        "ind",
        "eng"
    ],
    "wof:name":"Nangkasari",
    "wof:placetype":"locality"
},
  "geometry": {"coordinates":[107.8827,-7.0984],"type":"Point"}
}