{
  "type": "Feature",
  "properties": {
    "gn:admin1_code":"30",
    "gn:asciiname":"Los",
    "gn:country_code":"ID",
    "gn:dem":879,
    "gn:feature_class":"P",
    "gn:feature_code":"PPL",
    "gn:name":"Los",
    "gn:population":0,
    "gn:timezone":"Asia/Jakarta",
    "iso:country":"ID",
    "name:ind_x_preferred":[
        "Los"
    ],
    "name:und_x_variant":[
        "Elos"
    ],
    "wof:name":"Los",
    "wof:placetype":"locality"
},
  "geometry": {"coordinates":[107.62027999999999,-6.8675],"type":"Point"}
}