{
  "type": "Feature",
  "properties": {
    "gn:country":"ID",
    "gn:fcode":"ADM3",
    "gn:pop":0,
    "iso:country":"ID",
    "name:eng_x_preferred":[
        "Districts of Central Java"
    ],
    "name:ind_x_preferred":[
        "Kecamatan Boja"
    ],
    "name:unk_x_variant":[
        "Boja"
    ],
    "qs:name":"Kecamatan Boja",
    "qs:photos_9r":0,
    "qs:photos_sr":0,
    "qs:pop_sr":"0",
    "wd:wordcount":1175,
    "wof:name":"Kecamatan Boja",
    "wof:placetype":"localadmin",
    "wof:population":0
},
  "geometry": {"coordinates":[110.29049999999999,-7.1043],"type":"Point"}
}