{
  "type": "Feature",
  "properties": {
    "gn:country":"ID",
    "gn:fcode":"ADM4",
    "gn:pop":0,
    "iso:country":"ID",
    "name:ind_x_preferred":[
        "Desa Jumapolo"
    ],
    "name:unk_x_variant":[
        "Jumapolo"
    ],
    "qs:name":"Desa Jumapolo",
    "qs:photos_9r":0,
    "qs:photos_sr":0,
    "qs:pop_sr":"0",
    "wof:name":"Desa Jumapolo",
    "wof:placetype":"localadmin",
    "wof:population":0
},
  "geometry": {"coordinates":[111.00111,-7.70306],"type":"Point"}
}