{
  "type": "Feature",
  "properties": {
    "gn:admin1_code":"21",
    "gn:asciiname":"Tiwaa",
    "gn:country_code":"ID",
    "gn:dem":9,
    "gn:feature_class":"P",
    "gn:feature_code":"PPL",
    "gn:name":"Tiwaa",
    "gn:population":0,
    "gn:timezone":"Asia/Makassar",
    "iso:country":"ID",
    "name:ind_x_preferred":[
        "Tiwaa"
    ],
    "wof:name":"Tiwaa",
    "wof:placetype":"locality"
},
  "geometry": {"coordinates":[120.6215,-1.3017],"type":"Point"}
}