{
  "type": "Feature",
  "properties": {
    "gn:admin1_code":"2",
    "gn:asciiname":"Kemoning",
    "gn:country_code":"ID",
    "gn:dem":126,
    "gn:feature_class":"P",
    "gn:feature_code":"PPL",
    "gn:name":"Kemoning",
    "gn:population":0,
    "gn:timezone":"Asia/Makassar",
    "iso:country":"ID",
    "name:ind_x_preferred":[
        "Kemoning"
    ],
    "wof:name":"Kemoning",
    "wof:placetype":"locality"
},
  "geometry": {"coordinates":[114.5814,-8.285],"type":"Point"}
}