{
  "type": "Feature",
  "properties": {
    "gn:admin1_code":"36.0",
    "gn:asciiname":"Jamna",
    "gn:country_code":"ID",
    "gn:dem":24,
    "gn:feature_class":"P",
    "gn:feature_code":"PPL",
    "gn:name":"Jamna",
    "gn:population":0,
    "gn:timezone":"Asia/Jayapura",
    "iso:country":"ID",
    "name:ind_x_preferred":[
        "Jamna"
    ],
    "wof:name":"Jamna",
    "wof:placetype":"locality"
},
  "geometry": {"coordinates":[139.21600000000001,-2.09003],"type":"Point"}
}