{
  "type": "Feature",
  "properties": {
    "gn:admin1_code":"8.0",
    "gn:asciiname":"Balerejo Lor",
    "gn:country_code":"ID",
    "gn:dem":641,
    "gn:feature_class":"P",
    "gn:feature_code":"PPL",
    "gn:name":"Balerejo Lor",
    "gn:population":0,
    "gn:timezone":"Asia/Jakarta",
    "iso:country":"ID",
    "name:ind_x_preferred":[
        "Balerejo Lor"
    ],
    "wof:name":"Balerejo Lor",
    "wof:placetype":"locality"
},
  "geometry": {"coordinates":[112.77889999999999,-8.2812],"type":"Point"}
}