{
  "type": "Feature",
  "properties": {
    "gn:admin1_code":"33.0",
    "gn:asciiname":"Kadusabelah",
    "gn:country_code":"ID",
    "gn:dem":412,
    "gn:feature_class":"P",
    "gn:feature_code":"PPL",
    "gn:name":"Kadusabelah",
    "gn:population":0,
    "gn:timezone":"Asia/Jakarta",
    "iso:country":"ID",
    "name:ind_x_preferred":[
        "Kadusabelah"
    ],
    "wof:name":"Kadusabelah",
    "wof:placetype":"locality"
},
  "geometry": {"coordinates":[105.9654,-6.2562],"type":"Point"}
}