{
  "type": "Feature",
  "properties": {
    "gn:admin1_code":"0.0",
    "gn:asciiname":"Panjasan",
    "gn:cc2":"ID",
    "gn:country_code":"ID",
    "gn:dem":86,
    "gn:feature_class":"P",
    "gn:feature_code":"PPL",
    "gn:name":"Panjasan",
    "gn:population":0,
    "gn:timezone":"Asia/Jakarta",
    "iso:country":"ID",
    "name:und_x_variant":[
        "Pandjasan",
        "Pantjasan",
        "Panjasan"
    ],
    "wof:lang_x_official":[
        "ind"
    ],
    "wof:lang_x_spoken":[
        "ind",
        "eng"
    ],
    "wof:name":"Panjasan",
    "wof:placetype":"locality"
},
  "geometry": {"coordinates":[109.06667,-7.41667],"type":"Point"}
}