{
  "type": "Feature",
  "properties": {
    "gn:admin1_code":"30",
    "gn:asciiname":"Pacircinde",
    "gn:country_code":"ID",
    "gn:dem":350,
    "gn:feature_class":"P",
    "gn:feature_code":"PPL",
    "gn:name":"Pacircinde",
    "gn:population":0,
    "gn:timezone":"Asia/Jakarta",
    "iso:country":"ID",
    "name:ind_x_preferred":[
        "Pacircinde"
    ],
    "wof:name":"Pacircinde",
    "wof:placetype":"locality"
},
  "geometry": {"coordinates":[107.23721999999999,-6.8875],"type":"Point"}
}