{
  "type": "Feature",
  "properties": {
    "gn:admin1_code":"0.0",
    "gn:asciiname":"Ierelop",
    "gn:country_code":"ID",
    "gn:dem":1228,
    "gn:feature_class":"P",
    "gn:feature_code":"PPL",
    "gn:name":"Ierelop",
    "gn:population":0,
    "gn:timezone":"Asia/Jakarta",
    "iso:country":"ID",
    "wof:name":"Ierelop",
    "wof:placetype":"locality"
},
  "geometry": {"coordinates":[96.81667,4.56667],"type":"Point"}
}