{
  "type": "Feature",
  "properties": {
    "gn:admin1_code":"18.0",
    "gn:asciiname":"Waitiu",
    "gn:country_code":"ID",
    "gn:dem":19,
    "gn:feature_class":"P",
    "gn:feature_code":"PPL",
    "gn:name":"Waitiu",
    "gn:population":0,
    "gn:timezone":"Asia/Makassar",
    "iso:country":"ID",
    "name:ind_x_preferred":[
        "Waitiu"
    ],
    "wof:name":"Waitiu",
    "wof:placetype":"locality"
},
  "geometry": {"coordinates":[122.9179,-8.3253],"type":"Point"}
}