{
  "type": "Feature",
  "properties": {
    "gn:admin1_code":"30",
    "gn:asciiname":"Cihaok",
    "gn:country_code":"ID",
    "gn:dem":15,
    "gn:feature_class":"P",
    "gn:feature_code":"PPL",
    "gn:name":"Cihaok",
    "gn:population":0,
    "gn:timezone":"Asia/Jakarta",
    "iso:country":"ID",
    "name:ind_x_preferred":[
        "Cihaok"
    ],
    "wof:name":"Cihaok",
    "wof:placetype":"locality"
},
  "geometry": {"coordinates":[107.84528,-6.35917],"type":"Point"}
}