{
  "type": "Feature",
  "properties": {
    "gn:admin1_code":"8",
    "gn:asciiname":"Berekgunung",
    "gn:country_code":"ID",
    "gn:dem":223,
    "gn:feature_class":"P",
    "gn:feature_code":"PPL",
    "gn:name":"Berekgunung",
    "gn:population":0,
    "gn:timezone":"Asia/Jakarta",
    "iso:country":"ID",
    "name:ind_x_preferred":[
        "Berekgunung"
    ],
    "wof:name":"Berekgunung",
    "wof:placetype":"locality"
},
  "geometry": {"coordinates":[113.22839999999999,-7.9791],"type":"Point"}
}