{
  "type": "Feature",
  "properties": {
    "gn:admin1_code":"07",
    "gn:asciiname":"Waru",
    "gn:country_code":"ID",
    "gn:dem":255,
    "gn:feature_class":"P",
    "gn:feature_code":"PPL",
    "gn:name":"Waru",
    "gn:population":0,
    "gn:timezone":"Asia/Jakarta",
    "iso:country":"ID",
    "name:ceb_x_preferred":[
        "Waru"
    ],
    "name:ind_x_preferred":[
        "Waru"
    ],
    "name:nld_x_preferred":[
        "Waru"
    ],
    "name:rus_x_preferred":[
        "\u0412\u0430\u0440\u0443"
    ],
    "name:swe_x_preferred":[
        "Waru"
    ],
    "name:und_x_variant":[
        "Waru 2",
        "Waru Dua",
        "Waru"
    ],
    "wof:lang_x_official":[
        "ind"
    ],
    "wof:lang_x_spoken":[
        "ind",
        "eng"
    ],
    "wof:name":"Waru",
    "wof:placetype":"locality"
},
  "geometry": {"coordinates":[110.68083,-7.36472],"type":"Point"}
}