{
  "type": "Feature",
  "properties": {
    "gn:admin1_code":"17.0",
    "gn:asciiname":"Kebon Lauq",
    "gn:country_code":"ID",
    "gn:dem":18,
    "gn:feature_class":"P",
    "gn:feature_code":"PPL",
    "gn:name":"Kebon Lauq",
    "gn:population":0,
    "gn:timezone":"Asia/Makassar",
    "iso:country":"ID",
    "name:ind_x_preferred":[
        "Kebon Lauq"
    ],
    "wof:name":"Kebon Lauq",
    "wof:placetype":"locality"
},
  "geometry": {"coordinates":[116.1101,-8.6158],"type":"Point"}
}