{
  "type": "Feature",
  "properties": {
    "gn:admin1_code":"30.0",
    "gn:asciiname":"Karangdalem",
    "gn:country_code":"ID",
    "gn:dem":12,
    "gn:feature_class":"P",
    "gn:feature_code":"PPL",
    "gn:name":"Karangdalem",
    "gn:population":0,
    "gn:timezone":"Asia/Jakarta",
    "iso:country":"ID",
    "name:ind_x_preferred":[
        "Karangdalem"
    ],
    "wof:name":"Karangdalem",
    "wof:placetype":"locality"
},
  "geometry": {"coordinates":[108.45278,-6.67333],"type":"Point"}
}