{
  "type": "Feature",
  "properties": {
    "gn:admin1_code":"05",
    "gn:asciiname":"Sungaikeruh",
    "gn:country_code":"ID",
    "gn:dem":32,
    "gn:feature_class":"P",
    "gn:feature_code":"PPL",
    "gn:name":"Sungaikeruh",
    "gn:population":0,
    "gn:timezone":"Asia/Jakarta",
    "iso:country":"ID",
    "name:ind_x_preferred":[
        "Sungaikeruh"
    ],
    "wof:name":"Sungaikeruh",
    "wof:placetype":"locality"
},
  "geometry": {"coordinates":[102.55719999999999,-1.4796],"type":"Point"}
}