{
  "type": "Feature",
  "properties": {
    "gn:admin1_code":"18.0",
    "gn:asciiname":"Mase",
    "gn:country_code":"ID",
    "gn:dem":213,
    "gn:feature_class":"P",
    "gn:feature_code":"PPL",
    "gn:name":"Mase",
    "gn:population":0,
    "gn:timezone":"Asia/Makassar",
    "iso:country":"ID",
    "name:ast_x_preferred":[
        "Mase"
    ],
    "name:ces_x_preferred":[
        "Mase"
    ],
    "name:dan_x_preferred":[
        "Mase"
    ],
    "name:deu_x_preferred":[
        "Mase"
    ],
    "name:fas_x_preferred":[
        "\u0645\u06cc\u0633"
    ],
    "name:fin_x_preferred":[
        "Ma$e"
    ],
    "name:fra_x_preferred":[
        "Ma$e"
    ],
    "name:ind_x_preferred":[
        "Mase"
    ],
    "name:ita_x_preferred":[
        "Ma$e"
    ],
    "name:jpn_x_preferred":[
        "\u30e1\u30a4\u30b9"
    ],
    "name:kor_x_preferred":[
        "\uba54\uc774\uc2a4"
    ],
    "name:nld_x_preferred":[
        "Ma$e"
    ],
    "name:por_x_preferred":[
        "Mase"
    ],
    "name:rus_x_preferred":[
        "Mase"
    ],
    "name:spa_x_preferred":[
        "Mase"
    ],
    "name:swa_x_preferred":[
        "Mase"
    ],
    "name:swe_x_preferred":[
        "Mase"
    ],
    "name:tur_x_preferred":[
        "Mase"
    ],
    "wof:name":"Mase",
    "wof:placetype":"locality"
},
  "geometry": {"coordinates":[122.0461,-8.7089],"type":"Point"}
}