{
  "type": "Feature",
  "properties": {
    "gn:admin1_code":"33",
    "gn:asciiname":"Gunungpal",
    "gn:country_code":"ID",
    "gn:dem":78,
    "gn:feature_class":"P",
    "gn:feature_code":"PPL",
    "gn:name":"Gunungpal",
    "gn:population":0,
    "gn:timezone":"Asia/Jakarta",
    "iso:country":"ID",
    "name:ind_x_preferred":[
        "Gunungpal"
    ],
    "wof:name":"Gunungpal",
    "wof:placetype":"locality"
},
  "geometry": {"coordinates":[106.0194,-6.0602],"type":"Point"}
}