{
  "type": "Feature",
  "properties": {
    "gn:admin1_code":"30.0",
    "gn:asciiname":"Karangsari",
    "gn:country_code":"ID",
    "gn:dem":15,
    "gn:feature_class":"P",
    "gn:feature_code":"PPL",
    "gn:name":"Karangsari",
    "gn:population":0,
    "gn:timezone":"Asia/Jakarta",
    "iso:country":"ID",
    "name:ind_x_preferred":[
        "Karangsari"
    ],
    "name:und_x_variant":[
        "Karangsari Satu"
    ],
    "wof:name":"Karangsari",
    "wof:placetype":"locality"
},
  "geometry": {"coordinates":[108.7012,-7.504],"type":"Point"}
}