{
  "type": "Feature",
  "properties": {
    "gn:admin1_code":"30.0",
    "gn:asciiname":"Cicurug",
    "gn:country_code":"ID",
    "gn:dem":918,
    "gn:feature_class":"P",
    "gn:feature_code":"PPL",
    "gn:name":"Cicurug",
    "gn:population":0,
    "gn:timezone":"Asia/Jakarta",
    "iso:country":"ID",
    "name:ind_x_preferred":[
        "Cicurug"
    ],
    "name:jav_x_preferred":[
        "Cicurug"
    ],
    "name:mlg_x_preferred":[
        "Cicurug"
    ],
    "name:nld_x_preferred":[
        "Cicurug"
    ],
    "name:sun_x_preferred":[
        "Cicurug"
    ],
    "wof:lang_x_official":[
        "ind"
    ],
    "wof:lang_x_spoken":[
        "ind",
        "eng"
    ],
    "wof:name":"Cicurug",
    "wof:placetype":"locality"
},
  "geometry": {"coordinates":[107.4853,-7.3141],"type":"Point"}
}