{
  "type": "Feature",
  "properties": {
    "gn:admin1_code":"30",
    "gn:asciiname":"Wagir",
    "gn:country_code":"ID",
    "gn:dem":20,
    "gn:feature_class":"P",
    "gn:feature_code":"PPL",
    "gn:name":"Wagir",
    "gn:population":0,
    "gn:timezone":"Asia/Jakarta",
    "iso:country":"ID",
    "name:ind_x_preferred":[
        "Wagir"
    ],
    "wof:name":"Wagir",
    "wof:placetype":"locality"
},
  "geometry": {"coordinates":[107.41388999999999,-6.33111],"type":"Point"}
}