{
  "type": "Feature",
  "properties": {
    "gn:admin1_code":"38",
    "gn:asciiname":"Robo",
    "gn:country_code":"ID",
    "gn:dem":397,
    "gn:feature_class":"P",
    "gn:feature_code":"PPL",
    "gn:name":"Robo",
    "gn:population":0,
    "gn:timezone":"Asia/Makassar",
    "iso:country":"ID",
    "name:deu_x_preferred":[
        "Robo"
    ],
    "name:fra_x_preferred":[
        "Robo"
    ],
    "name:ind_x_preferred":[
        "Robo"
    ],
    "wof:lang_x_official":[
        "ind"
    ],
    "wof:lang_x_spoken":[
        "ind",
        "eng"
    ],
    "wof:name":"Robo",
    "wof:placetype":"locality"
},
  "geometry": {"coordinates":[119.7704,-5.0014],"type":"Point"}
}