{
  "type": "Feature",
  "properties": {
    "gn:admin1_code":"30.0",
    "gn:asciiname":"Dayeuhluhur",
    "gn:country_code":"ID",
    "gn:dem":879,
    "gn:feature_class":"P",
    "gn:feature_code":"PPL",
    "gn:name":"Dayeuhluhur",
    "gn:population":0,
    "gn:timezone":"Asia/Jakarta",
    "iso:country":"ID",
    "name:ind_x_preferred":[
        "Dayeuhluhur"
    ],
    "name:jav_x_preferred":[
        "Dayeuhluhur"
    ],
    "name:und_x_variant":[
        "Dajeuhluhur"
    ],
    "wof:lang_x_official":[
        "ind"
    ],
    "wof:lang_x_spoken":[
        "ind",
        "eng"
    ],
    "wof:name":"Dayeuhluhur",
    "wof:placetype":"locality"
},
  "geometry": {"coordinates":[107.97389,-6.88944],"type":"Point"}
}