{
  "type": "Feature",
  "properties": {
    "gn:admin1_code":"8",
    "gn:asciiname":"Banjarmlati",
    "gn:country_code":"ID",
    "gn:dem":23,
    "gn:feature_class":"P",
    "gn:feature_code":"PPL",
    "gn:name":"Banjarmlati",
    "gn:population":0,
    "gn:timezone":"Asia/Jakarta",
    "iso:country":"ID",
    "name:ind_x_preferred":[
        "Banjarmlati"
    ],
    "wof:name":"Banjarmlati",
    "wof:placetype":"locality"
},
  "geometry": {"coordinates":[112.4555,-7.3018],"type":"Point"}
}