{
  "type": "Feature",
  "properties": {
    "gn:admin1_code":"17",
    "gn:asciiname":"Sukamaju",
    "gn:country_code":"ID",
    "gn:dem":31,
    "gn:feature_class":"P",
    "gn:feature_code":"PPL",
    "gn:name":"Sukamaju",
    "gn:population":0,
    "gn:timezone":"Asia/Makassar",
    "iso:country":"ID",
    "name:ind_x_preferred":[
        "Sukamaju"
    ],
    "wof:name":"Sukamaju",
    "wof:placetype":"locality"
},
  "geometry": {"coordinates":[118.9264,-8.3131],"type":"Point"}
}