{
  "type": "Feature",
  "properties": {
    "gn:admin1_code":"30",
    "gn:asciiname":"Babakansukadana",
    "gn:country_code":"ID",
    "gn:dem":111,
    "gn:feature_class":"P",
    "gn:feature_code":"PPL",
    "gn:name":"Babakansukadana",
    "gn:population":0,
    "gn:timezone":"Asia/Jakarta",
    "iso:country":"ID",
    "name:ind_x_preferred":[
        "Babakansukadana"
    ],
    "wof:name":"Babakansukadana",
    "wof:placetype":"locality"
},
  "geometry": {"coordinates":[107.76667,-6.60833],"type":"Point"}
}