{
  "type": "Feature",
  "properties": {
    "gn:admin1_code":"33",
    "gn:asciiname":"Sanding",
    "gn:country_code":"ID",
    "gn:dem":53,
    "gn:feature_class":"P",
    "gn:feature_code":"PPL",
    "gn:name":"Sanding",
    "gn:population":0,
    "gn:timezone":"Asia/Jakarta",
    "iso:country":"ID",
    "name:ind_x_preferred":[
        "Sanding"
    ],
    "wof:name":"Sanding",
    "wof:placetype":"locality"
},
  "geometry": {"coordinates":[106.34180000000001,-6.3258],"type":"Point"}
}