{
  "type": "Feature",
  "properties": {
    "gn:admin1_code":"0.0",
    "gn:asciiname":"Sungaitampang",
    "gn:cc2":"ID",
    "gn:country_code":"ID",
    "gn:dem":2,
    "gn:feature_class":"P",
    "gn:feature_code":"PPL",
    "gn:name":"Sungaitampang",
    "gn:population":0,
    "gn:timezone":"Asia/Jakarta",
    "iso:country":"ID",
    "name:und_x_variant":[
        "Soengaitampang",
        "Sungaitampang"
    ],
    "wof:name":"Sungaitampang",
    "wof:placetype":"locality"
},
  "geometry": {"coordinates":[100.11667,2.33333],"type":"Point"}
}