{
  "type": "Feature",
  "properties": {
    "gn:admin1_code":"38",
    "gn:asciiname":"Parangboddong",
    "gn:country_code":"ID",
    "gn:dem":21,
    "gn:feature_class":"P",
    "gn:feature_code":"PPL",
    "gn:name":"Parangboddong",
    "gn:population":0,
    "gn:timezone":"Asia/Makassar",
    "iso:country":"ID",
    "name:ind_x_preferred":[
        "Parangboddong"
    ],
    "wof:name":"Parangboddong",
    "wof:placetype":"locality"
},
  "geometry": {"coordinates":[119.52,-5.051],"type":"Point"}
}