{
  "type": "Feature",
  "properties": {
    "gn:admin1_code":"0.0",
    "gn:asciiname":"Pangadang",
    "gn:country_code":"ID",
    "gn:dem":952,
    "gn:feature_class":"P",
    "gn:feature_code":"PPL",
    "gn:name":"Pangadang",
    "gn:population":0,
    "gn:timezone":"Asia/Makassar",
    "iso:country":"ID",
    "wof:lang_x_official":[
        "ind"
    ],
    "wof:lang_x_spoken":[
        "ind",
        "eng"
    ],
    "wof:name":"Pangadang",
    "wof:placetype":"locality"
},
  "geometry": {"coordinates":[117.53333000000001,-8.81667],"type":"Point"}
}