{
  "type": "Feature",
  "properties": {
    "gn:admin1_code":"1",
    "gn:asciiname":"Lubuk Sirambe",
    "gn:country_code":"ID",
    "gn:dem":7,
    "gn:feature_class":"P",
    "gn:feature_code":"PPL",
    "gn:name":"Lubuk Sirambe",
    "gn:population":0,
    "gn:timezone":"Asia/Jakarta",
    "iso:country":"ID",
    "name:ind_x_preferred":[
        "Lubuk Sirambe"
    ],
    "wof:name":"Lubuk Sirambe",
    "wof:placetype":"locality"
},
  "geometry": {"coordinates":[99.7308,2.9696],"type":"Point"}
}