{
  "type": "Feature",
  "properties": {
    "gn:admin1_code":"7.0",
    "gn:asciiname":"Sono Wetan",
    "gn:country_code":"ID",
    "gn:dem":383,
    "gn:feature_class":"P",
    "gn:feature_code":"PPL",
    "gn:name":"Sono Wetan",
    "gn:population":0,
    "gn:timezone":"Asia/Jakarta",
    "iso:country":"ID",
    "wof:name":"Sono Wetan",
    "wof:placetype":"locality"
},
  "geometry": {"coordinates":[110.33889000000001,-7.64444],"type":"Point"}
}