{
  "type": "Feature",
  "properties": {
    "gn:admin1_code":"30",
    "gn:asciiname":"Kertajaya",
    "gn:country_code":"ID",
    "gn:dem":159,
    "gn:feature_class":"P",
    "gn:feature_code":"PPL",
    "gn:name":"Kertajaya",
    "gn:population":0,
    "gn:timezone":"Asia/Jakarta",
    "iso:country":"ID",
    "name:ind_x_preferred":[
        "Kertajaya"
    ],
    "wof:name":"Kertajaya",
    "wof:placetype":"locality"
},
  "geometry": {"coordinates":[107.46138999999999,-6.57583],"type":"Point"}
}