{
  "type": "Feature",
  "properties": {
    "gn:admin1_code":"17",
    "gn:asciiname":"Aikgering",
    "gn:country_code":"ID",
    "gn:dem":391,
    "gn:feature_class":"P",
    "gn:feature_code":"PPL",
    "gn:name":"Aikgering",
    "gn:population":0,
    "gn:timezone":"Asia/Makassar",
    "iso:country":"ID",
    "name:ind_x_preferred":[
        "Aikgering"
    ],
    "wof:name":"Aikgering",
    "wof:placetype":"locality"
},
  "geometry": {"coordinates":[116.33620000000001,-8.6192],"type":"Point"}
}