{
  "type": "Feature",
  "properties": {
    "gn:admin1_code":"8.0",
    "gn:asciiname":"Rekesan Utara",
    "gn:country_code":"ID",
    "gn:dem":423,
    "gn:feature_class":"P",
    "gn:feature_code":"PPL",
    "gn:name":"Rekesan Utara",
    "gn:population":0,
    "gn:timezone":"Asia/Jakarta",
    "iso:country":"ID",
    "name:ind_x_preferred":[
        "Rekesan Utara"
    ],
    "wof:name":"Rekesan Utara",
    "wof:placetype":"locality"
},
  "geometry": {"coordinates":[112.70402,-8.14314],"type":"Point"}
}