{
  "type": "Feature",
  "properties": {
    "gn:admin1_code":"30.0",
    "gn:asciiname":"Puncakwangi",
    "gn:country_code":"ID",
    "gn:dem":504,
    "gn:feature_class":"P",
    "gn:feature_code":"PPLA4",
    "gn:name":"Puncakwangi",
    "gn:population":0,
    "gn:timezone":"Asia/Jakarta",
    "iso:country":"ID",
    "name:ind_x_preferred":[
        "Puncakwangi"
    ],
    "wof:name":"Puncakwangi",
    "wof:placetype":"locality"
},
  "geometry": {"coordinates":[107.066,-7.2961],"type":"Point"}
}