{
  "type": "Feature",
  "properties": {
    "gn:country":"ID",
    "gn:fcode":"PPL",
    "gn:pop":0,
    "iso:country":"ID",
    "name:ind_x_preferred":[
        "Cikole"
    ],
    "qs:name":"Cikole",
    "qs:name_adm0":"Indonesia",
    "qs:name_adm1":"Jawa Barat",
    "qs:photos":134,
    "qs:photos_1k":27,
    "qs:photos_9k":1,
    "qs:photos_9r":3,
    "qs:photos_all":134,
    "qs:photos_sr":3,
    "qs:placetype":"Town",
    "qs:pop_sr":"0",
    "wof:lang_x_official":[
        "ind"
    ],
    "wof:lang_x_spoken":[
        "ind",
        "eng"
    ],
    "wof:name":"Cikole",
    "wof:placetype":"locality",
    "wof:population":0
},
  "geometry": {"coordinates":[107.93556,-6.8075],"type":"Point"}
}