{
  "type": "Feature",
  "properties": {
    "gn:admin1_code":"7.0",
    "gn:asciiname":"Kaligusur",
    "gn:country_code":"ID",
    "gn:dem":26,
    "gn:feature_class":"P",
    "gn:feature_code":"PPL",
    "gn:name":"Kaligusur",
    "gn:population":0,
    "gn:timezone":"Asia/Jakarta",
    "iso:country":"ID",
    "name:ind_x_preferred":[
        "Kaligusur"
    ],
    "wof:name":"Kaligusur",
    "wof:placetype":"locality"
},
  "geometry": {"coordinates":[109.10361,-7.545],"type":"Point"}
}