{
  "type": "Feature",
  "properties": {
    "gn:admin1_code":"7.0",
    "gn:asciiname":"Kiyongsari",
    "gn:country_code":"ID",
    "gn:dem":19,
    "gn:feature_class":"P",
    "gn:feature_code":"PPL",
    "gn:name":"Kiyongsari",
    "gn:population":0,
    "gn:timezone":"Asia/Jakarta",
    "iso:country":"ID",
    "name:ind_x_preferred":[
        "Kiyongsari"
    ],
    "wof:name":"Kiyongsari",
    "wof:placetype":"locality"
},
  "geometry": {"coordinates":[110.6955,-6.5079],"type":"Point"}
}