{
  "type": "Feature",
  "properties": {
    "gn:admin1_code":"26.0",
    "gn:asciiname":"Pondok Afdeling G",
    "gn:country_code":"ID",
    "gn:dem":949,
    "gn:feature_class":"P",
    "gn:feature_code":"PPL",
    "gn:name":"Pondok Afdeling G",
    "gn:population":0,
    "gn:timezone":"Asia/Jakarta",
    "iso:country":"ID",
    "name:ind_x_preferred":[
        "Pondok Afdeling G"
    ],
    "wof:name":"Pondok Afdeling G",
    "wof:placetype":"locality"
},
  "geometry": {"coordinates":[98.8841,2.8688],"type":"Point"}
}