{
  "type": "Feature",
  "properties": {
    "gn:country":"ID",
    "gn:fcode":"PPL",
    "gn:pop":0,
    "iso:country":"ID",
    "name:ind_x_preferred":[
        "Labasari"
    ],
    "qs:name":"Laba Sari",
    "qs:name_adm0":"Indonesia",
    "qs:name_adm1":"Bali",
    "qs:photos":546,
    "qs:photos_1k":111,
    "qs:photos_9k":2,
    "qs:photos_9r":5,
    "qs:photos_all":546,
    "qs:photos_sr":7,
    "qs:placetype":"Town",
    "qs:pop_sr":"0",
    "wof:name":"Laba Sari",
    "wof:placetype":"locality",
    "wof:population":0
},
  "geometry": {"coordinates":[114.9002,-8.221],"type":"Point"}
}