{
  "type": "Feature",
  "properties": {
    "gn:admin1_code":"1.0",
    "gn:asciiname":"Busu",
    "gn:country_code":"ID",
    "gn:dem":28,
    "gn:feature_class":"P",
    "gn:feature_code":"PPL",
    "gn:name":"Busu",
    "gn:population":0,
    "gn:timezone":"Asia/Jakarta",
    "iso:country":"ID",
    "name:ceb_x_preferred":[
        "Busu"
    ],
    "name:ind_x_preferred":[
        "Busu"
    ],
    "wof:name":"Busu",
    "wof:placetype":"locality"
},
  "geometry": {"coordinates":[95.95740000000001,5.2872],"type":"Point"}
}