{
  "type": "Feature",
  "properties": {
    "gn:admin1_code":"1",
    "gn:asciiname":"Lamjampak",
    "gn:country_code":"ID",
    "gn:dem":19,
    "gn:feature_class":"P",
    "gn:feature_code":"PPL",
    "gn:name":"Lamjampak",
    "gn:population":0,
    "gn:timezone":"Asia/Jakarta",
    "iso:country":"ID",
    "name:ind_x_preferred":[
        "Lamjampak"
    ],
    "wof:name":"Lamjampak",
    "wof:placetype":"locality"
},
  "geometry": {"coordinates":[95.399,5.4868],"type":"Point"}
}