{
  "type": "Feature",
  "properties": {
    "gn:admin1_code":"30",
    "gn:asciiname":"Pasiripis",
    "gn:country_code":"ID",
    "gn:dem":876,
    "gn:feature_class":"P",
    "gn:feature_code":"PPL",
    "gn:name":"Pasiripis",
    "gn:population":0,
    "gn:timezone":"Asia/Jakarta",
    "iso:country":"ID",
    "name:ind_x_preferred":[
        "Pasiripis"
    ],
    "wof:name":"Pasiripis",
    "wof:placetype":"locality"
},
  "geometry": {"coordinates":[107.41630000000001,-7.0352],"type":"Point"}
}