{
  "type": "Feature",
  "properties": {
    "gn:admin1_code":"30",
    "gn:asciiname":"Curuggirang Tonggoh",
    "gn:country_code":"ID",
    "gn:dem":968,
    "gn:feature_class":"P",
    "gn:feature_code":"PPL",
    "gn:name":"Curuggirang Tonggoh",
    "gn:population":0,
    "gn:timezone":"Asia/Jakarta",
    "iso:country":"ID",
    "name:ind_x_preferred":[
        "Curuggirang Tonggoh"
    ],
    "wof:name":"Curuggirang Tonggoh",
    "wof:placetype":"locality"
},
  "geometry": {"coordinates":[106.53194000000001,-6.71444],"type":"Point"}
}