{
  "type": "Feature",
  "properties": {
    "gn:admin1_code":"8.0",
    "gn:asciiname":"Du'alas",
    "gn:country_code":"ID",
    "gn:dem":48,
    "gn:feature_class":"P",
    "gn:feature_code":"PPL",
    "gn:name":"Du\u2019alas",
    "gn:population":0,
    "gn:timezone":"Asia/Jakarta",
    "iso:country":"ID",
    "name:ind_x_preferred":[
        "Du\u2019alas"
    ],
    "wof:name":"Du'alas",
    "wof:placetype":"locality"
},
  "geometry": {"coordinates":[113.5462,-7.1247],"type":"Point"}
}