{
  "type": "Feature",
  "properties": {
    "gn:admin1_code":"0.0",
    "gn:asciiname":"Amar",
    "gn:country_code":"ID",
    "gn:dem":25,
    "gn:feature_class":"P",
    "gn:feature_code":"PPL",
    "gn:name":"Amar",
    "gn:population":0,
    "gn:timezone":"Asia/Jayapura",
    "iso:country":"ID",
    "name:ceb_x_preferred":[
        "Amar"
    ],
    "name:deu_x_preferred":[
        "Amar"
    ],
    "name:fas_x_preferred":[
        "\u0639\u0645\u0627\u0631"
    ],
    "name:fin_x_preferred":[
        "Amar"
    ],
    "name:fra_x_preferred":[
        "Amar"
    ],
    "name:gla_x_preferred":[
        "Amar"
    ],
    "name:heb_x_preferred":[
        "\u05e2\u05de\u05e8"
    ],
    "name:hin_x_preferred":[
        "\u0905\u092e\u0930"
    ],
    "name:ita_x_preferred":[
        "Amar"
    ],
    "name:lit_x_preferred":[
        "Amaras"
    ],
    "name:por_x_preferred":[
        "Amar"
    ],
    "name:rus_x_preferred":[
        "\u0410\u043c\u0430\u0440"
    ],
    "name:spa_x_preferred":[
        "Amar"
    ],
    "name:swe_x_preferred":[
        "Amar"
    ],
    "wof:lang_x_official":[
        "ind"
    ],
    "wof:lang_x_spoken":[
        "ind",
        "eng"
    ],
    "wof:name":"Amar",
    "wof:placetype":"locality"
},
  "geometry": {"coordinates":[131.32644999999999,-4.09749],"type":"Point"}
}