{
  "type": "Feature",
  "properties": {
    "gn:admin1_code":"26",
    "gn:asciiname":"Hutalangit",
    "gn:country_code":"ID",
    "gn:dem":967,
    "gn:feature_class":"P",
    "gn:feature_code":"PPL",
    "gn:name":"Hutalangit",
    "gn:population":0,
    "gn:timezone":"Asia/Jakarta",
    "iso:country":"ID",
    "name:ind_x_preferred":[
        "Hutalangit"
    ],
    "wof:name":"Hutalangit",
    "wof:placetype":"locality"
},
  "geometry": {"coordinates":[98.9511,2.0397],"type":"Point"}
}