{
  "type": "Feature",
  "properties": {
    "gn:admin1_code":"38",
    "gn:asciiname":"Lamone",
    "gn:country_code":"ID",
    "gn:dem":18,
    "gn:feature_class":"P",
    "gn:feature_code":"PPL",
    "gn:name":"Lamone",
    "gn:population":0,
    "gn:timezone":"Asia/Makassar",
    "iso:country":"ID",
    "name:als_x_preferred":[
        "Lamone"
    ],
    "name:ast_x_preferred":[
        "Lamone"
    ],
    "name:ceb_x_preferred":[
        "Lamone"
    ],
    "name:deu_x_preferred":[
        "Lamone"
    ],
    "name:epo_x_preferred":[
        "Lamone"
    ],
    "name:eus_x_preferred":[
        "Lamone"
    ],
    "name:fra_x_preferred":[
        "Lamone"
    ],
    "name:ind_x_preferred":[
        "Lamone"
    ],
    "name:ita_x_preferred":[
        "Lamone"
    ],
    "name:lmo_x_preferred":[
        "Lamon"
    ],
    "name:msa_x_preferred":[
        "Lamone"
    ],
    "name:nld_x_preferred":[
        "Lamone"
    ],
    "name:nno_x_preferred":[
        "Lamone"
    ],
    "name:por_x_preferred":[
        "Lamone"
    ],
    "name:roh_x_preferred":[
        "Lamone"
    ],
    "name:spa_x_preferred":[
        "Lamone"
    ],
    "name:sqi_x_preferred":[
        "Lamone"
    ],
    "name:vol_x_preferred":[
        "Lamone"
    ],
    "name:war_x_preferred":[
        "Lamone"
    ],
    "name:zho_x_preferred":[
        "\u62c9\u83ab\u5167"
    ],
    "wof:lang_x_official":[
        "ind"
    ],
    "wof:lang_x_spoken":[
        "ind",
        "eng"
    ],
    "wof:name":"Lamone",
    "wof:placetype":"locality"
},
  "geometry": {"coordinates":[120.2529,-3.1307],"type":"Point"}
}