{
  "type": "Feature",
  "properties": {
    "gn:admin1_code":"26",
    "gn:asciiname":"Besulah",
    "gn:country_code":"ID",
    "gn:dem":427,
    "gn:feature_class":"P",
    "gn:feature_code":"PPL",
    "gn:name":"Besulah",
    "gn:population":0,
    "gn:timezone":"Asia/Jakarta",
    "iso:country":"ID",
    "name:ind_x_preferred":[
        "Besulah"
    ],
    "wof:name":"Besulah",
    "wof:placetype":"locality"
},
  "geometry": {"coordinates":[98.69580000000001,3.2237],"type":"Point"}
}