{
  "type": "Feature",
  "properties": {
    "gn:admin1_code":"30.0",
    "gn:asciiname":"Cihateup",
    "gn:country_code":"ID",
    "gn:dem":534,
    "gn:feature_class":"P",
    "gn:feature_code":"PPLA4",
    "gn:name":"Cihateup",
    "gn:population":0,
    "gn:timezone":"Asia/Jakarta",
    "iso:country":"ID",
    "name:ind_x_preferred":[
        "Cihateup"
    ],
    "wof:name":"Cihateup",
    "wof:placetype":"locality"
},
  "geometry": {"coordinates":[108.17,-7.2139],"type":"Point"}
}