{
  "type": "Feature",
  "properties": {
    "gn:admin1_code":"26",
    "gn:asciiname":"Bandar Muda",
    "gn:country_code":"ID",
    "gn:dem":86,
    "gn:feature_class":"P",
    "gn:feature_code":"PPL",
    "gn:name":"Bandar Muda",
    "gn:population":0,
    "gn:timezone":"Asia/Jakarta",
    "iso:country":"ID",
    "name:ind_x_preferred":[
        "Bandar Muda"
    ],
    "wof:name":"Bandar Muda",
    "wof:placetype":"locality"
},
  "geometry": {"coordinates":[98.2576,3.5429],"type":"Point"}
}