{
  "type": "Feature",
  "properties": {
    "gn:admin1_code":"36.0",
    "gn:asciiname":"Dobo",
    "gn:country_code":"ID",
    "gn:dem":78,
    "gn:feature_class":"P",
    "gn:feature_code":"PPL",
    "gn:name":"Dobo",
    "gn:population":0,
    "gn:timezone":"Asia/Jayapura",
    "iso:country":"ID",
    "name:ind_x_preferred":[
        "Dobo"
    ],
    "wof:name":"Dobo",
    "wof:placetype":"locality"
},
  "geometry": {"coordinates":[138.8407,-2.3399],"type":"Point"}
}