{
  "type": "Feature",
  "properties": {
    "gn:admin1_code":"8.0",
    "gn:asciiname":"Ludelep",
    "gn:country_code":"ID",
    "gn:dem":47,
    "gn:feature_class":"P",
    "gn:feature_code":"PPL",
    "gn:name":"Ludelep",
    "gn:population":0,
    "gn:timezone":"Asia/Jakarta",
    "iso:country":"ID",
    "name:ind_x_preferred":[
        "Ludelep"
    ],
    "wof:name":"Ludelep",
    "wof:placetype":"locality"
},
  "geometry": {"coordinates":[111.53879999999999,-8.2925],"type":"Point"}
}