{
  "type": "Feature",
  "properties": {
    "gn:admin1_code":"15.0",
    "gn:asciiname":"Pagersari",
    "gn:country_code":"ID",
    "gn:dem":130,
    "gn:feature_class":"P",
    "gn:feature_code":"PPL",
    "gn:name":"Pagersari",
    "gn:population":0,
    "gn:timezone":"Asia/Jakarta",
    "iso:country":"ID",
    "name:ind_x_preferred":[
        "Pagersari"
    ],
    "wof:name":"Pagersari",
    "wof:placetype":"locality"
},
  "geometry": {"coordinates":[104.94001000000002,-5.36662],"type":"Point"}
}