{
  "type": "Feature",
  "properties": {
    "gn:admin1_code":"30.0",
    "gn:asciiname":"Cikedewul",
    "gn:country_code":"ID",
    "gn:dem":292,
    "gn:feature_class":"P",
    "gn:feature_code":"PPL",
    "gn:name":"Cikedewul",
    "gn:population":0,
    "gn:timezone":"Asia/Jakarta",
    "iso:country":"ID",
    "name:ind_x_preferred":[
        "Cikedewul"
    ],
    "name:und_x_variant":[
        "Tjikamoel"
    ],
    "wof:name":"Cikedewul",
    "wof:placetype":"locality"
},
  "geometry": {"coordinates":[108.1853,-7.3885],"type":"Point"}
}