{
  "type": "Feature",
  "properties": {
    "gn:country":"ID",
    "gn:fcode":"PPL",
    "gn:pop":0,
    "iso:country":"ID",
    "name:eng_x_preferred":[
        "Districts of North Sumatra"
    ],
    "name:unk_x_variant":[
        "Udjung Runggu"
    ],
    "qs:name":"Ujung Runggu",
    "qs:name_adm0":"Indonesia",
    "qs:name_adm1":"Sumatera Utara",
    "qs:photos":25,
    "qs:photos_1k":5,
    "qs:photos_9k":1,
    "qs:photos_9r":1,
    "qs:photos_all":25,
    "qs:photos_sr":1,
    "qs:placetype":"Town",
    "qs:pop_sr":"0",
    "wd:wordcount":1202,
    "wof:lang_x_official":[
        "ind"
    ],
    "wof:lang_x_spoken":[
        "ind",
        "eng"
    ],
    "wof:name":"Ujung Runggu",
    "wof:placetype":"locality",
    "wof:population":0
},
  "geometry": {"coordinates":[98.93333,2.45],"type":"Point"}
}