{
  "type": "Feature",
  "properties": {
    "gn:admin1_code":"7.0",
    "gn:asciiname":"Bulurejo",
    "gn:country_code":"ID",
    "gn:dem":399,
    "gn:feature_class":"P",
    "gn:feature_code":"PPL",
    "gn:name":"Bulurejo",
    "gn:population":0,
    "gn:timezone":"Asia/Jakarta",
    "iso:country":"ID",
    "wof:name":"Bulurejo",
    "wof:placetype":"locality"
},
  "geometry": {"coordinates":[110.49527999999999,-7.66528],"type":"Point"}
}