{
  "type": "Feature",
  "properties": {
    "gn:admin1_code":"8.0",
    "gn:asciiname":"Sumbersih",
    "gn:country_code":"ID",
    "gn:dem":380,
    "gn:feature_class":"P",
    "gn:feature_code":"PPL",
    "gn:name":"Sumbersih",
    "gn:population":0,
    "gn:timezone":"Asia/Jakarta",
    "iso:country":"ID",
    "name:ind_x_preferred":[
        "Sumbersih"
    ],
    "wof:name":"Sumbersih",
    "wof:placetype":"locality"
},
  "geometry": {"coordinates":[112.4743,-8.3085],"type":"Point"}
}