{
  "type": "Feature",
  "properties": {
    "gn:admin1_code":"30.0",
    "gn:asciiname":"Rancawiru",
    "gn:country_code":"ID",
    "gn:dem":158,
    "gn:feature_class":"P",
    "gn:feature_code":"PPL",
    "gn:name":"Rancawiru",
    "gn:population":0,
    "gn:timezone":"Asia/Jakarta",
    "iso:country":"ID",
    "name:ind_x_preferred":[
        "Rancawiru"
    ],
    "wof:name":"Rancawiru",
    "wof:placetype":"locality"
},
  "geometry": {"coordinates":[108.3823,-7.3102],"type":"Point"}
}