{
  "type": "Feature",
  "properties": {
    "gn:admin1_code":"18",
    "gn:asciiname":"Tonbesi",
    "gn:country_code":"ID",
    "gn:dem":722,
    "gn:feature_class":"P",
    "gn:feature_code":"PPL",
    "gn:name":"Tonbesi",
    "gn:population":0,
    "gn:timezone":"Asia/Makassar",
    "iso:country":"ID",
    "wof:name":"Tonbesi",
    "wof:placetype":"locality"
},
  "geometry": {"coordinates":[124.54667000000001,-9.35528],"type":"Point"}
}