{
  "type": "Feature",
  "properties": {
    "gn:admin1_code":"33",
    "gn:asciiname":"Masigit",
    "gn:country_code":"ID",
    "gn:dem":42,
    "gn:feature_class":"P",
    "gn:feature_code":"PPL",
    "gn:name":"Masigit",
    "gn:population":0,
    "gn:timezone":"Asia/Jakarta",
    "iso:country":"ID",
    "name:ind_x_preferred":[
        "Masigit"
    ],
    "wof:name":"Masigit",
    "wof:placetype":"locality"
},
  "geometry": {"coordinates":[106.10939999999999,-6.0801],"type":"Point"}
}