{
  "type": "Feature",
  "properties": {
    "gn:admin1_code":"18.0",
    "gn:asciiname":"Karieta",
    "gn:country_code":"ID",
    "gn:dem":819,
    "gn:feature_class":"P",
    "gn:feature_code":"PPL",
    "gn:name":"Karieta",
    "gn:population":0,
    "gn:timezone":"Asia/Makassar",
    "iso:country":"ID",
    "name:ind_x_preferred":[
        "Karieta"
    ],
    "wof:name":"Karieta",
    "wof:placetype":"locality"
},
  "geometry": {"coordinates":[124.6699,-8.2321],"type":"Point"}
}