{
  "type": "Feature",
  "properties": {
    "gn:admin1_code":"38",
    "gn:asciiname":"Maranae",
    "gn:country_code":"ID",
    "gn:dem":5,
    "gn:feature_class":"P",
    "gn:feature_code":"PPL",
    "gn:name":"Maranae",
    "gn:population":0,
    "gn:timezone":"Asia/Makassar",
    "iso:country":"ID",
    "name:ind_x_preferred":[
        "Maranae"
    ],
    "wof:name":"Maranae",
    "wof:placetype":"locality"
},
  "geometry": {"coordinates":[119.61579999999999,-4.441],"type":"Point"}
}