{
  "type": "Feature",
  "properties": {
    "gn:admin1_code":"18.0",
    "gn:asciiname":"Raintobi",
    "gn:country_code":"ID",
    "gn:dem":60,
    "gn:feature_class":"P",
    "gn:feature_code":"PPL",
    "gn:name":"Raintobi",
    "gn:population":0,
    "gn:timezone":"Asia/Makassar",
    "iso:country":"ID",
    "name:ind_x_preferred":[
        "Raintobi"
    ],
    "wof:name":"Raintobi",
    "wof:placetype":"locality"
},
  "geometry": {"coordinates":[123.51246,-8.24055],"type":"Point"}
}