{
  "type": "Feature",
  "properties": {
    "gn:admin1_code":"31",
    "gn:asciiname":"Airprang",
    "gn:country_code":"ID",
    "gn:dem":43,
    "gn:feature_class":"P",
    "gn:feature_code":"PPL",
    "gn:name":"Airprang",
    "gn:population":0,
    "gn:timezone":"Asia/Makassar",
    "iso:country":"ID",
    "name:ind_x_preferred":[
        "Airprang"
    ],
    "wof:lang_x_official":[
        "ind"
    ],
    "wof:lang_x_spoken":[
        "ind",
        "eng"
    ],
    "wof:name":"Airprang",
    "wof:placetype":"locality"
},
  "geometry": {"coordinates":[125.2337,1.48088],"type":"Point"}
}