{
  "type": "Feature",
  "properties": {
    "gn:admin1_code":"30",
    "gn:asciiname":"Pasirsereh",
    "gn:country_code":"ID",
    "gn:dem":689,
    "gn:feature_class":"P",
    "gn:feature_code":"PPL",
    "gn:name":"Pasirsereh",
    "gn:population":0,
    "gn:timezone":"Asia/Jakarta",
    "iso:country":"ID",
    "name:ind_x_preferred":[
        "Pasirsereh"
    ],
    "wof:name":"Pasirsereh",
    "wof:placetype":"locality"
},
  "geometry": {"coordinates":[107.43917,-6.99806],"type":"Point"}
}