{
  "type": "Feature",
  "properties": {
    "gn:admin1_code":"8.0",
    "gn:asciiname":"Ketro",
    "gn:country_code":"ID",
    "gn:dem":529,
    "gn:feature_class":"P",
    "gn:feature_code":"PPL",
    "gn:name":"Ketro",
    "gn:population":0,
    "gn:timezone":"Asia/Jakarta",
    "iso:country":"ID",
    "name:ind_x_preferred":[
        "Ketro"
    ],
    "wof:name":"Ketro",
    "wof:placetype":"locality"
},
  "geometry": {"coordinates":[111.19917,-8.17639],"type":"Point"}
}