{
  "type": "Feature",
  "properties": {
    "gn:admin1_code":"7.0",
    "gn:asciiname":"Kejobong",
    "gn:country_code":"ID",
    "gn:dem":159,
    "gn:feature_class":"P",
    "gn:feature_code":"PPL",
    "gn:name":"Kejobong",
    "gn:population":0,
    "gn:timezone":"Asia/Jakarta",
    "iso:country":"ID",
    "name:ind_x_preferred":[
        "Kejobong"
    ],
    "name:und_x_variant":[
        "Kedjobong"
    ],
    "wof:lang_x_official":[
        "ind"
    ],
    "wof:lang_x_spoken":[
        "ind",
        "eng"
    ],
    "wof:name":"Kejobong",
    "wof:placetype":"locality"
},
  "geometry": {"coordinates":[109.50861,-7.39083],"type":"Point"}
}