{
  "type": "Feature",
  "properties": {
    "gn:admin1_code":"7.0",
    "gn:asciiname":"Karangpetir",
    "gn:country_code":"ID",
    "gn:dem":23,
    "gn:feature_class":"P",
    "gn:feature_code":"PPL",
    "gn:name":"Karangpetir",
    "gn:population":0,
    "gn:timezone":"Asia/Jakarta",
    "iso:country":"ID",
    "name:ind_x_preferred":[
        "Karangpetir"
    ],
    "wof:name":"Karangpetir",
    "wof:placetype":"locality"
},
  "geometry": {"coordinates":[109.39806000000002,-7.6175],"type":"Point"}
}