{
  "type": "Feature",
  "properties": {
    "gn:admin1_code":"30",
    "gn:asciiname":"Pasekon",
    "gn:country_code":"ID",
    "gn:dem":801,
    "gn:feature_class":"P",
    "gn:feature_code":"PPL",
    "gn:name":"Pasekon",
    "gn:population":0,
    "gn:timezone":"Asia/Jakarta",
    "iso:country":"ID",
    "name:ind_x_preferred":[
        "Pasekon"
    ],
    "wof:name":"Pasekon",
    "wof:placetype":"locality"
},
  "geometry": {"coordinates":[106.99722,-6.89333],"type":"Point"}
}