{
  "type": "Feature",
  "properties": {
    "gn:admin1_code":"38.0",
    "gn:asciiname":"Asa",
    "gn:country_code":"ID",
    "gn:dem":820,
    "gn:feature_class":"P",
    "gn:feature_code":"PPL",
    "gn:name":"Asa",
    "gn:population":0,
    "gn:timezone":"Asia/Makassar",
    "iso:country":"ID",
    "name:cat_x_preferred":[
        "Asa"
    ],
    "name:ceb_x_preferred":[
        "Asa"
    ],
    "name:fin_x_preferred":[
        "Asa"
    ],
    "name:heb_x_preferred":[
        "\u05d0\u05e1\u05d0"
    ],
    "name:ind_x_preferred":[
        "Asa"
    ],
    "name:jpn_x_preferred":[
        "\u30a2\u30b5"
    ],
    "name:lmo_x_preferred":[
        "As\u00e0"
    ],
    "name:nld_x_preferred":[
        "Asa"
    ],
    "name:pol_x_preferred":[
        "Asa"
    ],
    "name:por_x_preferred":[
        "Asa"
    ],
    "name:spa_x_preferred":[
        "Asa"
    ],
    "name:swe_x_preferred":[
        "Asa"
    ],
    "wof:lang_x_official":[
        "ind"
    ],
    "wof:lang_x_spoken":[
        "ind",
        "eng"
    ],
    "wof:name":"Asa",
    "wof:placetype":"locality"
},
  "geometry": {"coordinates":[119.91549999999999,-2.974],"type":"Point"}
}