{
  "type": "Feature",
  "properties": {
    "gn:admin1_code":"12.0",
    "gn:asciiname":"Gemuruh",
    "gn:country_code":"ID",
    "gn:dem":16,
    "gn:feature_class":"P",
    "gn:feature_code":"PPL",
    "gn:name":"Gemuruh",
    "gn:population":0,
    "gn:timezone":"Asia/Makassar",
    "iso:country":"ID",
    "name:ind_x_preferred":[
        "Gemuruh"
    ],
    "name:und_x_variant":[
        "Gomoeroe",
        "Gemoeroe",
        "Gemuru"
    ],
    "wof:name":"Gemuruh",
    "wof:placetype":"locality"
},
  "geometry": {"coordinates":[116.0719,-3.9598],"type":"Point"}
}