{
  "type": "Feature",
  "properties": {
    "gn:admin1_code":"7",
    "gn:asciiname":"Temanjang",
    "gn:country_code":"ID",
    "gn:dem":140,
    "gn:feature_class":"P",
    "gn:feature_code":"PPLA4",
    "gn:name":"Temanjang",
    "gn:population":0,
    "gn:timezone":"Asia/Jakarta",
    "iso:country":"ID",
    "name:ind_x_preferred":[
        "Temanjang"
    ],
    "wof:lang_x_official":[
        "ind"
    ],
    "wof:lang_x_spoken":[
        "ind",
        "eng"
    ],
    "wof:name":"Temanjang",
    "wof:placetype":"locality"
},
  "geometry": {"coordinates":[111.3929,-7.0931],"type":"Point"}
}