{
  "type": "Feature",
  "properties": {
    "gn:admin1_code":"7",
    "gn:asciiname":"Ngrambe",
    "gn:country_code":"ID",
    "gn:dem":357,
    "gn:feature_class":"P",
    "gn:feature_code":"PPL",
    "gn:name":"Ngrambe",
    "gn:population":0,
    "gn:timezone":"Asia/Jakarta",
    "iso:country":"ID",
    "name:ind_x_preferred":[
        "Ngrambe"
    ],
    "wof:name":"Ngrambe",
    "wof:placetype":"locality"
},
  "geometry": {"coordinates":[110.89449999999999,-6.536],"type":"Point"}
}