{
  "type": "Feature",
  "properties": {
    "gn:admin1_code":"0.0",
    "gn:asciiname":"Taban",
    "gn:country_code":"ID",
    "gn:dem":16,
    "gn:feature_class":"P",
    "gn:feature_code":"PPL",
    "gn:name":"Taban",
    "gn:population":0,
    "gn:timezone":"Asia/Jakarta",
    "iso:country":"ID",
    "name:ceb_x_preferred":[
        "Taban"
    ],
    "name:deu_x_preferred":[
        "Taban"
    ],
    "name:hun_x_preferred":[
        "Tab\u00e1n"
    ],
    "name:swe_x_preferred":[
        "Taban"
    ],
    "name:tur_x_preferred":[
        "Taban"
    ],
    "wof:lang_x_official":[
        "ind"
    ],
    "wof:lang_x_spoken":[
        "ind",
        "eng"
    ],
    "wof:name":"Taban",
    "wof:placetype":"locality"
},
  "geometry": {"coordinates":[112.16667,-7.16667],"type":"Point"}
}