{
  "type": "Feature",
  "properties": {
    "gn:admin1_code":"8.0",
    "gn:asciiname":"Congaben",
    "gn:country_code":"ID",
    "gn:dem":23,
    "gn:feature_class":"P",
    "gn:feature_code":"PPL",
    "gn:name":"Congaben",
    "gn:population":0,
    "gn:timezone":"Asia/Jakarta",
    "iso:country":"ID",
    "name:ind_x_preferred":[
        "Congaben"
    ],
    "wof:name":"Congaben",
    "wof:placetype":"locality"
},
  "geometry": {"coordinates":[113.43729999999999,-7.1484],"type":"Point"}
}