{
  "type": "Feature",
  "properties": {
    "gn:admin1_code":"7.0",
    "gn:asciiname":"Padangsari",
    "gn:country_code":"ID",
    "gn:dem":408,
    "gn:feature_class":"P",
    "gn:feature_code":"PPL",
    "gn:name":"Padangsari",
    "gn:population":0,
    "gn:timezone":"Asia/Jakarta",
    "iso:country":"ID",
    "wof:name":"Padangsari",
    "wof:placetype":"locality"
},
  "geometry": {"coordinates":[110.63778000000001,-7.39861],"type":"Point"}
}