{
  "type": "Feature",
  "properties": {
    "gn:admin1_code":"7.0",
    "gn:asciiname":"Gesikan",
    "gn:country_code":"ID",
    "gn:dem":394,
    "gn:feature_class":"P",
    "gn:feature_code":"PPL",
    "gn:name":"Gesikan",
    "gn:population":0,
    "gn:timezone":"Asia/Jakarta",
    "iso:country":"ID",
    "wof:name":"Gesikan",
    "wof:placetype":"locality"
},
  "geometry": {"coordinates":[110.33778,-7.63917],"type":"Point"}
}