{
  "type": "Feature",
  "properties": {
    "gn:admin1_code":"30.0",
    "gn:asciiname":"Cintabodas",
    "gn:country_code":"ID",
    "gn:dem":451,
    "gn:feature_class":"P",
    "gn:feature_code":"PPL",
    "gn:name":"Cintabodas",
    "gn:population":0,
    "gn:timezone":"Asia/Jakarta",
    "iso:country":"ID",
    "name:ind_x_preferred":[
        "Cintabodas"
    ],
    "name:und_x_variant":[
        "Tjintabodas",
        "Cintabodas"
    ],
    "wof:lang_x_official":[
        "ind"
    ],
    "wof:lang_x_spoken":[
        "ind",
        "eng"
    ],
    "wof:name":"Cintabodas",
    "wof:placetype":"locality"
},
  "geometry": {"coordinates":[108.0515,-7.6076],"type":"Point"}
}