{
  "type": "Feature",
  "properties": {
    "gn:admin1_code":"8",
    "gn:asciiname":"Jabung",
    "gn:country_code":"ID",
    "gn:dem":51,
    "gn:feature_class":"P",
    "gn:feature_code":"PPL",
    "gn:name":"Jabung",
    "gn:population":0,
    "gn:timezone":"Asia/Jakarta",
    "iso:country":"ID",
    "name:ind_x_preferred":[
        "Jabung"
    ],
    "name:ind_x_variant":[
        "Candi Jabung"
    ],
    "name:jav_x_preferred":[
        "Candhi Jabung"
    ],
    "wof:lang_x_official":[
        "ind"
    ],
    "wof:lang_x_spoken":[
        "ind",
        "eng"
    ],
    "wof:name":"Jabung",
    "wof:placetype":"locality"
},
  "geometry": {"coordinates":[112.7727,-7.1243],"type":"Point"}
}