{
  "type": "Feature",
  "properties": {
    "gn:admin1_code":"17",
    "gn:asciiname":"Rancak",
    "gn:country_code":"ID",
    "gn:dem":240,
    "gn:feature_class":"P",
    "gn:feature_code":"PPL",
    "gn:name":"Rancak",
    "gn:population":0,
    "gn:timezone":"Asia/Makassar",
    "iso:country":"ID",
    "name:ind_x_preferred":[
        "Rancak"
    ],
    "wof:name":"Rancak",
    "wof:placetype":"locality"
},
  "geometry": {"coordinates":[116.3289,-8.7009],"type":"Point"}
}