{
  "type": "Feature",
  "properties": {
    "gn:admin1_code":"2.0",
    "gn:asciiname":"Tumbu Kelod",
    "gn:country_code":"ID",
    "gn:dem":99,
    "gn:feature_class":"P",
    "gn:feature_code":"PPL",
    "gn:name":"Tumbu Kelod",
    "gn:population":0,
    "gn:timezone":"Asia/Makassar",
    "iso:country":"ID",
    "name:ind_x_preferred":[
        "Tumbu Kelod"
    ],
    "wof:name":"Tumbu Kelod",
    "wof:placetype":"locality"
},
  "geometry": {"coordinates":[115.6279,-8.4476],"type":"Point"}
}