{
  "type": "Feature",
  "properties": {
    "gn:admin1_code":"7",
    "gn:asciiname":"Bubakan",
    "gn:country_code":"ID",
    "gn:dem":525,
    "gn:feature_class":"P",
    "gn:feature_code":"PPL",
    "gn:name":"Bubakan",
    "gn:population":0,
    "gn:timezone":"Asia/Jakarta",
    "iso:country":"ID",
    "name:ind_x_preferred":[
        "Bubakan"
    ],
    "wof:name":"Bubakan",
    "wof:placetype":"locality"
},
  "geometry": {"coordinates":[111.07250000000001,-7.56833],"type":"Point"}
}