{
  "type": "Feature",
  "properties": {
    "gn:admin1_code":"8.0",
    "gn:asciiname":"Nglumbu",
    "gn:country_code":"ID",
    "gn:dem":51,
    "gn:feature_class":"P",
    "gn:feature_code":"PPL",
    "gn:name":"Nglumbu",
    "gn:population":0,
    "gn:timezone":"Asia/Jakarta",
    "iso:country":"ID",
    "name:ind_x_preferred":[
        "Nglumbu"
    ],
    "wof:name":"Nglumbu",
    "wof:placetype":"locality"
},
  "geometry": {"coordinates":[111.09944,-8.17028],"type":"Point"}
}