{
  "type": "Feature",
  "properties": {
    "gn:admin1_code":"26",
    "gn:asciiname":"Besilamhulu",
    "gn:country_code":"ID",
    "gn:dem":38,
    "gn:feature_class":"P",
    "gn:feature_code":"PPL",
    "gn:name":"Besilamhulu",
    "gn:population":0,
    "gn:timezone":"Asia/Jakarta",
    "iso:country":"ID",
    "name:ind_x_preferred":[
        "Besilamhulu"
    ],
    "wof:name":"Besilamhulu",
    "wof:placetype":"locality"
},
  "geometry": {"coordinates":[98.30070000000001,3.6675],"type":"Point"}
}