{
  "type": "Feature",
  "properties": {
    "gn:admin1_code":"7.0",
    "gn:asciiname":"Gegerjeruk",
    "gn:country_code":"ID",
    "gn:dem":497,
    "gn:feature_class":"P",
    "gn:feature_code":"PPL",
    "gn:name":"Gegerjeruk",
    "gn:population":0,
    "gn:timezone":"Asia/Jakarta",
    "iso:country":"ID",
    "wof:name":"Gegerjeruk",
    "wof:placetype":"locality"
},
  "geometry": {"coordinates":[110.00694,-7.58389],"type":"Point"}
}