{
  "type": "Feature",
  "properties": {
    "gn:admin1_code":"30.0",
    "gn:asciiname":"Saunggunung",
    "gn:country_code":"ID",
    "gn:dem":550,
    "gn:feature_class":"P",
    "gn:feature_code":"PPL",
    "gn:name":"Saunggunung",
    "gn:population":0,
    "gn:timezone":"Asia/Jakarta",
    "iso:country":"ID",
    "name:ind_x_preferred":[
        "Saunggunung"
    ],
    "name:und_x_variant":[
        "Saoenggoenoeng"
    ],
    "wof:lang_x_official":[
        "ind"
    ],
    "wof:lang_x_spoken":[
        "ind",
        "eng"
    ],
    "wof:name":"Saunggunung",
    "wof:placetype":"locality"
},
  "geometry": {"coordinates":[108.0715,-7.0445],"type":"Point"}
}