{
  "type": "Feature",
  "properties": {
    "gn:admin1_code":"7.0",
    "gn:asciiname":"Weru Lor",
    "gn:country_code":"ID",
    "gn:dem":405,
    "gn:feature_class":"P",
    "gn:feature_code":"PPL",
    "gn:name":"Weru Lor",
    "gn:population":0,
    "gn:timezone":"Asia/Jakarta",
    "iso:country":"ID",
    "wof:name":"Weru Lor",
    "wof:placetype":"locality"
},
  "geometry": {"coordinates":[110.49806,-7.66167],"type":"Point"}
}