{
  "type": "Feature",
  "properties": {
    "gn:admin1_code":"8",
    "gn:asciiname":"Ngandu",
    "gn:country_code":"ID",
    "gn:dem":769,
    "gn:feature_class":"P",
    "gn:feature_code":"PPL",
    "gn:name":"Ngandu",
    "gn:population":0,
    "gn:timezone":"Asia/Jakarta",
    "iso:country":"ID",
    "name:ceb_x_preferred":[
        "Ngandu"
    ],
    "name:ind_x_preferred":[
        "Ngandu"
    ],
    "name:swe_x_preferred":[
        "Ngandu"
    ],
    "wof:lang_x_official":[
        "ind"
    ],
    "wof:lang_x_spoken":[
        "ind",
        "eng"
    ],
    "wof:name":"Ngandu",
    "wof:placetype":"locality"
},
  "geometry": {"coordinates":[111.30500000000001,-8.10083],"type":"Point"}
}