{
  "type": "Feature",
  "properties": {
    "gn:admin1_code":"30.0",
    "gn:asciiname":"Karangjaya",
    "gn:country_code":"ID",
    "gn:dem":344,
    "gn:feature_class":"P",
    "gn:feature_code":"PPL",
    "gn:name":"Karangjaya",
    "gn:population":0,
    "gn:timezone":"Asia/Jakarta",
    "iso:country":"ID",
    "name:ind_x_preferred":[
        "Karangjaya"
    ],
    "wof:name":"Karangjaya",
    "wof:placetype":"locality"
},
  "geometry": {"coordinates":[108.27200000000001,-7.3756],"type":"Point"}
}