{
  "type": "Feature",
  "properties": {
    "gn:admin1_code":"30.0",
    "gn:asciiname":"Cibentang",
    "gn:country_code":"ID",
    "gn:dem":281,
    "gn:feature_class":"P",
    "gn:feature_code":"PPL",
    "gn:name":"Cibentang",
    "gn:population":0,
    "gn:timezone":"Asia/Jakarta",
    "iso:country":"ID",
    "name:ind_x_preferred":[
        "Cibentang"
    ],
    "wof:name":"Cibentang",
    "wof:placetype":"locality"
},
  "geometry": {"coordinates":[107.84496,-7.55375],"type":"Point"}
}