{
  "type": "Feature",
  "properties": {
    "gn:admin1_code":"8",
    "gn:asciiname":"Morsabah",
    "gn:country_code":"ID",
    "gn:dem":35,
    "gn:feature_class":"P",
    "gn:feature_code":"PPL",
    "gn:name":"Morsabah",
    "gn:population":0,
    "gn:timezone":"Asia/Jakarta",
    "iso:country":"ID",
    "name:ind_x_preferred":[
        "Morsabah"
    ],
    "wof:name":"Morsabah",
    "wof:placetype":"locality"
},
  "geometry": {"coordinates":[112.8647,-7.0829],"type":"Point"}
}