{
  "type": "Feature",
  "properties": {
    "gn:admin1_code":"7.0",
    "gn:asciiname":"Kemirikerep Kidul",
    "gn:country_code":"ID",
    "gn:dem":955,
    "gn:feature_class":"P",
    "gn:feature_code":"PPL",
    "gn:name":"Kemirikerep Kidul",
    "gn:population":0,
    "gn:timezone":"Asia/Jakarta",
    "iso:country":"ID",
    "wof:name":"Kemirikerep Kidul",
    "wof:placetype":"locality"
},
  "geometry": {"coordinates":[110.14306000000001,-7.37889],"type":"Point"}
}