{
  "type": "Feature",
  "properties": {
    "gn:admin1_code":"30",
    "gn:asciiname":"Cibeber",
    "gn:cc2":"ID",
    "gn:country_code":"ID",
    "gn:dem":95,
    "gn:feature_class":"P",
    "gn:feature_code":"PPL",
    "gn:name":"Cibeber",
    "gn:population":0,
    "gn:timezone":"Asia/Jakarta",
    "iso:country":"ID",
    "name:und_x_variant":[
        "Tjibeber",
        "Cibeber"
    ],
    "wof:name":"Cibeber",
    "wof:placetype":"locality"
},
  "geometry": {"coordinates":[106.97167,-6.455],"type":"Point"}
}