{
  "type": "Feature",
  "properties": {
    "gn:admin1_code":"30.0",
    "gn:asciiname":"Cimentek",
    "gn:country_code":"ID",
    "gn:dem":15,
    "gn:feature_class":"P",
    "gn:feature_code":"PPL",
    "gn:name":"Cimentek",
    "gn:population":0,
    "gn:timezone":"Asia/Jakarta",
    "iso:country":"ID",
    "name:ind_x_preferred":[
        "Cimentek"
    ],
    "name:und_x_variant":[
        "Tjimentek"
    ],
    "wof:name":"Cimentek",
    "wof:placetype":"locality"
},
  "geometry": {"coordinates":[108.6352,-7.4621],"type":"Point"}
}