{
  "type": "Feature",
  "properties": {
    "gn:admin1_code":"2.0",
    "gn:asciiname":"Bukit",
    "gn:country_code":"ID",
    "gn:dem":65,
    "gn:feature_class":"P",
    "gn:feature_code":"PPL",
    "gn:name":"Bukit",
    "gn:population":0,
    "gn:timezone":"Asia/Makassar",
    "iso:country":"ID",
    "name:ceb_x_preferred":[
        "Bukit"
    ],
    "name:ind_x_preferred":[
        "Bukit"
    ],
    "name:nld_x_preferred":[
        "Bukit"
    ],
    "name:swe_x_preferred":[
        "Bukit"
    ],
    "wof:lang_x_official":[
        "ind"
    ],
    "wof:lang_x_spoken":[
        "ind",
        "eng"
    ],
    "wof:name":"Bukit",
    "wof:placetype":"locality"
},
  "geometry": {"coordinates":[115.51690000000001,-8.2236],"type":"Point"}
}