{
  "type": "Feature",
  "properties": {
    "gn:admin1_code":"8",
    "gn:asciiname":"Duwet",
    "gn:country_code":"ID",
    "gn:dem":360,
    "gn:feature_class":"P",
    "gn:feature_code":"PPL",
    "gn:name":"Duwet",
    "gn:population":0,
    "gn:timezone":"Asia/Jakarta",
    "iso:country":"ID",
    "name:ind_x_preferred":[
        "Duwet"
    ],
    "wof:name":"Duwet",
    "wof:placetype":"locality"
},
  "geometry": {"coordinates":[111.32528000000001,-7.74861],"type":"Point"}
}