{
  "type": "Feature",
  "properties": {
    "gn:admin1_code":"17",
    "gn:asciiname":"Temas Daya",
    "gn:country_code":"ID",
    "gn:dem":295,
    "gn:feature_class":"P",
    "gn:feature_code":"PPL",
    "gn:name":"Temas Daya",
    "gn:population":0,
    "gn:timezone":"Asia/Makassar",
    "iso:country":"ID",
    "name:ind_x_preferred":[
        "Temas Daya"
    ],
    "wof:name":"Temas Daya",
    "wof:placetype":"locality"
},
  "geometry": {"coordinates":[116.2516,-8.5498],"type":"Point"}
}