{
  "type": "Feature",
  "properties": {
    "gn:admin1_code":"07",
    "gn:asciiname":"Candi",
    "gn:country_code":"ID",
    "gn:dem":270,
    "gn:feature_class":"P",
    "gn:feature_code":"PPL",
    "gn:name":"Candi",
    "gn:population":0,
    "gn:timezone":"Asia/Jakarta",
    "iso:country":"ID",
    "name:und_x_variant":[
        "Candi Dua",
        "Tjandi 2",
        "Candi"
    ],
    "wof:name":"Candi",
    "wof:placetype":"locality"
},
  "geometry": {"coordinates":[110.65222,-7.43028],"type":"Point"}
}