{
  "type": "Feature",
  "properties": {
    "gn:admin1_code":"38.0",
    "gn:asciiname":"Danteguci",
    "gn:country_code":"ID",
    "gn:dem":944,
    "gn:feature_class":"P",
    "gn:feature_code":"PPL",
    "gn:name":"Danteguci",
    "gn:population":0,
    "gn:timezone":"Asia/Makassar",
    "iso:country":"ID",
    "name:ind_x_preferred":[
        "Danteguci"
    ],
    "wof:name":"Danteguci",
    "wof:placetype":"locality"
},
  "geometry": {"coordinates":[119.97732000000001,-3.55693],"type":"Point"}
}