{
  "type": "Feature",
  "properties": {
    "gn:admin1_code":"18",
    "gn:asciiname":"Damar",
    "gn:country_code":"ID",
    "gn:dem":940,
    "gn:feature_class":"P",
    "gn:feature_code":"PPL",
    "gn:name":"Damar",
    "gn:population":0,
    "gn:timezone":"Asia/Makassar",
    "iso:country":"ID",
    "name:aze_x_preferred":[
        "Damar sistemi"
    ],
    "name:ceb_x_preferred":[
        "Damar"
    ],
    "name:deu_x_preferred":[
        "Damar"
    ],
    "name:ind_x_preferred":[
        "Damar"
    ],
    "name:ita_x_preferred":[
        "Damar"
    ],
    "name:jav_x_preferred":[
        "Damar"
    ],
    "name:msa_x_preferred":[
        "Damar"
    ],
    "name:nld_x_preferred":[
        "Damar"
    ],
    "name:por_x_preferred":[
        "Damar"
    ],
    "name:swe_x_preferred":[
        "Damar"
    ],
    "name:tur_x_preferred":[
        "Damar"
    ],
    "wof:name":"Damar",
    "wof:placetype":"locality"
},
  "geometry": {"coordinates":[120.30500000000001,-8.6809],"type":"Point"}
}