{
  "type": "Feature",
  "properties": {
    "gn:admin1_code":"18",
    "gn:asciiname":"Mbuja",
    "gn:country_code":"ID",
    "gn:dem":611,
    "gn:feature_class":"P",
    "gn:feature_code":"PPL",
    "gn:name":"Mbuja",
    "gn:population":0,
    "gn:timezone":"Asia/Makassar",
    "iso:country":"ID",
    "name:ind_x_preferred":[
        "Mbuja"
    ],
    "wof:name":"Mbuja",
    "wof:placetype":"locality"
},
  "geometry": {"coordinates":[121.6474,-8.7593],"type":"Point"}
}