{
  "type": "Feature",
  "properties": {
    "gn:admin1_code":"41",
    "gn:asciiname":"Landongi",
    "gn:country_code":"ID",
    "gn:dem":102,
    "gn:feature_class":"P",
    "gn:feature_code":"PPL",
    "gn:name":"Landongi",
    "gn:population":0,
    "gn:timezone":"Asia/Makassar",
    "iso:country":"ID",
    "name:ind_x_preferred":[
        "Landongi"
    ],
    "wof:name":"Landongi",
    "wof:placetype":"locality"
},
  "geometry": {"coordinates":[119.08329999999999,-3.4013],"type":"Point"}
}