{
  "type": "Feature",
  "properties": {
    "gn:admin1_code":"38.0",
    "gn:asciiname":"Padangloang",
    "gn:country_code":"ID",
    "gn:dem":59,
    "gn:feature_class":"P",
    "gn:feature_code":"PPL",
    "gn:name":"Padangloang",
    "gn:population":0,
    "gn:timezone":"Asia/Makassar",
    "iso:country":"ID",
    "name:ind_x_preferred":[
        "Padangloang"
    ],
    "wof:name":"Padangloang",
    "wof:placetype":"locality"
},
  "geometry": {"coordinates":[120.26900000000001,-4.6038],"type":"Point"}
}