{
  "type": "Feature",
  "properties": {
    "gn:admin1_code":"8.0",
    "gn:asciiname":"Tajek Lor",
    "gn:country_code":"ID",
    "gn:dem":203,
    "gn:feature_class":"P",
    "gn:feature_code":"PPL",
    "gn:name":"Tajek Lor",
    "gn:population":0,
    "gn:timezone":"Asia/Jakarta",
    "iso:country":"ID",
    "name:ind_x_preferred":[
        "Tajek Lor"
    ],
    "wof:name":"Tajek Lor",
    "wof:placetype":"locality"
},
  "geometry": {"coordinates":[113.6036,-8.1431],"type":"Point"}
}