{
  "type": "Feature",
  "properties": {
    "gn:admin1_code":"30",
    "gn:asciiname":"Hegarmanah",
    "gn:country_code":"ID",
    "gn:dem":1053,
    "gn:feature_class":"P",
    "gn:feature_code":"PPL",
    "gn:name":"Hegarmanah",
    "gn:population":0,
    "gn:timezone":"Asia/Jakarta",
    "iso:country":"ID",
    "name:ind_x_preferred":[
        "Hegarmanah"
    ],
    "wof:name":"Hegarmanah",
    "wof:placetype":"locality"
},
  "geometry": {"coordinates":[107.4888,-7.0549],"type":"Point"}
}