{
  "type": "Feature",
  "properties": {
    "gn:admin1_code":"26",
    "gn:asciiname":"Muara Oreh Satu",
    "gn:country_code":"ID",
    "gn:dem":11,
    "gn:feature_class":"P",
    "gn:feature_code":"PPL",
    "gn:name":"Muara Oreh Satu",
    "gn:population":0,
    "gn:timezone":"Asia/Jakarta",
    "iso:country":"ID",
    "name:ind_x_preferred":[
        "Muara Oreh Satu"
    ],
    "name:und_x_variant":[
        "Muara Oreh 1"
    ],
    "wof:name":"Muara Oreh Satu",
    "wof:placetype":"locality"
},
  "geometry": {"coordinates":[98.2619,2.1545],"type":"Point"}
}