{
  "type": "Feature",
  "properties": {
    "gn:admin1_code":"18.0",
    "gn:asciiname":"Kaput",
    "gn:country_code":"ID",
    "gn:dem":464,
    "gn:feature_class":"P",
    "gn:feature_code":"PPL",
    "gn:name":"Kaput",
    "gn:population":0,
    "gn:timezone":"Asia/Makassar",
    "iso:country":"ID",
    "name:aze_x_preferred":[
        "Kaput"
    ],
    "name:ceb_x_preferred":[
        "K\u0101p\u016bt"
    ],
    "name:fas_x_preferred":[
        "\u06a9\u0627\u067e\u0648\u062a"
    ],
    "name:ind_x_preferred":[
        "Kaput"
    ],
    "name:msa_x_preferred":[
        "Kaput"
    ],
    "name:swe_x_preferred":[
        "K\u0101p\u016bt"
    ],
    "wof:name":"Kaput",
    "wof:placetype":"locality"
},
  "geometry": {"coordinates":[120.6767,-8.7727],"type":"Point"}
}