{
  "type": "Feature",
  "properties": {
    "gn:admin1_code":"38",
    "gn:asciiname":"Kuanglambe",
    "gn:country_code":"ID",
    "gn:dem":851,
    "gn:feature_class":"P",
    "gn:feature_code":"PPL",
    "gn:name":"Kuanglambe",
    "gn:population":0,
    "gn:timezone":"Asia/Makassar",
    "iso:country":"ID",
    "name:ind_x_preferred":[
        "Kuanglambe"
    ],
    "wof:name":"Kuanglambe",
    "wof:placetype":"locality"
},
  "geometry": {"coordinates":[119.8447,-3.0786],"type":"Point"}
}