{
  "type": "Feature",
  "properties": {
    "gn:admin1_code":"37",
    "gn:asciiname":"Liriklima",
    "gn:country_code":"ID",
    "gn:dem":43,
    "gn:feature_class":"P",
    "gn:feature_code":"PPL",
    "gn:name":"Liriklima",
    "gn:population":0,
    "gn:timezone":"Asia/Jakarta",
    "iso:country":"ID",
    "name:ind_x_preferred":[
        "Liriklima"
    ],
    "wof:name":"Liriklima",
    "wof:placetype":"locality"
},
  "geometry": {"coordinates":[102.19977,0.11731],"type":"Point"}
}