{
  "type": "Feature",
  "properties": {
    "gn:admin1_code":"33",
    "gn:asciiname":"Leuwiteureup",
    "gn:country_code":"ID",
    "gn:dem":76,
    "gn:feature_class":"P",
    "gn:feature_code":"PPL",
    "gn:name":"Leuwiteureup",
    "gn:population":0,
    "gn:timezone":"Asia/Jakarta",
    "iso:country":"ID",
    "name:ind_x_preferred":[
        "Leuwiteureup"
    ],
    "wof:name":"Leuwiteureup",
    "wof:placetype":"locality"
},
  "geometry": {"coordinates":[106.30710000000001,-6.3722],"type":"Point"}
}