{
  "type": "Feature",
  "properties": {
    "gn:admin1_code":"18.0",
    "gn:asciiname":"Oetuke",
    "gn:country_code":"ID",
    "gn:dem":459,
    "gn:feature_class":"P",
    "gn:feature_code":"PPLA4",
    "gn:name":"Oetuke",
    "gn:population":0,
    "gn:timezone":"Asia/Makassar",
    "iso:country":"ID",
    "name:und_x_variant":[
        "O\u00ebtoeke",
        "Oetuke"
    ],
    "wof:name":"Oetuke",
    "wof:placetype":"locality"
},
  "geometry": {"coordinates":[124.5543,-9.9909],"type":"Point"}
}