{
  "type": "Feature",
  "properties": {
    "gn:admin1_code":"7",
    "gn:asciiname":"Terem",
    "gn:country_code":"ID",
    "gn:dem":9,
    "gn:feature_class":"P",
    "gn:feature_code":"PPL",
    "gn:name":"Terem",
    "gn:population":0,
    "gn:timezone":"Asia/Jakarta",
    "iso:country":"ID",
    "name:fra_x_preferred":[
        "Terem"
    ],
    "name:ind_x_preferred":[
        "Terem"
    ],
    "wof:name":"Terem",
    "wof:placetype":"locality"
},
  "geometry": {"coordinates":[109.99472,-7.87972],"type":"Point"}
}