{
  "type": "Feature",
  "properties": {
    "gn:admin1_code":"7",
    "gn:asciiname":"Ngledok",
    "gn:country_code":"ID",
    "gn:dem":672,
    "gn:feature_class":"P",
    "gn:feature_code":"PPL",
    "gn:name":"Ngledok",
    "gn:population":0,
    "gn:timezone":"Asia/Jakarta",
    "iso:country":"ID",
    "name:ind_x_preferred":[
        "Ngledok"
    ],
    "wof:name":"Ngledok",
    "wof:placetype":"locality"
},
  "geometry": {"coordinates":[111.08972,-7.59417],"type":"Point"}
}