{
  "type": "Feature",
  "properties": {
    "gn:admin1_code":"10",
    "gn:asciiname":"Bedug",
    "gn:country_code":"ID",
    "gn:dem":200,
    "gn:feature_class":"P",
    "gn:feature_code":"PPL",
    "gn:name":"Bedug",
    "gn:population":0,
    "gn:timezone":"Asia/Jakarta",
    "iso:country":"ID",
    "name:bjn_x_preferred":[
        "Dauh"
    ],
    "name:bul_x_preferred":[
        "\u0411\u0435\u0434\u0443\u0433"
    ],
    "name:ind_x_preferred":[
        "Bedug"
    ],
    "name:jav_x_preferred":[
        "Bedhug"
    ],
    "name:por_x_preferred":[
        "Bedug"
    ],
    "name:sun_x_preferred":[
        "Bedug"
    ],
    "wof:name":"Bedug",
    "wof:placetype":"locality"
},
  "geometry": {"coordinates":[110.43639,-8.07083],"type":"Point"}
}