{
  "type": "Feature",
  "properties": {
    "gn:admin1_code":"8.0",
    "gn:asciiname":"Kaligentong",
    "gn:country_code":"ID",
    "gn:dem":944,
    "gn:feature_class":"P",
    "gn:feature_code":"PPL",
    "gn:name":"Kaligentong",
    "gn:population":0,
    "gn:timezone":"Asia/Jakarta",
    "iso:country":"ID",
    "name:ind_x_preferred":[
        "Kaligentong"
    ],
    "wof:name":"Kaligentong",
    "wof:placetype":"locality"
},
  "geometry": {"coordinates":[111.4883,-8.1348],"type":"Point"}
}