{
  "type": "Feature",
  "properties": {
    "gn:admin1_code":"30.0",
    "gn:asciiname":"Ciantenherang",
    "gn:country_code":"ID",
    "gn:dem":912,
    "gn:feature_class":"P",
    "gn:feature_code":"PPL",
    "gn:name":"Ciantenherang",
    "gn:population":0,
    "gn:timezone":"Asia/Jakarta",
    "iso:country":"ID",
    "name:ind_x_preferred":[
        "Ciantenherang"
    ],
    "name:und_x_variant":[
        "Tjianten",
        "Tjiantenherang"
    ],
    "wof:lang_x_official":[
        "ind"
    ],
    "wof:lang_x_spoken":[
        "ind",
        "eng"
    ],
    "wof:name":"Ciantenherang",
    "wof:placetype":"locality"
},
  "geometry": {"coordinates":[106.60833,-6.71833],"type":"Point"}
}