{
  "type": "Feature",
  "properties": {
    "gn:admin1_code":"8",
    "gn:asciiname":"Koteh",
    "gn:country_code":"ID",
    "gn:dem":33,
    "gn:feature_class":"P",
    "gn:feature_code":"PPL",
    "gn:name":"Koteh",
    "gn:population":0,
    "gn:timezone":"Asia/Jakarta",
    "iso:country":"ID",
    "name:ind_x_preferred":[
        "Koteh"
    ],
    "wof:name":"Koteh",
    "wof:placetype":"locality"
},
  "geometry": {"coordinates":[112.7508,-7.1162],"type":"Point"}
}