{
  "type": "Feature",
  "properties": {
    "gn:admin1_code":"30.0",
    "gn:asciiname":"Bobojong",
    "gn:country_code":"ID",
    "gn:dem":419,
    "gn:feature_class":"P",
    "gn:feature_code":"PPL",
    "gn:name":"Bobojong",
    "gn:population":0,
    "gn:timezone":"Asia/Jakarta",
    "iso:country":"ID",
    "name:ind_x_preferred":[
        "Bobojong"
    ],
    "wof:name":"Bobojong",
    "wof:placetype":"locality"
},
  "geometry": {"coordinates":[106.8215,-7.1387],"type":"Point"}
}