{
  "type": "Feature",
  "properties": {
    "gn:admin1_code":"18",
    "gn:asciiname":"Fatubibi",
    "gn:country_code":"ID",
    "gn:dem":456,
    "gn:feature_class":"P",
    "gn:feature_code":"PPL",
    "gn:name":"Fatubibi",
    "gn:population":0,
    "gn:timezone":"Asia/Makassar",
    "iso:country":"ID",
    "wof:name":"Fatubibi",
    "wof:placetype":"locality"
},
  "geometry": {"coordinates":[124.83778,-9.36472],"type":"Point"}
}