{
  "type": "Feature",
  "properties": {
    "gn:country":"ID",
    "gn:fcode":"PPL",
    "gn:pop":126181,
    "iso:country":"ID",
    "name:ind_x_preferred":[
        "Paseh"
    ],
    "qs:name":"Paseh",
    "qs:photos_9r":0,
    "qs:photos_sr":0,
    "qs:pop_sr":"9",
    "wof:lang_x_official":[
        "ind"
    ],
    "wof:lang_x_spoken":[
        "ind",
        "eng"
    ],
    "wof:name":"Paseh",
    "wof:placetype":"locality",
    "wof:population":126181
},
  "geometry": {"coordinates":[107.7641,-7.1026],"type":"Point"}
}