{
  "type": "Feature",
  "properties": {
    "gn:admin1_code":"8.0",
    "gn:asciiname":"Sukorejo",
    "gn:country_code":"ID",
    "gn:dem":356,
    "gn:feature_class":"P",
    "gn:feature_code":"PPL",
    "gn:name":"Sukorejo",
    "gn:population":0,
    "gn:timezone":"Asia/Jakarta",
    "iso:country":"ID",
    "name:ind_x_preferred":[
        "Sukorejo"
    ],
    "wof:name":"Sukorejo",
    "wof:placetype":"locality"
},
  "geometry": {"coordinates":[112.32250000000001,-7.8248],"type":"Point"}
}