{
  "type": "Feature",
  "properties": {
    "gn:country":"ID",
    "gn:fcode":"PPL",
    "gn:pop":0,
    "iso:country":"ID",
    "name:unk_x_variant":[
        "Tawangsori"
    ],
    "qs:name":"Tawangsari",
    "qs:name_adm0":"Indonesia",
    "qs:name_adm1":"Provinsi Jawa Tengah",
    "qs:photos_9r":0,
    "qs:photos_sr":0,
    "qs:placetype":"Town",
    "qs:pop_sr":"0",
    "wof:name":"Tawangsari",
    "wof:placetype":"locality",
    "wof:population":0
},
  "geometry": {"coordinates":[110.79555999999999,-7.73556],"type":"Point"}
}