{
  "type": "Feature",
  "properties": {
    "gn:admin1_code":"30.0",
    "gn:asciiname":"Kalangsapi",
    "gn:country_code":"ID",
    "gn:dem":761,
    "gn:feature_class":"P",
    "gn:feature_code":"PPL",
    "gn:name":"Kalangsapi",
    "gn:population":0,
    "gn:timezone":"Asia/Jakarta",
    "iso:country":"ID",
    "name:ind_x_preferred":[
        "Kalangsapi"
    ],
    "wof:name":"Kalangsapi",
    "wof:placetype":"locality"
},
  "geometry": {"coordinates":[107.9098,-7.2361],"type":"Point"}
}