{
  "type": "Feature",
  "properties": {
    "gn:admin1_code":"7",
    "gn:asciiname":"Kudailelangon",
    "gn:country_code":"ID",
    "gn:dem":35,
    "gn:feature_class":"P",
    "gn:feature_code":"PPL",
    "gn:name":"Kudailelangon",
    "gn:population":0,
    "gn:timezone":"Asia/Jakarta",
    "iso:country":"ID",
    "name:ind_x_preferred":[
        "Kudailelangon"
    ],
    "wof:name":"Kudailelangon",
    "wof:placetype":"locality"
},
  "geometry": {"coordinates":[109.136,-6.964],"type":"Point"}
}