{
  "type": "Feature",
  "properties": {
    "gn:admin1_code":"30",
    "gn:asciiname":"Kertasari",
    "gn:country_code":"ID",
    "gn:dem":31,
    "gn:feature_class":"P",
    "gn:feature_code":"PPL",
    "gn:name":"Kertasari",
    "gn:population":0,
    "gn:timezone":"Asia/Jakarta",
    "iso:country":"ID",
    "name:ind_x_preferred":[
        "Kertasari"
    ],
    "wof:name":"Kertasari",
    "wof:placetype":"locality"
},
  "geometry": {"coordinates":[108.23944,-6.6825],"type":"Point"}
}