{
  "type": "Feature",
  "properties": {
    "gn:admin1_code":"8.0",
    "gn:asciiname":"Suruhwadang",
    "gn:country_code":"ID",
    "gn:dem":258,
    "gn:feature_class":"P",
    "gn:feature_code":"PPLA4",
    "gn:name":"Suruhwadang",
    "gn:population":0,
    "gn:timezone":"Asia/Jakarta",
    "iso:country":"ID",
    "name:ind_x_preferred":[
        "Suruhwadang"
    ],
    "name:und_x_variant":[
        "Soeroehwadang"
    ],
    "wof:name":"Suruhwadang",
    "wof:placetype":"locality"
},
  "geometry": {"coordinates":[112.1049,-8.1985],"type":"Point"}
}