{
  "type": "Feature",
  "properties": {
    "gn:admin1_code":"7.0",
    "gn:asciiname":"Talang",
    "gn:country_code":"ID",
    "gn:dem":119,
    "gn:feature_class":"P",
    "gn:feature_code":"PPL",
    "gn:name":"Talang",
    "gn:population":0,
    "gn:timezone":"Asia/Jakarta",
    "iso:country":"ID",
    "name:ceb_x_preferred":[
        "Talang"
    ],
    "name:fra_x_preferred":[
        "Talang"
    ],
    "name:ind_x_preferred":[
        "Talang"
    ],
    "name:nld_x_preferred":[
        "Talang"
    ],
    "name:pol_x_preferred":[
        "Talang"
    ],
    "name:swe_x_preferred":[
        "Talang"
    ],
    "wof:lang_x_official":[
        "ind"
    ],
    "wof:lang_x_spoken":[
        "ind",
        "eng"
    ],
    "wof:name":"Talang",
    "wof:placetype":"locality"
},
  "geometry": {"coordinates":[110.74694,-7.58028],"type":"Point"}
}