{
  "type": "Feature",
  "properties": {
    "gn:admin1_code":"32.0",
    "gn:asciiname":"Sukabumi",
    "gn:country_code":"ID",
    "gn:dem":712,
    "gn:feature_class":"P",
    "gn:feature_code":"PPL",
    "gn:name":"Sukabumi",
    "gn:population":0,
    "gn:timezone":"Asia/Jakarta",
    "iso:country":"ID",
    "name:ind_x_preferred":[
        "Sukabumi"
    ],
    "wof:name":"Sukabumi",
    "wof:placetype":"locality"
},
  "geometry": {"coordinates":[103.97736999999999,-4.78325],"type":"Point"}
}