{
  "type": "Feature",
  "properties": {
    "gn:admin1_code":"7.0",
    "gn:asciiname":"Gondangsari",
    "gn:country_code":"ID",
    "gn:dem":718,
    "gn:feature_class":"P",
    "gn:feature_code":"PPL",
    "gn:name":"Gondangsari",
    "gn:population":0,
    "gn:timezone":"Asia/Jakarta",
    "iso:country":"ID",
    "wof:name":"Gondangsari",
    "wof:placetype":"locality"
},
  "geometry": {"coordinates":[110.53943999999998,-7.47889],"type":"Point"}
}