{
  "type": "Feature",
  "properties": {
    "gn:admin1_code":"17",
    "gn:asciiname":"Sinar",
    "gn:country_code":"ID",
    "gn:dem":25,
    "gn:feature_class":"P",
    "gn:feature_code":"PPL",
    "gn:name":"Sinar",
    "gn:population":0,
    "gn:timezone":"Asia/Makassar",
    "iso:country":"ID",
    "name:deu_x_preferred":[
        "Sinar"
    ],
    "name:fas_x_preferred":[
        "\u0633\u06cc\u0646\u0627\u0631"
    ],
    "name:fra_x_preferred":[
        "Sinar"
    ],
    "name:ind_x_preferred":[
        "Sinar"
    ],
    "name:jpn_x_preferred":[
        "\u30b8\u30ca\u30fc"
    ],
    "name:nld_x_preferred":[
        "Sinar"
    ],
    "name:rus_x_preferred":[
        "Sinar"
    ],
    "name:tur_x_preferred":[
        "Sinar"
    ],
    "wof:name":"Sinar",
    "wof:placetype":"locality"
},
  "geometry": {"coordinates":[118.69398,-8.59212],"type":"Point"}
}