{
  "type": "Feature",
  "properties": {
    "gn:admin1_code":"30",
    "gn:asciiname":"Siliwangi",
    "gn:country_code":"ID",
    "gn:dem":19,
    "gn:feature_class":"P",
    "gn:feature_code":"PPL",
    "gn:name":"Siliwangi",
    "gn:population":0,
    "gn:timezone":"Asia/Jakarta",
    "iso:country":"ID",
    "name:ind_x_preferred":[
        "Siliwangi"
    ],
    "wof:name":"Siliwangi",
    "wof:placetype":"locality"
},
  "geometry": {"coordinates":[108.71210000000001,-6.9189],"type":"Point"}
}