{
  "type": "Feature",
  "properties": {
    "gn:admin1_code":"18.0",
    "gn:asciiname":"Riimajja",
    "gn:country_code":"ID",
    "gn:dem":49,
    "gn:feature_class":"P",
    "gn:feature_code":"PPL",
    "gn:name":"Riimajja",
    "gn:population":0,
    "gn:timezone":"Asia/Makassar",
    "iso:country":"ID",
    "name:ind_x_preferred":[
        "Riimajja"
    ],
    "wof:name":"Riimajja",
    "wof:placetype":"locality"
},
  "geometry": {"coordinates":[120.59948,-9.90709],"type":"Point"}
}