{
  "type": "Feature",
  "properties": {
    "gn:admin1_code":"18.0",
    "gn:asciiname":"Kuruladu",
    "gn:country_code":"ID",
    "gn:dem":410,
    "gn:feature_class":"P",
    "gn:feature_code":"PPL",
    "gn:name":"Kuruladu",
    "gn:population":0,
    "gn:timezone":"Asia/Makassar",
    "iso:country":"ID",
    "name:ind_x_preferred":[
        "Kuruladu"
    ],
    "wof:name":"Kuruladu",
    "wof:placetype":"locality"
},
  "geometry": {"coordinates":[121.11750000000001,-8.8633],"type":"Point"}
}