{
  "type": "Feature",
  "properties": {
    "gn:admin1_code":"18.0",
    "gn:asciiname":"Dareraga",
    "gn:country_code":"ID",
    "gn:dem":114,
    "gn:feature_class":"P",
    "gn:feature_code":"PPL",
    "gn:name":"Dareraga",
    "gn:population":0,
    "gn:timezone":"Asia/Makassar",
    "iso:country":"ID",
    "name:ind_x_preferred":[
        "Dareraga"
    ],
    "wof:name":"Dareraga",
    "wof:placetype":"locality"
},
  "geometry": {"coordinates":[121.95269999999999,-10.4945],"type":"Point"}
}