{
  "type": "Feature",
  "properties": {
    "gn:admin1_code":"10.0",
    "gn:asciiname":"Dedel Kulon",
    "gn:country_code":"ID",
    "gn:dem":315,
    "gn:feature_class":"P",
    "gn:feature_code":"PPL",
    "gn:name":"Dedel Kulon",
    "gn:population":0,
    "gn:timezone":"Asia/Jakarta",
    "iso:country":"ID",
    "name:ind_x_preferred":[
        "Dedel Kulon"
    ],
    "wof:name":"Dedel Kulon",
    "wof:placetype":"locality"
},
  "geometry": {"coordinates":[110.68805999999999,-8.05889],"type":"Point"}
}