{
  "type": "Feature",
  "properties": {
    "gn:admin1_code":"26",
    "gn:asciiname":"Sungai Bamban",
    "gn:country_code":"ID",
    "gn:dem":38,
    "gn:feature_class":"P",
    "gn:feature_code":"PPL",
    "gn:name":"Sungai Bamban",
    "gn:population":0,
    "gn:timezone":"Asia/Jakarta",
    "iso:country":"ID",
    "name:ind_x_preferred":[
        "Sungai Bamban"
    ],
    "wof:name":"Sungai Bamban",
    "wof:placetype":"locality"
},
  "geometry": {"coordinates":[98.224,3.7287],"type":"Point"}
}