{
  "type": "Feature",
  "properties": {
    "gn:admin1_code":"38",
    "gn:asciiname":"Sabang",
    "gn:country_code":"ID",
    "gn:dem":182,
    "gn:feature_class":"P",
    "gn:feature_code":"PPL",
    "gn:name":"Sabang",
    "gn:population":0,
    "gn:timezone":"Asia/Makassar",
    "iso:country":"ID",
    "name:ceb_x_preferred":[
        "Sabang"
    ],
    "name:fra_x_preferred":[
        "Sabang"
    ],
    "name:ind_x_preferred":[
        "Sabang"
    ],
    "name:swe_x_preferred":[
        "Sabang"
    ],
    "wof:lang_x_official":[
        "ind"
    ],
    "wof:lang_x_spoken":[
        "ind",
        "eng"
    ],
    "wof:name":"Sabang",
    "wof:placetype":"locality"
},
  "geometry": {"coordinates":[120.13330000000001,-4.8539],"type":"Point"}
}