{
  "type": "Feature",
  "properties": {
    "gn:admin1_code":"8.0",
    "gn:asciiname":"Bangle",
    "gn:country_code":"ID",
    "gn:dem":18,
    "gn:feature_class":"P",
    "gn:feature_code":"PPL",
    "gn:name":"Bangle",
    "gn:population":0,
    "gn:timezone":"Asia/Jakarta",
    "iso:country":"ID",
    "name:azb_x_preferred":[
        "\u0628\u06cc\u0644\u0631\u0632\u06cc\u06a9"
    ],
    "name:ben_x_preferred":[
        "\u099a\u09c1\u09a1\u09bc\u09bf"
    ],
    "name:bih_x_preferred":[
        "\u091a\u0942\u0921\u093c\u0940"
    ],
    "name:deu_x_preferred":[
        "Glasarmring"
    ],
    "name:fas_x_preferred":[
        "\u0627\u0644\u0646\u06af\u0648"
    ],
    "name:hin_x_preferred":[
        "\u091a\u0942\u0921\u093c\u0940"
    ],
    "name:ind_x_preferred":[
        "Bangle"
    ],
    "name:jpn_x_preferred":[
        "\u30d0\u30f3\u30b0\u30eb"
    ],
    "name:kan_x_preferred":[
        "\u0cac\u0cb3\u0cc6"
    ],
    "name:mar_x_preferred":[
        "\u0915\u0902\u0915\u0923"
    ],
    "name:nep_x_preferred":[
        "\u091a\u0941\u0930\u093e"
    ],
    "name:nor_x_preferred":[
        "Bangel"
    ],
    "name:ori_x_preferred":[
        "\u0b1a\u0b41\u0b21\u0b3c\u0b3f"
    ],
    "name:pan_x_preferred":[
        "\u0a1a\u0a42\u0a5c\u0a40"
    ],
    "name:sat_x_preferred":[
        "\u1c6a\u1c69\u1c72\u1c64"
    ],
    "name:tam_x_preferred":[
        "\u0bb5\u0bb3\u0bc8\u0baf\u0bb2\u0bcd"
    ],
    "name:tel_x_preferred":[
        "\u0c17\u0c3e\u0c1c\u0c41"
    ],
    "name:tur_x_preferred":[
        "Bilezik"
    ],
    "name:urd_x_preferred":[
        "\u0686\u0648\u0691\u06cc"
    ],
    "wof:lang_x_official":[
        "ind"
    ],
    "wof:lang_x_spoken":[
        "ind",
        "eng"
    ],
    "wof:name":"Bangle",
    "wof:placetype":"locality"
},
  "geometry": {"coordinates":[112.0639,-7.1425],"type":"Point"}
}