{
  "type": "Feature",
  "properties": {
    "gn:admin1_code":"7.0",
    "gn:asciiname":"Tunjungan",
    "gn:country_code":"ID",
    "gn:dem":8,
    "gn:feature_class":"P",
    "gn:feature_code":"PPL",
    "gn:name":"Tunjungan",
    "gn:population":0,
    "gn:timezone":"Asia/Jakarta",
    "iso:country":"ID",
    "name:ind_x_preferred":[
        "Tunjungan"
    ],
    "wof:name":"Tunjungan",
    "wof:placetype":"locality"
},
  "geometry": {"coordinates":[111.06771000000001,-6.59232],"type":"Point"}
}