{
  "type": "Feature",
  "properties": {
    "gn:admin1_code":"7",
    "gn:asciiname":"Krakch",
    "gn:country_code":"ID",
    "gn:dem":210,
    "gn:feature_class":"P",
    "gn:feature_code":"PPL",
    "gn:name":"Krakch",
    "gn:population":0,
    "gn:timezone":"Asia/Jakarta",
    "iso:country":"ID",
    "name:ind_x_preferred":[
        "Krakch"
    ],
    "wof:name":"Krakch",
    "wof:placetype":"locality"
},
  "geometry": {"coordinates":[110.992,-6.6511],"type":"Point"}
}