{
  "type": "Feature",
  "properties": {
    "gn:admin1_code":"30.0",
    "gn:asciiname":"Galudrangumpuk",
    "gn:country_code":"ID",
    "gn:dem":992,
    "gn:feature_class":"P",
    "gn:feature_code":"PPL",
    "gn:name":"Galudrangumpuk",
    "gn:population":0,
    "gn:timezone":"Asia/Jakarta",
    "iso:country":"ID",
    "name:ind_x_preferred":[
        "Galudrangumpuk"
    ],
    "name:und_x_variant":[
        "Galoedrangoepoek"
    ],
    "wof:lang_x_official":[
        "ind"
    ],
    "wof:lang_x_spoken":[
        "ind",
        "eng"
    ],
    "wof:name":"Galudrangumpuk",
    "wof:placetype":"locality"
},
  "geometry": {"coordinates":[107.91670000000001,-7.2977],"type":"Point"}
}