{
  "type": "Feature",
  "properties": {
    "gn:admin1_code":"41.0",
    "gn:asciiname":"Tanetepolo",
    "gn:country_code":"ID",
    "gn:dem":917,
    "gn:feature_class":"P",
    "gn:feature_code":"PPL",
    "gn:name":"Tanetepolo",
    "gn:population":0,
    "gn:timezone":"Asia/Makassar",
    "iso:country":"ID",
    "name:ind_x_preferred":[
        "Tanetepolo"
    ],
    "wof:lang_x_official":[
        "ind"
    ],
    "wof:lang_x_spoken":[
        "ind",
        "eng"
    ],
    "wof:name":"Tanetepolo",
    "wof:placetype":"locality"
},
  "geometry": {"coordinates":[119.4335,-3.3956],"type":"Point"}
}