{
  "type": "Feature",
  "properties": {
    "gn:admin1_code":"11",
    "gn:asciiname":"Puajeujung",
    "gn:country_code":"ID",
    "gn:dem":25,
    "gn:feature_class":"P",
    "gn:feature_code":"PPL",
    "gn:name":"Puajeujung",
    "gn:population":0,
    "gn:timezone":"Asia/Pontianak",
    "iso:country":"ID",
    "name:ind_x_preferred":[
        "Puajeujung"
    ],
    "wof:name":"Puajeujung",
    "wof:placetype":"locality"
},
  "geometry": {"coordinates":[109.12387,0.84881],"type":"Point"}
}