{
  "type": "Feature",
  "properties": {
    "gn:admin1_code":"7.0",
    "gn:asciiname":"Dukuhmakam",
    "gn:country_code":"ID",
    "gn:dem":755,
    "gn:feature_class":"P",
    "gn:feature_code":"PPL",
    "gn:name":"Dukuhmakam",
    "gn:population":0,
    "gn:timezone":"Asia/Jakarta",
    "iso:country":"ID",
    "name:ind_x_preferred":[
        "Dukuhmakam"
    ],
    "wof:name":"Dukuhmakam",
    "wof:placetype":"locality"
},
  "geometry": {"coordinates":[109.08083000000001,-7.22861],"type":"Point"}
}