{
  "type": "Feature",
  "properties": {
    "gn:admin1_code":"8",
    "gn:asciiname":"Boros",
    "gn:country_code":"ID",
    "gn:dem":558,
    "gn:feature_class":"P",
    "gn:feature_code":"PPL",
    "gn:name":"Boros",
    "gn:population":0,
    "gn:timezone":"Asia/Jakarta",
    "iso:country":"ID",
    "name:deu_x_preferred":[
        "Boros"
    ],
    "name:ell_x_preferred":[
        "\u0392\u03ce\u03c1\u03bf\u03c2"
    ],
    "name:fra_x_preferred":[
        "Boros"
    ],
    "name:ind_x_preferred":[
        "Boros"
    ],
    "name:ita_x_preferred":[
        "Boros"
    ],
    "name:nld_x_preferred":[
        "Boros"
    ],
    "name:slk_x_preferred":[
        "B\u00f3ros"
    ],
    "wof:lang_x_official":[
        "ind"
    ],
    "wof:lang_x_spoken":[
        "ind",
        "eng"
    ],
    "wof:name":"Boros",
    "wof:placetype":"locality"
},
  "geometry": {"coordinates":[112.77119999999999,-8.1441],"type":"Point"}
}