{
  "type": "Feature",
  "properties": {
    "gn:admin1_code":"7.0",
    "gn:asciiname":"Goito",
    "gn:country_code":"ID",
    "gn:dem":54,
    "gn:feature_class":"P",
    "gn:feature_code":"PPL",
    "gn:name":"Goito",
    "gn:population":0,
    "gn:timezone":"Asia/Jakarta",
    "iso:country":"ID",
    "name:azb_x_preferred":[
        "\u0642\u0648\u06cc\u062a\u0648"
    ],
    "name:bar_x_preferred":[
        "Goito"
    ],
    "name:bul_x_preferred":[
        "\u0413\u043e\u0439\u0442\u043e"
    ],
    "name:cat_x_preferred":[
        "Goito"
    ],
    "name:ceb_x_preferred":[
        "Goito"
    ],
    "name:deu_x_preferred":[
        "Goito"
    ],
    "name:eml_x_preferred":[
        "G\u00f9it"
    ],
    "name:epo_x_preferred":[
        "Goito"
    ],
    "name:eus_x_preferred":[
        "Goito"
    ],
    "name:fas_x_preferred":[
        "\u06af\u0648\u06cc\u062a\u0648"
    ],
    "name:fin_x_preferred":[
        "Goito"
    ],
    "name:fra_x_preferred":[
        "Goito"
    ],
    "name:hun_x_preferred":[
        "Goito"
    ],
    "name:hye_x_preferred":[
        "\u0533\u0578\u0575\u057f\u0578"
    ],
    "name:ind_x_preferred":[
        "Goito"
    ],
    "name:ita_x_preferred":[
        "Goito"
    ],
    "name:jpn_x_preferred":[
        "\u30b4\u30fc\u30a4\u30c8"
    ],
    "name:kaz_x_preferred":[
        "\u0413\u043e\u0439\u0442\u043e"
    ],
    "name:lat_x_preferred":[
        "Goitum"
    ],
    "name:lmo_x_preferred":[
        "G\u00f9it"
    ],
    "name:msa_x_preferred":[
        "Goito"
    ],
    "name:nap_x_preferred":[
        "Goito"
    ],
    "name:nld_x_preferred":[
        "Goito"
    ],
    "name:pms_x_preferred":[
        "Goito"
    ],
    "name:pol_x_preferred":[
        "Goito"
    ],
    "name:por_x_preferred":[
        "Goito"
    ],
    "name:ron_x_preferred":[
        "Goito"
    ],
    "name:rus_x_preferred":[
        "\u0413\u043e\u0439\u0442\u043e"
    ],
    "name:scn_x_preferred":[
        "Goito"
    ],
    "name:spa_x_preferred":[
        "Goito"
    ],
    "name:srp_x_preferred":[
        "\u0413\u043e\u0438\u0442\u043e"
    ],
    "name:tgl_x_preferred":[
        "Goito"
    ],
    "name:ukr_x_preferred":[
        "\u0413\u043e\u0457\u0442\u043e"
    ],
    "name:uzb_x_preferred":[
        "Goito"
    ],
    "name:vec_x_preferred":[
        "Goito"
    ],
    "name:vie_x_preferred":[
        "Goito"
    ],
    "name:vol_x_preferred":[
        "Goito"
    ],
    "name:war_x_preferred":[
        "Goito"
    ],
    "name:zho_x_preferred":[
        "\u6208\u4f0a\u6258"
    ],
    "wof:name":"Goito",
    "wof:placetype":"locality"
},
  "geometry": {"coordinates":[111.4393,-7.2362],"type":"Point"}
}