{
  "type": "Feature",
  "properties": {
    "gn:admin1_code":"30",
    "gn:asciiname":"Cisentul Kulon",
    "gn:country_code":"ID",
    "gn:dem":496,
    "gn:feature_class":"P",
    "gn:feature_code":"PPL",
    "gn:name":"Cisentul Kulon",
    "gn:population":0,
    "gn:timezone":"Asia/Jakarta",
    "iso:country":"ID",
    "name:ind_x_preferred":[
        "Cisentul Kulon"
    ],
    "wof:name":"Cisentul Kulon",
    "wof:placetype":"locality"
},
  "geometry": {"coordinates":[107.11194,-6.86222],"type":"Point"}
}