{
  "type": "Feature",
  "properties": {
    "gn:admin1_code":"41",
    "gn:asciiname":"Salurano",
    "gn:country_code":"ID",
    "gn:dem":1032,
    "gn:feature_class":"P",
    "gn:feature_code":"PPL",
    "gn:name":"Salurano",
    "gn:population":0,
    "gn:timezone":"Asia/Makassar",
    "iso:country":"ID",
    "name:ind_x_preferred":[
        "Salurano"
    ],
    "wof:name":"Salurano",
    "wof:placetype":"locality"
},
  "geometry": {"coordinates":[119.31270000000001,-3.0256],"type":"Point"}
}