{
  "type": "Feature",
  "properties": {
    "gn:admin1_code":"8.0",
    "gn:asciiname":"Mojorumpuk",
    "gn:country_code":"ID",
    "gn:dem":106,
    "gn:feature_class":"P",
    "gn:feature_code":"PPL",
    "gn:name":"Mojorumpuk",
    "gn:population":0,
    "gn:timezone":"Asia/Jakarta",
    "iso:country":"ID",
    "name:ind_x_preferred":[
        "Mojorumpuk"
    ],
    "wof:name":"Mojorumpuk",
    "wof:placetype":"locality"
},
  "geometry": {"coordinates":[111.4512,-7.9299],"type":"Point"}
}