{
  "type": "Feature",
  "properties": {
    "gn:admin1_code":"30",
    "gn:asciiname":"Bojongbolang",
    "gn:country_code":"ID",
    "gn:dem":677,
    "gn:feature_class":"P",
    "gn:feature_code":"PPL",
    "gn:name":"Bojongbolang",
    "gn:population":0,
    "gn:timezone":"Asia/Jakarta",
    "iso:country":"ID",
    "name:ind_x_preferred":[
        "Bojongbolang"
    ],
    "wof:name":"Bojongbolang",
    "wof:placetype":"locality"
},
  "geometry": {"coordinates":[107.80389,-6.9625],"type":"Point"}
}