{
  "type": "Feature",
  "properties": {
    "gn:admin1_code":"38",
    "gn:asciiname":"Karipo",
    "gn:country_code":"ID",
    "gn:dem":82,
    "gn:feature_class":"P",
    "gn:feature_code":"PPL",
    "gn:name":"Karipo",
    "gn:population":0,
    "gn:timezone":"Asia/Makassar",
    "iso:country":"ID",
    "name:ind_x_preferred":[
        "Karipo"
    ],
    "wof:name":"Karipo",
    "wof:placetype":"locality"
},
  "geometry": {"coordinates":[120.39279999999999,-5.3701],"type":"Point"}
}