{
  "type": "Feature",
  "properties": {
    "gn:admin1_code":"26",
    "gn:asciiname":"Mondang",
    "gn:country_code":"ID",
    "gn:dem":226,
    "gn:feature_class":"P",
    "gn:feature_code":"PPL",
    "gn:name":"Mondang",
    "gn:population":0,
    "gn:timezone":"Asia/Jakarta",
    "iso:country":"ID",
    "name:ind_x_preferred":[
        "Mondang"
    ],
    "wof:name":"Mondang",
    "wof:placetype":"locality"
},
  "geometry": {"coordinates":[99.38993000000001,1.20042],"type":"Point"}
}