{
  "type": "Feature",
  "properties": {
    "gn:admin1_code":"30",
    "gn:asciiname":"Goa",
    "gn:country_code":"ID",
    "gn:dem":742,
    "gn:feature_class":"P",
    "gn:feature_code":"PPL",
    "gn:name":"Goa",
    "gn:population":0,
    "gn:timezone":"Asia/Jakarta",
    "iso:country":"ID",
    "wof:name":"Goa",
    "wof:placetype":"locality"
},
  "geometry": {"coordinates":[107.71805999999999,-7.06306],"type":"Point"}
}