{
  "type": "Feature",
  "properties": {
    "gn:admin1_code":"18.0",
    "gn:asciiname":"Lewolein",
    "gn:country_code":"ID",
    "gn:dem":130,
    "gn:feature_class":"P",
    "gn:feature_code":"PPL",
    "gn:name":"Lewolein",
    "gn:population":0,
    "gn:timezone":"Asia/Makassar",
    "iso:country":"ID",
    "name:ind_x_preferred":[
        "Lewolein"
    ],
    "wof:name":"Lewolein",
    "wof:placetype":"locality"
},
  "geometry": {"coordinates":[122.9743,-8.2519],"type":"Point"}
}