{
  "type": "Feature",
  "properties": {
    "gn:admin1_code":"08",
    "gn:asciiname":"Morkoneng",
    "gn:country_code":"ID",
    "gn:dem":80,
    "gn:feature_class":"P",
    "gn:feature_code":"PPL",
    "gn:name":"Morkoneng",
    "gn:population":0,
    "gn:timezone":"Asia/Jakarta",
    "iso:country":"ID",
    "name:ind_x_preferred":[
        "Morkoneng"
    ],
    "name:und_x_variant":[
        "Somorkoning 1",
        "Somorkoning Satu"
    ],
    "wof:name":"Morkoneng",
    "wof:placetype":"locality"
},
  "geometry": {"coordinates":[112.883,-7.1218],"type":"Point"}
}