{
  "type": "Feature",
  "properties": {
    "gn:admin1_code":"38",
    "gn:asciiname":"Kayuloe",
    "gn:country_code":"ID",
    "gn:dem":699,
    "gn:feature_class":"P",
    "gn:feature_code":"PPL",
    "gn:name":"Kayuloe",
    "gn:population":0,
    "gn:timezone":"Asia/Makassar",
    "iso:country":"ID",
    "name:ind_x_preferred":[
        "Kayuloe"
    ],
    "wof:name":"Kayuloe",
    "wof:placetype":"locality"
},
  "geometry": {"coordinates":[119.976,-5.4647],"type":"Point"}
}