{
  "type": "Feature",
  "properties": {
    "gn:admin1_code":"33.0",
    "gn:asciiname":"Ciluluk",
    "gn:country_code":"ID",
    "gn:dem":25,
    "gn:feature_class":"P",
    "gn:feature_code":"PPL",
    "gn:name":"Ciluluk",
    "gn:population":0,
    "gn:timezone":"Asia/Jakarta",
    "iso:country":"ID",
    "name:ind_x_preferred":[
        "Ciluluk"
    ],
    "wof:name":"Ciluluk",
    "wof:placetype":"locality"
},
  "geometry": {"coordinates":[105.78149999999999,-6.8162],"type":"Point"}
}