{
  "type": "Feature",
  "properties": {
    "gn:admin1_code":"30",
    "gn:asciiname":"Cilangkap",
    "gn:cc2":"ID",
    "gn:country_code":"ID",
    "gn:dem":115,
    "gn:feature_class":"P",
    "gn:feature_code":"PPL",
    "gn:name":"Cilangkap",
    "gn:population":0,
    "gn:timezone":"Asia/Jakarta",
    "iso:country":"ID",
    "name:und_x_variant":[
        "Tjilangkap",
        "Cilangkap"
    ],
    "wof:name":"Cilangkap",
    "wof:placetype":"locality"
},
  "geometry": {"coordinates":[106.70778,-6.46583],"type":"Point"}
}