{
  "type": "Feature",
  "properties": {
    "gn:admin1_code":"10.0",
    "gn:asciiname":"Mulo",
    "gn:country_code":"ID",
    "gn:dem":166,
    "gn:feature_class":"P",
    "gn:feature_code":"PPL",
    "gn:name":"Mulo",
    "gn:population":0,
    "gn:timezone":"Asia/Jakarta",
    "iso:country":"ID",
    "name:ceb_x_preferred":[
        "Mulo"
    ],
    "name:deu_x_preferred":[
        "Mulo"
    ],
    "name:epo_x_preferred":[
        "Mulo"
    ],
    "name:ind_x_preferred":[
        "Mulo"
    ],
    "name:ita_x_preferred":[
        "Mulo"
    ],
    "name:swe_x_preferred":[
        "Mulo"
    ],
    "name:und_x_variant":[
        "Moelo",
        "Moela"
    ],
    "wof:lang_x_official":[
        "ind"
    ],
    "wof:lang_x_spoken":[
        "ind",
        "eng"
    ],
    "wof:name":"Mulo",
    "wof:placetype":"locality"
},
  "geometry": {"coordinates":[110.58778,-8.01806],"type":"Point"}
}