{
  "type": "Feature",
  "properties": {
    "gn:admin1_code":"30.0",
    "gn:asciiname":"Mulyasari",
    "gn:country_code":"ID",
    "gn:dem":269,
    "gn:feature_class":"P",
    "gn:feature_code":"PPL",
    "gn:name":"Mulyasari",
    "gn:population":0,
    "gn:timezone":"Asia/Jakarta",
    "iso:country":"ID",
    "name:ind_x_preferred":[
        "Mulyasari"
    ],
    "wof:name":"Mulyasari",
    "wof:placetype":"locality"
},
  "geometry": {"coordinates":[108.47580000000001,-7.5952],"type":"Point"}
}