{
  "type": "Feature",
  "properties": {
    "gn:admin1_code":"7.0",
    "gn:asciiname":"Bulakrejo",
    "gn:country_code":"ID",
    "gn:dem":134,
    "gn:feature_class":"P",
    "gn:feature_code":"PPL",
    "gn:name":"Bulakrejo",
    "gn:population":0,
    "gn:timezone":"Asia/Jakarta",
    "iso:country":"ID",
    "wof:name":"Bulakrejo",
    "wof:placetype":"locality"
},
  "geometry": {"coordinates":[110.85889,-7.27306],"type":"Point"}
}