{
  "type": "Feature",
  "properties": {
    "gn:admin1_code":"26",
    "gn:asciiname":"Rimbun",
    "gn:country_code":"ID",
    "gn:dem":280,
    "gn:feature_class":"P",
    "gn:feature_code":"PPL",
    "gn:name":"Rimbun",
    "gn:population":0,
    "gn:timezone":"Asia/Jakarta",
    "iso:country":"ID",
    "name:ind_x_preferred":[
        "Rimbun"
    ],
    "name:und_x_variant":[
        "Rembun"
    ],
    "wof:lang_x_official":[
        "ind"
    ],
    "wof:lang_x_spoken":[
        "ind",
        "eng"
    ],
    "wof:name":"Rimbun",
    "wof:placetype":"locality"
},
  "geometry": {"coordinates":[98.98399999999999,3.0726],"type":"Point"}
}