{
  "type": "Feature",
  "properties": {
    "gn:admin1_code":"30",
    "gn:asciiname":"Barujamaah",
    "gn:country_code":"ID",
    "gn:dem":1006,
    "gn:feature_class":"P",
    "gn:feature_code":"PPL",
    "gn:name":"Barujamaah",
    "gn:population":0,
    "gn:timezone":"Asia/Jakarta",
    "iso:country":"ID",
    "name:ind_x_preferred":[
        "Barujamaah"
    ],
    "wof:name":"Barujamaah",
    "wof:placetype":"locality"
},
  "geometry": {"coordinates":[107.50778,-6.78278],"type":"Point"}
}