{
  "type": "Feature",
  "properties": {
    "gn:admin1_code":"26.0",
    "gn:asciiname":"Janjimaria Dua",
    "gn:country_code":"ID",
    "gn:dem":1037,
    "gn:feature_class":"P",
    "gn:feature_code":"PPL",
    "gn:name":"Janjimaria Dua",
    "gn:population":0,
    "gn:timezone":"Asia/Jakarta",
    "iso:country":"ID",
    "name:ind_x_preferred":[
        "Janjimaria Dua"
    ],
    "name:und_x_variant":[
        "Janjimaria 2"
    ],
    "wof:lang_x_official":[
        "ind"
    ],
    "wof:lang_x_spoken":[
        "ind",
        "eng"
    ],
    "wof:name":"Janjimaria Dua",
    "wof:placetype":"locality"
},
  "geometry": {"coordinates":[98.62309999999999,2.1136],"type":"Point"}
}