{
  "type": "Feature",
  "properties": {
    "gn:admin1_code":"1",
    "gn:asciiname":"Parsaoran Dua",
    "gn:country_code":"ID",
    "gn:dem":112,
    "gn:feature_class":"P",
    "gn:feature_code":"PPL",
    "gn:name":"Parsaoran Dua",
    "gn:population":0,
    "gn:timezone":"Asia/Jakarta",
    "iso:country":"ID",
    "name:ind_x_preferred":[
        "Parsaoran Dua"
    ],
    "name:und_x_variant":[
        "Parsaoran 2"
    ],
    "wof:name":"Parsaoran Dua",
    "wof:placetype":"locality"
},
  "geometry": {"coordinates":[97.92189999999999,3.3057],"type":"Point"}
}