{
  "type": "Feature",
  "properties": {
    "gn:admin1_code":"30.0",
    "gn:asciiname":"Amlong",
    "gn:country_code":"ID",
    "gn:dem":211,
    "gn:feature_class":"P",
    "gn:feature_code":"PPL",
    "gn:name":"Amlong",
    "gn:population":0,
    "gn:timezone":"Asia/Jakarta",
    "iso:country":"ID",
    "name:ind_x_preferred":[
        "Amlong"
    ],
    "wof:name":"Amlong",
    "wof:placetype":"locality"
},
  "geometry": {"coordinates":[107.0926,-7.2653],"type":"Point"}
}