{
  "type": "Feature",
  "properties": {
    "gn:admin1_code":"2",
    "gn:asciiname":"Banjar Tegal",
    "gn:country_code":"ID",
    "gn:dem":56,
    "gn:feature_class":"P",
    "gn:feature_code":"PPL",
    "gn:name":"Banjar Tegal",
    "gn:population":0,
    "gn:timezone":"Asia/Makassar",
    "iso:country":"ID",
    "name:ind_x_preferred":[
        "Banjar Tegal"
    ],
    "wof:name":"Banjar Tegal",
    "wof:placetype":"locality"
},
  "geometry": {"coordinates":[115.2813,-8.6046],"type":"Point"}
}