{
  "type": "Feature",
  "properties": {
    "gn:admin1_code":"30.0",
    "gn:asciiname":"Galoh",
    "gn:country_code":"ID",
    "gn:dem":55,
    "gn:feature_class":"P",
    "gn:feature_code":"PPL",
    "gn:name":"Galoh",
    "gn:population":0,
    "gn:timezone":"Asia/Jakarta",
    "iso:country":"ID",
    "name:ind_x_preferred":[
        "Galoh"
    ],
    "wof:name":"Galoh",
    "wof:placetype":"locality"
},
  "geometry": {"coordinates":[111.4534,-7.4355],"type":"Point"}
}