{
  "type": "Feature",
  "properties": {
    "gn:admin1_code":"26",
    "gn:asciiname":"Panyongkolan",
    "gn:country_code":"ID",
    "gn:dem":662,
    "gn:feature_class":"P",
    "gn:feature_code":"PPL",
    "gn:name":"Panyongkolan",
    "gn:population":0,
    "gn:timezone":"Asia/Jakarta",
    "iso:country":"ID",
    "name:ind_x_preferred":[
        "Panyongkolan"
    ],
    "name:ind_x_variant":[
        "Panongkalan"
    ],
    "wof:lang_x_official":[
        "ind"
    ],
    "wof:lang_x_spoken":[
        "ind",
        "eng"
    ],
    "wof:name":"Panyongkolan",
    "wof:placetype":"locality"
},
  "geometry": {"coordinates":[99.21997,1.75408],"type":"Point"}
}