{
  "type": "Feature",
  "properties": {
    "gn:admin1_code":"7.0",
    "gn:asciiname":"Tegalputih",
    "gn:country_code":"ID",
    "gn:dem":116,
    "gn:feature_class":"P",
    "gn:feature_code":"PPL",
    "gn:name":"Tegalputih",
    "gn:population":0,
    "gn:timezone":"Asia/Jakarta",
    "iso:country":"ID",
    "name:ind_x_preferred":[
        "Tegalputih"
    ],
    "wof:name":"Tegalputih",
    "wof:placetype":"locality"
},
  "geometry": {"coordinates":[111.2612,-6.9408],"type":"Point"}
}