{
  "type": "Feature",
  "properties": {
    "gn:admin1_code":"18",
    "gn:asciiname":"Leolaes",
    "gn:country_code":"ID",
    "gn:dem":70,
    "gn:feature_class":"P",
    "gn:feature_code":"PPL",
    "gn:name":"Leolaes",
    "gn:population":0,
    "gn:timezone":"Asia/Makassar",
    "iso:country":"ID",
    "wof:name":"Leolaes",
    "wof:placetype":"locality"
},
  "geometry": {"coordinates":[124.50749999999999,-9.21667],"type":"Point"}
}