{
  "type": "Feature",
  "properties": {
    "gn:admin1_code":"24",
    "gn:asciiname":"Bukitkandung",
    "gn:country_code":"ID",
    "gn:dem":463,
    "gn:feature_class":"P",
    "gn:feature_code":"PPL",
    "gn:name":"Bukitkandung",
    "gn:population":0,
    "gn:timezone":"Asia/Jakarta",
    "iso:country":"ID",
    "name:ind_x_preferred":[
        "Bukitkandung"
    ],
    "wof:name":"Bukitkandung",
    "wof:placetype":"locality"
},
  "geometry": {"coordinates":[100.60266,-0.57151],"type":"Point"}
}