{
  "type": "Feature",
  "properties": {
    "gn:admin1_code":"15.0",
    "gn:asciiname":"Koncang",
    "gn:country_code":"ID",
    "gn:dem":129,
    "gn:feature_class":"P",
    "gn:feature_code":"PPL",
    "gn:name":"Koncang",
    "gn:population":0,
    "gn:timezone":"Asia/Jakarta",
    "iso:country":"ID",
    "name:ind_x_preferred":[
        "Koncang"
    ],
    "wof:name":"Koncang",
    "wof:placetype":"locality"
},
  "geometry": {"coordinates":[104.88334999999999,-5.43502],"type":"Point"}
}