{
  "type": "Feature",
  "properties": {
    "gn:admin1_code":"7",
    "gn:asciiname":"Mergayasa",
    "gn:country_code":"ID",
    "gn:dem":1351,
    "gn:feature_class":"P",
    "gn:feature_code":"PPL",
    "gn:name":"Mergayasa",
    "gn:population":0,
    "gn:timezone":"Asia/Jakarta",
    "iso:country":"ID",
    "name:ind_x_preferred":[
        "Mergayasa"
    ],
    "wof:name":"Mergayasa",
    "wof:placetype":"locality"
},
  "geometry": {"coordinates":[109.6875,-7.20944],"type":"Point"}
}