{
  "type": "Feature",
  "properties": {
    "gn:country":"ID",
    "gn:fcode":"ADM3",
    "gn:pop":0,
    "iso:country":"ID",
    "name:ind_x_preferred":[
        "Kecamatan Tanjunganom"
    ],
    "name:unk_x_variant":[
        "Tanjunganom"
    ],
    "qs:name":"Kecamatan Tanjunganom",
    "qs:photos_9r":0,
    "qs:photos_sr":0,
    "qs:pop_sr":"0",
    "wof:name":"Kecamatan Tanjunganom",
    "wof:placetype":"localadmin",
    "wof:population":0
},
  "geometry": {"coordinates":[112.0048,-7.6265],"type":"Point"}
}