{
  "type": "Feature",
  "properties": {
    "gn:admin1_code":"30",
    "gn:asciiname":"Cipaera",
    "gn:country_code":"ID",
    "gn:dem":692,
    "gn:feature_class":"P",
    "gn:feature_code":"PPL",
    "gn:name":"Cipaera",
    "gn:population":0,
    "gn:timezone":"Asia/Jakarta",
    "iso:country":"ID",
    "name:ind_x_preferred":[
        "Cipaera"
    ],
    "wof:name":"Cipaera",
    "wof:placetype":"locality"
},
  "geometry": {"coordinates":[107.62333,-6.92056],"type":"Point"}
}