{
  "type": "Feature",
  "properties": {
    "gn:admin1_code":"38.0",
    "gn:asciiname":"Bau",
    "gn:country_code":"ID",
    "gn:dem":906,
    "gn:feature_class":"P",
    "gn:feature_code":"PPL",
    "gn:name":"Bau",
    "gn:population":0,
    "gn:timezone":"Asia/Makassar",
    "iso:country":"ID",
    "name:ceb_x_preferred":[
        "Bau"
    ],
    "name:ces_x_preferred":[
        "Bau"
    ],
    "name:deu_x_preferred":[
        "Bau"
    ],
    "name:fin_x_preferred":[
        "Bau"
    ],
    "name:ind_x_preferred":[
        "Bau"
    ],
    "name:nld_x_preferred":[
        "Bau"
    ],
    "name:por_x_preferred":[
        "Bau"
    ],
    "name:slk_x_preferred":[
        "Bau"
    ],
    "name:spa_x_preferred":[
        "Bau"
    ],
    "name:swe_x_preferred":[
        "Bau"
    ],
    "name:vie_x_preferred":[
        "Bau"
    ],
    "wof:lang_x_official":[
        "ind"
    ],
    "wof:lang_x_spoken":[
        "ind",
        "eng"
    ],
    "wof:name":"Bau",
    "wof:placetype":"locality"
},
  "geometry": {"coordinates":[119.96510000000001,-3.299],"type":"Point"}
}