{
  "type": "Feature",
  "properties": {
    "gn:admin1_code":"30.0",
    "gn:asciiname":"Dugaleun",
    "gn:country_code":"ID",
    "gn:dem":686,
    "gn:feature_class":"P",
    "gn:feature_code":"PPL",
    "gn:name":"Dugaleun",
    "gn:population":0,
    "gn:timezone":"Asia/Jakarta",
    "iso:country":"ID",
    "name:und_x_variant":[
        "Doegaleun"
    ],
    "wof:name":"Dugaleun",
    "wof:placetype":"locality"
},
  "geometry": {"coordinates":[108.03859,-7.29879],"type":"Point"}
}