{
  "type": "Feature",
  "properties": {
    "gn:admin1_code":"7",
    "gn:asciiname":"Gumenggeng",
    "gn:country_code":"ID",
    "gn:dem":169,
    "gn:feature_class":"P",
    "gn:feature_code":"PPL",
    "gn:name":"Gumenggeng",
    "gn:population":0,
    "gn:timezone":"Asia/Jakarta",
    "iso:country":"ID",
    "name:ind_x_preferred":[
        "Gumenggeng"
    ],
    "wof:name":"Gumenggeng",
    "wof:placetype":"locality"
},
  "geometry": {"coordinates":[109.70820000000001,-7.0206],"type":"Point"}
}