{
  "type": "Feature",
  "properties": {
    "gn:admin1_code":"7.0",
    "gn:asciiname":"Banaran",
    "gn:country_code":"ID",
    "gn:dem":413,
    "gn:feature_class":"P",
    "gn:feature_code":"PPL",
    "gn:name":"Banaran",
    "gn:population":0,
    "gn:timezone":"Asia/Jakarta",
    "iso:country":"ID",
    "wof:name":"Banaran",
    "wof:placetype":"locality"
},
  "geometry": {"coordinates":[110.10861,-7.52778],"type":"Point"}
}