{
  "type": "Feature",
  "properties": {
    "gn:admin1_code":"30",
    "gn:asciiname":"Cipanas",
    "gn:country_code":"ID",
    "gn:dem":370,
    "gn:feature_class":"P",
    "gn:feature_code":"PPL",
    "gn:name":"Cipanas",
    "gn:population":0,
    "gn:timezone":"Asia/Jakarta",
    "iso:country":"ID",
    "name:ara_x_preferred":[
        "\u0633\u064a\u0628\u0627\u0646\u0627\u0633"
    ],
    "name:ind_x_preferred":[
        "Cipanas"
    ],
    "wof:name":"Cipanas",
    "wof:placetype":"locality"
},
  "geometry": {"coordinates":[106.77943999999999,-6.90056],"type":"Point"}
}