{
  "type": "Feature",
  "properties": {
    "gn:admin1_code":"30",
    "gn:asciiname":"Cisagaten",
    "gn:country_code":"ID",
    "gn:dem":1093,
    "gn:feature_class":"P",
    "gn:feature_code":"PPL",
    "gn:name":"Cisagaten",
    "gn:population":0,
    "gn:timezone":"Asia/Jakarta",
    "iso:country":"ID",
    "name:ind_x_preferred":[
        "Cisagaten"
    ],
    "wof:name":"Cisagaten",
    "wof:placetype":"locality"
},
  "geometry": {"coordinates":[107.84269999999999,-7.0568],"type":"Point"}
}