{
  "type": "Feature",
  "properties": {
    "gn:admin1_code":"7.0",
    "gn:asciiname":"Wangan",
    "gn:country_code":"ID",
    "gn:dem":1218,
    "gn:feature_class":"P",
    "gn:feature_code":"PPL",
    "gn:name":"Wangan",
    "gn:population":0,
    "gn:timezone":"Asia/Jakarta",
    "iso:country":"ID",
    "wof:name":"Wangan",
    "wof:placetype":"locality"
},
  "geometry": {"coordinates":[110.48694,-7.455],"type":"Point"}
}