{
  "type": "Feature",
  "properties": {
    "gn:admin1_code":"8.0",
    "gn:asciiname":"Cowekan",
    "gn:country_code":"ID",
    "gn:dem":129,
    "gn:feature_class":"P",
    "gn:feature_code":"PPL",
    "gn:name":"Cowekan",
    "gn:population":0,
    "gn:timezone":"Asia/Jakarta",
    "iso:country":"ID",
    "name:ind_x_preferred":[
        "Cowekan"
    ],
    "wof:name":"Cowekan",
    "wof:placetype":"locality"
},
  "geometry": {"coordinates":[111.9383,-7.7824],"type":"Point"}
}