{
  "type": "Feature",
  "properties": {
    "gn:admin1_code":"8.0",
    "gn:asciiname":"Baderan",
    "gn:country_code":"ID",
    "gn:dem":55,
    "gn:feature_class":"P",
    "gn:feature_code":"PPL",
    "gn:name":"Baderan",
    "gn:population":0,
    "gn:timezone":"Asia/Jakarta",
    "iso:country":"ID",
    "name:ind_x_preferred":[
        "Baderan"
    ],
    "wof:name":"Baderan",
    "wof:placetype":"locality"
},
  "geometry": {"coordinates":[111.45959999999999,-7.5119],"type":"Point"}
}