{
  "type": "Feature",
  "properties": {
    "gn:admin1_code":"30.0",
    "gn:asciiname":"Cijulang",
    "gn:country_code":"ID",
    "gn:dem":180,
    "gn:feature_class":"P",
    "gn:feature_code":"PPL",
    "gn:name":"Cijulang",
    "gn:population":0,
    "gn:timezone":"Asia/Jakarta",
    "iso:country":"ID",
    "name:ind_x_preferred":[
        "Cijulang"
    ],
    "wof:name":"Cijulang",
    "wof:placetype":"locality"
},
  "geometry": {"coordinates":[107.0737,-7.2513],"type":"Point"}
}