{
  "type": "Feature",
  "properties": {
    "gn:admin1_code":"38.0",
    "gn:asciiname":"Kalumbia",
    "gn:country_code":"ID",
    "gn:dem":779,
    "gn:feature_class":"P",
    "gn:feature_code":"PPL",
    "gn:name":"Kalumbia",
    "gn:population":0,
    "gn:timezone":"Asia/Makassar",
    "iso:country":"ID",
    "name:ind_x_preferred":[
        "Kalumbia"
    ],
    "wof:name":"Kalumbia",
    "wof:placetype":"locality"
},
  "geometry": {"coordinates":[119.7457,-3.2342],"type":"Point"}
}