{
  "type": "Feature",
  "properties": {
    "gn:admin1_code":"1",
    "gn:asciiname":"Pante Lhong",
    "gn:country_code":"ID",
    "gn:dem":19,
    "gn:feature_class":"P",
    "gn:feature_code":"PPL",
    "gn:name":"Pante Lhong",
    "gn:population":0,
    "gn:timezone":"Asia/Jakarta",
    "iso:country":"ID",
    "name:ind_x_preferred":[
        "Pante Lhong"
    ],
    "wof:name":"Pante Lhong",
    "wof:placetype":"locality"
},
  "geometry": {"coordinates":[97.50449999999999,5.0336],"type":"Point"}
}