{
  "type": "Feature",
  "properties": {
    "gn:admin1_code":"30.0",
    "gn:asciiname":"Leuwikecapi",
    "gn:country_code":"ID",
    "gn:dem":242,
    "gn:feature_class":"P",
    "gn:feature_code":"PPL",
    "gn:name":"Leuwikecapi",
    "gn:population":0,
    "gn:timezone":"Asia/Jakarta",
    "iso:country":"ID",
    "name:ind_x_preferred":[
        "Leuwikecapi"
    ],
    "wof:name":"Leuwikecapi",
    "wof:placetype":"locality"
},
  "geometry": {"coordinates":[107.7227,-7.5531],"type":"Point"}
}