{
  "type": "Feature",
  "properties": {
    "gn:admin1_code":"22.0",
    "gn:asciiname":"Hendea",
    "gn:country_code":"ID",
    "gn:dem":279,
    "gn:feature_class":"P",
    "gn:feature_code":"PPL",
    "gn:name":"Hendea",
    "gn:population":0,
    "gn:timezone":"Asia/Makassar",
    "iso:country":"ID",
    "name:ind_x_preferred":[
        "Hendea"
    ],
    "wof:name":"Hendea",
    "wof:placetype":"locality"
},
  "geometry": {"coordinates":[122.7478,-5.4979],"type":"Point"}
}