{
  "type": "Feature",
  "properties": {
    "gn:gn_country":"ID",
    "gn:gn_fcode":"PPL",
    "gn:gn_pop":0,
    "iso:country":"ID",
    "name:ind_x_preferred":[
        "Kuningan Barat"
    ],
    "name:unk_x_variant":[
        "Kuningan Satu"
    ],
    "qs_pg:aaroncc":"ID",
    "qs_pg:gn_country":"ID",
    "qs_pg:gn_fcode":"PPL",
    "qs_pg:gn_pop":0,
    "qs_pg:name":"Kuningan Barat",
    "qs_pg:name_adm0":"Indonesia",
    "qs_pg:name_adm1":"Jakarta Raya",
    "qs_pg:photos_9r":0,
    "qs_pg:photos_sr":0,
    "qs_pg:pop_sr":0,
    "qs_pg:qs_pg_placetype":"neighbourhood",
    "qs_pg:qs_pg_placetype_gp":"Suburb",
    "qs_pg:woe_adm0":23424846,
    "woe:adm0_id":23424846,
    "woe:name_adm0":"Indonesia",
    "woe:name_adm1":"Jakarta Raya",
    "woe:placetype":"Suburb",
    "wof:name":"Kuningan Barat",
    "wof:placetype":"neighbourhood"
},
  "geometry": {"coordinates":[106.82089999999999,-6.2374],"type":"Point"}
}