{
  "type": "Feature",
  "properties": {
    "gn:admin1_code":"1",
    "gn:asciiname":"Sabar Menanti",
    "gn:country_code":"ID",
    "gn:dem":14,
    "gn:feature_class":"P",
    "gn:feature_code":"PPL",
    "gn:name":"Sabar Menanti",
    "gn:population":0,
    "gn:timezone":"Asia/Jakarta",
    "iso:country":"ID",
    "name:ind_x_preferred":[
        "Sabar Menanti"
    ],
    "wof:name":"Sabar Menanti",
    "wof:placetype":"locality"
},
  "geometry": {"coordinates":[99.7248,2.8649],"type":"Point"}
}