{
  "type": "Feature",
  "properties": {
    "gn:admin1_code":"17.0",
    "gn:asciiname":"Sepi",
    "gn:country_code":"ID",
    "gn:dem":9,
    "gn:feature_class":"P",
    "gn:feature_code":"PPL",
    "gn:name":"Sepi",
    "gn:population":0,
    "gn:timezone":"Asia/Makassar",
    "iso:country":"ID",
    "name:ind_x_preferred":[
        "Sepi"
    ],
    "wof:name":"Sepi",
    "wof:placetype":"locality"
},
  "geometry": {"coordinates":[116.06140000000001,-8.8517],"type":"Point"}
}