{
  "type": "Feature",
  "properties": {
    "gn:admin1_code":"30.0",
    "gn:asciiname":"Palawija",
    "gn:country_code":"ID",
    "gn:dem":246,
    "gn:feature_class":"P",
    "gn:feature_code":"PPL",
    "gn:name":"Palawija",
    "gn:population":0,
    "gn:timezone":"Asia/Jakarta",
    "iso:country":"ID",
    "name:ind_x_preferred":[
        "Palawija"
    ],
    "name:und_x_variant":[
        "Palawidja",
        "Palawija",
        "Blawija"
    ],
    "wof:lang_x_official":[
        "ind"
    ],
    "wof:lang_x_spoken":[
        "ind",
        "eng"
    ],
    "wof:name":"Palawija",
    "wof:placetype":"locality"
},
  "geometry": {"coordinates":[108.2495,-7.559],"type":"Point"}
}