{
  "type": "Feature",
  "properties": {
    "gn:admin1_code":"8.0",
    "gn:asciiname":"Talok",
    "gn:country_code":"ID",
    "gn:dem":73,
    "gn:feature_class":"P",
    "gn:feature_code":"PPL",
    "gn:name":"Talok",
    "gn:population":0,
    "gn:timezone":"Asia/Jakarta",
    "iso:country":"ID",
    "name:fas_x_preferred":[
        "\u062a\u0644\u06a9"
    ],
    "name:ind_x_preferred":[
        "Talok"
    ],
    "name:msa_x_preferred":[
        "Talok"
    ],
    "wof:lang_x_official":[
        "ind"
    ],
    "wof:lang_x_spoken":[
        "ind",
        "eng"
    ],
    "wof:name":"Talok",
    "wof:placetype":"locality"
},
  "geometry": {"coordinates":[112.0917,-7.3242],"type":"Point"}
}