{
  "type": "Feature",
  "properties": {
    "gn:admin1_code":"38.0",
    "gn:asciiname":"Torrodasi",
    "gn:country_code":"ID",
    "gn:dem":1236,
    "gn:feature_class":"P",
    "gn:feature_code":"PPL",
    "gn:name":"Torrodasi",
    "gn:population":0,
    "gn:timezone":"Asia/Makassar",
    "iso:country":"ID",
    "name:ind_x_preferred":[
        "Torrodasi"
    ],
    "wof:name":"Torrodasi",
    "wof:placetype":"locality"
},
  "geometry": {"coordinates":[119.8997,-2.8945],"type":"Point"}
}