{
  "type": "Feature",
  "properties": {
    "gn:admin1_code":"30",
    "gn:asciiname":"Cikumpa Dua",
    "gn:cc2":"ID",
    "gn:country_code":"ID",
    "gn:dem":93,
    "gn:feature_class":"P",
    "gn:feature_code":"PPL",
    "gn:name":"Cikumpa Dua",
    "gn:population":0,
    "gn:timezone":"Asia/Jakarta",
    "iso:country":"ID",
    "name:und_x_variant":[
        "Tjikumpa 2",
        "Tjikumpa Dua",
        "Cikumpa Dua"
    ],
    "wof:lang_x_official":[
        "ind"
    ],
    "wof:lang_x_spoken":[
        "ind",
        "eng"
    ],
    "wof:name":"Cikumpa Dua",
    "wof:placetype":"locality"
},
  "geometry": {"coordinates":[106.83139,-6.4125],"type":"Point"}
}