{
  "type": "Feature",
  "properties": {
    "gn:admin1_code":"30.0",
    "gn:asciiname":"Kawungrendeng",
    "gn:country_code":"ID",
    "gn:dem":690,
    "gn:feature_class":"P",
    "gn:feature_code":"PPL",
    "gn:name":"Kawungrendeng",
    "gn:population":0,
    "gn:timezone":"Asia/Jakarta",
    "iso:country":"ID",
    "name:ind_x_preferred":[
        "Kawungrendeng"
    ],
    "name:und_x_variant":[
        "Kawoenggarendeng"
    ],
    "wof:lang_x_official":[
        "ind"
    ],
    "wof:lang_x_spoken":[
        "ind",
        "eng"
    ],
    "wof:name":"Kawungrendeng",
    "wof:placetype":"locality"
},
  "geometry": {"coordinates":[107.93989999999999,-7.1759],"type":"Point"}
}