{
  "type": "Feature",
  "properties": {
    "gn:admin1_code":"8.0",
    "gn:asciiname":"Den Timur",
    "gn:country_code":"ID",
    "gn:dem":182,
    "gn:feature_class":"P",
    "gn:feature_code":"PPLA4",
    "gn:name":"Den Timur",
    "gn:population":0,
    "gn:timezone":"Asia/Jakarta",
    "iso:country":"ID",
    "name:ind_x_preferred":[
        "Den Timur"
    ],
    "wof:name":"Den Timur",
    "wof:placetype":"locality"
},
  "geometry": {"coordinates":[113.6771,-6.9634],"type":"Point"}
}