{
  "type": "Feature",
  "properties": {
    "gn:admin1_code":"35",
    "gn:asciiname":"Ketap",
    "gn:country_code":"ID",
    "gn:dem":17,
    "gn:feature_class":"P",
    "gn:feature_code":"PPL",
    "gn:name":"Ketap",
    "gn:population":0,
    "gn:timezone":"Asia/Jakarta",
    "iso:country":"ID",
    "name:ind_x_preferred":[
        "Ketap"
    ],
    "wof:name":"Ketap",
    "wof:placetype":"locality"
},
  "geometry": {"coordinates":[105.4614,-1.67644],"type":"Point"}
}