{
  "type": "Feature",
  "properties": {
    "gn:admin1_code":"36.0",
    "gn:asciiname":"Manepsimnee",
    "gn:country_code":"ID",
    "gn:dem":21,
    "gn:feature_class":"P",
    "gn:feature_code":"PPL",
    "gn:name":"Manepsimnee",
    "gn:population":0,
    "gn:timezone":"Asia/Jayapura",
    "iso:country":"ID",
    "name:ind_x_preferred":[
        "Manepsimnee"
    ],
    "name:und_x_variant":[
        "Manep-Simnee"
    ],
    "wof:name":"Manepsimnee",
    "wof:placetype":"locality"
},
  "geometry": {"coordinates":[138.51407,-5.14089],"type":"Point"}
}