{
  "type": "Feature",
  "properties": {
    "gn:admin1_code":"8",
    "gn:asciiname":"Krajan",
    "gn:country_code":"ID",
    "gn:dem":261,
    "gn:feature_class":"P",
    "gn:feature_code":"PPL",
    "gn:name":"Krajan",
    "gn:population":0,
    "gn:timezone":"Asia/Jakarta",
    "iso:country":"ID",
    "name:ind_x_preferred":[
        "Krajan"
    ],
    "wof:name":"Krajan",
    "wof:placetype":"locality"
},
  "geometry": {"coordinates":[113.6652,-8.1307],"type":"Point"}
}