{
  "type": "Feature",
  "properties": {
    "gn:admin1_code":"7.0",
    "gn:asciiname":"Bobosan",
    "gn:country_code":"ID",
    "gn:dem":115,
    "gn:feature_class":"P",
    "gn:feature_code":"PPL",
    "gn:name":"Bobosan",
    "gn:population":0,
    "gn:timezone":"Asia/Jakarta",
    "iso:country":"ID",
    "wof:name":"Bobosan",
    "wof:placetype":"locality"
},
  "geometry": {"coordinates":[110.74806,-7.61361],"type":"Point"}
}