{
  "type": "Feature",
  "properties": {
    "gn:admin1_code":"30.0",
    "gn:asciiname":"Cikeusal",
    "gn:country_code":"ID",
    "gn:dem":446,
    "gn:feature_class":"P",
    "gn:feature_code":"PPLA4",
    "gn:name":"Cikeusal",
    "gn:population":0,
    "gn:timezone":"Asia/Jakarta",
    "iso:country":"ID",
    "name:ind_x_preferred":[
        "Cikeusal"
    ],
    "wof:name":"Cikeusal",
    "wof:placetype":"locality"
},
  "geometry": {"coordinates":[108.11490000000001,-7.4328],"type":"Point"}
}