{
  "type": "Feature",
  "properties": {
    "gn:admin1_code":"18",
    "gn:asciiname":"Tanadereng",
    "gn:country_code":"ID",
    "gn:dem":30,
    "gn:feature_class":"P",
    "gn:feature_code":"PPL",
    "gn:name":"Tanadereng",
    "gn:population":0,
    "gn:timezone":"Asia/Makassar",
    "iso:country":"ID",
    "name:ind_x_preferred":[
        "Tanadereng"
    ],
    "wof:name":"Tanadereng",
    "wof:placetype":"locality"
},
  "geometry": {"coordinates":[119.90130000000001,-8.574],"type":"Point"}
}