{
  "type": "Feature",
  "properties": {
    "gn:admin1_code":"30",
    "gn:asciiname":"Gunungputri Tiga",
    "gn:cc2":"ID",
    "gn:country_code":"ID",
    "gn:dem":94,
    "gn:feature_class":"P",
    "gn:feature_code":"PPL",
    "gn:name":"Gunungputri Tiga",
    "gn:population":0,
    "gn:timezone":"Asia/Jakarta",
    "iso:country":"ID",
    "name:und_x_variant":[
        "Gunungputri 3",
        "Gunungputri Tiga"
    ],
    "wof:name":"Gunungputri Tiga",
    "wof:placetype":"locality"
},
  "geometry": {"coordinates":[106.89972,-6.46528],"type":"Point"}
}