{
  "type": "Feature",
  "properties": {
    "gn:admin1_code":"30.0",
    "gn:asciiname":"Cidahon",
    "gn:country_code":"ID",
    "gn:dem":14,
    "gn:feature_class":"P",
    "gn:feature_code":"PPL",
    "gn:name":"Cidahon",
    "gn:population":0,
    "gn:timezone":"Asia/Jakarta",
    "iso:country":"ID",
    "name:ind_x_preferred":[
        "Cidahon"
    ],
    "wof:name":"Cidahon",
    "wof:placetype":"locality"
},
  "geometry": {"coordinates":[108.3511,-7.8144],"type":"Point"}
}