{
  "type": "Feature",
  "properties": {
    "gn:admin1_code":"2.0",
    "gn:asciiname":"Bhuanamerta",
    "gn:country_code":"ID",
    "gn:dem":19,
    "gn:feature_class":"P",
    "gn:feature_code":"PPL",
    "gn:name":"Bhuanamerta",
    "gn:population":0,
    "gn:timezone":"Asia/Makassar",
    "iso:country":"ID",
    "name:ind_x_preferred":[
        "Bhuanamerta"
    ],
    "wof:name":"Bhuanamerta",
    "wof:placetype":"locality"
},
  "geometry": {"coordinates":[115.19710000000001,-8.6659],"type":"Point"}
}