{
  "type": "Feature",
  "properties": {
    "gn:admin1_code":"24",
    "gn:asciiname":"Kotolamo",
    "gn:country_code":"ID",
    "gn:dem":192,
    "gn:feature_class":"P",
    "gn:feature_code":"PPL",
    "gn:name":"Kotolamo",
    "gn:population":0,
    "gn:timezone":"Asia/Jakarta",
    "iso:country":"ID",
    "name:ind_x_preferred":[
        "Kotolamo"
    ],
    "wof:name":"Kotolamo",
    "wof:placetype":"locality"
},
  "geometry": {"coordinates":[100.52800000000001,0.1569],"type":"Point"}
}