{
  "type": "Feature",
  "properties": {
    "gn:admin1_code":"7",
    "gn:asciiname":"Sigedong",
    "gn:country_code":"ID",
    "gn:dem":1204,
    "gn:feature_class":"P",
    "gn:feature_code":"PPL",
    "gn:name":"Sigedong",
    "gn:population":0,
    "gn:timezone":"Asia/Jakarta",
    "iso:country":"ID",
    "name:ind_x_preferred":[
        "Sigedong"
    ],
    "wof:name":"Sigedong",
    "wof:placetype":"locality"
},
  "geometry": {"coordinates":[109.98806,-7.18028],"type":"Point"}
}