{
  "type": "Feature",
  "properties": {
    "gn:admin1_code":"38",
    "gn:asciiname":"Walanga",
    "gn:country_code":"ID",
    "gn:dem":37,
    "gn:feature_class":"P",
    "gn:feature_code":"PPL",
    "gn:name":"Walanga",
    "gn:population":0,
    "gn:timezone":"Asia/Makassar",
    "iso:country":"ID",
    "name:ind_x_preferred":[
        "Walanga"
    ],
    "wof:name":"Walanga",
    "wof:placetype":"locality"
},
  "geometry": {"coordinates":[120.2253,-4.0522],"type":"Point"}
}