{
  "type": "Feature",
  "properties": {
    "gn:admin1_code":"18.0",
    "gn:asciiname":"Laba",
    "gn:country_code":"ID",
    "gn:dem":379,
    "gn:feature_class":"P",
    "gn:feature_code":"PPL",
    "gn:name":"Laba",
    "gn:population":0,
    "gn:timezone":"Asia/Makassar",
    "iso:country":"ID",
    "name:bel_x_preferred":[
        "\u041b\u0430\u0431\u0430"
    ],
    "name:ceb_x_preferred":[
        "Laba"
    ],
    "name:ces_x_preferred":[
        "Laba"
    ],
    "name:deu_x_preferred":[
        "Laba"
    ],
    "name:est_x_preferred":[
        "Laba"
    ],
    "name:ind_x_preferred":[
        "Laba"
    ],
    "name:kat_x_preferred":[
        "\u10da\u10d0\u10d1\u10d0"
    ],
    "name:lit_x_preferred":[
        "Laba"
    ],
    "name:oss_x_preferred":[
        "\u041b\u0430\u0431\u00e6"
    ],
    "name:pol_x_preferred":[
        "\u0141aba"
    ],
    "name:rus_x_preferred":[
        "\u041b\u0430\u0431\u0430"
    ],
    "name:spa_x_preferred":[
        "Laba"
    ],
    "name:swe_x_preferred":[
        "Laba"
    ],
    "name:ukr_x_preferred":[
        "\u041b\u0430\u0431\u0430"
    ],
    "wof:name":"Laba",
    "wof:placetype":"locality"
},
  "geometry": {"coordinates":[120.0004,-8.6447],"type":"Point"}
}