{
  "type": "Feature",
  "properties": {
    "gn:admin1_code":"18.0",
    "gn:asciiname":"Kisan",
    "gn:country_code":"ID",
    "gn:dem":429,
    "gn:feature_class":"P",
    "gn:feature_code":"PPL",
    "gn:name":"Kisan",
    "gn:population":0,
    "gn:timezone":"Asia/Makassar",
    "iso:country":"ID",
    "name:ind_x_preferred":[
        "Kisan"
    ],
    "wof:name":"Kisan",
    "wof:placetype":"locality"
},
  "geometry": {"coordinates":[123.7841,-10.2465],"type":"Point"}
}