{
  "type": "Feature",
  "properties": {
    "gn:admin1_code":"12",
    "gn:asciiname":"Mandilibak",
    "gn:country_code":"ID",
    "gn:dem":25,
    "gn:feature_class":"P",
    "gn:feature_code":"PPL",
    "gn:name":"Mandilibak",
    "gn:population":0,
    "gn:timezone":"Asia/Makassar",
    "iso:country":"ID",
    "name:ind_x_preferred":[
        "Mandilibak"
    ],
    "wof:name":"Mandilibak",
    "wof:placetype":"locality"
},
  "geometry": {"coordinates":[116.3848,-3.5534],"type":"Point"}
}