{
  "type": "Feature",
  "properties": {
    "gn:admin1_code":"1",
    "gn:asciiname":"Meugit Sagoe",
    "gn:country_code":"ID",
    "gn:dem":24,
    "gn:feature_class":"P",
    "gn:feature_code":"PPL",
    "gn:name":"Meugit Sagoe",
    "gn:population":0,
    "gn:timezone":"Asia/Jakarta",
    "iso:country":"ID",
    "name:ind_x_preferred":[
        "Meugit Sagoe"
    ],
    "wof:name":"Meugit Sagoe",
    "wof:placetype":"locality"
},
  "geometry": {"coordinates":[96.3266,5.1842],"type":"Point"}
}