{
  "type": "Feature",
  "properties": {
    "gn:admin1_code":"24",
    "gn:asciiname":"Telaga Satu",
    "gn:country_code":"ID",
    "gn:dem":560,
    "gn:feature_class":"P",
    "gn:feature_code":"PPL",
    "gn:name":"Telaga Satu",
    "gn:population":0,
    "gn:timezone":"Asia/Jakarta",
    "iso:country":"ID",
    "name:ind_x_preferred":[
        "Telaga Satu"
    ],
    "name:und_x_variant":[
        "Telaga 1"
    ],
    "wof:name":"Telaga Satu",
    "wof:placetype":"locality"
},
  "geometry": {"coordinates":[100.5127,-0.10911],"type":"Point"}
}