{
  "type": "Feature",
  "properties": {
    "gn:admin1_code":"30",
    "gn:asciiname":"Jati",
    "gn:country_code":"ID",
    "gn:dem":790,
    "gn:feature_class":"P",
    "gn:feature_code":"PPL",
    "gn:name":"Jati",
    "gn:population":0,
    "gn:timezone":"Asia/Jakarta",
    "iso:country":"ID",
    "name:ind_x_preferred":[
        "Jati"
    ],
    "wof:name":"Jati",
    "wof:placetype":"locality"
},
  "geometry": {"coordinates":[107.55583,-6.87472],"type":"Point"}
}