{
  "type": "Feature",
  "properties": {
    "gn:admin1_code":"18.0",
    "gn:asciiname":"Toloep Dua",
    "gn:country_code":"ID",
    "gn:dem":290,
    "gn:feature_class":"P",
    "gn:feature_code":"PPL",
    "gn:name":"Toloep Dua",
    "gn:population":0,
    "gn:timezone":"Asia/Makassar",
    "iso:country":"ID",
    "name:ind_x_preferred":[
        "Teloep Dua"
    ],
    "name:ind_x_variant":[
        "Toloep Dua"
    ],
    "wof:name":"Toloep Dua",
    "wof:placetype":"locality"
},
  "geometry": {"coordinates":[124.6251,-9.5383],"type":"Point"}
}