{
  "type": "Feature",
  "properties": {
    "gn:admin1_code":"30.0",
    "gn:asciiname":"Nenggeng",
    "gn:country_code":"ID",
    "gn:dem":625,
    "gn:feature_class":"P",
    "gn:feature_code":"PPL",
    "gn:name":"Nenggeng",
    "gn:population":0,
    "gn:timezone":"Asia/Jakarta",
    "iso:country":"ID",
    "name:ind_x_preferred":[
        "Nenggeng"
    ],
    "wof:name":"Nenggeng",
    "wof:placetype":"locality"
},
  "geometry": {"coordinates":[107.947,-7.0994],"type":"Point"}
}