{
  "type": "Feature",
  "properties": {
    "gn:admin1_code":"33",
    "gn:asciiname":"Giripada",
    "gn:country_code":"ID",
    "gn:dem":21,
    "gn:feature_class":"P",
    "gn:feature_code":"PPL",
    "gn:name":"Giripada",
    "gn:population":0,
    "gn:timezone":"Asia/Jakarta",
    "iso:country":"ID",
    "name:ind_x_preferred":[
        "Giripada"
    ],
    "wof:name":"Giripada",
    "wof:placetype":"locality"
},
  "geometry": {"coordinates":[106.10680000000001,-6.053],"type":"Point"}
}