{
  "type": "Feature",
  "properties": {
    "gn:admin1_code":"30",
    "gn:asciiname":"Rancakaso",
    "gn:country_code":"ID",
    "gn:dem":21,
    "gn:feature_class":"P",
    "gn:feature_code":"PPL",
    "gn:name":"Rancakaso",
    "gn:population":0,
    "gn:timezone":"Asia/Jakarta",
    "iso:country":"ID",
    "name:ind_x_preferred":[
        "Rancakaso"
    ],
    "wof:name":"Rancakaso",
    "wof:placetype":"locality"
},
  "geometry": {"coordinates":[107.22194,-6.3425],"type":"Point"}
}