{
  "type": "Feature",
  "properties": {
    "gn:admin1_code":"8",
    "gn:asciiname":"Pejitalang Kidul",
    "gn:country_code":"ID",
    "gn:dem":136,
    "gn:feature_class":"P",
    "gn:feature_code":"PPL",
    "gn:name":"Pejitalang Kidul",
    "gn:population":0,
    "gn:timezone":"Asia/Jakarta",
    "iso:country":"ID",
    "name:ind_x_preferred":[
        "Pejitalang Kidul"
    ],
    "wof:name":"Pejitalang Kidul",
    "wof:placetype":"locality"
},
  "geometry": {"coordinates":[113.7636,-8.2315],"type":"Point"}
}