{
  "type": "Feature",
  "properties": {
    "gn:admin1_code":"7.0",
    "gn:asciiname":"Tegalpanggung",
    "gn:country_code":"ID",
    "gn:dem":686,
    "gn:feature_class":"P",
    "gn:feature_code":"PPL",
    "gn:name":"Tegalpanggung",
    "gn:population":0,
    "gn:timezone":"Asia/Jakarta",
    "iso:country":"ID",
    "wof:name":"Tegalpanggung",
    "wof:placetype":"locality"
},
  "geometry": {"coordinates":[110.40528,-7.61389],"type":"Point"}
}