{
  "type": "Feature",
  "properties": {
    "gn:admin1_code":"38",
    "gn:asciiname":"Damba",
    "gn:country_code":"ID",
    "gn:dem":134,
    "gn:feature_class":"P",
    "gn:feature_code":"PPL",
    "gn:name":"Damba",
    "gn:population":0,
    "gn:timezone":"Asia/Makassar",
    "iso:country":"ID",
    "name:cat_x_preferred":[
        "Paretroplus damii"
    ],
    "name:ceb_x_preferred":[
        "Paretroplus damii"
    ],
    "name:eus_x_preferred":[
        "Paretroplus damii"
    ],
    "name:fas_x_preferred":[
        "\u062f\u0645\u0628\u0627"
    ],
    "name:ind_x_preferred":[
        "Damba"
    ],
    "name:nld_x_preferred":[
        "Paretroplus damii"
    ],
    "name:por_x_preferred":[
        "Paretroplus damii"
    ],
    "name:spa_x_preferred":[
        "Paretroplus damii"
    ],
    "name:swe_x_preferred":[
        "Paretroplus damii"
    ],
    "name:vie_x_preferred":[
        "Paretroplus damii"
    ],
    "name:war_x_preferred":[
        "Paretroplus damii"
    ],
    "name:zho_x_preferred":[
        "\u9054\u7c73\u6c0f\u526f\u71b1\u9bdb"
    ],
    "wof:lang_x_official":[
        "ind"
    ],
    "wof:lang_x_spoken":[
        "ind",
        "eng"
    ],
    "wof:name":"Damba",
    "wof:placetype":"locality"
},
  "geometry": {"coordinates":[120.3252,-5.3085],"type":"Point"}
}