{
  "type": "Feature",
  "properties": {
    "gn:admin1_code":"38",
    "gn:asciiname":"Damba",
    "gn:country_code":"ID",
    "gn:dem":134,
    "gn:feature_class":"P",
    "gn:feature_code":"PPL",
    "gn:name":"Damba",
    "gn:population":0,
    "gn:timezone":"Asia/Makassar",
    "iso:country":"ID",
    "name:ind_x_preferred":[
        "Damba"
    ],
    "wof:name":"Damba",
    "wof:placetype":"locality"
},
  "geometry": {"coordinates":[120.3252,-5.3085],"type":"Point"}
}