{
  "type": "Feature",
  "properties": {
    "gn:admin1_code":"8",
    "gn:asciiname":"Nglogung",
    "gn:country_code":"ID",
    "gn:dem":233,
    "gn:feature_class":"P",
    "gn:feature_code":"PPL",
    "gn:name":"Nglogung",
    "gn:population":0,
    "gn:timezone":"Asia/Jakarta",
    "iso:country":"ID",
    "name:ind_x_preferred":[
        "Nglogung"
    ],
    "wof:name":"Nglogung",
    "wof:placetype":"locality"
},
  "geometry": {"coordinates":[111.55500000000001,-7.8062],"type":"Point"}
}