{
  "type": "Feature",
  "properties": {
    "gn:admin1_code":"30",
    "gn:asciiname":"Legokbatu",
    "gn:country_code":"ID",
    "gn:dem":265,
    "gn:feature_class":"P",
    "gn:feature_code":"PPL",
    "gn:name":"Legokbatu",
    "gn:population":0,
    "gn:timezone":"Asia/Jakarta",
    "iso:country":"ID",
    "name:ind_x_preferred":[
        "Legokbatu"
    ],
    "wof:name":"Legokbatu",
    "wof:placetype":"locality"
},
  "geometry": {"coordinates":[106.50972,-6.92472],"type":"Point"}
}