{
  "type": "Feature",
  "properties": {
    "gn:admin1_code":"30.0",
    "gn:asciiname":"Pasirhirung",
    "gn:country_code":"ID",
    "gn:dem":1051,
    "gn:feature_class":"P",
    "gn:feature_code":"PPL",
    "gn:name":"Pasirhirung",
    "gn:population":0,
    "gn:timezone":"Asia/Jakarta",
    "iso:country":"ID",
    "name:ind_x_preferred":[
        "Pasirhirung"
    ],
    "wof:name":"Pasirhirung",
    "wof:placetype":"locality"
},
  "geometry": {"coordinates":[107.53700000000001,-7.2822],"type":"Point"}
}