{
  "type": "Feature",
  "properties": {
    "gn:admin1_code":"7",
    "gn:asciiname":"Karangtengah",
    "gn:country_code":"ID",
    "gn:dem":816,
    "gn:feature_class":"P",
    "gn:feature_code":"PPL",
    "gn:name":"Karangtengah",
    "gn:population":0,
    "gn:timezone":"Asia/Jakarta",
    "iso:country":"ID",
    "name:ind_x_preferred":[
        "Karangtengah"
    ],
    "wof:name":"Karangtengah",
    "wof:placetype":"locality"
},
  "geometry": {"coordinates":[110.22583,-7.21778],"type":"Point"}
}