{
  "type": "Feature",
  "properties": {
    "gn:admin1_code":"1",
    "gn:asciiname":"Aek Nauli",
    "gn:country_code":"ID",
    "gn:dem":14,
    "gn:feature_class":"P",
    "gn:feature_code":"PPL",
    "gn:name":"Aek Nauli",
    "gn:population":0,
    "gn:timezone":"Asia/Jakarta",
    "iso:country":"ID",
    "name:ind_x_preferred":[
        "Aek Nauli"
    ],
    "wof:name":"Aek Nauli",
    "wof:placetype":"locality"
},
  "geometry": {"coordinates":[99.7055,2.7753],"type":"Point"}
}