{
  "type": "Feature",
  "properties": {
    "gn:admin1_code":"26.0",
    "gn:asciiname":"Tumpak Raya",
    "gn:country_code":"ID",
    "gn:dem":911,
    "gn:feature_class":"P",
    "gn:feature_code":"PPL",
    "gn:name":"Tumpak Raya",
    "gn:population":0,
    "gn:timezone":"Asia/Jakarta",
    "iso:country":"ID",
    "name:ind_x_preferred":[
        "Tumpak Raya"
    ],
    "name:und_x_variant":[
        "Toempakradja",
        "Tumpakradja",
        "Tumpakraja"
    ],
    "wof:lang_x_official":[
        "ind"
    ],
    "wof:lang_x_spoken":[
        "ind",
        "eng"
    ],
    "wof:name":"Tumpak Raya",
    "wof:placetype":"locality"
},
  "geometry": {"coordinates":[98.36060000000001,2.8528],"type":"Point"}
}