{
  "type": "Feature",
  "properties": {
    "gn:admin1_code":"24",
    "gn:asciiname":"Kotabaru",
    "gn:country_code":"ID",
    "gn:dem":389,
    "gn:feature_class":"P",
    "gn:feature_code":"PPL",
    "gn:name":"Kotabaru",
    "gn:population":0,
    "gn:timezone":"Asia/Jakarta",
    "iso:country":"ID",
    "name:ind_x_preferred":[
        "Kotabaru"
    ],
    "wof:name":"Kotabaru",
    "wof:placetype":"locality"
},
  "geometry": {"coordinates":[100.65107999999999,-0.82105],"type":"Point"}
}