{
  "type": "Feature",
  "properties": {
    "gn:admin1_code":"30.0",
    "gn:asciiname":"Cikalong",
    "gn:country_code":"ID",
    "gn:dem":231,
    "gn:feature_class":"P",
    "gn:feature_code":"PPL",
    "gn:name":"Cikalong",
    "gn:population":0,
    "gn:timezone":"Asia/Jakarta",
    "iso:country":"ID",
    "name:ind_x_preferred":[
        "Cikalong"
    ],
    "name:und_x_variant":[
        "Tjikalong 2"
    ],
    "wof:lang_x_official":[
        "ind"
    ],
    "wof:lang_x_spoken":[
        "ind",
        "eng"
    ],
    "wof:name":"Cikalong",
    "wof:placetype":"locality"
},
  "geometry": {"coordinates":[108.0476,-7.6625],"type":"Point"}
}