{
  "type": "Feature",
  "properties": {
    "gn:admin1_code":"0.0",
    "gn:asciiname":"Botorejo",
    "gn:cc2":"ID",
    "gn:country_code":"ID",
    "gn:dem":209,
    "gn:feature_class":"P",
    "gn:feature_code":"PPL",
    "gn:name":"Botorejo",
    "gn:population":0,
    "gn:timezone":"Asia/Jakarta",
    "iso:country":"ID",
    "name:und_x_variant":[
        "Botoredjo",
        "Buluredjo",
        "Botorejo"
    ],
    "wof:name":"Botorejo",
    "wof:placetype":"locality"
},
  "geometry": {"coordinates":[109.93333,-7.56667],"type":"Point"}
}