{
  "type": "Feature",
  "properties": {
    "gn:admin1_code":"30",
    "gn:asciiname":"Kandanggede",
    "gn:cc2":"ID",
    "gn:country_code":"ID",
    "gn:dem":11,
    "gn:feature_class":"P",
    "gn:feature_code":"PPL",
    "gn:name":"Kandanggede",
    "gn:population":0,
    "gn:timezone":"Asia/Jakarta",
    "iso:country":"ID",
    "name:und_x_variant":[
        "Kandanggede Dua",
        "Kandanggede 2",
        "Kandanggede"
    ],
    "wof:name":"Kandanggede",
    "wof:placetype":"locality"
},
  "geometry": {"coordinates":[106.42722000000001,-6.09444],"type":"Point"}
}