{
  "type": "Feature",
  "properties": {
    "gn:admin1_code":"37.0",
    "gn:asciiname":"Pulausialang",
    "gn:country_code":"ID",
    "gn:dem":22,
    "gn:feature_class":"P",
    "gn:feature_code":"PPL",
    "gn:name":"Pulausialang",
    "gn:population":0,
    "gn:timezone":"Asia/Jakarta",
    "iso:country":"ID",
    "name:ind_x_preferred":[
        "Pulausialang"
    ],
    "wof:name":"Pulausialang",
    "wof:placetype":"locality"
},
  "geometry": {"coordinates":[102.17975,-0.48457],"type":"Point"}
}