{
  "type": "Feature",
  "properties": {
    "gn:admin1_code":"30.0",
    "gn:asciiname":"Dangiang",
    "gn:country_code":"ID",
    "gn:dem":739,
    "gn:feature_class":"P",
    "gn:feature_code":"PPL",
    "gn:name":"Dangiang",
    "gn:population":0,
    "gn:timezone":"Asia/Jakarta",
    "iso:country":"ID",
    "name:ind_x_preferred":[
        "Dangiang"
    ],
    "wof:name":"Dangiang",
    "wof:placetype":"locality"
},
  "geometry": {"coordinates":[108.11920000000001,-7.1061],"type":"Point"}
}