{
  "type": "Feature",
  "properties": {
    "gn:admin1_code":"8.0",
    "gn:asciiname":"Redonkrapyak",
    "gn:country_code":"ID",
    "gn:dem":187,
    "gn:feature_class":"P",
    "gn:feature_code":"PPL",
    "gn:name":"Redonkrapyak",
    "gn:population":0,
    "gn:timezone":"Asia/Jakarta",
    "iso:country":"ID",
    "name:ind_x_preferred":[
        "Redonkrapyak"
    ],
    "wof:name":"Redonkrapyak",
    "wof:placetype":"locality"
},
  "geometry": {"coordinates":[112.07380000000001,-8.2456],"type":"Point"}
}