{
  "type": "Feature",
  "properties": {
    "gn:admin1_code":"12",
    "gn:asciiname":"Karangintan",
    "gn:country_code":"ID",
    "gn:dem":18,
    "gn:feature_class":"P",
    "gn:feature_code":"PPL",
    "gn:name":"Karangintan",
    "gn:population":0,
    "gn:timezone":"Asia/Makassar",
    "iso:country":"ID",
    "name:ind_x_preferred":[
        "Karangintan"
    ],
    "wof:name":"Karangintan",
    "wof:placetype":"locality"
},
  "geometry": {"coordinates":[115.75709999999999,-3.5664],"type":"Point"}
}