{
  "type": "Feature",
  "properties": {
    "gn:admin1_code":"7.0",
    "gn:asciiname":"Kenja",
    "gn:country_code":"ID",
    "gn:dem":75,
    "gn:feature_class":"P",
    "gn:feature_code":"PPL",
    "gn:name":"Kenja",
    "gn:population":0,
    "gn:timezone":"Asia/Jakarta",
    "iso:country":"ID",
    "name:ind_x_preferred":[
        "Kenja"
    ],
    "wof:name":"Kenja",
    "wof:placetype":"locality"
},
  "geometry": {"coordinates":[109.45722000000001,-7.75222],"type":"Point"}
}