{
  "type": "Feature",
  "properties": {
    "gn:admin1_code":"30",
    "gn:asciiname":"Tenjolaut",
    "gn:country_code":"ID",
    "gn:dem":382,
    "gn:feature_class":"P",
    "gn:feature_code":"PPL",
    "gn:name":"Tenjolaut",
    "gn:population":0,
    "gn:timezone":"Asia/Jakarta",
    "iso:country":"ID",
    "name:ind_x_preferred":[
        "Tenjolaut"
    ],
    "wof:name":"Tenjolaut",
    "wof:placetype":"locality"
},
  "geometry": {"coordinates":[108.02417,-6.77389],"type":"Point"}
}