{
  "type": "Feature",
  "properties": {
    "gn:admin1_code":"30",
    "gn:asciiname":"Cibolang",
    "gn:country_code":"ID",
    "gn:dem":569,
    "gn:feature_class":"P",
    "gn:feature_code":"PPL",
    "gn:name":"Cibolang",
    "gn:population":0,
    "gn:timezone":"Asia/Jakarta",
    "iso:country":"ID",
    "name:ind_x_preferred":[
        "Cibolang"
    ],
    "wof:name":"Cibolang",
    "wof:placetype":"locality"
},
  "geometry": {"coordinates":[107.93971999999999,-6.90333],"type":"Point"}
}