{
  "type": "Feature",
  "properties": {
    "gn:admin1_code":"8",
    "gn:asciiname":"Pesantren",
    "gn:country_code":"ID",
    "gn:dem":34,
    "gn:feature_class":"P",
    "gn:feature_code":"PPL",
    "gn:name":"Pesantren",
    "gn:population":0,
    "gn:timezone":"Asia/Jakarta",
    "iso:country":"ID",
    "name:ace_x_preferred":[
        "Dayah"
    ],
    "name:ara_x_preferred":[
        "\u0628\u064a\u0633\u0646\u062a\u0631\u064a\u0646"
    ],
    "name:ind_x_preferred":[
        "Pesantren"
    ],
    "name:jav_x_preferred":[
        "Pesantr\u00e8n"
    ],
    "name:jpn_x_preferred":[
        "\u30d7\u30b5\u30f3\u30c8\u30ec\u30f3"
    ],
    "name:msa_x_preferred":[
        "Sekolah pondok"
    ],
    "name:sun_x_preferred":[
        "Pasantr\u00e9n"
    ],
    "wof:lang_x_official":[
        "ind"
    ],
    "wof:lang_x_spoken":[
        "ind",
        "eng"
    ],
    "wof:name":"Pesantren",
    "wof:placetype":"locality"
},
  "geometry": {"coordinates":[112.2316,-7.4924],"type":"Point"}
}