{
  "type": "Feature",
  "properties": {
    "iso:country":"ID",
    "name:eng_x_preferred":[
        "Toegoe"
    ],
    "name:unk_x_variant":[
        "Toegoe"
    ],
    "qs:gn_adm0_cc":"ID",
    "qs:gn_local":1621177,
    "qs:local_max":2385,
    "qs:local_sum":9009,
    "qs:localhoods":9,
    "qs:name":"Toegoe",
    "qs:name_adm0":"Indonesia",
    "qs:name_adm1":"Daerah Istimewa Yogyakarta",
    "qs:name_adm2":"Bantul",
    "qs:name_local":"Yogyakarta",
    "qs:photo_max":6,
    "qs:photo_sum":51,
    "qs:placetype":"Suburb",
    "qs:quad_count":15,
    "qs:woe_adm0":23424846,
    "qs:woe_adm1":2345719,
    "qs:woe_adm2":56000247,
    "qs:woe_lau":0,
    "qs:woe_local":1047065,
    "qs:woe_ver":"7.10.0",
    "wof:lang":[
        "eng"
    ],
    "wof:name":"Toegoe",
    "wof:placetype":"neighbourhood"
},
  "geometry": {"coordinates":[110.35041200000001,-7.783159],"type":"Point"}
}