{
  "type": "Feature",
  "properties": {
    "gn:admin1_code":"10.0",
    "gn:asciiname":"Nepi",
    "gn:country_code":"ID",
    "gn:dem":23,
    "gn:feature_class":"P",
    "gn:feature_code":"PPL",
    "gn:name":"Nepi",
    "gn:population":0,
    "gn:timezone":"Asia/Jakarta",
    "iso:country":"ID",
    "name:azb_x_preferred":[
        "\u0646\u067e\u06cc"
    ],
    "name:bcl_x_preferred":[
        "Nepi"
    ],
    "name:bul_x_preferred":[
        "\u041d\u0435\u043f\u0438"
    ],
    "name:cat_x_preferred":[
        "Nepi"
    ],
    "name:ceb_x_preferred":[
        "Nepi"
    ],
    "name:deu_x_preferred":[
        "Nepi"
    ],
    "name:epo_x_preferred":[
        "Nepi"
    ],
    "name:eus_x_preferred":[
        "Nepi"
    ],
    "name:fas_x_preferred":[
        "\u0646\u067e\u06cc"
    ],
    "name:fra_x_preferred":[
        "Nepi"
    ],
    "name:hun_x_preferred":[
        "Nepi"
    ],
    "name:hye_x_preferred":[
        "\u0546\u0565\u057a\u056b"
    ],
    "name:ina_x_preferred":[
        "Nepi"
    ],
    "name:ita_x_preferred":[
        "Nepi"
    ],
    "name:jpn_x_preferred":[
        "\u30cd\u30fc\u30d4"
    ],
    "name:kaz_x_preferred":[
        "\u041d\u0435\u043f\u0438"
    ],
    "name:lat_x_preferred":[
        "Nepete"
    ],
    "name:lmo_x_preferred":[
        "Nepi"
    ],
    "name:msa_x_preferred":[
        "Nepi"
    ],
    "name:nap_x_preferred":[
        "Nepi"
    ],
    "name:nld_x_preferred":[
        "Nepi"
    ],
    "name:pms_x_preferred":[
        "Nepi"
    ],
    "name:pol_x_preferred":[
        "Nepi"
    ],
    "name:por_x_preferred":[
        "Nepi"
    ],
    "name:ron_x_preferred":[
        "Nepi"
    ],
    "name:rus_x_preferred":[
        "\u041d\u0435\u043f\u0438"
    ],
    "name:scn_x_preferred":[
        "Nepi"
    ],
    "name:spa_x_preferred":[
        "Nepi"
    ],
    "name:srp_x_preferred":[
        "\u041d\u0435\u043f\u0438"
    ],
    "name:swe_x_preferred":[
        "Nepi"
    ],
    "name:tur_x_preferred":[
        "Nepi"
    ],
    "name:ukr_x_preferred":[
        "\u041d\u0435\u043f\u0456"
    ],
    "name:uzb_x_preferred":[
        "Nepi"
    ],
    "name:vie_x_preferred":[
        "Nepi"
    ],
    "name:vol_x_preferred":[
        "Nepi"
    ],
    "name:war_x_preferred":[
        "Nepi"
    ],
    "name:zho_x_preferred":[
        "\u5185\u76ae"
    ],
    "wof:lang_x_official":[
        "ind"
    ],
    "wof:lang_x_spoken":[
        "ind",
        "eng"
    ],
    "wof:name":"Nepi",
    "wof:placetype":"locality"
},
  "geometry": {"coordinates":[110.23139,-7.94833],"type":"Point"}
}