{
  "type": "Feature",
  "properties": {
    "gn:admin1_code":"30",
    "gn:asciiname":"Jereget",
    "gn:country_code":"ID",
    "gn:dem":1062,
    "gn:feature_class":"P",
    "gn:feature_code":"PPL",
    "gn:name":"Jereget",
    "gn:population":0,
    "gn:timezone":"Asia/Jakarta",
    "iso:country":"ID",
    "name:ind_x_preferred":[
        "Jereget"
    ],
    "wof:lang_x_official":[
        "ind"
    ],
    "wof:lang_x_spoken":[
        "ind",
        "eng"
    ],
    "wof:name":"Jereget",
    "wof:placetype":"locality"
},
  "geometry": {"coordinates":[107.80880000000001,-7.1979],"type":"Point"}
}