{
  "type": "Feature",
  "properties": {
    "gn:admin1_code":"8.0",
    "gn:asciiname":"Janti",
    "gn:country_code":"ID",
    "gn:dem":109,
    "gn:feature_class":"P",
    "gn:feature_code":"PPL",
    "gn:name":"Janti",
    "gn:population":0,
    "gn:timezone":"Asia/Jakarta",
    "iso:country":"ID",
    "name:fra_x_preferred":[
        "Jante"
    ],
    "name:ind_x_preferred":[
        "Janti"
    ],
    "name:ita_x_preferred":[
        "Janti"
    ],
    "name:mai_x_preferred":[
        "\u091c\u0928\u094d\u0924\u0940"
    ],
    "name:msa_x_preferred":[
        "Janti"
    ],
    "name:new_x_preferred":[
        "\u091c\u093e\u0901\u0924\u0947 \u0917\u093e\u0935\u093f\u0938"
    ],
    "name:pol_x_preferred":[
        "Jante"
    ],
    "name:urd_x_preferred":[
        "\u062c\u0627\u0646\u062a\u06cc"
    ],
    "wof:lang_x_official":[
        "ind"
    ],
    "wof:lang_x_spoken":[
        "ind",
        "eng"
    ],
    "wof:name":"Janti",
    "wof:placetype":"locality"
},
  "geometry": {"coordinates":[111.41379999999999,-7.9383],"type":"Point"}
}