{
  "type": "Feature",
  "properties": {
    "gn:admin1_code":"30",
    "gn:asciiname":"Babakanciamis",
    "gn:country_code":"ID",
    "gn:dem":354,
    "gn:feature_class":"P",
    "gn:feature_code":"PPL",
    "gn:name":"Babakanciamis",
    "gn:population":0,
    "gn:timezone":"Asia/Jakarta",
    "iso:country":"ID",
    "name:ind_x_preferred":[
        "Babakanciamis"
    ],
    "wof:name":"Babakanciamis",
    "wof:placetype":"locality"
},
  "geometry": {"coordinates":[106.88222,-6.55222],"type":"Point"}
}