{
  "type": "Feature",
  "properties": {
    "gn:admin1_code":"30",
    "gn:asciiname":"Kobaklopang",
    "gn:country_code":"ID",
    "gn:dem":13,
    "gn:feature_class":"P",
    "gn:feature_code":"PPL",
    "gn:name":"Kobaklopang",
    "gn:population":0,
    "gn:timezone":"Asia/Jakarta",
    "iso:country":"ID",
    "name:ind_x_preferred":[
        "Kobaklopang"
    ],
    "name:und_x_variant":[
        "Kobaklompong"
    ],
    "wof:name":"Kobaklopang",
    "wof:placetype":"locality"
},
  "geometry": {"coordinates":[107.18722,-6.18389],"type":"Point"}
}