{
  "type": "Feature",
  "properties": {
    "gn:admin1_code":"34.0",
    "gn:asciiname":"Batubata",
    "gn:country_code":"ID",
    "gn:dem":17,
    "gn:feature_class":"P",
    "gn:feature_code":"PPL",
    "gn:name":"Batubata",
    "gn:population":0,
    "gn:timezone":"Asia/Makassar",
    "iso:country":"ID",
    "name:ind_x_preferred":[
        "Batubata"
    ],
    "wof:name":"Batubata",
    "wof:placetype":"locality"
},
  "geometry": {"coordinates":[123.03579999999999,0.5809],"type":"Point"}
}