{
  "type": "Feature",
  "properties": {
    "gn:admin1_code":"30.0",
    "gn:asciiname":"Rancarongge",
    "gn:country_code":"ID",
    "gn:dem":438,
    "gn:feature_class":"P",
    "gn:feature_code":"PPL",
    "gn:name":"Rancarongge",
    "gn:population":0,
    "gn:timezone":"Asia/Jakarta",
    "iso:country":"ID",
    "name:ind_x_preferred":[
        "Rancarongge"
    ],
    "wof:name":"Rancarongge",
    "wof:placetype":"locality"
},
  "geometry": {"coordinates":[108.032,-7.4298],"type":"Point"}
}