{
  "type": "Feature",
  "properties": {
    "gn:admin1_code":"7",
    "gn:asciiname":"Beto",
    "gn:country_code":"ID",
    "gn:dem":438,
    "gn:feature_class":"P",
    "gn:feature_code":"PPL",
    "gn:name":"Beto",
    "gn:population":0,
    "gn:timezone":"Asia/Jakarta",
    "iso:country":"ID",
    "name:heb_x_preferred":[
        "\u05d1\u05d8\u05d5"
    ],
    "name:ind_x_preferred":[
        "Beto"
    ],
    "wof:lang_x_official":[
        "ind"
    ],
    "wof:lang_x_spoken":[
        "ind",
        "eng"
    ],
    "wof:name":"Beto",
    "wof:placetype":"locality"
},
  "geometry": {"coordinates":[110.8222,-6.6539],"type":"Point"}
}