{
  "type": "Feature",
  "properties": {
    "gn:admin1_code":"30",
    "gn:asciiname":"Narogong",
    "gn:country_code":"ID",
    "gn:dem":673,
    "gn:feature_class":"P",
    "gn:feature_code":"PPL",
    "gn:name":"Narogong",
    "gn:population":0,
    "gn:timezone":"Asia/Jakarta",
    "iso:country":"ID",
    "name:ind_x_preferred":[
        "Narogong"
    ],
    "name:und_x_variant":[
        "Nurogang"
    ],
    "wof:name":"Narogong",
    "wof:placetype":"locality"
},
  "geometry": {"coordinates":[107.42638999999998,-6.99722],"type":"Point"}
}