{
  "type": "Feature",
  "properties": {
    "gn:admin1_code":"30.0",
    "gn:asciiname":"Cikerud",
    "gn:country_code":"ID",
    "gn:dem":890,
    "gn:feature_class":"P",
    "gn:feature_code":"PPL",
    "gn:name":"Cikerud",
    "gn:population":0,
    "gn:timezone":"Asia/Jakarta",
    "iso:country":"ID",
    "name:ind_x_preferred":[
        "Cikerud"
    ],
    "wof:name":"Cikerud",
    "wof:placetype":"locality"
},
  "geometry": {"coordinates":[107.9562,-7.51],"type":"Point"}
}