{
  "type": "Feature",
  "properties": {
    "gn:country":"ID",
    "gn:fcode":"PPL",
    "gn:pop":0,
    "iso:country":"ID",
    "name:ban_x_preferred":[
        "Kapanewon"
    ],
    "qs:name":"Girimulyo",
    "qs:name_adm0":"Indonesia",
    "qs:name_adm1":"Daerah Istimewa Yogyakarta",
    "qs:photos_9r":0,
    "qs:photos_sr":0,
    "qs:placetype":"Town",
    "qs:pop_sr":"0",
    "wd:wordcount":224,
    "wof:lang_x_official":[
        "ind"
    ],
    "wof:lang_x_spoken":[
        "ind",
        "eng"
    ],
    "wof:name":"Girimulyo",
    "wof:placetype":"locality",
    "wof:population":0
},
  "geometry": {"coordinates":[110.61333,-7.68861],"type":"Point"}
}