{
  "type": "Feature",
  "properties": {
    "gn:admin1_code":"38",
    "gn:asciiname":"Seko",
    "gn:country_code":"ID",
    "gn:dem":679,
    "gn:feature_class":"P",
    "gn:feature_code":"PPL",
    "gn:name":"Seko",
    "gn:population":0,
    "gn:timezone":"Asia/Makassar",
    "iso:country":"ID",
    "name:ceb_x_preferred":[
        "Seko"
    ],
    "name:deu_x_preferred":[
        "Seko"
    ],
    "name:ind_x_preferred":[
        "Seko"
    ],
    "name:rus_x_preferred":[
        "\u0421\u044d\u043a\u043e"
    ],
    "wof:lang_x_official":[
        "ind"
    ],
    "wof:lang_x_spoken":[
        "ind",
        "eng"
    ],
    "wof:name":"Seko",
    "wof:placetype":"locality"
},
  "geometry": {"coordinates":[119.77719999999999,-4.9216],"type":"Point"}
}