{
  "type": "Feature",
  "properties": {
    "gn:admin1_code":"30.0",
    "gn:asciiname":"Kadupandak",
    "gn:country_code":"ID",
    "gn:dem":368,
    "gn:feature_class":"P",
    "gn:feature_code":"PPLA4",
    "gn:name":"Kadupandak",
    "gn:population":0,
    "gn:timezone":"Asia/Jakarta",
    "iso:country":"ID",
    "name:ind_x_preferred":[
        "Kadupandak"
    ],
    "name:und_x_variant":[
        "Kadoepandak"
    ],
    "wof:lang_x_official":[
        "ind"
    ],
    "wof:lang_x_spoken":[
        "ind",
        "eng"
    ],
    "wof:name":"Kadupandak",
    "wof:placetype":"locality"
},
  "geometry": {"coordinates":[108.2525,-7.3717],"type":"Point"}
}