{
  "type": "Feature",
  "properties": {
    "gn:admin1_code":"26",
    "gn:asciiname":"Basam",
    "gn:country_code":"ID",
    "gn:dem":1394,
    "gn:feature_class":"P",
    "gn:feature_code":"PPL",
    "gn:name":"Basam",
    "gn:population":0,
    "gn:timezone":"Asia/Jakarta",
    "iso:country":"ID",
    "name:ind_x_preferred":[
        "Basam"
    ],
    "wof:name":"Basam",
    "wof:placetype":"locality"
},
  "geometry": {"coordinates":[98.5455,3.1889],"type":"Point"}
}