{
  "type": "Feature",
  "properties": {
    "gn:admin1_code":"24",
    "gn:asciiname":"Pisang Satu",
    "gn:country_code":"ID",
    "gn:dem":14,
    "gn:feature_class":"P",
    "gn:feature_code":"PPL",
    "gn:name":"Pisang Satu",
    "gn:population":0,
    "gn:timezone":"Asia/Jakarta",
    "iso:country":"ID",
    "name:ind_x_preferred":[
        "Pisang Satu"
    ],
    "name:und_x_variant":[
        "Pisang 1"
    ],
    "wof:name":"Pisang Satu",
    "wof:placetype":"locality"
},
  "geometry": {"coordinates":[100.35838,-0.82126],"type":"Point"}
}