{
  "type": "Feature",
  "properties": {
    "gn:admin1_code":"0.0",
    "gn:asciiname":"Cibuntu",
    "gn:cc2":"ID",
    "gn:country_code":"ID",
    "gn:dem":253,
    "gn:feature_class":"P",
    "gn:feature_code":"PPL",
    "gn:name":"Cibuntu",
    "gn:population":0,
    "gn:timezone":"Asia/Jakarta",
    "iso:country":"ID",
    "name:und_x_variant":[
        "Tjibuntu",
        "Cibuntu"
    ],
    "wof:name":"Cibuntu",
    "wof:placetype":"locality"
},
  "geometry": {"coordinates":[107.28333000000001,-6.51667],"type":"Point"}
}