{
  "type": "Feature",
  "properties": {
    "gn:admin1_code":"1",
    "gn:asciiname":"Tumbu",
    "gn:country_code":"ID",
    "gn:dem":7,
    "gn:feature_class":"P",
    "gn:feature_code":"PPL",
    "gn:name":"Tumbu",
    "gn:population":0,
    "gn:timezone":"Asia/Jakarta",
    "iso:country":"ID",
    "name:ceb_x_preferred":[
        "Tumbu"
    ],
    "name:ind_x_preferred":[
        "Tumbu"
    ],
    "name:swe_x_preferred":[
        "Tumbu"
    ],
    "wof:lang_x_official":[
        "ind"
    ],
    "wof:lang_x_spoken":[
        "ind",
        "eng"
    ],
    "wof:name":"Tumbu",
    "wof:placetype":"locality"
},
  "geometry": {"coordinates":[95.9307,5.3775],"type":"Point"}
}