{
  "type": "Feature",
  "properties": {
    "gn:admin1_code":"26",
    "gn:asciiname":"Sidoarjo",
    "gn:country_code":"ID",
    "gn:dem":17,
    "gn:feature_class":"P",
    "gn:feature_code":"PPL",
    "gn:name":"Sidoarjo",
    "gn:population":0,
    "gn:timezone":"Asia/Jakarta",
    "iso:country":"ID",
    "name:ind_x_preferred":[
        "Sidoarjo"
    ],
    "wof:name":"Sidoarjo",
    "wof:placetype":"locality"
},
  "geometry": {"coordinates":[98.3109,3.8136],"type":"Point"}
}