{
  "type": "Feature",
  "properties": {
    "gn:admin1_code":"21.0",
    "gn:asciiname":"Tone",
    "gn:country_code":"ID",
    "gn:dem":26,
    "gn:feature_class":"P",
    "gn:feature_code":"PPL",
    "gn:name":"Tone",
    "gn:population":0,
    "gn:timezone":"Asia/Makassar",
    "iso:country":"ID",
    "name:ara_x_preferred":[
        "\u0646\u063a\u0645\u0629"
    ],
    "name:ben_x_preferred":[
        "\u099f\u09cb\u09a8"
    ],
    "name:ceb_x_preferred":[
        "Tone"
    ],
    "name:deu_x_preferred":[
        "Tone"
    ],
    "name:ell_x_preferred":[
        "\u03a4\u03cc\u03bf\u03c5\u03bd"
    ],
    "name:fin_x_preferred":[
        "Tone"
    ],
    "name:fra_x_preferred":[
        "Tone"
    ],
    "name:ind_x_preferred":[
        "Tone"
    ],
    "name:ita_x_preferred":[
        "Tone"
    ],
    "name:lav_x_preferred":[
        "Tone"
    ],
    "name:nld_x_preferred":[
        "Tone"
    ],
    "name:nno_x_preferred":[
        "Tone"
    ],
    "name:nor_x_preferred":[
        "Tone"
    ],
    "name:pol_x_preferred":[
        "Tone"
    ],
    "name:por_x_preferred":[
        "Tone"
    ],
    "name:rus_x_preferred":[
        "\u0422\u043e\u043d\u0435"
    ],
    "name:slk_x_preferred":[
        "Tone"
    ],
    "name:spa_x_preferred":[
        "Tone"
    ],
    "name:swe_x_preferred":[
        "Tone"
    ],
    "name:ukr_x_preferred":[
        "\u0422\u043e\u043d\u0435"
    ],
    "name:urd_x_preferred":[
        "\u0679\u0648\u0646"
    ],
    "wof:lang_x_official":[
        "ind"
    ],
    "wof:lang_x_spoken":[
        "ind",
        "eng"
    ],
    "wof:name":"Tone",
    "wof:placetype":"locality"
},
  "geometry": {"coordinates":[123.5278,-1.4129],"type":"Point"}
}