{
  "type": "Feature",
  "properties": {
    "gn:admin1_code":"8",
    "gn:asciiname":"Tempuran",
    "gn:country_code":"ID",
    "gn:dem":457,
    "gn:feature_class":"P",
    "gn:feature_code":"PPL",
    "gn:name":"Tempuran",
    "gn:population":0,
    "gn:timezone":"Asia/Jakarta",
    "iso:country":"ID",
    "name:ind_x_preferred":[
        "Tempuran"
    ],
    "wof:name":"Tempuran",
    "wof:placetype":"locality"
},
  "geometry": {"coordinates":[112.6824,-7.9785],"type":"Point"}
}