{
  "type": "Feature",
  "properties": {
    "gn:admin1_code":"07",
    "gn:asciiname":"Bonagung Dua",
    "gn:cc2":"ID",
    "gn:country_code":"ID",
    "gn:dem":179,
    "gn:feature_class":"P",
    "gn:feature_code":"PPL",
    "gn:name":"Bonagung Dua",
    "gn:population":0,
    "gn:timezone":"Asia/Jakarta",
    "iso:country":"ID",
    "name:und_x_variant":[
        "Bonagung 2",
        "Bonagung Dua"
    ],
    "wof:name":"Bonagung Dua",
    "wof:placetype":"locality"
},
  "geometry": {"coordinates":[110.65555999999999,-7.29972],"type":"Point"}
}