{
  "type": "Feature",
  "properties": {
    "gn:admin1_code":"36.0",
    "gn:asciiname":"Toghompatu",
    "gn:country_code":"ID",
    "gn:dem":22,
    "gn:feature_class":"P",
    "gn:feature_code":"PPL",
    "gn:name":"Toghompatu",
    "gn:population":0,
    "gn:timezone":"Asia/Jayapura",
    "iso:country":"ID",
    "name:ind_x_preferred":[
        "Toghompatu"
    ],
    "name:und_x_variant":[
        "Toghom-Patu"
    ],
    "wof:name":"Toghompatu",
    "wof:placetype":"locality"
},
  "geometry": {"coordinates":[139.48418000000001,-6.28688],"type":"Point"}
}