{
  "type": "Feature",
  "properties": {
    "gn:admin1_code":"30",
    "gn:asciiname":"Calung",
    "gn:country_code":"ID",
    "gn:dem":497,
    "gn:feature_class":"P",
    "gn:feature_code":"PPL",
    "gn:name":"Calung",
    "gn:population":0,
    "gn:timezone":"Asia/Jakarta",
    "iso:country":"ID",
    "name:ind_x_preferred":[
        "Calung"
    ],
    "wof:name":"Calung",
    "wof:placetype":"locality"
},
  "geometry": {"coordinates":[107.94889000000001,-6.83306],"type":"Point"}
}