{
  "type": "Feature",
  "properties": {
    "gn:admin1_code":"32.0",
    "gn:asciiname":"Rempasai",
    "gn:country_code":"ID",
    "gn:dem":991,
    "gn:feature_class":"P",
    "gn:feature_code":"PPL",
    "gn:name":"Rempasai",
    "gn:population":0,
    "gn:timezone":"Asia/Jakarta",
    "iso:country":"ID",
    "name:ind_x_preferred":[
        "Rempasai"
    ],
    "name:ind_x_variant":[
        "Rempasari"
    ],
    "wof:lang_x_official":[
        "ind"
    ],
    "wof:lang_x_spoken":[
        "ind",
        "eng"
    ],
    "wof:name":"Rempasai",
    "wof:placetype":"locality"
},
  "geometry": {"coordinates":[103.30184,-4.1181],"type":"Point"}
}