{
  "type": "Feature",
  "properties": {
    "gn:admin1_code":"38",
    "gn:asciiname":"Tasiada",
    "gn:country_code":"ID",
    "gn:dem":52,
    "gn:feature_class":"P",
    "gn:feature_code":"PPL",
    "gn:name":"Tasiada",
    "gn:population":0,
    "gn:timezone":"Asia/Makassar",
    "iso:country":"ID",
    "name:ind_x_preferred":[
        "Tasiada"
    ],
    "wof:name":"Tasiada",
    "wof:placetype":"locality"
},
  "geometry": {"coordinates":[120.27083,-4.45389],"type":"Point"}
}