{
  "type": "Feature",
  "properties": {
    "gn:admin1_code":"7",
    "gn:asciiname":"Banjardowo",
    "gn:country_code":"ID",
    "gn:dem":38,
    "gn:feature_class":"P",
    "gn:feature_code":"PPL",
    "gn:name":"Banjardowo",
    "gn:population":0,
    "gn:timezone":"Asia/Jakarta",
    "iso:country":"ID",
    "name:ind_x_preferred":[
        "Banjardowo"
    ],
    "wof:name":"Banjardowo",
    "wof:placetype":"locality"
},
  "geometry": {"coordinates":[110.99930000000001,-7.1099],"type":"Point"}
}