{
  "type": "Feature",
  "properties": {
    "gn:admin1_code":"7.0",
    "gn:asciiname":"Bangkle",
    "gn:country_code":"ID",
    "gn:dem":91,
    "gn:feature_class":"P",
    "gn:feature_code":"PPLA3",
    "gn:name":"Bangkle",
    "gn:population":0,
    "gn:timezone":"Asia/Jakarta",
    "iso:country":"ID",
    "name:ind_x_preferred":[
        "Bangkle"
    ],
    "wof:lang_x_official":[
        "ind"
    ],
    "wof:lang_x_spoken":[
        "ind",
        "eng"
    ],
    "wof:name":"Bangkle",
    "wof:placetype":"locality"
},
  "geometry": {"coordinates":[111.4307,-6.9706],"type":"Point"}
}