{
  "type": "Feature",
  "properties": {
    "gn:admin1_code":"26",
    "gn:asciiname":"Ujung Rambung Enam",
    "gn:country_code":"ID",
    "gn:dem":11,
    "gn:feature_class":"P",
    "gn:feature_code":"PPL",
    "gn:name":"Ujung Rambung Enam",
    "gn:population":0,
    "gn:timezone":"Asia/Jakarta",
    "iso:country":"ID",
    "name:ind_x_preferred":[
        "Ujung Rambung Enam"
    ],
    "name:und_x_variant":[
        "Ujungrambung 6"
    ],
    "wof:lang_x_official":[
        "ind"
    ],
    "wof:lang_x_spoken":[
        "ind",
        "eng"
    ],
    "wof:name":"Ujung Rambung Enam",
    "wof:placetype":"locality"
},
  "geometry": {"coordinates":[98.93001,3.59829],"type":"Point"}
}