{
  "type": "Feature",
  "properties": {
    "gn:admin1_code":"38",
    "gn:asciiname":"Kaluku",
    "gn:country_code":"ID",
    "gn:dem":396,
    "gn:feature_class":"P",
    "gn:feature_code":"PPL",
    "gn:name":"Kaluku",
    "gn:population":0,
    "gn:timezone":"Asia/Makassar",
    "iso:country":"ID",
    "name:ind_x_preferred":[
        "Kaluku"
    ],
    "wof:name":"Kaluku",
    "wof:placetype":"locality"
},
  "geometry": {"coordinates":[119.77889999999999,-4.9909],"type":"Point"}
}