{
  "type": "Feature",
  "properties": {
    "gn:admin1_code":"8.0",
    "gn:asciiname":"Wonoboyo Dua",
    "gn:country_code":"ID",
    "gn:dem":294,
    "gn:feature_class":"P",
    "gn:feature_code":"PPL",
    "gn:name":"Wonoboyo Dua",
    "gn:population":0,
    "gn:timezone":"Asia/Jakarta",
    "iso:country":"ID",
    "name:ind_x_preferred":[
        "Wonoboyo Dua"
    ],
    "wof:name":"Wonoboyo Dua",
    "wof:placetype":"locality"
},
  "geometry": {"coordinates":[113.8819,-7.7978],"type":"Point"}
}