{
  "type": "Feature",
  "properties": {
    "gn:admin1_code":"30",
    "gn:asciiname":"Nagruk",
    "gn:country_code":"ID",
    "gn:dem":1182,
    "gn:feature_class":"P",
    "gn:feature_code":"PPL",
    "gn:name":"Nagruk",
    "gn:population":0,
    "gn:timezone":"Asia/Jakarta",
    "iso:country":"ID",
    "name:ind_x_preferred":[
        "Nagruk"
    ],
    "name:und_x_variant":[
        "Nagrog 2",
        "Nagrog Dua"
    ],
    "wof:name":"Nagruk",
    "wof:placetype":"locality"
},
  "geometry": {"coordinates":[107.45780000000001,-7.1095],"type":"Point"}
}