{
  "type": "Feature",
  "properties": {
    "gn:admin1_code":"18.0",
    "gn:asciiname":"Toda",
    "gn:country_code":"ID",
    "gn:dem":297,
    "gn:feature_class":"P",
    "gn:feature_code":"PPL",
    "gn:name":"Toda",
    "gn:population":0,
    "gn:timezone":"Asia/Makassar",
    "iso:country":"ID",
    "name:cat_x_preferred":[
        "Toda"
    ],
    "name:ceb_x_preferred":[
        "Toda"
    ],
    "name:deu_x_preferred":[
        "Toda"
    ],
    "name:fra_x_preferred":[
        "Toda"
    ],
    "name:ind_x_preferred":[
        "Toda"
    ],
    "name:ita_x_preferred":[
        "Toda"
    ],
    "name:lav_x_preferred":[
        "Toda"
    ],
    "name:nld_x_preferred":[
        "Toda"
    ],
    "name:pol_x_preferred":[
        "Toda"
    ],
    "name:por_x_preferred":[
        "Toda"
    ],
    "name:rus_x_preferred":[
        "\u0422\u043e\u0434\u0430"
    ],
    "name:spa_x_preferred":[
        "Analfabetismo digital"
    ],
    "name:swe_x_preferred":[
        "Toda"
    ],
    "name:ukr_x_preferred":[
        "\u0422\u043e\u0434\u0430"
    ],
    "wof:lang_x_official":[
        "ind"
    ],
    "wof:lang_x_spoken":[
        "ind",
        "eng"
    ],
    "wof:name":"Toda",
    "wof:placetype":"locality"
},
  "geometry": {"coordinates":[120.32340000000001,-8.3141],"type":"Point"}
}