{
  "type": "Feature",
  "properties": {
    "gn:admin1_code":"10",
    "gn:asciiname":"Karangayu",
    "gn:country_code":"ID",
    "gn:dem":188,
    "gn:feature_class":"P",
    "gn:feature_code":"PPL",
    "gn:name":"Karangayu",
    "gn:population":0,
    "gn:timezone":"Asia/Jakarta",
    "iso:country":"ID",
    "wof:name":"Karangayu",
    "wof:placetype":"locality"
},
  "geometry": {"coordinates":[110.66306000000002,-7.97972],"type":"Point"}
}