{
  "type": "Feature",
  "properties": {
    "gn:admin1_code":"8.0",
    "gn:asciiname":"Banjar",
    "gn:country_code":"ID",
    "gn:dem":860,
    "gn:feature_class":"P",
    "gn:feature_code":"PPL",
    "gn:name":"Banjar",
    "gn:population":0,
    "gn:timezone":"Asia/Jakarta",
    "iso:country":"ID",
    "name:ind_x_preferred":[
        "Banjar"
    ],
    "wof:name":"Banjar",
    "wof:placetype":"locality"
},
  "geometry": {"coordinates":[111.5802,-8.1371],"type":"Point"}
}