{
  "type": "Feature",
  "properties": {
    "gn:admin1_code":"33.0",
    "gn:asciiname":"Cibunar",
    "gn:country_code":"ID",
    "gn:dem":70,
    "gn:feature_class":"P",
    "gn:feature_code":"PPL",
    "gn:name":"Cibunar",
    "gn:population":0,
    "gn:timezone":"Asia/Jakarta",
    "iso:country":"ID",
    "name:ind_x_preferred":[
        "Cibunar"
    ],
    "name:und_x_variant":[
        "Tjibunar",
        "Cibunar"
    ],
    "wof:name":"Cibunar",
    "wof:placetype":"locality"
},
  "geometry": {"coordinates":[106.08163,-6.84136],"type":"Point"}
}