{
  "type": "Feature",
  "properties": {
    "gn:admin1_code":"7.0",
    "gn:asciiname":"Gupit",
    "gn:country_code":"ID",
    "gn:dem":113,
    "gn:feature_class":"P",
    "gn:feature_code":"PPL",
    "gn:name":"Gupit",
    "gn:population":0,
    "gn:timezone":"Asia/Jakarta",
    "iso:country":"ID",
    "name:ind_x_preferred":[
        "Gupit"
    ],
    "wof:name":"Gupit",
    "wof:placetype":"locality"
},
  "geometry": {"coordinates":[109.81583000000001,-7.62417],"type":"Point"}
}