{
  "type": "Feature",
  "properties": {
    "gn:admin1_code":"26",
    "gn:asciiname":"Arangan Jurjur",
    "gn:country_code":"ID",
    "gn:dem":1499,
    "gn:feature_class":"P",
    "gn:feature_code":"PPL",
    "gn:name":"Arangan Jurjur",
    "gn:population":0,
    "gn:timezone":"Asia/Jakarta",
    "iso:country":"ID",
    "name:ind_x_preferred":[
        "Arangan Jurjur"
    ],
    "wof:lang_x_official":[
        "ind"
    ],
    "wof:lang_x_spoken":[
        "ind",
        "eng"
    ],
    "wof:name":"Arangan Jurjur",
    "wof:placetype":"locality"
},
  "geometry": {"coordinates":[98.94499999999999,2.2893],"type":"Point"}
}