{
  "type": "Feature",
  "properties": {
    "gn:admin1_code":"1",
    "gn:asciiname":"Indrapura",
    "gn:country_code":"ID",
    "gn:dem":7,
    "gn:feature_class":"P",
    "gn:feature_code":"PPL",
    "gn:name":"Indrapura",
    "gn:population":0,
    "gn:timezone":"Asia/Jakarta",
    "iso:country":"ID",
    "name:ind_x_preferred":[
        "Indrapura"
    ],
    "wof:name":"Indrapura",
    "wof:placetype":"locality"
},
  "geometry": {"coordinates":[97.0031,3.5483],"type":"Point"}
}