{
  "type": "Feature",
  "properties": {
    "gn:admin1_code":"10",
    "gn:asciiname":"Gandu",
    "gn:country_code":"ID",
    "gn:dem":273,
    "gn:feature_class":"P",
    "gn:feature_code":"PPL",
    "gn:name":"Gandu",
    "gn:population":0,
    "gn:timezone":"Asia/Jakarta",
    "iso:country":"ID",
    "name:ind_x_preferred":[
        "Gandu"
    ],
    "wof:name":"Gandu",
    "wof:placetype":"locality"
},
  "geometry": {"coordinates":[110.52443999999998,-8.06806],"type":"Point"}
}