{
  "type": "Feature",
  "properties": {
    "gn:admin1_code":"22.0",
    "gn:asciiname":"Ataku",
    "gn:country_code":"ID",
    "gn:dem":114,
    "gn:feature_class":"P",
    "gn:feature_code":"PPL",
    "gn:name":"Ataku",
    "gn:population":0,
    "gn:timezone":"Asia/Makassar",
    "iso:country":"ID",
    "name:ind_x_preferred":[
        "Ataku"
    ],
    "wof:name":"Ataku",
    "wof:placetype":"locality"
},
  "geometry": {"coordinates":[122.3222,-4.3453],"type":"Point"}
}