{
  "type": "Feature",
  "properties": {
    "gn:admin1_code":"15.0",
    "gn:asciiname":"Sukarajatiga Satu",
    "gn:country_code":"ID",
    "gn:dem":32,
    "gn:feature_class":"P",
    "gn:feature_code":"PPL",
    "gn:name":"Sukarajatiga Satu",
    "gn:population":0,
    "gn:timezone":"Asia/Jakarta",
    "iso:country":"ID",
    "name:ind_x_preferred":[
        "Sukarajatiga Satu"
    ],
    "name:und_x_variant":[
        "Sukarajatiga 1"
    ],
    "wof:lang_x_official":[
        "ind"
    ],
    "wof:lang_x_spoken":[
        "ind",
        "eng"
    ],
    "wof:name":"Sukarajatiga Satu",
    "wof:placetype":"locality"
},
  "geometry": {"coordinates":[105.48323000000001,-5.22753],"type":"Point"}
}