{
  "type": "Feature",
  "properties": {
    "gn:admin1_code":"1",
    "gn:asciiname":"Angkup",
    "gn:country_code":"ID",
    "gn:dem":996,
    "gn:feature_class":"P",
    "gn:feature_code":"PPLA3",
    "gn:name":"Angkup",
    "gn:population":0,
    "gn:timezone":"Asia/Jakarta",
    "iso:country":"ID",
    "name:ind_x_preferred":[
        "Angkup"
    ],
    "wof:lang_x_official":[
        "ind"
    ],
    "wof:lang_x_spoken":[
        "ind",
        "eng"
    ],
    "wof:name":"Angkup",
    "wof:placetype":"locality"
},
  "geometry": {"coordinates":[96.72280000000001,4.6216],"type":"Point"}
}