{
  "type": "Feature",
  "properties": {
    "gn:admin1_code":"18.0",
    "gn:asciiname":"Leolado",
    "gn:country_code":"ID",
    "gn:dem":213,
    "gn:feature_class":"P",
    "gn:feature_code":"PPL",
    "gn:name":"Leolado",
    "gn:population":0,
    "gn:timezone":"Asia/Makassar",
    "iso:country":"ID",
    "name:ind_x_preferred":[
        "Leolado"
    ],
    "wof:name":"Leolado",
    "wof:placetype":"locality"
},
  "geometry": {"coordinates":[121.8227,-10.5824],"type":"Point"}
}