{
  "type": "Feature",
  "properties": {
    "gn:admin1_code":"22",
    "gn:asciiname":"Sukakarya",
    "gn:country_code":"ID",
    "gn:dem":72,
    "gn:feature_class":"P",
    "gn:feature_code":"PPL",
    "gn:name":"Sukakarya",
    "gn:population":0,
    "gn:timezone":"Asia/Makassar",
    "iso:country":"ID",
    "name:ind_x_preferred":[
        "Sukakarya"
    ],
    "wof:name":"Sukakarya",
    "wof:placetype":"locality"
},
  "geometry": {"coordinates":[122.59699999999999,-4.1077],"type":"Point"}
}