{
  "type": "Feature",
  "properties": {
    "gn:admin1_code":"7",
    "gn:asciiname":"Pejagan",
    "gn:country_code":"ID",
    "gn:dem":4,
    "gn:feature_class":"P",
    "gn:feature_code":"PPL",
    "gn:name":"Pejagan",
    "gn:population":0,
    "gn:timezone":"Asia/Jakarta",
    "iso:country":"ID",
    "name:ind_x_preferred":[
        "Pejagan"
    ],
    "wof:name":"Pejagan",
    "wof:placetype":"locality"
},
  "geometry": {"coordinates":[108.8839,-6.8722],"type":"Point"}
}