{
  "type": "Feature",
  "properties": {
    "gn:admin1_code":"18.0",
    "gn:asciiname":"Airkom",
    "gn:country_code":"ID",
    "gn:dem":25,
    "gn:feature_class":"P",
    "gn:feature_code":"PPL",
    "gn:name":"Airkom",
    "gn:population":0,
    "gn:timezone":"Asia/Makassar",
    "iso:country":"ID",
    "name:ind_x_preferred":[
        "Airkom"
    ],
    "wof:name":"Airkom",
    "wof:placetype":"locality"
},
  "geometry": {"coordinates":[123.8546,-10.0908],"type":"Point"}
}