{
  "type": "Feature",
  "properties": {
    "gn:admin1_code":"8.0",
    "gn:asciiname":"Balongampel",
    "gn:country_code":"ID",
    "gn:dem":13,
    "gn:feature_class":"P",
    "gn:feature_code":"PPL",
    "gn:name":"Balongampel",
    "gn:population":0,
    "gn:timezone":"Asia/Jakarta",
    "iso:country":"ID",
    "name:ind_x_preferred":[
        "Balongampel"
    ],
    "wof:name":"Balongampel",
    "wof:placetype":"locality"
},
  "geometry": {"coordinates":[112.6297,-7.5219],"type":"Point"}
}