{
  "type": "Feature",
  "properties": {
    "gn:admin1_code":"26",
    "gn:asciiname":"Sitalmak",
    "gn:country_code":"ID",
    "gn:dem":1016,
    "gn:feature_class":"P",
    "gn:feature_code":"PPL",
    "gn:name":"Sitalmak",
    "gn:population":0,
    "gn:timezone":"Asia/Jakarta",
    "iso:country":"ID",
    "name:ind_x_preferred":[
        "Sitalmak"
    ],
    "wof:lang_x_official":[
        "ind"
    ],
    "wof:lang_x_spoken":[
        "ind",
        "eng"
    ],
    "wof:name":"Sitalmak",
    "wof:placetype":"locality"
},
  "geometry": {"coordinates":[98.39960000000001,2.7358],"type":"Point"}
}