{
  "type": "Feature",
  "properties": {
    "gn:admin1_code":"7.0",
    "gn:asciiname":"Paras",
    "gn:country_code":"ID",
    "gn:dem":18,
    "gn:feature_class":"P",
    "gn:feature_code":"PPL",
    "gn:name":"Paras",
    "gn:population":0,
    "gn:timezone":"Asia/Jakarta",
    "iso:country":"ID",
    "name:ceb_x_preferred":[
        "Paras"
    ],
    "name:fin_x_preferred":[
        "Paras"
    ],
    "name:fra_x_preferred":[
        "Paras"
    ],
    "name:ind_x_preferred":[
        "Paras"
    ],
    "name:mar_x_preferred":[
        "\u092a\u093e\u0930\u0938"
    ],
    "name:nld_x_preferred":[
        "Paras"
    ],
    "name:rus_x_preferred":[
        "\u041f\u0430\u0440\u0430\u0441"
    ],
    "name:srp_x_preferred":[
        "\u041f\u0430\u0440\u0430\u0441"
    ],
    "name:swe_x_preferred":[
        "Paras"
    ],
    "wof:name":"Paras",
    "wof:placetype":"locality"
},
  "geometry": {"coordinates":[111.05710000000001,-6.8393],"type":"Point"}
}