{
  "type": "Feature",
  "properties": {
    "gn:admin1_code":"7.0",
    "gn:asciiname":"Mertokusuman",
    "gn:country_code":"ID",
    "gn:dem":12,
    "gn:feature_class":"P",
    "gn:feature_code":"PPL",
    "gn:name":"Mertokusuman",
    "gn:population":0,
    "gn:timezone":"Asia/Jakarta",
    "iso:country":"ID",
    "name:ind_x_preferred":[
        "Mertokusuman"
    ],
    "wof:name":"Mertokusuman",
    "wof:placetype":"locality"
},
  "geometry": {"coordinates":[111.04340000000001,-6.7532],"type":"Point"}
}