{
  "type": "Feature",
  "properties": {
    "gn:admin1_code":"4.0",
    "gn:asciiname":"Kebonpala",
    "gn:country_code":"ID",
    "gn:dem":26,
    "gn:feature_class":"P",
    "gn:feature_code":"PPL",
    "gn:name":"Kebonpala",
    "gn:population":0,
    "gn:timezone":"Asia/Jakarta",
    "iso:country":"ID",
    "name:ind_x_preferred":[
        "Kebonpala"
    ],
    "wof:name":"Kebonpala",
    "wof:placetype":"locality"
},
  "geometry": {"coordinates":[106.8794,-6.2594],"type":"Point"}
}