{
  "type": "Feature",
  "properties": {
    "gn:admin1_code":"7.0",
    "gn:asciiname":"Cageran",
    "gn:country_code":"ID",
    "gn:dem":201,
    "gn:feature_class":"P",
    "gn:feature_code":"PPL",
    "gn:name":"Cageran",
    "gn:population":0,
    "gn:timezone":"Asia/Jakarta",
    "iso:country":"ID",
    "wof:name":"Cageran",
    "wof:placetype":"locality"
},
  "geometry": {"coordinates":[110.49167,-7.72194],"type":"Point"}
}