{
  "type": "Feature",
  "properties": {
    "gn:admin1_code":"0.0",
    "gn:asciiname":"Lemahabang",
    "gn:country_code":"ID",
    "gn:dem":54,
    "gn:feature_class":"P",
    "gn:feature_code":"PPL",
    "gn:name":"Lemahabang",
    "gn:population":0,
    "gn:timezone":"Asia/Jakarta",
    "iso:country":"ID",
    "wof:name":"Lemahabang",
    "wof:placetype":"locality"
},
  "geometry": {"coordinates":[106.21666999999999,-6.23333],"type":"Point"}
}