{
  "type": "Feature",
  "properties": {
    "gn:admin1_code":"30",
    "gn:asciiname":"Puncak",
    "gn:country_code":"ID",
    "gn:dem":1070,
    "gn:feature_class":"P",
    "gn:feature_code":"PPL",
    "gn:name":"Puncak",
    "gn:population":0,
    "gn:timezone":"Asia/Jakarta",
    "iso:country":"ID",
    "name:ara_x_preferred":[
        "\u0628\u0648\u0646\u0634\u0627\u0643"
    ],
    "name:ind_x_preferred":[
        "Puncak"
    ],
    "name:nld_x_preferred":[
        "Puncak"
    ],
    "wof:name":"Puncak",
    "wof:placetype":"locality"
},
  "geometry": {"coordinates":[107.78082999999999,-6.87389],"type":"Point"}
}