{
  "type": "Feature",
  "properties": {
    "gn:admin1_code":"7",
    "gn:asciiname":"Tampaan",
    "gn:country_code":"ID",
    "gn:dem":699,
    "gn:feature_class":"P",
    "gn:feature_code":"PPL",
    "gn:name":"Tampaan",
    "gn:population":0,
    "gn:timezone":"Asia/Jakarta",
    "iso:country":"ID",
    "name:ind_x_preferred":[
        "Tampaan"
    ],
    "wof:name":"Tampaan",
    "wof:placetype":"locality"
},
  "geometry": {"coordinates":[111.10944000000001,-7.75417],"type":"Point"}
}