{
  "type": "Feature",
  "properties": {
    "gn:admin1_code":"30",
    "gn:asciiname":"Bojongjambu",
    "gn:country_code":"ID",
    "gn:dem":1079,
    "gn:feature_class":"P",
    "gn:feature_code":"PPL",
    "gn:name":"Bojongjambu",
    "gn:population":0,
    "gn:timezone":"Asia/Jakarta",
    "iso:country":"ID",
    "name:ind_x_preferred":[
        "Bojongjambu"
    ],
    "name:und_x_variant":[
        "Bodjongdjambu"
    ],
    "wof:name":"Bojongjambu",
    "wof:placetype":"locality"
},
  "geometry": {"coordinates":[107.4696,-7.0689],"type":"Point"}
}