{
  "type": "Feature",
  "properties": {
    "gn:admin1_code":"32.0",
    "gn:asciiname":"Talanggelundi",
    "gn:country_code":"ID",
    "gn:dem":50,
    "gn:feature_class":"P",
    "gn:feature_code":"PPL",
    "gn:name":"Talanggelundi",
    "gn:population":0,
    "gn:timezone":"Asia/Jakarta",
    "iso:country":"ID",
    "name:ind_x_preferred":[
        "Talanggelundi"
    ],
    "wof:name":"Talanggelundi",
    "wof:placetype":"locality"
},
  "geometry": {"coordinates":[104.14239999999999,-3.578],"type":"Point"}
}