{
  "type": "Feature",
  "properties": {
    "gn:gn_country":"ID",
    "gn:gn_fcode":"PPL",
    "gn:gn_pop":73010,
    "gn:population":73010,
    "iso:country":"ID",
    "name:ace_x_preferred":[
        "Jatibarang"
    ],
    "name:ceb_x_preferred":[
        "Desa Jatibarang"
    ],
    "name:deu_x_preferred":[
        "Jatibarang"
    ],
    "name:eng_x_preferred":[
        "Jatibarang"
    ],
    "name:fra_x_preferred":[
        "Jatibarang"
    ],
    "name:gor_x_preferred":[
        "Jatibarang"
    ],
    "name:ind_x_preferred":[
        "Jatibarang"
    ],
    "name:jav_x_preferred":[
        "Jatibarang"
    ],
    "name:msa_x_preferred":[
        "Jatibarang"
    ],
    "name:nld_x_preferred":[
        "Jatibarang"
    ],
    "name:por_x_preferred":[
        "Jatibarang"
    ],
    "name:spa_x_preferred":[
        "Jatibarang"
    ],
    "name:spa_x_variant":[
        "Jati Bening"
    ],
    "name:sun_x_preferred":[
        "Jatibarang"
    ],
    "name:swe_x_preferred":[
        "Desa Jatibarang"
    ],
    "qs_pg:aaroncc":"ID",
    "qs_pg:gn_country":"ID",
    "qs_pg:gn_fcode":"PPL",
    "qs_pg:gn_pop":73010,
    "qs_pg:name":"Djatibarang",
    "qs_pg:name_adm0":"Indonesia",
    "qs_pg:name_adm1":"Jawa Barat",
    "qs_pg:photos_9k":1,
    "qs_pg:photos_9r":4,
    "qs_pg:photos_all":186,
    "qs_pg:photos_sr":0,
    "qs_pg:pop_sr":8,
    "qs_pg:qs_pg_placetype":"locality",
    "qs_pg:qs_pg_placetype_gp":"Town",
    "qs_pg:woe_adm0":23424846,
    "woe:adm0_id":23424846,
    "woe:name_adm0":"Indonesia",
    "woe:name_adm1":"Jawa Barat",
    "woe:placetype":"Town",
    "wof:lang_x_official":[
        "ind"
    ],
    "wof:lang_x_spoken":[
        "ind",
        "eng"
    ],
    "wof:name":"Djatibarang",
    "wof:placetype":"locality",
    "wof:population":73010
},
  "geometry": {"coordinates":[108.31528,-6.47472],"type":"Point"}
}