{
  "type": "Feature",
  "properties": {
    "gn:admin1_code":"18.0",
    "gn:asciiname":"Pemakat",
    "gn:country_code":"ID",
    "gn:dem":29,
    "gn:feature_class":"P",
    "gn:feature_code":"PPL",
    "gn:name":"Pemakat",
    "gn:population":0,
    "gn:timezone":"Asia/Makassar",
    "iso:country":"ID",
    "name:ind_x_preferred":[
        "Pemakat"
    ],
    "wof:name":"Pemakat",
    "wof:placetype":"locality"
},
  "geometry": {"coordinates":[119.95350000000001,-9.9525],"type":"Point"}
}