{
  "type": "Feature",
  "properties": {
    "gn:admin1_code":"38",
    "gn:asciiname":"Kaballokang",
    "gn:country_code":"ID",
    "gn:dem":98,
    "gn:feature_class":"P",
    "gn:feature_code":"PPL",
    "gn:name":"Kaballokang",
    "gn:population":0,
    "gn:timezone":"Asia/Makassar",
    "iso:country":"ID",
    "name:ind_x_preferred":[
        "Kaballokang"
    ],
    "wof:name":"Kaballokang",
    "wof:placetype":"locality"
},
  "geometry": {"coordinates":[119.6139,-5.2646],"type":"Point"}
}