{
  "type": "Feature",
  "properties": {
    "gn:admin1_code":"37",
    "gn:asciiname":"Kepayang",
    "gn:country_code":"ID",
    "gn:dem":44,
    "gn:feature_class":"P",
    "gn:feature_code":"PPL",
    "gn:name":"Kepayang",
    "gn:population":0,
    "gn:timezone":"Asia/Jakarta",
    "iso:country":"ID",
    "name:ind_x_preferred":[
        "Kepayang"
    ],
    "name:nld_x_preferred":[
        "Kepayang"
    ],
    "wof:name":"Kepayang",
    "wof:placetype":"locality"
},
  "geometry": {"coordinates":[100.42928000000001,1.04237],"type":"Point"}
}