{
  "type": "Feature",
  "properties": {
    "gn:admin1_code":"11",
    "gn:asciiname":"Kenunai",
    "gn:country_code":"ID",
    "gn:dem":74,
    "gn:feature_class":"P",
    "gn:feature_code":"PPL",
    "gn:name":"Kenunai",
    "gn:population":0,
    "gn:timezone":"Asia/Pontianak",
    "iso:country":"ID",
    "name:ind_x_preferred":[
        "Kenunai"
    ],
    "wof:name":"Kenunai",
    "wof:placetype":"locality"
},
  "geometry": {"coordinates":[110.76908,-0.51216],"type":"Point"}
}