{
  "type": "Feature",
  "properties": {
    "gn:admin1_code":"0.0",
    "gn:asciiname":"Lolong",
    "gn:country_code":"ID",
    "gn:dem":315,
    "gn:feature_class":"P",
    "gn:feature_code":"PPL",
    "gn:name":"Lolong",
    "gn:population":0,
    "gn:timezone":"Asia/Jakarta",
    "iso:country":"ID",
    "wof:name":"Lolong",
    "wof:placetype":"locality"
},
  "geometry": {"coordinates":[109.63333,-7.06667],"type":"Point"}
}