{
  "type": "Feature",
  "properties": {
    "gn:admin1_code":"0.0",
    "gn:asciiname":"Lolong",
    "gn:country_code":"ID",
    "gn:dem":315,
    "gn:feature_class":"P",
    "gn:feature_code":"PPL",
    "gn:name":"Lolong",
    "gn:population":0,
    "gn:timezone":"Asia/Jakarta",
    "iso:country":"ID",
    "name:deu_x_preferred":[
        "Lolong"
    ],
    "name:fra_x_preferred":[
        "Lolong"
    ],
    "name:heb_x_preferred":[
        "\u05dc\u05d5\u05dc\u05d5\u05e0\u05d2"
    ],
    "name:por_x_preferred":[
        "Lolong"
    ],
    "name:rus_x_preferred":[
        "\u041b\u043e\u043b\u043e\u043d\u0433"
    ],
    "name:spa_x_preferred":[
        "Lolong"
    ],
    "name:swe_x_preferred":[
        "Lolong"
    ],
    "name:tgl_x_preferred":[
        "Lolong"
    ],
    "name:tur_x_preferred":[
        "Lolong"
    ],
    "wof:lang_x_official":[
        "ind"
    ],
    "wof:lang_x_spoken":[
        "ind",
        "eng"
    ],
    "wof:name":"Lolong",
    "wof:placetype":"locality"
},
  "geometry": {"coordinates":[109.63333,-7.06667],"type":"Point"}
}