{
  "type": "Feature",
  "properties": {
    "gn:admin1_code":"26",
    "gn:asciiname":"Pongkalan Satu",
    "gn:country_code":"ID",
    "gn:dem":947,
    "gn:feature_class":"P",
    "gn:feature_code":"PPL",
    "gn:name":"Pongkalan Satu",
    "gn:population":0,
    "gn:timezone":"Asia/Jakarta",
    "iso:country":"ID",
    "name:ind_x_preferred":[
        "Pongkalan Satu"
    ],
    "name:und_x_variant":[
        "Pongkalan 1"
    ],
    "wof:name":"Pongkalan Satu",
    "wof:placetype":"locality"
},
  "geometry": {"coordinates":[99.1322,2.5145],"type":"Point"}
}