{
  "type": "Feature",
  "properties": {
    "gn:admin1_code":"18.0",
    "gn:asciiname":"Pateng",
    "gn:country_code":"ID",
    "gn:dem":527,
    "gn:feature_class":"P",
    "gn:feature_code":"PPL",
    "gn:name":"Pateng",
    "gn:population":0,
    "gn:timezone":"Asia/Makassar",
    "iso:country":"ID",
    "name:ind_x_preferred":[
        "Pateng"
    ],
    "wof:name":"Pateng",
    "wof:placetype":"locality"
},
  "geometry": {"coordinates":[120.27509999999999,-8.3941],"type":"Point"}
}