{
  "type": "Feature",
  "properties": {
    "gn:admin1_code":"7",
    "gn:asciiname":"Wareg",
    "gn:country_code":"ID",
    "gn:dem":96,
    "gn:feature_class":"P",
    "gn:feature_code":"PPL",
    "gn:name":"Wareg",
    "gn:population":0,
    "gn:timezone":"Asia/Jakarta",
    "iso:country":"ID",
    "name:ind_x_preferred":[
        "Wareg"
    ],
    "wof:name":"Wareg",
    "wof:placetype":"locality"
},
  "geometry": {"coordinates":[111.05444,-7.43139],"type":"Point"}
}