{
  "type": "Feature",
  "properties": {
    "gn:admin1_code":"41.0",
    "gn:asciiname":"Tusan",
    "gn:country_code":"ID",
    "gn:dem":1174,
    "gn:feature_class":"P",
    "gn:feature_code":"PPL",
    "gn:name":"Tusan",
    "gn:population":0,
    "gn:timezone":"Asia/Makassar",
    "iso:country":"ID",
    "name:ind_x_preferred":[
        "Tusan"
    ],
    "wof:name":"Tusan",
    "wof:placetype":"locality"
},
  "geometry": {"coordinates":[119.38039999999999,-2.9341],"type":"Point"}
}