{
  "type": "Feature",
  "properties": {
    "gn:admin1_code":"38.0",
    "gn:asciiname":"Dangu",
    "gn:country_code":"ID",
    "gn:dem":1231,
    "gn:feature_class":"P",
    "gn:feature_code":"PPL",
    "gn:name":"Dangu",
    "gn:population":0,
    "gn:timezone":"Asia/Makassar",
    "iso:country":"ID",
    "name:ceb_x_preferred":[
        "Dangu"
    ],
    "name:ind_x_preferred":[
        "Dangu"
    ],
    "name:srp_x_preferred":[
        "\u0414\u0430\u043d\u0433\u0443"
    ],
    "name:swe_x_preferred":[
        "Dangu"
    ],
    "wof:lang_x_official":[
        "ind"
    ],
    "wof:lang_x_spoken":[
        "ind",
        "eng"
    ],
    "wof:name":"Dangu",
    "wof:placetype":"locality"
},
  "geometry": {"coordinates":[119.96802,-2.58168],"type":"Point"}
}