{
  "type": "Feature",
  "properties": {
    "gn:admin1_code":"8",
    "gn:asciiname":"Kayulawang",
    "gn:country_code":"ID",
    "gn:dem":249,
    "gn:feature_class":"P",
    "gn:feature_code":"PPL",
    "gn:name":"Kayulawang",
    "gn:population":0,
    "gn:timezone":"Asia/Jakarta",
    "iso:country":"ID",
    "name:ind_x_preferred":[
        "Kayulawang"
    ],
    "wof:name":"Kayulawang",
    "wof:placetype":"locality"
},
  "geometry": {"coordinates":[111.13889,-8.06778],"type":"Point"}
}