{
  "type": "Feature",
  "properties": {
    "gn:admin1_code":"26.0",
    "gn:asciiname":"Gamba",
    "gn:country_code":"ID",
    "gn:dem":993,
    "gn:feature_class":"P",
    "gn:feature_code":"PPL",
    "gn:name":"Gamba",
    "gn:population":0,
    "gn:timezone":"Asia/Jakarta",
    "iso:country":"ID",
    "name:ara_x_preferred":[
        "\u062c\u0627\u0645\u0628\u0627"
    ],
    "name:ben_x_preferred":[
        "\u0997\u09be\u09ae\u09cd\u09ac\u09be"
    ],
    "name:cat_x_preferred":[
        "Gamba"
    ],
    "name:ceb_x_preferred":[
        "Gamba"
    ],
    "name:ces_x_preferred":[
        "Gamba"
    ],
    "name:deu_x_preferred":[
        "Gamba"
    ],
    "name:ell_x_preferred":[
        "\u0393\u03ba\u03ac\u03bc\u03c0\u03b1"
    ],
    "name:fas_x_preferred":[
        "\u06af\u0627\u0645\u0628\u0627"
    ],
    "name:fra_x_preferred":[
        "Gamba"
    ],
    "name:glg_x_preferred":[
        "Gamba"
    ],
    "name:heb_x_preferred":[
        "\u05d2\u05de\u05d1\u05d4"
    ],
    "name:hin_x_preferred":[
        "\u0917\u093e\u092e\u094d\u092c\u093e"
    ],
    "name:hun_x_preferred":[
        "Gamba"
    ],
    "name:ind_x_preferred":[
        "Gamba"
    ],
    "name:ita_x_preferred":[
        "Gamba"
    ],
    "name:kor_x_preferred":[
        "\uac10\ubc14"
    ],
    "name:nld_x_preferred":[
        "Gamba"
    ],
    "name:pol_x_preferred":[
        "Gamba"
    ],
    "name:por_x_preferred":[
        "Gamba"
    ],
    "name:rus_x_preferred":[
        "\u0413\u0430\u043c\u0431\u0430"
    ],
    "name:slk_x_preferred":[
        "Gamba"
    ],
    "name:spa_x_preferred":[
        "Gamba"
    ],
    "name:srp_x_preferred":[
        "Gamba"
    ],
    "name:swa_x_preferred":[
        "Gamba"
    ],
    "name:swe_x_preferred":[
        "Gamba"
    ],
    "name:tur_x_preferred":[
        "Gamba"
    ],
    "name:ukr_x_preferred":[
        "\u0413\u0430\u043c\u0431\u0430"
    ],
    "name:urd_x_preferred":[
        "\u06af\u06cc\u0645\u0628\u0627"
    ],
    "name:vie_x_preferred":[
        "Gamba"
    ],
    "wof:lang_x_official":[
        "ind"
    ],
    "wof:lang_x_spoken":[
        "ind",
        "eng"
    ],
    "wof:name":"Gamba",
    "wof:placetype":"locality"
},
  "geometry": {"coordinates":[98.7054,2.6185],"type":"Point"}
}