{
  "type": "Feature",
  "properties": {
    "gn:admin1_code":"26.0",
    "gn:asciiname":"Gamba",
    "gn:country_code":"ID",
    "gn:dem":993,
    "gn:feature_class":"P",
    "gn:feature_code":"PPL",
    "gn:name":"Gamba",
    "gn:population":0,
    "gn:timezone":"Asia/Jakarta",
    "iso:country":"ID",
    "name:cat_x_preferred":[
        "Gamba"
    ],
    "name:ceb_x_preferred":[
        "Gamba"
    ],
    "name:ces_x_preferred":[
        "Gamba"
    ],
    "name:deu_x_preferred":[
        "Gamba"
    ],
    "name:fra_x_preferred":[
        "Gamba"
    ],
    "name:glg_x_preferred":[
        "Gamba"
    ],
    "name:hun_x_preferred":[
        "Gamba"
    ],
    "name:ind_x_preferred":[
        "Gamba"
    ],
    "name:ita_x_preferred":[
        "Gamba"
    ],
    "name:nld_x_preferred":[
        "Gamba"
    ],
    "name:pol_x_preferred":[
        "Gamba"
    ],
    "name:por_x_preferred":[
        "Gamba"
    ],
    "name:rus_x_preferred":[
        "\u0413\u0430\u043c\u0431\u0430"
    ],
    "name:slk_x_preferred":[
        "Gamba"
    ],
    "name:spa_x_preferred":[
        "Gamba"
    ],
    "name:srp_x_preferred":[
        "Gamba"
    ],
    "name:swa_x_preferred":[
        "Gamba"
    ],
    "name:swe_x_preferred":[
        "Gamba"
    ],
    "wof:name":"Gamba",
    "wof:placetype":"locality"
},
  "geometry": {"coordinates":[98.7054,2.6185],"type":"Point"}
}