{
  "type": "Feature",
  "properties": {
    "gn:admin1_code":"18.0",
    "gn:asciiname":"Tetaf",
    "gn:country_code":"ID",
    "gn:dem":858,
    "gn:feature_class":"P",
    "gn:feature_code":"PPLA4",
    "gn:name":"Tetaf",
    "gn:population":0,
    "gn:timezone":"Asia/Makassar",
    "iso:country":"ID",
    "name:ind_x_preferred":[
        "Tetaf"
    ],
    "wof:lang_x_official":[
        "ind"
    ],
    "wof:lang_x_spoken":[
        "ind",
        "eng"
    ],
    "wof:name":"Tetaf",
    "wof:placetype":"locality"
},
  "geometry": {"coordinates":[124.43271,-9.83565],"type":"Point"}
}