{
  "type": "Feature",
  "properties": {
    "gn:admin1_code":"30",
    "gn:asciiname":"Cikaret-kecil",
    "gn:cc2":"ID",
    "gn:country_code":"ID",
    "gn:dem":122,
    "gn:feature_class":"P",
    "gn:feature_code":"PPL",
    "gn:name":"Cikaret-kecil",
    "gn:population":0,
    "gn:timezone":"Asia/Jakarta",
    "iso:country":"ID",
    "name:und_x_variant":[
        "Tjikaret-ketjil",
        "Cikaret-kecil"
    ],
    "wof:lang_x_official":[
        "ind"
    ],
    "wof:lang_x_spoken":[
        "ind",
        "eng"
    ],
    "wof:name":"Cikaret-kecil",
    "wof:placetype":"locality"
},
  "geometry": {"coordinates":[106.84721999999999,-6.46944],"type":"Point"}
}