{
  "type": "Feature",
  "properties": {
    "gn:admin1_code":"12",
    "gn:asciiname":"Gedambaan",
    "gn:country_code":"ID",
    "gn:dem":23,
    "gn:feature_class":"P",
    "gn:feature_code":"PPL",
    "gn:name":"Gedambaan",
    "gn:population":0,
    "gn:timezone":"Asia/Makassar",
    "iso:country":"ID",
    "name:ind_x_preferred":[
        "Gedambaan"
    ],
    "wof:name":"Gedambaan",
    "wof:placetype":"locality"
},
  "geometry": {"coordinates":[116.268,-3.2787],"type":"Point"}
}