{
  "type": "Feature",
  "properties": {
    "gn:country":"ID",
    "gn:fcode":"PPL",
    "gn:pop":0,
    "iso:country":"ID",
    "name:ind_x_preferred":[
        "Ciwandan"
    ],
    "name:unk_x_variant":[
        "Tjiwandan"
    ],
    "qs:name":"Ciwandan",
    "qs:name_adm0":"Indonesia",
    "qs:name_adm1":"Banten",
    "qs:photos_9k":1,
    "qs:photos_9r":1,
    "qs:photos_all":4,
    "qs:photos_sr":0,
    "qs:placetype":"Town",
    "qs:pop_sr":"0",
    "wof:name":"Ciwandan",
    "wof:placetype":"locality",
    "wof:population":0
},
  "geometry": {"coordinates":[105.95,-6.0271],"type":"Point"}
}