{
  "type": "Feature",
  "properties": {
    "gn:admin1_code":"26",
    "gn:asciiname":"Lobunarambir",
    "gn:country_code":"ID",
    "gn:dem":23,
    "gn:feature_class":"P",
    "gn:feature_code":"PPL",
    "gn:name":"Lobunarambir",
    "gn:population":0,
    "gn:timezone":"Asia/Jakarta",
    "iso:country":"ID",
    "name:ind_x_preferred":[
        "Lobunarambir"
    ],
    "wof:name":"Lobunarambir",
    "wof:placetype":"locality"
},
  "geometry": {"coordinates":[98.6382,1.8988],"type":"Point"}
}