{
  "type": "Feature",
  "properties": {
    "gn:admin1_code":"7.0",
    "gn:asciiname":"Derman",
    "gn:country_code":"ID",
    "gn:dem":192,
    "gn:feature_class":"P",
    "gn:feature_code":"PPL",
    "gn:name":"Derman",
    "gn:population":0,
    "gn:timezone":"Asia/Jakarta",
    "iso:country":"ID",
    "name:deu_x_preferred":[
        "Derman"
    ],
    "name:ind_x_preferred":[
        "Derman"
    ],
    "name:rus_x_preferred":[
        "\u0414\u0435\u0440\u043c\u0430\u043d"
    ],
    "name:tur_x_preferred":[
        "Derman"
    ],
    "wof:name":"Derman",
    "wof:placetype":"locality"
},
  "geometry": {"coordinates":[109.59999999999999,-7.40861],"type":"Point"}
}