{
  "type": "Feature",
  "properties": {
    "gn:admin1_code":"7",
    "gn:asciiname":"Krajan Kidul",
    "gn:country_code":"ID",
    "gn:dem":41,
    "gn:feature_class":"P",
    "gn:feature_code":"PPL",
    "gn:name":"Krajan Kidul",
    "gn:population":0,
    "gn:timezone":"Asia/Jakarta",
    "iso:country":"ID",
    "name:ind_x_preferred":[
        "Krajan Kidul"
    ],
    "wof:name":"Krajan Kidul",
    "wof:placetype":"locality"
},
  "geometry": {"coordinates":[110.59829999999999,-7.1209],"type":"Point"}
}