{
  "type": "Feature",
  "properties": {
    "gn:admin1_code":"30",
    "gn:asciiname":"Blokmarsijan",
    "gn:country_code":"ID",
    "gn:dem":5,
    "gn:feature_class":"P",
    "gn:feature_code":"PPL",
    "gn:name":"Blokmarsijan",
    "gn:population":0,
    "gn:timezone":"Asia/Jakarta",
    "iso:country":"ID",
    "name:ind_x_preferred":[
        "Blokmarsijan"
    ],
    "wof:name":"Blokmarsijan",
    "wof:placetype":"locality"
},
  "geometry": {"coordinates":[108.32193999999998,-6.37222],"type":"Point"}
}