{
  "type": "Feature",
  "properties": {
    "gn:admin1_code":"38.0",
    "gn:asciiname":"Salu",
    "gn:country_code":"ID",
    "gn:dem":893,
    "gn:feature_class":"P",
    "gn:feature_code":"PPL",
    "gn:name":"Salu",
    "gn:population":0,
    "gn:timezone":"Asia/Makassar",
    "iso:country":"ID",
    "name:ceb_x_preferred":[
        "Salu"
    ],
    "name:deu_x_preferred":[
        "Salu"
    ],
    "name:est_x_preferred":[
        "Salu"
    ],
    "name:hye_x_preferred":[
        "\u054d\u0561\u056c\u0578\u0582"
    ],
    "name:ind_x_preferred":[
        "Salu"
    ],
    "name:pol_x_preferred":[
        "Salu"
    ],
    "name:swe_x_preferred":[
        "Salu"
    ],
    "name:ukr_x_preferred":[
        "\u0421\u0430\u043b\u0443"
    ],
    "name:vol_x_preferred":[
        "Salu"
    ],
    "wof:name":"Salu",
    "wof:placetype":"locality"
},
  "geometry": {"coordinates":[119.73480000000001,-3.3701],"type":"Point"}
}