{
  "type": "Feature",
  "properties": {
    "gn:admin1_code":"15.0",
    "gn:asciiname":"Talangaman",
    "gn:country_code":"ID",
    "gn:dem":193,
    "gn:feature_class":"P",
    "gn:feature_code":"PPL",
    "gn:name":"Talangaman",
    "gn:population":0,
    "gn:timezone":"Asia/Jakarta",
    "iso:country":"ID",
    "name:ind_x_preferred":[
        "Talangaman"
    ],
    "wof:name":"Talangaman",
    "wof:placetype":"locality"
},
  "geometry": {"coordinates":[104.68478,-5.488],"type":"Point"}
}