{
  "type": "Feature",
  "properties": {
    "gn:admin1_code":"8",
    "gn:asciiname":"Pageran",
    "gn:country_code":"ID",
    "gn:dem":568,
    "gn:feature_class":"P",
    "gn:feature_code":"PPL",
    "gn:name":"Pageran",
    "gn:population":0,
    "gn:timezone":"Asia/Jakarta",
    "iso:country":"ID",
    "name:ind_x_preferred":[
        "Pageran"
    ],
    "wof:name":"Pageran",
    "wof:placetype":"locality"
},
  "geometry": {"coordinates":[111.18861,-8.03444],"type":"Point"}
}