{
  "type": "Feature",
  "properties": {
    "gn:admin1_code":"8",
    "gn:asciiname":"Selungguh",
    "gn:country_code":"ID",
    "gn:dem":184,
    "gn:feature_class":"P",
    "gn:feature_code":"PPL",
    "gn:name":"Selungguh",
    "gn:population":0,
    "gn:timezone":"Asia/Jakarta",
    "iso:country":"ID",
    "name:ind_x_preferred":[
        "Selungguh"
    ],
    "wof:name":"Selungguh",
    "wof:placetype":"locality"
},
  "geometry": {"coordinates":[111.38160000000001,-7.7534],"type":"Point"}
}