{
  "type": "Feature",
  "properties": {
    "gn:admin1_code":"17.0",
    "gn:asciiname":"Papak",
    "gn:country_code":"ID",
    "gn:dem":12,
    "gn:feature_class":"P",
    "gn:feature_code":"PPL",
    "gn:name":"Papak",
    "gn:population":0,
    "gn:timezone":"Asia/Makassar",
    "iso:country":"ID",
    "name:bel_x_preferred":[
        "\u041f\u0430\u043f\u0430\u043a"
    ],
    "name:ces_x_preferred":[
        "P\u00e1pak"
    ],
    "name:fra_x_preferred":[
        "Papak"
    ],
    "name:ind_x_preferred":[
        "Papak"
    ],
    "name:rus_x_preferred":[
        "\u041f\u0430\u043f\u0430\u043a"
    ],
    "name:slk_x_preferred":[
        "P\u00e1pak"
    ],
    "name:tgk_x_preferred":[
        "\u0411\u043e\u0431\u0430\u043a"
    ],
    "name:ukr_x_preferred":[
        "\u041f\u0430\u043f\u0430\u043a"
    ],
    "wof:name":"Papak",
    "wof:placetype":"locality"
},
  "geometry": {"coordinates":[116.2002,-8.3077],"type":"Point"}
}