{
  "type": "Feature",
  "properties": {
    "gn:admin1_code":"0.0",
    "gn:asciiname":"Longobangkuang",
    "gn:cc2":"ID",
    "gn:country_code":"ID",
    "gn:dem":13,
    "gn:feature_class":"P",
    "gn:feature_code":"PPL",
    "gn:name":"Longobangkuang",
    "gn:population":0,
    "gn:timezone":"Asia/Jakarta",
    "iso:country":"ID",
    "name:und_x_variant":[
        "Longobangkoeng",
        "Longobangkuang"
    ],
    "wof:name":"Longobangkuang",
    "wof:placetype":"locality"
},
  "geometry": {"coordinates":[100.34999999999999,1.85],"type":"Point"}
}