{
  "type": "Feature",
  "properties": {
    "gn:admin1_code":"2",
    "gn:asciiname":"Banjar Pengending",
    "gn:country_code":"ID",
    "gn:dem":61,
    "gn:feature_class":"P",
    "gn:feature_code":"PPL",
    "gn:name":"Banjar Pengending",
    "gn:population":0,
    "gn:timezone":"Asia/Makassar",
    "iso:country":"ID",
    "name:ind_x_preferred":[
        "Banjar Pengending"
    ],
    "wof:name":"Banjar Pengending",
    "wof:placetype":"locality"
},
  "geometry": {"coordinates":[115.1587,-8.6238],"type":"Point"}
}