{
  "type": "Feature",
  "properties": {
    "gn:admin1_code":"30.0",
    "gn:asciiname":"Cidadap",
    "gn:country_code":"ID",
    "gn:dem":436,
    "gn:feature_class":"P",
    "gn:feature_code":"PPL",
    "gn:name":"Cidadap",
    "gn:population":0,
    "gn:timezone":"Asia/Jakarta",
    "iso:country":"ID",
    "name:ind_x_preferred":[
        "Cidadap"
    ],
    "name:und_x_variant":[
        "Tjidadap"
    ],
    "wof:name":"Cidadap",
    "wof:placetype":"locality"
},
  "geometry": {"coordinates":[108.18258,-7.2613],"type":"Point"}
}