{
  "type": "Feature",
  "properties": {
    "gn:admin1_code":"08",
    "gn:asciiname":"Sudimoro",
    "gn:country_code":"ID",
    "gn:dem":426,
    "gn:feature_class":"P",
    "gn:feature_code":"PPLA4",
    "gn:name":"Sudimoro",
    "gn:population":0,
    "gn:timezone":"Asia/Jakarta",
    "iso:country":"ID",
    "name:ind_x_preferred":[
        "Sudimoro"
    ],
    "name:und_x_variant":[
        "Sudimoro 1",
        "Sudimoro Satu"
    ],
    "wof:name":"Sudimoro",
    "wof:placetype":"locality"
},
  "geometry": {"coordinates":[112.67310000000001,-8.1237],"type":"Point"}
}