{
  "type": "Feature",
  "properties": {
    "gn:admin1_code":"18",
    "gn:asciiname":"Railuli",
    "gn:country_code":"ID",
    "gn:dem":16,
    "gn:feature_class":"P",
    "gn:feature_code":"PPL",
    "gn:name":"Railuli",
    "gn:population":0,
    "gn:timezone":"Asia/Makassar",
    "iso:country":"ID",
    "wof:name":"Railuli",
    "wof:placetype":"locality"
},
  "geometry": {"coordinates":[124.87888999999998,-8.98417],"type":"Point"}
}