{
  "type": "Feature",
  "properties": {
    "gn:admin1_code":"30.0",
    "gn:asciiname":"Cibodas",
    "gn:country_code":"ID",
    "gn:dem":103,
    "gn:feature_class":"P",
    "gn:feature_code":"PPL",
    "gn:name":"Cibodas",
    "gn:population":0,
    "gn:timezone":"Asia/Jakarta",
    "iso:country":"ID",
    "name:ind_x_preferred":[
        "Cibodas"
    ],
    "name:jav_x_preferred":[
        "Cibodas"
    ],
    "name:msa_x_preferred":[
        "Cibodas"
    ],
    "name:sun_x_preferred":[
        "Cibodas"
    ],
    "name:und_x_variant":[
        "Tjibodas Tiga"
    ],
    "wof:name":"Cibodas",
    "wof:placetype":"locality"
},
  "geometry": {"coordinates":[108.3087,-7.763],"type":"Point"}
}