{
  "type": "Feature",
  "properties": {
    "gn:admin1_code":"30",
    "gn:asciiname":"Citeulang",
    "gn:country_code":"ID",
    "gn:dem":450,
    "gn:feature_class":"P",
    "gn:feature_code":"PPL",
    "gn:name":"Citeulang",
    "gn:population":0,
    "gn:timezone":"Asia/Jakarta",
    "iso:country":"ID",
    "name:ind_x_preferred":[
        "Citeulang"
    ],
    "wof:name":"Citeulang",
    "wof:placetype":"locality"
},
  "geometry": {"coordinates":[108.51139999999999,-6.8935],"type":"Point"}
}