{
  "type": "Feature",
  "properties": {
    "gn:admin1_code":"1",
    "gn:asciiname":"Alue Calong",
    "gn:country_code":"ID",
    "gn:dem":187,
    "gn:feature_class":"P",
    "gn:feature_code":"PPL",
    "gn:name":"Alue Calong",
    "gn:population":0,
    "gn:timezone":"Asia/Jakarta",
    "iso:country":"ID",
    "name:ind_x_preferred":[
        "Alue Calong"
    ],
    "wof:name":"Alue Calong",
    "wof:placetype":"locality"
},
  "geometry": {"coordinates":[95.8747,5.155],"type":"Point"}
}