{
  "type": "Feature",
  "properties": {
    "gn:admin1_code":"7.0",
    "gn:asciiname":"Kedawung",
    "gn:country_code":"ID",
    "gn:dem":572,
    "gn:feature_class":"P",
    "gn:feature_code":"PPL",
    "gn:name":"Kedawung",
    "gn:population":0,
    "gn:timezone":"Asia/Jakarta",
    "iso:country":"ID",
    "wof:name":"Kedawung",
    "wof:placetype":"locality"
},
  "geometry": {"coordinates":[110.35138999999999,-7.59194],"type":"Point"}
}