{
  "type": "Feature",
  "properties": {
    "gn:admin1_code":"08",
    "gn:asciiname":"Sobiah",
    "gn:country_code":"ID",
    "gn:dem":22,
    "gn:feature_class":"P",
    "gn:feature_code":"PPL",
    "gn:name":"Sobiah",
    "gn:population":0,
    "gn:timezone":"Asia/Jakarta",
    "iso:country":"ID",
    "name:ind_x_preferred":[
        "Sobiah"
    ],
    "name:und_x_variant":[
        "Sobih"
    ],
    "wof:name":"Sobiah",
    "wof:placetype":"locality"
},
  "geometry": {"coordinates":[112.80249999999999,-7.0397],"type":"Point"}
}