{
  "type": "Feature",
  "properties": {
    "gn:admin1_code":"1",
    "gn:asciiname":"Cot Laba",
    "gn:country_code":"ID",
    "gn:dem":7,
    "gn:feature_class":"P",
    "gn:feature_code":"PPL",
    "gn:name":"Cot Laba",
    "gn:population":0,
    "gn:timezone":"Asia/Jakarta",
    "iso:country":"ID",
    "name:ind_x_preferred":[
        "Cot Laba"
    ],
    "wof:name":"Cot Laba",
    "wof:placetype":"locality"
},
  "geometry": {"coordinates":[97.33110000000001,5.1586],"type":"Point"}
}