{
  "type": "Feature",
  "properties": {
    "gn:admin1_code":"30",
    "gn:asciiname":"Cipaok",
    "gn:country_code":"ID",
    "gn:dem":517,
    "gn:feature_class":"P",
    "gn:feature_code":"PPL",
    "gn:name":"Cipaok",
    "gn:population":0,
    "gn:timezone":"Asia/Jakarta",
    "iso:country":"ID",
    "name:ind_x_preferred":[
        "Cipaok"
    ],
    "wof:name":"Cipaok",
    "wof:placetype":"locality"
},
  "geometry": {"coordinates":[106.79944,-6.68889],"type":"Point"}
}