{
  "type": "Feature",
  "properties": {
    "gn:admin1_code":"18.0",
    "gn:asciiname":"Laikauwa",
    "gn:country_code":"ID",
    "gn:dem":488,
    "gn:feature_class":"P",
    "gn:feature_code":"PPL",
    "gn:name":"Laikauwa",
    "gn:population":0,
    "gn:timezone":"Asia/Makassar",
    "iso:country":"ID",
    "name:ind_x_preferred":[
        "Laikauwa"
    ],
    "wof:name":"Laikauwa",
    "wof:placetype":"locality"
},
  "geometry": {"coordinates":[119.5907,-9.564],"type":"Point"}
}