{
  "type": "Feature",
  "properties": {
    "gn:admin1_code":"7.0",
    "gn:asciiname":"Kalipacet",
    "gn:country_code":"ID",
    "gn:dem":570,
    "gn:feature_class":"P",
    "gn:feature_code":"PPL",
    "gn:name":"Kalipacet",
    "gn:population":0,
    "gn:timezone":"Asia/Jakarta",
    "iso:country":"ID",
    "wof:name":"Kalipacet",
    "wof:placetype":"locality"
},
  "geometry": {"coordinates":[110.44861000000002,-7.34083],"type":"Point"}
}