{
  "type": "Feature",
  "properties": {
    "gn:admin1_code":"1",
    "gn:asciiname":"Kampung Aceh",
    "gn:country_code":"ID",
    "gn:dem":6,
    "gn:feature_class":"P",
    "gn:feature_code":"PPL",
    "gn:name":"Kampung Aceh",
    "gn:population":0,
    "gn:timezone":"Asia/Jakarta",
    "iso:country":"ID",
    "name:ind_x_preferred":[
        "Kampung Aceh"
    ],
    "wof:name":"Kampung Aceh",
    "wof:placetype":"locality"
},
  "geometry": {"coordinates":[97.7687,4.9485],"type":"Point"}
}