{
  "type": "Feature",
  "properties": {
    "gn:admin1_code":"30",
    "gn:asciiname":"Tinggarjaya Girang",
    "gn:country_code":"ID",
    "gn:dem":795,
    "gn:feature_class":"P",
    "gn:feature_code":"PPL",
    "gn:name":"Tinggarjaya Girang",
    "gn:population":0,
    "gn:timezone":"Asia/Jakarta",
    "iso:country":"ID",
    "wof:name":"Tinggarjaya Girang",
    "wof:placetype":"locality"
},
  "geometry": {"coordinates":[107.55667,-7.08917],"type":"Point"}
}