{
  "type": "Feature",
  "properties": {
    "gn:admin1_code":"33.0",
    "gn:asciiname":"Cijengkol Girang",
    "gn:country_code":"ID",
    "gn:dem":125,
    "gn:feature_class":"P",
    "gn:feature_code":"PPL",
    "gn:name":"Cijengkol Girang",
    "gn:population":0,
    "gn:timezone":"Asia/Jakarta",
    "iso:country":"ID",
    "name:ind_x_preferred":[
        "Cijengkol Girang"
    ],
    "wof:name":"Cijengkol Girang",
    "wof:placetype":"locality"
},
  "geometry": {"coordinates":[106.1614,-6.8503],"type":"Point"}
}