{
  "type": "Feature",
  "properties": {
    "gn:admin1_code":"21.0",
    "gn:asciiname":"Oud Mantok",
    "gn:cc2":"ID",
    "gn:country_code":"ID",
    "gn:dem":254,
    "gn:feature_class":"P",
    "gn:feature_code":"PPL",
    "gn:name":"Oud Mantok",
    "gn:population":0,
    "gn:timezone":"Asia/Makassar",
    "iso:country":"ID",
    "name:und_x_variant":[
        "Mantok",
        "Oud Mantok"
    ],
    "wof:lang_x_official":[
        "ind"
    ],
    "wof:lang_x_spoken":[
        "ind",
        "eng"
    ],
    "wof:name":"Oud Mantok",
    "wof:placetype":"locality"
},
  "geometry": {"coordinates":[123.23528,-0.94472],"type":"Point"}
}