{
  "type": "Feature",
  "properties": {
    "gn:admin1_code":"8.0",
    "gn:asciiname":"Tumpakwatu Lor",
    "gn:country_code":"ID",
    "gn:dem":151,
    "gn:feature_class":"P",
    "gn:feature_code":"PPL",
    "gn:name":"Tumpakwatu Lor",
    "gn:population":0,
    "gn:timezone":"Asia/Jakarta",
    "iso:country":"ID",
    "name:ind_x_preferred":[
        "Tumpakwatu Lor"
    ],
    "wof:name":"Tumpakwatu Lor",
    "wof:placetype":"locality"
},
  "geometry": {"coordinates":[110.92389,-8.1975],"type":"Point"}
}