{
  "type": "Feature",
  "properties": {
    "gn:admin1_code":"22",
    "gn:asciiname":"Baho",
    "gn:country_code":"ID",
    "gn:dem":17,
    "gn:feature_class":"P",
    "gn:feature_code":"PPL",
    "gn:name":"Baho",
    "gn:population":0,
    "gn:timezone":"Asia/Makassar",
    "iso:country":"ID",
    "name:arg_x_preferred":[
        "Bao"
    ],
    "name:bre_x_preferred":[
        "Bao"
    ],
    "name:bug_x_preferred":[
        "Baho"
    ],
    "name:cat_x_preferred":[
        "Bao"
    ],
    "name:ceb_x_preferred":[
        "Baho"
    ],
    "name:dan_x_preferred":[
        "Baho"
    ],
    "name:deu_x_preferred":[
        "Baho"
    ],
    "name:eus_x_preferred":[
        "Baho"
    ],
    "name:fra_x_preferred":[
        "Baho"
    ],
    "name:hun_x_preferred":[
        "Baho"
    ],
    "name:ind_x_preferred":[
        "Baho"
    ],
    "name:ita_x_preferred":[
        "Baho"
    ],
    "name:kaz_x_preferred":[
        "\u0411\u0430\u043e"
    ],
    "name:lat_x_preferred":[
        "Baho"
    ],
    "name:lmo_x_preferred":[
        "Baho"
    ],
    "name:msa_x_preferred":[
        "Baho"
    ],
    "name:nld_x_preferred":[
        "Baho"
    ],
    "name:oci_x_preferred":[
        "Ba\u00f3"
    ],
    "name:pol_x_preferred":[
        "Baho"
    ],
    "name:ron_x_preferred":[
        "Baho"
    ],
    "name:slk_x_preferred":[
        "Baho"
    ],
    "name:spa_x_preferred":[
        "Baho"
    ],
    "name:sqi_x_preferred":[
        "Baho"
    ],
    "name:srp_x_preferred":[
        "\u0411\u0430\u043e"
    ],
    "name:swe_x_preferred":[
        "Baho"
    ],
    "name:ukr_x_preferred":[
        "\u0411\u0430\u043e"
    ],
    "name:vie_x_preferred":[
        "Baho"
    ],
    "name:vol_x_preferred":[
        "Baho"
    ],
    "name:war_x_preferred":[
        "Baho"
    ],
    "name:zho_x_preferred":[
        "\u535a"
    ],
    "wof:lang_x_official":[
        "ind"
    ],
    "wof:lang_x_spoken":[
        "ind",
        "eng"
    ],
    "wof:name":"Baho",
    "wof:placetype":"locality"
},
  "geometry": {"coordinates":[122.79179999999999,-4.0627],"type":"Point"}
}