{
  "type": "Feature",
  "properties": {
    "gn:admin1_code":"30.0",
    "gn:asciiname":"Sukasari",
    "gn:country_code":"ID",
    "gn:dem":374,
    "gn:feature_class":"P",
    "gn:feature_code":"PPL",
    "gn:name":"Sukasari",
    "gn:population":0,
    "gn:timezone":"Asia/Jakarta",
    "iso:country":"ID",
    "name:ind_x_preferred":[
        "Sukasari"
    ],
    "wof:name":"Sukasari",
    "wof:placetype":"locality"
},
  "geometry": {"coordinates":[108.21899999999999,-7.3945],"type":"Point"}
}