{
  "type": "Feature",
  "properties": {
    "gn:admin1_code":"8",
    "gn:asciiname":"Dorayot",
    "gn:country_code":"ID",
    "gn:dem":130,
    "gn:feature_class":"P",
    "gn:feature_code":"PPL",
    "gn:name":"Dorayot",
    "gn:population":0,
    "gn:timezone":"Asia/Jakarta",
    "iso:country":"ID",
    "name:ind_x_preferred":[
        "Dorayot"
    ],
    "wof:name":"Dorayot",
    "wof:placetype":"locality"
},
  "geometry": {"coordinates":[112.02670000000001,-7.4593],"type":"Point"}
}