{
  "type": "Feature",
  "properties": {
    "gn:admin1_code":"18.0",
    "gn:asciiname":"Pejek",
    "gn:country_code":"ID",
    "gn:dem":980,
    "gn:feature_class":"P",
    "gn:feature_code":"PPLA4",
    "gn:name":"Pejek",
    "gn:population":0,
    "gn:timezone":"Asia/Makassar",
    "iso:country":"ID",
    "name:ind_x_preferred":[
        "Pejek"
    ],
    "wof:lang_x_official":[
        "ind"
    ],
    "wof:lang_x_spoken":[
        "ind",
        "eng"
    ],
    "wof:name":"Pejek",
    "wof:placetype":"locality"
},
  "geometry": {"coordinates":[120.7225,-8.6461],"type":"Point"}
}