{
  "type": "Feature",
  "properties": {
    "gn:admin1_code":"30",
    "gn:asciiname":"Ragamukti Tengah",
    "gn:country_code":"ID",
    "gn:dem":1057,
    "gn:feature_class":"P",
    "gn:feature_code":"PPL",
    "gn:name":"Ragamukti Tengah",
    "gn:population":0,
    "gn:timezone":"Asia/Jakarta",
    "iso:country":"ID",
    "name:ind_x_preferred":[
        "Ragamukti Tengah"
    ],
    "wof:name":"Ragamukti Tengah",
    "wof:placetype":"locality"
},
  "geometry": {"coordinates":[107.8049,-7.2238],"type":"Point"}
}