{
  "type": "Feature",
  "properties": {
    "gn:admin1_code":"30",
    "gn:asciiname":"Rancabalong",
    "gn:country_code":"ID",
    "gn:dem":470,
    "gn:feature_class":"P",
    "gn:feature_code":"PPL",
    "gn:name":"Rancabalong",
    "gn:population":0,
    "gn:timezone":"Asia/Jakarta",
    "iso:country":"ID",
    "name:ind_x_preferred":[
        "Rancabalong"
    ],
    "wof:name":"Rancabalong",
    "wof:placetype":"locality"
},
  "geometry": {"coordinates":[108.21722,-6.99528],"type":"Point"}
}