{
  "type": "Feature",
  "properties": {
    "gn:admin1_code":"4",
    "gn:asciiname":"Bulakbaru",
    "gn:country_code":"ID",
    "gn:dem":8,
    "gn:feature_class":"P",
    "gn:feature_code":"PPL",
    "gn:name":"Bulakbaru",
    "gn:population":0,
    "gn:timezone":"Asia/Jakarta",
    "iso:country":"ID",
    "name:ind_x_preferred":[
        "Bulakbaru"
    ],
    "wof:name":"Bulakbaru",
    "wof:placetype":"locality"
},
  "geometry": {"coordinates":[106.9016,-6.1864],"type":"Point"}
}