{
  "type": "Feature",
  "properties": {
    "gn:admin1_code":"30.0",
    "gn:asciiname":"Bojonghaur",
    "gn:country_code":"ID",
    "gn:dem":835,
    "gn:feature_class":"P",
    "gn:feature_code":"PPL",
    "gn:name":"Bojonghaur",
    "gn:population":0,
    "gn:timezone":"Asia/Jakarta",
    "iso:country":"ID",
    "name:ind_x_preferred":[
        "Bojonghaur"
    ],
    "wof:name":"Bojonghaur",
    "wof:placetype":"locality"
},
  "geometry": {"coordinates":[107.51390000000001,-7.2961],"type":"Point"}
}