{
  "type": "Feature",
  "properties": {
    "gn:admin1_code":"7",
    "gn:asciiname":"Gembiro",
    "gn:country_code":"ID",
    "gn:dem":27,
    "gn:feature_class":"P",
    "gn:feature_code":"PPL",
    "gn:name":"Gembiro",
    "gn:population":0,
    "gn:timezone":"Asia/Jakarta",
    "iso:country":"ID",
    "name:ind_x_preferred":[
        "Gembiro"
    ],
    "wof:name":"Gembiro",
    "wof:placetype":"locality"
},
  "geometry": {"coordinates":[109.53489999999999,-6.9993],"type":"Point"}
}