{
  "type": "Feature",
  "properties": {
    "gn:admin1_code":"8",
    "gn:asciiname":"Prajin",
    "gn:country_code":"ID",
    "gn:dem":18,
    "gn:feature_class":"P",
    "gn:feature_code":"PPL",
    "gn:name":"Prajin",
    "gn:population":0,
    "gn:timezone":"Asia/Jakarta",
    "iso:country":"ID",
    "name:ind_x_preferred":[
        "Prajin"
    ],
    "wof:name":"Prajin",
    "wof:placetype":"locality"
},
  "geometry": {"coordinates":[113.24460000000001,-7.1246],"type":"Point"}
}