{
  "type": "Feature",
  "properties": {
    "gn:admin1_code":"18.0",
    "gn:asciiname":"Dahuqramuq",
    "gn:country_code":"ID",
    "gn:dem":112,
    "gn:feature_class":"P",
    "gn:feature_code":"PPL",
    "gn:name":"Dahuqramuq",
    "gn:population":0,
    "gn:timezone":"Asia/Makassar",
    "iso:country":"ID",
    "name:ind_x_preferred":[
        "Dahuqramuq"
    ],
    "wof:name":"Dahuqramuq",
    "wof:placetype":"locality"
},
  "geometry": {"coordinates":[123.7513,-8.1978],"type":"Point"}
}