{
  "type": "Feature",
  "properties": {
    "gn:admin1_code":"30.0",
    "gn:asciiname":"Sindangjaya",
    "gn:country_code":"ID",
    "gn:dem":17,
    "gn:feature_class":"P",
    "gn:feature_code":"PPLA4",
    "gn:name":"Sindangjaya",
    "gn:population":0,
    "gn:timezone":"Asia/Jakarta",
    "iso:country":"ID",
    "name:ind_x_preferred":[
        "Sindangjaya"
    ],
    "name:und_x_variant":[
        "Sindangdjaja",
        "Sindangjaya"
    ],
    "wof:name":"Sindangjaya",
    "wof:placetype":"locality"
},
  "geometry": {"coordinates":[108.66160000000001,-7.4815],"type":"Point"}
}