{
  "type": "Feature",
  "properties": {
    "gn:admin1_code":"15.0",
    "gn:asciiname":"Umbulan Kemiring",
    "gn:country_code":"ID",
    "gn:dem":43,
    "gn:feature_class":"P",
    "gn:feature_code":"PPL",
    "gn:name":"Umbulan Kemiring",
    "gn:population":0,
    "gn:timezone":"Asia/Jakarta",
    "iso:country":"ID",
    "name:ind_x_preferred":[
        "Umbulan Kemiring"
    ],
    "wof:name":"Umbulan Kemiring",
    "wof:placetype":"locality"
},
  "geometry": {"coordinates":[105.15535,-5.03114],"type":"Point"}
}