{
  "type": "Feature",
  "properties": {
    "gn:admin1_code":"33.0",
    "gn:asciiname":"Pangalengan",
    "gn:country_code":"ID",
    "gn:dem":14,
    "gn:feature_class":"P",
    "gn:feature_code":"PPL",
    "gn:name":"Pangalengan",
    "gn:population":0,
    "gn:timezone":"Asia/Jakarta",
    "iso:country":"ID",
    "name:ind_x_preferred":[
        "Pangalengan"
    ],
    "wof:name":"Pangalengan",
    "wof:placetype":"locality"
},
  "geometry": {"coordinates":[105.8914,-6.4744],"type":"Point"}
}