{
  "type": "Feature",
  "properties": {
    "gn:admin1_code":"38",
    "gn:asciiname":"Buku",
    "gn:country_code":"ID",
    "gn:dem":840,
    "gn:feature_class":"P",
    "gn:feature_code":"PPL",
    "gn:name":"Buku",
    "gn:population":0,
    "gn:timezone":"Asia/Makassar",
    "iso:country":"ID",
    "name:ceb_x_preferred":[
        "Buku"
    ],
    "name:ind_x_preferred":[
        "Buku"
    ],
    "name:swe_x_preferred":[
        "Buku"
    ],
    "wof:lang_x_official":[
        "ind"
    ],
    "wof:lang_x_spoken":[
        "ind",
        "eng"
    ],
    "wof:name":"Buku",
    "wof:placetype":"locality"
},
  "geometry": {"coordinates":[119.9066,-3.095],"type":"Point"}
}