{
  "type": "Feature",
  "properties": {
    "gn:admin1_code":"18.0",
    "gn:asciiname":"Kajelowati",
    "gn:country_code":"ID",
    "gn:dem":130,
    "gn:feature_class":"P",
    "gn:feature_code":"PPL",
    "gn:name":"Kajelowati",
    "gn:population":0,
    "gn:timezone":"Asia/Makassar",
    "iso:country":"ID",
    "name:ind_x_preferred":[
        "Kajelowati"
    ],
    "wof:name":"Kajelowati",
    "wof:placetype":"locality"
},
  "geometry": {"coordinates":[119.26000000000001,-9.7273],"type":"Point"}
}