{
  "type": "Feature",
  "properties": {
    "gn:admin1_code":"26",
    "gn:asciiname":"Banyumas",
    "gn:country_code":"ID",
    "gn:dem":17,
    "gn:feature_class":"P",
    "gn:feature_code":"PPL",
    "gn:name":"Banyumas",
    "gn:population":0,
    "gn:timezone":"Asia/Jakarta",
    "iso:country":"ID",
    "name:ind_x_preferred":[
        "Banyumas"
    ],
    "wof:name":"Banyumas",
    "wof:placetype":"locality"
},
  "geometry": {"coordinates":[98.4294,3.7133],"type":"Point"}
}