{
  "type": "Feature",
  "properties": {
    "gn:admin1_code":"30",
    "gn:asciiname":"Poncol",
    "gn:country_code":"ID",
    "gn:dem":5,
    "gn:feature_class":"P",
    "gn:feature_code":"PPL",
    "gn:name":"Poncol",
    "gn:population":0,
    "gn:timezone":"Asia/Jakarta",
    "iso:country":"ID",
    "name:ind_x_preferred":[
        "Poncol"
    ],
    "wof:name":"Poncol",
    "wof:placetype":"locality"
},
  "geometry": {"coordinates":[107.26000000000001,-6.09306],"type":"Point"}
}