{
  "type": "Feature",
  "properties": {
    "gn:admin1_code":"30.0",
    "gn:asciiname":"Babakan Kananga",
    "gn:country_code":"ID",
    "gn:dem":914,
    "gn:feature_class":"P",
    "gn:feature_code":"PPL",
    "gn:name":"Babakan Kananga",
    "gn:population":0,
    "gn:timezone":"Asia/Jakarta",
    "iso:country":"ID",
    "name:ind_x_preferred":[
        "Babakan Kananga"
    ],
    "wof:name":"Babakan Kananga",
    "wof:placetype":"locality"
},
  "geometry": {"coordinates":[107.94070000000001,-7.3115],"type":"Point"}
}