{
  "type": "Feature",
  "properties": {
    "gn:admin1_code":"30",
    "gn:asciiname":"Punduan",
    "gn:country_code":"ID",
    "gn:dem":47,
    "gn:feature_class":"P",
    "gn:feature_code":"PPL",
    "gn:name":"Punduan",
    "gn:population":0,
    "gn:timezone":"Asia/Jakarta",
    "iso:country":"ID",
    "name:ind_x_preferred":[
        "Punduan"
    ],
    "wof:name":"Punduan",
    "wof:placetype":"locality"
},
  "geometry": {"coordinates":[107.97444,-6.53806],"type":"Point"}
}