{
  "type": "Feature",
  "properties": {
    "gn:admin1_code":"08",
    "gn:asciiname":"Tenggina",
    "gn:country_code":"ID",
    "gn:dem":168,
    "gn:feature_class":"P",
    "gn:feature_code":"PPL",
    "gn:name":"Tenggina",
    "gn:population":0,
    "gn:timezone":"Asia/Jakarta",
    "iso:country":"ID",
    "name:ind_x_preferred":[
        "Tenggina"
    ],
    "name:und_x_variant":[
        "Tenggina 5",
        "Tenggina Lima"
    ],
    "wof:name":"Tenggina",
    "wof:placetype":"locality"
},
  "geometry": {"coordinates":[112.97450000000001,-7.1137],"type":"Point"}
}