{
  "type": "Feature",
  "properties": {
    "gn:admin1_code":"15.0",
    "gn:asciiname":"Talangsebaris",
    "gn:country_code":"ID",
    "gn:dem":533,
    "gn:feature_class":"P",
    "gn:feature_code":"PPL",
    "gn:name":"Talangsebaris",
    "gn:population":0,
    "gn:timezone":"Asia/Jakarta",
    "iso:country":"ID",
    "name:ind_x_preferred":[
        "Talangsebaris"
    ],
    "wof:name":"Talangsebaris",
    "wof:placetype":"locality"
},
  "geometry": {"coordinates":[104.60897,-5.20007],"type":"Point"}
}