{
  "type": "Feature",
  "properties": {
    "gn:admin1_code":"2",
    "gn:asciiname":"Banjar Tamansari",
    "gn:country_code":"ID",
    "gn:dem":68,
    "gn:feature_class":"P",
    "gn:feature_code":"PPL",
    "gn:name":"Banjar Tamansari",
    "gn:population":0,
    "gn:timezone":"Asia/Makassar",
    "iso:country":"ID",
    "name:ind_x_preferred":[
        "Banjar Tamansari"
    ],
    "wof:name":"Banjar Tamansari",
    "wof:placetype":"locality"
},
  "geometry": {"coordinates":[115.1216,-8.5933],"type":"Point"}
}