{
  "type": "Feature",
  "properties": {
    "gn:admin1_code":"4.0",
    "gn:asciiname":"Tanahtinggi",
    "gn:country_code":"ID",
    "gn:dem":7,
    "gn:feature_class":"P",
    "gn:feature_code":"PPL",
    "gn:name":"Tanahtinggi",
    "gn:population":0,
    "gn:timezone":"Asia/Jakarta",
    "iso:country":"ID",
    "name:ind_x_preferred":[
        "Tanahtinggi"
    ],
    "name:und_x_variant":[
        "Tanahtinggi-pontjol"
    ],
    "wof:name":"Tanahtinggi",
    "wof:placetype":"locality"
},
  "geometry": {"coordinates":[106.8494,-6.1816],"type":"Point"}
}