{
  "type": "Feature",
  "properties": {
    "gn:admin1_code":"30",
    "gn:asciiname":"Leugoknangka",
    "gn:country_code":"ID",
    "gn:dem":744,
    "gn:feature_class":"P",
    "gn:feature_code":"PPL",
    "gn:name":"Leugoknangka",
    "gn:population":0,
    "gn:timezone":"Asia/Jakarta",
    "iso:country":"ID",
    "wof:name":"Leugoknangka",
    "wof:placetype":"locality"
},
  "geometry": {"coordinates":[107.52028,-7.04139],"type":"Point"}
}