{
  "type": "Feature",
  "properties": {
    "gn:admin1_code":"18.0",
    "gn:asciiname":"Blidit",
    "gn:country_code":"ID",
    "gn:dem":155,
    "gn:feature_class":"P",
    "gn:feature_code":"PPL",
    "gn:name":"Blidit",
    "gn:population":0,
    "gn:timezone":"Asia/Makassar",
    "iso:country":"ID",
    "name:ind_x_preferred":[
        "Blidit"
    ],
    "wof:name":"Blidit",
    "wof:placetype":"locality"
},
  "geometry": {"coordinates":[122.4251,-8.6337],"type":"Point"}
}