{
  "type": "Feature",
  "properties": {
    "gn:admin1_code":"38",
    "gn:asciiname":"Balaikembang",
    "gn:country_code":"ID",
    "gn:dem":70,
    "gn:feature_class":"P",
    "gn:feature_code":"PPL",
    "gn:name":"Balaikembang",
    "gn:population":0,
    "gn:timezone":"Asia/Makassar",
    "iso:country":"ID",
    "name:ind_x_preferred":[
        "Balaikembang"
    ],
    "name:und_x_variant":[
        "Badaikembang"
    ],
    "wof:lang_x_official":[
        "ind"
    ],
    "wof:lang_x_spoken":[
        "ind",
        "eng"
    ],
    "wof:name":"Balaikembang",
    "wof:placetype":"locality"
},
  "geometry": {"coordinates":[120.7911,-2.4966],"type":"Point"}
}