{
  "type": "Feature",
  "properties": {
    "gn:admin1_code":"15.0",
    "gn:asciiname":"Umbulan Kandau",
    "gn:country_code":"ID",
    "gn:dem":63,
    "gn:feature_class":"P",
    "gn:feature_code":"PPL",
    "gn:name":"Umbulan Kandau",
    "gn:population":0,
    "gn:timezone":"Asia/Jakarta",
    "iso:country":"ID",
    "name:ind_x_preferred":[
        "Umbulan Kandau"
    ],
    "wof:name":"Umbulan Kandau",
    "wof:placetype":"locality"
},
  "geometry": {"coordinates":[104.73430999999999,-4.67408],"type":"Point"}
}