{
  "type": "Feature",
  "properties": {
    "gn:admin1_code":"0.0",
    "gn:asciiname":"Korombuak",
    "gn:cc2":"ID",
    "gn:country_code":"ID",
    "gn:dem":1,
    "gn:feature_class":"P",
    "gn:feature_code":"PPL",
    "gn:name":"Korombuak",
    "gn:population":0,
    "gn:timezone":"Asia/Jayapura",
    "iso:country":"ID",
    "name:und_x_variant":[
        "Karoemboeak",
        "Koroemboeak",
        "Koromboeak",
        "Korombuak"
    ],
    "wof:lang_x_official":[
        "ind"
    ],
    "wof:lang_x_spoken":[
        "ind",
        "eng"
    ],
    "wof:name":"Korombuak",
    "wof:placetype":"locality"
},
  "geometry": {"coordinates":[139.36667,-7.08333],"type":"Point"}
}