{
  "type": "Feature",
  "properties": {
    "gn:admin1_code":"30",
    "gn:asciiname":"Empang",
    "gn:country_code":"ID",
    "gn:dem":707,
    "gn:feature_class":"P",
    "gn:feature_code":"PPL",
    "gn:name":"Empang",
    "gn:population":0,
    "gn:timezone":"Asia/Jakarta",
    "iso:country":"ID",
    "wof:name":"Empang",
    "wof:placetype":"locality"
},
  "geometry": {"coordinates":[107.59222,-7.06389],"type":"Point"}
}