{
  "type": "Feature",
  "properties": {
    "gn:admin1_code":"15.0",
    "gn:asciiname":"Kepayang",
    "gn:country_code":"ID",
    "gn:dem":70,
    "gn:feature_class":"P",
    "gn:feature_code":"PPL",
    "gn:name":"Kepayang",
    "gn:population":0,
    "gn:timezone":"Asia/Jakarta",
    "iso:country":"ID",
    "name:ind_x_preferred":[
        "Kepayang"
    ],
    "name:nld_x_preferred":[
        "Kepayang"
    ],
    "wof:name":"Kepayang",
    "wof:placetype":"locality"
},
  "geometry": {"coordinates":[104.89081000000002,-4.93476],"type":"Point"}
}