{
  "type": "Feature",
  "properties": {
    "gn:admin1_code":"38.0",
    "gn:asciiname":"Salaga",
    "gn:country_code":"ID",
    "gn:dem":1482,
    "gn:feature_class":"P",
    "gn:feature_code":"PPL",
    "gn:name":"Salaga",
    "gn:population":0,
    "gn:timezone":"Asia/Makassar",
    "iso:country":"ID",
    "name:cat_x_preferred":[
        "Salaga"
    ],
    "name:ceb_x_preferred":[
        "Salaga"
    ],
    "name:deu_x_preferred":[
        "Salaga"
    ],
    "name:fra_x_preferred":[
        "Salaga"
    ],
    "name:ind_x_preferred":[
        "Salaga"
    ],
    "name:ita_x_preferred":[
        "Salaga"
    ],
    "name:ron_x_preferred":[
        "Salaga"
    ],
    "name:swe_x_preferred":[
        "Salaga"
    ],
    "name:urd_x_preferred":[
        "\u0633\u0627\u0644\u0627\u06af\u0627"
    ],
    "wof:lang_x_official":[
        "ind"
    ],
    "wof:lang_x_spoken":[
        "ind",
        "eng"
    ],
    "wof:name":"Salaga",
    "wof:placetype":"locality"
},
  "geometry": {"coordinates":[119.85469999999999,-2.8958],"type":"Point"}
}