{
  "type": "Feature",
  "properties": {
    "gn:admin1_code":"18.0",
    "gn:asciiname":"Praimini",
    "gn:country_code":"ID",
    "gn:dem":108,
    "gn:feature_class":"P",
    "gn:feature_code":"PPL",
    "gn:name":"Praimini",
    "gn:population":0,
    "gn:timezone":"Asia/Makassar",
    "iso:country":"ID",
    "name:ind_x_preferred":[
        "Praimini"
    ],
    "wof:name":"Praimini",
    "wof:placetype":"locality"
},
  "geometry": {"coordinates":[120.62286,-9.99863],"type":"Point"}
}