{
  "type": "Feature",
  "properties": {
    "gn:admin1_code":"22.0",
    "gn:asciiname":"Moromemoroa",
    "gn:country_code":"ID",
    "gn:dem":27,
    "gn:feature_class":"P",
    "gn:feature_code":"PPL",
    "gn:name":"Moromemoroa",
    "gn:population":0,
    "gn:timezone":"Asia/Makassar",
    "iso:country":"ID",
    "name:ind_x_preferred":[
        "Moromemoroa"
    ],
    "wof:name":"Moromemoroa",
    "wof:placetype":"locality"
},
  "geometry": {"coordinates":[122.10850000000001,-4.0105],"type":"Point"}
}