{
  "type": "Feature",
  "properties": {
    "gn:admin1_code":"7.0",
    "gn:asciiname":"Benowo",
    "gn:country_code":"ID",
    "gn:dem":801,
    "gn:feature_class":"P",
    "gn:feature_code":"PPL",
    "gn:name":"Benowo",
    "gn:population":0,
    "gn:timezone":"Asia/Jakarta",
    "iso:country":"ID",
    "name:ceb_x_preferred":[
        "Benowo"
    ],
    "name:nld_x_preferred":[
        "Benowo"
    ],
    "name:pol_x_preferred":[
        "Benowo"
    ],
    "name:ukr_x_preferred":[
        "\u0411\u0435\u043d\u043e\u0432\u043e"
    ],
    "wof:name":"Benowo",
    "wof:placetype":"locality"
},
  "geometry": {"coordinates":[110.12306,-7.63472],"type":"Point"}
}