{
  "type": "Feature",
  "properties": {
    "gn:admin1_code":"1",
    "gn:asciiname":"Alue Krut",
    "gn:country_code":"ID",
    "gn:dem":338,
    "gn:feature_class":"P",
    "gn:feature_code":"PPL",
    "gn:name":"Alue Krut",
    "gn:population":0,
    "gn:timezone":"Asia/Jakarta",
    "iso:country":"ID",
    "name:ind_x_preferred":[
        "Alue Krut"
    ],
    "wof:name":"Alue Krut",
    "wof:placetype":"locality"
},
  "geometry": {"coordinates":[96.066,4.8834],"type":"Point"}
}