{
  "type": "Feature",
  "properties": {
    "gn:admin1_code":"8.0",
    "gn:asciiname":"Tegalmanik Timur",
    "gn:country_code":"ID",
    "gn:dem":338,
    "gn:feature_class":"P",
    "gn:feature_code":"PPL",
    "gn:name":"Tegalmanik Timur",
    "gn:population":0,
    "gn:timezone":"Asia/Jakarta",
    "iso:country":"ID",
    "name:ind_x_preferred":[
        "Tegalmanik Timur"
    ],
    "wof:name":"Tegalmanik Timur",
    "wof:placetype":"locality"
},
  "geometry": {"coordinates":[113.8522,-7.9801],"type":"Point"}
}