{
  "type": "Feature",
  "properties": {
    "gn:admin1_code":"8.0",
    "gn:asciiname":"Tlotok",
    "gn:country_code":"ID",
    "gn:dem":133,
    "gn:feature_class":"P",
    "gn:feature_code":"PPL",
    "gn:name":"Tlotok",
    "gn:population":0,
    "gn:timezone":"Asia/Jakarta",
    "iso:country":"ID",
    "name:ind_x_preferred":[
        "Tlotok"
    ],
    "wof:name":"Tlotok",
    "wof:placetype":"locality"
},
  "geometry": {"coordinates":[111.79430000000001,-7.3341],"type":"Point"}
}