{
  "type": "Feature",
  "properties": {
    "gn:admin1_code":"11",
    "gn:asciiname":"Sei Keran",
    "gn:country_code":"ID",
    "gn:dem":1,
    "gn:feature_class":"P",
    "gn:feature_code":"PPL",
    "gn:name":"Sei Keran",
    "gn:population":0,
    "gn:timezone":"Asia/Pontianak",
    "iso:country":"ID",
    "name:ind_x_preferred":[
        "Sei Keran"
    ],
    "wof:name":"Sei Keran",
    "wof:placetype":"locality"
},
  "geometry": {"coordinates":[108.91313999999998,0.69815],"type":"Point"}
}