{
  "type": "Feature",
  "properties": {
    "gn:admin1_code":"8",
    "gn:asciiname":"Galeh",
    "gn:country_code":"ID",
    "gn:dem":386,
    "gn:feature_class":"P",
    "gn:feature_code":"PPL",
    "gn:name":"Galeh",
    "gn:population":0,
    "gn:timezone":"Asia/Jakarta",
    "iso:country":"ID",
    "name:fas_x_preferred":[
        "\u06af\u0644\u0647"
    ],
    "name:ind_x_preferred":[
        "Galeh"
    ],
    "wof:lang_x_official":[
        "ind"
    ],
    "wof:lang_x_spoken":[
        "ind",
        "eng"
    ],
    "wof:name":"Galeh",
    "wof:placetype":"locality"
},
  "geometry": {"coordinates":[111.94840000000001,-7.0466],"type":"Point"}
}