{
  "type": "Feature",
  "properties": {
    "gn:admin1_code":"08",
    "gn:asciiname":"Tamanharjo",
    "gn:cc2":"ID",
    "gn:country_code":"ID",
    "gn:dem":502,
    "gn:feature_class":"P",
    "gn:feature_code":"PPL",
    "gn:name":"Tamanharjo",
    "gn:population":0,
    "gn:timezone":"Asia/Jakarta",
    "iso:country":"ID",
    "name:und_x_variant":[
        "Tamanhardjo",
        "Tamanharjo"
    ],
    "wof:lang_x_official":[
        "ind"
    ],
    "wof:lang_x_spoken":[
        "ind",
        "eng"
    ],
    "wof:name":"Tamanharjo",
    "wof:placetype":"locality"
},
  "geometry": {"coordinates":[112.68056,-7.89417],"type":"Point"}
}