{
  "type": "Feature",
  "properties": {
    "gn:admin1_code":"30.0",
    "gn:asciiname":"Belendung",
    "gn:country_code":"ID",
    "gn:dem":5,
    "gn:feature_class":"P",
    "gn:feature_code":"PPL",
    "gn:name":"Belendung",
    "gn:population":0,
    "gn:timezone":"Asia/Jakarta",
    "iso:country":"ID",
    "name:ind_x_preferred":[
        "Belendung"
    ],
    "name:und_x_variant":[
        "Belendoeng"
    ],
    "wof:name":"Belendung",
    "wof:placetype":"locality"
},
  "geometry": {"coordinates":[107.05472,-6.13056],"type":"Point"}
}