{
  "type": "Feature",
  "properties": {
    "gn:admin1_code":"42.0",
    "gn:asciiname":"Kujau",
    "gn:country_code":"ID",
    "gn:dem":12,
    "gn:feature_class":"P",
    "gn:feature_code":"PPL",
    "gn:name":"Kujau",
    "gn:population":0,
    "gn:timezone":"Asia/Makassar",
    "iso:country":"ID",
    "name:deu_x_preferred":[
        "Kujau"
    ],
    "name:ind_x_preferred":[
        "Kajau"
    ],
    "name:und_x_variant":[
        "Kudjau",
        "Koedjau",
        "Kujau"
    ],
    "wof:lang_x_official":[
        "ind"
    ],
    "wof:lang_x_spoken":[
        "ind",
        "eng"
    ],
    "wof:name":"Kujau",
    "wof:placetype":"locality"
},
  "geometry": {"coordinates":[117.06195,3.32309],"type":"Point"}
}