{
  "type": "Feature",
  "properties": {
    "gn:admin1_code":"26",
    "gn:asciiname":"Cempedakbejokan",
    "gn:country_code":"ID",
    "gn:dem":52,
    "gn:feature_class":"P",
    "gn:feature_code":"PPL",
    "gn:name":"Cempedakbejokan",
    "gn:population":0,
    "gn:timezone":"Asia/Jakarta",
    "iso:country":"ID",
    "name:ind_x_preferred":[
        "Cempedakbejokan"
    ],
    "name:und_x_variant":[
        "Tjempedakbedjokan"
    ],
    "wof:lang_x_official":[
        "ind"
    ],
    "wof:lang_x_spoken":[
        "ind",
        "eng"
    ],
    "wof:name":"Cempedakbejokan",
    "wof:placetype":"locality"
},
  "geometry": {"coordinates":[99.0142,3.3517],"type":"Point"}
}