{
  "type": "Feature",
  "properties": {
    "gn:admin1_code":"7",
    "gn:asciiname":"Klawean",
    "gn:country_code":"ID",
    "gn:dem":11,
    "gn:feature_class":"P",
    "gn:feature_code":"PPL",
    "gn:name":"Klawean",
    "gn:population":0,
    "gn:timezone":"Asia/Jakarta",
    "iso:country":"ID",
    "name:ind_x_preferred":[
        "Klawean"
    ],
    "wof:name":"Klawean",
    "wof:placetype":"locality"
},
  "geometry": {"coordinates":[110.6502,-6.9032],"type":"Point"}
}