{
  "type": "Feature",
  "properties": {
    "gn:admin1_code":"7.0",
    "gn:asciiname":"Tlogo Tengah",
    "gn:country_code":"ID",
    "gn:dem":215,
    "gn:feature_class":"P",
    "gn:feature_code":"PPL",
    "gn:name":"Tlogo Tengah",
    "gn:population":0,
    "gn:timezone":"Asia/Jakarta",
    "iso:country":"ID",
    "name:ind_x_preferred":[
        "Tlogo Tengah"
    ],
    "wof:name":"Tlogo Tengah",
    "wof:placetype":"locality"
},
  "geometry": {"coordinates":[109.41528,-7.70333],"type":"Point"}
}