{
  "type": "Feature",
  "properties": {
    "gn:admin1_code":"26.0",
    "gn:asciiname":"Hutaimbaru",
    "gn:country_code":"ID",
    "gn:dem":98,
    "gn:feature_class":"P",
    "gn:feature_code":"PPL",
    "gn:name":"Hutaimbaru",
    "gn:population":0,
    "gn:timezone":"Asia/Jakarta",
    "iso:country":"ID",
    "name:ind_x_preferred":[
        "Hutaimbaru Satu"
    ],
    "name:und_x_variant":[
        "Hutarimbaru",
        "Hoetaimbaroe",
        "Hoetarimbaroe",
        "Hutaimbaru"
    ],
    "wof:name":"Hutaimbaru",
    "wof:placetype":"locality"
},
  "geometry": {"coordinates":[99.72328,1.57827],"type":"Point"}
}