{
  "type": "Feature",
  "properties": {
    "gn:admin1_code":"26.0",
    "gn:asciiname":"Pengkol",
    "gn:country_code":"ID",
    "gn:dem":549,
    "gn:feature_class":"P",
    "gn:feature_code":"PPL",
    "gn:name":"Pengkol",
    "gn:population":0,
    "gn:timezone":"Asia/Jakarta",
    "iso:country":"ID",
    "name:ind_x_preferred":[
        "Pengkol"
    ],
    "name:und_x_variant":[
        "Pengkot"
    ],
    "wof:name":"Pengkol",
    "wof:placetype":"locality"
},
  "geometry": {"coordinates":[98.11750000000001,3.0738],"type":"Point"}
}