{
  "type": "Feature",
  "properties": {
    "gn:admin1_code":"8.0",
    "gn:asciiname":"Curahlilih",
    "gn:country_code":"ID",
    "gn:dem":113,
    "gn:feature_class":"P",
    "gn:feature_code":"PPL",
    "gn:name":"Curahlilih",
    "gn:population":0,
    "gn:timezone":"Asia/Jakarta",
    "iso:country":"ID",
    "name:ind_x_preferred":[
        "Curahlilih"
    ],
    "wof:name":"Curahlilih",
    "wof:placetype":"locality"
},
  "geometry": {"coordinates":[113.38346,-7.8624],"type":"Point"}
}