{
  "type": "Feature",
  "properties": {
    "gn:admin1_code":"30.0",
    "gn:asciiname":"Cimasuk Wetan",
    "gn:country_code":"ID",
    "gn:dem":1168,
    "gn:feature_class":"P",
    "gn:feature_code":"PPL",
    "gn:name":"Cimasuk Wetan",
    "gn:population":0,
    "gn:timezone":"Asia/Jakarta",
    "iso:country":"ID",
    "name:ind_x_preferred":[
        "Cimasuk Wetan"
    ],
    "wof:lang_x_official":[
        "ind"
    ],
    "wof:lang_x_spoken":[
        "ind",
        "eng"
    ],
    "wof:name":"Cimasuk Wetan",
    "wof:placetype":"locality"
},
  "geometry": {"coordinates":[108.06829999999999,-7.1485],"type":"Point"}
}