{
  "type": "Feature",
  "properties": {
    "gn:admin1_code":"7",
    "gn:asciiname":"Gili",
    "gn:country_code":"ID",
    "gn:dem":15,
    "gn:feature_class":"P",
    "gn:feature_code":"PPL",
    "gn:name":"Gili",
    "gn:population":0,
    "gn:timezone":"Asia/Jakarta",
    "iso:country":"ID",
    "name:ceb_x_preferred":[
        "Gili"
    ],
    "name:deu_x_preferred":[
        "Gili"
    ],
    "name:fra_x_preferred":[
        "Gili"
    ],
    "name:ind_x_preferred":[
        "Gili"
    ],
    "name:nld_x_preferred":[
        "Gili"
    ],
    "name:swe_x_preferred":[
        "Gili"
    ],
    "wof:name":"Gili",
    "wof:placetype":"locality"
},
  "geometry": {"coordinates":[110.67400000000001,-6.9929],"type":"Point"}
}