{
  "type": "Feature",
  "properties": {
    "gn:admin1_code":"30.0",
    "gn:asciiname":"Sindangserang",
    "gn:country_code":"ID",
    "gn:dem":1058,
    "gn:feature_class":"P",
    "gn:feature_code":"PPL",
    "gn:name":"Sindangserang",
    "gn:population":0,
    "gn:timezone":"Asia/Jakarta",
    "iso:country":"ID",
    "name:ind_x_preferred":[
        "Sindangserang"
    ],
    "wof:name":"Sindangserang",
    "wof:placetype":"locality"
},
  "geometry": {"coordinates":[107.8169,-7.2788],"type":"Point"}
}