{
  "type": "Feature",
  "properties": {
    "gn:admin1_code":"8.0",
    "gn:asciiname":"Mbetro",
    "gn:country_code":"ID",
    "gn:dem":357,
    "gn:feature_class":"P",
    "gn:feature_code":"PPL",
    "gn:name":"Mbetro",
    "gn:population":0,
    "gn:timezone":"Asia/Jakarta",
    "iso:country":"ID",
    "name:ind_x_preferred":[
        "Mbetro"
    ],
    "wof:name":"Mbetro",
    "wof:placetype":"locality"
},
  "geometry": {"coordinates":[112.6527,-7.6266],"type":"Point"}
}