{
  "type": "Feature",
  "properties": {
    "gn:admin1_code":"30",
    "gn:asciiname":"Tajurhalang Pojok",
    "gn:country_code":"ID",
    "gn:dem":663,
    "gn:feature_class":"P",
    "gn:feature_code":"PPL",
    "gn:name":"Tajurhalang Pojok",
    "gn:population":0,
    "gn:timezone":"Asia/Jakarta",
    "iso:country":"ID",
    "name:ind_x_preferred":[
        "Tajurhalang Pojok"
    ],
    "wof:name":"Tajurhalang Pojok",
    "wof:placetype":"locality"
},
  "geometry": {"coordinates":[106.77611,-6.67694],"type":"Point"}
}