{
  "type": "Feature",
  "properties": {
    "gn:admin1_code":"7.0",
    "gn:asciiname":"Borobudur",
    "gn:country_code":"ID",
    "gn:dem":257,
    "gn:feature_class":"P",
    "gn:feature_code":"PPL",
    "gn:name":"Borobudur",
    "gn:population":150,
    "gn:timezone":"Asia/Jakarta",
    "iso:country":"ID",
    "name:und_x_variant":[
        "Baraboedoer",
        "Boroboedoer",
        "Balaboedoer",
        "Borobudur"
    ],
    "wof:name":"Borobudur",
    "wof:placetype":"locality",
    "wof:population":150
},
  "geometry": {"coordinates":[110.20444000000001,-7.60111],"type":"Point"}
}