{
  "type": "Feature",
  "properties": {
    "gn:admin1_code":"17.0",
    "gn:asciiname":"Pagesangan Selatan",
    "gn:country_code":"ID",
    "gn:dem":13,
    "gn:feature_class":"P",
    "gn:feature_code":"PPL",
    "gn:name":"Pagesangan Selatan",
    "gn:population":0,
    "gn:timezone":"Asia/Makassar",
    "iso:country":"ID",
    "name:ind_x_preferred":[
        "Pagesangan Selatan"
    ],
    "wof:name":"Pagesangan Selatan",
    "wof:placetype":"locality"
},
  "geometry": {"coordinates":[116.10339999999999,-8.601],"type":"Point"}
}