{
  "type": "Feature",
  "properties": {
    "gn:admin1_code":"30.0",
    "gn:asciiname":"Pelelangan",
    "gn:cc2":"ID",
    "gn:country_code":"ID",
    "gn:dem":3,
    "gn:feature_class":"P",
    "gn:feature_code":"PPL",
    "gn:name":"Pelelangan",
    "gn:population":0,
    "gn:timezone":"Asia/Jakarta",
    "iso:country":"ID",
    "name:und_x_variant":[
        "Palelangan",
        "Pelalangan",
        "Pelelangan"
    ],
    "wof:name":"Pelelangan",
    "wof:placetype":"locality"
},
  "geometry": {"coordinates":[106.51000000000001,-6.03889],"type":"Point"}
}