{
  "type": "Feature",
  "properties": {
    "gn:admin1_code":"0.0",
    "gn:asciiname":"Mauwara",
    "gn:cc2":"ID",
    "gn:country_code":"ID",
    "gn:dem":221,
    "gn:feature_class":"P",
    "gn:feature_code":"PPL",
    "gn:name":"Mauwara",
    "gn:population":0,
    "gn:timezone":"Asia/Jayapura",
    "iso:country":"ID",
    "name:und_x_variant":[
        "Madoewa",
        "Maoewara",
        "Miwara",
        "Mauwara"
    ],
    "wof:lang_x_official":[
        "ind"
    ],
    "wof:lang_x_spoken":[
        "ind",
        "eng"
    ],
    "wof:name":"Mauwara",
    "wof:placetype":"locality"
},
  "geometry": {"coordinates":[133.98333,-3.83333],"type":"Point"}
}