{
  "type": "Feature",
  "properties": {
    "gn:admin1_code":"7.0",
    "gn:asciiname":"Babrik",
    "gn:country_code":"ID",
    "gn:dem":1378,
    "gn:feature_class":"P",
    "gn:feature_code":"PPL",
    "gn:name":"Babrik",
    "gn:population":0,
    "gn:timezone":"Asia/Jakarta",
    "iso:country":"ID",
    "wof:name":"Babrik",
    "wof:placetype":"locality"
},
  "geometry": {"coordinates":[110.39278,-7.41222],"type":"Point"}
}