{
  "type": "Feature",
  "properties": {
    "gn:admin1_code":"32.0",
    "gn:asciiname":"Simpangsender",
    "gn:country_code":"ID",
    "gn:dem":728,
    "gn:feature_class":"P",
    "gn:feature_code":"PPL",
    "gn:name":"Simpangsender",
    "gn:population":0,
    "gn:timezone":"Asia/Jakarta",
    "iso:country":"ID",
    "name:ind_x_preferred":[
        "Simpangsender"
    ],
    "name:und_x_variant":[
        "Simpangsukarame"
    ],
    "wof:lang_x_official":[
        "ind"
    ],
    "wof:lang_x_spoken":[
        "ind",
        "eng"
    ],
    "wof:name":"Simpangsender",
    "wof:placetype":"locality"
},
  "geometry": {"coordinates":[104.01488999999999,-4.80655],"type":"Point"}
}