{
  "type": "Feature",
  "properties": {
    "gn:admin1_code":"7.0",
    "gn:asciiname":"Peundeuy",
    "gn:country_code":"ID",
    "gn:dem":183,
    "gn:feature_class":"P",
    "gn:feature_code":"PPL",
    "gn:name":"Peundeuy",
    "gn:population":0,
    "gn:timezone":"Asia/Jakarta",
    "iso:country":"ID",
    "name:ind_x_preferred":[
        "Peundeuy"
    ],
    "wof:name":"Peundeuy",
    "wof:placetype":"locality"
},
  "geometry": {"coordinates":[108.5787,-7.2891],"type":"Point"}
}