{
  "type": "Feature",
  "properties": {
    "gn:admin1_code":"30.0",
    "gn:asciiname":"Sukasirna",
    "gn:country_code":"ID",
    "gn:dem":330,
    "gn:feature_class":"P",
    "gn:feature_code":"PPLA4",
    "gn:name":"Sukasirna",
    "gn:population":0,
    "gn:timezone":"Asia/Jakarta",
    "iso:country":"ID",
    "name:ind_x_preferred":[
        "Sukasirna"
    ],
    "wof:name":"Sukasirna",
    "wof:placetype":"locality"
},
  "geometry": {"coordinates":[108.2778,-7.3655],"type":"Point"}
}