{
  "type": "Feature",
  "properties": {
    "gn:admin1_code":"1.0",
    "gn:asciiname":"Buyot",
    "gn:country_code":"ID",
    "gn:dem":80,
    "gn:feature_class":"P",
    "gn:feature_code":"PPL",
    "gn:name":"Buyot",
    "gn:population":0,
    "gn:timezone":"Asia/Jakarta",
    "iso:country":"ID",
    "name:ind_x_preferred":[
        "Buyot"
    ],
    "wof:name":"Buyot",
    "wof:placetype":"locality"
},
  "geometry": {"coordinates":[96.71111000000001,5.04127],"type":"Point"}
}