{
  "type": "Feature",
  "properties": {
    "gn:admin1_code":"7.0",
    "gn:asciiname":"Mungkalprau",
    "gn:country_code":"ID",
    "gn:dem":196,
    "gn:feature_class":"P",
    "gn:feature_code":"PPL",
    "gn:name":"Mungkalprau",
    "gn:population":0,
    "gn:timezone":"Asia/Jakarta",
    "iso:country":"ID",
    "name:ind_x_preferred":[
        "Mungkalprau"
    ],
    "wof:name":"Mungkalprau",
    "wof:placetype":"locality"
},
  "geometry": {"coordinates":[108.81189999999999,-7.2492],"type":"Point"}
}