{
  "type": "Feature",
  "properties": {
    "gn:admin1_code":"18.0",
    "gn:asciiname":"Boto",
    "gn:country_code":"ID",
    "gn:dem":539,
    "gn:feature_class":"P",
    "gn:feature_code":"PPLA4",
    "gn:name":"Boto",
    "gn:population":0,
    "gn:timezone":"Asia/Makassar",
    "iso:country":"ID",
    "name:ind_x_preferred":[
        "Boto"
    ],
    "wof:name":"Boto",
    "wof:placetype":"locality"
},
  "geometry": {"coordinates":[123.37609999999999,-8.5078],"type":"Point"}
}