{
  "type": "Feature",
  "properties": {
    "gn:admin1_code":"8.0",
    "gn:asciiname":"Kendung",
    "gn:country_code":"ID",
    "gn:dem":245,
    "gn:feature_class":"P",
    "gn:feature_code":"PPL",
    "gn:name":"Kendung",
    "gn:population":0,
    "gn:timezone":"Asia/Jakarta",
    "iso:country":"ID",
    "name:ind_x_preferred":[
        "Kendung"
    ],
    "wof:name":"Kendung",
    "wof:placetype":"locality"
},
  "geometry": {"coordinates":[113.5348,-7.0626],"type":"Point"}
}