{
  "type": "Feature",
  "properties": {
    "gn:admin1_code":"33",
    "gn:asciiname":"Tajurlebak",
    "gn:country_code":"ID",
    "gn:dem":46,
    "gn:feature_class":"P",
    "gn:feature_code":"PPL",
    "gn:name":"Tajurlebak",
    "gn:population":0,
    "gn:timezone":"Asia/Jakarta",
    "iso:country":"ID",
    "name:ind_x_preferred":[
        "Tajurlebak"
    ],
    "wof:name":"Tajurlebak",
    "wof:placetype":"locality"
},
  "geometry": {"coordinates":[106.212,-6.3508],"type":"Point"}
}