{
  "type": "Feature",
  "properties": {
    "gn:admin1_code":"32.0",
    "gn:asciiname":"Talangkuang",
    "gn:country_code":"ID",
    "gn:dem":63,
    "gn:feature_class":"P",
    "gn:feature_code":"PPL",
    "gn:name":"Talangkuang",
    "gn:population":0,
    "gn:timezone":"Asia/Jakarta",
    "iso:country":"ID",
    "name:ind_x_preferred":[
        "Talangkuang"
    ],
    "wof:name":"Talangkuang",
    "wof:placetype":"locality"
},
  "geometry": {"coordinates":[104.2552,-3.9154],"type":"Point"}
}