{
  "type": "Feature",
  "properties": {
    "gn:admin1_code":"26",
    "gn:asciiname":"Sigalagala",
    "gn:country_code":"ID",
    "gn:dem":369,
    "gn:feature_class":"P",
    "gn:feature_code":"PPL",
    "gn:name":"Sigalagala",
    "gn:population":0,
    "gn:timezone":"Asia/Jakarta",
    "iso:country":"ID",
    "name:ind_x_preferred":[
        "Sigalagala"
    ],
    "name:ind_x_variant":[
        "Sigala Gala"
    ],
    "wof:lang_x_official":[
        "ind"
    ],
    "wof:lang_x_spoken":[
        "ind",
        "eng"
    ],
    "wof:name":"Sigalagala",
    "wof:placetype":"locality"
},
  "geometry": {"coordinates":[99.60308000000001,1.83369],"type":"Point"}
}