{
  "type": "Feature",
  "properties": {
    "gn:admin1_code":"22.0",
    "gn:asciiname":"Usuku",
    "gn:country_code":"ID",
    "gn:dem":25,
    "gn:feature_class":"P",
    "gn:feature_code":"PPL",
    "gn:name":"Usuku",
    "gn:population":0,
    "gn:timezone":"Asia/Makassar",
    "iso:country":"ID",
    "name:ind_x_preferred":[
        "Usuku"
    ],
    "name:und_x_variant":[
        "Usku"
    ],
    "wof:name":"Usuku",
    "wof:placetype":"locality"
},
  "geometry": {"coordinates":[123.93940000000001,-5.7761],"type":"Point"}
}