{
  "type": "Feature",
  "properties": {
    "gn:admin1_code":"8",
    "gn:asciiname":"Patalan",
    "gn:country_code":"ID",
    "gn:dem":10,
    "gn:feature_class":"P",
    "gn:feature_code":"PPL",
    "gn:name":"Patalan",
    "gn:population":0,
    "gn:timezone":"Asia/Jakarta",
    "iso:country":"ID",
    "name:ind_x_preferred":[
        "Patalan"
    ],
    "wof:name":"Patalan",
    "wof:placetype":"locality"
},
  "geometry": {"coordinates":[112.2178,-7.0538],"type":"Point"}
}