{
  "type": "Feature",
  "properties": {
    "gn:country":"ID",
    "gn:fcode":"PPL",
    "gn:pop":0,
    "iso:country":"ID",
    "name:ind_x_preferred":[
        "Banding Agung"
    ],
    "qs:name":"Banding Agung",
    "qs:name_adm0":"Indonesia",
    "qs:name_adm1":"Sumatera Selatan",
    "qs:photos_9k":1,
    "qs:photos_9r":1,
    "qs:photos_all":3,
    "qs:photos_sr":0,
    "qs:placetype":"Town",
    "qs:pop_sr":"0",
    "wd:wordcount":679,
    "wof:name":"Banding Agung",
    "wof:placetype":"locality",
    "wof:population":0
},
  "geometry": {"coordinates":[104.4217,-4.08283],"type":"Point"}
}