{
  "type": "Feature",
  "properties": {
    "gn:admin1_code":"30",
    "gn:asciiname":"Cipinang",
    "gn:country_code":"ID",
    "gn:dem":348,
    "gn:feature_class":"P",
    "gn:feature_code":"PPL",
    "gn:name":"Cipinang",
    "gn:population":0,
    "gn:timezone":"Asia/Jakarta",
    "iso:country":"ID",
    "name:ind_x_preferred":[
        "Cipinang"
    ],
    "wof:name":"Cipinang",
    "wof:placetype":"locality"
},
  "geometry": {"coordinates":[107.37139000000001,-6.745],"type":"Point"}
}