{
  "type": "Feature",
  "properties": {
    "gn:admin1_code":"7.0",
    "gn:asciiname":"Bulupayung",
    "gn:country_code":"ID",
    "gn:dem":7,
    "gn:feature_class":"P",
    "gn:feature_code":"PPL",
    "gn:name":"Bulupayung",
    "gn:population":0,
    "gn:timezone":"Asia/Jakarta",
    "iso:country":"ID",
    "name:ind_x_preferred":[
        "Bulupayung"
    ],
    "wof:name":"Bulupayung",
    "wof:placetype":"locality"
},
  "geometry": {"coordinates":[108.78417,-7.57784],"type":"Point"}
}