{
  "type": "Feature",
  "properties": {
    "gn:admin1_code":"34",
    "gn:asciiname":"Karyagaluh Dua",
    "gn:country_code":"ID",
    "gn:dem":72,
    "gn:feature_class":"P",
    "gn:feature_code":"PPL",
    "gn:name":"Karyagaluh Dua",
    "gn:population":0,
    "gn:timezone":"Asia/Makassar",
    "iso:country":"ID",
    "name:ind_x_preferred":[
        "Karyagaluh Dua"
    ],
    "name:und_x_variant":[
        "Karyagaluh 2"
    ],
    "wof:name":"Karyagaluh Dua",
    "wof:placetype":"locality"
},
  "geometry": {"coordinates":[122.40470000000001,0.6983],"type":"Point"}
}