{
  "type": "Feature",
  "properties": {
    "gn:admin1_code":"7.0",
    "gn:asciiname":"Soropandan",
    "gn:country_code":"ID",
    "gn:dem":489,
    "gn:feature_class":"P",
    "gn:feature_code":"PPL",
    "gn:name":"Soropandan",
    "gn:population":0,
    "gn:timezone":"Asia/Jakarta",
    "iso:country":"ID",
    "wof:name":"Soropandan",
    "wof:placetype":"locality"
},
  "geometry": {"coordinates":[110.32917,-7.59139],"type":"Point"}
}