{
  "type": "Feature",
  "properties": {
    "gn:admin1_code":"26.0",
    "gn:asciiname":"Marimari",
    "gn:country_code":"ID",
    "gn:dem":1273,
    "gn:feature_class":"P",
    "gn:feature_code":"PPL",
    "gn:name":"Marimari",
    "gn:population":0,
    "gn:timezone":"Asia/Jakarta",
    "iso:country":"ID",
    "name:ind_x_preferred":[
        "Marimari"
    ],
    "wof:name":"Marimari",
    "wof:placetype":"locality"
},
  "geometry": {"coordinates":[98.6377,2.1834],"type":"Point"}
}