{
  "type": "Feature",
  "properties": {
    "gn:admin1_code":"7.0",
    "gn:asciiname":"Bantarwuni",
    "gn:country_code":"ID",
    "gn:dem":117,
    "gn:feature_class":"P",
    "gn:feature_code":"PPL",
    "gn:name":"Bantarwuni",
    "gn:population":0,
    "gn:timezone":"Asia/Jakarta",
    "iso:country":"ID",
    "name:ind_x_preferred":[
        "Bantarwuni"
    ],
    "wof:name":"Bantarwuni",
    "wof:placetype":"locality"
},
  "geometry": {"coordinates":[109.26888999999998,-7.39722],"type":"Point"}
}