{
  "type": "Feature",
  "properties": {
    "gn:admin1_code":"30",
    "gn:asciiname":"Cikuda Dua",
    "gn:cc2":"ID",
    "gn:country_code":"ID",
    "gn:dem":94,
    "gn:feature_class":"P",
    "gn:feature_code":"PPL",
    "gn:name":"Cikuda Dua",
    "gn:population":0,
    "gn:timezone":"Asia/Jakarta",
    "iso:country":"ID",
    "name:und_x_variant":[
        "Tjikuda 2",
        "Tjikuda Dua",
        "Cikuda Dua"
    ],
    "wof:lang_x_official":[
        "ind"
    ],
    "wof:lang_x_spoken":[
        "ind",
        "eng"
    ],
    "wof:name":"Cikuda Dua",
    "wof:placetype":"locality"
},
  "geometry": {"coordinates":[106.90416999999999,-6.43278],"type":"Point"}
}