{
  "type": "Feature",
  "properties": {
    "gn:admin1_code":"30",
    "gn:asciiname":"Bojongjati",
    "gn:cc2":"ID",
    "gn:country_code":"ID",
    "gn:dem":668,
    "gn:feature_class":"P",
    "gn:feature_code":"PPL",
    "gn:name":"Bojongjati",
    "gn:population":0,
    "gn:timezone":"Asia/Jakarta",
    "iso:country":"ID",
    "name:und_x_variant":[
        "Bodjongdjati",
        "Bojongjati"
    ],
    "wof:name":"Bojongjati",
    "wof:placetype":"locality"
},
  "geometry": {"coordinates":[107.72056000000001,-7.00417],"type":"Point"}
}