{
  "type": "Feature",
  "properties": {
    "gn:admin1_code":"30.0",
    "gn:asciiname":"Kates Kidul",
    "gn:country_code":"ID",
    "gn:dem":124,
    "gn:feature_class":"P",
    "gn:feature_code":"PPL",
    "gn:name":"Kates Kidul",
    "gn:population":0,
    "gn:timezone":"Asia/Jakarta",
    "iso:country":"ID",
    "name:ind_x_preferred":[
        "Kates Kidul"
    ],
    "wof:name":"Kates Kidul",
    "wof:placetype":"locality"
},
  "geometry": {"coordinates":[111.49720000000001,-7.3066],"type":"Point"}
}