{
  "type": "Feature",
  "properties": {
    "gn:admin1_code":"30.0",
    "gn:asciiname":"Cimenteng",
    "gn:country_code":"ID",
    "gn:dem":501,
    "gn:feature_class":"P",
    "gn:feature_code":"PPL",
    "gn:name":"Cimenteng",
    "gn:population":0,
    "gn:timezone":"Asia/Jakarta",
    "iso:country":"ID",
    "name:ind_x_preferred":[
        "Cimenteng"
    ],
    "name:und_x_variant":[
        "Tjimenteng"
    ],
    "wof:name":"Cimenteng",
    "wof:placetype":"locality"
},
  "geometry": {"coordinates":[107.23909999999999,-7.356],"type":"Point"}
}