{
  "type": "Feature",
  "properties": {
    "gn:admin1_code":"7.0",
    "gn:asciiname":"Kemloko",
    "gn:country_code":"ID",
    "gn:dem":984,
    "gn:feature_class":"P",
    "gn:feature_code":"PPL",
    "gn:name":"Kemloko",
    "gn:population":0,
    "gn:timezone":"Asia/Jakarta",
    "iso:country":"ID",
    "wof:name":"Kemloko",
    "wof:placetype":"locality"
},
  "geometry": {"coordinates":[110.13943999999999,-7.36694],"type":"Point"}
}