{
  "type": "Feature",
  "properties": {
    "gn:admin1_code":"18.0",
    "gn:asciiname":"Kabuni",
    "gn:country_code":"ID",
    "gn:dem":65,
    "gn:feature_class":"P",
    "gn:feature_code":"PPL",
    "gn:name":"Kabuni",
    "gn:population":0,
    "gn:timezone":"Asia/Makassar",
    "iso:country":"ID",
    "name:ind_x_preferred":[
        "Kabuni"
    ],
    "name:pol_x_preferred":[
        "Kabuni"
    ],
    "name:sqi_x_preferred":[
        "Kabunia"
    ],
    "wof:name":"Kabuni",
    "wof:placetype":"locality"
},
  "geometry": {"coordinates":[119.0423,-9.6691],"type":"Point"}
}