{
  "type": "Feature",
  "properties": {
    "gn:admin1_code":"33",
    "gn:asciiname":"Panyandungan",
    "gn:country_code":"ID",
    "gn:dem":172,
    "gn:feature_class":"P",
    "gn:feature_code":"PPL",
    "gn:name":"Panyandungan",
    "gn:population":0,
    "gn:timezone":"Asia/Jakarta",
    "iso:country":"ID",
    "name:ind_x_preferred":[
        "Panyandungan"
    ],
    "wof:name":"Panyandungan",
    "wof:placetype":"locality"
},
  "geometry": {"coordinates":[106.13460000000001,-6.311],"type":"Point"}
}