{
  "type": "Feature",
  "properties": {
    "gn:admin1_code":"8",
    "gn:asciiname":"Tanjungpecinan Selatan",
    "gn:country_code":"ID",
    "gn:dem":9,
    "gn:feature_class":"P",
    "gn:feature_code":"PPL",
    "gn:name":"Tanjungpecinan Selatan",
    "gn:population":0,
    "gn:timezone":"Asia/Jakarta",
    "iso:country":"ID",
    "name:ind_x_preferred":[
        "Tanjungpecinan Selatan"
    ],
    "wof:lang_x_official":[
        "ind"
    ],
    "wof:lang_x_spoken":[
        "ind",
        "eng"
    ],
    "wof:name":"Tanjungpecinan Selatan",
    "wof:placetype":"locality"
},
  "geometry": {"coordinates":[114.0318,-7.6375],"type":"Point"}
}