{
  "type": "Feature",
  "properties": {
    "gn:admin1_code":"30.0",
    "gn:asciiname":"Sodung",
    "gn:country_code":"ID",
    "gn:dem":174,
    "gn:feature_class":"P",
    "gn:feature_code":"PPL",
    "gn:name":"Sodung",
    "gn:population":0,
    "gn:timezone":"Asia/Jakarta",
    "iso:country":"ID",
    "name:ind_x_preferred":[
        "Sodung"
    ],
    "wof:name":"Sodung",
    "wof:placetype":"locality"
},
  "geometry": {"coordinates":[106.6266,-7.325],"type":"Point"}
}