{
  "type": "Feature",
  "properties": {
    "gn:admin1_code":"30",
    "gn:asciiname":"Weninggalih",
    "gn:country_code":"ID",
    "gn:dem":962,
    "gn:feature_class":"P",
    "gn:feature_code":"PPL",
    "gn:name":"Weninggalih",
    "gn:population":0,
    "gn:timezone":"Asia/Jakarta",
    "iso:country":"ID",
    "name:ind_x_preferred":[
        "Weninggalih"
    ],
    "wof:lang_x_official":[
        "ind"
    ],
    "wof:lang_x_spoken":[
        "ind",
        "eng"
    ],
    "wof:name":"Weninggalih",
    "wof:placetype":"locality"
},
  "geometry": {"coordinates":[107.38809999999999,-7.0196],"type":"Point"}
}