{
  "type": "Feature",
  "properties": {
    "gn:admin1_code":"38",
    "gn:asciiname":"Pepabri",
    "gn:country_code":"ID",
    "gn:dem":31,
    "gn:feature_class":"P",
    "gn:feature_code":"PPL",
    "gn:name":"Pepabri",
    "gn:population":0,
    "gn:timezone":"Asia/Makassar",
    "iso:country":"ID",
    "name:ind_x_preferred":[
        "Pepabri"
    ],
    "name:und_x_variant":[
        "Popabri"
    ],
    "wof:lang_x_official":[
        "ind"
    ],
    "wof:lang_x_spoken":[
        "ind",
        "eng"
    ],
    "wof:name":"Pepabri",
    "wof:placetype":"locality"
},
  "geometry": {"coordinates":[120.1748,-2.9354],"type":"Point"}
}