{
  "type": "Feature",
  "properties": {
    "gn:admin1_code":"17",
    "gn:asciiname":"Mesaleng",
    "gn:country_code":"ID",
    "gn:dem":110,
    "gn:feature_class":"P",
    "gn:feature_code":"PPL",
    "gn:name":"Mesaleng",
    "gn:population":0,
    "gn:timezone":"Asia/Makassar",
    "iso:country":"ID",
    "name:ind_x_preferred":[
        "Mesaleng"
    ],
    "wof:name":"Mesaleng",
    "wof:placetype":"locality"
},
  "geometry": {"coordinates":[116.2008,-8.6185],"type":"Point"}
}