{
  "type": "Feature",
  "properties": {
    "gn:country":"ID",
    "gn:fcode":"PPL",
    "gn:pop":0,
    "iso:country":"ID",
    "name:ace_x_preferred":[
        "Batuan"
    ],
    "name:ban_x_preferred":[
        "Batuan"
    ],
    "name:ceb_x_preferred":[
        "Desa Batuan"
    ],
    "name:deu_x_preferred":[
        "Batuan"
    ],
    "name:eng_x_preferred":[
        "Batuan"
    ],
    "name:fra_x_preferred":[
        "Batuan"
    ],
    "name:ind_x_preferred":[
        "Batuan"
    ],
    "name:ind_x_variant":[
        "Rumbia"
    ],
    "name:jav_x_preferred":[
        "Batuan"
    ],
    "name:msa_x_preferred":[
        "Batuan"
    ],
    "name:nld_x_preferred":[
        "Batuan"
    ],
    "name:por_x_preferred":[
        "Batuan"
    ],
    "name:spa_x_preferred":[
        "Batuan"
    ],
    "name:zho_x_preferred":[
        "\u5df4\u5716\u5e03\u862d\u6587\u5316\u6751"
    ],
    "qs:name":"Batuan",
    "qs:name_adm0":"Indonesia",
    "qs:name_adm1":"Bali",
    "qs:photos_9k":2,
    "qs:photos_9r":5,
    "qs:photos_all":473,
    "qs:photos_sr":0,
    "qs:placetype":"Town",
    "qs:pop_sr":"0",
    "wd:wordcount":56,
    "wof:lang_x_official":[
        "ind"
    ],
    "wof:lang_x_spoken":[
        "ind",
        "eng"
    ],
    "wof:name":"Batuan",
    "wof:placetype":"locality",
    "wof:population":0
},
  "geometry": {"coordinates":[115.27525,-8.58577],"type":"Point"}
}