{
  "type": "Feature",
  "properties": {
    "gn:admin1_code":"30",
    "gn:asciiname":"Pangupukan",
    "gn:country_code":"ID",
    "gn:dem":793,
    "gn:feature_class":"P",
    "gn:feature_code":"PPL",
    "gn:name":"Pangupukan",
    "gn:population":0,
    "gn:timezone":"Asia/Jakarta",
    "iso:country":"ID",
    "wof:name":"Pangupukan",
    "wof:placetype":"locality"
},
  "geometry": {"coordinates":[107.68722,-7.06111],"type":"Point"}
}