{
  "type": "Feature",
  "properties": {
    "gn:admin1_code":"8.0",
    "gn:asciiname":"Manggar",
    "gn:country_code":"ID",
    "gn:dem":116,
    "gn:feature_class":"P",
    "gn:feature_code":"PPL",
    "gn:name":"Manggar",
    "gn:population":0,
    "gn:timezone":"Asia/Jakarta",
    "iso:country":"ID",
    "name:ceb_x_preferred":[
        "Manggar"
    ],
    "name:fra_x_preferred":[
        "Manggar"
    ],
    "name:ind_x_preferred":[
        "Manggar"
    ],
    "name:min_x_preferred":[
        "Manggar"
    ],
    "name:mlg_x_preferred":[
        "Manggar"
    ],
    "name:msa_x_preferred":[
        "Manggar"
    ],
    "name:rus_x_preferred":[
        "\u041c\u0430\u043d\u0433\u0433\u0430\u0440"
    ],
    "wof:name":"Manggar",
    "wof:placetype":"locality"
},
  "geometry": {"coordinates":[113.4058,-7.0136],"type":"Point"}
}