{
  "type": "Feature",
  "properties": {
    "gn:admin1_code":"30.0",
    "gn:asciiname":"Nangewer",
    "gn:country_code":"ID",
    "gn:dem":800,
    "gn:feature_class":"P",
    "gn:feature_code":"PPL",
    "gn:name":"Nangewer",
    "gn:population":0,
    "gn:timezone":"Asia/Jakarta",
    "iso:country":"ID",
    "name:ind_x_preferred":[
        "Nangewer"
    ],
    "wof:name":"Nangewer",
    "wof:placetype":"locality"
},
  "geometry": {"coordinates":[107.8944,-7.4891],"type":"Point"}
}