{
  "type": "Feature",
  "properties": {
    "gn:admin1_code":"26",
    "gn:asciiname":"Sitaluama Satu",
    "gn:country_code":"ID",
    "gn:dem":918,
    "gn:feature_class":"P",
    "gn:feature_code":"PPL",
    "gn:name":"Sitaluama Satu",
    "gn:population":0,
    "gn:timezone":"Asia/Jakarta",
    "iso:country":"ID",
    "name:ind_x_preferred":[
        "Sitaluama Satu"
    ],
    "name:und_x_variant":[
        "Sitaluama 1"
    ],
    "wof:lang_x_official":[
        "ind"
    ],
    "wof:lang_x_spoken":[
        "ind",
        "eng"
    ],
    "wof:name":"Sitaluama Satu",
    "wof:placetype":"locality"
},
  "geometry": {"coordinates":[99.1481,2.3818],"type":"Point"}
}