{
  "type": "Feature",
  "properties": {
    "gn:admin1_code":"30",
    "gn:asciiname":"Neglasari",
    "gn:country_code":"ID",
    "gn:dem":895,
    "gn:feature_class":"P",
    "gn:feature_code":"PPL",
    "gn:name":"Neglasari",
    "gn:population":0,
    "gn:timezone":"Asia/Jakarta",
    "iso:country":"ID",
    "wof:name":"Neglasari",
    "wof:placetype":"locality"
},
  "geometry": {"coordinates":[107.65889,-7.05306],"type":"Point"}
}