{
  "type": "Feature",
  "properties": {
    "gn:admin1_code":"18.0",
    "gn:asciiname":"Wanolura",
    "gn:country_code":"ID",
    "gn:dem":557,
    "gn:feature_class":"P",
    "gn:feature_code":"PPL",
    "gn:name":"Wanolura",
    "gn:population":0,
    "gn:timezone":"Asia/Makassar",
    "iso:country":"ID",
    "name:ind_x_preferred":[
        "Wanolura"
    ],
    "wof:name":"Wanolura",
    "wof:placetype":"locality"
},
  "geometry": {"coordinates":[119.36790000000001,-9.5408],"type":"Point"}
}