{
  "type": "Feature",
  "properties": {
    "gn:admin1_code":"30",
    "gn:asciiname":"Panaragan Baru",
    "gn:country_code":"ID",
    "gn:dem":225,
    "gn:feature_class":"P",
    "gn:feature_code":"PPL",
    "gn:name":"Panaragan Baru",
    "gn:population":0,
    "gn:timezone":"Asia/Jakarta",
    "iso:country":"ID",
    "name:ind_x_preferred":[
        "Panaragan Baru"
    ],
    "wof:name":"Panaragan Baru",
    "wof:placetype":"locality"
},
  "geometry": {"coordinates":[106.78389,-6.59806],"type":"Point"}
}