{
  "type": "Feature",
  "properties": {
    "gn:admin1_code":"26",
    "gn:admin2_code":"1205",
    "gn:asciiname":"Huta Raja Habinsaran",
    "gn:country_code":"ID",
    "gn:dem":1152,
    "gn:feature_class":"P",
    "gn:feature_code":"PPL",
    "gn:name":"Huta Raja Habinsaran",
    "gn:population":0,
    "gn:timezone":"Asia/Jakarta",
    "iso:country":"ID",
    "name:ind_x_preferred":[
        "Huta Raja Habinsaran"
    ],
    "wof:lang_x_official":[
        "ind"
    ],
    "wof:lang_x_spoken":[
        "ind",
        "eng"
    ],
    "wof:name":"Huta Raja Habinsaran",
    "wof:placetype":"locality"
},
  "geometry": {"coordinates":[98.9627,2.1431],"type":"Point"}
}