{
  "type": "Feature",
  "properties": {
    "gn:admin1_code":"7.0",
    "gn:asciiname":"Paketen",
    "gn:country_code":"ID",
    "gn:dem":678,
    "gn:feature_class":"P",
    "gn:feature_code":"PPL",
    "gn:name":"Paketen",
    "gn:population":0,
    "gn:timezone":"Asia/Jakarta",
    "iso:country":"ID",
    "name:ind_x_preferred":[
        "Paketen"
    ],
    "wof:name":"Paketen",
    "wof:placetype":"locality"
},
  "geometry": {"coordinates":[109.73222,-7.34278],"type":"Point"}
}