{
  "type": "Feature",
  "properties": {
    "gn:admin1_code":"22",
    "gn:asciiname":"Tanjungpinang",
    "gn:country_code":"ID",
    "gn:dem":3,
    "gn:feature_class":"P",
    "gn:feature_code":"PPL",
    "gn:name":"Tanjungpinang",
    "gn:population":0,
    "gn:timezone":"Asia/Makassar",
    "iso:country":"ID",
    "name:hun_x_preferred":[
        "Tanjungpinang"
    ],
    "name:ind_x_preferred":[
        "Tanjungpinang"
    ],
    "name:por_x_preferred":[
        "Tanjung Pinang"
    ],
    "name:und_x_variant":[
        "Tanjungpinag"
    ],
    "wof:lang_x_official":[
        "ind"
    ],
    "wof:lang_x_spoken":[
        "ind",
        "eng"
    ],
    "wof:name":"Tanjungpinang",
    "wof:placetype":"locality"
},
  "geometry": {"coordinates":[122.5337,-4.7032],"type":"Point"}
}