{
  "type": "Feature",
  "properties": {
    "gn:country":"ID",
    "gn:fcode":"ADM4",
    "gn:pop":0,
    "iso:country":"ID",
    "name:ind_x_preferred":[
        "Desa Kalisari"
    ],
    "name:unk_x_variant":[
        "Kalisari"
    ],
    "qs:name":"Desa Kalisari",
    "qs:photos_9r":0,
    "qs:photos_sr":0,
    "qs:pop_sr":"0",
    "wof:name":"Desa Kalisari",
    "wof:placetype":"localadmin",
    "wof:population":0
},
  "geometry": {"coordinates":[109.11167,-7.38694],"type":"Point"}
}