{
  "type": "Feature",
  "properties": {
    "gn:admin1_code":"30",
    "gn:asciiname":"Sekebungur",
    "gn:country_code":"ID",
    "gn:dem":665,
    "gn:feature_class":"P",
    "gn:feature_code":"PPL",
    "gn:name":"Sekebungur",
    "gn:population":0,
    "gn:timezone":"Asia/Jakarta",
    "iso:country":"ID",
    "name:ind_x_preferred":[
        "Sekebungur"
    ],
    "wof:name":"Sekebungur",
    "wof:placetype":"locality"
},
  "geometry": {"coordinates":[107.54861,-6.98278],"type":"Point"}
}