{
  "type": "Feature",
  "properties": {
    "gn:admin1_code":"15.0",
    "gn:asciiname":"Giritarto",
    "gn:country_code":"ID",
    "gn:dem":177,
    "gn:feature_class":"P",
    "gn:feature_code":"PPL",
    "gn:name":"Giritarto",
    "gn:population":0,
    "gn:timezone":"Asia/Jakarta",
    "iso:country":"ID",
    "name:ind_x_preferred":[
        "Giritarto"
    ],
    "wof:name":"Giritarto",
    "wof:placetype":"locality"
},
  "geometry": {"coordinates":[105.22884000000001,-5.38758],"type":"Point"}
}