{
  "type": "Feature",
  "properties": {
    "gn:admin1_code":"21",
    "gn:asciiname":"Mpanau",
    "gn:country_code":"ID",
    "gn:dem":67,
    "gn:feature_class":"P",
    "gn:feature_code":"PPL",
    "gn:name":"Mpanau",
    "gn:population":0,
    "gn:timezone":"Asia/Makassar",
    "iso:country":"ID",
    "name:ind_x_preferred":[
        "Mpanau"
    ],
    "wof:name":"Mpanau",
    "wof:placetype":"locality"
},
  "geometry": {"coordinates":[119.9158,-0.9506],"type":"Point"}
}