{
  "type": "Feature",
  "properties": {
    "gn:admin1_code":"0.0",
    "gn:asciiname":"Wirango",
    "gn:cc2":"ID",
    "gn:country_code":"ID",
    "gn:dem":141,
    "gn:feature_class":"P",
    "gn:feature_code":"PPL",
    "gn:name":"Wirango",
    "gn:population":0,
    "gn:timezone":"Asia/Jayapura",
    "iso:country":"ID",
    "name:und_x_variant":[
        "Mawar",
        "Wirango"
    ],
    "wof:name":"Wirango",
    "wof:placetype":"locality"
},
  "geometry": {"coordinates":[132.13333,-2.68333],"type":"Point"}
}