{
  "type": "Feature",
  "properties": {
    "gn:admin1_code":"0.0",
    "gn:asciiname":"Selebam",
    "gn:cc2":"ID",
    "gn:country_code":"ID",
    "gn:dem":21,
    "gn:feature_class":"P",
    "gn:feature_code":"PPL",
    "gn:name":"Selebam",
    "gn:population":0,
    "gn:timezone":"Asia/Jayapura",
    "iso:country":"ID",
    "name:und_x_variant":[
        "Kampoeng Salabam",
        "Selebam"
    ],
    "wof:name":"Selebam",
    "wof:placetype":"locality"
},
  "geometry": {"coordinates":[131.18333000000001,-1.21667],"type":"Point"}
}