{
  "type": "Feature",
  "properties": {
    "gn:admin1_code":"28.0",
    "gn:asciiname":"Herit",
    "gn:country_code":"ID",
    "gn:dem":13,
    "gn:feature_class":"P",
    "gn:feature_code":"PPL",
    "gn:name":"Herit",
    "gn:population":0,
    "gn:timezone":"Asia/Jayapura",
    "iso:country":"ID",
    "name:ind_x_preferred":[
        "Hirit"
    ],
    "name:ind_x_variant":[
        "Herit"
    ],
    "name:sin_x_preferred":[
        "\u0dc4\u0dd9\u0dbb\u0dd2\u0da7\u0dca"
    ],
    "name:tha_x_preferred":[
        "\u0e40\u0e2e\u0e23\u0e34\u0e17"
    ],
    "wof:lang_x_official":[
        "ind"
    ],
    "wof:lang_x_spoken":[
        "ind",
        "eng"
    ],
    "wof:name":"Herit",
    "wof:placetype":"locality"
},
  "geometry": {"coordinates":[131.96397999999999,-5.3734],"type":"Point"}
}