{
  "type": "Feature",
  "properties": {
    "gn:admin1_code":"18.0",
    "gn:asciiname":"Sosalain",
    "gn:country_code":"ID",
    "gn:dem":222,
    "gn:feature_class":"P",
    "gn:feature_code":"PPL",
    "gn:name":"Sosalain",
    "gn:population":0,
    "gn:timezone":"Asia/Makassar",
    "iso:country":"ID",
    "name:ind_x_preferred":[
        "Sosalain"
    ],
    "wof:name":"Sosalain",
    "wof:placetype":"locality"
},
  "geometry": {"coordinates":[123.1896,-10.8068],"type":"Point"}
}