{
  "type": "Feature",
  "properties": {
    "gn:admin1_code":"30",
    "gn:asciiname":"Pasircau Tengah",
    "gn:country_code":"ID",
    "gn:dem":654,
    "gn:feature_class":"P",
    "gn:feature_code":"PPL",
    "gn:name":"Pasircau Tengah",
    "gn:population":0,
    "gn:timezone":"Asia/Jakarta",
    "iso:country":"ID",
    "name:ind_x_preferred":[
        "Pasircau Tengah"
    ],
    "name:und_x_variant":[
        "Pasircau Tengan"
    ],
    "wof:lang_x_official":[
        "ind"
    ],
    "wof:lang_x_spoken":[
        "ind",
        "eng"
    ],
    "wof:name":"Pasircau Tengah",
    "wof:placetype":"locality"
},
  "geometry": {"coordinates":[107.07832999999999,-6.84611],"type":"Point"}
}