{
  "type": "Feature",
  "properties": {
    "gn:admin1_code":"11.0",
    "gn:asciiname":"Cupeng",
    "gn:country_code":"ID",
    "gn:dem":74,
    "gn:feature_class":"P",
    "gn:feature_code":"PPL",
    "gn:name":"Cupeng",
    "gn:population":0,
    "gn:timezone":"Asia/Pontianak",
    "iso:country":"ID",
    "name:ind_x_preferred":[
        "Cupeng"
    ],
    "name:und_x_variant":[
        "Tjoepang",
        "Tjupang",
        "Cupang"
    ],
    "wof:name":"Cupeng",
    "wof:placetype":"locality"
},
  "geometry": {"coordinates":[110.95354,-0.26275],"type":"Point"}
}