{
  "type": "Feature",
  "properties": {
    "gn:admin1_code":"38.0",
    "gn:asciiname":"Buto",
    "gn:country_code":"ID",
    "gn:dem":44,
    "gn:feature_class":"P",
    "gn:feature_code":"PPL",
    "gn:name":"Buto",
    "gn:population":0,
    "gn:timezone":"Asia/Makassar",
    "iso:country":"ID",
    "name:ind_x_preferred":[
        "Buto"
    ],
    "wof:name":"Buto",
    "wof:placetype":"locality"
},
  "geometry": {"coordinates":[119.77196000000001,-3.63139],"type":"Point"}
}