{
  "type": "Feature",
  "properties": {
    "gn:admin1_code":"38.0",
    "gn:asciiname":"Buto",
    "gn:country_code":"ID",
    "gn:dem":44,
    "gn:feature_class":"P",
    "gn:feature_code":"PPL",
    "gn:name":"Buto",
    "gn:population":0,
    "gn:timezone":"Asia/Makassar",
    "iso:country":"ID",
    "name:ara_x_preferred":[
        "\u0628\u0648\u062a\u0648"
    ],
    "name:arz_x_preferred":[
        "\u0628\u0648\u062a\u0648"
    ],
    "name:bul_x_preferred":[
        "\u0411\u0443\u0442\u043e"
    ],
    "name:cat_x_preferred":[
        "Buto"
    ],
    "name:ceb_x_preferred":[
        "Buto"
    ],
    "name:ces_x_preferred":[
        "B\u00fat\u00f3"
    ],
    "name:deu_x_preferred":[
        "Buto"
    ],
    "name:ell_x_preferred":[
        "\u0392\u03bf\u03c5\u03c4\u03ce"
    ],
    "name:eus_x_preferred":[
        "Buto"
    ],
    "name:fas_x_preferred":[
        "\u0628\u0648\u062a\u0648"
    ],
    "name:fra_x_preferred":[
        "Bouto"
    ],
    "name:hun_x_preferred":[
        "Per Uadzset"
    ],
    "name:ind_x_preferred":[
        "Buto"
    ],
    "name:ita_x_preferred":[
        "Buto"
    ],
    "name:lit_x_preferred":[
        "Buto"
    ],
    "name:nld_x_preferred":[
        "Boeto"
    ],
    "name:pol_x_preferred":[
        "Buto"
    ],
    "name:por_x_preferred":[
        "Buto"
    ],
    "name:rus_x_preferred":[
        "\u0411\u0443\u0442\u043e"
    ],
    "name:slk_x_preferred":[
        "Pervad\u017eet"
    ],
    "name:spa_x_preferred":[
        "Buto"
    ],
    "name:swe_x_preferred":[
        "Buto"
    ],
    "name:ukr_x_preferred":[
        "\u0411\u0443\u0442\u043e"
    ],
    "name:urd_x_preferred":[
        "\u0628\u0648\u062a\u0648"
    ],
    "wof:name":"Buto",
    "wof:placetype":"locality"
},
  "geometry": {"coordinates":[119.77196000000001,-3.63139],"type":"Point"}
}