{
  "type": "Feature",
  "properties": {
    "gn:admin1_code":"12",
    "gn:asciiname":"Kirtawar",
    "gn:country_code":"ID",
    "gn:dem":8,
    "gn:feature_class":"P",
    "gn:feature_code":"PPL",
    "gn:name":"Kirtawar",
    "gn:population":0,
    "gn:timezone":"Asia/Makassar",
    "iso:country":"ID",
    "name:ind_x_preferred":[
        "Kirtawar"
    ],
    "wof:name":"Kirtawar",
    "wof:placetype":"locality"
},
  "geometry": {"coordinates":[116.16119999999999,-2.9033],"type":"Point"}
}