{
  "type": "Feature",
  "properties": {
    "gn:admin1_code":"7.0",
    "gn:asciiname":"Bumiwanamukti",
    "gn:country_code":"ID",
    "gn:dem":29,
    "gn:feature_class":"P",
    "gn:feature_code":"PPL",
    "gn:name":"Bumiwanamukti",
    "gn:population":0,
    "gn:timezone":"Asia/Jakarta",
    "iso:country":"ID",
    "name:ind_x_preferred":[
        "Bumiwanamukti"
    ],
    "wof:name":"Bumiwanamukti",
    "wof:placetype":"locality"
},
  "geometry": {"coordinates":[110.4594,-7.0312],"type":"Point"}
}