{
  "type": "Feature",
  "properties": {
    "gn:admin1_code":"8",
    "gn:asciiname":"Pace",
    "gn:country_code":"ID",
    "gn:dem":601,
    "gn:feature_class":"P",
    "gn:feature_code":"PPL",
    "gn:name":"Pace",
    "gn:population":0,
    "gn:timezone":"Asia/Jakarta",
    "iso:country":"ID",
    "name:cat_x_preferred":[
        "Pace"
    ],
    "name:ceb_x_preferred":[
        "Pace"
    ],
    "name:ces_x_preferred":[
        "Pace"
    ],
    "name:deu_x_preferred":[
        "Pace"
    ],
    "name:fra_x_preferred":[
        "Pace"
    ],
    "name:ind_x_preferred":[
        "Pace"
    ],
    "name:ita_x_preferred":[
        "Pace"
    ],
    "name:nld_x_preferred":[
        "Pace"
    ],
    "name:pol_x_preferred":[
        "Pace"
    ],
    "name:por_x_preferred":[
        "Pace"
    ],
    "name:ron_x_preferred":[
        "Pace"
    ],
    "name:rus_x_preferred":[
        "\u0422\u0435\u043c\u043f"
    ],
    "name:srp_x_preferred":[
        "\u041f\u0435\u0458\u0441"
    ],
    "name:swe_x_preferred":[
        "Pace"
    ],
    "name:ukr_x_preferred":[
        "\u041f\u0435\u0439\u0441"
    ],
    "name:vol_x_preferred":[
        "Pace"
    ],
    "wof:lang_x_official":[
        "ind"
    ],
    "wof:lang_x_spoken":[
        "ind",
        "eng"
    ],
    "wof:name":"Pace",
    "wof:placetype":"locality"
},
  "geometry": {"coordinates":[113.9204,-8.0285],"type":"Point"}
}