{
  "type": "Feature",
  "properties": {
    "gn:admin1_code":"8",
    "gn:asciiname":"Secangan Temor",
    "gn:country_code":"ID",
    "gn:dem":414,
    "gn:feature_class":"P",
    "gn:feature_code":"PPL",
    "gn:name":"Secangan Temor",
    "gn:population":0,
    "gn:timezone":"Asia/Jakarta",
    "iso:country":"ID",
    "name:ind_x_preferred":[
        "Secangan Temor"
    ],
    "wof:name":"Secangan Temor",
    "wof:placetype":"locality"
},
  "geometry": {"coordinates":[113.6335,-7.7636],"type":"Point"}
}