{
  "type": "Feature",
  "properties": {
    "gn:admin1_code":"26",
    "gn:asciiname":"Rajabulu",
    "gn:country_code":"ID",
    "gn:dem":95,
    "gn:feature_class":"P",
    "gn:feature_code":"PPL",
    "gn:name":"Rajabulu",
    "gn:population":0,
    "gn:timezone":"Asia/Jakarta",
    "iso:country":"ID",
    "name:ind_x_preferred":[
        "Rajabulu"
    ],
    "wof:name":"Rajabulu",
    "wof:placetype":"locality"
},
  "geometry": {"coordinates":[98.95650000000001,3.2941],"type":"Point"}
}