{
  "type": "Feature",
  "properties": {
    "gn:admin1_code":"18.0",
    "gn:asciiname":"Wairiang",
    "gn:country_code":"ID",
    "gn:dem":26,
    "gn:feature_class":"P",
    "gn:feature_code":"PPLA3",
    "gn:name":"Wairiang",
    "gn:population":0,
    "gn:timezone":"Asia/Makassar",
    "iso:country":"ID",
    "name:ind_x_preferred":[
        "Wairiang"
    ],
    "wof:lang_x_official":[
        "ind"
    ],
    "wof:lang_x_spoken":[
        "ind",
        "eng"
    ],
    "wof:name":"Wairiang",
    "wof:placetype":"locality"
},
  "geometry": {"coordinates":[123.81870000000001,-8.1921],"type":"Point"}
}