{
  "type": "Feature",
  "properties": {
    "gn:admin1_code":"30.0",
    "gn:asciiname":"Karangasem",
    "gn:country_code":"ID",
    "gn:dem":58,
    "gn:feature_class":"P",
    "gn:feature_code":"PPL",
    "gn:name":"Karangasem",
    "gn:population":0,
    "gn:timezone":"Asia/Jakarta",
    "iso:country":"ID",
    "name:ind_x_preferred":[
        "Karangasem"
    ],
    "wof:name":"Karangasem",
    "wof:placetype":"locality"
},
  "geometry": {"coordinates":[111.41160000000001,-7.4784],"type":"Point"}
}