{
  "type": "Feature",
  "properties": {
    "gn:admin1_code":"7.0",
    "gn:asciiname":"Simo",
    "gn:country_code":"ID",
    "gn:dem":21,
    "gn:feature_class":"P",
    "gn:feature_code":"PPL",
    "gn:name":"Simo",
    "gn:population":0,
    "gn:timezone":"Asia/Jakarta",
    "iso:country":"ID",
    "name:ceb_x_preferred":[
        "Simo"
    ],
    "name:deu_x_preferred":[
        "Simo"
    ],
    "name:fin_x_preferred":[
        "Simo"
    ],
    "name:fra_x_preferred":[
        "Simo"
    ],
    "name:ind_x_preferred":[
        "Simo"
    ],
    "name:ita_x_preferred":[
        "Simo"
    ],
    "name:lit_x_preferred":[
        "Simas"
    ],
    "name:nld_x_preferred":[
        "Simo"
    ],
    "name:pol_x_preferred":[
        "Simo"
    ],
    "name:spa_x_preferred":[
        "Simo"
    ],
    "name:swe_x_preferred":[
        "Simo"
    ],
    "wof:lang_x_official":[
        "ind"
    ],
    "wof:lang_x_spoken":[
        "ind",
        "eng"
    ],
    "wof:name":"Simo",
    "wof:placetype":"locality"
},
  "geometry": {"coordinates":[111.4332,-6.7538],"type":"Point"}
}