{
  "type": "Feature",
  "properties": {
    "gn:admin1_code":"30.0",
    "gn:asciiname":"Cikaramas",
    "gn:country_code":"ID",
    "gn:dem":540,
    "gn:feature_class":"P",
    "gn:feature_code":"PPL",
    "gn:name":"Cikaramas",
    "gn:population":0,
    "gn:timezone":"Asia/Jakarta",
    "iso:country":"ID",
    "name:ind_x_preferred":[
        "Cikaramas"
    ],
    "name:und_x_variant":[
        "Tjikaramas",
        "Cikaramas 2"
    ],
    "wof:lang_x_official":[
        "ind"
    ],
    "wof:lang_x_spoken":[
        "ind",
        "eng"
    ],
    "wof:name":"Cikaramas",
    "wof:placetype":"locality"
},
  "geometry": {"coordinates":[107.83972,-6.76528],"type":"Point"}
}