{
  "type": "Feature",
  "properties": {
    "gn:admin1_code":"38",
    "gn:asciiname":"Balatamaya",
    "gn:country_code":"ID",
    "gn:dem":18,
    "gn:feature_class":"P",
    "gn:feature_code":"PPL",
    "gn:name":"Balatamaya",
    "gn:population":0,
    "gn:timezone":"Asia/Makassar",
    "iso:country":"ID",
    "name:ind_x_preferred":[
        "Balatamaya"
    ],
    "wof:name":"Balatamaya",
    "wof:placetype":"locality"
},
  "geometry": {"coordinates":[119.48869999999999,-5.3711],"type":"Point"}
}