{
  "type": "Feature",
  "properties": {
    "gn:admin1_code":"30.0",
    "gn:asciiname":"Majapahit",
    "gn:country_code":"ID",
    "gn:dem":64,
    "gn:feature_class":"P",
    "gn:feature_code":"PPL",
    "gn:name":"Majapahit",
    "gn:population":0,
    "gn:timezone":"Asia/Jakarta",
    "iso:country":"ID",
    "name:afr_x_preferred":[
        "Majapahit"
    ],
    "name:ara_x_preferred":[
        "\u0625\u0645\u0628\u0631\u0627\u0637\u0648\u0631\u064a\u0629 \u0645\u0627\u062c\u0627\u0628\u0627\u0647\u064a\u062a"
    ],
    "name:ast_x_preferred":[
        "Imperiu mayapajit"
    ],
    "name:bak_x_preferred":[
        "\u041c\u0430\u0434\u0436\u0430\u043f\u0430\u0445\u0438\u0442"
    ],
    "name:bel_x_preferred":[
        "\u041c\u0430\u0434\u0436\u0430\u043f\u0430\u0445\u0456\u0442"
    ],
    "name:bul_x_preferred":[
        "\u041c\u0430\u0434\u0436\u0430\u043f\u0430\u0445\u0438\u0442"
    ],
    "name:ces_x_preferred":[
        "Mad\u017eapahit"
    ],
    "name:deu_x_preferred":[
        "Majapahit"
    ],
    "name:eus_x_preferred":[
        "Majapahit Inperioa"
    ],
    "name:fin_x_preferred":[
        "Majapahit"
    ],
    "name:fra_x_preferred":[
        "Majapahit"
    ],
    "name:heb_x_preferred":[
        "\u05de\u05d2'\u05e4\u05d4\u05d9\u05d8"
    ],
    "name:hin_x_preferred":[
        "\u092e\u091c\u093e\u092a\u0939\u093f\u0924 \u0938\u093e\u092e\u094d\u0930\u093e\u091c\u094d\u092f"
    ],
    "name:ind_x_preferred":[
        "Majapahit"
    ],
    "name:ita_x_preferred":[
        "Majapahit"
    ],
    "name:jav_x_preferred":[
        "Majapait"
    ],
    "name:jpn_x_preferred":[
        "\u30de\u30b8\u30e3\u30d1\u30d2\u30c8\u738b\u56fd"
    ],
    "name:kat_x_preferred":[
        "\u10db\u10d0\u10ef\u10d0\u10de\u10d0\u10f0\u10d8\u10e2\u10d8"
    ],
    "name:kor_x_preferred":[
        "\ub9c8\uc790\ud30c\ud79b \uc81c\uad6d"
    ],
    "name:lit_x_preferred":[
        "Mad\u017eapahitas"
    ],
    "name:mal_x_preferred":[
        "\u0d2e\u0d1c\u0d2a\u0d39\u0d3f\u0d24\u0d4d"
    ],
    "name:mar_x_preferred":[
        "\u092e\u091c\u093e\u092a\u0939\u093f\u0924"
    ],
    "name:msa_x_preferred":[
        "Majapahit"
    ],
    "name:nld_x_preferred":[
        "Koninkrijk Majapahit"
    ],
    "name:nor_x_preferred":[
        "Majapahit"
    ],
    "name:pol_x_preferred":[
        "Majapahit"
    ],
    "name:rus_x_preferred":[
        "\u041c\u0430\u0434\u0436\u0430\u043f\u0430\u0445\u0438\u0442"
    ],
    "name:san_x_preferred":[
        "\u092e\u091c\u093e\u092a\u0939\u093f\u0924\u0938\u093e\u092e\u094d\u0930\u093e\u091c\u094d\u092f\u092e\u094d"
    ],
    "name:spa_x_preferred":[
        "Imperio mayapajit"
    ],
    "name:srp_x_preferred":[
        "\u041c\u0430\u045f\u0430\u043f\u0430\u0445\u0438\u0442"
    ],
    "name:sun_x_preferred":[
        "Majapahit"
    ],
    "name:swe_x_preferred":[
        "Majapahitriket"
    ],
    "name:tam_x_preferred":[
        "\u0bae\u0baf\u0bbe\u0baa\u0bbe\u0b95\u0bbf\u0ba4\u0bcd\u0ba4\u0bc1 \u0baa\u0bc7\u0bb0\u0bb0\u0b9a\u0bc1"
    ],
    "name:tgl_x_preferred":[
        "Majapahit"
    ],
    "name:tha_x_preferred":[
        "\u0e2d\u0e32\u0e13\u0e32\u0e08\u0e31\u0e01\u0e23\u0e21\u0e31\u0e0a\u0e1b\u0e32\u0e2b\u0e34\u0e15"
    ],
    "name:tur_x_preferred":[
        "Majapahit"
    ],
    "name:ukr_x_preferred":[
        "\u041c\u0430\u0434\u0436\u0430\u043f\u0430\u0433\u0456\u0442"
    ],
    "name:vie_x_preferred":[
        "Majapahit"
    ],
    "name:wuu_x_preferred":[
        "\u6ee1\u8005\u4f2f\u5937"
    ],
    "name:zho_x_preferred":[
        "\u6ee1\u8005\u4f2f\u5937"
    ],
    "wof:name":"Majapahit",
    "wof:placetype":"locality"
},
  "geometry": {"coordinates":[108.34639,-6.74278],"type":"Point"}
}