{
  "type": "Feature",
  "properties": {
    "gn:admin1_code":"30.0",
    "gn:asciiname":"Sawahlega",
    "gn:country_code":"ID",
    "gn:dem":1022,
    "gn:feature_class":"P",
    "gn:feature_code":"PPL",
    "gn:name":"Sawahlega",
    "gn:population":0,
    "gn:timezone":"Asia/Jakarta",
    "iso:country":"ID",
    "name:ind_x_preferred":[
        "Sawahlega"
    ],
    "wof:name":"Sawahlega",
    "wof:placetype":"locality"
},
  "geometry": {"coordinates":[108.07850000000001,-7.1091],"type":"Point"}
}