{
  "type": "Feature",
  "properties": {
    "gn:admin1_code":"26",
    "gn:asciiname":"Huta Dolok",
    "gn:country_code":"ID",
    "gn:dem":117,
    "gn:feature_class":"P",
    "gn:feature_code":"PPL",
    "gn:name":"Huta Dolok",
    "gn:population":0,
    "gn:timezone":"Asia/Jakarta",
    "iso:country":"ID",
    "name:ind_x_preferred":[
        "Huta Dolok"
    ],
    "wof:name":"Huta Dolok",
    "wof:placetype":"locality"
},
  "geometry": {"coordinates":[99.59538000000001,1.46214],"type":"Point"}
}