{
  "type": "Feature",
  "properties": {
    "gn:admin1_code":"26",
    "gn:asciiname":"Cabangkanan",
    "gn:country_code":"ID",
    "gn:dem":8,
    "gn:feature_class":"P",
    "gn:feature_code":"PPL",
    "gn:name":"Cabangkanan",
    "gn:population":0,
    "gn:timezone":"Asia/Jakarta",
    "iso:country":"ID",
    "name:ind_x_preferred":[
        "Cabangkanan"
    ],
    "wof:name":"Cabangkanan",
    "wof:placetype":"locality"
},
  "geometry": {"coordinates":[98.5112,3.8018],"type":"Point"}
}