{
  "type": "Feature",
  "properties": {
    "gn:admin1_code":"30.0",
    "gn:asciiname":"Canghiran",
    "gn:country_code":"ID",
    "gn:dem":419,
    "gn:feature_class":"P",
    "gn:feature_code":"PPL",
    "gn:name":"Canghiran",
    "gn:population":0,
    "gn:timezone":"Asia/Jakarta",
    "iso:country":"ID",
    "name:ind_x_preferred":[
        "Canghiran"
    ],
    "wof:name":"Canghiran",
    "wof:placetype":"locality"
},
  "geometry": {"coordinates":[108.4701,-7.2234],"type":"Point"}
}