{
  "type": "Feature",
  "properties": {
    "gn:admin1_code":"18",
    "gn:asciiname":"Tali",
    "gn:country_code":"ID",
    "gn:dem":791,
    "gn:feature_class":"P",
    "gn:feature_code":"PPL",
    "gn:name":"Tali",
    "gn:population":0,
    "gn:timezone":"Asia/Makassar",
    "iso:country":"ID",
    "name:ceb_x_preferred":[
        "Tali"
    ],
    "name:deu_x_preferred":[
        "Tali"
    ],
    "name:fin_x_preferred":[
        "Tali"
    ],
    "name:fra_x_preferred":[
        "Tali"
    ],
    "name:heb_x_preferred":[
        "\u05d8\u05dc\u05d9"
    ],
    "name:nld_x_preferred":[
        "Tali"
    ],
    "name:ron_x_preferred":[
        "Tali"
    ],
    "name:rus_x_preferred":[
        "\u0422\u0430\u043b\u0438"
    ],
    "name:swe_x_preferred":[
        "Tali"
    ],
    "wof:lang_x_official":[
        "ind"
    ],
    "wof:lang_x_spoken":[
        "ind",
        "eng"
    ],
    "wof:name":"Tali",
    "wof:placetype":"locality"
},
  "geometry": {"coordinates":[124.20778,-9.42194],"type":"Point"}
}