{
  "type": "Feature",
  "properties": {
    "gn:admin1_code":"38",
    "gn:asciiname":"Kayuosing",
    "gn:country_code":"ID",
    "gn:dem":1059,
    "gn:feature_class":"P",
    "gn:feature_code":"PPL",
    "gn:name":"Kayuosing",
    "gn:population":0,
    "gn:timezone":"Asia/Makassar",
    "iso:country":"ID",
    "name:ind_x_preferred":[
        "Kayuosing"
    ],
    "wof:name":"Kayuosing",
    "wof:placetype":"locality"
},
  "geometry": {"coordinates":[119.76130000000001,-3.1438],"type":"Point"}
}