{
  "type": "Feature",
  "properties": {
    "gn:country":"ID",
    "gn:fcode":"ADM3",
    "gn:pop":0,
    "iso:country":"ID",
    "name:ind_x_preferred":[
        "Kecamatan Sumur Bandung"
    ],
    "name:unk_x_variant":[
        "Sumur Bandung"
    ],
    "qs:name":"Kecamatan Sumur Bandung",
    "qs:photos_9r":0,
    "qs:photos_sr":0,
    "qs:pop_sr":"0",
    "wof:name":"Kecamatan Sumur Bandung",
    "wof:placetype":"localadmin",
    "wof:population":0
},
  "geometry": {"coordinates":[107.61694,-6.91611],"type":"Point"}
}