{
  "type": "Feature",
  "properties": {
    "gn:admin1_code":"33.0",
    "gn:asciiname":"Keusik",
    "gn:country_code":"ID",
    "gn:dem":9,
    "gn:feature_class":"P",
    "gn:feature_code":"PPL",
    "gn:name":"Keusik",
    "gn:population":0,
    "gn:timezone":"Asia/Jakarta",
    "iso:country":"ID",
    "name:ind_x_preferred":[
        "Keusik"
    ],
    "wof:lang_x_official":[
        "ind"
    ],
    "wof:lang_x_spoken":[
        "ind",
        "eng"
    ],
    "wof:name":"Keusik",
    "wof:placetype":"locality"
},
  "geometry": {"coordinates":[105.76600000000001,-6.5289],"type":"Point"}
}