{
  "type": "Feature",
  "properties": {
    "gn:country":"ID",
    "gn:fcode":"ADM3",
    "gn:pop":0,
    "iso:country":"ID",
    "name:ind_x_preferred":[
        "Kecamatan Panti"
    ],
    "name:unk_x_variant":[
        "Panti"
    ],
    "qs:name":"Kecamatan Panti",
    "qs:photos_9r":0,
    "qs:photos_sr":0,
    "qs:pop_sr":"0",
    "wd:wordcount":626,
    "wof:name":"Kecamatan Panti",
    "wof:placetype":"localadmin",
    "wof:population":0
},
  "geometry": {"coordinates":[113.6164,-8.0647],"type":"Point"}
}