{
  "type": "Feature",
  "properties": {
    "gn:admin1_code":"30.0",
    "gn:asciiname":"Panyauangan",
    "gn:country_code":"ID",
    "gn:dem":250,
    "gn:feature_class":"P",
    "gn:feature_code":"PPL",
    "gn:name":"Panyauangan",
    "gn:population":0,
    "gn:timezone":"Asia/Jakarta",
    "iso:country":"ID",
    "name:ind_x_preferred":[
        "Panyauangan"
    ],
    "name:und_x_variant":[
        "Panjawungan",
        "Penjawungan",
        "Penyawungan"
    ],
    "wof:name":"Panyauangan",
    "wof:placetype":"locality"
},
  "geometry": {"coordinates":[106.56111,-6.56917],"type":"Point"}
}