{
  "type": "Feature",
  "properties": {
    "gn:admin1_code":"30",
    "gn:asciiname":"Cigintung",
    "gn:country_code":"ID",
    "gn:dem":506,
    "gn:feature_class":"P",
    "gn:feature_code":"PPL",
    "gn:name":"Cigintung",
    "gn:population":0,
    "gn:timezone":"Asia/Jakarta",
    "iso:country":"ID",
    "name:ind_x_preferred":[
        "Cigintung"
    ],
    "wof:name":"Cigintung",
    "wof:placetype":"locality"
},
  "geometry": {"coordinates":[106.98972000000001,-6.53944],"type":"Point"}
}