{
  "type": "Feature",
  "properties": {
    "gn:admin1_code":"4",
    "gn:asciiname":"Pasirputih",
    "gn:country_code":"ID",
    "gn:dem":2,
    "gn:feature_class":"P",
    "gn:feature_code":"PPL",
    "gn:name":"Pasirputih",
    "gn:population":0,
    "gn:timezone":"Asia/Jakarta",
    "iso:country":"ID",
    "name:ind_x_preferred":[
        "Pasirputih"
    ],
    "wof:name":"Pasirputih",
    "wof:placetype":"locality"
},
  "geometry": {"coordinates":[106.8475,-6.123],"type":"Point"}
}