{
  "type": "Feature",
  "properties": {
    "gn:admin1_code":"32.0",
    "gn:asciiname":"Lingkis",
    "gn:country_code":"ID",
    "gn:dem":8,
    "gn:feature_class":"P",
    "gn:feature_code":"PPL",
    "gn:name":"Lingkis",
    "gn:population":0,
    "gn:timezone":"Asia/Jakarta",
    "iso:country":"ID",
    "name:ind_x_preferred":[
        "Lingkis"
    ],
    "wof:name":"Lingkis",
    "wof:placetype":"locality"
},
  "geometry": {"coordinates":[104.87194,-3.17344],"type":"Point"}
}