{
  "type": "Feature",
  "properties": {
    "gn:admin1_code":"38",
    "gn:asciiname":"Bontotala",
    "gn:country_code":"ID",
    "gn:dem":25,
    "gn:feature_class":"P",
    "gn:feature_code":"PPL",
    "gn:name":"Bontotala",
    "gn:population":0,
    "gn:timezone":"Asia/Makassar",
    "iso:country":"ID",
    "name:ind_x_preferred":[
        "Bontotala"
    ],
    "wof:name":"Bontotala",
    "wof:placetype":"locality"
},
  "geometry": {"coordinates":[119.5501,-5.5494],"type":"Point"}
}