{
  "type": "Feature",
  "properties": {
    "gn:admin1_code":"15.0",
    "gn:asciiname":"Waspada",
    "gn:country_code":"ID",
    "gn:dem":305,
    "gn:feature_class":"P",
    "gn:feature_code":"PPL",
    "gn:name":"Waspada",
    "gn:population":0,
    "gn:timezone":"Asia/Jakarta",
    "iso:country":"ID",
    "name:ind_x_preferred":[
        "Waspada"
    ],
    "wof:name":"Waspada",
    "wof:placetype":"locality"
},
  "geometry": {"coordinates":[104.73076,-5.27313],"type":"Point"}
}