{
  "type": "Feature",
  "properties": {
    "gn:admin1_code":"30",
    "gn:asciiname":"Kampungwarung",
    "gn:country_code":"ID",
    "gn:dem":682,
    "gn:feature_class":"P",
    "gn:feature_code":"PPL",
    "gn:name":"Kampungwarung",
    "gn:population":0,
    "gn:timezone":"Asia/Jakarta",
    "iso:country":"ID",
    "name:ind_x_preferred":[
        "Kampungwarung"
    ],
    "name:und_x_variant":[
        "Warung"
    ],
    "wof:name":"Kampungwarung",
    "wof:placetype":"locality"
},
  "geometry": {"coordinates":[107.39221999999999,-6.95528],"type":"Point"}
}