{
  "type": "Feature",
  "properties": {
    "gn:admin1_code":"38",
    "gn:asciiname":"Sangkala",
    "gn:country_code":"ID",
    "gn:dem":78,
    "gn:feature_class":"P",
    "gn:feature_code":"PPL",
    "gn:name":"Sangkala",
    "gn:population":0,
    "gn:timezone":"Asia/Makassar",
    "iso:country":"ID",
    "name:ind_x_preferred":[
        "Sangkala"
    ],
    "wof:name":"Sangkala",
    "wof:placetype":"locality"
},
  "geometry": {"coordinates":[120.28789999999999,-5.3443],"type":"Point"}
}