{
  "type": "Feature",
  "properties": {
    "gn:admin1_code":"14",
    "gn:asciiname":"Batubesaung",
    "gn:country_code":"ID",
    "gn:dem":14,
    "gn:feature_class":"P",
    "gn:feature_code":"PPL",
    "gn:name":"Batubesaung",
    "gn:population":0,
    "gn:timezone":"Asia/Makassar",
    "iso:country":"ID",
    "name:ind_x_preferred":[
        "Batubesaung"
    ],
    "wof:name":"Batubesaung",
    "wof:placetype":"locality"
},
  "geometry": {"coordinates":[117.1636,-0.3839],"type":"Point"}
}