{
  "type": "Feature",
  "properties": {
    "gn:admin1_code":"26",
    "gn:asciiname":"Sambirejo Timur Empat",
    "gn:country_code":"ID",
    "gn:dem":13,
    "gn:feature_class":"P",
    "gn:feature_code":"PPL",
    "gn:name":"Sambirejo Timur Empat",
    "gn:population":0,
    "gn:timezone":"Asia/Jakarta",
    "iso:country":"ID",
    "name:ind_x_preferred":[
        "Sambirejo Timur Empat"
    ],
    "name:und_x_variant":[
        "Sambirejo Timur 4"
    ],
    "wof:lang_x_official":[
        "ind"
    ],
    "wof:lang_x_spoken":[
        "ind",
        "eng"
    ],
    "wof:name":"Sambirejo Timur Empat",
    "wof:placetype":"locality"
},
  "geometry": {"coordinates":[98.7734,3.5941],"type":"Point"}
}