{
  "type": "Feature",
  "properties": {
    "gn:admin1_code":"30",
    "gn:asciiname":"Bojonggenteng Girang",
    "gn:country_code":"ID",
    "gn:dem":503,
    "gn:feature_class":"P",
    "gn:feature_code":"PPL",
    "gn:name":"Bojonggenteng Girang",
    "gn:population":0,
    "gn:timezone":"Asia/Jakarta",
    "iso:country":"ID",
    "name:ind_x_preferred":[
        "Bojonggenteng Girang"
    ],
    "wof:name":"Bojonggenteng Girang",
    "wof:placetype":"locality"
},
  "geometry": {"coordinates":[106.70638999999998,-6.8425],"type":"Point"}
}