{
  "type": "Feature",
  "properties": {
    "gn:admin1_code":"8",
    "gn:asciiname":"Sumbersoko Kidul",
    "gn:country_code":"ID",
    "gn:dem":65,
    "gn:feature_class":"P",
    "gn:feature_code":"PPL",
    "gn:name":"Sumbersoko Kidul",
    "gn:population":0,
    "gn:timezone":"Asia/Jakarta",
    "iso:country":"ID",
    "name:ind_x_preferred":[
        "Sumbersoko Kidul"
    ],
    "wof:name":"Sumbersoko Kidul",
    "wof:placetype":"locality"
},
  "geometry": {"coordinates":[113.0227,-7.763],"type":"Point"}
}