{
  "type": "Feature",
  "properties": {
    "gn:admin1_code":"1.0",
    "gn:asciiname":"Lanting",
    "gn:country_code":"ID",
    "gn:dem":11,
    "gn:feature_class":"P",
    "gn:feature_code":"PPL",
    "gn:name":"Lanting",
    "gn:population":0,
    "gn:timezone":"Asia/Jakarta",
    "iso:country":"ID",
    "name:ind_x_preferred":[
        "Lanting"
    ],
    "name:und_x_variant":[
        "Lanteng"
    ],
    "wof:name":"Lanting",
    "wof:placetype":"locality"
},
  "geometry": {"coordinates":[95.1575,5.6409],"type":"Point"}
}