{
  "type": "Feature",
  "properties": {
    "gn:admin1_code":"38.0",
    "gn:asciiname":"Marante",
    "gn:country_code":"ID",
    "gn:dem":811,
    "gn:feature_class":"P",
    "gn:feature_code":"PPL",
    "gn:name":"Marante",
    "gn:population":0,
    "gn:timezone":"Asia/Makassar",
    "iso:country":"ID",
    "name:ind_x_preferred":[
        "Marante"
    ],
    "wof:name":"Marante",
    "wof:placetype":"locality"
},
  "geometry": {"coordinates":[119.93129999999999,-2.9543],"type":"Point"}
}