{
  "type": "Feature",
  "properties": {
    "gn:admin1_code":"32.0",
    "gn:asciiname":"Tanjung Menang Ilir",
    "gn:country_code":"ID",
    "gn:dem":180,
    "gn:feature_class":"P",
    "gn:feature_code":"PPL",
    "gn:name":"Tanjung Menang Ilir",
    "gn:population":0,
    "gn:timezone":"Asia/Jakarta",
    "iso:country":"ID",
    "name:ind_x_preferred":[
        "Tanjung Menang Ilir"
    ],
    "wof:name":"Tanjung Menang Ilir",
    "wof:placetype":"locality"
},
  "geometry": {"coordinates":[103.91,-4.55207],"type":"Point"}
}