{
  "type": "Feature",
  "properties": {
    "gn:admin1_code":"26",
    "gn:asciiname":"Lumbanjulu Dua",
    "gn:country_code":"ID",
    "gn:dem":965,
    "gn:feature_class":"P",
    "gn:feature_code":"PPL",
    "gn:name":"Lumbanjulu Dua",
    "gn:population":0,
    "gn:timezone":"Asia/Jakarta",
    "iso:country":"ID",
    "name:ind_x_preferred":[
        "Lumbanjulu Dua"
    ],
    "name:und_x_variant":[
        "Lumbanjulu 2",
        "Lumbandjulu 2"
    ],
    "wof:lang_x_official":[
        "ind"
    ],
    "wof:lang_x_spoken":[
        "ind",
        "eng"
    ],
    "wof:name":"Lumbanjulu Dua",
    "wof:placetype":"locality"
},
  "geometry": {"coordinates":[99.11450000000001,2.5241],"type":"Point"}
}