{
  "type": "Feature",
  "properties": {
    "gn:admin1_code":"1",
    "gn:asciiname":"Terusan-hulu Dua",
    "gn:country_code":"ID",
    "gn:dem":37,
    "gn:feature_class":"P",
    "gn:feature_code":"PPL",
    "gn:name":"Terusan-hulu Dua",
    "gn:population":0,
    "gn:timezone":"Asia/Jakarta",
    "iso:country":"ID",
    "name:ind_x_preferred":[
        "Terusan-hulu Dua"
    ],
    "name:und_x_variant":[
        "Terusan-hulu 2"
    ],
    "wof:name":"Terusan-hulu Dua",
    "wof:placetype":"locality"
},
  "geometry": {"coordinates":[99.53830000000001,2.8523],"type":"Point"}
}