{
  "type": "Feature",
  "properties": {
    "gn:admin1_code":"3.0",
    "gn:asciiname":"Tanjungdalam",
    "gn:country_code":"ID",
    "gn:dem":629,
    "gn:feature_class":"P",
    "gn:feature_code":"PPL",
    "gn:name":"Tanjungdalam",
    "gn:population":0,
    "gn:timezone":"Asia/Jakarta",
    "iso:country":"ID",
    "name:ind_x_preferred":[
        "Tanjungdalam"
    ],
    "wof:name":"Tanjungdalam",
    "wof:placetype":"locality"
},
  "geometry": {"coordinates":[102.47709999999999,-3.4996],"type":"Point"}
}