{
  "type": "Feature",
  "properties": {
    "gn:admin1_code":"30.0",
    "gn:asciiname":"Sisicai",
    "gn:country_code":"ID",
    "gn:dem":715,
    "gn:feature_class":"P",
    "gn:feature_code":"PPL",
    "gn:name":"Sisicai",
    "gn:population":0,
    "gn:timezone":"Asia/Jakarta",
    "iso:country":"ID",
    "name:ind_x_preferred":[
        "Sisicai"
    ],
    "name:und_x_variant":[
        "Sititjai"
    ],
    "wof:name":"Sisicai",
    "wof:placetype":"locality"
},
  "geometry": {"coordinates":[107.90730000000001,-7.169],"type":"Point"}
}