{
  "type": "Feature",
  "properties": {
    "gn:admin1_code":"1.0",
    "gn:asciiname":"Matangnibung",
    "gn:country_code":"ID",
    "gn:dem":1,
    "gn:feature_class":"P",
    "gn:feature_code":"PPL",
    "gn:name":"Matangnibung",
    "gn:population":0,
    "gn:timezone":"Asia/Jakarta",
    "iso:country":"ID",
    "name:ind_x_preferred":[
        "Matangnibung"
    ],
    "name:und_x_variant":[
        "Matangnibong",
        "Matanibung"
    ],
    "wof:name":"Matangnibung",
    "wof:placetype":"locality"
},
  "geometry": {"coordinates":[97.956,4.6067],"type":"Point"}
}