{
  "type": "Feature",
  "properties": {
    "gn:admin1_code":"0.0",
    "gn:asciiname":"Anuwe",
    "gn:cc2":"ID",
    "gn:country_code":"ID",
    "gn:dem":28,
    "gn:feature_class":"P",
    "gn:feature_code":"PPL",
    "gn:name":"Anuwe",
    "gn:population":0,
    "gn:timezone":"Asia/Jayapura",
    "iso:country":"ID",
    "name:und_x_variant":[
        "Anoewe",
        "Anuwe"
    ],
    "wof:name":"Anuwe",
    "wof:placetype":"locality"
},
  "geometry": {"coordinates":[137.16666999999998,-4.73333],"type":"Point"}
}