{
  "type": "Feature",
  "properties": {
    "gn:admin1_code":"8.0",
    "gn:asciiname":"Pengulubanyu",
    "gn:country_code":"ID",
    "gn:dem":464,
    "gn:feature_class":"P",
    "gn:feature_code":"PPL",
    "gn:name":"Pengulubanyu",
    "gn:population":0,
    "gn:timezone":"Asia/Jakarta",
    "iso:country":"ID",
    "name:ind_x_preferred":[
        "Pengulubanyu"
    ],
    "wof:name":"Pengulubanyu",
    "wof:placetype":"locality"
},
  "geometry": {"coordinates":[112.4169,-7.6591],"type":"Point"}
}