{
  "type": "Feature",
  "properties": {
    "gn:admin1_code":"30",
    "gn:asciiname":"Gadog",
    "gn:country_code":"ID",
    "gn:dem":517,
    "gn:feature_class":"P",
    "gn:feature_code":"PPL",
    "gn:name":"Gadog",
    "gn:population":0,
    "gn:timezone":"Asia/Jakarta",
    "iso:country":"ID",
    "name:ind_x_preferred":[
        "Gadog"
    ],
    "wof:name":"Gadog",
    "wof:placetype":"locality"
},
  "geometry": {"coordinates":[106.79611,-6.68389],"type":"Point"}
}