{
  "type": "Feature",
  "properties": {
    "gn:admin1_code":"7.0",
    "gn:asciiname":"Klesem",
    "gn:country_code":"ID",
    "gn:dem":953,
    "gn:feature_class":"P",
    "gn:feature_code":"PPL",
    "gn:name":"Klesem",
    "gn:population":0,
    "gn:timezone":"Asia/Jakarta",
    "iso:country":"ID",
    "wof:name":"Klesem",
    "wof:placetype":"locality"
},
  "geometry": {"coordinates":[110.1425,-7.40444],"type":"Point"}
}