{
  "type": "Feature",
  "properties": {
    "gn:admin1_code":"7.0",
    "gn:asciiname":"Cirungkung",
    "gn:country_code":"ID",
    "gn:dem":18,
    "gn:feature_class":"P",
    "gn:feature_code":"PPL",
    "gn:name":"Cirungkung",
    "gn:population":0,
    "gn:timezone":"Asia/Jakarta",
    "iso:country":"ID",
    "name:ind_x_preferred":[
        "Cirungkung"
    ],
    "wof:name":"Cirungkung",
    "wof:placetype":"locality"
},
  "geometry": {"coordinates":[109.20222,-7.67417],"type":"Point"}
}