{
  "type": "Feature",
  "properties": {
    "gn:admin1_code":"30",
    "gn:asciiname":"Karangasem",
    "gn:country_code":"ID",
    "gn:dem":108,
    "gn:feature_class":"P",
    "gn:feature_code":"PPL",
    "gn:name":"Karangasem",
    "gn:population":0,
    "gn:timezone":"Asia/Jakarta",
    "iso:country":"ID",
    "name:ceb_x_preferred":[
        "Karangasem"
    ],
    "name:ind_x_preferred":[
        "Karangasem"
    ],
    "name:nld_x_preferred":[
        "Karangasem"
    ],
    "name:rus_x_preferred":[
        "\u041a\u0430\u0440\u0430\u043d\u0433\u0430\u0441\u0435\u043c"
    ],
    "name:swe_x_preferred":[
        "Karangasem"
    ],
    "wof:lang_x_official":[
        "ind"
    ],
    "wof:lang_x_spoken":[
        "ind",
        "eng"
    ],
    "wof:name":"Karangasem",
    "wof:placetype":"locality"
},
  "geometry": {"coordinates":[108.44222000000001,-6.7625],"type":"Point"}
}