{
  "type": "Feature",
  "properties": {
    "gn:admin1_code":"30.0",
    "gn:asciiname":"Desa Cilangkap",
    "gn:country_code":"ID",
    "gn:dem":269,
    "gn:feature_class":"P",
    "gn:feature_code":"PPLA4",
    "gn:name":"Desa Cilangkap",
    "gn:population":0,
    "gn:timezone":"Asia/Jakarta",
    "iso:country":"ID",
    "name:ind_x_preferred":[
        "Desa Cilangkap"
    ],
    "name:und_x_variant":[
        "Tjilangkap Satu"
    ],
    "wof:lang_x_official":[
        "ind"
    ],
    "wof:lang_x_spoken":[
        "ind",
        "eng"
    ],
    "wof:name":"Desa Cilangkap",
    "wof:placetype":"locality"
},
  "geometry": {"coordinates":[108.33450000000001,-7.3616],"type":"Point"}
}