{
  "type": "Feature",
  "properties": {
    "gn:admin1_code":"7.0",
    "gn:asciiname":"Jambean",
    "gn:country_code":"ID",
    "gn:dem":477,
    "gn:feature_class":"P",
    "gn:feature_code":"PPL",
    "gn:name":"Jambean",
    "gn:population":0,
    "gn:timezone":"Asia/Jakarta",
    "iso:country":"ID",
    "wof:name":"Jambean",
    "wof:placetype":"locality"
},
  "geometry": {"coordinates":[110.10306,-7.57028],"type":"Point"}
}