{
  "type": "Feature",
  "properties": {
    "gn:admin1_code":"0.0",
    "gn:asciiname":"Telukmerbau",
    "gn:cc2":"ID",
    "gn:country_code":"ID",
    "gn:dem":7,
    "gn:feature_class":"P",
    "gn:feature_code":"PPL",
    "gn:name":"Telukmerbau",
    "gn:population":0,
    "gn:timezone":"Asia/Jakarta",
    "iso:country":"ID",
    "name:und_x_variant":[
        "Teloekmerbau",
        "Telukmerbau"
    ],
    "wof:name":"Telukmerbau",
    "wof:placetype":"locality"
},
  "geometry": {"coordinates":[100.63333,2.06667],"type":"Point"}
}