{
  "type": "Feature",
  "properties": {
    "gn:admin1_code":"30.0",
    "gn:asciiname":"Cimunar",
    "gn:country_code":"ID",
    "gn:dem":356,
    "gn:feature_class":"P",
    "gn:feature_code":"PPL",
    "gn:name":"Cimunar",
    "gn:population":0,
    "gn:timezone":"Asia/Jakarta",
    "iso:country":"ID",
    "name:ind_x_preferred":[
        "Cimunar"
    ],
    "wof:name":"Cimunar",
    "wof:placetype":"locality"
},
  "geometry": {"coordinates":[107.61709999999999,-7.4721],"type":"Point"}
}