{
  "type": "Feature",
  "properties": {
    "gn:admin1_code":"7.0",
    "gn:asciiname":"Penjalin",
    "gn:country_code":"ID",
    "gn:dem":115,
    "gn:feature_class":"P",
    "gn:feature_code":"PPL",
    "gn:name":"Penjalin",
    "gn:population":0,
    "gn:timezone":"Asia/Jakarta",
    "iso:country":"ID",
    "name:ind_x_preferred":[
        "Penjalin"
    ],
    "wof:name":"Penjalin",
    "wof:placetype":"locality"
},
  "geometry": {"coordinates":[109.43389000000001,-7.36722],"type":"Point"}
}