{
  "type": "Feature",
  "properties": {
    "gn:admin1_code":"36.0",
    "gn:asciiname":"Iweka Temare",
    "gn:country_code":"ID",
    "gn:dem":35,
    "gn:feature_class":"P",
    "gn:feature_code":"PPL",
    "gn:name":"Iweka Temare",
    "gn:population":0,
    "gn:timezone":"Asia/Jayapura",
    "iso:country":"ID",
    "name:ind_x_preferred":[
        "Iweka Temare"
    ],
    "name:und_x_variant":[
        "Iweka",
        "Iweka-Temare"
    ],
    "wof:lang_x_official":[
        "ind"
    ],
    "wof:lang_x_spoken":[
        "ind",
        "eng"
    ],
    "wof:name":"Iweka Temare",
    "wof:placetype":"locality"
},
  "geometry": {"coordinates":[136.6935,-4.5279],"type":"Point"}
}