{
  "type": "Feature",
  "properties": {
    "gn:admin1_code":"18",
    "gn:asciiname":"Lui",
    "gn:country_code":"ID",
    "gn:dem":537,
    "gn:feature_class":"P",
    "gn:feature_code":"PPL",
    "gn:name":"Lui",
    "gn:population":0,
    "gn:timezone":"Asia/Makassar",
    "iso:country":"ID",
    "name:ind_x_preferred":[
        "Lui"
    ],
    "wof:name":"Lui",
    "wof:placetype":"locality"
},
  "geometry": {"coordinates":[120.68000000000001,-8.4199],"type":"Point"}
}