{
  "type": "Feature",
  "properties": {
    "gn:admin1_code":"8",
    "gn:asciiname":"Geger",
    "gn:country_code":"ID",
    "gn:dem":38,
    "gn:feature_class":"P",
    "gn:feature_code":"PPL",
    "gn:name":"Geger",
    "gn:population":0,
    "gn:timezone":"Asia/Jakarta",
    "iso:country":"ID",
    "name:ind_x_preferred":[
        "Geger"
    ],
    "name:spa_x_preferred":[
        "Geger"
    ],
    "wof:name":"Geger",
    "wof:placetype":"locality"
},
  "geometry": {"coordinates":[112.4132,-7.2157],"type":"Point"}
}