{
  "type": "Feature",
  "properties": {
    "gn:admin1_code":"21",
    "gn:asciiname":"Tingkeao",
    "gn:country_code":"ID",
    "gn:dem":53,
    "gn:feature_class":"P",
    "gn:feature_code":"PPL",
    "gn:name":"Tingkeao",
    "gn:population":0,
    "gn:timezone":"Asia/Makassar",
    "iso:country":"ID",
    "name:ind_x_preferred":[
        "Tingkeao"
    ],
    "wof:name":"Tingkeao",
    "wof:placetype":"locality"
},
  "geometry": {"coordinates":[121.2409,-2.1451],"type":"Point"}
}