{
  "type": "Feature",
  "properties": {
    "gn:admin1_code":"8.0",
    "gn:asciiname":"Gadu",
    "gn:country_code":"ID",
    "gn:dem":684,
    "gn:feature_class":"P",
    "gn:feature_code":"PPL",
    "gn:name":"Gadu",
    "gn:population":0,
    "gn:timezone":"Asia/Jakarta",
    "iso:country":"ID",
    "name:ind_x_preferred":[
        "Gadu"
    ],
    "wof:name":"Gadu",
    "wof:placetype":"locality"
},
  "geometry": {"coordinates":[112.3768,-7.8374],"type":"Point"}
}