{
  "type": "Feature",
  "properties": {
    "gn:admin1_code":"17",
    "gn:asciiname":"Timbabune",
    "gn:country_code":"ID",
    "gn:dem":543,
    "gn:feature_class":"P",
    "gn:feature_code":"PPL",
    "gn:name":"Timbabune",
    "gn:population":0,
    "gn:timezone":"Asia/Makassar",
    "iso:country":"ID",
    "name:ind_x_preferred":[
        "Timbabune"
    ],
    "wof:name":"Timbabune",
    "wof:placetype":"locality"
},
  "geometry": {"coordinates":[116.4888,-8.538],"type":"Point"}
}