{
  "type": "Feature",
  "properties": {
    "gn:admin1_code":"18.0",
    "gn:asciiname":"Winumuru",
    "gn:country_code":"ID",
    "gn:dem":664,
    "gn:feature_class":"P",
    "gn:feature_code":"PPL",
    "gn:name":"Winumuru",
    "gn:population":0,
    "gn:timezone":"Asia/Makassar",
    "iso:country":"ID",
    "name:ind_x_preferred":[
        "Winumuru"
    ],
    "wof:name":"Winumuru",
    "wof:placetype":"locality"
},
  "geometry": {"coordinates":[120.3291,-10.073],"type":"Point"}
}