{
  "type": "Feature",
  "properties": {
    "gn:admin1_code":"33",
    "gn:asciiname":"Pasirkadu",
    "gn:country_code":"ID",
    "gn:dem":20,
    "gn:feature_class":"P",
    "gn:feature_code":"PPL",
    "gn:name":"Pasirkadu",
    "gn:population":0,
    "gn:timezone":"Asia/Jakarta",
    "iso:country":"ID",
    "name:ind_x_preferred":[
        "Pasirkadu"
    ],
    "wof:name":"Pasirkadu",
    "wof:placetype":"locality"
},
  "geometry": {"coordinates":[106.27760000000001,-6.2719],"type":"Point"}
}