{
  "type": "Feature",
  "properties": {
    "gn:admin1_code":"30.0",
    "gn:asciiname":"Datarhuni",
    "gn:country_code":"ID",
    "gn:dem":623,
    "gn:feature_class":"P",
    "gn:feature_code":"PPL",
    "gn:name":"Datarhuni",
    "gn:population":0,
    "gn:timezone":"Asia/Jakarta",
    "iso:country":"ID",
    "name:ind_x_preferred":[
        "Datarhuni"
    ],
    "wof:name":"Datarhuni",
    "wof:placetype":"locality"
},
  "geometry": {"coordinates":[107.4922,-7.314],"type":"Point"}
}