{
  "type": "Feature",
  "properties": {
    "gn:admin1_code":"15.0",
    "gn:asciiname":"Taman Sari",
    "gn:country_code":"ID",
    "gn:dem":178,
    "gn:feature_class":"P",
    "gn:feature_code":"PPL",
    "gn:name":"Taman Sari",
    "gn:population":0,
    "gn:timezone":"Asia/Jakarta",
    "iso:country":"ID",
    "name:ind_x_preferred":[
        "Taman Sari"
    ],
    "name:nld_x_preferred":[
        "Taman Sari"
    ],
    "wof:name":"Taman Sari",
    "wof:placetype":"locality"
},
  "geometry": {"coordinates":[105.14337999999999,-5.36406],"type":"Point"}
}