{
  "type": "Feature",
  "properties": {
    "gn:admin1_code":"18",
    "gn:asciiname":"Wolosoko",
    "gn:country_code":"ID",
    "gn:dem":696,
    "gn:feature_class":"P",
    "gn:feature_code":"PPL",
    "gn:name":"Wolosoko",
    "gn:population":0,
    "gn:timezone":"Asia/Makassar",
    "iso:country":"ID",
    "name:ind_x_preferred":[
        "Wolosoko"
    ],
    "wof:name":"Wolosoko",
    "wof:placetype":"locality"
},
  "geometry": {"coordinates":[121.8441,-8.8039],"type":"Point"}
}