{
  "type": "Feature",
  "properties": {
    "gn:admin1_code":"8",
    "gn:asciiname":"Gunting Dua",
    "gn:country_code":"ID",
    "gn:dem":466,
    "gn:feature_class":"P",
    "gn:feature_code":"PPL",
    "gn:name":"Gunting Dua",
    "gn:population":0,
    "gn:timezone":"Asia/Jakarta",
    "iso:country":"ID",
    "name:ind_x_preferred":[
        "Gunting Dua"
    ],
    "wof:name":"Gunting Dua",
    "wof:placetype":"locality"
},
  "geometry": {"coordinates":[111.16611,-7.51889],"type":"Point"}
}