{
  "type": "Feature",
  "properties": {
    "gn:admin1_code":"1",
    "gn:asciiname":"Ulaktanah-merah",
    "gn:country_code":"ID",
    "gn:dem":37,
    "gn:feature_class":"P",
    "gn:feature_code":"PPL",
    "gn:name":"Ulaktanah-merah",
    "gn:population":0,
    "gn:timezone":"Asia/Jakarta",
    "iso:country":"ID",
    "name:ind_x_preferred":[
        "Ulaktanah-merah"
    ],
    "wof:name":"Ulaktanah-merah",
    "wof:placetype":"locality"
},
  "geometry": {"coordinates":[99.5403,2.9032],"type":"Point"}
}