{
  "type": "Feature",
  "properties": {
    "gn:admin1_code":"24.0",
    "gn:asciiname":"Mandahiling",
    "gn:country_code":"ID",
    "gn:dem":237,
    "gn:feature_class":"P",
    "gn:feature_code":"PPL",
    "gn:name":"Mandahiling",
    "gn:population":0,
    "gn:timezone":"Asia/Jakarta",
    "iso:country":"ID",
    "name:ind_x_preferred":[
        "Mandahiling"
    ],
    "name:und_x_variant":[
        "Mandailing"
    ],
    "wof:lang_x_official":[
        "ind"
    ],
    "wof:lang_x_spoken":[
        "ind",
        "eng"
    ],
    "wof:name":"Mandahiling",
    "wof:placetype":"locality"
},
  "geometry": {"coordinates":[100.73111,-0.62881],"type":"Point"}
}