{
  "type": "Feature",
  "properties": {
    "gn:admin1_code":"7",
    "gn:asciiname":"Penjalan Timur",
    "gn:country_code":"ID",
    "gn:dem":3,
    "gn:feature_class":"P",
    "gn:feature_code":"PPL",
    "gn:name":"Penjalan Timur",
    "gn:population":0,
    "gn:timezone":"Asia/Jakarta",
    "iso:country":"ID",
    "name:ind_x_preferred":[
        "Penjalan Timur"
    ],
    "wof:name":"Penjalan Timur",
    "wof:placetype":"locality"
},
  "geometry": {"coordinates":[109.14790000000001,-6.8523],"type":"Point"}
}