{
  "type": "Feature",
  "properties": {
    "gn:admin1_code":"18",
    "gn:asciiname":"Golomowa",
    "gn:country_code":"ID",
    "gn:dem":958,
    "gn:feature_class":"P",
    "gn:feature_code":"PPL",
    "gn:name":"Golomowa",
    "gn:population":0,
    "gn:timezone":"Asia/Makassar",
    "iso:country":"ID",
    "name:ind_x_preferred":[
        "Golomowa"
    ],
    "wof:name":"Golomowa",
    "wof:placetype":"locality"
},
  "geometry": {"coordinates":[120.6743,-8.5031],"type":"Point"}
}