{
  "type": "Feature",
  "properties": {
    "gn:admin1_code":"11.0",
    "gn:asciiname":"Toho",
    "gn:country_code":"ID",
    "gn:dem":26,
    "gn:feature_class":"P",
    "gn:feature_code":"PPLA3",
    "gn:name":"Toho",
    "gn:population":0,
    "gn:timezone":"Asia/Pontianak",
    "iso:country":"ID",
    "name:ind_x_preferred":[
        "Toho"
    ],
    "wof:name":"Toho",
    "wof:placetype":"locality"
},
  "geometry": {"coordinates":[109.22001000000002,0.41795],"type":"Point"}
}