{
  "type": "Feature",
  "properties": {
    "gn:admin1_code":"38",
    "gn:asciiname":"Laponrong",
    "gn:country_code":"ID",
    "gn:dem":68,
    "gn:feature_class":"P",
    "gn:feature_code":"PPL",
    "gn:name":"Laponrong",
    "gn:population":0,
    "gn:timezone":"Asia/Makassar",
    "iso:country":"ID",
    "name:ind_x_preferred":[
        "Laponrong"
    ],
    "wof:name":"Laponrong",
    "wof:placetype":"locality"
},
  "geometry": {"coordinates":[120.1533,-4.3382],"type":"Point"}
}