{
  "type": "Feature",
  "properties": {
    "gn:admin1_code":"41.0",
    "gn:asciiname":"Binuang",
    "gn:country_code":"ID",
    "gn:dem":7,
    "gn:feature_class":"P",
    "gn:feature_code":"PPL",
    "gn:name":"Binuang",
    "gn:population":0,
    "gn:timezone":"Asia/Makassar",
    "iso:country":"ID",
    "name:ind_x_preferred":[
        "Binuang"
    ],
    "name:und_x_variant":[
        "Binoeang",
        "Binuang"
    ],
    "wof:name":"Binuang",
    "wof:placetype":"locality"
},
  "geometry": {"coordinates":[119.41240000000001,-3.4623],"type":"Point"}
}