{
  "type": "Feature",
  "properties": {
    "gn:admin1_code":"15.0",
    "gn:asciiname":"Umbulan Kibang Tua",
    "gn:country_code":"ID",
    "gn:dem":40,
    "gn:feature_class":"P",
    "gn:feature_code":"PPL",
    "gn:name":"Umbulan Kibang Tua",
    "gn:population":0,
    "gn:timezone":"Asia/Jakarta",
    "iso:country":"ID",
    "name:ind_x_preferred":[
        "Umbulan Kibang Tua"
    ],
    "name:ind_x_variant":[
        "Umbulankibangtua",
        "Oemboelan Kibang Toe\u014f"
    ],
    "wof:lang_x_official":[
        "ind"
    ],
    "wof:lang_x_spoken":[
        "ind",
        "eng"
    ],
    "wof:name":"Umbulan Kibang Tua",
    "wof:placetype":"locality"
},
  "geometry": {"coordinates":[105.11020000000001,-4.48287],"type":"Point"}
}