{
  "type": "Feature",
  "properties": {
    "gn:admin1_code":"18",
    "gn:asciiname":"Laindarohe",
    "gn:country_code":"ID",
    "gn:dem":536,
    "gn:feature_class":"P",
    "gn:feature_code":"PPL",
    "gn:name":"Laindarohe",
    "gn:population":0,
    "gn:timezone":"Asia/Makassar",
    "iso:country":"ID",
    "name:ind_x_preferred":[
        "Laindarohe"
    ],
    "wof:name":"Laindarohe",
    "wof:placetype":"locality"
},
  "geometry": {"coordinates":[119.9145,-9.6499],"type":"Point"}
}