{
  "type": "Feature",
  "properties": {
    "gn:admin1_code":"2",
    "gn:asciiname":"Banjar Ambengankehon",
    "gn:country_code":"ID",
    "gn:dem":381,
    "gn:feature_class":"P",
    "gn:feature_code":"PPL",
    "gn:name":"Banjar Ambengankehon",
    "gn:population":0,
    "gn:timezone":"Asia/Makassar",
    "iso:country":"ID",
    "name:ind_x_preferred":[
        "Banjar Ambengankehon"
    ],
    "wof:name":"Banjar Ambengankehon",
    "wof:placetype":"locality"
},
  "geometry": {"coordinates":[115.12569999999999,-8.1776],"type":"Point"}
}