{
  "type": "Feature",
  "properties": {
    "gn:admin1_code":"26",
    "gn:asciiname":"Permandian",
    "gn:country_code":"ID",
    "gn:dem":406,
    "gn:feature_class":"P",
    "gn:feature_code":"PPL",
    "gn:name":"Permandian",
    "gn:population":0,
    "gn:timezone":"Asia/Jakarta",
    "iso:country":"ID",
    "name:ind_x_preferred":[
        "Permandian"
    ],
    "wof:name":"Permandian",
    "wof:placetype":"locality"
},
  "geometry": {"coordinates":[98.6039,3.3179],"type":"Point"}
}