{
  "type": "Feature",
  "properties": {
    "gn:admin1_code":"30",
    "gn:asciiname":"Kalimati",
    "gn:country_code":"ID",
    "gn:dem":12,
    "gn:feature_class":"P",
    "gn:feature_code":"PPL",
    "gn:name":"Kalimati",
    "gn:population":0,
    "gn:timezone":"Asia/Jakarta",
    "iso:country":"ID",
    "name:ind_x_preferred":[
        "Kalimati"
    ],
    "wof:name":"Kalimati",
    "wof:placetype":"locality"
},
  "geometry": {"coordinates":[107.13388999999999,-6.05333],"type":"Point"}
}