{
  "type": "Feature",
  "properties": {
    "gn:admin1_code":"7",
    "gn:asciiname":"Nyangkringan",
    "gn:country_code":"ID",
    "gn:dem":4,
    "gn:feature_class":"P",
    "gn:feature_code":"PPL",
    "gn:name":"Nyangkringan",
    "gn:population":0,
    "gn:timezone":"Asia/Jakarta",
    "iso:country":"ID",
    "name:ind_x_preferred":[
        "Nyangkringan"
    ],
    "wof:name":"Nyangkringan",
    "wof:placetype":"locality"
},
  "geometry": {"coordinates":[110.479,-6.9407],"type":"Point"}
}