{
  "type": "Feature",
  "properties": {
    "gn:admin1_code":"17.0",
    "gn:asciiname":"Nandus",
    "gn:country_code":"ID",
    "gn:dem":13,
    "gn:feature_class":"P",
    "gn:feature_code":"PPL",
    "gn:name":"Nandus",
    "gn:population":0,
    "gn:timezone":"Asia/Makassar",
    "iso:country":"ID",
    "name:cat_x_preferred":[
        "Nandus"
    ],
    "name:ceb_x_preferred":[
        "Nandus"
    ],
    "name:deu_x_preferred":[
        "Nanderbarsche"
    ],
    "name:ind_x_preferred":[
        "Nandus"
    ],
    "name:nld_x_preferred":[
        "Nandus"
    ],
    "name:pol_x_preferred":[
        "Nandus"
    ],
    "name:swe_x_preferred":[
        "Nandus"
    ],
    "name:tha_x_preferred":[
        "\u0e1b\u0e25\u0e32\u0e41\u0e19\u0e19\u0e14\u0e31\u0e2a"
    ],
    "name:ukr_x_preferred":[
        "\u041d\u0430\u043d\u0434\u0443\u0441"
    ],
    "name:war_x_preferred":[
        "Nandus"
    ],
    "wof:name":"Nandus",
    "wof:placetype":"locality"
},
  "geometry": {"coordinates":[116.334,-8.8878],"type":"Point"}
}