{
  "type": "Feature",
  "properties": {
    "gn:admin1_code":"8",
    "gn:asciiname":"Gambiran Kulon",
    "gn:country_code":"ID",
    "gn:dem":229,
    "gn:feature_class":"P",
    "gn:feature_code":"PPL",
    "gn:name":"Gambiran Kulon",
    "gn:population":0,
    "gn:timezone":"Asia/Jakarta",
    "iso:country":"ID",
    "name:ind_x_preferred":[
        "Gambiran Kulon"
    ],
    "wof:lang_x_official":[
        "ind"
    ],
    "wof:lang_x_spoken":[
        "ind",
        "eng"
    ],
    "wof:name":"Gambiran Kulon",
    "wof:placetype":"locality"
},
  "geometry": {"coordinates":[113.8075,-8.1536],"type":"Point"}
}