{
  "type": "Feature",
  "properties": {
    "gn:admin1_code":"38",
    "gn:asciiname":"Parangluara",
    "gn:country_code":"ID",
    "gn:dem":34,
    "gn:feature_class":"P",
    "gn:feature_code":"PPL",
    "gn:name":"Parangluara",
    "gn:population":0,
    "gn:timezone":"Asia/Makassar",
    "iso:country":"ID",
    "name:ind_x_preferred":[
        "Parangluara"
    ],
    "wof:name":"Parangluara",
    "wof:placetype":"locality"
},
  "geometry": {"coordinates":[119.5966,-5.5584],"type":"Point"}
}