{
  "type": "Feature",
  "properties": {
    "gn:admin1_code":"30.0",
    "gn:asciiname":"Cipatat Dua",
    "gn:country_code":"ID",
    "gn:dem":598,
    "gn:feature_class":"P",
    "gn:feature_code":"PPL",
    "gn:name":"Cipatat Dua",
    "gn:population":0,
    "gn:timezone":"Asia/Jakarta",
    "iso:country":"ID",
    "name:ind_x_preferred":[
        "Cipatat Dua"
    ],
    "wof:name":"Cipatat Dua",
    "wof:placetype":"locality"
},
  "geometry": {"coordinates":[106.45699999999999,-6.8811],"type":"Point"}
}