{
  "type": "Feature",
  "properties": {
    "gn:admin1_code":"1",
    "gn:asciiname":"Blangara",
    "gn:country_code":"ID",
    "gn:dem":1410,
    "gn:feature_class":"P",
    "gn:feature_code":"PPL",
    "gn:name":"Blangara",
    "gn:population":0,
    "gn:timezone":"Asia/Jakarta",
    "iso:country":"ID",
    "name:ind_x_preferred":[
        "Blangara"
    ],
    "wof:name":"Blangara",
    "wof:placetype":"locality"
},
  "geometry": {"coordinates":[96.8955,4.7367],"type":"Point"}
}