{
  "type": "Feature",
  "properties": {
    "gn:country":"ID",
    "gn:fcode":"PPL",
    "gn:pop":0,
    "iso:country":"ID",
    "name:ind_x_preferred":[
        "Lumban Julu"
    ],
    "qs:name":"Lumban Julu",
    "qs:name_adm0":"Indonesia",
    "qs:name_adm1":"Sumatera Utara",
    "qs:photos_9r":0,
    "qs:photos_sr":0,
    "qs:placetype":"Town",
    "qs:pop_sr":"0",
    "wof:name":"Lumban Julu",
    "wof:placetype":"locality",
    "wof:population":0
},
  "geometry": {"coordinates":[99.06829999999999,2.8203],"type":"Point"}
}