{
  "type": "Feature",
  "properties": {
    "gn:admin1_code":"7.0",
    "gn:asciiname":"Klapasawit",
    "gn:country_code":"ID",
    "gn:dem":39,
    "gn:feature_class":"P",
    "gn:feature_code":"PPL",
    "gn:name":"Klapasawit",
    "gn:population":0,
    "gn:timezone":"Asia/Jakarta",
    "iso:country":"ID",
    "name:ind_x_preferred":[
        "Klapasawit"
    ],
    "wof:name":"Klapasawit",
    "wof:placetype":"locality"
},
  "geometry": {"coordinates":[109.66167,-7.58861],"type":"Point"}
}