{
  "type": "Feature",
  "properties": {
    "gn:admin1_code":"18",
    "gn:asciiname":"Lando",
    "gn:country_code":"ID",
    "gn:dem":941,
    "gn:feature_class":"P",
    "gn:feature_code":"PPL",
    "gn:name":"Lando",
    "gn:population":0,
    "gn:timezone":"Asia/Makassar",
    "iso:country":"ID",
    "name:ceb_x_preferred":[
        "Lando"
    ],
    "name:deu_x_preferred":[
        "Lando"
    ],
    "name:fra_x_preferred":[
        "Lando"
    ],
    "name:heb_x_preferred":[
        "\u05dc\u05e0\u05d3\u05d5"
    ],
    "name:ind_x_preferred":[
        "Lando"
    ],
    "name:ita_x_preferred":[
        "Lando"
    ],
    "name:rus_x_preferred":[
        "\u041b\u0430\u043d\u0434\u043e"
    ],
    "name:swe_x_preferred":[
        "Lando"
    ],
    "name:ukr_x_preferred":[
        "\u041b\u0430\u043d\u0434\u043e"
    ],
    "name:zho_x_preferred":[
        "\u534a\u655e\u7bf7\u8eca"
    ],
    "wof:lang_x_official":[
        "ind"
    ],
    "wof:lang_x_spoken":[
        "ind",
        "eng"
    ],
    "wof:name":"Lando",
    "wof:placetype":"locality"
},
  "geometry": {"coordinates":[120.7865,-8.6086],"type":"Point"}
}