{
  "type": "Feature",
  "properties": {
    "gn:admin1_code":"18",
    "gn:asciiname":"Lando",
    "gn:country_code":"ID",
    "gn:dem":941,
    "gn:feature_class":"P",
    "gn:feature_code":"PPL",
    "gn:name":"Lando",
    "gn:population":0,
    "gn:timezone":"Asia/Makassar",
    "iso:country":"ID",
    "name:ind_x_preferred":[
        "Lando"
    ],
    "wof:name":"Lando",
    "wof:placetype":"locality"
},
  "geometry": {"coordinates":[120.7865,-8.6086],"type":"Point"}
}