{
  "type": "Feature",
  "properties": {
    "gn:admin1_code":"7.0",
    "gn:asciiname":"Bojanegara",
    "gn:country_code":"ID",
    "gn:dem":35,
    "gn:feature_class":"P",
    "gn:feature_code":"PPL",
    "gn:name":"Bojanegara",
    "gn:population":0,
    "gn:timezone":"Asia/Jakarta",
    "iso:country":"ID",
    "name:ind_x_preferred":[
        "Bojanegara"
    ],
    "wof:name":"Bojanegara",
    "wof:placetype":"locality"
},
  "geometry": {"coordinates":[108.89361,-7.45194],"type":"Point"}
}