{
  "type": "Feature",
  "properties": {
    "gn:admin1_code":"11.0",
    "gn:asciiname":"Arai",
    "gn:country_code":"ID",
    "gn:dem":89,
    "gn:feature_class":"P",
    "gn:feature_code":"PPL",
    "gn:name":"Arai",
    "gn:population":0,
    "gn:timezone":"Asia/Pontianak",
    "iso:country":"ID",
    "name:deu_x_preferred":[
        "Arai"
    ],
    "name:fra_x_preferred":[
        "Arai"
    ],
    "name:ind_x_preferred":[
        "Arai"
    ],
    "name:ita_x_preferred":[
        "Arai"
    ],
    "name:kor_x_preferred":[
        "\uc544\ub77c\uc774"
    ],
    "name:mlg_x_preferred":[
        "Arai"
    ],
    "name:rus_x_preferred":[
        "\u0410\u0440\u0430\u0438"
    ],
    "name:spa_x_preferred":[
        "Arai"
    ],
    "name:swe_x_preferred":[
        "Arai"
    ],
    "name:ukr_x_preferred":[
        "\u0410\u0440\u0430\u0457"
    ],
    "wof:lang_x_official":[
        "ind"
    ],
    "wof:lang_x_spoken":[
        "ind",
        "eng"
    ],
    "wof:name":"Arai",
    "wof:placetype":"locality"
},
  "geometry": {"coordinates":[111.28464,-0.31839],"type":"Point"}
}