{
  "type": "Feature",
  "properties": {
    "gn:admin1_code":"30.0",
    "gn:asciiname":"Cisandag",
    "gn:country_code":"ID",
    "gn:dem":439,
    "gn:feature_class":"P",
    "gn:feature_code":"PPL",
    "gn:name":"Cisandag",
    "gn:population":0,
    "gn:timezone":"Asia/Jakarta",
    "iso:country":"ID",
    "name:ind_x_preferred":[
        "Cisandag"
    ],
    "name:und_x_variant":[
        "Tjisanda"
    ],
    "wof:name":"Cisandag",
    "wof:placetype":"locality"
},
  "geometry": {"coordinates":[108.5917,-7.0681],"type":"Point"}
}