{
  "type": "Feature",
  "properties": {
    "gn:admin1_code":"8.0",
    "gn:asciiname":"Soco",
    "gn:country_code":"ID",
    "gn:dem":63,
    "gn:feature_class":"P",
    "gn:feature_code":"PPL",
    "gn:name":"Soco",
    "gn:population":0,
    "gn:timezone":"Asia/Jakarta",
    "iso:country":"ID",
    "name:ceb_x_preferred":[
        "Soco"
    ],
    "name:ind_x_preferred":[
        "Soco"
    ],
    "name:nld_x_preferred":[
        "Soco"
    ],
    "name:por_x_preferred":[
        "Soco"
    ],
    "name:swe_x_preferred":[
        "Soco"
    ],
    "wof:lang_x_official":[
        "ind"
    ],
    "wof:lang_x_spoken":[
        "ind",
        "eng"
    ],
    "wof:name":"Soco",
    "wof:placetype":"locality"
},
  "geometry": {"coordinates":[112.20399999999999,-7.3715],"type":"Point"}
}