{
  "type": "Feature",
  "properties": {
    "gn:admin1_code":"26.0",
    "gn:asciiname":"Huta Urat Dua",
    "gn:country_code":"ID",
    "gn:dem":1058,
    "gn:feature_class":"P",
    "gn:feature_code":"PPL",
    "gn:name":"Huta Urat Dua",
    "gn:population":0,
    "gn:timezone":"Asia/Jakarta",
    "iso:country":"ID",
    "name:ind_x_preferred":[
        "Huta Urat Dua"
    ],
    "name:und_x_variant":[
        "Huta Urat 2"
    ],
    "wof:lang_x_official":[
        "ind"
    ],
    "wof:lang_x_spoken":[
        "ind",
        "eng"
    ],
    "wof:name":"Huta Urat Dua",
    "wof:placetype":"locality"
},
  "geometry": {"coordinates":[98.6306,2.6069],"type":"Point"}
}