{
  "type": "Feature",
  "properties": {
    "gn:admin1_code":"15.0",
    "gn:asciiname":"Sukarante",
    "gn:country_code":"ID",
    "gn:dem":235,
    "gn:feature_class":"P",
    "gn:feature_code":"PPL",
    "gn:name":"Sukarante",
    "gn:population":0,
    "gn:timezone":"Asia/Jakarta",
    "iso:country":"ID",
    "name:ind_x_preferred":[
        "Sukarante"
    ],
    "wof:name":"Sukarante",
    "wof:placetype":"locality"
},
  "geometry": {"coordinates":[105.21326000000001,-5.45542],"type":"Point"}
}