{
  "type": "Feature",
  "properties": {
    "gn:admin1_code":"1",
    "gn:asciiname":"Simpang Tiga",
    "gn:country_code":"ID",
    "gn:dem":4,
    "gn:feature_class":"P",
    "gn:feature_code":"PPL",
    "gn:name":"Simpang Tiga",
    "gn:population":0,
    "gn:timezone":"Asia/Jakarta",
    "iso:country":"ID",
    "name:epo_x_preferred":[
        "Simpang Tiga"
    ],
    "name:ind_x_preferred":[
        "Simpang Tiga"
    ],
    "name:msa_x_preferred":[
        "Simpang Tiga"
    ],
    "wof:name":"Simpang Tiga",
    "wof:placetype":"locality"
},
  "geometry": {"coordinates":[98.1704,4.3878],"type":"Point"}
}