{
  "type": "Feature",
  "properties": {
    "gn:admin1_code":"30.0",
    "gn:asciiname":"Pasirpogor",
    "gn:country_code":"ID",
    "gn:dem":446,
    "gn:feature_class":"P",
    "gn:feature_code":"PPL",
    "gn:name":"Pasirpogor",
    "gn:population":0,
    "gn:timezone":"Asia/Jakarta",
    "iso:country":"ID",
    "name:ind_x_preferred":[
        "Pasirpogor"
    ],
    "wof:name":"Pasirpogor",
    "wof:placetype":"locality"
},
  "geometry": {"coordinates":[106.611,-7.2034],"type":"Point"}
}