{
  "type": "Feature",
  "properties": {
    "gn:admin1_code":"30",
    "gn:asciiname":"Kawung",
    "gn:country_code":"ID",
    "gn:dem":701,
    "gn:feature_class":"P",
    "gn:feature_code":"PPL",
    "gn:name":"Kawung",
    "gn:population":0,
    "gn:timezone":"Asia/Jakarta",
    "iso:country":"ID",
    "name:ind_x_preferred":[
        "Kawung"
    ],
    "wof:name":"Kawung",
    "wof:placetype":"locality"
},
  "geometry": {"coordinates":[106.89888999999999,-6.87694],"type":"Point"}
}