{
  "type": "Feature",
  "properties": {
    "gn:admin1_code":"30.0",
    "gn:asciiname":"Sukarata",
    "gn:country_code":"ID",
    "gn:dem":8,
    "gn:feature_class":"P",
    "gn:feature_code":"PPL",
    "gn:name":"Sukarata",
    "gn:population":0,
    "gn:timezone":"Asia/Jakarta",
    "iso:country":"ID",
    "name:ind_x_preferred":[
        "Sukarata"
    ],
    "wof:name":"Sukarata",
    "wof:placetype":"locality"
},
  "geometry": {"coordinates":[106.6896,-7.4103],"type":"Point"}
}