{
  "type": "Feature",
  "properties": {
    "gn:admin1_code":"2.0",
    "gn:asciiname":"Batumadeg Kelod",
    "gn:country_code":"ID",
    "gn:dem":262,
    "gn:feature_class":"P",
    "gn:feature_code":"PPL",
    "gn:name":"Batumadeg Kelod",
    "gn:population":0,
    "gn:timezone":"Asia/Makassar",
    "iso:country":"ID",
    "name:ind_x_preferred":[
        "Batumadeg Kelod"
    ],
    "wof:name":"Batumadeg Kelod",
    "wof:placetype":"locality"
},
  "geometry": {"coordinates":[115.50620000000001,-8.7473],"type":"Point"}
}