{
  "type": "Feature",
  "properties": {
    "gn:admin1_code":"8.0",
    "gn:asciiname":"Ngrejo",
    "gn:country_code":"ID",
    "gn:dem":107,
    "gn:feature_class":"P",
    "gn:feature_code":"PPLA4",
    "gn:name":"Ngrejo",
    "gn:population":0,
    "gn:timezone":"Asia/Jakarta",
    "iso:country":"ID",
    "name:ind_x_preferred":[
        "Ngrejo"
    ],
    "wof:name":"Ngrejo",
    "wof:placetype":"locality"
},
  "geometry": {"coordinates":[111.9427,-8.177],"type":"Point"}
}