{
  "type": "Feature",
  "properties": {
    "gn:admin1_code":"28.0",
    "gn:asciiname":"Kilmasasiteniweye",
    "gn:country_code":"ID",
    "gn:dem":-9999,
    "gn:feature_class":"P",
    "gn:feature_code":"PPL",
    "gn:name":"Kilmasasiteniweye",
    "gn:population":0,
    "gn:timezone":"Asia/Jayapura",
    "iso:country":"ID",
    "name:ind_x_preferred":[
        "Kilmasasiteniweye"
    ],
    "name:und_x_variant":[
        "Kilmasa-siteniweye",
        "Kilmasa-siteniweje",
        "Kilmasaasiteniweye",
        "Kilmasasitenimeye",
        "Kilmasasiteniweje"
    ],
    "wof:lang_x_official":[
        "ind"
    ],
    "wof:lang_x_spoken":[
        "ind",
        "eng"
    ],
    "wof:name":"Kilmasasiteniweye",
    "wof:placetype":"locality"
},
  "geometry": {"coordinates":[131.62638999999999,-7.63008],"type":"Point"}
}