{
  "type": "Feature",
  "properties": {
    "gn:admin1_code":"7",
    "gn:asciiname":"Kedungkendang",
    "gn:country_code":"ID",
    "gn:dem":74,
    "gn:feature_class":"P",
    "gn:feature_code":"PPL",
    "gn:name":"Kedungkendang",
    "gn:population":0,
    "gn:timezone":"Asia/Jakarta",
    "iso:country":"ID",
    "name:ind_x_preferred":[
        "Kedungkendang"
    ],
    "wof:name":"Kedungkendang",
    "wof:placetype":"locality"
},
  "geometry": {"coordinates":[111.08360999999999,-7.36139],"type":"Point"}
}