{
  "type": "Feature",
  "properties": {
    "gn:admin1_code":"22.0",
    "gn:asciiname":"Ombo",
    "gn:country_code":"ID",
    "gn:dem":3,
    "gn:feature_class":"P",
    "gn:feature_code":"PPL",
    "gn:name":"Ombo",
    "gn:population":0,
    "gn:timezone":"Asia/Makassar",
    "iso:country":"ID",
    "name:ceb_x_preferred":[
        "Ombo"
    ],
    "name:dan_x_preferred":[
        "Ombo"
    ],
    "name:deu_x_preferred":[
        "Ombo"
    ],
    "name:ind_x_preferred":[
        "Ombo"
    ],
    "name:nno_x_preferred":[
        "Ombo"
    ],
    "name:nor_x_preferred":[
        "Ombo"
    ],
    "wof:lang_x_official":[
        "ind"
    ],
    "wof:lang_x_spoken":[
        "ind",
        "eng"
    ],
    "wof:name":"Ombo",
    "wof:placetype":"locality"
},
  "geometry": {"coordinates":[121.5157,-4.4488],"type":"Point"}
}