{
  "type": "Feature",
  "properties": {
    "gn:admin1_code":"10",
    "gn:asciiname":"Jetis",
    "gn:country_code":"ID",
    "gn:dem":206,
    "gn:feature_class":"P",
    "gn:feature_code":"PPL",
    "gn:name":"Jetis",
    "gn:population":0,
    "gn:timezone":"Asia/Jakarta",
    "iso:country":"ID",
    "wof:name":"Jetis",
    "wof:placetype":"locality"
},
  "geometry": {"coordinates":[110.69889000000001,-7.95083],"type":"Point"}
}