{
  "type": "Feature",
  "properties": {
    "gn:admin1_code":"7",
    "gn:asciiname":"Dinuk Sebayur",
    "gn:country_code":"ID",
    "gn:dem":8,
    "gn:feature_class":"P",
    "gn:feature_code":"PPL",
    "gn:name":"Dinuk Sebayur",
    "gn:population":0,
    "gn:timezone":"Asia/Jakarta",
    "iso:country":"ID",
    "name:ind_x_preferred":[
        "Dinuk Sebayur"
    ],
    "wof:name":"Dinuk Sebayur",
    "wof:placetype":"locality"
},
  "geometry": {"coordinates":[109.1789,-6.8814],"type":"Point"}
}