{
  "type": "Feature",
  "properties": {
    "gn:country":"ID",
    "gn:fcode":"ADMD",
    "gn:pop":0,
    "iso:country":"ID",
    "name:unk_x_variant":[
        "Daerah Tingkat II Magetan"
    ],
    "qs:name":"Kabupaten Magetan",
    "qs:photos_9r":0,
    "qs:photos_sr":0,
    "qs:pop_sr":"0",
    "wof:lang_x_official":[
        "ind"
    ],
    "wof:lang_x_spoken":[
        "ind",
        "eng"
    ],
    "wof:name":"Kabupaten Magetan",
    "wof:placetype":"localadmin",
    "wof:population":0
},
  "geometry": {"coordinates":[111.58333,-7.66667],"type":"Point"}
}