{
  "type": "Feature",
  "properties": {
    "gn:admin1_code":"10",
    "gn:asciiname":"Cerme",
    "gn:country_code":"ID",
    "gn:dem":237,
    "gn:feature_class":"P",
    "gn:feature_code":"PPL",
    "gn:name":"Cerme",
    "gn:population":0,
    "gn:timezone":"Asia/Jakarta",
    "iso:country":"ID",
    "name:ind_x_preferred":[
        "Cerme"
    ],
    "wof:name":"Cerme",
    "wof:placetype":"locality"
},
  "geometry": {"coordinates":[110.57611,-8.06639],"type":"Point"}
}