{
  "type": "Feature",
  "properties": {
    "gn:admin1_code":"8.0",
    "gn:asciiname":"Kucur",
    "gn:country_code":"ID",
    "gn:dem":197,
    "gn:feature_class":"P",
    "gn:feature_code":"PPL",
    "gn:name":"Kucur",
    "gn:population":0,
    "gn:timezone":"Asia/Jakarta",
    "iso:country":"ID",
    "name:ind_x_preferred":[
        "Kucur"
    ],
    "wof:name":"Kucur",
    "wof:placetype":"locality"
},
  "geometry": {"coordinates":[111.92319999999999,-7.7418],"type":"Point"}
}