{
  "type": "Feature",
  "properties": {
    "gn:admin1_code":"1",
    "gn:asciiname":"Sarahpanjang",
    "gn:country_code":"ID",
    "gn:dem":28,
    "gn:feature_class":"P",
    "gn:feature_code":"PPL",
    "gn:name":"Sarahpanjang",
    "gn:population":0,
    "gn:timezone":"Asia/Jakarta",
    "iso:country":"ID",
    "name:ind_x_preferred":[
        "Sarahpanjang"
    ],
    "wof:name":"Sarahpanjang",
    "wof:placetype":"locality"
},
  "geometry": {"coordinates":[95.9239,4.55],"type":"Point"}
}