{
  "type": "Feature",
  "properties": {
    "gn:admin1_code":"4.0",
    "gn:asciiname":"Cipinangmuara",
    "gn:country_code":"ID",
    "gn:dem":14,
    "gn:feature_class":"P",
    "gn:feature_code":"PPL",
    "gn:name":"Cipinangmuara",
    "gn:population":0,
    "gn:timezone":"Asia/Jakarta",
    "iso:country":"ID",
    "name:ind_x_preferred":[
        "Cipinangmuara"
    ],
    "name:und_x_variant":[
        "Muaratjipinang",
        "Moearatjipinang",
        "Muaracipinang"
    ],
    "wof:lang_x_official":[
        "ind"
    ],
    "wof:lang_x_spoken":[
        "ind",
        "eng"
    ],
    "wof:name":"Cipinangmuara",
    "wof:placetype":"locality"
},
  "geometry": {"coordinates":[106.8869,-6.2266],"type":"Point"}
}