{
  "type": "Feature",
  "properties": {
    "gn:admin1_code":"18.0",
    "gn:asciiname":"Rende",
    "gn:country_code":"ID",
    "gn:dem":152,
    "gn:feature_class":"P",
    "gn:feature_code":"PPL",
    "gn:name":"Rende",
    "gn:population":0,
    "gn:timezone":"Asia/Makassar",
    "iso:country":"ID",
    "name:ind_x_preferred":[
        "Rende"
    ],
    "wof:name":"Rende",
    "wof:placetype":"locality"
},
  "geometry": {"coordinates":[119.06440000000001,-9.5786],"type":"Point"}
}