{
  "type": "Feature",
  "properties": {
    "gn:admin1_code":"26",
    "gn:asciiname":"Keling",
    "gn:country_code":"ID",
    "gn:dem":6,
    "gn:feature_class":"P",
    "gn:feature_code":"PPL",
    "gn:name":"Keling",
    "gn:population":0,
    "gn:timezone":"Asia/Jakarta",
    "iso:country":"ID",
    "name:ind_x_preferred":[
        "Keling"
    ],
    "name:msa_x_preferred":[
        "Keling"
    ],
    "name:tam_x_preferred":[
        "\u0b9a\u0b9e\u0bcd\u0b9a\u0bbf\u0b95\u0bcd\u0b95\u0bc2\u0bb2\u0bbf"
    ],
    "wof:lang_x_official":[
        "ind"
    ],
    "wof:lang_x_spoken":[
        "ind",
        "eng"
    ],
    "wof:name":"Keling",
    "wof:placetype":"locality"
},
  "geometry": {"coordinates":[98.2864,4.0181],"type":"Point"}
}