{
  "type": "Feature",
  "properties": {
    "gn:admin1_code":"07",
    "gn:asciiname":"Jagang",
    "gn:country_code":"ID",
    "gn:dem":1084,
    "gn:feature_class":"P",
    "gn:feature_code":"PPL",
    "gn:name":"Jagang",
    "gn:population":0,
    "gn:timezone":"Asia/Jakarta",
    "iso:country":"ID",
    "name:ind_x_preferred":[
        "Jagang"
    ],
    "name:und_x_variant":[
        "Djagang"
    ],
    "wof:lang_x_official":[
        "ind"
    ],
    "wof:lang_x_spoken":[
        "ind",
        "eng"
    ],
    "wof:name":"Jagang",
    "wof:placetype":"locality"
},
  "geometry": {"coordinates":[110.27139,-7.235],"type":"Point"}
}