{
  "type": "Feature",
  "properties": {
    "gn:admin1_code":"5.0",
    "gn:asciiname":"Talangsekundur",
    "gn:country_code":"ID",
    "gn:dem":290,
    "gn:feature_class":"P",
    "gn:feature_code":"PPL",
    "gn:name":"Talangsekundur",
    "gn:population":0,
    "gn:timezone":"Asia/Jakarta",
    "iso:country":"ID",
    "name:ind_x_preferred":[
        "Talangsekundur"
    ],
    "wof:name":"Talangsekundur",
    "wof:placetype":"locality"
},
  "geometry": {"coordinates":[102.2848,-2.4483],"type":"Point"}
}