{
  "type": "Feature",
  "properties": {
    "gn:admin1_code":"18.0",
    "gn:asciiname":"Purangka",
    "gn:country_code":"ID",
    "gn:dem":571,
    "gn:feature_class":"P",
    "gn:feature_code":"PPL",
    "gn:name":"Purangka",
    "gn:population":0,
    "gn:timezone":"Asia/Makassar",
    "iso:country":"ID",
    "name:ind_x_preferred":[
        "Purangka"
    ],
    "wof:name":"Purangka",
    "wof:placetype":"locality"
},
  "geometry": {"coordinates":[120.58580000000001,-8.7062],"type":"Point"}
}