{
  "type": "Feature",
  "properties": {
    "gn:admin1_code":"7.0",
    "gn:asciiname":"Melung",
    "gn:country_code":"ID",
    "gn:dem":180,
    "gn:feature_class":"P",
    "gn:feature_code":"PPL",
    "gn:name":"Melung",
    "gn:population":0,
    "gn:timezone":"Asia/Jakarta",
    "iso:country":"ID",
    "name:ceb_x_preferred":[
        "Melung"
    ],
    "name:ind_x_preferred":[
        "Melung"
    ],
    "name:msa_x_preferred":[
        "Melung"
    ],
    "name:new_x_preferred":[
        "\u092e\u0947\u0932\u0941\u0919\u094d\u0917"
    ],
    "name:pol_x_preferred":[
        "Melung"
    ],
    "wof:lang_x_official":[
        "ind"
    ],
    "wof:lang_x_spoken":[
        "ind",
        "eng"
    ],
    "wof:name":"Melung",
    "wof:placetype":"locality"
},
  "geometry": {"coordinates":[109.51222,-7.37806],"type":"Point"}
}