{
  "type": "Feature",
  "properties": {
    "gn:admin1_code":"40.0",
    "gn:asciiname":"Lubuksemut",
    "gn:country_code":"ID",
    "gn:dem":9,
    "gn:feature_class":"P",
    "gn:feature_code":"PPL",
    "gn:name":"Lubuksemut",
    "gn:population":0,
    "gn:timezone":"Asia/Jakarta",
    "iso:country":"ID",
    "name:ind_x_preferred":[
        "Lubuksemut"
    ],
    "name:und_x_variant":[
        "Loeboeksemoet"
    ],
    "wof:name":"Lubuksemut",
    "wof:placetype":"locality"
},
  "geometry": {"coordinates":[103.43436,1.00438],"type":"Point"}
}