{
  "type": "Feature",
  "properties": {
    "gn:admin1_code":"18.0",
    "gn:asciiname":"Letenggarong",
    "gn:country_code":"ID",
    "gn:dem":557,
    "gn:feature_class":"P",
    "gn:feature_code":"PPL",
    "gn:name":"Letenggarong",
    "gn:population":0,
    "gn:timezone":"Asia/Makassar",
    "iso:country":"ID",
    "name:ind_x_preferred":[
        "Letenggarong"
    ],
    "wof:name":"Letenggarong",
    "wof:placetype":"locality"
},
  "geometry": {"coordinates":[119.2394,-9.5032],"type":"Point"}
}