{
  "type": "Feature",
  "properties": {
    "gn:admin1_code":"7",
    "gn:asciiname":"Sumberejo",
    "gn:country_code":"ID",
    "gn:dem":11,
    "gn:feature_class":"P",
    "gn:feature_code":"PPL",
    "gn:name":"Sumberejo",
    "gn:population":0,
    "gn:timezone":"Asia/Jakarta",
    "iso:country":"ID",
    "name:ind_x_preferred":[
        "Sumberejo"
    ],
    "wof:name":"Sumberejo",
    "wof:placetype":"locality"
},
  "geometry": {"coordinates":[109.92638999999998,-7.80889],"type":"Point"}
}