{
  "type": "Feature",
  "properties": {
    "gn:admin1_code":"30.0",
    "gn:asciiname":"Krontorejo",
    "gn:country_code":"ID",
    "gn:dem":460,
    "gn:feature_class":"P",
    "gn:feature_code":"PPL",
    "gn:name":"Krontorejo",
    "gn:population":0,
    "gn:timezone":"Asia/Jakarta",
    "iso:country":"ID",
    "name:ind_x_preferred":[
        "Krontorejo"
    ],
    "name:und_x_variant":[
        "Kronto"
    ],
    "wof:name":"Krontorejo",
    "wof:placetype":"locality"
},
  "geometry": {"coordinates":[112.9409,-7.7997],"type":"Point"}
}