{
  "type": "Feature",
  "properties": {
    "gn:admin1_code":"30.0",
    "gn:asciiname":"Nangkaloya",
    "gn:country_code":"ID",
    "gn:dem":266,
    "gn:feature_class":"P",
    "gn:feature_code":"PPL",
    "gn:name":"Nangkaloya",
    "gn:population":0,
    "gn:timezone":"Asia/Jakarta",
    "iso:country":"ID",
    "name:ind_x_preferred":[
        "Nangkaloya"
    ],
    "wof:name":"Nangkaloya",
    "wof:placetype":"locality"
},
  "geometry": {"coordinates":[106.6163,-7.2306],"type":"Point"}
}