{
  "type": "Feature",
  "properties": {
    "gn:admin1_code":"30.0",
    "gn:asciiname":"Linggasari",
    "gn:country_code":"ID",
    "gn:dem":996,
    "gn:feature_class":"P",
    "gn:feature_code":"PPL",
    "gn:name":"Linggasari",
    "gn:population":0,
    "gn:timezone":"Asia/Jakarta",
    "iso:country":"ID",
    "name:ind_x_preferred":[
        "Linggasari"
    ],
    "wof:name":"Linggasari",
    "wof:placetype":"locality"
},
  "geometry": {"coordinates":[106.98950000000001,-7.0818],"type":"Point"}
}