{
  "type": "Feature",
  "properties": {
    "gn:admin1_code":"17.0",
    "gn:asciiname":"Manik",
    "gn:country_code":"ID",
    "gn:dem":223,
    "gn:feature_class":"P",
    "gn:feature_code":"PPL",
    "gn:name":"Manik",
    "gn:population":0,
    "gn:timezone":"Asia/Makassar",
    "iso:country":"ID",
    "name:deu_x_preferred":[
        "Manik"
    ],
    "name:ind_x_preferred":[
        "Manik"
    ],
    "name:rus_x_preferred":[
        "\u041c\u0430\u043d\u0438\u043a"
    ],
    "wof:lang_x_official":[
        "ind"
    ],
    "wof:lang_x_spoken":[
        "ind",
        "eng"
    ],
    "wof:name":"Manik",
    "wof:placetype":"locality"
},
  "geometry": {"coordinates":[116.0157,-8.7655],"type":"Point"}
}