{
  "type": "Feature",
  "properties": {
    "gn:admin1_code":"38",
    "gn:asciiname":"Malimongan",
    "gn:country_code":"ID",
    "gn:dem":1190,
    "gn:feature_class":"P",
    "gn:feature_code":"PPL",
    "gn:name":"Malimongan",
    "gn:population":0,
    "gn:timezone":"Asia/Makassar",
    "iso:country":"ID",
    "name:ind_x_preferred":[
        "Malimongan"
    ],
    "wof:name":"Malimongan",
    "wof:placetype":"locality"
},
  "geometry": {"coordinates":[119.91240000000001,-3.1397],"type":"Point"}
}