{
  "type": "Feature",
  "properties": {
    "gn:admin1_code":"30.0",
    "gn:asciiname":"Sindangmangu",
    "gn:country_code":"ID",
    "gn:dem":126,
    "gn:feature_class":"P",
    "gn:feature_code":"PPL",
    "gn:name":"Sindangmangu",
    "gn:population":0,
    "gn:timezone":"Asia/Jakarta",
    "iso:country":"ID",
    "name:ind_x_preferred":[
        "Sindangmangu"
    ],
    "name:und_x_variant":[
        "Sindangmangoe"
    ],
    "wof:lang_x_official":[
        "ind"
    ],
    "wof:lang_x_spoken":[
        "ind",
        "eng"
    ],
    "wof:name":"Sindangmangu",
    "wof:placetype":"locality"
},
  "geometry": {"coordinates":[108.76298,-7.67207],"type":"Point"}
}