{
  "type": "Feature",
  "properties": {
    "gn:admin1_code":"15.0",
    "gn:asciiname":"Tanjungarum Pinggir",
    "gn:country_code":"ID",
    "gn:dem":53,
    "gn:feature_class":"P",
    "gn:feature_code":"PPL",
    "gn:name":"Tanjungarum Pinggir",
    "gn:population":0,
    "gn:timezone":"Asia/Jakarta",
    "iso:country":"ID",
    "name:ind_x_preferred":[
        "Tanjungarum Pinggir"
    ],
    "wof:name":"Tanjungarum Pinggir",
    "wof:placetype":"locality"
},
  "geometry": {"coordinates":[104.95453999999999,-4.91338],"type":"Point"}
}