{
  "type": "Feature",
  "properties": {
    "gn:admin1_code":"18.0",
    "gn:asciiname":"Nelabesa",
    "gn:country_code":"ID",
    "gn:dem":606,
    "gn:feature_class":"P",
    "gn:feature_code":"PPL",
    "gn:name":"Nelabesa",
    "gn:population":0,
    "gn:timezone":"Asia/Makassar",
    "iso:country":"ID",
    "name:ind_x_preferred":[
        "Nelabesa"
    ],
    "wof:name":"Nelabesa",
    "wof:placetype":"locality"
},
  "geometry": {"coordinates":[124.4695,-9.9377],"type":"Point"}
}