{
  "type": "Feature",
  "properties": {
    "gn:admin1_code":"7",
    "gn:asciiname":"Ngelo",
    "gn:country_code":"ID",
    "gn:dem":134,
    "gn:feature_class":"P",
    "gn:feature_code":"PPL",
    "gn:name":"Ngelo",
    "gn:population":0,
    "gn:timezone":"Asia/Jakarta",
    "iso:country":"ID",
    "name:ind_x_preferred":[
        "Ngelo"
    ],
    "wof:name":"Ngelo",
    "wof:placetype":"locality"
},
  "geometry": {"coordinates":[111.12833000000001,-7.2925],"type":"Point"}
}