{
  "type": "Feature",
  "properties": {
    "gn:admin1_code":"33.0",
    "gn:asciiname":"Cikeder",
    "gn:country_code":"ID",
    "gn:dem":44,
    "gn:feature_class":"P",
    "gn:feature_code":"PPL",
    "gn:name":"Cikeder",
    "gn:population":0,
    "gn:timezone":"Asia/Jakarta",
    "iso:country":"ID",
    "name:ind_x_preferred":[
        "Cikeder"
    ],
    "wof:name":"Cikeder",
    "wof:placetype":"locality"
},
  "geometry": {"coordinates":[105.8777,-6.5163],"type":"Point"}
}