{
  "type": "Feature",
  "properties": {
    "gn:admin1_code":"30",
    "gn:asciiname":"Tarikolot",
    "gn:country_code":"ID",
    "gn:dem":745,
    "gn:feature_class":"P",
    "gn:feature_code":"PPL",
    "gn:name":"Tarikolot",
    "gn:population":0,
    "gn:timezone":"Asia/Jakarta",
    "iso:country":"ID",
    "name:ind_x_preferred":[
        "Tarikolot"
    ],
    "wof:name":"Tarikolot",
    "wof:placetype":"locality"
},
  "geometry": {"coordinates":[106.91443999999998,-6.87472],"type":"Point"}
}