{
  "type": "Feature",
  "properties": {
    "gn:admin1_code":"21",
    "gn:asciiname":"Bukaakan",
    "gn:country_code":"ID",
    "gn:dem":67,
    "gn:feature_class":"P",
    "gn:feature_code":"PPL",
    "gn:name":"Bukaakan",
    "gn:population":0,
    "gn:timezone":"Asia/Makassar",
    "iso:country":"ID",
    "name:ind_x_preferred":[
        "Bukaakan"
    ],
    "wof:name":"Bukaakan",
    "wof:placetype":"locality"
},
  "geometry": {"coordinates":[122.9748,-0.8614],"type":"Point"}
}