{
  "type": "Feature",
  "properties": {
    "gn:admin1_code":"39.0",
    "gn:asciiname":"Aiserukwa",
    "gn:country_code":"ID",
    "gn:dem":219,
    "gn:feature_class":"P",
    "gn:feature_code":"PPL",
    "gn:name":"Aiserukwa",
    "gn:population":0,
    "gn:timezone":"Asia/Jayapura",
    "iso:country":"ID",
    "name:ind_x_preferred":[
        "Aiserukwa"
    ],
    "wof:name":"Aiserukwa",
    "wof:placetype":"locality"
},
  "geometry": {"coordinates":[133.84460000000001,-1.8212],"type":"Point"}
}