{
  "type": "Feature",
  "properties": {
    "gn:admin1_code":"4.0",
    "gn:asciiname":"Rawakuning",
    "gn:country_code":"ID",
    "gn:dem":16,
    "gn:feature_class":"P",
    "gn:feature_code":"PPL",
    "gn:name":"Rawakuning",
    "gn:population":0,
    "gn:timezone":"Asia/Jakarta",
    "iso:country":"ID",
    "name:ind_x_preferred":[
        "Rawakuning"
    ],
    "name:und_x_variant":[
        "Rawakoening"
    ],
    "wof:name":"Rawakuning",
    "wof:placetype":"locality"
},
  "geometry": {"coordinates":[106.9576,-6.2005],"type":"Point"}
}