{
  "type": "Feature",
  "properties": {
    "gn:admin1_code":"7",
    "gn:asciiname":"Singkil",
    "gn:country_code":"ID",
    "gn:dem":234,
    "gn:feature_class":"P",
    "gn:feature_code":"PPL",
    "gn:name":"Singkil",
    "gn:population":0,
    "gn:timezone":"Asia/Jakarta",
    "iso:country":"ID",
    "name:ind_x_preferred":[
        "Singkil"
    ],
    "name:mlg_x_preferred":[
        "Singkil"
    ],
    "name:tgl_x_preferred":[
        "Singkil"
    ],
    "wof:lang_x_official":[
        "ind"
    ],
    "wof:lang_x_spoken":[
        "ind",
        "eng"
    ],
    "wof:name":"Singkil",
    "wof:placetype":"locality"
},
  "geometry": {"coordinates":[110.788,-6.6499],"type":"Point"}
}