{
  "type": "Feature",
  "properties": {
    "gn:admin1_code":"29.0",
    "gn:asciiname":"Patelei",
    "gn:country_code":"ID",
    "gn:dem":9,
    "gn:feature_class":"P",
    "gn:feature_code":"PPL",
    "gn:name":"Patelei",
    "gn:population":0,
    "gn:timezone":"Asia/Jayapura",
    "iso:country":"ID",
    "name:ind_x_preferred":[
        "Patelei"
    ],
    "wof:name":"Patelei",
    "wof:placetype":"locality"
},
  "geometry": {"coordinates":[128.47326000000001,0.59927],"type":"Point"}
}