{
  "type": "Feature",
  "properties": {
    "gn:admin1_code":"30.0",
    "gn:asciiname":"Sakerta Timur",
    "gn:country_code":"ID",
    "gn:dem":732,
    "gn:feature_class":"P",
    "gn:feature_code":"PPLA4",
    "gn:name":"Sakerta Timur",
    "gn:population":0,
    "gn:timezone":"Asia/Jakarta",
    "iso:country":"ID",
    "name:ind_x_preferred":[
        "Sakerta Timur"
    ],
    "wof:lang_x_official":[
        "ind"
    ],
    "wof:lang_x_spoken":[
        "ind",
        "eng"
    ],
    "wof:name":"Sakerta Timur",
    "wof:placetype":"locality"
},
  "geometry": {"coordinates":[108.41589999999999,-7.0366],"type":"Point"}
}