{
  "type": "Feature",
  "properties": {
    "gn:admin1_code":"18.0",
    "gn:asciiname":"Kunatena",
    "gn:country_code":"ID",
    "gn:dem":475,
    "gn:feature_class":"P",
    "gn:feature_code":"PPL",
    "gn:name":"Kunatena",
    "gn:population":0,
    "gn:timezone":"Asia/Makassar",
    "iso:country":"ID",
    "name:ind_x_preferred":[
        "Kunatena"
    ],
    "wof:name":"Kunatena",
    "wof:placetype":"locality"
},
  "geometry": {"coordinates":[125.00920000000001,-8.2819],"type":"Point"}
}