{
  "type": "Feature",
  "properties": {
    "gn:admin1_code":"30.0",
    "gn:asciiname":"Nusawangi",
    "gn:country_code":"ID",
    "gn:dem":356,
    "gn:feature_class":"P",
    "gn:feature_code":"PPL",
    "gn:name":"Nusawangi",
    "gn:population":0,
    "gn:timezone":"Asia/Jakarta",
    "iso:country":"ID",
    "name:ind_x_preferred":[
        "Nusawangi"
    ],
    "wof:name":"Nusawangi",
    "wof:placetype":"locality"
},
  "geometry": {"coordinates":[108.21769999999999,-7.3356],"type":"Point"}
}