{
  "type": "Feature",
  "properties": {
    "gn:admin1_code":"30.0",
    "gn:asciiname":"Ciguha Tengah",
    "gn:country_code":"ID",
    "gn:dem":1017,
    "gn:feature_class":"P",
    "gn:feature_code":"PPLA4",
    "gn:name":"Ciguha Tengah",
    "gn:population":0,
    "gn:timezone":"Asia/Jakarta",
    "iso:country":"ID",
    "name:ind_x_preferred":[
        "Ciguha Tengah"
    ],
    "name:und_x_variant":[
        "Tjiguha",
        "Ciguha"
    ],
    "wof:lang_x_official":[
        "ind"
    ],
    "wof:lang_x_spoken":[
        "ind",
        "eng"
    ],
    "wof:name":"Ciguha Tengah",
    "wof:placetype":"locality"
},
  "geometry": {"coordinates":[107.05540000000001,-7.111],"type":"Point"}
}