{
  "type": "Feature",
  "properties": {
    "gn:country":"ID",
    "gn:fcode":"ADM3",
    "gn:pop":0,
    "iso:country":"ID",
    "name:eng_x_preferred":[
        "Districts of West Java"
    ],
    "name:ind_x_preferred":[
        "Kecamatan Gempol"
    ],
    "name:unk_x_variant":[
        "Gempol"
    ],
    "qs:name":"Kecamatan Gempol",
    "qs:photos_9r":0,
    "qs:photos_sr":0,
    "qs:pop_sr":"0",
    "wd:wordcount":1319,
    "wof:name":"Kecamatan Gempol",
    "wof:placetype":"localadmin",
    "wof:population":0
},
  "geometry": {"coordinates":[112.6859,-7.5966],"type":"Point"}
}