{
  "type": "Feature",
  "properties": {
    "gn:admin1_code":"8",
    "gn:asciiname":"Boro Lor",
    "gn:country_code":"ID",
    "gn:dem":585,
    "gn:feature_class":"P",
    "gn:feature_code":"PPL",
    "gn:name":"Boro Lor",
    "gn:population":0,
    "gn:timezone":"Asia/Jakarta",
    "iso:country":"ID",
    "name:ind_x_preferred":[
        "Boro Lor"
    ],
    "wof:lang_x_official":[
        "ind"
    ],
    "wof:lang_x_spoken":[
        "ind",
        "eng"
    ],
    "wof:name":"Boro Lor",
    "wof:placetype":"locality"
},
  "geometry": {"coordinates":[112.74120000000001,-7.9106],"type":"Point"}
}