{
  "type": "Feature",
  "properties": {
    "gn:admin1_code":"30",
    "gn:asciiname":"Medalwangi",
    "gn:country_code":"ID",
    "gn:dem":294,
    "gn:feature_class":"P",
    "gn:feature_code":"PPL",
    "gn:name":"Medalwangi",
    "gn:population":0,
    "gn:timezone":"Asia/Jakarta",
    "iso:country":"ID",
    "name:ind_x_preferred":[
        "Medalwangi"
    ],
    "wof:name":"Medalwangi",
    "wof:placetype":"locality"
},
  "geometry": {"coordinates":[107.33333,-6.82806],"type":"Point"}
}