{
  "type": "Feature",
  "properties": {
    "gn:admin1_code":"30.0",
    "gn:asciiname":"Sukarasa",
    "gn:country_code":"ID",
    "gn:dem":464,
    "gn:feature_class":"P",
    "gn:feature_code":"PPL",
    "gn:name":"Sukarasa",
    "gn:population":0,
    "gn:timezone":"Asia/Jakarta",
    "iso:country":"ID",
    "name:ind_x_preferred":[
        "Sukarasa"
    ],
    "name:und_x_variant":[
        "Soekakarsa"
    ],
    "wof:lang_x_official":[
        "ind"
    ],
    "wof:lang_x_spoken":[
        "ind",
        "eng"
    ],
    "wof:name":"Sukarasa",
    "wof:placetype":"locality"
},
  "geometry": {"coordinates":[108.0821,-7.3722],"type":"Point"}
}