{
  "type": "Feature",
  "properties": {
    "gn:admin1_code":"17",
    "gn:asciiname":"Rade",
    "gn:country_code":"ID",
    "gn:dem":18,
    "gn:feature_class":"P",
    "gn:feature_code":"PPL",
    "gn:name":"Rade",
    "gn:population":0,
    "gn:timezone":"Asia/Makassar",
    "iso:country":"ID",
    "name:ceb_x_preferred":[
        "Rade"
    ],
    "name:dan_x_preferred":[
        "Rade"
    ],
    "name:deu_x_preferred":[
        "Rade"
    ],
    "name:eus_x_preferred":[
        "Rade"
    ],
    "name:fra_x_preferred":[
        "Rade"
    ],
    "name:ind_x_preferred":[
        "Rade"
    ],
    "name:ita_x_preferred":[
        "Rade"
    ],
    "name:mkd_x_preferred":[
        "\u0420\u0430\u0434\u0435"
    ],
    "name:nds_x_preferred":[
        "Rade"
    ],
    "name:nld_x_preferred":[
        "Rade"
    ],
    "name:pol_x_preferred":[
        "Rade"
    ],
    "name:por_x_preferred":[
        "Rade"
    ],
    "name:rus_x_preferred":[
        "\u0420\u0430\u0434\u0435"
    ],
    "name:swe_x_preferred":[
        "Rade"
    ],
    "wof:lang_x_official":[
        "ind"
    ],
    "wof:lang_x_spoken":[
        "ind",
        "eng"
    ],
    "wof:name":"Rade",
    "wof:placetype":"locality"
},
  "geometry": {"coordinates":[118.62571,-8.50375],"type":"Point"}
}