{
  "type": "Feature",
  "properties": {
    "gn:admin1_code":"8",
    "gn:asciiname":"Panggungjangjang",
    "gn:country_code":"ID",
    "gn:dem":330,
    "gn:feature_class":"P",
    "gn:feature_code":"PPL",
    "gn:name":"Panggungjangjang",
    "gn:population":0,
    "gn:timezone":"Asia/Jakarta",
    "iso:country":"ID",
    "name:ind_x_preferred":[
        "Panggungjangjang"
    ],
    "wof:name":"Panggungjangjang",
    "wof:placetype":"locality"
},
  "geometry": {"coordinates":[112.1628,-8.2331],"type":"Point"}
}