{
  "type": "Feature",
  "properties": {
    "gn:admin1_code":"30",
    "gn:asciiname":"Pasirgajah",
    "gn:country_code":"ID",
    "gn:dem":798,
    "gn:feature_class":"P",
    "gn:feature_code":"PPL",
    "gn:name":"Pasirgajah",
    "gn:population":0,
    "gn:timezone":"Asia/Jakarta",
    "iso:country":"ID",
    "name:ind_x_preferred":[
        "Pasirgajah"
    ],
    "wof:name":"Pasirgajah",
    "wof:placetype":"locality"
},
  "geometry": {"coordinates":[107.16777999999999,-6.99972],"type":"Point"}
}