{
  "type": "Feature",
  "properties": {
    "gn:admin1_code":"17.0",
    "gn:asciiname":"Sangiang",
    "gn:country_code":"ID",
    "gn:dem":361,
    "gn:feature_class":"P",
    "gn:feature_code":"PPL",
    "gn:name":"Sangiang",
    "gn:population":0,
    "gn:timezone":"Asia/Makassar",
    "iso:country":"ID",
    "name:ind_x_preferred":[
        "Sangiang"
    ],
    "wof:name":"Sangiang",
    "wof:placetype":"locality"
},
  "geometry": {"coordinates":[116.2962,-8.3041],"type":"Point"}
}