{
  "type": "Feature",
  "properties": {
    "gn:admin1_code":"28",
    "gn:asciiname":"Dorianpatah",
    "gn:country_code":"ID",
    "gn:dem":10,
    "gn:feature_class":"P",
    "gn:feature_code":"PPL",
    "gn:name":"Dorianpatah",
    "gn:population":0,
    "gn:timezone":"Asia/Jayapura",
    "iso:country":"ID",
    "name:ind_x_preferred":[
        "Dorianpatali"
    ],
    "name:ind_x_variant":[
        "Dorianpatah"
    ],
    "name:und_x_variant":[
        "Durianpatah"
    ],
    "wof:name":"Dorianpatah",
    "wof:placetype":"locality"
},
  "geometry": {"coordinates":[128.21516,-3.63117],"type":"Point"}
}