{
  "type": "Feature",
  "properties": {
    "gn:admin1_code":"8.0",
    "gn:asciiname":"Mesjid",
    "gn:country_code":"ID",
    "gn:dem":388,
    "gn:feature_class":"P",
    "gn:feature_code":"PPL",
    "gn:name":"Mesjid",
    "gn:population":0,
    "gn:timezone":"Asia/Jakarta",
    "iso:country":"ID",
    "name:ind_x_preferred":[
        "Mesjid"
    ],
    "wof:name":"Mesjid",
    "wof:placetype":"locality"
},
  "geometry": {"coordinates":[113.7732,-7.8969],"type":"Point"}
}