{
  "type": "Feature",
  "properties": {
    "gn:admin1_code":"5.0",
    "gn:asciiname":"Dusunbarunalo",
    "gn:country_code":"ID",
    "gn:dem":120,
    "gn:feature_class":"P",
    "gn:feature_code":"PPL",
    "gn:name":"Dusunbarunalo",
    "gn:population":0,
    "gn:timezone":"Asia/Jakarta",
    "iso:country":"ID",
    "name:und_x_variant":[
        "Dusunnalo",
        "Doesoenbaroenalo",
        "Doesoennalo",
        "Dusunbarunalo"
    ],
    "wof:lang_x_official":[
        "ind"
    ],
    "wof:lang_x_spoken":[
        "ind",
        "eng"
    ],
    "wof:name":"Dusunbarunalo",
    "wof:placetype":"locality"
},
  "geometry": {"coordinates":[102.0693,-2.0319],"type":"Point"}
}