{
  "type": "Feature",
  "properties": {
    "gn:admin1_code":"15.0",
    "gn:asciiname":"Airabang",
    "gn:country_code":"ID",
    "gn:dem":772,
    "gn:feature_class":"P",
    "gn:feature_code":"PPL",
    "gn:name":"Airabang",
    "gn:population":0,
    "gn:timezone":"Asia/Jakarta",
    "iso:country":"ID",
    "name:ind_x_preferred":[
        "Airabang"
    ],
    "wof:name":"Airabang",
    "wof:placetype":"locality"
},
  "geometry": {"coordinates":[104.6134,-5.33947],"type":"Point"}
}