{
  "type": "Feature",
  "properties": {
    "gn:admin1_code":"34.0",
    "gn:asciiname":"Hutino",
    "gn:country_code":"ID",
    "gn:dem":24,
    "gn:feature_class":"P",
    "gn:feature_code":"PPL",
    "gn:name":"Hutino",
    "gn:population":0,
    "gn:timezone":"Asia/Makassar",
    "iso:country":"ID",
    "name:ind_x_preferred":[
        "Hutino"
    ],
    "wof:name":"Hutino",
    "wof:placetype":"locality"
},
  "geometry": {"coordinates":[121.9402,0.5046],"type":"Point"}
}