{
  "type": "Feature",
  "properties": {
    "gn:admin1_code":"8.0",
    "gn:asciiname":"Paliyan",
    "gn:country_code":"ID",
    "gn:dem":142,
    "gn:feature_class":"P",
    "gn:feature_code":"PPL",
    "gn:name":"Paliyan",
    "gn:population":0,
    "gn:timezone":"Asia/Jakarta",
    "iso:country":"ID",
    "name:bel_x_preferred":[
        "\u041f\u0430\u043b\u0456\u044f\u043d"
    ],
    "name:ind_x_preferred":[
        "Paliyan"
    ],
    "name:tam_x_preferred":[
        "\u0baa\u0bb4\u0bbf\u0baf\u0bb0\u0bcd"
    ],
    "wof:name":"Paliyan",
    "wof:placetype":"locality"
},
  "geometry": {"coordinates":[113.6202,-7.0689],"type":"Point"}
}