{
  "type": "Feature",
  "properties": {
    "gn:admin1_code":"30.0",
    "gn:asciiname":"Cimahi 2",
    "gn:country_code":"ID",
    "gn:dem":28,
    "gn:feature_class":"P",
    "gn:feature_code":"PPL",
    "gn:name":"Cimahi 2",
    "gn:population":0,
    "gn:timezone":"Asia/Jakarta",
    "iso:country":"ID",
    "name:und_x_variant":[
        "Tjimahi",
        "Cimahi 2"
    ],
    "wof:name":"Cimahi 2",
    "wof:placetype":"locality"
},
  "geometry": {"coordinates":[107.37278000000001,-6.41417],"type":"Point"}
}