{
  "type": "Feature",
  "properties": {
    "gn:admin1_code":"40",
    "gn:asciiname":"Tanggalangit",
    "gn:country_code":"ID",
    "gn:dem":8,
    "gn:feature_class":"P",
    "gn:feature_code":"PPL",
    "gn:name":"Tanggalangit",
    "gn:population":0,
    "gn:timezone":"Asia/Jakarta",
    "iso:country":"ID",
    "name:ind_x_preferred":[
        "Tanggarangit"
    ],
    "name:ind_x_variant":[
        "Tanggalangit"
    ],
    "wof:name":"Tanggalangit",
    "wof:placetype":"locality"
},
  "geometry": {"coordinates":[103.42816999999999,0.87251],"type":"Point"}
}