{
  "type": "Feature",
  "properties": {
    "gn:admin1_code":"18.0",
    "gn:asciiname":"Toenoa",
    "gn:country_code":"ID",
    "gn:dem":314,
    "gn:feature_class":"P",
    "gn:feature_code":"PPL",
    "gn:name":"Toenoa",
    "gn:population":0,
    "gn:timezone":"Asia/Makassar",
    "iso:country":"ID",
    "name:ind_x_preferred":[
        "Toenoa"
    ],
    "wof:name":"Toenoa",
    "wof:placetype":"locality"
},
  "geometry": {"coordinates":[124.18680000000001,-9.935],"type":"Point"}
}