{
  "type": "Feature",
  "properties": {
    "gn:admin1_code":"7.0",
    "gn:asciiname":"Argasari",
    "gn:country_code":"ID",
    "gn:dem":529,
    "gn:feature_class":"P",
    "gn:feature_code":"PPL",
    "gn:name":"Argasari",
    "gn:population":0,
    "gn:timezone":"Asia/Jakarta",
    "iso:country":"ID",
    "wof:name":"Argasari",
    "wof:placetype":"locality"
},
  "geometry": {"coordinates":[110.19722,-7.32444],"type":"Point"}
}