{
  "type": "Feature",
  "properties": {
    "gn:admin1_code":"30",
    "gn:asciiname":"Situsumur",
    "gn:country_code":"ID",
    "gn:dem":1272,
    "gn:feature_class":"P",
    "gn:feature_code":"PPL",
    "gn:name":"Situsumur",
    "gn:population":0,
    "gn:timezone":"Asia/Jakarta",
    "iso:country":"ID",
    "name:ind_x_preferred":[
        "Situsumur"
    ],
    "wof:name":"Situsumur",
    "wof:placetype":"locality"
},
  "geometry": {"coordinates":[107.3759,-7.0644],"type":"Point"}
}