{
  "type": "Feature",
  "properties": {
    "gn:admin1_code":"26",
    "gn:asciiname":"Sitondik",
    "gn:country_code":"ID",
    "gn:dem":592,
    "gn:feature_class":"P",
    "gn:feature_code":"PPL",
    "gn:name":"Sitondik",
    "gn:population":0,
    "gn:timezone":"Asia/Jakarta",
    "iso:country":"ID",
    "name:ind_x_preferred":[
        "Sitondik"
    ],
    "wof:name":"Sitondik",
    "wof:placetype":"locality"
},
  "geometry": {"coordinates":[99.07850000000001,2.8026],"type":"Point"}
}