{
  "type": "Feature",
  "properties": {
    "gn:admin1_code":"17.0",
    "gn:asciiname":"Penjor",
    "gn:country_code":"ID",
    "gn:dem":201,
    "gn:feature_class":"P",
    "gn:feature_code":"PPL",
    "gn:name":"Penjor",
    "gn:population":0,
    "gn:timezone":"Asia/Makassar",
    "iso:country":"ID",
    "name:ind_x_preferred":[
        "Penjor"
    ],
    "wof:name":"Penjor",
    "wof:placetype":"locality"
},
  "geometry": {"coordinates":[116.22329999999999,-8.3385],"type":"Point"}
}