{
  "type": "Feature",
  "properties": {
    "gn:admin1_code":"8.0",
    "gn:asciiname":"Kelabang",
    "gn:country_code":"ID",
    "gn:dem":15,
    "gn:feature_class":"P",
    "gn:feature_code":"PPLA4",
    "gn:name":"Kelabang",
    "gn:population":0,
    "gn:timezone":"Asia/Jakarta",
    "iso:country":"ID",
    "name:ind_x_preferred":[
        "Kelabang"
    ],
    "wof:name":"Kelabang",
    "wof:placetype":"locality"
},
  "geometry": {"coordinates":[111.7274,-6.7799],"type":"Point"}
}