{
  "type": "Feature",
  "properties": {
    "gn:admin1_code":"8.0",
    "gn:asciiname":"Kedungsari",
    "gn:country_code":"ID",
    "gn:dem":112,
    "gn:feature_class":"P",
    "gn:feature_code":"PPL",
    "gn:name":"Kedungsari",
    "gn:population":0,
    "gn:timezone":"Asia/Jakarta",
    "iso:country":"ID",
    "name:ind_x_preferred":[
        "Kedungsari"
    ],
    "wof:name":"Kedungsari",
    "wof:placetype":"locality"
},
  "geometry": {"coordinates":[112.50530000000001,-7.5657],"type":"Point"}
}