{
  "type": "Feature",
  "properties": {
    "gn:admin1_code":"3.0",
    "gn:asciiname":"Tanjungkemuning",
    "gn:country_code":"ID",
    "gn:dem":60,
    "gn:feature_class":"P",
    "gn:feature_code":"PPL",
    "gn:name":"Tanjungkemuning",
    "gn:population":0,
    "gn:timezone":"Asia/Jakarta",
    "iso:country":"ID",
    "name:und_x_variant":[
        "Tandjungkemuning",
        "Tandjoengkemoening",
        "Tanjungkemuning"
    ],
    "wof:name":"Tanjungkemuning",
    "wof:placetype":"locality"
},
  "geometry": {"coordinates":[103.18306,-4.60635],"type":"Point"}
}