{
  "type": "Feature",
  "properties": {
    "gn:admin1_code":"30.0",
    "gn:asciiname":"Cimanggu",
    "gn:country_code":"ID",
    "gn:dem":260,
    "gn:feature_class":"P",
    "gn:feature_code":"PPLA4",
    "gn:name":"Cimanggu",
    "gn:population":0,
    "gn:timezone":"Asia/Jakarta",
    "iso:country":"ID",
    "name:ind_x_preferred":[
        "Cimanggu"
    ],
    "name:und_x_variant":[
        "Tjimanggoe"
    ],
    "wof:name":"Cimanggu",
    "wof:placetype":"locality"
},
  "geometry": {"coordinates":[108.1414,-7.6106],"type":"Point"}
}