{
  "type": "Feature",
  "properties": {
    "gn:admin1_code":"33",
    "gn:asciiname":"Leuwibanteng Lebak",
    "gn:country_code":"ID",
    "gn:dem":19,
    "gn:feature_class":"P",
    "gn:feature_code":"PPL",
    "gn:name":"Leuwibanteng Lebak",
    "gn:population":0,
    "gn:timezone":"Asia/Jakarta",
    "iso:country":"ID",
    "name:ind_x_preferred":[
        "Leuwibanteng Lebak"
    ],
    "name:und_x_variant":[
        "Leuwibanteng"
    ],
    "wof:lang_x_official":[
        "ind"
    ],
    "wof:lang_x_spoken":[
        "ind",
        "eng"
    ],
    "wof:name":"Leuwibanteng Lebak",
    "wof:placetype":"locality"
},
  "geometry": {"coordinates":[106.27070000000001,-6.2884],"type":"Point"}
}