{
  "type": "Feature",
  "properties": {
    "gn:admin1_code":"26",
    "gn:asciiname":"Marendal Pasar Enam",
    "gn:country_code":"ID",
    "gn:dem":51,
    "gn:feature_class":"P",
    "gn:feature_code":"PPL",
    "gn:name":"Marendal Pasar Enam",
    "gn:population":0,
    "gn:timezone":"Asia/Jakarta",
    "iso:country":"ID",
    "name:ind_x_preferred":[
        "Marendal Pasar Enam"
    ],
    "name:und_x_variant":[
        "Marendalpasar 6"
    ],
    "wof:name":"Marendal Pasar Enam",
    "wof:placetype":"locality"
},
  "geometry": {"coordinates":[98.69750000000001,3.5087],"type":"Point"}
}