{
  "type": "Feature",
  "properties": {
    "gn:admin1_code":"38",
    "gn:asciiname":"Pakkawarue",
    "gn:country_code":"ID",
    "gn:dem":75,
    "gn:feature_class":"P",
    "gn:feature_code":"PPL",
    "gn:name":"Pakkawarue",
    "gn:population":0,
    "gn:timezone":"Asia/Makassar",
    "iso:country":"ID",
    "name:ind_x_preferred":[
        "Pakkawarue"
    ],
    "wof:name":"Pakkawarue",
    "wof:placetype":"locality"
},
  "geometry": {"coordinates":[119.98909999999999,-4.5553],"type":"Point"}
}