{
  "type": "Feature",
  "properties": {
    "gn:admin1_code":"8",
    "gn:asciiname":"Korek",
    "gn:country_code":"ID",
    "gn:dem":70,
    "gn:feature_class":"P",
    "gn:feature_code":"PPL",
    "gn:name":"Korek",
    "gn:population":0,
    "gn:timezone":"Asia/Jakarta",
    "iso:country":"ID",
    "name:deu_x_preferred":[
        "Korek"
    ],
    "name:ind_x_preferred":[
        "Korek"
    ],
    "name:pol_x_preferred":[
        "Korek"
    ],
    "wof:lang_x_official":[
        "ind"
    ],
    "wof:lang_x_spoken":[
        "ind",
        "eng"
    ],
    "wof:name":"Korek",
    "wof:placetype":"locality"
},
  "geometry": {"coordinates":[111.36278,-7.35028],"type":"Point"}
}