{
  "type": "Feature",
  "properties": {
    "gn:admin1_code":"30",
    "gn:asciiname":"Mijen",
    "gn:country_code":"ID",
    "gn:dem":8,
    "gn:feature_class":"P",
    "gn:feature_code":"PPL",
    "gn:name":"Mijen",
    "gn:population":0,
    "gn:timezone":"Asia/Jakarta",
    "iso:country":"ID",
    "name:ind_x_preferred":[
        "Mijen"
    ],
    "wof:name":"Mijen",
    "wof:placetype":"locality"
},
  "geometry": {"coordinates":[108.22693999999998,-6.4225],"type":"Point"}
}