{
  "type": "Feature",
  "properties": {
    "gn:admin1_code":"8.0",
    "gn:asciiname":"Kaliboto",
    "gn:country_code":"ID",
    "gn:dem":69,
    "gn:feature_class":"P",
    "gn:feature_code":"PPL",
    "gn:name":"Kaliboto",
    "gn:population":0,
    "gn:timezone":"Asia/Jakarta",
    "iso:country":"ID",
    "name:ind_x_preferred":[
        "Kaliboto"
    ],
    "wof:name":"Kaliboto",
    "wof:placetype":"locality"
},
  "geometry": {"coordinates":[111.94840000000001,-7.7225],"type":"Point"}
}