{
  "type": "Feature",
  "properties": {
    "gn:admin1_code":"8.0",
    "gn:asciiname":"Buyutan",
    "gn:country_code":"ID",
    "gn:dem":474,
    "gn:feature_class":"P",
    "gn:feature_code":"PPL",
    "gn:name":"Buyutan",
    "gn:population":0,
    "gn:timezone":"Asia/Jakarta",
    "iso:country":"ID",
    "name:ind_x_preferred":[
        "Buyutan"
    ],
    "wof:name":"Buyutan",
    "wof:placetype":"locality"
},
  "geometry": {"coordinates":[111.19306,-8.13639],"type":"Point"}
}