{
  "type": "Feature",
  "properties": {
    "gn:admin1_code":"7",
    "gn:asciiname":"Sindangambo",
    "gn:country_code":"ID",
    "gn:dem":20,
    "gn:feature_class":"P",
    "gn:feature_code":"PPL",
    "gn:name":"Sindangambo",
    "gn:population":0,
    "gn:timezone":"Asia/Jakarta",
    "iso:country":"ID",
    "name:ind_x_preferred":[
        "Sindangambo"
    ],
    "wof:name":"Sindangambo",
    "wof:placetype":"locality"
},
  "geometry": {"coordinates":[109.10680000000001,-6.9487],"type":"Point"}
}