{
  "type": "Feature",
  "properties": {
    "gn:admin1_code":"7.0",
    "gn:asciiname":"Karanggayam",
    "gn:country_code":"ID",
    "gn:dem":53,
    "gn:feature_class":"P",
    "gn:feature_code":"PPL",
    "gn:name":"Karanggayam",
    "gn:population":0,
    "gn:timezone":"Asia/Jakarta",
    "iso:country":"ID",
    "name:ind_x_preferred":[
        "Karanggayam"
    ],
    "wof:name":"Karanggayam",
    "wof:placetype":"locality"
},
  "geometry": {"coordinates":[109.44556,-7.74917],"type":"Point"}
}