{
  "type": "Feature",
  "properties": {
    "gn:admin1_code":"1",
    "gn:asciiname":"Puloloih",
    "gn:country_code":"ID",
    "gn:dem":50,
    "gn:feature_class":"P",
    "gn:feature_code":"PPL",
    "gn:name":"Puloloih",
    "gn:population":0,
    "gn:timezone":"Asia/Jakarta",
    "iso:country":"ID",
    "name:ind_x_preferred":[
        "Puloloih"
    ],
    "wof:name":"Puloloih",
    "wof:placetype":"locality"
},
  "geometry": {"coordinates":[95.91419999999999,5.2275],"type":"Point"}
}