{
  "type": "Feature",
  "properties": {
    "gn:admin1_code":"7.0",
    "gn:asciiname":"Krajan Satu Kembang",
    "gn:country_code":"ID",
    "gn:dem":10,
    "gn:feature_class":"P",
    "gn:feature_code":"PPLA4",
    "gn:name":"Krajan Satu Kembang",
    "gn:population":0,
    "gn:timezone":"Asia/Jakarta",
    "iso:country":"ID",
    "name:ind_x_preferred":[
        "Krajan Satu Kembang"
    ],
    "name:und_x_variant":[
        "Krajan 1 Kembang"
    ],
    "wof:lang_x_official":[
        "ind"
    ],
    "wof:lang_x_spoken":[
        "ind",
        "eng"
    ],
    "wof:name":"Krajan Satu Kembang",
    "wof:placetype":"locality"
},
  "geometry": {"coordinates":[111.0223,-6.452],"type":"Point"}
}