{
  "type": "Feature",
  "properties": {
    "gn:admin1_code":"8.0",
    "gn:asciiname":"Karajan",
    "gn:country_code":"ID",
    "gn:dem":22,
    "gn:feature_class":"P",
    "gn:feature_code":"PPL",
    "gn:name":"Karajan",
    "gn:population":0,
    "gn:timezone":"Asia/Jakarta",
    "iso:country":"ID",
    "name:deu_x_preferred":[
        "Karajan"
    ],
    "name:fra_x_preferred":[
        "Karajan"
    ],
    "name:ind_x_preferred":[
        "Karajan"
    ],
    "name:nds_x_preferred":[
        "Karajan"
    ],
    "name:pol_x_preferred":[
        "Karajan"
    ],
    "name:rus_x_preferred":[
        "\u041a\u0430\u0440\u0430\u044f\u043d"
    ],
    "wof:lang_x_official":[
        "ind"
    ],
    "wof:lang_x_spoken":[
        "ind",
        "eng"
    ],
    "wof:name":"Karajan",
    "wof:placetype":"locality"
},
  "geometry": {"coordinates":[113.8702,-6.9935],"type":"Point"}
}