{
  "type": "Feature",
  "properties": {
    "gn:admin1_code":"30.0",
    "gn:asciiname":"Geger",
    "gn:country_code":"ID",
    "gn:dem":811,
    "gn:feature_class":"P",
    "gn:feature_code":"PPL",
    "gn:name":"Geger",
    "gn:population":0,
    "gn:timezone":"Asia/Jakarta",
    "iso:country":"ID",
    "name:ind_x_preferred":[
        "Geger"
    ],
    "name:spa_x_preferred":[
        "Geger"
    ],
    "wof:lang_x_official":[
        "ind"
    ],
    "wof:lang_x_spoken":[
        "ind",
        "eng"
    ],
    "wof:name":"Geger",
    "wof:placetype":"locality"
},
  "geometry": {"coordinates":[107.1888,-7.2686],"type":"Point"}
}