{
  "type": "Feature",
  "properties": {
    "gn:admin1_code":"8",
    "gn:asciiname":"Pateguhan",
    "gn:country_code":"ID",
    "gn:dem":556,
    "gn:feature_class":"P",
    "gn:feature_code":"PPL",
    "gn:name":"Pateguhan",
    "gn:population":0,
    "gn:timezone":"Asia/Jakarta",
    "iso:country":"ID",
    "name:ind_x_preferred":[
        "Pateguhan"
    ],
    "wof:name":"Pateguhan",
    "wof:placetype":"locality"
},
  "geometry": {"coordinates":[112.7632,-7.9453],"type":"Point"}
}