{
  "type": "Feature",
  "properties": {
    "gn:admin1_code":"41",
    "gn:asciiname":"Pateraan",
    "gn:country_code":"ID",
    "gn:dem":15,
    "gn:feature_class":"P",
    "gn:feature_code":"PPL",
    "gn:name":"Pateraan",
    "gn:population":0,
    "gn:timezone":"Asia/Makassar",
    "iso:country":"ID",
    "name:ind_x_preferred":[
        "Pateraan"
    ],
    "wof:name":"Pateraan",
    "wof:placetype":"locality"
},
  "geometry": {"coordinates":[119.2333,-2.3189],"type":"Point"}
}