{
  "type": "Feature",
  "properties": {
    "gn:admin1_code":"38",
    "gn:asciiname":"Paku",
    "gn:country_code":"ID",
    "gn:dem":500,
    "gn:feature_class":"P",
    "gn:feature_code":"PPL",
    "gn:name":"Paku",
    "gn:population":0,
    "gn:timezone":"Asia/Makassar",
    "iso:country":"ID",
    "name:ceb_x_preferred":[
        "Paku"
    ],
    "name:deu_x_preferred":[
        "Paku"
    ],
    "name:ind_x_preferred":[
        "Paku"
    ],
    "name:swe_x_preferred":[
        "Paku"
    ],
    "wof:lang_x_official":[
        "ind"
    ],
    "wof:lang_x_spoken":[
        "ind",
        "eng"
    ],
    "wof:name":"Paku",
    "wof:placetype":"locality"
},
  "geometry": {"coordinates":[120.1151,-5.365],"type":"Point"}
}