{
  "type": "Feature",
  "properties": {
    "gn:admin1_code":"33.0",
    "gn:asciiname":"Tanagara",
    "gn:country_code":"ID",
    "gn:dem":483,
    "gn:feature_class":"P",
    "gn:feature_code":"PPLA4",
    "gn:name":"Tanagara",
    "gn:population":0,
    "gn:timezone":"Asia/Jakarta",
    "iso:country":"ID",
    "name:ind_x_preferred":[
        "Tanagara"
    ],
    "wof:lang_x_official":[
        "ind"
    ],
    "wof:lang_x_spoken":[
        "ind",
        "eng"
    ],
    "wof:name":"Tanagara",
    "wof:placetype":"locality"
},
  "geometry": {"coordinates":[106.09529999999999,-6.2654],"type":"Point"}
}