{
  "type": "Feature",
  "properties": {
    "gn:country":"ID",
    "gn:fcode":"PPL",
    "gn:pop":0,
    "iso:country":"ID",
    "name:ban_x_preferred":[
        "Candi Kalasan"
    ],
    "name:bho_x_preferred":[
        "\u091a\u0902\u0921\u093f \u0915\u093e\u0932\u093e\u0938\u0928"
    ],
    "name:eng_x_preferred":[
        "Kalasan"
    ],
    "name:ind_x_preferred":[
        "Candi Kalasan"
    ],
    "name:jav_x_preferred":[
        "Candhi Kalasan"
    ],
    "name:jpn_x_preferred":[
        "\u30ab\u30e9\u30b5\u30f3\u5bfa\u9662"
    ],
    "name:mal_x_preferred":[
        "\u0d15\u0d32\u0d3e\u0d38\u0d7b"
    ],
    "name:spa_x_preferred":[
        "Kalasan"
    ],
    "name:sun_x_preferred":[
        "Candi Kalasan"
    ],
    "name:tam_x_preferred":[
        "\u0b95\u0bb2\u0bbe\u0b9a\u0bbe\u0ba9\u0bcd \u0b95\u0bcb\u0baf\u0bbf\u0bb2\u0bcd"
    ],
    "name:zho_x_preferred":[
        "\u5361\u62c9\u73ca\u5bfa"
    ],
    "qs:name":"Kalasan",
    "qs:name_adm0":"Indonesia",
    "qs:name_adm1":"Daerah Istimewa Yogyakarta",
    "qs:photos":74,
    "qs:photos_1k":15,
    "qs:photos_9k":1,
    "qs:photos_9r":2,
    "qs:photos_all":74,
    "qs:photos_sr":2,
    "qs:placetype":"Town",
    "qs:pop_sr":"5",
    "wd:wordcount":841,
    "wof:lang_x_official":[
        "ind"
    ],
    "wof:lang_x_spoken":[
        "ind",
        "eng"
    ],
    "wof:name":"Kalasan",
    "wof:placetype":"locality",
    "wof:population":0
},
  "geometry": {"coordinates":[110.46167,-7.7725],"type":"Point"}
}