{
  "type": "Feature",
  "properties": {
    "gn:admin1_code":"26",
    "gn:asciiname":"Parigi",
    "gn:country_code":"ID",
    "gn:dem":120,
    "gn:feature_class":"P",
    "gn:feature_code":"PPL",
    "gn:name":"Parigi",
    "gn:population":0,
    "gn:timezone":"Asia/Jakarta",
    "iso:country":"ID",
    "name:ceb_x_preferred":[
        "Parigi"
    ],
    "name:deu_x_preferred":[
        "Parigi"
    ],
    "name:fra_x_preferred":[
        "Parigi"
    ],
    "name:ind_x_preferred":[
        "Parigi"
    ],
    "name:ita_x_preferred":[
        "Parigi"
    ],
    "name:nld_x_preferred":[
        "Parigi"
    ],
    "name:srp_x_preferred":[
        "Parigi"
    ],
    "name:swe_x_preferred":[
        "Parigi"
    ],
    "wof:lang_x_official":[
        "ind"
    ],
    "wof:lang_x_spoken":[
        "ind",
        "eng"
    ],
    "wof:name":"Parigi",
    "wof:placetype":"locality"
},
  "geometry": {"coordinates":[99.6934,1.78476],"type":"Point"}
}