{
  "type": "Feature",
  "properties": {
    "gn:admin1_code":"0.0",
    "gn:asciiname":"Teluknyirih",
    "gn:cc2":"ID",
    "gn:country_code":"ID",
    "gn:dem":10,
    "gn:feature_class":"P",
    "gn:feature_code":"PPL",
    "gn:name":"Teluknyirih",
    "gn:population":0,
    "gn:timezone":"Asia/Jakarta",
    "iso:country":"ID",
    "name:und_x_variant":[
        "Teluknjirih",
        "Teloeknjirih",
        "Teluknyirih"
    ],
    "wof:lang_x_official":[
        "ind"
    ],
    "wof:lang_x_spoken":[
        "ind",
        "eng"
    ],
    "wof:name":"Teluknyirih",
    "wof:placetype":"locality"
},
  "geometry": {"coordinates":[103.56667,0.23333],"type":"Point"}
}