{
  "type": "Feature",
  "properties": {
    "gn:admin1_code":"7.0",
    "gn:asciiname":"Karangjambu",
    "gn:country_code":"ID",
    "gn:dem":193,
    "gn:feature_class":"P",
    "gn:feature_code":"PPL",
    "gn:name":"Karangjambu",
    "gn:population":0,
    "gn:timezone":"Asia/Jakarta",
    "iso:country":"ID",
    "name:ind_x_preferred":[
        "Karangjambu"
    ],
    "wof:name":"Karangjambu",
    "wof:placetype":"locality"
},
  "geometry": {"coordinates":[108.95111,-7.42056],"type":"Point"}
}