{
  "type": "Feature",
  "properties": {
    "gn:admin1_code":"1.0",
    "gn:asciiname":"Pante Raja",
    "gn:country_code":"ID",
    "gn:dem":72,
    "gn:feature_class":"P",
    "gn:feature_code":"PPLA3",
    "gn:name":"Pante Raja",
    "gn:population":0,
    "gn:timezone":"Asia/Jakarta",
    "iso:country":"ID",
    "name:ind_x_preferred":[
        "Pante Raja"
    ],
    "wof:name":"Pante Raja",
    "wof:placetype":"locality"
},
  "geometry": {"coordinates":[96.14624000000001,5.24525],"type":"Point"}
}