{
  "type": "Feature",
  "properties": {
    "gn:admin1_code":"28.0",
    "gn:asciiname":"Aboru",
    "gn:country_code":"ID",
    "gn:dem":5,
    "gn:feature_class":"P",
    "gn:feature_code":"PPL",
    "gn:name":"Aboru",
    "gn:population":0,
    "gn:timezone":"Asia/Jayapura",
    "iso:country":"ID",
    "name:ind_x_preferred":[
        "Aboru"
    ],
    "wof:name":"Aboru",
    "wof:placetype":"locality"
},
  "geometry": {"coordinates":[128.51156,-3.60485],"type":"Point"}
}