{
  "type": "Feature",
  "properties": {
    "gn:admin1_code":"8.0",
    "gn:asciiname":"Lampeyan",
    "gn:country_code":"ID",
    "gn:dem":89,
    "gn:feature_class":"P",
    "gn:feature_code":"PPL",
    "gn:name":"Lampeyan",
    "gn:population":0,
    "gn:timezone":"Asia/Jakarta",
    "iso:country":"ID",
    "name:ind_x_preferred":[
        "Lampeyan"
    ],
    "wof:name":"Lampeyan",
    "wof:placetype":"locality"
},
  "geometry": {"coordinates":[112.0885,-7.355],"type":"Point"}
}