{
  "type": "Feature",
  "properties": {
    "gn:admin1_code":"37",
    "gn:asciiname":"Telukkeladi",
    "gn:country_code":"ID",
    "gn:dem":13,
    "gn:feature_class":"P",
    "gn:feature_code":"PPL",
    "gn:name":"Telukkeladi",
    "gn:population":0,
    "gn:timezone":"Asia/Jakarta",
    "iso:country":"ID",
    "name:eng_x_preferred":[
        "Telukkeladi"
    ],
    "wof:name":"Telukkeladi",
    "wof:placetype":"locality"
},
  "geometry": {"coordinates":[101.8925,0.3525],"type":"Point"}
}