{
  "type": "Feature",
  "properties": {
    "gn:admin1_code":"30",
    "gn:asciiname":"Babakangunung",
    "gn:country_code":"ID",
    "gn:dem":984,
    "gn:feature_class":"P",
    "gn:feature_code":"PPL",
    "gn:name":"Babakangunung",
    "gn:population":0,
    "gn:timezone":"Asia/Jakarta",
    "iso:country":"ID",
    "name:ind_x_preferred":[
        "Babakangunung"
    ],
    "wof:name":"Babakangunung",
    "wof:placetype":"locality"
},
  "geometry": {"coordinates":[107.65582999999999,-6.73139],"type":"Point"}
}