{
  "type": "Feature",
  "properties": {
    "gn:admin1_code":"2",
    "gn:asciiname":"Banjar Mengandang",
    "gn:country_code":"ID",
    "gn:dem":1118,
    "gn:feature_class":"P",
    "gn:feature_code":"PPL",
    "gn:name":"Banjar Mengandang",
    "gn:population":0,
    "gn:timezone":"Asia/Makassar",
    "iso:country":"ID",
    "name:ind_x_preferred":[
        "Banjar Mengandang"
    ],
    "wof:name":"Banjar Mengandang",
    "wof:placetype":"locality"
},
  "geometry": {"coordinates":[115.22790000000001,-8.1931],"type":"Point"}
}