{
  "type": "Feature",
  "properties": {
    "gn:admin1_code":"30",
    "gn:asciiname":"Dusunpon",
    "gn:country_code":"ID",
    "gn:dem":201,
    "gn:feature_class":"P",
    "gn:feature_code":"PPL",
    "gn:name":"Dusunpon",
    "gn:population":0,
    "gn:timezone":"Asia/Jakarta",
    "iso:country":"ID",
    "name:ind_x_preferred":[
        "Dusunpon"
    ],
    "wof:name":"Dusunpon",
    "wof:placetype":"locality"
},
  "geometry": {"coordinates":[108.49111000000001,-6.7875],"type":"Point"}
}