{
  "type": "Feature",
  "properties": {
    "gn:admin1_code":"7",
    "gn:asciiname":"Pilalengkung",
    "gn:country_code":"ID",
    "gn:dem":139,
    "gn:feature_class":"P",
    "gn:feature_code":"PPL",
    "gn:name":"Pilalengkung",
    "gn:population":0,
    "gn:timezone":"Asia/Jakarta",
    "iso:country":"ID",
    "name:ind_x_preferred":[
        "Pilalengkung"
    ],
    "wof:name":"Pilalengkung",
    "wof:placetype":"locality"
},
  "geometry": {"coordinates":[111.09361,-7.24528],"type":"Point"}
}