{
  "type": "Feature",
  "properties": {
    "gn:admin1_code":"30",
    "gn:asciiname":"Cisasah",
    "gn:country_code":"ID",
    "gn:dem":385,
    "gn:feature_class":"P",
    "gn:feature_code":"PPL",
    "gn:name":"Cisasah",
    "gn:population":0,
    "gn:timezone":"Asia/Jakarta",
    "iso:country":"ID",
    "name:ind_x_preferred":[
        "Cisasah"
    ],
    "wof:name":"Cisasah",
    "wof:placetype":"locality"
},
  "geometry": {"coordinates":[106.71861,-6.62333],"type":"Point"}
}