{
  "type": "Feature",
  "properties": {
    "gn:admin1_code":"33",
    "gn:asciiname":"Paru",
    "gn:country_code":"ID",
    "gn:dem":127,
    "gn:feature_class":"P",
    "gn:feature_code":"PPL",
    "gn:name":"Paru",
    "gn:population":0,
    "gn:timezone":"Asia/Jakarta",
    "iso:country":"ID",
    "name:ast_x_preferred":[
        "Paru"
    ],
    "name:fra_x_preferred":[
        "Paru"
    ],
    "name:scn_x_preferred":[
        "Paru"
    ],
    "wof:name":"Paru",
    "wof:placetype":"locality"
},
  "geometry": {"coordinates":[106.38249999999999,-6.49028],"type":"Point"}
}