{
  "type": "Feature",
  "properties": {
    "gn:admin1_code":"18.0",
    "gn:asciiname":"Paudolor",
    "gn:country_code":"ID",
    "gn:dem":358,
    "gn:feature_class":"P",
    "gn:feature_code":"PPL",
    "gn:name":"Paudolor",
    "gn:population":0,
    "gn:timezone":"Asia/Makassar",
    "iso:country":"ID",
    "name:ind_x_preferred":[
        "Paudolor"
    ],
    "wof:name":"Paudolor",
    "wof:placetype":"locality"
},
  "geometry": {"coordinates":[122.5018,-8.624],"type":"Point"}
}