{
  "type": "Feature",
  "properties": {
    "gn:admin1_code":"33.0",
    "gn:asciiname":"Kadubalenyomplong",
    "gn:country_code":"ID",
    "gn:dem":140,
    "gn:feature_class":"P",
    "gn:feature_code":"PPL",
    "gn:name":"Kadubalenyomplong",
    "gn:population":0,
    "gn:timezone":"Asia/Jakarta",
    "iso:country":"ID",
    "name:ind_x_preferred":[
        "Kadubalenyomplong"
    ],
    "wof:name":"Kadubalenyomplong",
    "wof:placetype":"locality"
},
  "geometry": {"coordinates":[106.1027,-6.3495],"type":"Point"}
}