{
  "type": "Feature",
  "properties": {
    "gn:admin1_code":"15.0",
    "gn:asciiname":"Umbulan Sukarukun",
    "gn:country_code":"ID",
    "gn:dem":50,
    "gn:feature_class":"P",
    "gn:feature_code":"PPL",
    "gn:name":"Umbulan Sukarukun",
    "gn:population":0,
    "gn:timezone":"Asia/Jakarta",
    "iso:country":"ID",
    "name:ind_x_preferred":[
        "Umbulan Sukarukun"
    ],
    "wof:name":"Umbulan Sukarukun",
    "wof:placetype":"locality"
},
  "geometry": {"coordinates":[104.86286,-4.76989],"type":"Point"}
}