{
  "type": "Feature",
  "properties": {
    "gn:admin1_code":"0.0",
    "gn:asciiname":"Buayan",
    "gn:cc2":"ID",
    "gn:country_code":"ID",
    "gn:dem":18,
    "gn:feature_class":"P",
    "gn:feature_code":"PPL",
    "gn:name":"Buayan",
    "gn:population":0,
    "gn:timezone":"Asia/Pontianak",
    "iso:country":"ID",
    "name:und_x_variant":[
        "Buajan",
        "Boeajan",
        "Boewajan",
        "Buayan"
    ],
    "wof:name":"Buayan",
    "wof:placetype":"locality"
},
  "geometry": {"coordinates":[109.83333,0.16667],"type":"Point"}
}