{
  "type": "Feature",
  "properties": {
    "gn:admin1_code":"30",
    "gn:asciiname":"Curug",
    "gn:cc2":"ID",
    "gn:country_code":"ID",
    "gn:dem":815,
    "gn:feature_class":"P",
    "gn:feature_code":"PPL",
    "gn:name":"Curug",
    "gn:population":0,
    "gn:timezone":"Asia/Jakarta",
    "iso:country":"ID",
    "name:und_x_variant":[
        "Tjurug",
        "Curug"
    ],
    "wof:name":"Curug",
    "wof:placetype":"locality"
},
  "geometry": {"coordinates":[107.66777999999999,-7.04111],"type":"Point"}
}