{
  "type": "Feature",
  "properties": {
    "gn:admin1_code":"7.0",
    "gn:asciiname":"Cikakak",
    "gn:country_code":"ID",
    "gn:dem":44,
    "gn:feature_class":"P",
    "gn:feature_code":"PPL",
    "gn:name":"Cikakak",
    "gn:population":0,
    "gn:timezone":"Asia/Jakarta",
    "iso:country":"ID",
    "name:ind_x_preferred":[
        "Cikakak"
    ],
    "wof:name":"Cikakak",
    "wof:placetype":"locality"
},
  "geometry": {"coordinates":[109.05833,-7.4775],"type":"Point"}
}