{
  "type": "Feature",
  "properties": {
    "gn:admin1_code":"07",
    "gn:asciiname":"Gumiwang A",
    "gn:country_code":"ID",
    "gn:dem":922,
    "gn:feature_class":"P",
    "gn:feature_code":"PPL",
    "gn:name":"Gumiwang A",
    "gn:population":0,
    "gn:timezone":"Asia/Jakarta",
    "iso:country":"ID",
    "name:und_x_variant":[
        "Gumiwang",
        "Gumiwang A"
    ],
    "wof:name":"Gumiwang A",
    "wof:placetype":"locality"
},
  "geometry": {"coordinates":[110.34417000000001,-7.42167],"type":"Point"}
}