{
  "type": "Feature",
  "properties": {
    "gn:admin1_code":"26",
    "gn:asciiname":"Pondok Timbang Deli",
    "gn:country_code":"ID",
    "gn:dem":39,
    "gn:feature_class":"P",
    "gn:feature_code":"PPL",
    "gn:name":"Pondok Timbang Deli",
    "gn:population":0,
    "gn:timezone":"Asia/Jakarta",
    "iso:country":"ID",
    "name:ind_x_preferred":[
        "Pondok Timbang Deli"
    ],
    "wof:name":"Pondok Timbang Deli",
    "wof:placetype":"locality"
},
  "geometry": {"coordinates":[98.9016,3.4519],"type":"Point"}
}