{
  "type": "Feature",
  "properties": {
    "gn:admin1_code":"18.0",
    "gn:asciiname":"Waturiku",
    "gn:country_code":"ID",
    "gn:dem":1157,
    "gn:feature_class":"P",
    "gn:feature_code":"PPL",
    "gn:name":"Waturiku",
    "gn:population":0,
    "gn:timezone":"Asia/Makassar",
    "iso:country":"ID",
    "name:ind_x_preferred":[
        "Waturiku"
    ],
    "wof:name":"Waturiku",
    "wof:placetype":"locality"
},
  "geometry": {"coordinates":[120.98690000000001,-8.7694],"type":"Point"}
}