{
  "type": "Feature",
  "properties": {
    "gn:admin1_code":"30",
    "gn:asciiname":"Kadongdong",
    "gn:country_code":"ID",
    "gn:dem":23,
    "gn:feature_class":"P",
    "gn:feature_code":"PPL",
    "gn:name":"Kadongdong",
    "gn:population":0,
    "gn:timezone":"Asia/Jakarta",
    "iso:country":"ID",
    "name:ind_x_preferred":[
        "Kadongdong"
    ],
    "wof:name":"Kadongdong",
    "wof:placetype":"locality"
},
  "geometry": {"coordinates":[107.41889,-6.35889],"type":"Point"}
}