{
  "type": "Feature",
  "properties": {
    "gn:admin1_code":"1",
    "gn:asciiname":"Seuneubok Peusangan",
    "gn:country_code":"ID",
    "gn:dem":6,
    "gn:feature_class":"P",
    "gn:feature_code":"PPL",
    "gn:name":"Seuneubok Peusangan",
    "gn:population":0,
    "gn:timezone":"Asia/Jakarta",
    "iso:country":"ID",
    "name:ind_x_preferred":[
        "Seuneubok Peusangan"
    ],
    "wof:name":"Seuneubok Peusangan",
    "wof:placetype":"locality"
},
  "geometry": {"coordinates":[97.90089999999999,4.7637],"type":"Point"}
}