{
  "type": "Feature",
  "properties": {
    "gn:country":"ID",
    "gn:fcode":"PPL",
    "gn:pop":0,
    "iso:country":"ID",
    "name:ace_x_preferred":[
        "Ulee Kareung"
    ],
    "name:bug_x_preferred":[
        "Ulee Kareung"
    ],
    "name:cat_x_preferred":[
        "Ulee Kareung"
    ],
    "name:deu_x_preferred":[
        "Ulee Kareung"
    ],
    "name:eng_x_preferred":[
        "Ulee Kareung"
    ],
    "name:fra_x_preferred":[
        "Ulee Kareung"
    ],
    "name:glg_x_preferred":[
        "Ulee Kareung"
    ],
    "name:ind_x_preferred":[
        "Ulee Kareng"
    ],
    "name:ind_x_variant":[
        "Desa Sokaraja Kidul",
        "Ulee Kareung"
    ],
    "name:jav_x_preferred":[
        "Ulee Kareung"
    ],
    "name:msa_x_preferred":[
        "Ulee Kareung"
    ],
    "name:nld_x_preferred":[
        "Ulee Kareung"
    ],
    "name:por_x_preferred":[
        "Ulee Kareung"
    ],
    "name:spa_x_preferred":[
        "Ulee Kareung"
    ],
    "name:sun_x_preferred":[
        "Ulee Kareung"
    ],
    "name:unk_x_variant":[
        "Uleekaneng"
    ],
    "qs:name":"Ulee Kareng",
    "qs:name_adm0":"Indonesia",
    "qs:name_adm1":"Nanggroe Aceh Darussalam",
    "qs:photos":99,
    "qs:photos_1k":20,
    "qs:photos_9k":1,
    "qs:photos_9r":3,
    "qs:photos_all":99,
    "qs:photos_sr":3,
    "qs:placetype":"Town",
    "qs:pop_sr":"0",
    "wof:lang_x_official":[
        "ind"
    ],
    "wof:lang_x_spoken":[
        "ind",
        "eng"
    ],
    "wof:name":"Ulee Kareng",
    "wof:placetype":"locality",
    "wof:population":0
},
  "geometry": {"coordinates":[95.3558,5.551],"type":"Point"}
}