{
  "type": "Feature",
  "properties": {
    "gn:admin1_code":"22.0",
    "gn:asciiname":"Labuan Tubelo",
    "gn:cc2":"ID",
    "gn:country_code":"ID",
    "gn:dem":56,
    "gn:feature_class":"P",
    "gn:feature_code":"PPL",
    "gn:name":"Labuan Tubelo",
    "gn:population":0,
    "gn:timezone":"Asia/Makassar",
    "iso:country":"ID",
    "name:und_x_variant":[
        "Laboean-tobelo",
        "Laboehantobelo",
        "Labuhantobelo",
        "Labuan Tubelo"
    ],
    "wof:lang_x_official":[
        "ind"
    ],
    "wof:lang_x_spoken":[
        "ind",
        "eng"
    ],
    "wof:name":"Labuan Tubelo",
    "wof:placetype":"locality"
},
  "geometry": {"coordinates":[122.96944000000001,-4.41306],"type":"Point"}
}