{
  "type": "Feature",
  "properties": {
    "gn:country":"ID",
    "gn:fcode":"PPLA3",
    "gn:pop":0,
    "iso:country":"ID",
    "name:ind_x_preferred":[
        "Gedongtataan"
    ],
    "name:ind_x_variant":[
        "Gedong Tataan"
    ],
    "qs:name":"Gedongtataan",
    "qs:photos_9r":0,
    "qs:photos_sr":0,
    "qs:pop_sr":"0",
    "wof:lang_x_official":[
        "ind"
    ],
    "wof:lang_x_spoken":[
        "ind",
        "eng"
    ],
    "wof:name":"Gedongtataan",
    "wof:placetype":"locality",
    "wof:population":0
},
  "geometry": {"coordinates":[105.0955,-5.3827],"type":"Point"}
}