{
  "type": "Feature",
  "properties": {
    "gn:admin1_code":"38.0",
    "gn:asciiname":"Karambua Satu",
    "gn:country_code":"ID",
    "gn:dem":23,
    "gn:feature_class":"P",
    "gn:feature_code":"PPL",
    "gn:name":"Karambua Satu",
    "gn:population":0,
    "gn:timezone":"Asia/Makassar",
    "iso:country":"ID",
    "name:ind_x_preferred":[
        "Karambua Satu"
    ],
    "name:und_x_variant":[
        "Karambua 1"
    ],
    "wof:name":"Karambua Satu",
    "wof:placetype":"locality"
},
  "geometry": {"coordinates":[120.8656,-2.572],"type":"Point"}
}