{
  "type": "Feature",
  "properties": {
    "gn:admin1_code":"30",
    "gn:asciiname":"Citapen",
    "gn:cc2":"ID",
    "gn:country_code":"ID",
    "gn:dem":1130,
    "gn:feature_class":"P",
    "gn:feature_code":"PPL",
    "gn:name":"Citapen",
    "gn:population":0,
    "gn:timezone":"Asia/Jakarta",
    "iso:country":"ID",
    "name:und_x_variant":[
        "Tjitapen",
        "Citapen"
    ],
    "wof:name":"Citapen",
    "wof:placetype":"locality"
},
  "geometry": {"coordinates":[107.67778,-6.86139],"type":"Point"}
}