{
  "type": "Feature",
  "properties": {
    "gn:admin1_code":"33.0",
    "gn:asciiname":"Kelapa",
    "gn:country_code":"ID",
    "gn:dem":17,
    "gn:feature_class":"P",
    "gn:feature_code":"PPL",
    "gn:name":"Kelapa",
    "gn:population":0,
    "gn:timezone":"Asia/Jakarta",
    "iso:country":"ID",
    "name:ceb_x_preferred":[
        "Kelapa"
    ],
    "name:ind_x_preferred":[
        "Kelapa"
    ],
    "name:nld_x_preferred":[
        "Kelapa"
    ],
    "name:swe_x_preferred":[
        "Kelapa"
    ],
    "wof:name":"Kelapa",
    "wof:placetype":"locality"
},
  "geometry": {"coordinates":[105.8021,-6.7636],"type":"Point"}
}