{
  "type": "Feature",
  "properties": {
    "gn:admin1_code":"30.0",
    "gn:asciiname":"Cirapih",
    "gn:country_code":"ID",
    "gn:dem":418,
    "gn:feature_class":"P",
    "gn:feature_code":"PPL",
    "gn:name":"Cirapih",
    "gn:population":0,
    "gn:timezone":"Asia/Jakarta",
    "iso:country":"ID",
    "name:ind_x_preferred":[
        "Cirapih"
    ],
    "name:und_x_variant":[
        "Tjiropoh"
    ],
    "wof:lang_x_official":[
        "ind"
    ],
    "wof:lang_x_spoken":[
        "ind",
        "eng"
    ],
    "wof:name":"Cirapih",
    "wof:placetype":"locality"
},
  "geometry": {"coordinates":[108.19370000000001,-7.2932],"type":"Point"}
}