{
  "type": "Feature",
  "properties": {
    "gn:admin1_code":"7.0",
    "gn:asciiname":"Randusari",
    "gn:country_code":"ID",
    "gn:dem":1001,
    "gn:feature_class":"P",
    "gn:feature_code":"PPL",
    "gn:name":"Randusari",
    "gn:population":0,
    "gn:timezone":"Asia/Jakarta",
    "iso:country":"ID",
    "wof:name":"Randusari",
    "wof:placetype":"locality"
},
  "geometry": {"coordinates":[110.50082999999999,-7.44778],"type":"Point"}
}