{
  "type": "Feature",
  "properties": {
    "gn:admin1_code":"08",
    "gn:asciiname":"Setingi",
    "gn:country_code":"ID",
    "gn:dem":35,
    "gn:feature_class":"P",
    "gn:feature_code":"PPL",
    "gn:name":"Setingi",
    "gn:population":0,
    "gn:timezone":"Asia/Jakarta",
    "iso:country":"ID",
    "name:ind_x_preferred":[
        "Setingi"
    ],
    "name:und_x_variant":[
        "Setinggi"
    ],
    "wof:name":"Setingi",
    "wof:placetype":"locality"
},
  "geometry": {"coordinates":[112.62260000000001,-7.1601],"type":"Point"}
}