{
  "type": "Feature",
  "properties": {
    "gn:admin1_code":"30",
    "gn:asciiname":"Rancalame",
    "gn:country_code":"ID",
    "gn:dem":663,
    "gn:feature_class":"P",
    "gn:feature_code":"PPL",
    "gn:name":"Rancalame",
    "gn:population":0,
    "gn:timezone":"Asia/Jakarta",
    "iso:country":"ID",
    "name:ind_x_preferred":[
        "Rancalame"
    ],
    "name:und_x_variant":[
        "Rantjalame"
    ],
    "wof:name":"Rancalame",
    "wof:placetype":"locality"
},
  "geometry": {"coordinates":[107.68222,-6.98694],"type":"Point"}
}