{
  "type": "Feature",
  "properties": {
    "gn:admin1_code":"7.0",
    "gn:asciiname":"Wanadri",
    "gn:country_code":"ID",
    "gn:dem":915,
    "gn:feature_class":"P",
    "gn:feature_code":"PPL",
    "gn:name":"Wanadri",
    "gn:population":0,
    "gn:timezone":"Asia/Jakarta",
    "iso:country":"ID",
    "wof:name":"Wanadri",
    "wof:placetype":"locality"
},
  "geometry": {"coordinates":[110.11388999999998,-7.45056],"type":"Point"}
}