{
  "type": "Feature",
  "properties": {
    "gn:admin1_code":"7.0",
    "gn:asciiname":"Sari",
    "gn:country_code":"ID",
    "gn:dem":1121,
    "gn:feature_class":"P",
    "gn:feature_code":"PPL",
    "gn:name":"Sari",
    "gn:population":0,
    "gn:timezone":"Asia/Jakarta",
    "iso:country":"ID",
    "wof:name":"Sari",
    "wof:placetype":"locality"
},
  "geometry": {"coordinates":[110.1125,-7.4275],"type":"Point"}
}