{
  "type": "Feature",
  "properties": {
    "gn:admin1_code":"7.0",
    "gn:asciiname":"Cikirai",
    "gn:country_code":"ID",
    "gn:dem":56,
    "gn:feature_class":"P",
    "gn:feature_code":"PPL",
    "gn:name":"Cikirai",
    "gn:population":0,
    "gn:timezone":"Asia/Jakarta",
    "iso:country":"ID",
    "name:ind_x_preferred":[
        "Cikirai"
    ],
    "wof:name":"Cikirai",
    "wof:placetype":"locality"
},
  "geometry": {"coordinates":[108.6802,-7.3209],"type":"Point"}
}