{
  "type": "Feature",
  "properties": {
    "gn:admin1_code":"32.0",
    "gn:asciiname":"Talangkotabesi",
    "gn:country_code":"ID",
    "gn:dem":24,
    "gn:feature_class":"P",
    "gn:feature_code":"PPL",
    "gn:name":"Talangkotabesi",
    "gn:population":0,
    "gn:timezone":"Asia/Jakarta",
    "iso:country":"ID",
    "name:ind_x_preferred":[
        "Talangkotabesi"
    ],
    "wof:name":"Talangkotabesi",
    "wof:placetype":"locality"
},
  "geometry": {"coordinates":[104.8776,-3.6134],"type":"Point"}
}