{
  "type": "Feature",
  "properties": {
    "gn:admin1_code":"26.0",
    "gn:asciiname":"Sosorgodang Dua",
    "gn:country_code":"ID",
    "gn:dem":947,
    "gn:feature_class":"P",
    "gn:feature_code":"PPL",
    "gn:name":"Sosorgodang Dua",
    "gn:population":0,
    "gn:timezone":"Asia/Jakarta",
    "iso:country":"ID",
    "name:ind_x_preferred":[
        "Sosorgodang Dua"
    ],
    "name:und_x_variant":[
        "Sosorgodang 2"
    ],
    "wof:name":"Sosorgodang Dua",
    "wof:placetype":"locality"
},
  "geometry": {"coordinates":[98.64709999999999,2.1194],"type":"Point"}
}