{
  "type": "Feature",
  "properties": {
    "gn:admin1_code":"07",
    "gn:asciiname":"Karanganyar",
    "gn:country_code":"ID",
    "gn:dem":423,
    "gn:feature_class":"P",
    "gn:feature_code":"PPL",
    "gn:name":"Karanganyar",
    "gn:population":0,
    "gn:timezone":"Asia/Jakarta",
    "iso:country":"ID",
    "name:ceb_x_preferred":[
        "Karanganyar"
    ],
    "name:ind_x_preferred":[
        "Karanganyar"
    ],
    "name:jav_x_preferred":[
        "Karanganyar"
    ],
    "name:nld_x_preferred":[
        "Karanganyar"
    ],
    "name:swe_x_preferred":[
        "Karanganyar"
    ],
    "name:und_x_variant":[
        "Kuranganjar",
        "Karanganyar"
    ],
    "wof:lang_x_official":[
        "ind"
    ],
    "wof:lang_x_spoken":[
        "ind",
        "eng"
    ],
    "wof:name":"Karanganyar",
    "wof:placetype":"locality"
},
  "geometry": {"coordinates":[110.25528,-7.44861],"type":"Point"}
}