{
  "type": "Feature",
  "properties": {
    "gn:admin1_code":"38",
    "gn:asciiname":"Silanggaya",
    "gn:country_code":"ID",
    "gn:dem":1212,
    "gn:feature_class":"P",
    "gn:feature_code":"PPL",
    "gn:name":"Silanggaya",
    "gn:population":0,
    "gn:timezone":"Asia/Makassar",
    "iso:country":"ID",
    "name:ind_x_preferred":[
        "Silanggaya"
    ],
    "wof:name":"Silanggaya",
    "wof:placetype":"locality"
},
  "geometry": {"coordinates":[119.9761,-5.2508],"type":"Point"}
}