{
  "type": "Feature",
  "properties": {
    "gn:admin1_code":"7.0",
    "gn:asciiname":"Cangkring",
    "gn:country_code":"ID",
    "gn:dem":58,
    "gn:feature_class":"P",
    "gn:feature_code":"PPL",
    "gn:name":"Cangkring",
    "gn:population":0,
    "gn:timezone":"Asia/Jakarta",
    "iso:country":"ID",
    "name:ind_x_preferred":[
        "Cangkring"
    ],
    "wof:name":"Cangkring",
    "wof:placetype":"locality"
},
  "geometry": {"coordinates":[111.036,-6.9125],"type":"Point"}
}