{
  "type": "Feature",
  "properties": {
    "gn:admin1_code":"8.0",
    "gn:asciiname":"Malang Dua",
    "gn:country_code":"ID",
    "gn:dem":109,
    "gn:feature_class":"P",
    "gn:feature_code":"PPL",
    "gn:name":"Malang Dua",
    "gn:population":0,
    "gn:timezone":"Asia/Jakarta",
    "iso:country":"ID",
    "name:ind_x_preferred":[
        "Malang Dua"
    ],
    "wof:name":"Malang Dua",
    "wof:placetype":"locality"
},
  "geometry": {"coordinates":[111.4268,-7.5963],"type":"Point"}
}