{
  "type": "Feature",
  "properties": {
    "gn:admin1_code":"26",
    "gn:asciiname":"Berasbulan",
    "gn:country_code":"ID",
    "gn:dem":115,
    "gn:feature_class":"P",
    "gn:feature_code":"PPL",
    "gn:name":"Berasbulan",
    "gn:population":0,
    "gn:timezone":"Asia/Jakarta",
    "iso:country":"ID",
    "name:ind_x_preferred":[
        "Berasbulan"
    ],
    "wof:name":"Berasbulan",
    "wof:placetype":"locality"
},
  "geometry": {"coordinates":[98.72709999999999,3.391],"type":"Point"}
}