{
  "type": "Feature",
  "properties": {
    "gn:admin1_code":"7",
    "gn:asciiname":"Ngendak",
    "gn:country_code":"ID",
    "gn:dem":464,
    "gn:feature_class":"P",
    "gn:feature_code":"PPL",
    "gn:name":"Ngendak",
    "gn:population":0,
    "gn:timezone":"Asia/Jakarta",
    "iso:country":"ID",
    "name:ind_x_preferred":[
        "Ngendak"
    ],
    "wof:name":"Ngendak",
    "wof:placetype":"locality"
},
  "geometry": {"coordinates":[111.17306000000001,-7.83056],"type":"Point"}
}