{
  "type": "Feature",
  "properties": {
    "gn:admin1_code":"30.0",
    "gn:asciiname":"Cigintung",
    "gn:country_code":"ID",
    "gn:dem":222,
    "gn:feature_class":"P",
    "gn:feature_code":"PPL",
    "gn:name":"Cigintung",
    "gn:population":0,
    "gn:timezone":"Asia/Jakarta",
    "iso:country":"ID",
    "name:ind_x_preferred":[
        "Cigintung"
    ],
    "name:und_x_variant":[
        "Tjigintoeng"
    ],
    "wof:name":"Cigintung",
    "wof:placetype":"locality"
},
  "geometry": {"coordinates":[108.45440000000001,-7.6048],"type":"Point"}
}