{
  "type": "Feature",
  "properties": {
    "gn:admin1_code":"8.0",
    "gn:asciiname":"Wonoasih Kulon",
    "gn:country_code":"ID",
    "gn:dem":488,
    "gn:feature_class":"P",
    "gn:feature_code":"PPL",
    "gn:name":"Wonoasih Kulon",
    "gn:population":0,
    "gn:timezone":"Asia/Jakarta",
    "iso:country":"ID",
    "name:ind_x_preferred":[
        "Wonoasih Kulon"
    ],
    "wof:name":"Wonoasih Kulon",
    "wof:placetype":"locality"
},
  "geometry": {"coordinates":[114.0703,-8.2665],"type":"Point"}
}