{
  "type": "Feature",
  "properties": {
    "gn:admin1_code":"7.0",
    "gn:asciiname":"Karangsambung",
    "gn:country_code":"ID",
    "gn:dem":406,
    "gn:feature_class":"P",
    "gn:feature_code":"PPL",
    "gn:name":"Karangsambung",
    "gn:population":0,
    "gn:timezone":"Asia/Jakarta",
    "iso:country":"ID",
    "wof:name":"Karangsambung",
    "wof:placetype":"locality"
},
  "geometry": {"coordinates":[110.18528000000001,-7.48167],"type":"Point"}
}