{
  "type": "Feature",
  "properties": {
    "gn:admin1_code":"30.0",
    "gn:asciiname":"Telagasari",
    "gn:country_code":"ID",
    "gn:dem":96,
    "gn:feature_class":"P",
    "gn:feature_code":"PPL",
    "gn:name":"Telagasari",
    "gn:population":0,
    "gn:timezone":"Asia/Jakarta",
    "iso:country":"ID",
    "name:ind_x_preferred":[
        "Telagasari"
    ],
    "wof:name":"Telagasari",
    "wof:placetype":"locality"
},
  "geometry": {"coordinates":[108.2022,-7.6317],"type":"Point"}
}