{
  "type": "Feature",
  "properties": {
    "gn:admin1_code":"7",
    "gn:asciiname":"Kaliseneng",
    "gn:country_code":"ID",
    "gn:dem":514,
    "gn:feature_class":"P",
    "gn:feature_code":"PPL",
    "gn:name":"Kaliseneng",
    "gn:population":0,
    "gn:timezone":"Asia/Jakarta",
    "iso:country":"ID",
    "name:ind_x_preferred":[
        "Kaliseneng"
    ],
    "wof:name":"Kaliseneng",
    "wof:placetype":"locality"
},
  "geometry": {"coordinates":[109.8309,-7.0524],"type":"Point"}
}