{
  "type": "Feature",
  "properties": {
    "gn:country":"ID",
    "gn:fcode":"PPL",
    "gn:pop":0,
    "iso:country":"ID",
    "name:ind_x_preferred":[
        "Cililitan"
    ],
    "name:unk_x_variant":[
        "Tjililitan"
    ],
    "qs:name":"Cililitan",
    "qs:name_adm0":"Indonesia",
    "qs:name_adm1":"Jakarta Raya",
    "qs:photos_9r":0,
    "qs:photos_sr":0,
    "qs:placetype":"Suburb",
    "qs:pop_sr":"0",
    "wof:name":"Cililitan",
    "wof:placetype":"neighbourhood",
    "wof:population":0
},
  "geometry": {"coordinates":[106.87130000000001,-6.2616],"type":"Point"}
}