{
  "type": "Feature",
  "properties": {
    "gn:admin1_code":"30.0",
    "gn:asciiname":"Leuwipanjang",
    "gn:country_code":"ID",
    "gn:dem":181,
    "gn:feature_class":"P",
    "gn:feature_code":"PPL",
    "gn:name":"Leuwipanjang",
    "gn:population":0,
    "gn:timezone":"Asia/Jakarta",
    "iso:country":"ID",
    "name:ind_x_preferred":[
        "Leuwipanjang"
    ],
    "wof:name":"Leuwipanjang",
    "wof:placetype":"locality"
},
  "geometry": {"coordinates":[106.74079999999999,-7.2848],"type":"Point"}
}