{
  "type": "Feature",
  "properties": {
    "gn:admin1_code":"7.0",
    "gn:asciiname":"Lengkong",
    "gn:country_code":"ID",
    "gn:dem":197,
    "gn:feature_class":"P",
    "gn:feature_code":"PPL",
    "gn:name":"Lengkong",
    "gn:population":0,
    "gn:timezone":"Asia/Jakarta",
    "iso:country":"ID",
    "name:ind_x_preferred":[
        "Lengkong"
    ],
    "wof:name":"Lengkong",
    "wof:placetype":"locality"
},
  "geometry": {"coordinates":[109.57666999999999,-7.39472],"type":"Point"}
}