{
  "type": "Feature",
  "properties": {
    "gn:admin1_code":"8.0",
    "gn:asciiname":"Karyabakti",
    "gn:country_code":"ID",
    "gn:dem":9,
    "gn:feature_class":"P",
    "gn:feature_code":"PPL",
    "gn:name":"Karyabakti",
    "gn:population":0,
    "gn:timezone":"Asia/Jakarta",
    "iso:country":"ID",
    "name:ind_x_preferred":[
        "Karyabakti"
    ],
    "wof:name":"Karyabakti",
    "wof:placetype":"locality"
},
  "geometry": {"coordinates":[112.8921,-7.645],"type":"Point"}
}