{
  "type": "Feature",
  "properties": {
    "gn:admin1_code":"18",
    "gn:asciiname":"Rambari",
    "gn:country_code":"ID",
    "gn:dem":493,
    "gn:feature_class":"P",
    "gn:feature_code":"PPL",
    "gn:name":"Rambari",
    "gn:population":0,
    "gn:timezone":"Asia/Makassar",
    "iso:country":"ID",
    "name:ind_x_preferred":[
        "Rambari"
    ],
    "wof:name":"Rambari",
    "wof:placetype":"locality"
},
  "geometry": {"coordinates":[119.81570000000001,-9.7314],"type":"Point"}
}