{
  "type": "Feature",
  "properties": {
    "gn:admin1_code":"07",
    "gn:asciiname":"Sremben",
    "gn:country_code":"ID",
    "gn:dem":1375,
    "gn:feature_class":"P",
    "gn:feature_code":"PPL",
    "gn:name":"Sremben",
    "gn:population":0,
    "gn:timezone":"Asia/Jakarta",
    "iso:country":"ID",
    "name:und_x_variant":[
        "Sremban",
        "Sremben"
    ],
    "wof:name":"Sremben",
    "wof:placetype":"locality"
},
  "geometry": {"coordinates":[110.39806000000002,-7.46333],"type":"Point"}
}