{
  "type": "Feature",
  "properties": {
    "gn:admin1_code":"15.0",
    "gn:asciiname":"Kuripan",
    "gn:country_code":"ID",
    "gn:dem":29,
    "gn:feature_class":"P",
    "gn:feature_code":"PPL",
    "gn:name":"Kuripan",
    "gn:population":0,
    "gn:timezone":"Asia/Jakarta",
    "iso:country":"ID",
    "name:ind_x_preferred":[
        "Kuripan"
    ],
    "name:und_x_variant":[
        "Koeripan"
    ],
    "wof:name":"Kuripan",
    "wof:placetype":"locality"
},
  "geometry": {"coordinates":[105.54944999999999,-5.07195],"type":"Point"}
}