{
  "type": "Feature",
  "properties": {
    "gn:admin1_code":"26",
    "gn:asciiname":"Tunggorono Empat",
    "gn:country_code":"ID",
    "gn:dem":29,
    "gn:feature_class":"P",
    "gn:feature_code":"PPL",
    "gn:name":"Tunggorono Empat",
    "gn:population":0,
    "gn:timezone":"Asia/Jakarta",
    "iso:country":"ID",
    "name:ind_x_preferred":[
        "Tunggorono Empat"
    ],
    "name:und_x_variant":[
        "Tunggorono 4"
    ],
    "wof:name":"Tunggorono Empat",
    "wof:placetype":"locality"
},
  "geometry": {"coordinates":[98.5146,3.608],"type":"Point"}
}