{
  "type": "Feature",
  "properties": {
    "gn:admin1_code":"7.0",
    "gn:asciiname":"Jatirejo",
    "gn:country_code":"ID",
    "gn:dem":237,
    "gn:feature_class":"P",
    "gn:feature_code":"PPL",
    "gn:name":"Jatirejo",
    "gn:population":0,
    "gn:timezone":"Asia/Jakarta",
    "iso:country":"ID",
    "wof:name":"Jatirejo",
    "wof:placetype":"locality"
},
  "geometry": {"coordinates":[110.83806,-7.90139],"type":"Point"}
}