{
  "type": "Feature",
  "properties": {
    "gn:country":"ID",
    "gn:fcode":"PPLA4",
    "gn:pop":0,
    "iso:country":"ID",
    "name:ind_x_preferred":[
        "Bumiayu"
    ],
    "qs:name":"Bumiayu",
    "qs:photos_9r":0,
    "qs:photos_sr":0,
    "qs:pop_sr":"0",
    "wof:lang_x_official":[
        "ind"
    ],
    "wof:lang_x_spoken":[
        "ind",
        "eng"
    ],
    "wof:name":"Bumiayu",
    "wof:placetype":"locality",
    "wof:population":0
},
  "geometry": {"coordinates":[112.6347,-8.0151],"type":"Point"}
}