{
  "type": "Feature",
  "properties": {
    "gn:admin1_code":"7.0",
    "gn:asciiname":"Badran",
    "gn:country_code":"ID",
    "gn:dem":590,
    "gn:feature_class":"P",
    "gn:feature_code":"PPL",
    "gn:name":"Badran",
    "gn:population":0,
    "gn:timezone":"Asia/Jakarta",
    "iso:country":"ID",
    "name:deu_x_preferred":[
        "Badran"
    ],
    "name:heb_x_preferred":[
        "\u05d1\u05d3\u05e8\u05d0\u05df"
    ],
    "name:nds_x_preferred":[
        "Badran"
    ],
    "name:nld_x_preferred":[
        "Badran"
    ],
    "wof:lang_x_official":[
        "ind"
    ],
    "wof:lang_x_spoken":[
        "ind",
        "eng"
    ],
    "wof:name":"Badran",
    "wof:placetype":"locality"
},
  "geometry": {"coordinates":[110.57333,-7.44361],"type":"Point"}
}