{
  "type": "Feature",
  "properties": {
    "gn:admin1_code":"30",
    "gn:asciiname":"Kresidenan",
    "gn:country_code":"ID",
    "gn:dem":253,
    "gn:feature_class":"P",
    "gn:feature_code":"PPL",
    "gn:name":"Kresidenan",
    "gn:population":0,
    "gn:timezone":"Asia/Jakarta",
    "iso:country":"ID",
    "name:ind_x_preferred":[
        "Kresidenan"
    ],
    "wof:name":"Kresidenan",
    "wof:placetype":"locality"
},
  "geometry": {"coordinates":[106.79361000000002,-6.59194],"type":"Point"}
}