{
  "type": "Feature",
  "properties": {
    "gn:admin1_code":"15.0",
    "gn:asciiname":"Talangebar",
    "gn:country_code":"ID",
    "gn:dem":232,
    "gn:feature_class":"P",
    "gn:feature_code":"PPL",
    "gn:name":"Talangebar",
    "gn:population":0,
    "gn:timezone":"Asia/Jakarta",
    "iso:country":"ID",
    "name:ind_x_preferred":[
        "Talangebar"
    ],
    "wof:name":"Talangebar",
    "wof:placetype":"locality"
},
  "geometry": {"coordinates":[104.78243000000001,-5.29896],"type":"Point"}
}