{
  "type": "Feature",
  "properties": {
    "gn:admin1_code":"1",
    "gn:asciiname":"Aekkupang",
    "gn:country_code":"ID",
    "gn:dem":34,
    "gn:feature_class":"P",
    "gn:feature_code":"PPL",
    "gn:name":"Aekkupang",
    "gn:population":0,
    "gn:timezone":"Asia/Jakarta",
    "iso:country":"ID",
    "name:ind_x_preferred":[
        "Aekkupang"
    ],
    "wof:name":"Aekkupang",
    "wof:placetype":"locality"
},
  "geometry": {"coordinates":[97.15940000000001,3.3274],"type":"Point"}
}