{
  "type": "Feature",
  "properties": {
    "gn:admin1_code":"30.0",
    "gn:asciiname":"Panyutran",
    "gn:country_code":"ID",
    "gn:dem":458,
    "gn:feature_class":"P",
    "gn:feature_code":"PPL",
    "gn:name":"Panyutran",
    "gn:population":0,
    "gn:timezone":"Asia/Jakarta",
    "iso:country":"ID",
    "name:ind_x_preferred":[
        "Panyutran"
    ],
    "name:und_x_variant":[
        "Panjutran",
        "Panyutran",
        "Panjoetran"
    ],
    "wof:lang_x_official":[
        "ind"
    ],
    "wof:lang_x_spoken":[
        "ind",
        "eng"
    ],
    "wof:name":"Panyutran",
    "wof:placetype":"locality"
},
  "geometry": {"coordinates":[108.6519,-7.5552],"type":"Point"}
}