{
  "type": "Feature",
  "properties": {
    "gn:admin1_code":"15.0",
    "gn:asciiname":"Tangkitserdang Dua",
    "gn:country_code":"ID",
    "gn:dem":250,
    "gn:feature_class":"P",
    "gn:feature_code":"PPL",
    "gn:name":"Tangkitserdang Dua",
    "gn:population":0,
    "gn:timezone":"Asia/Jakarta",
    "iso:country":"ID",
    "name:ind_x_preferred":[
        "Tangkitserdang Dua"
    ],
    "name:und_x_variant":[
        "Tangkitserdang 2"
    ],
    "wof:lang_x_official":[
        "ind"
    ],
    "wof:lang_x_spoken":[
        "ind",
        "eng"
    ],
    "wof:name":"Tangkitserdang Dua",
    "wof:placetype":"locality"
},
  "geometry": {"coordinates":[104.77979999999999,-5.31298],"type":"Point"}
}