{
  "type": "Feature",
  "properties": {
    "gn:admin1_code":"8.0",
    "gn:asciiname":"Kepeg Dua",
    "gn:country_code":"ID",
    "gn:dem":482,
    "gn:feature_class":"P",
    "gn:feature_code":"PPL",
    "gn:name":"Kepeg Dua",
    "gn:population":0,
    "gn:timezone":"Asia/Jakarta",
    "iso:country":"ID",
    "name:ind_x_preferred":[
        "Kepeg Dua"
    ],
    "wof:name":"Kepeg Dua",
    "wof:placetype":"locality"
},
  "geometry": {"coordinates":[114.0809,-7.8733],"type":"Point"}
}