{
  "type": "Feature",
  "properties": {
    "gn:admin1_code":"18.0",
    "gn:asciiname":"Kalala",
    "gn:country_code":"ID",
    "gn:dem":516,
    "gn:feature_class":"P",
    "gn:feature_code":"PPL",
    "gn:name":"Kalala",
    "gn:population":0,
    "gn:timezone":"Asia/Makassar",
    "iso:country":"ID",
    "name:ind_x_preferred":[
        "Kalala"
    ],
    "wof:name":"Kalala",
    "wof:placetype":"locality"
},
  "geometry": {"coordinates":[119.5003,-9.4931],"type":"Point"}
}