{
  "type": "Feature",
  "properties": {
    "gn:admin1_code":"31.0",
    "gn:asciiname":"Kengkubanang",
    "gn:country_code":"ID",
    "gn:dem":96,
    "gn:feature_class":"P",
    "gn:feature_code":"PPL",
    "gn:name":"Kengkubanang",
    "gn:population":0,
    "gn:timezone":"Asia/Makassar",
    "iso:country":"ID",
    "name:ind_x_preferred":[
        "Kengkubanang"
    ],
    "wof:name":"Kengkubanang",
    "wof:placetype":"locality"
},
  "geometry": {"coordinates":[125.529,3.6643],"type":"Point"}
}