{
  "type": "Feature",
  "properties": {
    "gn:admin1_code":"07",
    "gn:asciiname":"Beran",
    "gn:country_code":"ID",
    "gn:dem":129,
    "gn:feature_class":"P",
    "gn:feature_code":"PPL",
    "gn:name":"Beran",
    "gn:population":0,
    "gn:timezone":"Asia/Jakarta",
    "iso:country":"ID",
    "name:ceb_x_preferred":[
        "Beran"
    ],
    "name:ces_x_preferred":[
        "Beran"
    ],
    "name:deu_x_preferred":[
        "Beran"
    ],
    "name:fra_x_preferred":[
        "Beran"
    ],
    "name:glg_x_preferred":[
        "Ber\u00e1n"
    ],
    "name:nld_x_preferred":[
        "Beran"
    ],
    "name:slk_x_preferred":[
        "Beran"
    ],
    "name:slv_x_preferred":[
        "Beran"
    ],
    "name:swe_x_preferred":[
        "Beran"
    ],
    "wof:lang_x_official":[
        "ind"
    ],
    "wof:lang_x_spoken":[
        "ind",
        "eng"
    ],
    "wof:name":"Beran",
    "wof:placetype":"locality"
},
  "geometry": {"coordinates":[110.60306,-7.25194],"type":"Point"}
}