{
  "type": "Feature",
  "properties": {
    "gn:admin1_code":"18",
    "gn:asciiname":"Golonggorok",
    "gn:country_code":"ID",
    "gn:dem":1009,
    "gn:feature_class":"P",
    "gn:feature_code":"PPL",
    "gn:name":"Golonggorok",
    "gn:population":0,
    "gn:timezone":"Asia/Makassar",
    "iso:country":"ID",
    "name:ind_x_preferred":[
        "Golonggorok"
    ],
    "wof:name":"Golonggorok",
    "wof:placetype":"locality"
},
  "geometry": {"coordinates":[120.48439999999999,-8.4979],"type":"Point"}
}