{
  "type": "Feature",
  "properties": {
    "gn:admin1_code":"17",
    "gn:asciiname":"Pori Daya",
    "gn:country_code":"ID",
    "gn:dem":266,
    "gn:feature_class":"P",
    "gn:feature_code":"PPL",
    "gn:name":"Pori Daya",
    "gn:population":0,
    "gn:timezone":"Asia/Makassar",
    "iso:country":"ID",
    "name:ind_x_preferred":[
        "Pori Daya"
    ],
    "wof:name":"Pori Daya",
    "wof:placetype":"locality"
},
  "geometry": {"coordinates":[116.13200000000001,-8.7832],"type":"Point"}
}