{
  "type": "Feature",
  "properties": {
    "gn:admin1_code":"30.0",
    "gn:asciiname":"Leuwicukang",
    "gn:country_code":"ID",
    "gn:dem":645,
    "gn:feature_class":"P",
    "gn:feature_code":"PPL",
    "gn:name":"Leuwicukang",
    "gn:population":0,
    "gn:timezone":"Asia/Jakarta",
    "iso:country":"ID",
    "name:ind_x_preferred":[
        "Leuwicukang"
    ],
    "name:und_x_variant":[
        "Leuwitjoekang"
    ],
    "wof:name":"Leuwicukang",
    "wof:placetype":"locality"
},
  "geometry": {"coordinates":[107.88549999999999,-7.531],"type":"Point"}
}