{
  "type": "Feature",
  "properties": {
    "gn:admin1_code":"8.0",
    "gn:asciiname":"Cerme Lor",
    "gn:country_code":"ID",
    "gn:dem":91,
    "gn:feature_class":"P",
    "gn:feature_code":"PPL",
    "gn:name":"Cerme Lor",
    "gn:population":0,
    "gn:timezone":"Asia/Jakarta",
    "iso:country":"ID",
    "name:ind_x_preferred":[
        "Cerme Lor"
    ],
    "wof:name":"Cerme Lor",
    "wof:placetype":"locality"
},
  "geometry": {"coordinates":[111.8462,-8.1742],"type":"Point"}
}