{
  "type": "Feature",
  "properties": {
    "gn:admin1_code":"29.0",
    "gn:asciiname":"Aruk",
    "gn:country_code":"ID",
    "gn:dem":17,
    "gn:feature_class":"P",
    "gn:feature_code":"PPL",
    "gn:name":"Aruk",
    "gn:population":0,
    "gn:timezone":"Asia/Jayapura",
    "iso:country":"ID",
    "name:und_x_variant":[
        "Aroek",
        "Aruk"
    ],
    "wof:name":"Aruk",
    "wof:placetype":"locality"
},
  "geometry": {"coordinates":[127.62737,1.80348],"type":"Point"}
}