{
  "type": "Feature",
  "properties": {
    "gn:admin1_code":"8.0",
    "gn:asciiname":"Laoksongai",
    "gn:country_code":"ID",
    "gn:dem":61,
    "gn:feature_class":"P",
    "gn:feature_code":"PPL",
    "gn:name":"Laoksongai",
    "gn:population":0,
    "gn:timezone":"Asia/Jakarta",
    "iso:country":"ID",
    "name:ind_x_preferred":[
        "Laoksongai"
    ],
    "wof:name":"Laoksongai",
    "wof:placetype":"locality"
},
  "geometry": {"coordinates":[113.7471,-7.0507],"type":"Point"}
}