{
  "type": "Feature",
  "properties": {
    "gn:admin1_code":"18.0",
    "gn:asciiname":"Oeltaupi",
    "gn:country_code":"ID",
    "gn:dem":612,
    "gn:feature_class":"P",
    "gn:feature_code":"PPL",
    "gn:name":"Oeltaupi",
    "gn:population":0,
    "gn:timezone":"Asia/Makassar",
    "iso:country":"ID",
    "name:ind_x_preferred":[
        "Oeltaupi"
    ],
    "wof:name":"Oeltaupi",
    "wof:placetype":"locality"
},
  "geometry": {"coordinates":[124.1224,-9.7016],"type":"Point"}
}