{
  "type": "Feature",
  "properties": {
    "gn:admin1_code":"8",
    "gn:asciiname":"Nunuk",
    "gn:country_code":"ID",
    "gn:dem":15,
    "gn:feature_class":"P",
    "gn:feature_code":"PPL",
    "gn:name":"Nunuk",
    "gn:population":0,
    "gn:timezone":"Asia/Jakarta",
    "iso:country":"ID",
    "name:ind_x_preferred":[
        "Nunuk"
    ],
    "wof:name":"Nunuk",
    "wof:placetype":"locality"
},
  "geometry": {"coordinates":[112.06489999999999,-7.104],"type":"Point"}
}