{
  "type": "Feature",
  "properties": {
    "gn:admin1_code":"30.0",
    "gn:asciiname":"Cikanawe",
    "gn:country_code":"ID",
    "gn:dem":905,
    "gn:feature_class":"P",
    "gn:feature_code":"PPL",
    "gn:name":"Cikanawe",
    "gn:population":0,
    "gn:timezone":"Asia/Jakarta",
    "iso:country":"ID",
    "name:ind_x_preferred":[
        "Cikanawe"
    ],
    "wof:name":"Cikanawe",
    "wof:placetype":"locality"
},
  "geometry": {"coordinates":[107.9087,-7.2717],"type":"Point"}
}