{
  "type": "Feature",
  "properties": {
    "gn:admin1_code":"1",
    "gn:asciiname":"Lamlung",
    "gn:country_code":"ID",
    "gn:dem":39,
    "gn:feature_class":"P",
    "gn:feature_code":"PPL",
    "gn:name":"Lamlung",
    "gn:population":0,
    "gn:timezone":"Asia/Jakarta",
    "iso:country":"ID",
    "name:ind_x_preferred":[
        "Lamlung"
    ],
    "wof:name":"Lamlung",
    "wof:placetype":"locality"
},
  "geometry": {"coordinates":[95.4708,5.4226],"type":"Point"}
}