{
  "type": "Feature",
  "properties": {
    "gn:admin1_code":"8.0",
    "gn:asciiname":"Dukuh Tengah",
    "gn:country_code":"ID",
    "gn:dem":44,
    "gn:feature_class":"P",
    "gn:feature_code":"PPL",
    "gn:name":"Dukuh Tengah",
    "gn:population":0,
    "gn:timezone":"Asia/Jakarta",
    "iso:country":"ID",
    "name:ind_x_preferred":[
        "Dukuh Tengah"
    ],
    "wof:name":"Dukuh Tengah",
    "wof:placetype":"locality"
},
  "geometry": {"coordinates":[112.9803,-7.7486],"type":"Point"}
}