{
  "type": "Feature",
  "properties": {
    "gn:admin1_code":"29.0",
    "gn:asciiname":"Lekitobi",
    "gn:country_code":"ID",
    "gn:dem":11,
    "gn:feature_class":"P",
    "gn:feature_code":"PPL",
    "gn:name":"Lekitobi",
    "gn:population":0,
    "gn:timezone":"Asia/Jayapura",
    "iso:country":"ID",
    "name:ind_x_preferred":[
        "Lekitobi"
    ],
    "name:und_x_variant":[
        "Likitobi",
        "Lekitobi"
    ],
    "wof:name":"Lekitobi",
    "wof:placetype":"locality"
},
  "geometry": {"coordinates":[124.51896000000001,-1.97966],"type":"Point"}
}