{
  "type": "Feature",
  "properties": {
    "gn:admin1_code":"32.0",
    "gn:asciiname":"Kalangannanjungan",
    "gn:country_code":"ID",
    "gn:dem":655,
    "gn:feature_class":"P",
    "gn:feature_code":"PPL",
    "gn:name":"Kalangannanjungan",
    "gn:population":0,
    "gn:timezone":"Asia/Jakarta",
    "iso:country":"ID",
    "name:ind_x_preferred":[
        "Kalangannanjungan"
    ],
    "wof:name":"Kalangannanjungan",
    "wof:placetype":"locality"
},
  "geometry": {"coordinates":[103.5997,-4.0548],"type":"Point"}
}