{
  "type": "Feature",
  "properties": {
    "gn:admin1_code":"30.0",
    "gn:asciiname":"Selaawi",
    "gn:country_code":"ID",
    "gn:dem":120,
    "gn:feature_class":"P",
    "gn:feature_code":"PPL",
    "gn:name":"Selaawi",
    "gn:population":0,
    "gn:timezone":"Asia/Jakarta",
    "iso:country":"ID",
    "name:ind_x_preferred":[
        "Selaawi"
    ],
    "wof:name":"Selaawi",
    "wof:placetype":"locality"
},
  "geometry": {"coordinates":[107.575,-6.56639],"type":"Point"}
}