{
  "type": "Feature",
  "properties": {
    "gn:admin1_code":"15.0",
    "gn:asciiname":"Srimorosari",
    "gn:country_code":"ID",
    "gn:dem":17,
    "gn:feature_class":"P",
    "gn:feature_code":"PPL",
    "gn:name":"Srimorosari",
    "gn:population":0,
    "gn:timezone":"Asia/Jakarta",
    "iso:country":"ID",
    "name:ind_x_preferred":[
        "Srimorosari"
    ],
    "name:und_x_variant":[
        "Sriminasari"
    ],
    "wof:name":"Srimorosari",
    "wof:placetype":"locality"
},
  "geometry": {"coordinates":[105.81005999999999,-5.32988],"type":"Point"}
}