{
  "type": "Feature",
  "properties": {
    "gn:country":"ID",
    "gn:fcode":"ADM3",
    "gn:pop":0,
    "iso:country":"ID",
    "name:ind_x_preferred":[
        "Kecamatan Motoling"
    ],
    "name:unk_x_variant":[
        "Motoling"
    ],
    "qs:name":"Kecamatan Motoling",
    "qs:photos_9r":0,
    "qs:photos_sr":0,
    "qs:pop_sr":"0",
    "wof:name":"Kecamatan Motoling",
    "wof:placetype":"localadmin",
    "wof:population":0
},
  "geometry": {"coordinates":[124.4635,1.0241],"type":"Point"}
}