{
  "type": "Feature",
  "properties": {
    "gn:admin1_code":"7.0",
    "gn:asciiname":"Kenteng",
    "gn:country_code":"ID",
    "gn:dem":183,
    "gn:feature_class":"P",
    "gn:feature_code":"PPL",
    "gn:name":"Kenteng",
    "gn:population":0,
    "gn:timezone":"Asia/Jakarta",
    "iso:country":"ID",
    "wof:name":"Kenteng",
    "wof:placetype":"locality"
},
  "geometry": {"coordinates":[110.66722,-7.58833],"type":"Point"}
}