{
  "type": "Feature",
  "properties": {
    "gn:admin1_code":"26",
    "gn:asciiname":"Talun",
    "gn:country_code":"ID",
    "gn:dem":527,
    "gn:feature_class":"P",
    "gn:feature_code":"PPL",
    "gn:name":"Talun",
    "gn:population":0,
    "gn:timezone":"Asia/Jakarta",
    "iso:country":"ID",
    "name:ceb_x_preferred":[
        "T\u0101l\u016bn"
    ],
    "name:fas_x_preferred":[
        "\u0637\u0627\u0644\u0648\u0646"
    ],
    "name:ind_x_preferred":[
        "Talun"
    ],
    "name:swe_x_preferred":[
        "T\u0101l\u016bn"
    ],
    "name:und_x_variant":[
        "Dagangtelun"
    ],
    "wof:lang_x_official":[
        "ind"
    ],
    "wof:lang_x_spoken":[
        "ind",
        "eng"
    ],
    "wof:name":"Talun",
    "wof:placetype":"locality"
},
  "geometry": {"coordinates":[98.36150000000001,3.3644],"type":"Point"}
}