{
  "type": "Feature",
  "properties": {
    "gn:admin1_code":"18.0",
    "gn:asciiname":"Amaf",
    "gn:country_code":"ID",
    "gn:dem":245,
    "gn:feature_class":"P",
    "gn:feature_code":"PPL",
    "gn:name":"Amaf",
    "gn:population":0,
    "gn:timezone":"Asia/Makassar",
    "iso:country":"ID",
    "name:ind_x_preferred":[
        "Amaf"
    ],
    "wof:name":"Amaf",
    "wof:placetype":"locality"
},
  "geometry": {"coordinates":[124.19029999999999,-9.9132],"type":"Point"}
}