{
  "type": "Feature",
  "properties": {
    "gn:admin1_code":"7.0",
    "gn:asciiname":"Cigintung",
    "gn:country_code":"ID",
    "gn:dem":34,
    "gn:feature_class":"P",
    "gn:feature_code":"PPL",
    "gn:name":"Cigintung",
    "gn:population":0,
    "gn:timezone":"Asia/Jakarta",
    "iso:country":"ID",
    "name:ind_x_preferred":[
        "Cigintung"
    ],
    "wof:name":"Cigintung",
    "wof:placetype":"locality"
},
  "geometry": {"coordinates":[108.7277,-7.3434],"type":"Point"}
}