{
  "type": "Feature",
  "properties": {
    "gn:admin1_code":"15.0",
    "gn:asciiname":"Lubukmantang",
    "gn:country_code":"ID",
    "gn:dem":35,
    "gn:feature_class":"P",
    "gn:feature_code":"PPL",
    "gn:name":"Lubukmantang",
    "gn:population":0,
    "gn:timezone":"Asia/Jakarta",
    "iso:country":"ID",
    "name:ind_x_preferred":[
        "Lubukmantang"
    ],
    "wof:name":"Lubukmantang",
    "wof:placetype":"locality"
},
  "geometry": {"coordinates":[105.50713,-5.47234],"type":"Point"}
}