{
  "type": "Feature",
  "properties": {
    "gn:admin1_code":"18.0",
    "gn:asciiname":"Mbulir",
    "gn:country_code":"ID",
    "gn:dem":26,
    "gn:feature_class":"P",
    "gn:feature_code":"PPL",
    "gn:name":"Mbulir",
    "gn:population":0,
    "gn:timezone":"Asia/Makassar",
    "iso:country":"ID",
    "name:ind_x_preferred":[
        "Mbulir"
    ],
    "wof:name":"Mbulir",
    "wof:placetype":"locality"
},
  "geometry": {"coordinates":[119.018,-9.6554],"type":"Point"}
}