{
  "type": "Feature",
  "properties": {
    "gn:admin1_code":"0.0",
    "gn:asciiname":"Patrol",
    "gn:country_code":"ID",
    "gn:dem":1213,
    "gn:feature_class":"P",
    "gn:feature_code":"PPL",
    "gn:name":"Patrol",
    "gn:population":0,
    "gn:timezone":"Asia/Jakarta",
    "iso:country":"ID",
    "wof:name":"Patrol",
    "wof:placetype":"locality"
},
  "geometry": {"coordinates":[107.68333,-6.81667],"type":"Point"}
}