{
  "type": "Feature",
  "properties": {
    "gn:admin1_code":"30.0",
    "gn:asciiname":"Loji",
    "gn:country_code":"ID",
    "gn:dem":108,
    "gn:feature_class":"P",
    "gn:feature_code":"PPL",
    "gn:name":"Loji",
    "gn:population":0,
    "gn:timezone":"Asia/Jakarta",
    "iso:country":"ID",
    "name:ind_x_preferred":[
        "Loji"
    ],
    "wof:name":"Loji",
    "wof:placetype":"locality"
},
  "geometry": {"coordinates":[106.52370000000001,-7.3331],"type":"Point"}
}