{
  "type": "Feature",
  "properties": {
    "gn:admin1_code":"26.0",
    "gn:asciiname":"Binangara Dua",
    "gn:country_code":"ID",
    "gn:dem":933,
    "gn:feature_class":"P",
    "gn:feature_code":"PPL",
    "gn:name":"Binangara Dua",
    "gn:population":0,
    "gn:timezone":"Asia/Jakarta",
    "iso:country":"ID",
    "name:ind_x_preferred":[
        "Binangara Dua"
    ],
    "name:und_x_variant":[
        "Binangara 2",
        "Binanga\u00e4ra"
    ],
    "wof:lang_x_official":[
        "ind"
    ],
    "wof:lang_x_spoken":[
        "ind",
        "eng"
    ],
    "wof:name":"Binangara Dua",
    "wof:placetype":"locality"
},
  "geometry": {"coordinates":[98.5823,2.7335],"type":"Point"}
}