{
  "type": "Feature",
  "properties": {
    "gn:admin1_code":"8.0",
    "gn:asciiname":"Kedungagung",
    "gn:country_code":"ID",
    "gn:dem":62,
    "gn:feature_class":"P",
    "gn:feature_code":"PPL",
    "gn:name":"Kedungagung",
    "gn:population":0,
    "gn:timezone":"Asia/Jakarta",
    "iso:country":"ID",
    "name:ind_x_preferred":[
        "Kedungagung"
    ],
    "wof:name":"Kedungagung",
    "wof:placetype":"locality"
},
  "geometry": {"coordinates":[114.14879999999999,-8.5183],"type":"Point"}
}