{
  "type": "Feature",
  "properties": {
    "gn:admin1_code":"30.0",
    "gn:asciiname":"Cicangkrung",
    "gn:country_code":"ID",
    "gn:dem":546,
    "gn:feature_class":"P",
    "gn:feature_code":"PPL",
    "gn:name":"Cicangkrung",
    "gn:population":0,
    "gn:timezone":"Asia/Jakarta",
    "iso:country":"ID",
    "name:ind_x_preferred":[
        "Cicangkrung"
    ],
    "name:und_x_variant":[
        "Tjitjangkroeng"
    ],
    "wof:name":"Cicangkrung",
    "wof:placetype":"locality"
},
  "geometry": {"coordinates":[108.4147,-7.1458],"type":"Point"}
}