{
  "type": "Feature",
  "properties": {
    "gn:admin1_code":"28.0",
    "gn:asciiname":"Nuniali",
    "gn:country_code":"ID",
    "gn:dem":14,
    "gn:feature_class":"P",
    "gn:feature_code":"PPL",
    "gn:name":"Nuniali",
    "gn:population":0,
    "gn:timezone":"Asia/Jayapura",
    "iso:country":"ID",
    "name:ind_x_preferred":[
        "Nuniali"
    ],
    "name:und_x_variant":[
        "Noniali",
        "Noeniali",
        "Nuniali"
    ],
    "wof:name":"Nuniali",
    "wof:placetype":"locality"
},
  "geometry": {"coordinates":[128.39616999999998,-2.87129],"type":"Point"}
}