{
  "type": "Feature",
  "properties": {
    "gn:admin1_code":"26",
    "gn:asciiname":"Paneurpangko",
    "gn:country_code":"ID",
    "gn:dem":174,
    "gn:feature_class":"P",
    "gn:feature_code":"PPL",
    "gn:name":"Paneurpangko",
    "gn:population":0,
    "gn:timezone":"Asia/Jakarta",
    "iso:country":"ID",
    "name:ind_x_preferred":[
        "Paneurpangko"
    ],
    "wof:name":"Paneurpangko",
    "wof:placetype":"locality"
},
  "geometry": {"coordinates":[99.52513999999999,1.51341],"type":"Point"}
}