{
  "type": "Feature",
  "properties": {
    "gn:admin1_code":"18",
    "gn:asciiname":"Saga",
    "gn:country_code":"ID",
    "gn:dem":748,
    "gn:feature_class":"P",
    "gn:feature_code":"PPLA4",
    "gn:name":"Saga",
    "gn:population":0,
    "gn:timezone":"Asia/Makassar",
    "iso:country":"ID",
    "name:ind_x_preferred":[
        "Saga"
    ],
    "wof:name":"Saga",
    "wof:placetype":"locality"
},
  "geometry": {"coordinates":[121.7349,-8.7694],"type":"Point"}
}