{
  "type": "Feature",
  "properties": {
    "gn:admin1_code":"26",
    "gn:asciiname":"Sosor Ladang",
    "gn:country_code":"ID",
    "gn:dem":948,
    "gn:feature_class":"P",
    "gn:feature_code":"PPL",
    "gn:name":"Sosor Ladang",
    "gn:population":0,
    "gn:timezone":"Asia/Jakarta",
    "iso:country":"ID",
    "name:ind_x_preferred":[
        "Sosor Ladang"
    ],
    "wof:name":"Sosor Ladang",
    "wof:placetype":"locality"
},
  "geometry": {"coordinates":[99.1883,2.4655],"type":"Point"}
}