{
  "type": "Feature",
  "properties": {
    "gn:country":"ID",
    "gn:fcode":"PPL",
    "gn:pop":0,
    "iso:country":"ID",
    "name:ind_x_preferred":[
        "Beureunun"
    ],
    "name:unk_x_variant":[
        "Beureunoen"
    ],
    "qs:name":"Beureunun",
    "qs:name_adm0":"Indonesia",
    "qs:name_adm1":"Nanggroe Aceh Darussalam",
    "qs:photos_9k":1,
    "qs:photos_9r":1,
    "qs:photos_all":1,
    "qs:photos_sr":0,
    "qs:placetype":"Town",
    "qs:pop_sr":"0",
    "wof:lang_x_official":[
        "ind"
    ],
    "wof:lang_x_spoken":[
        "ind",
        "eng"
    ],
    "wof:name":"Beureunun",
    "wof:placetype":"locality",
    "wof:population":0
},
  "geometry": {"coordinates":[95.98139999999999,5.2792],"type":"Point"}
}