{
  "type": "Feature",
  "properties": {
    "gn:admin1_code":"36.0",
    "gn:asciiname":"Manwinopuri",
    "gn:country_code":"ID",
    "gn:dem":7,
    "gn:feature_class":"P",
    "gn:feature_code":"PPL",
    "gn:name":"Manwinopuri",
    "gn:population":0,
    "gn:timezone":"Asia/Jayapura",
    "iso:country":"ID",
    "name:ind_x_preferred":[
        "Manwinopuri"
    ],
    "name:und_x_variant":[
        "Manoinoepoeri",
        "Manoewenopori",
        "Manoinepoeri",
        "Manwinopuri"
    ],
    "wof:lang_x_official":[
        "ind"
    ],
    "wof:lang_x_spoken":[
        "ind",
        "eng"
    ],
    "wof:name":"Manwinopuri",
    "wof:placetype":"locality"
},
  "geometry": {"coordinates":[135.8663,-1.1727],"type":"Point"}
}