{
  "type": "Feature",
  "properties": {
    "gn:admin1_code":"30.0",
    "gn:asciiname":"Sangiang",
    "gn:country_code":"ID",
    "gn:dem":80,
    "gn:feature_class":"P",
    "gn:feature_code":"PPL",
    "gn:name":"Sangiang",
    "gn:population":0,
    "gn:timezone":"Asia/Jakarta",
    "iso:country":"ID",
    "name:ara_x_preferred":[
        "\u0633\u0627\u0646\u063a\u064a\u0627\u0646\u063a"
    ],
    "name:ceb_x_preferred":[
        "Pulau Sangiang"
    ],
    "name:deu_x_preferred":[
        "Sangiang"
    ],
    "name:fra_x_preferred":[
        "Sangiang"
    ],
    "name:hak_x_preferred":[
        "Sangiang"
    ],
    "name:ind_x_preferred":[
        "Sangiang"
    ],
    "name:ind_x_variant":[
        "Pulau Sangiang"
    ],
    "name:ita_x_preferred":[
        "Sangiang"
    ],
    "name:nld_x_preferred":[
        "Sangiang"
    ],
    "name:swe_x_preferred":[
        "Pulau Sangiang"
    ],
    "name:zho_x_preferred":[
        "\u6851\u5409\u6602\u5cf6"
    ],
    "wof:name":"Sangiang",
    "wof:placetype":"locality"
},
  "geometry": {"coordinates":[107.83410000000001,-7.6243],"type":"Point"}
}