{
  "type": "Feature",
  "properties": {
    "gn:admin1_code":"41",
    "gn:asciiname":"Todangtodang",
    "gn:country_code":"ID",
    "gn:dem":381,
    "gn:feature_class":"P",
    "gn:feature_code":"PPL",
    "gn:name":"Todangtodang",
    "gn:population":0,
    "gn:timezone":"Asia/Makassar",
    "iso:country":"ID",
    "name:ind_x_preferred":[
        "Todangtodang"
    ],
    "wof:name":"Todangtodang",
    "wof:placetype":"locality"
},
  "geometry": {"coordinates":[119.0429,-3.4544],"type":"Point"}
}