{
  "type": "Feature",
  "properties": {
    "gn:admin1_code":"18.0",
    "gn:asciiname":"Lus Timur",
    "gn:country_code":"ID",
    "gn:dem":262,
    "gn:feature_class":"P",
    "gn:feature_code":"PPL",
    "gn:name":"Lus Timur",
    "gn:population":0,
    "gn:timezone":"Asia/Makassar",
    "iso:country":"ID",
    "name:ind_x_preferred":[
        "Lus Timur"
    ],
    "wof:name":"Lus Timur",
    "wof:placetype":"locality"
},
  "geometry": {"coordinates":[120.1962,-8.6987],"type":"Point"}
}