{
  "type": "Feature",
  "properties": {
    "gn:admin1_code":"30.0",
    "gn:asciiname":"Cicondong",
    "gn:country_code":"ID",
    "gn:dem":317,
    "gn:feature_class":"P",
    "gn:feature_code":"PPL",
    "gn:name":"Cicondong",
    "gn:population":0,
    "gn:timezone":"Asia/Jakarta",
    "iso:country":"ID",
    "name:ind_x_preferred":[
        "Cicondong"
    ],
    "name:und_x_variant":[
        "Tjitjondong"
    ],
    "wof:name":"Cicondong",
    "wof:placetype":"locality"
},
  "geometry": {"coordinates":[108.1746,-7.3854],"type":"Point"}
}