{
  "type": "Feature",
  "properties": {
    "gn:admin1_code":"26.0",
    "gn:asciiname":"Sanggar Nagungun",
    "gn:country_code":"ID",
    "gn:dem":1221,
    "gn:feature_class":"P",
    "gn:feature_code":"PPL",
    "gn:name":"Sanggar Nagungun",
    "gn:population":0,
    "gn:timezone":"Asia/Jakarta",
    "iso:country":"ID",
    "name:ind_x_preferred":[
        "Sanggar Nagungun"
    ],
    "wof:name":"Sanggar Nagungun",
    "wof:placetype":"locality"
},
  "geometry": {"coordinates":[98.7209,2.6724],"type":"Point"}
}