{
  "type": "Feature",
  "properties": {
    "gn:admin1_code":"30.0",
    "gn:asciiname":"Cibogo",
    "gn:country_code":"ID",
    "gn:dem":884,
    "gn:feature_class":"P",
    "gn:feature_code":"PPL",
    "gn:name":"Cibogo",
    "gn:population":0,
    "gn:timezone":"Asia/Jakarta",
    "iso:country":"ID",
    "name:ind_x_preferred":[
        "Cibogo"
    ],
    "name:und_x_variant":[
        "Tjibogo",
        "Cibogo",
        "Tjibogo 1"
    ],
    "wof:lang_x_official":[
        "ind"
    ],
    "wof:lang_x_spoken":[
        "ind",
        "eng"
    ],
    "wof:name":"Cibogo",
    "wof:placetype":"locality"
},
  "geometry": {"coordinates":[107.10826,-7.13145],"type":"Point"}
}