{
  "type": "Feature",
  "properties": {
    "gn:admin1_code":"15.0",
    "gn:asciiname":"Sidorahayu",
    "gn:country_code":"ID",
    "gn:dem":76,
    "gn:feature_class":"P",
    "gn:feature_code":"PPL",
    "gn:name":"Sidorahayu",
    "gn:population":0,
    "gn:timezone":"Asia/Jakarta",
    "iso:country":"ID",
    "name:ind_x_preferred":[
        "Sidorahayu"
    ],
    "wof:name":"Sidorahayu",
    "wof:placetype":"locality"
},
  "geometry": {"coordinates":[104.92597000000001,-5.07538],"type":"Point"}
}