{
  "type": "Feature",
  "properties": {
    "gn:admin1_code":"33.0",
    "gn:asciiname":"Sinarwaras",
    "gn:country_code":"ID",
    "gn:dem":53,
    "gn:feature_class":"P",
    "gn:feature_code":"PPL",
    "gn:name":"Sinarwaras",
    "gn:population":0,
    "gn:timezone":"Asia/Jakarta",
    "iso:country":"ID",
    "name:ind_x_preferred":[
        "Sinarwaras"
    ],
    "wof:name":"Sinarwaras",
    "wof:placetype":"locality"
},
  "geometry": {"coordinates":[106.07037,-6.83806],"type":"Point"}
}