{
  "type": "Feature",
  "properties": {
    "gn:admin1_code":"30",
    "gn:asciiname":"Cikanyere",
    "gn:country_code":"ID",
    "gn:dem":470,
    "gn:feature_class":"P",
    "gn:feature_code":"PPL",
    "gn:name":"Cikanyere",
    "gn:population":0,
    "gn:timezone":"Asia/Jakarta",
    "iso:country":"ID",
    "name:ind_x_preferred":[
        "Cikanyere"
    ],
    "wof:name":"Cikanyere",
    "wof:placetype":"locality"
},
  "geometry": {"coordinates":[106.78972,-6.88583],"type":"Point"}
}