{
  "type": "Feature",
  "properties": {
    "gn:admin1_code":"8",
    "gn:asciiname":"Panggang",
    "gn:country_code":"ID",
    "gn:dem":21,
    "gn:feature_class":"P",
    "gn:feature_code":"PPL",
    "gn:name":"Panggang",
    "gn:population":0,
    "gn:timezone":"Asia/Jakarta",
    "iso:country":"ID",
    "name:ind_x_preferred":[
        "Panggang"
    ],
    "wof:name":"Panggang",
    "wof:placetype":"locality"
},
  "geometry": {"coordinates":[112.5427,-7.3906],"type":"Point"}
}