{
  "type": "Feature",
  "properties": {
    "gn:admin1_code":"28.0",
    "gn:asciiname":"Har",
    "gn:country_code":"ID",
    "gn:dem":32,
    "gn:feature_class":"P",
    "gn:feature_code":"PPL",
    "gn:name":"Har",
    "gn:population":0,
    "gn:timezone":"Asia/Jayapura",
    "iso:country":"ID",
    "name:ceb_x_preferred":[
        "Har"
    ],
    "name:isl_x_preferred":[
        "H\u00e1r"
    ],
    "name:por_x_preferred":[
        "Har"
    ],
    "name:swe_x_preferred":[
        "Har"
    ],
    "name:und_x_variant":[
        "Haar",
        "Har"
    ],
    "wof:lang_x_official":[
        "ind"
    ],
    "wof:lang_x_spoken":[
        "ind",
        "eng"
    ],
    "wof:name":"Har",
    "wof:placetype":"locality"
},
  "geometry": {"coordinates":[133.1808,-5.334],"type":"Point"}
}