{
  "type": "Feature",
  "properties": {
    "gn:admin1_code":"24",
    "gn:asciiname":"Guguksolok",
    "gn:country_code":"ID",
    "gn:dem":482,
    "gn:feature_class":"P",
    "gn:feature_code":"PPL",
    "gn:name":"Guguksolok",
    "gn:population":0,
    "gn:timezone":"Asia/Jakarta",
    "iso:country":"ID",
    "name:ind_x_preferred":[
        "Guguksolok"
    ],
    "wof:name":"Guguksolok",
    "wof:placetype":"locality"
},
  "geometry": {"coordinates":[100.74281999999999,-0.50346],"type":"Point"}
}