{
  "type": "Feature",
  "properties": {
    "gn:admin1_code":"10",
    "gn:asciiname":"Tungkakpakel",
    "gn:country_code":"ID",
    "gn:dem":94,
    "gn:feature_class":"P",
    "gn:feature_code":"PPL",
    "gn:name":"Tungkakpakel",
    "gn:population":0,
    "gn:timezone":"Asia/Jakarta",
    "iso:country":"ID",
    "wof:name":"Tungkakpakel",
    "wof:placetype":"locality"
},
  "geometry": {"coordinates":[110.38249999999999,-7.81583],"type":"Point"}
}