{
  "type": "Feature",
  "properties": {
    "gn:admin1_code":"30.0",
    "gn:asciiname":"Rancaucing",
    "gn:country_code":"ID",
    "gn:dem":607,
    "gn:feature_class":"P",
    "gn:feature_code":"PPL",
    "gn:name":"Rancaucing",
    "gn:population":0,
    "gn:timezone":"Asia/Jakarta",
    "iso:country":"ID",
    "name:ind_x_preferred":[
        "Rancaucing"
    ],
    "wof:name":"Rancaucing",
    "wof:placetype":"locality"
},
  "geometry": {"coordinates":[107.66289999999999,-7.435],"type":"Point"}
}