{
  "type": "Feature",
  "properties": {
    "gn:admin1_code":"18.0",
    "gn:asciiname":"Oelete",
    "gn:country_code":"ID",
    "gn:dem":703,
    "gn:feature_class":"P",
    "gn:feature_code":"PPL",
    "gn:name":"Oelete",
    "gn:population":0,
    "gn:timezone":"Asia/Makassar",
    "iso:country":"ID",
    "name:ind_x_preferred":[
        "Oelete"
    ],
    "wof:name":"Oelete",
    "wof:placetype":"locality"
},
  "geometry": {"coordinates":[124.34050000000001,-9.9421],"type":"Point"}
}