{
  "type": "Feature",
  "properties": {
    "gn:country":"ID",
    "gn:fcode":"PPL",
    "gn:pop":0,
    "iso:country":"ID",
    "name:arg_x_preferred":[
        "Limo"
    ],
    "name:ceb_x_preferred":[
        "Limo"
    ],
    "name:deu_x_preferred":[
        "Limo"
    ],
    "name:epo_x_preferred":[
        "Limo"
    ],
    "name:fin_x_preferred":[
        "Limo"
    ],
    "name:fra_x_preferred":[
        "Limo"
    ],
    "name:ind_x_preferred":[
        "Limo"
    ],
    "name:ita_x_preferred":[
        "Limo"
    ],
    "name:nld_x_preferred":[
        "Limo"
    ],
    "name:pol_x_preferred":[
        "Limo"
    ],
    "name:swe_x_preferred":[
        "Limo"
    ],
    "qs:name":"Limo",
    "qs:name_adm0":"Indonesia",
    "qs:name_adm1":"Jawa Barat",
    "qs:photos_9k":1,
    "qs:photos_9r":1,
    "qs:photos_all":19,
    "qs:photos_sr":0,
    "qs:placetype":"Town",
    "qs:pop_sr":"0",
    "wd:wordcount":143,
    "wof:name":"Limo",
    "wof:placetype":"locality",
    "wof:population":0
},
  "geometry": {"coordinates":[106.7761,-6.3606],"type":"Point"}
}