{
  "type": "Feature",
  "properties": {
    "gn:admin1_code":"0.0",
    "gn:asciiname":"Sedau",
    "gn:country_code":"ID",
    "gn:dem":76,
    "gn:feature_class":"P",
    "gn:feature_code":"PPL",
    "gn:name":"Sedau",
    "gn:population":0,
    "gn:timezone":"Asia/Pontianak",
    "iso:country":"ID",
    "wof:name":"Sedau",
    "wof:placetype":"locality"
},
  "geometry": {"coordinates":[108.95,0.86667],"type":"Point"}
}