{
  "type": "Feature",
  "properties": {
    "gn:admin1_code":"1",
    "gn:asciiname":"Semadam Asal",
    "gn:country_code":"ID",
    "gn:dem":132,
    "gn:feature_class":"P",
    "gn:feature_code":"PPL",
    "gn:name":"Semadam Asal",
    "gn:population":0,
    "gn:timezone":"Asia/Jakarta",
    "iso:country":"ID",
    "name:ind_x_preferred":[
        "Semadam Asal"
    ],
    "wof:name":"Semadam Asal",
    "wof:placetype":"locality"
},
  "geometry": {"coordinates":[97.8835,3.3928],"type":"Point"}
}