{
  "type": "Feature",
  "properties": {
    "gn:admin1_code":"30.0",
    "gn:asciiname":"Pasirlaja Satu",
    "gn:country_code":"ID",
    "gn:dem":12,
    "gn:feature_class":"P",
    "gn:feature_code":"PPL",
    "gn:name":"Pasirlaja Satu",
    "gn:population":0,
    "gn:timezone":"Asia/Jakarta",
    "iso:country":"ID",
    "name:ind_x_preferred":[
        "Pasirlaja Satu"
    ],
    "wof:name":"Pasirlaja Satu",
    "wof:placetype":"locality"
},
  "geometry": {"coordinates":[107.96939999999999,-7.732],"type":"Point"}
}