{
  "type": "Feature",
  "properties": {
    "gn:admin1_code":"38",
    "gn:asciiname":"Sumillin",
    "gn:country_code":"ID",
    "gn:dem":209,
    "gn:feature_class":"P",
    "gn:feature_code":"PPL",
    "gn:name":"Sumillin",
    "gn:population":0,
    "gn:timezone":"Asia/Makassar",
    "iso:country":"ID",
    "name:ind_x_preferred":[
        "Sumillin"
    ],
    "name:und_x_variant":[
        "Sumilin"
    ],
    "wof:name":"Sumillin",
    "wof:placetype":"locality"
},
  "geometry": {"coordinates":[120.3258,-2.4855],"type":"Point"}
}