{
  "type": "Feature",
  "properties": {
    "gn:admin1_code":"30",
    "gn:asciiname":"Ciharashas",
    "gn:country_code":"ID",
    "gn:dem":695,
    "gn:feature_class":"P",
    "gn:feature_code":"PPL",
    "gn:name":"Ciharashas",
    "gn:population":0,
    "gn:timezone":"Asia/Jakarta",
    "iso:country":"ID",
    "name:ind_x_preferred":[
        "Ciharashas"
    ],
    "name:und_x_variant":[
        "Tjiharashes",
        "Ciharashes"
    ],
    "wof:lang_x_official":[
        "ind"
    ],
    "wof:lang_x_spoken":[
        "ind",
        "eng"
    ],
    "wof:name":"Ciharashas",
    "wof:placetype":"locality"
},
  "geometry": {"coordinates":[107.50583,-6.85861],"type":"Point"}
}