{
  "type": "Feature",
  "properties": {
    "gn:admin1_code":"33.0",
    "gn:asciiname":"Cirinten",
    "gn:country_code":"ID",
    "gn:dem":346,
    "gn:feature_class":"P",
    "gn:feature_code":"PPLA4",
    "gn:name":"Cirinten",
    "gn:population":0,
    "gn:timezone":"Asia/Jakarta",
    "iso:country":"ID",
    "name:ind_x_preferred":[
        "Cirinten"
    ],
    "name:und_x_variant":[
        "Tjirinten",
        "Cirinten"
    ],
    "wof:lang_x_official":[
        "ind"
    ],
    "wof:lang_x_spoken":[
        "ind",
        "eng"
    ],
    "wof:name":"Cirinten",
    "wof:placetype":"locality"
},
  "geometry": {"coordinates":[106.1572,-6.6324],"type":"Point"}
}