{
  "type": "Feature",
  "properties": {
    "gn:admin1_code":"7.0",
    "gn:asciiname":"Jerukmenyan",
    "gn:country_code":"ID",
    "gn:dem":606,
    "gn:feature_class":"P",
    "gn:feature_code":"PPL",
    "gn:name":"Jerukmenyan",
    "gn:population":0,
    "gn:timezone":"Asia/Jakarta",
    "iso:country":"ID",
    "name:ind_x_preferred":[
        "Jerukmenyan"
    ],
    "name:und_x_variant":[
        "Djeroekmenjan"
    ],
    "wof:lang_x_official":[
        "ind"
    ],
    "wof:lang_x_spoken":[
        "ind",
        "eng"
    ],
    "wof:name":"Jerukmenyan",
    "wof:placetype":"locality"
},
  "geometry": {"coordinates":[108.6035,-7.1864],"type":"Point"}
}