{
  "type": "Feature",
  "properties": {
    "gn:admin1_code":"26",
    "gn:asciiname":"Bahgunung",
    "gn:country_code":"ID",
    "gn:dem":136,
    "gn:feature_class":"P",
    "gn:feature_code":"PPL",
    "gn:name":"Bahgunung",
    "gn:population":0,
    "gn:timezone":"Asia/Jakarta",
    "iso:country":"ID",
    "name:ind_x_preferred":[
        "Bahgunung"
    ],
    "wof:name":"Bahgunung",
    "wof:placetype":"locality"
},
  "geometry": {"coordinates":[99.19629999999999,3.0747],"type":"Point"}
}