{
  "type": "Feature",
  "properties": {
    "gn:admin1_code":"30",
    "gn:asciiname":"Citeureup",
    "gn:cc2":"ID",
    "gn:country_code":"ID",
    "gn:dem":665,
    "gn:feature_class":"P",
    "gn:feature_code":"PPL",
    "gn:name":"Citeureup",
    "gn:population":0,
    "gn:timezone":"Asia/Jakarta",
    "iso:country":"ID",
    "name:ind_x_preferred":[
        "Citeureup"
    ],
    "name:jav_x_preferred":[
        "Citeureup"
    ],
    "name:mlg_x_preferred":[
        "Citeureup"
    ],
    "name:sun_x_preferred":[
        "Citeureup"
    ],
    "name:und_x_variant":[
        "Tjiteureup 1",
        "Citeureup Satu",
        "Citeureup"
    ],
    "wof:name":"Citeureup",
    "wof:placetype":"locality"
},
  "geometry": {"coordinates":[107.57778,-7.00111],"type":"Point"}
}