{
  "type": "Feature",
  "properties": {
    "gn:admin1_code":"18.0",
    "gn:asciiname":"Tadanu",
    "gn:country_code":"ID",
    "gn:dem":30,
    "gn:feature_class":"P",
    "gn:feature_code":"PPL",
    "gn:name":"Tadanu",
    "gn:population":0,
    "gn:timezone":"Asia/Makassar",
    "iso:country":"ID",
    "name:ind_x_preferred":[
        "Tadanu"
    ],
    "wof:name":"Tadanu",
    "wof:placetype":"locality"
},
  "geometry": {"coordinates":[120.67321,-9.92881],"type":"Point"}
}