{
  "type": "Feature",
  "properties": {
    "gn:admin1_code":"11.0",
    "gn:asciiname":"Rasau",
    "gn:country_code":"ID",
    "gn:dem":45,
    "gn:feature_class":"P",
    "gn:feature_code":"PPL",
    "gn:name":"Rasau",
    "gn:population":0,
    "gn:timezone":"Asia/Pontianak",
    "iso:country":"ID",
    "name:deu_x_preferred":[
        "Rasau"
    ],
    "name:und_x_variant":[
        "Asau",
        "Rasau"
    ],
    "wof:lang_x_official":[
        "ind"
    ],
    "wof:lang_x_spoken":[
        "ind",
        "eng"
    ],
    "wof:name":"Rasau",
    "wof:placetype":"locality"
},
  "geometry": {"coordinates":[111.09999999999999,0.93333],"type":"Point"}
}