{
  "type": "Feature",
  "properties": {
    "gn:admin1_code":"8",
    "gn:asciiname":"Kebaran",
    "gn:country_code":"ID",
    "gn:dem":411,
    "gn:feature_class":"P",
    "gn:feature_code":"PPL",
    "gn:name":"Kebaran",
    "gn:population":0,
    "gn:timezone":"Asia/Jakarta",
    "iso:country":"ID",
    "name:ind_x_preferred":[
        "Kebaran"
    ],
    "wof:name":"Kebaran",
    "wof:placetype":"locality"
},
  "geometry": {"coordinates":[111.31667,-7.64111],"type":"Point"}
}