{
  "type": "Feature",
  "properties": {
    "gn:admin1_code":"8",
    "gn:asciiname":"Kebaran",
    "gn:country_code":"ID",
    "gn:dem":411,
    "gn:feature_class":"P",
    "gn:feature_code":"PPL",
    "gn:name":"Kebaran",
    "gn:population":0,
    "gn:timezone":"Asia/Jakarta",
    "iso:country":"ID",
    "name:ara_x_preferred":[
        "\u062b\u0642\u0627\u0641\u0629 \u0643\u0628\u0627\u0631\u064a\u0629"
    ],
    "name:cat_x_preferred":[
        "Kebari\u00e0"
    ],
    "name:ces_x_preferred":[
        "Kebaran"
    ],
    "name:deu_x_preferred":[
        "Kebarien"
    ],
    "name:fin_x_preferred":[
        "Kebaran kulttuuri"
    ],
    "name:fra_x_preferred":[
        "K\u00e9barien"
    ],
    "name:heb_x_preferred":[
        "\u05d4\u05ea\u05e8\u05d1\u05d5\u05ea \u05d4\u05db\u05d1\u05d0\u05e8\u05d9\u05ea"
    ],
    "name:hun_x_preferred":[
        "Kebara-kult\u00fara"
    ],
    "name:ind_x_preferred":[
        "Kebaran"
    ],
    "name:ita_x_preferred":[
        "Cultura kebariana"
    ],
    "name:nld_x_preferred":[
        "Kebaracultuur"
    ],
    "name:pol_x_preferred":[
        "Kultura kebaryjska"
    ],
    "name:rus_x_preferred":[
        "\u041a\u0435\u0431\u0430\u0440\u0441\u043a\u0430\u044f \u043a\u0443\u043b\u044c\u0442\u0443\u0440\u0430"
    ],
    "name:spa_x_preferred":[
        "Kebariense"
    ],
    "name:ukr_x_preferred":[
        "\u041a\u0435\u0431\u0430\u0440\u0430\u043d\u0441\u044c\u043a\u0430 \u043a\u0443\u043b\u044c\u0442\u0443\u0440\u0430"
    ],
    "wof:lang_x_official":[
        "ind"
    ],
    "wof:lang_x_spoken":[
        "ind",
        "eng"
    ],
    "wof:name":"Kebaran",
    "wof:placetype":"locality"
},
  "geometry": {"coordinates":[111.31667,-7.64111],"type":"Point"}
}