{
  "type": "Feature",
  "properties": {
    "gn:admin1_code":"38.0",
    "gn:asciiname":"Olang Dua",
    "gn:country_code":"ID",
    "gn:dem":30,
    "gn:feature_class":"P",
    "gn:feature_code":"PPL",
    "gn:name":"Olang Dua",
    "gn:population":0,
    "gn:timezone":"Asia/Makassar",
    "iso:country":"ID",
    "name:ind_x_preferred":[
        "Olang Dua"
    ],
    "wof:name":"Olang Dua",
    "wof:placetype":"locality"
},
  "geometry": {"coordinates":[120.31780000000001,-3.2648],"type":"Point"}
}