{
  "type": "Feature",
  "properties": {
    "gn:admin1_code":"30",
    "gn:asciiname":"Pasirtangkil",
    "gn:country_code":"ID",
    "gn:dem":407,
    "gn:feature_class":"P",
    "gn:feature_code":"PPL",
    "gn:name":"Pasirtangkil",
    "gn:population":0,
    "gn:timezone":"Asia/Jakarta",
    "iso:country":"ID",
    "name:ind_x_preferred":[
        "Pasirtangkil"
    ],
    "wof:name":"Pasirtangkil",
    "wof:placetype":"locality"
},
  "geometry": {"coordinates":[107.16278,-6.88361],"type":"Point"}
}