{
  "type": "Feature",
  "properties": {
    "gn:admin1_code":"30",
    "gn:asciiname":"Warungawi",
    "gn:country_code":"ID",
    "gn:dem":656,
    "gn:feature_class":"P",
    "gn:feature_code":"PPL",
    "gn:name":"Warungawi",
    "gn:population":0,
    "gn:timezone":"Asia/Jakarta",
    "iso:country":"ID",
    "name:ind_x_preferred":[
        "Warungawi"
    ],
    "wof:name":"Warungawi",
    "wof:placetype":"locality"
},
  "geometry": {"coordinates":[107.41806,-6.95278],"type":"Point"}
}