{
  "type": "Feature",
  "properties": {
    "gn:admin1_code":"7.0",
    "gn:asciiname":"Kesambi",
    "gn:country_code":"ID",
    "gn:dem":24,
    "gn:feature_class":"P",
    "gn:feature_code":"PPL",
    "gn:name":"Kesambi",
    "gn:population":0,
    "gn:timezone":"Asia/Jakarta",
    "iso:country":"ID",
    "name:ind_x_preferred":[
        "Kesambi"
    ],
    "wof:name":"Kesambi",
    "wof:placetype":"locality"
},
  "geometry": {"coordinates":[109.66361000000001,-7.65722],"type":"Point"}
}