{
  "type": "Feature",
  "properties": {
    "gn:admin1_code":"7.0",
    "gn:asciiname":"Sampad Satu",
    "gn:country_code":"ID",
    "gn:dem":401,
    "gn:feature_class":"P",
    "gn:feature_code":"PPL",
    "gn:name":"Sampad Satu",
    "gn:population":0,
    "gn:timezone":"Asia/Jakarta",
    "iso:country":"ID",
    "wof:name":"Sampad Satu",
    "wof:placetype":"locality"
},
  "geometry": {"coordinates":[110.12194,-7.52667],"type":"Point"}
}