{
  "type": "Feature",
  "properties": {
    "gn:admin1_code":"38",
    "gn:asciiname":"Baraka",
    "gn:country_code":"ID",
    "gn:dem":465,
    "gn:feature_class":"P",
    "gn:feature_code":"PPLA3",
    "gn:name":"Baraka",
    "gn:population":0,
    "gn:timezone":"Asia/Makassar",
    "iso:country":"ID",
    "name:ceb_x_preferred":[
        "Baraka"
    ],
    "name:ces_x_preferred":[
        "Baraka"
    ],
    "name:deu_x_preferred":[
        "Baraka"
    ],
    "name:fin_x_preferred":[
        "Baraka"
    ],
    "name:fra_x_preferred":[
        "Baraka"
    ],
    "name:ind_x_preferred":[
        "Baraka"
    ],
    "name:ita_x_preferred":[
        "Baraka"
    ],
    "name:jpn_x_preferred":[
        "\u30d0\u30e9\u30ab"
    ],
    "name:kor_x_preferred":[
        "\ubc14\ub77c\uce74"
    ],
    "name:nld_x_preferred":[
        "Baraka"
    ],
    "name:por_x_preferred":[
        "Baraca"
    ],
    "name:slk_x_preferred":[
        "Baraka"
    ],
    "name:spa_x_preferred":[
        "Baraka"
    ],
    "name:swe_x_preferred":[
        "Baraka"
    ],
    "name:vie_x_preferred":[
        "Baraka"
    ],
    "wof:lang_x_official":[
        "ind"
    ],
    "wof:lang_x_spoken":[
        "ind",
        "eng"
    ],
    "wof:name":"Baraka",
    "wof:placetype":"locality"
},
  "geometry": {"coordinates":[119.85590000000001,-3.4079],"type":"Point"}
}