{
  "type": "Feature",
  "properties": {
    "gn:admin1_code":"38",
    "gn:asciiname":"Baraka",
    "gn:country_code":"ID",
    "gn:dem":465,
    "gn:feature_class":"P",
    "gn:feature_code":"PPLA3",
    "gn:name":"Baraka",
    "gn:population":0,
    "gn:timezone":"Asia/Makassar",
    "iso:country":"ID",
    "name:ind_x_preferred":[
        "Baraka"
    ],
    "wof:name":"Baraka",
    "wof:placetype":"locality"
},
  "geometry": {"coordinates":[119.85590000000001,-3.4079],"type":"Point"}
}