{
  "type": "Feature",
  "properties": {
    "gn:admin1_code":"30",
    "gn:asciiname":"Lingga",
    "gn:country_code":"ID",
    "gn:dem":825,
    "gn:feature_class":"P",
    "gn:feature_code":"PPL",
    "gn:name":"Lingga",
    "gn:population":0,
    "gn:timezone":"Asia/Jakarta",
    "iso:country":"ID",
    "name:ind_x_preferred":[
        "Lingga"
    ],
    "wof:name":"Lingga",
    "wof:placetype":"locality"
},
  "geometry": {"coordinates":[107.8676,-7.2166],"type":"Point"}
}