{
  "type": "Feature",
  "properties": {
    "gn:admin1_code":"30",
    "gn:asciiname":"Cukanggaleh",
    "gn:country_code":"ID",
    "gn:dem":717,
    "gn:feature_class":"P",
    "gn:feature_code":"PPL",
    "gn:name":"Cukanggaleh",
    "gn:population":0,
    "gn:timezone":"Asia/Jakarta",
    "iso:country":"ID",
    "name:ind_x_preferred":[
        "Cukanggaleh"
    ],
    "name:und_x_variant":[
        "Tjukanggaleuh",
        "Cukanggaleuh"
    ],
    "wof:lang_x_official":[
        "ind"
    ],
    "wof:lang_x_spoken":[
        "ind",
        "eng"
    ],
    "wof:name":"Cukanggaleh",
    "wof:placetype":"locality"
},
  "geometry": {"coordinates":[107.32528000000001,-6.92833],"type":"Point"}
}