{
  "type": "Feature",
  "properties": {
    "gn:admin1_code":"28.0",
    "gn:asciiname":"Walpangat",
    "gn:country_code":"ID",
    "gn:dem":1113,
    "gn:feature_class":"P",
    "gn:feature_code":"PPL",
    "gn:name":"Walpangat",
    "gn:population":0,
    "gn:timezone":"Asia/Jayapura",
    "iso:country":"ID",
    "name:ind_x_preferred":[
        "Walpangat"
    ],
    "name:und_x_variant":[
        "Wal\u2019 Pangat"
    ],
    "wof:lang_x_official":[
        "ind"
    ],
    "wof:lang_x_spoken":[
        "ind",
        "eng"
    ],
    "wof:name":"Walpangat",
    "wof:placetype":"locality"
},
  "geometry": {"coordinates":[126.54261,-3.35599],"type":"Point"}
}