{
  "type": "Feature",
  "properties": {
    "gn:admin1_code":"30.0",
    "gn:asciiname":"Jingkang",
    "gn:country_code":"ID",
    "gn:dem":582,
    "gn:feature_class":"P",
    "gn:feature_code":"PPL",
    "gn:name":"Jingkang",
    "gn:population":0,
    "gn:timezone":"Asia/Jakarta",
    "iso:country":"ID",
    "name:ind_x_preferred":[
        "Jingkang"
    ],
    "name:und_x_variant":[
        "Djingkang"
    ],
    "wof:name":"Jingkang",
    "wof:placetype":"locality"
},
  "geometry": {"coordinates":[107.86388999999998,-6.71361],"type":"Point"}
}