{
  "type": "Feature",
  "properties": {
    "gn:admin1_code":"7.0",
    "gn:asciiname":"Cijengjing",
    "gn:country_code":"ID",
    "gn:dem":330,
    "gn:feature_class":"P",
    "gn:feature_code":"PPL",
    "gn:name":"Cijengjing",
    "gn:population":0,
    "gn:timezone":"Asia/Jakarta",
    "iso:country":"ID",
    "name:ind_x_preferred":[
        "Cijengjing"
    ],
    "name:und_x_variant":[
        "Tjidjengdjing"
    ],
    "wof:lang_x_official":[
        "ind"
    ],
    "wof:lang_x_spoken":[
        "ind",
        "eng"
    ],
    "wof:name":"Cijengjing",
    "wof:placetype":"locality"
},
  "geometry": {"coordinates":[108.7392,-7.2725],"type":"Point"}
}