{
  "type": "Feature",
  "properties": {
    "gn:admin1_code":"26",
    "gn:asciiname":"Paniasih",
    "gn:country_code":"ID",
    "gn:dem":378,
    "gn:feature_class":"P",
    "gn:feature_code":"PPL",
    "gn:name":"Paniasih",
    "gn:population":0,
    "gn:timezone":"Asia/Jakarta",
    "iso:country":"ID",
    "name:ind_x_preferred":[
        "Paniasih"
    ],
    "wof:name":"Paniasih",
    "wof:placetype":"locality"
},
  "geometry": {"coordinates":[99.0827,2.9352],"type":"Point"}
}