{
  "type": "Feature",
  "properties": {
    "gn:admin1_code":"17",
    "gn:asciiname":"Batunyala",
    "gn:country_code":"ID",
    "gn:dem":100,
    "gn:feature_class":"P",
    "gn:feature_code":"PPL",
    "gn:name":"Batunyala",
    "gn:population":0,
    "gn:timezone":"Asia/Makassar",
    "iso:country":"ID",
    "name:ind_x_preferred":[
        "Batunyala"
    ],
    "wof:name":"Batunyala",
    "wof:placetype":"locality"
},
  "geometry": {"coordinates":[116.51909999999999,-8.7146],"type":"Point"}
}