{
  "type": "Feature",
  "properties": {
    "gn:admin1_code":"30",
    "gn:asciiname":"Cirangkong Girang",
    "gn:country_code":"ID",
    "gn:dem":586,
    "gn:feature_class":"P",
    "gn:feature_code":"PPL",
    "gn:name":"Cirangkong Girang",
    "gn:population":0,
    "gn:timezone":"Asia/Jakarta",
    "iso:country":"ID",
    "name:ind_x_preferred":[
        "Cirangkong Girang"
    ],
    "wof:name":"Cirangkong Girang",
    "wof:placetype":"locality"
},
  "geometry": {"coordinates":[106.68056,-6.83861],"type":"Point"}
}