{
  "type": "Feature",
  "properties": {
    "gn:admin1_code":"7",
    "gn:asciiname":"Gumiwang",
    "gn:country_code":"ID",
    "gn:dem":543,
    "gn:feature_class":"P",
    "gn:feature_code":"PPL",
    "gn:name":"Gumiwang",
    "gn:population":0,
    "gn:timezone":"Asia/Jakarta",
    "iso:country":"ID",
    "name:ind_x_preferred":[
        "Gumiwang"
    ],
    "wof:name":"Gumiwang",
    "wof:placetype":"locality"
},
  "geometry": {"coordinates":[109.88778000000001,-7.48833],"type":"Point"}
}