{
  "type": "Feature",
  "properties": {
    "gn:admin1_code":"24",
    "gn:asciiname":"Muarabandar",
    "gn:country_code":"ID",
    "gn:dem":89,
    "gn:feature_class":"P",
    "gn:feature_code":"PPL",
    "gn:name":"Muarabandar",
    "gn:population":0,
    "gn:timezone":"Asia/Jakarta",
    "iso:country":"ID",
    "name:ind_x_preferred":[
        "Muarabandar"
    ],
    "wof:name":"Muarabandar",
    "wof:placetype":"locality"
},
  "geometry": {"coordinates":[100.7401,0.0869],"type":"Point"}
}