{
  "type": "Feature",
  "properties": {
    "gn:admin1_code":"0.0",
    "gn:asciiname":"Tanjungbatu",
    "gn:cc2":"ID",
    "gn:country_code":"ID",
    "gn:dem":45,
    "gn:feature_class":"P",
    "gn:feature_code":"PPL",
    "gn:name":"Tanjungbatu",
    "gn:population":0,
    "gn:timezone":"Asia/Pontianak",
    "iso:country":"ID",
    "name:und_x_variant":[
        "Tandjungbatu",
        "Tandjoengbatoe",
        "Tanjungbatu"
    ],
    "wof:name":"Tanjungbatu",
    "wof:placetype":"locality"
},
  "geometry": {"coordinates":[110.59999999999999,-2.05],"type":"Point"}
}