{
  "type": "Feature",
  "properties": {
    "gn:admin1_code":"37.0",
    "gn:asciiname":"Simpangayam",
    "gn:country_code":"ID",
    "gn:dem":14,
    "gn:feature_class":"P",
    "gn:feature_code":"PPL",
    "gn:name":"Simpangayam",
    "gn:population":0,
    "gn:timezone":"Asia/Jakarta",
    "iso:country":"ID",
    "name:und_x_variant":[
        "Simpangajam",
        "Simpangayam"
    ],
    "wof:name":"Simpangayam",
    "wof:placetype":"locality"
},
  "geometry": {"coordinates":[102.05,1.58333],"type":"Point"}
}