{
  "type": "Feature",
  "properties": {
    "gn:admin1_code":"0.0",
    "gn:asciiname":"Maki",
    "gn:country_code":"ID",
    "gn:dem":12,
    "gn:feature_class":"P",
    "gn:feature_code":"PPL",
    "gn:name":"Maki",
    "gn:population":0,
    "gn:timezone":"Asia/Jayapura",
    "iso:country":"ID",
    "name:ara_x_preferred":[
        "\u0645\u0627\u0643\u064a"
    ],
    "name:cat_x_preferred":[
        "Maki"
    ],
    "name:ceb_x_preferred":[
        "Maki"
    ],
    "name:ces_x_preferred":[
        "Maki"
    ],
    "name:dan_x_preferred":[
        "Maki"
    ],
    "name:deu_x_preferred":[
        "Maki"
    ],
    "name:eus_x_preferred":[
        "Maki"
    ],
    "name:fas_x_preferred":[
        "\u0645\u06a9\u06cc"
    ],
    "name:fin_x_preferred":[
        "Maki"
    ],
    "name:fra_x_preferred":[
        "Maki"
    ],
    "name:ind_x_preferred":[
        "Maki"
    ],
    "name:ita_x_preferred":[
        "Maki"
    ],
    "name:pol_x_preferred":[
        "Maki"
    ],
    "name:por_x_preferred":[
        "Maki"
    ],
    "name:spa_x_preferred":[
        "Maki"
    ],
    "name:swe_x_preferred":[
        "Maki"
    ],
    "wof:lang_x_official":[
        "ind"
    ],
    "wof:lang_x_spoken":[
        "ind",
        "eng"
    ],
    "wof:name":"Maki",
    "wof:placetype":"locality"
},
  "geometry": {"coordinates":[138.83332999999999,-7.25],"type":"Point"}
}