{
  "type": "Feature",
  "properties": {
    "gn:admin1_code":"30.0",
    "gn:asciiname":"Sukamulya",
    "gn:country_code":"ID",
    "gn:dem":1138,
    "gn:feature_class":"P",
    "gn:feature_code":"PPL",
    "gn:name":"Sukamulya",
    "gn:population":0,
    "gn:timezone":"Asia/Jakarta",
    "iso:country":"ID",
    "name:ind_x_preferred":[
        "Sukamulya"
    ],
    "name:jav_x_preferred":[
        "Sukamulya"
    ],
    "name:msa_x_preferred":[
        "Sukamulya"
    ],
    "wof:name":"Sukamulya",
    "wof:placetype":"locality"
},
  "geometry": {"coordinates":[106.4956,-6.8013],"type":"Point"}
}