{
  "type": "Feature",
  "properties": {
    "gn:admin1_code":"18.0",
    "gn:asciiname":"Tarunggawang",
    "gn:country_code":"ID",
    "gn:dem":240,
    "gn:feature_class":"P",
    "gn:feature_code":"PPL",
    "gn:name":"Tarunggawang",
    "gn:population":0,
    "gn:timezone":"Asia/Makassar",
    "iso:country":"ID",
    "name:ind_x_preferred":[
        "Tarunggawang"
    ],
    "wof:name":"Tarunggawang",
    "wof:placetype":"locality"
},
  "geometry": {"coordinates":[122.1906,-8.7206],"type":"Point"}
}