{
  "type": "Feature",
  "properties": {
    "gn:admin1_code":"30",
    "gn:asciiname":"Kawungluwuk Girang",
    "gn:country_code":"ID",
    "gn:dem":334,
    "gn:feature_class":"P",
    "gn:feature_code":"PPL",
    "gn:name":"Kawungluwuk Girang",
    "gn:population":0,
    "gn:timezone":"Asia/Jakarta",
    "iso:country":"ID",
    "name:ind_x_preferred":[
        "Kawungluwuk Girang"
    ],
    "wof:name":"Kawungluwuk Girang",
    "wof:placetype":"locality"
},
  "geometry": {"coordinates":[106.59556000000001,-6.54722],"type":"Point"}
}