{
  "type": "Feature",
  "properties": {
    "gn:admin1_code":"30.0",
    "gn:asciiname":"Karangmulya",
    "gn:country_code":"ID",
    "gn:dem":322,
    "gn:feature_class":"P",
    "gn:feature_code":"PPL",
    "gn:name":"Karangmulya",
    "gn:population":0,
    "gn:timezone":"Asia/Jakarta",
    "iso:country":"ID",
    "name:ind_x_preferred":[
        "Karangmulya"
    ],
    "wof:name":"Karangmulya",
    "wof:placetype":"locality"
},
  "geometry": {"coordinates":[108.28830000000001,-7.3622],"type":"Point"}
}