{
  "type": "Feature",
  "properties": {
    "gn:admin1_code":"28.0",
    "gn:asciiname":"Tehua",
    "gn:country_code":"ID",
    "gn:dem":64,
    "gn:feature_class":"P",
    "gn:feature_code":"PPL",
    "gn:name":"Tehua",
    "gn:population":0,
    "gn:timezone":"Asia/Jayapura",
    "iso:country":"ID",
    "name:fra_x_preferred":[
        "Tehua"
    ],
    "name:spa_x_preferred":[
        "Tehua"
    ],
    "wof:lang_x_official":[
        "ind"
    ],
    "wof:lang_x_spoken":[
        "ind",
        "eng"
    ],
    "wof:name":"Tehua",
    "wof:placetype":"locality"
},
  "geometry": {"coordinates":[129.69166999999999,-3.31167],"type":"Point"}
}