{
  "type": "Feature",
  "properties": {
    "gn:admin1_code":"0.0",
    "gn:asciiname":"Sebawan",
    "gn:country_code":"ID",
    "gn:dem":103,
    "gn:feature_class":"P",
    "gn:feature_code":"PPL",
    "gn:name":"Sebawan",
    "gn:population":0,
    "gn:timezone":"Asia/Pontianak",
    "iso:country":"ID",
    "wof:name":"Sebawan",
    "wof:placetype":"locality"
},
  "geometry": {"coordinates":[111.91667,-1.28333],"type":"Point"}
}