{
  "type": "Feature",
  "properties": {
    "gn:admin1_code":"30.0",
    "gn:asciiname":"Kawungluwuk",
    "gn:country_code":"ID",
    "gn:dem":890,
    "gn:feature_class":"P",
    "gn:feature_code":"PPL",
    "gn:name":"Kawungluwuk",
    "gn:population":0,
    "gn:timezone":"Asia/Jakarta",
    "iso:country":"ID",
    "name:ind_x_preferred":[
        "Kawungluwuk"
    ],
    "name:und_x_variant":[
        "Kawoenglawoek"
    ],
    "wof:lang_x_official":[
        "ind"
    ],
    "wof:lang_x_spoken":[
        "ind",
        "eng"
    ],
    "wof:name":"Kawungluwuk",
    "wof:placetype":"locality"
},
  "geometry": {"coordinates":[107.8984,-7.2519],"type":"Point"}
}