{
  "type": "Feature",
  "properties": {
    "gn:admin1_code":"8.0",
    "gn:asciiname":"Krasak",
    "gn:country_code":"ID",
    "gn:dem":354,
    "gn:feature_class":"P",
    "gn:feature_code":"PPL",
    "gn:name":"Krasak",
    "gn:population":0,
    "gn:timezone":"Asia/Jakarta",
    "iso:country":"ID",
    "name:ind_x_preferred":[
        "Krasak"
    ],
    "wof:name":"Krasak",
    "wof:placetype":"locality"
},
  "geometry": {"coordinates":[113.7901,-7.8908],"type":"Point"}
}