{
  "type": "Feature",
  "properties": {
    "gn:admin1_code":"7.0",
    "gn:asciiname":"Gale",
    "gn:country_code":"ID",
    "gn:dem":15,
    "gn:feature_class":"P",
    "gn:feature_code":"PPL",
    "gn:name":"Gale",
    "gn:population":0,
    "gn:timezone":"Asia/Jakarta",
    "iso:country":"ID",
    "name:ara_x_preferred":[
        "\u0631\u064a\u062d \u0647\u0648\u062c\u0627\u0621"
    ],
    "name:cat_x_preferred":[
        "Temporal"
    ],
    "name:dan_x_preferred":[
        "Kuling"
    ],
    "name:deu_x_preferred":[
        "Starkwind"
    ],
    "name:ind_x_preferred":[
        "Gale"
    ],
    "name:ita_x_preferred":[
        "Burrasca"
    ],
    "name:lav_x_preferred":[
        "Auka"
    ],
    "name:nno_x_preferred":[
        "Kuling"
    ],
    "name:nor_x_preferred":[
        "Kuling"
    ],
    "name:pol_x_preferred":[
        "Wicher"
    ],
    "name:scn_x_preferred":[
        "Burrasca"
    ],
    "name:spa_x_preferred":[
        "Temporal"
    ],
    "name:swe_x_preferred":[
        "Kuling"
    ],
    "wof:lang_x_official":[
        "ind"
    ],
    "wof:lang_x_spoken":[
        "ind",
        "eng"
    ],
    "wof:name":"Gale",
    "wof:placetype":"locality"
},
  "geometry": {"coordinates":[111.0192,-6.8521],"type":"Point"}
}