{
  "type": "Feature",
  "properties": {
    "gn:admin1_code":"38",
    "gn:asciiname":"Bontotangnga",
    "gn:country_code":"ID",
    "gn:dem":7,
    "gn:feature_class":"P",
    "gn:feature_code":"PPL",
    "gn:name":"Bontotangnga",
    "gn:population":0,
    "gn:timezone":"Asia/Makassar",
    "iso:country":"ID",
    "name:ind_x_preferred":[
        "Bontotangnga"
    ],
    "wof:name":"Bontotangnga",
    "wof:placetype":"locality"
},
  "geometry": {"coordinates":[119.5908,-5.0027],"type":"Point"}
}