{
  "type": "Feature",
  "properties": {
    "gn:admin1_code":"36.0",
    "gn:asciiname":"Titar",
    "gn:country_code":"ID",
    "gn:dem":2300,
    "gn:feature_class":"P",
    "gn:feature_code":"PPL",
    "gn:name":"Titar",
    "gn:population":0,
    "gn:timezone":"Asia/Jayapura",
    "iso:country":"ID",
    "name:ind_x_preferred":[
        "Titar"
    ],
    "name:und_x_variant":[
        "Titare"
    ],
    "wof:lang_x_official":[
        "ind"
    ],
    "wof:lang_x_spoken":[
        "ind",
        "eng"
    ],
    "wof:name":"Titar",
    "wof:placetype":"locality"
},
  "geometry": {"coordinates":[138.39240000000001,-3.6306],"type":"Point"}
}