{
  "type": "Feature",
  "properties": {
    "gn:admin1_code":"30",
    "gn:asciiname":"Cibule",
    "gn:country_code":"ID",
    "gn:dem":266,
    "gn:feature_class":"P",
    "gn:feature_code":"PPL",
    "gn:name":"Cibule",
    "gn:population":0,
    "gn:timezone":"Asia/Jakarta",
    "iso:country":"ID",
    "name:ind_x_preferred":[
        "Cibule"
    ],
    "wof:name":"Cibule",
    "wof:placetype":"locality"
},
  "geometry": {"coordinates":[107.16361000000001,-6.65056],"type":"Point"}
}