{
  "type": "Feature",
  "properties": {
    "gn:admin1_code":"30",
    "gn:asciiname":"Pameukpeuk",
    "gn:country_code":"ID",
    "gn:dem":856,
    "gn:feature_class":"P",
    "gn:feature_code":"PPL",
    "gn:name":"Pameukpeuk",
    "gn:population":0,
    "gn:timezone":"Asia/Jakarta",
    "iso:country":"ID",
    "name:ind_x_preferred":[
        "Pameukpeuk"
    ],
    "wof:name":"Pameukpeuk",
    "wof:placetype":"locality"
},
  "geometry": {"coordinates":[107.86369999999999,-7.2308],"type":"Point"}
}