{
  "type": "Feature",
  "properties": {
    "gn:admin1_code":"2",
    "gn:asciiname":"Banjar Mundukanggrek",
    "gn:country_code":"ID",
    "gn:dem":125,
    "gn:feature_class":"P",
    "gn:feature_code":"PPL",
    "gn:name":"Banjar Mundukanggrek",
    "gn:population":0,
    "gn:timezone":"Asia/Makassar",
    "iso:country":"ID",
    "name:ind_x_preferred":[
        "Banjar Mundukanggrek"
    ],
    "wof:name":"Banjar Mundukanggrek",
    "wof:placetype":"locality"
},
  "geometry": {"coordinates":[114.7516,-8.3535],"type":"Point"}
}