{
  "type": "Feature",
  "properties": {
    "gn:admin1_code":"8",
    "gn:asciiname":"Klubuk Wetan",
    "gn:country_code":"ID",
    "gn:dem":101,
    "gn:feature_class":"P",
    "gn:feature_code":"PPL",
    "gn:name":"Klubuk Wetan",
    "gn:population":0,
    "gn:timezone":"Asia/Jakarta",
    "iso:country":"ID",
    "name:ind_x_preferred":[
        "Klubuk Wetan"
    ],
    "wof:name":"Klubuk Wetan",
    "wof:placetype":"locality"
},
  "geometry": {"coordinates":[112.87090000000001,-7.7577],"type":"Point"}
}