{
  "type": "Feature",
  "properties": {
    "gn:admin1_code":"17.0",
    "gn:asciiname":"Karangjuet",
    "gn:country_code":"ID",
    "gn:dem":39,
    "gn:feature_class":"P",
    "gn:feature_code":"PPL",
    "gn:name":"Karangjuet",
    "gn:population":0,
    "gn:timezone":"Asia/Makassar",
    "iso:country":"ID",
    "name:ind_x_preferred":[
        "Karangjuet"
    ],
    "wof:name":"Karangjuet",
    "wof:placetype":"locality"
},
  "geometry": {"coordinates":[116.17359999999999,-8.3676],"type":"Point"}
}