{
  "type": "Feature",
  "properties": {
    "gn:admin1_code":"8.0",
    "gn:asciiname":"Tlogosari",
    "gn:country_code":"ID",
    "gn:dem":449,
    "gn:feature_class":"P",
    "gn:feature_code":"PPLA4",
    "gn:name":"Tlogosari",
    "gn:population":0,
    "gn:timezone":"Asia/Jakarta",
    "iso:country":"ID",
    "name:ind_x_preferred":[
        "Tlogosari"
    ],
    "name:und_x_variant":[
        "Telogosari"
    ],
    "wof:name":"Tlogosari",
    "wof:placetype":"locality"
},
  "geometry": {"coordinates":[112.47329999999999,-8.281],"type":"Point"}
}