{
  "type": "Feature",
  "properties": {
    "gn:admin1_code":"18.0",
    "gn:asciiname":"Andalara",
    "gn:country_code":"ID",
    "gn:dem":406,
    "gn:feature_class":"P",
    "gn:feature_code":"PPL",
    "gn:name":"Andalara",
    "gn:population":0,
    "gn:timezone":"Asia/Makassar",
    "iso:country":"ID",
    "name:ind_x_preferred":[
        "Andalara"
    ],
    "wof:name":"Andalara",
    "wof:placetype":"locality"
},
  "geometry": {"coordinates":[119.1908,-9.5566],"type":"Point"}
}