{
  "type": "Feature",
  "properties": {
    "gn:admin1_code":"26",
    "gn:asciiname":"Kampung Gajing",
    "gn:country_code":"ID",
    "gn:dem":181,
    "gn:feature_class":"P",
    "gn:feature_code":"PPL",
    "gn:name":"Kampung Gajing",
    "gn:population":0,
    "gn:timezone":"Asia/Jakarta",
    "iso:country":"ID",
    "name:ind_x_preferred":[
        "Kampung Gajing"
    ],
    "name:und_x_variant":[
        "Gadjingbaju"
    ],
    "wof:name":"Kampung Gajing",
    "wof:placetype":"locality"
},
  "geometry": {"coordinates":[99.18340000000001,3.0167],"type":"Point"}
}