{
  "type": "Feature",
  "properties": {
    "gn:admin1_code":"30.0",
    "gn:asciiname":"Sindangraja",
    "gn:country_code":"ID",
    "gn:dem":439,
    "gn:feature_class":"P",
    "gn:feature_code":"PPL",
    "gn:name":"Sindangraja",
    "gn:population":0,
    "gn:timezone":"Asia/Jakarta",
    "iso:country":"ID",
    "name:ind_x_preferred":[
        "Sindangraja"
    ],
    "name:und_x_variant":[
        "Sindangradja"
    ],
    "wof:name":"Sindangraja",
    "wof:placetype":"locality"
},
  "geometry": {"coordinates":[108.363,-7.1532],"type":"Point"}
}