{
  "type": "Feature",
  "properties": {
    "gn:admin1_code":"38",
    "gn:asciiname":"Sero",
    "gn:country_code":"ID",
    "gn:dem":167,
    "gn:feature_class":"P",
    "gn:feature_code":"PPL",
    "gn:name":"Sero",
    "gn:population":0,
    "gn:timezone":"Asia/Makassar",
    "iso:country":"ID",
    "name:ind_x_preferred":[
        "Sero"
    ],
    "wof:name":"Sero",
    "wof:placetype":"locality"
},
  "geometry": {"coordinates":[119.89490000000001,-4.5053],"type":"Point"}
}