{
  "type": "Feature",
  "properties": {
    "gn:admin1_code":"8.0",
    "gn:asciiname":"Langsepan",
    "gn:country_code":"ID",
    "gn:dem":64,
    "gn:feature_class":"P",
    "gn:feature_code":"PPL",
    "gn:name":"Langsepan",
    "gn:population":0,
    "gn:timezone":"Asia/Jakarta",
    "iso:country":"ID",
    "name:ind_x_preferred":[
        "Langsepan"
    ],
    "wof:name":"Langsepan",
    "wof:placetype":"locality"
},
  "geometry": {"coordinates":[113.651,-8.2571],"type":"Point"}
}