{
  "type": "Feature",
  "properties": {
    "gn:admin1_code":"7.0",
    "gn:asciiname":"Gadingpasar Dua",
    "gn:country_code":"ID",
    "gn:dem":15,
    "gn:feature_class":"P",
    "gn:feature_code":"PPL",
    "gn:name":"Gadingpasar Dua",
    "gn:population":0,
    "gn:timezone":"Asia/Jakarta",
    "iso:country":"ID",
    "name:ind_x_preferred":[
        "Gadingpasar Dua"
    ],
    "wof:name":"Gadingpasar Dua",
    "wof:placetype":"locality"
},
  "geometry": {"coordinates":[109.86388999999998,-7.81944],"type":"Point"}
}