{
  "type": "Feature",
  "properties": {
    "gn:admin1_code":"30",
    "gn:asciiname":"Lodog",
    "gn:country_code":"ID",
    "gn:dem":34,
    "gn:feature_class":"P",
    "gn:feature_code":"PPL",
    "gn:name":"Lodog",
    "gn:population":0,
    "gn:timezone":"Asia/Jakarta",
    "iso:country":"ID",
    "name:ind_x_preferred":[
        "Lodog"
    ],
    "name:und_x_variant":[
        "Ladog"
    ],
    "wof:name":"Lodog",
    "wof:placetype":"locality"
},
  "geometry": {"coordinates":[106.43556,-6.28556],"type":"Point"}
}