{
  "type": "Feature",
  "properties": {
    "gn:admin1_code":"1",
    "gn:asciiname":"Padangseureuel",
    "gn:country_code":"ID",
    "gn:dem":8,
    "gn:feature_class":"P",
    "gn:feature_code":"PPL",
    "gn:name":"Padangseureuel",
    "gn:population":0,
    "gn:timezone":"Asia/Jakarta",
    "iso:country":"ID",
    "name:ind_x_preferred":[
        "Padangseureuel"
    ],
    "wof:name":"Padangseureuel",
    "wof:placetype":"locality"
},
  "geometry": {"coordinates":[96.1588,4.1411],"type":"Point"}
}