{
  "type": "Feature",
  "properties": {
    "gn:admin1_code":"7.0",
    "gn:asciiname":"Krisik",
    "gn:country_code":"ID",
    "gn:dem":289,
    "gn:feature_class":"P",
    "gn:feature_code":"PPL",
    "gn:name":"Krisik",
    "gn:population":0,
    "gn:timezone":"Asia/Jakarta",
    "iso:country":"ID",
    "name:ind_x_preferred":[
        "Krisik"
    ],
    "wof:name":"Krisik",
    "wof:placetype":"locality"
},
  "geometry": {"coordinates":[109.45471999999999,-7.55139],"type":"Point"}
}