{
  "type": "Feature",
  "properties": {
    "gn:admin1_code":"7.0",
    "gn:asciiname":"Gedogan",
    "gn:country_code":"ID",
    "gn:dem":617,
    "gn:feature_class":"P",
    "gn:feature_code":"PPL",
    "gn:name":"Gedogan",
    "gn:population":0,
    "gn:timezone":"Asia/Jakarta",
    "iso:country":"ID",
    "wof:name":"Gedogan",
    "wof:placetype":"locality"
},
  "geometry": {"coordinates":[110.30806,-7.43111],"type":"Point"}
}