{
  "type": "Feature",
  "properties": {
    "gn:admin1_code":"7.0",
    "gn:asciiname":"Salipputih",
    "gn:country_code":"ID",
    "gn:dem":741,
    "gn:feature_class":"P",
    "gn:feature_code":"PPL",
    "gn:name":"Salipputih",
    "gn:population":0,
    "gn:timezone":"Asia/Jakarta",
    "iso:country":"ID",
    "wof:name":"Salipputih",
    "wof:placetype":"locality"
},
  "geometry": {"coordinates":[110.48,-7.35972],"type":"Point"}
}