{
  "type": "Feature",
  "properties": {
    "gn:admin1_code":"8",
    "gn:asciiname":"Merau",
    "gn:country_code":"ID",
    "gn:dem":78,
    "gn:feature_class":"P",
    "gn:feature_code":"PPL",
    "gn:name":"Merau",
    "gn:population":0,
    "gn:timezone":"Asia/Jakarta",
    "iso:country":"ID",
    "name:ind_x_preferred":[
        "Merau"
    ],
    "wof:name":"Merau",
    "wof:placetype":"locality"
},
  "geometry": {"coordinates":[111.6563,-7.5337],"type":"Point"}
}