{
  "type": "Feature",
  "properties": {
    "gn:admin1_code":"7.0",
    "gn:asciiname":"Ngadisari",
    "gn:country_code":"ID",
    "gn:dem":876,
    "gn:feature_class":"P",
    "gn:feature_code":"PPL",
    "gn:name":"Ngadisari",
    "gn:population":0,
    "gn:timezone":"Asia/Jakarta",
    "iso:country":"ID",
    "wof:name":"Ngadisari",
    "wof:placetype":"locality"
},
  "geometry": {"coordinates":[110.01389,-7.45361],"type":"Point"}
}