{
  "type": "Feature",
  "properties": {
    "gn:admin1_code":"41",
    "gn:asciiname":"Batasawa",
    "gn:country_code":"ID",
    "gn:dem":908,
    "gn:feature_class":"P",
    "gn:feature_code":"PPL",
    "gn:name":"Batasawa",
    "gn:population":0,
    "gn:timezone":"Asia/Makassar",
    "iso:country":"ID",
    "name:ind_x_preferred":[
        "Batasawa"
    ],
    "wof:name":"Batasawa",
    "wof:placetype":"locality"
},
  "geometry": {"coordinates":[119.3066,-3.1536],"type":"Point"}
}