{
  "type": "Feature",
  "properties": {
    "gn:admin1_code":"8.0",
    "gn:asciiname":"Ongga'an",
    "gn:country_code":"ID",
    "gn:dem":45,
    "gn:feature_class":"P",
    "gn:feature_code":"PPL",
    "gn:name":"Ongga\u2019an",
    "gn:population":0,
    "gn:timezone":"Asia/Jakarta",
    "iso:country":"ID",
    "name:ind_x_preferred":[
        "Ongga\u2019an"
    ],
    "wof:name":"Ongga'an",
    "wof:placetype":"locality"
},
  "geometry": {"coordinates":[113.952,-7.0776],"type":"Point"}
}