{
  "type": "Feature",
  "properties": {
    "gn:admin1_code":"7.0",
    "gn:asciiname":"Kecila Tiga",
    "gn:country_code":"ID",
    "gn:dem":17,
    "gn:feature_class":"P",
    "gn:feature_code":"PPL",
    "gn:name":"Kecila Tiga",
    "gn:population":0,
    "gn:timezone":"Asia/Jakarta",
    "iso:country":"ID",
    "name:ind_x_preferred":[
        "Kecila Tiga"
    ],
    "wof:name":"Kecila Tiga",
    "wof:placetype":"locality"
},
  "geometry": {"coordinates":[109.31833,-7.605],"type":"Point"}
}