{
  "type": "Feature",
  "properties": {
    "gn:admin1_code":"08",
    "gn:asciiname":"Pakematas",
    "gn:country_code":"ID",
    "gn:dem":68,
    "gn:feature_class":"P",
    "gn:feature_code":"PPL",
    "gn:name":"Pakematas",
    "gn:population":0,
    "gn:timezone":"Asia/Jakarta",
    "iso:country":"ID",
    "name:ind_x_preferred":[
        "Pakematas"
    ],
    "name:und_x_variant":[
        "Pakem"
    ],
    "wof:name":"Pakematas",
    "wof:placetype":"locality"
},
  "geometry": {"coordinates":[112.8305,-7.0294],"type":"Point"}
}