{
  "type": "Feature",
  "properties": {
    "gn:admin1_code":"26.0",
    "gn:asciiname":"Bulu Pange",
    "gn:country_code":"ID",
    "gn:dem":898,
    "gn:feature_class":"P",
    "gn:feature_code":"PPL",
    "gn:name":"Bulu Pange",
    "gn:population":0,
    "gn:timezone":"Asia/Jakarta",
    "iso:country":"ID",
    "name:ind_x_preferred":[
        "Bulu Pange"
    ],
    "wof:name":"Bulu Pange",
    "wof:placetype":"locality"
},
  "geometry": {"coordinates":[98.8974,2.9364],"type":"Point"}
}