{
  "type": "Feature",
  "properties": {
    "gn:admin1_code":"30",
    "gn:asciiname":"Tutugan",
    "gn:country_code":"ID",
    "gn:dem":939,
    "gn:feature_class":"P",
    "gn:feature_code":"PPL",
    "gn:name":"Tutugan",
    "gn:population":0,
    "gn:timezone":"Asia/Jakarta",
    "iso:country":"ID",
    "name:ind_x_preferred":[
        "Tutugan"
    ],
    "wof:name":"Tutugan",
    "wof:placetype":"locality"
},
  "geometry": {"coordinates":[107.14943999999998,-6.99389],"type":"Point"}
}