{
  "type": "Feature",
  "properties": {
    "gn:admin1_code":"7",
    "gn:asciiname":"Kliwonan",
    "gn:country_code":"ID",
    "gn:dem":879,
    "gn:feature_class":"P",
    "gn:feature_code":"PPL",
    "gn:name":"Kliwonan",
    "gn:population":0,
    "gn:timezone":"Asia/Jakarta",
    "iso:country":"ID",
    "name:ind_x_preferred":[
        "Kliwonan"
    ],
    "wof:name":"Kliwonan",
    "wof:placetype":"locality"
},
  "geometry": {"coordinates":[109.96222,-7.38139],"type":"Point"}
}