{
  "type": "Feature",
  "properties": {
    "gn:country":"ID",
    "gn:fcode":"PPLA3",
    "gn:pop":0,
    "iso:country":"ID",
    "name:ace_x_preferred":[
        "Pameungpeuk"
    ],
    "name:ceb_x_preferred":[
        "Desa Pameungpeuk"
    ],
    "name:deu_x_preferred":[
        "Pameungpeuk"
    ],
    "name:eng_x_preferred":[
        "Pameungpeuk"
    ],
    "name:fra_x_preferred":[
        "Pameungpeuk"
    ],
    "name:ind_x_preferred":[
        "Pameungpeuk"
    ],
    "name:mlg_x_preferred":[
        "Pameungpeuk"
    ],
    "name:msa_x_preferred":[
        "Pameungpeuk"
    ],
    "name:nld_x_preferred":[
        "Pameungpeuk"
    ],
    "name:por_x_preferred":[
        "Pameungpeuk"
    ],
    "name:spa_x_preferred":[
        "Pameungpeuk"
    ],
    "name:sun_x_preferred":[
        "Pameungpeuk"
    ],
    "name:swe_x_preferred":[
        "Desa Pameungpeuk"
    ],
    "name:unk_x_variant":[
        "Pamoungpeuk"
    ],
    "name:urd_x_preferred":[
        "Manyaran"
    ],
    "qs:name":"Pameungpeuk",
    "qs:photos_9r":0,
    "qs:photos_sr":0,
    "qs:pop_sr":"0",
    "wd:wordcount":379,
    "wof:lang_x_official":[
        "ind"
    ],
    "wof:lang_x_spoken":[
        "ind",
        "eng"
    ],
    "wof:name":"Pameungpeuk",
    "wof:placetype":"locality",
    "wof:population":0
},
  "geometry": {"coordinates":[107.7332,-7.6413],"type":"Point"}
}