{
  "type": "Feature",
  "properties": {
    "gn:admin1_code":"1",
    "gn:asciiname":"Kedaipante Breuh",
    "gn:country_code":"ID",
    "gn:dem":10,
    "gn:feature_class":"P",
    "gn:feature_code":"PPL",
    "gn:name":"Kedaipante Breuh",
    "gn:population":0,
    "gn:timezone":"Asia/Jakarta",
    "iso:country":"ID",
    "name:ind_x_preferred":[
        "Kedaipante Breuh"
    ],
    "wof:name":"Kedaipante Breuh",
    "wof:placetype":"locality"
},
  "geometry": {"coordinates":[97.4472,5.1303],"type":"Point"}
}