{
  "type": "Feature",
  "properties": {
    "gn:admin1_code":"26",
    "gn:asciiname":"Gunung Menumpak-A",
    "gn:country_code":"ID",
    "gn:dem":358,
    "gn:feature_class":"P",
    "gn:feature_code":"PPL",
    "gn:name":"Gunung Menumpak-A",
    "gn:population":0,
    "gn:timezone":"Asia/Jakarta",
    "iso:country":"ID",
    "name:ind_x_preferred":[
        "Gunung Menumpak-A"
    ],
    "name:und_x_variant":[
        "Gunungmenumpak"
    ],
    "wof:name":"Gunung Menumpak-A",
    "wof:placetype":"locality"
},
  "geometry": {"coordinates":[98.73,3.2392],"type":"Point"}
}