{
  "type": "Feature",
  "properties": {
    "gn:admin1_code":"30.0",
    "gn:asciiname":"Hanyawar",
    "gn:country_code":"ID",
    "gn:dem":913,
    "gn:feature_class":"P",
    "gn:feature_code":"PPL",
    "gn:name":"Hanyawar",
    "gn:population":0,
    "gn:timezone":"Asia/Jakarta",
    "iso:country":"ID",
    "name:ind_x_preferred":[
        "Hanyawar"
    ],
    "wof:name":"Hanyawar",
    "wof:placetype":"locality"
},
  "geometry": {"coordinates":[107.20820000000001,-7.0508],"type":"Point"}
}