{
  "type": "Feature",
  "properties": {
    "gn:admin1_code":"30.0",
    "gn:asciiname":"Gunungbatara",
    "gn:country_code":"ID",
    "gn:dem":454,
    "gn:feature_class":"P",
    "gn:feature_code":"PPLA4",
    "gn:name":"Gunungbatara",
    "gn:population":0,
    "gn:timezone":"Asia/Jakarta",
    "iso:country":"ID",
    "name:ind_x_preferred":[
        "Gunungbatara"
    ],
    "name:und_x_variant":[
        "Koebangbatara"
    ],
    "wof:lang_x_official":[
        "ind"
    ],
    "wof:lang_x_spoken":[
        "ind",
        "eng"
    ],
    "wof:name":"Gunungbatara",
    "wof:placetype":"locality"
},
  "geometry": {"coordinates":[108.1407,-7.3194],"type":"Point"}
}