{
  "type": "Feature",
  "properties": {
    "gn:admin1_code":"10",
    "gn:asciiname":"Karanglo",
    "gn:country_code":"ID",
    "gn:dem":139,
    "gn:feature_class":"P",
    "gn:feature_code":"PPL",
    "gn:name":"Karanglo",
    "gn:population":0,
    "gn:timezone":"Asia/Jakarta",
    "iso:country":"ID",
    "wof:name":"Karanglo",
    "wof:placetype":"locality"
},
  "geometry": {"coordinates":[110.44333,-7.77167],"type":"Point"}
}