{
  "type": "Feature",
  "properties": {
    "gn:admin1_code":"30",
    "gn:asciiname":"Bengle",
    "gn:country_code":"ID",
    "gn:dem":13,
    "gn:feature_class":"P",
    "gn:feature_code":"PPL",
    "gn:name":"Bengle",
    "gn:population":0,
    "gn:timezone":"Asia/Jakarta",
    "iso:country":"ID",
    "name:ind_x_preferred":[
        "Bengle"
    ],
    "name:ind_x_variant":[
        "Tegalbengle"
    ],
    "wof:name":"Bengle",
    "wof:placetype":"locality"
},
  "geometry": {"coordinates":[107.28111,-6.125],"type":"Point"}
}