{
  "type": "Feature",
  "properties": {
    "gn:admin1_code":"30",
    "gn:asciiname":"Kebonkalapa",
    "gn:country_code":"ID",
    "gn:dem":654,
    "gn:feature_class":"P",
    "gn:feature_code":"PPL",
    "gn:name":"Kebonkalapa",
    "gn:population":0,
    "gn:timezone":"Asia/Jakarta",
    "iso:country":"ID",
    "name:ind_x_preferred":[
        "Kebonkalapa"
    ],
    "wof:name":"Kebonkalapa",
    "wof:placetype":"locality"
},
  "geometry": {"coordinates":[107.43889,-6.94111],"type":"Point"}
}