{
  "type": "Feature",
  "properties": {
    "gn:admin1_code":"7",
    "gn:asciiname":"Geri",
    "gn:country_code":"ID",
    "gn:dem":40,
    "gn:feature_class":"P",
    "gn:feature_code":"PPL",
    "gn:name":"Geri",
    "gn:population":0,
    "gn:timezone":"Asia/Jakarta",
    "iso:country":"ID",
    "name:ceb_x_preferred":[
        "Geri"
    ],
    "name:deu_x_preferred":[
        "Geri"
    ],
    "name:fra_x_preferred":[
        "Geri"
    ],
    "name:ind_x_preferred":[
        "Geri"
    ],
    "name:kat_x_preferred":[
        "\u10d2\u10d4\u10e0\u10d8"
    ],
    "name:pol_x_preferred":[
        "Geri"
    ],
    "name:por_x_preferred":[
        "Geri"
    ],
    "name:swe_x_preferred":[
        "Geri"
    ],
    "wof:lang_x_official":[
        "ind"
    ],
    "wof:lang_x_spoken":[
        "ind",
        "eng"
    ],
    "wof:name":"Geri",
    "wof:placetype":"locality"
},
  "geometry": {"coordinates":[110.95639,-7.12528],"type":"Point"}
}