{
  "type": "Feature",
  "properties": {
    "gn:admin1_code":"18.0",
    "gn:asciiname":"Kuwu",
    "gn:country_code":"ID",
    "gn:dem":971,
    "gn:feature_class":"P",
    "gn:feature_code":"PPL",
    "gn:name":"Kuwu",
    "gn:population":0,
    "gn:timezone":"Asia/Makassar",
    "iso:country":"ID",
    "name:ind_x_preferred":[
        "Kuwu"
    ],
    "name:und_x_variant":[
        "Koeowe",
        "Koewoe"
    ],
    "wof:name":"Kuwu",
    "wof:placetype":"locality"
},
  "geometry": {"coordinates":[120.49039999999999,-8.5188],"type":"Point"}
}