{
  "type": "Feature",
  "properties": {
    "gn:admin1_code":"31.0",
    "gn:asciiname":"Polaso",
    "gn:country_code":"ID",
    "gn:dem":8,
    "gn:feature_class":"P",
    "gn:feature_code":"PPL",
    "gn:name":"Polaso",
    "gn:population":0,
    "gn:timezone":"Asia/Makassar",
    "iso:country":"ID",
    "name:ind_x_preferred":[
        "Polaso"
    ],
    "wof:name":"Polaso",
    "wof:placetype":"locality"
},
  "geometry": {"coordinates":[123.1461,0.9097],"type":"Point"}
}