{
  "type": "Feature",
  "properties": {
    "gn:admin1_code":"15.0",
    "gn:asciiname":"Umbulan Tumijajar",
    "gn:country_code":"ID",
    "gn:dem":182,
    "gn:feature_class":"P",
    "gn:feature_code":"PPL",
    "gn:name":"Umbulan Tumijajar",
    "gn:population":0,
    "gn:timezone":"Asia/Jakarta",
    "iso:country":"ID",
    "name:ind_x_preferred":[
        "Umbulan Tumijajar"
    ],
    "name:und_x_variant":[
        "Umbulantumijajar"
    ],
    "wof:lang_x_official":[
        "ind"
    ],
    "wof:lang_x_spoken":[
        "ind",
        "eng"
    ],
    "wof:name":"Umbulan Tumijajar",
    "wof:placetype":"locality"
},
  "geometry": {"coordinates":[104.60263999999999,-4.85318],"type":"Point"}
}