{
  "type": "Feature",
  "properties": {
    "gn:admin1_code":"8",
    "gn:asciiname":"Sarangan",
    "gn:country_code":"ID",
    "gn:dem":104,
    "gn:feature_class":"P",
    "gn:feature_code":"PPL",
    "gn:name":"Sarangan",
    "gn:population":0,
    "gn:timezone":"Asia/Jakarta",
    "iso:country":"ID",
    "name:ind_x_preferred":[
        "Sarangan"
    ],
    "wof:name":"Sarangan",
    "wof:placetype":"locality"
},
  "geometry": {"coordinates":[111.50839999999999,-7.743],"type":"Point"}
}