{
  "type": "Feature",
  "properties": {
    "gn:admin1_code":"26",
    "gn:asciiname":"Bukit Satu",
    "gn:country_code":"ID",
    "gn:dem":964,
    "gn:feature_class":"P",
    "gn:feature_code":"PPL",
    "gn:name":"Bukit Satu",
    "gn:population":0,
    "gn:timezone":"Asia/Jakarta",
    "iso:country":"ID",
    "name:ind_x_preferred":[
        "Bukit Satu"
    ],
    "name:und_x_variant":[
        "Bukit 1"
    ],
    "wof:lang_x_official":[
        "ind"
    ],
    "wof:lang_x_spoken":[
        "ind",
        "eng"
    ],
    "wof:name":"Bukit Satu",
    "wof:placetype":"locality"
},
  "geometry": {"coordinates":[98.33839999999999,2.8555],"type":"Point"}
}