{
  "type": "Feature",
  "properties": {
    "gn:admin1_code":"07",
    "gn:asciiname":"Gondoriyo",
    "gn:country_code":"ID",
    "gn:dem":336,
    "gn:feature_class":"P",
    "gn:feature_code":"PPL",
    "gn:name":"Gondoriyo",
    "gn:population":0,
    "gn:timezone":"Asia/Jakarta",
    "iso:country":"ID",
    "name:ind_x_preferred":[
        "Gondoriyo"
    ],
    "name:und_x_variant":[
        "Gondorio 2",
        "Gondorio Dua"
    ],
    "wof:lang_x_official":[
        "ind"
    ],
    "wof:lang_x_spoken":[
        "ind",
        "eng"
    ],
    "wof:name":"Gondoriyo",
    "wof:placetype":"locality"
},
  "geometry": {"coordinates":[110.47139,-7.16194],"type":"Point"}
}