{
  "type": "Feature",
  "properties": {
    "gn:admin1_code":"17",
    "gn:asciiname":"Lape Atas",
    "gn:country_code":"ID",
    "gn:dem":30,
    "gn:feature_class":"P",
    "gn:feature_code":"PPL",
    "gn:name":"Lape Atas",
    "gn:population":0,
    "gn:timezone":"Asia/Makassar",
    "iso:country":"ID",
    "name:ind_x_preferred":[
        "Lape Atas"
    ],
    "wof:name":"Lape Atas",
    "wof:placetype":"locality"
},
  "geometry": {"coordinates":[117.6099,-8.6326],"type":"Point"}
}