{
  "type": "Feature",
  "properties": {
    "gn:admin1_code":"7.0",
    "gn:asciiname":"Tlaga",
    "gn:country_code":"ID",
    "gn:dem":226,
    "gn:feature_class":"P",
    "gn:feature_code":"PPL",
    "gn:name":"Tlaga",
    "gn:population":0,
    "gn:timezone":"Asia/Jakarta",
    "iso:country":"ID",
    "name:ind_x_preferred":[
        "Tlaga"
    ],
    "wof:name":"Tlaga",
    "wof:placetype":"locality"
},
  "geometry": {"coordinates":[109.49694,-7.34556],"type":"Point"}
}