{
  "type": "Feature",
  "properties": {
    "gn:admin1_code":"33",
    "gn:asciiname":"Paradot",
    "gn:country_code":"ID",
    "gn:dem":23,
    "gn:feature_class":"P",
    "gn:feature_code":"PPL",
    "gn:name":"Paradot",
    "gn:population":0,
    "gn:timezone":"Asia/Jakarta",
    "iso:country":"ID",
    "name:ind_x_preferred":[
        "Paradot"
    ],
    "name:und_x_variant":[
        "Porodot"
    ],
    "wof:name":"Paradot",
    "wof:placetype":"locality"
},
  "geometry": {"coordinates":[106.3663,-6.2727],"type":"Point"}
}