{
  "type": "Feature",
  "properties": {
    "gn:admin1_code":"30",
    "gn:asciiname":"Situmulya",
    "gn:country_code":"ID",
    "gn:dem":699,
    "gn:feature_class":"P",
    "gn:feature_code":"PPL",
    "gn:name":"Situmulya",
    "gn:population":0,
    "gn:timezone":"Asia/Jakarta",
    "iso:country":"ID",
    "wof:name":"Situmulya",
    "wof:placetype":"locality"
},
  "geometry": {"coordinates":[107.52056,-7.00306],"type":"Point"}
}