{
  "type": "Feature",
  "properties": {
    "gn:admin1_code":"8.0",
    "gn:asciiname":"Pagerukir",
    "gn:country_code":"ID",
    "gn:dem":227,
    "gn:feature_class":"P",
    "gn:feature_code":"PPL",
    "gn:name":"Pagerukir",
    "gn:population":0,
    "gn:timezone":"Asia/Jakarta",
    "iso:country":"ID",
    "name:ind_x_preferred":[
        "Pagerukir"
    ],
    "wof:name":"Pagerukir",
    "wof:placetype":"locality"
},
  "geometry": {"coordinates":[111.6318,-8.1259],"type":"Point"}
}