{
  "type": "Feature",
  "properties": {
    "gn:admin1_code":"30.0",
    "gn:asciiname":"Babakan Nyampay",
    "gn:country_code":"ID",
    "gn:dem":609,
    "gn:feature_class":"P",
    "gn:feature_code":"PPLA4",
    "gn:name":"Babakan Nyampay",
    "gn:population":0,
    "gn:timezone":"Asia/Jakarta",
    "iso:country":"ID",
    "name:ind_x_preferred":[
        "Babakan Nyampay"
    ],
    "name:und_x_variant":[
        "Babakan Njampaj"
    ],
    "wof:lang_x_official":[
        "ind"
    ],
    "wof:lang_x_spoken":[
        "ind",
        "eng"
    ],
    "wof:name":"Babakan Nyampay",
    "wof:placetype":"locality"
},
  "geometry": {"coordinates":[108.087,-7.0465],"type":"Point"}
}