{
  "type": "Feature",
  "properties": {
    "gn:admin1_code":"10",
    "gn:asciiname":"Pentuk",
    "gn:country_code":"ID",
    "gn:dem":192,
    "gn:feature_class":"P",
    "gn:feature_code":"PPL",
    "gn:name":"Pentuk",
    "gn:population":0,
    "gn:timezone":"Asia/Jakarta",
    "iso:country":"ID",
    "wof:name":"Pentuk",
    "wof:placetype":"locality"
},
  "geometry": {"coordinates":[110.56556,-7.81],"type":"Point"}
}