{
  "type": "Feature",
  "properties": {
    "gn:admin1_code":"7.0",
    "gn:asciiname":"Bongsri",
    "gn:country_code":"ID",
    "gn:dem":34,
    "gn:feature_class":"P",
    "gn:feature_code":"PPL",
    "gn:name":"Bongsri",
    "gn:population":0,
    "gn:timezone":"Asia/Jakarta",
    "iso:country":"ID",
    "name:ind_x_preferred":[
        "Bongsri"
    ],
    "wof:name":"Bongsri",
    "wof:placetype":"locality"
},
  "geometry": {"coordinates":[111.01949999999999,-6.7285],"type":"Point"}
}