{
  "type": "Feature",
  "properties": {
    "gn:admin1_code":"1.0",
    "gn:asciiname":"Salut",
    "gn:country_code":"ID",
    "gn:dem":10,
    "gn:feature_class":"P",
    "gn:feature_code":"PPL",
    "gn:name":"Salut",
    "gn:population":0,
    "gn:timezone":"Asia/Jakarta",
    "iso:country":"ID",
    "name:aze_x_preferred":[
        "Salut"
    ],
    "name:bul_x_preferred":[
        "\u0421\u0430\u043b\u0443\u0442"
    ],
    "name:fas_x_preferred":[
        "\u0633\u0627\u0644\u0648\u062a"
    ],
    "name:fra_x_preferred":[
        "Salut"
    ],
    "name:hye_x_preferred":[
        "\u054d\u0561\u056c\u0578\u0582\u057f"
    ],
    "name:ind_x_preferred":[
        "Salut"
    ],
    "name:ita_x_preferred":[
        "Salut"
    ],
    "name:kat_x_preferred":[
        "\u10e1\u10d0\u10da\u10e3\u10e2\u10d8"
    ],
    "name:msa_x_preferred":[
        "Salut"
    ],
    "name:spa_x_preferred":[
        "Salut"
    ],
    "name:und_x_variant":[
        "Saloet",
        "Saloel",
        "Salul-ili",
        "Salul",
        "Saluluir"
    ],
    "name:vie_x_preferred":[
        "Salut"
    ],
    "wof:lang_x_official":[
        "ind"
    ],
    "wof:lang_x_spoken":[
        "ind",
        "eng"
    ],
    "wof:name":"Salut",
    "wof:placetype":"locality"
},
  "geometry": {"coordinates":[96.23690000000001,2.4417],"type":"Point"}
}