{
  "type": "Feature",
  "properties": {
    "gn:admin1_code":"1.0",
    "gn:asciiname":"Salut",
    "gn:country_code":"ID",
    "gn:dem":10,
    "gn:feature_class":"P",
    "gn:feature_code":"PPL",
    "gn:name":"Salut",
    "gn:population":0,
    "gn:timezone":"Asia/Jakarta",
    "iso:country":"ID",
    "name:ind_x_preferred":[
        "Salut"
    ],
    "name:und_x_variant":[
        "Saloet",
        "Saloel",
        "Salul-ili",
        "Salul",
        "Saluluir"
    ],
    "wof:name":"Salut",
    "wof:placetype":"locality"
},
  "geometry": {"coordinates":[96.23690000000001,2.4417],"type":"Point"}
}