{
  "type": "Feature",
  "properties": {
    "gn:admin1_code":"7.0",
    "gn:asciiname":"Cimahi",
    "gn:country_code":"ID",
    "gn:dem":247,
    "gn:feature_class":"P",
    "gn:feature_code":"PPLA4",
    "gn:name":"Cimahi",
    "gn:population":0,
    "gn:timezone":"Asia/Jakarta",
    "iso:country":"ID",
    "name:afr_x_preferred":[
        "Cimahi"
    ],
    "name:ara_x_preferred":[
        "\u0634\u064a\u0645\u0627\u0647\u064a"
    ],
    "name:azb_x_preferred":[
        "\u0633\u06cc\u0645\u0627\u0647\u06cc"
    ],
    "name:aze_x_preferred":[
        "Cimahi"
    ],
    "name:ceb_x_preferred":[
        "Kota Cimahi"
    ],
    "name:deu_x_preferred":[
        "Cimahi"
    ],
    "name:fas_x_preferred":[
        "\u0633\u06cc\u0645\u0627\u0647\u06cc"
    ],
    "name:fra_x_preferred":[
        "Cimahi"
    ],
    "name:ind_x_preferred":[
        "Cimahi"
    ],
    "name:ind_x_variant":[
        "Kota Cimahi"
    ],
    "name:ita_x_preferred":[
        "Cimahi"
    ],
    "name:jav_x_preferred":[
        "Kutha Cimahi"
    ],
    "name:jpn_x_preferred":[
        "\u30c1\u30de\u30d2"
    ],
    "name:kat_x_preferred":[
        "\u10e9\u10d8\u10db\u10d0\u10f0\u10d8"
    ],
    "name:kor_x_preferred":[
        "\uce58\ub9c8\ud788"
    ],
    "name:mlg_x_preferred":[
        "Kota Cimahi"
    ],
    "name:msa_x_preferred":[
        "Cimahi"
    ],
    "name:nld_x_preferred":[
        "Cimahi"
    ],
    "name:nor_x_preferred":[
        "Cimahi"
    ],
    "name:pol_x_preferred":[
        "Cimahi"
    ],
    "name:rus_x_preferred":[
        "\u0427\u0438\u043c\u0430\u0445\u0438"
    ],
    "name:sun_x_preferred":[
        "Kota Cimahi"
    ],
    "name:swe_x_preferred":[
        "Cimahi"
    ],
    "name:tam_x_preferred":[
        "\u0b9a\u0bbf\u0bae\u0bbe\u0b95\u0bbf"
    ],
    "name:tur_x_preferred":[
        "Cimahi"
    ],
    "name:ukr_x_preferred":[
        "\u0427\u0456\u043c\u0430\u0445\u0456"
    ],
    "name:urd_x_preferred":[
        "\u0633\u06cc\u0645\u0627\u06c1\u06cc"
    ],
    "name:war_x_preferred":[
        "Cimahi"
    ],
    "name:zho_x_preferred":[
        "\u829d\u99ac\u589f"
    ],
    "wof:name":"Cimahi",
    "wof:placetype":"locality"
},
  "geometry": {"coordinates":[108.586,-7.2026],"type":"Point"}
}