{
  "type": "Feature",
  "properties": {
    "gn:admin1_code":"7.0",
    "gn:asciiname":"Cimahi",
    "gn:country_code":"ID",
    "gn:dem":247,
    "gn:feature_class":"P",
    "gn:feature_code":"PPLA4",
    "gn:name":"Cimahi",
    "gn:population":0,
    "gn:timezone":"Asia/Jakarta",
    "iso:country":"ID",
    "name:ind_x_preferred":[
        "Cimahi"
    ],
    "wof:name":"Cimahi",
    "wof:placetype":"locality"
},
  "geometry": {"coordinates":[108.586,-7.2026],"type":"Point"}
}