{
  "type": "Feature",
  "properties": {
    "gn:admin1_code":"8",
    "gn:asciiname":"Sentul",
    "gn:country_code":"ID",
    "gn:dem":558,
    "gn:feature_class":"P",
    "gn:feature_code":"PPL",
    "gn:name":"Sentul",
    "gn:population":0,
    "gn:timezone":"Asia/Jakarta",
    "iso:country":"ID",
    "name:ceb_x_preferred":[
        "Sentul"
    ],
    "name:ind_x_preferred":[
        "Sentul"
    ],
    "name:nld_x_preferred":[
        "Sentul"
    ],
    "name:swe_x_preferred":[
        "Sentul"
    ],
    "wof:lang_x_official":[
        "ind"
    ],
    "wof:lang_x_spoken":[
        "ind",
        "eng"
    ],
    "wof:name":"Sentul",
    "wof:placetype":"locality"
},
  "geometry": {"coordinates":[111.29139000000001,-7.69167],"type":"Point"}
}