{
  "type": "Feature",
  "properties": {
    "gn:admin1_code":"2.0",
    "gn:asciiname":"Bumiasri",
    "gn:country_code":"ID",
    "gn:dem":16,
    "gn:feature_class":"P",
    "gn:feature_code":"PPL",
    "gn:name":"Bumiasri",
    "gn:population":0,
    "gn:timezone":"Asia/Makassar",
    "iso:country":"ID",
    "name:ind_x_preferred":[
        "Bumiasri"
    ],
    "wof:name":"Bumiasri",
    "wof:placetype":"locality"
},
  "geometry": {"coordinates":[115.2094,-8.6808],"type":"Point"}
}