{
  "type": "Feature",
  "properties": {
    "gn:admin1_code":"30",
    "gn:asciiname":"Ciandam",
    "gn:country_code":"ID",
    "gn:dem":682,
    "gn:feature_class":"P",
    "gn:feature_code":"PPL",
    "gn:name":"Ciandam",
    "gn:population":0,
    "gn:timezone":"Asia/Jakarta",
    "iso:country":"ID",
    "name:ind_x_preferred":[
        "Ciandam"
    ],
    "name:und_x_variant":[
        "Ciandam 2"
    ],
    "wof:name":"Ciandam",
    "wof:placetype":"locality"
},
  "geometry": {"coordinates":[107.12888999999998,-6.77056],"type":"Point"}
}