{
  "type": "Feature",
  "properties": {
    "gn:admin1_code":"7.0",
    "gn:asciiname":"Beningsari",
    "gn:country_code":"ID",
    "gn:dem":175,
    "gn:feature_class":"P",
    "gn:feature_code":"PPL",
    "gn:name":"Beningsari",
    "gn:population":0,
    "gn:timezone":"Asia/Jakarta",
    "iso:country":"ID",
    "wof:name":"Beningsari",
    "wof:placetype":"locality"
},
  "geometry": {"coordinates":[110.96832999999999,-7.59222],"type":"Point"}
}