{
  "type": "Feature",
  "properties": {
    "gn:admin1_code":"26",
    "gn:asciiname":"Marihatbandar Dua",
    "gn:country_code":"ID",
    "gn:dem":76,
    "gn:feature_class":"P",
    "gn:feature_code":"PPL",
    "gn:name":"Marihatbandar Dua",
    "gn:population":0,
    "gn:timezone":"Asia/Jakarta",
    "iso:country":"ID",
    "name:ind_x_preferred":[
        "Marihatbandar Dua"
    ],
    "name:und_x_variant":[
        "Marihatbandar 2"
    ],
    "wof:name":"Marihatbandar Dua",
    "wof:placetype":"locality"
},
  "geometry": {"coordinates":[99.28,3.112],"type":"Point"}
}