{
  "type": "Feature",
  "properties": {
    "gn:admin1_code":"38.0",
    "gn:asciiname":"Allakuang",
    "gn:country_code":"ID",
    "gn:dem":27,
    "gn:feature_class":"P",
    "gn:feature_code":"PPL",
    "gn:name":"Allakuang",
    "gn:population":0,
    "gn:timezone":"Asia/Makassar",
    "iso:country":"ID",
    "name:ind_x_preferred":[
        "Allakuang"
    ],
    "name:und_x_variant":[
        "Alakuang",
        "Alakoeang",
        "Allakuang"
    ],
    "wof:lang_x_official":[
        "ind"
    ],
    "wof:lang_x_spoken":[
        "ind",
        "eng"
    ],
    "wof:name":"Allakuang",
    "wof:placetype":"locality"
},
  "geometry": {"coordinates":[119.7959,-3.9726],"type":"Point"}
}