{
  "type": "Feature",
  "properties": {
    "gn:admin1_code":"30",
    "gn:asciiname":"Sasak",
    "gn:country_code":"ID",
    "gn:dem":678,
    "gn:feature_class":"P",
    "gn:feature_code":"PPL",
    "gn:name":"Sasak",
    "gn:population":0,
    "gn:timezone":"Asia/Jakarta",
    "iso:country":"ID",
    "name:ind_x_preferred":[
        "Sasak"
    ],
    "wof:name":"Sasak",
    "wof:placetype":"locality"
},
  "geometry": {"coordinates":[107.37528,-6.95889],"type":"Point"}
}