{
  "type": "Feature",
  "properties": {
    "gn:admin1_code":"33.0",
    "gn:asciiname":"Simpanggarung",
    "gn:country_code":"ID",
    "gn:dem":273,
    "gn:feature_class":"P",
    "gn:feature_code":"PPLA4",
    "gn:name":"Simpanggarung",
    "gn:population":0,
    "gn:timezone":"Asia/Jakarta",
    "iso:country":"ID",
    "name:ind_x_preferred":[
        "Simpanggarung"
    ],
    "name:und_x_variant":[
        "Garoeng"
    ],
    "wof:lang_x_official":[
        "ind"
    ],
    "wof:lang_x_spoken":[
        "ind",
        "eng"
    ],
    "wof:name":"Simpanggarung",
    "wof:placetype":"locality"
},
  "geometry": {"coordinates":[106.04940000000001,-6.7099],"type":"Point"}
}