{
  "type": "Feature",
  "properties": {
    "gn:admin1_code":"33.0",
    "gn:asciiname":"Obyek",
    "gn:country_code":"ID",
    "gn:dem":132,
    "gn:feature_class":"P",
    "gn:feature_code":"PPL",
    "gn:name":"Obyek",
    "gn:population":0,
    "gn:timezone":"Asia/Jakarta",
    "iso:country":"ID",
    "name:ind_x_preferred":[
        "Obyek"
    ],
    "wof:name":"Obyek",
    "wof:placetype":"locality"
},
  "geometry": {"coordinates":[105.71250000000001,-6.7316],"type":"Point"}
}