{
  "type": "Feature",
  "properties": {
    "gn:admin1_code":"30",
    "gn:asciiname":"Cisupa",
    "gn:country_code":"ID",
    "gn:dem":36,
    "gn:feature_class":"P",
    "gn:feature_code":"PPL",
    "gn:name":"Cisupa",
    "gn:population":0,
    "gn:timezone":"Asia/Jakarta",
    "iso:country":"ID",
    "name:ind_x_preferred":[
        "Cisupa"
    ],
    "wof:name":"Cisupa",
    "wof:placetype":"locality"
},
  "geometry": {"coordinates":[107.39082999999999,-6.445],"type":"Point"}
}