{
  "type": "Feature",
  "properties": {
    "gn:admin1_code":"29.0",
    "gn:asciiname":"Wasile",
    "gn:country_code":"ID",
    "gn:dem":11,
    "gn:feature_class":"P",
    "gn:feature_code":"PPL",
    "gn:name":"Wasile",
    "gn:population":0,
    "gn:timezone":"Asia/Jayapura",
    "iso:country":"ID",
    "name:und_x_variant":[
        "Wajapiakal",
        "Wasile",
        "Waisile"
    ],
    "wof:name":"Wasile",
    "wof:placetype":"locality"
},
  "geometry": {"coordinates":[127.98005000000001,1.06981],"type":"Point"}
}