{
  "type": "Feature",
  "properties": {
    "gn:admin1_code":"30.0",
    "gn:asciiname":"Cibetra",
    "gn:country_code":"ID",
    "gn:dem":295,
    "gn:feature_class":"P",
    "gn:feature_code":"PPL",
    "gn:name":"Cibetra",
    "gn:population":0,
    "gn:timezone":"Asia/Jakarta",
    "iso:country":"ID",
    "name:ind_x_preferred":[
        "Cibetra"
    ],
    "name:und_x_variant":[
        "Tjibetra"
    ],
    "wof:lang_x_official":[
        "ind"
    ],
    "wof:lang_x_spoken":[
        "ind",
        "eng"
    ],
    "wof:name":"Cibetra",
    "wof:placetype":"locality"
},
  "geometry": {"coordinates":[108.2144,-7.5037],"type":"Point"}
}