{
  "type": "Feature",
  "properties": {
    "gn:admin1_code":"1.0",
    "gn:asciiname":"Benteng",
    "gn:country_code":"ID",
    "gn:dem":22,
    "gn:feature_class":"P",
    "gn:feature_code":"PPL",
    "gn:name":"Benteng",
    "gn:population":0,
    "gn:timezone":"Asia/Jakarta",
    "iso:country":"ID",
    "name:ceb_x_preferred":[
        "Benteng"
    ],
    "name:ind_x_preferred":[
        "Benteng"
    ],
    "name:nld_x_preferred":[
        "Benteng"
    ],
    "name:swe_x_preferred":[
        "Benteng"
    ],
    "wof:lang_x_official":[
        "ind"
    ],
    "wof:lang_x_spoken":[
        "ind",
        "eng"
    ],
    "wof:name":"Benteng",
    "wof:placetype":"locality"
},
  "geometry": {"coordinates":[97.6948,4.8848],"type":"Point"}
}