{
  "type": "Feature",
  "properties": {
    "gn:admin1_code":"26.0",
    "gn:asciiname":"Lumban Sinaga Dua",
    "gn:country_code":"ID",
    "gn:dem":932,
    "gn:feature_class":"P",
    "gn:feature_code":"PPL",
    "gn:name":"Lumban Sinaga Dua",
    "gn:population":0,
    "gn:timezone":"Asia/Jakarta",
    "iso:country":"ID",
    "name:ind_x_preferred":[
        "Lumban Sinaga Dua"
    ],
    "name:und_x_variant":[
        "Lumban Sinaga 2"
    ],
    "wof:lang_x_official":[
        "ind"
    ],
    "wof:lang_x_spoken":[
        "ind",
        "eng"
    ],
    "wof:name":"Lumban Sinaga Dua",
    "wof:placetype":"locality"
},
  "geometry": {"coordinates":[98.6742,2.5446],"type":"Point"}
}