{
  "type": "Feature",
  "properties": {
    "gn:admin1_code":"7.0",
    "gn:asciiname":"Benda Wetan",
    "gn:country_code":"ID",
    "gn:dem":34,
    "gn:feature_class":"P",
    "gn:feature_code":"PPL",
    "gn:name":"Benda Wetan",
    "gn:population":0,
    "gn:timezone":"Asia/Jakarta",
    "iso:country":"ID",
    "name:ind_x_preferred":[
        "Benda Wetan"
    ],
    "name:und_x_variant":[
        "Benda"
    ],
    "wof:lang_x_official":[
        "ind"
    ],
    "wof:lang_x_spoken":[
        "ind",
        "eng"
    ],
    "wof:name":"Benda Wetan",
    "wof:placetype":"locality"
},
  "geometry": {"coordinates":[108.788,-7.3203],"type":"Point"}
}