{
  "type": "Feature",
  "properties": {
    "gn:admin1_code":"26",
    "gn:asciiname":"Siringoringo Dua",
    "gn:country_code":"ID",
    "gn:dem":974,
    "gn:feature_class":"P",
    "gn:feature_code":"PPL",
    "gn:name":"Siringoringo Dua",
    "gn:population":0,
    "gn:timezone":"Asia/Jakarta",
    "iso:country":"ID",
    "name:ind_x_preferred":[
        "Siringoringo Dua"
    ],
    "name:und_x_variant":[
        "Siringoringo 2"
    ],
    "wof:name":"Siringoringo Dua",
    "wof:placetype":"locality"
},
  "geometry": {"coordinates":[98.4979,2.3174],"type":"Point"}
}