{
  "type": "Feature",
  "properties": {
    "gn:admin1_code":"14.0",
    "gn:asciiname":"Longbluu",
    "gn:country_code":"ID",
    "gn:dem":185,
    "gn:feature_class":"P",
    "gn:feature_code":"PPL",
    "gn:name":"Longbluu",
    "gn:population":0,
    "gn:timezone":"Asia/Makassar",
    "iso:country":"ID",
    "name:und_x_variant":[
        "Blo\u00e9oe",
        "Long Bluo",
        "Long Bloe\u00f6e",
        "Longbluu",
        "Kampung Lubukbluu"
    ],
    "wof:lang_x_official":[
        "ind"
    ],
    "wof:lang_x_spoken":[
        "ind",
        "eng"
    ],
    "wof:name":"Longbluu",
    "wof:placetype":"locality"
},
  "geometry": {"coordinates":[114.41667,0.73333],"type":"Point"}
}