{
  "type": "Feature",
  "properties": {
    "gn:admin1_code":"30",
    "gn:asciiname":"Lokapraja",
    "gn:country_code":"ID",
    "gn:dem":487,
    "gn:feature_class":"P",
    "gn:feature_code":"PPL",
    "gn:name":"Lokapraja",
    "gn:population":0,
    "gn:timezone":"Asia/Jakarta",
    "iso:country":"ID",
    "name:ind_x_preferred":[
        "Lokapraja"
    ],
    "wof:name":"Lokapraja",
    "wof:placetype":"locality"
},
  "geometry": {"coordinates":[108.37778,-6.81139],"type":"Point"}
}