{
  "type": "Feature",
  "properties": {
    "gn:admin1_code":"17",
    "gn:asciiname":"Songkok",
    "gn:country_code":"ID",
    "gn:dem":132,
    "gn:feature_class":"P",
    "gn:feature_code":"PPL",
    "gn:name":"Songkok",
    "gn:population":0,
    "gn:timezone":"Asia/Makassar",
    "iso:country":"ID",
    "name:aze_x_preferred":[
        "Sonqkok"
    ],
    "name:bjn_x_preferred":[
        "Kupiah"
    ],
    "name:deu_x_preferred":[
        "Songkok"
    ],
    "name:epo_x_preferred":[
        "Songkok"
    ],
    "name:ind_x_preferred":[
        "Songkok"
    ],
    "name:ita_x_preferred":[
        "Peci"
    ],
    "name:jav_x_preferred":[
        "P\u00e8ci"
    ],
    "name:kaz_x_preferred":[
        "\u0421\u043e\u043d\u0433\u043a\u043e\u043a"
    ],
    "name:msa_x_preferred":[
        "Songkok"
    ],
    "name:rus_x_preferred":[
        "\u0421\u043e\u043d\u0433\u043a\u043e\u043a"
    ],
    "name:sun_x_preferred":[
        "Kop\u00e9ah"
    ],
    "name:zho_x_preferred":[
        "\u5b8b\u8c37\u5e3d"
    ],
    "wof:lang_x_official":[
        "ind"
    ],
    "wof:lang_x_spoken":[
        "ind",
        "eng"
    ],
    "wof:name":"Songkok",
    "wof:placetype":"locality"
},
  "geometry": {"coordinates":[116.3502,-8.7566],"type":"Point"}
}