{
  "type": "Feature",
  "properties": {
    "gn:admin1_code":"17",
    "gn:asciiname":"Songkok",
    "gn:country_code":"ID",
    "gn:dem":132,
    "gn:feature_class":"P",
    "gn:feature_code":"PPL",
    "gn:name":"Songkok",
    "gn:population":0,
    "gn:timezone":"Asia/Makassar",
    "iso:country":"ID",
    "name:ind_x_preferred":[
        "Songkok"
    ],
    "wof:name":"Songkok",
    "wof:placetype":"locality"
},
  "geometry": {"coordinates":[116.3502,-8.7566],"type":"Point"}
}