{
  "type": "Feature",
  "properties": {
    "gn:admin1_code":"8.0",
    "gn:asciiname":"Siwalan",
    "gn:country_code":"ID",
    "gn:dem":20,
    "gn:feature_class":"P",
    "gn:feature_code":"PPL",
    "gn:name":"Siwalan",
    "gn:population":0,
    "gn:timezone":"Asia/Jakarta",
    "iso:country":"ID",
    "name:ind_x_preferred":[
        "Siwalan"
    ],
    "wof:name":"Siwalan",
    "wof:placetype":"locality"
},
  "geometry": {"coordinates":[111.91674,-7.14782],"type":"Point"}
}