{
  "type": "Feature",
  "properties": {
    "gn:admin1_code":"30.0",
    "gn:asciiname":"Urug Hilir",
    "gn:country_code":"ID",
    "gn:dem":336,
    "gn:feature_class":"P",
    "gn:feature_code":"PPLA4",
    "gn:name":"Urug Hilir",
    "gn:population":0,
    "gn:timezone":"Asia/Jakarta",
    "iso:country":"ID",
    "name:ind_x_preferred":[
        "Urug Hilir"
    ],
    "wof:name":"Urug Hilir",
    "wof:placetype":"locality"
},
  "geometry": {"coordinates":[108.3639,-7.2363],"type":"Point"}
}