{
  "type": "Feature",
  "properties": {
    "gn:admin1_code":"38.0",
    "gn:asciiname":"Ara",
    "gn:country_code":"ID",
    "gn:dem":341,
    "gn:feature_class":"P",
    "gn:feature_code":"PPL",
    "gn:name":"Ara",
    "gn:population":0,
    "gn:timezone":"Asia/Makassar",
    "iso:country":"ID",
    "name:ind_x_preferred":[
        "Ara"
    ],
    "wof:name":"Ara",
    "wof:placetype":"locality"
},
  "geometry": {"coordinates":[119.6332,-3.5541],"type":"Point"}
}