{
  "type": "Feature",
  "properties": {
    "gn:admin1_code":"38.0",
    "gn:asciiname":"Ara",
    "gn:country_code":"ID",
    "gn:dem":341,
    "gn:feature_class":"P",
    "gn:feature_code":"PPL",
    "gn:name":"Ara",
    "gn:population":0,
    "gn:timezone":"Asia/Makassar",
    "iso:country":"ID",
    "name:bre_x_preferred":[
        "Ara"
    ],
    "name:cat_x_preferred":[
        "Ara"
    ],
    "name:ceb_x_preferred":[
        "Ara"
    ],
    "name:ces_x_preferred":[
        "Ara"
    ],
    "name:deu_x_preferred":[
        "Ara"
    ],
    "name:eus_x_preferred":[
        "Ara"
    ],
    "name:fas_x_preferred":[
        "\u0622\u0631\u0627"
    ],
    "name:fin_x_preferred":[
        "Ara"
    ],
    "name:fra_x_preferred":[
        "Ara"
    ],
    "name:glg_x_preferred":[
        "Ara"
    ],
    "name:ind_x_preferred":[
        "Ara"
    ],
    "name:kaz_x_preferred":[
        "\u0410\u0440\u0430"
    ],
    "name:msa_x_preferred":[
        "Ara"
    ],
    "name:nld_x_preferred":[
        "Ara"
    ],
    "name:nno_x_preferred":[
        "Ara"
    ],
    "name:nor_x_preferred":[
        "Ara"
    ],
    "name:pol_x_preferred":[
        "Ara"
    ],
    "name:por_x_preferred":[
        "Ara"
    ],
    "name:ron_x_preferred":[
        "Ara"
    ],
    "name:rus_x_preferred":[
        "\u0410\u0440\u0430"
    ],
    "name:slk_x_preferred":[
        "Ara"
    ],
    "name:spa_x_preferred":[
        "Ara"
    ],
    "name:swe_x_preferred":[
        "Ara"
    ],
    "name:tur_x_preferred":[
        "Ara"
    ],
    "name:ukr_x_preferred":[
        "\u0410\u0440\u0430"
    ],
    "name:vie_x_preferred":[
        "Ara"
    ],
    "wof:lang_x_official":[
        "ind"
    ],
    "wof:lang_x_spoken":[
        "ind",
        "eng"
    ],
    "wof:name":"Ara",
    "wof:placetype":"locality"
},
  "geometry": {"coordinates":[119.6332,-3.5541],"type":"Point"}
}