{
  "type": "Feature",
  "properties": {
    "gn:admin1_code":"7.0",
    "gn:asciiname":"Sawangan",
    "gn:country_code":"ID",
    "gn:dem":156,
    "gn:feature_class":"P",
    "gn:feature_code":"PPL",
    "gn:name":"Sawangan",
    "gn:population":0,
    "gn:timezone":"Asia/Jakarta",
    "iso:country":"ID",
    "name:bjn_x_preferred":[
        "Sawangan"
    ],
    "name:fas_x_preferred":[
        "\u0633\u0627\u0648\u0646\u06af\u0646"
    ],
    "name:ind_x_preferred":[
        "Sawangan"
    ],
    "name:jav_x_preferred":[
        "Sawangan"
    ],
    "name:mlg_x_preferred":[
        "Sawangan"
    ],
    "name:sun_x_preferred":[
        "Sawangan"
    ],
    "wof:lang_x_official":[
        "ind"
    ],
    "wof:lang_x_spoken":[
        "ind",
        "eng"
    ],
    "wof:name":"Sawangan",
    "wof:placetype":"locality"
},
  "geometry": {"coordinates":[109.4425,-7.58389],"type":"Point"}
}