{
  "type": "Feature",
  "properties": {
    "gn:admin1_code":"37.0",
    "gn:asciiname":"Kualalala",
    "gn:country_code":"ID",
    "gn:dem":22,
    "gn:feature_class":"P",
    "gn:feature_code":"PPL",
    "gn:name":"Kualalala",
    "gn:population":0,
    "gn:timezone":"Asia/Jakarta",
    "iso:country":"ID",
    "name:ind_x_preferred":[
        "Kualalala"
    ],
    "wof:name":"Kualalala",
    "wof:placetype":"locality"
},
  "geometry": {"coordinates":[102.24424,-0.40033],"type":"Point"}
}