{
  "type": "Feature",
  "properties": {
    "gn:admin1_code":"18.0",
    "gn:asciiname":"Balauring Utara",
    "gn:country_code":"ID",
    "gn:dem":39,
    "gn:feature_class":"P",
    "gn:feature_code":"PPL",
    "gn:name":"Balauring Utara",
    "gn:population":0,
    "gn:timezone":"Asia/Makassar",
    "iso:country":"ID",
    "name:ind_x_preferred":[
        "Balauring Utara"
    ],
    "wof:name":"Balauring Utara",
    "wof:placetype":"locality"
},
  "geometry": {"coordinates":[123.7068,-8.2329],"type":"Point"}
}