{
  "type": "Feature",
  "properties": {
    "gn:admin1_code":"8.0",
    "gn:asciiname":"Renteng",
    "gn:country_code":"ID",
    "gn:dem":445,
    "gn:feature_class":"P",
    "gn:feature_code":"PPL",
    "gn:name":"Renteng",
    "gn:population":0,
    "gn:timezone":"Asia/Jakarta",
    "iso:country":"ID",
    "name:ind_x_preferred":[
        "Renteng"
    ],
    "wof:name":"Renteng",
    "wof:placetype":"locality"
},
  "geometry": {"coordinates":[113.47280000000001,-7.87118],"type":"Point"}
}