{
  "type": "Feature",
  "properties": {
    "gn:admin1_code":"08",
    "gn:asciiname":"Majang Tengah",
    "gn:country_code":"ID",
    "gn:dem":392,
    "gn:feature_class":"P",
    "gn:feature_code":"PPLA4",
    "gn:name":"Majang Tengah",
    "gn:population":0,
    "gn:timezone":"Asia/Jakarta",
    "iso:country":"ID",
    "name:ind_x_preferred":[
        "Majang Tengah"
    ],
    "name:und_x_variant":[
        "Madjangtengah 1",
        "Majangtengah Satu"
    ],
    "wof:name":"Majang Tengah",
    "wof:placetype":"locality"
},
  "geometry": {"coordinates":[112.72057,-8.19706],"type":"Point"}
}