{
  "type": "Feature",
  "properties": {
    "gn:admin1_code":"18.0",
    "gn:asciiname":"Lakafeng",
    "gn:country_code":"ID",
    "gn:dem":951,
    "gn:feature_class":"P",
    "gn:feature_code":"PPL",
    "gn:name":"Lakafeng",
    "gn:population":0,
    "gn:timezone":"Asia/Makassar",
    "iso:country":"ID",
    "name:ind_x_preferred":[
        "Lakafeng"
    ],
    "wof:name":"Lakafeng",
    "wof:placetype":"locality"
},
  "geometry": {"coordinates":[124.6109,-8.346],"type":"Point"}
}