{
  "type": "Feature",
  "properties": {
    "gn:admin1_code":"30.0",
    "gn:asciiname":"Tegalsari",
    "gn:country_code":"ID",
    "gn:dem":28,
    "gn:feature_class":"P",
    "gn:feature_code":"PPL",
    "gn:name":"Tegalsari",
    "gn:population":0,
    "gn:timezone":"Asia/Jakarta",
    "iso:country":"ID",
    "name:ind_x_preferred":[
        "Tegalsari"
    ],
    "wof:name":"Tegalsari",
    "wof:placetype":"locality"
},
  "geometry": {"coordinates":[108.64100000000001,-7.5023],"type":"Point"}
}