{
  "type": "Feature",
  "properties": {
    "gn:admin1_code":"18.0",
    "gn:asciiname":"Demudede",
    "gn:country_code":"ID",
    "gn:dem":347,
    "gn:feature_class":"P",
    "gn:feature_code":"PPL",
    "gn:name":"Demudede",
    "gn:population":0,
    "gn:timezone":"Asia/Makassar",
    "iso:country":"ID",
    "name:ind_x_preferred":[
        "Demudede"
    ],
    "wof:name":"Demudede",
    "wof:placetype":"locality"
},
  "geometry": {"coordinates":[119.3073,-9.6214],"type":"Point"}
}