{
  "type": "Feature",
  "properties": {
    "gn:admin1_code":"30.0",
    "gn:asciiname":"Ganassabrang",
    "gn:country_code":"ID",
    "gn:dem":537,
    "gn:feature_class":"P",
    "gn:feature_code":"PPL",
    "gn:name":"Ganassabrang",
    "gn:population":0,
    "gn:timezone":"Asia/Jakarta",
    "iso:country":"ID",
    "name:ind_x_preferred":[
        "Ganassabrang"
    ],
    "name:und_x_variant":[
        "Ganasabrang"
    ],
    "wof:name":"Ganassabrang",
    "wof:placetype":"locality"
},
  "geometry": {"coordinates":[108.029,-7.5507],"type":"Point"}
}