{
  "type": "Feature",
  "properties": {
    "gn:admin1_code":"8.0",
    "gn:asciiname":"Kemisan Satu",
    "gn:country_code":"ID",
    "gn:dem":192,
    "gn:feature_class":"P",
    "gn:feature_code":"PPL",
    "gn:name":"Kemisan Satu",
    "gn:population":0,
    "gn:timezone":"Asia/Jakarta",
    "iso:country":"ID",
    "name:ind_x_preferred":[
        "Kemisan Satu"
    ],
    "wof:name":"Kemisan Satu",
    "wof:placetype":"locality"
},
  "geometry": {"coordinates":[113.34099999999999,-7.8869],"type":"Point"}
}