{
  "type": "Feature",
  "properties": {
    "gn:admin1_code":"38",
    "gn:asciiname":"Pagagingan",
    "gn:country_code":"ID",
    "gn:dem":837,
    "gn:feature_class":"P",
    "gn:feature_code":"PPL",
    "gn:name":"Pagagingan",
    "gn:population":0,
    "gn:timezone":"Asia/Makassar",
    "iso:country":"ID",
    "name:ind_x_preferred":[
        "Pagagingan"
    ],
    "wof:name":"Pagagingan",
    "wof:placetype":"locality"
},
  "geometry": {"coordinates":[119.88079999999999,-3.0538],"type":"Point"}
}