{
  "type": "Feature",
  "properties": {
    "gn:admin1_code":"0.0",
    "gn:asciiname":"Nangaseke",
    "gn:cc2":"ID",
    "gn:country_code":"ID",
    "gn:dem":170,
    "gn:feature_class":"P",
    "gn:feature_code":"PPL",
    "gn:name":"Nangaseke",
    "gn:population":0,
    "gn:timezone":"Asia/Pontianak",
    "iso:country":"ID",
    "name:und_x_variant":[
        "Nangah Seke",
        "Nangaseke"
    ],
    "wof:lang_x_official":[
        "ind"
    ],
    "wof:lang_x_spoken":[
        "ind",
        "eng"
    ],
    "wof:name":"Nangaseke",
    "wof:placetype":"locality"
},
  "geometry": {"coordinates":[112.76667,-0.06667],"type":"Point"}
}