{
  "type": "Feature",
  "properties": {
    "gn:admin1_code":"8",
    "gn:asciiname":"Gumuktopi",
    "gn:country_code":"ID",
    "gn:dem":17,
    "gn:feature_class":"P",
    "gn:feature_code":"PPL",
    "gn:name":"Gumuktopi",
    "gn:population":0,
    "gn:timezone":"Asia/Jakarta",
    "iso:country":"ID",
    "name:ind_x_preferred":[
        "Gumuktopi"
    ],
    "wof:name":"Gumuktopi",
    "wof:placetype":"locality"
},
  "geometry": {"coordinates":[113.3635,-8.2467],"type":"Point"}
}