{
  "type": "Feature",
  "properties": {
    "gn:admin1_code":"08",
    "gn:asciiname":"Urek-urek",
    "gn:country_code":"ID",
    "gn:dem":401,
    "gn:feature_class":"P",
    "gn:feature_code":"PPLA4",
    "gn:name":"Urek-urek",
    "gn:population":0,
    "gn:timezone":"Asia/Jakarta",
    "iso:country":"ID",
    "wof:name":"Urek-urek",
    "wof:placetype":"locality"
},
  "geometry": {"coordinates":[112.66409,-8.14151],"type":"Point"}
}