{
  "type": "Feature",
  "properties": {
    "gn:admin1_code":"26",
    "gn:asciiname":"Pondok Empat Belas",
    "gn:country_code":"ID",
    "gn:dem":19,
    "gn:feature_class":"P",
    "gn:feature_code":"PPL",
    "gn:name":"Pondok Empat Belas",
    "gn:population":0,
    "gn:timezone":"Asia/Jakarta",
    "iso:country":"ID",
    "name:ind_x_preferred":[
        "Pondok Empat Belas"
    ],
    "name:und_x_variant":[
        "Pondok 14"
    ],
    "wof:name":"Pondok Empat Belas",
    "wof:placetype":"locality"
},
  "geometry": {"coordinates":[98.28230000000001,3.8043],"type":"Point"}
}