{
  "type": "Feature",
  "properties": {
    "gn:admin1_code":"33.0",
    "gn:asciiname":"Gunungtangeran",
    "gn:country_code":"ID",
    "gn:dem":456,
    "gn:feature_class":"P",
    "gn:feature_code":"PPL",
    "gn:name":"Gunungtangeran",
    "gn:population":0,
    "gn:timezone":"Asia/Jakarta",
    "iso:country":"ID",
    "name:ind_x_preferred":[
        "Gunungtangeran"
    ],
    "wof:name":"Gunungtangeran",
    "wof:placetype":"locality"
},
  "geometry": {"coordinates":[105.99420000000001,-6.3587],"type":"Point"}
}