{
  "type": "Feature",
  "properties": {
    "gn:admin1_code":"07",
    "gn:asciiname":"Malang",
    "gn:country_code":"ID",
    "gn:dem":1458,
    "gn:feature_class":"P",
    "gn:feature_code":"PPL",
    "gn:name":"Malang",
    "gn:population":0,
    "gn:timezone":"Asia/Jakarta",
    "iso:country":"ID",
    "wof:name":"Malang",
    "wof:placetype":"locality"
},
  "geometry": {"coordinates":[110.41443999999998,-7.48361],"type":"Point"}
}