{
  "type": "Feature",
  "properties": {
    "gn:admin1_code":"8",
    "gn:asciiname":"Semboropasar",
    "gn:country_code":"ID",
    "gn:dem":28,
    "gn:feature_class":"P",
    "gn:feature_code":"PPLA4",
    "gn:name":"Semboropasar",
    "gn:population":0,
    "gn:timezone":"Asia/Jakarta",
    "iso:country":"ID",
    "name:ind_x_preferred":[
        "Semboropasar"
    ],
    "wof:name":"Semboropasar",
    "wof:placetype":"locality"
},
  "geometry": {"coordinates":[113.44508,-8.21054],"type":"Point"}
}