{
  "type": "Feature",
  "properties": {
    "gn:admin1_code":"7.0",
    "gn:asciiname":"Cungging",
    "gn:country_code":"ID",
    "gn:dem":576,
    "gn:feature_class":"P",
    "gn:feature_code":"PPL",
    "gn:name":"Cungging",
    "gn:population":0,
    "gn:timezone":"Asia/Jakarta",
    "iso:country":"ID",
    "name:ind_x_preferred":[
        "Cungging"
    ],
    "name:und_x_variant":[
        "Tjoengging"
    ],
    "wof:lang_x_official":[
        "ind"
    ],
    "wof:lang_x_spoken":[
        "ind",
        "eng"
    ],
    "wof:name":"Cungging",
    "wof:placetype":"locality"
},
  "geometry": {"coordinates":[108.7573,-7.1571],"type":"Point"}
}