{
  "type": "Feature",
  "properties": {
    "gn:admin1_code":"30",
    "gn:asciiname":"Cijawura Hilir",
    "gn:country_code":"ID",
    "gn:dem":671,
    "gn:feature_class":"P",
    "gn:feature_code":"PPL",
    "gn:name":"Cijawura Hilir",
    "gn:population":0,
    "gn:timezone":"Asia/Jakarta",
    "iso:country":"ID",
    "name:ind_x_preferred":[
        "Cijawura Hilir"
    ],
    "name:und_x_variant":[
        "Tjidjawura 2",
        "Cijawura Dua"
    ],
    "wof:lang_x_official":[
        "ind"
    ],
    "wof:lang_x_spoken":[
        "ind",
        "eng"
    ],
    "wof:name":"Cijawura Hilir",
    "wof:placetype":"locality"
},
  "geometry": {"coordinates":[107.65806000000001,-6.96278],"type":"Point"}
}