{
  "type": "Feature",
  "properties": {
    "gn:gn_country":"ID",
    "gn:gn_fcode":"PPL",
    "gn:gn_pop":0,
    "iso:country":"ID",
    "name:deu_x_preferred":[
        "Watansoppeng"
    ],
    "name:eng_x_preferred":[
        "Watansoppeng"
    ],
    "name:fra_x_preferred":[
        "Watansoppeng"
    ],
    "name:ind_x_preferred":[
        "Watansoppeng"
    ],
    "name:jpn_x_preferred":[
        "\u30ef\u30bf\u30f3\u30bd\u30d7\u30f3"
    ],
    "name:nld_x_preferred":[
        "Watansoppeng"
    ],
    "name:unk_x_variant":[
        "Watan Sopeng"
    ],
    "name:zho_x_preferred":[
        "\u675c\u9081"
    ],
    "name:zho_x_variant":[
        "\u74e6\u5766\u7d22\u5f6d"
    ],
    "qs_pg:aaroncc":"ID",
    "qs_pg:gn_country":"ID",
    "qs_pg:gn_fcode":"PPL",
    "qs_pg:gn_pop":0,
    "qs_pg:name":"Watansopeng",
    "qs_pg:name_adm0":"Indonesia",
    "qs_pg:name_adm1":"Sulawesi Selatan",
    "qs_pg:photos_9k":1,
    "qs_pg:photos_9r":1,
    "qs_pg:photos_all":8,
    "qs_pg:photos_sr":0,
    "qs_pg:pop_sr":0,
    "qs_pg:qs_pg_placetype":"locality",
    "qs_pg:qs_pg_placetype_gp":"Town",
    "qs_pg:woe_adm0":23424846,
    "woe:adm0_id":23424846,
    "woe:name_adm0":"Indonesia",
    "woe:name_adm1":"Sulawesi Selatan",
    "woe:placetype":"Town",
    "wof:lang_x_official":[
        "ind"
    ],
    "wof:lang_x_spoken":[
        "ind",
        "eng"
    ],
    "wof:name":"Watansopeng",
    "wof:placetype":"locality"
},
  "geometry": {"coordinates":[119.8841,-4.3522],"type":"Point"}
}