{
  "type": "Feature",
  "properties": {
    "gn:admin1_code":"8.0",
    "gn:asciiname":"Sugihwaras",
    "gn:country_code":"ID",
    "gn:dem":36,
    "gn:feature_class":"P",
    "gn:feature_code":"PPL",
    "gn:name":"Sugihwaras",
    "gn:population":0,
    "gn:timezone":"Asia/Jakarta",
    "iso:country":"ID",
    "name:ind_x_preferred":[
        "Sugihwaras"
    ],
    "wof:name":"Sugihwaras",
    "wof:placetype":"locality"
},
  "geometry": {"coordinates":[111.99048000000001,-7.24013],"type":"Point"}
}