{
  "type": "Feature",
  "properties": {
    "gn:admin1_code":"18.0",
    "gn:asciiname":"Wadului",
    "gn:country_code":"ID",
    "gn:dem":190,
    "gn:feature_class":"P",
    "gn:feature_code":"PPL",
    "gn:name":"Wadului",
    "gn:population":0,
    "gn:timezone":"Asia/Makassar",
    "iso:country":"ID",
    "name:ind_x_preferred":[
        "Wadului"
    ],
    "wof:name":"Wadului",
    "wof:placetype":"locality"
},
  "geometry": {"coordinates":[121.8954,-10.5332],"type":"Point"}
}