{
  "type": "Feature",
  "properties": {
    "gn:admin1_code":"7",
    "gn:asciiname":"Sirukun",
    "gn:country_code":"ID",
    "gn:dem":222,
    "gn:feature_class":"P",
    "gn:feature_code":"PPL",
    "gn:name":"Sirukun",
    "gn:population":0,
    "gn:timezone":"Asia/Jakarta",
    "iso:country":"ID",
    "name:ind_x_preferred":[
        "Sirukun"
    ],
    "wof:name":"Sirukun",
    "wof:placetype":"locality"
},
  "geometry": {"coordinates":[109.6409,-7.0729],"type":"Point"}
}