{
  "type": "Feature",
  "properties": {
    "gn:admin1_code":"1.0",
    "gn:asciiname":"Rangkeuem",
    "gn:country_code":"ID",
    "gn:dem":19,
    "gn:feature_class":"P",
    "gn:feature_code":"PPL",
    "gn:name":"Rangkeuem",
    "gn:population":0,
    "gn:timezone":"Asia/Jakarta",
    "iso:country":"ID",
    "name:ind_x_preferred":[
        "Rangkeuem"
    ],
    "wof:name":"Rangkeuem",
    "wof:placetype":"locality"
},
  "geometry": {"coordinates":[95.8797,5.4159],"type":"Point"}
}