{
  "type": "Feature",
  "properties": {
    "gn:admin1_code":"33",
    "gn:asciiname":"Pasirpeundeuy",
    "gn:country_code":"ID",
    "gn:dem":24,
    "gn:feature_class":"P",
    "gn:feature_code":"PPL",
    "gn:name":"Pasirpeundeuy",
    "gn:population":0,
    "gn:timezone":"Asia/Jakarta",
    "iso:country":"ID",
    "name:ind_x_preferred":[
        "Pasirpeundeuy"
    ],
    "name:und_x_variant":[
        "Pasirpeundeur"
    ],
    "wof:lang_x_official":[
        "ind"
    ],
    "wof:lang_x_spoken":[
        "ind",
        "eng"
    ],
    "wof:name":"Pasirpeundeuy",
    "wof:placetype":"locality"
},
  "geometry": {"coordinates":[106.27979999999999,-6.2865],"type":"Point"}
}