{
  "type": "Feature",
  "properties": {
    "gn:admin1_code":"1.0",
    "gn:asciiname":"Lining",
    "gn:cc2":"ID",
    "gn:country_code":"ID",
    "gn:dem":707,
    "gn:feature_class":"P",
    "gn:feature_code":"PPL",
    "gn:name":"Lining",
    "gn:population":0,
    "gn:timezone":"Asia/Jakarta",
    "iso:country":"ID",
    "name:deu_x_preferred":[
        "Lining"
    ],
    "name:ind_x_preferred":[
        "Lining"
    ],
    "name:und_x_variant":[
        "Lenang"
    ],
    "wof:lang_x_official":[
        "ind"
    ],
    "wof:lang_x_spoken":[
        "ind",
        "eng"
    ],
    "wof:name":"Lining",
    "wof:placetype":"locality"
},
  "geometry": {"coordinates":[97.00722,4.45389],"type":"Point"}
}