{
  "type": "Feature",
  "properties": {
    "gn:admin1_code":"28.0",
    "gn:asciiname":"Laninoiha",
    "gn:country_code":"ID",
    "gn:dem":42,
    "gn:feature_class":"P",
    "gn:feature_code":"PPL",
    "gn:name":"Laninoiha",
    "gn:population":0,
    "gn:timezone":"Asia/Jayapura",
    "iso:country":"ID",
    "name:ind_x_preferred":[
        "Laninoiha"
    ],
    "wof:name":"Laninoiha",
    "wof:placetype":"locality"
},
  "geometry": {"coordinates":[131.93625,-7.03722],"type":"Point"}
}