{
  "type": "Feature",
  "properties": {
    "gn:admin1_code":"7",
    "gn:asciiname":"Wedeg",
    "gn:country_code":"ID",
    "gn:dem":86,
    "gn:feature_class":"P",
    "gn:feature_code":"PPL",
    "gn:name":"Wedeg",
    "gn:population":0,
    "gn:timezone":"Asia/Jakarta",
    "iso:country":"ID",
    "name:ind_x_preferred":[
        "Wedeg"
    ],
    "wof:name":"Wedeg",
    "wof:placetype":"locality"
},
  "geometry": {"coordinates":[111.34690000000001,-7.0596],"type":"Point"}
}