{
  "type": "Feature",
  "properties": {
    "gn:admin1_code":"26",
    "gn:asciiname":"Sihobuk",
    "gn:country_code":"ID",
    "gn:dem":475,
    "gn:feature_class":"P",
    "gn:feature_code":"PPL",
    "gn:name":"Sihobuk",
    "gn:population":0,
    "gn:timezone":"Asia/Jakarta",
    "iso:country":"ID",
    "name:ind_x_preferred":[
        "Sihobuk"
    ],
    "wof:name":"Sihobuk",
    "wof:placetype":"locality"
},
  "geometry": {"coordinates":[99.09605000000001,1.79594],"type":"Point"}
}