{
  "type": "Feature",
  "properties": {
    "gn:admin1_code":"26",
    "gn:asciiname":"Cebahen",
    "gn:country_code":"ID",
    "gn:dem":1117,
    "gn:feature_class":"P",
    "gn:feature_code":"PPL",
    "gn:name":"Cebahen",
    "gn:population":0,
    "gn:timezone":"Asia/Jakarta",
    "iso:country":"ID",
    "name:ind_x_preferred":[
        "Cebahen"
    ],
    "name:und_x_variant":[
        "Tjebahen"
    ],
    "wof:lang_x_official":[
        "ind"
    ],
    "wof:lang_x_spoken":[
        "ind",
        "eng"
    ],
    "wof:name":"Cebahen",
    "wof:placetype":"locality"
},
  "geometry": {"coordinates":[98.33329999999999,3.1829],"type":"Point"}
}