{
  "type": "Feature",
  "properties": {
    "gn:admin1_code":"8",
    "gn:asciiname":"Rancak",
    "gn:country_code":"ID",
    "gn:dem":42,
    "gn:feature_class":"P",
    "gn:feature_code":"PPL",
    "gn:name":"Rancak",
    "gn:population":0,
    "gn:timezone":"Asia/Jakarta",
    "iso:country":"ID",
    "name:ind_x_preferred":[
        "Rancak"
    ],
    "wof:name":"Rancak",
    "wof:placetype":"locality"
},
  "geometry": {"coordinates":[112.81140000000001,-7.6659],"type":"Point"}
}