{
  "type": "Feature",
  "properties": {
    "gn:admin1_code":"7",
    "gn:asciiname":"Peniron Wetan",
    "gn:country_code":"ID",
    "gn:dem":174,
    "gn:feature_class":"P",
    "gn:feature_code":"PPL",
    "gn:name":"Peniron Wetan",
    "gn:population":0,
    "gn:timezone":"Asia/Jakarta",
    "iso:country":"ID",
    "name:ind_x_preferred":[
        "Peniron Wetan"
    ],
    "wof:name":"Peniron Wetan",
    "wof:placetype":"locality"
},
  "geometry": {"coordinates":[109.92333000000001,-7.60694],"type":"Point"}
}