{
  "type": "Feature",
  "properties": {
    "gn:admin1_code":"31",
    "gn:asciiname":"Tuutu",
    "gn:country_code":"ID",
    "gn:dem":697,
    "gn:feature_class":"P",
    "gn:feature_code":"PPL",
    "gn:name":"Tuutu",
    "gn:population":0,
    "gn:timezone":"Asia/Makassar",
    "iso:country":"ID",
    "name:ind_x_preferred":[
        "Tuutu"
    ],
    "wof:name":"Tuutu",
    "wof:placetype":"locality"
},
  "geometry": {"coordinates":[124.9046,1.2984],"type":"Point"}
}