{
  "type": "Feature",
  "properties": {
    "gn:admin1_code":"30.0",
    "gn:asciiname":"Lebakjero",
    "gn:country_code":"ID",
    "gn:dem":374,
    "gn:feature_class":"P",
    "gn:feature_code":"PPL",
    "gn:name":"Lebakjero",
    "gn:population":0,
    "gn:timezone":"Asia/Jakarta",
    "iso:country":"ID",
    "name:ind_x_preferred":[
        "Lebakjero"
    ],
    "name:und_x_variant":[
        "Lebakdjero"
    ],
    "wof:name":"Lebakjero",
    "wof:placetype":"locality"
},
  "geometry": {"coordinates":[108.4854,-7.564],"type":"Point"}
}