{
  "type": "Feature",
  "properties": {
    "gn:admin1_code":"30.0",
    "gn:asciiname":"Bubuay",
    "gn:country_code":"ID",
    "gn:dem":373,
    "gn:feature_class":"P",
    "gn:feature_code":"PPL",
    "gn:name":"Bubuay",
    "gn:population":0,
    "gn:timezone":"Asia/Jakarta",
    "iso:country":"ID",
    "name:ind_x_preferred":[
        "Bubuay"
    ],
    "name:und_x_variant":[
        "Boeboewaj 2"
    ],
    "wof:lang_x_official":[
        "ind"
    ],
    "wof:lang_x_spoken":[
        "ind",
        "eng"
    ],
    "wof:name":"Bubuay",
    "wof:placetype":"locality"
},
  "geometry": {"coordinates":[108.069,-7.5446],"type":"Point"}
}