{
  "type": "Feature",
  "properties": {
    "gn:admin1_code":"33.0",
    "gn:asciiname":"Babakankubang",
    "gn:country_code":"ID",
    "gn:dem":242,
    "gn:feature_class":"P",
    "gn:feature_code":"PPL",
    "gn:name":"Babakankubang",
    "gn:population":0,
    "gn:timezone":"Asia/Jakarta",
    "iso:country":"ID",
    "name:ind_x_preferred":[
        "Babakankubang"
    ],
    "wof:name":"Babakankubang",
    "wof:placetype":"locality"
},
  "geometry": {"coordinates":[106.0397,-6.6925],"type":"Point"}
}