{
  "type": "Feature",
  "properties": {
    "gn:admin1_code":"30.0",
    "gn:asciiname":"Neglasari",
    "gn:country_code":"ID",
    "gn:dem":82,
    "gn:feature_class":"P",
    "gn:feature_code":"PPL",
    "gn:name":"Neglasari",
    "gn:population":0,
    "gn:timezone":"Asia/Jakarta",
    "iso:country":"ID",
    "name:ind_x_preferred":[
        "Neglasari"
    ],
    "wof:name":"Neglasari",
    "wof:placetype":"locality"
},
  "geometry": {"coordinates":[108.2056,-7.7539],"type":"Point"}
}