{
  "type": "Feature",
  "properties": {
    "gn:admin1_code":"15.0",
    "gn:asciiname":"Geremlebo Dua",
    "gn:country_code":"ID",
    "gn:dem":88,
    "gn:feature_class":"P",
    "gn:feature_code":"PPL",
    "gn:name":"Geremlebo Dua",
    "gn:population":0,
    "gn:timezone":"Asia/Jakarta",
    "iso:country":"ID",
    "name:ind_x_preferred":[
        "Geremlebo Dua"
    ],
    "name:und_x_variant":[
        "Geremlebo 2"
    ],
    "wof:lang_x_official":[
        "ind"
    ],
    "wof:lang_x_spoken":[
        "ind",
        "eng"
    ],
    "wof:name":"Geremlebo Dua",
    "wof:placetype":"locality"
},
  "geometry": {"coordinates":[105.56807000000001,-5.19558],"type":"Point"}
}