{
  "type": "Feature",
  "properties": {
    "gn:admin1_code":"30",
    "gn:asciiname":"Ciluwuk Kulon",
    "gn:cc2":"ID",
    "gn:country_code":"ID",
    "gn:dem":110,
    "gn:feature_class":"P",
    "gn:feature_code":"PPL",
    "gn:name":"Ciluwuk Kulon",
    "gn:population":0,
    "gn:timezone":"Asia/Jakarta",
    "iso:country":"ID",
    "name:und_x_variant":[
        "Tjilukuk",
        "Cilukuk",
        "Ciluwuk Kulon"
    ],
    "wof:lang_x_official":[
        "ind"
    ],
    "wof:lang_x_spoken":[
        "ind",
        "eng"
    ],
    "wof:name":"Ciluwuk Kulon",
    "wof:placetype":"locality"
},
  "geometry": {"coordinates":[106.32722,-6.43361],"type":"Point"}
}