{
  "type": "Feature",
  "properties": {
    "gn:admin1_code":"8.0",
    "gn:asciiname":"Gundik",
    "gn:country_code":"ID",
    "gn:dem":6,
    "gn:feature_class":"P",
    "gn:feature_code":"PPL",
    "gn:name":"Gundik",
    "gn:population":0,
    "gn:timezone":"Asia/Jakarta",
    "iso:country":"ID",
    "name:ind_x_preferred":[
        "Gundik"
    ],
    "wof:name":"Gundik",
    "wof:placetype":"locality"
},
  "geometry": {"coordinates":[112.42019999999999,-7.0417],"type":"Point"}
}