{
  "type": "Feature",
  "properties": {
    "gn:admin1_code":"30.0",
    "gn:asciiname":"Sodongrigen",
    "gn:country_code":"ID",
    "gn:dem":595,
    "gn:feature_class":"P",
    "gn:feature_code":"PPL",
    "gn:name":"Sodongrigen",
    "gn:population":0,
    "gn:timezone":"Asia/Jakarta",
    "iso:country":"ID",
    "name:ind_x_preferred":[
        "Sodongrigen"
    ],
    "wof:name":"Sodongrigen",
    "wof:placetype":"locality"
},
  "geometry": {"coordinates":[107.5176,-7.3283],"type":"Point"}
}