{
  "type": "Feature",
  "properties": {
    "gn:country":"ID",
    "gn:fcode":"PPLX",
    "gn:pop":0,
    "iso:country":"ID",
    "qs:name":"Tangerangscheweg",
    "qs:name_adm0":"Indonesia",
    "qs:name_adm1":"Jakarta Raya",
    "qs:photos":34,
    "qs:photos_1k":7,
    "qs:photos_9k":1,
    "qs:photos_9r":2,
    "qs:photos_all":34,
    "qs:photos_sr":2,
    "qs:placetype":"Suburb",
    "qs:pop_sr":"0",
    "wof:name":"Tangerangscheweg",
    "wof:placetype":"neighbourhood",
    "wof:population":0
},
  "geometry": {"coordinates":[106.80333,-6.16333],"type":"Point"}
}