{
  "type": "Feature",
  "properties": {
    "gn:admin1_code":"33",
    "gn:asciiname":"Telukbako",
    "gn:country_code":"ID",
    "gn:dem":8,
    "gn:feature_class":"P",
    "gn:feature_code":"PPL",
    "gn:name":"Telukbako",
    "gn:population":0,
    "gn:timezone":"Asia/Jakarta",
    "iso:country":"ID",
    "name:ind_x_preferred":[
        "Telukbako"
    ],
    "wof:name":"Telukbako",
    "wof:placetype":"locality"
},
  "geometry": {"coordinates":[106.0823,-5.9878],"type":"Point"}
}