{
  "type": "Feature",
  "properties": {
    "gn:admin1_code":"7.0",
    "gn:asciiname":"Mlandangan",
    "gn:country_code":"ID",
    "gn:dem":301,
    "gn:feature_class":"P",
    "gn:feature_code":"PPL",
    "gn:name":"Mlandangan",
    "gn:population":0,
    "gn:timezone":"Asia/Jakarta",
    "iso:country":"ID",
    "wof:name":"Mlandangan",
    "wof:placetype":"locality"
},
  "geometry": {"coordinates":[110.61472000000001,-7.60278],"type":"Point"}
}