{
  "type": "Feature",
  "properties": {
    "gn:admin1_code":"30.0",
    "gn:asciiname":"Cileuksa Lebak",
    "gn:country_code":"ID",
    "gn:dem":513,
    "gn:feature_class":"P",
    "gn:feature_code":"PPL",
    "gn:name":"Cileuksa Lebak",
    "gn:population":0,
    "gn:timezone":"Asia/Jakarta",
    "iso:country":"ID",
    "name:ind_x_preferred":[
        "Cileuksa Lebak"
    ],
    "wof:name":"Cileuksa Lebak",
    "wof:placetype":"locality"
},
  "geometry": {"coordinates":[106.4447,-6.6064],"type":"Point"}
}