{
  "type": "Feature",
  "properties": {
    "gn:admin1_code":"15.0",
    "gn:asciiname":"Rantautijang",
    "gn:country_code":"ID",
    "gn:dem":155,
    "gn:feature_class":"P",
    "gn:feature_code":"PPL",
    "gn:name":"Rantautijang",
    "gn:population":0,
    "gn:timezone":"Asia/Jakarta",
    "iso:country":"ID",
    "name:ind_x_preferred":[
        "Rantautijang"
    ],
    "name:und_x_variant":[
        "Rantautidjang"
    ],
    "wof:name":"Rantautijang",
    "wof:placetype":"locality"
},
  "geometry": {"coordinates":[104.85545999999999,-5.36389],"type":"Point"}
}