{
  "type": "Feature",
  "properties": {
    "gn:admin1_code":"30.0",
    "gn:asciiname":"Cikanyere",
    "gn:country_code":"ID",
    "gn:dem":257,
    "gn:feature_class":"P",
    "gn:feature_code":"PPL",
    "gn:name":"Cikanyere",
    "gn:population":0,
    "gn:timezone":"Asia/Jakarta",
    "iso:country":"ID",
    "name:ind_x_preferred":[
        "Cikanyere"
    ],
    "name:und_x_variant":[
        "Tjikanjere Satu"
    ],
    "wof:lang_x_official":[
        "ind"
    ],
    "wof:lang_x_spoken":[
        "ind",
        "eng"
    ],
    "wof:name":"Cikanyere",
    "wof:placetype":"locality"
},
  "geometry": {"coordinates":[108.3656,-7.3768],"type":"Point"}
}