{
  "type": "Feature",
  "properties": {
    "gn:admin1_code":"22.0",
    "gn:asciiname":"Lakaponu",
    "gn:country_code":"ID",
    "gn:dem":24,
    "gn:feature_class":"P",
    "gn:feature_code":"PPL",
    "gn:name":"Lakaponu",
    "gn:population":0,
    "gn:timezone":"Asia/Makassar",
    "iso:country":"ID",
    "name:ind_x_preferred":[
        "Lakaponu"
    ],
    "wof:name":"Lakaponu",
    "wof:placetype":"locality"
},
  "geometry": {"coordinates":[122.4562,-5.1004],"type":"Point"}
}