{
  "type": "Feature",
  "properties": {
    "gn:admin1_code":"30",
    "gn:asciiname":"Bumiasri",
    "gn:country_code":"ID",
    "gn:dem":26,
    "gn:feature_class":"P",
    "gn:feature_code":"PPL",
    "gn:name":"Bumiasri",
    "gn:population":0,
    "gn:timezone":"Asia/Jakarta",
    "iso:country":"ID",
    "name:ind_x_preferred":[
        "Bumiasri"
    ],
    "wof:name":"Bumiasri",
    "wof:placetype":"locality"
},
  "geometry": {"coordinates":[107.03556,-6.27806],"type":"Point"}
}