{
  "type": "Feature",
  "properties": {
    "gn:admin1_code":"18.0",
    "gn:asciiname":"Blarat",
    "gn:country_code":"ID",
    "gn:dem":487,
    "gn:feature_class":"P",
    "gn:feature_code":"PPL",
    "gn:name":"Blarat",
    "gn:population":0,
    "gn:timezone":"Asia/Makassar",
    "iso:country":"ID",
    "name:ind_x_preferred":[
        "Blarat"
    ],
    "wof:name":"Blarat",
    "wof:placetype":"locality"
},
  "geometry": {"coordinates":[122.3621,-8.7184],"type":"Point"}
}