{
  "type": "Feature",
  "properties": {
    "gn:admin1_code":"8",
    "gn:asciiname":"Jetakngasri",
    "gn:country_code":"ID",
    "gn:dem":611,
    "gn:feature_class":"P",
    "gn:feature_code":"PPL",
    "gn:name":"Jetakngasri",
    "gn:population":0,
    "gn:timezone":"Asia/Jakarta",
    "iso:country":"ID",
    "name:ind_x_preferred":[
        "Jetakngasri"
    ],
    "wof:name":"Jetakngasri",
    "wof:placetype":"locality"
},
  "geometry": {"coordinates":[112.57980000000001,-7.9231],"type":"Point"}
}