{
  "type": "Feature",
  "properties": {
    "gn:admin1_code":"41.0",
    "gn:asciiname":"Timbaang",
    "gn:country_code":"ID",
    "gn:dem":625,
    "gn:feature_class":"P",
    "gn:feature_code":"PPL",
    "gn:name":"Timbaang",
    "gn:population":0,
    "gn:timezone":"Asia/Makassar",
    "iso:country":"ID",
    "name:ind_x_preferred":[
        "Timbaang"
    ],
    "wof:name":"Timbaang",
    "wof:placetype":"locality"
},
  "geometry": {"coordinates":[119.1755,-2.9366],"type":"Point"}
}