{
  "type": "Feature",
  "properties": {
    "gn:admin1_code":"11",
    "gn:asciiname":"Parikan",
    "gn:country_code":"ID",
    "gn:dem":58,
    "gn:feature_class":"P",
    "gn:feature_code":"PPL",
    "gn:name":"Parikan",
    "gn:population":0,
    "gn:timezone":"Asia/Pontianak",
    "iso:country":"ID",
    "name:ind_x_preferred":[
        "Parikan"
    ],
    "wof:name":"Parikan",
    "wof:placetype":"locality"
},
  "geometry": {"coordinates":[109.21386,0.37441],"type":"Point"}
}