{
  "type": "Feature",
  "properties": {
    "gn:admin1_code":"18.0",
    "gn:asciiname":"Pawu",
    "gn:country_code":"ID",
    "gn:dem":599,
    "gn:feature_class":"P",
    "gn:feature_code":"PPL",
    "gn:name":"Pawu",
    "gn:population":0,
    "gn:timezone":"Asia/Makassar",
    "iso:country":"ID",
    "name:ind_x_preferred":[
        "Pawu"
    ],
    "wof:name":"Pawu",
    "wof:placetype":"locality"
},
  "geometry": {"coordinates":[120.4016,-8.7128],"type":"Point"}
}