{
  "type": "Feature",
  "properties": {
    "gn:admin1_code":"18.0",
    "gn:asciiname":"Kiba",
    "gn:country_code":"ID",
    "gn:dem":286,
    "gn:feature_class":"P",
    "gn:feature_code":"PPL",
    "gn:name":"Kiba",
    "gn:population":0,
    "gn:timezone":"Asia/Makassar",
    "iso:country":"ID",
    "name:ceb_x_preferred":[
        "Kiba"
    ],
    "name:deu_x_preferred":[
        "Kiba"
    ],
    "name:ell_x_preferred":[
        "Kiba"
    ],
    "name:hun_x_preferred":[
        "Kiba"
    ],
    "name:ind_x_preferred":[
        "Kiba"
    ],
    "name:jpn_x_preferred":[
        "\u7259"
    ],
    "name:kor_x_preferred":[
        "\ud0a4\ubc14"
    ],
    "name:spa_x_preferred":[
        "Kiba"
    ],
    "name:swe_x_preferred":[
        "Kiba"
    ],
    "wof:lang_x_official":[
        "ind"
    ],
    "wof:lang_x_spoken":[
        "ind",
        "eng"
    ],
    "wof:name":"Kiba",
    "wof:placetype":"locality"
},
  "geometry": {"coordinates":[124.65730000000001,-9.7455],"type":"Point"}
}