{
  "type": "Feature",
  "properties": {
    "gn:admin1_code":"21",
    "gn:asciiname":"Tinombala",
    "gn:country_code":"ID",
    "gn:dem":69,
    "gn:feature_class":"P",
    "gn:feature_code":"PPL",
    "gn:name":"Tinombala",
    "gn:population":0,
    "gn:timezone":"Asia/Makassar",
    "iso:country":"ID",
    "name:ind_x_preferred":[
        "Tinombala"
    ],
    "wof:name":"Tinombala",
    "wof:placetype":"locality"
},
  "geometry": {"coordinates":[120.76560000000001,0.579],"type":"Point"}
}