{
  "type": "Feature",
  "properties": {
    "gn:admin1_code":"30.0",
    "gn:asciiname":"Cigombong Satu",
    "gn:country_code":"ID",
    "gn:dem":878,
    "gn:feature_class":"P",
    "gn:feature_code":"PPL",
    "gn:name":"Cigombong Satu",
    "gn:population":0,
    "gn:timezone":"Asia/Jakarta",
    "iso:country":"ID",
    "name:ind_x_preferred":[
        "Cigombong Satu"
    ],
    "wof:name":"Cigombong Satu",
    "wof:placetype":"locality"
},
  "geometry": {"coordinates":[106.95529999999999,-7.0782],"type":"Point"}
}