{
  "type": "Feature",
  "properties": {
    "gn:admin1_code":"17.0",
    "gn:asciiname":"Sowa",
    "gn:country_code":"ID",
    "gn:dem":11,
    "gn:feature_class":"P",
    "gn:feature_code":"PPLA4",
    "gn:name":"Sowa",
    "gn:population":0,
    "gn:timezone":"Asia/Makassar",
    "iso:country":"ID",
    "name:ceb_x_preferred":[
        "Sowa"
    ],
    "name:deu_x_preferred":[
        "Sowa"
    ],
    "name:fas_x_preferred":[
        "\u0633\u0648\u0648\u0627"
    ],
    "name:fra_x_preferred":[
        "Sowa"
    ],
    "name:heb_x_preferred":[
        "\u05e1\u05d5\u05d5\u05d4"
    ],
    "name:hun_x_preferred":[
        "Sowa"
    ],
    "name:ind_x_preferred":[
        "Sowa"
    ],
    "name:ltz_x_preferred":[
        "Sowa"
    ],
    "name:pol_x_preferred":[
        "Sowa"
    ],
    "name:zho_cn_x_preferred":[
        "\u7d22\u74e6"
    ],
    "name:zho_tw_x_preferred":[
        "\u7d22\u74e6"
    ],
    "wof:lang_x_official":[
        "ind"
    ],
    "wof:lang_x_spoken":[
        "ind",
        "eng"
    ],
    "wof:name":"Sowa",
    "wof:placetype":"locality"
},
  "geometry": {"coordinates":[118.69009,-8.37509],"type":"Point"}
}