{
  "type": "Feature",
  "properties": {
    "gn:admin1_code":"17.0",
    "gn:asciiname":"Sowa",
    "gn:country_code":"ID",
    "gn:dem":11,
    "gn:feature_class":"P",
    "gn:feature_code":"PPLA4",
    "gn:name":"Sowa",
    "gn:population":0,
    "gn:timezone":"Asia/Makassar",
    "iso:country":"ID",
    "name:ind_x_preferred":[
        "Sowa"
    ],
    "wof:name":"Sowa",
    "wof:placetype":"locality"
},
  "geometry": {"coordinates":[118.69008999999998,-8.37509],"type":"Point"}
}