{
  "type": "Feature",
  "properties": {
    "gn:admin1_code":"08",
    "gn:asciiname":"Duduk",
    "gn:country_code":"ID",
    "gn:dem":7,
    "gn:feature_class":"P",
    "gn:feature_code":"PPL",
    "gn:name":"Duduk",
    "gn:population":0,
    "gn:timezone":"Asia/Jakarta",
    "iso:country":"ID",
    "name:ind_x_preferred":[
        "Duduk"
    ],
    "wof:name":"Duduk",
    "wof:placetype":"locality"
},
  "geometry": {"coordinates":[112.517,-7.1495],"type":"Point"}
}