{
  "type": "Feature",
  "properties": {
    "gn:admin1_code":"2.0",
    "gn:asciiname":"Gitgit",
    "gn:country_code":"ID",
    "gn:dem":561,
    "gn:feature_class":"P",
    "gn:feature_code":"PPL",
    "gn:name":"Gitgit",
    "gn:population":0,
    "gn:timezone":"Asia/Makassar",
    "iso:country":"ID",
    "name:ind_x_preferred":[
        "Banjar Gitgit"
    ],
    "wof:name":"Gitgit",
    "wof:placetype":"locality"
},
  "geometry": {"coordinates":[115.1366,-8.1885],"type":"Point"}
}