{
  "type": "Feature",
  "properties": {
    "gn:admin1_code":"7.0",
    "gn:asciiname":"Banjarsari",
    "gn:country_code":"ID",
    "gn:dem":28,
    "gn:feature_class":"P",
    "gn:feature_code":"PPL",
    "gn:name":"Banjarsari",
    "gn:population":0,
    "gn:timezone":"Asia/Jakarta",
    "iso:country":"ID",
    "name:ind_x_preferred":[
        "Banjarsari"
    ],
    "name:und_x_variant":[
        "Bandjarsari",
        "Banjarsari"
    ],
    "wof:name":"Banjarsari",
    "wof:placetype":"locality"
},
  "geometry": {"coordinates":[108.7766,-7.3416],"type":"Point"}
}