{
  "type": "Feature",
  "properties": {
    "gn:admin1_code":"15.0",
    "gn:asciiname":"Umbulan Waikarang",
    "gn:country_code":"ID",
    "gn:dem":20,
    "gn:feature_class":"P",
    "gn:feature_code":"PPL",
    "gn:name":"Umbulan Waikarang",
    "gn:population":0,
    "gn:timezone":"Asia/Jakarta",
    "iso:country":"ID",
    "name:ind_x_preferred":[
        "Umbulan Waikarang"
    ],
    "name:und_x_variant":[
        "Oemboelan Waikarang"
    ],
    "wof:name":"Umbulan Waikarang",
    "wof:placetype":"locality"
},
  "geometry": {"coordinates":[104.45564,-5.45576],"type":"Point"}
}