{
  "type": "Feature",
  "properties": {
    "gn:admin1_code":"7.0",
    "gn:asciiname":"Kamal",
    "gn:country_code":"ID",
    "gn:dem":713,
    "gn:feature_class":"P",
    "gn:feature_code":"PPL",
    "gn:name":"Kamal",
    "gn:population":0,
    "gn:timezone":"Asia/Jakarta",
    "iso:country":"ID",
    "name:deu_x_preferred":[
        "Kamal"
    ],
    "name:nor_x_preferred":[
        "Kamal"
    ],
    "wof:name":"Kamal",
    "wof:placetype":"locality"
},
  "geometry": {"coordinates":[110.11861,-7.25806],"type":"Point"}
}