{
  "type": "Feature",
  "properties": {
    "gn:admin1_code":"30",
    "gn:asciiname":"Leuwilisung",
    "gn:country_code":"ID",
    "gn:dem":189,
    "gn:feature_class":"P",
    "gn:feature_code":"PPL",
    "gn:name":"Leuwilisung",
    "gn:population":0,
    "gn:timezone":"Asia/Jakarta",
    "iso:country":"ID",
    "name:ind_x_preferred":[
        "Leuwilisung"
    ],
    "wof:name":"Leuwilisung",
    "wof:placetype":"locality"
},
  "geometry": {"coordinates":[106.61333,-6.56472],"type":"Point"}
}