{
  "type": "Feature",
  "properties": {
    "gn:admin1_code":"38.0",
    "gn:asciiname":"Siddo",
    "gn:country_code":"ID",
    "gn:dem":7,
    "gn:feature_class":"P",
    "gn:feature_code":"PPL",
    "gn:name":"Siddo",
    "gn:population":0,
    "gn:timezone":"Asia/Makassar",
    "iso:country":"ID",
    "name:ind_x_preferred":[
        "Siddo"
    ],
    "name:und_x_variant":[
        "Sido"
    ],
    "wof:name":"Siddo",
    "wof:placetype":"locality"
},
  "geometry": {"coordinates":[119.62430000000001,-4.2373],"type":"Point"}
}