{
  "type": "Feature",
  "properties": {
    "gn:admin1_code":"7",
    "gn:asciiname":"Gawis Wetan",
    "gn:country_code":"ID",
    "gn:dem":577,
    "gn:feature_class":"P",
    "gn:feature_code":"PPL",
    "gn:name":"Gawis Wetan",
    "gn:population":0,
    "gn:timezone":"Asia/Jakarta",
    "iso:country":"ID",
    "name:ind_x_preferred":[
        "Gawis Wetan"
    ],
    "wof:name":"Gawis Wetan",
    "wof:placetype":"locality"
},
  "geometry": {"coordinates":[109.98528,-7.50722],"type":"Point"}
}