{
  "type": "Feature",
  "properties": {
    "gn:admin1_code":"7.0",
    "gn:asciiname":"Bambir",
    "gn:country_code":"ID",
    "gn:dem":82,
    "gn:feature_class":"P",
    "gn:feature_code":"PPL",
    "gn:name":"Bambir",
    "gn:population":0,
    "gn:timezone":"Asia/Jakarta",
    "iso:country":"ID",
    "name:hye_x_preferred":[
        "\u0532\u0561\u0574\u0562\u056b\u057c"
    ],
    "name:hyw_x_preferred":[
        "\u0532\u0561\u0574\u0562\u056b\u057c"
    ],
    "name:rus_x_preferred":[
        "Bambir"
    ],
    "name:tur_x_preferred":[
        "Bambir"
    ],
    "wof:lang_x_official":[
        "ind"
    ],
    "wof:lang_x_spoken":[
        "ind",
        "eng"
    ],
    "wof:name":"Bambir",
    "wof:placetype":"locality"
},
  "geometry": {"coordinates":[110.9225,-7.46222],"type":"Point"}
}