{
  "type": "Feature",
  "properties": {
    "gn:admin1_code":"7",
    "gn:asciiname":"Doromantek",
    "gn:country_code":"ID",
    "gn:dem":223,
    "gn:feature_class":"P",
    "gn:feature_code":"PPL",
    "gn:name":"Doromantek",
    "gn:population":0,
    "gn:timezone":"Asia/Jakarta",
    "iso:country":"ID",
    "name:ind_x_preferred":[
        "Doromantek"
    ],
    "wof:name":"Doromantek",
    "wof:placetype":"locality"
},
  "geometry": {"coordinates":[109.6855,-7.0374],"type":"Point"}
}