{
  "type": "Feature",
  "properties": {
    "gn:admin1_code":"8.0",
    "gn:asciiname":"Gerih",
    "gn:country_code":"ID",
    "gn:dem":70,
    "gn:feature_class":"P",
    "gn:feature_code":"PPL",
    "gn:name":"Gerih",
    "gn:population":0,
    "gn:timezone":"Asia/Jakarta",
    "iso:country":"ID",
    "name:ind_x_preferred":[
        "Gerih"
    ],
    "wof:name":"Gerih",
    "wof:placetype":"locality"
},
  "geometry": {"coordinates":[111.41240000000001,-7.5171],"type":"Point"}
}