{
  "type": "Feature",
  "properties": {
    "gn:admin1_code":"26",
    "gn:asciiname":"Ujung Rambe Penampungan",
    "gn:country_code":"ID",
    "gn:dem":74,
    "gn:feature_class":"P",
    "gn:feature_code":"PPL",
    "gn:name":"Ujung Rambe Penampungan",
    "gn:population":0,
    "gn:timezone":"Asia/Jakarta",
    "iso:country":"ID",
    "name:ind_x_preferred":[
        "Ujung Rambe Penampungan"
    ],
    "wof:name":"Ujung Rambe Penampungan",
    "wof:placetype":"locality"
},
  "geometry": {"coordinates":[98.79130000000001,3.4309],"type":"Point"}
}