{
  "type": "Feature",
  "properties": {
    "gn:admin1_code":"31",
    "gn:asciiname":"Kopi",
    "gn:country_code":"ID",
    "gn:dem":-9999,
    "gn:feature_class":"P",
    "gn:feature_code":"PPL",
    "gn:name":"Kopi",
    "gn:population":0,
    "gn:timezone":"Asia/Makassar",
    "iso:country":"ID",
    "name:ceb_x_preferred":[
        "Kopi"
    ],
    "name:ind_x_preferred":[
        "Kopi"
    ],
    "name:jav_x_preferred":[
        "Kopi"
    ],
    "name:swe_x_preferred":[
        "Kopi"
    ],
    "wof:lang_x_official":[
        "ind"
    ],
    "wof:lang_x_spoken":[
        "ind",
        "eng"
    ],
    "wof:name":"Kopi",
    "wof:placetype":"locality"
},
  "geometry": {"coordinates":[124.70581,1.6481],"type":"Point"}
}