{
  "type": "Feature",
  "properties": {
    "gn:admin1_code":"26",
    "gn:asciiname":"Lubuk Rohan",
    "gn:country_code":"ID",
    "gn:dem":9,
    "gn:feature_class":"P",
    "gn:feature_code":"PPL",
    "gn:name":"Lubuk Rohan",
    "gn:population":0,
    "gn:timezone":"Asia/Jakarta",
    "iso:country":"ID",
    "name:ind_x_preferred":[
        "Lubuk Rohan"
    ],
    "wof:name":"Lubuk Rohan",
    "wof:placetype":"locality"
},
  "geometry": {"coordinates":[98.485,3.8069],"type":"Point"}
}