{
  "type": "Feature",
  "properties": {
    "gn:admin1_code":"38",
    "gn:asciiname":"Lapabekeng",
    "gn:country_code":"ID",
    "gn:dem":480,
    "gn:feature_class":"P",
    "gn:feature_code":"PPL",
    "gn:name":"Lapabekeng",
    "gn:population":0,
    "gn:timezone":"Asia/Makassar",
    "iso:country":"ID",
    "name:ind_x_preferred":[
        "Lapabekeng"
    ],
    "wof:name":"Lapabekeng",
    "wof:placetype":"locality"
},
  "geometry": {"coordinates":[120.09869999999999,-4.5399],"type":"Point"}
}