{
  "type": "Feature",
  "properties": {
    "gn:admin1_code":"38",
    "gn:asciiname":"Biringaparang",
    "gn:country_code":"ID",
    "gn:dem":688,
    "gn:feature_class":"P",
    "gn:feature_code":"PPL",
    "gn:name":"Biringaparang",
    "gn:population":0,
    "gn:timezone":"Asia/Makassar",
    "iso:country":"ID",
    "name:ind_x_preferred":[
        "Biringaparang"
    ],
    "wof:name":"Biringaparang",
    "wof:placetype":"locality"
},
  "geometry": {"coordinates":[120.07980000000001,-5.2781],"type":"Point"}
}