{
  "type": "Feature",
  "properties": {
    "gn:admin1_code":"38.0",
    "gn:asciiname":"Toila",
    "gn:country_code":"ID",
    "gn:dem":768,
    "gn:feature_class":"P",
    "gn:feature_code":"PPL",
    "gn:name":"Toila",
    "gn:population":0,
    "gn:timezone":"Asia/Makassar",
    "iso:country":"ID",
    "name:ceb_x_preferred":[
        "Toila"
    ],
    "name:deu_x_preferred":[
        "Toila"
    ],
    "name:est_x_preferred":[
        "Toila"
    ],
    "name:fra_x_preferred":[
        "Toila"
    ],
    "name:hye_x_preferred":[
        "\u054f\u0578\u056b\u056c\u0561"
    ],
    "name:ind_x_preferred":[
        "Toila"
    ],
    "name:nld_x_preferred":[
        "Toila"
    ],
    "name:pol_x_preferred":[
        "Toila"
    ],
    "name:rus_x_preferred":[
        "\u0422\u043e\u0439\u043b\u0430"
    ],
    "name:spa_x_preferred":[
        "Toila"
    ],
    "name:swe_x_preferred":[
        "Toila"
    ],
    "name:vol_x_preferred":[
        "Toila"
    ],
    "name:zho_x_preferred":[
        "\u6258\u4f0a\u62c9"
    ],
    "wof:name":"Toila",
    "wof:placetype":"locality"
},
  "geometry": {"coordinates":[120.1028,-3.1366],"type":"Point"}
}