{
  "type": "Feature",
  "properties": {
    "gn:admin1_code":"38.0",
    "gn:asciiname":"Toila",
    "gn:country_code":"ID",
    "gn:dem":768,
    "gn:feature_class":"P",
    "gn:feature_code":"PPL",
    "gn:name":"Toila",
    "gn:population":0,
    "gn:timezone":"Asia/Makassar",
    "iso:country":"ID",
    "name:ind_x_preferred":[
        "Toila"
    ],
    "wof:name":"Toila",
    "wof:placetype":"locality"
},
  "geometry": {"coordinates":[120.1028,-3.1366],"type":"Point"}
}