{
  "type": "Feature",
  "properties": {
    "gn:admin1_code":"7",
    "gn:asciiname":"Ujungalit",
    "gn:country_code":"ID",
    "gn:dem":22,
    "gn:feature_class":"P",
    "gn:feature_code":"PPL",
    "gn:name":"Ujungalit",
    "gn:population":0,
    "gn:timezone":"Asia/Jakarta",
    "iso:country":"ID",
    "name:ind_x_preferred":[
        "Ujungalit"
    ],
    "wof:name":"Ujungalit",
    "wof:placetype":"locality"
},
  "geometry": {"coordinates":[109.50060000000001,-6.9578],"type":"Point"}
}