{
  "type": "Feature",
  "properties": {
    "gn:admin1_code":"38.0",
    "gn:asciiname":"Talapa",
    "gn:country_code":"ID",
    "gn:dem":20,
    "gn:feature_class":"P",
    "gn:feature_code":"PPL",
    "gn:name":"Talapa",
    "gn:population":0,
    "gn:timezone":"Asia/Makassar",
    "iso:country":"ID",
    "name:ind_x_preferred":[
        "Talapa"
    ],
    "wof:name":"Talapa",
    "wof:placetype":"locality"
},
  "geometry": {"coordinates":[120.401,-3.5628],"type":"Point"}
}