{
  "type": "Feature",
  "properties": {
    "gn:admin1_code":"8.0",
    "gn:asciiname":"Koatas Lao",
    "gn:country_code":"ID",
    "gn:dem":115,
    "gn:feature_class":"P",
    "gn:feature_code":"PPLA4",
    "gn:name":"Koatas Lao",
    "gn:population":0,
    "gn:timezone":"Asia/Jakarta",
    "iso:country":"ID",
    "name:ind_x_preferred":[
        "Koatas Lao"
    ],
    "wof:lang_x_official":[
        "ind"
    ],
    "wof:lang_x_spoken":[
        "ind",
        "eng"
    ],
    "wof:name":"Koatas Lao",
    "wof:placetype":"locality"
},
  "geometry": {"coordinates":[114.3603,-7.1432],"type":"Point"}
}