{
  "type": "Feature",
  "properties": {
    "gn:admin1_code":"34.0",
    "gn:asciiname":"Kiambang",
    "gn:country_code":"ID",
    "gn:dem":9,
    "gn:feature_class":"P",
    "gn:feature_code":"PPL",
    "gn:name":"Kiambang",
    "gn:population":0,
    "gn:timezone":"Asia/Makassar",
    "iso:country":"ID",
    "name:ind_x_preferred":[
        "Kiambang"
    ],
    "wof:name":"Kiambang",
    "wof:placetype":"locality"
},
  "geometry": {"coordinates":[123.0147,0.5758],"type":"Point"}
}