{
  "type": "Feature",
  "properties": {
    "gn:admin1_code":"30.0",
    "gn:asciiname":"Bojongkaratom",
    "gn:cc2":"ID",
    "gn:country_code":"ID",
    "gn:dem":0,
    "gn:feature_class":"P",
    "gn:feature_code":"PPL",
    "gn:name":"Bojongkaratom",
    "gn:population":0,
    "gn:timezone":"Asia/Jakarta",
    "iso:country":"ID",
    "name:und_x_variant":[
        "Bodjongkaratom",
        "Bojongkaratom"
    ],
    "wof:lang_x_official":[
        "ind"
    ],
    "wof:lang_x_spoken":[
        "ind",
        "eng"
    ],
    "wof:name":"Bojongkaratom",
    "wof:placetype":"locality"
},
  "geometry": {"coordinates":[106.98528,-6.12056],"type":"Point"}
}