{
  "type": "Feature",
  "properties": {
    "gn:admin1_code":"18.0",
    "gn:asciiname":"Lewota'a",
    "gn:country_code":"ID",
    "gn:dem":677,
    "gn:feature_class":"P",
    "gn:feature_code":"PPL",
    "gn:name":"Lewota\u2019a",
    "gn:population":0,
    "gn:timezone":"Asia/Makassar",
    "iso:country":"ID",
    "name:ind_x_preferred":[
        "Lewota\u2019a"
    ],
    "wof:name":"Lewota'a",
    "wof:placetype":"locality"
},
  "geometry": {"coordinates":[123.6559,-8.3529],"type":"Point"}
}