{
  "type": "Feature",
  "properties": {
    "gn:admin1_code":"30.0",
    "gn:asciiname":"Kedungjarian",
    "gn:country_code":"ID",
    "gn:dem":16,
    "gn:feature_class":"P",
    "gn:feature_code":"PPL",
    "gn:name":"Kedungjarian",
    "gn:population":0,
    "gn:timezone":"Asia/Jakarta",
    "iso:country":"ID",
    "name:ind_x_preferred":[
        "Kedungjarian"
    ],
    "name:und_x_variant":[
        "Kedungdjaran",
        "Kedungjaran",
        "Kedungdjarian"
    ],
    "wof:name":"Kedungjarian",
    "wof:placetype":"locality"
},
  "geometry": {"coordinates":[108.6979,-7.4087],"type":"Point"}
}