{
  "type": "Feature",
  "properties": {
    "gn:admin1_code":"18.0",
    "gn:asciiname":"Belen",
    "gn:country_code":"ID",
    "gn:dem":33,
    "gn:feature_class":"P",
    "gn:feature_code":"PPL",
    "gn:name":"Belen",
    "gn:population":0,
    "gn:timezone":"Asia/Makassar",
    "iso:country":"ID",
    "name:bul_x_preferred":[
        "\u0411\u0435\u043b\u0435\u043d"
    ],
    "name:ceb_x_preferred":[
        "Belen"
    ],
    "name:hye_x_preferred":[
        "\u0532\u0565\u056c\u0565\u0576"
    ],
    "name:ind_x_preferred":[
        "Belen"
    ],
    "name:jpn_x_preferred":[
        "\u30d9\u30ec\u30f3"
    ],
    "name:kaz_x_preferred":[
        "\u0411\u0435\u043b\u0435\u043d"
    ],
    "name:min_x_preferred":[
        "Belen"
    ],
    "name:nld_x_preferred":[
        "Belen"
    ],
    "name:rus_x_preferred":[
        "\u0411\u0435\u043b\u0435\u043d"
    ],
    "name:sco_x_preferred":[
        "Belen"
    ],
    "name:srp_x_preferred":[
        "\u0411\u0435\u043b\u0435\u043d"
    ],
    "name:swe_x_preferred":[
        "Belen"
    ],
    "name:tur_x_preferred":[
        "Belen"
    ],
    "name:ukr_x_preferred":[
        "\u0411\u0435\u043b\u0435\u043d"
    ],
    "wof:lang_x_official":[
        "ind"
    ],
    "wof:lang_x_spoken":[
        "ind",
        "eng"
    ],
    "wof:name":"Belen",
    "wof:placetype":"locality"
},
  "geometry": {"coordinates":[123.51139999999999,-8.3658],"type":"Point"}
}