{
  "type": "Feature",
  "properties": {
    "gn:admin1_code":"30.0",
    "gn:asciiname":"Cikalong",
    "gn:country_code":"ID",
    "gn:dem":382,
    "gn:feature_class":"P",
    "gn:feature_code":"PPL",
    "gn:name":"Cikalong",
    "gn:population":0,
    "gn:timezone":"Asia/Jakarta",
    "iso:country":"ID",
    "name:ind_x_preferred":[
        "Cikalong"
    ],
    "wof:name":"Cikalong",
    "wof:placetype":"locality"
},
  "geometry": {"coordinates":[108.3781,-7.1895],"type":"Point"}
}