{
  "type": "Feature",
  "properties": {
    "gn:admin1_code":"30.0",
    "gn:asciiname":"Karangwangi",
    "gn:country_code":"ID",
    "gn:dem":26,
    "gn:feature_class":"P",
    "gn:feature_code":"PPL",
    "gn:name":"Karangwangi",
    "gn:population":0,
    "gn:timezone":"Asia/Jakarta",
    "iso:country":"ID",
    "name:ind_x_preferred":[
        "Karangwangi"
    ],
    "wof:name":"Karangwangi",
    "wof:placetype":"locality"
},
  "geometry": {"coordinates":[108.36306,-6.68111],"type":"Point"}
}