{
  "type": "Feature",
  "properties": {
    "gn:admin1_code":"26.0",
    "gn:asciiname":"Sait Nihuta",
    "gn:country_code":"ID",
    "gn:dem":916,
    "gn:feature_class":"P",
    "gn:feature_code":"PPL",
    "gn:name":"Sait Nihuta",
    "gn:population":0,
    "gn:timezone":"Asia/Jakarta",
    "iso:country":"ID",
    "name:ind_x_preferred":[
        "Sait Nihuta"
    ],
    "name:und_x_variant":[
        "Sait Ni Hoeta"
    ],
    "wof:lang_x_official":[
        "ind"
    ],
    "wof:lang_x_spoken":[
        "ind",
        "eng"
    ],
    "wof:name":"Sait Nihuta",
    "wof:placetype":"locality"
},
  "geometry": {"coordinates":[98.8267,2.7677],"type":"Point"}
}