{
  "type": "Feature",
  "properties": {
    "gn:admin1_code":"18.0",
    "gn:asciiname":"Watoona",
    "gn:country_code":"ID",
    "gn:dem":37,
    "gn:feature_class":"P",
    "gn:feature_code":"PPLA4",
    "gn:name":"Watoona",
    "gn:population":0,
    "gn:timezone":"Asia/Makassar",
    "iso:country":"ID",
    "name:ind_x_preferred":[
        "Watoona"
    ],
    "wof:name":"Watoona",
    "wof:placetype":"locality"
},
  "geometry": {"coordinates":[123.0902,-8.4793],"type":"Point"}
}