{
  "type": "Feature",
  "properties": {
    "gn:admin1_code":"8.0",
    "gn:asciiname":"Tumpak",
    "gn:country_code":"ID",
    "gn:dem":99,
    "gn:feature_class":"P",
    "gn:feature_code":"PPL",
    "gn:name":"Tumpak",
    "gn:population":0,
    "gn:timezone":"Asia/Jakarta",
    "iso:country":"ID",
    "name:ind_x_preferred":[
        "Tumpak"
    ],
    "wof:name":"Tumpak",
    "wof:placetype":"locality"
},
  "geometry": {"coordinates":[112.7067,-8.3771],"type":"Point"}
}