{
  "type": "Feature",
  "properties": {
    "gn:country":"ID",
    "gn:fcode":"ADM4",
    "gn:pop":0,
    "iso:country":"ID",
    "name:ind_x_preferred":[
        "Desa Pusakajaya"
    ],
    "name:unk_x_variant":[
        "Pusakajaya"
    ],
    "qs:name":"Desa Pusakajaya",
    "qs:photos_9r":0,
    "qs:photos_sr":0,
    "qs:pop_sr":"0",
    "wof:name":"Desa Pusakajaya",
    "wof:placetype":"localadmin",
    "wof:population":0
},
  "geometry": {"coordinates":[107.87222,-6.29556],"type":"Point"}
}