{
  "type": "Feature",
  "properties": {
    "gn:admin1_code":"8.0",
    "gn:asciiname":"Kelis Lor",
    "gn:country_code":"ID",
    "gn:dem":307,
    "gn:feature_class":"P",
    "gn:feature_code":"PPL",
    "gn:name":"Kelis Lor",
    "gn:population":0,
    "gn:timezone":"Asia/Jakarta",
    "iso:country":"ID",
    "name:ind_x_preferred":[
        "Kelis Lor"
    ],
    "wof:name":"Kelis Lor",
    "wof:placetype":"locality"
},
  "geometry": {"coordinates":[111.4054,-8.1805],"type":"Point"}
}