{
  "type": "Feature",
  "properties": {
    "gn:admin1_code":"26",
    "gn:asciiname":"Medan Krio B",
    "gn:country_code":"ID",
    "gn:dem":34,
    "gn:feature_class":"P",
    "gn:feature_code":"PPL",
    "gn:name":"Medan Krio B",
    "gn:population":0,
    "gn:timezone":"Asia/Jakarta",
    "iso:country":"ID",
    "name:ind_x_preferred":[
        "Medan Krio B"
    ],
    "wof:name":"Medan Krio B",
    "wof:placetype":"locality"
},
  "geometry": {"coordinates":[98.5857,3.5716],"type":"Point"}
}