{
  "type": "Feature",
  "properties": {
    "gn:admin1_code":"30",
    "gn:asciiname":"Cisanggarung Kidul",
    "gn:country_code":"ID",
    "gn:dem":967,
    "gn:feature_class":"P",
    "gn:feature_code":"PPL",
    "gn:name":"Cisanggarung Kidul",
    "gn:population":0,
    "gn:timezone":"Asia/Jakarta",
    "iso:country":"ID",
    "name:ind_x_preferred":[
        "Cisanggarung Kidul"
    ],
    "wof:name":"Cisanggarung Kidul",
    "wof:placetype":"locality"
},
  "geometry": {"coordinates":[107.68444,-6.87556],"type":"Point"}
}