{
  "type": "Feature",
  "properties": {
    "gn:admin1_code":"30",
    "gn:asciiname":"Plawad Satu",
    "gn:cc2":"ID",
    "gn:country_code":"ID",
    "gn:dem":19,
    "gn:feature_class":"P",
    "gn:feature_code":"PPL",
    "gn:name":"Plawad Satu",
    "gn:population":0,
    "gn:timezone":"Asia/Jakarta",
    "iso:country":"ID",
    "name:und_x_variant":[
        "Plawad 1",
        "Plawad Satu"
    ],
    "wof:name":"Plawad Satu",
    "wof:placetype":"locality"
},
  "geometry": {"coordinates":[106.65333,-6.18611],"type":"Point"}
}