{
  "type": "Feature",
  "properties": {
    "gn:admin1_code":"30",
    "gn:asciiname":"Cibuluh",
    "gn:country_code":"ID",
    "gn:dem":185,
    "gn:feature_class":"P",
    "gn:feature_code":"PPL",
    "gn:name":"Cibuluh",
    "gn:population":0,
    "gn:timezone":"Asia/Jakarta",
    "iso:country":"ID",
    "name:ind_x_preferred":[
        "Cibuluh"
    ],
    "name:und_x_variant":[
        "Cibuluh 1"
    ],
    "wof:name":"Cibuluh",
    "wof:placetype":"locality"
},
  "geometry": {"coordinates":[107.72750000000001,-6.59639],"type":"Point"}
}