{
  "type": "Feature",
  "properties": {
    "gn:admin1_code":"26.0",
    "gn:asciiname":"Pinal",
    "gn:country_code":"ID",
    "gn:dem":919,
    "gn:feature_class":"P",
    "gn:feature_code":"PPL",
    "gn:name":"Pinal",
    "gn:population":0,
    "gn:timezone":"Asia/Jakarta",
    "iso:country":"ID",
    "name:ceb_x_preferred":[
        "Pinal"
    ],
    "name:deu_x_preferred":[
        "Pinal"
    ],
    "name:fra_x_preferred":[
        "Pinal"
    ],
    "name:ind_x_preferred":[
        "Pinal"
    ],
    "name:rus_x_preferred":[
        "\u041f\u0438\u043d\u0430\u043b"
    ],
    "name:spa_x_preferred":[
        "Pinal"
    ],
    "name:srp_x_preferred":[
        "\u041f\u0438\u043d\u0430\u043b"
    ],
    "name:swe_x_preferred":[
        "Pinal"
    ],
    "wof:lang_x_official":[
        "ind"
    ],
    "wof:lang_x_spoken":[
        "ind",
        "eng"
    ],
    "wof:name":"Pinal",
    "wof:placetype":"locality"
},
  "geometry": {"coordinates":[98.6033,2.7102],"type":"Point"}
}