{
  "type": "Feature",
  "properties": {
    "gn:admin1_code":"30",
    "gn:asciiname":"Seda",
    "gn:country_code":"ID",
    "gn:dem":734,
    "gn:feature_class":"P",
    "gn:feature_code":"PPL",
    "gn:name":"Seda",
    "gn:population":0,
    "gn:timezone":"Asia/Jakarta",
    "iso:country":"ID",
    "wof:name":"Seda",
    "wof:placetype":"locality"
},
  "geometry": {"coordinates":[107.5175,-7.0225],"type":"Point"}
}