{
  "type": "Feature",
  "properties": {
    "gn:admin1_code":"38",
    "gn:asciiname":"Lumbaja",
    "gn:country_code":"ID",
    "gn:dem":1151,
    "gn:feature_class":"P",
    "gn:feature_code":"PPL",
    "gn:name":"Lumbaja",
    "gn:population":0,
    "gn:timezone":"Asia/Makassar",
    "iso:country":"ID",
    "name:ind_x_preferred":[
        "Lumbaja"
    ],
    "wof:name":"Lumbaja",
    "wof:placetype":"locality"
},
  "geometry": {"coordinates":[119.81310000000001,-3.2823],"type":"Point"}
}