{
  "type": "Feature",
  "properties": {
    "gn:admin1_code":"7.0",
    "gn:asciiname":"Karangjinem",
    "gn:country_code":"ID",
    "gn:dem":1051,
    "gn:feature_class":"P",
    "gn:feature_code":"PPL",
    "gn:name":"Karangjinem",
    "gn:population":0,
    "gn:timezone":"Asia/Jakarta",
    "iso:country":"ID",
    "wof:name":"Karangjinem",
    "wof:placetype":"locality"
},
  "geometry": {"coordinates":[110.00388999999998,-7.40944],"type":"Point"}
}