{
  "type": "Feature",
  "properties": {
    "gn:admin1_code":"7.0",
    "gn:asciiname":"Perumnas Ngringo",
    "gn:country_code":"ID",
    "gn:dem":102,
    "gn:feature_class":"P",
    "gn:feature_code":"PPL",
    "gn:name":"Perumnas Ngringo",
    "gn:population":0,
    "gn:timezone":"Asia/Jakarta",
    "iso:country":"ID",
    "wof:name":"Perumnas Ngringo",
    "wof:placetype":"locality"
},
  "geometry": {"coordinates":[110.87721999999999,-7.55944],"type":"Point"}
}