{
  "type": "Feature",
  "properties": {
    "gn:admin1_code":"18.0",
    "gn:asciiname":"Pogo",
    "gn:country_code":"ID",
    "gn:dem":790,
    "gn:feature_class":"P",
    "gn:feature_code":"PPLA4",
    "gn:name":"Pogo",
    "gn:population":0,
    "gn:timezone":"Asia/Makassar",
    "iso:country":"ID",
    "name:deu_x_preferred":[
        "Pogo"
    ],
    "name:est_x_preferred":[
        "Pogo"
    ],
    "name:fin_x_preferred":[
        "Pogo"
    ],
    "name:fra_x_preferred":[
        "Pogo"
    ],
    "name:hun_x_preferred":[
        "Pogo"
    ],
    "name:ind_x_preferred":[
        "Pogo"
    ],
    "name:ita_x_preferred":[
        "Pogo"
    ],
    "name:nld_x_preferred":[
        "Pogo"
    ],
    "name:pol_x_preferred":[
        "Pogo"
    ],
    "name:rus_x_preferred":[
        "\u041f\u043e\u0433\u043e"
    ],
    "name:spa_x_preferred":[
        "Pogo"
    ],
    "wof:lang_x_official":[
        "ind"
    ],
    "wof:lang_x_spoken":[
        "ind",
        "eng"
    ],
    "wof:name":"Pogo",
    "wof:placetype":"locality"
},
  "geometry": {"coordinates":[121.1086,-8.7962],"type":"Point"}
}