{
  "type": "Feature",
  "properties": {
    "gn:admin1_code":"30",
    "gn:asciiname":"Cigalunggung",
    "gn:country_code":"ID",
    "gn:dem":676,
    "gn:feature_class":"P",
    "gn:feature_code":"PPL",
    "gn:name":"Cigalunggung",
    "gn:population":0,
    "gn:timezone":"Asia/Jakarta",
    "iso:country":"ID",
    "name:ind_x_preferred":[
        "Cigalunggung"
    ],
    "name:und_x_variant":[
        "Tjigarunggung",
        "Cigarunggung"
    ],
    "wof:lang_x_official":[
        "ind"
    ],
    "wof:lang_x_spoken":[
        "ind",
        "eng"
    ],
    "wof:name":"Cigalunggung",
    "wof:placetype":"locality"
},
  "geometry": {"coordinates":[107.40472,-6.94611],"type":"Point"}
}