{
  "type": "Feature",
  "properties": {
    "gn:admin1_code":"38.0",
    "gn:asciiname":"Sarong",
    "gn:country_code":"ID",
    "gn:dem":522,
    "gn:feature_class":"P",
    "gn:feature_code":"PPL",
    "gn:name":"Sarong",
    "gn:population":0,
    "gn:timezone":"Asia/Makassar",
    "iso:country":"ID",
    "name:ind_x_preferred":[
        "Sarong"
    ],
    "wof:name":"Sarong",
    "wof:placetype":"locality"
},
  "geometry": {"coordinates":[119.79649999999999,-3.52976],"type":"Point"}
}