{
  "type": "Feature",
  "properties": {
    "gn:admin1_code":"7.0",
    "gn:asciiname":"Godan Barat",
    "gn:country_code":"ID",
    "gn:dem":53,
    "gn:feature_class":"P",
    "gn:feature_code":"PPL",
    "gn:name":"Godan Barat",
    "gn:population":0,
    "gn:timezone":"Asia/Jakarta",
    "iso:country":"ID",
    "name:ind_x_preferred":[
        "Godan Barat"
    ],
    "wof:name":"Godan Barat",
    "wof:placetype":"locality"
},
  "geometry": {"coordinates":[111.0218,-7.05],"type":"Point"}
}