{
  "type": "Feature",
  "properties": {
    "gn:admin1_code":"33",
    "gn:asciiname":"Maruga",
    "gn:country_code":"ID",
    "gn:dem":32,
    "gn:feature_class":"P",
    "gn:feature_code":"PPL",
    "gn:name":"Maruga",
    "gn:population":0,
    "gn:timezone":"Asia/Jakarta",
    "iso:country":"ID",
    "name:ind_x_preferred":[
        "Maruga"
    ],
    "wof:name":"Maruga",
    "wof:placetype":"locality"
},
  "geometry": {"coordinates":[106.0844,-6.0591],"type":"Point"}
}