{
  "type": "Feature",
  "properties": {
    "gn:admin1_code":"26",
    "gn:asciiname":"Lau Mil Gadong",
    "gn:country_code":"ID",
    "gn:dem":432,
    "gn:feature_class":"P",
    "gn:feature_code":"PPL",
    "gn:name":"Lau Mil Gadong",
    "gn:population":0,
    "gn:timezone":"Asia/Jakarta",
    "iso:country":"ID",
    "name:ind_x_preferred":[
        "Lau Mil Gadong"
    ],
    "wof:name":"Lau Mil Gadong",
    "wof:placetype":"locality"
},
  "geometry": {"coordinates":[98.1818,2.9102],"type":"Point"}
}