{
  "type": "Feature",
  "properties": {
    "gn:admin1_code":"0.0",
    "gn:asciiname":"Sagadikobu",
    "gn:cc2":"ID",
    "gn:country_code":"ID",
    "gn:dem":1,
    "gn:feature_class":"P",
    "gn:feature_code":"PPL",
    "gn:name":"Sagadikobu",
    "gn:population":0,
    "gn:timezone":"Asia/Jayapura",
    "iso:country":"ID",
    "name:und_x_variant":[
        "Sagadikoboe",
        "Sagadikobu"
    ],
    "wof:name":"Sagadikobu",
    "wof:placetype":"locality"
},
  "geometry": {"coordinates":[133.41666999999998,-3.41667],"type":"Point"}
}