{
  "type": "Feature",
  "properties": {
    "gn:admin1_code":"30.0",
    "gn:asciiname":"Pasundan",
    "gn:country_code":"ID",
    "gn:dem":352,
    "gn:feature_class":"P",
    "gn:feature_code":"PPL",
    "gn:name":"Pasundan",
    "gn:population":0,
    "gn:timezone":"Asia/Jakarta",
    "iso:country":"ID",
    "name:ind_x_preferred":[
        "Pasundan"
    ],
    "name:ind_x_variant":[
        "Negara Pasundan"
    ],
    "name:ita_x_preferred":[
        "Pasundan"
    ],
    "name:jpn_x_preferred":[
        "\u30d1\u30b9\u30f3\u30c0\u30f3\u56fd"
    ],
    "name:rus_x_preferred":[
        "\u0413\u043e\u0441\u0443\u0434\u0430\u0440\u0441\u0442\u0432\u043e \u041f\u0430\u0441\u0443\u043d\u0434\u0430\u043d"
    ],
    "wof:lang_x_official":[
        "ind"
    ],
    "wof:lang_x_spoken":[
        "ind",
        "eng"
    ],
    "wof:name":"Pasundan",
    "wof:placetype":"locality"
},
  "geometry": {"coordinates":[108.2229,-7.3258],"type":"Point"}
}