{
  "type": "Feature",
  "properties": {
    "gn:admin1_code":"30.0",
    "gn:asciiname":"Pasundan",
    "gn:country_code":"ID",
    "gn:dem":352,
    "gn:feature_class":"P",
    "gn:feature_code":"PPL",
    "gn:name":"Pasundan",
    "gn:population":0,
    "gn:timezone":"Asia/Jakarta",
    "iso:country":"ID",
    "name:ind_x_preferred":[
        "Pasundan"
    ],
    "wof:name":"Pasundan",
    "wof:placetype":"locality"
},
  "geometry": {"coordinates":[108.2229,-7.3258],"type":"Point"}
}