{
  "type": "Feature",
  "properties": {
    "gn:country":"ID",
    "gn:fcode":"PPL",
    "gn:pop":0,
    "iso:country":"ID",
    "name:ind_x_preferred":[
        "Giriwoyo"
    ],
    "name:unk_x_variant":[
        "Giriwojo"
    ],
    "qs:name":"Giriwoyo",
    "qs:name_adm0":"Indonesia",
    "qs:name_adm1":"Provinsi Jawa Tengah",
    "qs:photos_9r":0,
    "qs:photos_sr":0,
    "qs:placetype":"Town",
    "qs:pop_sr":"0",
    "wof:name":"Giriwoyo",
    "wof:placetype":"locality",
    "wof:population":0
},
  "geometry": {"coordinates":[110.93556,-8.03222],"type":"Point"}
}