{
  "type": "Feature",
  "properties": {
    "gn:admin1_code":"30.0",
    "gn:asciiname":"Cikaramat",
    "gn:country_code":"ID",
    "gn:dem":598,
    "gn:feature_class":"P",
    "gn:feature_code":"PPL",
    "gn:name":"Cikaramat",
    "gn:population":0,
    "gn:timezone":"Asia/Jakarta",
    "iso:country":"ID",
    "name:ind_x_preferred":[
        "Cikaramat"
    ],
    "wof:name":"Cikaramat",
    "wof:placetype":"locality"
},
  "geometry": {"coordinates":[107.49299999999999,-7.3116],"type":"Point"}
}