{
  "type": "Feature",
  "properties": {
    "gn:admin1_code":"29.0",
    "gn:asciiname":"Duono",
    "gn:country_code":"ID",
    "gn:dem":105,
    "gn:feature_class":"P",
    "gn:feature_code":"PPL",
    "gn:name":"Duono",
    "gn:population":0,
    "gn:timezone":"Asia/Jayapura",
    "iso:country":"ID",
    "name:und_x_variant":[
        "Doeono",
        "Duono"
    ],
    "wof:name":"Duono",
    "wof:placetype":"locality"
},
  "geometry": {"coordinates":[127.60160999999999,1.5408],"type":"Point"}
}