{
  "type": "Feature",
  "properties": {
    "gn:admin1_code":"10",
    "gn:asciiname":"Bandut Lor",
    "gn:country_code":"ID",
    "gn:dem":70,
    "gn:feature_class":"P",
    "gn:feature_code":"PPL",
    "gn:name":"Bandut Lor",
    "gn:population":0,
    "gn:timezone":"Asia/Jakarta",
    "iso:country":"ID",
    "wof:name":"Bandut Lor",
    "wof:placetype":"locality"
},
  "geometry": {"coordinates":[110.26639,-7.81806],"type":"Point"}
}