{
  "type": "Feature",
  "properties": {
    "gn:admin1_code":"30.0",
    "gn:asciiname":"Muaraciamis",
    "gn:country_code":"ID",
    "gn:dem":109,
    "gn:feature_class":"P",
    "gn:feature_code":"PPL",
    "gn:name":"Muaraciamis",
    "gn:population":0,
    "gn:timezone":"Asia/Jakarta",
    "iso:country":"ID",
    "name:ind_x_preferred":[
        "Muaraciamis"
    ],
    "wof:name":"Muaraciamis",
    "wof:placetype":"locality"
},
  "geometry": {"coordinates":[108.35590000000001,-7.7558],"type":"Point"}
}