{
  "type": "Feature",
  "properties": {
    "gn:admin1_code":"30.0",
    "gn:asciiname":"Nagrok",
    "gn:country_code":"ID",
    "gn:dem":684,
    "gn:feature_class":"P",
    "gn:feature_code":"PPL",
    "gn:name":"Nagrok",
    "gn:population":0,
    "gn:timezone":"Asia/Jakarta",
    "iso:country":"ID",
    "name:ind_x_preferred":[
        "Nagrok"
    ],
    "wof:name":"Nagrok",
    "wof:placetype":"locality"
},
  "geometry": {"coordinates":[107.9815,-7.3653],"type":"Point"}
}