{
  "type": "Feature",
  "properties": {
    "gn:admin1_code":"8.0",
    "gn:asciiname":"Boom",
    "gn:country_code":"ID",
    "gn:dem":5,
    "gn:feature_class":"P",
    "gn:feature_code":"PPL",
    "gn:name":"Boom",
    "gn:population":0,
    "gn:timezone":"Asia/Jakarta",
    "iso:country":"ID",
    "name:ceb_x_preferred":[
        "Boom"
    ],
    "name:ces_x_preferred":[
        "Boom"
    ],
    "name:deu_x_preferred":[
        "Boom"
    ],
    "name:epo_x_preferred":[
        "Bumo"
    ],
    "name:est_x_preferred":[
        "Boom"
    ],
    "name:fin_x_preferred":[
        "Boom"
    ],
    "name:fra_x_preferred":[
        "Boom"
    ],
    "name:hun_x_preferred":[
        "Boom"
    ],
    "name:ind_x_preferred":[
        "Boom"
    ],
    "name:ita_x_preferred":[
        "Boom"
    ],
    "name:jpn_x_preferred":[
        "\u30d6\u30fc\u30e0"
    ],
    "name:nds_x_preferred":[
        "Boom"
    ],
    "name:nld_x_preferred":[
        "Boom"
    ],
    "name:pol_x_preferred":[
        "Boom"
    ],
    "name:por_x_preferred":[
        "Boom"
    ],
    "name:ron_x_preferred":[
        "Boom"
    ],
    "name:rus_x_preferred":[
        "Boom"
    ],
    "name:slk_x_preferred":[
        "Boom"
    ],
    "name:spa_x_preferred":[
        "Boom"
    ],
    "name:tha_x_preferred":[
        "\u0e1a\u0e39\u0e21"
    ],
    "wof:lang_x_official":[
        "ind"
    ],
    "wof:lang_x_spoken":[
        "ind",
        "eng"
    ],
    "wof:name":"Boom",
    "wof:placetype":"locality"
},
  "geometry": {"coordinates":[113.9028,-7.042],"type":"Point"}
}