{
  "type": "Feature",
  "properties": {
    "gn:admin1_code":"30",
    "gn:asciiname":"Elos",
    "gn:country_code":"ID",
    "gn:dem":358,
    "gn:feature_class":"P",
    "gn:feature_code":"PPL",
    "gn:name":"Elos",
    "gn:population":0,
    "gn:timezone":"Asia/Jakarta",
    "iso:country":"ID",
    "name:ara_x_preferred":[
        "\u0625\u0644\u0648\u0633"
    ],
    "name:ceb_x_preferred":[
        "\u00c9los"
    ],
    "name:ell_x_preferred":[
        "\u0388\u03bb\u03bf\u03c2 \u039b\u03b1\u03ba\u03c9\u03bd\u03af\u03b1\u03c2"
    ],
    "name:fin_x_preferred":[
        "\u00c9los"
    ],
    "name:ind_x_preferred":[
        "Elos"
    ],
    "name:ita_x_preferred":[
        "Elos"
    ],
    "name:nno_x_preferred":[
        "\u00c9los"
    ],
    "name:ron_x_preferred":[
        "Elos"
    ],
    "wof:lang_x_official":[
        "ind"
    ],
    "wof:lang_x_spoken":[
        "ind",
        "eng"
    ],
    "wof:name":"Elos",
    "wof:placetype":"locality"
},
  "geometry": {"coordinates":[108.09556000000001,-6.96333],"type":"Point"}
}