{
  "type": "Feature",
  "properties": {
    "gn:admin1_code":"22.0",
    "gn:asciiname":"Tikonu",
    "gn:country_code":"ID",
    "gn:dem":42,
    "gn:feature_class":"P",
    "gn:feature_code":"PPL",
    "gn:name":"Tikonu",
    "gn:population":0,
    "gn:timezone":"Asia/Makassar",
    "iso:country":"ID",
    "name:ind_x_preferred":[
        "Tikonu"
    ],
    "name:und_x_variant":[
        "Tikonoe"
    ],
    "wof:name":"Tikonu",
    "wof:placetype":"locality"
},
  "geometry": {"coordinates":[121.68259999999999,-4.1152],"type":"Point"}
}