{
  "type": "Feature",
  "properties": {
    "gn:admin1_code":"30",
    "gn:asciiname":"Nangleng",
    "gn:country_code":"ID",
    "gn:dem":862,
    "gn:feature_class":"P",
    "gn:feature_code":"PPL",
    "gn:name":"Nangleng",
    "gn:population":0,
    "gn:timezone":"Asia/Jakarta",
    "iso:country":"ID",
    "name:ind_x_preferred":[
        "Nangleng"
    ],
    "wof:name":"Nangleng",
    "wof:placetype":"locality"
},
  "geometry": {"coordinates":[107.06861000000001,-6.70833],"type":"Point"}
}