{
  "type": "Feature",
  "properties": {
    "gn:admin1_code":"33.0",
    "gn:asciiname":"Leungsir",
    "gn:country_code":"ID",
    "gn:dem":65,
    "gn:feature_class":"P",
    "gn:feature_code":"PPL",
    "gn:name":"Leungsir",
    "gn:population":0,
    "gn:timezone":"Asia/Jakarta",
    "iso:country":"ID",
    "name:ind_x_preferred":[
        "Leungsir"
    ],
    "wof:name":"Leungsir",
    "wof:placetype":"locality"
},
  "geometry": {"coordinates":[106.1998,-6.5026],"type":"Point"}
}