{
  "type": "Feature",
  "properties": {
    "gn:admin1_code":"1",
    "gn:asciiname":"Seuradeu Satu",
    "gn:country_code":"ID",
    "gn:dem":29,
    "gn:feature_class":"P",
    "gn:feature_code":"PPL",
    "gn:name":"Seuradeu Satu",
    "gn:population":0,
    "gn:timezone":"Asia/Jakarta",
    "iso:country":"ID",
    "name:ind_x_preferred":[
        "Seuradeu Satu"
    ],
    "name:und_x_variant":[
        "Seuradeu 1"
    ],
    "wof:lang_x_official":[
        "ind"
    ],
    "wof:lang_x_spoken":[
        "ind",
        "eng"
    ],
    "wof:name":"Seuradeu Satu",
    "wof:placetype":"locality"
},
  "geometry": {"coordinates":[96.0566,4.5115],"type":"Point"}
}