{
  "type": "Feature",
  "properties": {
    "gn:admin1_code":"26",
    "gn:asciiname":"Tasik",
    "gn:country_code":"ID",
    "gn:dem":23,
    "gn:feature_class":"P",
    "gn:feature_code":"PPL",
    "gn:name":"Tasik",
    "gn:population":0,
    "gn:timezone":"Asia/Jakarta",
    "iso:country":"ID",
    "name:fas_x_preferred":[
        "\u062a\u0627\u0633\u06cc\u06a9"
    ],
    "name:fra_x_preferred":[
        "Tasik"
    ],
    "name:hye_x_preferred":[
        "\u0539\u0561\u057d\u056b\u056f"
    ],
    "name:ind_x_preferred":[
        "Tasik"
    ],
    "name:ita_x_preferred":[
        "Tasik"
    ],
    "name:kat_x_preferred":[
        "\u10d7\u10d0\u10e1\u10d8\u10d9\u10d8"
    ],
    "name:msa_x_preferred":[
        "Tasik"
    ],
    "name:sco_x_preferred":[
        "Tasik"
    ],
    "name:spa_x_preferred":[
        "Tasik"
    ],
    "name:vie_x_preferred":[
        "Tasik"
    ],
    "wof:lang_x_official":[
        "ind"
    ],
    "wof:lang_x_spoken":[
        "ind",
        "eng"
    ],
    "wof:name":"Tasik",
    "wof:placetype":"locality"
},
  "geometry": {"coordinates":[98.2602,3.7828],"type":"Point"}
}