{
  "type": "Feature",
  "properties": {
    "gn:admin1_code":"30.0",
    "gn:asciiname":"Cileungsir",
    "gn:country_code":"ID",
    "gn:dem":359,
    "gn:feature_class":"P",
    "gn:feature_code":"PPLA4",
    "gn:name":"Cileungsir",
    "gn:population":0,
    "gn:timezone":"Asia/Jakarta",
    "iso:country":"ID",
    "name:ind_x_preferred":[
        "Cileungsir"
    ],
    "name:und_x_variant":[
        "Tjileungsir"
    ],
    "wof:lang_x_official":[
        "ind"
    ],
    "wof:lang_x_spoken":[
        "ind",
        "eng"
    ],
    "wof:name":"Cileungsir",
    "wof:placetype":"locality"
},
  "geometry": {"coordinates":[108.48950000000001,-7.2051],"type":"Point"}
}