{
  "type": "Feature",
  "properties": {
    "gn:admin1_code":"30",
    "gn:asciiname":"Cilubang",
    "gn:country_code":"ID",
    "gn:dem":422,
    "gn:feature_class":"P",
    "gn:feature_code":"PPL",
    "gn:name":"Cilubang",
    "gn:population":0,
    "gn:timezone":"Asia/Jakarta",
    "iso:country":"ID",
    "name:ind_x_preferred":[
        "Cilubang"
    ],
    "wof:name":"Cilubang",
    "wof:placetype":"locality"
},
  "geometry": {"coordinates":[106.80138999999998,-6.91722],"type":"Point"}
}