{
  "type": "Feature",
  "properties": {
    "gn:admin1_code":"30",
    "gn:asciiname":"Asem",
    "gn:country_code":"ID",
    "gn:dem":63,
    "gn:feature_class":"P",
    "gn:feature_code":"PPL",
    "gn:name":"Asem",
    "gn:population":0,
    "gn:timezone":"Asia/Jakarta",
    "iso:country":"ID",
    "name:ara_x_preferred":[
        "\u0639\u0627\u0635\u0645"
    ],
    "name:ind_x_preferred":[
        "Asem"
    ],
    "name:nld_x_preferred":[
        "Asem"
    ],
    "name:ron_x_preferred":[
        "Asem"
    ],
    "name:urd_x_preferred":[
        "\u0639\u0627\u0635\u0645"
    ],
    "wof:lang_x_official":[
        "ind"
    ],
    "wof:lang_x_spoken":[
        "ind",
        "eng"
    ],
    "wof:name":"Asem",
    "wof:placetype":"locality"
},
  "geometry": {"coordinates":[108.6135,-6.8474],"type":"Point"}
}