{
  "type": "Feature",
  "properties": {
    "gn:admin1_code":"7",
    "gn:asciiname":"Dukuharen",
    "gn:country_code":"ID",
    "gn:dem":766,
    "gn:feature_class":"P",
    "gn:feature_code":"PPL",
    "gn:name":"Dukuharen",
    "gn:population":0,
    "gn:timezone":"Asia/Jakarta",
    "iso:country":"ID",
    "name:ind_x_preferred":[
        "Dukuharen"
    ],
    "wof:name":"Dukuharen",
    "wof:placetype":"locality"
},
  "geometry": {"coordinates":[109.18472,-7.13139],"type":"Point"}
}