{
  "type": "Feature",
  "properties": {
    "gn:admin1_code":"7.0",
    "gn:asciiname":"Kalitelu",
    "gn:country_code":"ID",
    "gn:dem":977,
    "gn:feature_class":"P",
    "gn:feature_code":"PPL",
    "gn:name":"Kalitelu",
    "gn:population":0,
    "gn:timezone":"Asia/Jakarta",
    "iso:country":"ID",
    "name:ind_x_preferred":[
        "Kalitelu"
    ],
    "wof:name":"Kalitelu",
    "wof:placetype":"locality"
},
  "geometry": {"coordinates":[109.87306,-7.31167],"type":"Point"}
}