{
  "type": "Feature",
  "properties": {
    "gn:admin1_code":"26",
    "gn:asciiname":"Negeri Bayu",
    "gn:country_code":"ID",
    "gn:dem":193,
    "gn:feature_class":"P",
    "gn:feature_code":"PPL",
    "gn:name":"Negeri Bayu",
    "gn:population":0,
    "gn:timezone":"Asia/Jakarta",
    "iso:country":"ID",
    "name:ind_x_preferred":[
        "Negeri Bayu"
    ],
    "name:und_x_variant":[
        "Nagurbaju"
    ],
    "wof:name":"Negeri Bayu",
    "wof:placetype":"locality"
},
  "geometry": {"coordinates":[99.03440000000001,3.1055],"type":"Point"}
}