{
  "type": "Feature",
  "properties": {
    "gn:admin1_code":"1.0",
    "gn:asciiname":"Tualangcut",
    "gn:country_code":"ID",
    "gn:dem":9,
    "gn:feature_class":"P",
    "gn:feature_code":"PPLA3",
    "gn:name":"Tualangcut",
    "gn:population":0,
    "gn:timezone":"Asia/Jakarta",
    "iso:country":"ID",
    "name:ind_x_preferred":[
        "Tualangcut"
    ],
    "name:und_x_variant":[
        "Toealang-Tjot",
        "Toealang-Tjoet",
        "Tualangtjut",
        "Tualancut",
        "Tualang Cut"
    ],
    "wof:lang_x_official":[
        "ind"
    ],
    "wof:lang_x_spoken":[
        "ind",
        "eng"
    ],
    "wof:name":"Tualangcut",
    "wof:placetype":"locality"
},
  "geometry": {"coordinates":[98.0722,4.4018],"type":"Point"}
}