{
  "type": "Feature",
  "properties": {
    "gn:admin1_code":"33.0",
    "gn:asciiname":"Beber",
    "gn:country_code":"ID",
    "gn:dem":222,
    "gn:feature_class":"P",
    "gn:feature_code":"PPL",
    "gn:name":"Beber",
    "gn:population":0,
    "gn:timezone":"Asia/Jakarta",
    "iso:country":"ID",
    "name:ceb_x_preferred":[
        "Beber"
    ],
    "name:deu_x_preferred":[
        "Beber"
    ],
    "name:ind_x_preferred":[
        "Beber"
    ],
    "name:nld_x_preferred":[
        "Beber"
    ],
    "name:swe_x_preferred":[
        "Beber"
    ],
    "wof:lang_x_official":[
        "ind"
    ],
    "wof:lang_x_spoken":[
        "ind",
        "eng"
    ],
    "wof:name":"Beber",
    "wof:placetype":"locality"
},
  "geometry": {"coordinates":[106.0569,-6.7399],"type":"Point"}
}