{
  "type": "Feature",
  "properties": {
    "gn:admin1_code":"18.0",
    "gn:asciiname":"Kurukodi",
    "gn:country_code":"ID",
    "gn:dem":452,
    "gn:feature_class":"P",
    "gn:feature_code":"PPL",
    "gn:name":"Kurukodi",
    "gn:population":0,
    "gn:timezone":"Asia/Makassar",
    "iso:country":"ID",
    "name:ind_x_preferred":[
        "Kurukodi"
    ],
    "wof:name":"Kurukodi",
    "wof:placetype":"locality"
},
  "geometry": {"coordinates":[119.4251,-9.6194],"type":"Point"}
}