{
  "type": "Feature",
  "properties": {
    "gn:admin1_code":"8",
    "gn:asciiname":"Taman",
    "gn:country_code":"ID",
    "gn:dem":50,
    "gn:feature_class":"P",
    "gn:feature_code":"PPL",
    "gn:name":"Taman",
    "gn:population":0,
    "gn:timezone":"Asia/Jakarta",
    "iso:country":"ID",
    "name:ind_x_preferred":[
        "Taman"
    ],
    "wof:name":"Taman",
    "wof:placetype":"locality"
},
  "geometry": {"coordinates":[114.04389999999999,-7.7217],"type":"Point"}
}