{
  "type": "Feature",
  "properties": {
    "gn:admin1_code":"8",
    "gn:asciiname":"Pohgiri Kulon",
    "gn:country_code":"ID",
    "gn:dem":36,
    "gn:feature_class":"P",
    "gn:feature_code":"PPL",
    "gn:name":"Pohgiri Kulon",
    "gn:population":0,
    "gn:timezone":"Asia/Jakarta",
    "iso:country":"ID",
    "name:ind_x_preferred":[
        "Pohgiri Kulon"
    ],
    "wof:name":"Pohgiri Kulon",
    "wof:placetype":"locality"
},
  "geometry": {"coordinates":[112.44540000000001,-7.511],"type":"Point"}
}