{
  "type": "Feature",
  "properties": {
    "gn:admin1_code":"8.0",
    "gn:asciiname":"Nagasareh",
    "gn:country_code":"ID",
    "gn:dem":63,
    "gn:feature_class":"P",
    "gn:feature_code":"PPL",
    "gn:name":"Nagasareh",
    "gn:population":0,
    "gn:timezone":"Asia/Jakarta",
    "iso:country":"ID",
    "name:ind_x_preferred":[
        "Nagasareh"
    ],
    "wof:name":"Nagasareh",
    "wof:placetype":"locality"
},
  "geometry": {"coordinates":[113.181,-6.9456],"type":"Point"}
}