{
  "type": "Feature",
  "properties": {
    "gn:admin1_code":"0.0",
    "gn:asciiname":"Tanjungwira",
    "gn:cc2":"ID",
    "gn:country_code":"ID",
    "gn:dem":12,
    "gn:feature_class":"P",
    "gn:feature_code":"PPL",
    "gn:name":"Tanjungwira",
    "gn:population":0,
    "gn:timezone":"Asia/Makassar",
    "iso:country":"ID",
    "name:und_x_variant":[
        "Tandjoengwira",
        "Tandjungwira",
        "Tanjungwira"
    ],
    "wof:name":"Tanjungwira",
    "wof:placetype":"locality"
},
  "geometry": {"coordinates":[117.43333,-0.05],"type":"Point"}
}