{
  "type": "Feature",
  "properties": {
    "gn:admin1_code":"8.0",
    "gn:asciiname":"Wonokoyo Wetan",
    "gn:country_code":"ID",
    "gn:dem":30,
    "gn:feature_class":"P",
    "gn:feature_code":"PPL",
    "gn:name":"Wonokoyo Wetan",
    "gn:population":0,
    "gn:timezone":"Asia/Jakarta",
    "iso:country":"ID",
    "name:ind_x_preferred":[
        "Wonokoyo Wetan"
    ],
    "wof:name":"Wonokoyo Wetan",
    "wof:placetype":"locality"
},
  "geometry": {"coordinates":[112.7204,-7.5932],"type":"Point"}
}