{
  "type": "Feature",
  "properties": {
    "gn:admin1_code":"7",
    "gn:asciiname":"Ngeduk",
    "gn:country_code":"ID",
    "gn:dem":352,
    "gn:feature_class":"P",
    "gn:feature_code":"PPL",
    "gn:name":"Ngeduk",
    "gn:population":0,
    "gn:timezone":"Asia/Jakarta",
    "iso:country":"ID",
    "name:ind_x_preferred":[
        "Ngeduk"
    ],
    "wof:name":"Ngeduk",
    "wof:placetype":"locality"
},
  "geometry": {"coordinates":[110.8627,-6.6897],"type":"Point"}
}