{
  "type": "Feature",
  "properties": {
    "gn:admin1_code":"15.0",
    "gn:asciiname":"Banjarnegeri",
    "gn:country_code":"ID",
    "gn:dem":128,
    "gn:feature_class":"P",
    "gn:feature_code":"PPL",
    "gn:name":"Banjarnegeri",
    "gn:population":0,
    "gn:timezone":"Asia/Jakarta",
    "iso:country":"ID",
    "name:ind_x_preferred":[
        "Banjarnegeri"
    ],
    "name:und_x_variant":[
        "Bandjarn\u0115g\u0115ri"
    ],
    "wof:name":"Banjarnegeri",
    "wof:placetype":"locality"
},
  "geometry": {"coordinates":[105.04452000000001,-5.41699],"type":"Point"}
}