{
  "type": "Feature",
  "properties": {
    "gn:admin1_code":"15.0",
    "gn:asciiname":"Sawangdaya",
    "gn:country_code":"ID",
    "gn:dem":11,
    "gn:feature_class":"P",
    "gn:feature_code":"PPL",
    "gn:name":"Sawangdaya",
    "gn:population":0,
    "gn:timezone":"Asia/Jakarta",
    "iso:country":"ID",
    "name:ind_x_preferred":[
        "Sawangdaya"
    ],
    "wof:name":"Sawangdaya",
    "wof:placetype":"locality"
},
  "geometry": {"coordinates":[104.78989,-5.76342],"type":"Point"}
}