{
  "type": "Feature",
  "properties": {
    "gn:admin1_code":"30",
    "gn:asciiname":"Komplek Pertamina Mundu",
    "gn:country_code":"ID",
    "gn:dem":7,
    "gn:feature_class":"P",
    "gn:feature_code":"PPL",
    "gn:name":"Komplek Pertamina Mundu",
    "gn:population":0,
    "gn:timezone":"Asia/Jakarta",
    "iso:country":"ID",
    "name:ind_x_preferred":[
        "Komplek Pertamina Mundu"
    ],
    "wof:name":"Komplek Pertamina Mundu",
    "wof:placetype":"locality"
},
  "geometry": {"coordinates":[108.42667,-6.48056],"type":"Point"}
}