{
  "type": "Feature",
  "properties": {
    "gn:admin1_code":"11.0",
    "gn:asciiname":"Lumut",
    "gn:country_code":"ID",
    "gn:dem":39,
    "gn:feature_class":"P",
    "gn:feature_code":"PPL",
    "gn:name":"Lumut",
    "gn:population":0,
    "gn:timezone":"Asia/Pontianak",
    "iso:country":"ID",
    "name:ind_x_preferred":[
        "Lumut"
    ],
    "wof:name":"Lumut",
    "wof:placetype":"locality"
},
  "geometry": {"coordinates":[111.79946,-0.05601],"type":"Point"}
}