{
  "type": "Feature",
  "properties": {
    "gn:admin1_code":"26",
    "gn:asciiname":"Gompulon",
    "gn:country_code":"ID",
    "gn:dem":514,
    "gn:feature_class":"P",
    "gn:feature_code":"PPL",
    "gn:name":"Gompulon",
    "gn:population":0,
    "gn:timezone":"Asia/Jakarta",
    "iso:country":"ID",
    "name:ind_x_preferred":[
        "Gompulon"
    ],
    "wof:name":"Gompulon",
    "wof:placetype":"locality"
},
  "geometry": {"coordinates":[98.8339,1.8225],"type":"Point"}
}