{
  "type": "Feature",
  "properties": {
    "gn:admin1_code":"17",
    "gn:asciiname":"Aba",
    "gn:country_code":"ID",
    "gn:dem":98,
    "gn:feature_class":"P",
    "gn:feature_code":"PPL",
    "gn:name":"Aba",
    "gn:population":0,
    "gn:timezone":"Asia/Makassar",
    "iso:country":"ID",
    "name:ara_x_preferred":[
        "\u0622\u0628\u0627"
    ],
    "name:bel_x_preferred":[
        "\u0410\u0431\u0430"
    ],
    "name:bre_x_preferred":[
        "Aba"
    ],
    "name:bul_x_preferred":[
        "\u0410\u0431\u0430"
    ],
    "name:cat_x_preferred":[
        "Aba"
    ],
    "name:ceb_x_preferred":[
        "Aba"
    ],
    "name:ces_x_preferred":[
        "Aba"
    ],
    "name:che_x_preferred":[
        "\u0410\u0431\u0430"
    ],
    "name:deu_x_preferred":[
        "Aba"
    ],
    "name:est_x_preferred":[
        "Aba"
    ],
    "name:fas_x_preferred":[
        "\u0622\u0628\u0627"
    ],
    "name:fin_x_preferred":[
        "Aba"
    ],
    "name:fra_x_preferred":[
        "Aba"
    ],
    "name:gla_x_preferred":[
        "Aba"
    ],
    "name:glg_x_preferred":[
        "Aba"
    ],
    "name:heb_x_preferred":[
        "\u05d0\u05d1\u05d0"
    ],
    "name:hrv_x_preferred":[
        "Aba"
    ],
    "name:hun_x_preferred":[
        "Aba"
    ],
    "name:hye_x_preferred":[
        "\u0531\u0562\u0561"
    ],
    "name:ind_x_preferred":[
        "Aba"
    ],
    "name:kat_x_preferred":[
        "\u10d0\u10d1\u10d0"
    ],
    "name:kor_x_preferred":[
        "\uc544\ubc14"
    ],
    "name:lit_x_preferred":[
        "Aba"
    ],
    "name:mlg_x_preferred":[
        "Aba"
    ],
    "name:nld_x_preferred":[
        "Aba"
    ],
    "name:nno_x_preferred":[
        "Aba"
    ],
    "name:nor_x_preferred":[
        "Aba"
    ],
    "name:pol_x_preferred":[
        "Aba"
    ],
    "name:por_x_preferred":[
        "Aba"
    ],
    "name:ron_x_preferred":[
        "Aba"
    ],
    "name:rus_x_preferred":[
        "\u0410\u0431\u0430"
    ],
    "name:slk_x_preferred":[
        "Aba"
    ],
    "name:srp_x_preferred":[
        "\u0410\u0431\u0430"
    ],
    "name:swe_x_preferred":[
        "Aba"
    ],
    "name:tur_x_preferred":[
        "Aba"
    ],
    "name:ukr_x_preferred":[
        "\u0410\u0431\u0430"
    ],
    "name:vie_x_preferred":[
        "A B\u00e1"
    ],
    "name:yor_x_preferred":[
        "Aba"
    ],
    "wof:name":"Aba",
    "wof:placetype":"locality"
},
  "geometry": {"coordinates":[116.2808,-8.7747],"type":"Point"}
}