{
  "type": "Feature",
  "properties": {
    "gn:admin1_code":"38",
    "gn:asciiname":"Raya",
    "gn:country_code":"ID",
    "gn:dem":854,
    "gn:feature_class":"P",
    "gn:feature_code":"PPL",
    "gn:name":"Raya",
    "gn:population":0,
    "gn:timezone":"Asia/Makassar",
    "iso:country":"ID",
    "name:bpy_x_preferred":[
        "\u09b0\u09be\u09af\u09bc\u09be"
    ],
    "name:ceb_x_preferred":[
        "Raya"
    ],
    "name:deu_x_preferred":[
        "Raya"
    ],
    "name:ind_x_preferred":[
        "Raya"
    ],
    "name:msa_x_preferred":[
        "Raya"
    ],
    "name:new_x_preferred":[
        "\u0930\u092f\u093e"
    ],
    "name:nld_x_preferred":[
        "Raya"
    ],
    "name:pol_x_preferred":[
        "Raya"
    ],
    "name:spa_x_preferred":[
        "Raya"
    ],
    "name:swe_x_preferred":[
        "Raya"
    ],
    "wof:lang_x_official":[
        "ind"
    ],
    "wof:lang_x_spoken":[
        "ind",
        "eng"
    ],
    "wof:name":"Raya",
    "wof:placetype":"locality"
},
  "geometry": {"coordinates":[119.7679,-3.1576],"type":"Point"}
}