{
  "type": "Feature",
  "properties": {
    "gn:admin1_code":"7.0",
    "gn:asciiname":"Kalibetung",
    "gn:country_code":"ID",
    "gn:dem":996,
    "gn:feature_class":"P",
    "gn:feature_code":"PPL",
    "gn:name":"Kalibetung",
    "gn:population":0,
    "gn:timezone":"Asia/Jakarta",
    "iso:country":"ID",
    "wof:name":"Kalibetung",
    "wof:placetype":"locality"
},
  "geometry": {"coordinates":[110.05694,-7.265],"type":"Point"}
}