{
  "type": "Feature",
  "properties": {
    "gn:country":"ID",
    "gn:fcode":"PPLA3",
    "gn:pop":0,
    "iso:country":"ID",
    "name:ind_x_preferred":[
        "Salawu"
    ],
    "name:unk_x_variant":[
        "Salawoe"
    ],
    "qs:name":"Salawu",
    "qs:photos_9r":0,
    "qs:photos_sr":0,
    "qs:pop_sr":"0",
    "wof:name":"Salawu",
    "wof:placetype":"locality",
    "wof:population":0
},
  "geometry": {"coordinates":[108.0325,-7.3755],"type":"Point"}
}