{
  "type": "Feature",
  "properties": {
    "gn:country":"ID",
    "gn:fcode":"ADM4",
    "gn:pop":0,
    "iso:country":"ID",
    "name:ind_x_preferred":[
        "Kelurahan Way Lunik"
    ],
    "name:unk_x_variant":[
        "Wal Tunik"
    ],
    "qs:name":"Kelurahan Way Lunik",
    "qs:photos_9r":0,
    "qs:photos_sr":0,
    "qs:pop_sr":"0",
    "wof:name":"Kelurahan Way Lunik",
    "wof:placetype":"localadmin",
    "wof:population":0
},
  "geometry": {"coordinates":[105.30928,-5.45014],"type":"Point"}
}