{
  "type": "Feature",
  "properties": {
    "gn:admin1_code":"1",
    "gn:asciiname":"Meunasah Ketapang",
    "gn:country_code":"ID",
    "gn:dem":5,
    "gn:feature_class":"P",
    "gn:feature_code":"PPL",
    "gn:name":"Meunasah Ketapang",
    "gn:population":0,
    "gn:timezone":"Asia/Jakarta",
    "iso:country":"ID",
    "name:ind_x_preferred":[
        "Meunasah Ketapang"
    ],
    "wof:name":"Meunasah Ketapang",
    "wof:placetype":"locality"
},
  "geometry": {"coordinates":[97.3108,5.0646],"type":"Point"}
}