{
  "type": "Feature",
  "properties": {
    "gn:admin1_code":"1.0",
    "gn:asciiname":"Lassihing",
    "gn:country_code":"ID",
    "gn:dem":11,
    "gn:feature_class":"P",
    "gn:feature_code":"PPL",
    "gn:name":"Lassihing",
    "gn:population":0,
    "gn:timezone":"Asia/Jakarta",
    "iso:country":"ID",
    "name:ind_x_preferred":[
        "Lassihing"
    ],
    "name:und_x_variant":[
        "Las\u00e9h\u00e9ng",
        "Lasihing",
        "Lasikin"
    ],
    "wof:lang_x_official":[
        "ind"
    ],
    "wof:lang_x_spoken":[
        "ind",
        "eng"
    ],
    "wof:name":"Lassihing",
    "wof:placetype":"locality"
},
  "geometry": {"coordinates":[96.3142,2.4225],"type":"Point"}
}