{
  "type": "Feature",
  "properties": {
    "gn:admin1_code":"18.0",
    "gn:asciiname":"Rara",
    "gn:country_code":"ID",
    "gn:dem":390,
    "gn:feature_class":"P",
    "gn:feature_code":"PPL",
    "gn:name":"Rara",
    "gn:population":0,
    "gn:timezone":"Asia/Makassar",
    "iso:country":"ID",
    "name:deu_x_preferred":[
        "Rara"
    ],
    "name:fra_x_preferred":[
        "Rara"
    ],
    "name:hat_x_preferred":[
        "Rara"
    ],
    "name:ind_x_preferred":[
        "Rara"
    ],
    "name:rus_x_preferred":[
        "\u0420\u0430\u0440\u0430"
    ],
    "wof:name":"Rara",
    "wof:placetype":"locality"
},
  "geometry": {"coordinates":[119.191,-9.5652],"type":"Point"}
}