{
  "type": "Feature",
  "properties": {
    "gn:admin1_code":"38",
    "gn:asciiname":"Lempangan",
    "gn:country_code":"ID",
    "gn:dem":942,
    "gn:feature_class":"P",
    "gn:feature_code":"PPL",
    "gn:name":"Lempangan",
    "gn:population":0,
    "gn:timezone":"Asia/Makassar",
    "iso:country":"ID",
    "name:ind_x_preferred":[
        "Lempangan"
    ],
    "wof:name":"Lempangan",
    "wof:placetype":"locality"
},
  "geometry": {"coordinates":[119.9314,-3.1264],"type":"Point"}
}