{
  "type": "Feature",
  "properties": {
    "gn:admin1_code":"18.0",
    "gn:asciiname":"Waipapa",
    "gn:country_code":"ID",
    "gn:dem":134,
    "gn:feature_class":"P",
    "gn:feature_code":"PPL",
    "gn:name":"Waipapa",
    "gn:population":0,
    "gn:timezone":"Asia/Makassar",
    "iso:country":"ID",
    "name:deu_x_preferred":[
        "Waipapa"
    ],
    "name:ind_x_preferred":[
        "Waipapa"
    ],
    "wof:name":"Waipapa",
    "wof:placetype":"locality"
},
  "geometry": {"coordinates":[123.0882,-8.3867],"type":"Point"}
}