{
  "type": "Feature",
  "properties": {
    "gn:admin1_code":"10.0",
    "gn:asciiname":"Bletuk",
    "gn:cc2":"ID",
    "gn:country_code":"ID",
    "gn:dem":116,
    "gn:feature_class":"P",
    "gn:feature_code":"PPL",
    "gn:name":"Bletuk",
    "gn:population":0,
    "gn:timezone":"Asia/Jakarta",
    "iso:country":"ID",
    "name:und_x_variant":[
        "Betuk",
        "Bletuk"
    ],
    "wof:name":"Bletuk",
    "wof:placetype":"locality"
},
  "geometry": {"coordinates":[110.26778,-7.7575],"type":"Point"}
}