{
  "type": "Feature",
  "properties": {
    "gn:admin1_code":"38",
    "gn:asciiname":"Bancee",
    "gn:country_code":"ID",
    "gn:dem":289,
    "gn:feature_class":"P",
    "gn:feature_code":"PPL",
    "gn:name":"Bancee",
    "gn:population":0,
    "gn:timezone":"Asia/Makassar",
    "iso:country":"ID",
    "name:ind_x_preferred":[
        "Bancee"
    ],
    "wof:name":"Bancee",
    "wof:placetype":"locality"
},
  "geometry": {"coordinates":[119.947,-4.8177],"type":"Point"}
}