{
  "type": "Feature",
  "properties": {
    "gn:admin1_code":"18.0",
    "gn:asciiname":"Ketoka",
    "gn:country_code":"ID",
    "gn:dem":527,
    "gn:feature_class":"P",
    "gn:feature_code":"PPL",
    "gn:name":"Ketoka",
    "gn:population":0,
    "gn:timezone":"Asia/Makassar",
    "iso:country":"ID",
    "name:ind_x_preferred":[
        "Ketoka"
    ],
    "wof:name":"Ketoka",
    "wof:placetype":"locality"
},
  "geometry": {"coordinates":[119.46259999999999,-9.5416],"type":"Point"}
}