{
  "type": "Feature",
  "properties": {
    "gn:admin1_code":"7.0",
    "gn:asciiname":"Lebak Timur",
    "gn:country_code":"ID",
    "gn:dem":30,
    "gn:feature_class":"P",
    "gn:feature_code":"PPL",
    "gn:name":"Lebak Timur",
    "gn:population":0,
    "gn:timezone":"Asia/Jakarta",
    "iso:country":"ID",
    "name:ind_x_preferred":[
        "Lebak Timur"
    ],
    "wof:name":"Lebak Timur",
    "wof:placetype":"locality"
},
  "geometry": {"coordinates":[109.10389000000001,-7.53417],"type":"Point"}
}