{
  "type": "Feature",
  "properties": {
    "gn:admin1_code":"26",
    "gn:asciiname":"Patal",
    "gn:country_code":"ID",
    "gn:dem":768,
    "gn:feature_class":"P",
    "gn:feature_code":"PPL",
    "gn:name":"Patal",
    "gn:population":0,
    "gn:timezone":"Asia/Jakarta",
    "iso:country":"ID",
    "name:fas_x_preferred":[
        "\u067e\u0627\u062a\u0644"
    ],
    "name:ind_x_preferred":[
        "Patal"
    ],
    "wof:lang_x_official":[
        "ind"
    ],
    "wof:lang_x_spoken":[
        "ind",
        "eng"
    ],
    "wof:name":"Patal",
    "wof:placetype":"locality"
},
  "geometry": {"coordinates":[99.0296,2.7923],"type":"Point"}
}