{
  "type": "Feature",
  "properties": {
    "gn:admin1_code":"7",
    "gn:asciiname":"Jarak",
    "gn:country_code":"ID",
    "gn:dem":337,
    "gn:feature_class":"P",
    "gn:feature_code":"PPL",
    "gn:name":"Jarak",
    "gn:population":0,
    "gn:timezone":"Asia/Jakarta",
    "iso:country":"ID",
    "name:ind_x_preferred":[
        "Jarak"
    ],
    "wof:name":"Jarak",
    "wof:placetype":"locality"
},
  "geometry": {"coordinates":[111.03333000000001,-7.80528],"type":"Point"}
}