{
  "type": "Feature",
  "properties": {
    "gn:admin1_code":"18.0",
    "gn:asciiname":"Palindi",
    "gn:country_code":"ID",
    "gn:dem":383,
    "gn:feature_class":"P",
    "gn:feature_code":"PPL",
    "gn:name":"Palindi",
    "gn:population":0,
    "gn:timezone":"Asia/Makassar",
    "iso:country":"ID",
    "name:ind_x_preferred":[
        "Palindi"
    ],
    "wof:name":"Palindi",
    "wof:placetype":"locality"
},
  "geometry": {"coordinates":[119.9007,-9.8542],"type":"Point"}
}