{
  "type": "Feature",
  "properties": {
    "gn:admin1_code":"30",
    "gn:asciiname":"Patrol",
    "gn:country_code":"ID",
    "gn:dem":1267,
    "gn:feature_class":"P",
    "gn:feature_code":"PPL",
    "gn:name":"Patrol",
    "gn:population":0,
    "gn:timezone":"Asia/Jakarta",
    "iso:country":"ID",
    "name:ind_x_preferred":[
        "Patrol"
    ],
    "wof:name":"Patrol",
    "wof:placetype":"locality"
},
  "geometry": {"coordinates":[107.42449999999999,-7.0803],"type":"Point"}
}