{
  "type": "Feature",
  "properties": {
    "gn:admin1_code":"30",
    "gn:asciiname":"Nanggerang Barat",
    "gn:country_code":"ID",
    "gn:dem":120,
    "gn:feature_class":"P",
    "gn:feature_code":"PPL",
    "gn:name":"Nanggerang Barat",
    "gn:population":0,
    "gn:timezone":"Asia/Jakarta",
    "iso:country":"ID",
    "wof:name":"Nanggerang Barat",
    "wof:placetype":"locality"
},
  "geometry": {"coordinates":[106.77778000000001,-6.45944],"type":"Point"}
}