{
  "type": "Feature",
  "properties": {
    "gn:admin1_code":"30",
    "gn:asciiname":"Pasarean",
    "gn:cc2":"ID",
    "gn:country_code":"ID",
    "gn:dem":847,
    "gn:feature_class":"P",
    "gn:feature_code":"PPL",
    "gn:name":"Pasarean",
    "gn:population":0,
    "gn:timezone":"Asia/Jakarta",
    "iso:country":"ID",
    "name:und_x_variant":[
        "Pasareah",
        "Pasarean"
    ],
    "wof:lang_x_official":[
        "ind"
    ],
    "wof:lang_x_spoken":[
        "ind",
        "eng"
    ],
    "wof:name":"Pasarean",
    "wof:placetype":"locality"
},
  "geometry": {"coordinates":[107.56722000000001,-7.09167],"type":"Point"}
}