{
  "type": "Feature",
  "properties": {
    "gn:admin1_code":"07",
    "gn:asciiname":"Sikembang",
    "gn:country_code":"ID",
    "gn:dem":595,
    "gn:feature_class":"P",
    "gn:feature_code":"PPL",
    "gn:name":"Sikembang",
    "gn:population":0,
    "gn:timezone":"Asia/Jakarta",
    "iso:country":"ID",
    "wof:name":"Sikembang",
    "wof:placetype":"locality"
},
  "geometry": {"coordinates":[110.25360999999999,-7.16444],"type":"Point"}
}