{
  "type": "Feature",
  "properties": {
    "gn:admin1_code":"08",
    "gn:asciiname":"Krajan Gebangan",
    "gn:country_code":"ID",
    "gn:dem":13,
    "gn:feature_class":"P",
    "gn:feature_code":"PPLA4",
    "gn:name":"Krajan Gebangan",
    "gn:population":0,
    "gn:timezone":"Asia/Jakarta",
    "iso:country":"ID",
    "name:ind_x_preferred":[
        "Krajan Gebangan"
    ],
    "name:ind_x_variant":[
        "Krajan"
    ],
    "name:und_x_variant":[
        "Gebangan-wetan"
    ],
    "wof:name":"Krajan Gebangan",
    "wof:placetype":"locality"
},
  "geometry": {"coordinates":[114.06440000000001,-7.6752],"type":"Point"}
}