{
  "type": "Feature",
  "properties": {
    "gn:admin1_code":"1",
    "gn:asciiname":"Blang Kumat Baroh",
    "gn:country_code":"ID",
    "gn:dem":51,
    "gn:feature_class":"P",
    "gn:feature_code":"PPL",
    "gn:name":"Blang Kumat Baroh",
    "gn:population":0,
    "gn:timezone":"Asia/Jakarta",
    "iso:country":"ID",
    "name:ind_x_preferred":[
        "Blang Kumat Baroh"
    ],
    "wof:lang_x_official":[
        "ind"
    ],
    "wof:lang_x_spoken":[
        "ind",
        "eng"
    ],
    "wof:name":"Blang Kumat Baroh",
    "wof:placetype":"locality"
},
  "geometry": {"coordinates":[95.9495,5.2282],"type":"Point"}
}