{
  "type": "Feature",
  "properties": {
    "gn:admin1_code":"7.0",
    "gn:asciiname":"Tempurejo",
    "gn:country_code":"ID",
    "gn:dem":28,
    "gn:feature_class":"P",
    "gn:feature_code":"PPL",
    "gn:name":"Tempurejo",
    "gn:population":0,
    "gn:timezone":"Asia/Jakarta",
    "iso:country":"ID",
    "name:ind_x_preferred":[
        "Tempurejo"
    ],
    "wof:name":"Tempurejo",
    "wof:placetype":"locality"
},
  "geometry": {"coordinates":[111.4221,-6.7766],"type":"Point"}
}