{
  "type": "Feature",
  "properties": {
    "gn:admin1_code":"30.0",
    "gn:asciiname":"Ciinjuk",
    "gn:country_code":"ID",
    "gn:dem":475,
    "gn:feature_class":"P",
    "gn:feature_code":"PPLA4",
    "gn:name":"Ciinjuk",
    "gn:population":0,
    "gn:timezone":"Asia/Jakarta",
    "iso:country":"ID",
    "name:ind_x_preferred":[
        "Ciinjuk"
    ],
    "name:und_x_variant":[
        "Tjiindjoek"
    ],
    "wof:lang_x_official":[
        "ind"
    ],
    "wof:lang_x_spoken":[
        "ind",
        "eng"
    ],
    "wof:name":"Ciinjuk",
    "wof:placetype":"locality"
},
  "geometry": {"coordinates":[108.18680000000001,-7.2069],"type":"Point"}
}