{
  "type": "Feature",
  "properties": {
    "gn:admin1_code":"15.0",
    "gn:asciiname":"Labuhanratu",
    "gn:country_code":"ID",
    "gn:dem":15,
    "gn:feature_class":"P",
    "gn:feature_code":"PPL",
    "gn:name":"Labuhanratu",
    "gn:population":0,
    "gn:timezone":"Asia/Jakarta",
    "iso:country":"ID",
    "name:ind_x_preferred":[
        "Labuhanratu"
    ],
    "wof:name":"Labuhanratu",
    "wof:placetype":"locality"
},
  "geometry": {"coordinates":[105.28716,-4.29355],"type":"Point"}
}