{
  "type": "Feature",
  "properties": {
    "gn:admin1_code":"18.0",
    "gn:asciiname":"Edekalada",
    "gn:country_code":"ID",
    "gn:dem":407,
    "gn:feature_class":"P",
    "gn:feature_code":"PPL",
    "gn:name":"Edekalada",
    "gn:population":0,
    "gn:timezone":"Asia/Makassar",
    "iso:country":"ID",
    "name:ind_x_preferred":[
        "Edekalada"
    ],
    "wof:name":"Edekalada",
    "wof:placetype":"locality"
},
  "geometry": {"coordinates":[119.20140000000001,-9.5988],"type":"Point"}
}