{
  "type": "Feature",
  "properties": {
    "gn:admin1_code":"07",
    "gn:asciiname":"Bulusan",
    "gn:country_code":"ID",
    "gn:dem":207,
    "gn:feature_class":"P",
    "gn:feature_code":"PPL",
    "gn:name":"Bulusan",
    "gn:population":0,
    "gn:timezone":"Asia/Jakarta",
    "iso:country":"ID",
    "name:ind_x_preferred":[
        "Bulusan"
    ],
    "wof:name":"Bulusan",
    "wof:placetype":"locality"
},
  "geometry": {"coordinates":[110.44410000000001,-7.061],"type":"Point"}
}