{
  "type": "Feature",
  "properties": {
    "gn:admin1_code":"7.0",
    "gn:asciiname":"Kalimongko",
    "gn:country_code":"ID",
    "gn:dem":683,
    "gn:feature_class":"P",
    "gn:feature_code":"PPL",
    "gn:name":"Kalimongko",
    "gn:population":0,
    "gn:timezone":"Asia/Jakarta",
    "iso:country":"ID",
    "wof:name":"Kalimongko",
    "wof:placetype":"locality"
},
  "geometry": {"coordinates":[110.14667,-7.45389],"type":"Point"}
}