{
  "type": "Feature",
  "properties": {
    "gn:admin1_code":"38.0",
    "gn:asciiname":"Pajalesang",
    "gn:country_code":"ID",
    "gn:dem":26,
    "gn:feature_class":"P",
    "gn:feature_code":"PPL",
    "gn:name":"Pajalesang",
    "gn:population":0,
    "gn:timezone":"Asia/Makassar",
    "iso:country":"ID",
    "name:ind_x_preferred":[
        "Pajalesang"
    ],
    "wof:name":"Pajalesang",
    "wof:placetype":"locality"
},
  "geometry": {"coordinates":[120.3296,-4.6229],"type":"Point"}
}