{
  "type": "Feature",
  "properties": {
    "gn:admin1_code":"30",
    "gn:asciiname":"Cimanglid",
    "gn:country_code":"ID",
    "gn:dem":542,
    "gn:feature_class":"P",
    "gn:feature_code":"PPL",
    "gn:name":"Cimanglid",
    "gn:population":0,
    "gn:timezone":"Asia/Jakarta",
    "iso:country":"ID",
    "name:ind_x_preferred":[
        "Cimanglid"
    ],
    "wof:name":"Cimanglid",
    "wof:placetype":"locality"
},
  "geometry": {"coordinates":[107.70694,-6.705],"type":"Point"}
}