{
  "type": "Feature",
  "properties": {
    "gn:admin1_code":"1",
    "gn:asciiname":"Blangtampoh",
    "gn:country_code":"ID",
    "gn:dem":640,
    "gn:feature_class":"P",
    "gn:feature_code":"PPL",
    "gn:name":"Blangtampoh",
    "gn:population":0,
    "gn:timezone":"Asia/Jakarta",
    "iso:country":"ID",
    "name:ind_x_preferred":[
        "Blangtampoh"
    ],
    "wof:name":"Blangtampoh",
    "wof:placetype":"locality"
},
  "geometry": {"coordinates":[96.53870000000001,4.4559],"type":"Point"}
}