{
  "type": "Feature",
  "properties": {
    "gn:admin1_code":"8",
    "gn:asciiname":"Bunut",
    "gn:country_code":"ID",
    "gn:dem":491,
    "gn:feature_class":"P",
    "gn:feature_code":"PPL",
    "gn:name":"Bunut",
    "gn:population":0,
    "gn:timezone":"Asia/Jakarta",
    "iso:country":"ID",
    "name:ceb_x_preferred":[
        "Bunut"
    ],
    "name:ind_x_preferred":[
        "Bunut"
    ],
    "name:nld_x_preferred":[
        "Bunut"
    ],
    "name:swe_x_preferred":[
        "Bunut"
    ],
    "wof:name":"Bunut",
    "wof:placetype":"locality"
},
  "geometry": {"coordinates":[112.64109999999999,-7.9059],"type":"Point"}
}