{
  "type": "Feature",
  "properties": {
    "gn:admin1_code":"8.0",
    "gn:asciiname":"Dukuh",
    "gn:country_code":"ID",
    "gn:dem":18,
    "gn:feature_class":"P",
    "gn:feature_code":"PPL",
    "gn:name":"Dukuh",
    "gn:population":0,
    "gn:timezone":"Asia/Jakarta",
    "iso:country":"ID",
    "name:ind_x_preferred":[
        "Dukuh"
    ],
    "name:und_x_variant":[
        "Doekoeh",
        "Doekoehagoeng"
    ],
    "wof:name":"Dukuh",
    "wof:placetype":"locality"
},
  "geometry": {"coordinates":[112.429,-7.1804],"type":"Point"}
}