{
  "type": "Feature",
  "properties": {
    "gn:admin1_code":"7",
    "gn:asciiname":"Ngembongan",
    "gn:country_code":"ID",
    "gn:dem":320,
    "gn:feature_class":"P",
    "gn:feature_code":"PPL",
    "gn:name":"Ngembongan",
    "gn:population":0,
    "gn:timezone":"Asia/Jakarta",
    "iso:country":"ID",
    "name:ind_x_preferred":[
        "Ngembongan"
    ],
    "wof:name":"Ngembongan",
    "wof:placetype":"locality"
},
  "geometry": {"coordinates":[111.13916999999999,-7.86667],"type":"Point"}
}