{
  "type": "Feature",
  "properties": {
    "gn:admin1_code":"18.0",
    "gn:asciiname":"Galumareda",
    "gn:country_code":"ID",
    "gn:dem":650,
    "gn:feature_class":"P",
    "gn:feature_code":"PPL",
    "gn:name":"Galumareda",
    "gn:population":0,
    "gn:timezone":"Asia/Makassar",
    "iso:country":"ID",
    "name:ind_x_preferred":[
        "Galumareda"
    ],
    "wof:name":"Galumareda",
    "wof:placetype":"locality"
},
  "geometry": {"coordinates":[119.43429999999999,-9.5389],"type":"Point"}
}