{
  "type": "Feature",
  "properties": {
    "gn:admin1_code":"26",
    "gn:asciiname":"Donasari",
    "gn:country_code":"ID",
    "gn:dem":89,
    "gn:feature_class":"P",
    "gn:feature_code":"PPL",
    "gn:name":"Donasari",
    "gn:population":0,
    "gn:timezone":"Asia/Jakarta",
    "iso:country":"ID",
    "name:ind_x_preferred":[
        "Donasari"
    ],
    "wof:name":"Donasari",
    "wof:placetype":"locality"
},
  "geometry": {"coordinates":[98.3121,3.4688],"type":"Point"}
}