{
  "type": "Feature",
  "properties": {
    "gn:admin1_code":"30",
    "gn:asciiname":"Pejagan",
    "gn:cc2":"ID",
    "gn:country_code":"ID",
    "gn:dem":18,
    "gn:feature_class":"P",
    "gn:feature_code":"PPL",
    "gn:name":"Pejagan",
    "gn:population":0,
    "gn:timezone":"Asia/Jakarta",
    "iso:country":"ID",
    "name:und_x_variant":[
        "Pajagan",
        "Pedjagan",
        "Pejagan"
    ],
    "wof:name":"Pejagan",
    "wof:placetype":"locality"
},
  "geometry": {"coordinates":[106.37639,-6.20833],"type":"Point"}
}