{
  "type": "Feature",
  "properties": {
    "gn:admin1_code":"07",
    "gn:asciiname":"Ngrapah",
    "gn:country_code":"ID",
    "gn:dem":195,
    "gn:feature_class":"P",
    "gn:feature_code":"PPL",
    "gn:name":"Ngrapah",
    "gn:population":0,
    "gn:timezone":"Asia/Jakarta",
    "iso:country":"ID",
    "wof:name":"Ngrapah",
    "wof:placetype":"locality"
},
  "geometry": {"coordinates":[110.96193999999998,-7.63056],"type":"Point"}
}