{
  "type": "Feature",
  "properties": {
    "gn:admin1_code":"30.0",
    "gn:asciiname":"Mekarsari",
    "gn:country_code":"ID",
    "gn:dem":242,
    "gn:feature_class":"P",
    "gn:feature_code":"PPL",
    "gn:name":"Mekarsari",
    "gn:population":0,
    "gn:timezone":"Asia/Jakarta",
    "iso:country":"ID",
    "name:ind_x_preferred":[
        "Mekarsari"
    ],
    "wof:name":"Mekarsari",
    "wof:placetype":"locality"
},
  "geometry": {"coordinates":[106.5656,-7.2595],"type":"Point"}
}