{
  "type": "Feature",
  "properties": {
    "gn:admin1_code":"0.0",
    "gn:asciiname":"Petak-lor",
    "gn:country_code":"ID",
    "gn:dem":90,
    "gn:feature_class":"P",
    "gn:feature_code":"PPL",
    "gn:name":"Petak-lor",
    "gn:population":0,
    "gn:timezone":"Asia/Jakarta",
    "iso:country":"ID",
    "wof:name":"Petak-lor",
    "wof:placetype":"locality"
},
  "geometry": {"coordinates":[111.46666999999999,-7.16667],"type":"Point"}
}