{
  "type": "Feature",
  "properties": {
    "gn:admin1_code":"18.0",
    "gn:asciiname":"Kandaghutana",
    "gn:country_code":"ID",
    "gn:dem":66,
    "gn:feature_class":"P",
    "gn:feature_code":"PPL",
    "gn:name":"Kandaghutana",
    "gn:population":0,
    "gn:timezone":"Asia/Makassar",
    "iso:country":"ID",
    "name:ind_x_preferred":[
        "Kandaghutana"
    ],
    "wof:name":"Kandaghutana",
    "wof:placetype":"locality"
},
  "geometry": {"coordinates":[118.9817,-9.5366],"type":"Point"}
}