{
  "type": "Feature",
  "properties": {
    "gn:admin1_code":"0.0",
    "gn:asciiname":"Bojong",
    "gn:cc2":"ID",
    "gn:country_code":"ID",
    "gn:dem":643,
    "gn:feature_class":"P",
    "gn:feature_code":"PPL",
    "gn:name":"Bojong",
    "gn:population":0,
    "gn:timezone":"Asia/Jakarta",
    "iso:country":"ID",
    "name:ind_x_preferred":[
        "Bojong"
    ],
    "name:und_x_variant":[
        "Bodjong",
        "Bojong"
    ],
    "wof:lang_x_official":[
        "ind"
    ],
    "wof:lang_x_spoken":[
        "ind",
        "eng"
    ],
    "wof:name":"Bojong",
    "wof:placetype":"locality"
},
  "geometry": {"coordinates":[108.46666999999999,-6.88333],"type":"Point"}
}