{
  "type": "Feature",
  "properties": {
    "gn:admin1_code":"8",
    "gn:asciiname":"Parang-parang",
    "gn:country_code":"ID",
    "gn:dem":1054,
    "gn:feature_class":"P",
    "gn:feature_code":"PPL",
    "gn:name":"Parang-parang",
    "gn:population":0,
    "gn:timezone":"Asia/Jakarta",
    "iso:country":"ID",
    "name:ind_x_preferred":[
        "Parang-parang"
    ],
    "wof:name":"Parang-parang",
    "wof:placetype":"locality"
},
  "geometry": {"coordinates":[112.8459,-8.1431],"type":"Point"}
}