{
  "type": "Feature",
  "properties": {
    "gn:admin1_code":"30",
    "gn:asciiname":"Haurkolot Dua",
    "gn:country_code":"ID",
    "gn:dem":27,
    "gn:feature_class":"P",
    "gn:feature_code":"PPL",
    "gn:name":"Haurkolot Dua",
    "gn:population":0,
    "gn:timezone":"Asia/Jakarta",
    "iso:country":"ID",
    "name:ind_x_preferred":[
        "Haurkolot Dua"
    ],
    "wof:name":"Haurkolot Dua",
    "wof:placetype":"locality"
},
  "geometry": {"coordinates":[107.94722,-6.47139],"type":"Point"}
}