{
  "type": "Feature",
  "properties": {
    "gn:admin1_code":"8.0",
    "gn:asciiname":"Ngeluk",
    "gn:country_code":"ID",
    "gn:dem":106,
    "gn:feature_class":"P",
    "gn:feature_code":"PPL",
    "gn:name":"Ngeluk",
    "gn:population":0,
    "gn:timezone":"Asia/Jakarta",
    "iso:country":"ID",
    "name:ind_x_preferred":[
        "Ngeluk"
    ],
    "wof:name":"Ngeluk",
    "wof:placetype":"locality"
},
  "geometry": {"coordinates":[111.422,-7.9019],"type":"Point"}
}