{
  "type": "Feature",
  "properties": {
    "gn:admin1_code":"7",
    "gn:asciiname":"Wonotirto",
    "gn:country_code":"ID",
    "gn:dem":688,
    "gn:feature_class":"P",
    "gn:feature_code":"PPL",
    "gn:name":"Wonotirto",
    "gn:population":0,
    "gn:timezone":"Asia/Jakarta",
    "iso:country":"ID",
    "name:ind_x_preferred":[
        "Wonotirto"
    ],
    "wof:name":"Wonotirto",
    "wof:placetype":"locality"
},
  "geometry": {"coordinates":[109.9714,-7.0931],"type":"Point"}
}