{
  "type": "Feature",
  "properties": {
    "gn:admin1_code":"30",
    "gn:asciiname":"Babakanmenteng",
    "gn:country_code":"ID",
    "gn:dem":83,
    "gn:feature_class":"P",
    "gn:feature_code":"PPL",
    "gn:name":"Babakanmenteng",
    "gn:population":0,
    "gn:timezone":"Asia/Jakarta",
    "iso:country":"ID",
    "name:ind_x_preferred":[
        "Babakanmenteng"
    ],
    "wof:name":"Babakanmenteng",
    "wof:placetype":"locality"
},
  "geometry": {"coordinates":[107.20694,-6.52028],"type":"Point"}
}