{
  "type": "Feature",
  "properties": {
    "gn:admin1_code":"1.0",
    "gn:asciiname":"Kruengraya",
    "gn:country_code":"ID",
    "gn:dem":5,
    "gn:feature_class":"P",
    "gn:feature_code":"PPLA3",
    "gn:name":"Kruengraya",
    "gn:population":0,
    "gn:timezone":"Asia/Jakarta",
    "iso:country":"ID",
    "name:ind_x_preferred":[
        "Kruengraya"
    ],
    "name:und_x_variant":[
        "Kruengraja",
        "Kroe\u00ebngraja",
        "Malhayati Port"
    ],
    "wof:lang_x_official":[
        "ind"
    ],
    "wof:lang_x_spoken":[
        "ind",
        "eng"
    ],
    "wof:name":"Kruengraya",
    "wof:placetype":"locality"
},
  "geometry": {"coordinates":[95.5145,5.5895],"type":"Point"}
}