{
  "type": "Feature",
  "properties": {
    "gn:admin1_code":"18.0",
    "gn:asciiname":"Abila",
    "gn:country_code":"ID",
    "gn:dem":16,
    "gn:feature_class":"P",
    "gn:feature_code":"PPL",
    "gn:name":"Abila",
    "gn:population":0,
    "gn:timezone":"Asia/Makassar",
    "iso:country":"ID",
    "name:ind_x_preferred":[
        "Abila"
    ],
    "wof:name":"Abila",
    "wof:placetype":"locality"
},
  "geometry": {"coordinates":[124.32599999999999,-8.284],"type":"Point"}
}