{
  "type": "Feature",
  "properties": {
    "gn:admin1_code":"31.0",
    "gn:asciiname":"Lobo",
    "gn:country_code":"ID",
    "gn:dem":10,
    "gn:feature_class":"P",
    "gn:feature_code":"PPL",
    "gn:name":"Lobo",
    "gn:population":0,
    "gn:timezone":"Asia/Makassar",
    "iso:country":"ID",
    "name:ceb_x_preferred":[
        "Lobo"
    ],
    "name:deu_x_preferred":[
        "Lobo"
    ],
    "name:epo_x_preferred":[
        "Lobo"
    ],
    "name:fin_x_preferred":[
        "Lobo"
    ],
    "name:fra_x_preferred":[
        "Lobo"
    ],
    "name:glg_x_preferred":[
        "Lobo"
    ],
    "name:ido_x_preferred":[
        "Lobo"
    ],
    "name:ind_x_preferred":[
        "Lobo"
    ],
    "name:ita_x_preferred":[
        "Lobo"
    ],
    "name:nld_x_preferred":[
        "Lobo"
    ],
    "name:pol_x_preferred":[
        "Lobo"
    ],
    "name:por_x_preferred":[
        "Lobo"
    ],
    "name:rus_x_preferred":[
        "\u041b\u043e\u0431\u043e"
    ],
    "name:spa_x_preferred":[
        "Lobo"
    ],
    "name:swe_x_preferred":[
        "Lobo"
    ],
    "name:tgl_x_preferred":[
        "Lobo"
    ],
    "name:tha_x_preferred":[
        "\u0e42\u0e25\u0e42\u0e1a"
    ],
    "wof:lang_x_official":[
        "ind"
    ],
    "wof:lang_x_spoken":[
        "ind",
        "eng"
    ],
    "wof:name":"Lobo",
    "wof:placetype":"locality"
},
  "geometry": {"coordinates":[126.72226999999999,4.2674],"type":"Point"}
}