{
  "type": "Feature",
  "properties": {
    "gn:admin1_code":"31.0",
    "gn:asciiname":"Lobo",
    "gn:country_code":"ID",
    "gn:dem":10,
    "gn:feature_class":"P",
    "gn:feature_code":"PPL",
    "gn:name":"Lobo",
    "gn:population":0,
    "gn:timezone":"Asia/Makassar",
    "iso:country":"ID",
    "name:ind_x_preferred":[
        "Lobo"
    ],
    "wof:name":"Lobo",
    "wof:placetype":"locality"
},
  "geometry": {"coordinates":[126.72226999999999,4.2674],"type":"Point"}
}