{
  "type": "Feature",
  "properties": {
    "gn:admin1_code":"30.0",
    "gn:asciiname":"Lebakwangi",
    "gn:cc2":"ID",
    "gn:country_code":"ID",
    "gn:dem":680,
    "gn:feature_class":"P",
    "gn:feature_code":"PPL",
    "gn:name":"Lebakwangi",
    "gn:population":0,
    "gn:timezone":"Asia/Jakarta",
    "iso:country":"ID",
    "name:und_x_variant":[
        "Lebakwangi 2",
        "Lebakwangi Dua",
        "Lebakwangi"
    ],
    "wof:name":"Lebakwangi",
    "wof:placetype":"locality"
},
  "geometry": {"coordinates":[107.54389,-7.0175],"type":"Point"}
}