{
  "type": "Feature",
  "properties": {
    "gn:admin1_code":"37",
    "gn:asciiname":"Kotatengah",
    "gn:country_code":"ID",
    "gn:dem":50,
    "gn:feature_class":"P",
    "gn:feature_code":"PPL",
    "gn:name":"Kotatengah",
    "gn:population":0,
    "gn:timezone":"Asia/Jakarta",
    "iso:country":"ID",
    "name:ind_x_preferred":[
        "Kotatengah"
    ],
    "wof:name":"Kotatengah",
    "wof:placetype":"locality"
},
  "geometry": {"coordinates":[100.62990000000001,0.822],"type":"Point"}
}