{
  "type": "Feature",
  "properties": {
    "gn:admin1_code":"7.0",
    "gn:asciiname":"Sijenggung",
    "gn:country_code":"ID",
    "gn:dem":530,
    "gn:feature_class":"P",
    "gn:feature_code":"PPL",
    "gn:name":"Sijenggung",
    "gn:population":0,
    "gn:timezone":"Asia/Jakarta",
    "iso:country":"ID",
    "name:ind_x_preferred":[
        "Sijenggung"
    ],
    "wof:name":"Sijenggung",
    "wof:placetype":"locality"
},
  "geometry": {"coordinates":[109.66194,-7.29694],"type":"Point"}
}