{
  "type": "Feature",
  "properties": {
    "gn:admin1_code":"35.0",
    "gn:asciiname":"Penyak",
    "gn:country_code":"ID",
    "gn:dem":5,
    "gn:feature_class":"P",
    "gn:feature_code":"PPL",
    "gn:name":"Penyak",
    "gn:population":0,
    "gn:timezone":"Asia/Jakarta",
    "iso:country":"ID",
    "name:und_x_variant":[
        "Penjak",
        "Penyak"
    ],
    "wof:name":"Penyak",
    "wof:placetype":"locality"
},
  "geometry": {"coordinates":[106.29548,-2.41988],"type":"Point"}
}