{
  "type": "Feature",
  "properties": {
    "gn:admin1_code":"7",
    "gn:asciiname":"Kayuapu Wetan",
    "gn:country_code":"ID",
    "gn:dem":53,
    "gn:feature_class":"P",
    "gn:feature_code":"PPL",
    "gn:name":"Kayuapu Wetan",
    "gn:population":0,
    "gn:timezone":"Asia/Jakarta",
    "iso:country":"ID",
    "name:ind_x_preferred":[
        "Kayuapu Wetan"
    ],
    "wof:name":"Kayuapu Wetan",
    "wof:placetype":"locality"
},
  "geometry": {"coordinates":[110.879,-6.7758],"type":"Point"}
}