{
  "type": "Feature",
  "properties": {
    "gn:admin1_code":"38",
    "gn:asciiname":"Goyang",
    "gn:country_code":"ID",
    "gn:dem":96,
    "gn:feature_class":"P",
    "gn:feature_code":"PPL",
    "gn:name":"Goyang",
    "gn:population":0,
    "gn:timezone":"Asia/Makassar",
    "iso:country":"ID",
    "name:afr_x_preferred":[
        "Goyang"
    ],
    "name:ara_x_preferred":[
        "\u063a\u0648\u064a\u0627\u0646\u063a"
    ],
    "name:ast_x_preferred":[
        "Goyang"
    ],
    "name:ceb_x_preferred":[
        "Goyang-si"
    ],
    "name:ces_x_preferred":[
        "Kojang"
    ],
    "name:deu_x_preferred":[
        "Goyang"
    ],
    "name:ell_x_preferred":[
        "\u0393\u03ba\u03cc\u03b3\u03b9\u03b1\u03bd\u03b3\u03ba"
    ],
    "name:epo_x_preferred":[
        "Gojang"
    ],
    "name:fas_x_preferred":[
        "\u06af\u0648\u06cc\u0627\u0646\u06af"
    ],
    "name:fin_x_preferred":[
        "Goyang"
    ],
    "name:fra_x_preferred":[
        "Goyang"
    ],
    "name:hak_x_preferred":[
        "Goyang S\u1e73"
    ],
    "name:heb_x_preferred":[
        "\u05e7\u05d5\u05d9\u05d0\u05e0\u05d2"
    ],
    "name:hun_x_preferred":[
        "Kojang"
    ],
    "name:ind_x_preferred":[
        "Goyang"
    ],
    "name:ita_x_preferred":[
        "Goyang"
    ],
    "name:jav_x_preferred":[
        "Goyang"
    ],
    "name:jpn_x_preferred":[
        "\u9ad8\u967d"
    ],
    "name:jpn_x_variant":[
        "\u9ad8\u967d\u5e02"
    ],
    "name:kat_x_preferred":[
        "\u10d9\u10dd\u10d8\u10d0\u10dc\u10d8"
    ],
    "name:kaz_x_preferred":[
        "\u041a\u043e\u044f\u043d"
    ],
    "name:kor_x_preferred":[
        "\uace0\uc591\uc2dc"
    ],
    "name:lit_x_preferred":[
        "Kojangas"
    ],
    "name:mon_x_preferred":[
        "\u041a\u0443\u044f\u043d \u0445\u043e\u0442"
    ],
    "name:msa_x_preferred":[
        "Goyang"
    ],
    "name:nld_x_preferred":[
        "Goyang"
    ],
    "name:nor_x_preferred":[
        "Goyang"
    ],
    "name:pol_x_preferred":[
        "Goyang"
    ],
    "name:por_x_preferred":[
        "Goyang"
    ],
    "name:ron_x_preferred":[
        "Goyang"
    ],
    "name:rus_x_preferred":[
        "\u041a\u043e\u044f\u043d"
    ],
    "name:sco_x_preferred":[
        "Goyang"
    ],
    "name:spa_x_preferred":[
        "Goyang"
    ],
    "name:swe_x_preferred":[
        "Goyang"
    ],
    "name:tgl_x_preferred":[
        "Goyang"
    ],
    "name:tur_x_preferred":[
        "Goyang"
    ],
    "name:ukr_x_preferred":[
        "\u041a\u043e\u044f\u043d"
    ],
    "name:urd_x_preferred":[
        "\u06af\u0648\u06cc\u0627\u0646\u06af"
    ],
    "name:vie_x_preferred":[
        "Goyang"
    ],
    "name:war_x_preferred":[
        "Goyang"
    ],
    "name:zho_x_preferred":[
        "\u9ad8\u967d\u5e02"
    ],
    "wof:lang_x_official":[
        "ind"
    ],
    "wof:lang_x_spoken":[
        "ind",
        "eng"
    ],
    "wof:name":"Goyang",
    "wof:placetype":"locality"
},
  "geometry": {"coordinates":[119.8503,-5.5692],"type":"Point"}
}