{
  "type": "Feature",
  "properties": {
    "gn:admin1_code":"38",
    "gn:asciiname":"Goyang",
    "gn:country_code":"ID",
    "gn:dem":96,
    "gn:feature_class":"P",
    "gn:feature_code":"PPL",
    "gn:name":"Goyang",
    "gn:population":0,
    "gn:timezone":"Asia/Makassar",
    "iso:country":"ID",
    "name:ind_x_preferred":[
        "Goyang"
    ],
    "wof:name":"Goyang",
    "wof:placetype":"locality"
},
  "geometry": {"coordinates":[119.8503,-5.5692],"type":"Point"}
}