{
  "type": "Feature",
  "properties": {
    "gn:admin1_code":"18",
    "gn:asciiname":"Puusu",
    "gn:country_code":"ID",
    "gn:dem":744,
    "gn:feature_class":"P",
    "gn:feature_code":"PPL",
    "gn:name":"Puusu",
    "gn:population":0,
    "gn:timezone":"Asia/Makassar",
    "iso:country":"ID",
    "name:ind_x_preferred":[
        "Puusu"
    ],
    "wof:name":"Puusu",
    "wof:placetype":"locality"
},
  "geometry": {"coordinates":[121.7435,-8.746],"type":"Point"}
}