{
  "type": "Feature",
  "properties": {
    "gn:admin1_code":"30.0",
    "gn:asciiname":"Rawabebek",
    "gn:country_code":"ID",
    "gn:dem":15,
    "gn:feature_class":"P",
    "gn:feature_code":"PPL",
    "gn:name":"Rawabebek",
    "gn:population":0,
    "gn:timezone":"Asia/Jakarta",
    "iso:country":"ID",
    "name:ind_x_preferred":[
        "Rawabebek"
    ],
    "name:und_x_variant":[
        "Rawabebek Dua",
        "Rawabebek 2",
        "Rawabebekbendungan"
    ],
    "wof:lang_x_official":[
        "ind"
    ],
    "wof:lang_x_spoken":[
        "ind",
        "eng"
    ],
    "wof:name":"Rawabebek",
    "wof:placetype":"locality"
},
  "geometry": {"coordinates":[106.96420000000001,-6.2197],"type":"Point"}
}