{
  "type": "Feature",
  "properties": {
    "gn:admin1_code":"7.0",
    "gn:asciiname":"Graul",
    "gn:country_code":"ID",
    "gn:dem":902,
    "gn:feature_class":"P",
    "gn:feature_code":"PPL",
    "gn:name":"Graul",
    "gn:population":0,
    "gn:timezone":"Asia/Jakarta",
    "iso:country":"ID",
    "name:ind_x_preferred":[
        "Graul"
    ],
    "wof:name":"Graul",
    "wof:placetype":"locality"
},
  "geometry": {"coordinates":[109.095,-7.21028],"type":"Point"}
}