{
  "type": "Feature",
  "properties": {
    "gn:admin1_code":"30.0",
    "gn:asciiname":"Pebayuran",
    "gn:country_code":"ID",
    "gn:dem":14,
    "gn:feature_class":"P",
    "gn:feature_code":"PPL",
    "gn:name":"Pebayuran",
    "gn:population":0,
    "gn:timezone":"Asia/Jakarta",
    "iso:country":"ID",
    "name:ind_x_preferred":[
        "Pebayuran"
    ],
    "name:und_x_variant":[
        "Pebajurah",
        "Pabayuran",
        "Pebayurah"
    ],
    "wof:name":"Pebayuran",
    "wof:placetype":"locality"
},
  "geometry": {"coordinates":[107.28556,-6.21278],"type":"Point"}
}