{
  "type": "Feature",
  "properties": {
    "gn:admin1_code":"8",
    "gn:asciiname":"Sedodol",
    "gn:country_code":"ID",
    "gn:dem":30,
    "gn:feature_class":"P",
    "gn:feature_code":"PPL",
    "gn:name":"Sedodol",
    "gn:population":0,
    "gn:timezone":"Asia/Jakarta",
    "iso:country":"ID",
    "name:ind_x_preferred":[
        "Sedodol"
    ],
    "wof:name":"Sedodol",
    "wof:placetype":"locality"
},
  "geometry": {"coordinates":[112.8546,-7.6791],"type":"Point"}
}