{
  "type": "Feature",
  "properties": {
    "gn:admin1_code":"18",
    "gn:asciiname":"Raka",
    "gn:country_code":"ID",
    "gn:dem":682,
    "gn:feature_class":"P",
    "gn:feature_code":"PPL",
    "gn:name":"Raka",
    "gn:population":0,
    "gn:timezone":"Asia/Makassar",
    "iso:country":"ID",
    "name:ceb_x_preferred":[
        "Raka"
    ],
    "name:deu_x_preferred":[
        "Raka"
    ],
    "name:est_x_preferred":[
        "Raka"
    ],
    "name:heb_x_preferred":[
        "\u05e8\u05e7\u05d4"
    ],
    "name:hye_x_preferred":[
        "\u054c\u0561\u056f\u0561"
    ],
    "name:ind_x_preferred":[
        "Raka"
    ],
    "name:ita_x_preferred":[
        "Raka"
    ],
    "name:lit_x_preferred":[
        "Raka"
    ],
    "name:nld_x_preferred":[
        "Raka"
    ],
    "name:pol_x_preferred":[
        "Raka"
    ],
    "name:rus_x_preferred":[
        "\u0420\u0430\u043a\u0430"
    ],
    "name:sco_x_preferred":[
        "Raka"
    ],
    "name:spa_x_preferred":[
        "Raka"
    ],
    "name:srp_x_preferred":[
        "\u0420\u0430\u043a\u0430"
    ],
    "name:swe_x_preferred":[
        "Raka"
    ],
    "name:ukr_x_preferred":[
        "\u0420\u0430\u043a\u0430"
    ],
    "name:vol_x_preferred":[
        "Raka"
    ],
    "wof:lang_x_official":[
        "ind"
    ],
    "wof:lang_x_spoken":[
        "ind",
        "eng"
    ],
    "wof:name":"Raka",
    "wof:placetype":"locality"
},
  "geometry": {"coordinates":[120.33459999999999,-8.5291],"type":"Point"}
}