{
  "type": "Feature",
  "properties": {
    "gn:admin1_code":"18.0",
    "gn:asciiname":"Bangkelak",
    "gn:country_code":"ID",
    "gn:dem":134,
    "gn:feature_class":"P",
    "gn:feature_code":"PPL",
    "gn:name":"Bangkelak",
    "gn:population":0,
    "gn:timezone":"Asia/Makassar",
    "iso:country":"ID",
    "name:ind_x_preferred":[
        "Bangkelak"
    ],
    "wof:name":"Bangkelak",
    "wof:placetype":"locality"
},
  "geometry": {"coordinates":[122.8613,-8.2955],"type":"Point"}
}