{
  "type": "Feature",
  "properties": {
    "gn:admin1_code":"38",
    "gn:asciiname":"Asarajange",
    "gn:country_code":"ID",
    "gn:dem":146,
    "gn:feature_class":"P",
    "gn:feature_code":"PPL",
    "gn:name":"Asarajange",
    "gn:population":0,
    "gn:timezone":"Asia/Makassar",
    "iso:country":"ID",
    "name:ind_x_preferred":[
        "Asarajange"
    ],
    "wof:name":"Asarajange",
    "wof:placetype":"locality"
},
  "geometry": {"coordinates":[120.1168,-5.006],"type":"Point"}
}