{
  "type": "Feature",
  "properties": {
    "gn:admin1_code":"30",
    "gn:asciiname":"Babakansukalarang",
    "gn:country_code":"ID",
    "gn:dem":924,
    "gn:feature_class":"P",
    "gn:feature_code":"PPL",
    "gn:name":"Babakansukalarang",
    "gn:population":0,
    "gn:timezone":"Asia/Jakarta",
    "iso:country":"ID",
    "name:ind_x_preferred":[
        "Babakansukalarang"
    ],
    "wof:name":"Babakansukalarang",
    "wof:placetype":"locality"
},
  "geometry": {"coordinates":[107.00722,-6.87611],"type":"Point"}
}