{
  "type": "Feature",
  "properties": {
    "gn:admin1_code":"33",
    "gn:asciiname":"Cisalak Lebak",
    "gn:country_code":"ID",
    "gn:dem":95,
    "gn:feature_class":"P",
    "gn:feature_code":"PPL",
    "gn:name":"Cisalak Lebak",
    "gn:population":0,
    "gn:timezone":"Asia/Jakarta",
    "iso:country":"ID",
    "name:ind_x_preferred":[
        "Cisalak Lebak"
    ],
    "wof:name":"Cisalak Lebak",
    "wof:placetype":"locality"
},
  "geometry": {"coordinates":[106.13679999999999,-6.4925],"type":"Point"}
}