{
  "type": "Feature",
  "properties": {
    "gn:admin1_code":"8.0",
    "gn:asciiname":"Taraban",
    "gn:country_code":"ID",
    "gn:dem":21,
    "gn:feature_class":"P",
    "gn:feature_code":"PPL",
    "gn:name":"Taraban",
    "gn:population":0,
    "gn:timezone":"Asia/Jakarta",
    "iso:country":"ID",
    "name:ind_x_preferred":[
        "Taraban"
    ],
    "name:pol_x_preferred":[
        "Taraban"
    ],
    "name:slk_x_preferred":[
        "Taraban"
    ],
    "wof:lang_x_official":[
        "ind"
    ],
    "wof:lang_x_spoken":[
        "ind",
        "eng"
    ],
    "wof:name":"Taraban",
    "wof:placetype":"locality"
},
  "geometry": {"coordinates":[111.95348,-7.13469],"type":"Point"}
}