{
  "type": "Feature",
  "properties": {
    "gn:admin1_code":"7.0",
    "gn:asciiname":"Daleman",
    "gn:country_code":"ID",
    "gn:dem":568,
    "gn:feature_class":"P",
    "gn:feature_code":"PPL",
    "gn:name":"Daleman",
    "gn:population":0,
    "gn:timezone":"Asia/Jakarta",
    "iso:country":"ID",
    "wof:name":"Daleman",
    "wof:placetype":"locality"
},
  "geometry": {"coordinates":[110.20583000000001,-7.295],"type":"Point"}
}