{
  "type": "Feature",
  "properties": {
    "gn:admin1_code":"38.0",
    "gn:asciiname":"Kadempa",
    "gn:country_code":"ID",
    "gn:dem":65,
    "gn:feature_class":"P",
    "gn:feature_code":"PPL",
    "gn:name":"Kadempa",
    "gn:population":0,
    "gn:timezone":"Asia/Makassar",
    "iso:country":"ID",
    "name:ind_x_preferred":[
        "Kadempa"
    ],
    "wof:name":"Kadempa",
    "wof:placetype":"locality"
},
  "geometry": {"coordinates":[120.49979999999999,-6.0092],"type":"Point"}
}