{
  "type": "Feature",
  "properties": {
    "gn:admin1_code":"17",
    "gn:asciiname":"Palung Timur",
    "gn:country_code":"ID",
    "gn:dem":231,
    "gn:feature_class":"P",
    "gn:feature_code":"PPL",
    "gn:name":"Palung Timur",
    "gn:population":0,
    "gn:timezone":"Asia/Makassar",
    "iso:country":"ID",
    "name:ind_x_preferred":[
        "Palung Timur"
    ],
    "wof:name":"Palung Timur",
    "wof:placetype":"locality"
},
  "geometry": {"coordinates":[116.456,-8.6928],"type":"Point"}
}