{
  "type": "Feature",
  "properties": {
    "gn:admin1_code":"34.0",
    "gn:asciiname":"Tolango Kiki",
    "gn:country_code":"ID",
    "gn:dem":9,
    "gn:feature_class":"P",
    "gn:feature_code":"PPL",
    "gn:name":"Tolango Kiki",
    "gn:population":0,
    "gn:timezone":"Asia/Makassar",
    "iso:country":"ID",
    "name:ind_x_preferred":[
        "Tolango Kiki"
    ],
    "wof:name":"Tolango Kiki",
    "wof:placetype":"locality"
},
  "geometry": {"coordinates":[122.75190000000001,0.848],"type":"Point"}
}