{
  "type": "Feature",
  "properties": {
    "gn:admin1_code":"30",
    "gn:asciiname":"Lebarkmaja",
    "gn:cc2":"ID",
    "gn:country_code":"ID",
    "gn:dem":829,
    "gn:feature_class":"P",
    "gn:feature_code":"PPL",
    "gn:name":"Lebarkmaja",
    "gn:population":0,
    "gn:timezone":"Asia/Jakarta",
    "iso:country":"ID",
    "name:und_x_variant":[
        "Lebarkmadja",
        "Lebarkmaja"
    ],
    "wof:name":"Lebarkmaja",
    "wof:placetype":"locality"
},
  "geometry": {"coordinates":[107.74028,-7.09889],"type":"Point"}
}