{
  "type": "Feature",
  "properties": {
    "gn:admin1_code":"17",
    "gn:asciiname":"Repoklis",
    "gn:country_code":"ID",
    "gn:dem":9,
    "gn:feature_class":"P",
    "gn:feature_code":"PPL",
    "gn:name":"Repoklis",
    "gn:population":0,
    "gn:timezone":"Asia/Makassar",
    "iso:country":"ID",
    "name:ind_x_preferred":[
        "Repoklis"
    ],
    "wof:name":"Repoklis",
    "wof:placetype":"locality"
},
  "geometry": {"coordinates":[116.473,-8.81],"type":"Point"}
}