{
  "type": "Feature",
  "properties": {
    "gn:admin1_code":"7",
    "gn:asciiname":"Mandang",
    "gn:country_code":"ID",
    "gn:dem":688,
    "gn:feature_class":"P",
    "gn:feature_code":"PPL",
    "gn:name":"Mandang",
    "gn:population":0,
    "gn:timezone":"Asia/Jakarta",
    "iso:country":"ID",
    "name:ind_x_preferred":[
        "Mandang"
    ],
    "wof:name":"Mandang",
    "wof:placetype":"locality"
},
  "geometry": {"coordinates":[110.17694,-7.18167],"type":"Point"}
}