{
  "type": "Feature",
  "properties": {
    "gn:admin1_code":"30.0",
    "gn:asciiname":"Rancagintung",
    "gn:country_code":"ID",
    "gn:dem":266,
    "gn:feature_class":"P",
    "gn:feature_code":"PPL",
    "gn:name":"Rancagintung",
    "gn:population":0,
    "gn:timezone":"Asia/Jakarta",
    "iso:country":"ID",
    "name:ind_x_preferred":[
        "Rancagintung"
    ],
    "wof:name":"Rancagintung",
    "wof:placetype":"locality"
},
  "geometry": {"coordinates":[108.1503,-7.6241],"type":"Point"}
}