{
  "type": "Feature",
  "properties": {
    "gn:admin1_code":"1",
    "gn:asciiname":"Punjot",
    "gn:country_code":"ID",
    "gn:dem":2,
    "gn:feature_class":"P",
    "gn:feature_code":"PPL",
    "gn:name":"Punjot",
    "gn:population":0,
    "gn:timezone":"Asia/Jakarta",
    "iso:country":"ID",
    "name:ind_x_preferred":[
        "Punjot"
    ],
    "name:und_x_variant":[
        "Pundjot"
    ],
    "wof:lang_x_official":[
        "ind"
    ],
    "wof:lang_x_spoken":[
        "ind",
        "eng"
    ],
    "wof:name":"Punjot",
    "wof:placetype":"locality"
},
  "geometry": {"coordinates":[96.81780000000001,5.2576],"type":"Point"}
}