{
  "type": "Feature",
  "properties": {
    "gn:admin1_code":"26",
    "gn:asciiname":"Pondok Sembilan",
    "gn:country_code":"ID",
    "gn:dem":12,
    "gn:feature_class":"P",
    "gn:feature_code":"PPL",
    "gn:name":"Pondok Sembilan",
    "gn:population":0,
    "gn:timezone":"Asia/Jakarta",
    "iso:country":"ID",
    "name:ind_x_preferred":[
        "Pondok Sembilan"
    ],
    "name:und_x_variant":[
        "Pondok IX"
    ],
    "wof:name":"Pondok Sembilan",
    "wof:placetype":"locality"
},
  "geometry": {"coordinates":[99.50239999999999,3.1626],"type":"Point"}
}