{
  "type": "Feature",
  "properties": {
    "gn:admin1_code":"26.0",
    "gn:asciiname":"Lumban Tapian",
    "gn:country_code":"ID",
    "gn:dem":911,
    "gn:feature_class":"P",
    "gn:feature_code":"PPL",
    "gn:name":"Lumban Tapian",
    "gn:population":0,
    "gn:timezone":"Asia/Jakarta",
    "iso:country":"ID",
    "name:ind_x_preferred":[
        "Lumban Tapian"
    ],
    "wof:name":"Lumban Tapian",
    "wof:placetype":"locality"
},
  "geometry": {"coordinates":[98.7619,2.7419],"type":"Point"}
}