{
  "type": "Feature",
  "properties": {
    "gn:admin1_code":"38",
    "gn:asciiname":"Jamu",
    "gn:country_code":"ID",
    "gn:dem":60,
    "gn:feature_class":"P",
    "gn:feature_code":"PPL",
    "gn:name":"Jamu",
    "gn:population":0,
    "gn:timezone":"Asia/Makassar",
    "iso:country":"ID",
    "name:deu_x_preferred":[
        "Jamu"
    ],
    "name:ind_x_preferred":[
        "Jamu"
    ],
    "name:jav_x_preferred":[
        "Jamu"
    ],
    "name:msa_x_preferred":[
        "Jamu"
    ],
    "name:tur_x_preferred":[
        "Jamu"
    ],
    "wof:lang_x_official":[
        "ind"
    ],
    "wof:lang_x_spoken":[
        "ind",
        "eng"
    ],
    "wof:name":"Jamu",
    "wof:placetype":"locality"
},
  "geometry": {"coordinates":[120.331,-5.3021],"type":"Point"}
}