{
  "type": "Feature",
  "properties": {
    "gn:admin1_code":"26",
    "gn:asciiname":"Lingga",
    "gn:country_code":"ID",
    "gn:dem":151,
    "gn:feature_class":"P",
    "gn:feature_code":"PPL",
    "gn:name":"Lingga",
    "gn:population":0,
    "gn:timezone":"Asia/Jakarta",
    "iso:country":"ID",
    "name:ind_x_preferred":[
        "Lingga"
    ],
    "wof:name":"Lingga",
    "wof:placetype":"locality"
},
  "geometry": {"coordinates":[98.50360000000001,3.4508],"type":"Point"}
}