{
  "type": "Feature",
  "properties": {
    "gn:admin1_code":"7.0",
    "gn:asciiname":"Pasunggingan",
    "gn:country_code":"ID",
    "gn:dem":127,
    "gn:feature_class":"P",
    "gn:feature_code":"PPL",
    "gn:name":"Pasunggingan",
    "gn:population":0,
    "gn:timezone":"Asia/Jakarta",
    "iso:country":"ID",
    "name:ind_x_preferred":[
        "Pasunggingan"
    ],
    "wof:name":"Pasunggingan",
    "wof:placetype":"locality"
},
  "geometry": {"coordinates":[109.48721999999999,-7.38806],"type":"Point"}
}