{
  "type": "Feature",
  "properties": {
    "gn:admin1_code":"7.0",
    "gn:asciiname":"Bantarmangu",
    "gn:country_code":"ID",
    "gn:dem":72,
    "gn:feature_class":"P",
    "gn:feature_code":"PPLA4",
    "gn:name":"Bantarmangu",
    "gn:population":0,
    "gn:timezone":"Asia/Jakarta",
    "iso:country":"ID",
    "name:ind_x_preferred":[
        "Bantarmangu"
    ],
    "name:und_x_variant":[
        "Bantarmangoe"
    ],
    "wof:lang_x_official":[
        "ind"
    ],
    "wof:lang_x_spoken":[
        "ind",
        "eng"
    ],
    "wof:name":"Bantarmangu",
    "wof:placetype":"locality"
},
  "geometry": {"coordinates":[108.8661,-7.3393],"type":"Point"}
}