{
  "type": "Feature",
  "properties": {
    "gn:admin1_code":"26.0",
    "gn:asciiname":"Hilibadalu",
    "gn:country_code":"ID",
    "gn:dem":196,
    "gn:feature_class":"P",
    "gn:feature_code":"PPL",
    "gn:name":"Hilibadalu",
    "gn:population":0,
    "gn:timezone":"Asia/Jakarta",
    "iso:country":"ID",
    "name:ind_x_preferred":[
        "Hilibadalu"
    ],
    "wof:name":"Hilibadalu",
    "wof:placetype":"locality"
},
  "geometry": {"coordinates":[97.7166,0.9635],"type":"Point"}
}