{
  "type": "Feature",
  "properties": {
    "gn:admin1_code":"7",
    "gn:asciiname":"Seloromo",
    "gn:country_code":"ID",
    "gn:dem":368,
    "gn:feature_class":"P",
    "gn:feature_code":"PPL",
    "gn:name":"Seloromo",
    "gn:population":0,
    "gn:timezone":"Asia/Jakarta",
    "iso:country":"ID",
    "name:ind_x_preferred":[
        "Seloromo"
    ],
    "wof:name":"Seloromo",
    "wof:placetype":"locality"
},
  "geometry": {"coordinates":[111.09917,-7.53278],"type":"Point"}
}