{
  "type": "Feature",
  "properties": {
    "gn:admin1_code":"18.0",
    "gn:asciiname":"Lada",
    "gn:country_code":"ID",
    "gn:dem":292,
    "gn:feature_class":"P",
    "gn:feature_code":"PPL",
    "gn:name":"Lada",
    "gn:population":0,
    "gn:timezone":"Asia/Makassar",
    "iso:country":"ID",
    "name:ara_x_preferred":[
        "\u0644\u0627\u062f\u0627"
    ],
    "name:aze_x_preferred":[
        "Lada"
    ],
    "name:bul_x_preferred":[
        "\u041b\u0430\u0434\u0430"
    ],
    "name:dan_x_preferred":[
        "Lada"
    ],
    "name:ell_x_preferred":[
        "Lada"
    ],
    "name:est_x_preferred":[
        "Lada"
    ],
    "name:fas_x_preferred":[
        "\u0644\u0627\u062f\u0627"
    ],
    "name:fin_x_preferred":[
        "Lada"
    ],
    "name:fra_x_preferred":[
        "Lada-AvtoVAZ"
    ],
    "name:heb_x_preferred":[
        "\u05dc\u05d0\u05d3\u05d4"
    ],
    "name:hrv_x_preferred":[
        "Lada"
    ],
    "name:hun_x_preferred":[
        "Lada"
    ],
    "name:ind_x_preferred":[
        "Lada"
    ],
    "name:ita_x_preferred":[
        "Lada-Vaz"
    ],
    "name:jpn_x_preferred":[
        "\u30e9\u30fc\u30c0"
    ],
    "name:kor_x_preferred":[
        "\ub77c\ub2e4 \uc790\ub3d9\ucc28"
    ],
    "name:lav_x_preferred":[
        "Lada"
    ],
    "name:lit_x_preferred":[
        "Lada"
    ],
    "name:nld_x_preferred":[
        "Lada"
    ],
    "name:nno_x_preferred":[
        "Lada"
    ],
    "name:nor_x_preferred":[
        "Lada"
    ],
    "name:pol_x_preferred":[
        "\u0141ada"
    ],
    "name:por_x_preferred":[
        "Lada"
    ],
    "name:ron_x_preferred":[
        "Lada"
    ],
    "name:rus_x_preferred":[
        "Lada"
    ],
    "name:slk_x_preferred":[
        "Lada"
    ],
    "name:spa_x_preferred":[
        "Lada"
    ],
    "name:srp_x_preferred":[
        "\u041b\u0430\u0434\u0430"
    ],
    "name:swe_x_preferred":[
        "Lada"
    ],
    "name:tur_x_preferred":[
        "Lada"
    ],
    "name:ukr_x_preferred":[
        "\u041b\u0430\u0434\u0430"
    ],
    "name:vie_x_preferred":[
        "Lada"
    ],
    "name:zho_x_preferred":[
        "\u62c9\u9054\u6c7d\u8eca"
    ],
    "wof:lang_x_official":[
        "ind"
    ],
    "wof:lang_x_spoken":[
        "ind",
        "eng"
    ],
    "wof:name":"Lada",
    "wof:placetype":"locality"
},
  "geometry": {"coordinates":[120.50749999999999,-8.3326],"type":"Point"}
}