{
  "type": "Feature",
  "properties": {
    "gn:admin1_code":"15.0",
    "gn:asciiname":"Airpisangan",
    "gn:country_code":"ID",
    "gn:dem":466,
    "gn:feature_class":"P",
    "gn:feature_code":"PPL",
    "gn:name":"Airpisangan",
    "gn:population":0,
    "gn:timezone":"Asia/Jakarta",
    "iso:country":"ID",
    "name:ind_x_preferred":[
        "Airpisangan"
    ],
    "wof:name":"Airpisangan",
    "wof:placetype":"locality"
},
  "geometry": {"coordinates":[104.64735,-5.21122],"type":"Point"}
}