{
  "type": "Feature",
  "properties": {
    "gn:admin1_code":"07",
    "gn:asciiname":"Wiro",
    "gn:country_code":"ID",
    "gn:dem":115,
    "gn:feature_class":"P",
    "gn:feature_code":"PPL",
    "gn:name":"Wiro",
    "gn:population":0,
    "gn:timezone":"Asia/Jakarta",
    "iso:country":"ID",
    "name:deu_x_preferred":[
        "Wiro"
    ],
    "name:nld_x_preferred":[
        "Wiro"
    ],
    "wof:lang_x_official":[
        "ind"
    ],
    "wof:lang_x_spoken":[
        "ind",
        "eng"
    ],
    "wof:name":"Wiro",
    "wof:placetype":"locality"
},
  "geometry": {"coordinates":[110.65944,-7.75806],"type":"Point"}
}