{
  "type": "Feature",
  "properties": {
    "gn:admin1_code":"7",
    "gn:asciiname":"Sigentong",
    "gn:country_code":"ID",
    "gn:dem":5,
    "gn:feature_class":"P",
    "gn:feature_code":"PPL",
    "gn:name":"Sigentong",
    "gn:population":0,
    "gn:timezone":"Asia/Jakarta",
    "iso:country":"ID",
    "name:ind_x_preferred":[
        "Sigentong"
    ],
    "wof:name":"Sigentong",
    "wof:placetype":"locality"
},
  "geometry": {"coordinates":[110.0462,-6.9096],"type":"Point"}
}