{
  "type": "Feature",
  "properties": {
    "gn:admin1_code":"32.0",
    "gn:asciiname":"Darmo",
    "gn:country_code":"ID",
    "gn:dem":62,
    "gn:feature_class":"P",
    "gn:feature_code":"PPL",
    "gn:name":"Darmo",
    "gn:population":0,
    "gn:timezone":"Asia/Jakarta",
    "iso:country":"ID",
    "name:und_x_variant":[
        "Daramo",
        "Darma",
        "Darmo"
    ],
    "wof:name":"Darmo",
    "wof:placetype":"locality"
},
  "geometry": {"coordinates":[103.80028,-3.80694],"type":"Point"}
}