{
  "type": "Feature",
  "properties": {
    "gn:admin1_code":"1",
    "gn:asciiname":"Totor Uyet",
    "gn:country_code":"ID",
    "gn:dem":1379,
    "gn:feature_class":"P",
    "gn:feature_code":"PPL",
    "gn:name":"Totor Uyet",
    "gn:population":0,
    "gn:timezone":"Asia/Jakarta",
    "iso:country":"ID",
    "name:ind_x_preferred":[
        "Totor Uyet"
    ],
    "wof:name":"Totor Uyet",
    "wof:placetype":"locality"
},
  "geometry": {"coordinates":[96.8112,4.6326],"type":"Point"}
}