{
  "type": "Feature",
  "properties": {
    "gn:admin1_code":"8.0",
    "gn:asciiname":"Klakah Lor",
    "gn:country_code":"ID",
    "gn:dem":459,
    "gn:feature_class":"P",
    "gn:feature_code":"PPL",
    "gn:name":"Klakah Lor",
    "gn:population":0,
    "gn:timezone":"Asia/Jakarta",
    "iso:country":"ID",
    "name:ind_x_preferred":[
        "Klakah Lor"
    ],
    "wof:name":"Klakah Lor",
    "wof:placetype":"locality"
},
  "geometry": {"coordinates":[112.3887,-8.0544],"type":"Point"}
}