{
  "type": "Feature",
  "properties": {
    "gn:admin1_code":"8.0",
    "gn:asciiname":"Darmarakyattrawas",
    "gn:country_code":"ID",
    "gn:dem":604,
    "gn:feature_class":"P",
    "gn:feature_code":"PPL",
    "gn:name":"Darmarakyattrawas",
    "gn:population":0,
    "gn:timezone":"Asia/Jakarta",
    "iso:country":"ID",
    "name:ind_x_preferred":[
        "Darmarakyattrawas"
    ],
    "wof:name":"Darmarakyattrawas",
    "wof:placetype":"locality"
},
  "geometry": {"coordinates":[112.62130000000001,-7.6647],"type":"Point"}
}