{
  "type": "Feature",
  "properties": {
    "gn:admin1_code":"30",
    "gn:asciiname":"Jembatan",
    "gn:country_code":"ID",
    "gn:dem":332,
    "gn:feature_class":"P",
    "gn:feature_code":"PPL",
    "gn:name":"Jembatan",
    "gn:population":0,
    "gn:timezone":"Asia/Jakarta",
    "iso:country":"ID",
    "name:ind_x_preferred":[
        "Jembatan"
    ],
    "wof:name":"Jembatan",
    "wof:placetype":"locality"
},
  "geometry": {"coordinates":[106.52222,-6.59556],"type":"Point"}
}