{
  "type": "Feature",
  "properties": {
    "gn:admin1_code":"8.0",
    "gn:asciiname":"Kerang",
    "gn:country_code":"ID",
    "gn:dem":77,
    "gn:feature_class":"P",
    "gn:feature_code":"PPL",
    "gn:name":"Kerang",
    "gn:population":0,
    "gn:timezone":"Asia/Jakarta",
    "iso:country":"ID",
    "name:ind_x_preferred":[
        "Kerang"
    ],
    "wof:name":"Kerang",
    "wof:placetype":"locality"
},
  "geometry": {"coordinates":[111.49760000000001,-7.6739],"type":"Point"}
}