{
  "type": "Feature",
  "properties": {
    "gn:admin1_code":"30",
    "gn:asciiname":"Cijambe",
    "gn:country_code":"ID",
    "gn:dem":483,
    "gn:feature_class":"P",
    "gn:feature_code":"PPL",
    "gn:name":"Cijambe",
    "gn:population":0,
    "gn:timezone":"Asia/Jakarta",
    "iso:country":"ID",
    "name:ind_x_preferred":[
        "Cijambe"
    ],
    "wof:name":"Cijambe",
    "wof:placetype":"locality"
},
  "geometry": {"coordinates":[106.60361,-6.50167],"type":"Point"}
}