{
  "type": "Feature",
  "properties": {
    "gn:admin1_code":"7",
    "gn:asciiname":"Keplik",
    "gn:country_code":"ID",
    "gn:dem":38,
    "gn:feature_class":"P",
    "gn:feature_code":"PPL",
    "gn:name":"Keplik",
    "gn:population":0,
    "gn:timezone":"Asia/Jakarta",
    "iso:country":"ID",
    "name:ind_x_preferred":[
        "Keplik"
    ],
    "wof:name":"Keplik",
    "wof:placetype":"locality"
},
  "geometry": {"coordinates":[109.1172,-6.9728],"type":"Point"}
}