{
  "type": "Feature",
  "properties": {
    "gn:admin1_code":"26",
    "gn:asciiname":"Pondok Bahhapit",
    "gn:country_code":"ID",
    "gn:dem":197,
    "gn:feature_class":"P",
    "gn:feature_code":"PPL",
    "gn:name":"Pondok Bahhapit",
    "gn:population":0,
    "gn:timezone":"Asia/Jakarta",
    "iso:country":"ID",
    "name:ind_x_preferred":[
        "Pondok Bahhapit"
    ],
    "wof:name":"Pondok Bahhapit",
    "wof:placetype":"locality"
},
  "geometry": {"coordinates":[99.0553,3.0865],"type":"Point"}
}