{
  "type": "Feature",
  "properties": {
    "gn:admin1_code":"05",
    "gn:asciiname":"Telukleban",
    "gn:country_code":"ID",
    "gn:dem":35,
    "gn:feature_class":"P",
    "gn:feature_code":"PPL",
    "gn:name":"Telukleban",
    "gn:population":0,
    "gn:timezone":"Asia/Jakarta",
    "iso:country":"ID",
    "name:ind_x_preferred":[
        "Telukleban"
    ],
    "wof:name":"Telukleban",
    "wof:placetype":"locality"
},
  "geometry": {"coordinates":[102.794,-1.6371],"type":"Point"}
}