{
  "type": "Feature",
  "properties": {
    "gn:admin1_code":"41.0",
    "gn:asciiname":"Kaliee",
    "gn:country_code":"ID",
    "gn:dem":117,
    "gn:feature_class":"P",
    "gn:feature_code":"PPL",
    "gn:name":"Kaliee",
    "gn:population":0,
    "gn:timezone":"Asia/Makassar",
    "iso:country":"ID",
    "name:ind_x_preferred":[
        "Kaliee"
    ],
    "wof:name":"Kaliee",
    "wof:placetype":"locality"
},
  "geometry": {"coordinates":[119.33625000000001,-1.58652],"type":"Point"}
}