{
  "type": "Feature",
  "properties": {
    "gn:admin1_code":"30",
    "gn:asciiname":"Padarek",
    "gn:country_code":"ID",
    "gn:dem":463,
    "gn:feature_class":"P",
    "gn:feature_code":"PPL",
    "gn:name":"Padarek",
    "gn:population":0,
    "gn:timezone":"Asia/Jakarta",
    "iso:country":"ID",
    "name:ind_x_preferred":[
        "Padarek"
    ],
    "wof:name":"Padarek",
    "wof:placetype":"locality"
},
  "geometry": {"coordinates":[108.5085,-6.958],"type":"Point"}
}