{
  "type": "Feature",
  "properties": {
    "gn:admin1_code":"30",
    "gn:asciiname":"Miji",
    "gn:country_code":"ID",
    "gn:dem":677,
    "gn:feature_class":"P",
    "gn:feature_code":"PPL",
    "gn:name":"Miji",
    "gn:population":0,
    "gn:timezone":"Asia/Jakarta",
    "iso:country":"ID",
    "name:ceb_x_preferred":[
        "Miji"
    ],
    "name:ind_x_preferred":[
        "Miji"
    ],
    "name:nld_x_preferred":[
        "Miji"
    ],
    "name:swe_x_preferred":[
        "Miji"
    ],
    "wof:lang_x_official":[
        "ind"
    ],
    "wof:lang_x_spoken":[
        "ind",
        "eng"
    ],
    "wof:name":"Miji",
    "wof:placetype":"locality"
},
  "geometry": {"coordinates":[107.81610999999999,-6.99333],"type":"Point"}
}