{
  "type": "Feature",
  "properties": {
    "gn:admin1_code":"38",
    "gn:asciiname":"Lahuwa Satu",
    "gn:country_code":"ID",
    "gn:dem":114,
    "gn:feature_class":"P",
    "gn:feature_code":"PPL",
    "gn:name":"Lahuwa Satu",
    "gn:population":0,
    "gn:timezone":"Asia/Makassar",
    "iso:country":"ID",
    "name:ind_x_preferred":[
        "Lahuwa Satu"
    ],
    "name:und_x_variant":[
        "Lahuwa 1"
    ],
    "wof:lang_x_official":[
        "ind"
    ],
    "wof:lang_x_spoken":[
        "ind",
        "eng"
    ],
    "wof:name":"Lahuwa Satu",
    "wof:placetype":"locality"
},
  "geometry": {"coordinates":[120.21939999999999,-5.0026],"type":"Point"}
}