{
  "type": "Feature",
  "properties": {
    "gn:admin1_code":"7",
    "gn:asciiname":"Mangonan",
    "gn:country_code":"ID",
    "gn:dem":26,
    "gn:feature_class":"P",
    "gn:feature_code":"PPL",
    "gn:name":"Mangonan",
    "gn:population":0,
    "gn:timezone":"Asia/Jakarta",
    "iso:country":"ID",
    "name:ind_x_preferred":[
        "Mangonan"
    ],
    "wof:name":"Mangonan",
    "wof:placetype":"locality"
},
  "geometry": {"coordinates":[110.8819,-7.038],"type":"Point"}
}