{
  "type": "Feature",
  "properties": {
    "gn:admin1_code":"30",
    "gn:asciiname":"Sirnagalih",
    "gn:country_code":"ID",
    "gn:dem":681,
    "gn:feature_class":"P",
    "gn:feature_code":"PPL",
    "gn:name":"Sirnagalih",
    "gn:population":0,
    "gn:timezone":"Asia/Jakarta",
    "iso:country":"ID",
    "name:ind_x_preferred":[
        "Sirnagalih"
    ],
    "wof:name":"Sirnagalih",
    "wof:placetype":"locality"
},
  "geometry": {"coordinates":[107.77306000000002,-6.95389],"type":"Point"}
}