{
  "type": "Feature",
  "properties": {
    "gn:admin1_code":"33",
    "gn:asciiname":"Saronge",
    "gn:country_code":"ID",
    "gn:dem":50,
    "gn:feature_class":"P",
    "gn:feature_code":"PPL",
    "gn:name":"Saronge",
    "gn:population":0,
    "gn:timezone":"Asia/Jakarta",
    "iso:country":"ID",
    "name:ind_x_preferred":[
        "Saronge"
    ],
    "name:und_x_variant":[
        "Dunguspitung"
    ],
    "wof:name":"Saronge",
    "wof:placetype":"locality"
},
  "geometry": {"coordinates":[106.36369999999999,-6.3487],"type":"Point"}
}