{
  "type": "Feature",
  "properties": {
    "gn:admin1_code":"00",
    "gn:asciiname":"Cilincing",
    "gn:cc2":"ID",
    "gn:country_code":"ID",
    "gn:dem":100,
    "gn:feature_class":"P",
    "gn:feature_code":"PPL",
    "gn:name":"Cilincing",
    "gn:population":0,
    "gn:timezone":"Asia/Jakarta",
    "iso:country":"ID",
    "name:ceb_x_preferred":[
        "Kecamatan Cilincing"
    ],
    "name:gor_x_preferred":[
        "Cilincing"
    ],
    "name:ind_x_preferred":[
        "Cilincing"
    ],
    "name:jav_x_preferred":[
        "Cilincing"
    ],
    "name:nld_x_preferred":[
        "Cilincing"
    ],
    "name:pol_x_preferred":[
        "Cilincing"
    ],
    "name:sun_x_preferred":[
        "Cilincing"
    ],
    "name:swe_x_preferred":[
        "Kecamatan Cilincing"
    ],
    "name:und_x_variant":[
        "Tjilintjing",
        "Cilincing"
    ],
    "wof:lang_x_official":[
        "ind"
    ],
    "wof:lang_x_spoken":[
        "ind",
        "eng"
    ],
    "wof:name":"Cilincing",
    "wof:placetype":"locality"
},
  "geometry": {"coordinates":[106.66556,-6.4275],"type":"Point"}
}