{
  "type": "Feature",
  "properties": {
    "gn:admin1_code":"8",
    "gn:asciiname":"Macekan",
    "gn:country_code":"ID",
    "gn:dem":19,
    "gn:feature_class":"P",
    "gn:feature_code":"PPL",
    "gn:name":"Macekan",
    "gn:population":0,
    "gn:timezone":"Asia/Jakarta",
    "iso:country":"ID",
    "name:ind_x_preferred":[
        "Macekan"
    ],
    "wof:name":"Macekan",
    "wof:placetype":"locality"
},
  "geometry": {"coordinates":[112.5064,-7.4515],"type":"Point"}
}