{
  "type": "Feature",
  "properties": {
    "gn:admin1_code":"18",
    "gn:asciiname":"Pela",
    "gn:country_code":"ID",
    "gn:dem":865,
    "gn:feature_class":"P",
    "gn:feature_code":"PPL",
    "gn:name":"Pela",
    "gn:population":0,
    "gn:timezone":"Asia/Makassar",
    "iso:country":"ID",
    "name:ceb_x_preferred":[
        "Pela"
    ],
    "name:ind_x_preferred":[
        "Pela"
    ],
    "name:nld_x_preferred":[
        "Pela"
    ],
    "name:pol_x_preferred":[
        "Pela"
    ],
    "name:por_x_preferred":[
        "Pela"
    ],
    "name:swe_x_preferred":[
        "Pela"
    ],
    "wof:lang_x_official":[
        "ind"
    ],
    "wof:lang_x_spoken":[
        "ind",
        "eng"
    ],
    "wof:name":"Pela",
    "wof:placetype":"locality"
},
  "geometry": {"coordinates":[120.4811,-8.5607],"type":"Point"}
}