{
  "type": "Feature",
  "properties": {
    "gn:admin1_code":"7",
    "gn:asciiname":"Pedawang Barat",
    "gn:country_code":"ID",
    "gn:dem":139,
    "gn:feature_class":"P",
    "gn:feature_code":"PPL",
    "gn:name":"Pedawang Barat",
    "gn:population":0,
    "gn:timezone":"Asia/Jakarta",
    "iso:country":"ID",
    "name:ind_x_preferred":[
        "Pedawang Barat"
    ],
    "wof:name":"Pedawang Barat",
    "wof:placetype":"locality"
},
  "geometry": {"coordinates":[109.642,-7.0426],"type":"Point"}
}