{
  "type": "Feature",
  "properties": {
    "gn:admin1_code":"18",
    "gn:asciiname":"Geleba",
    "gn:country_code":"ID",
    "gn:dem":988,
    "gn:feature_class":"P",
    "gn:feature_code":"PPL",
    "gn:name":"Geleba",
    "gn:population":0,
    "gn:timezone":"Asia/Makassar",
    "iso:country":"ID",
    "wof:name":"Geleba",
    "wof:placetype":"locality"
},
  "geometry": {"coordinates":[125.16500000000001,-9.15111],"type":"Point"}
}