{
  "type": "Feature",
  "properties": {
    "gn:admin1_code":"31",
    "gn:asciiname":"Pungkol",
    "gn:country_code":"ID",
    "gn:dem":7,
    "gn:feature_class":"P",
    "gn:feature_code":"PPL",
    "gn:name":"Pungkol",
    "gn:population":0,
    "gn:timezone":"Asia/Makassar",
    "iso:country":"ID",
    "name:ind_x_preferred":[
        "Pungkol"
    ],
    "wof:name":"Pungkol",
    "wof:placetype":"locality"
},
  "geometry": {"coordinates":[124.5356,1.3393],"type":"Point"}
}