{
  "type": "Feature",
  "properties": {
    "gn:admin1_code":"38",
    "gn:asciiname":"Tanassang",
    "gn:country_code":"ID",
    "gn:dem":128,
    "gn:feature_class":"P",
    "gn:feature_code":"PPL",
    "gn:name":"Tanassang",
    "gn:population":0,
    "gn:timezone":"Asia/Makassar",
    "iso:country":"ID",
    "name:ind_x_preferred":[
        "Tanassang"
    ],
    "name:und_x_variant":[
        "Tanasang"
    ],
    "wof:name":"Tanassang",
    "wof:placetype":"locality"
},
  "geometry": {"coordinates":[120.0523,-4.7034],"type":"Point"}
}