{
  "type": "Feature",
  "properties": {
    "gn:admin1_code":"30",
    "gn:asciiname":"Palalangon Dua",
    "gn:country_code":"ID",
    "gn:dem":666,
    "gn:feature_class":"P",
    "gn:feature_code":"PPL",
    "gn:name":"Palalangon Dua",
    "gn:population":0,
    "gn:timezone":"Asia/Jakarta",
    "iso:country":"ID",
    "name:ind_x_preferred":[
        "Palalangon Dua"
    ],
    "name:und_x_variant":[
        "Palalangon 2"
    ],
    "wof:lang_x_official":[
        "ind"
    ],
    "wof:lang_x_spoken":[
        "ind",
        "eng"
    ],
    "wof:name":"Palalangon Dua",
    "wof:placetype":"locality"
},
  "geometry": {"coordinates":[106.77943999999999,-6.72944],"type":"Point"}
}