{
  "type": "Feature",
  "properties": {
    "gn:admin1_code":"30",
    "gn:asciiname":"Pasirmuncang",
    "gn:country_code":"ID",
    "gn:dem":1064,
    "gn:feature_class":"P",
    "gn:feature_code":"PPL",
    "gn:name":"Pasirmuncang",
    "gn:population":0,
    "gn:timezone":"Asia/Jakarta",
    "iso:country":"ID",
    "name:ind_x_preferred":[
        "Pasirmuncang"
    ],
    "wof:lang_x_official":[
        "ind"
    ],
    "wof:lang_x_spoken":[
        "ind",
        "eng"
    ],
    "wof:name":"Pasirmuncang",
    "wof:placetype":"locality"
},
  "geometry": {"coordinates":[107.82040000000001,-7.1921],"type":"Point"}
}