{
  "type": "Feature",
  "properties": {
    "gn:admin1_code":"8",
    "gn:asciiname":"Kedungjati",
    "gn:country_code":"ID",
    "gn:dem":207,
    "gn:feature_class":"P",
    "gn:feature_code":"PPL",
    "gn:name":"Kedungjati",
    "gn:population":0,
    "gn:timezone":"Asia/Jakarta",
    "iso:country":"ID",
    "name:ind_x_preferred":[
        "Kedungjati"
    ],
    "wof:name":"Kedungjati",
    "wof:placetype":"locality"
},
  "geometry": {"coordinates":[112.3335,-8.2032],"type":"Point"}
}