{
  "type": "Feature",
  "properties": {
    "gn:admin1_code":"10.0",
    "gn:asciiname":"Pakwungu",
    "gn:country_code":"ID",
    "gn:dem":271,
    "gn:feature_class":"P",
    "gn:feature_code":"PPL",
    "gn:name":"Pakwungu",
    "gn:population":0,
    "gn:timezone":"Asia/Jakarta",
    "iso:country":"ID",
    "name:ind_x_preferred":[
        "Pakwungu"
    ],
    "wof:name":"Pakwungu",
    "wof:placetype":"locality"
},
  "geometry": {"coordinates":[110.65639,-8.08361],"type":"Point"}
}