{
  "type": "Feature",
  "properties": {
    "gn:admin1_code":"38",
    "gn:asciiname":"Baroko",
    "gn:country_code":"ID",
    "gn:dem":1514,
    "gn:feature_class":"P",
    "gn:feature_code":"PPL",
    "gn:name":"Baroko",
    "gn:population":0,
    "gn:timezone":"Asia/Makassar",
    "iso:country":"ID",
    "name:ind_x_preferred":[
        "Baroko"
    ],
    "wof:name":"Baroko",
    "wof:placetype":"locality"
},
  "geometry": {"coordinates":[119.8237,-2.8704],"type":"Point"}
}