{
  "type": "Feature",
  "properties": {
    "gn:admin1_code":"30",
    "gn:asciiname":"Ampel",
    "gn:cc2":"ID",
    "gn:country_code":"ID",
    "gn:dem":31,
    "gn:feature_class":"P",
    "gn:feature_code":"PPL",
    "gn:name":"Ampel",
    "gn:population":0,
    "gn:timezone":"Asia/Jakarta",
    "iso:country":"ID",
    "name:ind_x_preferred":[
        "Ampel"
    ],
    "name:nld_x_preferred":[
        "Ampel"
    ],
    "name:und_x_variant":[
        "Ampel 1",
        "Ampel Satu",
        "Ampel"
    ],
    "wof:lang_x_official":[
        "ind"
    ],
    "wof:lang_x_spoken":[
        "ind",
        "eng"
    ],
    "wof:name":"Ampel",
    "wof:placetype":"locality"
},
  "geometry": {"coordinates":[106.31889,-6.21889],"type":"Point"}
}