{
  "type": "Feature",
  "properties": {
    "gn:admin1_code":"18.0",
    "gn:asciiname":"Papungga",
    "gn:country_code":"ID",
    "gn:dem":768,
    "gn:feature_class":"P",
    "gn:feature_code":"PPL",
    "gn:name":"Papungga",
    "gn:population":0,
    "gn:timezone":"Asia/Makassar",
    "iso:country":"ID",
    "name:ind_x_preferred":[
        "Papungga"
    ],
    "wof:name":"Papungga",
    "wof:placetype":"locality"
},
  "geometry": {"coordinates":[121.0642,-8.4972],"type":"Point"}
}