{
  "type": "Feature",
  "properties": {
    "gn:admin1_code":"30",
    "gn:asciiname":"Jambeberun",
    "gn:country_code":"ID",
    "gn:dem":712,
    "gn:feature_class":"P",
    "gn:feature_code":"PPL",
    "gn:name":"Jambeberun",
    "gn:population":0,
    "gn:timezone":"Asia/Jakarta",
    "iso:country":"ID",
    "name:ind_x_preferred":[
        "Jambeberun"
    ],
    "wof:name":"Jambeberun",
    "wof:placetype":"locality"
},
  "geometry": {"coordinates":[107.40639,-6.99028],"type":"Point"}
}