{
  "type": "Feature",
  "properties": {
    "gn:admin1_code":"18.0",
    "gn:asciiname":"Mesa",
    "gn:country_code":"ID",
    "gn:dem":8,
    "gn:feature_class":"P",
    "gn:feature_code":"PPLA4",
    "gn:name":"Mesa",
    "gn:population":0,
    "gn:timezone":"Asia/Makassar",
    "iso:country":"ID",
    "name:afr_x_preferred":[
        "Mesa"
    ],
    "name:als_x_preferred":[
        "Tafelberg"
    ],
    "name:ara_x_preferred":[
        "\u0645\u0627\u0626\u062f\u0629 \u0635\u062d\u0631\u0627\u0648\u064a\u0629"
    ],
    "name:bih_x_preferred":[
        "\u092e\u0947\u0938\u093e"
    ],
    "name:cat_x_preferred":[
        "Mesa"
    ],
    "name:ces_x_preferred":[
        "Stolov\u00e1 hora"
    ],
    "name:dan_x_preferred":[
        "Taffelbjerg"
    ],
    "name:deu_x_preferred":[
        "Tafelberg"
    ],
    "name:epo_x_preferred":[
        "Tablomonto"
    ],
    "name:fas_x_preferred":[
        "\u062a\u062e\u062a\u200c\u062a\u067e\u0647"
    ],
    "name:fin_x_preferred":[
        "P\u00f6yt\u00e4vuori"
    ],
    "name:fra_x_preferred":[
        "Mesa"
    ],
    "name:fry_x_preferred":[
        "Tafelberch"
    ],
    "name:glg_x_preferred":[
        "Mesa"
    ],
    "name:heb_x_preferred":[
        "\u05d4\u05e8 \u05e9\u05d5\u05dc\u05d7\u05df"
    ],
    "name:hrv_x_preferred":[
        "Ravna gora"
    ],
    "name:hye_x_preferred":[
        "\u054d\u0565\u0572\u0561\u0576\u0561\u0571\u0587 \u056c\u0565\u057c\u0576\u0565\u0580"
    ],
    "name:ind_x_preferred":[
        "Mesa"
    ],
    "name:ita_x_preferred":[
        "Mesa"
    ],
    "name:kat_x_preferred":[
        "\u10db\u10d0\u10d2\u10d8\u10d3\u10d0 \u10db\u10d7\u10d0"
    ],
    "name:lit_x_preferred":[
        "Stalkalnis"
    ],
    "name:nld_x_preferred":[
        "Tafelberg"
    ],
    "name:nno_x_preferred":[
        "Bordfjell"
    ],
    "name:nor_x_preferred":[
        "Mesa"
    ],
    "name:pol_x_preferred":[
        "Stoliwo"
    ],
    "name:por_x_preferred":[
        "Mesa"
    ],
    "name:rus_x_preferred":[
        "\u0421\u0442\u043e\u043b\u043e\u0432\u0430\u044f \u0433\u043e\u0440\u0430"
    ],
    "name:spa_x_preferred":[
        "Mesa"
    ],
    "name:srd_x_preferred":[
        "Mesa"
    ],
    "name:swe_x_preferred":[
        "Mesa"
    ],
    "name:tha_x_preferred":[
        "\u0e20\u0e39\u0e40\u0e02\u0e32\u0e22\u0e2d\u0e14\u0e23\u0e32\u0e1a"
    ],
    "name:tur_x_preferred":[
        "D\u00fcz tepe"
    ],
    "name:ukr_x_preferred":[
        "\u0421\u0442\u043e\u043b\u043e\u0432\u0430 \u0433\u043e\u0440\u0430"
    ],
    "name:zho_x_preferred":[
        "\u5e73\u9802\u5c71"
    ],
    "wof:lang_x_official":[
        "ind"
    ],
    "wof:lang_x_spoken":[
        "ind",
        "eng"
    ],
    "wof:name":"Mesa",
    "wof:placetype":"locality"
},
  "geometry": {"coordinates":[119.7461,-8.528],"type":"Point"}
}