{
  "type": "Feature",
  "properties": {
    "gn:admin1_code":"33.0",
    "gn:asciiname":"Cibadak Girang",
    "gn:country_code":"ID",
    "gn:dem":302,
    "gn:feature_class":"P",
    "gn:feature_code":"PPL",
    "gn:name":"Cibadak Girang",
    "gn:population":0,
    "gn:timezone":"Asia/Jakarta",
    "iso:country":"ID",
    "name:ind_x_preferred":[
        "Cibadak Girang"
    ],
    "wof:name":"Cibadak Girang",
    "wof:placetype":"locality"
},
  "geometry": {"coordinates":[106.07689999999999,-6.7097],"type":"Point"}
}