{
  "type": "Feature",
  "properties": {
    "gn:admin1_code":"18.0",
    "gn:asciiname":"Malumbi Satu",
    "gn:country_code":"ID",
    "gn:dem":32,
    "gn:feature_class":"P",
    "gn:feature_code":"PPL",
    "gn:name":"Malumbi Satu",
    "gn:population":0,
    "gn:timezone":"Asia/Makassar",
    "iso:country":"ID",
    "name:ind_x_preferred":[
        "Malumbi Satu"
    ],
    "name:und_x_variant":[
        "Malumbi 1"
    ],
    "wof:name":"Malumbi Satu",
    "wof:placetype":"locality"
},
  "geometry": {"coordinates":[120.2779,-9.7187],"type":"Point"}
}