{
  "type": "Feature",
  "properties": {
    "gn:admin1_code":"30.0",
    "gn:asciiname":"Bantarkawung",
    "gn:country_code":"ID",
    "gn:dem":27,
    "gn:feature_class":"P",
    "gn:feature_code":"PPL",
    "gn:name":"Bantarkawung",
    "gn:population":0,
    "gn:timezone":"Asia/Jakarta",
    "iso:country":"ID",
    "name:ind_x_preferred":[
        "Bantarkawung"
    ],
    "wof:name":"Bantarkawung",
    "wof:placetype":"locality"
},
  "geometry": {"coordinates":[108.45099999999999,-7.7138],"type":"Point"}
}