{
  "type": "Feature",
  "properties": {
    "gn:admin1_code":"30.0",
    "gn:asciiname":"Cikahuripan",
    "gn:country_code":"ID",
    "gn:dem":148,
    "gn:feature_class":"P",
    "gn:feature_code":"PPLA4",
    "gn:name":"Cikahuripan",
    "gn:population":0,
    "gn:timezone":"Asia/Jakarta",
    "iso:country":"ID",
    "name:ind_x_preferred":[
        "Cikahuripan"
    ],
    "name:und_x_variant":[
        "Tjikahoeripan"
    ],
    "wof:name":"Cikahuripan",
    "wof:placetype":"locality"
},
  "geometry": {"coordinates":[108.5484,-7.0354],"type":"Point"}
}