{
  "type": "Feature",
  "properties": {
    "gn:admin1_code":"18",
    "gn:asciiname":"Peke",
    "gn:country_code":"ID",
    "gn:dem":89,
    "gn:feature_class":"P",
    "gn:feature_code":"PPL",
    "gn:name":"Peke",
    "gn:population":0,
    "gn:timezone":"Asia/Makassar",
    "iso:country":"ID",
    "name:ceb_x_preferred":[
        "Peke"
    ],
    "name:swe_x_preferred":[
        "Peke"
    ],
    "wof:name":"Peke",
    "wof:placetype":"locality"
},
  "geometry": {"coordinates":[124.7775,-9.76833],"type":"Point"}
}