{
  "type": "Feature",
  "properties": {
    "gn:admin1_code":"15.0",
    "gn:asciiname":"Talangliak",
    "gn:country_code":"ID",
    "gn:dem":137,
    "gn:feature_class":"P",
    "gn:feature_code":"PPL",
    "gn:name":"Talangliak",
    "gn:population":0,
    "gn:timezone":"Asia/Jakarta",
    "iso:country":"ID",
    "name:ind_x_preferred":[
        "Talangliak"
    ],
    "wof:name":"Talangliak",
    "wof:placetype":"locality"
},
  "geometry": {"coordinates":[105.45869999999999,-5.59234],"type":"Point"}
}