{
  "type": "Feature",
  "properties": {
    "gn:admin1_code":"30.0",
    "gn:asciiname":"Tonjong Kidul",
    "gn:country_code":"ID",
    "gn:dem":506,
    "gn:feature_class":"P",
    "gn:feature_code":"PPL",
    "gn:name":"Tonjong Kidul",
    "gn:population":0,
    "gn:timezone":"Asia/Jakarta",
    "iso:country":"ID",
    "name:ind_x_preferred":[
        "Tonjong Kidul"
    ],
    "wof:name":"Tonjong Kidul",
    "wof:placetype":"locality"
},
  "geometry": {"coordinates":[108.1728,-7.1857],"type":"Point"}
}