{
  "type": "Feature",
  "properties": {
    "gn:admin1_code":"15.0",
    "gn:asciiname":"Kampungpedamaran",
    "gn:country_code":"ID",
    "gn:dem":356,
    "gn:feature_class":"P",
    "gn:feature_code":"PPL",
    "gn:name":"Kampungpedamaran",
    "gn:population":0,
    "gn:timezone":"Asia/Jakarta",
    "iso:country":"ID",
    "name:ind_x_preferred":[
        "Kampungpedamaran"
    ],
    "wof:name":"Kampungpedamaran",
    "wof:placetype":"locality"
},
  "geometry": {"coordinates":[104.57639,-5.63058],"type":"Point"}
}