{
  "type": "Feature",
  "properties": {
    "gn:admin1_code":"38.0",
    "gn:asciiname":"Pangrata",
    "gn:country_code":"ID",
    "gn:dem":1166,
    "gn:feature_class":"P",
    "gn:feature_code":"PPL",
    "gn:name":"Pangrata",
    "gn:population":0,
    "gn:timezone":"Asia/Makassar",
    "iso:country":"ID",
    "name:ind_x_preferred":[
        "Pangrata"
    ],
    "wof:name":"Pangrata",
    "wof:placetype":"locality"
},
  "geometry": {"coordinates":[119.8272,-2.9994],"type":"Point"}
}