{
  "type": "Feature",
  "properties": {
    "gn:admin1_code":"7",
    "gn:asciiname":"Randusari",
    "gn:country_code":"ID",
    "gn:dem":333,
    "gn:feature_class":"P",
    "gn:feature_code":"PPL",
    "gn:name":"Randusari",
    "gn:population":0,
    "gn:timezone":"Asia/Jakarta",
    "iso:country":"ID",
    "name:ind_x_preferred":[
        "Randusari"
    ],
    "wof:name":"Randusari",
    "wof:placetype":"locality"
},
  "geometry": {"coordinates":[111.02110999999999,-7.77389],"type":"Point"}
}