{
  "type": "Feature",
  "properties": {
    "gn:admin1_code":"18.0",
    "gn:asciiname":"Mehona",
    "gn:country_code":"ID",
    "gn:dem":176,
    "gn:feature_class":"P",
    "gn:feature_code":"PPLA4",
    "gn:name":"Mehona",
    "gn:population":0,
    "gn:timezone":"Asia/Makassar",
    "iso:country":"ID",
    "name:ind_x_preferred":[
        "Mehona"
    ],
    "wof:name":"Mehona",
    "wof:placetype":"locality"
},
  "geometry": {"coordinates":[121.8335,-10.5951],"type":"Point"}
}