{
  "type": "Feature",
  "properties": {
    "gn:admin1_code":"30",
    "gn:asciiname":"Maja",
    "gn:country_code":"ID",
    "gn:dem":484,
    "gn:feature_class":"P",
    "gn:feature_code":"PPL",
    "gn:name":"Maja",
    "gn:population":0,
    "gn:timezone":"Asia/Jakarta",
    "iso:country":"ID",
    "name:ind_x_preferred":[
        "Maja"
    ],
    "wof:name":"Maja",
    "wof:placetype":"locality"
},
  "geometry": {"coordinates":[108.5128,-6.9268],"type":"Point"}
}