{
  "type": "Feature",
  "properties": {
    "gn:admin1_code":"26",
    "gn:asciiname":"Sidorejo",
    "gn:country_code":"ID",
    "gn:dem":5,
    "gn:feature_class":"P",
    "gn:feature_code":"PPL",
    "gn:name":"Sidorejo",
    "gn:population":0,
    "gn:timezone":"Asia/Jakarta",
    "iso:country":"ID",
    "name:ind_x_preferred":[
        "Sidorejo"
    ],
    "wof:name":"Sidorejo",
    "wof:placetype":"locality"
},
  "geometry": {"coordinates":[99.5615,3.1533],"type":"Point"}
}