{
  "type": "Feature",
  "properties": {
    "gn:admin1_code":"38",
    "gn:asciiname":"Sabbamparu",
    "gn:country_code":"ID",
    "gn:dem":11,
    "gn:feature_class":"P",
    "gn:feature_code":"PPL",
    "gn:name":"Sabbamparu",
    "gn:population":0,
    "gn:timezone":"Asia/Makassar",
    "iso:country":"ID",
    "name:ind_x_preferred":[
        "Sabbamparu"
    ],
    "wof:name":"Sabbamparu",
    "wof:placetype":"locality"
},
  "geometry": {"coordinates":[120.1888,-2.9912],"type":"Point"}
}