{
  "type": "Feature",
  "properties": {
    "gn:admin1_code":"18.0",
    "gn:asciiname":"Wudu",
    "gn:country_code":"ID",
    "gn:dem":305,
    "gn:feature_class":"P",
    "gn:feature_code":"PPL",
    "gn:name":"Wudu",
    "gn:population":0,
    "gn:timezone":"Asia/Makassar",
    "iso:country":"ID",
    "name:ara_x_preferred":[
        "\u0648\u0636\u0648\u0621"
    ],
    "name:aze_x_preferred":[
        "D\u0259st\u0259maz"
    ],
    "name:ben_x_preferred":[
        "\u0985\u09af\u09c1"
    ],
    "name:bos_x_preferred":[
        "Abdest"
    ],
    "name:bul_x_preferred":[
        "\u0410\u0431\u0434\u0435\u0441\u0442"
    ],
    "name:dan_x_preferred":[
        "Abdest"
    ],
    "name:deu_x_preferred":[
        "Wud\u016b'"
    ],
    "name:epo_x_preferred":[
        "Vozuo"
    ],
    "name:est_x_preferred":[
        "Abdest"
    ],
    "name:fas_x_preferred":[
        "\u0648\u0636\u0648"
    ],
    "name:fin_x_preferred":[
        "Abdest"
    ],
    "name:fra_x_preferred":[
        "Wodz\u016b"
    ],
    "name:guj_x_preferred":[
        "\u0ab5\u0ac1\u0a9d\u0ac2"
    ],
    "name:hau_x_preferred":[
        "Alwala"
    ],
    "name:heb_x_preferred":[
        "\u05d5\u05d5\u05d3\u05d5\u05d0"
    ],
    "name:hin_x_preferred":[
        "\u0935\u0941\u091c\u093c\u0942"
    ],
    "name:hrv_x_preferred":[
        "Abdest"
    ],
    "name:ind_x_preferred":[
        "Wudu"
    ],
    "name:ita_x_preferred":[
        "Wu\u1e0d\u016b\u02be"
    ],
    "name:jav_x_preferred":[
        "Wudu"
    ],
    "name:jpn_x_preferred":[
        "\u30a6\u30c9\u30a5"
    ],
    "name:kor_x_preferred":[
        "\uc6b0\ub450"
    ],
    "name:kur_x_preferred":[
        "Destnim\u00eaj"
    ],
    "name:lbe_x_preferred":[
        "\u0418\u0441\u0441\u0430\u0432\u0443"
    ],
    "name:mal_x_preferred":[
        "\u0d35\u0d41\u0d26\u0d41"
    ],
    "name:mkd_x_preferred":[
        "\u0410\u0431\u0434\u0435\u0441\u0442"
    ],
    "name:msa_x_preferred":[
        "Wuduk"
    ],
    "name:nld_x_preferred":[
        "Woedoe"
    ],
    "name:nor_x_preferred":[
        "Wudu"
    ],
    "name:pol_x_preferred":[
        "Abdest"
    ],
    "name:por_x_preferred":[
        "Abdesto"
    ],
    "name:rus_x_preferred":[
        "\u0412\u0443\u0434\u0443"
    ],
    "name:spa_x_preferred":[
        "Wudu"
    ],
    "name:sqi_x_preferred":[
        "Abdesi"
    ],
    "name:srp_x_preferred":[
        "\u0410\u0431\u0434\u0435\u0441\u0442"
    ],
    "name:sun_x_preferred":[
        "Abdas"
    ],
    "name:swe_x_preferred":[
        "Abdest"
    ],
    "name:tgk_x_preferred":[
        "\u0412\u0443\u0437\u04ef"
    ],
    "name:tur_x_preferred":[
        "Abdest"
    ],
    "name:urd_x_preferred":[
        "\u0648\u0636\u0648"
    ],
    "wof:name":"Wudu",
    "wof:placetype":"locality"
},
  "geometry": {"coordinates":[119.88064,-9.46557],"type":"Point"}
}