{
  "type": "Feature",
  "properties": {
    "gn:admin1_code":"30",
    "gn:asciiname":"Cisuba",
    "gn:country_code":"ID",
    "gn:dem":600,
    "gn:feature_class":"P",
    "gn:feature_code":"PPL",
    "gn:name":"Cisuba",
    "gn:population":0,
    "gn:timezone":"Asia/Jakarta",
    "iso:country":"ID",
    "name:ind_x_preferred":[
        "Cisuba"
    ],
    "wof:name":"Cisuba",
    "wof:placetype":"locality"
},
  "geometry": {"coordinates":[106.71028,-6.90111],"type":"Point"}
}