{
  "type": "Feature",
  "properties": {
    "gn:admin1_code":"17.0",
    "gn:asciiname":"Gapit",
    "gn:country_code":"ID",
    "gn:dem":13,
    "gn:feature_class":"P",
    "gn:feature_code":"PPL",
    "gn:name":"Gapit",
    "gn:population":0,
    "gn:timezone":"Asia/Makassar",
    "iso:country":"ID",
    "name:ind_x_preferred":[
        "Gapit"
    ],
    "wof:name":"Gapit",
    "wof:placetype":"locality"
},
  "geometry": {"coordinates":[117.93980000000001,-8.7692],"type":"Point"}
}