{
  "type": "Feature",
  "properties": {
    "gn:admin1_code":"31.0",
    "gn:asciiname":"Lingkungan Satu Inobonto Satu",
    "gn:country_code":"ID",
    "gn:dem":5,
    "gn:feature_class":"P",
    "gn:feature_code":"PPL",
    "gn:name":"Lingkungan Satu Inobonto Satu",
    "gn:population":0,
    "gn:timezone":"Asia/Makassar",
    "iso:country":"ID",
    "name:ind_x_preferred":[
        "Lingkungan Satu Inobonto Satu"
    ],
    "name:und_x_variant":[
        "Lingkungan 1 Inobonto 1"
    ],
    "wof:lang_x_official":[
        "ind"
    ],
    "wof:lang_x_spoken":[
        "ind",
        "eng"
    ],
    "wof:name":"Lingkungan Satu Inobonto Satu",
    "wof:placetype":"locality"
},
  "geometry": {"coordinates":[124.09699999999999,0.9175],"type":"Point"}
}