{
  "type": "Feature",
  "properties": {
    "gn:admin1_code":"30",
    "gn:asciiname":"Cinangka",
    "gn:country_code":"ID",
    "gn:dem":48,
    "gn:feature_class":"P",
    "gn:feature_code":"PPL",
    "gn:name":"Cinangka",
    "gn:population":0,
    "gn:timezone":"Asia/Jakarta",
    "iso:country":"ID",
    "name:ind_x_preferred":[
        "Cinangka"
    ],
    "name:jav_x_preferred":[
        "Cinangka"
    ],
    "name:msa_x_preferred":[
        "Cinangka"
    ],
    "name:nld_x_preferred":[
        "Cinangka"
    ],
    "name:sun_x_preferred":[
        "Cinangka"
    ],
    "wof:name":"Cinangka",
    "wof:placetype":"locality"
},
  "geometry": {"coordinates":[107.84028000000001,-6.52083],"type":"Point"}
}