{
  "type": "Feature",
  "properties": {
    "gn:admin1_code":"18.0",
    "gn:asciiname":"Lina",
    "gn:country_code":"ID",
    "gn:dem":753,
    "gn:feature_class":"P",
    "gn:feature_code":"PPL",
    "gn:name":"Lina",
    "gn:population":0,
    "gn:timezone":"Asia/Makassar",
    "iso:country":"ID",
    "name:ara_x_preferred":[
        "\u0644\u064a\u0646\u0627"
    ],
    "name:bul_x_preferred":[
        "\u041b\u0438\u043d\u0430"
    ],
    "name:deu_x_preferred":[
        "Lina"
    ],
    "name:fin_x_preferred":[
        "Lina"
    ],
    "name:fra_x_preferred":[
        "Lina"
    ],
    "name:heb_x_preferred":[
        "\u05dc\u05d9\u05e0\u05d4"
    ],
    "name:ind_x_preferred":[
        "Lina"
    ],
    "name:ita_x_preferred":[
        "Lina"
    ],
    "name:mkd_x_preferred":[
        "\u041b\u0438\u043d\u0430"
    ],
    "name:nor_x_preferred":[
        "Lina"
    ],
    "name:pol_x_preferred":[
        "Lina"
    ],
    "name:rus_x_preferred":[
        "\u041b\u0438\u043d\u0430"
    ],
    "name:slv_x_preferred":[
        "Lina"
    ],
    "name:srp_x_preferred":[
        "\u041b\u0438\u043d\u0430"
    ],
    "name:swe_x_preferred":[
        "Lina"
    ],
    "name:ukr_x_preferred":[
        "\u041b\u0456\u043d\u0430"
    ],
    "name:vie_x_preferred":[
        "Lina"
    ],
    "wof:name":"Lina",
    "wof:placetype":"locality"
},
  "geometry": {"coordinates":[124.52249999999999,-9.9957],"type":"Point"}
}