{
  "type": "Feature",
  "properties": {
    "gn:admin1_code":"18",
    "gn:asciiname":"Bung",
    "gn:country_code":"ID",
    "gn:dem":873,
    "gn:feature_class":"P",
    "gn:feature_code":"PPL",
    "gn:name":"Bung",
    "gn:population":0,
    "gn:timezone":"Asia/Makassar",
    "iso:country":"ID",
    "name:ind_x_preferred":[
        "Bung"
    ],
    "wof:name":"Bung",
    "wof:placetype":"locality"
},
  "geometry": {"coordinates":[120.3623,-8.6367],"type":"Point"}
}