{
  "type": "Feature",
  "properties": {
    "gn:admin1_code":"38",
    "gn:asciiname":"Lahatung",
    "gn:country_code":"ID",
    "gn:dem":95,
    "gn:feature_class":"P",
    "gn:feature_code":"PPL",
    "gn:name":"Lahatung",
    "gn:population":0,
    "gn:timezone":"Asia/Makassar",
    "iso:country":"ID",
    "name:ind_x_preferred":[
        "Lahatung"
    ],
    "wof:name":"Lahatung",
    "wof:placetype":"locality"
},
  "geometry": {"coordinates":[120.31319999999999,-5.4213],"type":"Point"}
}