{
  "type": "Feature",
  "properties": {
    "gn:admin1_code":"8.0",
    "gn:asciiname":"Bong",
    "gn:country_code":"ID",
    "gn:dem":9,
    "gn:feature_class":"P",
    "gn:feature_code":"PPLA4",
    "gn:name":"Bong",
    "gn:population":0,
    "gn:timezone":"Asia/Jakarta",
    "iso:country":"ID",
    "name:ind_x_preferred":[
        "Bong"
    ],
    "wof:name":"Bong",
    "wof:placetype":"locality"
},
  "geometry": {"coordinates":[113.50008,-7.22608],"type":"Point"}
}