{
  "type": "Feature",
  "properties": {
    "gn:admin1_code":"1",
    "gn:asciiname":"Sungai Belimbing",
    "gn:country_code":"ID",
    "gn:dem":12,
    "gn:feature_class":"P",
    "gn:feature_code":"PPL",
    "gn:name":"Sungai Belimbing",
    "gn:population":0,
    "gn:timezone":"Asia/Jakarta",
    "iso:country":"ID",
    "name:ind_x_preferred":[
        "Sungai Belimbing"
    ],
    "wof:name":"Sungai Belimbing",
    "wof:placetype":"locality"
},
  "geometry": {"coordinates":[99.6888,2.7367],"type":"Point"}
}