{
  "type": "Feature",
  "properties": {
    "gn:admin1_code":"07",
    "gn:asciiname":"Kaden",
    "gn:country_code":"ID",
    "gn:dem":105,
    "gn:feature_class":"P",
    "gn:feature_code":"PPL",
    "gn:name":"Kaden",
    "gn:population":0,
    "gn:timezone":"Asia/Jakarta",
    "iso:country":"ID",
    "name:ara_x_preferred":[
        "\u0643\u0627\u062f\u0646"
    ],
    "name:ceb_x_preferred":[
        "Kaden"
    ],
    "name:deu_x_preferred":[
        "Kaden"
    ],
    "name:epo_x_preferred":[
        "Kaden"
    ],
    "name:eus_x_preferred":[
        "Kaden"
    ],
    "name:fas_x_preferred":[
        "\u06a9\u0627\u062f\u0646"
    ],
    "name:fra_x_preferred":[
        "Kaden"
    ],
    "name:hun_x_preferred":[
        "Kaden"
    ],
    "name:ita_x_preferred":[
        "Kaden"
    ],
    "name:kaz_x_preferred":[
        "\u041a\u0430\u0434\u0435\u043d"
    ],
    "name:kir_x_preferred":[
        "\u041a\u0430\u0434\u0435\u043d"
    ],
    "name:msa_x_preferred":[
        "Kaden"
    ],
    "name:nld_x_preferred":[
        "Kaden"
    ],
    "name:pol_x_preferred":[
        "Kaden"
    ],
    "name:por_x_preferred":[
        "Kaden"
    ],
    "name:ron_x_preferred":[
        "Kaden"
    ],
    "name:rus_x_preferred":[
        "\u041a\u0430\u0434\u0435\u043d"
    ],
    "name:spa_x_preferred":[
        "Kaden"
    ],
    "name:srp_x_preferred":[
        "\u041a\u0430\u0434\u0435\u043d"
    ],
    "name:ukr_x_preferred":[
        "\u041a\u0430\u0434\u0435\u043d"
    ],
    "name:uzb_x_preferred":[
        "Kaden"
    ],
    "name:vol_x_preferred":[
        "Kaden"
    ],
    "name:war_x_preferred":[
        "Kaden"
    ],
    "wof:lang_x_official":[
        "ind"
    ],
    "wof:lang_x_spoken":[
        "ind",
        "eng"
    ],
    "wof:name":"Kaden",
    "wof:placetype":"locality"
},
  "geometry": {"coordinates":[110.71111000000001,-7.74833],"type":"Point"}
}