{
  "type": "Feature",
  "properties": {
    "gn:admin1_code":"8.0",
    "gn:asciiname":"Alastipis",
    "gn:country_code":"ID",
    "gn:dem":5,
    "gn:feature_class":"P",
    "gn:feature_code":"PPL",
    "gn:name":"Alastipis",
    "gn:population":0,
    "gn:timezone":"Asia/Jakarta",
    "iso:country":"ID",
    "name:ind_x_preferred":[
        "Alastipis"
    ],
    "wof:name":"Alastipis",
    "wof:placetype":"locality"
},
  "geometry": {"coordinates":[112.7478,-7.3657],"type":"Point"}
}