{
  "type": "Feature",
  "properties": {
    "gn:admin1_code":"8",
    "gn:asciiname":"Jlorong",
    "gn:country_code":"ID",
    "gn:dem":47,
    "gn:feature_class":"P",
    "gn:feature_code":"PPL",
    "gn:name":"Jlorong",
    "gn:population":0,
    "gn:timezone":"Asia/Jakarta",
    "iso:country":"ID",
    "name:ind_x_preferred":[
        "Jlorong"
    ],
    "wof:name":"Jlorong",
    "wof:placetype":"locality"
},
  "geometry": {"coordinates":[112.806,-7.67],"type":"Point"}
}