{
  "type": "Feature",
  "properties": {
    "gn:admin1_code":"30.0",
    "gn:asciiname":"Gelarmukti",
    "gn:country_code":"ID",
    "gn:dem":365,
    "gn:feature_class":"P",
    "gn:feature_code":"PPLA4",
    "gn:name":"Gelarmukti",
    "gn:population":0,
    "gn:timezone":"Asia/Jakarta",
    "iso:country":"ID",
    "name:ind_x_preferred":[
        "Gelarmukti"
    ],
    "wof:name":"Gelarmukti",
    "wof:placetype":"locality"
},
  "geometry": {"coordinates":[107.06950000000001,-7.3398],"type":"Point"}
}