{
  "type": "Feature",
  "properties": {
    "gn:admin1_code":"1",
    "gn:asciiname":"Bugeng",
    "gn:country_code":"ID",
    "gn:dem":10,
    "gn:feature_class":"P",
    "gn:feature_code":"PPL",
    "gn:name":"Bugeng",
    "gn:population":0,
    "gn:timezone":"Asia/Jakarta",
    "iso:country":"ID",
    "name:ind_x_preferred":[
        "Bugeng"
    ],
    "wof:name":"Bugeng",
    "wof:placetype":"locality"
},
  "geometry": {"coordinates":[96.8258,5.2485],"type":"Point"}
}