{
  "type": "Feature",
  "properties": {
    "gn:admin1_code":"18",
    "gn:asciiname":"Maudemi",
    "gn:country_code":"ID",
    "gn:dem":928,
    "gn:feature_class":"P",
    "gn:feature_code":"PPL",
    "gn:name":"Maudemi",
    "gn:population":0,
    "gn:timezone":"Asia/Makassar",
    "iso:country":"ID",
    "wof:name":"Maudemi",
    "wof:placetype":"locality"
},
  "geometry": {"coordinates":[125.05,-9.12694],"type":"Point"}
}