{
  "type": "Feature",
  "properties": {
    "gn:admin1_code":"31.0",
    "gn:asciiname":"Bune",
    "gn:country_code":"ID",
    "gn:dem":23,
    "gn:feature_class":"P",
    "gn:feature_code":"PPL",
    "gn:name":"Bune",
    "gn:population":0,
    "gn:timezone":"Asia/Makassar",
    "iso:country":"ID",
    "name:und_x_variant":[
        "Boeneh",
        "Buneh",
        "Boene",
        "Bune"
    ],
    "wof:name":"Bune",
    "wof:placetype":"locality"
},
  "geometry": {"coordinates":[126.85082,4.47264],"type":"Point"}
}