{
  "type": "Feature",
  "properties": {
    "gn:admin1_code":"8",
    "gn:asciiname":"Sendanganyar",
    "gn:country_code":"ID",
    "gn:dem":20,
    "gn:feature_class":"P",
    "gn:feature_code":"PPL",
    "gn:name":"Sendanganyar",
    "gn:population":0,
    "gn:timezone":"Asia/Jakarta",
    "iso:country":"ID",
    "name:ind_x_preferred":[
        "Sendanganyar"
    ],
    "wof:name":"Sendanganyar",
    "wof:placetype":"locality"
},
  "geometry": {"coordinates":[112.11660000000001,-7.1185],"type":"Point"}
}