{
  "type": "Feature",
  "properties": {
    "gn:admin1_code":"1.0",
    "gn:asciiname":"Krueng Lingka Barat",
    "gn:country_code":"ID",
    "gn:dem":10,
    "gn:feature_class":"P",
    "gn:feature_code":"PPL",
    "gn:name":"Krueng Lingka Barat",
    "gn:population":0,
    "gn:timezone":"Asia/Jakarta",
    "iso:country":"ID",
    "name:ind_x_preferred":[
        "Krueng Lingka Barat"
    ],
    "name:und_x_variant":[
        "Lingka-barat"
    ],
    "wof:name":"Krueng Lingka Barat",
    "wof:placetype":"locality"
},
  "geometry": {"coordinates":[97.42659999999999,5.1566],"type":"Point"}
}