{
  "type": "Feature",
  "properties": {
    "gn:admin1_code":"18.0",
    "gn:asciiname":"Gurilogo",
    "gn:country_code":"ID",
    "gn:dem":71,
    "gn:feature_class":"P",
    "gn:feature_code":"PPL",
    "gn:name":"Gurilogo",
    "gn:population":0,
    "gn:timezone":"Asia/Makassar",
    "iso:country":"ID",
    "name:ind_x_preferred":[
        "Gurilogo"
    ],
    "wof:name":"Gurilogo",
    "wof:placetype":"locality"
},
  "geometry": {"coordinates":[121.8823,-10.5821],"type":"Point"}
}