{
  "type": "Feature",
  "properties": {
    "gn:admin1_code":"7.0",
    "gn:asciiname":"Cemororejo",
    "gn:country_code":"ID",
    "gn:dem":228,
    "gn:feature_class":"P",
    "gn:feature_code":"PPL",
    "gn:name":"Cemororejo",
    "gn:population":0,
    "gn:timezone":"Asia/Jakarta",
    "iso:country":"ID",
    "wof:name":"Cemororejo",
    "wof:placetype":"locality"
},
  "geometry": {"coordinates":[110.30028,-7.675],"type":"Point"}
}