{
  "type": "Feature",
  "properties": {
    "gn:admin1_code":"8.0",
    "gn:asciiname":"Bulaksani",
    "gn:country_code":"ID",
    "gn:dem":301,
    "gn:feature_class":"P",
    "gn:feature_code":"PPL",
    "gn:name":"Bulaksani",
    "gn:population":0,
    "gn:timezone":"Asia/Jakarta",
    "iso:country":"ID",
    "name:ind_x_preferred":[
        "Bulaksani"
    ],
    "wof:name":"Bulaksani",
    "wof:placetype":"locality"
},
  "geometry": {"coordinates":[112.6683,-7.6663],"type":"Point"}
}