{
  "type": "Feature",
  "properties": {
    "gn:admin1_code":"31.0",
    "gn:asciiname":"Sapaeng",
    "gn:country_code":"ID",
    "gn:dem":29,
    "gn:feature_class":"P",
    "gn:feature_code":"PPL",
    "gn:name":"Sapaeng",
    "gn:population":0,
    "gn:timezone":"Asia/Makassar",
    "iso:country":"ID",
    "name:ind_x_preferred":[
        "Sapaeng"
    ],
    "wof:name":"Sapaeng",
    "wof:placetype":"locality"
},
  "geometry": {"coordinates":[125.5733,3.339],"type":"Point"}
}