{
  "type": "Feature",
  "properties": {
    "gn:admin1_code":"38",
    "gn:asciiname":"Ujung",
    "gn:country_code":"ID",
    "gn:dem":30,
    "gn:feature_class":"P",
    "gn:feature_code":"PPL",
    "gn:name":"Ujung",
    "gn:population":0,
    "gn:timezone":"Asia/Makassar",
    "iso:country":"ID",
    "name:ind_x_preferred":[
        "Ujung"
    ],
    "name:nld_x_preferred":[
        "Ujung"
    ],
    "wof:name":"Ujung",
    "wof:placetype":"locality"
},
  "geometry": {"coordinates":[119.7422,-3.764],"type":"Point"}
}