{
  "type": "Feature",
  "properties": {
    "gn:admin1_code":"18.0",
    "gn:asciiname":"Gade",
    "gn:country_code":"ID",
    "gn:dem":355,
    "gn:feature_class":"P",
    "gn:feature_code":"PPL",
    "gn:name":"Gade",
    "gn:population":0,
    "gn:timezone":"Asia/Makassar",
    "iso:country":"ID",
    "name:dan_x_preferred":[
        "Gade"
    ],
    "name:deu_x_preferred":[
        "Gade"
    ],
    "name:ind_x_preferred":[
        "Gade"
    ],
    "name:jpn_x_preferred":[
        "\u30b2\u30fc\u30bc"
    ],
    "name:nld_x_preferred":[
        "Gade"
    ],
    "name:nor_x_preferred":[
        "Gade"
    ],
    "name:por_x_preferred":[
        "Gade"
    ],
    "name:spa_x_preferred":[
        "Gade"
    ],
    "name:swe_x_preferred":[
        "Gade"
    ],
    "name:wln_x_preferred":[
        "Gade"
    ],
    "wof:lang_x_official":[
        "ind"
    ],
    "wof:lang_x_spoken":[
        "ind",
        "eng"
    ],
    "wof:name":"Gade",
    "wof:placetype":"locality"
},
  "geometry": {"coordinates":[122.2606,-8.7286],"type":"Point"}
}