{
  "type": "Feature",
  "properties": {
    "gn:admin1_code":"7.0",
    "gn:asciiname":"Tanjung Timur",
    "gn:country_code":"ID",
    "gn:dem":51,
    "gn:feature_class":"P",
    "gn:feature_code":"PPLA4",
    "gn:name":"Tanjung Timur",
    "gn:population":0,
    "gn:timezone":"Asia/Jakarta",
    "iso:country":"ID",
    "name:ind_x_preferred":[
        "Tanjung Timur"
    ],
    "name:ind_x_variant":[
        "Rumah Tanjung Timur"
    ],
    "wof:name":"Tanjung Timur",
    "wof:placetype":"locality"
},
  "geometry": {"coordinates":[111.4987,-7.187],"type":"Point"}
}