{
  "type": "Feature",
  "properties": {
    "gn:admin1_code":"15.0",
    "gn:asciiname":"Wayrate",
    "gn:country_code":"ID",
    "gn:dem":76,
    "gn:feature_class":"P",
    "gn:feature_code":"PPL",
    "gn:name":"Wayrate",
    "gn:population":0,
    "gn:timezone":"Asia/Jakarta",
    "iso:country":"ID",
    "name:ind_x_preferred":[
        "Wayrate"
    ],
    "wof:name":"Wayrate",
    "wof:placetype":"locality"
},
  "geometry": {"coordinates":[105.15354000000001,-5.25712],"type":"Point"}
}