{
  "type": "Feature",
  "properties": {
    "gn:admin1_code":"7.0",
    "gn:asciiname":"Langkap",
    "gn:country_code":"ID",
    "gn:dem":132,
    "gn:feature_class":"P",
    "gn:feature_code":"PPL",
    "gn:name":"Langkap",
    "gn:population":0,
    "gn:timezone":"Asia/Jakarta",
    "iso:country":"ID",
    "name:epo_x_preferred":[
        "Langkap"
    ],
    "name:ind_x_preferred":[
        "Langkap"
    ],
    "name:msa_x_preferred":[
        "Langkap"
    ],
    "wof:name":"Langkap",
    "wof:placetype":"locality"
},
  "geometry": {"coordinates":[110.79306,-7.75694],"type":"Point"}
}