{
  "type": "Feature",
  "properties": {
    "gn:admin1_code":"18",
    "gn:asciiname":"Matalong",
    "gn:country_code":"ID",
    "gn:dem":540,
    "gn:feature_class":"P",
    "gn:feature_code":"PPL",
    "gn:name":"Matalong",
    "gn:population":0,
    "gn:timezone":"Asia/Makassar",
    "iso:country":"ID",
    "name:ind_x_preferred":[
        "Matalong"
    ],
    "wof:name":"Matalong",
    "wof:placetype":"locality"
},
  "geometry": {"coordinates":[119.9254,-9.6401],"type":"Point"}
}