{
  "type": "Feature",
  "properties": {
    "gn:admin1_code":"8",
    "gn:asciiname":"Kemiri",
    "gn:country_code":"ID",
    "gn:dem":328,
    "gn:feature_class":"P",
    "gn:feature_code":"PPL",
    "gn:name":"Kemiri",
    "gn:population":0,
    "gn:timezone":"Asia/Jakarta",
    "iso:country":"ID",
    "name:ind_x_preferred":[
        "Kemiri"
    ],
    "wof:name":"Kemiri",
    "wof:placetype":"locality"
},
  "geometry": {"coordinates":[111.5783,-7.8063],"type":"Point"}
}