{
  "type": "Feature",
  "properties": {
    "gn:admin1_code":"7",
    "gn:asciiname":"Kaliampo",
    "gn:country_code":"ID",
    "gn:dem":24,
    "gn:feature_class":"P",
    "gn:feature_code":"PPL",
    "gn:name":"Kaliampo",
    "gn:population":0,
    "gn:timezone":"Asia/Jakarta",
    "iso:country":"ID",
    "name:ind_x_preferred":[
        "Kaliampo"
    ],
    "wof:name":"Kaliampo",
    "wof:placetype":"locality"
},
  "geometry": {"coordinates":[110.9751,-6.7904],"type":"Point"}
}