{
  "type": "Feature",
  "properties": {
    "gn:admin1_code":"1",
    "gn:asciiname":"Pauk",
    "gn:country_code":"ID",
    "gn:dem":13,
    "gn:feature_class":"P",
    "gn:feature_code":"PPL",
    "gn:name":"Pauk",
    "gn:population":0,
    "gn:timezone":"Asia/Jakarta",
    "iso:country":"ID",
    "name:ind_x_preferred":[
        "Pauk"
    ],
    "wof:name":"Pauk",
    "wof:placetype":"locality"
},
  "geometry": {"coordinates":[96.19029999999999,4.2656],"type":"Point"}
}