{
  "type": "Feature",
  "properties": {
    "gn:admin1_code":"1",
    "gn:asciiname":"Pauk",
    "gn:country_code":"ID",
    "gn:dem":13,
    "gn:feature_class":"P",
    "gn:feature_code":"PPL",
    "gn:name":"Pauk",
    "gn:population":0,
    "gn:timezone":"Asia/Jakarta",
    "iso:country":"ID",
    "name:ind_x_preferred":[
        "Pauk"
    ],
    "name:mya_x_preferred":[
        "\u1015\u1031\u102b\u1000\u103a\u1019\u103c\u102d\u102f\u1037"
    ],
    "name:shn_x_preferred":[
        "\u1015\u103d\u1075\u103a\u1089\u104a \u101d\u1035\u1004\u103a\u1038"
    ],
    "name:zho_x_preferred":[
        "\u5305"
    ],
    "wof:name":"Pauk",
    "wof:placetype":"locality"
},
  "geometry": {"coordinates":[96.19029999999999,4.2656],"type":"Point"}
}