{
  "type": "Feature",
  "properties": {
    "gn:admin1_code":"26",
    "gn:asciiname":"Limpata",
    "gn:country_code":"ID",
    "gn:dem":291,
    "gn:feature_class":"P",
    "gn:feature_code":"PPL",
    "gn:name":"Limpata",
    "gn:population":0,
    "gn:timezone":"Asia/Jakarta",
    "iso:country":"ID",
    "name:ind_x_preferred":[
        "Limpata"
    ],
    "wof:name":"Limpata",
    "wof:placetype":"locality"
},
  "geometry": {"coordinates":[99.29609000000001,1.34598],"type":"Point"}
}