{
  "type": "Feature",
  "properties": {
    "gn:admin1_code":"2.0",
    "gn:asciiname":"Seribatu",
    "gn:country_code":"ID",
    "gn:dem":826,
    "gn:feature_class":"P",
    "gn:feature_code":"PPL",
    "gn:name":"Seribatu",
    "gn:population":0,
    "gn:timezone":"Asia/Makassar",
    "iso:country":"ID",
    "name:ind_x_preferred":[
        "Banjar Seribatu"
    ],
    "name:und_x_variant":[
        "Seribatoe",
        "Seribatu"
    ],
    "wof:lang_x_official":[
        "ind"
    ],
    "wof:lang_x_spoken":[
        "ind",
        "eng"
    ],
    "wof:name":"Seribatu",
    "wof:placetype":"locality"
},
  "geometry": {"coordinates":[115.3441,-8.3682],"type":"Point"}
}