{
  "type": "Feature",
  "properties": {
    "gn:admin1_code":"17.0",
    "gn:asciiname":"Punik",
    "gn:country_code":"ID",
    "gn:dem":12,
    "gn:feature_class":"P",
    "gn:feature_code":"PPL",
    "gn:name":"Punik",
    "gn:population":0,
    "gn:timezone":"Asia/Makassar",
    "iso:country":"ID",
    "name:aze_x_preferred":[
        "D\u0259d\u0259q\u0131\u015flaq"
    ],
    "name:fas_x_preferred":[
        "\u067e\u0648\u0646\u06cc\u06a9"
    ],
    "name:hye_x_preferred":[
        "\u0553\u0575\u0578\u0582\u0576\u056b\u056f"
    ],
    "name:ind_x_preferred":[
        "Punik"
    ],
    "wof:name":"Punik",
    "wof:placetype":"locality"
},
  "geometry": {"coordinates":[116.6567,-8.5335],"type":"Point"}
}