{
  "type": "Feature",
  "properties": {
    "gn:admin1_code":"36.0",
    "gn:asciiname":"Magguwop",
    "gn:country_code":"ID",
    "gn:dem":57,
    "gn:feature_class":"P",
    "gn:feature_code":"PPL",
    "gn:name":"Magguwop",
    "gn:population":0,
    "gn:timezone":"Asia/Jayapura",
    "iso:country":"ID",
    "name:ind_x_preferred":[
        "Magguwop"
    ],
    "wof:name":"Magguwop",
    "wof:placetype":"locality"
},
  "geometry": {"coordinates":[140.38721000000001,-5.99339],"type":"Point"}
}