{
  "type": "Feature",
  "properties": {
    "gn:admin1_code":"17.0",
    "gn:asciiname":"Sambitangga",
    "gn:country_code":"ID",
    "gn:dem":36,
    "gn:feature_class":"P",
    "gn:feature_code":"PPL",
    "gn:name":"Sambitangga",
    "gn:population":0,
    "gn:timezone":"Asia/Makassar",
    "iso:country":"ID",
    "name:ind_x_preferred":[
        "Sambitangga"
    ],
    "wof:name":"Sambitangga",
    "wof:placetype":"locality"
},
  "geometry": {"coordinates":[118.5835,-8.5242],"type":"Point"}
}