{
  "type": "Feature",
  "properties": {
    "gn:admin1_code":"7.0",
    "gn:asciiname":"Plongokan",
    "gn:country_code":"ID",
    "gn:dem":14,
    "gn:feature_class":"P",
    "gn:feature_code":"PPL",
    "gn:name":"Plongokan",
    "gn:population":0,
    "gn:timezone":"Asia/Jakarta",
    "iso:country":"ID",
    "name:ind_x_preferred":[
        "Plongokan"
    ],
    "wof:name":"Plongokan",
    "wof:placetype":"locality"
},
  "geometry": {"coordinates":[109.49388999999999,-7.72889],"type":"Point"}
}