{
  "type": "Feature",
  "properties": {
    "gn:admin1_code":"24",
    "gn:asciiname":"Paramanguo",
    "gn:country_code":"ID",
    "gn:dem":255,
    "gn:feature_class":"P",
    "gn:feature_code":"PPL",
    "gn:name":"Paramanguo",
    "gn:population":0,
    "gn:timezone":"Asia/Jakarta",
    "iso:country":"ID",
    "name:ind_x_preferred":[
        "Paramanguo"
    ],
    "wof:name":"Paramanguo",
    "wof:placetype":"locality"
},
  "geometry": {"coordinates":[99.5129,0.4359],"type":"Point"}
}