{
  "type": "Feature",
  "properties": {
    "gn:admin1_code":"8",
    "gn:asciiname":"Buntaran",
    "gn:country_code":"ID",
    "gn:dem":116,
    "gn:feature_class":"P",
    "gn:feature_code":"PPL",
    "gn:name":"Buntaran",
    "gn:population":0,
    "gn:timezone":"Asia/Jakarta",
    "iso:country":"ID",
    "name:ind_x_preferred":[
        "Buntaran"
    ],
    "wof:name":"Buntaran",
    "wof:placetype":"locality"
},
  "geometry": {"coordinates":[112.05,-8.1131],"type":"Point"}
}