{
  "type": "Feature",
  "properties": {
    "gn:admin1_code":"7.0",
    "gn:asciiname":"Jakensawahan",
    "gn:country_code":"ID",
    "gn:dem":35,
    "gn:feature_class":"P",
    "gn:feature_code":"PPL",
    "gn:name":"Jakensawahan",
    "gn:population":0,
    "gn:timezone":"Asia/Jakarta",
    "iso:country":"ID",
    "name:ind_x_preferred":[
        "Jakensawahan"
    ],
    "wof:name":"Jakensawahan",
    "wof:placetype":"locality"
},
  "geometry": {"coordinates":[111.2397,-6.7817],"type":"Point"}
}