{
  "type": "Feature",
  "properties": {
    "gn:country":"ID",
    "gn:fcode":"PPL",
    "gn:pop":0,
    "iso:country":"ID",
    "name:ind_x_preferred":[
        "Motoling"
    ],
    "name:unk_x_variant":[
        "Motaling"
    ],
    "qs:name":"Motoling",
    "qs:name_adm0":"Indonesia",
    "qs:name_adm1":"Sulawesi Utara",
    "qs:photos_9r":0,
    "qs:photos_sr":0,
    "qs:placetype":"Town",
    "qs:pop_sr":"6",
    "wof:lang_x_official":[
        "ind"
    ],
    "wof:lang_x_spoken":[
        "ind",
        "eng"
    ],
    "wof:name":"Motoling",
    "wof:placetype":"locality",
    "wof:population":0
},
  "geometry": {"coordinates":[124.4787,1.0403],"type":"Point"}
}