{
  "type": "Feature",
  "properties": {
    "gn:admin1_code":"30",
    "gn:asciiname":"Ciputat",
    "gn:country_code":"ID",
    "gn:dem":213,
    "gn:feature_class":"P",
    "gn:feature_code":"PPL",
    "gn:name":"Ciputat",
    "gn:population":0,
    "gn:timezone":"Asia/Jakarta",
    "iso:country":"ID",
    "name:ind_x_preferred":[
        "Ciputat"
    ],
    "wof:name":"Ciputat",
    "wof:placetype":"locality"
},
  "geometry": {"coordinates":[108.5809,-6.9758],"type":"Point"}
}