{
  "type": "Feature",
  "properties": {
    "gn:admin1_code":"33.0",
    "gn:asciiname":"Kadusarung",
    "gn:country_code":"ID",
    "gn:dem":139,
    "gn:feature_class":"P",
    "gn:feature_code":"PPL",
    "gn:name":"Kadusarung",
    "gn:population":0,
    "gn:timezone":"Asia/Jakarta",
    "iso:country":"ID",
    "name:ind_x_preferred":[
        "Kadusarung"
    ],
    "wof:name":"Kadusarung",
    "wof:placetype":"locality"
},
  "geometry": {"coordinates":[105.9118,-6.1672],"type":"Point"}
}