{
  "type": "Feature",
  "properties": {
    "gn:admin1_code":"18.0",
    "gn:asciiname":"Patupolo",
    "gn:country_code":"ID",
    "gn:dem":989,
    "gn:feature_class":"P",
    "gn:feature_code":"PPL",
    "gn:name":"Patupolo",
    "gn:population":0,
    "gn:timezone":"Asia/Makassar",
    "iso:country":"ID",
    "name:ind_x_preferred":[
        "Patupolo"
    ],
    "wof:name":"Patupolo",
    "wof:placetype":"locality"
},
  "geometry": {"coordinates":[124.25790000000001,-9.7344],"type":"Point"}
}