{
  "type": "Feature",
  "properties": {
    "gn:admin1_code":"21.0",
    "gn:asciiname":"Bolano Satu",
    "gn:country_code":"ID",
    "gn:dem":8,
    "gn:feature_class":"P",
    "gn:feature_code":"PPL",
    "gn:name":"Bolano Satu",
    "gn:population":0,
    "gn:timezone":"Asia/Makassar",
    "iso:country":"ID",
    "name:ind_x_preferred":[
        "Bolano Satu"
    ],
    "name:und_x_variant":[
        "Bolamo",
        "Bolano",
        "Boraa",
        "Bolano 1",
        "Balano"
    ],
    "wof:lang_x_official":[
        "ind"
    ],
    "wof:lang_x_spoken":[
        "ind",
        "eng"
    ],
    "wof:name":"Bolano Satu",
    "wof:placetype":"locality"
},
  "geometry": {"coordinates":[120.955,0.4427],"type":"Point"}
}