{
  "type": "Feature",
  "properties": {
    "gn:admin1_code":"17",
    "gn:asciiname":"Sigi",
    "gn:country_code":"ID",
    "gn:dem":35,
    "gn:feature_class":"P",
    "gn:feature_code":"PPL",
    "gn:name":"Sigi",
    "gn:population":0,
    "gn:timezone":"Asia/Makassar",
    "iso:country":"ID",
    "name:deu_x_preferred":[
        "Sigi"
    ],
    "name:fra_x_preferred":[
        "Sigi"
    ],
    "name:ind_x_preferred":[
        "Sigi"
    ],
    "name:kor_x_preferred":[
        "\uc2dc\uae30"
    ],
    "name:nld_x_preferred":[
        "Sigi"
    ],
    "name:spa_x_preferred":[
        "Sigi"
    ],
    "wof:lang_x_official":[
        "ind"
    ],
    "wof:lang_x_spoken":[
        "ind",
        "eng"
    ],
    "wof:name":"Sigi",
    "wof:placetype":"locality"
},
  "geometry": {"coordinates":[118.72499000000001,-8.62438],"type":"Point"}
}