{
  "type": "Feature",
  "properties": {
    "gn:admin1_code":"10.0",
    "gn:asciiname":"Kalibogo",
    "gn:cc2":"ID",
    "gn:country_code":"ID",
    "gn:dem":327,
    "gn:feature_class":"P",
    "gn:feature_code":"PPL",
    "gn:name":"Kalibogo",
    "gn:population":0,
    "gn:timezone":"Asia/Jakarta",
    "iso:country":"ID",
    "name:und_x_variant":[
        "Kalibuko",
        "Kalibogo"
    ],
    "wof:name":"Kalibogo",
    "wof:placetype":"locality"
},
  "geometry": {"coordinates":[110.0825,-7.82833],"type":"Point"}
}