{
  "type": "Feature",
  "properties": {
    "gn:admin1_code":"30",
    "gn:asciiname":"Pasireungit Landeuh",
    "gn:country_code":"ID",
    "gn:dem":401,
    "gn:feature_class":"P",
    "gn:feature_code":"PPL",
    "gn:name":"Pasireungit Landeuh",
    "gn:population":0,
    "gn:timezone":"Asia/Jakarta",
    "iso:country":"ID",
    "name:ind_x_preferred":[
        "Pasireungit Landeuh"
    ],
    "wof:name":"Pasireungit Landeuh",
    "wof:placetype":"locality"
},
  "geometry": {"coordinates":[108.01806000000001,-6.80083],"type":"Point"}
}