{
  "type": "Feature",
  "properties": {
    "gn:admin1_code":"33.0",
    "gn:asciiname":"Kadawung",
    "gn:country_code":"ID",
    "gn:dem":142,
    "gn:feature_class":"P",
    "gn:feature_code":"PPL",
    "gn:name":"Kadawung",
    "gn:population":0,
    "gn:timezone":"Asia/Jakarta",
    "iso:country":"ID",
    "name:ind_x_preferred":[
        "Kadawung"
    ],
    "wof:name":"Kadawung",
    "wof:placetype":"locality"
},
  "geometry": {"coordinates":[106.05840000000001,-6.3789],"type":"Point"}
}