{
  "type": "Feature",
  "properties": {
    "gn:admin1_code":"36.0",
    "gn:asciiname":"Tutainom",
    "gn:country_code":"ID",
    "gn:dem":40,
    "gn:feature_class":"P",
    "gn:feature_code":"PPL",
    "gn:name":"Tutainom",
    "gn:population":0,
    "gn:timezone":"Asia/Jayapura",
    "iso:country":"ID",
    "name:ind_x_preferred":[
        "Tutainom"
    ],
    "wof:name":"Tutainom",
    "wof:placetype":"locality"
},
  "geometry": {"coordinates":[140.36869999999999,-6.36977],"type":"Point"}
}