{
  "type": "Feature",
  "properties": {
    "gn:admin1_code":"8.0",
    "gn:asciiname":"Los",
    "gn:country_code":"ID",
    "gn:dem":246,
    "gn:feature_class":"P",
    "gn:feature_code":"PPL",
    "gn:name":"Los",
    "gn:population":0,
    "gn:timezone":"Asia/Jakarta",
    "iso:country":"ID",
    "name:bel_x_preferred":[
        "\u041b\u043e\u0441\u044c"
    ],
    "name:ceb_x_preferred":[
        "Los"
    ],
    "name:ces_x_preferred":[
        "Los"
    ],
    "name:deu_x_preferred":[
        "Los"
    ],
    "name:fin_x_preferred":[
        "Los"
    ],
    "name:ind_x_preferred":[
        "Los"
    ],
    "name:nld_x_preferred":[
        "Los"
    ],
    "name:nno_x_preferred":[
        "Los"
    ],
    "name:pol_x_preferred":[
        "Los"
    ],
    "name:rus_x_preferred":[
        "\u041b\u043e\u0441\u044c"
    ],
    "name:swe_x_preferred":[
        "Los"
    ],
    "name:ukr_x_preferred":[
        "\u041b\u043e\u0441\u044c"
    ],
    "wof:lang_x_official":[
        "ind"
    ],
    "wof:lang_x_spoken":[
        "ind",
        "eng"
    ],
    "wof:name":"Los",
    "wof:placetype":"locality"
},
  "geometry": {"coordinates":[113.8485,-7.8966],"type":"Point"}
}