{
  "type": "Feature",
  "properties": {
    "gn:admin1_code":"15.0",
    "gn:asciiname":"Talangsuganda",
    "gn:country_code":"ID",
    "gn:dem":933,
    "gn:feature_class":"P",
    "gn:feature_code":"PPL",
    "gn:name":"Talangsuganda",
    "gn:population":0,
    "gn:timezone":"Asia/Jakarta",
    "iso:country":"ID",
    "name:ind_x_preferred":[
        "Talangsuganda"
    ],
    "wof:name":"Talangsuganda",
    "wof:placetype":"locality"
},
  "geometry": {"coordinates":[104.59896000000001,-5.29624],"type":"Point"}
}