{
  "type": "Feature",
  "properties": {
    "gn:admin1_code":"30.0",
    "gn:asciiname":"Sukahening",
    "gn:country_code":"ID",
    "gn:dem":645,
    "gn:feature_class":"P",
    "gn:feature_code":"PPLA4",
    "gn:name":"Sukahening",
    "gn:population":0,
    "gn:timezone":"Asia/Jakarta",
    "iso:country":"ID",
    "name:ind_x_preferred":[
        "Sukahening"
    ],
    "name:und_x_variant":[
        "Soekahening"
    ],
    "wof:name":"Sukahening",
    "wof:placetype":"locality"
},
  "geometry": {"coordinates":[108.152,-7.2057],"type":"Point"}
}