{
  "type": "Feature",
  "properties": {
    "gn:admin1_code":"22.0",
    "gn:asciiname":"Pulausope",
    "gn:country_code":"ID",
    "gn:dem":8,
    "gn:feature_class":"P",
    "gn:feature_code":"PPL",
    "gn:name":"Pulausope",
    "gn:population":0,
    "gn:timezone":"Asia/Makassar",
    "iso:country":"ID",
    "name:ind_x_preferred":[
        "Pulausope"
    ],
    "wof:name":"Pulausope",
    "wof:placetype":"locality"
},
  "geometry": {"coordinates":[121.6421,-4.8083],"type":"Point"}
}