{
  "type": "Feature",
  "properties": {
    "gn:admin1_code":"33",
    "gn:asciiname":"Kandangsapi",
    "gn:country_code":"ID",
    "gn:dem":51,
    "gn:feature_class":"P",
    "gn:feature_code":"PPL",
    "gn:name":"Kandangsapi",
    "gn:population":0,
    "gn:timezone":"Asia/Jakarta",
    "iso:country":"ID",
    "name:ind_x_preferred":[
        "Kandangsapi"
    ],
    "wof:name":"Kandangsapi",
    "wof:placetype":"locality"
},
  "geometry": {"coordinates":[106.2739,-6.3547],"type":"Point"}
}