{
  "type": "Feature",
  "properties": {
    "gn:admin1_code":"30",
    "gn:asciiname":"Ciseke",
    "gn:country_code":"ID",
    "gn:dem":1458,
    "gn:feature_class":"P",
    "gn:feature_code":"PPL",
    "gn:name":"Ciseke",
    "gn:population":0,
    "gn:timezone":"Asia/Jakarta",
    "iso:country":"ID",
    "wof:name":"Ciseke",
    "wof:placetype":"locality"
},
  "geometry": {"coordinates":[107.54083,-7.21389],"type":"Point"}
}