{
  "type": "Feature",
  "properties": {
    "gn:admin1_code":"30",
    "gn:asciiname":"Angsana",
    "gn:country_code":"ID",
    "gn:dem":295,
    "gn:feature_class":"P",
    "gn:feature_code":"PPL",
    "gn:name":"Angsana",
    "gn:population":0,
    "gn:timezone":"Asia/Jakarta",
    "iso:country":"ID",
    "name:ind_x_preferred":[
        "Angsana"
    ],
    "wof:name":"Angsana",
    "wof:placetype":"locality"
},
  "geometry": {"coordinates":[107.29778,-6.87917],"type":"Point"}
}