{
  "type": "Feature",
  "properties": {
    "gn:admin1_code":"1",
    "gn:asciiname":"Abeuek Budi",
    "gn:country_code":"ID",
    "gn:dem":46,
    "gn:feature_class":"P",
    "gn:feature_code":"PPL",
    "gn:name":"Abeuek Budi",
    "gn:population":0,
    "gn:timezone":"Asia/Jakarta",
    "iso:country":"ID",
    "name:ind_x_preferred":[
        "Abeuek Budi"
    ],
    "name:und_x_variant":[
        "Abeuebudi"
    ],
    "wof:lang_x_official":[
        "ind"
    ],
    "wof:lang_x_spoken":[
        "ind",
        "eng"
    ],
    "wof:name":"Abeuek Budi",
    "wof:placetype":"locality"
},
  "geometry": {"coordinates":[96.72490000000001,5.1481],"type":"Point"}
}