{
  "type": "Feature",
  "properties": {
    "gn:admin1_code":"18.0",
    "gn:asciiname":"Lilkole",
    "gn:country_code":"ID",
    "gn:dem":105,
    "gn:feature_class":"P",
    "gn:feature_code":"PPL",
    "gn:name":"Lilkole",
    "gn:population":0,
    "gn:timezone":"Asia/Makassar",
    "iso:country":"ID",
    "name:ind_x_preferred":[
        "Lilkole"
    ],
    "wof:name":"Lilkole",
    "wof:placetype":"locality"
},
  "geometry": {"coordinates":[123.6953,-9.9206],"type":"Point"}
}