{
  "type": "Feature",
  "properties": {
    "gn:admin1_code":"8.0",
    "gn:asciiname":"Gedongan Kidul",
    "gn:country_code":"ID",
    "gn:dem":330,
    "gn:feature_class":"P",
    "gn:feature_code":"PPL",
    "gn:name":"Gedongan Kidul",
    "gn:population":0,
    "gn:timezone":"Asia/Jakarta",
    "iso:country":"ID",
    "name:ind_x_preferred":[
        "Gedongan Kidul"
    ],
    "wof:name":"Gedongan Kidul",
    "wof:placetype":"locality"
},
  "geometry": {"coordinates":[110.96583,-8.12528],"type":"Point"}
}