{
  "type": "Feature",
  "properties": {
    "gn:admin1_code":"18.0",
    "gn:asciiname":"Fanating",
    "gn:country_code":"ID",
    "gn:dem":23,
    "gn:feature_class":"P",
    "gn:feature_code":"PPL",
    "gn:name":"Fanating",
    "gn:population":0,
    "gn:timezone":"Asia/Makassar",
    "iso:country":"ID",
    "name:ind_x_preferred":[
        "Fanating"
    ],
    "wof:name":"Fanating",
    "wof:placetype":"locality"
},
  "geometry": {"coordinates":[124.5446,-8.2485],"type":"Point"}
}