{
  "type": "Feature",
  "properties": {
    "gn:admin1_code":"15.0",
    "gn:asciiname":"Bayas Lama",
    "gn:country_code":"ID",
    "gn:dem":328,
    "gn:feature_class":"P",
    "gn:feature_code":"PPL",
    "gn:name":"Bayas Lama",
    "gn:population":0,
    "gn:timezone":"Asia/Jakarta",
    "iso:country":"ID",
    "name:ind_x_preferred":[
        "Bayas Lama"
    ],
    "wof:name":"Bayas Lama",
    "wof:placetype":"locality"
},
  "geometry": {"coordinates":[104.99244,-5.54043],"type":"Point"}
}