{
  "type": "Feature",
  "properties": {
    "gn:admin1_code":"7",
    "gn:asciiname":"Singkreng",
    "gn:country_code":"ID",
    "gn:dem":268,
    "gn:feature_class":"P",
    "gn:feature_code":"PPL",
    "gn:name":"Singkreng",
    "gn:population":0,
    "gn:timezone":"Asia/Jakarta",
    "iso:country":"ID",
    "name:ind_x_preferred":[
        "Singkreng"
    ],
    "wof:name":"Singkreng",
    "wof:placetype":"locality"
},
  "geometry": {"coordinates":[109.6182,-7.0732],"type":"Point"}
}