{
  "type": "Feature",
  "properties": {
    "gn:admin1_code":"8.0",
    "gn:asciiname":"Benteng",
    "gn:country_code":"ID",
    "gn:dem":10,
    "gn:feature_class":"P",
    "gn:feature_code":"PPL",
    "gn:name":"Benteng",
    "gn:population":0,
    "gn:timezone":"Asia/Jakarta",
    "iso:country":"ID",
    "name:ind_x_preferred":[
        "Benteng"
    ],
    "wof:name":"Benteng",
    "wof:placetype":"locality"
},
  "geometry": {"coordinates":[113.6643,-6.8868],"type":"Point"}
}