{
  "type": "Feature",
  "properties": {
    "gn:admin1_code":"1",
    "gn:asciiname":"Cotgagoh",
    "gn:country_code":"ID",
    "gn:dem":109,
    "gn:feature_class":"P",
    "gn:feature_code":"PPL",
    "gn:name":"Cotgagoh",
    "gn:population":0,
    "gn:timezone":"Asia/Jakarta",
    "iso:country":"ID",
    "name:ind_x_preferred":[
        "Cotgagoh"
    ],
    "name:und_x_variant":[
        "Tjotgagoh"
    ],
    "wof:name":"Cotgagoh",
    "wof:placetype":"locality"
},
  "geometry": {"coordinates":[95.6392,5.2929],"type":"Point"}
}