{
  "type": "Feature",
  "properties": {
    "gn:admin1_code":"30.0",
    "gn:asciiname":"Baeud",
    "gn:country_code":"ID",
    "gn:dem":658,
    "gn:feature_class":"P",
    "gn:feature_code":"PPL",
    "gn:name":"Baeud",
    "gn:population":0,
    "gn:timezone":"Asia/Jakarta",
    "iso:country":"ID",
    "name:ind_x_preferred":[
        "Baeud"
    ],
    "wof:name":"Baeud",
    "wof:placetype":"locality"
},
  "geometry": {"coordinates":[107.91800000000001,-7.0649],"type":"Point"}
}