{
  "type": "Feature",
  "properties": {
    "gn:admin1_code":"7.0",
    "gn:asciiname":"Bajingjowo",
    "gn:country_code":"ID",
    "gn:dem":6,
    "gn:feature_class":"P",
    "gn:feature_code":"PPLA4",
    "gn:name":"Bajingjowo",
    "gn:population":0,
    "gn:timezone":"Asia/Jakarta",
    "iso:country":"ID",
    "name:ind_x_preferred":[
        "Bajingjowo"
    ],
    "wof:name":"Bajingjowo",
    "wof:placetype":"locality"
},
  "geometry": {"coordinates":[111.6709,-6.7411],"type":"Point"}
}