{
  "type": "Feature",
  "properties": {
    "gn:admin1_code":"15.0",
    "gn:asciiname":"Totoharjo",
    "gn:country_code":"ID",
    "gn:dem":143,
    "gn:feature_class":"P",
    "gn:feature_code":"PPL",
    "gn:name":"Totoharjo",
    "gn:population":0,
    "gn:timezone":"Asia/Jakarta",
    "iso:country":"ID",
    "name:ind_x_preferred":[
        "Totoharjo"
    ],
    "wof:name":"Totoharjo",
    "wof:placetype":"locality"
},
  "geometry": {"coordinates":[105.68919,-5.81527],"type":"Point"}
}