{
  "type": "Feature",
  "properties": {
    "gn:admin1_code":"26",
    "gn:asciiname":"Pematangnibung Dua",
    "gn:country_code":"ID",
    "gn:dem":5,
    "gn:feature_class":"P",
    "gn:feature_code":"PPL",
    "gn:name":"Pematangnibung Dua",
    "gn:population":0,
    "gn:timezone":"Asia/Jakarta",
    "iso:country":"ID",
    "name:ind_x_preferred":[
        "Pematangnibung Dua"
    ],
    "name:und_x_variant":[
        "Pematangnibung 2"
    ],
    "wof:name":"Pematangnibung Dua",
    "wof:placetype":"locality"
},
  "geometry": {"coordinates":[99.3785,3.3864],"type":"Point"}
}