{
  "type": "Feature",
  "properties": {
    "gn:admin1_code":"30.0",
    "gn:asciiname":"Pasirandu",
    "gn:country_code":"ID",
    "gn:dem":167,
    "gn:feature_class":"P",
    "gn:feature_code":"PPL",
    "gn:name":"Pasirandu",
    "gn:population":0,
    "gn:timezone":"Asia/Jakarta",
    "iso:country":"ID",
    "name:ind_x_preferred":[
        "Pasirandu"
    ],
    "wof:name":"Pasirandu",
    "wof:placetype":"locality"
},
  "geometry": {"coordinates":[106.4038,-6.9684],"type":"Point"}
}