{
  "type": "Feature",
  "properties": {
    "gn:admin1_code":"7",
    "gn:asciiname":"Kaliputih",
    "gn:country_code":"ID",
    "gn:dem":1175,
    "gn:feature_class":"P",
    "gn:feature_code":"PPL",
    "gn:name":"Kaliputih",
    "gn:population":0,
    "gn:timezone":"Asia/Jakarta",
    "iso:country":"ID",
    "name:ind_x_preferred":[
        "Kaliputih"
    ],
    "wof:name":"Kaliputih",
    "wof:placetype":"locality"
},
  "geometry": {"coordinates":[109.72833,-7.23],"type":"Point"}
}