{
  "type": "Feature",
  "properties": {
    "gn:admin1_code":"38",
    "gn:asciiname":"Talawe",
    "gn:country_code":"ID",
    "gn:dem":2,
    "gn:feature_class":"P",
    "gn:feature_code":"PPL",
    "gn:name":"Talawe",
    "gn:population":0,
    "gn:timezone":"Asia/Makassar",
    "iso:country":"ID",
    "name:ind_x_preferred":[
        "Talawe"
    ],
    "wof:name":"Talawe",
    "wof:placetype":"locality"
},
  "geometry": {"coordinates":[119.5604,-4.9383],"type":"Point"}
}