{
  "type": "Feature",
  "properties": {
    "gn:admin1_code":"18.0",
    "gn:asciiname":"Binakikulamboku",
    "gn:country_code":"ID",
    "gn:dem":561,
    "gn:feature_class":"P",
    "gn:feature_code":"PPL",
    "gn:name":"Binakikulamboku",
    "gn:population":0,
    "gn:timezone":"Asia/Makassar",
    "iso:country":"ID",
    "name:ind_x_preferred":[
        "Binakikulamboku"
    ],
    "wof:name":"Binakikulamboku",
    "wof:placetype":"locality"
},
  "geometry": {"coordinates":[119.4177,-9.5335],"type":"Point"}
}