{
  "type": "Feature",
  "properties": {
    "gn:admin1_code":"7.0",
    "gn:asciiname":"Ciwera",
    "gn:country_code":"ID",
    "gn:dem":281,
    "gn:feature_class":"P",
    "gn:feature_code":"PPL",
    "gn:name":"Ciwera",
    "gn:population":0,
    "gn:timezone":"Asia/Jakarta",
    "iso:country":"ID",
    "name:ind_x_preferred":[
        "Ciwera"
    ],
    "wof:name":"Ciwera",
    "wof:placetype":"locality"
},
  "geometry": {"coordinates":[109.03082999999999,-7.38306],"type":"Point"}
}