{
  "type": "Feature",
  "properties": {
    "gn:admin1_code":"7.0",
    "gn:asciiname":"Jatinegara",
    "gn:country_code":"ID",
    "gn:dem":32,
    "gn:feature_class":"P",
    "gn:feature_code":"PPL",
    "gn:name":"Jatinegara",
    "gn:population":0,
    "gn:timezone":"Asia/Jakarta",
    "iso:country":"ID",
    "name:ceb_x_preferred":[
        "Kelurahan Jatinegara"
    ],
    "name:deu_x_preferred":[
        "Jatinegara"
    ],
    "name:fra_x_preferred":[
        "Jatinegara"
    ],
    "name:ind_x_preferred":[
        "Jatinegara"
    ],
    "name:ita_x_preferred":[
        "Jatinegara"
    ],
    "name:jav_x_preferred":[
        "Jatinegara"
    ],
    "name:nld_x_preferred":[
        "Jatinegara"
    ],
    "name:pol_x_preferred":[
        "Jatinegara"
    ],
    "name:sun_x_preferred":[
        "Jatinegara"
    ],
    "name:swe_x_preferred":[
        "Kelurahan Jatinegara"
    ],
    "name:und_x_variant":[
        "Djatinegara"
    ],
    "wof:name":"Jatinegara",
    "wof:placetype":"locality"
},
  "geometry": {"coordinates":[108.77970000000001,-7.2967],"type":"Point"}
}