{
  "type": "Feature",
  "properties": {
    "gn:admin1_code":"12",
    "gn:asciiname":"Sungaipuntik",
    "gn:country_code":"ID",
    "gn:dem":5,
    "gn:feature_class":"P",
    "gn:feature_code":"PPLA3",
    "gn:name":"Sungaipuntik",
    "gn:population":0,
    "gn:timezone":"Asia/Makassar",
    "iso:country":"ID",
    "name:ind_x_preferred":[
        "Sungaipuntik"
    ],
    "wof:name":"Sungaipuntik",
    "wof:placetype":"locality"
},
  "geometry": {"coordinates":[114.68300000000001,-3.169],"type":"Point"}
}