{
  "type": "Feature",
  "properties": {
    "gn:admin1_code":"8.0",
    "gn:asciiname":"Curahsudo",
    "gn:country_code":"ID",
    "gn:dem":107,
    "gn:feature_class":"P",
    "gn:feature_code":"PPL",
    "gn:name":"Curahsudo",
    "gn:population":0,
    "gn:timezone":"Asia/Jakarta",
    "iso:country":"ID",
    "name:ind_x_preferred":[
        "Curahsudo"
    ],
    "wof:name":"Curahsudo",
    "wof:placetype":"locality"
},
  "geometry": {"coordinates":[112.7358,-7.6585],"type":"Point"}
}