{
  "type": "Feature",
  "properties": {
    "gn:admin1_code":"07",
    "gn:asciiname":"Karang",
    "gn:country_code":"ID",
    "gn:dem":425,
    "gn:feature_class":"P",
    "gn:feature_code":"PPL",
    "gn:name":"Karang",
    "gn:population":0,
    "gn:timezone":"Asia/Jakarta",
    "iso:country":"ID",
    "wof:name":"Karang",
    "wof:placetype":"locality"
},
  "geometry": {"coordinates":[110.57472,-7.30556],"type":"Point"}
}