{
  "type": "Feature",
  "properties": {
    "gn:admin1_code":"30",
    "gn:asciiname":"Rancakembang",
    "gn:cc2":"ID",
    "gn:country_code":"ID",
    "gn:dem":669,
    "gn:feature_class":"P",
    "gn:feature_code":"PPL",
    "gn:name":"Rancakembang",
    "gn:population":0,
    "gn:timezone":"Asia/Jakarta",
    "iso:country":"ID",
    "name:und_x_variant":[
        "Rantjakembang",
        "Rancakembang"
    ],
    "wof:name":"Rancakembang",
    "wof:placetype":"locality"
},
  "geometry": {"coordinates":[107.56056,-7.01361],"type":"Point"}
}