{
  "type": "Feature",
  "properties": {
    "gn:admin1_code":"07",
    "gn:asciiname":"Salakan Satu",
    "gn:cc2":"ID",
    "gn:country_code":"ID",
    "gn:dem":285,
    "gn:feature_class":"P",
    "gn:feature_code":"PPL",
    "gn:name":"Salakan Satu",
    "gn:population":0,
    "gn:timezone":"Asia/Jakarta",
    "iso:country":"ID",
    "name:und_x_variant":[
        "Salakan 1",
        "Salakan Satu"
    ],
    "wof:name":"Salakan Satu",
    "wof:placetype":"locality"
},
  "geometry": {"coordinates":[110.38028,-7.07889],"type":"Point"}
}