{
  "type": "Feature",
  "properties": {
    "gn:admin1_code":"30.0",
    "gn:asciiname":"Jambuleuwi",
    "gn:country_code":"ID",
    "gn:dem":244,
    "gn:feature_class":"P",
    "gn:feature_code":"PPL",
    "gn:name":"Jambuleuwi",
    "gn:population":0,
    "gn:timezone":"Asia/Jakarta",
    "iso:country":"ID",
    "name:ind_x_preferred":[
        "Jambuleuwi"
    ],
    "name:und_x_variant":[
        "Djamboeleuwi"
    ],
    "wof:lang_x_official":[
        "ind"
    ],
    "wof:lang_x_spoken":[
        "ind",
        "eng"
    ],
    "wof:name":"Jambuleuwi",
    "wof:placetype":"locality"
},
  "geometry": {"coordinates":[108.50660000000001,-7.0517],"type":"Point"}
}