{
  "type": "Feature",
  "properties": {
    "gn:admin1_code":"30",
    "gn:asciiname":"Legokjaya",
    "gn:country_code":"ID",
    "gn:dem":677,
    "gn:feature_class":"P",
    "gn:feature_code":"PPL",
    "gn:name":"Legokjaya",
    "gn:population":0,
    "gn:timezone":"Asia/Jakarta",
    "iso:country":"ID",
    "name:ind_x_preferred":[
        "Legokjaya"
    ],
    "wof:name":"Legokjaya",
    "wof:placetype":"locality"
},
  "geometry": {"coordinates":[107.07611,-6.84056],"type":"Point"}
}