{
  "type": "Feature",
  "properties": {
    "gn:admin1_code":"7.0",
    "gn:asciiname":"Kuto",
    "gn:country_code":"ID",
    "gn:dem":263,
    "gn:feature_class":"P",
    "gn:feature_code":"PPL",
    "gn:name":"Kuto",
    "gn:population":0,
    "gn:timezone":"Asia/Jakarta",
    "iso:country":"ID",
    "wof:name":"Kuto",
    "wof:placetype":"locality"
},
  "geometry": {"coordinates":[110.21556,-7.57417],"type":"Point"}
}