{
  "type": "Feature",
  "properties": {
    "gn:admin1_code":"33",
    "gn:asciiname":"Pabuaran",
    "gn:country_code":"ID",
    "gn:dem":25,
    "gn:feature_class":"P",
    "gn:feature_code":"PPL",
    "gn:name":"Pabuaran",
    "gn:population":0,
    "gn:timezone":"Asia/Jakarta",
    "iso:country":"ID",
    "name:ind_x_preferred":[
        "Pabuaran"
    ],
    "wof:name":"Pabuaran",
    "wof:placetype":"locality"
},
  "geometry": {"coordinates":[106.25109999999999,-6.3124],"type":"Point"}
}