{
  "type": "Feature",
  "properties": {
    "gn:admin1_code":"36.0",
    "gn:asciiname":"Epet",
    "gn:country_code":"ID",
    "gn:dem":23,
    "gn:feature_class":"P",
    "gn:feature_code":"PPL",
    "gn:name":"Epet",
    "gn:population":0,
    "gn:timezone":"Asia/Jayapura",
    "iso:country":"ID",
    "name:ind_x_preferred":[
        "Epet"
    ],
    "wof:name":"Epet",
    "wof:placetype":"locality"
},
  "geometry": {"coordinates":[137.92848999999998,-5.39591],"type":"Point"}
}