{
  "type": "Feature",
  "properties": {
    "gn:admin1_code":"7",
    "gn:asciiname":"Dusun Satu",
    "gn:country_code":"ID",
    "gn:dem":17,
    "gn:feature_class":"P",
    "gn:feature_code":"PPL",
    "gn:name":"Dusun Satu",
    "gn:population":0,
    "gn:timezone":"Asia/Jakarta",
    "iso:country":"ID",
    "name:ind_x_preferred":[
        "Dusun Satu"
    ],
    "wof:name":"Dusun Satu",
    "wof:placetype":"locality"
},
  "geometry": {"coordinates":[109.88472,-7.82889],"type":"Point"}
}