{
  "type": "Feature",
  "properties": {
    "gn:admin1_code":"30.0",
    "gn:asciiname":"Sawahlandeun",
    "gn:country_code":"ID",
    "gn:dem":646,
    "gn:feature_class":"P",
    "gn:feature_code":"PPL",
    "gn:name":"Sawahlandeun",
    "gn:population":0,
    "gn:timezone":"Asia/Jakarta",
    "iso:country":"ID",
    "name:ind_x_preferred":[
        "Sawahlandeun"
    ],
    "wof:name":"Sawahlandeun",
    "wof:placetype":"locality"
},
  "geometry": {"coordinates":[107.9935,-7.4088],"type":"Point"}
}