{
  "type": "Feature",
  "properties": {
    "gn:admin1_code":"30.0",
    "gn:asciiname":"Ancol",
    "gn:country_code":"ID",
    "gn:dem":582,
    "gn:feature_class":"P",
    "gn:feature_code":"PPL",
    "gn:name":"Ancol",
    "gn:population":0,
    "gn:timezone":"Asia/Jakarta",
    "iso:country":"ID",
    "name:ind_x_preferred":[
        "Ancol"
    ],
    "name:und_x_variant":[
        "Antjol"
    ],
    "wof:name":"Ancol",
    "wof:placetype":"locality"
},
  "geometry": {"coordinates":[108.2473,-7.1202],"type":"Point"}
}