{
  "type": "Feature",
  "properties": {
    "gn:admin1_code":"38",
    "gn:asciiname":"Pijae",
    "gn:country_code":"ID",
    "gn:dem":148,
    "gn:feature_class":"P",
    "gn:feature_code":"PPL",
    "gn:name":"Pijae",
    "gn:population":0,
    "gn:timezone":"Asia/Makassar",
    "iso:country":"ID",
    "name:ind_x_preferred":[
        "Pijae"
    ],
    "name:und_x_variant":[
        "Pijoe"
    ],
    "wof:name":"Pijae",
    "wof:placetype":"locality"
},
  "geometry": {"coordinates":[119.90179999999999,-4.4972],"type":"Point"}
}