{
  "type": "Feature",
  "properties": {
    "gn:admin1_code":"1",
    "gn:asciiname":"Sukadamai",
    "gn:country_code":"ID",
    "gn:dem":1085,
    "gn:feature_class":"P",
    "gn:feature_code":"PPL",
    "gn:name":"Sukadamai",
    "gn:population":0,
    "gn:timezone":"Asia/Jakarta",
    "iso:country":"ID",
    "name:ind_x_preferred":[
        "Sukadamai"
    ],
    "wof:name":"Sukadamai",
    "wof:placetype":"locality"
},
  "geometry": {"coordinates":[96.7627,4.769],"type":"Point"}
}