{
  "type": "Feature",
  "properties": {
    "gn:admin1_code":"18.0",
    "gn:asciiname":"Kabiu",
    "gn:country_code":"ID",
    "gn:dem":445,
    "gn:feature_class":"P",
    "gn:feature_code":"PPL",
    "gn:name":"Kabiu",
    "gn:population":0,
    "gn:timezone":"Asia/Makassar",
    "iso:country":"ID",
    "name:ind_x_preferred":[
        "Kabiu"
    ],
    "wof:name":"Kabiu",
    "wof:placetype":"locality"
},
  "geometry": {"coordinates":[119.3222,-9.5904],"type":"Point"}
}