{
  "type": "Feature",
  "properties": {
    "gn:admin1_code":"1",
    "gn:asciiname":"Mu Meu Aneuk",
    "gn:country_code":"ID",
    "gn:dem":13,
    "gn:feature_class":"P",
    "gn:feature_code":"PPL",
    "gn:name":"Mu Meu Aneuk",
    "gn:population":0,
    "gn:timezone":"Asia/Jakarta",
    "iso:country":"ID",
    "name:ind_x_preferred":[
        "Mu Meu Aneuk"
    ],
    "name:und_x_variant":[
        "Memeuaneu"
    ],
    "wof:lang_x_official":[
        "ind"
    ],
    "wof:lang_x_spoken":[
        "ind",
        "eng"
    ],
    "wof:name":"Mu Meu Aneuk",
    "wof:placetype":"locality"
},
  "geometry": {"coordinates":[95.9115,5.3769],"type":"Point"}
}