{
  "type": "Feature",
  "properties": {
    "gn:admin1_code":"31.0",
    "gn:asciiname":"Tona",
    "gn:country_code":"ID",
    "gn:dem":171,
    "gn:feature_class":"P",
    "gn:feature_code":"PPL",
    "gn:name":"Tona",
    "gn:population":0,
    "gn:timezone":"Asia/Makassar",
    "iso:country":"ID",
    "name:cat_x_preferred":[
        "Tona"
    ],
    "name:ceb_x_preferred":[
        "Tona"
    ],
    "name:deu_x_preferred":[
        "Tona"
    ],
    "name:eus_x_preferred":[
        "Tona"
    ],
    "name:fra_x_preferred":[
        "Tona"
    ],
    "name:glg_x_preferred":[
        "Tona"
    ],
    "name:ind_x_preferred":[
        "Tona"
    ],
    "name:ita_x_preferred":[
        "Tona"
    ],
    "name:lat_x_preferred":[
        "Tona"
    ],
    "name:msa_x_preferred":[
        "Tona"
    ],
    "name:nld_x_preferred":[
        "Tona"
    ],
    "name:oci_x_preferred":[
        "Tona"
    ],
    "name:pol_x_preferred":[
        "Tona"
    ],
    "name:por_x_preferred":[
        "Tona"
    ],
    "name:spa_x_preferred":[
        "Tona"
    ],
    "name:swe_x_preferred":[
        "Tona"
    ],
    "name:vie_x_preferred":[
        "Tona"
    ],
    "name:war_x_preferred":[
        "Tona"
    ],
    "wof:name":"Tona",
    "wof:placetype":"locality"
},
  "geometry": {"coordinates":[125.42529999999999,2.348],"type":"Point"}
}