{
  "type": "Feature",
  "properties": {
    "gn:admin1_code":"30",
    "gn:asciiname":"Sudimampir",
    "gn:country_code":"ID",
    "gn:dem":100,
    "gn:feature_class":"P",
    "gn:feature_code":"PPL",
    "gn:name":"Sudimampir",
    "gn:population":0,
    "gn:timezone":"Asia/Jakarta",
    "iso:country":"ID",
    "name:ind_x_preferred":[
        "Sudimampir"
    ],
    "wof:name":"Sudimampir",
    "wof:placetype":"locality"
},
  "geometry": {"coordinates":[107.69138999999998,-6.51583],"type":"Point"}
}