{
  "type": "Feature",
  "properties": {
    "gn:admin1_code":"1",
    "gn:asciiname":"Batee Ilik",
    "gn:country_code":"ID",
    "gn:dem":38,
    "gn:feature_class":"P",
    "gn:feature_code":"PPL",
    "gn:name":"Batee Ilik",
    "gn:population":0,
    "gn:timezone":"Asia/Jakarta",
    "iso:country":"ID",
    "name:ind_x_preferred":[
        "Batee Ilik"
    ],
    "name:und_x_variant":[
        "Bate\u00eb-ili\u00eb",
        "Bateeilie",
        "Batee-iliek",
        "Bateilik"
    ],
    "wof:name":"Batee Ilik",
    "wof:placetype":"locality"
},
  "geometry": {"coordinates":[96.3417,5.1701],"type":"Point"}
}