{
  "type": "Feature",
  "properties": {
    "gn:admin1_code":"24",
    "gn:asciiname":"Gurunpangyang",
    "gn:country_code":"ID",
    "gn:dem":7,
    "gn:feature_class":"P",
    "gn:feature_code":"PPL",
    "gn:name":"Gurunpangyang",
    "gn:population":0,
    "gn:timezone":"Asia/Jakarta",
    "iso:country":"ID",
    "name:ind_x_preferred":[
        "Gurunpangyang"
    ],
    "wof:name":"Gurunpangyang",
    "wof:placetype":"locality"
},
  "geometry": {"coordinates":[100.47843,-1.27704],"type":"Point"}
}