{
  "type": "Feature",
  "properties": {
    "gn:admin1_code":"30",
    "gn:asciiname":"Cipinang",
    "gn:cc2":"ID",
    "gn:country_code":"ID",
    "gn:dem":673,
    "gn:feature_class":"P",
    "gn:feature_code":"PPL",
    "gn:name":"Cipinang",
    "gn:population":0,
    "gn:timezone":"Asia/Jakarta",
    "iso:country":"ID",
    "name:und_x_variant":[
        "Tjipinang 2",
        "Cipinang Dua",
        "Cipinang"
    ],
    "wof:lang_x_official":[
        "ind"
    ],
    "wof:lang_x_spoken":[
        "ind",
        "eng"
    ],
    "wof:name":"Cipinang",
    "wof:placetype":"locality"
},
  "geometry": {"coordinates":[107.54971999999999,-7.01944],"type":"Point"}
}