{
  "type": "Feature",
  "properties": {
    "gn:admin1_code":"1",
    "gn:asciiname":"Lam Tui",
    "gn:country_code":"ID",
    "gn:dem":12,
    "gn:feature_class":"P",
    "gn:feature_code":"PPL",
    "gn:name":"Lam Tui",
    "gn:population":0,
    "gn:timezone":"Asia/Jakarta",
    "iso:country":"ID",
    "name:ind_x_preferred":[
        "Lam Tui"
    ],
    "wof:name":"Lam Tui",
    "wof:placetype":"locality"
},
  "geometry": {"coordinates":[95.3364,5.1124],"type":"Point"}
}