{
  "type": "Feature",
  "properties": {
    "gn:admin1_code":"30.0",
    "gn:asciiname":"Cireongpojok",
    "gn:country_code":"ID",
    "gn:dem":546,
    "gn:feature_class":"P",
    "gn:feature_code":"PPL",
    "gn:name":"Cireongpojok",
    "gn:population":0,
    "gn:timezone":"Asia/Jakarta",
    "iso:country":"ID",
    "name:ind_x_preferred":[
        "Cireongpojok"
    ],
    "wof:name":"Cireongpojok",
    "wof:placetype":"locality"
},
  "geometry": {"coordinates":[108.2546,-7.2669],"type":"Point"}
}