{
  "type": "Feature",
  "properties": {
    "gn:admin1_code":"5.0",
    "gn:asciiname":"Pelabuhan Dagang",
    "gn:country_code":"ID",
    "gn:dem":12,
    "gn:feature_class":"P",
    "gn:feature_code":"PPLA3",
    "gn:name":"Pelabuhan Dagang",
    "gn:population":0,
    "gn:timezone":"Asia/Jakarta",
    "iso:country":"ID",
    "name:ind_x_preferred":[
        "Pelabuhan Dagang"
    ],
    "name:und_x_variant":[
        "Talaboehandagang",
        "Pelaboehandagang",
        "Palaboehandagang"
    ],
    "wof:name":"Pelabuhan Dagang",
    "wof:placetype":"locality"
},
  "geometry": {"coordinates":[103.08494,-1.1463],"type":"Point"}
}