{
  "type": "Feature",
  "properties": {
    "gn:admin1_code":"15.0",
    "gn:asciiname":"Umbulan Terusan Satu",
    "gn:country_code":"ID",
    "gn:dem":39,
    "gn:feature_class":"P",
    "gn:feature_code":"PPL",
    "gn:name":"Umbulan Terusan Satu",
    "gn:population":0,
    "gn:timezone":"Asia/Jakarta",
    "iso:country":"ID",
    "name:ind_x_preferred":[
        "Umbulan Terusan Satu"
    ],
    "name:und_x_variant":[
        "Umbulanterusan 1"
    ],
    "wof:lang_x_official":[
        "ind"
    ],
    "wof:lang_x_spoken":[
        "ind",
        "eng"
    ],
    "wof:name":"Umbulan Terusan Satu",
    "wof:placetype":"locality"
},
  "geometry": {"coordinates":[104.99093999999999,-4.78858],"type":"Point"}
}