{
  "type": "Feature",
  "properties": {
    "gn:admin1_code":"18.0",
    "gn:asciiname":"Watukobu",
    "gn:country_code":"ID",
    "gn:dem":105,
    "gn:feature_class":"P",
    "gn:feature_code":"PPL",
    "gn:name":"Watukobu",
    "gn:population":0,
    "gn:timezone":"Asia/Makassar",
    "iso:country":"ID",
    "name:ind_x_preferred":[
        "Watukobu"
    ],
    "wof:name":"Watukobu",
    "wof:placetype":"locality"
},
  "geometry": {"coordinates":[122.28749999999999,-8.6689],"type":"Point"}
}