{
  "type": "Feature",
  "properties": {
    "gn:admin1_code":"18.0",
    "gn:asciiname":"Ingusapi",
    "gn:country_code":"ID",
    "gn:dem":82,
    "gn:feature_class":"P",
    "gn:feature_code":"PPL",
    "gn:name":"Ingusapi",
    "gn:population":0,
    "gn:timezone":"Asia/Makassar",
    "iso:country":"ID",
    "name:ind_x_preferred":[
        "Ingusapi"
    ],
    "wof:name":"Ingusapi",
    "wof:placetype":"locality"
},
  "geometry": {"coordinates":[123.4456,-10.1943],"type":"Point"}
}