{
  "type": "Feature",
  "properties": {
    "gn:admin1_code":"30",
    "gn:asciiname":"Pasirawi",
    "gn:country_code":"ID",
    "gn:dem":314,
    "gn:feature_class":"P",
    "gn:feature_code":"PPL",
    "gn:name":"Pasirawi",
    "gn:population":0,
    "gn:timezone":"Asia/Jakarta",
    "iso:country":"ID",
    "name:ind_x_preferred":[
        "Pasirawi"
    ],
    "wof:name":"Pasirawi",
    "wof:placetype":"locality"
},
  "geometry": {"coordinates":[106.59972,-6.59],"type":"Point"}
}