{
  "type": "Feature",
  "properties": {
    "gn:admin1_code":"2",
    "gn:asciiname":"Banjar Gunung",
    "gn:country_code":"ID",
    "gn:dem":52,
    "gn:feature_class":"P",
    "gn:feature_code":"PPL",
    "gn:name":"Banjar Gunung",
    "gn:population":0,
    "gn:timezone":"Asia/Makassar",
    "iso:country":"ID",
    "name:ind_x_preferred":[
        "Banjar Gunung"
    ],
    "wof:name":"Banjar Gunung",
    "wof:placetype":"locality"
},
  "geometry": {"coordinates":[115.2512,-8.6219],"type":"Point"}
}