{
  "type": "Feature",
  "properties": {
    "gn:admin1_code":"30.0",
    "gn:asciiname":"Cilangkap",
    "gn:country_code":"ID",
    "gn:dem":287,
    "gn:feature_class":"P",
    "gn:feature_code":"PPLA4",
    "gn:name":"Cilangkap",
    "gn:population":0,
    "gn:timezone":"Asia/Jakarta",
    "iso:country":"ID",
    "name:ind_x_preferred":[
        "Cilangkap"
    ],
    "wof:lang_x_official":[
        "ind"
    ],
    "wof:lang_x_spoken":[
        "ind",
        "eng"
    ],
    "wof:name":"Cilangkap",
    "wof:placetype":"locality"
},
  "geometry": {"coordinates":[108.256,-7.4523],"type":"Point"}
}