{
  "type": "Feature",
  "properties": {
    "gn:admin1_code":"34",
    "gn:asciiname":"Dulamayo",
    "gn:country_code":"ID",
    "gn:dem":19,
    "gn:feature_class":"P",
    "gn:feature_code":"PPL",
    "gn:name":"Dulamayo",
    "gn:population":0,
    "gn:timezone":"Asia/Makassar",
    "iso:country":"ID",
    "name:ind_x_preferred":[
        "Dulamayo"
    ],
    "wof:name":"Dulamayo",
    "wof:placetype":"locality"
},
  "geometry": {"coordinates":[122.9252,0.6403],"type":"Point"}
}