{
  "type": "Feature",
  "properties": {
    "gn:admin1_code":"38",
    "gn:asciiname":"Maccini",
    "gn:country_code":"ID",
    "gn:dem":99,
    "gn:feature_class":"P",
    "gn:feature_code":"PPL",
    "gn:name":"Maccini",
    "gn:population":0,
    "gn:timezone":"Asia/Makassar",
    "iso:country":"ID",
    "name:ind_x_preferred":[
        "Maccini"
    ],
    "wof:name":"Maccini",
    "wof:placetype":"locality"
},
  "geometry": {"coordinates":[119.9247,-4.4037],"type":"Point"}
}