{
  "type": "Feature",
  "properties": {
    "gn:admin1_code":"7.0",
    "gn:asciiname":"Sembong",
    "gn:country_code":"ID",
    "gn:dem":656,
    "gn:feature_class":"P",
    "gn:feature_code":"PPL",
    "gn:name":"Sembong",
    "gn:population":0,
    "gn:timezone":"Asia/Jakarta",
    "iso:country":"ID",
    "wof:name":"Sembong",
    "wof:placetype":"locality"
},
  "geometry": {"coordinates":[110.24111000000001,-7.28111],"type":"Point"}
}