{
  "type": "Feature",
  "properties": {
    "gn:admin1_code":"33.0",
    "gn:asciiname":"Lebaklame",
    "gn:country_code":"ID",
    "gn:dem":290,
    "gn:feature_class":"P",
    "gn:feature_code":"PPL",
    "gn:name":"Lebaklame",
    "gn:population":0,
    "gn:timezone":"Asia/Jakarta",
    "iso:country":"ID",
    "name:ind_x_preferred":[
        "Lebaklame"
    ],
    "wof:name":"Lebaklame",
    "wof:placetype":"locality"
},
  "geometry": {"coordinates":[106.35939999999999,-6.9044],"type":"Point"}
}