{
  "type": "Feature",
  "properties": {
    "gn:admin1_code":"18",
    "gn:asciiname":"Liti",
    "gn:country_code":"ID",
    "gn:dem":444,
    "gn:feature_class":"P",
    "gn:feature_code":"PPL",
    "gn:name":"Liti",
    "gn:population":0,
    "gn:timezone":"Asia/Makassar",
    "iso:country":"ID",
    "name:ceb_x_preferred":[
        "Liti"
    ],
    "name:ind_x_preferred":[
        "Liti"
    ],
    "name:swe_x_preferred":[
        "Liti"
    ],
    "wof:name":"Liti",
    "wof:placetype":"locality"
},
  "geometry": {"coordinates":[121.3536,-8.8572],"type":"Point"}
}