{
  "type": "Feature",
  "properties": {
    "gn:admin1_code":"1",
    "gn:asciiname":"Lubuktigasagi",
    "gn:country_code":"ID",
    "gn:dem":2,
    "gn:feature_class":"P",
    "gn:feature_code":"PPL",
    "gn:name":"Lubuktigasagi",
    "gn:population":0,
    "gn:timezone":"Asia/Jakarta",
    "iso:country":"ID",
    "name:ind_x_preferred":[
        "Lubuktigasagi"
    ],
    "wof:name":"Lubuktigasagi",
    "wof:placetype":"locality"
},
  "geometry": {"coordinates":[98.21720000000001,4.4091],"type":"Point"}
}