{
  "type": "Feature",
  "properties": {
    "gn:admin1_code":"17.0",
    "gn:asciiname":"Majujaya",
    "gn:country_code":"ID",
    "gn:dem":42,
    "gn:feature_class":"P",
    "gn:feature_code":"PPL",
    "gn:name":"Majujaya",
    "gn:population":0,
    "gn:timezone":"Asia/Makassar",
    "iso:country":"ID",
    "name:ind_x_preferred":[
        "Majujaya"
    ],
    "wof:name":"Majujaya",
    "wof:placetype":"locality"
},
  "geometry": {"coordinates":[117.6846,-8.9057],"type":"Point"}
}