{
  "type": "Feature",
  "properties": {
    "gn:admin1_code":"21.0",
    "gn:asciiname":"Loliindah",
    "gn:country_code":"ID",
    "gn:dem":81,
    "gn:feature_class":"P",
    "gn:feature_code":"PPL",
    "gn:name":"Loliindah",
    "gn:population":0,
    "gn:timezone":"Asia/Makassar",
    "iso:country":"ID",
    "name:ind_x_preferred":[
        "Loliindah"
    ],
    "wof:name":"Loliindah",
    "wof:placetype":"locality"
},
  "geometry": {"coordinates":[119.7955,-0.7939],"type":"Point"}
}