{
  "type": "Feature",
  "properties": {
    "gn:admin1_code":"7",
    "gn:asciiname":"Ngrawan",
    "gn:country_code":"ID",
    "gn:dem":83,
    "gn:feature_class":"P",
    "gn:feature_code":"PPL",
    "gn:name":"Ngrawan",
    "gn:population":0,
    "gn:timezone":"Asia/Jakarta",
    "iso:country":"ID",
    "name:ind_x_preferred":[
        "Ngrawan"
    ],
    "wof:name":"Ngrawan",
    "wof:placetype":"locality"
},
  "geometry": {"coordinates":[111.005,-7.21472],"type":"Point"}
}