{
  "type": "Feature",
  "properties": {
    "gn:admin1_code":"30",
    "gn:asciiname":"Simpang",
    "gn:country_code":"ID",
    "gn:dem":429,
    "gn:feature_class":"P",
    "gn:feature_code":"PPL",
    "gn:name":"Simpang",
    "gn:population":0,
    "gn:timezone":"Asia/Jakarta",
    "iso:country":"ID",
    "name:ind_x_preferred":[
        "Simpang"
    ],
    "name:mlg_x_preferred":[
        "Simpang"
    ],
    "wof:name":"Simpang",
    "wof:placetype":"locality"
},
  "geometry": {"coordinates":[107.15582999999999,-6.89139],"type":"Point"}
}