{
  "type": "Feature",
  "properties": {
    "gn:admin1_code":"30.0",
    "gn:asciiname":"Cijalu Girang",
    "gn:country_code":"ID",
    "gn:dem":864,
    "gn:feature_class":"P",
    "gn:feature_code":"PPL",
    "gn:name":"Cijalu Girang",
    "gn:population":0,
    "gn:timezone":"Asia/Jakarta",
    "iso:country":"ID",
    "name:ind_x_preferred":[
        "Cijalu Girang"
    ],
    "name:und_x_variant":[
        "Tjidjaloe girang"
    ],
    "wof:lang_x_official":[
        "ind"
    ],
    "wof:lang_x_spoken":[
        "ind",
        "eng"
    ],
    "wof:name":"Cijalu Girang",
    "wof:placetype":"locality"
},
  "geometry": {"coordinates":[107.9766,-7.4619],"type":"Point"}
}