{
  "type": "Feature",
  "properties": {
    "gn:admin1_code":"30.0",
    "gn:asciiname":"Parungcangkudu",
    "gn:country_code":"ID",
    "gn:dem":214,
    "gn:feature_class":"P",
    "gn:feature_code":"PPL",
    "gn:name":"Parungcangkudu",
    "gn:population":0,
    "gn:timezone":"Asia/Jakarta",
    "iso:country":"ID",
    "name:ind_x_preferred":[
        "Parungcangkudu"
    ],
    "name:und_x_variant":[
        "Paroengtjangkoedoe"
    ],
    "wof:name":"Parungcangkudu",
    "wof:placetype":"locality"
},
  "geometry": {"coordinates":[108.242,-7.6223],"type":"Point"}
}