{
  "type": "Feature",
  "properties": {
    "gn:country":"ID",
    "gn:fcode":"ADM4",
    "gn:pop":0,
    "iso:country":"ID",
    "name:ace_x_preferred":[
        "Gelgel"
    ],
    "name:ban_x_preferred":[
        "G\u00e9lg\u00e9l"
    ],
    "name:ceb_x_preferred":[
        "Desa Gelgel"
    ],
    "name:deu_x_preferred":[
        "Gelgel"
    ],
    "name:eng_x_preferred":[
        "Kecamatan Cicadas"
    ],
    "name:eng_x_variant":[
        "Gelgel"
    ],
    "name:ind_x_preferred":[
        "Desa Gelgel"
    ],
    "name:ind_x_variant":[
        "Gelgel"
    ],
    "name:ita_x_preferred":[
        "Gelgel"
    ],
    "name:jav_x_preferred":[
        "Gelgel"
    ],
    "name:jpn_x_preferred":[
        "\u30b2\u30eb\u30b2\u30eb\u738b\u56fd"
    ],
    "name:msa_x_preferred":[
        "Gelgel"
    ],
    "name:nld_x_preferred":[
        "Gelgel"
    ],
    "name:por_x_preferred":[
        "Gelgel"
    ],
    "name:rus_x_preferred":[
        "\u0413\u0435\u043b\u044c\u0433\u0435\u043b\u044c"
    ],
    "name:spa_x_preferred":[
        "Gelgel"
    ],
    "name:swe_x_preferred":[
        "Desa Gelgel"
    ],
    "name:unk_x_variant":[
        "Gelgel"
    ],
    "name:zho_x_preferred":[
        "\u5370\u5c3cGelgel\u738b\u671d"
    ],
    "qs:name":"Desa Gelgel",
    "qs:photos_9r":0,
    "qs:photos_sr":0,
    "qs:pop_sr":"0",
    "wd:wordcount":1523,
    "wof:lang_x_official":[
        "ind"
    ],
    "wof:lang_x_spoken":[
        "ind",
        "eng"
    ],
    "wof:name":"Desa Gelgel",
    "wof:placetype":"localadmin",
    "wof:population":0
},
  "geometry": {"coordinates":[115.4105,-8.5637],"type":"Point"}
}