{
  "type": "Feature",
  "properties": {
    "gn:admin1_code":"30.0",
    "gn:asciiname":"Cihaseum",
    "gn:country_code":"ID",
    "gn:dem":580,
    "gn:feature_class":"P",
    "gn:feature_code":"PPLA4",
    "gn:name":"Cihaseum",
    "gn:population":0,
    "gn:timezone":"Asia/Jakarta",
    "iso:country":"ID",
    "name:ind_x_preferred":[
        "Cihaseum"
    ],
    "name:und_x_variant":[
        "Tjihaseum 2"
    ],
    "wof:lang_x_official":[
        "ind"
    ],
    "wof:lang_x_spoken":[
        "ind",
        "eng"
    ],
    "wof:name":"Cihaseum",
    "wof:placetype":"locality"
},
  "geometry": {"coordinates":[108.1138,-7.2781],"type":"Point"}
}