{
  "type": "Feature",
  "properties": {
    "gn:admin1_code":"8",
    "gn:asciiname":"Sidomulyo",
    "gn:country_code":"ID",
    "gn:dem":28,
    "gn:feature_class":"P",
    "gn:feature_code":"PPL",
    "gn:name":"Sidomulyo",
    "gn:population":0,
    "gn:timezone":"Asia/Jakarta",
    "iso:country":"ID",
    "name:ind_x_preferred":[
        "Sidomulyo"
    ],
    "wof:name":"Sidomulyo",
    "wof:placetype":"locality"
},
  "geometry": {"coordinates":[113.4485,-8.2255],"type":"Point"}
}