{
  "type": "Feature",
  "properties": {
    "gn:admin1_code":"31",
    "gn:asciiname":"Kotamenara",
    "gn:country_code":"ID",
    "gn:dem":504,
    "gn:feature_class":"P",
    "gn:feature_code":"PPL",
    "gn:name":"Kotamenara",
    "gn:population":0,
    "gn:timezone":"Asia/Makassar",
    "iso:country":"ID",
    "name:ind_x_preferred":[
        "Kotamenara"
    ],
    "wof:name":"Kotamenara",
    "wof:placetype":"locality"
},
  "geometry": {"coordinates":[124.6772,1.1741],"type":"Point"}
}