{
  "type": "Feature",
  "properties": {
    "gn:admin1_code":"22.0",
    "gn:asciiname":"Lasoso",
    "gn:country_code":"ID",
    "gn:dem":19,
    "gn:feature_class":"P",
    "gn:feature_code":"PPL",
    "gn:name":"Lasoso",
    "gn:population":0,
    "gn:timezone":"Asia/Makassar",
    "iso:country":"ID",
    "name:ind_x_preferred":[
        "Lasoso"
    ],
    "wof:name":"Lasoso",
    "wof:placetype":"locality"
},
  "geometry": {"coordinates":[122.4367,-3.9653],"type":"Point"}
}