{
  "type": "Feature",
  "properties": {
    "gn:admin1_code":"7.0",
    "gn:asciiname":"Kretek",
    "gn:country_code":"ID",
    "gn:dem":41,
    "gn:feature_class":"P",
    "gn:feature_code":"PPL",
    "gn:name":"Kretek",
    "gn:population":0,
    "gn:timezone":"Asia/Jakarta",
    "iso:country":"ID",
    "name:ces_x_preferred":[
        "Kretek"
    ],
    "name:deu_x_preferred":[
        "Nelkenzigarette"
    ],
    "name:fra_x_preferred":[
        "Kretek"
    ],
    "name:ind_x_preferred":[
        "Kretek"
    ],
    "name:ita_x_preferred":[
        "Kretek"
    ],
    "name:jav_x_preferred":[
        "Kr\u00e8t\u00e8k"
    ],
    "name:jpn_x_preferred":[
        "\u30af\u30ec\u30c6\u30c3\u30af"
    ],
    "name:kat_x_preferred":[
        "\u10d9\u10e0\u10d4\u10e2\u10d4\u10d9\u10d8"
    ],
    "name:msa_x_preferred":[
        "Kretek"
    ],
    "name:nld_x_preferred":[
        "Kretek"
    ],
    "name:pol_x_preferred":[
        "Kretek"
    ],
    "name:por_x_preferred":[
        "Kretek"
    ],
    "name:rus_x_preferred":[
        "\u041a\u0440\u0435\u0442\u0435\u043a"
    ],
    "name:swe_x_preferred":[
        "Kretek"
    ],
    "name:tur_x_preferred":[
        "Kretek"
    ],
    "wof:name":"Kretek",
    "wof:placetype":"locality"
},
  "geometry": {"coordinates":[111.1276,-6.8684],"type":"Point"}
}