{
  "type": "Feature",
  "properties": {
    "iso:country":"ID",
    "qs:name":"Girsang Sipangan Bolon",
    "qs:name_adm0":"Indonesia",
    "qs:name_adm1":"Sumatera Utara",
    "qs:photos":173,
    "qs:photos_1k":35,
    "qs:photos_9k":1,
    "qs:photos_9r":4,
    "qs:photos_all":173,
    "qs:photos_sr":4,
    "qs:placetype":"Town",
    "qs:pop_sr":"0",
    "wof:name":"Girsang Sipangan Bolon",
    "wof:placetype":"locality"
},
  "geometry": {"coordinates":[98.946304,2.590517],"type":"Point"}
}