{
  "type": "Feature",
  "properties": {
    "gn:admin1_code":"30.0",
    "gn:asciiname":"Pasirmuncang",
    "gn:country_code":"ID",
    "gn:dem":349,
    "gn:feature_class":"P",
    "gn:feature_code":"PPL",
    "gn:name":"Pasirmuncang",
    "gn:population":0,
    "gn:timezone":"Asia/Jakarta",
    "iso:country":"ID",
    "name:ind_x_preferred":[
        "Pasirmuncang"
    ],
    "name:und_x_variant":[
        "Pasirmuntjang",
        "Pasirmuncang",
        "Pasirmoentjang"
    ],
    "wof:name":"Pasirmuncang",
    "wof:placetype":"locality"
},
  "geometry": {"coordinates":[107.46514999999999,-7.43772],"type":"Point"}
}