{
  "type": "Feature",
  "properties": {
    "gn:admin1_code":"26",
    "gn:asciiname":"Hilihoya",
    "gn:country_code":"ID",
    "gn:dem":15,
    "gn:feature_class":"P",
    "gn:feature_code":"PPL",
    "gn:name":"Hilihoya",
    "gn:population":0,
    "gn:timezone":"Asia/Jakarta",
    "iso:country":"ID",
    "name:ind_x_preferred":[
        "Hilihoya"
    ],
    "name:und_x_variant":[
        "Hilihoja"
    ],
    "wof:lang_x_official":[
        "ind"
    ],
    "wof:lang_x_spoken":[
        "ind",
        "eng"
    ],
    "wof:name":"Hilihoya",
    "wof:placetype":"locality"
},
  "geometry": {"coordinates":[97.5943,0.8497],"type":"Point"}
}