{
  "type": "Feature",
  "properties": {
    "gn:admin1_code":"33",
    "gn:asciiname":"Cikowak",
    "gn:country_code":"ID",
    "gn:dem":29,
    "gn:feature_class":"P",
    "gn:feature_code":"PPL",
    "gn:name":"Cikowak",
    "gn:population":0,
    "gn:timezone":"Asia/Jakarta",
    "iso:country":"ID",
    "name:ind_x_preferred":[
        "Cikowak"
    ],
    "name:und_x_variant":[
        "Tjikoak 2",
        "Tjikoak Dua",
        "Cikoak Dua"
    ],
    "wof:name":"Cikowak",
    "wof:placetype":"locality"
},
  "geometry": {"coordinates":[106.3142,-6.2798],"type":"Point"}
}