{
  "type": "Feature",
  "properties": {
    "gn:admin1_code":"08",
    "gn:asciiname":"Palaan",
    "gn:country_code":"ID",
    "gn:dem":356,
    "gn:feature_class":"P",
    "gn:feature_code":"PPLA4",
    "gn:name":"Palaan",
    "gn:population":0,
    "gn:timezone":"Asia/Jakarta",
    "iso:country":"ID",
    "name:ind_x_preferred":[
        "Palaan"
    ],
    "name:und_x_variant":[
        "Palahan"
    ],
    "wof:lang_x_official":[
        "ind"
    ],
    "wof:lang_x_spoken":[
        "ind",
        "eng"
    ],
    "wof:name":"Palaan",
    "wof:placetype":"locality"
},
  "geometry": {"coordinates":[112.5478,-8.1049],"type":"Point"}
}