{
  "type": "Feature",
  "properties": {
    "gn:admin1_code":"12.0",
    "gn:asciiname":"Sungaikupang",
    "gn:country_code":"ID",
    "gn:dem":14,
    "gn:feature_class":"P",
    "gn:feature_code":"PPLA3",
    "gn:name":"Sungaikupang",
    "gn:population":0,
    "gn:timezone":"Asia/Makassar",
    "iso:country":"ID",
    "name:und_x_variant":[
        "Kupang",
        "Soengaikoepang",
        "Sungaikupang"
    ],
    "wof:name":"Sungaikupang",
    "wof:placetype":"locality"
},
  "geometry": {"coordinates":[115.9918,-3.0438],"type":"Point"}
}