{
  "type": "Feature",
  "properties": {
    "gn:admin1_code":"17",
    "gn:asciiname":"Pelangsang",
    "gn:country_code":"ID",
    "gn:dem":114,
    "gn:feature_class":"P",
    "gn:feature_code":"PPL",
    "gn:name":"Pelangsang",
    "gn:population":0,
    "gn:timezone":"Asia/Makassar",
    "iso:country":"ID",
    "name:ind_x_preferred":[
        "Pelangsang"
    ],
    "wof:lang_x_official":[
        "ind"
    ],
    "wof:lang_x_spoken":[
        "ind",
        "eng"
    ],
    "wof:name":"Pelangsang",
    "wof:placetype":"locality"
},
  "geometry": {"coordinates":[116.2826,-8.7908],"type":"Point"}
}