{
  "type": "Feature",
  "properties": {
    "gn:admin1_code":"29.0",
    "gn:asciiname":"Tawa",
    "gn:country_code":"ID",
    "gn:dem":12,
    "gn:feature_class":"P",
    "gn:feature_code":"PPL",
    "gn:name":"Tawa",
    "gn:population":0,
    "gn:timezone":"Asia/Jayapura",
    "iso:country":"ID",
    "name:ind_x_preferred":[
        "Tawa"
    ],
    "wof:name":"Tawa",
    "wof:placetype":"locality"
},
  "geometry": {"coordinates":[128.06963000000002,-0.71758],"type":"Point"}
}