{
  "type": "Feature",
  "properties": {
    "gn:admin1_code":"29.0",
    "gn:asciiname":"Tawa",
    "gn:country_code":"ID",
    "gn:dem":12,
    "gn:feature_class":"P",
    "gn:feature_code":"PPL",
    "gn:name":"Tawa",
    "gn:population":0,
    "gn:timezone":"Asia/Jayapura",
    "iso:country":"ID",
    "name:ceb_x_preferred":[
        "Tawa"
    ],
    "name:deu_x_preferred":[
        "Tawa"
    ],
    "name:ind_x_preferred":[
        "Tawa"
    ],
    "name:ita_x_preferred":[
        "Tawa"
    ],
    "name:spa_x_preferred":[
        "Tawa"
    ],
    "name:swe_x_preferred":[
        "Tawa"
    ],
    "name:vie_x_preferred":[
        "Tawa"
    ],
    "wof:lang_x_official":[
        "ind"
    ],
    "wof:lang_x_spoken":[
        "ind",
        "eng"
    ],
    "wof:name":"Tawa",
    "wof:placetype":"locality"
},
  "geometry": {"coordinates":[128.06962999999999,-0.71758],"type":"Point"}
}