{
  "type": "Feature",
  "properties": {
    "gn:admin1_code":"38",
    "gn:asciiname":"Buttaguntung",
    "gn:country_code":"ID",
    "gn:dem":12,
    "gn:feature_class":"P",
    "gn:feature_code":"PPL",
    "gn:name":"Buttaguntung",
    "gn:population":0,
    "gn:timezone":"Asia/Makassar",
    "iso:country":"ID",
    "name:ind_x_preferred":[
        "Buttaguntung"
    ],
    "wof:name":"Buttaguntung",
    "wof:placetype":"locality"
},
  "geometry": {"coordinates":[119.5472,-5.6256],"type":"Point"}
}