{
  "type": "Feature",
  "properties": {
    "gn:admin1_code":"8",
    "gn:asciiname":"Ginuk",
    "gn:country_code":"ID",
    "gn:dem":195,
    "gn:feature_class":"P",
    "gn:feature_code":"PPL",
    "gn:name":"Ginuk",
    "gn:population":0,
    "gn:timezone":"Asia/Jakarta",
    "iso:country":"ID",
    "name:ind_x_preferred":[
        "Ginuk"
    ],
    "wof:name":"Ginuk",
    "wof:placetype":"locality"
},
  "geometry": {"coordinates":[111.34944,-7.58472],"type":"Point"}
}