{
  "type": "Feature",
  "properties": {
    "gn:admin1_code":"18.0",
    "gn:asciiname":"Fatumalelat",
    "gn:country_code":"ID",
    "gn:dem":300,
    "gn:feature_class":"P",
    "gn:feature_code":"PPL",
    "gn:name":"Fatumalelat",
    "gn:population":0,
    "gn:timezone":"Asia/Makassar",
    "iso:country":"ID",
    "name:ind_x_preferred":[
        "Fatumalelat"
    ],
    "wof:name":"Fatumalelat",
    "wof:placetype":"locality"
},
  "geometry": {"coordinates":[123.70959999999999,-10.2234],"type":"Point"}
}