{
  "type": "Feature",
  "properties": {
    "gn:admin1_code":"1",
    "gn:asciiname":"Atgeatu",
    "gn:country_code":"ID",
    "gn:dem":1180,
    "gn:feature_class":"P",
    "gn:feature_code":"PPL",
    "gn:name":"Atgeatu",
    "gn:population":0,
    "gn:timezone":"Asia/Jakarta",
    "iso:country":"ID",
    "name:ind_x_preferred":[
        "Atgeatu"
    ],
    "wof:name":"Atgeatu",
    "wof:placetype":"locality"
},
  "geometry": {"coordinates":[97.2385,4.0125],"type":"Point"}
}