{
  "type": "Feature",
  "properties": {
    "gn:admin1_code":"41.0",
    "gn:asciiname":"Malabo",
    "gn:country_code":"ID",
    "gn:dem":1077,
    "gn:feature_class":"P",
    "gn:feature_code":"PPL",
    "gn:name":"Malabo",
    "gn:population":0,
    "gn:timezone":"Asia/Makassar",
    "iso:country":"ID",
    "name:ind_x_preferred":[
        "Malabo"
    ],
    "wof:name":"Malabo",
    "wof:placetype":"locality"
},
  "geometry": {"coordinates":[119.3039,-3.0352],"type":"Point"}
}