{
  "type": "Feature",
  "properties": {
    "gn:admin1_code":"8.0",
    "gn:asciiname":"Batuan",
    "gn:country_code":"ID",
    "gn:dem":85,
    "gn:feature_class":"P",
    "gn:feature_code":"PPL",
    "gn:name":"Batuan",
    "gn:population":0,
    "gn:timezone":"Asia/Jakarta",
    "iso:country":"ID",
    "name:ceb_x_preferred":[
        "Batuan"
    ],
    "name:deu_x_preferred":[
        "Batuan"
    ],
    "name:fra_x_preferred":[
        "Batuan"
    ],
    "name:ind_x_preferred":[
        "Batuan"
    ],
    "name:ita_x_preferred":[
        "Batuan"
    ],
    "name:nld_x_preferred":[
        "Batuan"
    ],
    "name:nor_x_preferred":[
        "Batuan"
    ],
    "name:swe_x_preferred":[
        "Batuan"
    ],
    "name:war_x_preferred":[
        "Batuan"
    ],
    "wof:lang_x_official":[
        "ind"
    ],
    "wof:lang_x_spoken":[
        "ind",
        "eng"
    ],
    "wof:name":"Batuan",
    "wof:placetype":"locality"
},
  "geometry": {"coordinates":[113.48233,-7.80393],"type":"Point"}
}