{
  "type": "Feature",
  "properties": {
    "gn:admin1_code":"8",
    "gn:asciiname":"Selang",
    "gn:country_code":"ID",
    "gn:dem":428,
    "gn:feature_class":"P",
    "gn:feature_code":"PPL",
    "gn:name":"Selang",
    "gn:population":0,
    "gn:timezone":"Asia/Jakarta",
    "iso:country":"ID",
    "name:ind_x_preferred":[
        "Selang"
    ],
    "wof:name":"Selang",
    "wof:placetype":"locality"
},
  "geometry": {"coordinates":[111.27528,-8.07944],"type":"Point"}
}