{
  "type": "Feature",
  "properties": {
    "gn:admin1_code":"11.0",
    "gn:asciiname":"Rijal",
    "gn:country_code":"ID",
    "gn:dem":154,
    "gn:feature_class":"P",
    "gn:feature_code":"PPL",
    "gn:name":"Rijal",
    "gn:population":0,
    "gn:timezone":"Asia/Pontianak",
    "iso:country":"ID",
    "name:ind_x_preferred":[
        "Rijal"
    ],
    "wof:name":"Rijal",
    "wof:placetype":"locality"
},
  "geometry": {"coordinates":[111.33953,-0.5478],"type":"Point"}
}