{
  "type": "Feature",
  "properties": {
    "gn:admin1_code":"30.0",
    "gn:asciiname":"Cijeruk",
    "gn:country_code":"ID",
    "gn:dem":489,
    "gn:feature_class":"P",
    "gn:feature_code":"PPL",
    "gn:name":"Cijeruk",
    "gn:population":0,
    "gn:timezone":"Asia/Jakarta",
    "iso:country":"ID",
    "name:ind_x_preferred":[
        "Cijeruk"
    ],
    "wof:name":"Cijeruk",
    "wof:placetype":"locality"
},
  "geometry": {"coordinates":[107.81827,-7.54377],"type":"Point"}
}