{
  "type": "Feature",
  "properties": {
    "gn:admin1_code":"38",
    "gn:asciiname":"Bulutabbampang",
    "gn:country_code":"ID",
    "gn:dem":13,
    "gn:feature_class":"P",
    "gn:feature_code":"PPL",
    "gn:name":"Bulutabbampang",
    "gn:population":0,
    "gn:timezone":"Asia/Makassar",
    "iso:country":"ID",
    "name:ind_x_preferred":[
        "Bulutabbampang"
    ],
    "wof:name":"Bulutabbampang",
    "wof:placetype":"locality"
},
  "geometry": {"coordinates":[119.639,-4.8989],"type":"Point"}
}