{
  "type": "Feature",
  "properties": {
    "gn:country":"ID",
    "gn:fcode":"PPL",
    "gn:pop":0,
    "iso:country":"ID",
    "name:ace_x_preferred":[
        "Pemuteran"
    ],
    "name:deu_x_preferred":[
        "Pemuteran"
    ],
    "name:eng_x_preferred":[
        "Pemuteran"
    ],
    "name:fra_x_preferred":[
        "Pemuteran"
    ],
    "name:ind_x_preferred":[
        "Pemuteran"
    ],
    "name:msa_x_preferred":[
        "Pemuteran"
    ],
    "name:nld_x_preferred":[
        "Pemuteran"
    ],
    "name:por_x_preferred":[
        "Pemuteran"
    ],
    "name:spa_x_preferred":[
        "Pemuteran"
    ],
    "qs:name":"Pemuteran",
    "qs:name_adm0":"Indonesia",
    "qs:name_adm1":"Bali",
    "qs:photos":775,
    "qs:photos_1k":157,
    "qs:photos_9k":3,
    "qs:photos_9r":6,
    "qs:photos_all":775,
    "qs:photos_sr":9,
    "qs:placetype":"Town",
    "qs:pop_sr":"0",
    "wof:name":"Pemuteran",
    "wof:placetype":"locality",
    "wof:population":0
},
  "geometry": {"coordinates":[114.63048999999999,-8.16358],"type":"Point"}
}