{
  "type": "Feature",
  "properties": {
    "gn:admin1_code":"17",
    "gn:asciiname":"Pelulan",
    "gn:country_code":"ID",
    "gn:dem":53,
    "gn:feature_class":"P",
    "gn:feature_code":"PPL",
    "gn:name":"Pelulan",
    "gn:population":0,
    "gn:timezone":"Asia/Makassar",
    "iso:country":"ID",
    "name:ind_x_preferred":[
        "Pelulan"
    ],
    "wof:name":"Pelulan",
    "wof:placetype":"locality"
},
  "geometry": {"coordinates":[116.182,-8.6467],"type":"Point"}
}