{
  "type": "Feature",
  "properties": {
    "gn:admin1_code":"7.0",
    "gn:asciiname":"Karangdawung",
    "gn:country_code":"ID",
    "gn:dem":306,
    "gn:feature_class":"P",
    "gn:feature_code":"PPL",
    "gn:name":"Karangdawung",
    "gn:population":0,
    "gn:timezone":"Asia/Jakarta",
    "iso:country":"ID",
    "wof:name":"Karangdawung",
    "wof:placetype":"locality"
},
  "geometry": {"coordinates":[110.63306,-7.36583],"type":"Point"}
}