{
  "type": "Feature",
  "properties": {
    "gn:admin1_code":"30.0",
    "gn:asciiname":"Babakanpeundeuy",
    "gn:country_code":"ID",
    "gn:dem":438,
    "gn:feature_class":"P",
    "gn:feature_code":"PPL",
    "gn:name":"Babakanpeundeuy",
    "gn:population":0,
    "gn:timezone":"Asia/Jakarta",
    "iso:country":"ID",
    "name:ind_x_preferred":[
        "Babakanpeundeuy"
    ],
    "wof:name":"Babakanpeundeuy",
    "wof:placetype":"locality"
},
  "geometry": {"coordinates":[108.1815,-7.2768],"type":"Point"}
}