{
  "type": "Feature",
  "properties": {
    "gn:admin1_code":"8.0",
    "gn:asciiname":"Bumireja",
    "gn:country_code":"ID",
    "gn:dem":618,
    "gn:feature_class":"P",
    "gn:feature_code":"PPL",
    "gn:name":"Bumireja",
    "gn:population":0,
    "gn:timezone":"Asia/Jakarta",
    "iso:country":"ID",
    "name:ind_x_preferred":[
        "Bumireja"
    ],
    "name:und_x_variant":[
        "Bumiredjo",
        "Bumirejo"
    ],
    "wof:name":"Bumireja",
    "wof:placetype":"locality"
},
  "geometry": {"coordinates":[112.5004,-8.054],"type":"Point"}
}