{
  "type": "Feature",
  "properties": {
    "gn:admin1_code":"33.0",
    "gn:asciiname":"Kandang Timur",
    "gn:country_code":"ID",
    "gn:dem":16,
    "gn:feature_class":"P",
    "gn:feature_code":"PPLA4",
    "gn:name":"Kandang Timur",
    "gn:population":0,
    "gn:timezone":"Asia/Jakarta",
    "iso:country":"ID",
    "name:ind_x_preferred":[
        "Kandang"
    ],
    "name:ind_x_variant":[
        "Kandang Timur"
    ],
    "wof:lang_x_official":[
        "ind"
    ],
    "wof:lang_x_spoken":[
        "ind",
        "eng"
    ],
    "wof:name":"Kandang Timur",
    "wof:placetype":"locality"
},
  "geometry": {"coordinates":[106.00597999999999,-6.80416],"type":"Point"}
}