{
  "type": "Feature",
  "properties": {
    "gn:admin1_code":"17",
    "gn:asciiname":"Batungapih",
    "gn:country_code":"ID",
    "gn:dem":19,
    "gn:feature_class":"P",
    "gn:feature_code":"PPL",
    "gn:name":"Batungapih",
    "gn:population":0,
    "gn:timezone":"Asia/Makassar",
    "iso:country":"ID",
    "name:ind_x_preferred":[
        "Batungapih"
    ],
    "wof:name":"Batungapih",
    "wof:placetype":"locality"
},
  "geometry": {"coordinates":[116.5003,-8.7761],"type":"Point"}
}