{
  "type": "Feature",
  "properties": {
    "gn:admin1_code":"30",
    "gn:asciiname":"Tapos Girang",
    "gn:country_code":"ID",
    "gn:dem":458,
    "gn:feature_class":"P",
    "gn:feature_code":"PPL",
    "gn:name":"Tapos Girang",
    "gn:population":0,
    "gn:timezone":"Asia/Jakarta",
    "iso:country":"ID",
    "name:ind_x_preferred":[
        "Tapos Girang"
    ],
    "name:und_x_variant":[
        "Tapas-girang"
    ],
    "wof:lang_x_official":[
        "ind"
    ],
    "wof:lang_x_spoken":[
        "ind",
        "eng"
    ],
    "wof:name":"Tapos Girang",
    "wof:placetype":"locality"
},
  "geometry": {"coordinates":[107.405,-6.76861],"type":"Point"}
}