{
  "type": "Feature",
  "properties": {
    "gn:admin1_code":"38",
    "gn:asciiname":"Pakkali",
    "gn:country_code":"ID",
    "gn:dem":30,
    "gn:feature_class":"P",
    "gn:feature_code":"PPL",
    "gn:name":"Pakkali",
    "gn:population":0,
    "gn:timezone":"Asia/Makassar",
    "iso:country":"ID",
    "name:ind_x_preferred":[
        "Pakkali"
    ],
    "wof:name":"Pakkali",
    "wof:placetype":"locality"
},
  "geometry": {"coordinates":[120.3396,-2.5958],"type":"Point"}
}