{
  "type": "Feature",
  "properties": {
    "gn:admin1_code":"8",
    "gn:asciiname":"Banyurejo Lor",
    "gn:country_code":"ID",
    "gn:dem":579,
    "gn:feature_class":"P",
    "gn:feature_code":"PPL",
    "gn:name":"Banyurejo Lor",
    "gn:population":0,
    "gn:timezone":"Asia/Jakarta",
    "iso:country":"ID",
    "name:ind_x_preferred":[
        "Banyurejo Lor"
    ],
    "wof:name":"Banyurejo Lor",
    "wof:placetype":"locality"
},
  "geometry": {"coordinates":[114.17709000000001,-8.19035],"type":"Point"}
}