{
  "type": "Feature",
  "properties": {
    "gn:admin1_code":"07",
    "gn:asciiname":"Wolorejo",
    "gn:country_code":"ID",
    "gn:dem":797,
    "gn:feature_class":"P",
    "gn:feature_code":"PPL",
    "gn:name":"Wolorejo",
    "gn:population":0,
    "gn:timezone":"Asia/Jakarta",
    "iso:country":"ID",
    "wof:name":"Wolorejo",
    "wof:placetype":"locality"
},
  "geometry": {"coordinates":[110.51000000000001,-7.58278],"type":"Point"}
}