{
  "type": "Feature",
  "properties": {
    "gn:admin1_code":"30",
    "gn:asciiname":"Cihonje",
    "gn:country_code":"ID",
    "gn:dem":312,
    "gn:feature_class":"P",
    "gn:feature_code":"PPL",
    "gn:name":"Cihonje",
    "gn:population":0,
    "gn:timezone":"Asia/Jakarta",
    "iso:country":"ID",
    "name:ind_x_preferred":[
        "Cihonje"
    ],
    "wof:name":"Cihonje",
    "wof:placetype":"locality"
},
  "geometry": {"coordinates":[106.76667,-6.98667],"type":"Point"}
}