{
  "type": "Feature",
  "properties": {
    "gn:admin1_code":"32.0",
    "gn:asciiname":"Talangtinggi",
    "gn:country_code":"ID",
    "gn:dem":848,
    "gn:feature_class":"P",
    "gn:feature_code":"PPL",
    "gn:name":"Talangtinggi",
    "gn:population":0,
    "gn:timezone":"Asia/Jakarta",
    "iso:country":"ID",
    "name:ind_x_preferred":[
        "Talangtinggi"
    ],
    "wof:name":"Talangtinggi",
    "wof:placetype":"locality"
},
  "geometry": {"coordinates":[103.1387,-3.9386],"type":"Point"}
}