{
  "type": "Feature",
  "properties": {
    "gn:admin1_code":"10.0",
    "gn:asciiname":"Ngurakurak",
    "gn:country_code":"ID",
    "gn:dem":353,
    "gn:feature_class":"P",
    "gn:feature_code":"PPL",
    "gn:name":"Ngurakurak",
    "gn:population":0,
    "gn:timezone":"Asia/Jakarta",
    "iso:country":"ID",
    "name:ind_x_preferred":[
        "Ngurakurak"
    ],
    "wof:name":"Ngurakurak",
    "wof:placetype":"locality"
},
  "geometry": {"coordinates":[110.72583,-8.07139],"type":"Point"}
}