{
  "type": "Feature",
  "properties": {
    "gn:admin1_code":"15.0",
    "gn:asciiname":"Bumijaya",
    "gn:country_code":"ID",
    "gn:dem":556,
    "gn:feature_class":"P",
    "gn:feature_code":"PPL",
    "gn:name":"Bumijaya",
    "gn:population":0,
    "gn:timezone":"Asia/Jakarta",
    "iso:country":"ID",
    "name:ind_x_preferred":[
        "Bumijaya"
    ],
    "wof:name":"Bumijaya",
    "wof:placetype":"locality"
},
  "geometry": {"coordinates":[104.21988,-5.11373],"type":"Point"}
}