{
  "type": "Feature",
  "properties": {
    "gn:admin1_code":"7",
    "gn:asciiname":"Dukuh Wetan",
    "gn:country_code":"ID",
    "gn:dem":18,
    "gn:feature_class":"P",
    "gn:feature_code":"PPL",
    "gn:name":"Dukuh Wetan",
    "gn:population":0,
    "gn:timezone":"Asia/Jakarta",
    "iso:country":"ID",
    "name:ind_x_preferred":[
        "Dukuh Wetan"
    ],
    "wof:name":"Dukuh Wetan",
    "wof:placetype":"locality"
},
  "geometry": {"coordinates":[109.84556000000001,-7.67861],"type":"Point"}
}