{
  "type": "Feature",
  "properties": {
    "gn:admin1_code":"26.0",
    "gn:asciiname":"Hiliotaluwa",
    "gn:country_code":"ID",
    "gn:dem":47,
    "gn:feature_class":"P",
    "gn:feature_code":"PPL",
    "gn:name":"Hiliotaluwa",
    "gn:population":0,
    "gn:timezone":"Asia/Jakarta",
    "iso:country":"ID",
    "name:ind_x_preferred":[
        "Hiliotaluwa"
    ],
    "name:und_x_variant":[
        "Hiliotaloewa"
    ],
    "wof:name":"Hiliotaluwa",
    "wof:placetype":"locality"
},
  "geometry": {"coordinates":[97.88890000000001,0.7312],"type":"Point"}
}