{
  "type": "Feature",
  "properties": {
    "gn:admin1_code":"1",
    "gn:asciiname":"Bugo",
    "gn:country_code":"ID",
    "gn:dem":22,
    "gn:feature_class":"P",
    "gn:feature_code":"PPL",
    "gn:name":"Bugo",
    "gn:population":0,
    "gn:timezone":"Asia/Jakarta",
    "iso:country":"ID",
    "name:ind_x_preferred":[
        "Bugo"
    ],
    "name:ita_x_preferred":[
        "Bugo"
    ],
    "wof:name":"Bugo",
    "wof:placetype":"locality"
},
  "geometry": {"coordinates":[95.3556,5.4666],"type":"Point"}
}