{
  "type": "Feature",
  "properties": {
    "gn:admin1_code":"30",
    "gn:asciiname":"Selaawi Tiga",
    "gn:country_code":"ID",
    "gn:dem":129,
    "gn:feature_class":"P",
    "gn:feature_code":"PPL",
    "gn:name":"Selaawi Tiga",
    "gn:population":0,
    "gn:timezone":"Asia/Jakarta",
    "iso:country":"ID",
    "name:ind_x_preferred":[
        "Selaawi Tiga"
    ],
    "wof:lang_x_official":[
        "ind"
    ],
    "wof:lang_x_spoken":[
        "ind",
        "eng"
    ],
    "wof:name":"Selaawi Tiga",
    "wof:placetype":"locality"
},
  "geometry": {"coordinates":[107.4875,-6.55556],"type":"Point"}
}