{
  "type": "Feature",
  "properties": {
    "gn:admin1_code":"30",
    "gn:asciiname":"Bakung",
    "gn:country_code":"ID",
    "gn:dem":9,
    "gn:feature_class":"P",
    "gn:feature_code":"PPL",
    "gn:name":"Bakung",
    "gn:population":0,
    "gn:timezone":"Asia/Jakarta",
    "iso:country":"ID",
    "name:ind_x_preferred":[
        "Bakung"
    ],
    "wof:name":"Bakung",
    "wof:placetype":"locality"
},
  "geometry": {"coordinates":[108.46693999999999,-6.51778],"type":"Point"}
}