{
  "type": "Feature",
  "properties": {
    "gn:admin1_code":"30",
    "gn:asciiname":"Batuh",
    "gn:country_code":"ID",
    "gn:dem":825,
    "gn:feature_class":"P",
    "gn:feature_code":"PPL",
    "gn:name":"Batuh",
    "gn:population":0,
    "gn:timezone":"Asia/Jakarta",
    "iso:country":"ID",
    "wof:name":"Batuh",
    "wof:placetype":"locality"
},
  "geometry": {"coordinates":[107.71666999999999,-7.09361],"type":"Point"}
}