{
  "type": "Feature",
  "properties": {
    "gn:admin1_code":"30",
    "gn:asciiname":"Babakansuma",
    "gn:country_code":"ID",
    "gn:dem":56,
    "gn:feature_class":"P",
    "gn:feature_code":"PPL",
    "gn:name":"Babakansuma",
    "gn:population":0,
    "gn:timezone":"Asia/Jakarta",
    "iso:country":"ID",
    "name:ind_x_preferred":[
        "Babakansuma"
    ],
    "wof:name":"Babakansuma",
    "wof:placetype":"locality"
},
  "geometry": {"coordinates":[107.78417,-6.5075],"type":"Point"}
}