{
  "type": "Feature",
  "properties": {
    "gn:admin1_code":"30",
    "gn:asciiname":"Baros",
    "gn:country_code":"ID",
    "gn:dem":715,
    "gn:feature_class":"P",
    "gn:feature_code":"PPL",
    "gn:name":"Baros",
    "gn:population":0,
    "gn:timezone":"Asia/Jakarta",
    "iso:country":"ID",
    "name:ceb_x_preferred":[
        "Baros"
    ],
    "name:deu_x_preferred":[
        "Baros"
    ],
    "name:ell_x_preferred":[
        "\u0392\u03ac\u03c1\u03bf\u03c2"
    ],
    "name:fra_x_preferred":[
        "Baroche"
    ],
    "name:hun_x_preferred":[
        "Baros"
    ],
    "name:ind_x_preferred":[
        "Baros"
    ],
    "name:ita_x_preferred":[
        "Baros"
    ],
    "name:nld_x_preferred":[
        "Baros"
    ],
    "name:ron_x_preferred":[
        "Baros"
    ],
    "name:rus_x_preferred":[
        "\u0411\u0430\u0440\u043e\u0448"
    ],
    "name:spa_x_preferred":[
        "Baros"
    ],
    "name:swe_x_preferred":[
        "Baros"
    ],
    "wof:lang_x_official":[
        "ind"
    ],
    "wof:lang_x_spoken":[
        "ind",
        "eng"
    ],
    "wof:name":"Baros",
    "wof:placetype":"locality"
},
  "geometry": {"coordinates":[107.55944,-6.69333],"type":"Point"}
}