{
  "type": "Feature",
  "properties": {
    "gn:admin1_code":"21",
    "gn:asciiname":"Longgolian",
    "gn:country_code":"ID",
    "gn:dem":13,
    "gn:feature_class":"P",
    "gn:feature_code":"PPL",
    "gn:name":"Longgolian",
    "gn:population":0,
    "gn:timezone":"Asia/Makassar",
    "iso:country":"ID",
    "name:ind_x_preferred":[
        "Longgolian"
    ],
    "wof:name":"Longgolian",
    "wof:placetype":"locality"
},
  "geometry": {"coordinates":[122.3236,-0.7877],"type":"Point"}
}