{
  "type": "Feature",
  "properties": {
    "gn:admin1_code":"7.0",
    "gn:asciiname":"Kepuh",
    "gn:country_code":"ID",
    "gn:dem":21,
    "gn:feature_class":"P",
    "gn:feature_code":"PPL",
    "gn:name":"Kepuh",
    "gn:population":0,
    "gn:timezone":"Asia/Jakarta",
    "iso:country":"ID",
    "name:ind_x_preferred":[
        "Kepuh"
    ],
    "wof:name":"Kepuh",
    "wof:placetype":"locality"
},
  "geometry": {"coordinates":[109.61278,-7.69278],"type":"Point"}
}