{
  "type": "Feature",
  "properties": {
    "gn:admin1_code":"38.0",
    "gn:asciiname":"Barunggalanda",
    "gn:country_code":"ID",
    "gn:dem":950,
    "gn:feature_class":"P",
    "gn:feature_code":"PPL",
    "gn:name":"Barunggalanda",
    "gn:population":0,
    "gn:timezone":"Asia/Makassar",
    "iso:country":"ID",
    "name:ind_x_preferred":[
        "Barunggalanda"
    ],
    "wof:name":"Barunggalanda",
    "wof:placetype":"locality"
},
  "geometry": {"coordinates":[119.5476,-3.3449],"type":"Point"}
}