{
  "type": "Feature",
  "properties": {
    "gn:admin1_code":"15.0",
    "gn:asciiname":"Umbulan Banyak",
    "gn:country_code":"ID",
    "gn:dem":31,
    "gn:feature_class":"P",
    "gn:feature_code":"PPL",
    "gn:name":"Umbulan Banyak",
    "gn:population":0,
    "gn:timezone":"Asia/Jakarta",
    "iso:country":"ID",
    "name:ind_x_preferred":[
        "Umbulan Banyak"
    ],
    "name:ind_x_variant":[
        "Umbulanbanyak"
    ],
    "wof:name":"Umbulan Banyak",
    "wof:placetype":"locality"
},
  "geometry": {"coordinates":[105.58684,-4.41254],"type":"Point"}
}