{
  "type": "Feature",
  "properties": {
    "gn:admin1_code":"18.0",
    "gn:asciiname":"Bestobe",
    "gn:country_code":"ID",
    "gn:dem":849,
    "gn:feature_class":"P",
    "gn:feature_code":"PPL",
    "gn:name":"Bestobe",
    "gn:population":0,
    "gn:timezone":"Asia/Makassar",
    "iso:country":"ID",
    "name:ind_x_preferred":[
        "Bestobe"
    ],
    "wof:name":"Bestobe",
    "wof:placetype":"locality"
},
  "geometry": {"coordinates":[124.49833,-9.85622],"type":"Point"}
}