{
  "type": "Feature",
  "properties": {
    "gn:admin1_code":"18.0",
    "gn:asciiname":"Kakabai",
    "gn:country_code":"ID",
    "gn:dem":25,
    "gn:feature_class":"P",
    "gn:feature_code":"PPL",
    "gn:name":"Kakabai",
    "gn:population":0,
    "gn:timezone":"Asia/Makassar",
    "iso:country":"ID",
    "name:ind_x_preferred":[
        "Kakabai"
    ],
    "wof:name":"Kakabai",
    "wof:placetype":"locality"
},
  "geometry": {"coordinates":[123.851,-10.0441],"type":"Point"}
}