{
  "type": "Feature",
  "properties": {
    "gn:admin1_code":"1",
    "gn:asciiname":"Kampung Blang",
    "gn:country_code":"ID",
    "gn:dem":7,
    "gn:feature_class":"P",
    "gn:feature_code":"PPL",
    "gn:name":"Kampung Blang",
    "gn:population":0,
    "gn:timezone":"Asia/Jakarta",
    "iso:country":"ID",
    "name:ind_x_preferred":[
        "Kampung Blang"
    ],
    "wof:name":"Kampung Blang",
    "wof:placetype":"locality"
},
  "geometry": {"coordinates":[95.291,5.5512],"type":"Point"}
}