{
  "type": "Feature",
  "properties": {
    "gn:country":"ID",
    "gn:fcode":"PPL",
    "gn:pop":0,
    "iso:country":"ID",
    "name:ace_x_preferred":[
        "Suliki"
    ],
    "name:deu_x_preferred":[
        "Suliki"
    ],
    "name:eng_x_preferred":[
        "Suliki"
    ],
    "name:eng_x_variant":[
        "Babakan Surabaya"
    ],
    "name:fra_x_preferred":[
        "Suliki"
    ],
    "name:ind_x_preferred":[
        "Suliki"
    ],
    "name:min_x_preferred":[
        "Suliki"
    ],
    "name:msa_x_preferred":[
        "Suliki"
    ],
    "name:nld_x_preferred":[
        "Suliki"
    ],
    "name:por_x_preferred":[
        "Suliki"
    ],
    "name:spa_x_preferred":[
        "Suliki"
    ],
    "name:unk_x_variant":[
        "Soelild"
    ],
    "qs:name":"Suliki",
    "qs:name_adm0":"Indonesia",
    "qs:name_adm1":"Sumatera Barat",
    "qs:photos_9k":1,
    "qs:photos_9r":1,
    "qs:photos_all":1,
    "qs:photos_sr":0,
    "qs:placetype":"Town",
    "qs:pop_sr":"0",
    "wd:wordcount":67,
    "wof:lang_x_official":[
        "ind"
    ],
    "wof:lang_x_spoken":[
        "ind",
        "eng"
    ],
    "wof:name":"Suliki",
    "wof:placetype":"locality",
    "wof:population":0
},
  "geometry": {"coordinates":[100.49847,-0.10625],"type":"Point"}
}