{
  "type": "Feature",
  "properties": {
    "gn:admin1_code":"30",
    "gn:asciiname":"Nangewer",
    "gn:country_code":"ID",
    "gn:dem":407,
    "gn:feature_class":"P",
    "gn:feature_code":"PPL",
    "gn:name":"Nangewer",
    "gn:population":0,
    "gn:timezone":"Asia/Jakarta",
    "iso:country":"ID",
    "name:ind_x_preferred":[
        "Nangewer"
    ],
    "name:und_x_variant":[
        "Nanggewer"
    ],
    "wof:name":"Nangewer",
    "wof:placetype":"locality"
},
  "geometry": {"coordinates":[107.15472,-6.875],"type":"Point"}
}