{
  "type": "Feature",
  "properties": {
    "gn:admin1_code":"33",
    "gn:asciiname":"Bumicibeberkencana",
    "gn:country_code":"ID",
    "gn:dem":18,
    "gn:feature_class":"P",
    "gn:feature_code":"PPL",
    "gn:name":"Bumicibeberkencana",
    "gn:population":0,
    "gn:timezone":"Asia/Jakarta",
    "iso:country":"ID",
    "name:ind_x_preferred":[
        "Bumicibeberkencana"
    ],
    "wof:name":"Bumicibeberkencana",
    "wof:placetype":"locality"
},
  "geometry": {"coordinates":[106.0628,-6.0406],"type":"Point"}
}