{
  "type": "Feature",
  "properties": {
    "gn:admin1_code":"1.0",
    "gn:asciiname":"Aluetiti",
    "gn:country_code":"ID",
    "gn:dem":24,
    "gn:feature_class":"P",
    "gn:feature_code":"PPL",
    "gn:name":"Aluetiti",
    "gn:population":0,
    "gn:timezone":"Asia/Jakarta",
    "iso:country":"ID",
    "name:ind_x_preferred":[
        "Aluetiti"
    ],
    "name:und_x_variant":[
        "Aloe\u00eb Titi"
    ],
    "wof:name":"Aluetiti",
    "wof:placetype":"locality"
},
  "geometry": {"coordinates":[95.56100000000001,4.6689],"type":"Point"}
}