{
  "type": "Feature",
  "properties": {
    "gn:admin1_code":"30.0",
    "gn:asciiname":"Babakansalam",
    "gn:country_code":"ID",
    "gn:dem":1101,
    "gn:feature_class":"P",
    "gn:feature_code":"PPL",
    "gn:name":"Babakansalam",
    "gn:population":0,
    "gn:timezone":"Asia/Jakarta",
    "iso:country":"ID",
    "name:ind_x_preferred":[
        "Babakansalam"
    ],
    "wof:name":"Babakansalam",
    "wof:placetype":"locality"
},
  "geometry": {"coordinates":[107.1133,-7.0488],"type":"Point"}
}