{
  "type": "Feature",
  "properties": {
    "gn:admin1_code":"30.0",
    "gn:asciiname":"Empangsari",
    "gn:country_code":"ID",
    "gn:dem":472,
    "gn:feature_class":"P",
    "gn:feature_code":"PPL",
    "gn:name":"Empangsari",
    "gn:population":0,
    "gn:timezone":"Asia/Jakarta",
    "iso:country":"ID",
    "name:ind_x_preferred":[
        "Empangsari"
    ],
    "wof:name":"Empangsari",
    "wof:placetype":"locality"
},
  "geometry": {"coordinates":[108.12909999999999,-7.3141],"type":"Point"}
}