{
  "type": "Feature",
  "properties": {
    "gn:admin1_code":"17",
    "gn:asciiname":"Karijawa Utara",
    "gn:country_code":"ID",
    "gn:dem":29,
    "gn:feature_class":"P",
    "gn:feature_code":"PPL",
    "gn:name":"Karijawa Utara",
    "gn:population":0,
    "gn:timezone":"Asia/Makassar",
    "iso:country":"ID",
    "name:ind_x_preferred":[
        "Karijawa Utara"
    ],
    "wof:name":"Karijawa Utara",
    "wof:placetype":"locality"
},
  "geometry": {"coordinates":[118.46129999999999,-8.5373],"type":"Point"}
}