{
  "type": "Feature",
  "properties": {
    "gn:admin1_code":"18.0",
    "gn:asciiname":"Welimwatu",
    "gn:country_code":"ID",
    "gn:dem":645,
    "gn:feature_class":"P",
    "gn:feature_code":"PPL",
    "gn:name":"Welimwatu",
    "gn:population":0,
    "gn:timezone":"Asia/Makassar",
    "iso:country":"ID",
    "name:ind_x_preferred":[
        "Welimwatu"
    ],
    "wof:name":"Welimwatu",
    "wof:placetype":"locality"
},
  "geometry": {"coordinates":[122.4365,-8.6982],"type":"Point"}
}