{
  "type": "Feature",
  "properties": {
    "gn:admin1_code":"41.0",
    "gn:asciiname":"Lomba",
    "gn:country_code":"ID",
    "gn:dem":1003,
    "gn:feature_class":"P",
    "gn:feature_code":"PPL",
    "gn:name":"Lomba",
    "gn:population":0,
    "gn:timezone":"Asia/Makassar",
    "iso:country":"ID",
    "name:ind_x_preferred":[
        "Lomba"
    ],
    "wof:name":"Lomba",
    "wof:placetype":"locality"
},
  "geometry": {"coordinates":[119.24120000000001,-2.9285],"type":"Point"}
}