{
  "type": "Feature",
  "properties": {
    "gn:admin1_code":"41.0",
    "gn:asciiname":"Lomba",
    "gn:country_code":"ID",
    "gn:dem":1003,
    "gn:feature_class":"P",
    "gn:feature_code":"PPL",
    "gn:name":"Lomba",
    "gn:population":0,
    "gn:timezone":"Asia/Makassar",
    "iso:country":"ID",
    "name:ceb_x_preferred":[
        "Lomba"
    ],
    "name:deu_x_preferred":[
        "Lomba"
    ],
    "name:fra_x_preferred":[
        "Lomba"
    ],
    "name:glg_x_preferred":[
        "Lomba"
    ],
    "name:ind_x_preferred":[
        "Lomba"
    ],
    "name:nld_x_preferred":[
        "Lomba"
    ],
    "name:por_x_preferred":[
        "Lomba"
    ],
    "name:rus_x_preferred":[
        "\u041b\u043e\u043c\u0431\u0430"
    ],
    "name:swe_x_preferred":[
        "Lomba"
    ],
    "wof:lang_x_official":[
        "ind"
    ],
    "wof:lang_x_spoken":[
        "ind",
        "eng"
    ],
    "wof:name":"Lomba",
    "wof:placetype":"locality"
},
  "geometry": {"coordinates":[119.24120000000001,-2.9285],"type":"Point"}
}