{
  "type": "Feature",
  "properties": {
    "gn:admin1_code":"8",
    "gn:asciiname":"Kandangsari Lor",
    "gn:country_code":"ID",
    "gn:dem":2029,
    "gn:feature_class":"P",
    "gn:feature_code":"PPL",
    "gn:name":"Kandangsari Lor",
    "gn:population":0,
    "gn:timezone":"Asia/Jakarta",
    "iso:country":"ID",
    "name:ind_x_preferred":[
        "Kandangsari Lor"
    ],
    "wof:lang_x_official":[
        "ind"
    ],
    "wof:lang_x_spoken":[
        "ind",
        "eng"
    ],
    "wof:name":"Kandangsari Lor",
    "wof:placetype":"locality"
},
  "geometry": {"coordinates":[112.8925,-7.9258],"type":"Point"}
}