{
  "type": "Feature",
  "properties": {
    "gn:admin1_code":"29.0",
    "gn:asciiname":"Samuya",
    "gn:country_code":"ID",
    "gn:dem":12,
    "gn:feature_class":"P",
    "gn:feature_code":"PPL",
    "gn:name":"Samuya",
    "gn:population":0,
    "gn:timezone":"Asia/Jayapura",
    "iso:country":"ID",
    "name:ind_x_preferred":[
        "Samuya"
    ],
    "name:und_x_variant":[
        "Samuja",
        "Samoeja",
        "Samuya"
    ],
    "wof:lang_x_official":[
        "ind"
    ],
    "wof:lang_x_spoken":[
        "ind",
        "eng"
    ],
    "wof:name":"Samuya",
    "wof:placetype":"locality"
},
  "geometry": {"coordinates":[125.29307,-1.78314],"type":"Point"}
}