{
  "type": "Feature",
  "properties": {
    "gn:admin1_code":"30",
    "gn:asciiname":"Serang Kulon",
    "gn:country_code":"ID",
    "gn:dem":13,
    "gn:feature_class":"P",
    "gn:feature_code":"PPL",
    "gn:name":"Serang Kulon",
    "gn:population":0,
    "gn:timezone":"Asia/Jakarta",
    "iso:country":"ID",
    "name:ind_x_preferred":[
        "Serang Kulon"
    ],
    "wof:name":"Serang Kulon",
    "wof:placetype":"locality"
},
  "geometry": {"coordinates":[108.7043,-6.8696],"type":"Point"}
}