{
  "type": "Feature",
  "properties": {
    "gn:admin1_code":"8.0",
    "gn:asciiname":"Kampung Tengah",
    "gn:country_code":"ID",
    "gn:dem":465,
    "gn:feature_class":"P",
    "gn:feature_code":"PPL",
    "gn:name":"Kampung Tengah",
    "gn:population":0,
    "gn:timezone":"Asia/Jakarta",
    "iso:country":"ID",
    "name:ind_x_preferred":[
        "Kampung Tengah"
    ],
    "name:msa_x_preferred":[
        "Kampung Tengah"
    ],
    "wof:name":"Kampung Tengah",
    "wof:placetype":"locality"
},
  "geometry": {"coordinates":[112.8747,-8.2621],"type":"Point"}
}