{
  "type": "Feature",
  "properties": {
    "gn:admin1_code":"8.0",
    "gn:asciiname":"Ngawuk",
    "gn:country_code":"ID",
    "gn:dem":116,
    "gn:feature_class":"P",
    "gn:feature_code":"PPL",
    "gn:name":"Ngawuk",
    "gn:population":0,
    "gn:timezone":"Asia/Jakarta",
    "iso:country":"ID",
    "name:ind_x_preferred":[
        "Ngawuk"
    ],
    "name:und_x_variant":[
        "Ngawoek"
    ],
    "wof:name":"Ngawuk",
    "wof:placetype":"locality"
},
  "geometry": {"coordinates":[111.7602,-8.2186],"type":"Point"}
}