{
  "type": "Feature",
  "properties": {
    "gn:admin1_code":"15.0",
    "gn:asciiname":"Kebon Kelapa",
    "gn:country_code":"ID",
    "gn:dem":22,
    "gn:feature_class":"P",
    "gn:feature_code":"PPL",
    "gn:name":"Kebon Kelapa",
    "gn:population":0,
    "gn:timezone":"Asia/Jakarta",
    "iso:country":"ID",
    "name:ind_x_preferred":[
        "Kebon Kelapa"
    ],
    "wof:name":"Kebon Kelapa",
    "wof:placetype":"locality"
},
  "geometry": {"coordinates":[105.79952,-5.34917],"type":"Point"}
}