{
  "type": "Feature",
  "properties": {
    "gn:admin1_code":"26",
    "gn:asciiname":"Sosor Mangador",
    "gn:country_code":"ID",
    "gn:dem":956,
    "gn:feature_class":"P",
    "gn:feature_code":"PPL",
    "gn:name":"Sosor Mangador",
    "gn:population":0,
    "gn:timezone":"Asia/Jakarta",
    "iso:country":"ID",
    "name:ind_x_preferred":[
        "Sosor Mangador"
    ],
    "wof:name":"Sosor Mangador",
    "wof:placetype":"locality"
},
  "geometry": {"coordinates":[98.94159999999999,2.4536],"type":"Point"}
}