{
  "type": "Feature",
  "properties": {
    "gn:admin1_code":"05",
    "gn:asciiname":"Pulausungaiduo",
    "gn:country_code":"ID",
    "gn:dem":5,
    "gn:feature_class":"P",
    "gn:feature_code":"PPL",
    "gn:name":"Pulausungaiduo",
    "gn:population":0,
    "gn:timezone":"Asia/Jakarta",
    "iso:country":"ID",
    "name:ind_x_preferred":[
        "Pulausungaiduo"
    ],
    "wof:name":"Pulausungaiduo",
    "wof:placetype":"locality"
},
  "geometry": {"coordinates":[104.10975000000001,-1.21106],"type":"Point"}
}