{
  "type": "Feature",
  "properties": {
    "gn:admin1_code":"8.0",
    "gn:asciiname":"Wotpiji",
    "gn:country_code":"ID",
    "gn:dem":756,
    "gn:feature_class":"P",
    "gn:feature_code":"PPL",
    "gn:name":"Wotpiji",
    "gn:population":0,
    "gn:timezone":"Asia/Jakarta",
    "iso:country":"ID",
    "name:ind_x_preferred":[
        "Wotpiji"
    ],
    "wof:name":"Wotpiji",
    "wof:placetype":"locality"
},
  "geometry": {"coordinates":[111.5393,-8.044],"type":"Point"}
}