{
  "type": "Feature",
  "properties": {
    "gn:admin1_code":"1",
    "gn:asciiname":"Kayeebalam",
    "gn:country_code":"ID",
    "gn:dem":17,
    "gn:feature_class":"P",
    "gn:feature_code":"PPL",
    "gn:name":"Kayeebalam",
    "gn:population":0,
    "gn:timezone":"Asia/Jakarta",
    "iso:country":"ID",
    "name:ind_x_preferred":[
        "Kayeebalam"
    ],
    "name:und_x_variant":[
        "Kajeebalam"
    ],
    "wof:lang_x_official":[
        "ind"
    ],
    "wof:lang_x_spoken":[
        "ind",
        "eng"
    ],
    "wof:name":"Kayeebalam",
    "wof:placetype":"locality"
},
  "geometry": {"coordinates":[96.1969,4.2038],"type":"Point"}
}