{
  "type": "Feature",
  "properties": {
    "gn:admin1_code":"30",
    "gn:asciiname":"Jogjogan Satu",
    "gn:country_code":"ID",
    "gn:dem":826,
    "gn:feature_class":"P",
    "gn:feature_code":"PPL",
    "gn:name":"Jogjogan Satu",
    "gn:population":0,
    "gn:timezone":"Asia/Jakarta",
    "iso:country":"ID",
    "name:ind_x_preferred":[
        "Jogjogan Satu"
    ],
    "name:und_x_variant":[
        "Jogjogan 1"
    ],
    "wof:lang_x_official":[
        "ind"
    ],
    "wof:lang_x_spoken":[
        "ind",
        "eng"
    ],
    "wof:name":"Jogjogan Satu",
    "wof:placetype":"locality"
},
  "geometry": {"coordinates":[106.94499999999999,-6.67083],"type":"Point"}
}