{
  "type": "Feature",
  "properties": {
    "gn:admin1_code":"18",
    "gn:asciiname":"Redakodi",
    "gn:country_code":"ID",
    "gn:dem":95,
    "gn:feature_class":"P",
    "gn:feature_code":"PPLA4",
    "gn:name":"Redakodi",
    "gn:population":0,
    "gn:timezone":"Asia/Makassar",
    "iso:country":"ID",
    "name:ind_x_preferred":[
        "Redakodi"
    ],
    "wof:name":"Redakodi",
    "wof:placetype":"locality"
},
  "geometry": {"coordinates":[119.22709999999999,-9.4542],"type":"Point"}
}