{
  "type": "Feature",
  "properties": {
    "gn:admin1_code":"31.0",
    "gn:asciiname":"Kanonang Satu",
    "gn:country_code":"ID",
    "gn:dem":782,
    "gn:feature_class":"P",
    "gn:feature_code":"PPL",
    "gn:name":"Kanonang Satu",
    "gn:population":0,
    "gn:timezone":"Asia/Makassar",
    "iso:country":"ID",
    "name:ind_x_preferred":[
        "Kanonang Satu"
    ],
    "name:und_x_variant":[
        "Kanonang 1"
    ],
    "wof:name":"Kanonang Satu",
    "wof:placetype":"locality"
},
  "geometry": {"coordinates":[124.7801,1.187],"type":"Point"}
}