{
  "type": "Feature",
  "properties": {
    "gn:admin1_code":"30.0",
    "gn:asciiname":"Bojongnangka",
    "gn:country_code":"ID",
    "gn:dem":467,
    "gn:feature_class":"P",
    "gn:feature_code":"PPL",
    "gn:name":"Bojongnangka",
    "gn:population":0,
    "gn:timezone":"Asia/Jakarta",
    "iso:country":"ID",
    "name:ind_x_preferred":[
        "Bojongnangka"
    ],
    "wof:name":"Bojongnangka",
    "wof:placetype":"locality"
},
  "geometry": {"coordinates":[108.0749,-7.3467],"type":"Point"}
}