{
  "type": "Feature",
  "properties": {
    "gn:admin1_code":"30.0",
    "gn:asciiname":"Ciaul Dua",
    "gn:country_code":"ID",
    "gn:dem":948,
    "gn:feature_class":"P",
    "gn:feature_code":"PPL",
    "gn:name":"Ciaul Dua",
    "gn:population":0,
    "gn:timezone":"Asia/Jakarta",
    "iso:country":"ID",
    "name:ind_x_preferred":[
        "Ciaul Dua"
    ],
    "wof:name":"Ciaul Dua",
    "wof:placetype":"locality"
},
  "geometry": {"coordinates":[106.9939,-7.0932],"type":"Point"}
}