{
  "type": "Feature",
  "properties": {
    "gn:admin1_code":"1",
    "gn:asciiname":"Kampung Stasiun Teluk Dalam",
    "gn:country_code":"ID",
    "gn:dem":43,
    "gn:feature_class":"P",
    "gn:feature_code":"PPL",
    "gn:name":"Kampung Stasiun Teluk Dalam",
    "gn:population":0,
    "gn:timezone":"Asia/Jakarta",
    "iso:country":"ID",
    "name:ind_x_preferred":[
        "Kampung Stasiun Teluk Dalam"
    ],
    "wof:lang_x_official":[
        "ind"
    ],
    "wof:lang_x_spoken":[
        "ind",
        "eng"
    ],
    "wof:name":"Kampung Stasiun Teluk Dalam",
    "wof:placetype":"locality"
},
  "geometry": {"coordinates":[99.62730000000001,2.8294],"type":"Point"}
}