{
  "type": "Feature",
  "properties": {
    "gn:admin1_code":"30.0",
    "gn:asciiname":"Bumiasih",
    "gn:country_code":"ID",
    "gn:dem":362,
    "gn:feature_class":"P",
    "gn:feature_code":"PPL",
    "gn:name":"Bumiasih",
    "gn:population":0,
    "gn:timezone":"Asia/Jakarta",
    "iso:country":"ID",
    "name:ind_x_preferred":[
        "Bumiasih"
    ],
    "wof:name":"Bumiasih",
    "wof:placetype":"locality"
},
  "geometry": {"coordinates":[108.2105,-7.3357],"type":"Point"}
}