{
  "type": "Feature",
  "properties": {
    "gn:admin1_code":"7.0",
    "gn:asciiname":"Ranjingan",
    "gn:country_code":"ID",
    "gn:dem":28,
    "gn:feature_class":"P",
    "gn:feature_code":"PPL",
    "gn:name":"Ranjingan",
    "gn:population":0,
    "gn:timezone":"Asia/Jakarta",
    "iso:country":"ID",
    "name:ind_x_preferred":[
        "Ranjingan"
    ],
    "wof:name":"Ranjingan",
    "wof:placetype":"locality"
},
  "geometry": {"coordinates":[109.05583,-7.52833],"type":"Point"}
}