{
  "type": "Feature",
  "properties": {
    "gn:admin1_code":"30",
    "gn:asciiname":"Jatisura B",
    "gn:country_code":"ID",
    "gn:dem":18,
    "gn:feature_class":"P",
    "gn:feature_code":"PPL",
    "gn:name":"Jatisura B",
    "gn:population":0,
    "gn:timezone":"Asia/Jakarta",
    "iso:country":"ID",
    "name:ind_x_preferred":[
        "Jatisura B"
    ],
    "wof:name":"Jatisura B",
    "wof:placetype":"locality"
},
  "geometry": {"coordinates":[108.205,-6.51611],"type":"Point"}
}