{
  "type": "Feature",
  "properties": {
    "gn:admin1_code":"21",
    "gn:asciiname":"Sintuwu",
    "gn:country_code":"ID",
    "gn:dem":561,
    "gn:feature_class":"P",
    "gn:feature_code":"PPL",
    "gn:name":"Sintuwu",
    "gn:population":0,
    "gn:timezone":"Asia/Makassar",
    "iso:country":"ID",
    "name:ind_x_preferred":[
        "Sintuwu"
    ],
    "name:und_x_variant":[
        "Siutuwu"
    ],
    "wof:lang_x_official":[
        "ind"
    ],
    "wof:lang_x_spoken":[
        "ind",
        "eng"
    ],
    "wof:name":"Sintuwu",
    "wof:placetype":"locality"
},
  "geometry": {"coordinates":[120.04900000000001,-1.1601],"type":"Point"}
}