{
  "type": "Feature",
  "properties": {
    "gn:admin1_code":"36.0",
    "gn:asciiname":"Benyom",
    "gn:country_code":"ID",
    "gn:dem":53,
    "gn:feature_class":"P",
    "gn:feature_code":"PPL",
    "gn:name":"Benyom",
    "gn:population":0,
    "gn:timezone":"Asia/Jayapura",
    "iso:country":"ID",
    "name:und_x_variant":[
        "Benjom",
        "Penjom",
        "Benjoin",
        "Benyom"
    ],
    "wof:name":"Benyom",
    "wof:placetype":"locality"
},
  "geometry": {"coordinates":[140.15000000000001,-2.58333],"type":"Point"}
}