{
  "type": "Feature",
  "properties": {
    "gn:admin1_code":"18.0",
    "gn:asciiname":"Tutu",
    "gn:country_code":"ID",
    "gn:dem":1319,
    "gn:feature_class":"P",
    "gn:feature_code":"PPL",
    "gn:name":"Tutu",
    "gn:population":0,
    "gn:timezone":"Asia/Makassar",
    "iso:country":"ID",
    "name:ceb_x_preferred":[
        "Tutu"
    ],
    "name:deu_x_preferred":[
        "Tutu"
    ],
    "name:eus_x_preferred":[
        "Tutu"
    ],
    "name:fra_x_preferred":[
        "Tutu"
    ],
    "name:ind_x_preferred":[
        "Tutu"
    ],
    "name:ita_x_preferred":[
        "Tutu"
    ],
    "name:jpn_x_preferred":[
        "\u30c8\u30a5\u30c8\u30a5"
    ],
    "name:nld_x_preferred":[
        "Tutu"
    ],
    "name:por_x_preferred":[
        "Tutu"
    ],
    "name:slk_x_preferred":[
        "Tutu"
    ],
    "name:spa_x_preferred":[
        "Tutu"
    ],
    "name:swe_x_preferred":[
        "Tutu"
    ],
    "name:tur_x_preferred":[
        "Tutu"
    ],
    "wof:lang_x_official":[
        "ind"
    ],
    "wof:lang_x_spoken":[
        "ind",
        "eng"
    ],
    "wof:name":"Tutu",
    "wof:placetype":"locality"
},
  "geometry": {"coordinates":[124.1801,-9.5469],"type":"Point"}
}