{
  "type": "Feature",
  "properties": {
    "gn:admin1_code":"15.0",
    "gn:asciiname":"Pujarahayu",
    "gn:country_code":"ID",
    "gn:dem":104,
    "gn:feature_class":"P",
    "gn:feature_code":"PPL",
    "gn:name":"Pujarahayu",
    "gn:population":0,
    "gn:timezone":"Asia/Jakarta",
    "iso:country":"ID",
    "name:ind_x_preferred":[
        "Pujarahayu"
    ],
    "wof:name":"Pujarahayu",
    "wof:placetype":"locality"
},
  "geometry": {"coordinates":[105.07142,-5.32764],"type":"Point"}
}