{
  "type": "Feature",
  "properties": {
    "gn:admin1_code":"30",
    "gn:asciiname":"Cisatong Lebak",
    "gn:country_code":"ID",
    "gn:dem":979,
    "gn:feature_class":"P",
    "gn:feature_code":"PPL",
    "gn:name":"Cisatong Lebak",
    "gn:population":0,
    "gn:timezone":"Asia/Jakarta",
    "iso:country":"ID",
    "name:ind_x_preferred":[
        "Cisatong Lebak"
    ],
    "name:und_x_variant":[
        "Tjisatong",
        "Cisatong"
    ],
    "wof:name":"Cisatong Lebak",
    "wof:placetype":"locality"
},
  "geometry": {"coordinates":[107.29694000000001,-6.95639],"type":"Point"}
}