{
  "type": "Feature",
  "properties": {
    "gn:admin1_code":"17",
    "gn:asciiname":"Hijrah",
    "gn:country_code":"ID",
    "gn:dem":40,
    "gn:feature_class":"P",
    "gn:feature_code":"PPL",
    "gn:name":"Hijrah",
    "gn:population":0,
    "gn:timezone":"Asia/Makassar",
    "iso:country":"ID",
    "name:ind_x_preferred":[
        "Hijrah"
    ],
    "wof:name":"Hijrah",
    "wof:placetype":"locality"
},
  "geometry": {"coordinates":[118.8917,-8.3178],"type":"Point"}
}