{
  "type": "Feature",
  "properties": {
    "gn:admin1_code":"26",
    "gn:asciiname":"Pondok Blok Empat Belas",
    "gn:country_code":"ID",
    "gn:dem":75,
    "gn:feature_class":"P",
    "gn:feature_code":"PPL",
    "gn:name":"Pondok Blok Empat Belas",
    "gn:population":0,
    "gn:timezone":"Asia/Jakarta",
    "iso:country":"ID",
    "name:ind_x_preferred":[
        "Pondok Blok Empat Belas"
    ],
    "name:und_x_variant":[
        "Pondok Blok XIV"
    ],
    "wof:lang_x_official":[
        "ind"
    ],
    "wof:lang_x_spoken":[
        "ind",
        "eng"
    ],
    "wof:name":"Pondok Blok Empat Belas",
    "wof:placetype":"locality"
},
  "geometry": {"coordinates":[99.03149999999999,3.2772],"type":"Point"}
}