{
  "type": "Feature",
  "properties": {
    "gn:admin1_code":"26",
    "gn:asciiname":"Lumban Sitorus",
    "gn:country_code":"ID",
    "gn:dem":929,
    "gn:feature_class":"P",
    "gn:feature_code":"PPL",
    "gn:name":"Lumban Sitorus",
    "gn:population":0,
    "gn:timezone":"Asia/Jakarta",
    "iso:country":"ID",
    "name:ind_x_preferred":[
        "Lumban Sitorus"
    ],
    "name:und_x_variant":[
        "Sitorus 1"
    ],
    "wof:lang_x_official":[
        "ind"
    ],
    "wof:lang_x_spoken":[
        "ind",
        "eng"
    ],
    "wof:name":"Lumban Sitorus",
    "wof:placetype":"locality"
},
  "geometry": {"coordinates":[99.1425,2.4872],"type":"Point"}
}