{
  "type": "Feature",
  "properties": {
    "gn:admin1_code":"8.0",
    "gn:asciiname":"Mortrebung",
    "gn:country_code":"ID",
    "gn:dem":52,
    "gn:feature_class":"P",
    "gn:feature_code":"PPL",
    "gn:name":"Mortrebung",
    "gn:population":0,
    "gn:timezone":"Asia/Jakarta",
    "iso:country":"ID",
    "name:ind_x_preferred":[
        "Mortrebung"
    ],
    "wof:name":"Mortrebung",
    "wof:placetype":"locality"
},
  "geometry": {"coordinates":[113.4002,-7.1626],"type":"Point"}
}