{
  "type": "Feature",
  "properties": {
    "gn:admin1_code":"30.0",
    "gn:asciiname":"Mekarmulya",
    "gn:country_code":"ID",
    "gn:dem":83,
    "gn:feature_class":"P",
    "gn:feature_code":"PPL",
    "gn:name":"Mekarmulya",
    "gn:population":0,
    "gn:timezone":"Asia/Jakarta",
    "iso:country":"ID",
    "name:ind_x_preferred":[
        "Mekarmulya"
    ],
    "wof:name":"Mekarmulya",
    "wof:placetype":"locality"
},
  "geometry": {"coordinates":[106.9529,-7.4026],"type":"Point"}
}