{
  "type": "Feature",
  "properties": {
    "gn:admin1_code":"0.0",
    "gn:asciiname":"Perbaungan",
    "gn:cc2":"ID",
    "gn:country_code":"ID",
    "gn:dem":45,
    "gn:feature_class":"P",
    "gn:feature_code":"PPL",
    "gn:name":"Perbaungan",
    "gn:population":0,
    "gn:timezone":"Asia/Jakarta",
    "iso:country":"ID",
    "name:und_x_variant":[
        "Perbaoengan",
        "Perbaungan"
    ],
    "wof:name":"Perbaungan",
    "wof:placetype":"locality"
},
  "geometry": {"coordinates":[99.96666999999999,2.05],"type":"Point"}
}