{
  "type": "Feature",
  "properties": {
    "gn:admin1_code":"28.0",
    "gn:asciiname":"Welora",
    "gn:country_code":"ID",
    "gn:dem":125,
    "gn:feature_class":"P",
    "gn:feature_code":"PPL",
    "gn:name":"Welora",
    "gn:population":0,
    "gn:timezone":"Asia/Jayapura",
    "iso:country":"ID",
    "name:ind_x_preferred":[
        "Welora"
    ],
    "wof:name":"Welora",
    "wof:placetype":"locality"
},
  "geometry": {"coordinates":[130.00274999999999,-7.70179],"type":"Point"}
}