{
  "type": "Feature",
  "properties": {
    "gn:admin1_code":"30.0",
    "gn:asciiname":"Pasirjeuti",
    "gn:country_code":"ID",
    "gn:dem":458,
    "gn:feature_class":"P",
    "gn:feature_code":"PPL",
    "gn:name":"Pasirjeuti",
    "gn:population":0,
    "gn:timezone":"Asia/Jakarta",
    "iso:country":"ID",
    "name:ind_x_preferred":[
        "Pasirjeuti"
    ],
    "wof:name":"Pasirjeuti",
    "wof:placetype":"locality"
},
  "geometry": {"coordinates":[107.8365,-7.538],"type":"Point"}
}