{
  "type": "Feature",
  "properties": {
    "gn:admin1_code":"15.0",
    "gn:asciiname":"Kebondamar",
    "gn:country_code":"ID",
    "gn:dem":8,
    "gn:feature_class":"P",
    "gn:feature_code":"PPL",
    "gn:name":"Kebondamar",
    "gn:population":0,
    "gn:timezone":"Asia/Jakarta",
    "iso:country":"ID",
    "name:ind_x_preferred":[
        "Kebondamar"
    ],
    "wof:name":"Kebondamar",
    "wof:placetype":"locality"
},
  "geometry": {"coordinates":[105.78577,-5.2684],"type":"Point"}
}