{
  "type": "Feature",
  "properties": {
    "gn:admin1_code":"29.0",
    "gn:asciiname":"Bajau",
    "gn:country_code":"ID",
    "gn:dem":5,
    "gn:feature_class":"P",
    "gn:feature_code":"PPL",
    "gn:name":"Bajau",
    "gn:population":0,
    "gn:timezone":"Asia/Jayapura",
    "iso:country":"ID",
    "name:ind_x_preferred":[
        "Bajau"
    ],
    "name:und_x_variant":[
        "Badjo"
    ],
    "wof:name":"Bajau",
    "wof:placetype":"locality"
},
  "geometry": {"coordinates":[125.97409,-2.00471],"type":"Point"}
}