{
  "type": "Feature",
  "properties": {
    "gn:admin1_code":"8",
    "gn:asciiname":"Benel",
    "gn:country_code":"ID",
    "gn:dem":369,
    "gn:feature_class":"P",
    "gn:feature_code":"PPL",
    "gn:name":"Benel",
    "gn:population":0,
    "gn:timezone":"Asia/Jakarta",
    "iso:country":"ID",
    "name:ind_x_preferred":[
        "Benel"
    ],
    "wof:name":"Benel",
    "wof:placetype":"locality"
},
  "geometry": {"coordinates":[114.3138,-8.1586],"type":"Point"}
}