{
  "type": "Feature",
  "properties": {
    "gn:admin1_code":"22",
    "gn:asciiname":"Labunia",
    "gn:country_code":"ID",
    "gn:dem":23,
    "gn:feature_class":"P",
    "gn:feature_code":"PPL",
    "gn:name":"Labunia",
    "gn:population":0,
    "gn:timezone":"Asia/Makassar",
    "iso:country":"ID",
    "name:ind_x_preferred":[
        "Labunia"
    ],
    "wof:name":"Labunia",
    "wof:placetype":"locality"
},
  "geometry": {"coordinates":[122.836,-4.9003],"type":"Point"}
}