{
  "type": "Feature",
  "properties": {
    "gn:admin1_code":"1",
    "gn:asciiname":"Cane",
    "gn:country_code":"ID",
    "gn:dem":324,
    "gn:feature_class":"P",
    "gn:feature_code":"PPL",
    "gn:name":"Cane",
    "gn:population":0,
    "gn:timezone":"Asia/Jakarta",
    "iso:country":"ID",
    "name:cat_x_preferred":[
        "Cane"
    ],
    "name:ceb_x_preferred":[
        "Cane"
    ],
    "name:deu_x_preferred":[
        "Cane"
    ],
    "name:fra_x_preferred":[
        "Cane"
    ],
    "name:ind_x_preferred":[
        "Cane"
    ],
    "name:ita_x_preferred":[
        "Cane"
    ],
    "name:jpn_x_preferred":[
        "\u30b1\u30fc\u30f3"
    ],
    "name:nld_x_preferred":[
        "Cane"
    ],
    "name:srp_x_preferred":[
        "Cane"
    ],
    "name:swe_x_preferred":[
        "Cane"
    ],
    "wof:name":"Cane",
    "wof:placetype":"locality"
},
  "geometry": {"coordinates":[97.5141,4.4499],"type":"Point"}
}