{
  "type": "Feature",
  "properties": {
    "gn:admin1_code":"33.0",
    "gn:asciiname":"Cimoyan",
    "gn:country_code":"ID",
    "gn:dem":25,
    "gn:feature_class":"P",
    "gn:feature_code":"PPL",
    "gn:name":"Cimoyan",
    "gn:population":0,
    "gn:timezone":"Asia/Jakarta",
    "iso:country":"ID",
    "name:ind_x_preferred":[
        "Cimoyan"
    ],
    "wof:name":"Cimoyan",
    "wof:placetype":"locality"
},
  "geometry": {"coordinates":[105.9453,-6.5192],"type":"Point"}
}