{
  "type": "Feature",
  "properties": {
    "gn:admin1_code":"7",
    "gn:asciiname":"Babakankrajan",
    "gn:country_code":"ID",
    "gn:dem":288,
    "gn:feature_class":"P",
    "gn:feature_code":"PPL",
    "gn:name":"Babakankrajan",
    "gn:population":0,
    "gn:timezone":"Asia/Jakarta",
    "iso:country":"ID",
    "name:ind_x_preferred":[
        "Babakankrajan"
    ],
    "wof:name":"Babakankrajan",
    "wof:placetype":"locality"
},
  "geometry": {"coordinates":[109.9294,-7.0144],"type":"Point"}
}