{
  "type": "Feature",
  "properties": {
    "gn:admin1_code":"18.0",
    "gn:asciiname":"Bona",
    "gn:country_code":"ID",
    "gn:dem":721,
    "gn:feature_class":"P",
    "gn:feature_code":"PPL",
    "gn:name":"Bona",
    "gn:population":0,
    "gn:timezone":"Asia/Makassar",
    "iso:country":"ID",
    "name:bel_x_preferred":[
        "\u0411\u043e\u043d\u0430"
    ],
    "name:bre_x_preferred":[
        "Bona"
    ],
    "name:ceb_x_preferred":[
        "Bona"
    ],
    "name:deu_x_preferred":[
        "Bona"
    ],
    "name:fra_x_preferred":[
        "Bona"
    ],
    "name:ind_x_preferred":[
        "Bona"
    ],
    "name:ita_x_preferred":[
        "Bona"
    ],
    "name:kaz_x_preferred":[
        "\u0411\u043e\u043d\u0430"
    ],
    "name:nld_x_preferred":[
        "Bona"
    ],
    "name:oci_x_preferred":[
        "Bona"
    ],
    "name:pol_x_preferred":[
        "Bona"
    ],
    "name:por_x_preferred":[
        "Bona"
    ],
    "name:rus_x_preferred":[
        "\u0411\u043e\u043d\u0430"
    ],
    "name:spa_x_preferred":[
        "Bona"
    ],
    "name:srp_x_preferred":[
        "\u0411\u043e\u043d\u0430"
    ],
    "name:swe_x_preferred":[
        "Bona"
    ],
    "name:ukr_x_preferred":[
        "\u0411\u043e\u043d\u0430"
    ],
    "name:vol_x_preferred":[
        "Bona"
    ],
    "wof:lang_x_official":[
        "ind"
    ],
    "wof:lang_x_spoken":[
        "ind",
        "eng"
    ],
    "wof:name":"Bona",
    "wof:placetype":"locality"
},
  "geometry": {"coordinates":[124.15179999999999,-9.729],"type":"Point"}
}