{
  "type": "Feature",
  "properties": {
    "gn:admin1_code":"18",
    "gn:asciiname":"Nggawang",
    "gn:country_code":"ID",
    "gn:dem":970,
    "gn:feature_class":"P",
    "gn:feature_code":"PPL",
    "gn:name":"Nggawang",
    "gn:population":0,
    "gn:timezone":"Asia/Makassar",
    "iso:country":"ID",
    "name:ind_x_preferred":[
        "Nggawang"
    ],
    "wof:name":"Nggawang",
    "wof:placetype":"locality"
},
  "geometry": {"coordinates":[120.36320000000001,-8.582],"type":"Point"}
}