{
  "type": "Feature",
  "properties": {
    "gn:admin1_code":"1.0",
    "gn:asciiname":"Meunasah Krueng",
    "gn:country_code":"ID",
    "gn:dem":21,
    "gn:feature_class":"P",
    "gn:feature_code":"PPL",
    "gn:name":"Meunasah Krueng",
    "gn:population":0,
    "gn:timezone":"Asia/Jakarta",
    "iso:country":"ID",
    "name:ind_x_preferred":[
        "Meunasah Krueng"
    ],
    "wof:name":"Meunasah Krueng",
    "wof:placetype":"locality"
},
  "geometry": {"coordinates":[96.221,5.2186],"type":"Point"}
}