{
  "type": "Feature",
  "properties": {
    "gn:admin1_code":"34",
    "gn:asciiname":"Biluanga",
    "gn:country_code":"ID",
    "gn:dem":39,
    "gn:feature_class":"P",
    "gn:feature_code":"PPL",
    "gn:name":"Biluanga",
    "gn:population":0,
    "gn:timezone":"Asia/Makassar",
    "iso:country":"ID",
    "name:ind_x_preferred":[
        "Biluanga"
    ],
    "name:und_x_variant":[
        "Biluango"
    ],
    "wof:name":"Biluanga",
    "wof:placetype":"locality"
},
  "geometry": {"coordinates":[123.0864,0.6127],"type":"Point"}
}