{
  "type": "Feature",
  "properties": {
    "gn:asciiname":"Gili Trawangan",
    "gn:country_code":"ID",
    "gn:dem":9,
    "gn:feature_class":"P",
    "gn:feature_code":"PPL",
    "gn:name":"Gili Trawangan",
    "gn:population":1500,
    "gn:timezone":"Asia/Makassar",
    "iso:country":"ID",
    "name:rus_x_preferred":[
        "\u0413\u0438\u043b\u0438 \u0422\u0440\u0430\u0432\u0430\u043d\u0433\u0430\u043d"
    ],
    "wof:name":"Gili Trawangan",
    "wof:placetype":"locality",
    "wof:population":1500
},
  "geometry": {"coordinates":[116.03700000000001,-8.34897],"type":"Point"}
}