{
  "type": "Feature",
  "properties": {
    "gn:admin1_code":"1",
    "gn:asciiname":"Kranji",
    "gn:country_code":"ID",
    "gn:dem":18,
    "gn:feature_class":"P",
    "gn:feature_code":"PPL",
    "gn:name":"Kranji",
    "gn:population":0,
    "gn:timezone":"Asia/Jakarta",
    "iso:country":"ID",
    "name:ind_x_preferred":[
        "Kranji"
    ],
    "name:mar_x_preferred":[
        "\u0915\u094d\u0930\u093e\u0902\u091c\u0940"
    ],
    "name:msa_x_preferred":[
        "Kranji"
    ],
    "name:pol_x_preferred":[
        "Kranji"
    ],
    "name:und_x_variant":[
        "Kerendji"
    ],
    "name:vie_x_preferred":[
        "Kranji"
    ],
    "wof:lang_x_official":[
        "ind"
    ],
    "wof:lang_x_spoken":[
        "ind",
        "eng"
    ],
    "wof:name":"Kranji",
    "wof:placetype":"locality"
},
  "geometry": {"coordinates":[98.0017,4.1228],"type":"Point"}
}