{
  "type": "Feature",
  "properties": {
    "gn:admin1_code":"1",
    "gn:asciiname":"Kranji",
    "gn:country_code":"ID",
    "gn:dem":18,
    "gn:feature_class":"P",
    "gn:feature_code":"PPL",
    "gn:name":"Kranji",
    "gn:population":0,
    "gn:timezone":"Asia/Jakarta",
    "iso:country":"ID",
    "name:ind_x_preferred":[
        "Kranji"
    ],
    "name:und_x_variant":[
        "Kerendji"
    ],
    "wof:name":"Kranji",
    "wof:placetype":"locality"
},
  "geometry": {"coordinates":[98.0017,4.1228],"type":"Point"}
}