{
  "type": "Feature",
  "properties": {
    "gn:admin1_code":"8.0",
    "gn:asciiname":"Sukowiyono Dua",
    "gn:country_code":"ID",
    "gn:dem":69,
    "gn:feature_class":"P",
    "gn:feature_code":"PPL",
    "gn:name":"Sukowiyono Dua",
    "gn:population":0,
    "gn:timezone":"Asia/Jakarta",
    "iso:country":"ID",
    "name:ind_x_preferred":[
        "Sukowiyono Dua"
    ],
    "wof:name":"Sukowiyono Dua",
    "wof:placetype":"locality"
},
  "geometry": {"coordinates":[111.542,-7.4485],"type":"Point"}
}