{
  "type": "Feature",
  "properties": {
    "gn:admin1_code":"8.0",
    "gn:asciiname":"Wonosari Lor",
    "gn:country_code":"ID",
    "gn:dem":2,
    "gn:feature_class":"P",
    "gn:feature_code":"PPL",
    "gn:name":"Wonosari Lor",
    "gn:population":0,
    "gn:timezone":"Asia/Jakarta",
    "iso:country":"ID",
    "name:ind_x_preferred":[
        "Wonosari Lor"
    ],
    "wof:name":"Wonosari Lor",
    "wof:placetype":"locality"
},
  "geometry": {"coordinates":[114.3806,-8.243],"type":"Point"}
}