{
  "type": "Feature",
  "properties": {
    "gn:admin1_code":"26",
    "gn:asciiname":"Seribujawa Dua",
    "gn:country_code":"ID",
    "gn:dem":466,
    "gn:feature_class":"P",
    "gn:feature_code":"PPL",
    "gn:name":"Seribujawa Dua",
    "gn:population":0,
    "gn:timezone":"Asia/Jakarta",
    "iso:country":"ID",
    "name:ind_x_preferred":[
        "Seribujawa Dua"
    ],
    "name:und_x_variant":[
        "Seribujawa 2"
    ],
    "wof:lang_x_official":[
        "ind"
    ],
    "wof:lang_x_spoken":[
        "ind",
        "eng"
    ],
    "wof:name":"Seribujawa Dua",
    "wof:placetype":"locality"
},
  "geometry": {"coordinates":[99.07689999999999,2.8577],"type":"Point"}
}