{
  "type": "Feature",
  "properties": {
    "gn:admin1_code":"8.0",
    "gn:asciiname":"Mentaraman Satu",
    "gn:country_code":"ID",
    "gn:dem":351,
    "gn:feature_class":"P",
    "gn:feature_code":"PPLA4",
    "gn:name":"Mentaraman Satu",
    "gn:population":0,
    "gn:timezone":"Asia/Jakarta",
    "iso:country":"ID",
    "name:ind_x_preferred":[
        "Mentaraman Satu"
    ],
    "name:und_x_variant":[
        "Mataraman 1"
    ],
    "wof:name":"Mentaraman Satu",
    "wof:placetype":"locality"
},
  "geometry": {"coordinates":[112.4246,-8.3049],"type":"Point"}
}