{
  "type": "Feature",
  "properties": {
    "gn:admin1_code":"8.0",
    "gn:asciiname":"Bira",
    "gn:country_code":"ID",
    "gn:dem":48,
    "gn:feature_class":"P",
    "gn:feature_code":"PPLA4",
    "gn:name":"Bira",
    "gn:population":0,
    "gn:timezone":"Asia/Jakarta",
    "iso:country":"ID",
    "name:ceb_x_preferred":[
        "Bira"
    ],
    "name:dan_x_preferred":[
        "Bira"
    ],
    "name:deu_x_preferred":[
        "Bira"
    ],
    "name:fra_x_preferred":[
        "Bira"
    ],
    "name:ind_x_preferred":[
        "Bira"
    ],
    "name:ita_x_preferred":[
        "Bira"
    ],
    "name:por_x_preferred":[
        "Bira"
    ],
    "name:sco_x_preferred":[
        "Bira"
    ],
    "name:spa_x_preferred":[
        "Bira"
    ],
    "name:swe_x_preferred":[
        "Bira"
    ],
    "wof:lang_x_official":[
        "ind"
    ],
    "wof:lang_x_spoken":[
        "ind",
        "eng"
    ],
    "wof:name":"Bira",
    "wof:placetype":"locality"
},
  "geometry": {"coordinates":[113.3917,-6.8998],"type":"Point"}
}