{
  "type": "Feature",
  "properties": {
    "gn:admin1_code":"38.0",
    "gn:asciiname":"Lebolebo",
    "gn:country_code":"ID",
    "gn:dem":1395,
    "gn:feature_class":"P",
    "gn:feature_code":"PPL",
    "gn:name":"Lebolebo",
    "gn:population":0,
    "gn:timezone":"Asia/Makassar",
    "iso:country":"ID",
    "name:ind_x_preferred":[
        "Lebolebo"
    ],
    "wof:name":"Lebolebo",
    "wof:placetype":"locality"
},
  "geometry": {"coordinates":[119.5577,-3.1837],"type":"Point"}
}