{
  "type": "Feature",
  "properties": {
    "gn:admin1_code":"26",
    "gn:asciiname":"Gurubenua",
    "gn:country_code":"ID",
    "gn:dem":1133,
    "gn:feature_class":"P",
    "gn:feature_code":"PPL",
    "gn:name":"Gurubenua",
    "gn:population":0,
    "gn:timezone":"Asia/Jakarta",
    "iso:country":"ID",
    "name:ind_x_preferred":[
        "Gurubenua"
    ],
    "name:und_x_variant":[
        "Kotagurubenua"
    ],
    "wof:name":"Gurubenua",
    "wof:placetype":"locality"
},
  "geometry": {"coordinates":[98.4432,3.0604],"type":"Point"}
}