{
  "type": "Feature",
  "properties": {
    "gn:admin1_code":"7.0",
    "gn:asciiname":"Duren",
    "gn:country_code":"ID",
    "gn:dem":230,
    "gn:feature_class":"P",
    "gn:feature_code":"PPL",
    "gn:name":"Duren",
    "gn:population":0,
    "gn:timezone":"Asia/Jakarta",
    "iso:country":"ID",
    "name:ind_x_preferred":[
        "Duren"
    ],
    "wof:name":"Duren",
    "wof:placetype":"locality"
},
  "geometry": {"coordinates":[109.62555999999999,-7.42778],"type":"Point"}
}