{
  "type": "Feature",
  "properties": {
    "gn:admin1_code":"30",
    "gn:asciiname":"Mandapa",
    "gn:country_code":"ID",
    "gn:dem":37,
    "gn:feature_class":"P",
    "gn:feature_code":"PPL",
    "gn:name":"Mandapa",
    "gn:population":0,
    "gn:timezone":"Asia/Jakarta",
    "iso:country":"ID",
    "name:deu_x_preferred":[
        "Mandapa"
    ],
    "name:fra_x_preferred":[
        "Mandapa"
    ],
    "name:hin_x_preferred":[
        "\u092e\u0923\u094d\u0921\u092a"
    ],
    "name:ind_x_preferred":[
        "Mandapa"
    ],
    "name:ita_x_preferred":[
        "Mandapa"
    ],
    "name:pol_x_preferred":[
        "Mandapa"
    ],
    "name:rus_x_preferred":[
        "\u041c\u0430\u043d\u0434\u0430\u043f\u0430"
    ],
    "name:spa_x_preferred":[
        "Mandapa"
    ],
    "name:sqi_x_preferred":[
        "Mandapa"
    ],
    "name:swe_x_preferred":[
        "Mandapa"
    ],
    "name:tam_x_preferred":[
        "\u0bae\u0ba3\u0bcd\u0b9f\u0baa\u0bae\u0bcd"
    ],
    "name:tha_x_preferred":[
        "\u0e21\u0e13\u0e11\u0e1b"
    ],
    "name:ukr_x_preferred":[
        "\u041c\u0430\u043d\u0434\u0430\u043f\u0430"
    ],
    "wof:name":"Mandapa",
    "wof:placetype":"locality"
},
  "geometry": {"coordinates":[108.22,-6.72972],"type":"Point"}
}