{
  "type": "Feature",
  "properties": {
    "gn:admin1_code":"30.0",
    "gn:asciiname":"Sindangsari",
    "gn:country_code":"ID",
    "gn:dem":123,
    "gn:feature_class":"P",
    "gn:feature_code":"PPLA4",
    "gn:name":"Sindangsari",
    "gn:population":0,
    "gn:timezone":"Asia/Jakarta",
    "iso:country":"ID",
    "name:ind_x_preferred":[
        "Sindangsari"
    ],
    "wof:name":"Sindangsari",
    "wof:placetype":"locality"
},
  "geometry": {"coordinates":[108.6253,-7.0309],"type":"Point"}
}