{
  "type": "Feature",
  "properties": {
    "gn:admin1_code":"41",
    "gn:asciiname":"Simbang",
    "gn:country_code":"ID",
    "gn:dem":181,
    "gn:feature_class":"P",
    "gn:feature_code":"PPL",
    "gn:name":"Simbang",
    "gn:population":0,
    "gn:timezone":"Asia/Makassar",
    "iso:country":"ID",
    "name:ind_x_preferred":[
        "Simbang"
    ],
    "wof:name":"Simbang",
    "wof:placetype":"locality"
},
  "geometry": {"coordinates":[118.9246,-3.4934],"type":"Point"}
}