{
  "type": "Feature",
  "properties": {
    "gn:admin1_code":"08",
    "gn:asciiname":"Melaten",
    "gn:country_code":"ID",
    "gn:dem":331,
    "gn:feature_class":"P",
    "gn:feature_code":"PPL",
    "gn:name":"Melaten",
    "gn:population":0,
    "gn:timezone":"Asia/Jakarta",
    "iso:country":"ID",
    "name:ind_x_preferred":[
        "Melaten"
    ],
    "name:und_x_variant":[
        "Mlaten"
    ],
    "wof:name":"Melaten",
    "wof:placetype":"locality"
},
  "geometry": {"coordinates":[112.568,-8.1528],"type":"Point"}
}