{
  "type": "Feature",
  "properties": {
    "gn:admin1_code":"33",
    "gn:asciiname":"Ambon",
    "gn:country_code":"ID",
    "gn:dem":6,
    "gn:feature_class":"P",
    "gn:feature_code":"PPL",
    "gn:name":"Ambon",
    "gn:population":0,
    "gn:timezone":"Asia/Jakarta",
    "iso:country":"ID",
    "name:bel_x_preferred":[
        "\u0410\u043c\u0431\u043e\u043d"
    ],
    "name:bre_x_preferred":[
        "Ambon"
    ],
    "name:ceb_x_preferred":[
        "Ambon"
    ],
    "name:deu_x_preferred":[
        "Ambon"
    ],
    "name:est_x_preferred":[
        "Ambon"
    ],
    "name:eus_x_preferred":[
        "Ambon"
    ],
    "name:fin_x_preferred":[
        "Ambon"
    ],
    "name:fra_x_preferred":[
        "Ambon"
    ],
    "name:heb_x_preferred":[
        "\u05d0\u05de\u05d1\u05d5\u05df"
    ],
    "name:hrv_x_preferred":[
        "Ambon"
    ],
    "name:hun_x_preferred":[
        "Ambon"
    ],
    "name:ind_x_preferred":[
        "Ambon"
    ],
    "name:ita_x_preferred":[
        "Ambon"
    ],
    "name:mlg_x_preferred":[
        "Ambon"
    ],
    "name:nld_x_preferred":[
        "Ambon"
    ],
    "name:pol_x_preferred":[
        "Ambon"
    ],
    "name:por_x_preferred":[
        "Ambon"
    ],
    "name:rus_x_preferred":[
        "\u0410\u043c\u0431\u043e\u043d"
    ],
    "name:spa_x_preferred":[
        "Ambon"
    ],
    "name:srp_x_preferred":[
        "\u0410\u043c\u0431\u043e\u043d"
    ],
    "name:swe_x_preferred":[
        "Ambon"
    ],
    "name:ukr_x_preferred":[
        "\u0410\u043c\u0431\u043e\u043d"
    ],
    "name:vie_x_preferred":[
        "Ambon"
    ],
    "wof:lang_x_official":[
        "ind"
    ],
    "wof:lang_x_spoken":[
        "ind",
        "eng"
    ],
    "wof:name":"Ambon",
    "wof:placetype":"locality"
},
  "geometry": {"coordinates":[106.17189999999999,-6.0421],"type":"Point"}
}