{
  "type": "Feature",
  "properties": {
    "gn:admin1_code":"8.0",
    "gn:asciiname":"Kampunganyar",
    "gn:country_code":"ID",
    "gn:dem":211,
    "gn:feature_class":"P",
    "gn:feature_code":"PPL",
    "gn:name":"Kampunganyar",
    "gn:population":0,
    "gn:timezone":"Asia/Jakarta",
    "iso:country":"ID",
    "name:ind_x_preferred":[
        "Kampunganyar"
    ],
    "wof:name":"Kampunganyar",
    "wof:placetype":"locality"
},
  "geometry": {"coordinates":[114.01739999999999,-8.3435],"type":"Point"}
}