{
  "type": "Feature",
  "properties": {
    "gn:admin1_code":"7.0",
    "gn:asciiname":"Kubangurang",
    "gn:country_code":"ID",
    "gn:dem":782,
    "gn:feature_class":"P",
    "gn:feature_code":"PPL",
    "gn:name":"Kubangurang",
    "gn:population":0,
    "gn:timezone":"Asia/Jakarta",
    "iso:country":"ID",
    "name:ind_x_preferred":[
        "Kubangurang"
    ],
    "wof:name":"Kubangurang",
    "wof:placetype":"locality"
},
  "geometry": {"coordinates":[109.06471999999999,-7.26194],"type":"Point"}
}