{
  "type": "Feature",
  "properties": {
    "gn:admin1_code":"8.0",
    "gn:asciiname":"Pasinan",
    "gn:country_code":"ID",
    "gn:dem":16,
    "gn:feature_class":"P",
    "gn:feature_code":"PPL",
    "gn:name":"Pasinan",
    "gn:population":0,
    "gn:timezone":"Asia/Jakarta",
    "iso:country":"ID",
    "name:ind_x_preferred":[
        "Pasinan"
    ],
    "name:und_x_variant":[
        "Pasinanlemahpoetih",
        "Pasinanlemahputih"
    ],
    "wof:name":"Pasinan",
    "wof:placetype":"locality"
},
  "geometry": {"coordinates":[112.57129999999999,-7.3867],"type":"Point"}
}