{
  "type": "Feature",
  "properties": {
    "gn:admin1_code":"8.0",
    "gn:asciiname":"Saredeng Kecil",
    "gn:country_code":"ID",
    "gn:dem":4,
    "gn:feature_class":"P",
    "gn:feature_code":"PPL",
    "gn:name":"Saredeng Kecil",
    "gn:population":0,
    "gn:timezone":"Asia/Jakarta",
    "iso:country":"ID",
    "name:ind_x_preferred":[
        "Saredeng Kecil"
    ],
    "wof:name":"Saredeng Kecil",
    "wof:placetype":"locality"
},
  "geometry": {"coordinates":[115.8034,-7.0538],"type":"Point"}
}