{
  "type": "Feature",
  "properties": {
    "gn:admin1_code":"00",
    "gn:asciiname":"Tegalkunir-kidul",
    "gn:country_code":"ID",
    "gn:dem":4,
    "gn:feature_class":"P",
    "gn:feature_code":"PPL",
    "gn:name":"Tegalkunir-kidul",
    "gn:population":0,
    "gn:timezone":"Asia/Jakarta",
    "iso:country":"ID",
    "wof:lang_x_official":[
        "ind"
    ],
    "wof:lang_x_spoken":[
        "ind",
        "eng"
    ],
    "wof:name":"Tegalkunir-kidul",
    "wof:placetype":"locality"
},
  "geometry": {"coordinates":[106.53139,-6.06444],"type":"Point"}
}