{
  "type": "Feature",
  "properties": {
    "gn:admin1_code":"17",
    "gn:asciiname":"Gubukdalam",
    "gn:country_code":"ID",
    "gn:dem":12,
    "gn:feature_class":"P",
    "gn:feature_code":"PPL",
    "gn:name":"Gubukdalam",
    "gn:population":0,
    "gn:timezone":"Asia/Makassar",
    "iso:country":"ID",
    "name:ind_x_preferred":[
        "Gubukdalam"
    ],
    "wof:name":"Gubukdalam",
    "wof:placetype":"locality"
},
  "geometry": {"coordinates":[116.5142,-8.7643],"type":"Point"}
}