{
  "type": "Feature",
  "properties": {
    "gn:admin1_code":"33",
    "gn:asciiname":"Gunungmulihpasir",
    "gn:country_code":"ID",
    "gn:dem":23,
    "gn:feature_class":"P",
    "gn:feature_code":"PPL",
    "gn:name":"Gunungmulihpasir",
    "gn:population":0,
    "gn:timezone":"Asia/Jakarta",
    "iso:country":"ID",
    "name:ind_x_preferred":[
        "Gunungmulihpasir"
    ],
    "name:und_x_variant":[
        "Gunungsugih"
    ],
    "wof:lang_x_official":[
        "ind"
    ],
    "wof:lang_x_spoken":[
        "ind",
        "eng"
    ],
    "wof:name":"Gunungmulihpasir",
    "wof:placetype":"locality"
},
  "geometry": {"coordinates":[106.26130000000001,-6.2818],"type":"Point"}
}