{
  "type": "Feature",
  "properties": {
    "gn:admin1_code":"8.0",
    "gn:asciiname":"Jaten",
    "gn:country_code":"ID",
    "gn:dem":510,
    "gn:feature_class":"P",
    "gn:feature_code":"PPL",
    "gn:name":"Jaten",
    "gn:population":0,
    "gn:timezone":"Asia/Jakarta",
    "iso:country":"ID",
    "name:ind_x_preferred":[
        "Jaten"
    ],
    "wof:name":"Jaten",
    "wof:placetype":"locality"
},
  "geometry": {"coordinates":[113.0848,-8.0849],"type":"Point"}
}