{
  "type": "Feature",
  "properties": {
    "gn:admin1_code":"7.0",
    "gn:asciiname":"Kerukbatur",
    "gn:country_code":"ID",
    "gn:dem":576,
    "gn:feature_class":"P",
    "gn:feature_code":"PPL",
    "gn:name":"Kerukbatur",
    "gn:population":0,
    "gn:timezone":"Asia/Jakarta",
    "iso:country":"ID",
    "wof:name":"Kerukbatur",
    "wof:placetype":"locality"
},
  "geometry": {"coordinates":[110.20999999999999,-7.64306],"type":"Point"}
}