{
  "type": "Feature",
  "properties": {
    "gn:admin1_code":"8",
    "gn:asciiname":"Sinoman",
    "gn:country_code":"ID",
    "gn:dem":706,
    "gn:feature_class":"P",
    "gn:feature_code":"PPL",
    "gn:name":"Sinoman",
    "gn:population":0,
    "gn:timezone":"Asia/Jakarta",
    "iso:country":"ID",
    "name:ind_x_preferred":[
        "Sinoman"
    ],
    "wof:name":"Sinoman",
    "wof:placetype":"locality"
},
  "geometry": {"coordinates":[111.6949,-7.9422],"type":"Point"}
}