{
  "type": "Feature",
  "properties": {
    "gn:admin1_code":"8.0",
    "gn:asciiname":"Lembana Barat",
    "gn:country_code":"ID",
    "gn:dem":67,
    "gn:feature_class":"P",
    "gn:feature_code":"PPL",
    "gn:name":"Lembana Barat",
    "gn:population":0,
    "gn:timezone":"Asia/Jakarta",
    "iso:country":"ID",
    "name:ind_x_preferred":[
        "Lembana Barat"
    ],
    "wof:name":"Lembana Barat",
    "wof:placetype":"locality"
},
  "geometry": {"coordinates":[113.6053,-7.1084],"type":"Point"}
}