{
  "type": "Feature",
  "properties": {
    "gn:admin1_code":"38",
    "gn:asciiname":"Pakkotangang",
    "gn:country_code":"ID",
    "gn:dem":769,
    "gn:feature_class":"P",
    "gn:feature_code":"PPL",
    "gn:name":"Pakkotangang",
    "gn:population":0,
    "gn:timezone":"Asia/Makassar",
    "iso:country":"ID",
    "name:ind_x_preferred":[
        "Pakkotangang"
    ],
    "wof:lang_x_official":[
        "ind"
    ],
    "wof:lang_x_spoken":[
        "ind",
        "eng"
    ],
    "wof:name":"Pakkotangang",
    "wof:placetype":"locality"
},
  "geometry": {"coordinates":[119.88120000000001,-5.4683],"type":"Point"}
}