{
  "type": "Feature",
  "properties": {
    "gn:admin1_code":"18",
    "gn:asciiname":"Ledang",
    "gn:country_code":"ID",
    "gn:dem":772,
    "gn:feature_class":"P",
    "gn:feature_code":"PPL",
    "gn:name":"Ledang",
    "gn:population":0,
    "gn:timezone":"Asia/Makassar",
    "iso:country":"ID",
    "name:ind_x_preferred":[
        "Ledang"
    ],
    "wof:name":"Ledang",
    "wof:placetype":"locality"
},
  "geometry": {"coordinates":[120.27849999999999,-8.6865],"type":"Point"}
}