{
  "type": "Feature",
  "properties": {
    "gn:admin1_code":"17",
    "gn:asciiname":"Sekunyit",
    "gn:country_code":"ID",
    "gn:dem":356,
    "gn:feature_class":"P",
    "gn:feature_code":"PPL",
    "gn:name":"Sekunyit",
    "gn:population":0,
    "gn:timezone":"Asia/Makassar",
    "iso:country":"ID",
    "name:ind_x_preferred":[
        "Sekunyit"
    ],
    "wof:name":"Sekunyit",
    "wof:placetype":"locality"
},
  "geometry": {"coordinates":[116.4149,-8.6243],"type":"Point"}
}