{
  "type": "Feature",
  "properties": {
    "gn:admin1_code":"26",
    "gn:asciiname":"Bangguron",
    "gn:country_code":"ID",
    "gn:dem":880,
    "gn:feature_class":"P",
    "gn:feature_code":"PPL",
    "gn:name":"Bangguron",
    "gn:population":0,
    "gn:timezone":"Asia/Jakarta",
    "iso:country":"ID",
    "name:ind_x_preferred":[
        "Bangguron"
    ],
    "wof:name":"Bangguron",
    "wof:placetype":"locality"
},
  "geometry": {"coordinates":[98.82859999999999,3.0178],"type":"Point"}
}