{
  "type": "Feature",
  "properties": {
    "gn:admin1_code":"8.0",
    "gn:asciiname":"Bangsobung",
    "gn:country_code":"ID",
    "gn:dem":23,
    "gn:feature_class":"P",
    "gn:feature_code":"PPL",
    "gn:name":"Bangsobung",
    "gn:population":0,
    "gn:timezone":"Asia/Jakarta",
    "iso:country":"ID",
    "name:ind_x_preferred":[
        "Bangsobung"
    ],
    "wof:name":"Bangsobung",
    "wof:placetype":"locality"
},
  "geometry": {"coordinates":[113.05119999999999,-7.1599],"type":"Point"}
}