{
  "type": "Feature",
  "properties": {
    "gn:admin1_code":"41",
    "gn:asciiname":"Ballapeu",
    "gn:country_code":"ID",
    "gn:dem":1376,
    "gn:feature_class":"P",
    "gn:feature_code":"PPL",
    "gn:name":"Ballapeu",
    "gn:population":0,
    "gn:timezone":"Asia/Makassar",
    "iso:country":"ID",
    "name:ind_x_preferred":[
        "Ballapeu"
    ],
    "wof:name":"Ballapeu",
    "wof:placetype":"locality"
},
  "geometry": {"coordinates":[119.295,-2.9871],"type":"Point"}
}