{
  "type": "Feature",
  "properties": {
    "gn:admin1_code":"2.0",
    "gn:asciiname":"Banjar Mundukanggrek",
    "gn:country_code":"ID",
    "gn:dem":33,
    "gn:feature_class":"P",
    "gn:feature_code":"PPLA4",
    "gn:name":"Banjar Mundukanggrek",
    "gn:population":0,
    "gn:timezone":"Asia/Makassar",
    "iso:country":"ID",
    "name:ind_x_preferred":[
        "Banjar Mundukanggrek"
    ],
    "name:und_x_variant":[
        "Mundukanggrek"
    ],
    "wof:lang_x_official":[
        "ind"
    ],
    "wof:lang_x_spoken":[
        "ind",
        "eng"
    ],
    "wof:name":"Banjar Mundukanggrek",
    "wof:placetype":"locality"
},
  "geometry": {"coordinates":[114.74274,-8.37758],"type":"Point"}
}