{
  "type": "Feature",
  "properties": {
    "gn:admin1_code":"8.0",
    "gn:asciiname":"Awu-awu",
    "gn:country_code":"ID",
    "gn:dem":278,
    "gn:feature_class":"P",
    "gn:feature_code":"PPL",
    "gn:name":"Awu-awu",
    "gn:population":0,
    "gn:timezone":"Asia/Jakarta",
    "iso:country":"ID",
    "name:ind_x_preferred":[
        "Awu-awu"
    ],
    "wof:name":"Awu-awu",
    "wof:placetype":"locality"
},
  "geometry": {"coordinates":[114.17010000000001,-8.2906],"type":"Point"}
}