{
  "type": "Feature",
  "properties": {
    "gn:admin1_code":"17",
    "gn:asciiname":"Batuampun",
    "gn:country_code":"ID",
    "gn:dem":129,
    "gn:feature_class":"P",
    "gn:feature_code":"PPL",
    "gn:name":"Batuampun",
    "gn:population":0,
    "gn:timezone":"Asia/Makassar",
    "iso:country":"ID",
    "name:ind_x_preferred":[
        "Batuampun"
    ],
    "wof:name":"Batuampun",
    "wof:placetype":"locality"
},
  "geometry": {"coordinates":[116.2015,-8.8415],"type":"Point"}
}