{
  "type": "Feature",
  "properties": {
    "gn:admin1_code":"26",
    "gn:asciiname":"Kantin",
    "gn:country_code":"ID",
    "gn:dem":786,
    "gn:feature_class":"P",
    "gn:feature_code":"PPL",
    "gn:name":"Kantin",
    "gn:population":0,
    "gn:timezone":"Asia/Jakarta",
    "iso:country":"ID",
    "name:ind_x_preferred":[
        "Kantin"
    ],
    "wof:name":"Kantin",
    "wof:placetype":"locality"
},
  "geometry": {"coordinates":[99.29919,1.4982],"type":"Point"}
}