{
  "type": "Feature",
  "properties": {
    "gn:admin1_code":"10.0",
    "gn:asciiname":"Wediutah",
    "gn:country_code":"ID",
    "gn:dem":159,
    "gn:feature_class":"P",
    "gn:feature_code":"PPL",
    "gn:name":"Wediutah",
    "gn:population":0,
    "gn:timezone":"Asia/Jakarta",
    "iso:country":"ID",
    "name:ind_x_preferred":[
        "Wediutah"
    ],
    "wof:name":"Wediutah",
    "wof:placetype":"locality"
},
  "geometry": {"coordinates":[110.66361000000001,-8.01917],"type":"Point"}
}