{
  "type": "Feature",
  "properties": {
    "gn:admin1_code":"18.0",
    "gn:asciiname":"Bombu",
    "gn:country_code":"ID",
    "gn:dem":806,
    "gn:feature_class":"P",
    "gn:feature_code":"PPLA4",
    "gn:name":"Bombu",
    "gn:population":0,
    "gn:timezone":"Asia/Makassar",
    "iso:country":"ID",
    "name:ind_x_preferred":[
        "Bombu"
    ],
    "wof:lang_x_official":[
        "ind"
    ],
    "wof:lang_x_spoken":[
        "ind",
        "eng"
    ],
    "wof:name":"Bombu",
    "wof:placetype":"locality"
},
  "geometry": {"coordinates":[120.5162,-8.6909],"type":"Point"}
}