{
  "type": "Feature",
  "properties": {
    "gn:admin1_code":"7.0",
    "gn:asciiname":"Cipakelgirang",
    "gn:country_code":"ID",
    "gn:dem":451,
    "gn:feature_class":"P",
    "gn:feature_code":"PPL",
    "gn:name":"Cipakelgirang",
    "gn:population":0,
    "gn:timezone":"Asia/Jakarta",
    "iso:country":"ID",
    "name:ind_x_preferred":[
        "Cipakelgirang"
    ],
    "wof:name":"Cipakelgirang",
    "wof:placetype":"locality"
},
  "geometry": {"coordinates":[108.87611,-7.28028],"type":"Point"}
}