{
  "type": "Feature",
  "properties": {
    "gn:admin1_code":"7.0",
    "gn:asciiname":"Kalibening",
    "gn:country_code":"ID",
    "gn:dem":364,
    "gn:feature_class":"P",
    "gn:feature_code":"PPL",
    "gn:name":"Kalibening",
    "gn:population":0,
    "gn:timezone":"Asia/Jakarta",
    "iso:country":"ID",
    "wof:name":"Kalibening",
    "wof:placetype":"locality"
},
  "geometry": {"coordinates":[110.21778,-7.42528],"type":"Point"}
}