{
  "type": "Feature",
  "properties": {
    "gn:admin1_code":"7",
    "gn:asciiname":"Klesem",
    "gn:country_code":"ID",
    "gn:dem":955,
    "gn:feature_class":"P",
    "gn:feature_code":"PPL",
    "gn:name":"Klesem",
    "gn:population":0,
    "gn:timezone":"Asia/Jakarta",
    "iso:country":"ID",
    "name:ind_x_preferred":[
        "Klesem"
    ],
    "wof:name":"Klesem",
    "wof:placetype":"locality"
},
  "geometry": {"coordinates":[110.04443999999999,-7.2375],"type":"Point"}
}