{
  "type": "Feature",
  "properties": {
    "gn:admin1_code":"38",
    "gn:asciiname":"Amaro",
    "gn:country_code":"ID",
    "gn:dem":5,
    "gn:feature_class":"P",
    "gn:feature_code":"PPL",
    "gn:name":"Amaro",
    "gn:population":0,
    "gn:timezone":"Asia/Makassar",
    "iso:country":"ID",
    "name:ceb_x_preferred":[
        "Amaro"
    ],
    "name:deu_x_preferred":[
        "Amaro"
    ],
    "name:glg_x_preferred":[
        "Amaro"
    ],
    "name:ind_x_preferred":[
        "Amaro"
    ],
    "name:ita_x_preferred":[
        "Amaro"
    ],
    "name:jpn_x_preferred":[
        "\u30a2\u30de\u30fc\u30ed"
    ],
    "name:nds_x_preferred":[
        "Amaro"
    ],
    "name:nld_x_preferred":[
        "Amaro"
    ],
    "name:por_x_preferred":[
        "Amaro"
    ],
    "name:rus_x_preferred":[
        "\u0410\u043c\u0430\u0440\u043e"
    ],
    "name:spa_x_preferred":[
        "Amaro"
    ],
    "name:swe_x_preferred":[
        "Amaro"
    ],
    "name:tur_x_preferred":[
        "Amaro"
    ],
    "wof:lang_x_official":[
        "ind"
    ],
    "wof:lang_x_spoken":[
        "ind",
        "eng"
    ],
    "wof:name":"Amaro",
    "wof:placetype":"locality"
},
  "geometry": {"coordinates":[119.6189,-4.4273],"type":"Point"}
}