{
  "type": "Feature",
  "properties": {
    "gn:admin1_code":"38",
    "gn:asciiname":"Amaro",
    "gn:country_code":"ID",
    "gn:dem":5,
    "gn:feature_class":"P",
    "gn:feature_code":"PPL",
    "gn:name":"Amaro",
    "gn:population":0,
    "gn:timezone":"Asia/Makassar",
    "iso:country":"ID",
    "name:ind_x_preferred":[
        "Amaro"
    ],
    "wof:name":"Amaro",
    "wof:placetype":"locality"
},
  "geometry": {"coordinates":[119.6189,-4.4273],"type":"Point"}
}