{
  "type": "Feature",
  "properties": {
    "gn:admin1_code":"17.0",
    "gn:asciiname":"Bangket Tengak",
    "gn:country_code":"ID",
    "gn:dem":109,
    "gn:feature_class":"P",
    "gn:feature_code":"PPL",
    "gn:name":"Bangket Tengak",
    "gn:population":0,
    "gn:timezone":"Asia/Makassar",
    "iso:country":"ID",
    "name:ind_x_preferred":[
        "Bangket Tengak"
    ],
    "wof:name":"Bangket Tengak",
    "wof:placetype":"locality"
},
  "geometry": {"coordinates":[116.2449,-8.6972],"type":"Point"}
}