{
  "type": "Feature",
  "properties": {
    "gn:admin1_code":"26",
    "gn:asciiname":"Aras Kabu Tiga",
    "gn:country_code":"ID",
    "gn:dem":13,
    "gn:feature_class":"P",
    "gn:feature_code":"PPL",
    "gn:name":"Aras Kabu Tiga",
    "gn:population":0,
    "gn:timezone":"Asia/Jakarta",
    "iso:country":"ID",
    "name:ind_x_preferred":[
        "Aras Kabu Tiga"
    ],
    "name:und_x_variant":[
        "Araskabu 3"
    ],
    "wof:lang_x_official":[
        "ind"
    ],
    "wof:lang_x_spoken":[
        "ind",
        "eng"
    ],
    "wof:name":"Aras Kabu Tiga",
    "wof:placetype":"locality"
},
  "geometry": {"coordinates":[98.8638,3.6222],"type":"Point"}
}