{
  "type": "Feature",
  "properties": {
    "gn:admin1_code":"39.0",
    "gn:asciiname":"Maiky",
    "gn:country_code":"ID",
    "gn:dem":1776,
    "gn:feature_class":"P",
    "gn:feature_code":"PPL",
    "gn:name":"Maiky",
    "gn:population":0,
    "gn:timezone":"Asia/Jayapura",
    "iso:country":"ID",
    "name:ind_x_preferred":[
        "Maiky"
    ],
    "name:und_x_variant":[
        "Makoe",
        "Maikoe",
        "Maiku"
    ],
    "wof:lang_x_official":[
        "ind"
    ],
    "wof:lang_x_spoken":[
        "ind",
        "eng"
    ],
    "wof:name":"Maiky",
    "wof:placetype":"locality"
},
  "geometry": {"coordinates":[133.94370000000001,-1.1528],"type":"Point"}
}