{
  "type": "Feature",
  "properties": {
    "gn:admin1_code":"07",
    "gn:asciiname":"Sanggar",
    "gn:country_code":"ID",
    "gn:dem":1129,
    "gn:feature_class":"P",
    "gn:feature_code":"PPL",
    "gn:name":"Sanggar",
    "gn:population":0,
    "gn:timezone":"Asia/Jakarta",
    "iso:country":"ID",
    "name:und_x_variant":[
        "Sanggan",
        "Sanggar"
    ],
    "wof:name":"Sanggar",
    "wof:placetype":"locality"
},
  "geometry": {"coordinates":[110.50111,-7.49833],"type":"Point"}
}