{
  "type": "Feature",
  "properties": {
    "gn:admin1_code":"8",
    "gn:asciiname":"Blandungan",
    "gn:country_code":"ID",
    "gn:dem":9,
    "gn:feature_class":"P",
    "gn:feature_code":"PPL",
    "gn:name":"Blandungan",
    "gn:population":0,
    "gn:timezone":"Asia/Jakarta",
    "iso:country":"ID",
    "name:ind_x_preferred":[
        "Blandungan"
    ],
    "wof:name":"Blandungan",
    "wof:placetype":"locality"
},
  "geometry": {"coordinates":[112.7239,-7.0429],"type":"Point"}
}