{
  "type": "Feature",
  "properties": {
    "gn:admin1_code":"18.0",
    "gn:asciiname":"Retelama",
    "gn:country_code":"ID",
    "gn:dem":372,
    "gn:feature_class":"P",
    "gn:feature_code":"PPL",
    "gn:name":"Retelama",
    "gn:population":0,
    "gn:timezone":"Asia/Makassar",
    "iso:country":"ID",
    "name:ind_x_preferred":[
        "Retelama"
    ],
    "wof:name":"Retelama",
    "wof:placetype":"locality"
},
  "geometry": {"coordinates":[119.1575,-9.5629],"type":"Point"}
}