{
  "type": "Feature",
  "properties": {
    "gn:admin1_code":"30",
    "gn:asciiname":"Cilendek Wetan",
    "gn:country_code":"ID",
    "gn:dem":211,
    "gn:feature_class":"P",
    "gn:feature_code":"PPL",
    "gn:name":"Cilendek Wetan",
    "gn:population":0,
    "gn:timezone":"Asia/Jakarta",
    "iso:country":"ID",
    "name:ind_x_preferred":[
        "Cilendek Wetan"
    ],
    "name:und_x_variant":[
        "Cilendak Wetan"
    ],
    "wof:lang_x_official":[
        "ind"
    ],
    "wof:lang_x_spoken":[
        "ind",
        "eng"
    ],
    "wof:name":"Cilendek Wetan",
    "wof:placetype":"locality"
},
  "geometry": {"coordinates":[106.77444,-6.57083],"type":"Point"}
}