{
  "type": "Feature",
  "properties": {
    "iso:country":"ID",
    "qs:name":"Tukadmungga",
    "qs:name_adm0":"Indonesia",
    "qs:name_adm1":"Bali",
    "qs:photos":45,
    "qs:photos_1k":9,
    "qs:photos_9k":1,
    "qs:photos_9r":2,
    "qs:photos_all":45,
    "qs:photos_sr":2,
    "qs:placetype":"Town",
    "qs:pop_sr":"0",
    "wof:lang_x_official":[
        "ind"
    ],
    "wof:lang_x_spoken":[
        "ind",
        "eng"
    ],
    "wof:name":"Tukadmungga",
    "wof:placetype":"locality"
},
  "geometry": {"coordinates":[115.0505,-8.141144],"type":"Point"}
}