{
  "type": "Feature",
  "properties": {
    "gn:admin1_code":"39.0",
    "gn:asciiname":"Waijaan",
    "gn:country_code":"ID",
    "gn:dem":26,
    "gn:feature_class":"P",
    "gn:feature_code":"PPL",
    "gn:name":"Waijaan",
    "gn:population":0,
    "gn:timezone":"Asia/Jayapura",
    "iso:country":"ID",
    "name:ind_x_preferred":[
        "Waijaan"
    ],
    "name:und_x_variant":[
        "Waijaar",
        "Wajaar",
        "Waiyaar"
    ],
    "wof:name":"Waijaan",
    "wof:placetype":"locality"
},
  "geometry": {"coordinates":[131.0616,-0.986],"type":"Point"}
}