{
  "type": "Feature",
  "properties": {
    "gn:admin1_code":"26",
    "gn:asciiname":"Batang Baruhar Julu",
    "gn:country_code":"ID",
    "gn:dem":145,
    "gn:feature_class":"P",
    "gn:feature_code":"PPL",
    "gn:name":"Batang Baruhar Julu",
    "gn:population":0,
    "gn:timezone":"Asia/Jakarta",
    "iso:country":"ID",
    "name:ind_x_preferred":[
        "Batang Baruhar Julu"
    ],
    "wof:name":"Batang Baruhar Julu",
    "wof:placetype":"locality"
},
  "geometry": {"coordinates":[99.66611,1.54744],"type":"Point"}
}