{
  "type": "Feature",
  "properties": {
    "gn:admin1_code":"18.0",
    "gn:asciiname":"Puru",
    "gn:country_code":"ID",
    "gn:dem":34,
    "gn:feature_class":"P",
    "gn:feature_code":"PPL",
    "gn:name":"Puru",
    "gn:population":0,
    "gn:timezone":"Asia/Makassar",
    "iso:country":"ID",
    "name:ceb_x_preferred":[
        "Puru"
    ],
    "name:deu_x_preferred":[
        "Puru"
    ],
    "name:eus_x_preferred":[
        "Puru"
    ],
    "name:ind_x_preferred":[
        "Puru"
    ],
    "name:que_x_preferred":[
        "Puru"
    ],
    "name:swe_x_preferred":[
        "Puru"
    ],
    "wof:name":"Puru",
    "wof:placetype":"locality"
},
  "geometry": {"coordinates":[123.68864000000001,-10.35122],"type":"Point"}
}