{
  "type": "Feature",
  "properties": {
    "gn:admin1_code":"1",
    "gn:asciiname":"Pisanglangien",
    "gn:country_code":"ID",
    "gn:dem":15,
    "gn:feature_class":"P",
    "gn:feature_code":"PPL",
    "gn:name":"Pisanglangien",
    "gn:population":0,
    "gn:timezone":"Asia/Jakarta",
    "iso:country":"ID",
    "name:ind_x_preferred":[
        "Pisanglangien"
    ],
    "wof:name":"Pisanglangien",
    "wof:placetype":"locality"
},
  "geometry": {"coordinates":[96.06789999999999,5.2493],"type":"Point"}
}