{
  "type": "Feature",
  "properties": {
    "gn:admin1_code":"18.0",
    "gn:asciiname":"Meobesi",
    "gn:country_code":"ID",
    "gn:dem":240,
    "gn:feature_class":"P",
    "gn:feature_code":"PPLA4",
    "gn:name":"Meobesi",
    "gn:population":0,
    "gn:timezone":"Asia/Makassar",
    "iso:country":"ID",
    "name:ind_x_preferred":[
        "Meobesi"
    ],
    "wof:lang_x_official":[
        "ind"
    ],
    "wof:lang_x_spoken":[
        "ind",
        "eng"
    ],
    "wof:name":"Meobesi",
    "wof:placetype":"locality"
},
  "geometry": {"coordinates":[123.98269999999999,-9.8458],"type":"Point"}
}