{
  "type": "Feature",
  "properties": {
    "gn:admin1_code":"18.0",
    "gn:asciiname":"Natatiwu",
    "gn:country_code":"ID",
    "gn:dem":729,
    "gn:feature_class":"P",
    "gn:feature_code":"PPL",
    "gn:name":"Natatiwu",
    "gn:population":0,
    "gn:timezone":"Asia/Makassar",
    "iso:country":"ID",
    "name:ind_x_preferred":[
        "Natatiwu"
    ],
    "wof:name":"Natatiwu",
    "wof:placetype":"locality"
},
  "geometry": {"coordinates":[121.12860000000001,-8.7856],"type":"Point"}
}