{
  "type": "Feature",
  "properties": {
    "gn:admin1_code":"36.0",
    "gn:asciiname":"Nubai",
    "gn:country_code":"ID",
    "gn:dem":17,
    "gn:feature_class":"P",
    "gn:feature_code":"PPL",
    "gn:name":"Nubai",
    "gn:population":0,
    "gn:timezone":"Asia/Jayapura",
    "iso:country":"ID",
    "name:ind_x_preferred":[
        "Nubai"
    ],
    "name:und_x_variant":[
        "Noeboai",
        "Naboeai",
        "Nabuai",
        "Nuboai"
    ],
    "wof:lang_x_official":[
        "ind"
    ],
    "wof:lang_x_spoken":[
        "ind",
        "eng"
    ],
    "wof:name":"Nubai",
    "wof:placetype":"locality"
},
  "geometry": {"coordinates":[136.52160000000001,-2.2504],"type":"Point"}
}