{
  "type": "Feature",
  "properties": {
    "gn:admin1_code":"1.0",
    "gn:asciiname":"Lamujong",
    "gn:country_code":"ID",
    "gn:dem":12,
    "gn:feature_class":"P",
    "gn:feature_code":"PPL",
    "gn:name":"Lamujong",
    "gn:population":0,
    "gn:timezone":"Asia/Jakarta",
    "iso:country":"ID",
    "name:ind_x_preferred":[
        "Lamujong"
    ],
    "name:und_x_variant":[
        "Lamnjong",
        "Lamnyong"
    ],
    "wof:name":"Lamujong",
    "wof:placetype":"locality"
},
  "geometry": {"coordinates":[95.3634,5.5477],"type":"Point"}
}