{
  "type": "Feature",
  "properties": {
    "gn:admin1_code":"8.0",
    "gn:asciiname":"Duwakpaka",
    "gn:country_code":"ID",
    "gn:dem":12,
    "gn:feature_class":"P",
    "gn:feature_code":"PPL",
    "gn:name":"Duwakpaka",
    "gn:population":0,
    "gn:timezone":"Asia/Jakarta",
    "iso:country":"ID",
    "name:ind_x_preferred":[
        "Duwakpaka"
    ],
    "wof:name":"Duwakpaka",
    "wof:placetype":"locality"
},
  "geometry": {"coordinates":[113.61409999999999,-7.1225],"type":"Point"}
}