{
  "type": "Feature",
  "properties": {
    "gn:admin1_code":"26",
    "gn:asciiname":"Gunung Tua Tumbu Jati",
    "gn:country_code":"ID",
    "gn:dem":186,
    "gn:feature_class":"P",
    "gn:feature_code":"PPL",
    "gn:name":"Gunung Tua Tumbu Jati",
    "gn:population":0,
    "gn:timezone":"Asia/Jakarta",
    "iso:country":"ID",
    "name:ind_x_preferred":[
        "Gunung Tua Tumbu Jati"
    ],
    "wof:lang_x_official":[
        "ind"
    ],
    "wof:lang_x_spoken":[
        "ind",
        "eng"
    ],
    "wof:name":"Gunung Tua Tumbu Jati",
    "wof:placetype":"locality"
},
  "geometry": {"coordinates":[99.46878,1.32723],"type":"Point"}
}