{
  "type": "Feature",
  "properties": {
    "gn:admin1_code":"38",
    "gn:asciiname":"Ujungkupa",
    "gn:country_code":"ID",
    "gn:dem":154,
    "gn:feature_class":"P",
    "gn:feature_code":"PPL",
    "gn:name":"Ujungkupa",
    "gn:population":0,
    "gn:timezone":"Asia/Makassar",
    "iso:country":"ID",
    "name:ind_x_preferred":[
        "Ujungkupa"
    ],
    "wof:name":"Ujungkupa",
    "wof:placetype":"locality"
},
  "geometry": {"coordinates":[119.621,-4.1285],"type":"Point"}
}