{
  "type": "Feature",
  "properties": {
    "gn:admin1_code":"26.0",
    "gn:asciiname":"Purbatuaetek",
    "gn:country_code":"ID",
    "gn:dem":1322,
    "gn:feature_class":"P",
    "gn:feature_code":"PPL",
    "gn:name":"Purbatuaetek",
    "gn:population":0,
    "gn:timezone":"Asia/Jakarta",
    "iso:country":"ID",
    "name:ind_x_preferred":[
        "Purbatuaetek"
    ],
    "wof:name":"Purbatuaetek",
    "wof:placetype":"locality"
},
  "geometry": {"coordinates":[98.6272,2.9959],"type":"Point"}
}