{
  "type": "Feature",
  "properties": {
    "gn:admin1_code":"30.0",
    "gn:asciiname":"Cibulakan",
    "gn:country_code":"ID",
    "gn:dem":926,
    "gn:feature_class":"P",
    "gn:feature_code":"PPL",
    "gn:name":"Cibulakan",
    "gn:population":0,
    "gn:timezone":"Asia/Jakarta",
    "iso:country":"ID",
    "name:ind_x_preferred":[
        "Cibulakan"
    ],
    "name:und_x_variant":[
        "Tjiboelakan"
    ],
    "wof:name":"Cibulakan",
    "wof:placetype":"locality"
},
  "geometry": {"coordinates":[108.0466,-7.1619],"type":"Point"}
}