{
  "type": "Feature",
  "properties": {
    "gn:admin1_code":"30.0",
    "gn:asciiname":"Cimenten",
    "gn:country_code":"ID",
    "gn:dem":55,
    "gn:feature_class":"P",
    "gn:feature_code":"PPL",
    "gn:name":"Cimenten",
    "gn:population":0,
    "gn:timezone":"Asia/Jakarta",
    "iso:country":"ID",
    "name:ind_x_preferred":[
        "Cimenten"
    ],
    "wof:name":"Cimenten",
    "wof:placetype":"locality"
},
  "geometry": {"coordinates":[106.489,-7.3425],"type":"Point"}
}