{
  "type": "Feature",
  "properties": {
    "gn:admin1_code":"8.0",
    "gn:asciiname":"Bangunrejo",
    "gn:country_code":"ID",
    "gn:dem":26,
    "gn:feature_class":"P",
    "gn:feature_code":"PPL",
    "gn:name":"Bangunrejo",
    "gn:population":0,
    "gn:timezone":"Asia/Jakarta",
    "iso:country":"ID",
    "name:ind_x_preferred":[
        "Bangunrejo"
    ],
    "wof:name":"Bangunrejo",
    "wof:placetype":"locality"
},
  "geometry": {"coordinates":[113.64709999999999,-8.3999],"type":"Point"}
}