{
  "type": "Feature",
  "properties": {
    "gn:admin1_code":"36.0",
    "gn:asciiname":"Sengge",
    "gn:country_code":"ID",
    "gn:dem":264,
    "gn:feature_class":"P",
    "gn:feature_code":"PPLA3",
    "gn:name":"Sengge",
    "gn:population":0,
    "gn:timezone":"Asia/Jayapura",
    "iso:country":"ID",
    "name:aze_x_preferred":[
        "Senqe"
    ],
    "name:fra_x_preferred":[
        "Sengge"
    ],
    "name:ind_x_preferred":[
        "Sengge"
    ],
    "name:mon_x_preferred":[
        "\u0421\u044d\u043d\u0433\u044d \u0445\u0443\u043d\u0442\u0430\u0439\u0436"
    ],
    "name:nld_x_preferred":[
        "Sengge"
    ],
    "name:rus_x_preferred":[
        "\u0421\u0435\u043d\u0433\u0435"
    ],
    "name:ukr_x_preferred":[
        "\u0421\u0435\u043d\u0491\u0435"
    ],
    "name:und_x_variant":[
        "Senggi"
    ],
    "wof:name":"Sengge",
    "wof:placetype":"locality"
},
  "geometry": {"coordinates":[140.77510000000001,-3.4475],"type":"Point"}
}