{
  "type": "Feature",
  "properties": {
    "gn:admin1_code":"7.0",
    "gn:asciiname":"Kalangsari",
    "gn:country_code":"ID",
    "gn:dem":494,
    "gn:feature_class":"P",
    "gn:feature_code":"PPL",
    "gn:name":"Kalangsari",
    "gn:population":0,
    "gn:timezone":"Asia/Jakarta",
    "iso:country":"ID",
    "name:ind_x_preferred":[
        "Kalangsari"
    ],
    "wof:name":"Kalangsari",
    "wof:placetype":"locality"
},
  "geometry": {"coordinates":[108.7632,-7.2108],"type":"Point"}
}