{
  "type": "Feature",
  "properties": {
    "gn:admin1_code":"8.0",
    "gn:asciiname":"Naiban",
    "gn:country_code":"ID",
    "gn:dem":90,
    "gn:feature_class":"P",
    "gn:feature_code":"PPL",
    "gn:name":"Naiban",
    "gn:population":0,
    "gn:timezone":"Asia/Jakarta",
    "iso:country":"ID",
    "name:ind_x_preferred":[
        "Naiban"
    ],
    "wof:name":"Naiban",
    "wof:placetype":"locality"
},
  "geometry": {"coordinates":[111.4661,-7.6845],"type":"Point"}
}