{
  "type": "Feature",
  "properties": {
    "gn:admin1_code":"8.0",
    "gn:asciiname":"Tosari",
    "gn:country_code":"ID",
    "gn:dem":485,
    "gn:feature_class":"P",
    "gn:feature_code":"PPL",
    "gn:name":"Tosari",
    "gn:population":0,
    "gn:timezone":"Asia/Jakarta",
    "iso:country":"ID",
    "name:bcl_x_preferred":[
        "Tosari"
    ],
    "name:ind_x_preferred":[
        "Tosari"
    ],
    "name:jav_x_preferred":[
        "Tosari"
    ],
    "name:nld_x_preferred":[
        "Tosari"
    ],
    "name:tgl_x_preferred":[
        "Tosari"
    ],
    "wof:lang_x_official":[
        "ind"
    ],
    "wof:lang_x_spoken":[
        "ind",
        "eng"
    ],
    "wof:name":"Tosari",
    "wof:placetype":"locality"
},
  "geometry": {"coordinates":[111.7882,-7.9942],"type":"Point"}
}