{
  "type": "Feature",
  "properties": {
    "gn:admin1_code":"38.0",
    "gn:asciiname":"Baubau",
    "gn:country_code":"ID",
    "gn:dem":19,
    "gn:feature_class":"P",
    "gn:feature_code":"PPL",
    "gn:name":"Baubau",
    "gn:population":0,
    "gn:timezone":"Asia/Makassar",
    "iso:country":"ID",
    "name:ara_x_preferred":[
        "\u0628\u0627\u0648 \u0628\u0627\u0648"
    ],
    "name:ceb_x_preferred":[
        "Baubau"
    ],
    "name:deu_x_preferred":[
        "Bau-Bau"
    ],
    "name:fra_x_preferred":[
        "Baubau"
    ],
    "name:gor_x_preferred":[
        "Kota Baubau"
    ],
    "name:ind_x_preferred":[
        "Baubau"
    ],
    "name:ind_x_variant":[
        "Kota Baubau"
    ],
    "name:ita_x_preferred":[
        "Bau-Bau"
    ],
    "name:jav_x_preferred":[
        "Kutha Bau-Bau"
    ],
    "name:jpn_x_preferred":[
        "\u30d0\u30a6\u30d0\u30a6"
    ],
    "name:kor_x_preferred":[
        "\ubc14\uc6b0\ubc14\uc6b0"
    ],
    "name:mlg_x_preferred":[
        "Kota Bau-Bau"
    ],
    "name:msa_x_preferred":[
        "Bau-Bau"
    ],
    "name:pol_x_preferred":[
        "Bau-Bau"
    ],
    "name:ron_x_preferred":[
        "Bau-Bau"
    ],
    "name:sco_x_preferred":[
        "Bau-Bau"
    ],
    "name:spa_x_preferred":[
        "Bau-Bau"
    ],
    "name:swe_x_preferred":[
        "Baubau"
    ],
    "name:tur_x_preferred":[
        "Baubau"
    ],
    "name:urd_x_preferred":[
        "\u0628\u0627\u0648 \u0628\u0627\u0648"
    ],
    "name:zho_x_preferred":[
        "\u5df4\u52a1\u5df4\u52a1"
    ],
    "wof:name":"Baubau",
    "wof:placetype":"locality"
},
  "geometry": {"coordinates":[120.40470000000001,-3.6745],"type":"Point"}
}