{
  "type": "Feature",
  "properties": {
    "gn:admin1_code":"38.0",
    "gn:asciiname":"Baubau",
    "gn:country_code":"ID",
    "gn:dem":19,
    "gn:feature_class":"P",
    "gn:feature_code":"PPL",
    "gn:name":"Baubau",
    "gn:population":0,
    "gn:timezone":"Asia/Makassar",
    "iso:country":"ID",
    "name:ind_x_preferred":[
        "Baubau"
    ],
    "wof:name":"Baubau",
    "wof:placetype":"locality"
},
  "geometry": {"coordinates":[120.40470000000001,-3.6745],"type":"Point"}
}