{
  "type": "Feature",
  "properties": {
    "gn:admin1_code":"38.0",
    "gn:asciiname":"Baubau",
    "gn:country_code":"ID",
    "gn:dem":19,
    "gn:feature_class":"P",
    "gn:feature_code":"PPL",
    "gn:name":"Baubau",
    "gn:population":0,
    "gn:timezone":"Asia/Makassar",
    "iso:country":"ID",
    "name:ara_x_preferred":[
        "\u0628\u0627\u0648 \u0628\u0627\u0648"
    ],
    "name:ben_x_preferred":[
        "\u09ac\u09cc\u09ac\u09cc"
    ],
    "name:ceb_x_preferred":[
        "Baubau"
    ],
    "name:deu_x_preferred":[
        "Bau-Bau"
    ],
    "name:ell_x_preferred":[
        "\u039c\u03c0\u03b1\u03bf\u03c5\u03bc\u03c0\u03ac\u03bf\u03c5"
    ],
    "name:fra_x_preferred":[
        "Baubau"
    ],
    "name:gor_x_preferred":[
        "Kota Baubau"
    ],
    "name:heb_x_preferred":[
        "\u05d1\u05d0\u05d5\u05d1\u05d0\u05d5"
    ],
    "name:hin_x_preferred":[
        "\u092c\u093e\u0909\u092c\u093e\u0909"
    ],
    "name:ind_x_preferred":[
        "Baubau"
    ],
    "name:ind_x_variant":[
        "Kota Baubau"
    ],
    "name:ita_x_preferred":[
        "Bau-Bau"
    ],
    "name:jav_x_preferred":[
        "Kutha Bau-Bau"
    ],
    "name:jpn_x_preferred":[
        "\u30d0\u30a6\u30d0\u30a6"
    ],
    "name:kor_x_preferred":[
        "\ubc14\uc6b0\ubc14\uc6b0"
    ],
    "name:mlg_x_preferred":[
        "Kota Bau-Bau"
    ],
    "name:msa_x_preferred":[
        "Bau-Bau"
    ],
    "name:pol_x_preferred":[
        "Bau-Bau"
    ],
    "name:ron_x_preferred":[
        "Bau-Bau"
    ],
    "name:rus_x_preferred":[
        "\u0411\u0430\u0443-\u0411\u0430\u0443"
    ],
    "name:sco_x_preferred":[
        "Bau-Bau"
    ],
    "name:spa_x_preferred":[
        "Bau-Bau"
    ],
    "name:swe_x_preferred":[
        "Baubau"
    ],
    "name:tur_x_preferred":[
        "Baubau"
    ],
    "name:ukr_x_preferred":[
        "\u0411\u0430\u0443\u0431\u0430\u0443"
    ],
    "name:urd_x_preferred":[
        "\u0628\u0627\u0648 \u0628\u0627\u0648"
    ],
    "name:zho_x_preferred":[
        "\u5df4\u52a1\u5df4\u52a1"
    ],
    "wof:lang_x_official":[
        "ind"
    ],
    "wof:lang_x_spoken":[
        "ind",
        "eng"
    ],
    "wof:name":"Baubau",
    "wof:placetype":"locality"
},
  "geometry": {"coordinates":[120.40470000000001,-3.6745],"type":"Point"}
}