{
  "type": "Feature",
  "properties": {
    "gn:admin1_code":"38",
    "gn:asciiname":"Tosulo",
    "gn:country_code":"ID",
    "gn:dem":11,
    "gn:feature_class":"P",
    "gn:feature_code":"PPL",
    "gn:name":"Tosulo",
    "gn:population":0,
    "gn:timezone":"Asia/Makassar",
    "iso:country":"ID",
    "name:ind_x_preferred":[
        "Tosulo"
    ],
    "wof:name":"Tosulo",
    "wof:placetype":"locality"
},
  "geometry": {"coordinates":[119.5508,-3.8475],"type":"Point"}
}