{
  "type": "Feature",
  "properties": {
    "gn:admin1_code":"26",
    "gn:asciiname":"Tanjung",
    "gn:country_code":"ID",
    "gn:dem":14,
    "gn:feature_class":"P",
    "gn:feature_code":"PPL",
    "gn:name":"Tanjung",
    "gn:population":0,
    "gn:timezone":"Asia/Jakarta",
    "iso:country":"ID",
    "name:ceb_x_preferred":[
        "Tanjung"
    ],
    "name:deu_x_preferred":[
        "Tanjung"
    ],
    "name:ind_x_preferred":[
        "Tanjung"
    ],
    "name:nld_x_preferred":[
        "Tanjung"
    ],
    "name:rus_x_preferred":[
        "\u0422\u0430\u043d\u0434\u0436\u0443\u043d\u0433"
    ],
    "name:sun_x_preferred":[
        "Tanjung"
    ],
    "name:swe_x_preferred":[
        "Tanjung"
    ],
    "wof:lang_x_official":[
        "ind"
    ],
    "wof:lang_x_spoken":[
        "ind",
        "eng"
    ],
    "wof:name":"Tanjung",
    "wof:placetype":"locality"
},
  "geometry": {"coordinates":[99.00920000000001,1.0675],"type":"Point"}
}