{
  "type": "Feature",
  "properties": {
    "gn:admin1_code":"26",
    "gn:asciiname":"Jaringnapoko",
    "gn:country_code":"ID",
    "gn:dem":598,
    "gn:feature_class":"P",
    "gn:feature_code":"PPL",
    "gn:name":"Jaringnapoko",
    "gn:population":0,
    "gn:timezone":"Asia/Jakarta",
    "iso:country":"ID",
    "name:ind_x_preferred":[
        "Jaringnapoko"
    ],
    "name:ind_x_variant":[
        "Joringnaposo"
    ],
    "wof:lang_x_official":[
        "ind"
    ],
    "wof:lang_x_spoken":[
        "ind",
        "eng"
    ],
    "wof:name":"Jaringnapoko",
    "wof:placetype":"locality"
},
  "geometry": {"coordinates":[99.24433000000001,1.44544],"type":"Point"}
}