{
  "type": "Feature",
  "properties": {
    "gn:admin1_code":"33.0",
    "gn:asciiname":"Cikadu",
    "gn:country_code":"ID",
    "gn:dem":242,
    "gn:feature_class":"P",
    "gn:feature_code":"PPLA4",
    "gn:name":"Cikadu",
    "gn:population":0,
    "gn:timezone":"Asia/Jakarta",
    "iso:country":"ID",
    "name:ind_x_preferred":[
        "Cikadu"
    ],
    "wof:lang_x_official":[
        "ind"
    ],
    "wof:lang_x_spoken":[
        "ind",
        "eng"
    ],
    "wof:name":"Cikadu",
    "wof:placetype":"locality"
},
  "geometry": {"coordinates":[106.09517,-6.78812],"type":"Point"}
}