{
  "type": "Feature",
  "properties": {
    "gn:admin1_code":"2.0",
    "gn:asciiname":"Sebunibus",
    "gn:country_code":"ID",
    "gn:dem":143,
    "gn:feature_class":"P",
    "gn:feature_code":"PPL",
    "gn:name":"Sebunibus",
    "gn:population":0,
    "gn:timezone":"Asia/Makassar",
    "iso:country":"ID",
    "name:ind_x_preferred":[
        "Sebunibus"
    ],
    "wof:name":"Sebunibus",
    "wof:placetype":"locality"
},
  "geometry": {"coordinates":[115.4901,-8.7028],"type":"Point"}
}