{
  "type": "Feature",
  "properties": {
    "gn:admin1_code":"07",
    "gn:asciiname":"Cabean",
    "gn:country_code":"ID",
    "gn:dem":995,
    "gn:feature_class":"P",
    "gn:feature_code":"PPL",
    "gn:name":"Cabean",
    "gn:population":0,
    "gn:timezone":"Asia/Jakarta",
    "iso:country":"ID",
    "wof:name":"Cabean",
    "wof:placetype":"locality"
},
  "geometry": {"coordinates":[110.51306,-7.52278],"type":"Point"}
}