{
  "type": "Feature",
  "properties": {
    "gn:admin1_code":"17.0",
    "gn:asciiname":"Sambikjengkel",
    "gn:country_code":"ID",
    "gn:dem":122,
    "gn:feature_class":"P",
    "gn:feature_code":"PPL",
    "gn:name":"Sambikjengkel",
    "gn:population":0,
    "gn:timezone":"Asia/Makassar",
    "iso:country":"ID",
    "name:ind_x_preferred":[
        "Sambikjengkel"
    ],
    "wof:name":"Sambikjengkel",
    "wof:placetype":"locality"
},
  "geometry": {"coordinates":[116.2989,-8.2643],"type":"Point"}
}