{
  "type": "Feature",
  "properties": {
    "gn:admin1_code":"30.0",
    "gn:asciiname":"Gaga",
    "gn:country_code":"ID",
    "gn:dem":0,
    "gn:feature_class":"P",
    "gn:feature_code":"PPL",
    "gn:name":"Gaga",
    "gn:population":0,
    "gn:timezone":"Asia/Jakarta",
    "iso:country":"ID",
    "name:ceb_x_preferred":[
        "Gaga"
    ],
    "name:ces_x_preferred":[
        "Gaga"
    ],
    "name:deu_x_preferred":[
        "Gaga"
    ],
    "name:fas_x_preferred":[
        "\u06af\u0627\u06af\u0627"
    ],
    "name:fra_x_preferred":[
        "Gaga"
    ],
    "name:ind_x_preferred":[
        "Gaga"
    ],
    "name:jav_x_preferred":[
        "Gaga"
    ],
    "name:nld_x_preferred":[
        "Gaga"
    ],
    "name:por_x_preferred":[
        "Gaga"
    ],
    "name:rus_x_preferred":[
        "Gaga"
    ],
    "name:swe_x_preferred":[
        "Gaga"
    ],
    "name:tgl_x_preferred":[
        "Gaga"
    ],
    "name:tur_x_preferred":[
        "Gaga"
    ],
    "name:ukr_x_preferred":[
        "\u0413\u0430\u0433\u0430"
    ],
    "name:vie_x_preferred":[
        "Gaga"
    ],
    "wof:lang_x_official":[
        "ind"
    ],
    "wof:lang_x_spoken":[
        "ind",
        "eng"
    ],
    "wof:name":"Gaga",
    "wof:placetype":"locality"
},
  "geometry": {"coordinates":[107.02444,-5.99667],"type":"Point"}
}