{
  "type": "Feature",
  "properties": {
    "gn:admin1_code":"18.0",
    "gn:asciiname":"Marau",
    "gn:country_code":"ID",
    "gn:dem":80,
    "gn:feature_class":"P",
    "gn:feature_code":"PPL",
    "gn:name":"Marau",
    "gn:population":0,
    "gn:timezone":"Asia/Makassar",
    "iso:country":"ID",
    "name:bpy_x_preferred":[
        "\u09ae\u09be\u09b0\u09be\u0989"
    ],
    "name:ceb_x_preferred":[
        "Marau"
    ],
    "name:epo_x_preferred":[
        "Marau"
    ],
    "name:eus_x_preferred":[
        "Marau"
    ],
    "name:fra_x_preferred":[
        "Marau"
    ],
    "name:ind_x_preferred":[
        "Marau"
    ],
    "name:ita_x_preferred":[
        "Marau"
    ],
    "name:kaz_x_preferred":[
        "\u041c\u0430\u0440\u0430\u0443"
    ],
    "name:mlg_x_preferred":[
        "Marau"
    ],
    "name:nor_x_preferred":[
        "Marau"
    ],
    "name:pol_x_preferred":[
        "Marau"
    ],
    "name:por_x_preferred":[
        "Marau"
    ],
    "name:ron_x_preferred":[
        "Marau"
    ],
    "name:rus_x_preferred":[
        "\u041c\u0430\u0440\u0430\u0443"
    ],
    "name:spa_x_preferred":[
        "Marau"
    ],
    "name:swe_x_preferred":[
        "Marau"
    ],
    "name:vie_x_preferred":[
        "Marau"
    ],
    "name:vol_x_preferred":[
        "Marau"
    ],
    "name:war_x_preferred":[
        "Marau"
    ],
    "wof:lang_x_official":[
        "ind"
    ],
    "wof:lang_x_spoken":[
        "ind",
        "eng"
    ],
    "wof:name":"Marau",
    "wof:placetype":"locality"
},
  "geometry": {"coordinates":[121.78440000000001,-10.5978],"type":"Point"}
}