{
  "type": "Feature",
  "properties": {
    "gn:admin1_code":"30",
    "gn:asciiname":"Batudua",
    "gn:country_code":"ID",
    "gn:dem":542,
    "gn:feature_class":"P",
    "gn:feature_code":"PPL",
    "gn:name":"Batudua",
    "gn:population":0,
    "gn:timezone":"Asia/Jakarta",
    "iso:country":"ID",
    "name:ind_x_preferred":[
        "Batudua"
    ],
    "wof:name":"Batudua",
    "wof:placetype":"locality"
},
  "geometry": {"coordinates":[106.57472,-6.59861],"type":"Point"}
}