{
  "type": "Feature",
  "properties": {
    "gn:admin1_code":"41.0",
    "gn:asciiname":"Conggo",
    "gn:country_code":"ID",
    "gn:dem":32,
    "gn:feature_class":"P",
    "gn:feature_code":"PPL",
    "gn:name":"Conggo",
    "gn:population":0,
    "gn:timezone":"Asia/Makassar",
    "iso:country":"ID",
    "name:ind_x_preferred":[
        "Conggo"
    ],
    "wof:name":"Conggo",
    "wof:placetype":"locality"
},
  "geometry": {"coordinates":[119.34569999999999,-3.4061],"type":"Point"}
}