{
  "type": "Feature",
  "properties": {
    "gn:admin1_code":"26",
    "gn:asciiname":"Horuon",
    "gn:country_code":"ID",
    "gn:dem":212,
    "gn:feature_class":"P",
    "gn:feature_code":"PPL",
    "gn:name":"Horuon",
    "gn:population":0,
    "gn:timezone":"Asia/Jakarta",
    "iso:country":"ID",
    "name:ind_x_preferred":[
        "Horuon"
    ],
    "wof:name":"Horuon",
    "wof:placetype":"locality"
},
  "geometry": {"coordinates":[99.73698,1.00779],"type":"Point"}
}