{
  "type": "Feature",
  "properties": {
    "gn:admin1_code":"7.0",
    "gn:asciiname":"Sadon Kulon",
    "gn:country_code":"ID",
    "gn:dem":108,
    "gn:feature_class":"P",
    "gn:feature_code":"PPL",
    "gn:name":"Sadon Kulon",
    "gn:population":0,
    "gn:timezone":"Asia/Jakarta",
    "iso:country":"ID",
    "wof:name":"Sadon Kulon",
    "wof:placetype":"locality"
},
  "geometry": {"coordinates":[110.80972,-7.52389],"type":"Point"}
}