{
  "type": "Feature",
  "properties": {
    "gn:admin1_code":"8.0",
    "gn:asciiname":"Mambang",
    "gn:country_code":"ID",
    "gn:dem":85,
    "gn:feature_class":"P",
    "gn:feature_code":"PPL",
    "gn:name":"Mambang",
    "gn:population":0,
    "gn:timezone":"Asia/Jakarta",
    "iso:country":"ID",
    "name:ind_x_preferred":[
        "Mambang"
    ],
    "wof:name":"Mambang",
    "wof:placetype":"locality"
},
  "geometry": {"coordinates":[113.78870000000001,-6.9565],"type":"Point"}
}