{
  "type": "Feature",
  "properties": {
    "gn:country":"ID",
    "gn:fcode":"PPLA3",
    "gn:pop":0,
    "iso:country":"ID",
    "name:ind_x_preferred":[
        "Pagerageung"
    ],
    "qs:name":"Pagerageung",
    "qs:photos_9r":0,
    "qs:photos_sr":0,
    "qs:pop_sr":"0",
    "wd:wordcount":1319,
    "wof:lang_x_official":[
        "ind"
    ],
    "wof:lang_x_spoken":[
        "ind",
        "eng"
    ],
    "wof:name":"Pagerageung",
    "wof:placetype":"locality",
    "wof:population":0
},
  "geometry": {"coordinates":[108.16679999999999,-7.1124],"type":"Point"}
}