{
  "type": "Feature",
  "properties": {
    "gn:admin1_code":"0.0",
    "gn:asciiname":"Uriya",
    "gn:cc2":"ID",
    "gn:country_code":"ID",
    "gn:dem":404,
    "gn:feature_class":"P",
    "gn:feature_code":"PPL",
    "gn:name":"Uriya",
    "gn:population":0,
    "gn:timezone":"Asia/Jayapura",
    "iso:country":"ID",
    "name:und_x_variant":[
        "Orija",
        "Urija",
        "Oerija",
        "Uriya"
    ],
    "wof:name":"Uriya",
    "wof:placetype":"locality"
},
  "geometry": {"coordinates":[134.31666999999999,-3.01667],"type":"Point"}
}