{
  "type": "Feature",
  "properties": {
    "gn:country":"ID",
    "gn:fcode":"PPL",
    "gn:pop":0,
    "iso:country":"ID",
    "name:ban_x_preferred":[
        "Cisauk"
    ],
    "name:deu_x_preferred":[
        "Cisauk"
    ],
    "name:eng_x_preferred":[
        "Cisauk"
    ],
    "name:fra_x_preferred":[
        "Cisauk"
    ],
    "name:ind_x_preferred":[
        "Cisauk"
    ],
    "name:jav_x_preferred":[
        "Cisauk"
    ],
    "name:msa_x_preferred":[
        "Cisauk"
    ],
    "name:nld_x_preferred":[
        "Cisauk"
    ],
    "name:unk_x_variant":[
        "Tjisoek"
    ],
    "qs:name":"Cisauk",
    "qs:name_adm0":"Indonesia",
    "qs:name_adm1":"Banten",
    "qs:photos_9k":1,
    "qs:photos_9r":1,
    "qs:photos_all":1,
    "qs:photos_sr":0,
    "qs:placetype":"Town",
    "qs:pop_sr":"0",
    "wd:wordcount":31,
    "wof:lang_x_official":[
        "ind"
    ],
    "wof:lang_x_spoken":[
        "ind",
        "eng"
    ],
    "wof:name":"Cisauk",
    "wof:placetype":"locality",
    "wof:population":0
},
  "geometry": {"coordinates":[106.6425,-6.32639],"type":"Point"}
}