{
  "type": "Feature",
  "properties": {
    "gn:admin1_code":"38",
    "gn:asciiname":"Taeng",
    "gn:country_code":"ID",
    "gn:dem":14,
    "gn:feature_class":"P",
    "gn:feature_code":"PPL",
    "gn:name":"Taeng",
    "gn:population":0,
    "gn:timezone":"Asia/Makassar",
    "iso:country":"ID",
    "name:ind_x_preferred":[
        "Taeng"
    ],
    "wof:name":"Taeng",
    "wof:placetype":"locality"
},
  "geometry": {"coordinates":[119.4346,-5.1954],"type":"Point"}
}