{
  "type": "Feature",
  "properties": {
    "gn:admin1_code":"7.0",
    "gn:asciiname":"Barakan",
    "gn:country_code":"ID",
    "gn:dem":470,
    "gn:feature_class":"P",
    "gn:feature_code":"PPL",
    "gn:name":"Barakan",
    "gn:population":0,
    "gn:timezone":"Asia/Jakarta",
    "iso:country":"ID",
    "wof:name":"Barakan",
    "wof:placetype":"locality"
},
  "geometry": {"coordinates":[110.48193999999999,-7.65222],"type":"Point"}
}