{
  "type": "Feature",
  "properties": {
    "gn:admin1_code":"30",
    "gn:asciiname":"Sawah Enam",
    "gn:cc2":"ID",
    "gn:country_code":"ID",
    "gn:dem":83,
    "gn:feature_class":"P",
    "gn:feature_code":"PPL",
    "gn:name":"Sawah Enam",
    "gn:population":0,
    "gn:timezone":"Asia/Jakarta",
    "iso:country":"ID",
    "name:und_x_variant":[
        "Sawah 6",
        "Sawah Enam"
    ],
    "wof:name":"Sawah Enam",
    "wof:placetype":"locality"
},
  "geometry": {"coordinates":[106.97693999999998,-6.41472],"type":"Point"}
}