{
  "type": "Feature",
  "properties": {
    "gn:admin1_code":"18.0",
    "gn:asciiname":"Weekalowo",
    "gn:country_code":"ID",
    "gn:dem":452,
    "gn:feature_class":"P",
    "gn:feature_code":"PPL",
    "gn:name":"Weekalowo",
    "gn:population":0,
    "gn:timezone":"Asia/Makassar",
    "iso:country":"ID",
    "name:ind_x_preferred":[
        "Weekalowo"
    ],
    "wof:name":"Weekalowo",
    "wof:placetype":"locality"
},
  "geometry": {"coordinates":[119.33620000000001,-9.5933],"type":"Point"}
}