{
  "type": "Feature",
  "properties": {
    "gn:admin1_code":"7",
    "gn:asciiname":"Tumut",
    "gn:country_code":"ID",
    "gn:dem":490,
    "gn:feature_class":"P",
    "gn:feature_code":"PPL",
    "gn:name":"Tumut",
    "gn:population":0,
    "gn:timezone":"Asia/Jakarta",
    "iso:country":"ID",
    "name:ara_x_preferred":[
        "\u062a\u0648\u0645\u0648\u062a"
    ],
    "name:ben_x_preferred":[
        "\u09a4\u09c1\u09ae\u09c1\u09a4"
    ],
    "name:ceb_x_preferred":[
        "Tumut"
    ],
    "name:deu_x_preferred":[
        "Tumut"
    ],
    "name:ell_x_preferred":[
        "\u03a4\u03bf\u03c5\u03bc\u03bf\u03cd\u03c4"
    ],
    "name:fas_x_preferred":[
        "\u062a\u0627\u0645\u0648\u062a"
    ],
    "name:fra_x_preferred":[
        "Tumut"
    ],
    "name:gle_x_preferred":[
        "Tumut"
    ],
    "name:heb_x_preferred":[
        "\u05d8\u05d5\u05e8\u05de\u05d5\u05d8"
    ],
    "name:hin_x_preferred":[
        "\u0924\u0941\u092e\u0942\u091f"
    ],
    "name:hun_x_preferred":[
        "Tumut"
    ],
    "name:ind_x_preferred":[
        "Tumut"
    ],
    "name:ita_x_preferred":[
        "Tumut"
    ],
    "name:jpn_x_preferred":[
        "\u30c8\u30a5\u30fc\u30e0\u30c3\u30c8"
    ],
    "name:kor_x_preferred":[
        "\ud22c\ubb34\ud2b8"
    ],
    "name:mlg_x_preferred":[
        "Tumut"
    ],
    "name:msa_x_preferred":[
        "Tumut"
    ],
    "name:por_x_preferred":[
        "Tumut"
    ],
    "name:rus_x_preferred":[
        "\u0422\u044c\u044e\u043c\u0443\u0442"
    ],
    "name:swe_x_preferred":[
        "Tumut"
    ],
    "name:tur_x_preferred":[
        "Tumut"
    ],
    "name:ukr_x_preferred":[
        "\u0422\u0443\u043c\u0443\u0442"
    ],
    "name:urd_x_preferred":[
        "\u062a\u0648\u0645\u0648\u062a"
    ],
    "name:vie_x_preferred":[
        "Tumut"
    ],
    "wof:lang_x_official":[
        "ind"
    ],
    "wof:lang_x_spoken":[
        "ind",
        "eng"
    ],
    "wof:name":"Tumut",
    "wof:placetype":"locality"
},
  "geometry": {"coordinates":[110.83029999999999,-6.6574],"type":"Point"}
}