{
  "type": "Feature",
  "properties": {
    "gn:admin1_code":"7",
    "gn:asciiname":"Tumut",
    "gn:country_code":"ID",
    "gn:dem":490,
    "gn:feature_class":"P",
    "gn:feature_code":"PPL",
    "gn:name":"Tumut",
    "gn:population":0,
    "gn:timezone":"Asia/Jakarta",
    "iso:country":"ID",
    "name:ind_x_preferred":[
        "Tumut"
    ],
    "wof:name":"Tumut",
    "wof:placetype":"locality"
},
  "geometry": {"coordinates":[110.83029999999999,-6.6574],"type":"Point"}
}