{
  "type": "Feature",
  "properties": {
    "gn:admin1_code":"7",
    "gn:asciiname":"Tumut",
    "gn:country_code":"ID",
    "gn:dem":490,
    "gn:feature_class":"P",
    "gn:feature_code":"PPL",
    "gn:name":"Tumut",
    "gn:population":0,
    "gn:timezone":"Asia/Jakarta",
    "iso:country":"ID",
    "name:ara_x_preferred":[
        "\u062a\u0648\u0645\u0648\u062a"
    ],
    "name:ceb_x_preferred":[
        "Tumut"
    ],
    "name:deu_x_preferred":[
        "Tumut"
    ],
    "name:fas_x_preferred":[
        "\u062a\u0627\u0645\u0648\u062a"
    ],
    "name:fra_x_preferred":[
        "Tumut"
    ],
    "name:gle_x_preferred":[
        "Tumut"
    ],
    "name:ind_x_preferred":[
        "Tumut"
    ],
    "name:mlg_x_preferred":[
        "Tumut"
    ],
    "name:msa_x_preferred":[
        "Tumut"
    ],
    "name:por_x_preferred":[
        "Tumut"
    ],
    "name:rus_x_preferred":[
        "\u0422\u044c\u044e\u043c\u0443\u0442"
    ],
    "name:swe_x_preferred":[
        "Tumut"
    ],
    "wof:name":"Tumut",
    "wof:placetype":"locality"
},
  "geometry": {"coordinates":[110.83029999999999,-6.6574],"type":"Point"}
}