{
  "type": "Feature",
  "properties": {
    "gn:admin1_code":"30.0",
    "gn:asciiname":"Dago Tengah",
    "gn:cc2":"ID",
    "gn:country_code":"ID",
    "gn:dem":67,
    "gn:feature_class":"P",
    "gn:feature_code":"PPL",
    "gn:name":"Dago Tengah",
    "gn:population":0,
    "gn:timezone":"Asia/Jakarta",
    "iso:country":"ID",
    "name:und_x_variant":[
        "Dago",
        "Dago Tengah"
    ],
    "wof:name":"Dago Tengah",
    "wof:placetype":"locality"
},
  "geometry": {"coordinates":[106.58667,-6.3975],"type":"Point"}
}