{
  "type": "Feature",
  "properties": {
    "gn:admin1_code":"18",
    "gn:asciiname":"Besnuku",
    "gn:country_code":"ID",
    "gn:dem":570,
    "gn:feature_class":"P",
    "gn:feature_code":"PPL",
    "gn:name":"Besnuku",
    "gn:population":0,
    "gn:timezone":"Asia/Makassar",
    "iso:country":"ID",
    "wof:name":"Besnuku",
    "wof:placetype":"locality"
},
  "geometry": {"coordinates":[124.47778,-9.32778],"type":"Point"}
}