{
  "type": "Feature",
  "properties": {
    "gn:admin1_code":"30.0",
    "gn:asciiname":"Gunungmuncang",
    "gn:country_code":"ID",
    "gn:dem":350,
    "gn:feature_class":"P",
    "gn:feature_code":"PPLA4",
    "gn:name":"Gunungmuncang",
    "gn:population":0,
    "gn:timezone":"Asia/Jakarta",
    "iso:country":"ID",
    "name:ind_x_preferred":[
        "Gunungmuncang"
    ],
    "name:und_x_variant":[
        "Goenoengmoentjang"
    ],
    "wof:lang_x_official":[
        "ind"
    ],
    "wof:lang_x_spoken":[
        "ind",
        "eng"
    ],
    "wof:name":"Gunungmuncang",
    "wof:placetype":"locality"
},
  "geometry": {"coordinates":[108.23820000000001,-7.351],"type":"Point"}
}