{
  "type": "Feature",
  "properties": {
    "gn:admin1_code":"8",
    "gn:asciiname":"Mahbang",
    "gn:country_code":"ID",
    "gn:dem":755,
    "gn:feature_class":"P",
    "gn:feature_code":"PPL",
    "gn:name":"Mahbang",
    "gn:population":0,
    "gn:timezone":"Asia/Jakarta",
    "iso:country":"ID",
    "name:ind_x_preferred":[
        "Mahbang"
    ],
    "wof:name":"Mahbang",
    "wof:placetype":"locality"
},
  "geometry": {"coordinates":[111.31528,-8.09861],"type":"Point"}
}