{
  "type": "Feature",
  "properties": {
    "gn:admin1_code":"26",
    "gn:asciiname":"Merendal Satu Pasar Enam",
    "gn:country_code":"ID",
    "gn:dem":47,
    "gn:feature_class":"P",
    "gn:feature_code":"PPL",
    "gn:name":"Merendal Satu Pasar Enam",
    "gn:population":0,
    "gn:timezone":"Asia/Jakarta",
    "iso:country":"ID",
    "name:ind_x_preferred":[
        "Merendal Satu Pasar Enam"
    ],
    "name:und_x_variant":[
        "Merendal 1 Pasar 6"
    ],
    "wof:name":"Merendal Satu Pasar Enam",
    "wof:placetype":"locality"
},
  "geometry": {"coordinates":[98.70310000000001,3.516],"type":"Point"}
}