{
  "type": "Feature",
  "properties": {
    "gn:admin1_code":"0.0",
    "gn:asciiname":"Candiwulan",
    "gn:cc2":"ID",
    "gn:country_code":"ID",
    "gn:dem":493,
    "gn:feature_class":"P",
    "gn:feature_code":"PPL",
    "gn:name":"Candiwulan",
    "gn:population":0,
    "gn:timezone":"Asia/Jakarta",
    "iso:country":"ID",
    "name:und_x_variant":[
        "Tjandiwoelan",
        "Tjandiwulan",
        "Candiwulan"
    ],
    "wof:lang_x_official":[
        "ind"
    ],
    "wof:lang_x_spoken":[
        "ind",
        "eng"
    ],
    "wof:name":"Candiwulan",
    "wof:placetype":"locality"
},
  "geometry": {"coordinates":[109.28333000000001,-7.31667],"type":"Point"}
}