{
  "type": "Feature",
  "properties": {
    "gn:admin1_code":"10.0",
    "gn:asciiname":"Girigondo",
    "gn:country_code":"ID",
    "gn:dem":25,
    "gn:feature_class":"P",
    "gn:feature_code":"PPL",
    "gn:name":"Girigondo",
    "gn:population":0,
    "gn:timezone":"Asia/Jakarta",
    "iso:country":"ID",
    "name:ind_x_preferred":[
        "Girigondo"
    ],
    "name:jav_x_preferred":[
        "Giriganda"
    ],
    "name:nld_x_preferred":[
        "Girigondo"
    ],
    "wof:lang_x_official":[
        "ind"
    ],
    "wof:lang_x_spoken":[
        "ind",
        "eng"
    ],
    "wof:name":"Girigondo",
    "wof:placetype":"locality"
},
  "geometry": {"coordinates":[110.09305999999999,-7.87528],"type":"Point"}
}