{
  "type": "Feature",
  "properties": {
    "gn:admin1_code":"33.0",
    "gn:asciiname":"Tongkol",
    "gn:country_code":"ID",
    "gn:dem":17,
    "gn:feature_class":"P",
    "gn:feature_code":"PPL",
    "gn:name":"Tongkol",
    "gn:population":0,
    "gn:timezone":"Asia/Jakarta",
    "iso:country":"ID",
    "name:ind_x_preferred":[
        "Tongkol"
    ],
    "wof:name":"Tongkol",
    "wof:placetype":"locality"
},
  "geometry": {"coordinates":[105.89449999999999,-6.4572],"type":"Point"}
}