{
  "type": "Feature",
  "properties": {
    "gn:admin1_code":"30",
    "gn:asciiname":"Mekarmukti",
    "gn:country_code":"ID",
    "gn:dem":1164,
    "gn:feature_class":"P",
    "gn:feature_code":"PPL",
    "gn:name":"Mekarmukti",
    "gn:population":0,
    "gn:timezone":"Asia/Jakarta",
    "iso:country":"ID",
    "wof:name":"Mekarmukti",
    "wof:placetype":"locality"
},
  "geometry": {"coordinates":[107.56610999999999,-7.14194],"type":"Point"}
}