{
  "type": "Feature",
  "properties": {
    "gn:admin1_code":"1",
    "gn:asciiname":"Keras",
    "gn:country_code":"ID",
    "gn:dem":103,
    "gn:feature_class":"P",
    "gn:feature_code":"PPL",
    "gn:name":"Keras",
    "gn:population":0,
    "gn:timezone":"Asia/Jakarta",
    "iso:country":"ID",
    "name:cat_x_preferred":[
        "Keras"
    ],
    "name:deu_x_preferred":[
        "Keras"
    ],
    "name:fas_x_preferred":[
        "\u06a9\u0631\u0633"
    ],
    "name:fra_x_preferred":[
        "Keras"
    ],
    "name:ind_x_preferred":[
        "Keras"
    ],
    "name:ita_x_preferred":[
        "Keras"
    ],
    "name:jpn_x_preferred":[
        "Keras"
    ],
    "name:kor_x_preferred":[
        "\ucf00\ub77c\uc2a4"
    ],
    "name:rus_x_preferred":[
        "Keras"
    ],
    "name:spa_x_preferred":[
        "Keras"
    ],
    "name:ukr_x_preferred":[
        "Keras"
    ],
    "name:zho_x_preferred":[
        "Keras"
    ],
    "wof:lang_x_official":[
        "ind"
    ],
    "wof:lang_x_spoken":[
        "ind",
        "eng"
    ],
    "wof:name":"Keras",
    "wof:placetype":"locality"
},
  "geometry": {"coordinates":[98.06189999999999,2.4892],"type":"Point"}
}