{
  "type": "Feature",
  "properties": {
    "gn:admin1_code":"30.0",
    "gn:asciiname":"Cidukuh",
    "gn:country_code":"ID",
    "gn:dem":772,
    "gn:feature_class":"P",
    "gn:feature_code":"PPL",
    "gn:name":"Cidukuh",
    "gn:population":0,
    "gn:timezone":"Asia/Jakarta",
    "iso:country":"ID",
    "name:ind_x_preferred":[
        "Cidukuh"
    ],
    "name:und_x_variant":[
        "Tjidoekoeh"
    ],
    "wof:lang_x_official":[
        "ind"
    ],
    "wof:lang_x_spoken":[
        "ind",
        "eng"
    ],
    "wof:name":"Cidukuh",
    "wof:placetype":"locality"
},
  "geometry": {"coordinates":[107.8489,-7.4942],"type":"Point"}
}