{
  "type": "Feature",
  "properties": {
    "gn:admin1_code":"7",
    "gn:asciiname":"Ngariboyo",
    "gn:country_code":"ID",
    "gn:dem":378,
    "gn:feature_class":"P",
    "gn:feature_code":"PPL",
    "gn:name":"Ngariboyo",
    "gn:population":0,
    "gn:timezone":"Asia/Jakarta",
    "iso:country":"ID",
    "name:ind_x_preferred":[
        "Ngariboyo"
    ],
    "wof:name":"Ngariboyo",
    "wof:placetype":"locality"
},
  "geometry": {"coordinates":[111.12860999999999,-7.51333],"type":"Point"}
}