{
  "type": "Feature",
  "properties": {
    "gn:admin1_code":"22.0",
    "gn:asciiname":"Mapalenda",
    "gn:country_code":"ID",
    "gn:dem":6,
    "gn:feature_class":"P",
    "gn:feature_code":"PPL",
    "gn:name":"Mapalenda",
    "gn:population":0,
    "gn:timezone":"Asia/Makassar",
    "iso:country":"ID",
    "name:ind_x_preferred":[
        "Mapalenda"
    ],
    "wof:name":"Mapalenda",
    "wof:placetype":"locality"
},
  "geometry": {"coordinates":[122.2675,-5.3279],"type":"Point"}
}