{
  "type": "Feature",
  "properties": {
    "gn:admin1_code":"17",
    "gn:asciiname":"Repokbile",
    "gn:country_code":"ID",
    "gn:dem":339,
    "gn:feature_class":"P",
    "gn:feature_code":"PPL",
    "gn:name":"Repokbile",
    "gn:population":0,
    "gn:timezone":"Asia/Makassar",
    "iso:country":"ID",
    "name:ind_x_preferred":[
        "Repokbile"
    ],
    "wof:name":"Repokbile",
    "wof:placetype":"locality"
},
  "geometry": {"coordinates":[116.39190000000001,-8.6333],"type":"Point"}
}