{
  "type": "Feature",
  "properties": {
    "gn:admin1_code":"30",
    "gn:asciiname":"Cirangganis",
    "gn:country_code":"ID",
    "gn:dem":846,
    "gn:feature_class":"P",
    "gn:feature_code":"PPL",
    "gn:name":"Cirangganis",
    "gn:population":0,
    "gn:timezone":"Asia/Jakarta",
    "iso:country":"ID",
    "name:ind_x_preferred":[
        "Cirangganis"
    ],
    "wof:name":"Cirangganis",
    "wof:placetype":"locality"
},
  "geometry": {"coordinates":[107.83138999999998,-6.89944],"type":"Point"}
}