{
  "type": "Feature",
  "properties": {
    "gn:admin1_code":"7",
    "gn:asciiname":"Puri",
    "gn:country_code":"ID",
    "gn:dem":19,
    "gn:feature_class":"P",
    "gn:feature_code":"PPL",
    "gn:name":"Puri",
    "gn:population":0,
    "gn:timezone":"Asia/Jakarta",
    "iso:country":"ID",
    "name:ara_x_preferred":[
        "\u0628\u0648\u0631\u064a"
    ],
    "name:asm_x_preferred":[
        "\u09aa\u09c1\u09f0\u09c0"
    ],
    "name:bel_x_preferred":[
        "\u041f\u0443\u0440\u044b"
    ],
    "name:ben_x_preferred":[
        "\u09aa\u09c1\u09b0\u09c0"
    ],
    "name:bih_x_preferred":[
        "\u092a\u0941\u0930\u0940"
    ],
    "name:bpy_x_preferred":[
        "\u09aa\u09c1\u09b0\u09bf"
    ],
    "name:cat_x_preferred":[
        "Puri"
    ],
    "name:ceb_x_preferred":[
        "Puri"
    ],
    "name:ces_x_preferred":[
        "Pur\u00ed"
    ],
    "name:cym_x_preferred":[
        "Puri"
    ],
    "name:deu_x_preferred":[
        "Puri"
    ],
    "name:dsb_x_preferred":[
        "Puri"
    ],
    "name:fas_x_preferred":[
        "\u067e\u0648\u0631\u06cc"
    ],
    "name:fin_x_preferred":[
        "Puri"
    ],
    "name:fra_x_preferred":[
        "Pur\u00ee"
    ],
    "name:guj_x_preferred":[
        "\u0a9c\u0a97\u0aa8\u0acd\u0aa8\u0abe\u0aa5\u0aaa\u0ac1\u0ab0\u0ac0"
    ],
    "name:heb_x_preferred":[
        "\u05e4\u05d5\u05e8\u05d9"
    ],
    "name:hin_x_preferred":[
        "\u092a\u0941\u0930\u0940"
    ],
    "name:hun_x_preferred":[
        "Puri"
    ],
    "name:ind_x_preferred":[
        "Puri"
    ],
    "name:ita_x_preferred":[
        "Puri"
    ],
    "name:jpn_x_preferred":[
        "\u30d7\u30ea\u30fc"
    ],
    "name:kan_x_preferred":[
        "\u0caa\u0cc1\u0cb0\u0cbf"
    ],
    "name:kat_x_preferred":[
        "\u10de\u10e3\u10e0\u10d8"
    ],
    "name:lit_x_preferred":[
        "Puris"
    ],
    "name:mai_x_preferred":[
        "\u092a\u0941\u0930\u0940"
    ],
    "name:mal_x_preferred":[
        "\u0d2a\u0d41\u0d30\u0d3f"
    ],
    "name:mar_x_preferred":[
        "\u092a\u0941\u0930\u0940"
    ],
    "name:msa_x_preferred":[
        "Puri"
    ],
    "name:nep_x_preferred":[
        "\u092a\u0941\u0930\u0940"
    ],
    "name:nld_x_preferred":[
        "Puri"
    ],
    "name:nno_x_preferred":[
        "Puri"
    ],
    "name:nor_x_preferred":[
        "Puri"
    ],
    "name:ori_x_preferred":[
        "\u0b2a\u0b41\u0b30\u0b40"
    ],
    "name:pam_x_preferred":[
        "Puri"
    ],
    "name:pol_x_preferred":[
        "Puri"
    ],
    "name:ron_x_preferred":[
        "Puri"
    ],
    "name:rus_x_preferred":[
        "\u041f\u0443\u0440\u0438"
    ],
    "name:san_x_preferred":[
        "\u091c\u0917\u0928\u094d\u0928\u093e\u0925\u092a\u0941\u0930\u0940"
    ],
    "name:sco_x_preferred":[
        "Puri"
    ],
    "name:spa_x_preferred":[
        "Puri"
    ],
    "name:sqi_x_preferred":[
        "Puri"
    ],
    "name:srp_x_preferred":[
        "\u041f\u0443\u0440\u0438"
    ],
    "name:swe_x_preferred":[
        "Puri"
    ],
    "name:tam_x_preferred":[
        "\u0baa\u0bc1\u0bb0\u0bbf"
    ],
    "name:tat_x_preferred":[
        "\u041f\u0443\u0440\u0438"
    ],
    "name:tel_x_preferred":[
        "\u0c2a\u0c42\u0c30\u0c40 \u0c2a\u0c1f\u0c4d\u0c1f\u0c23\u0c02"
    ],
    "name:ukr_x_preferred":[
        "\u041f\u0443\u0440\u0456"
    ],
    "name:urd_x_preferred":[
        "\u067e\u0648\u0631\u06cc"
    ],
    "name:vie_x_preferred":[
        "Puri"
    ],
    "name:war_x_preferred":[
        "Puri"
    ],
    "wof:lang_x_official":[
        "ind"
    ],
    "wof:lang_x_spoken":[
        "ind",
        "eng"
    ],
    "wof:name":"Puri",
    "wof:placetype":"locality"
},
  "geometry": {"coordinates":[110.9593,-6.9158],"type":"Point"}
}