{
  "type": "Feature",
  "properties": {
    "gn:admin1_code":"7.0",
    "gn:asciiname":"Niten",
    "gn:country_code":"ID",
    "gn:dem":682,
    "gn:feature_class":"P",
    "gn:feature_code":"PPL",
    "gn:name":"Niten",
    "gn:population":0,
    "gn:timezone":"Asia/Jakarta",
    "iso:country":"ID",
    "wof:name":"Niten",
    "wof:placetype":"locality"
},
  "geometry": {"coordinates":[110.55722,-7.40583],"type":"Point"}
}