{
  "type": "Feature",
  "properties": {
    "gn:admin1_code":"0.0",
    "gn:asciiname":"Noilmuke",
    "gn:cc2":"ID",
    "gn:country_code":"ID",
    "gn:dem":149,
    "gn:feature_class":"P",
    "gn:feature_code":"PPL",
    "gn:name":"Noilmuke",
    "gn:population":0,
    "gn:timezone":"Asia/Makassar",
    "iso:country":"ID",
    "name:und_x_variant":[
        "Noilmoeke",
        "Numuke",
        "Noilmuke"
    ],
    "wof:lang_x_official":[
        "ind"
    ],
    "wof:lang_x_spoken":[
        "ind",
        "eng"
    ],
    "wof:name":"Noilmuke",
    "wof:placetype":"locality"
},
  "geometry": {"coordinates":[124.34999999999999,-10.08333],"type":"Point"}
}