{
  "type": "Feature",
  "properties": {
    "gn:admin1_code":"26",
    "gn:asciiname":"Melayu",
    "gn:country_code":"ID",
    "gn:dem":197,
    "gn:feature_class":"P",
    "gn:feature_code":"PPL",
    "gn:name":"Melayu",
    "gn:population":0,
    "gn:timezone":"Asia/Jakarta",
    "iso:country":"ID",
    "name:ind_x_preferred":[
        "Melayu"
    ],
    "wof:name":"Melayu",
    "wof:placetype":"locality"
},
  "geometry": {"coordinates":[99.2315,2.9087],"type":"Point"}
}