{
  "type": "Feature",
  "properties": {
    "gn:admin1_code":"17",
    "gn:asciiname":"Banar",
    "gn:country_code":"ID",
    "gn:dem":264,
    "gn:feature_class":"P",
    "gn:feature_code":"PPL",
    "gn:name":"Banar",
    "gn:population":0,
    "gn:timezone":"Asia/Makassar",
    "iso:country":"ID",
    "name:ind_x_preferred":[
        "Banar"
    ],
    "wof:name":"Banar",
    "wof:placetype":"locality"
},
  "geometry": {"coordinates":[116.32170000000001,-8.6843],"type":"Point"}
}