{
  "type": "Feature",
  "properties": {
    "gn:admin1_code":"30.0",
    "gn:asciiname":"Nangung",
    "gn:country_code":"ID",
    "gn:dem":310,
    "gn:feature_class":"P",
    "gn:feature_code":"PPL",
    "gn:name":"Nangung",
    "gn:population":0,
    "gn:timezone":"Asia/Jakarta",
    "iso:country":"ID",
    "name:ind_x_preferred":[
        "Nangung"
    ],
    "name:und_x_variant":[
        "Nanggoeng",
        "Nanggung"
    ],
    "wof:lang_x_official":[
        "ind"
    ],
    "wof:lang_x_spoken":[
        "ind",
        "eng"
    ],
    "wof:name":"Nangung",
    "wof:placetype":"locality"
},
  "geometry": {"coordinates":[106.53888999999999,-6.60417],"type":"Point"}
}