{
  "type": "Feature",
  "properties": {
    "gn:admin1_code":"17.0",
    "gn:asciiname":"Bali Barat",
    "gn:country_code":"ID",
    "gn:dem":130,
    "gn:feature_class":"P",
    "gn:feature_code":"PPL",
    "gn:name":"Bali Barat",
    "gn:population":0,
    "gn:timezone":"Asia/Makassar",
    "iso:country":"ID",
    "name:ind_x_preferred":[
        "Bali Barat"
    ],
    "wof:name":"Bali Barat",
    "wof:placetype":"locality"
},
  "geometry": {"coordinates":[118.27930000000001,-8.5109],"type":"Point"}
}