{
  "type": "Feature",
  "properties": {
    "gn:admin1_code":"3.0",
    "gn:asciiname":"Airpriukan",
    "gn:country_code":"ID",
    "gn:dem":21,
    "gn:feature_class":"P",
    "gn:feature_code":"PPL",
    "gn:name":"Airpriukan",
    "gn:population":0,
    "gn:timezone":"Asia/Jakarta",
    "iso:country":"ID",
    "name:und_x_variant":[
        "Airperiukan",
        "Airprioekan",
        "Airpriukan"
    ],
    "wof:name":"Airpriukan",
    "wof:placetype":"locality"
},
  "geometry": {"coordinates":[102.4348,-3.9952],"type":"Point"}
}