{
  "type": "Feature",
  "properties": {
    "gn:admin1_code":"2",
    "gn:asciiname":"Pandangasah Satu",
    "gn:country_code":"ID",
    "gn:dem":238,
    "gn:feature_class":"P",
    "gn:feature_code":"PPL",
    "gn:name":"Pandangasah Satu",
    "gn:population":0,
    "gn:timezone":"Asia/Makassar",
    "iso:country":"ID",
    "name:ind_x_preferred":[
        "Pandangasah Satu"
    ],
    "wof:name":"Pandangasah Satu",
    "wof:placetype":"locality"
},
  "geometry": {"coordinates":[115.4896,-8.2465],"type":"Point"}
}