{
  "type": "Feature",
  "properties": {
    "gn:admin1_code":"8.0",
    "gn:asciiname":"Tenggina",
    "gn:country_code":"ID",
    "gn:dem":44,
    "gn:feature_class":"P",
    "gn:feature_code":"PPL",
    "gn:name":"Tenggina",
    "gn:population":0,
    "gn:timezone":"Asia/Jakarta",
    "iso:country":"ID",
    "name:ind_x_preferred":[
        "Tenggina"
    ],
    "wof:name":"Tenggina",
    "wof:placetype":"locality"
},
  "geometry": {"coordinates":[113.4572,-7.1256],"type":"Point"}
}