{
  "type": "Feature",
  "properties": {
    "gn:admin1_code":"38.0",
    "gn:asciiname":"Paopaoe",
    "gn:country_code":"ID",
    "gn:dem":462,
    "gn:feature_class":"P",
    "gn:feature_code":"PPL",
    "gn:name":"Paopaoe",
    "gn:population":0,
    "gn:timezone":"Asia/Makassar",
    "iso:country":"ID",
    "name:ind_x_preferred":[
        "Paopaoe"
    ],
    "wof:name":"Paopaoe",
    "wof:placetype":"locality"
},
  "geometry": {"coordinates":[120.1053,-4.5336],"type":"Point"}
}