{
  "type": "Feature",
  "properties": {
    "gn:admin1_code":"7.0",
    "gn:asciiname":"Purut",
    "gn:country_code":"ID",
    "gn:dem":173,
    "gn:feature_class":"P",
    "gn:feature_code":"PPL",
    "gn:name":"Purut",
    "gn:population":0,
    "gn:timezone":"Asia/Jakarta",
    "iso:country":"ID",
    "name:ind_x_preferred":[
        "Purut"
    ],
    "wof:name":"Purut",
    "wof:placetype":"locality"
},
  "geometry": {"coordinates":[109.14972,-7.42222],"type":"Point"}
}