{
  "type": "Feature",
  "properties": {
    "gn:admin1_code":"15.0",
    "gn:asciiname":"Umbulan Radentakunan",
    "gn:country_code":"ID",
    "gn:dem":17,
    "gn:feature_class":"P",
    "gn:feature_code":"PPL",
    "gn:name":"Umbulan Radentakunan",
    "gn:population":0,
    "gn:timezone":"Asia/Jakarta",
    "iso:country":"ID",
    "name:ind_x_preferred":[
        "Umbulan Radentakunan"
    ],
    "name:ind_x_variant":[
        "Umbulanrandentakunan"
    ],
    "wof:name":"Umbulan Radentakunan",
    "wof:placetype":"locality"
},
  "geometry": {"coordinates":[105.33004,-4.29148],"type":"Point"}
}