{
  "type": "Feature",
  "properties": {
    "gn:admin1_code":"08",
    "gn:asciiname":"Ikeriker",
    "gn:country_code":"ID",
    "gn:dem":9,
    "gn:feature_class":"P",
    "gn:feature_code":"PPL",
    "gn:name":"Ikeriker",
    "gn:population":0,
    "gn:timezone":"Asia/Jakarta",
    "iso:country":"ID",
    "name:ind_x_preferred":[
        "Ikeriker"
    ],
    "wof:name":"Ikeriker",
    "wof:placetype":"locality"
},
  "geometry": {"coordinates":[112.5595,-7.2427],"type":"Point"}
}