{
  "type": "Feature",
  "properties": {
    "gn:admin1_code":"30",
    "gn:asciiname":"Bojongsempur",
    "gn:country_code":"ID",
    "gn:dem":656,
    "gn:feature_class":"P",
    "gn:feature_code":"PPL",
    "gn:name":"Bojongsempur",
    "gn:population":0,
    "gn:timezone":"Asia/Jakarta",
    "iso:country":"ID",
    "name:ind_x_preferred":[
        "Bojongsempur"
    ],
    "wof:name":"Bojongsempur",
    "wof:placetype":"locality"
},
  "geometry": {"coordinates":[107.41388999999999,-6.96444],"type":"Point"}
}