{
  "type": "Feature",
  "properties": {
    "gn:admin1_code":"1",
    "gn:asciiname":"Meunasah Bungong",
    "gn:country_code":"ID",
    "gn:dem":11,
    "gn:feature_class":"P",
    "gn:feature_code":"PPL",
    "gn:name":"Meunasah Bungong",
    "gn:population":0,
    "gn:timezone":"Asia/Jakarta",
    "iso:country":"ID",
    "name:ind_x_preferred":[
        "Meunasah Bungong"
    ],
    "wof:name":"Meunasah Bungong",
    "wof:placetype":"locality"
},
  "geometry": {"coordinates":[96.4081,5.197],"type":"Point"}
}