{
  "type": "Feature",
  "properties": {
    "gn:admin1_code":"17.0",
    "gn:asciiname":"Soringonco",
    "gn:country_code":"ID",
    "gn:dem":5,
    "gn:feature_class":"P",
    "gn:feature_code":"PPL",
    "gn:name":"Soringonco",
    "gn:population":0,
    "gn:timezone":"Asia/Makassar",
    "iso:country":"ID",
    "name:ind_x_preferred":[
        "Soringonco"
    ],
    "wof:name":"Soringonco",
    "wof:placetype":"locality"
},
  "geometry": {"coordinates":[118.8822,-8.7643],"type":"Point"}
}