{
  "type": "Feature",
  "properties": {
    "gn:admin1_code":"2.0",
    "gn:asciiname":"Pulanganbaru",
    "gn:country_code":"ID",
    "gn:dem":361,
    "gn:feature_class":"P",
    "gn:feature_code":"PPL",
    "gn:name":"Pulanganbaru",
    "gn:population":0,
    "gn:timezone":"Asia/Makassar",
    "iso:country":"ID",
    "name:ind_x_preferred":[
        "Pulanganbaru"
    ],
    "wof:name":"Pulanganbaru",
    "wof:placetype":"locality"
},
  "geometry": {"coordinates":[115.5658,-8.7251],"type":"Point"}
}