{
  "type": "Feature",
  "properties": {
    "gn:admin1_code":"07",
    "gn:asciiname":"Sidotopo Lor",
    "gn:country_code":"ID",
    "gn:dem":809,
    "gn:feature_class":"P",
    "gn:feature_code":"PPL",
    "gn:name":"Sidotopo Lor",
    "gn:population":0,
    "gn:timezone":"Asia/Jakarta",
    "iso:country":"ID",
    "wof:name":"Sidotopo Lor",
    "wof:placetype":"locality"
},
  "geometry": {"coordinates":[110.53194000000001,-7.50556],"type":"Point"}
}