{
  "type": "Feature",
  "properties": {
    "gn:admin1_code":"8",
    "gn:asciiname":"Watuulo Satu",
    "gn:country_code":"ID",
    "gn:dem":60,
    "gn:feature_class":"P",
    "gn:feature_code":"PPL",
    "gn:name":"Watuulo Satu",
    "gn:population":0,
    "gn:timezone":"Asia/Jakarta",
    "iso:country":"ID",
    "name:ind_x_preferred":[
        "Watuulo Satu"
    ],
    "wof:name":"Watuulo Satu",
    "wof:placetype":"locality"
},
  "geometry": {"coordinates":[114.3456,-8.2249],"type":"Point"}
}