{
  "type": "Feature",
  "properties": {
    "gn:admin1_code":"30",
    "gn:asciiname":"Buluh Kidul",
    "gn:country_code":"ID",
    "gn:dem":716,
    "gn:feature_class":"P",
    "gn:feature_code":"PPL",
    "gn:name":"Buluh Kidul",
    "gn:population":0,
    "gn:timezone":"Asia/Jakarta",
    "iso:country":"ID",
    "name:ind_x_preferred":[
        "Buluh Kidul"
    ],
    "wof:name":"Buluh Kidul",
    "wof:placetype":"locality"
},
  "geometry": {"coordinates":[106.99639000000001,-6.90806],"type":"Point"}
}