{
  "type": "Feature",
  "properties": {
    "gn:admin1_code":"07",
    "gn:asciiname":"Bumuharjo Kidul",
    "gn:cc2":"ID",
    "gn:country_code":"ID",
    "gn:dem":107,
    "gn:feature_class":"P",
    "gn:feature_code":"PPL",
    "gn:name":"Bumuharjo Kidul",
    "gn:population":0,
    "gn:timezone":"Asia/Jakarta",
    "iso:country":"ID",
    "name:und_x_variant":[
        "Bumiharjo Kidul",
        "Bumuharjo Kidul"
    ],
    "wof:lang_x_official":[
        "ind"
    ],
    "wof:lang_x_spoken":[
        "ind",
        "eng"
    ],
    "wof:name":"Bumuharjo Kidul",
    "wof:placetype":"locality"
},
  "geometry": {"coordinates":[110.69750000000001,-7.74444],"type":"Point"}
}