{
  "type": "Feature",
  "properties": {
    "gn:admin1_code":"31",
    "gn:asciiname":"Koha",
    "gn:country_code":"ID",
    "gn:dem":252,
    "gn:feature_class":"P",
    "gn:feature_code":"PPL",
    "gn:name":"Koha",
    "gn:population":0,
    "gn:timezone":"Asia/Makassar",
    "iso:country":"ID",
    "name:ceb_x_preferred":[
        "Koha"
    ],
    "name:deu_x_preferred":[
        "Koha"
    ],
    "name:ind_x_preferred":[
        "Koha"
    ],
    "name:lav_x_preferred":[
        "Koha"
    ],
    "name:swe_x_preferred":[
        "Koha"
    ],
    "wof:lang_x_official":[
        "ind"
    ],
    "wof:lang_x_spoken":[
        "ind",
        "eng"
    ],
    "wof:name":"Koha",
    "wof:placetype":"locality"
},
  "geometry": {"coordinates":[124.7513,1.4184],"type":"Point"}
}