{
  "type": "Feature",
  "properties": {
    "gn:country":"ID",
    "gn:fcode":"PPL",
    "gn:pop":0,
    "iso:country":"ID",
    "name:ace_x_preferred":[
        "Tampan"
    ],
    "name:deu_x_preferred":[
        "Tampan"
    ],
    "name:eng_x_preferred":[
        "Tampan"
    ],
    "name:fra_x_preferred":[
        "Tampan"
    ],
    "name:ind_x_preferred":[
        "Tampan"
    ],
    "name:min_x_preferred":[
        "Tampan"
    ],
    "name:msa_x_preferred":[
        "Tampan"
    ],
    "name:nld_x_preferred":[
        "Tampan"
    ],
    "name:nor_x_preferred":[
        "Sindang"
    ],
    "name:por_x_preferred":[
        "Tampan"
    ],
    "name:spa_x_preferred":[
        "Tampan"
    ],
    "qs:name":"Tampan",
    "qs:name_adm0":"Indonesia",
    "qs:name_adm1":"Riau",
    "qs:photos_9k":1,
    "qs:photos_9r":2,
    "qs:photos_all":66,
    "qs:photos_sr":0,
    "qs:placetype":"Town",
    "qs:pop_sr":"0",
    "wof:name":"Tampan",
    "wof:placetype":"locality",
    "wof:population":0
},
  "geometry": {"coordinates":[101.4166,0.54],"type":"Point"}
}