{
  "type": "Feature",
  "properties": {
    "gn:admin1_code":"30.0",
    "gn:asciiname":"Garunggang",
    "gn:country_code":"ID",
    "gn:dem":360,
    "gn:feature_class":"P",
    "gn:feature_code":"PPLA4",
    "gn:name":"Garunggang",
    "gn:population":0,
    "gn:timezone":"Asia/Jakarta",
    "iso:country":"ID",
    "name:ind_x_preferred":[
        "Garunggang"
    ],
    "wof:name":"Garunggang",
    "wof:placetype":"locality"
},
  "geometry": {"coordinates":[108.2234,-7.4659],"type":"Point"}
}