{
  "type": "Feature",
  "properties": {
    "gn:admin1_code":"30",
    "gn:asciiname":"Genggong",
    "gn:country_code":"ID",
    "gn:dem":497,
    "gn:feature_class":"P",
    "gn:feature_code":"PPL",
    "gn:name":"Genggong",
    "gn:population":0,
    "gn:timezone":"Asia/Jakarta",
    "iso:country":"ID",
    "name:deu_x_preferred":[
        "Genggong"
    ],
    "name:ind_x_preferred":[
        "Genggong"
    ],
    "wof:lang_x_official":[
        "ind"
    ],
    "wof:lang_x_spoken":[
        "ind",
        "eng"
    ],
    "wof:name":"Genggong",
    "wof:placetype":"locality"
},
  "geometry": {"coordinates":[106.72139,-6.82028],"type":"Point"}
}