{
  "type": "Feature",
  "properties": {
    "gn:admin1_code":"41",
    "gn:asciiname":"Papasilumbang",
    "gn:country_code":"ID",
    "gn:dem":164,
    "gn:feature_class":"P",
    "gn:feature_code":"PPL",
    "gn:name":"Papasilumbang",
    "gn:population":0,
    "gn:timezone":"Asia/Makassar",
    "iso:country":"ID",
    "name:ind_x_preferred":[
        "Papasilumbang"
    ],
    "wof:name":"Papasilumbang",
    "wof:placetype":"locality"
},
  "geometry": {"coordinates":[119.0731,-3.3874],"type":"Point"}
}