{
  "type": "Feature",
  "properties": {
    "gn:admin1_code":"15.0",
    "gn:asciiname":"Umbulan Papon Satu",
    "gn:country_code":"ID",
    "gn:dem":98,
    "gn:feature_class":"P",
    "gn:feature_code":"PPL",
    "gn:name":"Umbulan Papon Satu",
    "gn:population":0,
    "gn:timezone":"Asia/Jakarta",
    "iso:country":"ID",
    "name:ind_x_preferred":[
        "Umbulan Papon Satu"
    ],
    "name:und_x_variant":[
        "Umbulanpapon 1"
    ],
    "wof:name":"Umbulan Papon Satu",
    "wof:placetype":"locality"
},
  "geometry": {"coordinates":[104.71836,-4.79003],"type":"Point"}
}