{
  "type": "Feature",
  "properties": {
    "gn:admin1_code":"26",
    "gn:asciiname":"Karang Rejo",
    "gn:country_code":"ID",
    "gn:dem":14,
    "gn:feature_class":"P",
    "gn:feature_code":"PPL",
    "gn:name":"Karang Rejo",
    "gn:population":0,
    "gn:timezone":"Asia/Jakarta",
    "iso:country":"ID",
    "name:ind_x_preferred":[
        "Karang Rejo"
    ],
    "wof:name":"Karang Rejo",
    "wof:placetype":"locality"
},
  "geometry": {"coordinates":[98.49590000000001,3.7208],"type":"Point"}
}