{
  "type": "Feature",
  "properties": {
    "gn:admin1_code":"33",
    "gn:asciiname":"Pelamunantegal",
    "gn:country_code":"ID",
    "gn:dem":20,
    "gn:feature_class":"P",
    "gn:feature_code":"PPL",
    "gn:name":"Pelamunantegal",
    "gn:population":0,
    "gn:timezone":"Asia/Jakarta",
    "iso:country":"ID",
    "name:ind_x_preferred":[
        "Pelamunantegal"
    ],
    "wof:name":"Pelamunantegal",
    "wof:placetype":"locality"
},
  "geometry": {"coordinates":[106.1253,-6.0735],"type":"Point"}
}