{
  "type": "Feature",
  "properties": {
    "gn:admin1_code":"38",
    "gn:asciiname":"Nonok",
    "gn:country_code":"ID",
    "gn:dem":840,
    "gn:feature_class":"P",
    "gn:feature_code":"PPL",
    "gn:name":"Nonok",
    "gn:population":0,
    "gn:timezone":"Asia/Makassar",
    "iso:country":"ID",
    "name:ind_x_preferred":[
        "Nonok"
    ],
    "wof:name":"Nonok",
    "wof:placetype":"locality"
},
  "geometry": {"coordinates":[119.7864,-3.1006],"type":"Point"}
}