{
  "type": "Feature",
  "properties": {
    "gn:admin1_code":"26",
    "gn:asciiname":"Tapiannadengan",
    "gn:country_code":"ID",
    "gn:dem":52,
    "gn:feature_class":"P",
    "gn:feature_code":"PPL",
    "gn:name":"Tapiannadengan",
    "gn:population":0,
    "gn:timezone":"Asia/Jakarta",
    "iso:country":"ID",
    "name:ind_x_preferred":[
        "Tapiannadengan"
    ],
    "name:ind_x_variant":[
        "Tapianadenggan"
    ],
    "wof:lang_x_official":[
        "ind"
    ],
    "wof:lang_x_spoken":[
        "ind",
        "eng"
    ],
    "wof:name":"Tapiannadengan",
    "wof:placetype":"locality"
},
  "geometry": {"coordinates":[99.83759999999999,1.71857],"type":"Point"}
}