{
  "type": "Feature",
  "properties": {
    "gn:admin1_code":"30",
    "gn:asciiname":"Cibiru",
    "gn:country_code":"ID",
    "gn:dem":553,
    "gn:feature_class":"P",
    "gn:feature_code":"PPL",
    "gn:name":"Cibiru",
    "gn:population":0,
    "gn:timezone":"Asia/Jakarta",
    "iso:country":"ID",
    "name:bjn_x_preferred":[
        "Cibiru"
    ],
    "name:ceb_x_preferred":[
        "Kecamatan Cibiru"
    ],
    "name:ind_x_preferred":[
        "Cibiru"
    ],
    "name:jav_x_preferred":[
        "Cibiru"
    ],
    "name:sun_x_preferred":[
        "Cibiru"
    ],
    "name:swe_x_preferred":[
        "Kecamatan Cibiru"
    ],
    "wof:lang_x_official":[
        "ind"
    ],
    "wof:lang_x_spoken":[
        "ind",
        "eng"
    ],
    "wof:name":"Cibiru",
    "wof:placetype":"locality"
},
  "geometry": {"coordinates":[107.91417,-6.81194],"type":"Point"}
}