{
  "type": "Feature",
  "properties": {
    "gn:admin1_code":"1",
    "gn:asciiname":"Silunggai",
    "gn:country_code":"ID",
    "gn:dem":10,
    "gn:feature_class":"P",
    "gn:feature_code":"PPL",
    "gn:name":"Silunggai",
    "gn:population":0,
    "gn:timezone":"Asia/Jakarta",
    "iso:country":"ID",
    "name:ind_x_preferred":[
        "Silunggai"
    ],
    "name:und_x_variant":[
        "Silongai"
    ],
    "wof:name":"Silunggai",
    "wof:placetype":"locality"
},
  "geometry": {"coordinates":[96.1279,2.526],"type":"Point"}
}