{
  "type": "Feature",
  "properties": {
    "gn:admin1_code":"30.0",
    "gn:asciiname":"Ciaremas",
    "gn:country_code":"ID",
    "gn:dem":648,
    "gn:feature_class":"P",
    "gn:feature_code":"PPL",
    "gn:name":"Ciaremas",
    "gn:population":0,
    "gn:timezone":"Asia/Jakarta",
    "iso:country":"ID",
    "name:ind_x_preferred":[
        "Ciaremas"
    ],
    "name:und_x_variant":[
        "Tjiaremas"
    ],
    "wof:name":"Ciaremas",
    "wof:placetype":"locality"
},
  "geometry": {"coordinates":[107.9044,-7.463],"type":"Point"}
}