{
  "type": "Feature",
  "properties": {
    "gn:admin1_code":"26",
    "gn:asciiname":"Sidomulyo Tiga",
    "gn:country_code":"ID",
    "gn:dem":20,
    "gn:feature_class":"P",
    "gn:feature_code":"PPL",
    "gn:name":"Sidomulyo Tiga",
    "gn:population":0,
    "gn:timezone":"Asia/Jakarta",
    "iso:country":"ID",
    "name:ind_x_preferred":[
        "Sidomulyo Tiga"
    ],
    "name:und_x_variant":[
        "Sido Mulyo 3"
    ],
    "wof:lang_x_official":[
        "ind"
    ],
    "wof:lang_x_spoken":[
        "ind",
        "eng"
    ],
    "wof:name":"Sidomulyo Tiga",
    "wof:placetype":"locality"
},
  "geometry": {"coordinates":[99.5917,3.0253],"type":"Point"}
}