{
  "type": "Feature",
  "properties": {
    "gn:admin1_code":"18.0",
    "gn:asciiname":"Botan",
    "gn:country_code":"ID",
    "gn:dem":509,
    "gn:feature_class":"P",
    "gn:feature_code":"PPL",
    "gn:name":"Botan",
    "gn:population":0,
    "gn:timezone":"Asia/Makassar",
    "iso:country":"ID",
    "name:ceb_x_preferred":[
        "Botan"
    ],
    "name:ces_x_preferred":[
        "Botan"
    ],
    "name:deu_x_preferred":[
        "Botan"
    ],
    "name:ind_x_preferred":[
        "Botan"
    ],
    "name:kaz_x_preferred":[
        "\u0411\u043e\u0442\u0430\u043d"
    ],
    "name:kur_x_preferred":[
        "Botan"
    ],
    "name:rus_x_preferred":[
        "\u0411\u043e\u0442\u0430\u043d"
    ],
    "name:srp_x_preferred":[
        "\u0411\u043e\u0442\u0430\u043d"
    ],
    "name:swe_x_preferred":[
        "Botan"
    ],
    "name:tha_x_preferred":[
        "\u0e42\u0e1a\u0e15\u0e31\u0e4b\u0e19"
    ],
    "name:ukr_x_preferred":[
        "\u0411\u043e\u0442\u0430\u043d"
    ],
    "wof:lang_x_official":[
        "ind"
    ],
    "wof:lang_x_spoken":[
        "ind",
        "eng"
    ],
    "wof:name":"Botan",
    "wof:placetype":"locality"
},
  "geometry": {"coordinates":[123.43899999999999,-8.4521],"type":"Point"}
}