{
  "type": "Feature",
  "properties": {
    "gn:admin1_code":"7",
    "gn:asciiname":"Cantel",
    "gn:country_code":"ID",
    "gn:dem":542,
    "gn:feature_class":"P",
    "gn:feature_code":"PPL",
    "gn:name":"Cantel",
    "gn:population":0,
    "gn:timezone":"Asia/Jakarta",
    "iso:country":"ID",
    "name:ceb_x_preferred":[
        "Cantel"
    ],
    "name:ind_x_preferred":[
        "Cantel"
    ],
    "name:swe_x_preferred":[
        "Cantel"
    ],
    "wof:name":"Cantel",
    "wof:placetype":"locality"
},
  "geometry": {"coordinates":[110.19777999999999,-7.20861],"type":"Point"}
}