{
  "type": "Feature",
  "properties": {
    "gn:admin1_code":"8.0",
    "gn:asciiname":"Sumberbening Lor",
    "gn:country_code":"ID",
    "gn:dem":339,
    "gn:feature_class":"P",
    "gn:feature_code":"PPL",
    "gn:name":"Sumberbening Lor",
    "gn:population":0,
    "gn:timezone":"Asia/Jakarta",
    "iso:country":"ID",
    "name:ind_x_preferred":[
        "Sumberbening Lor"
    ],
    "wof:name":"Sumberbening Lor",
    "wof:placetype":"locality"
},
  "geometry": {"coordinates":[112.5502,-8.3206],"type":"Point"}
}