{
  "type": "Feature",
  "properties": {
    "gn:admin1_code":"0.0",
    "gn:asciiname":"Mamponbokor",
    "gn:cc2":"ID",
    "gn:country_code":"ID",
    "gn:dem":19,
    "gn:feature_class":"P",
    "gn:feature_code":"PPL",
    "gn:name":"Mamponbokor",
    "gn:population":0,
    "gn:timezone":"Asia/Jayapura",
    "iso:country":"ID",
    "name:ind_x_preferred":[
        "Mamponbokor"
    ],
    "name:und_x_variant":[
        "Mamponboker",
        "Mamponbokor"
    ],
    "wof:name":"Mamponbokor",
    "wof:placetype":"locality"
},
  "geometry": {"coordinates":[135.78333000000001,-0.93333],"type":"Point"}
}