{
  "type": "Feature",
  "properties": {
    "gn:admin1_code":"1",
    "gn:asciiname":"Paya Bilie Dua",
    "gn:country_code":"ID",
    "gn:dem":5,
    "gn:feature_class":"P",
    "gn:feature_code":"PPL",
    "gn:name":"Paya Bilie Dua",
    "gn:population":0,
    "gn:timezone":"Asia/Jakarta",
    "iso:country":"ID",
    "name:ind_x_preferred":[
        "Paya Bilie Dua"
    ],
    "name:und_x_variant":[
        "Payabilie 2"
    ],
    "wof:name":"Paya Bilie Dua",
    "wof:placetype":"locality"
},
  "geometry": {"coordinates":[97.8377,4.8844],"type":"Point"}
}