{
  "type": "Feature",
  "properties": {
    "gn:admin1_code":"8.0",
    "gn:asciiname":"Bulakbunder",
    "gn:country_code":"ID",
    "gn:dem":90,
    "gn:feature_class":"P",
    "gn:feature_code":"PPL",
    "gn:name":"Bulakbunder",
    "gn:population":0,
    "gn:timezone":"Asia/Jakarta",
    "iso:country":"ID",
    "name:ind_x_preferred":[
        "Bulakbunder"
    ],
    "wof:name":"Bulakbunder",
    "wof:placetype":"locality"
},
  "geometry": {"coordinates":[111.381,-7.5279],"type":"Point"}
}