{
  "type": "Feature",
  "properties": {
    "gn:admin1_code":"30.0",
    "gn:asciiname":"Tarimulya",
    "gn:country_code":"ID",
    "gn:dem":507,
    "gn:feature_class":"P",
    "gn:feature_code":"PPL",
    "gn:name":"Tarimulya",
    "gn:population":0,
    "gn:timezone":"Asia/Jakarta",
    "iso:country":"ID",
    "name:ind_x_preferred":[
        "Tarimulya"
    ],
    "wof:name":"Tarimulya",
    "wof:placetype":"locality"
},
  "geometry": {"coordinates":[108.3715,-7.1436],"type":"Point"}
}