{
  "type": "Feature",
  "properties": {
    "gn:admin1_code":"0.0",
    "gn:asciiname":"Langa",
    "gn:country_code":"ID",
    "gn:dem":2,
    "gn:feature_class":"P",
    "gn:feature_code":"PPL",
    "gn:name":"Langa",
    "gn:population":0,
    "gn:timezone":"Asia/Makassar",
    "iso:country":"ID",
    "name:ceb_x_preferred":[
        "Langa"
    ],
    "name:deu_x_preferred":[
        "Langa"
    ],
    "name:ell_x_preferred":[
        "\u039b\u03ac\u03b3\u03ba\u03b1"
    ],
    "name:eus_x_preferred":[
        "Langa"
    ],
    "name:fra_x_preferred":[
        "Langa"
    ],
    "name:hsb_x_preferred":[
        "Langa"
    ],
    "name:ita_x_preferred":[
        "Langa"
    ],
    "name:pol_x_preferred":[
        "Langa"
    ],
    "name:por_x_preferred":[
        "Langa"
    ],
    "name:spa_x_preferred":[
        "Langa"
    ],
    "name:swe_x_preferred":[
        "Langa"
    ],
    "name:tur_x_preferred":[
        "Langa"
    ],
    "wof:lang_x_official":[
        "ind"
    ],
    "wof:lang_x_spoken":[
        "ind",
        "eng"
    ],
    "wof:name":"Langa",
    "wof:placetype":"locality"
},
  "geometry": {"coordinates":[119.51667,-3.85],"type":"Point"}
}