{
  "type": "Feature",
  "properties": {
    "gn:admin1_code":"37",
    "gn:asciiname":"Burungpanjang",
    "gn:country_code":"ID",
    "gn:dem":9,
    "gn:feature_class":"P",
    "gn:feature_code":"PPL",
    "gn:name":"Burungpanjang",
    "gn:population":0,
    "gn:timezone":"Asia/Jakarta",
    "iso:country":"ID",
    "name:ind_x_preferred":[
        "Burungpanjang"
    ],
    "wof:name":"Burungpanjang",
    "wof:placetype":"locality"
},
  "geometry": {"coordinates":[103.54322999999999,-0.01784],"type":"Point"}
}