{
  "type": "Feature",
  "properties": {
    "gn:admin1_code":"38",
    "gn:asciiname":"Lemosusu",
    "gn:country_code":"ID",
    "gn:dem":113,
    "gn:feature_class":"P",
    "gn:feature_code":"PPL",
    "gn:name":"Lemosusu",
    "gn:population":0,
    "gn:timezone":"Asia/Makassar",
    "iso:country":"ID",
    "name:ind_x_preferred":[
        "Lemosusu"
    ],
    "wof:name":"Lemosusu",
    "wof:placetype":"locality"
},
  "geometry": {"coordinates":[119.5372,-3.4591],"type":"Point"}
}