{
  "type": "Feature",
  "properties": {
    "gn:admin1_code":"26.0",
    "gn:asciiname":"Tanggabatu",
    "gn:country_code":"ID",
    "gn:dem":935,
    "gn:feature_class":"P",
    "gn:feature_code":"PPL",
    "gn:name":"Tanggabatu",
    "gn:population":0,
    "gn:timezone":"Asia/Jakarta",
    "iso:country":"ID",
    "name:ind_x_preferred":[
        "Tanggabatu"
    ],
    "name:und_x_variant":[
        "Tangahbatoe"
    ],
    "wof:lang_x_official":[
        "ind"
    ],
    "wof:lang_x_spoken":[
        "ind",
        "eng"
    ],
    "wof:name":"Tanggabatu",
    "wof:placetype":"locality"
},
  "geometry": {"coordinates":[98.687,2.8748],"type":"Point"}
}