{
  "type": "Feature",
  "properties": {
    "gn:admin1_code":"38",
    "gn:asciiname":"Welonge",
    "gn:country_code":"ID",
    "gn:dem":30,
    "gn:feature_class":"P",
    "gn:feature_code":"PPL",
    "gn:name":"Welonge",
    "gn:population":0,
    "gn:timezone":"Asia/Makassar",
    "iso:country":"ID",
    "name:ind_x_preferred":[
        "Welonge"
    ],
    "wof:name":"Welonge",
    "wof:placetype":"locality"
},
  "geometry": {"coordinates":[119.86279999999999,-4.124],"type":"Point"}
}