{
  "type": "Feature",
  "properties": {
    "gn:admin1_code":"18.0",
    "gn:asciiname":"Watunjanji",
    "gn:country_code":"ID",
    "gn:dem":87,
    "gn:feature_class":"P",
    "gn:feature_code":"PPL",
    "gn:name":"Watunjanji",
    "gn:population":0,
    "gn:timezone":"Asia/Makassar",
    "iso:country":"ID",
    "name:ind_x_preferred":[
        "Watunjanji"
    ],
    "wof:name":"Watunjanji",
    "wof:placetype":"locality"
},
  "geometry": {"coordinates":[120.1964,-9.8359],"type":"Point"}
}