{
  "type": "Feature",
  "properties": {
    "gn:admin1_code":"18",
    "gn:asciiname":"Doma",
    "gn:country_code":"ID",
    "gn:dem":427,
    "gn:feature_class":"P",
    "gn:feature_code":"PPLA4",
    "gn:name":"Doma",
    "gn:population":0,
    "gn:timezone":"Asia/Makassar",
    "iso:country":"ID",
    "name:ind_x_preferred":[
        "Doma"
    ],
    "wof:name":"Doma",
    "wof:placetype":"locality"
},
  "geometry": {"coordinates":[121.3278,-8.6846],"type":"Point"}
}