{
  "type": "Feature",
  "properties": {
    "gn:admin1_code":"18",
    "gn:asciiname":"Doma",
    "gn:country_code":"ID",
    "gn:dem":427,
    "gn:feature_class":"P",
    "gn:feature_code":"PPLA4",
    "gn:name":"Doma",
    "gn:population":0,
    "gn:timezone":"Asia/Makassar",
    "iso:country":"ID",
    "name:bar_x_preferred":[
        "Doma"
    ],
    "name:cat_x_preferred":[
        "Doma"
    ],
    "name:ceb_x_preferred":[
        "Doma"
    ],
    "name:deu_x_preferred":[
        "Doma"
    ],
    "name:fra_x_preferred":[
        "Doma"
    ],
    "name:ind_x_preferred":[
        "Doma"
    ],
    "name:ita_x_preferred":[
        "Doma"
    ],
    "name:oci_x_preferred":[
        "Doma"
    ],
    "name:rus_x_preferred":[
        "\u0414\u043e\u043c\u0430"
    ],
    "name:spa_x_preferred":[
        "Doma"
    ],
    "name:swe_x_preferred":[
        "Doma"
    ],
    "wof:lang_x_official":[
        "ind"
    ],
    "wof:lang_x_spoken":[
        "ind",
        "eng"
    ],
    "wof:name":"Doma",
    "wof:placetype":"locality"
},
  "geometry": {"coordinates":[121.3278,-8.6846],"type":"Point"}
}