{
  "type": "Feature",
  "properties": {
    "gn:admin1_code":"15.0",
    "gn:asciiname":"Umbulanburing Dua",
    "gn:country_code":"ID",
    "gn:dem":25,
    "gn:feature_class":"P",
    "gn:feature_code":"PPL",
    "gn:name":"Umbulanburing Dua",
    "gn:population":0,
    "gn:timezone":"Asia/Jakarta",
    "iso:country":"ID",
    "name:ind_x_preferred":[
        "Umbulanburing Dua"
    ],
    "name:ind_x_variant":[
        "Umbulanburing 2"
    ],
    "wof:name":"Umbulanburing Dua",
    "wof:placetype":"locality"
},
  "geometry": {"coordinates":[105.10325,-4.74175],"type":"Point"}
}