{
  "type": "Feature",
  "properties": {
    "gn:admin1_code":"8",
    "gn:asciiname":"Pohdoyong",
    "gn:country_code":"ID",
    "gn:dem":235,
    "gn:feature_class":"P",
    "gn:feature_code":"PPL",
    "gn:name":"Pohdoyong",
    "gn:population":0,
    "gn:timezone":"Asia/Jakarta",
    "iso:country":"ID",
    "name:ind_x_preferred":[
        "Pohdoyong"
    ],
    "wof:name":"Pohdoyong",
    "wof:placetype":"locality"
},
  "geometry": {"coordinates":[112.86239999999999,-7.7877],"type":"Point"}
}