{
  "type": "Feature",
  "properties": {
    "gn:admin1_code":"28.0",
    "gn:asciiname":"Wahega",
    "gn:country_code":"ID",
    "gn:dem":322,
    "gn:feature_class":"P",
    "gn:feature_code":"PPL",
    "gn:name":"Wahega",
    "gn:population":0,
    "gn:timezone":"Asia/Jayapura",
    "iso:country":"ID",
    "name:und_x_variant":[
        "Wa H\u00e9ga"
    ],
    "wof:name":"Wahega",
    "wof:placetype":"locality"
},
  "geometry": {"coordinates":[126.7381,-3.1286],"type":"Point"}
}