{
  "type": "Feature",
  "properties": {
    "gn:admin1_code":"21",
    "gn:asciiname":"Longkoga Timur",
    "gn:country_code":"ID",
    "gn:dem":6,
    "gn:feature_class":"P",
    "gn:feature_code":"PPL",
    "gn:name":"Longkoga Timur",
    "gn:population":0,
    "gn:timezone":"Asia/Makassar",
    "iso:country":"ID",
    "name:ind_x_preferred":[
        "Longkoga Timur"
    ],
    "name:und_x_variant":[
        "Longkogo"
    ],
    "wof:name":"Longkoga Timur",
    "wof:placetype":"locality"
},
  "geometry": {"coordinates":[123.1087,-0.574],"type":"Point"}
}