{
  "type": "Feature",
  "properties": {
    "gn:admin1_code":"8.0",
    "gn:asciiname":"Cengkrong",
    "gn:country_code":"ID",
    "gn:dem":60,
    "gn:feature_class":"P",
    "gn:feature_code":"PPL",
    "gn:name":"Cengkrong",
    "gn:population":0,
    "gn:timezone":"Asia/Jakarta",
    "iso:country":"ID",
    "name:ind_x_preferred":[
        "Cengkrong"
    ],
    "wof:name":"Cengkrong",
    "wof:placetype":"locality"
},
  "geometry": {"coordinates":[112.8938,-7.7484],"type":"Point"}
}