{
  "type": "Feature",
  "properties": {
    "gn:admin1_code":"18.0",
    "gn:asciiname":"Samamura",
    "gn:country_code":"ID",
    "gn:dem":33,
    "gn:feature_class":"P",
    "gn:feature_code":"PPL",
    "gn:name":"Samamura",
    "gn:population":0,
    "gn:timezone":"Asia/Makassar",
    "iso:country":"ID",
    "name:ind_x_preferred":[
        "Samamura"
    ],
    "wof:name":"Samamura",
    "wof:placetype":"locality"
},
  "geometry": {"coordinates":[121.1314,-8.8938],"type":"Point"}
}