{
  "type": "Feature",
  "properties": {
    "gn:admin1_code":"07",
    "gn:asciiname":"Magersari",
    "gn:country_code":"ID",
    "gn:dem":959,
    "gn:feature_class":"P",
    "gn:feature_code":"PPL",
    "gn:name":"Magersari",
    "gn:population":0,
    "gn:timezone":"Asia/Jakarta",
    "iso:country":"ID",
    "wof:name":"Magersari",
    "wof:placetype":"locality"
},
  "geometry": {"coordinates":[110.51167,-7.54944],"type":"Point"}
}