{
  "type": "Feature",
  "properties": {
    "gn:admin1_code":"30.0",
    "gn:asciiname":"Cipeusing",
    "gn:country_code":"ID",
    "gn:dem":177,
    "gn:feature_class":"P",
    "gn:feature_code":"PPL",
    "gn:name":"Cipeusing",
    "gn:population":0,
    "gn:timezone":"Asia/Jakarta",
    "iso:country":"ID",
    "name:ind_x_preferred":[
        "Cipeusing"
    ],
    "wof:name":"Cipeusing",
    "wof:placetype":"locality"
},
  "geometry": {"coordinates":[107.0192,-7.2434],"type":"Point"}
}