{
  "type": "Feature",
  "properties": {
    "gn:admin1_code":"30",
    "gn:asciiname":"Cibuntu",
    "gn:country_code":"ID",
    "gn:dem":510,
    "gn:feature_class":"P",
    "gn:feature_code":"PPL",
    "gn:name":"Cibuntu",
    "gn:population":0,
    "gn:timezone":"Asia/Jakarta",
    "iso:country":"ID",
    "name:ind_x_preferred":[
        "Cibuntu"
    ],
    "name:msa_x_preferred":[
        "Cibuntu"
    ],
    "name:nld_x_preferred":[
        "Cibuntu"
    ],
    "name:sun_x_preferred":[
        "Cibuntu"
    ],
    "wof:lang_x_official":[
        "ind"
    ],
    "wof:lang_x_spoken":[
        "ind",
        "eng"
    ],
    "wof:name":"Cibuntu",
    "wof:placetype":"locality"
},
  "geometry": {"coordinates":[107.72806,-6.66361],"type":"Point"}
}