{
  "type": "Feature",
  "properties": {
    "gn:admin1_code":"5.0",
    "gn:asciiname":"Barungbarung",
    "gn:country_code":"ID",
    "gn:dem":93,
    "gn:feature_class":"P",
    "gn:feature_code":"PPL",
    "gn:name":"Barungbarung",
    "gn:population":0,
    "gn:timezone":"Asia/Jakarta",
    "iso:country":"ID",
    "name:ind_x_preferred":[
        "Barungbarung"
    ],
    "wof:name":"Barungbarung",
    "wof:placetype":"locality"
},
  "geometry": {"coordinates":[102.5342,-2.5197],"type":"Point"}
}