{
  "type": "Feature",
  "properties": {
    "gn:admin1_code":"18.0",
    "gn:asciiname":"Rong",
    "gn:country_code":"ID",
    "gn:dem":352,
    "gn:feature_class":"P",
    "gn:feature_code":"PPL",
    "gn:name":"Rong",
    "gn:population":0,
    "gn:timezone":"Asia/Makassar",
    "iso:country":"ID",
    "name:deu_x_preferred":[
        "Rong"
    ],
    "name:fra_x_preferred":[
        "Rong"
    ],
    "name:ind_x_preferred":[
        "Rong"
    ],
    "name:nor_x_preferred":[
        "Rong"
    ],
    "wof:lang_x_official":[
        "ind"
    ],
    "wof:lang_x_spoken":[
        "ind",
        "eng"
    ],
    "wof:name":"Rong",
    "wof:placetype":"locality"
},
  "geometry": {"coordinates":[120.1571,-8.5038],"type":"Point"}
}