{
  "type": "Feature",
  "properties": {
    "gn:admin1_code":"30",
    "gn:asciiname":"Nyondol",
    "gn:country_code":"ID",
    "gn:dem":680,
    "gn:feature_class":"P",
    "gn:feature_code":"PPL",
    "gn:name":"Nyondol",
    "gn:population":0,
    "gn:timezone":"Asia/Jakarta",
    "iso:country":"ID",
    "name:ind_x_preferred":[
        "Nyondol"
    ],
    "name:und_x_variant":[
        "Njondol"
    ],
    "wof:name":"Nyondol",
    "wof:placetype":"locality"
},
  "geometry": {"coordinates":[107.46361,-6.79583],"type":"Point"}
}