{
  "type": "Feature",
  "properties": {
    "gn:admin1_code":"30",
    "gn:asciiname":"Dusunpon",
    "gn:country_code":"ID",
    "gn:dem":284,
    "gn:feature_class":"P",
    "gn:feature_code":"PPL",
    "gn:name":"Dusunpon",
    "gn:population":0,
    "gn:timezone":"Asia/Jakarta",
    "iso:country":"ID",
    "name:ind_x_preferred":[
        "Dusunpon"
    ],
    "wof:name":"Dusunpon",
    "wof:placetype":"locality"
},
  "geometry": {"coordinates":[108.46889,-6.80556],"type":"Point"}
}