{
  "type": "Feature",
  "properties": {
    "gn:admin1_code":"17",
    "gn:asciiname":"Temeran",
    "gn:country_code":"ID",
    "gn:dem":27,
    "gn:feature_class":"P",
    "gn:feature_code":"PPL",
    "gn:name":"Temeran",
    "gn:population":0,
    "gn:timezone":"Asia/Makassar",
    "iso:country":"ID",
    "name:ind_x_preferred":[
        "Temeran"
    ],
    "wof:name":"Temeran",
    "wof:placetype":"locality"
},
  "geometry": {"coordinates":[115.9453,-8.7538],"type":"Point"}
}