{
  "type": "Feature",
  "properties": {
    "gn:country":"ID",
    "gn:fcode":"PPL",
    "gn:pop":0,
    "iso:country":"ID",
    "name:ind_x_preferred":[
        "Kuwuh"
    ],
    "qs:name":"Kutuh",
    "qs:name_adm0":"Indonesia",
    "qs:name_adm1":"Bali",
    "qs:photos":588,
    "qs:photos_1k":119,
    "qs:photos_9k":3,
    "qs:photos_9r":5,
    "qs:photos_all":588,
    "qs:photos_sr":8,
    "qs:placetype":"Town",
    "qs:pop_sr":"0",
    "wof:lang_x_official":[
        "ind"
    ],
    "wof:lang_x_spoken":[
        "ind",
        "eng"
    ],
    "wof:name":"Kutuh",
    "wof:placetype":"locality",
    "wof:population":0
},
  "geometry": {"coordinates":[115.1589,-8.6616],"type":"Point"}
}