{
  "type": "Feature",
  "properties": {
    "gn:admin1_code":"8.0",
    "gn:asciiname":"Sukosewu",
    "gn:country_code":"ID",
    "gn:dem":27,
    "gn:feature_class":"P",
    "gn:feature_code":"PPL",
    "gn:name":"Sukosewu",
    "gn:population":0,
    "gn:timezone":"Asia/Jakarta",
    "iso:country":"ID",
    "name:ind_x_preferred":[
        "Sukosewu"
    ],
    "wof:name":"Sukosewu",
    "wof:placetype":"locality"
},
  "geometry": {"coordinates":[112.3883,-7.4565],"type":"Point"}
}