{
  "type": "Feature",
  "properties": {
    "gn:admin1_code":"7.0",
    "gn:asciiname":"Bagel",
    "gn:country_code":"ID",
    "gn:dem":23,
    "gn:feature_class":"P",
    "gn:feature_code":"PPL",
    "gn:name":"Bagel",
    "gn:population":0,
    "gn:timezone":"Asia/Jakarta",
    "iso:country":"ID",
    "name:afr_x_preferred":[
        "Bagel"
    ],
    "name:als_x_preferred":[
        "Bagel"
    ],
    "name:ang_x_preferred":[
        "B\u0113agel"
    ],
    "name:ara_x_preferred":[
        "\u0628\u0627\u064a\u063a\u0644"
    ],
    "name:aze_x_preferred":[
        "Bagel"
    ],
    "name:bar_x_preferred":[
        "Beigl"
    ],
    "name:cat_x_preferred":[
        "Bagel"
    ],
    "name:ces_x_preferred":[
        "Bagel"
    ],
    "name:dan_x_preferred":[
        "Bagel"
    ],
    "name:deu_x_preferred":[
        "Bagel"
    ],
    "name:ell_x_preferred":[
        "\u039c\u03c0\u03ad\u03b3\u03ba\u03b5\u03bb"
    ],
    "name:epo_x_preferred":[
        "Bagelo"
    ],
    "name:fas_x_preferred":[
        "\u0628\u06cc\u06af\u0644"
    ],
    "name:fin_x_preferred":[
        "Vesirinkeli"
    ],
    "name:fra_x_preferred":[
        "Bagel"
    ],
    "name:frp_x_preferred":[
        "Bagu\u00e8l"
    ],
    "name:glg_x_preferred":[
        "Bagel"
    ],
    "name:heb_x_preferred":[
        "\u05db\u05e2\u05da"
    ],
    "name:ind_x_preferred":[
        "Bagel"
    ],
    "name:isl_x_preferred":[
        "Beygla"
    ],
    "name:ita_x_preferred":[
        "Bagel"
    ],
    "name:jpn_x_preferred":[
        "\u30d9\u30fc\u30b0\u30eb"
    ],
    "name:kor_x_preferred":[
        "\ubca0\uc774\uae00"
    ],
    "name:lit_x_preferred":[
        "Didriestainis"
    ],
    "name:msa_x_preferred":[
        "Bagel"
    ],
    "name:nld_x_preferred":[
        "Bagel"
    ],
    "name:nor_x_preferred":[
        "Bagel"
    ],
    "name:pol_x_preferred":[
        "Bajgiel"
    ],
    "name:por_x_preferred":[
        "Bagel"
    ],
    "name:ron_x_preferred":[
        "Bagel"
    ],
    "name:rus_x_preferred":[
        "\u0411\u0435\u0439\u0433\u043b"
    ],
    "name:spa_x_preferred":[
        "Bagel"
    ],
    "name:swe_x_preferred":[
        "Bagel"
    ],
    "name:tgl_x_preferred":[
        "Beygel"
    ],
    "name:tha_x_preferred":[
        "\u0e40\u0e1a\u0e40\u0e01\u0e34\u0e25"
    ],
    "name:tur_x_preferred":[
        "Bagel"
    ],
    "name:ukr_x_preferred":[
        "\u0411\u0435\u0439\u0433\u043b"
    ],
    "wof:lang_x_official":[
        "ind"
    ],
    "wof:lang_x_spoken":[
        "ind",
        "eng"
    ],
    "wof:name":"Bagel",
    "wof:placetype":"locality"
},
  "geometry": {"coordinates":[111.34220000000001,-6.7417],"type":"Point"}
}