{
  "type": "Feature",
  "properties": {
    "gn:admin1_code":"38.0",
    "gn:asciiname":"Tutunganbia",
    "gn:country_code":"ID",
    "gn:dem":837,
    "gn:feature_class":"P",
    "gn:feature_code":"PPL",
    "gn:name":"Tutunganbia",
    "gn:population":0,
    "gn:timezone":"Asia/Makassar",
    "iso:country":"ID",
    "name:ind_x_preferred":[
        "Tutunganbia"
    ],
    "wof:name":"Tutunganbia",
    "wof:placetype":"locality"
},
  "geometry": {"coordinates":[119.8823,-2.9484],"type":"Point"}
}