{
  "type": "Feature",
  "properties": {
    "gn:admin1_code":"18.0",
    "gn:asciiname":"Kusumaraten",
    "gn:country_code":"ID",
    "gn:dem":73,
    "gn:feature_class":"P",
    "gn:feature_code":"PPL",
    "gn:name":"Kusumaraten",
    "gn:population":0,
    "gn:timezone":"Asia/Makassar",
    "iso:country":"ID",
    "name:ind_x_preferred":[
        "Kusumaraten"
    ],
    "wof:name":"Kusumaraten",
    "wof:placetype":"locality"
},
  "geometry": {"coordinates":[123.37130000000001,-10.6383],"type":"Point"}
}