{
  "type": "Feature",
  "properties": {
    "gn:admin1_code":"17",
    "gn:asciiname":"Tewang",
    "gn:country_code":"ID",
    "gn:dem":116,
    "gn:feature_class":"P",
    "gn:feature_code":"PPL",
    "gn:name":"Tewang",
    "gn:population":0,
    "gn:timezone":"Asia/Makassar",
    "iso:country":"ID",
    "name:ceb_x_preferred":[
        "Tewang"
    ],
    "name:fra_x_preferred":[
        "Tewang"
    ],
    "name:ind_x_preferred":[
        "Tewang"
    ],
    "name:mai_x_preferred":[
        "\u0924\u0947\u0935\u093e\u0919"
    ],
    "name:msa_x_preferred":[
        "Tewang"
    ],
    "name:nep_x_preferred":[
        "\u0924\u0947\u0935\u093e\u0919"
    ],
    "name:new_x_preferred":[
        "\u0924\u0947\u0935\u093e\u0919"
    ],
    "name:pol_x_preferred":[
        "Tewang"
    ],
    "wof:name":"Tewang",
    "wof:placetype":"locality"
},
  "geometry": {"coordinates":[116.2972,-8.8365],"type":"Point"}
}