{
  "type": "Feature",
  "properties": {
    "gn:admin1_code":"30",
    "gn:asciiname":"Cipasung",
    "gn:cc2":"ID",
    "gn:country_code":"ID",
    "gn:dem":670,
    "gn:feature_class":"P",
    "gn:feature_code":"PPL",
    "gn:name":"Cipasung",
    "gn:population":0,
    "gn:timezone":"Asia/Jakarta",
    "iso:country":"ID",
    "name:und_x_variant":[
        "Tjipasung",
        "Cipasung"
    ],
    "wof:name":"Cipasung",
    "wof:placetype":"locality"
},
  "geometry": {"coordinates":[107.58306,-7.02778],"type":"Point"}
}