{
  "type": "Feature",
  "properties": {
    "gn:admin1_code":"18.0",
    "gn:asciiname":"Tubutnana",
    "gn:country_code":"ID",
    "gn:dem":964,
    "gn:feature_class":"P",
    "gn:feature_code":"PPL",
    "gn:name":"Tubutnana",
    "gn:population":0,
    "gn:timezone":"Asia/Makassar",
    "iso:country":"ID",
    "name:ind_x_preferred":[
        "Tubutnana"
    ],
    "wof:name":"Tubutnana",
    "wof:placetype":"locality"
},
  "geometry": {"coordinates":[124.6049,-9.861],"type":"Point"}
}