{
  "type": "Feature",
  "properties": {
    "gn:admin1_code":"26",
    "gn:asciiname":"Tunggorono Tiga",
    "gn:country_code":"ID",
    "gn:dem":32,
    "gn:feature_class":"P",
    "gn:feature_code":"PPL",
    "gn:name":"Tunggorono Tiga",
    "gn:population":0,
    "gn:timezone":"Asia/Jakarta",
    "iso:country":"ID",
    "name:ind_x_preferred":[
        "Tunggorono Tiga"
    ],
    "name:und_x_variant":[
        "Tunggorono 3"
    ],
    "wof:name":"Tunggorono Tiga",
    "wof:placetype":"locality"
},
  "geometry": {"coordinates":[98.52460000000001,3.6061],"type":"Point"}
}