{
  "type": "Feature",
  "properties": {
    "gn:admin1_code":"5.0",
    "gn:asciiname":"Tanjungbojo",
    "gn:country_code":"ID",
    "gn:dem":13,
    "gn:feature_class":"P",
    "gn:feature_code":"PPL",
    "gn:name":"Tanjungbojo",
    "gn:population":0,
    "gn:timezone":"Asia/Jakarta",
    "iso:country":"ID",
    "name:und_x_variant":[
        "Tandjungbodjo",
        "Tandjoengbodjo",
        "Tanjungbojo"
    ],
    "wof:name":"Tanjungbojo",
    "wof:placetype":"locality"
},
  "geometry": {"coordinates":[102.9671,-1.0718],"type":"Point"}
}