{
  "type": "Feature",
  "properties": {
    "gn:admin1_code":"2",
    "gn:asciiname":"Mundukjuwet",
    "gn:country_code":"ID",
    "gn:dem":387,
    "gn:feature_class":"P",
    "gn:feature_code":"PPL",
    "gn:name":"Mundukjuwet",
    "gn:population":0,
    "gn:timezone":"Asia/Makassar",
    "iso:country":"ID",
    "name:ind_x_preferred":[
        "Mundukjuwet"
    ],
    "wof:name":"Mundukjuwet",
    "wof:placetype":"locality"
},
  "geometry": {"coordinates":[115.0942,-8.4385],"type":"Point"}
}