{
  "type": "Feature",
  "properties": {
    "gn:admin1_code":"32.0",
    "gn:asciiname":"Talang Gemuruh Satu",
    "gn:country_code":"ID",
    "gn:dem":37,
    "gn:feature_class":"P",
    "gn:feature_code":"PPL",
    "gn:name":"Talang Gemuruh Satu",
    "gn:population":0,
    "gn:timezone":"Asia/Jakarta",
    "iso:country":"ID",
    "name:ind_x_preferred":[
        "Talang Gemuruh Satu"
    ],
    "name:und_x_variant":[
        "Talang Gemuruh 1"
    ],
    "wof:lang_x_official":[
        "ind"
    ],
    "wof:lang_x_spoken":[
        "ind",
        "eng"
    ],
    "wof:name":"Talang Gemuruh Satu",
    "wof:placetype":"locality"
},
  "geometry": {"coordinates":[103.7308,-2.7552],"type":"Point"}
}