{
  "type": "Feature",
  "properties": {
    "gn:admin1_code":"0.0",
    "gn:asciiname":"Paritsungaisakadua",
    "gn:country_code":"ID",
    "gn:dem":8,
    "gn:feature_class":"P",
    "gn:feature_code":"PPL",
    "gn:name":"Paritsungaisakadua",
    "gn:population":0,
    "gn:timezone":"Asia/Jakarta",
    "iso:country":"ID",
    "name:ind_x_preferred":[
        "Paritsungaisakadua"
    ],
    "wof:name":"Paritsungaisakadua",
    "wof:placetype":"locality"
},
  "geometry": {"coordinates":[103.06475,-0.28692],"type":"Point"}
}