{
  "type": "Feature",
  "properties": {
    "gn:admin1_code":"18.0",
    "gn:asciiname":"Nono",
    "gn:country_code":"ID",
    "gn:dem":806,
    "gn:feature_class":"P",
    "gn:feature_code":"PPL",
    "gn:name":"Nono",
    "gn:population":0,
    "gn:timezone":"Asia/Makassar",
    "iso:country":"ID",
    "name:ceb_x_preferred":[
        "Nono"
    ],
    "name:deu_x_preferred":[
        "Nono"
    ],
    "name:fas_x_preferred":[
        "\u0646\u0648\u0646\u0648"
    ],
    "name:fra_x_preferred":[
        "Nono"
    ],
    "name:heb_x_preferred":[
        "\u05e0\u05d5\u05e0\u05d5"
    ],
    "name:ind_x_preferred":[
        "Nono"
    ],
    "name:ita_x_preferred":[
        "Nono"
    ],
    "name:por_x_preferred":[
        "Nono"
    ],
    "name:spa_x_preferred":[
        "Nono"
    ],
    "name:swe_x_preferred":[
        "Nono"
    ],
    "wof:name":"Nono",
    "wof:placetype":"locality"
},
  "geometry": {"coordinates":[124.5656,-9.8188],"type":"Point"}
}