{
  "type": "Feature",
  "properties": {
    "gn:admin1_code":"07",
    "gn:asciiname":"Nengahan",
    "gn:country_code":"ID",
    "gn:dem":131,
    "gn:feature_class":"P",
    "gn:feature_code":"PPL",
    "gn:name":"Nengahan",
    "gn:population":0,
    "gn:timezone":"Asia/Jakarta",
    "iso:country":"ID",
    "wof:name":"Nengahan",
    "wof:placetype":"locality"
},
  "geometry": {"coordinates":[110.64306000000001,-7.79361],"type":"Point"}
}