{
  "type": "Feature",
  "properties": {
    "gn:admin1_code":"7.0",
    "gn:asciiname":"Ngaglik",
    "gn:country_code":"ID",
    "gn:dem":899,
    "gn:feature_class":"P",
    "gn:feature_code":"PPL",
    "gn:name":"Ngaglik",
    "gn:population":0,
    "gn:timezone":"Asia/Jakarta",
    "iso:country":"ID",
    "wof:name":"Ngaglik",
    "wof:placetype":"locality"
},
  "geometry": {"coordinates":[110.15000000000001,-7.39306],"type":"Point"}
}