{
  "type": "Feature",
  "properties": {
    "gn:admin1_code":"17",
    "gn:asciiname":"Labuhan",
    "gn:country_code":"ID",
    "gn:dem":15,
    "gn:feature_class":"P",
    "gn:feature_code":"PPL",
    "gn:name":"Labuhan",
    "gn:population":0,
    "gn:timezone":"Asia/Makassar",
    "iso:country":"ID",
    "name:ind_x_preferred":[
        "Labuhan"
    ],
    "wof:name":"Labuhan",
    "wof:placetype":"locality"
},
  "geometry": {"coordinates":[118.3951,-8.7674],"type":"Point"}
}