{
  "type": "Feature",
  "properties": {
    "gn:admin1_code":"18.0",
    "gn:asciiname":"Koja Doi",
    "gn:country_code":"ID",
    "gn:dem":9,
    "gn:feature_class":"P",
    "gn:feature_code":"PPL",
    "gn:name":"Koja Doi",
    "gn:population":0,
    "gn:timezone":"Asia/Makassar",
    "iso:country":"ID",
    "name:ind_x_preferred":[
        "Koja Doi"
    ],
    "wof:name":"Koja Doi",
    "wof:placetype":"locality"
},
  "geometry": {"coordinates":[122.3986,-8.496],"type":"Point"}
}