{
  "type": "Feature",
  "properties": {
    "gn:admin1_code":"7.0",
    "gn:asciiname":"Gununggoong",
    "gn:country_code":"ID",
    "gn:dem":15,
    "gn:feature_class":"P",
    "gn:feature_code":"PPL",
    "gn:name":"Gununggoong",
    "gn:population":0,
    "gn:timezone":"Asia/Jakarta",
    "iso:country":"ID",
    "name:ind_x_preferred":[
        "Gununggoong"
    ],
    "wof:name":"Gununggoong",
    "wof:placetype":"locality"
},
  "geometry": {"coordinates":[108.7291,-7.4711],"type":"Point"}
}