{
  "type": "Feature",
  "properties": {
    "gn:admin1_code":"7.0",
    "gn:asciiname":"Cijawa",
    "gn:country_code":"ID",
    "gn:dem":520,
    "gn:feature_class":"P",
    "gn:feature_code":"PPL",
    "gn:name":"Cijawa",
    "gn:population":0,
    "gn:timezone":"Asia/Jakarta",
    "iso:country":"ID",
    "name:ind_x_preferred":[
        "Cijawa"
    ],
    "wof:name":"Cijawa",
    "wof:placetype":"locality"
},
  "geometry": {"coordinates":[108.6403,-7.2568],"type":"Point"}
}