{
  "type": "Feature",
  "properties": {
    "gn:admin1_code":"33",
    "gn:asciiname":"Cipeuteuy",
    "gn:country_code":"ID",
    "gn:dem":84,
    "gn:feature_class":"P",
    "gn:feature_code":"PPL",
    "gn:name":"Cipeuteuy",
    "gn:population":0,
    "gn:timezone":"Asia/Jakarta",
    "iso:country":"ID",
    "name:ind_x_preferred":[
        "Cipeuteuy"
    ],
    "wof:name":"Cipeuteuy",
    "wof:placetype":"locality"
},
  "geometry": {"coordinates":[106.2042,-6.2638],"type":"Point"}
}