{
  "type": "Feature",
  "properties": {
    "gn:admin1_code":"30.0",
    "gn:asciiname":"Muarapecah",
    "gn:country_code":"ID",
    "gn:dem":0,
    "gn:feature_class":"P",
    "gn:feature_code":"PPL",
    "gn:name":"Muarapecah",
    "gn:population":0,
    "gn:timezone":"Asia/Jakarta",
    "iso:country":"ID",
    "name:ind_x_preferred":[
        "Muarapecah"
    ],
    "name:und_x_variant":[
        "Moearapetjah",
        "Muarapetjah"
    ],
    "wof:lang_x_official":[
        "ind"
    ],
    "wof:lang_x_spoken":[
        "ind",
        "eng"
    ],
    "wof:name":"Muarapecah",
    "wof:placetype":"locality"
},
  "geometry": {"coordinates":[107.02167,-5.97083],"type":"Point"}
}