{
  "type": "Feature",
  "properties": {
    "gn:admin1_code":"26",
    "gn:asciiname":"Bagan",
    "gn:country_code":"ID",
    "gn:dem":4,
    "gn:feature_class":"P",
    "gn:feature_code":"PPL",
    "gn:name":"Bagan",
    "gn:population":0,
    "gn:timezone":"Asia/Jakarta",
    "iso:country":"ID",
    "name:ara_x_preferred":[
        "\u0628\u0627\u063a\u0627\u0646"
    ],
    "name:ast_x_preferred":[
        "Bagan"
    ],
    "name:aze_x_preferred":[
        "Baqan"
    ],
    "name:bul_x_preferred":[
        "\u0411\u0430\u0433\u0430\u043d"
    ],
    "name:cat_x_preferred":[
        "Bagan"
    ],
    "name:ceb_x_preferred":[
        "Pagan"
    ],
    "name:ces_x_preferred":[
        "Pagan"
    ],
    "name:deu_x_preferred":[
        "Bagan"
    ],
    "name:ell_x_preferred":[
        "\u039c\u03c0\u03b1\u03b3\u03ba\u03ac\u03bd"
    ],
    "name:est_x_preferred":[
        "Bagan"
    ],
    "name:eus_x_preferred":[
        "Bagan"
    ],
    "name:fin_x_preferred":[
        "Pagan"
    ],
    "name:fra_x_preferred":[
        "Bagan"
    ],
    "name:heb_x_preferred":[
        "\u05d1\u05d0\u05d2\u05d0\u05df"
    ],
    "name:hin_x_preferred":[
        "\u092a\u0941\u0917\u0902"
    ],
    "name:hrv_x_preferred":[
        "Bagan"
    ],
    "name:hun_x_preferred":[
        "Bagan"
    ],
    "name:ind_x_preferred":[
        "Bagan"
    ],
    "name:ita_x_preferred":[
        "Bagan"
    ],
    "name:jpn_x_preferred":[
        "\u30d0\u30ac\u30f3"
    ],
    "name:kan_x_preferred":[
        "\u0cac\u0cbe\u0c97\u0ca8\u0ccd"
    ],
    "name:lat_x_preferred":[
        "Pagan"
    ],
    "name:lav_x_preferred":[
        "Bagana"
    ],
    "name:lit_x_preferred":[
        "Baganas"
    ],
    "name:mya_x_preferred":[
        "\u1015\u102f\u1002\u1036"
    ],
    "name:nld_x_preferred":[
        "Pagan"
    ],
    "name:oci_x_preferred":[
        "Bagan"
    ],
    "name:pan_x_preferred":[
        "\u0a2c\u0a3e\u0a17\u0a3e\u0a28"
    ],
    "name:pol_x_preferred":[
        "Pagan"
    ],
    "name:por_x_preferred":[
        "Bagan"
    ],
    "name:rus_x_preferred":[
        "\u041f\u0430\u0433\u0430\u043d"
    ],
    "name:sco_x_preferred":[
        "Bagan"
    ],
    "name:shn_x_preferred":[
        "\u1015\u1030\u1038\u1075\u1019\u103a\u1087\u104a \u101d\u1035\u1004\u103a\u1038"
    ],
    "name:slv_x_preferred":[
        "Bagan"
    ],
    "name:spa_x_preferred":[
        "Bagan"
    ],
    "name:srp_x_preferred":[
        "\u0411\u0430\u0433\u0430\u043d"
    ],
    "name:swe_x_preferred":[
        "Pagan"
    ],
    "name:tam_x_preferred":[
        "\u0baa\u0bbe\u0b95\u0ba9\u0bcd"
    ],
    "name:tgl_x_preferred":[
        "Bagan"
    ],
    "name:tha_x_preferred":[
        "\u0e1e\u0e38\u0e01\u0e32\u0e21"
    ],
    "name:tur_x_preferred":[
        "Bagan"
    ],
    "name:ukr_x_preferred":[
        "\u041f\u0430\u0433\u0430\u043d"
    ],
    "name:vie_x_preferred":[
        "Bagan"
    ],
    "name:war_x_preferred":[
        "Bagan"
    ],
    "wof:lang_x_official":[
        "ind"
    ],
    "wof:lang_x_spoken":[
        "ind",
        "eng"
    ],
    "wof:name":"Bagan",
    "wof:placetype":"locality"
},
  "geometry": {"coordinates":[98.9867,3.6486],"type":"Point"}
}