{
  "type": "Feature",
  "properties": {
    "gn:admin1_code":"11",
    "gn:asciiname":"Sungai Pinggan",
    "gn:country_code":"ID",
    "gn:dem":11,
    "gn:feature_class":"P",
    "gn:feature_code":"PPL",
    "gn:name":"Sungai Pinggan",
    "gn:population":0,
    "gn:timezone":"Asia/Pontianak",
    "iso:country":"ID",
    "name:ind_x_preferred":[
        "Sungai Pinggan"
    ],
    "wof:name":"Sungai Pinggan",
    "wof:placetype":"locality"
},
  "geometry": {"coordinates":[109.16696,0.5128],"type":"Point"}
}