{
  "type": "Feature",
  "properties": {
    "gn:admin1_code":"30.0",
    "gn:asciiname":"Pabuaran",
    "gn:country_code":"ID",
    "gn:dem":30,
    "gn:feature_class":"P",
    "gn:feature_code":"PPL",
    "gn:name":"Pabuaran",
    "gn:population":0,
    "gn:timezone":"Asia/Jakarta",
    "iso:country":"ID",
    "name:ind_x_preferred":[
        "Pabuaran"
    ],
    "name:und_x_variant":[
        "Paboearan",
        "Paboewaran",
        "Pabuwaran"
    ],
    "wof:lang_x_official":[
        "ind"
    ],
    "wof:lang_x_spoken":[
        "ind",
        "eng"
    ],
    "wof:name":"Pabuaran",
    "wof:placetype":"locality"
},
  "geometry": {"coordinates":[107.58722,-6.41056],"type":"Point"}
}