{
  "type": "Feature",
  "properties": {
    "gn:admin1_code":"18.0",
    "gn:asciiname":"Taemetani",
    "gn:country_code":"ID",
    "gn:dem":434,
    "gn:feature_class":"P",
    "gn:feature_code":"PPL",
    "gn:name":"Taemetani",
    "gn:population":0,
    "gn:timezone":"Asia/Makassar",
    "iso:country":"ID",
    "name:ind_x_preferred":[
        "Taemetani"
    ],
    "wof:name":"Taemetani",
    "wof:placetype":"locality"
},
  "geometry": {"coordinates":[124.5599,-9.9943],"type":"Point"}
}