{
  "type": "Feature",
  "properties": {
    "gn:admin1_code":"11.0",
    "gn:asciiname":"Pana",
    "gn:country_code":"ID",
    "gn:dem":229,
    "gn:feature_class":"P",
    "gn:feature_code":"PPL",
    "gn:name":"Pana",
    "gn:population":0,
    "gn:timezone":"Asia/Pontianak",
    "iso:country":"ID",
    "name:ceb_x_preferred":[
        "Pana"
    ],
    "name:deu_x_preferred":[
        "Pana"
    ],
    "name:fra_x_preferred":[
        "Pana"
    ],
    "name:ind_x_preferred":[
        "Pana"
    ],
    "name:ita_x_preferred":[
        "Pana"
    ],
    "name:nld_x_preferred":[
        "Pana"
    ],
    "name:pol_x_preferred":[
        "Pana"
    ],
    "name:rus_x_preferred":[
        "\u041f\u0430\u043d\u0430"
    ],
    "name:spa_x_preferred":[
        "Pana"
    ],
    "name:swe_x_preferred":[
        "Pana"
    ],
    "wof:lang_x_official":[
        "ind"
    ],
    "wof:lang_x_spoken":[
        "ind",
        "eng"
    ],
    "wof:name":"Pana",
    "wof:placetype":"locality"
},
  "geometry": {"coordinates":[110.66231000000001,0.16976],"type":"Point"}
}