{
  "type": "Feature",
  "properties": {
    "gn:country":"ID",
    "gn:fcode":"PPLA3",
    "gn:pop":0,
    "iso:country":"ID",
    "name:ind_x_preferred":[
        "Merakurak"
    ],
    "qs:name":"Merakurak",
    "qs:photos_9r":0,
    "qs:photos_sr":0,
    "qs:pop_sr":"0",
    "wof:lang_x_official":[
        "ind"
    ],
    "wof:lang_x_spoken":[
        "ind",
        "eng"
    ],
    "wof:name":"Merakurak",
    "wof:placetype":"locality",
    "wof:population":0
},
  "geometry": {"coordinates":[111.9863,-6.8783],"type":"Point"}
}