{
  "type": "Feature",
  "properties": {
    "gn:admin1_code":"38",
    "gn:asciiname":"Pancana",
    "gn:country_code":"ID",
    "gn:dem":22,
    "gn:feature_class":"P",
    "gn:feature_code":"PPL",
    "gn:name":"Pancana",
    "gn:population":0,
    "gn:timezone":"Asia/Makassar",
    "iso:country":"ID",
    "name:bcl_x_preferred":[
        "Pancana"
    ],
    "name:ind_x_preferred":[
        "Pancana"
    ],
    "name:pms_x_preferred":[
        "Lenga pancana"
    ],
    "name:swa_x_preferred":[
        "Kipancana"
    ],
    "name:tgl_x_preferred":[
        "Wikang Pancana"
    ],
    "wof:lang_x_official":[
        "ind"
    ],
    "wof:lang_x_spoken":[
        "ind",
        "eng"
    ],
    "wof:name":"Pancana",
    "wof:placetype":"locality"
},
  "geometry": {"coordinates":[119.4521,-5.2718],"type":"Point"}
}