{
  "type": "Feature",
  "properties": {
    "gn:admin1_code":"30",
    "gn:asciiname":"Cipadarangkung",
    "gn:country_code":"ID",
    "gn:dem":666,
    "gn:feature_class":"P",
    "gn:feature_code":"PPL",
    "gn:name":"Cipadarangkung",
    "gn:population":0,
    "gn:timezone":"Asia/Jakarta",
    "iso:country":"ID",
    "name:ind_x_preferred":[
        "Cipadarangkung"
    ],
    "name:und_x_variant":[
        "Tjipodoranggon",
        "Cipodoranggon"
    ],
    "wof:lang_x_official":[
        "ind"
    ],
    "wof:lang_x_spoken":[
        "ind",
        "eng"
    ],
    "wof:name":"Cipadarangkung",
    "wof:placetype":"locality"
},
  "geometry": {"coordinates":[107.72667,-6.9925],"type":"Point"}
}