{
  "type": "Feature",
  "properties": {
    "gn:admin1_code":"26",
    "gn:asciiname":"Dewan Pimpinan Tingkat Daerah",
    "gn:country_code":"ID",
    "gn:dem":18,
    "gn:feature_class":"P",
    "gn:feature_code":"PPL",
    "gn:name":"Dewan Pimpinan Tingkat Daerah",
    "gn:population":0,
    "gn:timezone":"Asia/Jakarta",
    "iso:country":"ID",
    "name:ind_x_preferred":[
        "Dewan Pimpinan Tingkat Daerah"
    ],
    "name:und_x_variant":[
        "DPTD"
    ],
    "wof:name":"Dewan Pimpinan Tingkat Daerah",
    "wof:placetype":"locality"
},
  "geometry": {"coordinates":[98.7148,3.622],"type":"Point"}
}