{
  "type": "Feature",
  "properties": {
    "gn:admin1_code":"17",
    "gn:asciiname":"Selek",
    "gn:country_code":"ID",
    "gn:dem":345,
    "gn:feature_class":"P",
    "gn:feature_code":"PPL",
    "gn:name":"Selek",
    "gn:population":0,
    "gn:timezone":"Asia/Makassar",
    "iso:country":"ID",
    "name:ind_x_preferred":[
        "Selek"
    ],
    "wof:name":"Selek",
    "wof:placetype":"locality"
},
  "geometry": {"coordinates":[116.38039999999999,-8.6528],"type":"Point"}
}