{
  "type": "Feature",
  "properties": {
    "gn:admin1_code":"0.0",
    "gn:asciiname":"Manui",
    "gn:cc2":"ID",
    "gn:country_code":"ID",
    "gn:dem":122,
    "gn:feature_class":"P",
    "gn:feature_code":"PPL",
    "gn:name":"Manui",
    "gn:population":0,
    "gn:timezone":"Asia/Makassar",
    "iso:country":"ID",
    "name:ceb_x_preferred":[
        "\u00cele Manui"
    ],
    "name:ell_x_preferred":[
        "\u039c\u03b1\u03bd\u03bf\u03cd\u03b9"
    ],
    "name:fra_x_preferred":[
        "Manui"
    ],
    "name:mrj_x_preferred":[
        "\u041c\u0430\u043d\u0443\u0438"
    ],
    "name:rus_x_preferred":[
        "\u041c\u0430\u043d\u0443\u0438"
    ],
    "name:spa_x_preferred":[
        "Manui"
    ],
    "name:tah_x_preferred":[
        "Manui"
    ],
    "name:und_x_variant":[
        "Manoei",
        "Manui"
    ],
    "wof:lang_x_official":[
        "ind"
    ],
    "wof:lang_x_spoken":[
        "ind",
        "eng"
    ],
    "wof:name":"Manui",
    "wof:placetype":"locality"
},
  "geometry": {"coordinates":[123.15000000000001,-3.58333],"type":"Point"}
}