{
  "type": "Feature",
  "properties": {
    "gn:admin1_code":"0.0",
    "gn:asciiname":"Manui",
    "gn:cc2":"ID",
    "gn:country_code":"ID",
    "gn:dem":122,
    "gn:feature_class":"P",
    "gn:feature_code":"PPL",
    "gn:name":"Manui",
    "gn:population":0,
    "gn:timezone":"Asia/Makassar",
    "iso:country":"ID",
    "name:und_x_variant":[
        "Manoei",
        "Manui"
    ],
    "wof:name":"Manui",
    "wof:placetype":"locality"
},
  "geometry": {"coordinates":[123.15000000000001,-3.58333],"type":"Point"}
}