{
  "type": "Feature",
  "properties": {
    "gn:admin1_code":"33.0",
    "gn:asciiname":"Kadumelati",
    "gn:country_code":"ID",
    "gn:dem":56,
    "gn:feature_class":"P",
    "gn:feature_code":"PPLA4",
    "gn:name":"Kadumelati",
    "gn:population":0,
    "gn:timezone":"Asia/Jakarta",
    "iso:country":"ID",
    "name:ind_x_preferred":[
        "Kadumelati"
    ],
    "wof:name":"Kadumelati",
    "wof:placetype":"locality"
},
  "geometry": {"coordinates":[105.9212,-6.5056],"type":"Point"}
}