{
  "type": "Feature",
  "properties": {
    "gn:admin1_code":"33.0",
    "gn:asciiname":"Tamaga",
    "gn:country_code":"ID",
    "gn:dem":192,
    "gn:feature_class":"P",
    "gn:feature_code":"PPL",
    "gn:name":"Tamaga",
    "gn:population":0,
    "gn:timezone":"Asia/Jakarta",
    "iso:country":"ID",
    "name:ind_x_preferred":[
        "Tamaga"
    ],
    "name:und_x_variant":[
        "Tambaga"
    ],
    "wof:name":"Tamaga",
    "wof:placetype":"locality"
},
  "geometry": {"coordinates":[106.1687,-6.5396],"type":"Point"}
}