{
  "type": "Feature",
  "properties": {
    "gn:admin1_code":"30",
    "gn:asciiname":"Dukuheurih Kaler",
    "gn:country_code":"ID",
    "gn:dem":49,
    "gn:feature_class":"P",
    "gn:feature_code":"PPL",
    "gn:name":"Dukuheurih Kaler",
    "gn:population":0,
    "gn:timezone":"Asia/Jakarta",
    "iso:country":"ID",
    "name:ind_x_preferred":[
        "Dukuheurih Kaler"
    ],
    "wof:name":"Dukuheurih Kaler",
    "wof:placetype":"locality"
},
  "geometry": {"coordinates":[108.18111,-6.77333],"type":"Point"}
}