{
  "type": "Feature",
  "properties": {
    "gn:admin1_code":"30",
    "gn:asciiname":"Sempurbubulak",
    "gn:cc2":"ID",
    "gn:country_code":"ID",
    "gn:dem":39,
    "gn:feature_class":"P",
    "gn:feature_code":"PPL",
    "gn:name":"Sempurbubulak",
    "gn:population":0,
    "gn:timezone":"Asia/Jakarta",
    "iso:country":"ID",
    "name:und_x_variant":[
        "Sempur Dua",
        "Sempur 2",
        "Sempurbubulak"
    ],
    "wof:name":"Sempurbubulak",
    "wof:placetype":"locality"
},
  "geometry": {"coordinates":[106.50917,-6.26167],"type":"Point"}
}