{
  "type": "Feature",
  "properties": {
    "gn:admin1_code":"30.0",
    "gn:asciiname":"Citatah",
    "gn:country_code":"ID",
    "gn:dem":175,
    "gn:feature_class":"P",
    "gn:feature_code":"PPL",
    "gn:name":"Citatah",
    "gn:population":0,
    "gn:timezone":"Asia/Jakarta",
    "iso:country":"ID",
    "name:ind_x_preferred":[
        "Citatah"
    ],
    "wof:name":"Citatah",
    "wof:placetype":"locality"
},
  "geometry": {"coordinates":[106.87609999999999,-7.3383],"type":"Point"}
}