{
  "type": "Feature",
  "properties": {
    "gn:admin1_code":"38.0",
    "gn:asciiname":"Simoma",
    "gn:country_code":"ID",
    "gn:dem":21,
    "gn:feature_class":"P",
    "gn:feature_code":"PPL",
    "gn:name":"Simoma",
    "gn:population":0,
    "gn:timezone":"Asia/Makassar",
    "iso:country":"ID",
    "name:ind_x_preferred":[
        "Simoma"
    ],
    "name:nld_x_preferred":[
        "Simoma"
    ],
    "wof:name":"Simoma",
    "wof:placetype":"locality"
},
  "geometry": {"coordinates":[120.4064,-3.6253],"type":"Point"}
}