{
  "type": "Feature",
  "properties": {
    "gn:admin1_code":"33",
    "gn:asciiname":"Ciranggon",
    "gn:country_code":"ID",
    "gn:dem":15,
    "gn:feature_class":"P",
    "gn:feature_code":"PPL",
    "gn:name":"Ciranggon",
    "gn:population":0,
    "gn:timezone":"Asia/Jakarta",
    "iso:country":"ID",
    "name:ind_x_preferred":[
        "Ciranggon"
    ],
    "wof:name":"Ciranggon",
    "wof:placetype":"locality"
},
  "geometry": {"coordinates":[106.0881,-5.9696],"type":"Point"}
}