{
  "type": "Feature",
  "properties": {
    "gn:admin1_code":"8.0",
    "gn:asciiname":"Curahnongko",
    "gn:country_code":"ID",
    "gn:dem":44,
    "gn:feature_class":"P",
    "gn:feature_code":"PPLA4",
    "gn:name":"Curahnongko",
    "gn:population":0,
    "gn:timezone":"Asia/Jakarta",
    "iso:country":"ID",
    "name:und_x_variant":[
        "Tjurahnongko",
        "Curahnongko",
        "Tjoerahnangka"
    ],
    "wof:name":"Curahnongko",
    "wof:placetype":"locality"
},
  "geometry": {"coordinates":[113.7346,-8.4007],"type":"Point"}
}