{
  "type": "Feature",
  "properties": {
    "gn:admin1_code":"30.0",
    "gn:asciiname":"Lebakayu",
    "gn:country_code":"ID",
    "gn:dem":497,
    "gn:feature_class":"P",
    "gn:feature_code":"PPL",
    "gn:name":"Lebakayu",
    "gn:population":0,
    "gn:timezone":"Asia/Jakarta",
    "iso:country":"ID",
    "name:ind_x_preferred":[
        "Lebakayu"
    ],
    "name:und_x_variant":[
        "Lebakajoe"
    ],
    "wof:name":"Lebakayu",
    "wof:placetype":"locality"
},
  "geometry": {"coordinates":[108.4062,-7.1527],"type":"Point"}
}