{
  "type": "Feature",
  "properties": {
    "gn:admin1_code":"30",
    "gn:asciiname":"Cibelenok",
    "gn:country_code":"ID",
    "gn:dem":592,
    "gn:feature_class":"P",
    "gn:feature_code":"PPL",
    "gn:name":"Cibelenok",
    "gn:population":0,
    "gn:timezone":"Asia/Jakarta",
    "iso:country":"ID",
    "name:ind_x_preferred":[
        "Cibelenok"
    ],
    "name:und_x_variant":[
        "Cibelendo"
    ],
    "wof:lang_x_official":[
        "ind"
    ],
    "wof:lang_x_spoken":[
        "ind",
        "eng"
    ],
    "wof:name":"Cibelenok",
    "wof:placetype":"locality"
},
  "geometry": {"coordinates":[107.02139,-6.94306],"type":"Point"}
}