{
  "type": "Feature",
  "properties": {
    "gn:admin1_code":"8",
    "gn:asciiname":"Cungking",
    "gn:country_code":"ID",
    "gn:dem":57,
    "gn:feature_class":"P",
    "gn:feature_code":"PPLA4",
    "gn:name":"Cungking",
    "gn:population":0,
    "gn:timezone":"Asia/Jakarta",
    "iso:country":"ID",
    "name:ind_x_preferred":[
        "Cungking"
    ],
    "wof:lang_x_official":[
        "ind"
    ],
    "wof:lang_x_spoken":[
        "ind",
        "eng"
    ],
    "wof:name":"Cungking",
    "wof:placetype":"locality"
},
  "geometry": {"coordinates":[114.35429999999999,-8.217],"type":"Point"}
}