{
  "type": "Feature",
  "properties": {
    "gn:admin1_code":"30",
    "gn:asciiname":"Citatah",
    "gn:cc2":"ID",
    "gn:country_code":"ID",
    "gn:dem":78,
    "gn:feature_class":"P",
    "gn:feature_code":"PPL",
    "gn:name":"Citatah",
    "gn:population":0,
    "gn:timezone":"Asia/Jakarta",
    "iso:country":"ID",
    "name:und_x_variant":[
        "Pabuwarantjitatah",
        "Pabuwarancitatah",
        "Citatah"
    ],
    "wof:name":"Citatah",
    "wof:placetype":"locality"
},
  "geometry": {"coordinates":[106.50055999999999,-6.4275],"type":"Point"}
}