{
  "type": "Feature",
  "properties": {
    "gn:admin1_code":"30.0",
    "gn:asciiname":"Gunungsubang",
    "gn:country_code":"ID",
    "gn:dem":340,
    "gn:feature_class":"P",
    "gn:feature_code":"PPLA4",
    "gn:name":"Gunungsubang",
    "gn:population":0,
    "gn:timezone":"Asia/Jakarta",
    "iso:country":"ID",
    "name:ind_x_preferred":[
        "Gunungsubang"
    ],
    "name:und_x_variant":[
        "Goenoengsoebang"
    ],
    "wof:lang_x_official":[
        "ind"
    ],
    "wof:lang_x_spoken":[
        "ind",
        "eng"
    ],
    "wof:name":"Gunungsubang",
    "wof:placetype":"locality"
},
  "geometry": {"coordinates":[108.1949,-7.3716],"type":"Point"}
}