{
  "type": "Feature",
  "properties": {
    "gn:admin1_code":"07",
    "gn:asciiname":"Seru",
    "gn:country_code":"ID",
    "gn:dem":586,
    "gn:feature_class":"P",
    "gn:feature_code":"PPL",
    "gn:name":"Seru",
    "gn:population":0,
    "gn:timezone":"Asia/Jakarta",
    "iso:country":"ID",
    "name:fra_x_preferred":[
        "Seru"
    ],
    "name:zho_x_preferred":[
        "\u585e\u9b6f"
    ],
    "wof:name":"Seru",
    "wof:placetype":"locality"
},
  "geometry": {"coordinates":[110.56638999999998,-7.525],"type":"Point"}
}