{
  "type": "Feature",
  "properties": {
    "gn:admin1_code":"18.0",
    "gn:asciiname":"Lumbukaju",
    "gn:country_code":"ID",
    "gn:dem":68,
    "gn:feature_class":"P",
    "gn:feature_code":"PPL",
    "gn:name":"Lumbukaju",
    "gn:population":0,
    "gn:timezone":"Asia/Makassar",
    "iso:country":"ID",
    "name:ind_x_preferred":[
        "Lumbukaju"
    ],
    "wof:name":"Lumbukaju",
    "wof:placetype":"locality"
},
  "geometry": {"coordinates":[120.2687,-10.1899],"type":"Point"}
}