{
  "type": "Feature",
  "properties": {
    "gn:admin1_code":"18.0",
    "gn:asciiname":"Nunsena",
    "gn:country_code":"ID",
    "gn:dem":468,
    "gn:feature_class":"P",
    "gn:feature_code":"PPL",
    "gn:name":"Nunsena",
    "gn:population":0,
    "gn:timezone":"Asia/Makassar",
    "iso:country":"ID",
    "name:ind_x_preferred":[
        "Nunsena"
    ],
    "wof:name":"Nunsena",
    "wof:placetype":"locality"
},
  "geometry": {"coordinates":[124.58410000000001,-9.9537],"type":"Point"}
}