{
  "type": "Feature",
  "properties": {
    "gn:admin1_code":"13.0",
    "gn:asciiname":"Tjandjang",
    "gn:country_code":"ID",
    "gn:dem":10,
    "gn:feature_class":"P",
    "gn:feature_code":"PPL",
    "gn:name":"Tjandjang",
    "gn:population":0,
    "gn:timezone":"Asia/Pontianak",
    "iso:country":"ID",
    "name:ind_x_preferred":[
        "Tjandjang"
    ],
    "wof:name":"Tjandjang",
    "wof:placetype":"locality"
},
  "geometry": {"coordinates":[113.43413,-2.31766],"type":"Point"}
}