{
  "type": "Feature",
  "properties": {
    "gn:admin1_code":"11",
    "gn:asciiname":"Biyawak",
    "gn:country_code":"ID",
    "gn:dem":79,
    "gn:feature_class":"P",
    "gn:feature_code":"PPL",
    "gn:name":"Biyawak",
    "gn:population":0,
    "gn:timezone":"Asia/Pontianak",
    "iso:country":"ID",
    "name:ind_x_preferred":[
        "Biyawak"
    ],
    "wof:name":"Biyawak",
    "wof:placetype":"locality"
},
  "geometry": {"coordinates":[110.71575,-0.17063],"type":"Point"}
}