{
  "type": "Feature",
  "properties": {
    "gn:admin1_code":"21.0",
    "gn:asciiname":"Paneki",
    "gn:country_code":"ID",
    "gn:dem":177,
    "gn:feature_class":"P",
    "gn:feature_code":"PPL",
    "gn:name":"Paneki",
    "gn:population":0,
    "gn:timezone":"Asia/Makassar",
    "iso:country":"ID",
    "name:ind_x_preferred":[
        "Paneki"
    ],
    "wof:name":"Paneki",
    "wof:placetype":"locality"
},
  "geometry": {"coordinates":[119.955,-0.9747],"type":"Point"}
}