{
  "type": "Feature",
  "properties": {
    "gn:admin1_code":"30",
    "gn:asciiname":"Dusunbaru",
    "gn:country_code":"ID",
    "gn:dem":10,
    "gn:feature_class":"P",
    "gn:feature_code":"PPL",
    "gn:name":"Dusunbaru",
    "gn:population":0,
    "gn:timezone":"Asia/Jakarta",
    "iso:country":"ID",
    "name:ind_x_preferred":[
        "Dusunbaru"
    ],
    "wof:name":"Dusunbaru",
    "wof:placetype":"locality"
},
  "geometry": {"coordinates":[107.82193999999998,-6.28778],"type":"Point"}
}