{
  "type": "Feature",
  "properties": {
    "gn:admin1_code":"7.0",
    "gn:asciiname":"Silontar",
    "gn:country_code":"ID",
    "gn:dem":690,
    "gn:feature_class":"P",
    "gn:feature_code":"PPL",
    "gn:name":"Silontar",
    "gn:population":0,
    "gn:timezone":"Asia/Jakarta",
    "iso:country":"ID",
    "name:ind_x_preferred":[
        "Silontar"
    ],
    "wof:name":"Silontar",
    "wof:placetype":"locality"
},
  "geometry": {"coordinates":[109.06083,-7.23861],"type":"Point"}
}