{
  "type": "Feature",
  "properties": {
    "gn:admin1_code":"05",
    "gn:asciiname":"Rano",
    "gn:country_code":"ID",
    "gn:dem":14,
    "gn:feature_class":"P",
    "gn:feature_code":"PPL",
    "gn:name":"Rano",
    "gn:population":0,
    "gn:timezone":"Asia/Jakarta",
    "iso:country":"ID",
    "name:ind_x_preferred":[
        "Rano"
    ],
    "wof:name":"Rano",
    "wof:placetype":"locality"
},
  "geometry": {"coordinates":[103.77146999999999,-1.17894],"type":"Point"}
}