{
  "type": "Feature",
  "properties": {
    "gn:admin1_code":"33",
    "gn:asciiname":"Calingcing",
    "gn:country_code":"ID",
    "gn:dem":21,
    "gn:feature_class":"P",
    "gn:feature_code":"PPL",
    "gn:name":"Calingcing",
    "gn:population":0,
    "gn:timezone":"Asia/Jakarta",
    "iso:country":"ID",
    "name:ind_x_preferred":[
        "Calingcing"
    ],
    "name:und_x_variant":[
        "Tjalingtjing"
    ],
    "wof:name":"Calingcing",
    "wof:placetype":"locality"
},
  "geometry": {"coordinates":[106.2925,-6.2779],"type":"Point"}
}