{
  "type": "Feature",
  "properties": {
    "gn:admin1_code":"30.0",
    "gn:asciiname":"Sagarahiang",
    "gn:country_code":"ID",
    "gn:dem":925,
    "gn:feature_class":"P",
    "gn:feature_code":"PPL",
    "gn:name":"Sagarahiang",
    "gn:population":0,
    "gn:timezone":"Asia/Jakarta",
    "iso:country":"ID",
    "name:ind_x_preferred":[
        "Sagarahiang"
    ],
    "name:und_x_variant":[
        "Sagrahiang"
    ],
    "wof:name":"Sagarahiang",
    "wof:placetype":"locality"
},
  "geometry": {"coordinates":[108.42028000000001,-6.96944],"type":"Point"}
}