{
  "type": "Feature",
  "properties": {
    "gn:admin1_code":"30",
    "gn:asciiname":"Compreng",
    "gn:country_code":"ID",
    "gn:dem":23,
    "gn:feature_class":"P",
    "gn:feature_code":"PPL",
    "gn:name":"Compreng",
    "gn:population":0,
    "gn:timezone":"Asia/Jakarta",
    "iso:country":"ID",
    "name:ind_x_preferred":[
        "Compreng"
    ],
    "wof:name":"Compreng",
    "wof:placetype":"locality"
},
  "geometry": {"coordinates":[107.88249999999999,-6.415],"type":"Point"}
}