{
  "type": "Feature",
  "properties": {
    "gn:admin1_code":"26",
    "gn:asciiname":"Bukit Gantung",
    "gn:country_code":"ID",
    "gn:dem":11,
    "gn:feature_class":"P",
    "gn:feature_code":"PPL",
    "gn:name":"Bukit Gantung",
    "gn:population":0,
    "gn:timezone":"Asia/Jakarta",
    "iso:country":"ID",
    "name:ind_x_preferred":[
        "Bukit Gantung"
    ],
    "wof:name":"Bukit Gantung",
    "wof:placetype":"locality"
},
  "geometry": {"coordinates":[98.3717,3.7666],"type":"Point"}
}