{
  "type": "Feature",
  "properties": {
    "gn:admin1_code":"33.0",
    "gn:asciiname":"Simayeng",
    "gn:country_code":"ID",
    "gn:dem":238,
    "gn:feature_class":"P",
    "gn:feature_code":"PPL",
    "gn:name":"Simayeng",
    "gn:population":0,
    "gn:timezone":"Asia/Jakarta",
    "iso:country":"ID",
    "name:ind_x_preferred":[
        "Simayeng"
    ],
    "wof:name":"Simayeng",
    "wof:placetype":"locality"
},
  "geometry": {"coordinates":[106.0949,-6.2172],"type":"Point"}
}