{
  "type": "Feature",
  "properties": {
    "gn:admin1_code":"8",
    "gn:asciiname":"Bengloa",
    "gn:country_code":"ID",
    "gn:dem":35,
    "gn:feature_class":"P",
    "gn:feature_code":"PPL",
    "gn:name":"Bengloa",
    "gn:population":0,
    "gn:timezone":"Asia/Jakarta",
    "iso:country":"ID",
    "name:ind_x_preferred":[
        "Bengloa"
    ],
    "wof:name":"Bengloa",
    "wof:placetype":"locality"
},
  "geometry": {"coordinates":[112.7334,-7.1599],"type":"Point"}
}