{
  "type": "Feature",
  "properties": {
    "gn:admin1_code":"18.0",
    "gn:asciiname":"Puuwoo",
    "gn:country_code":"ID",
    "gn:dem":591,
    "gn:feature_class":"P",
    "gn:feature_code":"PPL",
    "gn:name":"Puuwoo",
    "gn:population":0,
    "gn:timezone":"Asia/Makassar",
    "iso:country":"ID",
    "name:ind_x_preferred":[
        "Puuwoo"
    ],
    "wof:name":"Puuwoo",
    "wof:placetype":"locality"
},
  "geometry": {"coordinates":[119.2821,-9.5493],"type":"Point"}
}