{
  "type": "Feature",
  "properties": {
    "gn:admin1_code":"30.0",
    "gn:asciiname":"Santosa",
    "gn:country_code":"ID",
    "gn:dem":1631,
    "gn:feature_class":"P",
    "gn:feature_code":"PPLA4",
    "gn:name":"Santosa",
    "gn:population":0,
    "gn:timezone":"Asia/Jakarta",
    "iso:country":"ID",
    "name:ind_x_preferred":[
        "Santosa"
    ],
    "wof:name":"Santosa",
    "wof:placetype":"locality"
},
  "geometry": {"coordinates":[107.6388,-7.2537],"type":"Point"}
}