{
  "type": "Feature",
  "properties": {
    "gn:country":"ID",
    "gn:fcode":"ADM4",
    "gn:pop":0,
    "iso:country":"ID",
    "name:ind_x_preferred":[
        "Kelurahan Pandanwangi"
    ],
    "name:unk_x_variant":[
        "Pandanwangi"
    ],
    "qs:name":"Kelurahan Pandanwangi",
    "qs:photos_9r":0,
    "qs:photos_sr":0,
    "qs:pop_sr":"0",
    "wof:name":"Kelurahan Pandanwangi",
    "wof:placetype":"localadmin",
    "wof:population":0
},
  "geometry": {"coordinates":[112.65900000000001,-7.9513],"type":"Point"}
}