{
  "type": "Feature",
  "properties": {
    "gn:admin1_code":"18.0",
    "gn:asciiname":"Nangka",
    "gn:country_code":"ID",
    "gn:dem":19,
    "gn:feature_class":"P",
    "gn:feature_code":"PPL",
    "gn:name":"Nangka",
    "gn:population":0,
    "gn:timezone":"Asia/Makassar",
    "iso:country":"ID",
    "name:ceb_x_preferred":[
        "Nangka"
    ],
    "name:ind_x_preferred":[
        "Nangka"
    ],
    "name:msa_x_preferred":[
        "Nangka"
    ],
    "name:swe_x_preferred":[
        "Nangka"
    ],
    "wof:lang_x_official":[
        "ind"
    ],
    "wof:lang_x_spoken":[
        "ind",
        "eng"
    ],
    "wof:name":"Nangka",
    "wof:placetype":"locality"
},
  "geometry": {"coordinates":[120.19540000000001,-8.3731],"type":"Point"}
}