{
  "type": "Feature",
  "properties": {
    "gn:admin1_code":"30",
    "gn:asciiname":"Babakansetia",
    "gn:country_code":"ID",
    "gn:dem":684,
    "gn:feature_class":"P",
    "gn:feature_code":"PPL",
    "gn:name":"Babakansetia",
    "gn:population":0,
    "gn:timezone":"Asia/Jakarta",
    "iso:country":"ID",
    "name:ind_x_preferred":[
        "Babakansetia"
    ],
    "wof:name":"Babakansetia",
    "wof:placetype":"locality"
},
  "geometry": {"coordinates":[107.80370000000001,-7.0269],"type":"Point"}
}