{
  "type": "Feature",
  "properties": {
    "gn:admin1_code":"26",
    "gn:asciiname":"Siganjang-ganjang",
    "gn:country_code":"ID",
    "gn:dem":930,
    "gn:feature_class":"P",
    "gn:feature_code":"PPL",
    "gn:name":"Siganjang-ganjang",
    "gn:population":0,
    "gn:timezone":"Asia/Jakarta",
    "iso:country":"ID",
    "name:ind_x_preferred":[
        "Siganjang-ganjang"
    ],
    "wof:name":"Siganjang-ganjang",
    "wof:placetype":"locality"
},
  "geometry": {"coordinates":[99.0716,2.4071],"type":"Point"}
}