{
  "type": "Feature",
  "properties": {
    "gn:admin1_code":"21",
    "gn:asciiname":"Palele",
    "gn:country_code":"ID",
    "gn:dem":19,
    "gn:feature_class":"P",
    "gn:feature_code":"PPL",
    "gn:name":"Palele",
    "gn:population":0,
    "gn:timezone":"Asia/Makassar",
    "iso:country":"ID",
    "name:ind_x_preferred":[
        "Palele"
    ],
    "wof:name":"Palele",
    "wof:placetype":"locality"
},
  "geometry": {"coordinates":[120.06610000000001,0.7037],"type":"Point"}
}