{
  "type": "Feature",
  "properties": {
    "gn:admin1_code":"30",
    "gn:asciiname":"Ciputih",
    "gn:cc2":"ID",
    "gn:country_code":"ID",
    "gn:dem":740,
    "gn:feature_class":"P",
    "gn:feature_code":"PPL",
    "gn:name":"Ciputih",
    "gn:population":0,
    "gn:timezone":"Asia/Jakarta",
    "iso:country":"ID",
    "name:und_x_variant":[
        "Tjiputih",
        "Ciputih"
    ],
    "wof:name":"Ciputih",
    "wof:placetype":"locality"
},
  "geometry": {"coordinates":[107.51667,-7.03694],"type":"Point"}
}