{
  "type": "Feature",
  "properties": {
    "gn:admin1_code":"30",
    "gn:asciiname":"Babakan Delapan",
    "gn:cc2":"ID",
    "gn:country_code":"ID",
    "gn:dem":114,
    "gn:feature_class":"P",
    "gn:feature_code":"PPL",
    "gn:name":"Babakan Delapan",
    "gn:population":0,
    "gn:timezone":"Asia/Jakarta",
    "iso:country":"ID",
    "name:und_x_variant":[
        "Babakan 8",
        "Babakan Delapan"
    ],
    "wof:name":"Babakan Delapan",
    "wof:placetype":"locality"
},
  "geometry": {"coordinates":[106.89417,-6.45194],"type":"Point"}
}