{
  "type": "Feature",
  "properties": {
    "gn:admin1_code":"11",
    "gn:asciiname":"Sungaibetung",
    "gn:country_code":"ID",
    "gn:dem":62,
    "gn:feature_class":"P",
    "gn:feature_code":"PPL",
    "gn:name":"Sungaibetung",
    "gn:population":0,
    "gn:timezone":"Asia/Pontianak",
    "iso:country":"ID",
    "name:ind_x_preferred":[
        "Sungaibetung"
    ],
    "wof:lang_x_official":[
        "ind"
    ],
    "wof:lang_x_spoken":[
        "ind",
        "eng"
    ],
    "wof:name":"Sungaibetung",
    "wof:placetype":"locality"
},
  "geometry": {"coordinates":[109.37965,0.81478],"type":"Point"}
}