{
  "type": "Feature",
  "properties": {
    "gn:admin1_code":"8",
    "gn:asciiname":"Ngebrugan",
    "gn:country_code":"ID",
    "gn:dem":48,
    "gn:feature_class":"P",
    "gn:feature_code":"PPL",
    "gn:name":"Ngebrugan",
    "gn:population":0,
    "gn:timezone":"Asia/Jakarta",
    "iso:country":"ID",
    "name:ind_x_preferred":[
        "Ngebrugan"
    ],
    "wof:name":"Ngebrugan",
    "wof:placetype":"locality"
},
  "geometry": {"coordinates":[112.0694,-7.6339],"type":"Point"}
}