{
  "type": "Feature",
  "properties": {
    "gn:admin1_code":"30",
    "gn:asciiname":"Leuwilarang",
    "gn:country_code":"ID",
    "gn:dem":1052,
    "gn:feature_class":"P",
    "gn:feature_code":"PPL",
    "gn:name":"Leuwilarang",
    "gn:population":0,
    "gn:timezone":"Asia/Jakarta",
    "iso:country":"ID",
    "name:ind_x_preferred":[
        "Leuwilarang"
    ],
    "name:und_x_variant":[
        "Leuwilarangan"
    ],
    "wof:lang_x_official":[
        "ind"
    ],
    "wof:lang_x_spoken":[
        "ind",
        "eng"
    ],
    "wof:name":"Leuwilarang",
    "wof:placetype":"locality"
},
  "geometry": {"coordinates":[107.318,-7.0282],"type":"Point"}
}