{
  "type": "Feature",
  "properties": {
    "gn:admin1_code":"8.0",
    "gn:asciiname":"Dodol",
    "gn:country_code":"ID",
    "gn:dem":192,
    "gn:feature_class":"P",
    "gn:feature_code":"PPL",
    "gn:name":"Dodol",
    "gn:population":0,
    "gn:timezone":"Asia/Jakarta",
    "iso:country":"ID",
    "name:hye_x_preferred":[
        "\u0534\u0578\u0564\u0578\u056c"
    ],
    "name:ind_x_preferred":[
        "Dodol"
    ],
    "name:jav_x_preferred":[
        "Jenang"
    ],
    "name:msa_x_preferred":[
        "Dodol"
    ],
    "name:pan_x_preferred":[
        "\u0a26\u0a4b\u0a26\u0a4b\u0a32"
    ],
    "name:rus_x_preferred":[
        "\u0414\u043e\u0434\u043e\u043b"
    ],
    "name:sun_x_preferred":[
        "Dodol"
    ],
    "name:tha_x_preferred":[
        "\u0e01\u0e30\u0e25\u0e30\u0e41\u0e21"
    ],
    "name:ukr_x_preferred":[
        "\u0414\u043e\u0434\u043e\u043b"
    ],
    "wof:name":"Dodol",
    "wof:placetype":"locality"
},
  "geometry": {"coordinates":[111.88679999999999,-7.4238],"type":"Point"}
}