{
  "type": "Feature",
  "properties": {
    "gn:admin1_code":"30",
    "gn:asciiname":"Dusun Tiga",
    "gn:country_code":"ID",
    "gn:dem":4,
    "gn:feature_class":"P",
    "gn:feature_code":"PPL",
    "gn:name":"Dusun Tiga",
    "gn:population":0,
    "gn:timezone":"Asia/Jakarta",
    "iso:country":"ID",
    "name:ind_x_preferred":[
        "Dusun Tiga"
    ],
    "wof:name":"Dusun Tiga",
    "wof:placetype":"locality"
},
  "geometry": {"coordinates":[108.45028000000001,-6.61944],"type":"Point"}
}