{
  "type": "Feature",
  "properties": {
    "gn:admin1_code":"18.0",
    "gn:asciiname":"Karabawatu",
    "gn:country_code":"ID",
    "gn:dem":377,
    "gn:feature_class":"P",
    "gn:feature_code":"PPL",
    "gn:name":"Karabawatu",
    "gn:population":0,
    "gn:timezone":"Asia/Makassar",
    "iso:country":"ID",
    "name:ind_x_preferred":[
        "Karabawatu"
    ],
    "wof:name":"Karabawatu",
    "wof:placetype":"locality"
},
  "geometry": {"coordinates":[119.48480000000001,-9.5268],"type":"Point"}
}