{
  "type": "Feature",
  "properties": {
    "gn:admin1_code":"18.0",
    "gn:asciiname":"Sufalaut",
    "gn:country_code":"ID",
    "gn:dem":175,
    "gn:feature_class":"P",
    "gn:feature_code":"PPL",
    "gn:name":"Sufalaut",
    "gn:population":0,
    "gn:timezone":"Asia/Makassar",
    "iso:country":"ID",
    "name:ind_x_preferred":[
        "Sufalaut"
    ],
    "wof:name":"Sufalaut",
    "wof:placetype":"locality"
},
  "geometry": {"coordinates":[124.7242,-9.7374],"type":"Point"}
}