{
  "type": "Feature",
  "properties": {
    "gn:admin1_code":"33",
    "gn:asciiname":"Manglid",
    "gn:country_code":"ID",
    "gn:dem":272,
    "gn:feature_class":"P",
    "gn:feature_code":"PPL",
    "gn:name":"Manglid",
    "gn:population":0,
    "gn:timezone":"Asia/Jakarta",
    "iso:country":"ID",
    "name:ind_x_preferred":[
        "Manglid"
    ],
    "wof:name":"Manglid",
    "wof:placetype":"locality"
},
  "geometry": {"coordinates":[106.0472,-5.9411],"type":"Point"}
}