{
  "type": "Feature",
  "properties": {
    "gn:admin1_code":"26",
    "gn:asciiname":"Pondok Pulau Gambar",
    "gn:country_code":"ID",
    "gn:dem":39,
    "gn:feature_class":"P",
    "gn:feature_code":"PPL",
    "gn:name":"Pondok Pulau Gambar",
    "gn:population":0,
    "gn:timezone":"Asia/Jakarta",
    "iso:country":"ID",
    "name:ind_x_preferred":[
        "Pondok Pulau Gambar"
    ],
    "wof:name":"Pondok Pulau Gambar",
    "wof:placetype":"locality"
},
  "geometry": {"coordinates":[98.9246,3.4316],"type":"Point"}
}