{
  "type": "Feature",
  "properties": {
    "gn:admin1_code":"34.0",
    "gn:asciiname":"Hungayokiki",
    "gn:country_code":"ID",
    "gn:dem":4,
    "gn:feature_class":"P",
    "gn:feature_code":"PPL",
    "gn:name":"Hungayokiki",
    "gn:population":0,
    "gn:timezone":"Asia/Makassar",
    "iso:country":"ID",
    "name:ind_x_preferred":[
        "Hungayokiki"
    ],
    "wof:name":"Hungayokiki",
    "wof:placetype":"locality"
},
  "geometry": {"coordinates":[123.1525,0.4097],"type":"Point"}
}