{
  "type": "Feature",
  "properties": {
    "gn:admin1_code":"7.0",
    "gn:asciiname":"Jagan",
    "gn:country_code":"ID",
    "gn:dem":278,
    "gn:feature_class":"P",
    "gn:feature_code":"PPL",
    "gn:name":"Jagan",
    "gn:population":0,
    "gn:timezone":"Asia/Jakarta",
    "iso:country":"ID",
    "name:hye_x_preferred":[
        "\u054b\u0561\u0563\u0561\u0576"
    ],
    "name:tam_x_preferred":[
        "\u0b9c\u0bc6\u0b95\u0ba9\u0bcd"
    ],
    "wof:name":"Jagan",
    "wof:placetype":"locality"
},
  "geometry": {"coordinates":[110.21250000000001,-7.56889],"type":"Point"}
}