{
  "type": "Feature",
  "properties": {
    "gn:admin1_code":"7",
    "gn:asciiname":"Jogoloyo Kidul",
    "gn:country_code":"ID",
    "gn:dem":7,
    "gn:feature_class":"P",
    "gn:feature_code":"PPL",
    "gn:name":"Jogoloyo Kidul",
    "gn:population":0,
    "gn:timezone":"Asia/Jakarta",
    "iso:country":"ID",
    "name:ind_x_preferred":[
        "Jogoloyo Kidul"
    ],
    "wof:name":"Jogoloyo Kidul",
    "wof:placetype":"locality"
},
  "geometry": {"coordinates":[110.6339,-6.9135],"type":"Point"}
}