{
  "type": "Feature",
  "properties": {
    "gn:country":"ID",
    "gn:fcode":"ADM3",
    "gn:pop":0,
    "iso:country":"ID",
    "name:eng_x_preferred":[
        "Districts of Central Java"
    ],
    "name:ind_x_preferred":[
        "Kecamatan Tegal Timur"
    ],
    "name:unk_x_variant":[
        "Tegal Timur"
    ],
    "qs:name":"Kecamatan Tegal Timur",
    "qs:photos_9r":0,
    "qs:photos_sr":0,
    "qs:pop_sr":"0",
    "wd:wordcount":1175,
    "wof:lang_x_official":[
        "ind"
    ],
    "wof:lang_x_spoken":[
        "ind",
        "eng"
    ],
    "wof:name":"Kecamatan Tegal Timur",
    "wof:placetype":"localadmin",
    "wof:population":0
},
  "geometry": {"coordinates":[109.143,-6.8645],"type":"Point"}
}