{
  "type": "Feature",
  "properties": {
    "gn:admin1_code":"30",
    "gn:asciiname":"Bojongloa Dua",
    "gn:cc2":"ID",
    "gn:country_code":"ID",
    "gn:dem":703,
    "gn:feature_class":"P",
    "gn:feature_code":"PPL",
    "gn:name":"Bojongloa Dua",
    "gn:population":0,
    "gn:timezone":"Asia/Jakarta",
    "iso:country":"ID",
    "name:und_x_variant":[
        "Bodjongloa 2",
        "Bojongloa Dua"
    ],
    "wof:name":"Bojongloa Dua",
    "wof:placetype":"locality"
},
  "geometry": {"coordinates":[107.59444000000001,-6.92611],"type":"Point"}
}