{
  "type": "Feature",
  "properties": {
    "gn:admin1_code":"18",
    "gn:asciiname":"Kalumbang",
    "gn:country_code":"ID",
    "gn:dem":411,
    "gn:feature_class":"P",
    "gn:feature_code":"PPL",
    "gn:name":"Kalumbang",
    "gn:population":0,
    "gn:timezone":"Asia/Makassar",
    "iso:country":"ID",
    "name:ind_x_preferred":[
        "Kalumbang"
    ],
    "wof:name":"Kalumbang",
    "wof:placetype":"locality"
},
  "geometry": {"coordinates":[120.4358,-9.845],"type":"Point"}
}