{
  "type": "Feature",
  "properties": {
    "gn:admin1_code":"8.0",
    "gn:asciiname":"Krajan Dua Bangsring",
    "gn:country_code":"ID",
    "gn:dem":34,
    "gn:feature_class":"P",
    "gn:feature_code":"PPL",
    "gn:name":"Krajan Dua Bangsring",
    "gn:population":0,
    "gn:timezone":"Asia/Jakarta",
    "iso:country":"ID",
    "name:ind_x_preferred":[
        "Krajan Dua Bangsring"
    ],
    "wof:name":"Krajan Dua Bangsring",
    "wof:placetype":"locality"
},
  "geometry": {"coordinates":[114.4152,-8.064],"type":"Point"}
}