{
  "type": "Feature",
  "properties": {
    "gn:admin1_code":"7",
    "gn:asciiname":"Kanyaran",
    "gn:country_code":"ID",
    "gn:dem":16,
    "gn:feature_class":"P",
    "gn:feature_code":"PPL",
    "gn:name":"Kanyaran",
    "gn:population":0,
    "gn:timezone":"Asia/Jakarta",
    "iso:country":"ID",
    "name:ind_x_preferred":[
        "Kanyaran"
    ],
    "wof:name":"Kanyaran",
    "wof:placetype":"locality"
},
  "geometry": {"coordinates":[109.66624,-6.9388],"type":"Point"}
}