{
  "type": "Feature",
  "properties": {
    "gn:admin1_code":"30",
    "gn:asciiname":"Moncol",
    "gn:country_code":"ID",
    "gn:dem":15,
    "gn:feature_class":"P",
    "gn:feature_code":"PPL",
    "gn:name":"Moncol",
    "gn:population":0,
    "gn:timezone":"Asia/Jakarta",
    "iso:country":"ID",
    "name:ind_x_preferred":[
        "Moncol"
    ],
    "wof:name":"Moncol",
    "wof:placetype":"locality"
},
  "geometry": {"coordinates":[108.33278,-6.50861],"type":"Point"}
}