{
  "type": "Feature",
  "properties": {
    "gn:admin1_code":"30",
    "gn:asciiname":"Salep",
    "gn:country_code":"ID",
    "gn:dem":70,
    "gn:feature_class":"P",
    "gn:feature_code":"PPL",
    "gn:name":"Salep",
    "gn:population":0,
    "gn:timezone":"Asia/Jakarta",
    "iso:country":"ID",
    "name:ara_x_preferred":[
        "\u0633\u062d\u0644\u0628"
    ],
    "name:bul_x_preferred":[
        "\u0421\u0430\u043b\u0435\u043f"
    ],
    "name:cat_x_preferred":[
        "Salep"
    ],
    "name:ces_x_preferred":[
        "Salep"
    ],
    "name:deu_x_preferred":[
        "Salep"
    ],
    "name:ell_x_preferred":[
        "\u03a3\u03b1\u03bb\u03ad\u03c0\u03b9"
    ],
    "name:fas_x_preferred":[
        "\u0622\u0631\u062f \u062b\u0639\u0644\u0628"
    ],
    "name:fra_x_preferred":[
        "Salep"
    ],
    "name:glg_x_preferred":[
        "Salep"
    ],
    "name:heb_x_preferred":[
        "\u05e1\u05d7\u05dc\u05d1"
    ],
    "name:ido_x_preferred":[
        "Salepo"
    ],
    "name:ind_x_preferred":[
        "Salep"
    ],
    "name:ita_x_preferred":[
        "Salep"
    ],
    "name:jpn_x_preferred":[
        "\u30b5\u30ec\u30c3\u30d7"
    ],
    "name:kaz_x_preferred":[
        "\u0421\u0430\u043b\u0435\u043f"
    ],
    "name:lat_x_preferred":[
        "Satyrion"
    ],
    "name:mkd_x_preferred":[
        "\u0421\u0430\u043b\u0435\u043f"
    ],
    "name:pol_x_preferred":[
        "Salep"
    ],
    "name:por_x_preferred":[
        "Salepo"
    ],
    "name:rus_x_preferred":[
        "\u0421\u0430\u043b\u0435\u043f"
    ],
    "name:spa_x_preferred":[
        "Salep"
    ],
    "name:sqi_x_preferred":[
        "Salepi"
    ],
    "name:swe_x_preferred":[
        "Salep"
    ],
    "name:tur_x_preferred":[
        "Salep"
    ],
    "name:ukr_x_preferred":[
        "\u0421\u0430\u043b\u0435\u043f"
    ],
    "name:zho_x_preferred":[
        "\u5170\u830e\u7c89"
    ],
    "wof:lang_x_official":[
        "ind"
    ],
    "wof:lang_x_spoken":[
        "ind",
        "eng"
    ],
    "wof:name":"Salep",
    "wof:placetype":"locality"
},
  "geometry": {"coordinates":[107.96167,-6.61111],"type":"Point"}
}