{
  "type": "Feature",
  "properties": {
    "gn:admin1_code":"30",
    "gn:asciiname":"Cigondog",
    "gn:country_code":"ID",
    "gn:dem":784,
    "gn:feature_class":"P",
    "gn:feature_code":"PPL",
    "gn:name":"Cigondog",
    "gn:population":0,
    "gn:timezone":"Asia/Jakarta",
    "iso:country":"ID",
    "name:ind_x_preferred":[
        "Cigondog"
    ],
    "wof:name":"Cigondog",
    "wof:placetype":"locality"
},
  "geometry": {"coordinates":[107.46972,-6.7525],"type":"Point"}
}