{
  "type": "Feature",
  "properties": {
    "gn:admin1_code":"7",
    "gn:asciiname":"Ringinmulyo",
    "gn:country_code":"ID",
    "gn:dem":12,
    "gn:feature_class":"P",
    "gn:feature_code":"PPL",
    "gn:name":"Ringinmulyo",
    "gn:population":0,
    "gn:timezone":"Asia/Jakarta",
    "iso:country":"ID",
    "name:ind_x_preferred":[
        "Ringinmulyo"
    ],
    "wof:name":"Ringinmulyo",
    "wof:placetype":"locality"
},
  "geometry": {"coordinates":[110.1532,-6.907],"type":"Point"}
}