{
  "type": "Feature",
  "properties": {
    "gn:admin1_code":"30",
    "gn:asciiname":"Tegalbatu",
    "gn:country_code":"ID",
    "gn:dem":939,
    "gn:feature_class":"P",
    "gn:feature_code":"PPL",
    "gn:name":"Tegalbatu",
    "gn:population":0,
    "gn:timezone":"Asia/Jakarta",
    "iso:country":"ID",
    "name:ind_x_preferred":[
        "Tegalbatu"
    ],
    "name:und_x_variant":[
        "Tagalbato"
    ],
    "wof:lang_x_official":[
        "ind"
    ],
    "wof:lang_x_spoken":[
        "ind",
        "eng"
    ],
    "wof:name":"Tegalbatu",
    "wof:placetype":"locality"
},
  "geometry": {"coordinates":[106.94306,-6.69139],"type":"Point"}
}