{
  "type": "Feature",
  "properties": {
    "gn:admin1_code":"7.0",
    "gn:asciiname":"Penaruban",
    "gn:country_code":"ID",
    "gn:dem":37,
    "gn:feature_class":"P",
    "gn:feature_code":"PPL",
    "gn:name":"Penaruban",
    "gn:population":0,
    "gn:timezone":"Asia/Jakarta",
    "iso:country":"ID",
    "name:ind_x_preferred":[
        "Penaruban"
    ],
    "wof:name":"Penaruban",
    "wof:placetype":"locality"
},
  "geometry": {"coordinates":[109.40278000000001,-7.41139],"type":"Point"}
}