{
  "type": "Feature",
  "properties": {
    "gn:admin1_code":"7",
    "gn:asciiname":"Krewisan",
    "gn:country_code":"ID",
    "gn:dem":608,
    "gn:feature_class":"P",
    "gn:feature_code":"PPL",
    "gn:name":"Krewisan",
    "gn:population":0,
    "gn:timezone":"Asia/Jakarta",
    "iso:country":"ID",
    "name:ind_x_preferred":[
        "Krewisan"
    ],
    "wof:name":"Krewisan",
    "wof:placetype":"locality"
},
  "geometry": {"coordinates":[110.16916999999999,-7.20083],"type":"Point"}
}