{
  "type": "Feature",
  "properties": {
    "gn:admin1_code":"7.0",
    "gn:asciiname":"Patraditan",
    "gn:country_code":"ID",
    "gn:dem":19,
    "gn:feature_class":"P",
    "gn:feature_code":"PPL",
    "gn:name":"Patraditan",
    "gn:population":0,
    "gn:timezone":"Asia/Jakarta",
    "iso:country":"ID",
    "name:ind_x_preferred":[
        "Patraditan"
    ],
    "wof:name":"Patraditan",
    "wof:placetype":"locality"
},
  "geometry": {"coordinates":[109.66361000000001,-7.76611],"type":"Point"}
}