{
  "type": "Feature",
  "properties": {
    "gn:admin1_code":"8",
    "gn:asciiname":"Kauman",
    "gn:country_code":"ID",
    "gn:dem":199,
    "gn:feature_class":"P",
    "gn:feature_code":"PPL",
    "gn:name":"Kauman",
    "gn:population":0,
    "gn:timezone":"Asia/Jakarta",
    "iso:country":"ID",
    "name:ind_x_preferred":[
        "Kauman"
    ],
    "name:msa_x_preferred":[
        "Kauman"
    ],
    "name:nld_x_preferred":[
        "Kauman"
    ],
    "wof:lang_x_official":[
        "ind"
    ],
    "wof:lang_x_spoken":[
        "ind",
        "eng"
    ],
    "wof:name":"Kauman",
    "wof:placetype":"locality"
},
  "geometry": {"coordinates":[113.24890000000001,-7.9914],"type":"Point"}
}