{
  "type": "Feature",
  "properties": {
    "gn:admin1_code":"32.0",
    "gn:asciiname":"Tanjungraja",
    "gn:country_code":"ID",
    "gn:dem":20,
    "gn:feature_class":"P",
    "gn:feature_code":"PPLA3",
    "gn:name":"Tanjungraja",
    "gn:population":0,
    "gn:timezone":"Asia/Jakarta",
    "iso:country":"ID",
    "name:und_x_variant":[
        "Tandjungradja",
        "Tandjoengradja",
        "Tanjungraja"
    ],
    "wof:name":"Tanjungraja",
    "wof:placetype":"locality"
},
  "geometry": {"coordinates":[104.77452,-3.33725],"type":"Point"}
}