{
  "type": "Feature",
  "properties": {
    "gn:admin1_code":"22.0",
    "gn:asciiname":"Laiba",
    "gn:country_code":"ID",
    "gn:dem":25,
    "gn:feature_class":"P",
    "gn:feature_code":"PPL",
    "gn:name":"Laiba",
    "gn:population":0,
    "gn:timezone":"Asia/Makassar",
    "iso:country":"ID",
    "name:ind_x_preferred":[
        "Laiba"
    ],
    "wof:name":"Laiba",
    "wof:placetype":"locality"
},
  "geometry": {"coordinates":[122.49509999999999,-5.065],"type":"Point"}
}