{
  "type": "Feature",
  "properties": {
    "gn:admin1_code":"7",
    "gn:asciiname":"Kedungbatur",
    "gn:country_code":"ID",
    "gn:dem":56,
    "gn:feature_class":"P",
    "gn:feature_code":"PPL",
    "gn:name":"Kedungbatur",
    "gn:population":0,
    "gn:timezone":"Asia/Jakarta",
    "iso:country":"ID",
    "name:ind_x_preferred":[
        "Kedungbatur"
    ],
    "wof:name":"Kedungbatur",
    "wof:placetype":"locality"
},
  "geometry": {"coordinates":[109.845,-7.64861],"type":"Point"}
}