{
  "type": "Feature",
  "properties": {
    "gn:admin1_code":"08",
    "gn:asciiname":"Turi Wetan",
    "gn:country_code":"ID",
    "gn:dem":560,
    "gn:feature_class":"P",
    "gn:feature_code":"PPL",
    "gn:name":"Turi Wetan",
    "gn:population":0,
    "gn:timezone":"Asia/Jakarta",
    "iso:country":"ID",
    "name:ind_x_preferred":[
        "Turi Wetan"
    ],
    "name:und_x_variant":[
        "Turiredjo 2",
        "Turirejo Dua"
    ],
    "wof:name":"Turi Wetan",
    "wof:placetype":"locality"
},
  "geometry": {"coordinates":[112.6939,-7.8191],"type":"Point"}
}