{
  "type": "Feature",
  "properties": {
    "gn:admin1_code":"30",
    "gn:asciiname":"Ciwaru",
    "gn:country_code":"ID",
    "gn:dem":67,
    "gn:feature_class":"P",
    "gn:feature_code":"PPL",
    "gn:name":"Ciwaru",
    "gn:population":0,
    "gn:timezone":"Asia/Jakarta",
    "iso:country":"ID",
    "name:ind_x_preferred":[
        "Ciwaru"
    ],
    "name:und_x_variant":[
        "Tjiwaru"
    ],
    "wof:name":"Ciwaru",
    "wof:placetype":"locality"
},
  "geometry": {"coordinates":[106.46111000000001,-6.33139],"type":"Point"}
}