{
  "type": "Feature",
  "properties": {
    "gn:admin1_code":"8.0",
    "gn:asciiname":"Tugu",
    "gn:country_code":"ID",
    "gn:dem":369,
    "gn:feature_class":"P",
    "gn:feature_code":"PPL",
    "gn:name":"Tugu",
    "gn:population":0,
    "gn:timezone":"Asia/Jakarta",
    "iso:country":"ID",
    "name:ind_x_preferred":[
        "Tugu"
    ],
    "wof:name":"Tugu",
    "wof:placetype":"locality"
},
  "geometry": {"coordinates":[111.38330000000001,-8.212],"type":"Point"}
}