{
  "type": "Feature",
  "properties": {
    "gn:admin1_code":"08",
    "gn:asciiname":"Cari",
    "gn:country_code":"ID",
    "gn:dem":5,
    "gn:feature_class":"P",
    "gn:feature_code":"PPL",
    "gn:name":"Cari",
    "gn:population":0,
    "gn:timezone":"Asia/Jakarta",
    "iso:country":"ID",
    "name:fra_x_preferred":[
        "Cari"
    ],
    "name:ind_x_preferred":[
        "Cari"
    ],
    "name:ita_x_preferred":[
        "Cari"
    ],
    "wof:lang_x_official":[
        "ind"
    ],
    "wof:lang_x_spoken":[
        "ind",
        "eng"
    ],
    "wof:name":"Cari",
    "wof:placetype":"locality"
},
  "geometry": {"coordinates":[112.74890000000001,-7.4146],"type":"Point"}
}