{
  "type": "Feature",
  "properties": {
    "gn:country":"ID",
    "gn:fcode":"PPL",
    "gn:pop":0,
    "iso:country":"ID",
    "name:ace_x_preferred":[
        "Buntu Pane"
    ],
    "name:deu_x_preferred":[
        "Buntu Pane"
    ],
    "name:eng_x_preferred":[
        "Buntu Pane"
    ],
    "name:fra_x_preferred":[
        "Buntu Pane"
    ],
    "name:ind_x_preferred":[
        "Buntu Pane"
    ],
    "name:ind_x_variant":[
        "Tirto"
    ],
    "name:msa_x_preferred":[
        "Buntu Pane"
    ],
    "name:nld_x_preferred":[
        "Buntu Pane"
    ],
    "name:por_x_preferred":[
        "Buntu Pane"
    ],
    "name:spa_x_preferred":[
        "Buntu Pane"
    ],
    "name:sun_x_preferred":[
        "Buntu Pane"
    ],
    "qs:name":"Buntu Pane",
    "qs:name_adm0":"Indonesia",
    "qs:name_adm1":"Sumatera Utara",
    "qs:photos_9r":0,
    "qs:photos_sr":0,
    "qs:placetype":"Town",
    "qs:pop_sr":"0",
    "wof:lang_x_official":[
        "ind"
    ],
    "wof:lang_x_spoken":[
        "ind",
        "eng"
    ],
    "wof:name":"Buntu Pane",
    "wof:placetype":"locality",
    "wof:population":0
},
  "geometry": {"coordinates":[99.496,2.8704],"type":"Point"}
}