{
  "type": "Feature",
  "properties": {
    "gn:admin1_code":"30",
    "gn:asciiname":"Citeureup",
    "gn:country_code":"ID",
    "gn:dem":652,
    "gn:feature_class":"P",
    "gn:feature_code":"PPL",
    "gn:name":"Citeureup",
    "gn:population":0,
    "gn:timezone":"Asia/Jakarta",
    "iso:country":"ID",
    "name:ind_x_preferred":[
        "Citeureup"
    ],
    "name:jav_x_preferred":[
        "Citeureup"
    ],
    "name:mlg_x_preferred":[
        "Citeureup"
    ],
    "name:sun_x_preferred":[
        "Citeureup"
    ],
    "wof:lang_x_official":[
        "ind"
    ],
    "wof:lang_x_spoken":[
        "ind",
        "eng"
    ],
    "wof:name":"Citeureup",
    "wof:placetype":"locality"
},
  "geometry": {"coordinates":[106.98111,-6.92111],"type":"Point"}
}