{
  "type": "Feature",
  "properties": {
    "gn:admin1_code":"17",
    "gn:asciiname":"Jempongeler",
    "gn:country_code":"ID",
    "gn:dem":192,
    "gn:feature_class":"P",
    "gn:feature_code":"PPL",
    "gn:name":"Jempongeler",
    "gn:population":0,
    "gn:timezone":"Asia/Makassar",
    "iso:country":"ID",
    "name:ind_x_preferred":[
        "Jempongeler"
    ],
    "wof:name":"Jempongeler",
    "wof:placetype":"locality"
},
  "geometry": {"coordinates":[116.2873,-8.679],"type":"Point"}
}