{
  "type": "Feature",
  "properties": {
    "gn:admin1_code":"41",
    "gn:asciiname":"Langsa",
    "gn:country_code":"ID",
    "gn:dem":794,
    "gn:feature_class":"P",
    "gn:feature_code":"PPL",
    "gn:name":"Langsa",
    "gn:population":0,
    "gn:timezone":"Asia/Makassar",
    "iso:country":"ID",
    "name:ace_x_preferred":[
        "Kota Langsa"
    ],
    "name:afr_x_preferred":[
        "Langsa"
    ],
    "name:ara_x_preferred":[
        "\u0644\u0627\u0646\u063a\u0633\u0627"
    ],
    "name:bel_x_preferred":[
        "\u041b\u0430\u043d\u0433\u0441\u0430"
    ],
    "name:bug_x_preferred":[
        "Langsa"
    ],
    "name:ceb_x_preferred":[
        "Langsa"
    ],
    "name:deu_x_preferred":[
        "Langsa"
    ],
    "name:fra_x_preferred":[
        "Langsa"
    ],
    "name:heb_x_preferred":[
        "\u05dc\u05e0\u05d2\u05e1\u05d4"
    ],
    "name:hun_x_preferred":[
        "Langsa"
    ],
    "name:ind_x_preferred":[
        "Langsa"
    ],
    "name:ind_x_variant":[
        "Kota Langsa"
    ],
    "name:ita_x_preferred":[
        "Langsa"
    ],
    "name:jav_x_preferred":[
        "Kutha Langsa"
    ],
    "name:jpn_x_preferred":[
        "\u30e9\u30f3\u30b5"
    ],
    "name:lit_x_preferred":[
        "Langsa"
    ],
    "name:min_x_preferred":[
        "Kota Langsa"
    ],
    "name:mlg_x_preferred":[
        "Kota Langsa"
    ],
    "name:msa_x_preferred":[
        "Langsa"
    ],
    "name:nld_x_preferred":[
        "Langsa"
    ],
    "name:pol_x_preferred":[
        "Langsa"
    ],
    "name:por_x_preferred":[
        "Langsa"
    ],
    "name:rus_x_preferred":[
        "\u041b\u0430\u043d\u0433\u0441\u0430"
    ],
    "name:spa_x_preferred":[
        "Kota Langsa"
    ],
    "name:swe_x_preferred":[
        "Langsa"
    ],
    "name:tur_x_preferred":[
        "Langsa"
    ],
    "name:urd_x_preferred":[
        "\u0644\u0627\u0646\u06af\u0633\u0627"
    ],
    "name:vie_x_preferred":[
        "Langsa"
    ],
    "wof:lang_x_official":[
        "ind"
    ],
    "wof:lang_x_spoken":[
        "ind",
        "eng"
    ],
    "wof:name":"Langsa",
    "wof:placetype":"locality"
},
  "geometry": {"coordinates":[119.2522,-2.7496],"type":"Point"}
}