{
  "type": "Feature",
  "properties": {
    "gn:admin1_code":"41",
    "gn:asciiname":"Langsa",
    "gn:country_code":"ID",
    "gn:dem":794,
    "gn:feature_class":"P",
    "gn:feature_code":"PPL",
    "gn:name":"Langsa",
    "gn:population":0,
    "gn:timezone":"Asia/Makassar",
    "iso:country":"ID",
    "name:ind_x_preferred":[
        "Langsa"
    ],
    "wof:name":"Langsa",
    "wof:placetype":"locality"
},
  "geometry": {"coordinates":[119.2522,-2.7496],"type":"Point"}
}