{
  "type": "Feature",
  "properties": {
    "gn:admin1_code":"10.0",
    "gn:asciiname":"Tunggalan",
    "gn:country_code":"ID",
    "gn:dem":248,
    "gn:feature_class":"P",
    "gn:feature_code":"PPL",
    "gn:name":"Tunggalan",
    "gn:population":0,
    "gn:timezone":"Asia/Jakarta",
    "iso:country":"ID",
    "wof:name":"Tunggalan",
    "wof:placetype":"locality"
},
  "geometry": {"coordinates":[110.43277999999999,-7.71639],"type":"Point"}
}