{
  "type": "Feature",
  "properties": {
    "gn:admin1_code":"7.0",
    "gn:asciiname":"Jelarang",
    "gn:country_code":"ID",
    "gn:dem":27,
    "gn:feature_class":"P",
    "gn:feature_code":"PPL",
    "gn:name":"Jelarang",
    "gn:population":0,
    "gn:timezone":"Asia/Jakarta",
    "iso:country":"ID",
    "name:ind_x_preferred":[
        "Jelarang"
    ],
    "wof:name":"Jelarang",
    "wof:placetype":"locality"
},
  "geometry": {"coordinates":[109.67528,-7.64639],"type":"Point"}
}