{
  "type": "Feature",
  "properties": {
    "gn:admin1_code":"24",
    "gn:asciiname":"Biabia Satu",
    "gn:country_code":"ID",
    "gn:dem":683,
    "gn:feature_class":"P",
    "gn:feature_code":"PPL",
    "gn:name":"Biabia Satu",
    "gn:population":0,
    "gn:timezone":"Asia/Jakarta",
    "iso:country":"ID",
    "name:ind_x_preferred":[
        "Biabia 1"
    ],
    "name:ind_x_variant":[
        "Biabia Satu"
    ],
    "wof:name":"Biabia Satu",
    "wof:placetype":"locality"
},
  "geometry": {"coordinates":[100.61753,-0.066],"type":"Point"}
}