{
  "type": "Feature",
  "properties": {
    "gn:admin1_code":"30.0",
    "gn:asciiname":"Leuwigoong",
    "gn:country_code":"ID",
    "gn:dem":338,
    "gn:feature_class":"P",
    "gn:feature_code":"PPL",
    "gn:name":"Leuwigoong",
    "gn:population":0,
    "gn:timezone":"Asia/Jakarta",
    "iso:country":"ID",
    "name:ind_x_preferred":[
        "Leuwigoong"
    ],
    "wof:name":"Leuwigoong",
    "wof:placetype":"locality"
},
  "geometry": {"coordinates":[106.91528,-6.57583],"type":"Point"}
}