{
  "type": "Feature",
  "properties": {
    "gn:admin1_code":"7",
    "gn:asciiname":"Ngemplak",
    "gn:country_code":"ID",
    "gn:dem":11,
    "gn:feature_class":"P",
    "gn:feature_code":"PPL",
    "gn:name":"Ngemplak",
    "gn:population":0,
    "gn:timezone":"Asia/Jakarta",
    "iso:country":"ID",
    "name:ind_x_preferred":[
        "Ngemplak"
    ],
    "wof:name":"Ngemplak",
    "wof:placetype":"locality"
},
  "geometry": {"coordinates":[110.6811,-6.9461],"type":"Point"}
}