{
  "type": "Feature",
  "properties": {
    "gn:admin1_code":"30.0",
    "gn:asciiname":"Pangauban",
    "gn:country_code":"ID",
    "gn:dem":565,
    "gn:feature_class":"P",
    "gn:feature_code":"PPL",
    "gn:name":"Pangauban",
    "gn:population":0,
    "gn:timezone":"Asia/Jakarta",
    "iso:country":"ID",
    "name:ind_x_preferred":[
        "Pangauban"
    ],
    "wof:name":"Pangauban",
    "wof:placetype":"locality"
},
  "geometry": {"coordinates":[108.0104,-7.0061],"type":"Point"}
}