{
  "type": "Feature",
  "properties": {
    "gn:admin1_code":"12",
    "gn:asciiname":"Karangmulya",
    "gn:country_code":"ID",
    "gn:dem":17,
    "gn:feature_class":"P",
    "gn:feature_code":"PPL",
    "gn:name":"Karangmulya",
    "gn:population":0,
    "gn:timezone":"Asia/Makassar",
    "iso:country":"ID",
    "name:ind_x_preferred":[
        "Karangmulya"
    ],
    "wof:name":"Karangmulya",
    "wof:placetype":"locality"
},
  "geometry": {"coordinates":[115.77889999999999,-3.6403],"type":"Point"}
}