{
  "type": "Feature",
  "properties": {
    "gn:admin1_code":"7",
    "gn:asciiname":"Kalijero",
    "gn:country_code":"ID",
    "gn:dem":71,
    "gn:feature_class":"P",
    "gn:feature_code":"PPL",
    "gn:name":"Kalijero",
    "gn:population":0,
    "gn:timezone":"Asia/Jakarta",
    "iso:country":"ID",
    "name:ind_x_preferred":[
        "Kalijero"
    ],
    "wof:name":"Kalijero",
    "wof:placetype":"locality"
},
  "geometry": {"coordinates":[109.37220000000001,-7.0094],"type":"Point"}
}