{
  "type": "Feature",
  "properties": {
    "gn:admin1_code":"07",
    "gn:asciiname":"Larangan",
    "gn:country_code":"ID",
    "gn:dem":264,
    "gn:feature_class":"P",
    "gn:feature_code":"PPL",
    "gn:name":"Larangan",
    "gn:population":0,
    "gn:timezone":"Asia/Jakarta",
    "iso:country":"ID",
    "name:ind_x_preferred":[
        "Larangan"
    ],
    "name:jav_x_preferred":[
        "Larangan"
    ],
    "name:msa_x_preferred":[
        "Larangan"
    ],
    "name:sun_x_preferred":[
        "Larangan"
    ],
    "name:und_x_variant":[
        "Larangan 1",
        "Larangan Satu"
    ],
    "name:urd_x_preferred":[
        "\u0644\u0627\u0631\u0627\u0646\u06af\u0627\u0646"
    ],
    "wof:lang_x_official":[
        "ind"
    ],
    "wof:lang_x_spoken":[
        "ind",
        "eng"
    ],
    "wof:name":"Larangan",
    "wof:placetype":"locality"
},
  "geometry": {"coordinates":[110.50583,-7.17917],"type":"Point"}
}