{
  "type": "Feature",
  "properties": {
    "gn:admin1_code":"8",
    "gn:asciiname":"Sumuran",
    "gn:country_code":"ID",
    "gn:dem":334,
    "gn:feature_class":"P",
    "gn:feature_code":"PPLA4",
    "gn:name":"Sumuran",
    "gn:population":0,
    "gn:timezone":"Asia/Jakarta",
    "iso:country":"ID",
    "name:ind_x_preferred":[
        "Sumuran"
    ],
    "wof:name":"Sumuran",
    "wof:placetype":"locality"
},
  "geometry": {"coordinates":[112.55419999999999,-8.2103],"type":"Point"}
}