{
  "type": "Feature",
  "properties": {
    "gn:admin1_code":"30.0",
    "gn:asciiname":"Sangkali",
    "gn:country_code":"ID",
    "gn:dem":375,
    "gn:feature_class":"P",
    "gn:feature_code":"PPL",
    "gn:name":"Sangkali",
    "gn:population":0,
    "gn:timezone":"Asia/Jakarta",
    "iso:country":"ID",
    "name:ind_x_preferred":[
        "Sangkali"
    ],
    "wof:name":"Sangkali",
    "wof:placetype":"locality"
},
  "geometry": {"coordinates":[108.2321,-7.381],"type":"Point"}
}