{
  "type": "Feature",
  "properties": {
    "gn:admin1_code":"30.0",
    "gn:asciiname":"Ciparat",
    "gn:country_code":"ID",
    "gn:dem":525,
    "gn:feature_class":"P",
    "gn:feature_code":"PPL",
    "gn:name":"Ciparat",
    "gn:population":0,
    "gn:timezone":"Asia/Jakarta",
    "iso:country":"ID",
    "name:ind_x_preferred":[
        "Ciparat"
    ],
    "wof:name":"Ciparat",
    "wof:placetype":"locality"
},
  "geometry": {"coordinates":[107.58589000000001,-7.44689],"type":"Point"}
}