{
  "type": "Feature",
  "properties": {
    "gn:admin1_code":"7.0",
    "gn:asciiname":"Blender",
    "gn:country_code":"ID",
    "gn:dem":25,
    "gn:feature_class":"P",
    "gn:feature_code":"PPL",
    "gn:name":"Blender",
    "gn:population":0,
    "gn:timezone":"Asia/Jakarta",
    "iso:country":"ID",
    "name:ind_x_preferred":[
        "Blender"
    ],
    "wof:name":"Blender",
    "wof:placetype":"locality"
},
  "geometry": {"coordinates":[109.05138999999998,-7.61361],"type":"Point"}
}