{
  "type": "Feature",
  "properties": {
    "gn:admin1_code":"36.0",
    "gn:asciiname":"Oburap",
    "gn:country_code":"ID",
    "gn:dem":305,
    "gn:feature_class":"P",
    "gn:feature_code":"PPL",
    "gn:name":"Oburap",
    "gn:population":0,
    "gn:timezone":"Asia/Jayapura",
    "iso:country":"ID",
    "name:ind_x_preferred":[
        "Oburap"
    ],
    "name:und_x_variant":[
        "Ubrop",
        "Nimbrap",
        "Oembrop",
        "Umbrop"
    ],
    "wof:lang_x_official":[
        "ind"
    ],
    "wof:lang_x_spoken":[
        "ind",
        "eng"
    ],
    "wof:name":"Oburap",
    "wof:placetype":"locality"
},
  "geometry": {"coordinates":[139.9365,-2.6267],"type":"Point"}
}