{
  "type": "Feature",
  "properties": {
    "gn:admin1_code":"30.0",
    "gn:asciiname":"Pakis",
    "gn:country_code":"ID",
    "gn:dem":6,
    "gn:feature_class":"P",
    "gn:feature_code":"PPL",
    "gn:name":"Pakis",
    "gn:population":0,
    "gn:timezone":"Asia/Jakarta",
    "iso:country":"ID",
    "name:ind_x_preferred":[
        "Pakis"
    ],
    "name:und_x_variant":[
        "Pakis Satu",
        "Pakis 1"
    ],
    "wof:name":"Pakis",
    "wof:placetype":"locality"
},
  "geometry": {"coordinates":[107.12888999999998,-5.97472],"type":"Point"}
}