{
  "type": "Feature",
  "properties": {
    "gn:admin1_code":"36",
    "gn:admin2_code":"9415",
    "gn:asciiname":"Ayr",
    "gn:country_code":"ID",
    "gn:dem":29,
    "gn:feature_class":"P",
    "gn:feature_code":"PPL",
    "gn:name":"Ayr",
    "gn:population":0,
    "gn:timezone":"Asia/Jayapura",
    "iso:country":"ID",
    "wof:name":"Ayr",
    "wof:placetype":"locality"
},
  "geometry": {"coordinates":[138.02251000000001,-5.12284],"type":"Point"}
}