{
  "type": "Feature",
  "properties": {
    "gn:admin1_code":"36",
    "gn:admin2_code":"9415",
    "gn:asciiname":"Ayr",
    "gn:country_code":"ID",
    "gn:dem":29,
    "gn:feature_class":"P",
    "gn:feature_code":"PPL",
    "gn:name":"Ayr",
    "gn:population":0,
    "gn:timezone":"Asia/Jayapura",
    "iso:country":"ID",
    "name:ara_x_preferred":[
        "\u0622\u064a\u0631"
    ],
    "name:azb_x_preferred":[
        "\u0627\u06cc\u0631"
    ],
    "name:aze_x_preferred":[
        "Eyr \u015f\u0259h\u0259ri"
    ],
    "name:bar_x_preferred":[
        "Ayr"
    ],
    "name:bre_x_preferred":[
        "Inbhir \u00c0ir"
    ],
    "name:cat_x_preferred":[
        "Ayr"
    ],
    "name:ceb_x_preferred":[
        "Ayr"
    ],
    "name:ces_x_preferred":[
        "Ayr"
    ],
    "name:cym_x_preferred":[
        "Ayr"
    ],
    "name:dan_x_preferred":[
        "Ayr"
    ],
    "name:deu_x_preferred":[
        "Ayr"
    ],
    "name:eus_x_preferred":[
        "Ayr"
    ],
    "name:fas_x_preferred":[
        "\u0627\u06cc\u0631"
    ],
    "name:fin_x_preferred":[
        "Ayr"
    ],
    "name:fra_x_preferred":[
        "Ayr"
    ],
    "name:gla_x_preferred":[
        "Inbhir \u00c0ir"
    ],
    "name:gle_x_preferred":[
        "Inbhir \u00c1ir"
    ],
    "name:glg_x_preferred":[
        "Ayr"
    ],
    "name:heb_x_preferred":[
        "\u05d0\u05d9\u05d9\u05e8"
    ],
    "name:ita_x_preferred":[
        "Ayr"
    ],
    "name:jpn_x_preferred":[
        "\u30a8\u30a2"
    ],
    "name:kor_x_preferred":[
        "\uc544\uc774\ub974"
    ],
    "name:kor_x_variant":[
        "\uc5d0\uc5b4"
    ],
    "name:lit_x_preferred":[
        "Eras"
    ],
    "name:mlg_x_preferred":[
        "Ayr"
    ],
    "name:nld_x_preferred":[
        "Ayr"
    ],
    "name:nno_x_preferred":[
        "Ayr"
    ],
    "name:nor_x_preferred":[
        "Ayr"
    ],
    "name:pnb_x_preferred":[
        "\u0622\u0626\u0631"
    ],
    "name:pol_x_preferred":[
        "Ayr"
    ],
    "name:por_x_preferred":[
        "Ayr"
    ],
    "name:ron_x_preferred":[
        "Ayr"
    ],
    "name:rus_x_preferred":[
        "\u042d\u0440"
    ],
    "name:sco_x_preferred":[
        "Ayr"
    ],
    "name:slk_x_preferred":[
        "Ayr"
    ],
    "name:spa_x_preferred":[
        "Ayr"
    ],
    "name:swe_x_preferred":[
        "Ayr"
    ],
    "name:tat_x_preferred":[
        "\u042d\u0440"
    ],
    "name:tur_x_preferred":[
        "Ayr"
    ],
    "name:ukr_x_preferred":[
        "\u0415\u0440"
    ],
    "name:urd_x_preferred":[
        "\u0622\u0626\u0631"
    ],
    "name:vie_x_preferred":[
        "Ayr"
    ],
    "name:zho_cn_x_preferred":[
        "\u827e\u5c14"
    ],
    "name:zho_tw_x_preferred":[
        "\u827e\u723e"
    ],
    "name:zho_x_preferred":[
        "\u827e\u5c14"
    ],
    "wof:lang_x_official":[
        "ind"
    ],
    "wof:lang_x_spoken":[
        "ind",
        "eng"
    ],
    "wof:name":"Ayr",
    "wof:placetype":"locality"
},
  "geometry": {"coordinates":[138.02251000000001,-5.12284],"type":"Point"}
}