{
  "type": "Feature",
  "properties": {
    "gn:admin1_code":"7",
    "gn:asciiname":"Arjamulya",
    "gn:country_code":"ID",
    "gn:dem":48,
    "gn:feature_class":"P",
    "gn:feature_code":"PPL",
    "gn:name":"Arjamulya",
    "gn:population":0,
    "gn:timezone":"Asia/Jakarta",
    "iso:country":"ID",
    "name:ind_x_preferred":[
        "Arjamulya"
    ],
    "wof:name":"Arjamulya",
    "wof:placetype":"locality"
},
  "geometry": {"coordinates":[109.4264,-7.0288],"type":"Point"}
}