{
  "type": "Feature",
  "properties": {
    "gn:admin1_code":"30",
    "gn:asciiname":"Manungtung Pos",
    "gn:country_code":"ID",
    "gn:dem":42,
    "gn:feature_class":"P",
    "gn:feature_code":"PPL",
    "gn:name":"Manungtung Pos",
    "gn:population":0,
    "gn:timezone":"Asia/Jakarta",
    "iso:country":"ID",
    "wof:name":"Manungtung Pos",
    "wof:placetype":"locality"
},
  "geometry": {"coordinates":[106.58138999999998,-6.29056],"type":"Point"}
}