{
  "type": "Feature",
  "properties": {
    "gn:admin1_code":"38",
    "gn:asciiname":"Botto",
    "gn:country_code":"ID",
    "gn:dem":158,
    "gn:feature_class":"P",
    "gn:feature_code":"PPL",
    "gn:name":"Botto",
    "gn:population":0,
    "gn:timezone":"Asia/Makassar",
    "iso:country":"ID",
    "name:ind_x_preferred":[
        "Botto"
    ],
    "wof:name":"Botto",
    "wof:placetype":"locality"
},
  "geometry": {"coordinates":[119.9693,-4.6107],"type":"Point"}
}