{
  "type": "Feature",
  "properties": {
    "gn:admin1_code":"37.0",
    "gn:asciiname":"Pematangbinjai",
    "gn:country_code":"ID",
    "gn:dem":13,
    "gn:feature_class":"P",
    "gn:feature_code":"PPL",
    "gn:name":"Pematangbinjai",
    "gn:population":0,
    "gn:timezone":"Asia/Jakarta",
    "iso:country":"ID",
    "name:ind_x_preferred":[
        "Pematangbinjai"
    ],
    "name:und_x_variant":[
        "Pematangbendjai",
        "Pematangbenjai"
    ],
    "wof:name":"Pematangbinjai",
    "wof:placetype":"locality"
},
  "geometry": {"coordinates":[100.90017,1.64103],"type":"Point"}
}