{
  "type": "Feature",
  "properties": {
    "gn:admin1_code":"30.0",
    "gn:asciiname":"Cimangir",
    "gn:country_code":"ID",
    "gn:dem":366,
    "gn:feature_class":"P",
    "gn:feature_code":"PPL",
    "gn:name":"Cimangir",
    "gn:population":0,
    "gn:timezone":"Asia/Jakarta",
    "iso:country":"ID",
    "name:ind_x_preferred":[
        "Cimangir"
    ],
    "wof:name":"Cimangir",
    "wof:placetype":"locality"
},
  "geometry": {"coordinates":[107.5583,-7.4866],"type":"Point"}
}