{
  "type": "Feature",
  "properties": {
    "gn:admin1_code":"28.0",
    "gn:asciiname":"Undur",
    "gn:country_code":"ID",
    "gn:dem":4,
    "gn:feature_class":"P",
    "gn:feature_code":"PPL",
    "gn:name":"Undur",
    "gn:population":0,
    "gn:timezone":"Asia/Jayapura",
    "iso:country":"ID",
    "name:und_x_variant":[
        "Oendoer",
        "Undur"
    ],
    "wof:name":"Undur",
    "wof:placetype":"locality"
},
  "geometry": {"coordinates":[130.61239,-3.78193],"type":"Point"}
}