{
  "type": "Feature",
  "properties": {
    "gn:country":"ID",
    "gn:fcode":"PPL",
    "gn:pop":83050,
    "iso:country":"ID",
    "name:ind_x_preferred":[
        "Galesong"
    ],
    "qs:name":"Galesong",
    "qs:photos_9r":0,
    "qs:photos_sr":0,
    "qs:pop_sr":"8",
    "wof:name":"Galesong",
    "wof:placetype":"locality",
    "wof:population":83050
},
  "geometry": {"coordinates":[119.3661,-5.3166],"type":"Point"}
}