{
  "type": "Feature",
  "properties": {
    "gn:admin1_code":"7.0",
    "gn:asciiname":"Beji",
    "gn:country_code":"ID",
    "gn:dem":333,
    "gn:feature_class":"P",
    "gn:feature_code":"PPL",
    "gn:name":"Beji",
    "gn:population":0,
    "gn:timezone":"Asia/Jakarta",
    "iso:country":"ID",
    "name:ind_x_preferred":[
        "Beji"
    ],
    "wof:name":"Beji",
    "wof:placetype":"locality"
},
  "geometry": {"coordinates":[109.03943999999998,-7.46556],"type":"Point"}
}