{
  "type": "Feature",
  "properties": {
    "gn:admin1_code":"8.0",
    "gn:asciiname":"Putuk",
    "gn:country_code":"ID",
    "gn:dem":184,
    "gn:feature_class":"P",
    "gn:feature_code":"PPL",
    "gn:name":"Putuk",
    "gn:population":0,
    "gn:timezone":"Asia/Jakarta",
    "iso:country":"ID",
    "name:ind_x_preferred":[
        "Putuk"
    ],
    "wof:name":"Putuk",
    "wof:placetype":"locality"
},
  "geometry": {"coordinates":[111.955,-7.4509],"type":"Point"}
}