{
  "type": "Feature",
  "properties": {
    "gn:admin1_code":"26",
    "gn:asciiname":"Telukbaru",
    "gn:country_code":"ID",
    "gn:dem":3,
    "gn:feature_class":"P",
    "gn:feature_code":"PPL",
    "gn:name":"Telukbaru",
    "gn:population":0,
    "gn:timezone":"Asia/Jakarta",
    "iso:country":"ID",
    "name:ind_x_preferred":[
        "Telukbaru"
    ],
    "name:und_x_variant":[
        "Telok-baru"
    ],
    "wof:name":"Telukbaru",
    "wof:placetype":"locality"
},
  "geometry": {"coordinates":[99.3991,3.3873],"type":"Point"}
}