{
  "type": "Feature",
  "properties": {
    "gn:admin1_code":"31",
    "gn:asciiname":"Sumalangka",
    "gn:country_code":"ID",
    "gn:dem":720,
    "gn:feature_class":"P",
    "gn:feature_code":"PPL",
    "gn:name":"Sumalangka",
    "gn:population":0,
    "gn:timezone":"Asia/Makassar",
    "iso:country":"ID",
    "name:ind_x_preferred":[
        "Sumalangka"
    ],
    "wof:name":"Sumalangka",
    "wof:placetype":"locality"
},
  "geometry": {"coordinates":[124.9049,1.3183],"type":"Point"}
}