{
  "type": "Feature",
  "properties": {
    "gn:admin1_code":"8.0",
    "gn:asciiname":"Sukosari Lor",
    "gn:country_code":"ID",
    "gn:dem":176,
    "gn:feature_class":"P",
    "gn:feature_code":"PPL",
    "gn:name":"Sukosari Lor",
    "gn:population":0,
    "gn:timezone":"Asia/Jakarta",
    "iso:country":"ID",
    "name:ind_x_preferred":[
        "Sukosari Lor"
    ],
    "wof:name":"Sukosari Lor",
    "wof:placetype":"locality"
},
  "geometry": {"coordinates":[113.5116,-8.1564],"type":"Point"}
}