{
  "type": "Feature",
  "properties": {
    "gn:admin1_code":"26",
    "gn:asciiname":"Derek",
    "gn:country_code":"ID",
    "gn:dem":62,
    "gn:feature_class":"P",
    "gn:feature_code":"PPL",
    "gn:name":"Derek",
    "gn:population":0,
    "gn:timezone":"Asia/Jakarta",
    "iso:country":"ID",
    "name:deu_x_preferred":[
        "Derek"
    ],
    "name:ind_x_preferred":[
        "Derek"
    ],
    "name:ita_x_preferred":[
        "Derek"
    ],
    "name:jpn_x_preferred":[
        "\u30c7\u30ec\u30af"
    ],
    "wof:name":"Derek",
    "wof:placetype":"locality"
},
  "geometry": {"coordinates":[99.0899,3.2198],"type":"Point"}
}