{
  "type": "Feature",
  "properties": {
    "gn:admin1_code":"30",
    "gn:asciiname":"Bangsal",
    "gn:country_code":"ID",
    "gn:dem":9,
    "gn:feature_class":"P",
    "gn:feature_code":"PPL",
    "gn:name":"Bangsal",
    "gn:population":0,
    "gn:timezone":"Asia/Jakarta",
    "iso:country":"ID",
    "name:ind_x_preferred":[
        "Bangsal"
    ],
    "wof:name":"Bangsal",
    "wof:placetype":"locality"
},
  "geometry": {"coordinates":[107.69499999999999,-6.315],"type":"Point"}
}