{
  "type": "Feature",
  "properties": {
    "gn:admin1_code":"30.0",
    "gn:asciiname":"Leuwiliang",
    "gn:country_code":"ID",
    "gn:dem":276,
    "gn:feature_class":"P",
    "gn:feature_code":"PPL",
    "gn:name":"Leuwiliang",
    "gn:population":0,
    "gn:timezone":"Asia/Jakarta",
    "iso:country":"ID",
    "name:azb_x_preferred":[
        "\u0644\u0648\u0648\u06cc\u0644\u06cc\u0627\u0646\u06af"
    ],
    "name:fas_x_preferred":[
        "\u0644\u0626\u0648\u0648\u06cc\u0644\u06cc\u0627\u0646\u06af"
    ],
    "name:fra_x_preferred":[
        "Leuwiliang"
    ],
    "name:ind_x_preferred":[
        "Leuwiliang"
    ],
    "name:jav_x_preferred":[
        "Leuwiliang"
    ],
    "name:nor_x_preferred":[
        "Leuwiliang"
    ],
    "name:sun_x_preferred":[
        "Leuwiliang"
    ],
    "wof:lang_x_official":[
        "ind"
    ],
    "wof:lang_x_spoken":[
        "ind",
        "eng"
    ],
    "wof:name":"Leuwiliang",
    "wof:placetype":"locality"
},
  "geometry": {"coordinates":[108.3065,-7.3793],"type":"Point"}
}