{
  "type": "Feature",
  "properties": {
    "gn:admin1_code":"30.0",
    "gn:asciiname":"Cianten",
    "gn:country_code":"ID",
    "gn:dem":560,
    "gn:feature_class":"P",
    "gn:feature_code":"PPL",
    "gn:name":"Cianten",
    "gn:population":0,
    "gn:timezone":"Asia/Jakarta",
    "iso:country":"ID",
    "name:ind_x_preferred":[
        "Cianten"
    ],
    "name:und_x_variant":[
        "Tjianten",
        "Cianten",
        "Tjianten 1"
    ],
    "wof:lang_x_official":[
        "ind"
    ],
    "wof:lang_x_spoken":[
        "ind",
        "eng"
    ],
    "wof:name":"Cianten",
    "wof:placetype":"locality"
},
  "geometry": {"coordinates":[107.9794,-7.0172],"type":"Point"}
}