{
  "type": "Feature",
  "properties": {
    "gn:admin1_code":"30",
    "gn:asciiname":"Kosambi",
    "gn:cc2":"ID",
    "gn:country_code":"ID",
    "gn:dem":11,
    "gn:feature_class":"P",
    "gn:feature_code":"PPL",
    "gn:name":"Kosambi",
    "gn:population":0,
    "gn:timezone":"Asia/Jakarta",
    "iso:country":"ID",
    "name:und_x_variant":[
        "Kesambi",
        "Kesambi Satu",
        "Kesambi 1",
        "Kosambi"
    ],
    "wof:name":"Kosambi",
    "wof:placetype":"locality"
},
  "geometry": {"coordinates":[106.56861000000001,-6.10583],"type":"Point"}
}