{
  "type": "Feature",
  "properties": {
    "gn:admin1_code":"1",
    "gn:asciiname":"Sibatu-batu Lima",
    "gn:country_code":"ID",
    "gn:dem":24,
    "gn:feature_class":"P",
    "gn:feature_code":"PPL",
    "gn:name":"Sibatu-batu Lima",
    "gn:population":0,
    "gn:timezone":"Asia/Jakarta",
    "iso:country":"ID",
    "name:ind_x_preferred":[
        "Sibatu-batu Lima"
    ],
    "name:und_x_variant":[
        "Sibatu-batu 5"
    ],
    "wof:lang_x_official":[
        "ind"
    ],
    "wof:lang_x_spoken":[
        "ind",
        "eng"
    ],
    "wof:name":"Sibatu-batu Lima",
    "wof:placetype":"locality"
},
  "geometry": {"coordinates":[99.6183,2.934],"type":"Point"}
}