{
  "type": "Feature",
  "properties": {
    "gn:admin1_code":"26",
    "gn:asciiname":"Singa",
    "gn:country_code":"ID",
    "gn:dem":1136,
    "gn:feature_class":"P",
    "gn:feature_code":"PPL",
    "gn:name":"Singa",
    "gn:population":0,
    "gn:timezone":"Asia/Jakarta",
    "iso:country":"ID",
    "name:ind_x_preferred":[
        "Singa"
    ],
    "name:und_x_variant":[
        "Kotasinga"
    ],
    "wof:name":"Singa",
    "wof:placetype":"locality"
},
  "geometry": {"coordinates":[98.46272999999999,3.07495],"type":"Point"}
}