{
  "type": "Feature",
  "properties": {
    "gn:admin1_code":"26",
    "gn:asciiname":"Singa",
    "gn:country_code":"ID",
    "gn:dem":1136,
    "gn:feature_class":"P",
    "gn:feature_code":"PPL",
    "gn:name":"Singa",
    "gn:population":0,
    "gn:timezone":"Asia/Jakarta",
    "iso:country":"ID",
    "name:ceb_x_preferred":[
        "Singa"
    ],
    "name:deu_x_preferred":[
        "Singa"
    ],
    "name:fra_x_preferred":[
        "Singa"
    ],
    "name:ind_x_preferred":[
        "Singa"
    ],
    "name:ita_x_preferred":[
        "Singa"
    ],
    "name:new_x_preferred":[
        "\u0938\u093f\u0902\u0917\u093e"
    ],
    "name:nld_x_preferred":[
        "Singa"
    ],
    "name:por_x_preferred":[
        "Singa"
    ],
    "name:swe_x_preferred":[
        "Singa"
    ],
    "name:und_x_variant":[
        "Kotasinga"
    ],
    "wof:lang_x_official":[
        "ind"
    ],
    "wof:lang_x_spoken":[
        "ind",
        "eng"
    ],
    "wof:name":"Singa",
    "wof:placetype":"locality"
},
  "geometry": {"coordinates":[98.46272999999999,3.07495],"type":"Point"}
}