{
  "type": "Feature",
  "properties": {
    "gn:admin1_code":"8.0",
    "gn:asciiname":"Jubel",
    "gn:country_code":"ID",
    "gn:dem":325,
    "gn:feature_class":"P",
    "gn:feature_code":"PPL",
    "gn:name":"Jubel",
    "gn:population":0,
    "gn:timezone":"Asia/Jakarta",
    "iso:country":"ID",
    "name:ind_x_preferred":[
        "Jubel"
    ],
    "name:und_x_variant":[
        "Djoebel"
    ],
    "wof:name":"Jubel",
    "wof:placetype":"locality"
},
  "geometry": {"coordinates":[112.60039999999999,-8.3008],"type":"Point"}
}