{
  "type": "Feature",
  "properties": {
    "gn:admin1_code":"17.0",
    "gn:asciiname":"Muhajirin",
    "gn:country_code":"ID",
    "gn:dem":54,
    "gn:feature_class":"P",
    "gn:feature_code":"PPLA4",
    "gn:name":"Muhajirin",
    "gn:population":0,
    "gn:timezone":"Asia/Makassar",
    "iso:country":"ID",
    "name:ind_x_preferred":[
        "Muhajirin"
    ],
    "wof:name":"Muhajirin",
    "wof:placetype":"locality"
},
  "geometry": {"coordinates":[117.7183,-8.9027],"type":"Point"}
}