{
  "type": "Feature",
  "properties": {
    "gn:admin1_code":"38",
    "gn:asciiname":"Siteba",
    "gn:country_code":"ID",
    "gn:dem":1321,
    "gn:feature_class":"P",
    "gn:feature_code":"PPL",
    "gn:name":"Siteba",
    "gn:population":0,
    "gn:timezone":"Asia/Makassar",
    "iso:country":"ID",
    "name:ind_x_preferred":[
        "Siteba"
    ],
    "wof:name":"Siteba",
    "wof:placetype":"locality"
},
  "geometry": {"coordinates":[119.92870000000001,-2.7412],"type":"Point"}
}