{
  "type": "Feature",
  "properties": {
    "gn:admin1_code":"08",
    "gn:asciiname":"Tanggulrejo Selatan",
    "gn:country_code":"ID",
    "gn:dem":5,
    "gn:feature_class":"P",
    "gn:feature_code":"PPL",
    "gn:name":"Tanggulrejo Selatan",
    "gn:population":0,
    "gn:timezone":"Asia/Jakarta",
    "iso:country":"ID",
    "name:ind_x_preferred":[
        "Tanggulrejo Selatan"
    ],
    "name:und_x_variant":[
        "Tanggulredjo",
        "Tanggulrejo"
    ],
    "wof:name":"Tanggulrejo Selatan",
    "wof:placetype":"locality"
},
  "geometry": {"coordinates":[112.5382,-7.0866],"type":"Point"}
}