{
  "type": "Feature",
  "properties": {
    "gn:admin1_code":"30",
    "gn:asciiname":"Sukadana",
    "gn:country_code":"ID",
    "gn:dem":20,
    "gn:feature_class":"P",
    "gn:feature_code":"PPL",
    "gn:name":"Sukadana",
    "gn:population":0,
    "gn:timezone":"Asia/Jakarta",
    "iso:country":"ID",
    "name:bjn_x_preferred":[
        "Sukadana"
    ],
    "name:ind_x_preferred":[
        "Sukadana"
    ],
    "name:msa_x_preferred":[
        "Sukadana"
    ],
    "name:wuu_x_preferred":[
        "\u82cf\u5361\u8fbe\u7eb3"
    ],
    "wof:lang_x_official":[
        "ind"
    ],
    "wof:lang_x_spoken":[
        "ind",
        "eng"
    ],
    "wof:name":"Sukadana",
    "wof:placetype":"locality"
},
  "geometry": {"coordinates":[107.30861,-6.34],"type":"Point"}
}