{
  "type": "Feature",
  "properties": {
    "gn:admin1_code":"41.0",
    "gn:asciiname":"Ulidang",
    "gn:country_code":"ID",
    "gn:dem":12,
    "gn:feature_class":"P",
    "gn:feature_code":"PPL",
    "gn:name":"Ulidang",
    "gn:population":0,
    "gn:timezone":"Asia/Makassar",
    "iso:country":"ID",
    "name:ind_x_preferred":[
        "Ulidang"
    ],
    "name:und_x_variant":[
        "Oelidang",
        "Ulidang",
        "Ulidong"
    ],
    "wof:name":"Ulidang",
    "wof:placetype":"locality"
},
  "geometry": {"coordinates":[118.83459999999999,-3.225],"type":"Point"}
}