{
  "type": "Feature",
  "properties": {
    "gn:admin1_code":"30",
    "gn:asciiname":"Wage",
    "gn:country_code":"ID",
    "gn:dem":63,
    "gn:feature_class":"P",
    "gn:feature_code":"PPL",
    "gn:name":"Wage",
    "gn:population":0,
    "gn:timezone":"Asia/Jakarta",
    "iso:country":"ID",
    "name:ind_x_preferred":[
        "Wage"
    ],
    "wof:name":"Wage",
    "wof:placetype":"locality"
},
  "geometry": {"coordinates":[108.57080000000001,-6.7943],"type":"Point"}
}