{
  "type": "Feature",
  "properties": {
    "gn:admin1_code":"26",
    "gn:asciiname":"Sidomulyo Satu",
    "gn:country_code":"ID",
    "gn:dem":16,
    "gn:feature_class":"P",
    "gn:feature_code":"PPL",
    "gn:name":"Sidomulyo Satu",
    "gn:population":0,
    "gn:timezone":"Asia/Jakarta",
    "iso:country":"ID",
    "name:ind_x_preferred":[
        "Sidomulyo Satu"
    ],
    "name:und_x_variant":[
        "Sidomulyo 1"
    ],
    "wof:name":"Sidomulyo Satu",
    "wof:placetype":"locality"
},
  "geometry": {"coordinates":[98.5016,3.6957],"type":"Point"}
}