{
  "type": "Feature",
  "properties": {
    "gn:admin1_code":"18",
    "gn:asciiname":"Ngolo",
    "gn:country_code":"ID",
    "gn:dem":16,
    "gn:feature_class":"P",
    "gn:feature_code":"PPL",
    "gn:name":"Ngolo",
    "gn:population":0,
    "gn:timezone":"Asia/Makassar",
    "iso:country":"ID",
    "name:ind_x_preferred":[
        "Ngolo"
    ],
    "wof:name":"Ngolo",
    "wof:placetype":"locality"
},
  "geometry": {"coordinates":[120.0732,-8.4521],"type":"Point"}
}