{
  "type": "Feature",
  "properties": {
    "gn:admin1_code":"17",
    "gn:asciiname":"Karangpetak",
    "gn:country_code":"ID",
    "gn:dem":434,
    "gn:feature_class":"P",
    "gn:feature_code":"PPL",
    "gn:name":"Karangpetak",
    "gn:population":0,
    "gn:timezone":"Asia/Makassar",
    "iso:country":"ID",
    "name:ind_x_preferred":[
        "Karangpetak"
    ],
    "wof:name":"Karangpetak",
    "wof:placetype":"locality"
},
  "geometry": {"coordinates":[116.51300000000001,-8.5418],"type":"Point"}
}