{
  "type": "Feature",
  "properties": {
    "gn:admin1_code":"7.0",
    "gn:asciiname":"Watubarut",
    "gn:country_code":"ID",
    "gn:dem":264,
    "gn:feature_class":"P",
    "gn:feature_code":"PPL",
    "gn:name":"Watubarut",
    "gn:population":0,
    "gn:timezone":"Asia/Jakarta",
    "iso:country":"ID",
    "name:ind_x_preferred":[
        "Watubarut"
    ],
    "wof:name":"Watubarut",
    "wof:placetype":"locality"
},
  "geometry": {"coordinates":[109.6375,-7.59917],"type":"Point"}
}