{
  "type": "Feature",
  "properties": {
    "gn:admin1_code":"18.0",
    "gn:asciiname":"Rita",
    "gn:country_code":"ID",
    "gn:dem":481,
    "gn:feature_class":"P",
    "gn:feature_code":"PPL",
    "gn:name":"Rita",
    "gn:population":0,
    "gn:timezone":"Asia/Makassar",
    "iso:country":"ID",
    "name:deu_x_preferred":[
        "Rita"
    ],
    "name:est_x_preferred":[
        "Rita"
    ],
    "name:fas_x_preferred":[
        "\u0631\u06cc\u062a\u0627"
    ],
    "name:fin_x_preferred":[
        "Rita"
    ],
    "name:fra_x_preferred":[
        "Rita"
    ],
    "name:heb_x_preferred":[
        "\u05e8\u05d9\u05d8\u05d4"
    ],
    "name:ind_x_preferred":[
        "Rita"
    ],
    "name:isl_x_preferred":[
        "Rita"
    ],
    "name:ita_x_preferred":[
        "Rita"
    ],
    "name:nld_x_preferred":[
        "Rita"
    ],
    "name:pol_x_preferred":[
        "Rita"
    ],
    "name:spa_x_preferred":[
        "Rita"
    ],
    "name:swe_x_preferred":[
        "Rita"
    ],
    "name:tam_x_preferred":[
        "\u0bb0\u0bc0\u0b9f\u0bcd\u0b9f\u0bbe"
    ],
    "wof:lang_x_official":[
        "ind"
    ],
    "wof:lang_x_spoken":[
        "ind",
        "eng"
    ],
    "wof:name":"Rita",
    "wof:placetype":"locality"
},
  "geometry": {"coordinates":[120.4564,-10.1496],"type":"Point"}
}