{
  "type": "Feature",
  "properties": {
    "gn:admin1_code":"26",
    "gn:asciiname":"Damak",
    "gn:country_code":"ID",
    "gn:dem":886,
    "gn:feature_class":"P",
    "gn:feature_code":"PPL",
    "gn:name":"Damak",
    "gn:population":0,
    "gn:timezone":"Asia/Jakarta",
    "iso:country":"ID",
    "name:bih_x_preferred":[
        "\u0926\u092e\u0915"
    ],
    "name:deu_x_preferred":[
        "Damak"
    ],
    "name:dty_x_preferred":[
        "\u0926\u092e\u0915 \u0928\u0917\u0930\u092a\u093e\u0932\u093f\u0915\u093e"
    ],
    "name:eus_x_preferred":[
        "Damak"
    ],
    "name:fin_x_preferred":[
        "Damak"
    ],
    "name:fra_x_preferred":[
        "Damak"
    ],
    "name:hif_x_preferred":[
        "Damak"
    ],
    "name:hin_x_preferred":[
        "\u0926\u092e\u0915"
    ],
    "name:ind_x_preferred":[
        "Damak"
    ],
    "name:ita_x_preferred":[
        "Damak"
    ],
    "name:jpn_x_preferred":[
        "\u30c0\u30de\u30af"
    ],
    "name:mai_x_preferred":[
        "\u0926\u092e\u0915 \u0928\u0917\u0930\u092a\u093e\u0932\u093f\u0915\u093e"
    ],
    "name:msa_x_preferred":[
        "Damak"
    ],
    "name:nep_x_preferred":[
        "\u0926\u092e\u0915 \u0928\u0917\u0930\u092a\u093e\u0932\u093f\u0915\u093e"
    ],
    "name:new_x_preferred":[
        "\u0926\u092e\u0915"
    ],
    "name:nld_x_preferred":[
        "Damak"
    ],
    "name:pol_x_preferred":[
        "Damak"
    ],
    "name:rus_x_preferred":[
        "\u0414\u0430\u043c\u0430\u043a"
    ],
    "name:urd_x_preferred":[
        "\u062f\u0645\u06a9"
    ],
    "name:zho_x_preferred":[
        "\u9053\u6bdb\u514b"
    ],
    "wof:lang_x_official":[
        "ind"
    ],
    "wof:lang_x_spoken":[
        "ind",
        "eng"
    ],
    "wof:name":"Damak",
    "wof:placetype":"locality"
},
  "geometry": {"coordinates":[98.84310000000001,3.0304],"type":"Point"}
}