{
  "type": "Feature",
  "properties": {
    "gn:admin1_code":"26",
    "gn:asciiname":"Damak",
    "gn:country_code":"ID",
    "gn:dem":886,
    "gn:feature_class":"P",
    "gn:feature_code":"PPL",
    "gn:name":"Damak",
    "gn:population":0,
    "gn:timezone":"Asia/Jakarta",
    "iso:country":"ID",
    "name:ind_x_preferred":[
        "Damak"
    ],
    "wof:name":"Damak",
    "wof:placetype":"locality"
},
  "geometry": {"coordinates":[98.84310000000001,3.0304],"type":"Point"}
}