{
  "type": "Feature",
  "properties": {
    "gn:admin1_code":"18.0",
    "gn:asciiname":"Lada",
    "gn:country_code":"ID",
    "gn:dem":815,
    "gn:feature_class":"P",
    "gn:feature_code":"PPL",
    "gn:name":"Lada",
    "gn:population":0,
    "gn:timezone":"Asia/Makassar",
    "iso:country":"ID",
    "name:ind_x_preferred":[
        "Lada"
    ],
    "wof:name":"Lada",
    "wof:placetype":"locality"
},
  "geometry": {"coordinates":[120.7189,-8.6801],"type":"Point"}
}