{
  "type": "Feature",
  "properties": {
    "gn:admin1_code":"30.0",
    "gn:asciiname":"Rancabitung",
    "gn:country_code":"ID",
    "gn:dem":695,
    "gn:feature_class":"P",
    "gn:feature_code":"PPL",
    "gn:name":"Rancabitung",
    "gn:population":0,
    "gn:timezone":"Asia/Jakarta",
    "iso:country":"ID",
    "name:ind_x_preferred":[
        "Rancabitung"
    ],
    "wof:name":"Rancabitung",
    "wof:placetype":"locality"
},
  "geometry": {"coordinates":[107.50409999999999,-7.3232],"type":"Point"}
}