{
  "type": "Feature",
  "properties": {
    "gn:admin1_code":"30",
    "gn:asciiname":"Panembong Wetan",
    "gn:country_code":"ID",
    "gn:dem":509,
    "gn:feature_class":"P",
    "gn:feature_code":"PPL",
    "gn:name":"Panembong Wetan",
    "gn:population":0,
    "gn:timezone":"Asia/Jakarta",
    "iso:country":"ID",
    "name:ind_x_preferred":[
        "Panembong Wetan"
    ],
    "wof:name":"Panembong Wetan",
    "wof:placetype":"locality"
},
  "geometry": {"coordinates":[107.12611,-6.81306],"type":"Point"}
}