{
  "type": "Feature",
  "properties": {
    "gn:admin1_code":"33.0",
    "gn:asciiname":"Pasirsireum",
    "gn:country_code":"ID",
    "gn:dem":262,
    "gn:feature_class":"P",
    "gn:feature_code":"PPL",
    "gn:name":"Pasirsireum",
    "gn:population":0,
    "gn:timezone":"Asia/Jakarta",
    "iso:country":"ID",
    "name:ind_x_preferred":[
        "Pasirsireum"
    ],
    "wof:name":"Pasirsireum",
    "wof:placetype":"locality"
},
  "geometry": {"coordinates":[106.09995000000001,-6.81543],"type":"Point"}
}