{
  "type": "Feature",
  "properties": {
    "gn:admin1_code":"7.0",
    "gn:asciiname":"Ngampel",
    "gn:country_code":"ID",
    "gn:dem":757,
    "gn:feature_class":"P",
    "gn:feature_code":"PPL",
    "gn:name":"Ngampel",
    "gn:population":0,
    "gn:timezone":"Asia/Jakarta",
    "iso:country":"ID",
    "wof:name":"Ngampel",
    "wof:placetype":"locality"
},
  "geometry": {"coordinates":[110.11221999999999,-7.48278],"type":"Point"}
}