{
  "type": "Feature",
  "properties": {
    "gn:admin1_code":"08",
    "gn:asciiname":"Glanggang",
    "gn:country_code":"ID",
    "gn:dem":381,
    "gn:feature_class":"P",
    "gn:feature_code":"PPLA4",
    "gn:name":"Glanggang",
    "gn:population":0,
    "gn:timezone":"Asia/Jakarta",
    "iso:country":"ID",
    "name:ind_x_preferred":[
        "Glanggang"
    ],
    "wof:name":"Glanggang",
    "wof:placetype":"locality"
},
  "geometry": {"coordinates":[112.59910000000001,-8.082],"type":"Point"}
}