{
  "type": "Feature",
  "properties": {
    "gn:admin1_code":"8.0",
    "gn:asciiname":"Kajang",
    "gn:country_code":"ID",
    "gn:dem":253,
    "gn:feature_class":"P",
    "gn:feature_code":"PPL",
    "gn:name":"Kajang",
    "gn:population":0,
    "gn:timezone":"Asia/Jakarta",
    "iso:country":"ID",
    "name:bul_x_preferred":[
        "\u041a\u0430\u0434\u0436\u0430\u043d\u0433"
    ],
    "name:ces_x_preferred":[
        "Kajang"
    ],
    "name:epo_x_preferred":[
        "Kajang"
    ],
    "name:fra_x_preferred":[
        "Kajang"
    ],
    "name:ind_x_preferred":[
        "Kajang"
    ],
    "name:ita_x_preferred":[
        "Kajang"
    ],
    "name:msa_x_preferred":[
        "Kajang"
    ],
    "name:nld_x_preferred":[
        "Kajang"
    ],
    "name:pol_x_preferred":[
        "Kajang-Sungai Chua"
    ],
    "name:tam_x_preferred":[
        "\u0b95\u0bbe\u0b9c\u0bbe\u0b99\u0bcd"
    ],
    "name:tha_x_preferred":[
        "\u0e01\u0e32\u0e08\u0e31\u0e07"
    ],
    "name:tur_x_preferred":[
        "Kajang"
    ],
    "name:urd_x_preferred":[
        "\u06a9\u0627\u062c\u0627\u0646\u06af"
    ],
    "name:vie_x_preferred":[
        "Kajang"
    ],
    "name:war_x_preferred":[
        "Kajang"
    ],
    "wof:name":"Kajang",
    "wof:placetype":"locality"
},
  "geometry": {"coordinates":[112.3081,-7.7924],"type":"Point"}
}