{
  "type": "Feature",
  "properties": {
    "gn:admin1_code":"7",
    "gn:asciiname":"Tawangrejo",
    "gn:country_code":"ID",
    "gn:dem":591,
    "gn:feature_class":"P",
    "gn:feature_code":"PPL",
    "gn:name":"Tawangrejo",
    "gn:population":0,
    "gn:timezone":"Asia/Jakarta",
    "iso:country":"ID",
    "name:ind_x_preferred":[
        "Tawangrejo"
    ],
    "wof:name":"Tawangrejo",
    "wof:placetype":"locality"
},
  "geometry": {"coordinates":[111.12778,-7.55056],"type":"Point"}
}