{
  "type": "Feature",
  "properties": {
    "gn:admin1_code":"18",
    "gn:asciiname":"Lawan",
    "gn:country_code":"ID",
    "gn:dem":673,
    "gn:feature_class":"P",
    "gn:feature_code":"PPL",
    "gn:name":"Lawan",
    "gn:population":0,
    "gn:timezone":"Asia/Makassar",
    "iso:country":"ID",
    "name:ind_x_preferred":[
        "Lawan"
    ],
    "wof:name":"Lawan",
    "wof:placetype":"locality"
},
  "geometry": {"coordinates":[120.7513,-8.5157],"type":"Point"}
}