{
  "type": "Feature",
  "properties": {
    "gn:admin1_code":"07",
    "gn:asciiname":"Kenangan",
    "gn:country_code":"ID",
    "gn:dem":1323,
    "gn:feature_class":"P",
    "gn:feature_code":"PPL",
    "gn:name":"Kenangan",
    "gn:population":0,
    "gn:timezone":"Asia/Jakarta",
    "iso:country":"ID",
    "name:und_x_variant":[
        "Kenanggan 2",
        "Kenanggan Dua",
        "Kenangan"
    ],
    "wof:name":"Kenangan",
    "wof:placetype":"locality"
},
  "geometry": {"coordinates":[110.38889,-7.43167],"type":"Point"}
}