{
  "type": "Feature",
  "properties": {
    "gn:country":"ID",
    "gn:fcode":"PPLA4",
    "gn:pop":0,
    "iso:country":"ID",
    "name:ind_x_preferred":[
        "Pagerwojo"
    ],
    "qs:name":"Pagerwojo",
    "qs:photos_9r":0,
    "qs:photos_sr":0,
    "qs:pop_sr":"0",
    "wof:name":"Pagerwojo",
    "wof:placetype":"locality",
    "wof:population":0
},
  "geometry": {"coordinates":[112.4021,-7.1196],"type":"Point"}
}