{
  "type": "Feature",
  "properties": {
    "gn:admin1_code":"22.0",
    "gn:asciiname":"Purwosari",
    "gn:country_code":"ID",
    "gn:dem":34,
    "gn:feature_class":"P",
    "gn:feature_code":"PPL",
    "gn:name":"Purwosari",
    "gn:population":0,
    "gn:timezone":"Asia/Makassar",
    "iso:country":"ID",
    "name:ind_x_preferred":[
        "Purwosari"
    ],
    "wof:name":"Purwosari",
    "wof:placetype":"locality"
},
  "geometry": {"coordinates":[122.0363,-3.8428],"type":"Point"}
}