{
  "type": "Feature",
  "properties": {
    "gn:admin1_code":"7.0",
    "gn:asciiname":"Dawe",
    "gn:country_code":"ID",
    "gn:dem":175,
    "gn:feature_class":"P",
    "gn:feature_code":"PPL",
    "gn:name":"Dawe",
    "gn:population":0,
    "gn:timezone":"Asia/Jakarta",
    "iso:country":"ID",
    "wof:name":"Dawe",
    "wof:placetype":"locality"
},
  "geometry": {"coordinates":[110.94110999999999,-7.99361],"type":"Point"}
}