{
  "type": "Feature",
  "properties": {
    "gn:admin1_code":"18.0",
    "gn:asciiname":"Nggolar",
    "gn:country_code":"ID",
    "gn:dem":424,
    "gn:feature_class":"P",
    "gn:feature_code":"PPL",
    "gn:name":"Nggolar",
    "gn:population":0,
    "gn:timezone":"Asia/Makassar",
    "iso:country":"ID",
    "name:ind_x_preferred":[
        "Nggolar"
    ],
    "wof:name":"Nggolar",
    "wof:placetype":"locality"
},
  "geometry": {"coordinates":[120.045,-8.6826],"type":"Point"}
}