{
  "type": "Feature",
  "properties": {
    "gn:admin1_code":"07",
    "gn:asciiname":"Candisari",
    "gn:country_code":"ID",
    "gn:dem":577,
    "gn:feature_class":"P",
    "gn:feature_code":"PPL",
    "gn:name":"Candisari",
    "gn:population":0,
    "gn:timezone":"Asia/Jakarta",
    "iso:country":"ID",
    "wof:name":"Candisari",
    "wof:placetype":"locality"
},
  "geometry": {"coordinates":[110.56806,-7.51167],"type":"Point"}
}