{
  "type": "Feature",
  "properties": {
    "gn:admin1_code":"18.0",
    "gn:asciiname":"Pukalokedo",
    "gn:country_code":"ID",
    "gn:dem":117,
    "gn:feature_class":"P",
    "gn:feature_code":"PPL",
    "gn:name":"Pukalokedo",
    "gn:population":0,
    "gn:timezone":"Asia/Makassar",
    "iso:country":"ID",
    "name:ind_x_preferred":[
        "Pukalokedo"
    ],
    "wof:name":"Pukalokedo",
    "wof:placetype":"locality"
},
  "geometry": {"coordinates":[119.3912,-9.4548],"type":"Point"}
}