{
  "type": "Feature",
  "properties": {
    "gn:admin1_code":"10",
    "gn:asciiname":"Sosrowijayan Wetan",
    "gn:country_code":"ID",
    "gn:dem":115,
    "gn:feature_class":"P",
    "gn:feature_code":"PPL",
    "gn:name":"Sosrowijayan Wetan",
    "gn:population":0,
    "gn:timezone":"Asia/Jakarta",
    "iso:country":"ID",
    "wof:name":"Sosrowijayan Wetan",
    "wof:placetype":"locality"
},
  "geometry": {"coordinates":[110.36028,-7.78944],"type":"Point"}
}