{
  "type": "Feature",
  "properties": {
    "gn:admin1_code":"18.0",
    "gn:asciiname":"Adiwiringabang",
    "gn:country_code":"ID",
    "gn:dem":21,
    "gn:feature_class":"P",
    "gn:feature_code":"PPL",
    "gn:name":"Adiwiringabang",
    "gn:population":0,
    "gn:timezone":"Asia/Makassar",
    "iso:country":"ID",
    "name:ind_x_preferred":[
        "Adiwiringabang"
    ],
    "wof:name":"Adiwiringabang",
    "wof:placetype":"locality"
},
  "geometry": {"coordinates":[124.3648,-8.3193],"type":"Point"}
}