{
  "type": "Feature",
  "properties": {
    "gn:admin1_code":"26.0",
    "gn:asciiname":"Sosorlangit",
    "gn:country_code":"ID",
    "gn:dem":955,
    "gn:feature_class":"P",
    "gn:feature_code":"PPL",
    "gn:name":"Sosorlangit",
    "gn:population":0,
    "gn:timezone":"Asia/Jakarta",
    "iso:country":"ID",
    "name:ind_x_preferred":[
        "Sosorlangit"
    ],
    "wof:name":"Sosorlangit",
    "wof:placetype":"locality"
},
  "geometry": {"coordinates":[98.5909,2.1409],"type":"Point"}
}