{
  "type": "Feature",
  "properties": {
    "gn:admin1_code":"8.0",
    "gn:asciiname":"Sidomakmur",
    "gn:country_code":"ID",
    "gn:dem":8,
    "gn:feature_class":"P",
    "gn:feature_code":"PPL",
    "gn:name":"Sidomakmur",
    "gn:population":0,
    "gn:timezone":"Asia/Jakarta",
    "iso:country":"ID",
    "name:ind_x_preferred":[
        "Sidomakmur"
    ],
    "wof:name":"Sidomakmur",
    "wof:placetype":"locality"
},
  "geometry": {"coordinates":[112.5502,-6.9684],"type":"Point"}
}