{
  "type": "Feature",
  "properties": {
    "gn:admin1_code":"30.0",
    "gn:asciiname":"Girikarya",
    "gn:country_code":"ID",
    "gn:dem":559,
    "gn:feature_class":"P",
    "gn:feature_code":"PPLA4",
    "gn:name":"Girikarya",
    "gn:population":0,
    "gn:timezone":"Asia/Jakarta",
    "iso:country":"ID",
    "name:ind_x_preferred":[
        "Girikarya"
    ],
    "wof:lang_x_official":[
        "ind"
    ],
    "wof:lang_x_spoken":[
        "ind",
        "eng"
    ],
    "wof:name":"Girikarya",
    "wof:placetype":"locality"
},
  "geometry": {"coordinates":[108.3847,-7.5315],"type":"Point"}
}