{
  "type": "Feature",
  "properties": {
    "gn:admin1_code":"07",
    "gn:asciiname":"Cleput",
    "gn:country_code":"ID",
    "gn:dem":290,
    "gn:feature_class":"P",
    "gn:feature_code":"PPL",
    "gn:name":"Cleput",
    "gn:population":0,
    "gn:timezone":"Asia/Jakarta",
    "iso:country":"ID",
    "wof:name":"Cleput",
    "wof:placetype":"locality"
},
  "geometry": {"coordinates":[110.53055999999999,-7.67694],"type":"Point"}
}