{
  "type": "Feature",
  "properties": {
    "gn:admin1_code":"7.0",
    "gn:asciiname":"Kauman",
    "gn:country_code":"ID",
    "gn:dem":446,
    "gn:feature_class":"P",
    "gn:feature_code":"PPL",
    "gn:name":"Kauman",
    "gn:population":0,
    "gn:timezone":"Asia/Jakarta",
    "iso:country":"ID",
    "name:ind_x_preferred":[
        "Kauman"
    ],
    "name:msa_x_preferred":[
        "Kauman"
    ],
    "name:nld_x_preferred":[
        "Kauman"
    ],
    "wof:name":"Kauman",
    "wof:placetype":"locality"
},
  "geometry": {"coordinates":[110.25333000000001,-7.4175],"type":"Point"}
}