{
  "type": "Feature",
  "properties": {
    "gn:admin1_code":"26",
    "gn:asciiname":"Ngikil",
    "gn:country_code":"ID",
    "gn:dem":247,
    "gn:feature_class":"P",
    "gn:feature_code":"PPL",
    "gn:name":"Ngikil",
    "gn:population":0,
    "gn:timezone":"Asia/Jakarta",
    "iso:country":"ID",
    "name:ind_x_preferred":[
        "Ngikil"
    ],
    "name:und_x_variant":[
        "Ngilkil"
    ],
    "wof:name":"Ngikil",
    "wof:placetype":"locality"
},
  "geometry": {"coordinates":[98.3147,3.4073],"type":"Point"}
}