{
  "type": "Feature",
  "properties": {
    "gn:admin1_code":"0.0",
    "gn:asciiname":"Jlegong",
    "gn:cc2":"ID",
    "gn:country_code":"ID",
    "gn:dem":84,
    "gn:feature_class":"P",
    "gn:feature_code":"PPL",
    "gn:name":"Jlegong",
    "gn:population":0,
    "gn:timezone":"Asia/Jakarta",
    "iso:country":"ID",
    "name:und_x_variant":[
        "Djlegong",
        "Jlegong"
    ],
    "wof:name":"Jlegong",
    "wof:placetype":"locality"
},
  "geometry": {"coordinates":[110.88333,-6.46667],"type":"Point"}
}