{
  "type": "Feature",
  "properties": {
    "gn:admin1_code":"29.0",
    "gn:asciiname":"Parapara",
    "gn:country_code":"ID",
    "gn:dem":10,
    "gn:feature_class":"P",
    "gn:feature_code":"PPL",
    "gn:name":"Parapara",
    "gn:population":0,
    "gn:timezone":"Asia/Jayapura",
    "iso:country":"ID",
    "name:ceb_x_preferred":[
        "Parapara"
    ],
    "name:deu_x_preferred":[
        "Parapara"
    ],
    "name:fra_x_preferred":[
        "Parapara"
    ],
    "wof:lang_x_official":[
        "ind"
    ],
    "wof:lang_x_spoken":[
        "ind",
        "eng"
    ],
    "wof:name":"Parapara",
    "wof:placetype":"locality"
},
  "geometry": {"coordinates":[127.90594,0.85369],"type":"Point"}
}