{
  "type": "Feature",
  "properties": {
    "gn:admin1_code":"21.0",
    "gn:asciiname":"Sea",
    "gn:country_code":"ID",
    "gn:dem":400,
    "gn:feature_class":"P",
    "gn:feature_code":"PPL",
    "gn:name":"Sea",
    "gn:population":0,
    "gn:timezone":"Asia/Makassar",
    "iso:country":"ID",
    "name:ind_x_preferred":[
        "Sea"
    ],
    "name:und_x_variant":[
        "Salea"
    ],
    "wof:name":"Sea",
    "wof:placetype":"locality"
},
  "geometry": {"coordinates":[121.8775,-1.5056],"type":"Point"}
}