{
  "type": "Feature",
  "properties": {
    "gn:admin1_code":"7",
    "gn:asciiname":"Wates",
    "gn:country_code":"ID",
    "gn:dem":61,
    "gn:feature_class":"P",
    "gn:feature_code":"PPL",
    "gn:name":"Wates",
    "gn:population":0,
    "gn:timezone":"Asia/Jakarta",
    "iso:country":"ID",
    "name:ceb_x_preferred":[
        "Wates"
    ],
    "name:ind_x_preferred":[
        "Wates"
    ],
    "name:nld_x_preferred":[
        "Wates"
    ],
    "name:swe_x_preferred":[
        "Wates"
    ],
    "wof:lang_x_official":[
        "ind"
    ],
    "wof:lang_x_spoken":[
        "ind",
        "eng"
    ],
    "wof:name":"Wates",
    "wof:placetype":"locality"
},
  "geometry": {"coordinates":[111.14472000000001,-7.15361],"type":"Point"}
}