{
  "type": "Feature",
  "properties": {
    "gn:admin1_code":"8",
    "gn:asciiname":"Banyurejo Kidul",
    "gn:country_code":"ID",
    "gn:dem":490,
    "gn:feature_class":"P",
    "gn:feature_code":"PPL",
    "gn:name":"Banyurejo Kidul",
    "gn:population":0,
    "gn:timezone":"Asia/Jakarta",
    "iso:country":"ID",
    "name:ind_x_preferred":[
        "Banyurejo Kidul"
    ],
    "wof:name":"Banyurejo Kidul",
    "wof:placetype":"locality"
},
  "geometry": {"coordinates":[114.18241999999999,-8.20532],"type":"Point"}
}