{
  "type": "Feature",
  "properties": {
    "gn:admin1_code":"8",
    "gn:asciiname":"Pangdekong",
    "gn:country_code":"ID",
    "gn:dem":15,
    "gn:feature_class":"P",
    "gn:feature_code":"PPL",
    "gn:name":"Pangdekong",
    "gn:population":0,
    "gn:timezone":"Asia/Jakarta",
    "iso:country":"ID",
    "name:ind_x_preferred":[
        "Pangdekong"
    ],
    "wof:name":"Pangdekong",
    "wof:placetype":"locality"
},
  "geometry": {"coordinates":[112.9376,-7.1766],"type":"Point"}
}