{
  "type": "Feature",
  "properties": {
    "gn:admin1_code":"18.0",
    "gn:asciiname":"Welnoah",
    "gn:country_code":"ID",
    "gn:dem":308,
    "gn:feature_class":"P",
    "gn:feature_code":"PPL",
    "gn:name":"Welnoah",
    "gn:population":0,
    "gn:timezone":"Asia/Makassar",
    "iso:country":"ID",
    "name:ind_x_preferred":[
        "Welnoah"
    ],
    "wof:name":"Welnoah",
    "wof:placetype":"locality"
},
  "geometry": {"coordinates":[123.8643,-9.788],"type":"Point"}
}