{
  "type": "Feature",
  "properties": {
    "gn:admin1_code":"0.0",
    "gn:asciiname":"Tumbangjuluh",
    "gn:cc2":"ID",
    "gn:country_code":"ID",
    "gn:dem":42,
    "gn:feature_class":"P",
    "gn:feature_code":"PPL",
    "gn:name":"Tumbangjuluh",
    "gn:population":0,
    "gn:timezone":"Asia/Pontianak",
    "iso:country":"ID",
    "name:und_x_variant":[
        "Tumbangdjuluh",
        "Toembangdjoeloeh",
        "Tumbangjuluh"
    ],
    "wof:lang_x_official":[
        "ind"
    ],
    "wof:lang_x_spoken":[
        "ind",
        "eng"
    ],
    "wof:name":"Tumbangjuluh",
    "wof:placetype":"locality"
},
  "geometry": {"coordinates":[113.53333000000001,-1.31667],"type":"Point"}
}