{
  "type": "Feature",
  "properties": {
    "gn:admin1_code":"30.0",
    "gn:asciiname":"Cibolang",
    "gn:country_code":"ID",
    "gn:dem":650,
    "gn:feature_class":"P",
    "gn:feature_code":"PPLA4",
    "gn:name":"Cibolang",
    "gn:population":0,
    "gn:timezone":"Asia/Jakarta",
    "iso:country":"ID",
    "name:ind_x_preferred":[
        "Cibolang"
    ],
    "name:und_x_variant":[
        "Pasirtjibolang"
    ],
    "wof:lang_x_official":[
        "ind"
    ],
    "wof:lang_x_spoken":[
        "ind",
        "eng"
    ],
    "wof:name":"Cibolang",
    "wof:placetype":"locality"
},
  "geometry": {"coordinates":[107.9333,-7.0927],"type":"Point"}
}