{
  "type": "Feature",
  "properties": {
    "gn:admin1_code":"7",
    "gn:asciiname":"Ngasinan",
    "gn:country_code":"ID",
    "gn:dem":14,
    "gn:feature_class":"P",
    "gn:feature_code":"PPL",
    "gn:name":"Ngasinan",
    "gn:population":0,
    "gn:timezone":"Asia/Jakarta",
    "iso:country":"ID",
    "name:ind_x_preferred":[
        "Ngasinan"
    ],
    "wof:name":"Ngasinan",
    "wof:placetype":"locality"
},
  "geometry": {"coordinates":[110.0873,-6.9702],"type":"Point"}
}