{
  "type": "Feature",
  "properties": {
    "gn:admin1_code":"30.0",
    "gn:asciiname":"Beubeudahan",
    "gn:country_code":"ID",
    "gn:dem":375,
    "gn:feature_class":"P",
    "gn:feature_code":"PPL",
    "gn:name":"Beubeudahan",
    "gn:population":0,
    "gn:timezone":"Asia/Jakarta",
    "iso:country":"ID",
    "name:ind_x_preferred":[
        "Beubeudahan"
    ],
    "name:und_x_variant":[
        "Bebedahan"
    ],
    "wof:lang_x_official":[
        "ind"
    ],
    "wof:lang_x_spoken":[
        "ind",
        "eng"
    ],
    "wof:name":"Beubeudahan",
    "wof:placetype":"locality"
},
  "geometry": {"coordinates":[108.1053,-7.5011],"type":"Point"}
}