{
  "type": "Feature",
  "properties": {
    "gn:admin1_code":"30.0",
    "gn:asciiname":"Mariuk",
    "gn:country_code":"ID",
    "gn:dem":12,
    "gn:feature_class":"P",
    "gn:feature_code":"PPL",
    "gn:name":"Mariuk",
    "gn:population":0,
    "gn:timezone":"Asia/Jakarta",
    "iso:country":"ID",
    "name:ind_x_preferred":[
        "Mariuk"
    ],
    "wof:name":"Mariuk",
    "wof:placetype":"locality"
},
  "geometry": {"coordinates":[107.80889000000001,-6.31639],"type":"Point"}
}