{
  "type": "Feature",
  "properties": {
    "gn:admin1_code":"18.0",
    "gn:asciiname":"Oetilo",
    "gn:country_code":"ID",
    "gn:dem":850,
    "gn:feature_class":"P",
    "gn:feature_code":"PPL",
    "gn:name":"Oetilo",
    "gn:population":0,
    "gn:timezone":"Asia/Makassar",
    "iso:country":"ID",
    "name:ind_x_preferred":[
        "Oetilo"
    ],
    "wof:name":"Oetilo",
    "wof:placetype":"locality"
},
  "geometry": {"coordinates":[124.5438,-9.9429],"type":"Point"}
}