{
  "type": "Feature",
  "properties": {
    "gn:admin1_code":"8.0",
    "gn:asciiname":"Budagan Satu",
    "gn:country_code":"ID",
    "gn:dem":117,
    "gn:feature_class":"P",
    "gn:feature_code":"PPL",
    "gn:name":"Budagan Satu",
    "gn:population":0,
    "gn:timezone":"Asia/Jakarta",
    "iso:country":"ID",
    "name:ind_x_preferred":[
        "Budagan Satu"
    ],
    "wof:name":"Budagan Satu",
    "wof:placetype":"locality"
},
  "geometry": {"coordinates":[113.5659,-7.1023],"type":"Point"}
}