{
  "type": "Feature",
  "properties": {
    "gn:admin1_code":"08",
    "gn:asciiname":"Lopaco",
    "gn:cc2":"ID",
    "gn:country_code":"ID",
    "gn:dem":402,
    "gn:feature_class":"P",
    "gn:feature_code":"PPL",
    "gn:name":"Lopaco",
    "gn:population":0,
    "gn:timezone":"Asia/Jakarta",
    "iso:country":"ID",
    "name:und_x_variant":[
        "Lopatjo",
        "Lopaco"
    ],
    "wof:lang_x_official":[
        "ind"
    ],
    "wof:lang_x_spoken":[
        "ind",
        "eng"
    ],
    "wof:name":"Lopaco",
    "wof:placetype":"locality"
},
  "geometry": {"coordinates":[112.63444,-8.11528],"type":"Point"}
}