{
  "type": "Feature",
  "properties": {
    "gn:admin1_code":"8.0",
    "gn:asciiname":"Talunsono",
    "gn:country_code":"ID",
    "gn:dem":73,
    "gn:feature_class":"P",
    "gn:feature_code":"PPL",
    "gn:name":"Talunsono",
    "gn:population":0,
    "gn:timezone":"Asia/Jakarta",
    "iso:country":"ID",
    "name:ind_x_preferred":[
        "Talunsono"
    ],
    "wof:name":"Talunsono",
    "wof:placetype":"locality"
},
  "geometry": {"coordinates":[112.0895,-7.3193],"type":"Point"}
}