{
  "type": "Feature",
  "properties": {
    "gn:admin1_code":"1",
    "gn:asciiname":"Mekhiau",
    "gn:country_code":"ID",
    "gn:dem":12,
    "gn:feature_class":"P",
    "gn:feature_code":"PPL",
    "gn:name":"Mekhiau",
    "gn:population":0,
    "gn:timezone":"Asia/Jakarta",
    "iso:country":"ID",
    "name:ind_x_preferred":[
        "Mekhiau"
    ],
    "name:und_x_variant":[
        "Mechiau"
    ],
    "wof:name":"Mekhiau",
    "wof:placetype":"locality"
},
  "geometry": {"coordinates":[95.9769,2.7902],"type":"Point"}
}