{
  "type": "Feature",
  "properties": {
    "gn:admin1_code":"30",
    "gn:asciiname":"Konar Lebak",
    "gn:country_code":"ID",
    "gn:dem":32,
    "gn:feature_class":"P",
    "gn:feature_code":"PPL",
    "gn:name":"Konar Lebak",
    "gn:population":0,
    "gn:timezone":"Asia/Jakarta",
    "iso:country":"ID",
    "name:ind_x_preferred":[
        "Konar Lebak"
    ],
    "name:und_x_variant":[
        "Konar 1",
        "Konar Satu"
    ],
    "wof:name":"Konar Lebak",
    "wof:placetype":"locality"
},
  "geometry": {"coordinates":[106.39167,-6.29],"type":"Point"}
}