{
  "type": "Feature",
  "properties": {
    "gn:admin1_code":"30",
    "gn:asciiname":"Jambuhala",
    "gn:country_code":"ID",
    "gn:dem":996,
    "gn:feature_class":"P",
    "gn:feature_code":"PPL",
    "gn:name":"Jambuhala",
    "gn:population":0,
    "gn:timezone":"Asia/Jakarta",
    "iso:country":"ID",
    "name:ind_x_preferred":[
        "Jambuhala"
    ],
    "name:und_x_variant":[
        "Djambuhala"
    ],
    "wof:name":"Jambuhala",
    "wof:placetype":"locality"
},
  "geometry": {"coordinates":[107.3472,-7.0065],"type":"Point"}
}