{
  "type": "Feature",
  "properties": {
    "gn:admin1_code":"17",
    "gn:asciiname":"Repok Barat",
    "gn:country_code":"ID",
    "gn:dem":423,
    "gn:feature_class":"P",
    "gn:feature_code":"PPL",
    "gn:name":"Repok Barat",
    "gn:population":0,
    "gn:timezone":"Asia/Makassar",
    "iso:country":"ID",
    "name:ind_x_preferred":[
        "Repok Barat"
    ],
    "wof:name":"Repok Barat",
    "wof:placetype":"locality"
},
  "geometry": {"coordinates":[116.464,-8.5678],"type":"Point"}
}