{
  "type": "Feature",
  "properties": {
    "gn:admin1_code":"31",
    "gn:asciiname":"Tinoor Dua",
    "gn:country_code":"ID",
    "gn:dem":609,
    "gn:feature_class":"P",
    "gn:feature_code":"PPL",
    "gn:name":"Tinoor Dua",
    "gn:population":0,
    "gn:timezone":"Asia/Makassar",
    "iso:country":"ID",
    "name:ind_x_preferred":[
        "Tinoor Dua"
    ],
    "name:und_x_variant":[
        "Tinoor 2"
    ],
    "wof:lang_x_official":[
        "ind"
    ],
    "wof:lang_x_spoken":[
        "ind",
        "eng"
    ],
    "wof:name":"Tinoor Dua",
    "wof:placetype":"locality"
},
  "geometry": {"coordinates":[124.82689999999999,1.3878],"type":"Point"}
}