{
  "type": "Feature",
  "properties": {
    "gn:admin1_code":"36.0",
    "gn:asciiname":"Urmenia",
    "gn:country_code":"ID",
    "gn:dem":186,
    "gn:feature_class":"P",
    "gn:feature_code":"PPL",
    "gn:name":"Urmenia",
    "gn:population":0,
    "gn:timezone":"Asia/Jayapura",
    "iso:country":"ID",
    "name:ind_x_preferred":[
        "Urmenia"
    ],
    "name:und_x_variant":[
        "Urmania"
    ],
    "wof:name":"Urmenia",
    "wof:placetype":"locality"
},
  "geometry": {"coordinates":[138.55539999999999,-2.1472],"type":"Point"}
}