{
  "type": "Feature",
  "properties": {
    "gn:admin1_code":"18.0",
    "gn:asciiname":"Otan Barat",
    "gn:country_code":"ID",
    "gn:dem":8,
    "gn:feature_class":"P",
    "gn:feature_code":"PPL",
    "gn:name":"Otan Barat",
    "gn:population":0,
    "gn:timezone":"Asia/Makassar",
    "iso:country":"ID",
    "name:ind_x_preferred":[
        "Otan Barat"
    ],
    "wof:name":"Otan Barat",
    "wof:placetype":"locality"
},
  "geometry": {"coordinates":[123.3896,-10.1673],"type":"Point"}
}