{
  "type": "Feature",
  "properties": {
    "gn:admin1_code":"30",
    "gn:asciiname":"Krasag",
    "gn:country_code":"ID",
    "gn:dem":12,
    "gn:feature_class":"P",
    "gn:feature_code":"PPL",
    "gn:name":"Krasag",
    "gn:population":0,
    "gn:timezone":"Asia/Jakarta",
    "iso:country":"ID",
    "name:ind_x_preferred":[
        "Krasag"
    ],
    "wof:name":"Krasag",
    "wof:placetype":"locality"
},
  "geometry": {"coordinates":[108.50960000000001,-6.6932],"type":"Point"}
}