{
  "type": "Feature",
  "properties": {
    "gn:admin1_code":"8",
    "gn:asciiname":"Kelun",
    "gn:country_code":"ID",
    "gn:dem":64,
    "gn:feature_class":"P",
    "gn:feature_code":"PPL",
    "gn:name":"Kelun",
    "gn:population":0,
    "gn:timezone":"Asia/Jakarta",
    "iso:country":"ID",
    "name:ind_x_preferred":[
        "Kelun"
    ],
    "name:ita_x_preferred":[
        "Kelun"
    ],
    "name:por_x_preferred":[
        "Kelun"
    ],
    "name:rus_x_preferred":[
        "Kelun"
    ],
    "wof:lang_x_official":[
        "ind"
    ],
    "wof:lang_x_spoken":[
        "ind",
        "eng"
    ],
    "wof:name":"Kelun",
    "wof:placetype":"locality"
},
  "geometry": {"coordinates":[111.5534,-7.5985],"type":"Point"}
}