{
  "type": "Feature",
  "properties": {
    "gn:country":"ID",
    "gn:fcode":"PPL",
    "gn:pop":0,
    "iso:country":"ID",
    "name:ceb_x_preferred":[
        "Subang"
    ],
    "name:fra_x_preferred":[
        "Subang"
    ],
    "name:ind_x_preferred":[
        "Subang"
    ],
    "name:jav_x_preferred":[
        "Subang"
    ],
    "name:nld_x_preferred":[
        "Subang"
    ],
    "name:swe_x_preferred":[
        "Subang"
    ],
    "qs:name":"Subang",
    "qs:name_adm0":"Indonesia",
    "qs:name_adm1":"Jawa Barat",
    "qs:photos_9k":1,
    "qs:photos_9r":1,
    "qs:photos_all":6,
    "qs:photos_sr":0,
    "qs:placetype":"Town",
    "qs:pop_sr":"0",
    "wd:wordcount":91,
    "wof:name":"Subang",
    "wof:placetype":"locality",
    "wof:population":0
},
  "geometry": {"coordinates":[108.244,-7.2899],"type":"Point"}
}