{
  "type": "Feature",
  "properties": {
    "gn:admin1_code":"3.0",
    "gn:asciiname":"Penandingan",
    "gn:country_code":"ID",
    "gn:dem":19,
    "gn:feature_class":"P",
    "gn:feature_code":"PPL",
    "gn:name":"Penandingan",
    "gn:population":0,
    "gn:timezone":"Asia/Jakarta",
    "iso:country":"ID",
    "name:ind_x_preferred":[
        "Penandingan"
    ],
    "wof:name":"Penandingan",
    "wof:placetype":"locality"
},
  "geometry": {"coordinates":[102.54723,-4.06002],"type":"Point"}
}