{
  "type": "Feature",
  "properties": {
    "gn:admin1_code":"30.0",
    "gn:asciiname":"Kranggan Kulon",
    "gn:country_code":"ID",
    "gn:dem":67,
    "gn:feature_class":"P",
    "gn:feature_code":"PPL",
    "gn:name":"Kranggan Kulon",
    "gn:population":0,
    "gn:timezone":"Asia/Jakarta",
    "iso:country":"ID",
    "name:ind_x_preferred":[
        "Kranggan Kulon"
    ],
    "name:und_x_variant":[
        "Karanggan-kulon",
        "Kranggan-kulon 1"
    ],
    "wof:name":"Kranggan Kulon",
    "wof:placetype":"locality"
},
  "geometry": {"coordinates":[106.9192,-6.365],"type":"Point"}
}