{
  "type": "Feature",
  "properties": {
    "gn:admin1_code":"7.0",
    "gn:asciiname":"Krajan Alasdowo",
    "gn:country_code":"ID",
    "gn:dem":9,
    "gn:feature_class":"P",
    "gn:feature_code":"PPLA4",
    "gn:name":"Krajan Alasdowo",
    "gn:population":0,
    "gn:timezone":"Asia/Jakarta",
    "iso:country":"ID",
    "name:ind_x_preferred":[
        "Krajan Alasdowo"
    ],
    "wof:name":"Krajan Alasdowo",
    "wof:placetype":"locality"
},
  "geometry": {"coordinates":[111.03794000000001,-6.47729],"type":"Point"}
}