{
  "type": "Feature",
  "properties": {
    "gn:admin1_code":"18.0",
    "gn:asciiname":"Were",
    "gn:country_code":"ID",
    "gn:dem":78,
    "gn:feature_class":"P",
    "gn:feature_code":"PPL",
    "gn:name":"Were",
    "gn:population":0,
    "gn:timezone":"Asia/Makassar",
    "iso:country":"ID",
    "name:ind_x_preferred":[
        "Were"
    ],
    "name:jpn_x_preferred":[
        "Were"
    ],
    "wof:name":"Were",
    "wof:placetype":"locality"
},
  "geometry": {"coordinates":[118.98779999999999,-9.5701],"type":"Point"}
}