{
  "type": "Feature",
  "properties": {
    "gn:admin1_code":"37",
    "gn:asciiname":"Panjang",
    "gn:country_code":"ID",
    "gn:dem":91,
    "gn:feature_class":"P",
    "gn:feature_code":"PPL",
    "gn:name":"Panjang",
    "gn:population":0,
    "gn:timezone":"Asia/Jakarta",
    "iso:country":"ID",
    "name:ceb_x_preferred":[
        "Panjang"
    ],
    "name:deu_x_preferred":[
        "Panjang"
    ],
    "name:eng_x_preferred":[
        "Pandjang"
    ],
    "name:ind_x_preferred":[
        "Kampungpanjang"
    ],
    "name:ind_x_variant":[
        "Panjang"
    ],
    "name:swe_x_preferred":[
        "Panjang"
    ],
    "wof:lang_x_official":[
        "ind"
    ],
    "wof:lang_x_spoken":[
        "ind",
        "eng"
    ],
    "wof:name":"Panjang",
    "wof:placetype":"locality"
},
  "geometry": {"coordinates":[100.6199,0.3087],"type":"Point"}
}