{
  "type": "Feature",
  "properties": {
    "gn:admin1_code":"8.0",
    "gn:asciiname":"Jatikoong",
    "gn:country_code":"ID",
    "gn:dem":96,
    "gn:feature_class":"P",
    "gn:feature_code":"PPL",
    "gn:name":"Jatikoong",
    "gn:population":0,
    "gn:timezone":"Asia/Jakarta",
    "iso:country":"ID",
    "name:ind_x_preferred":[
        "Jatikoong"
    ],
    "wof:name":"Jatikoong",
    "wof:placetype":"locality"
},
  "geometry": {"coordinates":[113.1356,-7.8161],"type":"Point"}
}