{
  "type": "Feature",
  "properties": {
    "gn:admin1_code":"7.0",
    "gn:asciiname":"Cabeyan",
    "gn:country_code":"ID",
    "gn:dem":399,
    "gn:feature_class":"P",
    "gn:feature_code":"PPL",
    "gn:name":"Cabeyan",
    "gn:population":0,
    "gn:timezone":"Asia/Jakarta",
    "iso:country":"ID",
    "wof:name":"Cabeyan",
    "wof:placetype":"locality"
},
  "geometry": {"coordinates":[110.61083000000001,-7.47667],"type":"Point"}
}