{
  "type": "Feature",
  "properties": {
    "gn:admin1_code":"7.0",
    "gn:asciiname":"Sabrang Wetan",
    "gn:country_code":"ID",
    "gn:dem":163,
    "gn:feature_class":"P",
    "gn:feature_code":"PPL",
    "gn:name":"Sabrang Wetan",
    "gn:population":0,
    "gn:timezone":"Asia/Jakarta",
    "iso:country":"ID",
    "name:ind_x_preferred":[
        "Sabrang Wetan"
    ],
    "wof:name":"Sabrang Wetan",
    "wof:placetype":"locality"
},
  "geometry": {"coordinates":[109.59193999999999,-7.48444],"type":"Point"}
}