{
  "type": "Feature",
  "properties": {
    "gn:admin1_code":"30.0",
    "gn:asciiname":"Cijagreg",
    "gn:country_code":"ID",
    "gn:dem":259,
    "gn:feature_class":"P",
    "gn:feature_code":"PPL",
    "gn:name":"Cijagreg",
    "gn:population":0,
    "gn:timezone":"Asia/Jakarta",
    "iso:country":"ID",
    "name:ind_x_preferred":[
        "Cijagreg"
    ],
    "wof:name":"Cijagreg",
    "wof:placetype":"locality"
},
  "geometry": {"coordinates":[106.813,-7.3123],"type":"Point"}
}