{
  "type": "Feature",
  "properties": {
    "gn:admin1_code":"17.0",
    "gn:asciiname":"Tetanjung",
    "gn:country_code":"ID",
    "gn:dem":12,
    "gn:feature_class":"P",
    "gn:feature_code":"PPL",
    "gn:name":"Tetanjung",
    "gn:population":0,
    "gn:timezone":"Asia/Makassar",
    "iso:country":"ID",
    "name:ind_x_preferred":[
        "Tetanjung"
    ],
    "wof:name":"Tetanjung",
    "wof:placetype":"locality"
},
  "geometry": {"coordinates":[116.6634,-8.5618],"type":"Point"}
}