{
  "type": "Feature",
  "properties": {
    "gn:admin1_code":"1.0",
    "gn:asciiname":"Rampaih",
    "gn:country_code":"ID",
    "gn:dem":24,
    "gn:feature_class":"P",
    "gn:feature_code":"PPL",
    "gn:name":"Rampaih",
    "gn:population":0,
    "gn:timezone":"Asia/Jakarta",
    "iso:country":"ID",
    "name:ind_x_preferred":[
        "Rampaih"
    ],
    "wof:name":"Rampaih",
    "wof:placetype":"locality"
},
  "geometry": {"coordinates":[97.4706,4.9036],"type":"Point"}
}