{
  "type": "Feature",
  "properties": {
    "gn:admin1_code":"30.0",
    "gn:asciiname":"Cidahu",
    "gn:country_code":"ID",
    "gn:dem":602,
    "gn:feature_class":"P",
    "gn:feature_code":"PPL",
    "gn:name":"Cidahu",
    "gn:population":0,
    "gn:timezone":"Asia/Jakarta",
    "iso:country":"ID",
    "name:ind_x_preferred":[
        "Cidahu"
    ],
    "name:und_x_variant":[
        "Tjidahu"
    ],
    "wof:lang_x_official":[
        "ind"
    ],
    "wof:lang_x_spoken":[
        "ind",
        "eng"
    ],
    "wof:name":"Cidahu",
    "wof:placetype":"locality"
},
  "geometry": {"coordinates":[106.75888999999999,-6.76944],"type":"Point"}
}