{
  "type": "Feature",
  "properties": {
    "gn:admin1_code":"13.0",
    "gn:asciiname":"Bapuyu",
    "gn:country_code":"ID",
    "gn:dem":0,
    "gn:feature_class":"P",
    "gn:feature_code":"PPL",
    "gn:name":"Bapuyu",
    "gn:population":0,
    "gn:timezone":"Asia/Pontianak",
    "iso:country":"ID",
    "name:und_x_variant":[
        "Bahaur",
        "Bapuju",
        "Bapoejoe",
        "Bapuyu"
    ],
    "wof:name":"Bapuyu",
    "wof:placetype":"locality"
},
  "geometry": {"coordinates":[114.0485,-3.3309],"type":"Point"}
}