{
  "type": "Feature",
  "properties": {
    "gn:admin1_code":"17.0",
    "gn:asciiname":"Tangsi",
    "gn:country_code":"ID",
    "gn:dem":10,
    "gn:feature_class":"P",
    "gn:feature_code":"PPL",
    "gn:name":"Tangsi",
    "gn:population":0,
    "gn:timezone":"Asia/Makassar",
    "iso:country":"ID",
    "name:ind_x_preferred":[
        "Tangsi"
    ],
    "wof:name":"Tangsi",
    "wof:placetype":"locality"
},
  "geometry": {"coordinates":[116.0772,-8.5754],"type":"Point"}
}