{
  "type": "Feature",
  "properties": {
    "gn:admin1_code":"38",
    "gn:asciiname":"Tallodo",
    "gn:country_code":"ID",
    "gn:dem":378,
    "gn:feature_class":"P",
    "gn:feature_code":"PPL",
    "gn:name":"Tallodo",
    "gn:population":0,
    "gn:timezone":"Asia/Makassar",
    "iso:country":"ID",
    "name:ind_x_preferred":[
        "Tallodo"
    ],
    "wof:name":"Tallodo",
    "wof:placetype":"locality"
},
  "geometry": {"coordinates":[120.1382,-2.5125],"type":"Point"}
}