{
  "type": "Feature",
  "properties": {
    "gn:admin1_code":"7",
    "gn:asciiname":"Blimbing",
    "gn:country_code":"ID",
    "gn:dem":352,
    "gn:feature_class":"P",
    "gn:feature_code":"PPL",
    "gn:name":"Blimbing",
    "gn:population":0,
    "gn:timezone":"Asia/Jakarta",
    "iso:country":"ID",
    "name:ind_x_preferred":[
        "Blimbing"
    ],
    "wof:name":"Blimbing",
    "wof:placetype":"locality"
},
  "geometry": {"coordinates":[111.14139,-7.84722],"type":"Point"}
}