{
  "type": "Feature",
  "properties": {
    "gn:admin1_code":"8",
    "gn:asciiname":"Jebuk",
    "gn:country_code":"ID",
    "gn:dem":489,
    "gn:feature_class":"P",
    "gn:feature_code":"PPL",
    "gn:name":"Jebuk",
    "gn:population":0,
    "gn:timezone":"Asia/Jakarta",
    "iso:country":"ID",
    "name:ind_x_preferred":[
        "Jebuk"
    ],
    "wof:name":"Jebuk",
    "wof:placetype":"locality"
},
  "geometry": {"coordinates":[112.7131,-7.9692],"type":"Point"}
}