{
  "type": "Feature",
  "properties": {
    "gn:admin1_code":"18.0",
    "gn:asciiname":"Lewololon",
    "gn:country_code":"ID",
    "gn:dem":43,
    "gn:feature_class":"P",
    "gn:feature_code":"PPL",
    "gn:name":"Lewololon",
    "gn:population":0,
    "gn:timezone":"Asia/Makassar",
    "iso:country":"ID",
    "name:ind_x_preferred":[
        "Lewololon"
    ],
    "wof:name":"Lewololon",
    "wof:placetype":"locality"
},
  "geometry": {"coordinates":[123.4139,-8.5768],"type":"Point"}
}