{
  "type": "Feature",
  "properties": {
    "gn:admin1_code":"8.0",
    "gn:asciiname":"Pulosari",
    "gn:country_code":"ID",
    "gn:dem":5,
    "gn:feature_class":"P",
    "gn:feature_code":"PPL",
    "gn:name":"Pulosari",
    "gn:population":0,
    "gn:timezone":"Asia/Jakarta",
    "iso:country":"ID",
    "name:fas_x_preferred":[
        "\u067e\u0648\u0644\u0648\u0633\u0627\u0631\u06cc"
    ],
    "name:ind_x_preferred":[
        "Pulosari"
    ],
    "name:ind_x_variant":[
        "Gunung Pulosari"
    ],
    "name:jav_x_preferred":[
        "Gunung Pulosari"
    ],
    "name:nld_x_preferred":[
        "Pulosari"
    ],
    "name:slk_x_preferred":[
        "Pulosari"
    ],
    "name:zho_x_preferred":[
        "\u666e\u6d1b\u85a9\u91cc\u706b\u5c71"
    ],
    "wof:name":"Pulosari",
    "wof:placetype":"locality"
},
  "geometry": {"coordinates":[112.7389,-7.3549],"type":"Point"}
}