{
  "type": "Feature",
  "properties": {
    "gn:admin1_code":"37.0",
    "gn:asciiname":"Ujunglabuh",
    "gn:country_code":"ID",
    "gn:dem":157,
    "gn:feature_class":"P",
    "gn:feature_code":"PPL",
    "gn:name":"Ujunglabuh",
    "gn:population":0,
    "gn:timezone":"Asia/Jakarta",
    "iso:country":"ID",
    "name:ind_x_preferred":[
        "Ujunglabuh"
    ],
    "wof:name":"Ujunglabuh",
    "wof:placetype":"locality"
},
  "geometry": {"coordinates":[101.4348,-0.477],"type":"Point"}
}