{
  "type": "Feature",
  "properties": {
    "gn:admin1_code":"18",
    "gn:asciiname":"Mauriti",
    "gn:country_code":"ID",
    "gn:dem":29,
    "gn:feature_class":"P",
    "gn:feature_code":"PPL",
    "gn:name":"Mauriti",
    "gn:population":0,
    "gn:timezone":"Asia/Makassar",
    "iso:country":"ID",
    "name:bpy_x_preferred":[
        "\u09ae\u09be\u0989\u09b0\u09bf\u099f\u09bf"
    ],
    "name:ceb_x_preferred":[
        "Mauriti"
    ],
    "name:eus_x_preferred":[
        "Mauriti"
    ],
    "name:fra_x_preferred":[
        "Mauriti"
    ],
    "name:ind_x_preferred":[
        "Mauriti"
    ],
    "name:ita_x_preferred":[
        "Mauriti"
    ],
    "name:kat_x_preferred":[
        "\u10db\u10d0\u10e3\u10e0\u10d8\u10e2\u10d8"
    ],
    "name:kaz_x_preferred":[
        "\u041c\u0430\u0443\u0440\u0438\u0442\u0438"
    ],
    "name:nld_x_preferred":[
        "Mauriti"
    ],
    "name:nor_x_preferred":[
        "Mauriti"
    ],
    "name:por_x_preferred":[
        "Mauriti"
    ],
    "name:ron_x_preferred":[
        "Mauriti"
    ],
    "name:rus_x_preferred":[
        "\u041c\u0430\u0443\u0440\u0438\u0442\u0438"
    ],
    "name:swe_x_preferred":[
        "Mauriti"
    ],
    "name:vie_x_preferred":[
        "Mauriti"
    ],
    "name:vol_x_preferred":[
        "Mauriti"
    ],
    "name:war_x_preferred":[
        "Mauriti"
    ],
    "name:zho_x_preferred":[
        "\u6bdb\u91cc\u8482"
    ],
    "wof:name":"Mauriti",
    "wof:placetype":"locality"
},
  "geometry": {"coordinates":[121.3706,-8.858],"type":"Point"}
}