{
  "type": "Feature",
  "properties": {
    "gn:admin1_code":"18",
    "gn:asciiname":"Mauriti",
    "gn:country_code":"ID",
    "gn:dem":29,
    "gn:feature_class":"P",
    "gn:feature_code":"PPL",
    "gn:name":"Mauriti",
    "gn:population":0,
    "gn:timezone":"Asia/Makassar",
    "iso:country":"ID",
    "name:ind_x_preferred":[
        "Mauriti"
    ],
    "wof:name":"Mauriti",
    "wof:placetype":"locality"
},
  "geometry": {"coordinates":[121.3706,-8.858],"type":"Point"}
}