{
  "type": "Feature",
  "properties": {
    "gn:admin1_code":"26.0",
    "gn:asciiname":"Pulo-pulo",
    "gn:country_code":"ID",
    "gn:dem":1517,
    "gn:feature_class":"P",
    "gn:feature_code":"PPL",
    "gn:name":"Pulo-pulo",
    "gn:population":0,
    "gn:timezone":"Asia/Jakarta",
    "iso:country":"ID",
    "name:ind_x_preferred":[
        "Pulo-pulo"
    ],
    "wof:name":"Pulo-pulo",
    "wof:placetype":"locality"
},
  "geometry": {"coordinates":[98.7886,2.642],"type":"Point"}
}