{
  "type": "Feature",
  "properties": {
    "gn:admin1_code":"17.0",
    "gn:asciiname":"Pagesangan Barat",
    "gn:country_code":"ID",
    "gn:dem":13,
    "gn:feature_class":"P",
    "gn:feature_code":"PPL",
    "gn:name":"Pagesangan Barat",
    "gn:population":0,
    "gn:timezone":"Asia/Makassar",
    "iso:country":"ID",
    "name:ind_x_preferred":[
        "Pagesangan Barat"
    ],
    "wof:name":"Pagesangan Barat",
    "wof:placetype":"locality"
},
  "geometry": {"coordinates":[116.0996,-8.6009],"type":"Point"}
}