{
  "type": "Feature",
  "properties": {
    "gn:admin1_code":"8.0",
    "gn:asciiname":"Penataran",
    "gn:country_code":"ID",
    "gn:dem":374,
    "gn:feature_class":"P",
    "gn:feature_code":"PPL",
    "gn:name":"Penataran",
    "gn:population":0,
    "gn:timezone":"Asia/Jakarta",
    "iso:country":"ID",
    "name:ind_x_preferred":[
        "Penataran"
    ],
    "name:und_x_variant":[
        "Panataran"
    ],
    "wof:name":"Penataran",
    "wof:placetype":"locality"
},
  "geometry": {"coordinates":[112.2182,-8.0191],"type":"Point"}
}