{
  "type": "Feature",
  "properties": {
    "gn:admin1_code":"8.0",
    "gn:asciiname":"Pasur",
    "gn:country_code":"ID",
    "gn:dem":68,
    "gn:feature_class":"P",
    "gn:feature_code":"PPL",
    "gn:name":"Pasur",
    "gn:population":0,
    "gn:timezone":"Asia/Jakarta",
    "iso:country":"ID",
    "name:fas_x_preferred":[
        "\u067e\u0627\u0633\u0648\u0631"
    ],
    "name:ind_x_preferred":[
        "Pasur"
    ],
    "name:urd_x_preferred":[
        "\u0628\u0631\u062c"
    ],
    "wof:lang_x_official":[
        "ind"
    ],
    "wof:lang_x_spoken":[
        "ind",
        "eng"
    ],
    "wof:name":"Pasur",
    "wof:placetype":"locality"
},
  "geometry": {"coordinates":[111.4579,-8.2127],"type":"Point"}
}