{
  "type": "Feature",
  "properties": {
    "gn:country":"ID",
    "gn:fcode":"PPL",
    "gn:pop":0,
    "iso:country":"ID",
    "name:deu_x_preferred":[
        "Selat"
    ],
    "name:eng_x_preferred":[
        "Selat"
    ],
    "name:ind_x_preferred":[
        "Selat Kaja"
    ],
    "name:ind_x_variant":[
        "Selat"
    ],
    "name:msa_x_preferred":[
        "Selat"
    ],
    "name:nld_x_preferred":[
        "Selat"
    ],
    "name:spa_x_preferred":[
        "selat"
    ],
    "name:sun_x_preferred":[
        "Selat"
    ],
    "qs:name":"Selat",
    "qs:name_adm0":"Indonesia",
    "qs:name_adm1":"Bali",
    "qs:photos_9r":0,
    "qs:photos_sr":0,
    "qs:placetype":"Town",
    "qs:pop_sr":"3",
    "wd:wordcount":54,
    "wof:lang_x_official":[
        "ind"
    ],
    "wof:lang_x_spoken":[
        "ind",
        "eng"
    ],
    "wof:name":"Selat",
    "wof:placetype":"locality",
    "wof:population":0
},
  "geometry": {"coordinates":[115.4753,-8.4355],"type":"Point"}
}