{
  "type": "Feature",
  "properties": {
    "gn:admin1_code":"42.0",
    "gn:asciiname":"Gong Solok",
    "gn:country_code":"ID",
    "gn:dem":28,
    "gn:feature_class":"P",
    "gn:feature_code":"PPL",
    "gn:name":"Gong Solok",
    "gn:population":0,
    "gn:timezone":"Asia/Makassar",
    "iso:country":"ID",
    "name:ind_x_preferred":[
        "Gong Solok"
    ],
    "name:und_x_variant":[
        "Gongsolok",
        "Gongsola"
    ],
    "wof:name":"Gong Solok",
    "wof:placetype":"locality"
},
  "geometry": {"coordinates":[116.54694000000001,3.3244],"type":"Point"}
}