{
  "type": "Feature",
  "properties": {
    "gn:admin1_code":"15.0",
    "gn:asciiname":"Batubalai",
    "gn:country_code":"ID",
    "gn:dem":5,
    "gn:feature_class":"P",
    "gn:feature_code":"PPL",
    "gn:name":"Batubalai",
    "gn:population":0,
    "gn:timezone":"Asia/Jakarta",
    "iso:country":"ID",
    "name:ind_x_preferred":[
        "Batubalai"
    ],
    "name:und_x_variant":[
        "Batoebalai Boenoek",
        "Batubalaiburuk"
    ],
    "wof:lang_x_official":[
        "ind"
    ],
    "wof:lang_x_spoken":[
        "ind",
        "eng"
    ],
    "wof:name":"Batubalai",
    "wof:placetype":"locality"
},
  "geometry": {"coordinates":[104.72759000000001,-5.54527],"type":"Point"}
}