{
  "type": "Feature",
  "properties": {
    "gn:admin1_code":"37",
    "gn:asciiname":"Banting",
    "gn:country_code":"ID",
    "gn:dem":18,
    "gn:feature_class":"P",
    "gn:feature_code":"PPL",
    "gn:name":"Banting",
    "gn:population":0,
    "gn:timezone":"Asia/Jakarta",
    "iso:country":"ID",
    "name:ind_x_preferred":[
        "Banting"
    ],
    "name:msa_x_preferred":[
        "Banting"
    ],
    "name:pol_x_preferred":[
        "Banting"
    ],
    "wof:lang_x_official":[
        "ind"
    ],
    "wof:lang_x_spoken":[
        "ind",
        "eng"
    ],
    "wof:name":"Banting",
    "wof:placetype":"locality"
},
  "geometry": {"coordinates":[103.56149000000001,-0.03628],"type":"Point"}
}