{
  "type": "Feature",
  "properties": {
    "gn:admin1_code":"30",
    "gn:asciiname":"Sukamantri",
    "gn:country_code":"ID",
    "gn:dem":310,
    "gn:feature_class":"P",
    "gn:feature_code":"PPL",
    "gn:name":"Sukamantri",
    "gn:population":0,
    "gn:timezone":"Asia/Jakarta",
    "iso:country":"ID",
    "name:ind_x_preferred":[
        "Sukamantri"
    ],
    "wof:name":"Sukamantri",
    "wof:placetype":"locality"
},
  "geometry": {"coordinates":[107.19750000000001,-6.79389],"type":"Point"}
}