{
  "type": "Feature",
  "properties": {
    "gn:admin1_code":"28.0",
    "gn:asciiname":"Kobrau",
    "gn:country_code":"ID",
    "gn:dem":19,
    "gn:feature_class":"P",
    "gn:feature_code":"PPL",
    "gn:name":"Kobrau",
    "gn:population":0,
    "gn:timezone":"Asia/Jayapura",
    "iso:country":"ID",
    "name:ind_x_preferred":[
        "Kobrau"
    ],
    "name:und_x_variant":[
        "Kobraoer",
        "Kobraur"
    ],
    "wof:name":"Kobrau",
    "wof:placetype":"locality"
},
  "geometry": {"coordinates":[134.32567,-5.98056],"type":"Point"}
}