{
  "type": "Feature",
  "properties": {
    "gn:admin1_code":"21.0",
    "gn:asciiname":"Bunga Tua",
    "gn:country_code":"ID",
    "gn:dem":17,
    "gn:feature_class":"P",
    "gn:feature_code":"PPL",
    "gn:name":"Bunga Tua",
    "gn:population":0,
    "gn:timezone":"Asia/Makassar",
    "iso:country":"ID",
    "name:ind_x_preferred":[
        "Bunga Tua"
    ],
    "wof:name":"Bunga Tua",
    "wof:placetype":"locality"
},
  "geometry": {"coordinates":[122.9101,-0.9179],"type":"Point"}
}