{
  "type": "Feature",
  "properties": {
    "gn:admin1_code":"3.0",
    "gn:asciiname":"Talangjenaman",
    "gn:country_code":"ID",
    "gn:dem":649,
    "gn:feature_class":"P",
    "gn:feature_code":"PPL",
    "gn:name":"Talangjenaman",
    "gn:population":0,
    "gn:timezone":"Asia/Jakarta",
    "iso:country":"ID",
    "name:ind_x_preferred":[
        "Talangjenaman"
    ],
    "wof:name":"Talangjenaman",
    "wof:placetype":"locality"
},
  "geometry": {"coordinates":[102.6255,-3.724],"type":"Point"}
}