{
  "type": "Feature",
  "properties": {
    "gn:admin1_code":"18",
    "gn:asciiname":"Beaceki",
    "gn:country_code":"ID",
    "gn:dem":845,
    "gn:feature_class":"P",
    "gn:feature_code":"PPL",
    "gn:name":"Beaceki",
    "gn:population":0,
    "gn:timezone":"Asia/Makassar",
    "iso:country":"ID",
    "name:ind_x_preferred":[
        "Beaceki"
    ],
    "wof:name":"Beaceki",
    "wof:placetype":"locality"
},
  "geometry": {"coordinates":[120.6086,-8.529],"type":"Point"}
}