{
  "type": "Feature",
  "properties": {
    "gn:admin1_code":"8",
    "gn:asciiname":"Wonokoyo",
    "gn:country_code":"ID",
    "gn:dem":63,
    "gn:feature_class":"P",
    "gn:feature_code":"PPL",
    "gn:name":"Wonokoyo",
    "gn:population":0,
    "gn:timezone":"Asia/Jakarta",
    "iso:country":"ID",
    "name:ind_x_preferred":[
        "Wonokoyo"
    ],
    "wof:name":"Wonokoyo",
    "wof:placetype":"locality"
},
  "geometry": {"coordinates":[112.285,-7.244],"type":"Point"}
}