{
  "type": "Feature",
  "properties": {
    "gn:admin1_code":"30.0",
    "gn:asciiname":"Cikoneng",
    "gn:country_code":"ID",
    "gn:dem":268,
    "gn:feature_class":"P",
    "gn:feature_code":"PPL",
    "gn:name":"Cikoneng",
    "gn:population":0,
    "gn:timezone":"Asia/Jakarta",
    "iso:country":"ID",
    "name:ind_x_preferred":[
        "Cikoneng"
    ],
    "wof:name":"Cikoneng",
    "wof:placetype":"locality"
},
  "geometry": {"coordinates":[106.7687,-7.2516],"type":"Point"}
}