{
  "type": "Feature",
  "properties": {
    "gn:admin1_code":"31.0",
    "gn:asciiname":"Rainis",
    "gn:country_code":"ID",
    "gn:dem":41,
    "gn:feature_class":"P",
    "gn:feature_code":"PPLA3",
    "gn:name":"Rainis",
    "gn:population":0,
    "gn:timezone":"Asia/Makassar",
    "iso:country":"ID",
    "name:und_x_variant":[
        "Painis",
        "Raimis",
        "Paniki",
        "Rainis Paniki",
        "Kampoeng Rainis",
        "Rainis"
    ],
    "wof:name":"Rainis",
    "wof:placetype":"locality"
},
  "geometry": {"coordinates":[126.86129,4.23282],"type":"Point"}
}