{
  "type": "Feature",
  "properties": {
    "gn:admin1_code":"31.0",
    "gn:asciiname":"Rainis",
    "gn:country_code":"ID",
    "gn:dem":41,
    "gn:feature_class":"P",
    "gn:feature_code":"PPLA3",
    "gn:name":"Rainis",
    "gn:population":0,
    "gn:timezone":"Asia/Makassar",
    "iso:country":"ID",
    "name:bel_x_preferred":[
        "\u0420\u0430\u0439\u043d\u0456\u0441"
    ],
    "name:bre_x_preferred":[
        "Rainis"
    ],
    "name:cat_x_preferred":[
        "Rainis"
    ],
    "name:ces_x_preferred":[
        "Rainis"
    ],
    "name:dan_x_preferred":[
        "Rainis"
    ],
    "name:deu_x_preferred":[
        "Rainis"
    ],
    "name:epo_x_preferred":[
        "Rainis"
    ],
    "name:est_x_preferred":[
        "Rainis"
    ],
    "name:eus_x_preferred":[
        "Rainis"
    ],
    "name:fin_x_preferred":[
        "Rainis"
    ],
    "name:fra_x_preferred":[
        "Rainis"
    ],
    "name:hun_x_preferred":[
        "Rainis"
    ],
    "name:hye_x_preferred":[
        "\u0545\u0561\u0576 \u054c\u0561\u0575\u0576\u056b\u057d"
    ],
    "name:ita_x_preferred":[
        "Rainis"
    ],
    "name:kir_x_preferred":[
        "\u0420\u0430\u0439\u043d\u0438\u0441"
    ],
    "name:kor_x_preferred":[
        "\ub77c\uc774\ub2c8\uc2a4"
    ],
    "name:lav_x_preferred":[
        "Rainis"
    ],
    "name:lit_x_preferred":[
        "Rainis"
    ],
    "name:nld_x_preferred":[
        "Rainis"
    ],
    "name:nor_x_preferred":[
        "Rainis"
    ],
    "name:pol_x_preferred":[
        "Rainis"
    ],
    "name:rus_x_preferred":[
        "\u0420\u0430\u0439\u043d\u0438\u0441"
    ],
    "name:spa_x_preferred":[
        "Rainis"
    ],
    "name:swe_x_preferred":[
        "Rainis"
    ],
    "name:ukr_x_preferred":[
        "\u0420\u0430\u0439\u043d\u0456\u0441"
    ],
    "name:und_x_variant":[
        "Painis",
        "Raimis",
        "Paniki",
        "Rainis Paniki",
        "Kampoeng Rainis",
        "Rainis"
    ],
    "name:uzb_x_preferred":[
        "Yan Raynis"
    ],
    "name:zho_x_preferred":[
        "\u745e\u5c3c\u65af"
    ],
    "wof:name":"Rainis",
    "wof:placetype":"locality"
},
  "geometry": {"coordinates":[126.86129,4.23282],"type":"Point"}
}