{
  "type": "Feature",
  "properties": {
    "gn:admin1_code":"07",
    "gn:asciiname":"Sampetan",
    "gn:country_code":"ID",
    "gn:dem":986,
    "gn:feature_class":"P",
    "gn:feature_code":"PPL",
    "gn:name":"Sampetan",
    "gn:population":0,
    "gn:timezone":"Asia/Jakarta",
    "iso:country":"ID",
    "wof:name":"Sampetan",
    "wof:placetype":"locality"
},
  "geometry": {"coordinates":[110.48917,-7.43583],"type":"Point"}
}