{
  "type": "Feature",
  "properties": {
    "gn:country":"ID",
    "gn:fcode":"PPLA3",
    "gn:pop":0,
    "iso:country":"ID",
    "name:ind_x_preferred":[
        "Wonorejo"
    ],
    "name:unk_x_variant":[
        "Wonoredjo"
    ],
    "qs:name":"Wonorejo",
    "qs:photos_9r":0,
    "qs:photos_sr":0,
    "qs:pop_sr":"0",
    "wof:name":"Wonorejo",
    "wof:placetype":"locality",
    "wof:population":0
},
  "geometry": {"coordinates":[120.8126,-2.4937],"type":"Point"}
}