{
  "type": "Feature",
  "properties": {
    "gn:admin1_code":"7.0",
    "gn:asciiname":"Sidomulyo",
    "gn:country_code":"ID",
    "gn:dem":161,
    "gn:feature_class":"P",
    "gn:feature_code":"PPL",
    "gn:name":"Sidomulyo",
    "gn:population":0,
    "gn:timezone":"Asia/Jakarta",
    "iso:country":"ID",
    "wof:name":"Sidomulyo",
    "wof:placetype":"locality"
},
  "geometry": {"coordinates":[110.68416999999999,-7.59778],"type":"Point"}
}