{
  "type": "Feature",
  "properties": {
    "gn:admin1_code":"22.0",
    "gn:asciiname":"Onemae",
    "gn:country_code":"ID",
    "gn:dem":6,
    "gn:feature_class":"P",
    "gn:feature_code":"PPL",
    "gn:name":"Onemae",
    "gn:population":0,
    "gn:timezone":"Asia/Makassar",
    "iso:country":"ID",
    "name:ind_x_preferred":[
        "Onemae"
    ],
    "wof:name":"Onemae",
    "wof:placetype":"locality"
},
  "geometry": {"coordinates":[123.9072,-5.7189],"type":"Point"}
}