{
  "type": "Feature",
  "properties": {
    "gn:admin1_code":"30",
    "gn:asciiname":"Ardaijaya",
    "gn:country_code":"ID",
    "gn:dem":2,
    "gn:feature_class":"P",
    "gn:feature_code":"PPL",
    "gn:name":"Ardaijaya",
    "gn:population":0,
    "gn:timezone":"Asia/Jakarta",
    "iso:country":"ID",
    "name:ind_x_preferred":[
        "Ardaijaya"
    ],
    "wof:name":"Ardaijaya",
    "wof:placetype":"locality"
},
  "geometry": {"coordinates":[107.24861,-6.05139],"type":"Point"}
}