{
  "type": "Feature",
  "properties": {
    "gn:admin1_code":"8.0",
    "gn:asciiname":"Wirasa Kidul",
    "gn:country_code":"ID",
    "gn:dem":22,
    "gn:feature_class":"P",
    "gn:feature_code":"PPL",
    "gn:name":"Wirasa Kidul",
    "gn:population":0,
    "gn:timezone":"Asia/Jakarta",
    "iso:country":"ID",
    "name:ind_x_preferred":[
        "Wirasa Kidul"
    ],
    "wof:name":"Wirasa Kidul",
    "wof:placetype":"locality"
},
  "geometry": {"coordinates":[112.04940000000001,-7.1845],"type":"Point"}
}