{
  "type": "Feature",
  "properties": {
    "gn:admin1_code":"30",
    "gn:asciiname":"Lio Kidul",
    "gn:country_code":"ID",
    "gn:dem":587,
    "gn:feature_class":"P",
    "gn:feature_code":"PPL",
    "gn:name":"Lio Kidul",
    "gn:population":0,
    "gn:timezone":"Asia/Jakarta",
    "iso:country":"ID",
    "name:ind_x_preferred":[
        "Lio Kidul"
    ],
    "wof:lang_x_official":[
        "ind"
    ],
    "wof:lang_x_spoken":[
        "ind",
        "eng"
    ],
    "wof:name":"Lio Kidul",
    "wof:placetype":"locality"
},
  "geometry": {"coordinates":[107.00194,-6.95139],"type":"Point"}
}