{
  "type": "Feature",
  "properties": {
    "gn:admin1_code":"38",
    "gn:asciiname":"Jompie",
    "gn:country_code":"ID",
    "gn:dem":149,
    "gn:feature_class":"P",
    "gn:feature_code":"PPL",
    "gn:name":"Jompie",
    "gn:population":0,
    "gn:timezone":"Asia/Makassar",
    "iso:country":"ID",
    "name:ind_x_preferred":[
        "Jompie"
    ],
    "wof:name":"Jompie",
    "wof:placetype":"locality"
},
  "geometry": {"coordinates":[120.18689999999999,-4.4892],"type":"Point"}
}