{
  "type": "Feature",
  "properties": {
    "gn:admin1_code":"33",
    "gn:asciiname":"Cikarang",
    "gn:country_code":"ID",
    "gn:dem":122,
    "gn:feature_class":"P",
    "gn:feature_code":"PPL",
    "gn:name":"Cikarang",
    "gn:population":0,
    "gn:timezone":"Asia/Jakarta",
    "iso:country":"ID",
    "name:fas_x_preferred":[
        "\u06a9\u06cc\u06a9\u0627\u0631\u0627\u0646\u06af"
    ],
    "name:ind_x_preferred":[
        "Cikarang"
    ],
    "name:mlg_x_preferred":[
        "Cikarang"
    ],
    "name:nld_x_preferred":[
        "Cibeber"
    ],
    "wof:name":"Cikarang",
    "wof:placetype":"locality"
},
  "geometry": {"coordinates":[105.9337,-6.0885],"type":"Point"}
}