{
  "type": "Feature",
  "properties": {
    "gn:admin1_code":"0.0",
    "gn:asciiname":"Uraiun",
    "gn:cc2":"ID",
    "gn:country_code":"ID",
    "gn:dem":37,
    "gn:feature_class":"P",
    "gn:feature_code":"PPL",
    "gn:name":"Uraiun",
    "gn:population":0,
    "gn:timezone":"Asia/Jayapura",
    "iso:country":"ID",
    "name:und_x_variant":[
        "Oeraioen",
        "Uraiun"
    ],
    "wof:name":"Uraiun",
    "wof:placetype":"locality"
},
  "geometry": {"coordinates":[134.40000000000001,-6.13333],"type":"Point"}
}