{
  "type": "Feature",
  "properties": {
    "gn:admin1_code":"30",
    "gn:asciiname":"Pasirandong",
    "gn:country_code":"ID",
    "gn:dem":363,
    "gn:feature_class":"P",
    "gn:feature_code":"PPL",
    "gn:name":"Pasirandong",
    "gn:population":0,
    "gn:timezone":"Asia/Jakarta",
    "iso:country":"ID",
    "name:ind_x_preferred":[
        "Pasirandong"
    ],
    "wof:name":"Pasirandong",
    "wof:placetype":"locality"
},
  "geometry": {"coordinates":[106.72693999999998,-6.62139],"type":"Point"}
}