{
  "type": "Feature",
  "properties": {
    "gn:admin1_code":"38.0",
    "gn:asciiname":"Kariango",
    "gn:country_code":"ID",
    "gn:dem":12,
    "gn:feature_class":"P",
    "gn:feature_code":"PPL",
    "gn:name":"Kariango",
    "gn:population":0,
    "gn:timezone":"Asia/Makassar",
    "iso:country":"ID",
    "name:ind_x_preferred":[
        "Kariango"
    ],
    "wof:name":"Kariango",
    "wof:placetype":"locality"
},
  "geometry": {"coordinates":[119.63030000000001,-3.8875],"type":"Point"}
}