{
  "type": "Feature",
  "properties": {
    "gn:admin1_code":"7.0",
    "gn:asciiname":"Gape",
    "gn:country_code":"ID",
    "gn:dem":106,
    "gn:feature_class":"P",
    "gn:feature_code":"PPL",
    "gn:name":"Gape",
    "gn:population":0,
    "gn:timezone":"Asia/Jakarta",
    "iso:country":"ID",
    "wof:name":"Gape",
    "wof:placetype":"locality"
},
  "geometry": {"coordinates":[110.01944,-7.68694],"type":"Point"}
}