{
  "type": "Feature",
  "properties": {
    "gn:admin1_code":"2",
    "gn:asciiname":"Munduktemu Kelod",
    "gn:country_code":"ID",
    "gn:dem":680,
    "gn:feature_class":"P",
    "gn:feature_code":"PPLA4",
    "gn:name":"Munduktemu Kelod",
    "gn:population":0,
    "gn:timezone":"Asia/Makassar",
    "iso:country":"ID",
    "name:ind_x_preferred":[
        "Munduktemu Kelod"
    ],
    "wof:lang_x_official":[
        "ind"
    ],
    "wof:lang_x_spoken":[
        "ind",
        "eng"
    ],
    "wof:name":"Munduktemu Kelod",
    "wof:placetype":"locality"
},
  "geometry": {"coordinates":[114.9689,-8.344],"type":"Point"}
}