{
  "type": "Feature",
  "properties": {
    "gn:admin1_code":"8",
    "gn:asciiname":"Tetelan Kulon",
    "gn:country_code":"ID",
    "gn:dem":268,
    "gn:feature_class":"P",
    "gn:feature_code":"PPL",
    "gn:name":"Tetelan Kulon",
    "gn:population":0,
    "gn:timezone":"Asia/Jakarta",
    "iso:country":"ID",
    "name:ind_x_preferred":[
        "Tetelan Kulon"
    ],
    "wof:name":"Tetelan Kulon",
    "wof:placetype":"locality"
},
  "geometry": {"coordinates":[114.2516,-8.2514],"type":"Point"}
}