{
  "type": "Feature",
  "properties": {
    "gn:admin1_code":"38",
    "gn:asciiname":"Mico Dua",
    "gn:country_code":"ID",
    "gn:dem":655,
    "gn:feature_class":"P",
    "gn:feature_code":"PPL",
    "gn:name":"Mico Dua",
    "gn:population":0,
    "gn:timezone":"Asia/Makassar",
    "iso:country":"ID",
    "name:ind_x_preferred":[
        "Mico Dua"
    ],
    "name:und_x_variant":[
        "Mico 2"
    ],
    "wof:name":"Mico Dua",
    "wof:placetype":"locality"
},
  "geometry": {"coordinates":[119.91030000000001,-4.6974],"type":"Point"}
}