{
  "type": "Feature",
  "properties": {
    "gn:admin1_code":"38",
    "gn:asciiname":"Lentu",
    "gn:country_code":"ID",
    "gn:dem":153,
    "gn:feature_class":"P",
    "gn:feature_code":"PPL",
    "gn:name":"Lentu",
    "gn:population":0,
    "gn:timezone":"Asia/Makassar",
    "iso:country":"ID",
    "name:ind_x_preferred":[
        "Lentu"
    ],
    "wof:lang_x_official":[
        "ind"
    ],
    "wof:lang_x_spoken":[
        "ind",
        "eng"
    ],
    "wof:name":"Lentu",
    "wof:placetype":"locality"
},
  "geometry": {"coordinates":[120.32980000000001,-5.3084],"type":"Point"}
}