{
  "type": "Feature",
  "properties": {
    "gn:admin1_code":"1",
    "gn:asciiname":"Lawe Tanduk",
    "gn:country_code":"ID",
    "gn:dem":185,
    "gn:feature_class":"P",
    "gn:feature_code":"PPL",
    "gn:name":"Lawe Tanduk",
    "gn:population":0,
    "gn:timezone":"Asia/Jakarta",
    "iso:country":"ID",
    "name:ind_x_preferred":[
        "Lawe Tanduk"
    ],
    "name:und_x_variant":[
        "Lawepetanduk"
    ],
    "wof:lang_x_official":[
        "ind"
    ],
    "wof:lang_x_spoken":[
        "ind",
        "eng"
    ],
    "wof:name":"Lawe Tanduk",
    "wof:placetype":"locality"
},
  "geometry": {"coordinates":[97.89190000000001,3.4146],"type":"Point"}
}