{
  "type": "Feature",
  "properties": {
    "gn:admin1_code":"30",
    "gn:asciiname":"Cidahu",
    "gn:country_code":"ID",
    "gn:dem":90,
    "gn:feature_class":"P",
    "gn:feature_code":"PPL",
    "gn:name":"Cidahu",
    "gn:population":0,
    "gn:timezone":"Asia/Jakarta",
    "iso:country":"ID",
    "name:ind_x_preferred":[
        "Cidahu"
    ],
    "name:und_x_variant":[
        "Cidah"
    ],
    "wof:name":"Cidahu",
    "wof:placetype":"locality"
},
  "geometry": {"coordinates":[107.73972000000001,-6.53556],"type":"Point"}
}