{
  "type": "Feature",
  "properties": {
    "gn:admin1_code":"41",
    "gn:asciiname":"Saluna",
    "gn:country_code":"ID",
    "gn:dem":20,
    "gn:feature_class":"P",
    "gn:feature_code":"PPL",
    "gn:name":"Saluna",
    "gn:population":0,
    "gn:timezone":"Asia/Makassar",
    "iso:country":"ID",
    "name:ind_x_preferred":[
        "Saluna"
    ],
    "wof:name":"Saluna",
    "wof:placetype":"locality"
},
  "geometry": {"coordinates":[118.9883,-3.4704],"type":"Point"}
}