{
  "type": "Feature",
  "properties": {
    "gn:admin1_code":"30.0",
    "gn:asciiname":"Cikananga Kulon",
    "gn:country_code":"ID",
    "gn:dem":13,
    "gn:feature_class":"P",
    "gn:feature_code":"PPL",
    "gn:name":"Cikananga Kulon",
    "gn:population":0,
    "gn:timezone":"Asia/Jakarta",
    "iso:country":"ID",
    "name:ind_x_preferred":[
        "Cikananga Kulon"
    ],
    "wof:name":"Cikananga Kulon",
    "wof:placetype":"locality"
},
  "geometry": {"coordinates":[106.9038,-7.4015],"type":"Point"}
}