{
  "type": "Feature",
  "properties": {
    "gn:admin1_code":"8",
    "gn:asciiname":"Wetangunung",
    "gn:country_code":"ID",
    "gn:dem":61,
    "gn:feature_class":"P",
    "gn:feature_code":"PPL",
    "gn:name":"Wetangunung",
    "gn:population":0,
    "gn:timezone":"Asia/Jakarta",
    "iso:country":"ID",
    "name:ind_x_preferred":[
        "Wetangunung"
    ],
    "wof:name":"Wetangunung",
    "wof:placetype":"locality"
},
  "geometry": {"coordinates":[113.6609,-8.27],"type":"Point"}
}