{
  "type": "Feature",
  "properties": {
    "gn:admin1_code":"30.0",
    "gn:asciiname":"Gantelan",
    "gn:country_code":"ID",
    "gn:dem":418,
    "gn:feature_class":"P",
    "gn:feature_code":"PPL",
    "gn:name":"Gantelan",
    "gn:population":0,
    "gn:timezone":"Asia/Jakarta",
    "iso:country":"ID",
    "name:ind_x_preferred":[
        "Gantelan"
    ],
    "name:und_x_variant":[
        "Gontelan"
    ],
    "wof:name":"Gantelan",
    "wof:placetype":"locality"
},
  "geometry": {"coordinates":[108.66,-7.5709],"type":"Point"}
}