{
  "type": "Feature",
  "properties": {
    "gn:admin1_code":"7.0",
    "gn:asciiname":"Kernen",
    "gn:country_code":"ID",
    "gn:dem":107,
    "gn:feature_class":"P",
    "gn:feature_code":"PPL",
    "gn:name":"Kernen",
    "gn:population":0,
    "gn:timezone":"Asia/Jakarta",
    "iso:country":"ID",
    "wof:name":"Kernen",
    "wof:placetype":"locality"
},
  "geometry": {"coordinates":[110.85693999999999,-7.67833],"type":"Point"}
}