{
  "type": "Feature",
  "properties": {
    "gn:admin1_code":"7.0",
    "gn:asciiname":"Kernen",
    "gn:country_code":"ID",
    "gn:dem":107,
    "gn:feature_class":"P",
    "gn:feature_code":"PPL",
    "gn:name":"Kernen",
    "gn:population":0,
    "gn:timezone":"Asia/Jakarta",
    "iso:country":"ID",
    "name:epo_x_preferred":[
        "Kernen"
    ],
    "name:eus_x_preferred":[
        "Kernen"
    ],
    "name:fas_x_preferred":[
        "\u06a9\u0631\u0646\u0646"
    ],
    "name:jpn_x_preferred":[
        "\u30b1\u30eb\u30cd\u30f3\u30fb\u30a4\u30e0\u30fb\u30ec\u30e0\u30b9\u30bf\u30fc\u30eb"
    ],
    "name:mkd_x_preferred":[
        "\u041a\u0435\u0440\u043d\u0435\u043d"
    ],
    "name:msa_x_preferred":[
        "Kernen"
    ],
    "name:rus_x_preferred":[
        "\u041a\u0435\u0440\u043d\u0435\u043d"
    ],
    "name:ukr_x_preferred":[
        "\u041a\u0435\u0440\u043d\u0435\u043d"
    ],
    "name:war_x_preferred":[
        "Kernen"
    ],
    "name:zho_x_preferred":[
        "\u96f7\u59c6\u65af\u6cb3\u8c37\u51ef\u5c14\u5ae9"
    ],
    "wof:lang_x_official":[
        "ind"
    ],
    "wof:lang_x_spoken":[
        "ind",
        "eng"
    ],
    "wof:name":"Kernen",
    "wof:placetype":"locality"
},
  "geometry": {"coordinates":[110.85693999999999,-7.67833],"type":"Point"}
}