{
  "type": "Feature",
  "properties": {
    "gn:admin1_code":"33",
    "gn:asciiname":"Pasirhuni",
    "gn:country_code":"ID",
    "gn:dem":40,
    "gn:feature_class":"P",
    "gn:feature_code":"PPL",
    "gn:name":"Pasirhuni",
    "gn:population":0,
    "gn:timezone":"Asia/Jakarta",
    "iso:country":"ID",
    "name:ind_x_preferred":[
        "Pasirhuni"
    ],
    "name:und_x_variant":[
        "Pasirhuni 2",
        "Pasirhuni Dua"
    ],
    "wof:name":"Pasirhuni",
    "wof:placetype":"locality"
},
  "geometry": {"coordinates":[106.3021,-6.3079],"type":"Point"}
}