{
  "type": "Feature",
  "properties": {
    "gn:admin1_code":"8.0",
    "gn:asciiname":"Sukowiyono Empat",
    "gn:country_code":"ID",
    "gn:dem":67,
    "gn:feature_class":"P",
    "gn:feature_code":"PPL",
    "gn:name":"Sukowiyono Empat",
    "gn:population":0,
    "gn:timezone":"Asia/Jakarta",
    "iso:country":"ID",
    "name:ind_x_preferred":[
        "Sukowiyono Empat"
    ],
    "wof:name":"Sukowiyono Empat",
    "wof:placetype":"locality"
},
  "geometry": {"coordinates":[111.54130000000001,-7.4517],"type":"Point"}
}