{
  "type": "Feature",
  "properties": {
    "gn:admin1_code":"30",
    "gn:asciiname":"Sodong Satu",
    "gn:cc2":"ID",
    "gn:country_code":"ID",
    "gn:dem":806,
    "gn:feature_class":"P",
    "gn:feature_code":"PPL",
    "gn:name":"Sodong Satu",
    "gn:population":0,
    "gn:timezone":"Asia/Jakarta",
    "iso:country":"ID",
    "name:und_x_variant":[
        "Sodong 1",
        "Sodong Satu"
    ],
    "wof:name":"Sodong Satu",
    "wof:placetype":"locality"
},
  "geometry": {"coordinates":[107.49889,-7.03222],"type":"Point"}
}