{
  "type": "Feature",
  "properties": {
    "gn:country":"ID",
    "gn:fcode":"PPL",
    "gn:pop":0,
    "iso:country":"ID",
    "name:ban_x_preferred":[
        "Pasar Kliwon"
    ],
    "name:ceb_x_preferred":[
        "Kecamatan Pasarkliwon"
    ],
    "name:deu_x_preferred":[
        "Pasar Kliwon"
    ],
    "name:eng_x_preferred":[
        "Pasar Kliwon"
    ],
    "name:fra_x_preferred":[
        "Pasar Kliwon"
    ],
    "name:ind_x_preferred":[
        "Pasar Kliwon"
    ],
    "name:jav_x_preferred":[
        "Pasar Kliwon"
    ],
    "name:jpn_x_preferred":[
        "\u30d1\u30b5\u30fc\u30eb\u30af\u30ea\u30a6\u30a9\u30f3"
    ],
    "name:nan_x_preferred":[
        "Pasar Kliwon"
    ],
    "name:nld_x_preferred":[
        "Pasar Kliwon"
    ],
    "name:swe_x_preferred":[
        "Kecamatan Pasarkliwon"
    ],
    "qs:name":"Gajahan",
    "qs:name_adm0":"Indonesia",
    "qs:name_adm1":"Provinsi Jawa Tengah",
    "qs:photos_9k":1,
    "qs:photos_9r":4,
    "qs:photos_all":235,
    "qs:photos_sr":0,
    "qs:placetype":"Town",
    "qs:pop_sr":"0",
    "wd:wordcount":160,
    "wof:lang_x_official":[
        "ind"
    ],
    "wof:lang_x_spoken":[
        "ind",
        "eng"
    ],
    "wof:name":"Gajahan",
    "wof:placetype":"locality",
    "wof:population":0
},
  "geometry": {"coordinates":[110.82250000000001,-7.58167],"type":"Point"}
}