{
  "type": "Feature",
  "properties": {
    "gn:country":"ID",
    "gn:fcode":"PPL",
    "gn:pop":0,
    "iso:country":"ID",
    "qs:name":"Gajahan",
    "qs:name_adm0":"Indonesia",
    "qs:name_adm1":"Provinsi Jawa Tengah",
    "qs:photos_9k":1,
    "qs:photos_9r":4,
    "qs:photos_all":235,
    "qs:photos_sr":0,
    "qs:placetype":"Town",
    "qs:pop_sr":"0",
    "wd:wordcount":160,
    "wof:name":"Gajahan",
    "wof:placetype":"locality",
    "wof:population":0
},
  "geometry": {"coordinates":[110.82250000000001,-7.58167],"type":"Point"}
}