{
  "type": "Feature",
  "properties": {
    "gn:admin1_code":"30.0",
    "gn:asciiname":"Cijampang",
    "gn:country_code":"ID",
    "gn:dem":214,
    "gn:feature_class":"P",
    "gn:feature_code":"PPL",
    "gn:name":"Cijampang",
    "gn:population":0,
    "gn:timezone":"Asia/Jakarta",
    "iso:country":"ID",
    "name:ind_x_preferred":[
        "Cijampang"
    ],
    "name:und_x_variant":[
        "Tjidjampang"
    ],
    "wof:lang_x_official":[
        "ind"
    ],
    "wof:lang_x_spoken":[
        "ind",
        "eng"
    ],
    "wof:name":"Cijampang",
    "wof:placetype":"locality"
},
  "geometry": {"coordinates":[107.0868,-7.2481],"type":"Point"}
}