{
  "type": "Feature",
  "properties": {
    "gn:admin1_code":"8.0",
    "gn:asciiname":"Jirak",
    "gn:country_code":"ID",
    "gn:dem":366,
    "gn:feature_class":"P",
    "gn:feature_code":"PPL",
    "gn:name":"Jirak",
    "gn:population":0,
    "gn:timezone":"Asia/Jakarta",
    "iso:country":"ID",
    "name:ind_x_preferred":[
        "Jirak"
    ],
    "wof:name":"Jirak",
    "wof:placetype":"locality"
},
  "geometry": {"coordinates":[111.9004,-8.1753],"type":"Point"}
}