{
  "type": "Feature",
  "properties": {
    "gn:admin1_code":"38.0",
    "gn:asciiname":"Kareccing",
    "gn:country_code":"ID",
    "gn:dem":26,
    "gn:feature_class":"P",
    "gn:feature_code":"PPL",
    "gn:name":"Kareccing",
    "gn:population":0,
    "gn:timezone":"Asia/Makassar",
    "iso:country":"ID",
    "name:ind_x_preferred":[
        "Kareccing"
    ],
    "wof:name":"Kareccing",
    "wof:placetype":"locality"
},
  "geometry": {"coordinates":[120.3699,-4.6857],"type":"Point"}
}