{
  "type": "Feature",
  "properties": {
    "gn:admin1_code":"08",
    "gn:asciiname":"Babatan",
    "gn:country_code":"ID",
    "gn:dem":541,
    "gn:feature_class":"P",
    "gn:feature_code":"PPL",
    "gn:name":"Babatan",
    "gn:population":0,
    "gn:timezone":"Asia/Jakarta",
    "iso:country":"ID",
    "wof:name":"Babatan",
    "wof:placetype":"locality"
},
  "geometry": {"coordinates":[112.605,-7.91333],"type":"Point"}
}