{
  "type": "Feature",
  "properties": {
    "gn:admin1_code":"10.0",
    "gn:asciiname":"Waru",
    "gn:country_code":"ID",
    "gn:dem":275,
    "gn:feature_class":"P",
    "gn:feature_code":"PPL",
    "gn:name":"Waru",
    "gn:population":0,
    "gn:timezone":"Asia/Jakarta",
    "iso:country":"ID",
    "name:ceb_x_preferred":[
        "Waru"
    ],
    "name:ind_x_preferred":[
        "Waru"
    ],
    "name:nld_x_preferred":[
        "Waru"
    ],
    "name:rus_x_preferred":[
        "\u0412\u0430\u0440\u0443"
    ],
    "name:swe_x_preferred":[
        "Waru"
    ],
    "wof:name":"Waru",
    "wof:placetype":"locality"
},
  "geometry": {"coordinates":[110.74417,-8.12806],"type":"Point"}
}