{
  "type": "Feature",
  "properties": {
    "gn:admin1_code":"26",
    "gn:asciiname":"Tangkahan Lagan",
    "gn:country_code":"ID",
    "gn:dem":9,
    "gn:feature_class":"P",
    "gn:feature_code":"PPL",
    "gn:name":"Tangkahan Lagan",
    "gn:population":0,
    "gn:timezone":"Asia/Jakarta",
    "iso:country":"ID",
    "name:ind_x_preferred":[
        "Tangkahan Lagan"
    ],
    "wof:name":"Tangkahan Lagan",
    "wof:placetype":"locality"
},
  "geometry": {"coordinates":[98.256,4.0036],"type":"Point"}
}