{
  "type": "Feature",
  "properties": {
    "gn:admin1_code":"18.0",
    "gn:asciiname":"Gege",
    "gn:country_code":"ID",
    "gn:dem":21,
    "gn:feature_class":"P",
    "gn:feature_code":"PPL",
    "gn:name":"Gege",
    "gn:population":0,
    "gn:timezone":"Asia/Makassar",
    "iso:country":"ID",
    "name:ceb_x_preferred":[
        "Gege"
    ],
    "name:deu_x_preferred":[
        "Gege"
    ],
    "name:ind_x_preferred":[
        "Gege"
    ],
    "name:swe_x_preferred":[
        "Gege"
    ],
    "wof:name":"Gege",
    "wof:placetype":"locality"
},
  "geometry": {"coordinates":[123.0021,-8.3293],"type":"Point"}
}