{
  "type": "Feature",
  "properties": {
    "gn:admin1_code":"18.0",
    "gn:asciiname":"Timbudona",
    "gn:country_code":"ID",
    "gn:dem":95,
    "gn:feature_class":"P",
    "gn:feature_code":"PPL",
    "gn:name":"Timbudona",
    "gn:population":0,
    "gn:timezone":"Asia/Makassar",
    "iso:country":"ID",
    "name:ind_x_preferred":[
        "Timbudona"
    ],
    "wof:name":"Timbudona",
    "wof:placetype":"locality"
},
  "geometry": {"coordinates":[119.3884,-9.448],"type":"Point"}
}