{
  "type": "Feature",
  "properties": {
    "gn:admin1_code":"30.0",
    "gn:asciiname":"Pasirkorek",
    "gn:country_code":"ID",
    "gn:dem":290,
    "gn:feature_class":"P",
    "gn:feature_code":"PPL",
    "gn:name":"Pasirkorek",
    "gn:population":0,
    "gn:timezone":"Asia/Jakarta",
    "iso:country":"ID",
    "name:ind_x_preferred":[
        "Pasirkorek"
    ],
    "wof:name":"Pasirkorek",
    "wof:placetype":"locality"
},
  "geometry": {"coordinates":[108.2835,-7.5972],"type":"Point"}
}