{
  "type": "Feature",
  "properties": {
    "gn:admin1_code":"1",
    "gn:asciiname":"Beukeut",
    "gn:country_code":"ID",
    "gn:dem":1341,
    "gn:feature_class":"P",
    "gn:feature_code":"PPL",
    "gn:name":"Beukeut",
    "gn:population":0,
    "gn:timezone":"Asia/Jakarta",
    "iso:country":"ID",
    "name:ind_x_preferred":[
        "Beukeut"
    ],
    "wof:name":"Beukeut",
    "wof:placetype":"locality"
},
  "geometry": {"coordinates":[96.9962,4.0454],"type":"Point"}
}