{
  "type": "Feature",
  "properties": {
    "gn:admin1_code":"8.0",
    "gn:asciiname":"Genenglo",
    "gn:country_code":"ID",
    "gn:dem":36,
    "gn:feature_class":"P",
    "gn:feature_code":"PPL",
    "gn:name":"Genenglo",
    "gn:population":0,
    "gn:timezone":"Asia/Jakarta",
    "iso:country":"ID",
    "name:ind_x_preferred":[
        "Genenglo"
    ],
    "wof:name":"Genenglo",
    "wof:placetype":"locality"
},
  "geometry": {"coordinates":[112.2749,-7.4139],"type":"Point"}
}