{
  "type": "Feature",
  "properties": {
    "gn:admin1_code":"29.0",
    "gn:asciiname":"Fat Kauyon",
    "gn:country_code":"ID",
    "gn:dem":12,
    "gn:feature_class":"P",
    "gn:feature_code":"PPL",
    "gn:name":"Fat Kauyon",
    "gn:population":0,
    "gn:timezone":"Asia/Jayapura",
    "iso:country":"ID",
    "name:ind_x_preferred":[
        "Fat Kauyon"
    ],
    "name:ind_x_variant":[
        "Fatkaujon"
    ],
    "name:und_x_variant":[
        "Fat Kaujon",
        "Fat Kauyon"
    ],
    "wof:lang_x_official":[
        "ind"
    ],
    "wof:lang_x_spoken":[
        "ind",
        "eng"
    ],
    "wof:name":"Fat Kauyon",
    "wof:placetype":"locality"
},
  "geometry": {"coordinates":[126.06811,-2.45401],"type":"Point"}
}