{
  "type": "Feature",
  "properties": {
    "gn:admin1_code":"08",
    "gn:asciiname":"Lawu",
    "gn:country_code":"ID",
    "gn:dem":4,
    "gn:feature_class":"P",
    "gn:feature_code":"PPL",
    "gn:name":"Lawu",
    "gn:population":0,
    "gn:timezone":"Asia/Jakarta",
    "iso:country":"ID",
    "name:ind_x_preferred":[
        "Lawu"
    ],
    "name:und_x_variant":[
        "Lawuh"
    ],
    "wof:name":"Lawu",
    "wof:placetype":"locality"
},
  "geometry": {"coordinates":[112.586,-7.0694],"type":"Point"}
}