{
  "type": "Feature",
  "properties": {
    "gn:admin1_code":"18.0",
    "gn:asciiname":"Asi",
    "gn:country_code":"ID",
    "gn:dem":10,
    "gn:feature_class":"P",
    "gn:feature_code":"PPL",
    "gn:name":"Asi",
    "gn:population":0,
    "gn:timezone":"Asia/Makassar",
    "iso:country":"ID",
    "name:ind_x_preferred":[
        "Asi"
    ],
    "wof:name":"Asi",
    "wof:placetype":"locality"
},
  "geometry": {"coordinates":[120.76179999999999,-8.3422],"type":"Point"}
}