{
  "type": "Feature",
  "properties": {
    "gn:admin1_code":"30.0",
    "gn:asciiname":"Gunungbango",
    "gn:country_code":"ID",
    "gn:dem":425,
    "gn:feature_class":"P",
    "gn:feature_code":"PPL",
    "gn:name":"Gunungbango",
    "gn:population":0,
    "gn:timezone":"Asia/Jakarta",
    "iso:country":"ID",
    "name:ind_x_preferred":[
        "Gunungbango"
    ],
    "name:und_x_variant":[
        "Goenoengbango"
    ],
    "wof:name":"Gunungbango",
    "wof:placetype":"locality"
},
  "geometry": {"coordinates":[108.1562,-7.3332],"type":"Point"}
}