{
  "type": "Feature",
  "properties": {
    "gn:admin1_code":"2",
    "gn:asciiname":"Banjar Petuludesa",
    "gn:country_code":"ID",
    "gn:dem":278,
    "gn:feature_class":"P",
    "gn:feature_code":"PPL",
    "gn:name":"Banjar Petuludesa",
    "gn:population":0,
    "gn:timezone":"Asia/Makassar",
    "iso:country":"ID",
    "name:ind_x_preferred":[
        "Banjar Petuludesa"
    ],
    "wof:name":"Banjar Petuludesa",
    "wof:placetype":"locality"
},
  "geometry": {"coordinates":[115.27419999999999,-8.4869],"type":"Point"}
}