{
  "type": "Feature",
  "properties": {
    "gn:admin1_code":"18",
    "gn:asciiname":"Bung",
    "gn:country_code":"ID",
    "gn:dem":728,
    "gn:feature_class":"P",
    "gn:feature_code":"PPL",
    "gn:name":"Bung",
    "gn:population":0,
    "gn:timezone":"Asia/Makassar",
    "iso:country":"ID",
    "name:ara_x_preferred":[
        "\u0641\u062f\u0627\u0645"
    ],
    "name:deu_x_preferred":[
        "Korken"
    ],
    "name:eml_x_preferred":[
        "S\u00f9ver"
    ],
    "name:glg_x_preferred":[
        "Rolla"
    ],
    "name:heb_x_preferred":[
        "\u05e4\u05e7\u05e7"
    ],
    "name:hrv_x_preferred":[
        "Pluteni \u010dep"
    ],
    "name:ind_x_preferred":[
        "Bung"
    ],
    "name:lat_x_preferred":[
        "Embolus"
    ],
    "name:lim_x_preferred":[
        "K\u00f6rk"
    ],
    "name:nap_x_preferred":[
        "Att\u00fappere"
    ],
    "name:new_x_preferred":[
        "\u092c\u0941\u0919"
    ],
    "name:nld_x_preferred":[
        "Kurk"
    ],
    "name:nor_x_preferred":[
        "Kork"
    ],
    "name:pol_x_preferred":[
        "Korek"
    ],
    "name:por_x_preferred":[
        "Rolha"
    ],
    "name:ron_x_preferred":[
        "Dop"
    ],
    "name:scn_x_preferred":[
        "Stuppagghiu"
    ],
    "name:spa_x_preferred":[
        "Tap\u00f3n"
    ],
    "name:srp_x_preferred":[
        "\u041f\u0430\u043c\u043f\u0443\u0440"
    ],
    "name:szl_x_preferred":[
        "Frup"
    ],
    "name:ukr_x_preferred":[
        "\u0427\u0456\u043f"
    ],
    "name:vec_x_preferred":[
        "Str\u00f2po\u0142o"
    ],
    "name:vep_x_preferred":[
        "T\u00fcp"
    ],
    "name:zho_x_preferred":[
        "\u8edf\u6728\u585e"
    ],
    "wof:lang_x_official":[
        "ind"
    ],
    "wof:lang_x_spoken":[
        "ind",
        "eng"
    ],
    "wof:name":"Bung",
    "wof:placetype":"locality"
},
  "geometry": {"coordinates":[120.4884,-8.5379],"type":"Point"}
}