{
  "type": "Feature",
  "properties": {
    "gn:admin1_code":"33.0",
    "gn:asciiname":"Banten",
    "gn:country_code":"ID",
    "gn:dem":3,
    "gn:feature_class":"P",
    "gn:feature_code":"PPL",
    "gn:name":"Banten",
    "gn:population":0,
    "gn:timezone":"Asia/Jakarta",
    "iso:country":"ID",
    "name:ara_x_preferred":[
        "\u0628\u0646\u062a\u0646"
    ],
    "name:cat_x_preferred":[
        "Bantam"
    ],
    "name:epo_x_preferred":[
        "Banten"
    ],
    "name:fra_x_preferred":[
        "Banten"
    ],
    "name:hun_x_preferred":[
        "Banten"
    ],
    "name:ind_x_preferred":[
        "Banten"
    ],
    "name:ita_x_preferred":[
        "Bantam"
    ],
    "name:msa_x_preferred":[
        "Banten"
    ],
    "name:nld_x_preferred":[
        "Banten"
    ],
    "name:pol_x_preferred":[
        "Banten"
    ],
    "name:rus_x_preferred":[
        "\u0411\u0430\u043d\u0442\u0435\u043d"
    ],
    "name:rus_x_variant":[
        "\u0411\u0430\u043d\u0442\u0430\u043c"
    ],
    "name:spa_x_preferred":[
        "Bant\u00e9n"
    ],
    "name:ukr_x_preferred":[
        "\u0411\u0430\u043d\u0442\u0430\u043c"
    ],
    "name:und_x_variant":[
        "Bantam",
        "Banten"
    ],
    "name:vie_x_preferred":[
        "Bantam"
    ],
    "wof:lang_x_official":[
        "ind"
    ],
    "wof:lang_x_spoken":[
        "ind",
        "eng"
    ],
    "wof:name":"Banten",
    "wof:placetype":"locality"
},
  "geometry": {"coordinates":[106.164,-6.0307],"type":"Point"}
}