{
  "type": "Feature",
  "properties": {
    "gn:admin1_code":"33.0",
    "gn:asciiname":"Banten",
    "gn:country_code":"ID",
    "gn:dem":3,
    "gn:feature_class":"P",
    "gn:feature_code":"PPL",
    "gn:name":"Banten",
    "gn:population":0,
    "gn:timezone":"Asia/Jakarta",
    "iso:country":"ID",
    "name:rus_x_preferred":[
        "\u0411\u0430\u043d\u0442\u0435\u043d"
    ],
    "name:und_x_variant":[
        "Bantam",
        "Banten"
    ],
    "wof:name":"Banten",
    "wof:placetype":"locality"
},
  "geometry": {"coordinates":[106.164,-6.0307],"type":"Point"}
}