{
  "type": "Feature",
  "properties": {
    "gn:admin1_code":"30",
    "gn:asciiname":"Bank Tabungan Negara",
    "gn:country_code":"ID",
    "gn:dem":92,
    "gn:feature_class":"P",
    "gn:feature_code":"PPL",
    "gn:name":"Bank Tabungan Negara",
    "gn:population":0,
    "gn:timezone":"Asia/Jakarta",
    "iso:country":"ID",
    "name:ind_x_preferred":[
        "Bank Tabungan Negara"
    ],
    "name:und_x_variant":[
        "BTN Ciheuleutindah"
    ],
    "wof:lang_x_official":[
        "ind"
    ],
    "wof:lang_x_spoken":[
        "ind",
        "eng"
    ],
    "wof:name":"Bank Tabungan Negara",
    "wof:placetype":"locality"
},
  "geometry": {"coordinates":[107.76833000000001,-6.57722],"type":"Point"}
}