{
  "type": "Feature",
  "properties": {
    "gn:admin1_code":"0.0",
    "gn:asciiname":"Lubukdalem",
    "gn:cc2":"ID",
    "gn:country_code":"ID",
    "gn:dem":26,
    "gn:feature_class":"P",
    "gn:feature_code":"PPL",
    "gn:name":"Lubukdalem",
    "gn:population":0,
    "gn:timezone":"Asia/Jakarta",
    "iso:country":"ID",
    "name:und_x_variant":[
        "Loeboekdalam",
        "Loeboekdalem",
        "Lubukdalem"
    ],
    "wof:lang_x_official":[
        "ind"
    ],
    "wof:lang_x_spoken":[
        "ind",
        "eng"
    ],
    "wof:name":"Lubukdalem",
    "wof:placetype":"locality"
},
  "geometry": {"coordinates":[99.83333,2.25],"type":"Point"}
}