{
  "type": "Feature",
  "properties": {
    "gn:admin1_code":"17.0",
    "gn:asciiname":"Rade Dua",
    "gn:country_code":"ID",
    "gn:dem":33,
    "gn:feature_class":"P",
    "gn:feature_code":"PPL",
    "gn:name":"Rade Dua",
    "gn:population":0,
    "gn:timezone":"Asia/Makassar",
    "iso:country":"ID",
    "name:ind_x_preferred":[
        "Rade Dua"
    ],
    "wof:name":"Rade Dua",
    "wof:placetype":"locality"
},
  "geometry": {"coordinates":[118.5855,-8.5219],"type":"Point"}
}