{
  "type": "Feature",
  "properties": {
    "gn:admin1_code":"30",
    "gn:asciiname":"Rancamukti",
    "gn:country_code":"ID",
    "gn:dem":49,
    "gn:feature_class":"P",
    "gn:feature_code":"PPL",
    "gn:name":"Rancamukti",
    "gn:population":0,
    "gn:timezone":"Asia/Jakarta",
    "iso:country":"ID",
    "name:ind_x_preferred":[
        "Rancamukti"
    ],
    "wof:name":"Rancamukti",
    "wof:placetype":"locality"
},
  "geometry": {"coordinates":[108.12139000000001,-6.63556],"type":"Point"}
}