{
  "type": "Feature",
  "properties": {
    "gn:admin1_code":"30",
    "gn:asciiname":"Hegarasih",
    "gn:country_code":"ID",
    "gn:dem":752,
    "gn:feature_class":"P",
    "gn:feature_code":"PPL",
    "gn:name":"Hegarasih",
    "gn:population":0,
    "gn:timezone":"Asia/Jakarta",
    "iso:country":"ID",
    "name:ind_x_preferred":[
        "Hegarasih"
    ],
    "wof:name":"Hegarasih",
    "wof:placetype":"locality"
},
  "geometry": {"coordinates":[107.60472,-6.88917],"type":"Point"}
}