{
  "type": "Feature",
  "properties": {
    "gn:admin1_code":"8",
    "gn:asciiname":"Tengger",
    "gn:country_code":"ID",
    "gn:dem":8,
    "gn:feature_class":"P",
    "gn:feature_code":"PPL",
    "gn:name":"Tengger",
    "gn:population":0,
    "gn:timezone":"Asia/Jakarta",
    "iso:country":"ID",
    "name:deu_x_preferred":[
        "Tengger"
    ],
    "name:fra_x_preferred":[
        "Tengger"
    ],
    "name:ind_x_preferred":[
        "Tengger"
    ],
    "name:nld_x_preferred":[
        "Tengger"
    ],
    "name:slk_x_preferred":[
        "Tengger"
    ],
    "name:tur_x_preferred":[
        "Tengger"
    ],
    "wof:name":"Tengger",
    "wof:placetype":"locality"
},
  "geometry": {"coordinates":[112.2824,-7.0628],"type":"Point"}
}