{
  "type": "Feature",
  "properties": {
    "gn:admin1_code":"24",
    "gn:asciiname":"Balasir",
    "gn:country_code":"ID",
    "gn:dem":573,
    "gn:feature_class":"P",
    "gn:feature_code":"PPL",
    "gn:name":"Balasir",
    "gn:population":0,
    "gn:timezone":"Asia/Jakarta",
    "iso:country":"ID",
    "name:ind_x_preferred":[
        "Balasir"
    ],
    "wof:name":"Balasir",
    "wof:placetype":"locality"
},
  "geometry": {"coordinates":[100.65347,-0.69387],"type":"Point"}
}