{
  "type": "Feature",
  "properties": {
    "gn:admin1_code":"7",
    "gn:asciiname":"Pabatan",
    "gn:country_code":"ID",
    "gn:dem":506,
    "gn:feature_class":"P",
    "gn:feature_code":"PPL",
    "gn:name":"Pabatan",
    "gn:population":0,
    "gn:timezone":"Asia/Jakarta",
    "iso:country":"ID",
    "name:ind_x_preferred":[
        "Pabatan"
    ],
    "wof:name":"Pabatan",
    "wof:placetype":"locality"
},
  "geometry": {"coordinates":[110.38611000000002,-7.14833],"type":"Point"}
}