{
  "type": "Feature",
  "properties": {
    "gn:admin1_code":"8",
    "gn:asciiname":"Dagen",
    "gn:country_code":"ID",
    "gn:dem":624,
    "gn:feature_class":"P",
    "gn:feature_code":"PPL",
    "gn:name":"Dagen",
    "gn:population":0,
    "gn:timezone":"Asia/Jakarta",
    "iso:country":"ID",
    "name:ceb_x_preferred":[
        "Dagen"
    ],
    "name:dan_x_preferred":[
        "Dagen"
    ],
    "name:ind_x_preferred":[
        "Dagen"
    ],
    "name:nor_x_preferred":[
        "Dagen"
    ],
    "name:swe_x_preferred":[
        "Dagen"
    ],
    "wof:lang_x_official":[
        "ind"
    ],
    "wof:lang_x_spoken":[
        "ind",
        "eng"
    ],
    "wof:name":"Dagen",
    "wof:placetype":"locality"
},
  "geometry": {"coordinates":[111.33667,-8.03889],"type":"Point"}
}