{
  "type": "Feature",
  "properties": {
    "gn:admin1_code":"30",
    "gn:asciiname":"Leuwianjing Satu",
    "gn:country_code":"ID",
    "gn:dem":71,
    "gn:feature_class":"P",
    "gn:feature_code":"PPL",
    "gn:name":"Leuwianjing Satu",
    "gn:population":0,
    "gn:timezone":"Asia/Jakarta",
    "iso:country":"ID",
    "name:ind_x_preferred":[
        "Leuwianjing Satu"
    ],
    "wof:name":"Leuwianjing Satu",
    "wof:placetype":"locality"
},
  "geometry": {"coordinates":[107.14055999999999,-6.51361],"type":"Point"}
}