{
  "type": "Feature",
  "properties": {
    "gn:country":"ID",
    "gn:fcode":"PPL",
    "gn:pop":1273,
    "iso:country":"ID",
    "name:unk_x_variant":[
        "Gunung Kendit"
    ],
    "qs:name":"Gunung Kendil",
    "qs:photos_9r":0,
    "qs:photos_sr":0,
    "qs:pop_sr":"3",
    "wof:lang_x_official":[
        "ind"
    ],
    "wof:lang_x_spoken":[
        "ind",
        "eng"
    ],
    "wof:name":"Gunung Kendil",
    "wof:placetype":"locality",
    "wof:population":1273
},
  "geometry": {"coordinates":[110.40416999999999,-7.33167],"type":"Point"}
}