{
  "type": "Feature",
  "properties": {
    "gn:admin1_code":"7",
    "gn:asciiname":"Denasri Kidul",
    "gn:country_code":"ID",
    "gn:dem":8,
    "gn:feature_class":"P",
    "gn:feature_code":"PPL",
    "gn:name":"Denasri Kidul",
    "gn:population":0,
    "gn:timezone":"Asia/Jakarta",
    "iso:country":"ID",
    "name:ind_x_preferred":[
        "Denasri Kidul"
    ],
    "wof:name":"Denasri Kidul",
    "wof:placetype":"locality"
},
  "geometry": {"coordinates":[109.7144,-6.89937],"type":"Point"}
}