{
  "type": "Feature",
  "properties": {
    "gn:admin1_code":"7",
    "gn:asciiname":"Ngundaan",
    "gn:country_code":"ID",
    "gn:dem":128,
    "gn:feature_class":"P",
    "gn:feature_code":"PPL",
    "gn:name":"Ngundaan",
    "gn:population":0,
    "gn:timezone":"Asia/Jakarta",
    "iso:country":"ID",
    "name:ind_x_preferred":[
        "Ngundaan"
    ],
    "wof:name":"Ngundaan",
    "wof:placetype":"locality"
},
  "geometry": {"coordinates":[111.30833,-7.29333],"type":"Point"}
}