{
  "type": "Feature",
  "properties": {
    "gn:admin1_code":"30.0",
    "gn:asciiname":"Ciangir",
    "gn:country_code":"ID",
    "gn:dem":102,
    "gn:feature_class":"P",
    "gn:feature_code":"PPLA4",
    "gn:name":"Ciangir",
    "gn:population":0,
    "gn:timezone":"Asia/Jakarta",
    "iso:country":"ID",
    "name:ind_x_preferred":[
        "Ciangir"
    ],
    "name:und_x_variant":[
        "Tjiangir"
    ],
    "wof:lang_x_official":[
        "ind"
    ],
    "wof:lang_x_spoken":[
        "ind",
        "eng"
    ],
    "wof:name":"Ciangir",
    "wof:placetype":"locality"
},
  "geometry": {"coordinates":[108.74639999999999,-7.0791],"type":"Point"}
}