{
  "type": "Feature",
  "properties": {
    "gn:admin1_code":"28.0",
    "gn:asciiname":"Fudbohot",
    "gn:country_code":"ID",
    "gn:dem":571,
    "gn:feature_class":"P",
    "gn:feature_code":"PPL",
    "gn:name":"Fudbohot",
    "gn:population":0,
    "gn:timezone":"Asia/Jayapura",
    "iso:country":"ID",
    "name:ind_x_preferred":[
        "Fudbohot"
    ],
    "name:und_x_variant":[
        "Foed\u2019 Bohot",
        "Foed",
        "Fud Bohot"
    ],
    "wof:name":"Fudbohot",
    "wof:placetype":"locality"
},
  "geometry": {"coordinates":[126.87781,-3.62066],"type":"Point"}
}