{
  "type": "Feature",
  "properties": {
    "gn:admin1_code":"7.0",
    "gn:asciiname":"Tondan",
    "gn:country_code":"ID",
    "gn:dem":160,
    "gn:feature_class":"P",
    "gn:feature_code":"PPL",
    "gn:name":"Tondan",
    "gn:population":0,
    "gn:timezone":"Asia/Jakarta",
    "iso:country":"ID",
    "name:ind_x_preferred":[
        "Tondan"
    ],
    "wof:name":"Tondan",
    "wof:placetype":"locality"
},
  "geometry": {"coordinates":[110.86417,-8.03361],"type":"Point"}
}