{
  "type": "Feature",
  "properties": {
    "gn:admin1_code":"26",
    "gn:asciiname":"Kuta Tengah",
    "gn:country_code":"ID",
    "gn:dem":480,
    "gn:feature_class":"P",
    "gn:feature_code":"PPL",
    "gn:name":"Kuta Tengah",
    "gn:population":0,
    "gn:timezone":"Asia/Jakarta",
    "iso:country":"ID",
    "name:ind_x_preferred":[
        "Kuta Tengah"
    ],
    "wof:name":"Kuta Tengah",
    "wof:placetype":"locality"
},
  "geometry": {"coordinates":[98.24890000000001,2.8964],"type":"Point"}
}