{
  "type": "Feature",
  "properties": {
    "gn:admin1_code":"30",
    "gn:asciiname":"Cieunteung",
    "gn:country_code":"ID",
    "gn:dem":517,
    "gn:feature_class":"P",
    "gn:feature_code":"PPL",
    "gn:name":"Cieunteung",
    "gn:population":0,
    "gn:timezone":"Asia/Jakarta",
    "iso:country":"ID",
    "name:ind_x_preferred":[
        "Cieunteung"
    ],
    "wof:name":"Cieunteung",
    "wof:placetype":"locality"
},
  "geometry": {"coordinates":[108.00139,-6.7575],"type":"Point"}
}