{
  "type": "Feature",
  "properties": {
    "gn:admin1_code":"8.0",
    "gn:asciiname":"Sendang Barat",
    "gn:country_code":"ID",
    "gn:dem":16,
    "gn:feature_class":"P",
    "gn:feature_code":"PPL",
    "gn:name":"Sendang Barat",
    "gn:population":0,
    "gn:timezone":"Asia/Jakarta",
    "iso:country":"ID",
    "name:ind_x_preferred":[
        "Sendang Barat"
    ],
    "wof:name":"Sendang Barat",
    "wof:placetype":"locality"
},
  "geometry": {"coordinates":[113.621,-7.1208],"type":"Point"}
}