{
  "type": "Feature",
  "properties": {
    "gn:admin1_code":"28.0",
    "gn:asciiname":"Tahaupu",
    "gn:country_code":"ID",
    "gn:dem":7,
    "gn:feature_class":"P",
    "gn:feature_code":"PPL",
    "gn:name":"Tahaupu",
    "gn:population":0,
    "gn:timezone":"Asia/Jayapura",
    "iso:country":"ID",
    "name:ind_x_preferred":[
        "Tahaupu"
    ],
    "name:und_x_variant":[
        "Tahaloepoe",
        "Tahalupu",
        "Lanaiupu"
    ],
    "wof:lang_x_official":[
        "ind"
    ],
    "wof:lang_x_spoken":[
        "ind",
        "eng"
    ],
    "wof:name":"Tahaupu",
    "wof:placetype":"locality"
},
  "geometry": {"coordinates":[127.65649000000001,-3.2331],"type":"Point"}
}