{
  "type": "Feature",
  "properties": {
    "gn:admin1_code":"30",
    "gn:asciiname":"Bulanbulan",
    "gn:country_code":"ID",
    "gn:dem":643,
    "gn:feature_class":"P",
    "gn:feature_code":"PPL",
    "gn:name":"Bulanbulan",
    "gn:population":0,
    "gn:timezone":"Asia/Jakarta",
    "iso:country":"ID",
    "name:ind_x_preferred":[
        "Bulanbulan"
    ],
    "wof:name":"Bulanbulan",
    "wof:placetype":"locality"
},
  "geometry": {"coordinates":[107.42028000000001,-6.84056],"type":"Point"}
}