{
  "type": "Feature",
  "properties": {
    "gn:country":"ID",
    "gn:fcode":"ADM3",
    "gn:pop":0,
    "iso:country":"ID",
    "name:eng_x_preferred":[
        "Districts of Central Java"
    ],
    "name:ind_x_preferred":[
        "Kecamatan Mayong"
    ],
    "name:unk_x_variant":[
        "Mayong"
    ],
    "qs:name":"Kecamatan Mayong",
    "qs:photos_9r":0,
    "qs:photos_sr":0,
    "qs:pop_sr":"0",
    "wd:wordcount":1175,
    "wof:name":"Kecamatan Mayong",
    "wof:placetype":"localadmin",
    "wof:population":0
},
  "geometry": {"coordinates":[110.7724,-6.7026],"type":"Point"}
}