{
  "type": "Feature",
  "properties": {
    "gn:admin1_code":"2",
    "gn:asciiname":"Banjar Penyaringan",
    "gn:country_code":"ID",
    "gn:dem":7,
    "gn:feature_class":"P",
    "gn:feature_code":"PPL",
    "gn:name":"Banjar Penyaringan",
    "gn:population":0,
    "gn:timezone":"Asia/Makassar",
    "iso:country":"ID",
    "name:ind_x_preferred":[
        "Banjar Penyaringan"
    ],
    "wof:name":"Banjar Penyaringan",
    "wof:placetype":"locality"
},
  "geometry": {"coordinates":[115.25360000000001,-8.6944],"type":"Point"}
}