{
  "type": "Feature",
  "properties": {
    "gn:admin1_code":"21.0",
    "gn:asciiname":"Negerilama",
    "gn:country_code":"ID",
    "gn:dem":9,
    "gn:feature_class":"P",
    "gn:feature_code":"PPL",
    "gn:name":"Negerilama",
    "gn:population":0,
    "gn:timezone":"Asia/Makassar",
    "iso:country":"ID",
    "name:ind_x_preferred":[
        "Negerilama"
    ],
    "name:und_x_variant":[
        "Lipoelagidoeno",
        "Naurilama",
        "Lipoelagidoen",
        "Negerilama"
    ],
    "wof:name":"Negerilama",
    "wof:placetype":"locality"
},
  "geometry": {"coordinates":[121.47029999999999,1.1217],"type":"Point"}
}