{
  "type": "Feature",
  "properties": {
    "gn:admin1_code":"30",
    "gn:asciiname":"Leungo",
    "gn:country_code":"ID",
    "gn:dem":768,
    "gn:feature_class":"P",
    "gn:feature_code":"PPL",
    "gn:name":"Leungo",
    "gn:population":0,
    "gn:timezone":"Asia/Jakarta",
    "iso:country":"ID",
    "name:ind_x_preferred":[
        "Leungo"
    ],
    "wof:name":"Leungo",
    "wof:placetype":"locality"
},
  "geometry": {"coordinates":[107.7817,-7.0687],"type":"Point"}
}