{
  "type": "Feature",
  "properties": {
    "gn:admin1_code":"30",
    "gn:asciiname":"Sungailabu",
    "gn:country_code":"ID",
    "gn:dem":3,
    "gn:feature_class":"P",
    "gn:feature_code":"PPL",
    "gn:name":"Sungailabu",
    "gn:population":0,
    "gn:timezone":"Asia/Jakarta",
    "iso:country":"ID",
    "name:ind_x_preferred":[
        "Sungailabu"
    ],
    "wof:name":"Sungailabu",
    "wof:placetype":"locality"
},
  "geometry": {"coordinates":[107.06583000000001,-6.03889],"type":"Point"}
}