{
  "type": "Feature",
  "properties": {
    "gn:admin1_code":"08",
    "gn:asciiname":"Morleban",
    "gn:country_code":"ID",
    "gn:dem":131,
    "gn:feature_class":"P",
    "gn:feature_code":"PPL",
    "gn:name":"Morleban",
    "gn:population":0,
    "gn:timezone":"Asia/Jakarta",
    "iso:country":"ID",
    "name:ind_x_preferred":[
        "Morleban"
    ],
    "wof:name":"Morleban",
    "wof:placetype":"locality"
},
  "geometry": {"coordinates":[112.90737,-7.11595],"type":"Point"}
}