{
  "type": "Feature",
  "properties": {
    "gn:admin1_code":"30.0",
    "gn:asciiname":"Cariu",
    "gn:country_code":"ID",
    "gn:dem":400,
    "gn:feature_class":"P",
    "gn:feature_code":"PPL",
    "gn:name":"Cariu",
    "gn:population":0,
    "gn:timezone":"Asia/Jakarta",
    "iso:country":"ID",
    "name:ind_x_preferred":[
        "Cariu"
    ],
    "name:und_x_variant":[
        "Tjitjatiu",
        "Cicatiu",
        "Tjitjarioe"
    ],
    "wof:name":"Cariu",
    "wof:placetype":"locality"
},
  "geometry": {"coordinates":[107.47026,-7.41136],"type":"Point"}
}