{
  "type": "Feature",
  "properties": {
    "gn:admin1_code":"7",
    "gn:asciiname":"Dipojaya",
    "gn:country_code":"ID",
    "gn:dem":1583,
    "gn:feature_class":"P",
    "gn:feature_code":"PPL",
    "gn:name":"Dipojaya",
    "gn:population":0,
    "gn:timezone":"Asia/Jakarta",
    "iso:country":"ID",
    "name:ind_x_preferred":[
        "Dipojaya"
    ],
    "wof:name":"Dipojaya",
    "wof:placetype":"locality"
},
  "geometry": {"coordinates":[109.26027999999999,-7.22167],"type":"Point"}
}