{
  "type": "Feature",
  "properties": {
    "gn:admin1_code":"30",
    "gn:asciiname":"Korehkotok",
    "gn:country_code":"ID",
    "gn:dem":681,
    "gn:feature_class":"P",
    "gn:feature_code":"PPL",
    "gn:name":"Korehkotok",
    "gn:population":0,
    "gn:timezone":"Asia/Jakarta",
    "iso:country":"ID",
    "name:ind_x_preferred":[
        "Korehkotok"
    ],
    "wof:name":"Korehkotok",
    "wof:placetype":"locality"
},
  "geometry": {"coordinates":[107.52806,-6.93944],"type":"Point"}
}