{
  "type": "Feature",
  "properties": {
    "gn:admin1_code":"7.0",
    "gn:asciiname":"Podo",
    "gn:country_code":"ID",
    "gn:dem":582,
    "gn:feature_class":"P",
    "gn:feature_code":"PPL",
    "gn:name":"Podo",
    "gn:population":0,
    "gn:timezone":"Asia/Jakarta",
    "iso:country":"ID",
    "wof:name":"Podo",
    "wof:placetype":"locality"
},
  "geometry": {"coordinates":[110.31194000000001,-7.51278],"type":"Point"}
}