{
  "type": "Feature",
  "properties": {
    "gn:admin1_code":"26.0",
    "gn:asciiname":"Banuaraja",
    "gn:country_code":"ID",
    "gn:dem":1192,
    "gn:feature_class":"P",
    "gn:feature_code":"PPL",
    "gn:name":"Banuaraja",
    "gn:population":0,
    "gn:timezone":"Asia/Jakarta",
    "iso:country":"ID",
    "name:ind_x_preferred":[
        "Banuaraja"
    ],
    "wof:name":"Banuaraja",
    "wof:placetype":"locality"
},
  "geometry": {"coordinates":[98.95480000000001,2.5093],"type":"Point"}
}