{
  "type": "Feature",
  "properties": {
    "gn:admin1_code":"17.0",
    "gn:asciiname":"Melah",
    "gn:country_code":"ID",
    "gn:dem":59,
    "gn:feature_class":"P",
    "gn:feature_code":"PPL",
    "gn:name":"Melah",
    "gn:population":0,
    "gn:timezone":"Asia/Makassar",
    "iso:country":"ID",
    "name:ind_x_preferred":[
        "Melah"
    ],
    "wof:name":"Melah",
    "wof:placetype":"locality"
},
  "geometry": {"coordinates":[116.048,-8.8205],"type":"Point"}
}