{
  "type": "Feature",
  "properties": {
    "gn:admin1_code":"38",
    "gn:asciiname":"Rappoalla",
    "gn:country_code":"ID",
    "gn:dem":902,
    "gn:feature_class":"P",
    "gn:feature_code":"PPL",
    "gn:name":"Rappoalla",
    "gn:population":0,
    "gn:timezone":"Asia/Makassar",
    "iso:country":"ID",
    "name:ind_x_preferred":[
        "Rappoalla"
    ],
    "wof:name":"Rappoalla",
    "wof:placetype":"locality"
},
  "geometry": {"coordinates":[119.8441,-5.4052],"type":"Point"}
}