{
  "type": "Feature",
  "properties": {
    "gn:admin1_code":"4",
    "gn:asciiname":"Ancol Barat",
    "gn:country_code":"ID",
    "gn:dem":2,
    "gn:feature_class":"P",
    "gn:feature_code":"PPL",
    "gn:name":"Ancol Barat",
    "gn:population":0,
    "gn:timezone":"Asia/Jakarta",
    "iso:country":"ID",
    "name:ind_x_preferred":[
        "Ancol Barat"
    ],
    "wof:name":"Ancol Barat",
    "wof:placetype":"locality"
},
  "geometry": {"coordinates":[106.8185,-6.1205],"type":"Point"}
}