{
  "type": "Feature",
  "properties": {
    "gn:admin1_code":"8.0",
    "gn:asciiname":"Triwung",
    "gn:country_code":"ID",
    "gn:dem":16,
    "gn:feature_class":"P",
    "gn:feature_code":"PPL",
    "gn:name":"Triwung",
    "gn:population":0,
    "gn:timezone":"Asia/Jakarta",
    "iso:country":"ID",
    "name:ind_x_preferred":[
        "Triwung"
    ],
    "wof:name":"Triwung",
    "wof:placetype":"locality"
},
  "geometry": {"coordinates":[113.37130000000001,-7.7832],"type":"Point"}
}