{
  "type": "Feature",
  "properties": {
    "gn:admin1_code":"7",
    "gn:asciiname":"Tenggar",
    "gn:country_code":"ID",
    "gn:dem":185,
    "gn:feature_class":"P",
    "gn:feature_code":"PPL",
    "gn:name":"Tenggar",
    "gn:population":0,
    "gn:timezone":"Asia/Jakarta",
    "iso:country":"ID",
    "name:ind_x_preferred":[
        "Tenggar"
    ],
    "wof:name":"Tenggar",
    "wof:placetype":"locality"
},
  "geometry": {"coordinates":[111.04167,-7.95889],"type":"Point"}
}