{
  "type": "Feature",
  "properties": {
    "gn:admin1_code":"17.0",
    "gn:asciiname":"Lapasari",
    "gn:country_code":"ID",
    "gn:dem":27,
    "gn:feature_class":"P",
    "gn:feature_code":"PPL",
    "gn:name":"Lapasari",
    "gn:population":0,
    "gn:timezone":"Asia/Makassar",
    "iso:country":"ID",
    "name:guj_x_preferred":[
        "\u0ab2\u0abe\u0aaa\u0abe\u0ab8\u0ab0\u0ac0"
    ],
    "name:hin_x_preferred":[
        "\u0932\u093e\u092a\u093e\u0938\u0930\u0940"
    ],
    "name:ind_x_preferred":[
        "Lapasari"
    ],
    "name:urd_x_preferred":[
        "\u0644\u0627\u067e\u0627\u0633\u0627\u0631\u06cc"
    ],
    "wof:lang_x_official":[
        "ind"
    ],
    "wof:lang_x_spoken":[
        "ind",
        "eng"
    ],
    "wof:name":"Lapasari",
    "wof:placetype":"locality"
},
  "geometry": {"coordinates":[118.6075,-8.509],"type":"Point"}
}