{
  "type": "Feature",
  "properties": {
    "gn:admin1_code":"17.0",
    "gn:asciiname":"Lapasari",
    "gn:country_code":"ID",
    "gn:dem":27,
    "gn:feature_class":"P",
    "gn:feature_code":"PPL",
    "gn:name":"Lapasari",
    "gn:population":0,
    "gn:timezone":"Asia/Makassar",
    "iso:country":"ID",
    "name:ind_x_preferred":[
        "Lapasari"
    ],
    "wof:name":"Lapasari",
    "wof:placetype":"locality"
},
  "geometry": {"coordinates":[118.6075,-8.509],"type":"Point"}
}