{
  "type": "Feature",
  "properties": {
    "gn:admin1_code":"24",
    "gn:asciiname":"Batukalang",
    "gn:country_code":"ID",
    "gn:dem":134,
    "gn:feature_class":"P",
    "gn:feature_code":"PPL",
    "gn:name":"Batukalang",
    "gn:population":0,
    "gn:timezone":"Asia/Jakarta",
    "iso:country":"ID",
    "name:ind_x_preferred":[
        "Batukalang"
    ],
    "wof:name":"Batukalang",
    "wof:placetype":"locality"
},
  "geometry": {"coordinates":[100.23795,-0.52521],"type":"Point"}
}