{
  "type": "Feature",
  "properties": {
    "gn:admin1_code":"26",
    "gn:asciiname":"Gunung",
    "gn:country_code":"ID",
    "gn:dem":182,
    "gn:feature_class":"P",
    "gn:feature_code":"PPL",
    "gn:name":"Gunung",
    "gn:population":0,
    "gn:timezone":"Asia/Jakarta",
    "iso:country":"ID",
    "name:ind_x_preferred":[
        "Gunung"
    ],
    "wof:name":"Gunung",
    "wof:placetype":"locality"
},
  "geometry": {"coordinates":[98.96299999999999,3.1555],"type":"Point"}
}