{
  "type": "Feature",
  "properties": {
    "gn:admin1_code":"8.0",
    "gn:asciiname":"Wonorejo",
    "gn:country_code":"ID",
    "gn:dem":20,
    "gn:feature_class":"P",
    "gn:feature_code":"PPL",
    "gn:name":"Wonorejo",
    "gn:population":0,
    "gn:timezone":"Asia/Jakarta",
    "iso:country":"ID",
    "name:ind_x_preferred":[
        "Wonorejo"
    ],
    "name:und_x_variant":[
        "Wonoredjo"
    ],
    "wof:name":"Wonorejo",
    "wof:placetype":"locality"
},
  "geometry": {"coordinates":[113.3875,-8.2843],"type":"Point"}
}