{
  "type": "Feature",
  "properties": {
    "gn:admin1_code":"30.0",
    "gn:asciiname":"Batusumbul",
    "gn:country_code":"ID",
    "gn:dem":296,
    "gn:feature_class":"P",
    "gn:feature_code":"PPL",
    "gn:name":"Batusumbul",
    "gn:population":0,
    "gn:timezone":"Asia/Jakarta",
    "iso:country":"ID",
    "name:ind_x_preferred":[
        "Batusumbul"
    ],
    "wof:name":"Batusumbul",
    "wof:placetype":"locality"
},
  "geometry": {"coordinates":[106.6874,-7.2704],"type":"Point"}
}