{
  "type": "Feature",
  "properties": {
    "gn:admin1_code":"30",
    "gn:asciiname":"Bayureja",
    "gn:country_code":"ID",
    "gn:dem":271,
    "gn:feature_class":"P",
    "gn:feature_code":"PPL",
    "gn:name":"Bayureja",
    "gn:population":0,
    "gn:timezone":"Asia/Jakarta",
    "iso:country":"ID",
    "name:ind_x_preferred":[
        "Bayureja"
    ],
    "wof:name":"Bayureja",
    "wof:placetype":"locality"
},
  "geometry": {"coordinates":[108.30472,-6.82],"type":"Point"}
}