{
  "type": "Feature",
  "properties": {
    "gn:admin1_code":"8.0",
    "gn:asciiname":"Tegalrejo",
    "gn:country_code":"ID",
    "gn:dem":38,
    "gn:feature_class":"P",
    "gn:feature_code":"PPL",
    "gn:name":"Tegalrejo",
    "gn:population":0,
    "gn:timezone":"Asia/Jakarta",
    "iso:country":"ID",
    "name:ind_x_preferred":[
        "Tegalrejo"
    ],
    "wof:name":"Tegalrejo",
    "wof:placetype":"locality"
},
  "geometry": {"coordinates":[112.1751,-7.2041],"type":"Point"}
}