{
  "type": "Feature",
  "properties": {
    "gn:admin1_code":"26",
    "gn:asciiname":"Singuak",
    "gn:country_code":"ID",
    "gn:dem":1165,
    "gn:feature_class":"P",
    "gn:feature_code":"PPL",
    "gn:name":"Singuak",
    "gn:population":0,
    "gn:timezone":"Asia/Jakarta",
    "iso:country":"ID",
    "name:ind_x_preferred":[
        "Singuak"
    ],
    "wof:name":"Singuak",
    "wof:placetype":"locality"
},
  "geometry": {"coordinates":[99.0335,2.1316],"type":"Point"}
}