{
  "type": "Feature",
  "properties": {
    "gn:admin1_code":"7",
    "gn:asciiname":"Gotri",
    "gn:country_code":"ID",
    "gn:dem":18,
    "gn:feature_class":"P",
    "gn:feature_code":"PPL",
    "gn:name":"Gotri",
    "gn:population":0,
    "gn:timezone":"Asia/Jakarta",
    "iso:country":"ID",
    "name:ceb_x_preferred":[
        "Gotree"
    ],
    "name:fra_x_preferred":[
        "Gotree"
    ],
    "name:ind_x_preferred":[
        "Gotri"
    ],
    "name:mai_x_preferred":[
        "\u0917\u094b\u0924\u094d\u0930\u0940"
    ],
    "name:msa_x_preferred":[
        "Gotree"
    ],
    "name:nep_x_preferred":[
        "\u0917\u094b\u0924\u094d\u0930\u0940"
    ],
    "name:new_x_preferred":[
        "\u0917\u094b\u0924\u094d\u0930\u0940"
    ],
    "name:pol_x_preferred":[
        "Gotree"
    ],
    "wof:lang_x_official":[
        "ind"
    ],
    "wof:lang_x_spoken":[
        "ind",
        "eng"
    ],
    "wof:name":"Gotri",
    "wof:placetype":"locality"
},
  "geometry": {"coordinates":[110.7261,-6.7319],"type":"Point"}
}