{
  "type": "Feature",
  "properties": {
    "gn:admin1_code":"30.0",
    "gn:asciiname":"Rancabadak",
    "gn:country_code":"ID",
    "gn:dem":20,
    "gn:feature_class":"P",
    "gn:feature_code":"PPL",
    "gn:name":"Rancabadak",
    "gn:population":0,
    "gn:timezone":"Asia/Jakarta",
    "iso:country":"ID",
    "name:ind_x_preferred":[
        "Rancabadak"
    ],
    "wof:name":"Rancabadak",
    "wof:placetype":"locality"
},
  "geometry": {"coordinates":[108.17829999999999,-7.7766],"type":"Point"}
}