{
  "type": "Feature",
  "properties": {
    "gn:admin1_code":"30.0",
    "gn:asciiname":"Sangiang",
    "gn:country_code":"ID",
    "gn:dem":666,
    "gn:feature_class":"P",
    "gn:feature_code":"PPL",
    "gn:name":"Sangiang",
    "gn:population":0,
    "gn:timezone":"Asia/Jakarta",
    "iso:country":"ID",
    "name:ind_x_preferred":[
        "Sangiang"
    ],
    "wof:name":"Sangiang",
    "wof:placetype":"locality"
},
  "geometry": {"coordinates":[107.92400000000001,-7.468],"type":"Point"}
}