{
  "type": "Feature",
  "properties": {
    "gn:admin1_code":"29.0",
    "gn:asciiname":"Lola",
    "gn:country_code":"ID",
    "gn:dem":6,
    "gn:feature_class":"P",
    "gn:feature_code":"PPL",
    "gn:name":"Lola",
    "gn:population":0,
    "gn:timezone":"Asia/Jayapura",
    "iso:country":"ID",
    "name:bre_x_preferred":[
        "Lola"
    ],
    "name:ceb_x_preferred":[
        "Lola"
    ],
    "name:deu_x_preferred":[
        "Lola"
    ],
    "name:est_x_preferred":[
        "Lola"
    ],
    "name:fas_x_preferred":[
        "\u0644\u0648\u0644\u0627"
    ],
    "name:fin_x_preferred":[
        "Lola"
    ],
    "name:fra_x_preferred":[
        "Lola"
    ],
    "name:heb_x_preferred":[
        "\u05dc\u05d5\u05dc\u05d4"
    ],
    "name:hun_x_preferred":[
        "Lola"
    ],
    "name:ita_x_preferred":[
        "Lola"
    ],
    "name:nld_x_preferred":[
        "Lola"
    ],
    "name:pol_x_preferred":[
        "Lola"
    ],
    "name:por_x_preferred":[
        "Lola"
    ],
    "name:rus_x_preferred":[
        "\u041b\u043e\u043b\u0430"
    ],
    "name:spa_x_preferred":[
        "Lola"
    ],
    "name:swe_x_preferred":[
        "Lola"
    ],
    "name:tur_x_preferred":[
        "Lola"
    ],
    "name:uzb_x_preferred":[
        "Lola"
    ],
    "wof:lang_x_official":[
        "ind"
    ],
    "wof:lang_x_spoken":[
        "ind",
        "eng"
    ],
    "wof:name":"Lola",
    "wof:placetype":"locality"
},
  "geometry": {"coordinates":[127.58333,0.4308],"type":"Point"}
}