{
  "type": "Feature",
  "properties": {
    "gn:admin1_code":"8",
    "gn:asciiname":"Singgahan",
    "gn:country_code":"ID",
    "gn:dem":90,
    "gn:feature_class":"P",
    "gn:feature_code":"PPL",
    "gn:name":"Singgahan",
    "gn:population":0,
    "gn:timezone":"Asia/Jakarta",
    "iso:country":"ID",
    "name:ind_x_preferred":[
        "Singgahan"
    ],
    "wof:name":"Singgahan",
    "wof:placetype":"locality"
},
  "geometry": {"coordinates":[111.50620000000001,-7.7204],"type":"Point"}
}