{
  "type": "Feature",
  "properties": {
    "gn:admin1_code":"30",
    "gn:asciiname":"Lagokbitung",
    "gn:country_code":"ID",
    "gn:dem":962,
    "gn:feature_class":"P",
    "gn:feature_code":"PPL",
    "gn:name":"Lagokbitung",
    "gn:population":0,
    "gn:timezone":"Asia/Jakarta",
    "iso:country":"ID",
    "name:ind_x_preferred":[
        "Lagokbitung"
    ],
    "wof:name":"Lagokbitung",
    "wof:placetype":"locality"
},
  "geometry": {"coordinates":[107.12222,-6.99444],"type":"Point"}
}