{
  "type": "Feature",
  "properties": {
    "gn:admin1_code":"17.0",
    "gn:admin2_code":"Sumbawa (undefined)",
    "gn:admin3_code":"8457466.0",
    "gn:asciiname":"Lunyuk",
    "gn:cc2":"ID",
    "gn:country_code":"ID",
    "gn:dem":14,
    "gn:feature_class":"P",
    "gn:feature_code":"PPL",
    "gn:name":"Lunyuk",
    "gn:population":0,
    "gn:timezone":"Asia/Makassar",
    "iso:country":"ID",
    "name:eng_x_preferred":[
        "Lunyuk"
    ],
    "name:und_x_variant":[
        "Loenjoek",
        "Lunjuk",
        "Lunyuk"
    ],
    "wof:lang_x_official":[
        "ind"
    ],
    "wof:lang_x_spoken":[
        "ind",
        "eng"
    ],
    "wof:name":"Lunyuk",
    "wof:placetype":"locality"
},
  "geometry": {"coordinates":[117.20884,-8.99292],"type":"Point"}
}