{
  "type": "Feature",
  "properties": {
    "gn:admin1_code":"8.0",
    "gn:asciiname":"Jati",
    "gn:country_code":"ID",
    "gn:dem":388,
    "gn:feature_class":"P",
    "gn:feature_code":"PPL",
    "gn:name":"Jati",
    "gn:population":0,
    "gn:timezone":"Asia/Jakarta",
    "iso:country":"ID",
    "name:ind_x_preferred":[
        "Jati"
    ],
    "wof:name":"Jati",
    "wof:placetype":"locality"
},
  "geometry": {"coordinates":[111.11417,-8.09889],"type":"Point"}
}