{
  "type": "Feature",
  "properties": {
    "gn:admin1_code":"18",
    "gn:asciiname":"Kalembuguro",
    "gn:country_code":"ID",
    "gn:dem":63,
    "gn:feature_class":"P",
    "gn:feature_code":"PPL",
    "gn:name":"Kalembuguro",
    "gn:population":0,
    "gn:timezone":"Asia/Makassar",
    "iso:country":"ID",
    "name:ind_x_preferred":[
        "Kalembuguro"
    ],
    "wof:name":"Kalembuguro",
    "wof:placetype":"locality"
},
  "geometry": {"coordinates":[119.17101,-9.4188],"type":"Point"}
}