{
  "type": "Feature",
  "properties": {
    "gn:admin1_code":"41",
    "gn:asciiname":"Malawa",
    "gn:country_code":"ID",
    "gn:dem":111,
    "gn:feature_class":"P",
    "gn:feature_code":"PPL",
    "gn:name":"Malawa",
    "gn:population":0,
    "gn:timezone":"Asia/Makassar",
    "iso:country":"ID",
    "name:ceb_x_preferred":[
        "Malawa"
    ],
    "name:deu_x_preferred":[
        "Malawa"
    ],
    "name:ind_x_preferred":[
        "Malawa"
    ],
    "name:pol_x_preferred":[
        "Malawa"
    ],
    "name:swe_x_preferred":[
        "Malawa"
    ],
    "name:ukr_x_preferred":[
        "\u041c\u0430\u043b\u044f\u0432\u0430"
    ],
    "wof:name":"Malawa",
    "wof:placetype":"locality"
},
  "geometry": {"coordinates":[118.7979,-2.6649],"type":"Point"}
}