{
  "type": "Feature",
  "properties": {
    "gn:admin1_code":"15.0",
    "gn:asciiname":"Kuningan",
    "gn:country_code":"ID",
    "gn:dem":17,
    "gn:feature_class":"P",
    "gn:feature_code":"PPL",
    "gn:name":"Kuningan",
    "gn:population":0,
    "gn:timezone":"Asia/Jakarta",
    "iso:country":"ID",
    "name:ceb_x_preferred":[
        "Kuningan"
    ],
    "name:ind_x_preferred":[
        "Kuningan"
    ],
    "name:jav_x_preferred":[
        "Kuningan"
    ],
    "name:khm_x_preferred":[
        "\u1782\u17bb\u1793\u17b8\u1784\u17a2\u17b6\u1793"
    ],
    "name:mlg_x_preferred":[
        "Kuningan"
    ],
    "name:sun_x_preferred":[
        "Kuningan"
    ],
    "wof:lang_x_official":[
        "ind"
    ],
    "wof:lang_x_spoken":[
        "ind",
        "eng"
    ],
    "wof:name":"Kuningan",
    "wof:placetype":"locality"
},
  "geometry": {"coordinates":[104.20251,-5.44878],"type":"Point"}
}