{
  "type": "Feature",
  "properties": {
    "gn:admin1_code":"0.0",
    "gn:asciiname":"Cibacang",
    "gn:cc2":"ID",
    "gn:country_code":"ID",
    "gn:dem":683,
    "gn:feature_class":"P",
    "gn:feature_code":"PPL",
    "gn:name":"Cibacang",
    "gn:population":0,
    "gn:timezone":"Asia/Jakarta",
    "iso:country":"ID",
    "name:und_x_variant":[
        "Tjibatjang",
        "Cibacang"
    ],
    "wof:name":"Cibacang",
    "wof:placetype":"locality"
},
  "geometry": {"coordinates":[107.16667,-7.15],"type":"Point"}
}