{
  "type": "Feature",
  "properties": {
    "gn:admin1_code":"38",
    "gn:asciiname":"Borongunti",
    "gn:country_code":"ID",
    "gn:dem":5,
    "gn:feature_class":"P",
    "gn:feature_code":"PPL",
    "gn:name":"Borongunti",
    "gn:population":0,
    "gn:timezone":"Asia/Makassar",
    "iso:country":"ID",
    "name:ind_x_preferred":[
        "Borongunti"
    ],
    "wof:name":"Borongunti",
    "wof:placetype":"locality"
},
  "geometry": {"coordinates":[119.40779999999999,-5.2153],"type":"Point"}
}