{
  "type": "Feature",
  "properties": {
    "gn:admin1_code":"38",
    "gn:asciiname":"Jarangnika",
    "gn:country_code":"ID",
    "gn:dem":7,
    "gn:feature_class":"P",
    "gn:feature_code":"PPL",
    "gn:name":"Jarangnika",
    "gn:population":0,
    "gn:timezone":"Asia/Makassar",
    "iso:country":"ID",
    "name:ind_x_preferred":[
        "Jarangnika"
    ],
    "wof:name":"Jarangnika",
    "wof:placetype":"locality"
},
  "geometry": {"coordinates":[119.4293,-5.4775],"type":"Point"}
}