{
  "type": "Feature",
  "properties": {
    "gn:admin1_code":"8",
    "gn:asciiname":"Pager",
    "gn:country_code":"ID",
    "gn:dem":574,
    "gn:feature_class":"P",
    "gn:feature_code":"PPL",
    "gn:name":"Pager",
    "gn:population":0,
    "gn:timezone":"Asia/Jakarta",
    "iso:country":"ID",
    "name:ind_x_preferred":[
        "Pager"
    ],
    "wof:name":"Pager",
    "wof:placetype":"locality"
},
  "geometry": {"coordinates":[111.34305999999999,-8.04],"type":"Point"}
}