{
  "type": "Feature",
  "properties": {
    "gn:admin1_code":"30.0",
    "gn:asciiname":"Jatirejo Dua",
    "gn:country_code":"ID",
    "gn:dem":436,
    "gn:feature_class":"P",
    "gn:feature_code":"PPL",
    "gn:name":"Jatirejo Dua",
    "gn:population":0,
    "gn:timezone":"Asia/Jakarta",
    "iso:country":"ID",
    "name:ind_x_preferred":[
        "Jatirejo Dua"
    ],
    "wof:name":"Jatirejo Dua",
    "wof:placetype":"locality"
},
  "geometry": {"coordinates":[113.94070000000001,-7.94],"type":"Point"}
}