{
  "type": "Feature",
  "properties": {
    "gn:admin1_code":"30.0",
    "gn:asciiname":"Bojongkoneng",
    "gn:country_code":"ID",
    "gn:dem":192,
    "gn:feature_class":"P",
    "gn:feature_code":"PPL",
    "gn:name":"Bojongkoneng",
    "gn:population":0,
    "gn:timezone":"Asia/Jakarta",
    "iso:country":"ID",
    "name:ind_x_preferred":[
        "Bojongkoneng"
    ],
    "wof:name":"Bojongkoneng",
    "wof:placetype":"locality"
},
  "geometry": {"coordinates":[107.03879999999999,-7.2771],"type":"Point"}
}