{
  "type": "Feature",
  "properties": {
    "gn:admin1_code":"15.0",
    "gn:asciiname":"Waikunang",
    "gn:country_code":"ID",
    "gn:dem":37,
    "gn:feature_class":"P",
    "gn:feature_code":"PPL",
    "gn:name":"Waikunang",
    "gn:population":0,
    "gn:timezone":"Asia/Jakarta",
    "iso:country":"ID",
    "name:ind_x_preferred":[
        "Waikunang"
    ],
    "wof:name":"Waikunang",
    "wof:placetype":"locality"
},
  "geometry": {"coordinates":[104.81622,-4.89151],"type":"Point"}
}