{
  "type": "Feature",
  "properties": {
    "gn:admin1_code":"2",
    "gn:asciiname":"Banjar Pempatan",
    "gn:country_code":"ID",
    "gn:dem":55,
    "gn:feature_class":"P",
    "gn:feature_code":"PPL",
    "gn:name":"Banjar Pempatan",
    "gn:population":0,
    "gn:timezone":"Asia/Makassar",
    "iso:country":"ID",
    "name:ind_x_preferred":[
        "Banjar Pempatan"
    ],
    "wof:name":"Banjar Pempatan",
    "wof:placetype":"locality"
},
  "geometry": {"coordinates":[115.14400000000001,-8.6176],"type":"Point"}
}