{
  "type": "Feature",
  "properties": {
    "gn:admin1_code":"8.0",
    "gn:asciiname":"Baloan",
    "gn:country_code":"ID",
    "gn:dem":307,
    "gn:feature_class":"P",
    "gn:feature_code":"PPL",
    "gn:name":"Baloan",
    "gn:population":0,
    "gn:timezone":"Asia/Jakarta",
    "iso:country":"ID",
    "name:ind_x_preferred":[
        "Baloan"
    ],
    "wof:name":"Baloan",
    "wof:placetype":"locality"
},
  "geometry": {"coordinates":[112.47239999999999,-8.1397],"type":"Point"}
}