{
  "type": "Feature",
  "properties": {
    "gn:admin1_code":"18",
    "gn:asciiname":"Waekara",
    "gn:country_code":"ID",
    "gn:dem":542,
    "gn:feature_class":"P",
    "gn:feature_code":"PPL",
    "gn:name":"Waekara",
    "gn:population":0,
    "gn:timezone":"Asia/Makassar",
    "iso:country":"ID",
    "name:ind_x_preferred":[
        "Waekara"
    ],
    "wof:name":"Waekara",
    "wof:placetype":"locality"
},
  "geometry": {"coordinates":[120.67619999999999,-8.437],"type":"Point"}
}