{
  "type": "Feature",
  "properties": {
    "gn:admin1_code":"8",
    "gn:asciiname":"Nurmanan",
    "gn:country_code":"ID",
    "gn:dem":103,
    "gn:feature_class":"P",
    "gn:feature_code":"PPL",
    "gn:name":"Nurmanan",
    "gn:population":0,
    "gn:timezone":"Asia/Jakarta",
    "iso:country":"ID",
    "name:ind_x_preferred":[
        "Nurmanan"
    ],
    "wof:name":"Nurmanan",
    "wof:placetype":"locality"
},
  "geometry": {"coordinates":[111.4646,-7.8605],"type":"Point"}
}