{
  "type": "Feature",
  "properties": {
    "gn:admin1_code":"33",
    "gn:asciiname":"Cireundeu Wetan",
    "gn:country_code":"ID",
    "gn:dem":50,
    "gn:feature_class":"P",
    "gn:feature_code":"PPL",
    "gn:name":"Cireundeu Wetan",
    "gn:population":0,
    "gn:timezone":"Asia/Jakarta",
    "iso:country":"ID",
    "name:ind_x_preferred":[
        "Cireundeu Wetan"
    ],
    "wof:name":"Cireundeu Wetan",
    "wof:placetype":"locality"
},
  "geometry": {"coordinates":[106.2282,-6.2551],"type":"Point"}
}