{
  "type": "Feature",
  "properties": {
    "gn:admin1_code":"30",
    "gn:asciiname":"Ciririp",
    "gn:country_code":"ID",
    "gn:dem":671,
    "gn:feature_class":"P",
    "gn:feature_code":"PPL",
    "gn:name":"Ciririp",
    "gn:population":0,
    "gn:timezone":"Asia/Jakarta",
    "iso:country":"ID",
    "name:ind_x_preferred":[
        "Ciririp"
    ],
    "name:und_x_variant":[
        "Tjiririp"
    ],
    "wof:name":"Ciririp",
    "wof:placetype":"locality"
},
  "geometry": {"coordinates":[107.43889,-6.98556],"type":"Point"}
}