{
  "type": "Feature",
  "properties": {
    "gn:admin1_code":"7.0",
    "gn:asciiname":"Tempuran",
    "gn:country_code":"ID",
    "gn:dem":263,
    "gn:feature_class":"P",
    "gn:feature_code":"PPL",
    "gn:name":"Tempuran",
    "gn:population":0,
    "gn:timezone":"Asia/Jakarta",
    "iso:country":"ID",
    "wof:name":"Tempuran",
    "wof:placetype":"locality"
},
  "geometry": {"coordinates":[110.99444,-7.79306],"type":"Point"}
}