{
  "type": "Feature",
  "properties": {
    "gn:admin1_code":"30",
    "gn:asciiname":"Babakangunungwaru Kaler",
    "gn:country_code":"ID",
    "gn:dem":432,
    "gn:feature_class":"P",
    "gn:feature_code":"PPL",
    "gn:name":"Babakangunungwaru Kaler",
    "gn:population":0,
    "gn:timezone":"Asia/Jakarta",
    "iso:country":"ID",
    "name:ind_x_preferred":[
        "Babakangunungwaru Kaler"
    ],
    "wof:lang_x_official":[
        "ind"
    ],
    "wof:lang_x_spoken":[
        "ind",
        "eng"
    ],
    "wof:name":"Babakangunungwaru Kaler",
    "wof:placetype":"locality"
},
  "geometry": {"coordinates":[106.59721999999999,-6.60306],"type":"Point"}
}