{
  "type": "Feature",
  "properties": {
    "gn:admin1_code":"2.0",
    "gn:asciiname":"Penyancangan",
    "gn:country_code":"ID",
    "gn:dem":427,
    "gn:feature_class":"P",
    "gn:feature_code":"PPL",
    "gn:name":"Penyancangan",
    "gn:population":0,
    "gn:timezone":"Asia/Makassar",
    "iso:country":"ID",
    "name:ind_x_preferred":[
        "Penyancangan"
    ],
    "wof:name":"Penyancangan",
    "wof:placetype":"locality"
},
  "geometry": {"coordinates":[115.56959999999999,-8.7698],"type":"Point"}
}