{
  "type": "Feature",
  "properties": {
    "gn:admin1_code":"30",
    "gn:asciiname":"Paduraksa",
    "gn:country_code":"ID",
    "gn:dem":454,
    "gn:feature_class":"P",
    "gn:feature_code":"PPL",
    "gn:name":"Paduraksa",
    "gn:population":0,
    "gn:timezone":"Asia/Jakarta",
    "iso:country":"ID",
    "name:ind_x_preferred":[
        "Paduraksa"
    ],
    "name:jav_x_preferred":[
        "Paduraksa"
    ],
    "name:mal_x_preferred":[
        "\u0d2a\u0d21\u0d41\u0d30\u0d15\u0d4d\u0d38"
    ],
    "name:por_x_preferred":[
        "Paduraksa"
    ],
    "wof:lang_x_official":[
        "ind"
    ],
    "wof:lang_x_spoken":[
        "ind",
        "eng"
    ],
    "wof:name":"Paduraksa",
    "wof:placetype":"locality"
},
  "geometry": {"coordinates":[108.51519999999999,-6.8923],"type":"Point"}
}