{
  "type": "Feature",
  "properties": {
    "gn:admin1_code":"34",
    "gn:asciiname":"Karangpelem",
    "gn:country_code":"ID",
    "gn:dem":39,
    "gn:feature_class":"P",
    "gn:feature_code":"PPL",
    "gn:name":"Karangpelem",
    "gn:population":0,
    "gn:timezone":"Asia/Makassar",
    "iso:country":"ID",
    "name:ind_x_preferred":[
        "Karangpelem"
    ],
    "wof:name":"Karangpelem",
    "wof:placetype":"locality"
},
  "geometry": {"coordinates":[122.6193,0.6546],"type":"Point"}
}