{
  "type": "Feature",
  "properties": {
    "gn:admin1_code":"10.0",
    "gn:asciiname":"Klangkapan Satu",
    "gn:country_code":"ID",
    "gn:dem":143,
    "gn:feature_class":"P",
    "gn:feature_code":"PPL",
    "gn:name":"Klangkapan Satu",
    "gn:population":0,
    "gn:timezone":"Asia/Jakarta",
    "iso:country":"ID",
    "wof:name":"Klangkapan Satu",
    "wof:placetype":"locality"
},
  "geometry": {"coordinates":[110.29694000000001,-7.74556],"type":"Point"}
}