{
  "type": "Feature",
  "properties": {
    "gn:admin1_code":"11",
    "gn:asciiname":"Sungai Tembaga",
    "gn:country_code":"ID",
    "gn:dem":17,
    "gn:feature_class":"P",
    "gn:feature_code":"PPL",
    "gn:name":"Sungai Tembaga",
    "gn:population":0,
    "gn:timezone":"Asia/Pontianak",
    "iso:country":"ID",
    "name:ind_x_preferred":[
        "Sungai Tembaga"
    ],
    "wof:name":"Sungai Tembaga",
    "wof:placetype":"locality"
},
  "geometry": {"coordinates":[109.05297,0.63874],"type":"Point"}
}