{
  "type": "Feature",
  "properties": {
    "gn:admin1_code":"7.0",
    "gn:asciiname":"Gondangsari",
    "gn:country_code":"ID",
    "gn:dem":397,
    "gn:feature_class":"P",
    "gn:feature_code":"PPL",
    "gn:name":"Gondangsari",
    "gn:population":0,
    "gn:timezone":"Asia/Jakarta",
    "iso:country":"ID",
    "name:ind_x_preferred":[
        "Gondangsari"
    ],
    "wof:name":"Gondangsari",
    "wof:placetype":"locality"
},
  "geometry": {"coordinates":[109.74083,-7.54361],"type":"Point"}
}