{
  "type": "Feature",
  "properties": {
    "gn:admin1_code":"38",
    "gn:asciiname":"Jambua",
    "gn:country_code":"ID",
    "gn:dem":72,
    "gn:feature_class":"P",
    "gn:feature_code":"PPL",
    "gn:name":"Jambua",
    "gn:population":0,
    "gn:timezone":"Asia/Makassar",
    "iso:country":"ID",
    "name:ind_x_preferred":[
        "Jambua"
    ],
    "wof:name":"Jambua",
    "wof:placetype":"locality"
},
  "geometry": {"coordinates":[119.57389999999999,-5.332],"type":"Point"}
}