{
  "type": "Feature",
  "properties": {
    "gn:admin1_code":"10",
    "gn:asciiname":"Ngangrangan Lor",
    "gn:country_code":"ID",
    "gn:dem":14,
    "gn:feature_class":"P",
    "gn:feature_code":"PPL",
    "gn:name":"Ngangrangan Lor",
    "gn:population":0,
    "gn:timezone":"Asia/Jakarta",
    "iso:country":"ID",
    "wof:name":"Ngangrangan Lor",
    "wof:placetype":"locality"
},
  "geometry": {"coordinates":[110.13916999999999,-7.90972],"type":"Point"}
}