{
  "type": "Feature",
  "properties": {
    "gn:admin1_code":"8.0",
    "gn:asciiname":"Jublang",
    "gn:country_code":"ID",
    "gn:dem":50,
    "gn:feature_class":"P",
    "gn:feature_code":"PPL",
    "gn:name":"Jublang",
    "gn:population":0,
    "gn:timezone":"Asia/Jakarta",
    "iso:country":"ID",
    "name:ind_x_preferred":[
        "Jublang"
    ],
    "wof:name":"Jublang",
    "wof:placetype":"locality"
},
  "geometry": {"coordinates":[112.34990000000001,-7.339],"type":"Point"}
}