{
  "type": "Feature",
  "properties": {
    "gn:admin1_code":"8.0",
    "gn:asciiname":"Kebonsari Kulon",
    "gn:country_code":"ID",
    "gn:dem":23,
    "gn:feature_class":"P",
    "gn:feature_code":"PPL",
    "gn:name":"Kebonsari Kulon",
    "gn:population":0,
    "gn:timezone":"Asia/Jakarta",
    "iso:country":"ID",
    "name:ind_x_preferred":[
        "Kebonsari Kulon"
    ],
    "wof:name":"Kebonsari Kulon",
    "wof:placetype":"locality"
},
  "geometry": {"coordinates":[113.4363,-8.2713],"type":"Point"}
}