{
  "type": "Feature",
  "properties": {
    "gn:admin1_code":"7",
    "gn:asciiname":"Kalibendo",
    "gn:country_code":"ID",
    "gn:dem":740,
    "gn:feature_class":"P",
    "gn:feature_code":"PPL",
    "gn:name":"Kalibendo",
    "gn:population":0,
    "gn:timezone":"Asia/Jakarta",
    "iso:country":"ID",
    "name:ind_x_preferred":[
        "Kalibendo"
    ],
    "wof:name":"Kalibendo",
    "wof:placetype":"locality"
},
  "geometry": {"coordinates":[109.87972000000001,-7.34611],"type":"Point"}
}