{
  "type": "Feature",
  "properties": {
    "gn:admin1_code":"1",
    "gn:asciiname":"Tibabruek",
    "gn:country_code":"ID",
    "gn:dem":26,
    "gn:feature_class":"P",
    "gn:feature_code":"PPL",
    "gn:name":"Tibabruek",
    "gn:population":0,
    "gn:timezone":"Asia/Jakarta",
    "iso:country":"ID",
    "name:ind_x_preferred":[
        "Tibabruek"
    ],
    "name:und_x_variant":[
        "Tiba"
    ],
    "wof:name":"Tibabruek",
    "wof:placetype":"locality"
},
  "geometry": {"coordinates":[95.96769999999999,5.2671],"type":"Point"}
}