{
  "type": "Feature",
  "properties": {
    "gn:admin1_code":"7",
    "gn:asciiname":"Balong",
    "gn:country_code":"ID",
    "gn:dem":526,
    "gn:feature_class":"P",
    "gn:feature_code":"PPL",
    "gn:name":"Balong",
    "gn:population":0,
    "gn:timezone":"Asia/Jakarta",
    "iso:country":"ID",
    "name:ind_x_preferred":[
        "Balong"
    ],
    "wof:name":"Balong",
    "wof:placetype":"locality"
},
  "geometry": {"coordinates":[109.81619999999999,-7.0693],"type":"Point"}
}