{
  "type": "Feature",
  "properties": {
    "gn:admin1_code":"18.0",
    "gn:asciiname":"Umikana",
    "gn:country_code":"ID",
    "gn:dem":669,
    "gn:feature_class":"P",
    "gn:feature_code":"PPL",
    "gn:name":"Umikana",
    "gn:population":0,
    "gn:timezone":"Asia/Makassar",
    "iso:country":"ID",
    "name:ind_x_preferred":[
        "Umikana"
    ],
    "wof:name":"Umikana",
    "wof:placetype":"locality"
},
  "geometry": {"coordinates":[124.3081,-9.9752],"type":"Point"}
}