{
  "type": "Feature",
  "properties": {
    "gn:admin1_code":"7",
    "gn:asciiname":"Karangsempu",
    "gn:country_code":"ID",
    "gn:dem":300,
    "gn:feature_class":"P",
    "gn:feature_code":"PPL",
    "gn:name":"Karangsempu",
    "gn:population":0,
    "gn:timezone":"Asia/Jakarta",
    "iso:country":"ID",
    "name:ind_x_preferred":[
        "Karangsempu"
    ],
    "wof:name":"Karangsempu",
    "wof:placetype":"locality"
},
  "geometry": {"coordinates":[109.49527999999999,-7.14083],"type":"Point"}
}