{
  "type": "Feature",
  "properties": {
    "gn:admin1_code":"30.0",
    "gn:asciiname":"Cimuncang",
    "gn:country_code":"ID",
    "gn:dem":187,
    "gn:feature_class":"P",
    "gn:feature_code":"PPL",
    "gn:name":"Cimuncang",
    "gn:population":0,
    "gn:timezone":"Asia/Jakarta",
    "iso:country":"ID",
    "name:ind_x_preferred":[
        "Cimuncang"
    ],
    "wof:name":"Cimuncang",
    "wof:placetype":"locality"
},
  "geometry": {"coordinates":[108.12260000000001,-7.4828],"type":"Point"}
}