{
  "type": "Feature",
  "properties": {
    "gn:admin1_code":"26",
    "gn:asciiname":"Pasar Tiga",
    "gn:country_code":"ID",
    "gn:dem":15,
    "gn:feature_class":"P",
    "gn:feature_code":"PPL",
    "gn:name":"Pasar Tiga",
    "gn:population":0,
    "gn:timezone":"Asia/Jakarta",
    "iso:country":"ID",
    "name:ind_x_preferred":[
        "Pasar Tiga"
    ],
    "name:und_x_variant":[
        "Pasar 3"
    ],
    "wof:name":"Pasar Tiga",
    "wof:placetype":"locality"
},
  "geometry": {"coordinates":[98.6031,3.6434],"type":"Point"}
}