{
  "type": "Feature",
  "properties": {
    "gn:admin1_code":"30",
    "gn:asciiname":"Pasirbenda",
    "gn:country_code":"ID",
    "gn:dem":446,
    "gn:feature_class":"P",
    "gn:feature_code":"PPL",
    "gn:name":"Pasirbenda",
    "gn:population":0,
    "gn:timezone":"Asia/Jakarta",
    "iso:country":"ID",
    "name:ind_x_preferred":[
        "Pasirbenda"
    ],
    "wof:name":"Pasirbenda",
    "wof:placetype":"locality"
},
  "geometry": {"coordinates":[106.67722000000001,-6.63667],"type":"Point"}
}