{
  "type": "Feature",
  "properties": {
    "gn:admin1_code":"30",
    "gn:asciiname":"Legoknangka",
    "gn:country_code":"ID",
    "gn:dem":655,
    "gn:feature_class":"P",
    "gn:feature_code":"PPL",
    "gn:name":"Legoknangka",
    "gn:population":0,
    "gn:timezone":"Asia/Jakarta",
    "iso:country":"ID",
    "name:ind_x_preferred":[
        "Legoknangka"
    ],
    "wof:name":"Legoknangka",
    "wof:placetype":"locality"
},
  "geometry": {"coordinates":[107.45917,-6.7975],"type":"Point"}
}