{
  "type": "Feature",
  "properties": {
    "gn:admin1_code":"07",
    "gn:asciiname":"Bulu",
    "gn:country_code":"ID",
    "gn:dem":100,
    "gn:feature_class":"P",
    "gn:feature_code":"PPL",
    "gn:name":"Bulu",
    "gn:population":0,
    "gn:timezone":"Asia/Jakarta",
    "iso:country":"ID",
    "wof:name":"Bulu",
    "wof:placetype":"locality"
},
  "geometry": {"coordinates":[110.71306,-7.78778],"type":"Point"}
}