{
  "type": "Feature",
  "properties": {
    "gn:admin1_code":"10",
    "gn:asciiname":"Gebang",
    "gn:country_code":"ID",
    "gn:dem":191,
    "gn:feature_class":"P",
    "gn:feature_code":"PPL",
    "gn:name":"Gebang",
    "gn:population":0,
    "gn:timezone":"Asia/Jakarta",
    "iso:country":"ID",
    "wof:name":"Gebang",
    "wof:placetype":"locality"
},
  "geometry": {"coordinates":[110.60972,-7.87417],"type":"Point"}
}