{
  "type": "Feature",
  "properties": {
    "gn:admin1_code":"7",
    "gn:asciiname":"Kalimargosari",
    "gn:country_code":"ID",
    "gn:dem":278,
    "gn:feature_class":"P",
    "gn:feature_code":"PPL",
    "gn:name":"Kalimargosari",
    "gn:population":0,
    "gn:timezone":"Asia/Jakarta",
    "iso:country":"ID",
    "name:ind_x_preferred":[
        "Kalimargosari"
    ],
    "wof:name":"Kalimargosari",
    "wof:placetype":"locality"
},
  "geometry": {"coordinates":[110.14919999999999,-7.0784],"type":"Point"}
}