{
  "type": "Feature",
  "properties": {
    "gn:admin1_code":"21.0",
    "gn:asciiname":"Boyapolo",
    "gn:country_code":"ID",
    "gn:dem":19,
    "gn:feature_class":"P",
    "gn:feature_code":"PPL",
    "gn:name":"Boyapolo",
    "gn:population":0,
    "gn:timezone":"Asia/Makassar",
    "iso:country":"ID",
    "name:ind_x_preferred":[
        "Boyapolo"
    ],
    "wof:name":"Boyapolo",
    "wof:placetype":"locality"
},
  "geometry": {"coordinates":[119.8458,-0.8972],"type":"Point"}
}