{
  "type": "Feature",
  "properties": {
    "gn:admin1_code":"1",
    "gn:asciiname":"Matang Ben",
    "gn:country_code":"ID",
    "gn:dem":8,
    "gn:feature_class":"P",
    "gn:feature_code":"PPL",
    "gn:name":"Matang Ben",
    "gn:population":0,
    "gn:timezone":"Asia/Jakarta",
    "iso:country":"ID",
    "name:ind_x_preferred":[
        "Matang Ben"
    ],
    "wof:name":"Matang Ben",
    "wof:placetype":"locality"
},
  "geometry": {"coordinates":[97.2889,5.0716],"type":"Point"}
}