{
  "type": "Feature",
  "properties": {
    "gn:admin1_code":"30.0",
    "gn:asciiname":"Pugadungan",
    "gn:country_code":"ID",
    "gn:dem":3,
    "gn:feature_class":"P",
    "gn:feature_code":"PPL",
    "gn:name":"Pugadungan",
    "gn:population":0,
    "gn:timezone":"Asia/Jakarta",
    "iso:country":"ID",
    "name:ind_x_preferred":[
        "Pugadungan"
    ],
    "name:und_x_variant":[
        "Pegadoengan",
        "Pegadangan",
        "Pegadungan"
    ],
    "wof:lang_x_official":[
        "ind"
    ],
    "wof:lang_x_spoken":[
        "ind",
        "eng"
    ],
    "wof:name":"Pugadungan",
    "wof:placetype":"locality"
},
  "geometry": {"coordinates":[107.14389,-6.04167],"type":"Point"}
}