{
  "type": "Feature",
  "properties": {
    "gn:admin1_code":"7.0",
    "gn:asciiname":"Aren",
    "gn:country_code":"ID",
    "gn:dem":943,
    "gn:feature_class":"P",
    "gn:feature_code":"PPL",
    "gn:name":"Aren",
    "gn:population":0,
    "gn:timezone":"Asia/Jakarta",
    "iso:country":"ID",
    "name:arg_x_preferred":[
        "Aren"
    ],
    "name:cat_x_preferred":[
        "Aren"
    ],
    "name:ceb_x_preferred":[
        "Aren"
    ],
    "name:deu_x_preferred":[
        "Aren"
    ],
    "name:fas_x_preferred":[
        "\u0622\u0631\u0646"
    ],
    "name:fra_x_preferred":[
        "Aren"
    ],
    "name:hun_x_preferred":[
        "Aren"
    ],
    "name:ind_x_preferred":[
        "Aren"
    ],
    "name:ita_x_preferred":[
        "Aren"
    ],
    "name:kaz_x_preferred":[
        "\u0410\u0440\u0430\u043d"
    ],
    "name:lat_x_preferred":[
        "Aren"
    ],
    "name:mlg_x_preferred":[
        "Aren"
    ],
    "name:msa_x_preferred":[
        "Aren"
    ],
    "name:nld_x_preferred":[
        "Aren"
    ],
    "name:oci_x_preferred":[
        "Aren"
    ],
    "name:pms_x_preferred":[
        "Aren"
    ],
    "name:pol_x_preferred":[
        "Aren"
    ],
    "name:por_x_preferred":[
        "Aren"
    ],
    "name:ron_x_preferred":[
        "Aren"
    ],
    "name:rus_x_preferred":[
        "\u0410\u0440\u0430\u043d"
    ],
    "name:slk_x_preferred":[
        "Aren"
    ],
    "name:spa_x_preferred":[
        "Aren"
    ],
    "name:srp_x_preferred":[
        "\u0410\u0440\u0430\u043d"
    ],
    "name:swe_x_preferred":[
        "Aren"
    ],
    "name:ukr_x_preferred":[
        "\u0410\u0440\u0430\u043d"
    ],
    "name:uzb_x_preferred":[
        "Aren"
    ],
    "name:vie_x_preferred":[
        "Aren"
    ],
    "name:vol_x_preferred":[
        "Aren"
    ],
    "name:war_x_preferred":[
        "Aren"
    ],
    "wof:name":"Aren",
    "wof:placetype":"locality"
},
  "geometry": {"coordinates":[109.11944,-7.17361],"type":"Point"}
}