{
  "type": "Feature",
  "properties": {
    "gn:admin1_code":"3.0",
    "gn:asciiname":"Belimbing",
    "gn:country_code":"ID",
    "gn:dem":153,
    "gn:feature_class":"P",
    "gn:feature_code":"PPL",
    "gn:name":"Belimbing",
    "gn:population":0,
    "gn:timezone":"Asia/Jakarta",
    "iso:country":"ID",
    "name:ind_x_preferred":[
        "Belimbing"
    ],
    "wof:name":"Belimbing",
    "wof:placetype":"locality"
},
  "geometry": {"coordinates":[102.9169,-3.4164],"type":"Point"}
}