{
  "type": "Feature",
  "properties": {
    "gn:admin1_code":"7",
    "gn:asciiname":"Blungu",
    "gn:country_code":"ID",
    "gn:dem":89,
    "gn:feature_class":"P",
    "gn:feature_code":"PPL",
    "gn:name":"Blungu",
    "gn:population":0,
    "gn:timezone":"Asia/Jakarta",
    "iso:country":"ID",
    "name:ind_x_preferred":[
        "Blungu"
    ],
    "wof:name":"Blungu",
    "wof:placetype":"locality"
},
  "geometry": {"coordinates":[111.4675,-7.0874],"type":"Point"}
}