{
  "type": "Feature",
  "properties": {
    "gn:admin1_code":"30.0",
    "gn:asciiname":"Margamukti",
    "gn:country_code":"ID",
    "gn:dem":315,
    "gn:feature_class":"P",
    "gn:feature_code":"PPL",
    "gn:name":"Margamukti",
    "gn:population":0,
    "gn:timezone":"Asia/Jakarta",
    "iso:country":"ID",
    "name:ind_x_preferred":[
        "Margamukti"
    ],
    "wof:name":"Margamukti",
    "wof:placetype":"locality"
},
  "geometry": {"coordinates":[108.48869999999999,-7.0326],"type":"Point"}
}