{
  "type": "Feature",
  "properties": {
    "gn:admin1_code":"33.0",
    "gn:asciiname":"Pasiranom",
    "gn:country_code":"ID",
    "gn:dem":145,
    "gn:feature_class":"P",
    "gn:feature_code":"PPL",
    "gn:name":"Pasiranom",
    "gn:population":0,
    "gn:timezone":"Asia/Jakarta",
    "iso:country":"ID",
    "name:ind_x_preferred":[
        "Pasiranom"
    ],
    "wof:name":"Pasiranom",
    "wof:placetype":"locality"
},
  "geometry": {"coordinates":[106.0166,-6.3755],"type":"Point"}
}