{
  "type": "Feature",
  "properties": {
    "gn:admin1_code":"33",
    "gn:asciiname":"Kedungleles",
    "gn:country_code":"ID",
    "gn:dem":13,
    "gn:feature_class":"P",
    "gn:feature_code":"PPL",
    "gn:name":"Kedungleles",
    "gn:population":0,
    "gn:timezone":"Asia/Jakarta",
    "iso:country":"ID",
    "name:ind_x_preferred":[
        "Kedungleles"
    ],
    "wof:name":"Kedungleles",
    "wof:placetype":"locality"
},
  "geometry": {"coordinates":[106.1459,-6.0711],"type":"Point"}
}