{
  "type": "Feature",
  "properties": {
    "gn:admin1_code":"33.0",
    "gn:asciiname":"Kaducukang",
    "gn:country_code":"ID",
    "gn:dem":86,
    "gn:feature_class":"P",
    "gn:feature_code":"PPLA4",
    "gn:name":"Kaducukang",
    "gn:population":0,
    "gn:timezone":"Asia/Jakarta",
    "iso:country":"ID",
    "name:ind_x_preferred":[
        "Kaducukang"
    ],
    "name:und_x_variant":[
        "Kadoetjoekang"
    ],
    "wof:lang_x_official":[
        "ind"
    ],
    "wof:lang_x_spoken":[
        "ind",
        "eng"
    ],
    "wof:name":"Kaducukang",
    "wof:placetype":"locality"
},
  "geometry": {"coordinates":[105.91800000000001,-6.3929],"type":"Point"}
}