{
  "type": "Feature",
  "properties": {
    "gn:admin1_code":"30",
    "gn:asciiname":"Haurpancuh",
    "gn:country_code":"ID",
    "gn:dem":745,
    "gn:feature_class":"P",
    "gn:feature_code":"PPL",
    "gn:name":"Haurpancuh",
    "gn:population":0,
    "gn:timezone":"Asia/Jakarta",
    "iso:country":"ID",
    "name:ind_x_preferred":[
        "Haurpancuh"
    ],
    "wof:name":"Haurpancuh",
    "wof:placetype":"locality"
},
  "geometry": {"coordinates":[107.62083,-6.89444],"type":"Point"}
}