{
  "type": "Feature",
  "properties": {
    "gn:admin1_code":"8",
    "gn:asciiname":"Jamblangsalak",
    "gn:country_code":"ID",
    "gn:dem":112,
    "gn:feature_class":"P",
    "gn:feature_code":"PPL",
    "gn:name":"Jamblangsalak",
    "gn:population":0,
    "gn:timezone":"Asia/Jakarta",
    "iso:country":"ID",
    "name:ind_x_preferred":[
        "Jamblangsalak"
    ],
    "wof:name":"Jamblangsalak",
    "wof:placetype":"locality"
},
  "geometry": {"coordinates":[111.14694,-7.42306],"type":"Point"}
}