{
  "type": "Feature",
  "properties": {
    "gn:admin1_code":"1",
    "gn:asciiname":"Glumpang Bungkok",
    "gn:country_code":"ID",
    "gn:dem":20,
    "gn:feature_class":"P",
    "gn:feature_code":"PPL",
    "gn:name":"Glumpang Bungkok",
    "gn:population":0,
    "gn:timezone":"Asia/Jakarta",
    "iso:country":"ID",
    "name:ind_x_preferred":[
        "Glumpang Bungkok"
    ],
    "wof:name":"Glumpang Bungkok",
    "wof:placetype":"locality"
},
  "geometry": {"coordinates":[96.3464,5.1934],"type":"Point"}
}