{
  "type": "Feature",
  "properties": {
    "gn:admin1_code":"8.0",
    "gn:asciiname":"Lebak Barat",
    "gn:country_code":"ID",
    "gn:dem":12,
    "gn:feature_class":"P",
    "gn:feature_code":"PPL",
    "gn:name":"Lebak Barat",
    "gn:population":0,
    "gn:timezone":"Asia/Jakarta",
    "iso:country":"ID",
    "name:ind_x_preferred":[
        "Lebak Barat"
    ],
    "wof:name":"Lebak Barat",
    "wof:placetype":"locality"
},
  "geometry": {"coordinates":[113.5277,-6.8958],"type":"Point"}
}