{
  "type": "Feature",
  "properties": {
    "gn:admin1_code":"18",
    "gn:asciiname":"Langgaliru",
    "gn:country_code":"ID",
    "gn:dem":421,
    "gn:feature_class":"P",
    "gn:feature_code":"PPL",
    "gn:name":"Langgaliru",
    "gn:population":0,
    "gn:timezone":"Asia/Makassar",
    "iso:country":"ID",
    "name:ind_x_preferred":[
        "Langgaliru"
    ],
    "wof:name":"Langgaliru",
    "wof:placetype":"locality"
},
  "geometry": {"coordinates":[119.8215,-9.6539],"type":"Point"}
}