{
  "type": "Feature",
  "properties": {
    "gn:admin1_code":"1",
    "gn:asciiname":"Pasi",
    "gn:country_code":"ID",
    "gn:dem":16,
    "gn:feature_class":"P",
    "gn:feature_code":"PPL",
    "gn:name":"Pasi",
    "gn:population":0,
    "gn:timezone":"Asia/Jakarta",
    "iso:country":"ID",
    "name:ceb_x_preferred":[
        "Pasi"
    ],
    "name:deu_x_preferred":[
        "Pasi"
    ],
    "name:fin_x_preferred":[
        "Pasi"
    ],
    "name:ind_x_preferred":[
        "Pasi"
    ],
    "name:ita_x_preferred":[
        "Pasi"
    ],
    "name:nld_x_preferred":[
        "Pasi"
    ],
    "name:swe_x_preferred":[
        "Pasi"
    ],
    "wof:lang_x_official":[
        "ind"
    ],
    "wof:lang_x_spoken":[
        "ind",
        "eng"
    ],
    "wof:name":"Pasi",
    "wof:placetype":"locality"
},
  "geometry": {"coordinates":[95.3712,5.5052],"type":"Point"}
}