{
  "type": "Feature",
  "properties": {
    "gn:admin1_code":"7",
    "gn:asciiname":"Putatan",
    "gn:country_code":"ID",
    "gn:dem":88,
    "gn:feature_class":"P",
    "gn:feature_code":"PPL",
    "gn:name":"Putatan",
    "gn:population":0,
    "gn:timezone":"Asia/Jakarta",
    "iso:country":"ID",
    "name:ceb_x_preferred":[
        "Putatan"
    ],
    "name:deu_x_preferred":[
        "Putatan"
    ],
    "name:ind_x_preferred":[
        "Putatan"
    ],
    "name:msa_x_preferred":[
        "Putatan"
    ],
    "name:nld_x_preferred":[
        "Putatan"
    ],
    "name:nor_x_preferred":[
        "Putatan"
    ],
    "name:pol_x_preferred":[
        "Putatan"
    ],
    "name:vie_x_preferred":[
        "Putatan"
    ],
    "wof:lang_x_official":[
        "ind"
    ],
    "wof:lang_x_spoken":[
        "ind",
        "eng"
    ],
    "wof:name":"Putatan",
    "wof:placetype":"locality"
},
  "geometry": {"coordinates":[111.03749999999999,-7.35806],"type":"Point"}
}