{
  "type": "Feature",
  "properties": {
    "gn:admin1_code":"8.0",
    "gn:asciiname":"Tengah Satu",
    "gn:country_code":"ID",
    "gn:dem":176,
    "gn:feature_class":"P",
    "gn:feature_code":"PPL",
    "gn:name":"Tengah Satu",
    "gn:population":0,
    "gn:timezone":"Asia/Jakarta",
    "iso:country":"ID",
    "name:ind_x_preferred":[
        "Tengah Satu"
    ],
    "wof:name":"Tengah Satu",
    "wof:placetype":"locality"
},
  "geometry": {"coordinates":[113.53919999999999,-6.9329],"type":"Point"}
}