{
  "type": "Feature",
  "properties": {
    "gn:admin1_code":"30",
    "gn:asciiname":"Pasirbuntu",
    "gn:country_code":"ID",
    "gn:dem":1147,
    "gn:feature_class":"P",
    "gn:feature_code":"PPL",
    "gn:name":"Pasirbuntu",
    "gn:population":0,
    "gn:timezone":"Asia/Jakarta",
    "iso:country":"ID",
    "name:ind_x_preferred":[
        "Pasirbuntu"
    ],
    "wof:name":"Pasirbuntu",
    "wof:placetype":"locality"
},
  "geometry": {"coordinates":[107.02806,-6.72917],"type":"Point"}
}