{
  "type": "Feature",
  "properties": {
    "gn:admin1_code":"38",
    "gn:asciiname":"Alang",
    "gn:country_code":"ID",
    "gn:dem":128,
    "gn:feature_class":"P",
    "gn:feature_code":"PPL",
    "gn:name":"Alang",
    "gn:population":0,
    "gn:timezone":"Asia/Makassar",
    "iso:country":"ID",
    "name:bpy_x_preferred":[
        "\u0986\u09b2\u0982"
    ],
    "name:dan_x_preferred":[
        "Alang"
    ],
    "name:deu_x_preferred":[
        "Alang"
    ],
    "name:fas_x_preferred":[
        "\u0627\u0644\u0627\u0646\u06af"
    ],
    "name:fin_x_preferred":[
        "Alang"
    ],
    "name:fra_x_preferred":[
        "Alang"
    ],
    "name:guj_x_preferred":[
        "\u0a85\u0ab2\u0a82\u0a97"
    ],
    "name:heb_x_preferred":[
        "\u05d0\u05dc\u05d0\u05e0\u05d2"
    ],
    "name:hin_x_preferred":[
        "\u0905\u0932\u093e\u0902\u0917"
    ],
    "name:ind_x_preferred":[
        "Alang"
    ],
    "name:ita_x_preferred":[
        "Alang"
    ],
    "name:min_x_preferred":[
        "Alang"
    ],
    "name:mlg_x_preferred":[
        "Alang"
    ],
    "name:msa_x_preferred":[
        "Alang"
    ],
    "name:new_x_preferred":[
        "\u0905\u0932\u0902\u0917"
    ],
    "name:nld_x_preferred":[
        "Alang"
    ],
    "name:nor_x_preferred":[
        "Alang"
    ],
    "name:por_x_preferred":[
        "Alang"
    ],
    "name:rus_x_preferred":[
        "\u0410\u043b\u0430\u043d\u0433"
    ],
    "name:spa_x_preferred":[
        "Alang"
    ],
    "name:swe_x_preferred":[
        "Alang"
    ],
    "name:tam_x_preferred":[
        "\u0b85\u0bb2\u0b99\u0bcd"
    ],
    "name:vie_x_preferred":[
        "Alang"
    ],
    "wof:lang_x_official":[
        "ind"
    ],
    "wof:lang_x_spoken":[
        "ind",
        "eng"
    ],
    "wof:name":"Alang",
    "wof:placetype":"locality"
},
  "geometry": {"coordinates":[120.04730000000001,-4.6984],"type":"Point"}
}