{
  "type": "Feature",
  "properties": {
    "gn:admin1_code":"15.0",
    "gn:asciiname":"Kampung Lambur",
    "gn:country_code":"ID",
    "gn:dem":6,
    "gn:feature_class":"P",
    "gn:feature_code":"PPL",
    "gn:name":"Kampung Lambur",
    "gn:population":0,
    "gn:timezone":"Asia/Jakarta",
    "iso:country":"ID",
    "name:ind_x_preferred":[
        "Kampung Lambur"
    ],
    "name:und_x_variant":[
        "Oemboelan Lamboer"
    ],
    "wof:name":"Kampung Lambur",
    "wof:placetype":"locality"
},
  "geometry": {"coordinates":[105.53167000000001,-5.67104],"type":"Point"}
}