{
  "type": "Feature",
  "properties": {
    "gn:admin1_code":"26",
    "gn:asciiname":"Kampung Gunung",
    "gn:country_code":"ID",
    "gn:dem":65,
    "gn:feature_class":"P",
    "gn:feature_code":"PPL",
    "gn:name":"Kampung Gunung",
    "gn:population":0,
    "gn:timezone":"Asia/Jakarta",
    "iso:country":"ID",
    "name:ind_x_preferred":[
        "Kampung Gunung"
    ],
    "wof:name":"Kampung Gunung",
    "wof:placetype":"locality"
},
  "geometry": {"coordinates":[99.30249999999999,3.1505],"type":"Point"}
}