{
  "type": "Feature",
  "properties": {
    "gn:admin1_code":"30",
    "gn:asciiname":"Cisampih Dua",
    "gn:country_code":"ID",
    "gn:dem":132,
    "gn:feature_class":"P",
    "gn:feature_code":"PPL",
    "gn:name":"Cisampih Dua",
    "gn:population":0,
    "gn:timezone":"Asia/Jakarta",
    "iso:country":"ID",
    "name:ind_x_preferred":[
        "Cisampih Dua"
    ],
    "wof:name":"Cisampih Dua",
    "wof:placetype":"locality"
},
  "geometry": {"coordinates":[107.40555999999999,-6.55806],"type":"Point"}
}