{
  "type": "Feature",
  "properties": {
    "gn:admin1_code":"7.0",
    "gn:asciiname":"Merden Wetan",
    "gn:country_code":"ID",
    "gn:dem":136,
    "gn:feature_class":"P",
    "gn:feature_code":"PPL",
    "gn:name":"Merden Wetan",
    "gn:population":0,
    "gn:timezone":"Asia/Jakarta",
    "iso:country":"ID",
    "name:ind_x_preferred":[
        "Merden Wetan"
    ],
    "wof:name":"Merden Wetan",
    "wof:placetype":"locality"
},
  "geometry": {"coordinates":[109.5475,-7.46444],"type":"Point"}
}