{
  "type": "Feature",
  "properties": {
    "gn:admin1_code":"15.0",
    "gn:asciiname":"Gedonggumanti",
    "gn:country_code":"ID",
    "gn:dem":71,
    "gn:feature_class":"P",
    "gn:feature_code":"PPL",
    "gn:name":"Gedonggumanti",
    "gn:population":0,
    "gn:timezone":"Asia/Jakarta",
    "iso:country":"ID",
    "name:ind_x_preferred":[
        "Gedonggumanti"
    ],
    "wof:name":"Gedonggumanti",
    "wof:placetype":"locality"
},
  "geometry": {"coordinates":[105.16329,-5.19723],"type":"Point"}
}