{
  "type": "Feature",
  "properties": {
    "gn:admin1_code":"18.0",
    "gn:asciiname":"Oemenu",
    "gn:country_code":"ID",
    "gn:dem":174,
    "gn:feature_class":"P",
    "gn:feature_code":"PPL",
    "gn:name":"Oemenu",
    "gn:population":0,
    "gn:timezone":"Asia/Makassar",
    "iso:country":"ID",
    "name:ind_x_preferred":[
        "Oemenu"
    ],
    "wof:name":"Oemenu",
    "wof:placetype":"locality"
},
  "geometry": {"coordinates":[124.07689999999999,-9.9992],"type":"Point"}
}