{
  "type": "Feature",
  "properties": {
    "gn:admin1_code":"18.0",
    "gn:asciiname":"Welio",
    "gn:country_code":"ID",
    "gn:dem":108,
    "gn:feature_class":"P",
    "gn:feature_code":"PPL",
    "gn:name":"Welio",
    "gn:population":0,
    "gn:timezone":"Asia/Makassar",
    "iso:country":"ID",
    "name:ind_x_preferred":[
        "Welio"
    ],
    "wof:name":"Welio",
    "wof:placetype":"locality"
},
  "geometry": {"coordinates":[119.3635,-9.7426],"type":"Point"}
}