{
  "type": "Feature",
  "properties": {
    "gn:admin1_code":"33.0",
    "gn:asciiname":"Cisoka",
    "gn:country_code":"ID",
    "gn:dem":177,
    "gn:feature_class":"P",
    "gn:feature_code":"PPL",
    "gn:name":"Cisoka",
    "gn:population":0,
    "gn:timezone":"Asia/Jakarta",
    "iso:country":"ID",
    "name:ind_x_preferred":[
        "Cisoka"
    ],
    "name:jav_x_preferred":[
        "Cisoka"
    ],
    "name:msa_x_preferred":[
        "Cisoka"
    ],
    "wof:lang_x_official":[
        "ind"
    ],
    "wof:lang_x_spoken":[
        "ind",
        "eng"
    ],
    "wof:name":"Cisoka",
    "wof:placetype":"locality"
},
  "geometry": {"coordinates":[106.0363,-6.5776],"type":"Point"}
}