{
  "type": "Feature",
  "properties": {
    "gn:admin1_code":"30",
    "gn:asciiname":"Legokpaci",
    "gn:country_code":"ID",
    "gn:dem":1174,
    "gn:feature_class":"P",
    "gn:feature_code":"PPL",
    "gn:name":"Legokpaci",
    "gn:population":0,
    "gn:timezone":"Asia/Jakarta",
    "iso:country":"ID",
    "name:ind_x_preferred":[
        "Legokpaci"
    ],
    "name:und_x_variant":[
        "Legokpari"
    ],
    "wof:lang_x_official":[
        "ind"
    ],
    "wof:lang_x_spoken":[
        "ind",
        "eng"
    ],
    "wof:name":"Legokpaci",
    "wof:placetype":"locality"
},
  "geometry": {"coordinates":[107.4328,-7.0694],"type":"Point"}
}