{
  "type": "Feature",
  "properties": {
    "gn:admin1_code":"30.0",
    "gn:asciiname":"Cikalong",
    "gn:country_code":"ID",
    "gn:dem":355,
    "gn:feature_class":"P",
    "gn:feature_code":"PPLA4",
    "gn:name":"Cikalong",
    "gn:population":0,
    "gn:timezone":"Asia/Jakarta",
    "iso:country":"ID",
    "name:ind_x_preferred":[
        "Cikalong"
    ],
    "name:und_x_variant":[
        "Tjikalong",
        "Cikalong"
    ],
    "wof:name":"Cikalong",
    "wof:placetype":"locality"
},
  "geometry": {"coordinates":[108.0518,-7.4599],"type":"Point"}
}