{
  "type": "Feature",
  "properties": {
    "gn:admin1_code":"30",
    "gn:asciiname":"Patrol",
    "gn:country_code":"ID",
    "gn:dem":817,
    "gn:feature_class":"P",
    "gn:feature_code":"PPL",
    "gn:name":"Patrol",
    "gn:population":0,
    "gn:timezone":"Asia/Jakarta",
    "iso:country":"ID",
    "wof:name":"Patrol",
    "wof:placetype":"locality"
},
  "geometry": {"coordinates":[107.62139000000001,-7.05],"type":"Point"}
}