{
  "type": "Feature",
  "properties": {
    "gn:admin1_code":"30",
    "gn:asciiname":"Muara",
    "gn:country_code":"ID",
    "gn:dem":443,
    "gn:feature_class":"P",
    "gn:feature_code":"PPL",
    "gn:name":"Muara",
    "gn:population":0,
    "gn:timezone":"Asia/Jakarta",
    "iso:country":"ID",
    "name:ceb_x_preferred":[
        "Muara"
    ],
    "name:ind_x_preferred":[
        "Muara"
    ],
    "name:nld_x_preferred":[
        "Muara"
    ],
    "name:swe_x_preferred":[
        "Muara"
    ],
    "wof:lang_x_official":[
        "ind"
    ],
    "wof:lang_x_spoken":[
        "ind",
        "eng"
    ],
    "wof:name":"Muara",
    "wof:placetype":"locality"
},
  "geometry": {"coordinates":[106.81806,-6.71833],"type":"Point"}
}