{
  "type": "Feature",
  "properties": {
    "gn:admin1_code":"8",
    "gn:asciiname":"Ngampin",
    "gn:country_code":"ID",
    "gn:dem":933,
    "gn:feature_class":"P",
    "gn:feature_code":"PPL",
    "gn:name":"Ngampin",
    "gn:population":0,
    "gn:timezone":"Asia/Jakarta",
    "iso:country":"ID",
    "name:ind_x_preferred":[
        "Ngampin"
    ],
    "wof:name":"Ngampin",
    "wof:placetype":"locality"
},
  "geometry": {"coordinates":[111.24833,-7.70889],"type":"Point"}
}