{
  "type": "Feature",
  "properties": {
    "gn:admin1_code":"17",
    "gn:asciiname":"Loka",
    "gn:country_code":"ID",
    "gn:dem":384,
    "gn:feature_class":"P",
    "gn:feature_code":"PPL",
    "gn:name":"Loka",
    "gn:population":0,
    "gn:timezone":"Asia/Makassar",
    "iso:country":"ID",
    "name:ind_x_preferred":[
        "Loka"
    ],
    "wof:name":"Loka",
    "wof:placetype":"locality"
},
  "geometry": {"coordinates":[118.843,-8.5163],"type":"Point"}
}