{
  "type": "Feature",
  "properties": {
    "gn:admin1_code":"8",
    "gn:asciiname":"Panggunglombok Lor",
    "gn:country_code":"ID",
    "gn:dem":283,
    "gn:feature_class":"P",
    "gn:feature_code":"PPL",
    "gn:name":"Panggunglombok Lor",
    "gn:population":0,
    "gn:timezone":"Asia/Jakarta",
    "iso:country":"ID",
    "name:ind_x_preferred":[
        "Panggunglombok Lor"
    ],
    "wof:name":"Panggunglombok Lor",
    "wof:placetype":"locality"
},
  "geometry": {"coordinates":[113.07429999999999,-8.2003],"type":"Point"}
}