{
  "type": "Feature",
  "properties": {
    "gn:admin1_code":"38",
    "gn:asciiname":"Jampu",
    "gn:country_code":"ID",
    "gn:dem":314,
    "gn:feature_class":"P",
    "gn:feature_code":"PPL",
    "gn:name":"Jampu",
    "gn:population":0,
    "gn:timezone":"Asia/Makassar",
    "iso:country":"ID",
    "name:ind_x_preferred":[
        "Jampu"
    ],
    "wof:name":"Jampu",
    "wof:placetype":"locality"
},
  "geometry": {"coordinates":[119.7306,-4.0081],"type":"Point"}
}