{
  "type": "Feature",
  "properties": {
    "gn:admin1_code":"30.0",
    "gn:asciiname":"Peuteuy",
    "gn:country_code":"ID",
    "gn:dem":147,
    "gn:feature_class":"P",
    "gn:feature_code":"PPL",
    "gn:name":"Peuteuy",
    "gn:population":0,
    "gn:timezone":"Asia/Jakarta",
    "iso:country":"ID",
    "name:ind_x_preferred":[
        "Peuteuy"
    ],
    "wof:name":"Peuteuy",
    "wof:placetype":"locality"
},
  "geometry": {"coordinates":[106.496,-6.5122],"type":"Point"}
}