{
  "type": "Feature",
  "properties": {
    "gn:admin1_code":"38",
    "gn:asciiname":"Kote",
    "gn:country_code":"ID",
    "gn:dem":788,
    "gn:feature_class":"P",
    "gn:feature_code":"PPL",
    "gn:name":"Kote",
    "gn:population":0,
    "gn:timezone":"Asia/Makassar",
    "iso:country":"ID",
    "name:ceb_x_preferred":[
        "Kote"
    ],
    "name:deu_x_preferred":[
        "Kote"
    ],
    "name:ind_x_preferred":[
        "Kote"
    ],
    "name:swe_x_preferred":[
        "Kote"
    ],
    "wof:name":"Kote",
    "wof:placetype":"locality"
},
  "geometry": {"coordinates":[119.8998,-3.0802],"type":"Point"}
}