{
  "type": "Feature",
  "properties": {
    "gn:admin1_code":"1",
    "gn:asciiname":"Tuwi Eumpeuk",
    "gn:country_code":"ID",
    "gn:dem":15,
    "gn:feature_class":"P",
    "gn:feature_code":"PPL",
    "gn:name":"Tuwi Eumpeuk",
    "gn:population":0,
    "gn:timezone":"Asia/Jakarta",
    "iso:country":"ID",
    "name:ind_x_preferred":[
        "Tuwi Eumpeuk"
    ],
    "wof:name":"Tuwi Eumpeuk",
    "wof:placetype":"locality"
},
  "geometry": {"coordinates":[95.7704,4.5513],"type":"Point"}
}