{
  "type": "Feature",
  "properties": {
    "gn:admin1_code":"10.0",
    "gn:asciiname":"Sedan",
    "gn:country_code":"ID",
    "gn:dem":26,
    "gn:feature_class":"P",
    "gn:feature_code":"PPL",
    "gn:name":"Sedan",
    "gn:population":0,
    "gn:timezone":"Asia/Jakarta",
    "iso:country":"ID",
    "name:ara_x_preferred":[
        "\u0633\u064a\u062f\u0627\u0646"
    ],
    "name:bre_x_preferred":[
        "Sedan"
    ],
    "name:bul_x_preferred":[
        "\u0421\u0435\u0434\u0430\u043d"
    ],
    "name:cat_x_preferred":[
        "Sedan"
    ],
    "name:ceb_x_preferred":[
        "Sedan"
    ],
    "name:ces_x_preferred":[
        "Sedan"
    ],
    "name:dan_x_preferred":[
        "Sedan"
    ],
    "name:deu_x_preferred":[
        "Sedan"
    ],
    "name:fra_x_preferred":[
        "Sedan"
    ],
    "name:hun_x_preferred":[
        "Sedan"
    ],
    "name:ita_x_preferred":[
        "Sedan"
    ],
    "name:jpn_x_preferred":[
        "\u30bb\u30c0\u30f3"
    ],
    "name:kaz_x_preferred":[
        "\u0421\u0435\u0434\u0430\u043d"
    ],
    "name:kor_x_preferred":[
        "\uc138\ub2e8"
    ],
    "name:lit_x_preferred":[
        "Sedanas"
    ],
    "name:nld_x_preferred":[
        "Sedan"
    ],
    "name:nor_x_preferred":[
        "Sedan"
    ],
    "name:pol_x_preferred":[
        "Sedan"
    ],
    "name:por_x_preferred":[
        "Sedan"
    ],
    "name:ron_x_preferred":[
        "Sedan"
    ],
    "name:rus_x_preferred":[
        "\u0421\u0435\u0434\u0430\u043d"
    ],
    "name:sco_x_preferred":[
        "Sedan"
    ],
    "name:slk_x_preferred":[
        "Sedan"
    ],
    "name:slv_x_preferred":[
        "Sedan"
    ],
    "name:spa_x_preferred":[
        "Sedan"
    ],
    "name:srp_x_preferred":[
        "\u0421\u0438\u0434\u0430\u043d"
    ],
    "name:swe_x_preferred":[
        "Sedan"
    ],
    "name:tur_x_preferred":[
        "Sedan"
    ],
    "name:ukr_x_preferred":[
        "\u0421\u0435\u0434\u0430\u043d"
    ],
    "name:vie_x_preferred":[
        "Sedan"
    ],
    "name:vol_x_preferred":[
        "Sedan"
    ],
    "wof:lang_x_official":[
        "ind"
    ],
    "wof:lang_x_spoken":[
        "ind",
        "eng"
    ],
    "wof:name":"Sedan",
    "wof:placetype":"locality"
},
  "geometry": {"coordinates":[110.24639000000001,-7.92611],"type":"Point"}
}