{
  "type": "Feature",
  "properties": {
    "gn:admin1_code":"8",
    "gn:asciiname":"Butoh",
    "gn:country_code":"ID",
    "gn:dem":62,
    "gn:feature_class":"P",
    "gn:feature_code":"PPL",
    "gn:name":"Butoh",
    "gn:population":0,
    "gn:timezone":"Asia/Jakarta",
    "iso:country":"ID",
    "name:ind_x_preferred":[
        "Butoh"
    ],
    "wof:name":"Butoh",
    "wof:placetype":"locality"
},
  "geometry": {"coordinates":[111.25306,-7.3675],"type":"Point"}
}