{
  "type": "Feature",
  "properties": {
    "gn:admin1_code":"8",
    "gn:asciiname":"Butoh",
    "gn:country_code":"ID",
    "gn:dem":62,
    "gn:feature_class":"P",
    "gn:feature_code":"PPL",
    "gn:name":"Butoh",
    "gn:population":0,
    "gn:timezone":"Asia/Jakarta",
    "iso:country":"ID",
    "name:dan_x_preferred":[
        "Butoh"
    ],
    "name:deu_x_preferred":[
        "Butoh"
    ],
    "name:epo_x_preferred":[
        "Butoo"
    ],
    "name:fin_x_preferred":[
        "But\u014d"
    ],
    "name:fra_x_preferred":[
        "But\u014d"
    ],
    "name:heb_x_preferred":[
        "\u05d1\u05d5\u05d8\u05d5"
    ],
    "name:ind_x_preferred":[
        "Butoh"
    ],
    "name:ita_x_preferred":[
        "But\u014d"
    ],
    "name:jpn_x_preferred":[
        "\u6697\u9ed2\u821e\u8e0f"
    ],
    "name:kor_x_preferred":[
        "\ubd80\ud1a0"
    ],
    "name:nor_x_preferred":[
        "Butoh"
    ],
    "name:pol_x_preferred":[
        "But\u014d"
    ],
    "name:por_x_preferred":[
        "Butoh"
    ],
    "name:ron_x_preferred":[
        "Butoh"
    ],
    "name:rus_x_preferred":[
        "\u0411\u0443\u0442\u043e"
    ],
    "name:spa_x_preferred":[
        "But\u014d"
    ],
    "name:swe_x_preferred":[
        "Butoh"
    ],
    "name:ukr_x_preferred":[
        "\u0411\u0443\u0442\u043e"
    ],
    "name:vie_x_preferred":[
        "Butoh"
    ],
    "wof:lang_x_official":[
        "ind"
    ],
    "wof:lang_x_spoken":[
        "ind",
        "eng"
    ],
    "wof:name":"Butoh",
    "wof:placetype":"locality"
},
  "geometry": {"coordinates":[111.25306,-7.3675],"type":"Point"}
}