{
  "type": "Feature",
  "properties": {
    "gn:admin1_code":"7",
    "gn:asciiname":"Nglorong",
    "gn:country_code":"ID",
    "gn:dem":474,
    "gn:feature_class":"P",
    "gn:feature_code":"PPL",
    "gn:name":"Nglorong",
    "gn:population":0,
    "gn:timezone":"Asia/Jakarta",
    "iso:country":"ID",
    "name:ind_x_preferred":[
        "Nglorong"
    ],
    "wof:name":"Nglorong",
    "wof:placetype":"locality"
},
  "geometry": {"coordinates":[111.09332999999999,-7.78833],"type":"Point"}
}