{
  "type": "Feature",
  "properties": {
    "gn:admin1_code":"30.0",
    "gn:asciiname":"Cilimus",
    "gn:country_code":"ID",
    "gn:dem":306,
    "gn:feature_class":"P",
    "gn:feature_code":"PPLA4",
    "gn:name":"Cilimus",
    "gn:population":0,
    "gn:timezone":"Asia/Jakarta",
    "iso:country":"ID",
    "name:ind_x_preferred":[
        "Cilimus"
    ],
    "name:und_x_variant":[
        "Tjilimoes Dua"
    ],
    "wof:lang_x_official":[
        "ind"
    ],
    "wof:lang_x_spoken":[
        "ind",
        "eng"
    ],
    "wof:name":"Cilimus",
    "wof:placetype":"locality"
},
  "geometry": {"coordinates":[108.46599999999999,-7.1096],"type":"Point"}
}