{
  "type": "Feature",
  "properties": {
    "gn:admin1_code":"1",
    "gn:asciiname":"Beranang",
    "gn:country_code":"ID",
    "gn:dem":1047,
    "gn:feature_class":"P",
    "gn:feature_code":"PPL",
    "gn:name":"Beranang",
    "gn:population":0,
    "gn:timezone":"Asia/Jakarta",
    "iso:country":"ID",
    "name:ind_x_preferred":[
        "Beranang"
    ],
    "name:msa_x_preferred":[
        "Beranang"
    ],
    "name:nld_x_preferred":[
        "Beranang"
    ],
    "name:und_x_variant":[
        "Beranan"
    ],
    "wof:lang_x_official":[
        "ind"
    ],
    "wof:lang_x_spoken":[
        "ind",
        "eng"
    ],
    "wof:name":"Beranang",
    "wof:placetype":"locality"
},
  "geometry": {"coordinates":[97.27670000000001,4.0119],"type":"Point"}
}