{
  "type": "Feature",
  "properties": {
    "gn:country":"ID",
    "gn:fcode":"PPL",
    "gn:pop":0,
    "iso:country":"ID",
    "name:ben_x_preferred":[
        "\u0995\u09be\u09aa\u09be\u09b8\u09be\u09a8"
    ],
    "name:bpy_x_preferred":[
        "\u0995\u09be\u09aa\u09be\u09b8\u09be\u09a8"
    ],
    "name:cat_x_preferred":[
        "Kapasan"
    ],
    "name:ceb_x_preferred":[
        "Kapasan"
    ],
    "name:hin_x_preferred":[
        "\u0915\u092a\u093e\u0938\u0928"
    ],
    "name:ind_x_preferred":[
        "Kapasan"
    ],
    "name:ita_x_preferred":[
        "Kapasan"
    ],
    "name:mlg_x_preferred":[
        "Kapasan"
    ],
    "name:msa_x_preferred":[
        "Kapasan"
    ],
    "name:new_x_preferred":[
        "\u0915\u092a\u093e\u0938\u0928"
    ],
    "name:por_x_preferred":[
        "Kapasan"
    ],
    "name:vie_x_preferred":[
        "Kapasan"
    ],
    "name:zho_x_preferred":[
        "\u5361\u5e15\u6851"
    ],
    "qs:name":"Kapasan",
    "qs:name_adm0":"Indonesia",
    "qs:name_adm1":"Jawa Timur",
    "qs:photos_9k":1,
    "qs:photos_9r":1,
    "qs:photos_all":1,
    "qs:photos_sr":0,
    "qs:placetype":"Town",
    "qs:pop_sr":"0",
    "wd:wordcount":216,
    "wof:lang_x_official":[
        "ind"
    ],
    "wof:lang_x_spoken":[
        "ind",
        "eng"
    ],
    "wof:name":"Kapasan",
    "wof:placetype":"locality",
    "wof:population":0
},
  "geometry": {"coordinates":[112.747,-7.2401],"type":"Point"}
}