{
  "type": "Feature",
  "properties": {
    "gn:admin1_code":"37.0",
    "gn:asciiname":"Paritsawe",
    "gn:country_code":"ID",
    "gn:dem":7,
    "gn:feature_class":"P",
    "gn:feature_code":"PPL",
    "gn:name":"Paritsawe",
    "gn:population":0,
    "gn:timezone":"Asia/Jakarta",
    "iso:country":"ID",
    "name:ind_x_preferred":[
        "Paritsawe"
    ],
    "name:und_x_variant":[
        "Parit Sawa"
    ],
    "wof:name":"Paritsawe",
    "wof:placetype":"locality"
},
  "geometry": {"coordinates":[103.46751999999999,-0.01536],"type":"Point"}
}