{
  "type": "Feature",
  "properties": {
    "gn:admin1_code":"8.0",
    "gn:asciiname":"Jambewangi",
    "gn:country_code":"ID",
    "gn:dem":215,
    "gn:feature_class":"P",
    "gn:feature_code":"PPLA4",
    "gn:name":"Jambewangi",
    "gn:population":0,
    "gn:timezone":"Asia/Jakarta",
    "iso:country":"ID",
    "name:ind_x_preferred":[
        "Jambewangi"
    ],
    "wof:name":"Jambewangi",
    "wof:placetype":"locality"
},
  "geometry": {"coordinates":[112.3064,-8.1308],"type":"Point"}
}