{
  "type": "Feature",
  "properties": {
    "gn:admin1_code":"30",
    "gn:asciiname":"Sulukuning",
    "gn:country_code":"ID",
    "gn:dem":99,
    "gn:feature_class":"P",
    "gn:feature_code":"PPL",
    "gn:name":"Sulukuning",
    "gn:population":0,
    "gn:timezone":"Asia/Jakarta",
    "iso:country":"ID",
    "name:ind_x_preferred":[
        "Sulukuning"
    ],
    "wof:name":"Sulukuning",
    "wof:placetype":"locality"
},
  "geometry": {"coordinates":[107.44444,-6.57083],"type":"Point"}
}