{
  "type": "Feature",
  "properties": {
    "gn:country":"ID",
    "gn:fcode":"ADM4",
    "gn:pop":0,
    "iso:country":"ID",
    "name:eng_x_preferred":[
        "Districts of West Java"
    ],
    "name:ind_x_preferred":[
        "Desa Sukaraja Kulon"
    ],
    "name:unk_x_variant":[
        "Sukaraja Kulon"
    ],
    "qs:name":"Desa Sukaraja Kulon",
    "qs:photos_9r":0,
    "qs:photos_sr":0,
    "qs:pop_sr":"0",
    "wd:wordcount":1319,
    "wof:lang_x_official":[
        "ind"
    ],
    "wof:lang_x_spoken":[
        "ind",
        "eng"
    ],
    "wof:name":"Desa Sukaraja Kulon",
    "wof:placetype":"localadmin",
    "wof:population":0
},
  "geometry": {"coordinates":[108.26694000000001,-6.77667],"type":"Point"}
}