{
  "type": "Feature",
  "properties": {
    "gn:admin1_code":"38.0",
    "gn:asciiname":"Bua",
    "gn:country_code":"ID",
    "gn:dem":17,
    "gn:feature_class":"P",
    "gn:feature_code":"PPL",
    "gn:name":"Bua",
    "gn:population":0,
    "gn:timezone":"Asia/Makassar",
    "iso:country":"ID",
    "name:ind_x_preferred":[
        "Bua"
    ],
    "name:und_x_variant":[
        "Buwa"
    ],
    "wof:name":"Bua",
    "wof:placetype":"locality"
},
  "geometry": {"coordinates":[119.6371,-3.8516],"type":"Point"}
}