{
  "type": "Feature",
  "properties": {
    "gn:admin1_code":"7.0",
    "gn:asciiname":"Pakol",
    "gn:country_code":"ID",
    "gn:dem":298,
    "gn:feature_class":"P",
    "gn:feature_code":"PPL",
    "gn:name":"Pakol",
    "gn:population":0,
    "gn:timezone":"Asia/Jakarta",
    "iso:country":"ID",
    "name:deu_x_preferred":[
        "Pakol"
    ],
    "name:epo_x_preferred":[
        "Pakol"
    ],
    "name:fas_x_preferred":[
        "\u067e\u06a9\u0648\u0644"
    ],
    "name:fin_x_preferred":[
        "Pakul"
    ],
    "name:fra_x_preferred":[
        "Pakol"
    ],
    "name:ind_x_preferred":[
        "Pakol"
    ],
    "name:ita_x_preferred":[
        "Pakol"
    ],
    "name:lat_x_preferred":[
        "Pakol"
    ],
    "name:lit_x_preferred":[
        "Pakolis"
    ],
    "name:pol_x_preferred":[
        "Pakol"
    ],
    "name:pus_x_preferred":[
        "\u067e\u06a9\u0648\u0644"
    ],
    "name:rus_x_preferred":[
        "\u041f\u0430\u043a\u043e\u043b\u044c"
    ],
    "name:spa_x_preferred":[
        "Pakul"
    ],
    "name:ukr_x_preferred":[
        "\u041f\u0430\u043a\u043e\u043b\u044c"
    ],
    "name:urd_x_preferred":[
        "\u067e\u06a9\u0648\u0644"
    ],
    "wof:lang_x_official":[
        "ind"
    ],
    "wof:lang_x_spoken":[
        "ind",
        "eng"
    ],
    "wof:name":"Pakol",
    "wof:placetype":"locality"
},
  "geometry": {"coordinates":[110.83389,-8.11694],"type":"Point"}
}