{
  "type": "Feature",
  "properties": {
    "gn:admin1_code":"7.0",
    "gn:asciiname":"Pakol",
    "gn:country_code":"ID",
    "gn:dem":298,
    "gn:feature_class":"P",
    "gn:feature_code":"PPL",
    "gn:name":"Pakol",
    "gn:population":0,
    "gn:timezone":"Asia/Jakarta",
    "iso:country":"ID",
    "name:ind_x_preferred":[
        "Pakol"
    ],
    "wof:name":"Pakol",
    "wof:placetype":"locality"
},
  "geometry": {"coordinates":[110.83389,-8.11694],"type":"Point"}
}