{
  "type": "Feature",
  "properties": {
    "gn:admin1_code":"14",
    "gn:asciiname":"Gunungsari Ilir",
    "gn:country_code":"ID",
    "gn:dem":12,
    "gn:feature_class":"P",
    "gn:feature_code":"PPL",
    "gn:name":"Gunungsari Ilir",
    "gn:population":0,
    "gn:timezone":"Asia/Makassar",
    "iso:country":"ID",
    "name:ind_x_preferred":[
        "Gunungsari Ilir"
    ],
    "wof:name":"Gunungsari Ilir",
    "wof:placetype":"locality"
},
  "geometry": {"coordinates":[116.83880000000001,-1.27],"type":"Point"}
}