{
  "type": "Feature",
  "properties": {
    "gn:admin1_code":"07",
    "gn:asciiname":"Kado",
    "gn:country_code":"ID",
    "gn:dem":391,
    "gn:feature_class":"P",
    "gn:feature_code":"PPL",
    "gn:name":"Kado",
    "gn:population":0,
    "gn:timezone":"Asia/Jakarta",
    "iso:country":"ID",
    "name:ceb_x_preferred":[
        "Kado"
    ],
    "name:deu_x_preferred":[
        "Kado"
    ],
    "name:epo_x_preferred":[
        "Kado"
    ],
    "name:fra_x_preferred":[
        "Kado"
    ],
    "name:rus_x_preferred":[
        "\u041a\u0430\u0434\u043e"
    ],
    "name:srp_x_preferred":[
        "\u041a\u0430\u0434\u043e"
    ],
    "name:swe_x_preferred":[
        "Kado"
    ],
    "wof:lang_x_official":[
        "ind"
    ],
    "wof:lang_x_spoken":[
        "ind",
        "eng"
    ],
    "wof:name":"Kado",
    "wof:placetype":"locality"
},
  "geometry": {"coordinates":[110.59389,-7.58278],"type":"Point"}
}