{
  "type": "Feature",
  "properties": {
    "gn:admin1_code":"30",
    "gn:asciiname":"Parigi Lebak",
    "gn:country_code":"ID",
    "gn:dem":340,
    "gn:feature_class":"P",
    "gn:feature_code":"PPL",
    "gn:name":"Parigi Lebak",
    "gn:population":0,
    "gn:timezone":"Asia/Jakarta",
    "iso:country":"ID",
    "name:ind_x_preferred":[
        "Parigi Lebak"
    ],
    "wof:name":"Parigi Lebak",
    "wof:placetype":"locality"
},
  "geometry": {"coordinates":[106.51888999999998,-6.59583],"type":"Point"}
}