{
  "type": "Feature",
  "properties": {
    "gn:admin1_code":"30",
    "gn:asciiname":"Cikawoan",
    "gn:country_code":"ID",
    "gn:dem":204,
    "gn:feature_class":"P",
    "gn:feature_code":"PPL",
    "gn:name":"Cikawoan",
    "gn:population":0,
    "gn:timezone":"Asia/Jakarta",
    "iso:country":"ID",
    "name:ind_x_preferred":[
        "Cikawoan"
    ],
    "wof:name":"Cikawoan",
    "wof:placetype":"locality"
},
  "geometry": {"coordinates":[108.21611,-6.90583],"type":"Point"}
}