{
  "type": "Feature",
  "properties": {
    "gn:admin1_code":"1",
    "gn:asciiname":"Meunasah Kumbang",
    "gn:country_code":"ID",
    "gn:dem":8,
    "gn:feature_class":"P",
    "gn:feature_code":"PPL",
    "gn:name":"Meunasah Kumbang",
    "gn:population":0,
    "gn:timezone":"Asia/Jakarta",
    "iso:country":"ID",
    "name:ind_x_preferred":[
        "Meunasah Kumbang"
    ],
    "wof:name":"Meunasah Kumbang",
    "wof:placetype":"locality"
},
  "geometry": {"coordinates":[97.2595,5.1347],"type":"Point"}
}