{
  "type": "Feature",
  "properties": {
    "gn:admin1_code":"30.0",
    "gn:asciiname":"Cibulan",
    "gn:country_code":"ID",
    "gn:dem":502,
    "gn:feature_class":"P",
    "gn:feature_code":"PPL",
    "gn:name":"Cibulan",
    "gn:population":0,
    "gn:timezone":"Asia/Jakarta",
    "iso:country":"ID",
    "name:ind_x_preferred":[
        "Cibulan"
    ],
    "name:und_x_variant":[
        "Tjiboeboehan 2"
    ],
    "wof:name":"Cibulan",
    "wof:placetype":"locality"
},
  "geometry": {"coordinates":[108.2171,-7.2545],"type":"Point"}
}