{
  "type": "Feature",
  "properties": {
    "gn:admin1_code":"7.0",
    "gn:asciiname":"Magersari",
    "gn:country_code":"ID",
    "gn:dem":928,
    "gn:feature_class":"P",
    "gn:feature_code":"PPL",
    "gn:name":"Magersari",
    "gn:population":0,
    "gn:timezone":"Asia/Jakarta",
    "iso:country":"ID",
    "wof:name":"Magersari",
    "wof:placetype":"locality"
},
  "geometry": {"coordinates":[110.34583000000001,-7.41472],"type":"Point"}
}