{
  "type": "Feature",
  "properties": {
    "gn:admin1_code":"18",
    "gn:asciiname":"Kataka",
    "gn:country_code":"ID",
    "gn:dem":27,
    "gn:feature_class":"P",
    "gn:feature_code":"PPL",
    "gn:name":"Kataka",
    "gn:population":0,
    "gn:timezone":"Asia/Makassar",
    "iso:country":"ID",
    "name:ceb_x_preferred":[
        "Kataka"
    ],
    "name:ind_x_preferred":[
        "Kataka"
    ],
    "name:swe_x_preferred":[
        "Kataka"
    ],
    "wof:name":"Kataka",
    "wof:placetype":"locality"
},
  "geometry": {"coordinates":[120.1168,-10.1807],"type":"Point"}
}