{
  "type": "Feature",
  "properties": {
    "gn:admin1_code":"17",
    "gn:asciiname":"Bolen Barat",
    "gn:country_code":"ID",
    "gn:dem":605,
    "gn:feature_class":"P",
    "gn:feature_code":"PPL",
    "gn:name":"Bolen Barat",
    "gn:population":0,
    "gn:timezone":"Asia/Makassar",
    "iso:country":"ID",
    "name:ind_x_preferred":[
        "Bolen Barat"
    ],
    "wof:name":"Bolen Barat",
    "wof:placetype":"locality"
},
  "geometry": {"coordinates":[116.441,-8.5472],"type":"Point"}
}