{
  "type": "Feature",
  "properties": {
    "gn:country":"ID",
    "gn:fcode":"PPL",
    "gn:pop":75,
    "iso:country":"ID",
    "name:eng_x_preferred":[
        "Districts of Lampung"
    ],
    "qs:name":"Pasir Bungur",
    "qs:photos_9r":0,
    "qs:photos_sr":0,
    "qs:pop_sr":"1",
    "wd:wordcount":669,
    "wof:name":"Pasir Bungur",
    "wof:placetype":"locality",
    "wof:population":75
},
  "geometry": {"coordinates":[108.41625999999999,-7.20002],"type":"Point"}
}