{
  "type": "Feature",
  "properties": {
    "gn:admin1_code":"8.0",
    "gn:asciiname":"Mojorejo",
    "gn:country_code":"ID",
    "gn:dem":396,
    "gn:feature_class":"P",
    "gn:feature_code":"PPLA4",
    "gn:name":"Mojorejo",
    "gn:population":0,
    "gn:timezone":"Asia/Jakarta",
    "iso:country":"ID",
    "name:ind_x_preferred":[
        "Mojorejo"
    ],
    "wof:name":"Mojorejo",
    "wof:placetype":"locality"
},
  "geometry": {"coordinates":[112.3558,-8.2609],"type":"Point"}
}