{
  "type": "Feature",
  "properties": {
    "gn:admin1_code":"18.0",
    "gn:asciiname":"Naukae",
    "gn:country_code":"ID",
    "gn:dem":857,
    "gn:feature_class":"P",
    "gn:feature_code":"PPLA4",
    "gn:name":"Naukae",
    "gn:population":0,
    "gn:timezone":"Asia/Makassar",
    "iso:country":"ID",
    "name:ind_x_preferred":[
        "Naukae"
    ],
    "wof:lang_x_official":[
        "ind"
    ],
    "wof:lang_x_spoken":[
        "ind",
        "eng"
    ],
    "wof:name":"Naukae",
    "wof:placetype":"locality"
},
  "geometry": {"coordinates":[124.43125999999999,-9.82487],"type":"Point"}
}