{
  "type": "Feature",
  "properties": {
    "gn:admin1_code":"30",
    "gn:asciiname":"Kartajaya",
    "gn:country_code":"ID",
    "gn:dem":15,
    "gn:feature_class":"P",
    "gn:feature_code":"PPL",
    "gn:name":"Kartajaya",
    "gn:population":0,
    "gn:timezone":"Asia/Jakarta",
    "iso:country":"ID",
    "name:ind_x_preferred":[
        "Kartajaya"
    ],
    "wof:name":"Kartajaya",
    "wof:placetype":"locality"
},
  "geometry": {"coordinates":[108.05278,-6.43583],"type":"Point"}
}