{
  "type": "Feature",
  "properties": {
    "gn:admin1_code":"31.0",
    "gn:asciiname":"Pindolili",
    "gn:country_code":"ID",
    "gn:dem":52,
    "gn:feature_class":"P",
    "gn:feature_code":"PPL",
    "gn:name":"Pindolili",
    "gn:population":0,
    "gn:timezone":"Asia/Makassar",
    "iso:country":"ID",
    "name:ind_x_preferred":[
        "Pindolili"
    ],
    "wof:name":"Pindolili",
    "wof:placetype":"locality"
},
  "geometry": {"coordinates":[124.0277,0.8323],"type":"Point"}
}