{
  "type": "Feature",
  "properties": {
    "gn:admin1_code":"07",
    "gn:asciiname":"Gejagan",
    "gn:country_code":"ID",
    "gn:dem":964,
    "gn:feature_class":"P",
    "gn:feature_code":"PPL",
    "gn:name":"Gejagan",
    "gn:population":0,
    "gn:timezone":"Asia/Jakarta",
    "iso:country":"ID",
    "name:und_x_variant":[
        "Kedjajan 2",
        "Kejayan Dua",
        "Gejagan"
    ],
    "wof:name":"Gejagan",
    "wof:placetype":"locality"
},
  "geometry": {"coordinates":[110.35056000000002,-7.46306],"type":"Point"}
}