{
  "type": "Feature",
  "properties": {
    "gn:admin1_code":"8.0",
    "gn:asciiname":"Prengguk",
    "gn:country_code":"ID",
    "gn:dem":105,
    "gn:feature_class":"P",
    "gn:feature_code":"PPL",
    "gn:name":"Prengguk",
    "gn:population":0,
    "gn:timezone":"Asia/Jakarta",
    "iso:country":"ID",
    "name:ind_x_preferred":[
        "Prengguk"
    ],
    "wof:name":"Prengguk",
    "wof:placetype":"locality"
},
  "geometry": {"coordinates":[111.4191,-7.9315],"type":"Point"}
}