{
  "type": "Feature",
  "properties": {
    "gn:admin1_code":"7.0",
    "gn:asciiname":"Dekoro",
    "gn:country_code":"ID",
    "gn:dem":380,
    "gn:feature_class":"P",
    "gn:feature_code":"PPL",
    "gn:name":"Dekoro",
    "gn:population":0,
    "gn:timezone":"Asia/Jakarta",
    "iso:country":"ID",
    "wof:name":"Dekoro",
    "wof:placetype":"locality"
},
  "geometry": {"coordinates":[110.19528,-7.47889],"type":"Point"}
}