{
  "type": "Feature",
  "properties": {
    "gn:admin1_code":"10",
    "gn:asciiname":"Slametan",
    "gn:country_code":"ID",
    "gn:dem":180,
    "gn:feature_class":"P",
    "gn:feature_code":"PPL",
    "gn:name":"Slametan",
    "gn:population":0,
    "gn:timezone":"Asia/Jakarta",
    "iso:country":"ID",
    "name:ind_x_preferred":[
        "Selamatan"
    ],
    "name:jav_x_preferred":[
        "Kendhuri"
    ],
    "name:nld_x_preferred":[
        "Slametan"
    ],
    "wof:name":"Slametan",
    "wof:placetype":"locality"
},
  "geometry": {"coordinates":[110.66306000000002,-7.975],"type":"Point"}
}