{
  "type": "Feature",
  "properties": {
    "gn:admin1_code":"30",
    "gn:asciiname":"Kordon",
    "gn:country_code":"ID",
    "gn:dem":887,
    "gn:feature_class":"P",
    "gn:feature_code":"PPL",
    "gn:name":"Kordon",
    "gn:population":0,
    "gn:timezone":"Asia/Jakarta",
    "iso:country":"ID",
    "name:ceb_x_preferred":[
        "Kordon"
    ],
    "name:deu_x_preferred":[
        "Kordon"
    ],
    "name:ind_x_preferred":[
        "Kordon"
    ],
    "name:pol_x_preferred":[
        "Kordon"
    ],
    "name:rus_x_preferred":[
        "\u041a\u043e\u0440\u0434\u043e\u043d"
    ],
    "name:tur_x_preferred":[
        "Kordon"
    ],
    "name:ukr_x_preferred":[
        "\u041a\u043e\u0440\u0434\u043e\u043d"
    ],
    "wof:lang_x_official":[
        "ind"
    ],
    "wof:lang_x_spoken":[
        "ind",
        "eng"
    ],
    "wof:name":"Kordon",
    "wof:placetype":"locality"
},
  "geometry": {"coordinates":[107.62472,-6.86306],"type":"Point"}
}