{
  "type": "Feature",
  "properties": {
    "gn:admin1_code":"14",
    "gn:asciiname":"Transmigrasi Kayen Satu",
    "gn:country_code":"ID",
    "gn:dem":14,
    "gn:feature_class":"P",
    "gn:feature_code":"PPL",
    "gn:name":"Transmigrasi Kayen Satu",
    "gn:population":0,
    "gn:timezone":"Asia/Makassar",
    "iso:country":"ID",
    "name:ind_x_preferred":[
        "Transmigrasi Kayen Satu"
    ],
    "wof:name":"Transmigrasi Kayen Satu",
    "wof:placetype":"locality"
},
  "geometry": {"coordinates":[116.2102,-1.5881],"type":"Point"}
}