{
  "type": "Feature",
  "properties": {
    "gn:admin1_code":"38",
    "gn:asciiname":"Ammerrung",
    "gn:country_code":"ID",
    "gn:dem":660,
    "gn:feature_class":"P",
    "gn:feature_code":"PPL",
    "gn:name":"Ammerrung",
    "gn:population":0,
    "gn:timezone":"Asia/Makassar",
    "iso:country":"ID",
    "name:ind_x_preferred":[
        "Ammerrung"
    ],
    "name:und_x_variant":[
        "Amerung"
    ],
    "wof:lang_x_official":[
        "ind"
    ],
    "wof:lang_x_spoken":[
        "ind",
        "eng"
    ],
    "wof:name":"Ammerrung",
    "wof:placetype":"locality"
},
  "geometry": {"coordinates":[119.753,-4.6037],"type":"Point"}
}