{
  "type": "Feature",
  "properties": {
    "gn:admin1_code":"15.0",
    "gn:asciiname":"Masgar Bumiagung",
    "gn:country_code":"ID",
    "gn:dem":63,
    "gn:feature_class":"P",
    "gn:feature_code":"PPL",
    "gn:name":"Masgar Bumiagung",
    "gn:population":0,
    "gn:timezone":"Asia/Jakarta",
    "iso:country":"ID",
    "name:ind_x_preferred":[
        "Masgar Bumiagung"
    ],
    "wof:name":"Masgar Bumiagung",
    "wof:placetype":"locality"
},
  "geometry": {"coordinates":[105.18201000000001,-5.15542],"type":"Point"}
}