{
  "type": "Feature",
  "properties": {
    "gn:admin1_code":"30",
    "gn:asciiname":"Puhun",
    "gn:country_code":"ID",
    "gn:dem":226,
    "gn:feature_class":"P",
    "gn:feature_code":"PPL",
    "gn:name":"Puhun",
    "gn:population":0,
    "gn:timezone":"Asia/Jakarta",
    "iso:country":"ID",
    "name:ind_x_preferred":[
        "Puhun"
    ],
    "wof:name":"Puhun",
    "wof:placetype":"locality"
},
  "geometry": {"coordinates":[108.58029999999999,-6.9672],"type":"Point"}
}