{
  "type": "Feature",
  "properties": {
    "gn:admin1_code":"30",
    "gn:asciiname":"Sangkan",
    "gn:country_code":"ID",
    "gn:dem":942,
    "gn:feature_class":"P",
    "gn:feature_code":"PPL",
    "gn:name":"Sangkan",
    "gn:population":0,
    "gn:timezone":"Asia/Jakarta",
    "iso:country":"ID",
    "name:ind_x_preferred":[
        "Sangkan"
    ],
    "wof:name":"Sangkan",
    "wof:placetype":"locality"
},
  "geometry": {"coordinates":[107.7723,-7.1019],"type":"Point"}
}