{
  "type": "Feature",
  "properties": {
    "gn:admin1_code":"24",
    "gn:asciiname":"Balai",
    "gn:country_code":"ID",
    "gn:dem":145,
    "gn:feature_class":"P",
    "gn:feature_code":"PPL",
    "gn:name":"Balai",
    "gn:population":0,
    "gn:timezone":"Asia/Jakarta",
    "iso:country":"ID",
    "name:ind_x_preferred":[
        "Balai"
    ],
    "name:mar_x_preferred":[
        "\u092c\u0932\u093e\u0908"
    ],
    "wof:name":"Balai",
    "wof:placetype":"locality"
},
  "geometry": {"coordinates":[100.09511999999999,-0.12012],"type":"Point"}
}