{
  "type": "Feature",
  "properties": {
    "gn:admin1_code":"7.0",
    "gn:asciiname":"Lungge Satu",
    "gn:country_code":"ID",
    "gn:dem":493,
    "gn:feature_class":"P",
    "gn:feature_code":"PPL",
    "gn:name":"Lungge Satu",
    "gn:population":0,
    "gn:timezone":"Asia/Jakarta",
    "iso:country":"ID",
    "wof:name":"Lungge Satu",
    "wof:placetype":"locality"
},
  "geometry": {"coordinates":[110.20083,-7.3475],"type":"Point"}
}