{
  "type": "Feature",
  "properties": {
    "gn:admin1_code":"26",
    "gn:asciiname":"Ajerpanas",
    "gn:country_code":"ID",
    "gn:dem":813,
    "gn:feature_class":"P",
    "gn:feature_code":"PPL",
    "gn:name":"Ajerpanas",
    "gn:population":0,
    "gn:timezone":"Asia/Jakarta",
    "iso:country":"ID",
    "name:ind_x_preferred":[
        "Ajerpanas"
    ],
    "wof:name":"Ajerpanas",
    "wof:placetype":"locality"
},
  "geometry": {"coordinates":[97.62139999999999,3.768],"type":"Point"}
}