{
  "type": "Feature",
  "properties": {
    "gn:admin1_code":"0.0",
    "gn:asciiname":"Daule",
    "gn:cc2":"ID",
    "gn:country_code":"ID",
    "gn:dem":0,
    "gn:feature_class":"P",
    "gn:feature_code":"PPL",
    "gn:name":"Daule",
    "gn:population":0,
    "gn:timezone":"Asia/Makassar",
    "iso:country":"ID",
    "name:ceb_x_preferred":[
        "Daule"
    ],
    "name:spa_x_preferred":[
        "Daule"
    ],
    "name:swe_x_preferred":[
        "Daule"
    ],
    "name:und_x_variant":[
        "Do\u00f3le",
        "Daoele",
        "Daole",
        "Daule"
    ],
    "wof:lang_x_official":[
        "ind"
    ],
    "wof:lang_x_spoken":[
        "ind",
        "eng"
    ],
    "wof:name":"Daule",
    "wof:placetype":"locality"
},
  "geometry": {"coordinates":[122.01667,-4.68333],"type":"Point"}
}