{
  "type": "Feature",
  "properties": {
    "gn:admin1_code":"30.0",
    "gn:asciiname":"Citeureup",
    "gn:country_code":"ID",
    "gn:dem":494,
    "gn:feature_class":"P",
    "gn:feature_code":"PPL",
    "gn:name":"Citeureup",
    "gn:population":0,
    "gn:timezone":"Asia/Jakarta",
    "iso:country":"ID",
    "name:ind_x_preferred":[
        "Citeureup"
    ],
    "wof:name":"Citeureup",
    "wof:placetype":"locality"
},
  "geometry": {"coordinates":[108.1639,-7.2449],"type":"Point"}
}