{
  "type": "Feature",
  "properties": {
    "gn:admin1_code":"8",
    "gn:asciiname":"Sidomoro",
    "gn:country_code":"ID",
    "gn:dem":17,
    "gn:feature_class":"P",
    "gn:feature_code":"PPL",
    "gn:name":"Sidomoro",
    "gn:population":0,
    "gn:timezone":"Asia/Jakarta",
    "iso:country":"ID",
    "name:ind_x_preferred":[
        "Sidomoro"
    ],
    "wof:name":"Sidomoro",
    "wof:placetype":"locality"
},
  "geometry": {"coordinates":[112.56610000000001,-7.3913],"type":"Point"}
}