{
  "type": "Feature",
  "properties": {
    "gn:admin1_code":"7",
    "gn:asciiname":"Tlogowungu",
    "gn:country_code":"ID",
    "gn:dem":207,
    "gn:feature_class":"P",
    "gn:feature_code":"PPL",
    "gn:name":"Tlogowungu",
    "gn:population":0,
    "gn:timezone":"Asia/Jakarta",
    "iso:country":"ID",
    "name:ind_x_preferred":[
        "Tlogowungu"
    ],
    "wof:name":"Tlogowungu",
    "wof:placetype":"locality"
},
  "geometry": {"coordinates":[109.93559999999999,-6.9711],"type":"Point"}
}