{
  "type": "Feature",
  "properties": {
    "gn:admin1_code":"7",
    "gn:asciiname":"Kentongan",
    "gn:country_code":"ID",
    "gn:dem":677,
    "gn:feature_class":"P",
    "gn:feature_code":"PPL",
    "gn:name":"Kentongan",
    "gn:population":0,
    "gn:timezone":"Asia/Jakarta",
    "iso:country":"ID",
    "name:ind_x_preferred":[
        "Kentongan"
    ],
    "wof:name":"Kentongan",
    "wof:placetype":"locality"
},
  "geometry": {"coordinates":[111.12083,-7.56139],"type":"Point"}
}