{
  "type": "Feature",
  "properties": {
    "gn:admin1_code":"33",
    "gn:asciiname":"Kupa",
    "gn:country_code":"ID",
    "gn:dem":218,
    "gn:feature_class":"P",
    "gn:feature_code":"PPL",
    "gn:name":"Kupa",
    "gn:population":0,
    "gn:timezone":"Asia/Jakarta",
    "iso:country":"ID",
    "name:ara_x_preferred":[
        "\u0646\u0647\u0631 \u0643\u0648\u0628\u0627"
    ],
    "name:azb_x_preferred":[
        "\u06a9\u0648\u067e\u0627 \u0686\u0627\u06cc\u06cc"
    ],
    "name:bel_x_preferred":[
        "\u041a\u0443\u043f\u0430"
    ],
    "name:bos_x_preferred":[
        "Kupa"
    ],
    "name:bul_x_preferred":[
        "\u041a\u0443\u043f\u0430"
    ],
    "name:cat_x_preferred":[
        "Riu Kupa"
    ],
    "name:ces_x_preferred":[
        "Kupa"
    ],
    "name:deu_x_preferred":[
        "Kupa"
    ],
    "name:ell_x_preferred":[
        "\u039a\u03bf\u03cd\u03c0\u03b1 \u03c0\u03bf\u03c4\u03b1\u03bc\u03cc\u03c2"
    ],
    "name:epo_x_preferred":[
        "Kupa"
    ],
    "name:est_x_preferred":[
        "Kupa"
    ],
    "name:eus_x_preferred":[
        "Kupa"
    ],
    "name:fas_x_preferred":[
        "\u06a9\u0648\u067e\u0627"
    ],
    "name:fin_x_preferred":[
        "Kupa"
    ],
    "name:fra_x_preferred":[
        "Kupa"
    ],
    "name:hrv_x_preferred":[
        "Kupa"
    ],
    "name:hun_x_preferred":[
        "Kulpa"
    ],
    "name:ind_x_preferred":[
        "Kupa"
    ],
    "name:ita_x_preferred":[
        "Kupa"
    ],
    "name:jpn_x_preferred":[
        "\u30af\u30d1\u5ddd"
    ],
    "name:kor_x_preferred":[
        "\ucfe0\ud30c\uac15"
    ],
    "name:lit_x_preferred":[
        "Kupa"
    ],
    "name:mkd_x_preferred":[
        "\u041a\u0443\u043f\u0430"
    ],
    "name:nld_x_preferred":[
        "Kupa"
    ],
    "name:nno_x_preferred":[
        "Kupa"
    ],
    "name:nor_x_preferred":[
        "Kupa"
    ],
    "name:pol_x_preferred":[
        "Kupa"
    ],
    "name:rus_x_preferred":[
        "\u041a\u0443\u043f\u0430"
    ],
    "name:slk_x_preferred":[
        "Kupa"
    ],
    "name:slv_x_preferred":[
        "Kolpa"
    ],
    "name:spa_x_preferred":[
        "R\u00edo Kolpa"
    ],
    "name:srp_x_preferred":[
        "\u041a\u0443\u043f\u0430"
    ],
    "name:swe_x_preferred":[
        "Kupa"
    ],
    "name:tur_x_preferred":[
        "Kupa Nehri"
    ],
    "name:ukr_x_preferred":[
        "\u041a\u0443\u043f\u0430"
    ],
    "name:zho_x_preferred":[
        "\u5eab\u5e15\u6cb3"
    ],
    "wof:lang_x_official":[
        "ind"
    ],
    "wof:lang_x_spoken":[
        "ind",
        "eng"
    ],
    "wof:name":"Kupa",
    "wof:placetype":"locality"
},
  "geometry": {"coordinates":[105.9661,-6.0971],"type":"Point"}
}