{
  "type": "Feature",
  "properties": {
    "gn:admin1_code":"26",
    "gn:asciiname":"Tebingtanjung Slamet",
    "gn:country_code":"ID",
    "gn:dem":22,
    "gn:feature_class":"P",
    "gn:feature_code":"PPL",
    "gn:name":"Tebingtanjung Slamet",
    "gn:population":0,
    "gn:timezone":"Asia/Jakarta",
    "iso:country":"ID",
    "name:ind_x_preferred":[
        "Tebingtanjung Slamet"
    ],
    "wof:name":"Tebingtanjung Slamet",
    "wof:placetype":"locality"
},
  "geometry": {"coordinates":[98.2693,3.7598],"type":"Point"}
}