{
  "type": "Feature",
  "properties": {
    "gn:admin1_code":"30",
    "gn:asciiname":"Waas Wetan",
    "gn:country_code":"ID",
    "gn:dem":374,
    "gn:feature_class":"P",
    "gn:feature_code":"PPL",
    "gn:name":"Waas Wetan",
    "gn:population":0,
    "gn:timezone":"Asia/Jakarta",
    "iso:country":"ID",
    "name:ind_x_preferred":[
        "Waas Wetan"
    ],
    "wof:name":"Waas Wetan",
    "wof:placetype":"locality"
},
  "geometry": {"coordinates":[107.17083,-6.81167],"type":"Point"}
}