{
  "type": "Feature",
  "properties": {
    "gn:admin1_code":"4.0",
    "gn:asciiname":"Lentengagung",
    "gn:country_code":"ID",
    "gn:dem":47,
    "gn:feature_class":"P",
    "gn:feature_code":"PPL",
    "gn:name":"Lentengagung",
    "gn:population":0,
    "gn:timezone":"Asia/Jakarta",
    "iso:country":"ID",
    "name:ind_x_preferred":[
        "Lentengagung"
    ],
    "name:und_x_variant":[
        "Lentengagoeng",
        "Lentangagung",
        "Lentang-agoeng"
    ],
    "wof:lang_x_official":[
        "ind"
    ],
    "wof:lang_x_spoken":[
        "ind",
        "eng"
    ],
    "wof:name":"Lentengagung",
    "wof:placetype":"locality"
},
  "geometry": {"coordinates":[106.8361,-6.3249],"type":"Point"}
}