{
  "type": "Feature",
  "properties": {
    "gn:admin1_code":"15.0",
    "gn:asciiname":"Sukabumi",
    "gn:country_code":"ID",
    "gn:dem":268,
    "gn:feature_class":"P",
    "gn:feature_code":"PPL",
    "gn:name":"Sukabumi",
    "gn:population":0,
    "gn:timezone":"Asia/Jakarta",
    "iso:country":"ID",
    "name:ind_x_preferred":[
        "Sukabumi"
    ],
    "wof:name":"Sukabumi",
    "wof:placetype":"locality"
},
  "geometry": {"coordinates":[104.77735,-5.37508],"type":"Point"}
}