{
  "type": "Feature",
  "properties": {
    "gn:admin1_code":"21.0",
    "gn:asciiname":"Lewanu",
    "gn:country_code":"ID",
    "gn:dem":13,
    "gn:feature_class":"P",
    "gn:feature_code":"PPL",
    "gn:name":"Lewanu",
    "gn:population":0,
    "gn:timezone":"Asia/Makassar",
    "iso:country":"ID",
    "name:ind_x_preferred":[
        "Lewanu"
    ],
    "wof:name":"Lewanu",
    "wof:placetype":"locality"
},
  "geometry": {"coordinates":[119.7067,-0.1388],"type":"Point"}
}