{
  "type": "Feature",
  "properties": {
    "gn:admin1_code":"30.0",
    "gn:asciiname":"Patrol",
    "gn:country_code":"ID",
    "gn:dem":760,
    "gn:feature_class":"P",
    "gn:feature_code":"PPL",
    "gn:name":"Patrol",
    "gn:population":0,
    "gn:timezone":"Asia/Jakarta",
    "iso:country":"ID",
    "name:ind_x_preferred":[
        "Patrol"
    ],
    "name:und_x_variant":[
        "Patrol Dua"
    ],
    "wof:name":"Patrol",
    "wof:placetype":"locality"
},
  "geometry": {"coordinates":[108.3984,-7.0418],"type":"Point"}
}