{
  "type": "Feature",
  "properties": {
    "gn:admin1_code":"30.0",
    "gn:asciiname":"Patrol",
    "gn:country_code":"ID",
    "gn:dem":760,
    "gn:feature_class":"P",
    "gn:feature_code":"PPL",
    "gn:name":"Patrol",
    "gn:population":0,
    "gn:timezone":"Asia/Jakarta",
    "iso:country":"ID",
    "name:deu_x_preferred":[
        "Streifendienst"
    ],
    "name:ell_x_preferred":[
        "\u03a0\u03b5\u03c1\u03af\u03c0\u03bf\u03bb\u03bf\u03c2"
    ],
    "name:fas_x_preferred":[
        "\u06af\u0634\u062a"
    ],
    "name:hye_x_preferred":[
        "\u054a\u0561\u0580\u0565\u056f"
    ],
    "name:ind_x_preferred":[
        "Patrol"
    ],
    "name:ind_x_variant":[
        "Patroli"
    ],
    "name:kaz_x_preferred":[
        "\u041f\u0430\u0442\u0440\u0443\u043b\u044c"
    ],
    "name:nor_x_preferred":[
        "Patrulje"
    ],
    "name:pol_x_preferred":[
        "Zast\u0119p"
    ],
    "name:por_x_preferred":[
        "Patrulha"
    ],
    "name:rus_x_preferred":[
        "\u041f\u0430\u0442\u0440\u0443\u043b\u044c"
    ],
    "name:swe_x_preferred":[
        "Patrull"
    ],
    "name:ukr_x_preferred":[
        "\u041f\u0430\u0442\u0440\u0443\u043b\u044c"
    ],
    "name:und_x_variant":[
        "Patrol Dua"
    ],
    "wof:lang_x_official":[
        "ind"
    ],
    "wof:lang_x_spoken":[
        "ind",
        "eng"
    ],
    "wof:name":"Patrol",
    "wof:placetype":"locality"
},
  "geometry": {"coordinates":[108.3984,-7.0418],"type":"Point"}
}