{
  "type": "Feature",
  "properties": {
    "gn:admin1_code":"1",
    "gn:asciiname":"Blang Reu",
    "gn:country_code":"ID",
    "gn:dem":11,
    "gn:feature_class":"P",
    "gn:feature_code":"PPL",
    "gn:name":"Blang Reu",
    "gn:population":0,
    "gn:timezone":"Asia/Jakarta",
    "iso:country":"ID",
    "name:ind_x_preferred":[
        "Blang Reu"
    ],
    "wof:name":"Blang Reu",
    "wof:placetype":"locality"
},
  "geometry": {"coordinates":[97.309,5.1589],"type":"Point"}
}