{
  "type": "Feature",
  "properties": {
    "gn:admin1_code":"32.0",
    "gn:asciiname":"Talang Bendi",
    "gn:country_code":"ID",
    "gn:dem":313,
    "gn:feature_class":"P",
    "gn:feature_code":"PPL",
    "gn:name":"Talang Bendi",
    "gn:population":0,
    "gn:timezone":"Asia/Jakarta",
    "iso:country":"ID",
    "name:ind_x_preferred":[
        "Talang Bendi"
    ],
    "name:und_x_variant":[
        "Kebubendi"
    ],
    "wof:lang_x_official":[
        "ind"
    ],
    "wof:lang_x_spoken":[
        "ind",
        "eng"
    ],
    "wof:name":"Talang Bendi",
    "wof:placetype":"locality"
},
  "geometry": {"coordinates":[104.05546,-4.65177],"type":"Point"}
}