{
  "type": "Feature",
  "properties": {
    "gn:admin1_code":"30.0",
    "gn:asciiname":"Cinyenang",
    "gn:country_code":"ID",
    "gn:dem":162,
    "gn:feature_class":"P",
    "gn:feature_code":"PPL",
    "gn:name":"Cinyenang",
    "gn:population":0,
    "gn:timezone":"Asia/Jakarta",
    "iso:country":"ID",
    "name:ind_x_preferred":[
        "Cinyenang"
    ],
    "name:und_x_variant":[
        "Tjitjenang"
    ],
    "wof:name":"Cinyenang",
    "wof:placetype":"locality"
},
  "geometry": {"coordinates":[108.4657,-7.3031],"type":"Point"}
}