{
  "type": "Feature",
  "properties": {
    "gn:admin1_code":"8.0",
    "gn:asciiname":"Brambang",
    "gn:country_code":"ID",
    "gn:dem":65,
    "gn:feature_class":"P",
    "gn:feature_code":"PPL",
    "gn:name":"Brambang",
    "gn:population":0,
    "gn:timezone":"Asia/Jakarta",
    "iso:country":"ID",
    "name:ind_x_preferred":[
        "Brambang"
    ],
    "wof:name":"Brambang",
    "wof:placetype":"locality"
},
  "geometry": {"coordinates":[111.94459999999999,-7.714],"type":"Point"}
}