{
  "type": "Feature",
  "properties": {
    "gn:admin1_code":"30.0",
    "gn:asciiname":"Rawamerta",
    "gn:country_code":"ID",
    "gn:dem":8,
    "gn:feature_class":"P",
    "gn:feature_code":"PPL",
    "gn:name":"Rawamerta",
    "gn:population":0,
    "gn:timezone":"Asia/Jakarta",
    "iso:country":"ID",
    "name:und_x_variant":[
        "Soekamerta",
        "Rawainerta",
        "Rawamerta"
    ],
    "wof:name":"Rawamerta",
    "wof:placetype":"locality"
},
  "geometry": {"coordinates":[107.38249999999999,-6.22861],"type":"Point"}
}