{
  "type": "Feature",
  "properties": {
    "gn:admin1_code":"30.0",
    "gn:asciiname":"Gunung Rosa",
    "gn:country_code":"ID",
    "gn:dem":991,
    "gn:feature_class":"P",
    "gn:feature_code":"PPL",
    "gn:name":"Gunung Rosa",
    "gn:population":0,
    "gn:timezone":"Asia/Jakarta",
    "iso:country":"ID",
    "name:ind_x_preferred":[
        "Gunung Rosa"
    ],
    "name:und_x_variant":[
        "Goenoengrosa"
    ],
    "wof:lang_x_official":[
        "ind"
    ],
    "wof:lang_x_spoken":[
        "ind",
        "eng"
    ],
    "wof:name":"Gunung Rosa",
    "wof:placetype":"locality"
},
  "geometry": {"coordinates":[107.08799999999999,-7.0103],"type":"Point"}
}