{
  "type": "Feature",
  "properties": {
    "gn:admin1_code":"8.0",
    "gn:asciiname":"Kletak",
    "gn:country_code":"ID",
    "gn:dem":423,
    "gn:feature_class":"P",
    "gn:feature_code":"PPL",
    "gn:name":"Kletak",
    "gn:population":0,
    "gn:timezone":"Asia/Jakarta",
    "iso:country":"ID",
    "name:ind_x_preferred":[
        "Kletak"
    ],
    "wof:name":"Kletak",
    "wof:placetype":"locality"
},
  "geometry": {"coordinates":[111.9051,-7.8453],"type":"Point"}
}