{
  "type": "Feature",
  "properties": {
    "gn:admin1_code":"30.0",
    "gn:asciiname":"Caringin",
    "gn:country_code":"ID",
    "gn:dem":843,
    "gn:feature_class":"P",
    "gn:feature_code":"PPL",
    "gn:name":"Caringin",
    "gn:population":0,
    "gn:timezone":"Asia/Jakarta",
    "iso:country":"ID",
    "name:ind_x_preferred":[
        "Caringin"
    ],
    "wof:name":"Caringin",
    "wof:placetype":"locality"
},
  "geometry": {"coordinates":[107.95180000000001,-7.346],"type":"Point"}
}