{
  "type": "Feature",
  "properties": {
    "gn:admin1_code":"18.0",
    "gn:asciiname":"Tuadale",
    "gn:country_code":"ID",
    "gn:dem":22,
    "gn:feature_class":"P",
    "gn:feature_code":"PPL",
    "gn:name":"Tuadale",
    "gn:population":0,
    "gn:timezone":"Asia/Makassar",
    "iso:country":"ID",
    "name:ind_x_preferred":[
        "Tuadale"
    ],
    "wof:name":"Tuadale",
    "wof:placetype":"locality"
},
  "geometry": {"coordinates":[123.5068,-10.3239],"type":"Point"}
}