{
  "type": "Feature",
  "properties": {
    "gn:admin1_code":"22",
    "gn:asciiname":"Wuna",
    "gn:country_code":"ID",
    "gn:dem":37,
    "gn:feature_class":"P",
    "gn:feature_code":"PPL",
    "gn:name":"Wuna",
    "gn:population":0,
    "gn:timezone":"Asia/Makassar",
    "iso:country":"ID",
    "name:ind_x_preferred":[
        "Wuna"
    ],
    "wof:name":"Wuna",
    "wof:placetype":"locality"
},
  "geometry": {"coordinates":[122.52070000000001,-4.8274],"type":"Point"}
}