{
  "type": "Feature",
  "properties": {
    "gn:admin1_code":"14.0",
    "gn:asciiname":"Muara Bem-lelakidau",
    "gn:country_code":"ID",
    "gn:dem":713,
    "gn:feature_class":"P",
    "gn:feature_code":"PPL",
    "gn:name":"Muara Bem-lelakidau",
    "gn:population":0,
    "gn:timezone":"Asia/Makassar",
    "iso:country":"ID",
    "name:und_x_variant":[
        "Moeara Bem-lelakidau",
        "Moeara Bem Lakidau",
        "Muara Bem-lelakidau"
    ],
    "wof:lang_x_official":[
        "ind"
    ],
    "wof:lang_x_spoken":[
        "ind",
        "eng"
    ],
    "wof:name":"Muara Bem-lelakidau",
    "wof:placetype":"locality"
},
  "geometry": {"coordinates":[115.00402,1.70014],"type":"Point"}
}