{
  "type": "Feature",
  "properties": {
    "gn:admin1_code":"07",
    "gn:asciiname":"Karangbawang",
    "gn:country_code":"ID",
    "gn:dem":949,
    "gn:feature_class":"P",
    "gn:feature_code":"PPL",
    "gn:name":"Karangbawang",
    "gn:population":0,
    "gn:timezone":"Asia/Jakarta",
    "iso:country":"ID",
    "wof:name":"Karangbawang",
    "wof:placetype":"locality"
},
  "geometry": {"coordinates":[110.41056,-7.3325],"type":"Point"}
}