{
  "type": "Feature",
  "properties": {
    "gn:admin1_code":"30",
    "gn:asciiname":"Babakannangka",
    "gn:country_code":"ID",
    "gn:dem":76,
    "gn:feature_class":"P",
    "gn:feature_code":"PPL",
    "gn:name":"Babakannangka",
    "gn:population":0,
    "gn:timezone":"Asia/Jakarta",
    "iso:country":"ID",
    "name:ind_x_preferred":[
        "Babakannangka"
    ],
    "wof:name":"Babakannangka",
    "wof:placetype":"locality"
},
  "geometry": {"coordinates":[107.55667,-6.52306],"type":"Point"}
}