{
  "type": "Feature",
  "properties": {
    "gn:admin1_code":"26.0",
    "gn:asciiname":"Bandar",
    "gn:country_code":"ID",
    "gn:dem":926,
    "gn:feature_class":"P",
    "gn:feature_code":"PPL",
    "gn:name":"Bandar",
    "gn:population":0,
    "gn:timezone":"Asia/Jakarta",
    "iso:country":"ID",
    "name:ind_x_preferred":[
        "Bandar"
    ],
    "name:und_x_variant":[
        "Badar"
    ],
    "wof:name":"Bandar",
    "wof:placetype":"locality"
},
  "geometry": {"coordinates":[98.8856,2.7239],"type":"Point"}
}