{
  "type": "Feature",
  "properties": {
    "gn:admin1_code":"3.0",
    "gn:asciiname":"Bunutinggi",
    "gn:country_code":"ID",
    "gn:dem":140,
    "gn:feature_class":"P",
    "gn:feature_code":"PPL",
    "gn:name":"Bunutinggi",
    "gn:population":0,
    "gn:timezone":"Asia/Jakarta",
    "iso:country":"ID",
    "name:ind_x_preferred":[
        "Bunutinggi"
    ],
    "wof:name":"Bunutinggi",
    "wof:placetype":"locality"
},
  "geometry": {"coordinates":[102.7253,-4.1453],"type":"Point"}
}