{
  "type": "Feature",
  "properties": {
    "gn:admin1_code":"12",
    "gn:asciiname":"Manunggulama",
    "gn:country_code":"ID",
    "gn:dem":17,
    "gn:feature_class":"P",
    "gn:feature_code":"PPLA3",
    "gn:name":"Manunggulama",
    "gn:population":0,
    "gn:timezone":"Asia/Makassar",
    "iso:country":"ID",
    "name:ind_x_preferred":[
        "Manunggulama"
    ],
    "wof:name":"Manunggulama",
    "wof:placetype":"locality"
},
  "geometry": {"coordinates":[116.1656,-2.5142],"type":"Point"}
}