{
  "type": "Feature",
  "properties": {
    "gn:admin1_code":"7.0",
    "gn:asciiname":"Bulu",
    "gn:country_code":"ID",
    "gn:dem":173,
    "gn:feature_class":"P",
    "gn:feature_code":"PPL",
    "gn:name":"Bulu",
    "gn:population":0,
    "gn:timezone":"Asia/Jakarta",
    "iso:country":"ID",
    "name:ceb_x_preferred":[
        "Bulu"
    ],
    "name:deu_x_preferred":[
        "Bulu"
    ],
    "name:fra_x_preferred":[
        "Bulu"
    ],
    "name:ind_x_preferred":[
        "Bulu"
    ],
    "name:ita_x_preferred":[
        "Bulu"
    ],
    "name:nld_x_preferred":[
        "Bulu"
    ],
    "name:srp_x_preferred":[
        "\u0411\u0443\u043b\u0443"
    ],
    "name:swe_x_preferred":[
        "Bulu"
    ],
    "wof:lang_x_official":[
        "ind"
    ],
    "wof:lang_x_spoken":[
        "ind",
        "eng"
    ],
    "wof:name":"Bulu",
    "wof:placetype":"locality"
},
  "geometry": {"coordinates":[109.52,-7.3875],"type":"Point"}
}