{
  "type": "Feature",
  "properties": {
    "gn:admin1_code":"30",
    "gn:asciiname":"Krangganpasar",
    "gn:country_code":"ID",
    "gn:dem":77,
    "gn:feature_class":"P",
    "gn:feature_code":"PPL",
    "gn:name":"Krangganpasar",
    "gn:population":0,
    "gn:timezone":"Asia/Jakarta",
    "iso:country":"ID",
    "name:ind_x_preferred":[
        "Krangganpasar"
    ],
    "wof:name":"Krangganpasar",
    "wof:placetype":"locality"
},
  "geometry": {"coordinates":[106.9251,-6.3697],"type":"Point"}
}