{
  "type": "Feature",
  "properties": {
    "gn:admin1_code":"30.0",
    "gn:asciiname":"Indrahayu",
    "gn:country_code":"ID",
    "gn:dem":347,
    "gn:feature_class":"P",
    "gn:feature_code":"PPL",
    "gn:name":"Indrahayu",
    "gn:population":0,
    "gn:timezone":"Asia/Jakarta",
    "iso:country":"ID",
    "name:ind_x_preferred":[
        "Indrahayu"
    ],
    "name:und_x_variant":[
        "Indrakila"
    ],
    "wof:name":"Indrahayu",
    "wof:placetype":"locality"
},
  "geometry": {"coordinates":[108.68940000000001,-7.0893],"type":"Point"}
}