{
  "type": "Feature",
  "properties": {
    "gn:country":"ID",
    "gn:fcode":"PPL",
    "gn:pop":0,
    "iso:country":"ID",
    "name:eng_x_preferred":[
        "Samiran"
    ],
    "qs:name":"Samiran",
    "qs:name_adm0":"Indonesia",
    "qs:name_adm1":"Provinsi Jawa Tengah",
    "qs:photos":290,
    "qs:photos_1k":59,
    "qs:photos_9k":1,
    "qs:photos_9r":4,
    "qs:photos_all":290,
    "qs:photos_sr":5,
    "qs:placetype":"Town",
    "qs:pop_sr":"0",
    "wd:wordcount":24,
    "wof:lang_x_official":[
        "ind"
    ],
    "wof:lang_x_spoken":[
        "ind",
        "eng"
    ],
    "wof:name":"Samiran",
    "wof:placetype":"locality",
    "wof:population":0
},
  "geometry": {"coordinates":[110.46417,-7.50222],"type":"Point"}
}