{
  "type": "Feature",
  "properties": {
    "gn:admin1_code":"18.0",
    "gn:asciiname":"Oeketun",
    "gn:country_code":"ID",
    "gn:dem":543,
    "gn:feature_class":"P",
    "gn:feature_code":"PPL",
    "gn:name":"Oeketun",
    "gn:population":0,
    "gn:timezone":"Asia/Makassar",
    "iso:country":"ID",
    "name:ind_x_preferred":[
        "Oeketun"
    ],
    "wof:name":"Oeketun",
    "wof:placetype":"locality"
},
  "geometry": {"coordinates":[123.83920000000001,-10.2873],"type":"Point"}
}