{
  "type": "Feature",
  "properties": {
    "gn:admin1_code":"18.0",
    "gn:asciiname":"Oepiak",
    "gn:country_code":"ID",
    "gn:dem":138,
    "gn:feature_class":"P",
    "gn:feature_code":"PPL",
    "gn:name":"Oepiak",
    "gn:population":0,
    "gn:timezone":"Asia/Makassar",
    "iso:country":"ID",
    "name:ind_x_preferred":[
        "Oepiak"
    ],
    "wof:name":"Oepiak",
    "wof:placetype":"locality"
},
  "geometry": {"coordinates":[123.0424,-10.781],"type":"Point"}
}