{
  "type": "Feature",
  "properties": {
    "gn:admin1_code":"30.0",
    "gn:asciiname":"Pasirdatar",
    "gn:country_code":"ID",
    "gn:dem":250,
    "gn:feature_class":"P",
    "gn:feature_code":"PPL",
    "gn:name":"Pasirdatar",
    "gn:population":0,
    "gn:timezone":"Asia/Jakarta",
    "iso:country":"ID",
    "name:ind_x_preferred":[
        "Pasirdatar"
    ],
    "wof:name":"Pasirdatar",
    "wof:placetype":"locality"
},
  "geometry": {"coordinates":[108.3428,-7.3046],"type":"Point"}
}