{
  "type": "Feature",
  "properties": {
    "gn:admin1_code":"7.0",
    "gn:asciiname":"Garas",
    "gn:country_code":"ID",
    "gn:dem":90,
    "gn:feature_class":"P",
    "gn:feature_code":"PPL",
    "gn:name":"Garas",
    "gn:population":0,
    "gn:timezone":"Asia/Jakarta",
    "iso:country":"ID",
    "name:ita_x_preferred":[
        "Garas"
    ],
    "wof:name":"Garas",
    "wof:placetype":"locality"
},
  "geometry": {"coordinates":[110.8775,-7.48944],"type":"Point"}
}