{
  "type": "Feature",
  "properties": {
    "gn:admin1_code":"8",
    "gn:asciiname":"Wide",
    "gn:country_code":"ID",
    "gn:dem":332,
    "gn:feature_class":"P",
    "gn:feature_code":"PPL",
    "gn:name":"Wide",
    "gn:population":0,
    "gn:timezone":"Asia/Jakarta",
    "iso:country":"ID",
    "name:deu_x_preferred":[
        "Wide"
    ],
    "name:fra_x_preferred":[
        "Wide"
    ],
    "name:ind_x_preferred":[
        "Wide"
    ],
    "name:ita_x_preferred":[
        "Wide"
    ],
    "name:jpn_x_preferred":[
        "\u30ef\u30a4\u30c9"
    ],
    "name:nld_x_preferred":[
        "Wide"
    ],
    "name:por_x_preferred":[
        "Wide"
    ],
    "wof:name":"Wide",
    "wof:placetype":"locality"
},
  "geometry": {"coordinates":[111.32193999999998,-7.61139],"type":"Point"}
}