{
  "type": "Feature",
  "properties": {
    "gn:admin1_code":"8.0",
    "gn:asciiname":"Wungu",
    "gn:country_code":"ID",
    "gn:dem":91,
    "gn:feature_class":"P",
    "gn:feature_code":"PPL",
    "gn:name":"Wungu",
    "gn:population":0,
    "gn:timezone":"Asia/Jakarta",
    "iso:country":"ID",
    "name:ind_x_preferred":[
        "Wungu"
    ],
    "wof:name":"Wungu",
    "wof:placetype":"locality"
},
  "geometry": {"coordinates":[111.81229999999999,-8.1539],"type":"Point"}
}