{
  "type": "Feature",
  "properties": {
    "gn:admin1_code":"30",
    "gn:asciiname":"Gobel",
    "gn:country_code":"ID",
    "gn:dem":38,
    "gn:feature_class":"P",
    "gn:feature_code":"PPL",
    "gn:name":"Gobel",
    "gn:population":0,
    "gn:timezone":"Asia/Jakarta",
    "iso:country":"ID",
    "name:ind_x_preferred":[
        "Gobel"
    ],
    "wof:name":"Gobel",
    "wof:placetype":"locality"
},
  "geometry": {"coordinates":[107.96944000000001,-6.51333],"type":"Point"}
}