{
  "type": "Feature",
  "properties": {
    "gn:admin1_code":"1.0",
    "gn:asciiname":"Kendawi",
    "gn:country_code":"ID",
    "gn:dem":904,
    "gn:feature_class":"P",
    "gn:feature_code":"PPL",
    "gn:name":"Kendawi",
    "gn:population":0,
    "gn:timezone":"Asia/Jakarta",
    "iso:country":"ID",
    "name:ind_x_preferred":[
        "Kendawi"
    ],
    "wof:lang_x_official":[
        "ind"
    ],
    "wof:lang_x_spoken":[
        "ind",
        "eng"
    ],
    "wof:name":"Kendawi",
    "wof:placetype":"locality"
},
  "geometry": {"coordinates":[97.3353,4.0508],"type":"Point"}
}