{
  "type": "Feature",
  "properties": {
    "gn:admin1_code":"10",
    "gn:asciiname":"Sundak",
    "gn:country_code":"ID",
    "gn:dem":0,
    "gn:feature_class":"P",
    "gn:feature_code":"PPL",
    "gn:name":"Sundak",
    "gn:population":0,
    "gn:timezone":"Asia/Jakarta",
    "iso:country":"ID",
    "name:ind_x_preferred":[
        "Sundak"
    ],
    "wof:name":"Sundak",
    "wof:placetype":"locality"
},
  "geometry": {"coordinates":[110.61083000000001,-8.14917],"type":"Point"}
}