{
  "type": "Feature",
  "properties": {
    "gn:admin1_code":"07",
    "gn:asciiname":"Panji",
    "gn:country_code":"ID",
    "gn:dem":212,
    "gn:feature_class":"P",
    "gn:feature_code":"PPL",
    "gn:name":"Panji",
    "gn:population":0,
    "gn:timezone":"Asia/Jakarta",
    "iso:country":"ID",
    "name:ceb_x_preferred":[
        "Panji"
    ],
    "name:fra_x_preferred":[
        "Panji"
    ],
    "name:ind_x_preferred":[
        "Panji"
    ],
    "name:nld_x_preferred":[
        "Panji"
    ],
    "name:swe_x_preferred":[
        "Panji"
    ],
    "name:und_x_variant":[
        "Pandji"
    ],
    "wof:name":"Panji",
    "wof:placetype":"locality"
},
  "geometry": {"coordinates":[110.3138,-7.0357],"type":"Point"}
}