{
  "type": "Feature",
  "properties": {
    "gn:admin1_code":"7.0",
    "gn:asciiname":"Dwagang",
    "gn:country_code":"ID",
    "gn:dem":481,
    "gn:feature_class":"P",
    "gn:feature_code":"PPL",
    "gn:name":"Dwagang",
    "gn:population":0,
    "gn:timezone":"Asia/Jakarta",
    "iso:country":"ID",
    "name:ind_x_preferred":[
        "Dwagang"
    ],
    "wof:name":"Dwagang",
    "wof:placetype":"locality"
},
  "geometry": {"coordinates":[109.36417,-7.53167],"type":"Point"}
}