{
  "type": "Feature",
  "properties": {
    "gn:admin1_code":"26",
    "gn:asciiname":"Sukajulu",
    "gn:country_code":"ID",
    "gn:dem":1242,
    "gn:feature_class":"P",
    "gn:feature_code":"PPL",
    "gn:name":"Sukajulu",
    "gn:population":0,
    "gn:timezone":"Asia/Jakarta",
    "iso:country":"ID",
    "name:ind_x_preferred":[
        "Sukajulu"
    ],
    "name:und_x_variant":[
        "Sukadjulu"
    ],
    "wof:name":"Sukajulu",
    "wof:placetype":"locality"
},
  "geometry": {"coordinates":[98.5621,3.1136],"type":"Point"}
}