{
  "type": "Feature",
  "properties": {
    "gn:admin1_code":"7.0",
    "gn:asciiname":"Sumurtumpang",
    "gn:country_code":"ID",
    "gn:dem":173,
    "gn:feature_class":"P",
    "gn:feature_code":"PPL",
    "gn:name":"Sumurtumpang",
    "gn:population":0,
    "gn:timezone":"Asia/Jakarta",
    "iso:country":"ID",
    "wof:name":"Sumurtumpang",
    "wof:placetype":"locality"
},
  "geometry": {"coordinates":[110.76083,-7.38972],"type":"Point"}
}