{
  "type": "Feature",
  "properties": {
    "gn:admin1_code":"26",
    "gn:asciiname":"Kalang Ujung",
    "gn:country_code":"ID",
    "gn:dem":1051,
    "gn:feature_class":"P",
    "gn:feature_code":"PPL",
    "gn:name":"Kalang Ujung",
    "gn:population":0,
    "gn:timezone":"Asia/Jakarta",
    "iso:country":"ID",
    "name:ind_x_preferred":[
        "Kalang Ujung"
    ],
    "wof:name":"Kalang Ujung",
    "wof:placetype":"locality"
},
  "geometry": {"coordinates":[98.30549999999999,2.7631],"type":"Point"}
}