{
  "type": "Feature",
  "properties": {
    "gn:admin1_code":"7.0",
    "gn:asciiname":"Mlereng",
    "gn:country_code":"ID",
    "gn:dem":670,
    "gn:feature_class":"P",
    "gn:feature_code":"PPL",
    "gn:name":"Mlereng",
    "gn:population":0,
    "gn:timezone":"Asia/Jakarta",
    "iso:country":"ID",
    "wof:name":"Mlereng",
    "wof:placetype":"locality"
},
  "geometry": {"coordinates":[110.23166999999999,-7.26361],"type":"Point"}
}