{
  "type": "Feature",
  "properties": {
    "gn:admin1_code":"24",
    "gn:asciiname":"Apa",
    "gn:country_code":"ID",
    "gn:dem":617,
    "gn:feature_class":"P",
    "gn:feature_code":"PPL",
    "gn:name":"Apa",
    "gn:population":0,
    "gn:timezone":"Asia/Jakarta",
    "iso:country":"ID",
    "name:ind_x_preferred":[
        "Apa"
    ],
    "wof:name":"Apa",
    "wof:placetype":"locality"
},
  "geometry": {"coordinates":[100.54233000000001,-0.70395],"type":"Point"}
}