{
  "type": "Feature",
  "properties": {
    "gn:admin1_code":"30",
    "gn:asciiname":"Parakankopo",
    "gn:country_code":"ID",
    "gn:dem":439,
    "gn:feature_class":"P",
    "gn:feature_code":"PPL",
    "gn:name":"Parakankopo",
    "gn:population":0,
    "gn:timezone":"Asia/Jakarta",
    "iso:country":"ID",
    "name:ind_x_preferred":[
        "Parakankopo"
    ],
    "wof:name":"Parakankopo",
    "wof:placetype":"locality"
},
  "geometry": {"coordinates":[107.39943999999998,-6.81083],"type":"Point"}
}