{
  "type": "Feature",
  "properties": {
    "gn:admin1_code":"30",
    "gn:asciiname":"Cipeusing",
    "gn:country_code":"ID",
    "gn:dem":1251,
    "gn:feature_class":"P",
    "gn:feature_code":"PPL",
    "gn:name":"Cipeusing",
    "gn:population":0,
    "gn:timezone":"Asia/Jakarta",
    "iso:country":"ID",
    "name:ind_x_preferred":[
        "Cipeusing"
    ],
    "name:und_x_variant":[
        "Tjipeusing 2",
        "Cipeusing Dua"
    ],
    "wof:name":"Cipeusing",
    "wof:placetype":"locality"
},
  "geometry": {"coordinates":[107.56222,-6.80583],"type":"Point"}
}