{
  "type": "Feature",
  "properties": {
    "gn:admin1_code":"8.0",
    "gn:asciiname":"Kori",
    "gn:country_code":"ID",
    "gn:dem":602,
    "gn:feature_class":"P",
    "gn:feature_code":"PPL",
    "gn:name":"Kori",
    "gn:population":0,
    "gn:timezone":"Asia/Jakarta",
    "iso:country":"ID",
    "name:ind_x_preferred":[
        "Kori"
    ],
    "wof:name":"Kori",
    "wof:placetype":"locality"
},
  "geometry": {"coordinates":[111.5778,-8.2194],"type":"Point"}
}