{
  "type": "Feature",
  "properties": {
    "gn:admin1_code":"21.0",
    "gn:asciiname":"Sinio",
    "gn:country_code":"ID",
    "gn:dem":992,
    "gn:feature_class":"P",
    "gn:feature_code":"PPL",
    "gn:name":"Sinio",
    "gn:population":0,
    "gn:timezone":"Asia/Makassar",
    "iso:country":"ID",
    "name:azb_x_preferred":[
        "\u0633\u06cc\u0646\u06cc\u0648"
    ],
    "name:bel_x_preferred":[
        "\u0421\u0456\u043d\u0456\u0430"
    ],
    "name:bul_x_preferred":[
        "\u0421\u0438\u043d\u0438\u043e"
    ],
    "name:ceb_x_preferred":[
        "Sinio"
    ],
    "name:deu_x_preferred":[
        "Sinio"
    ],
    "name:epo_x_preferred":[
        "Sinio"
    ],
    "name:est_x_preferred":[
        "Sinio"
    ],
    "name:eus_x_preferred":[
        "Sinio"
    ],
    "name:fas_x_preferred":[
        "\u0633\u06cc\u0646\u06cc\u0648"
    ],
    "name:fra_x_preferred":[
        "Sinio"
    ],
    "name:hun_x_preferred":[
        "Sinio"
    ],
    "name:hye_x_preferred":[
        "\u054d\u056b\u0576\u056b\u0578"
    ],
    "name:ind_x_preferred":[
        "Sinio"
    ],
    "name:ita_x_preferred":[
        "Sinio"
    ],
    "name:jpn_x_preferred":[
        "\u30b7\u30fc\u30cb\u30aa"
    ],
    "name:kaz_x_preferred":[
        "\u0421\u0438\u043d\u0438\u043e"
    ],
    "name:lat_x_preferred":[
        "Sinium"
    ],
    "name:lmo_x_preferred":[
        "Sinio"
    ],
    "name:msa_x_preferred":[
        "Sinio"
    ],
    "name:nap_x_preferred":[
        "Sinio"
    ],
    "name:nld_x_preferred":[
        "Sinio"
    ],
    "name:pms_x_preferred":[
        "Sin-i"
    ],
    "name:pol_x_preferred":[
        "Sinio"
    ],
    "name:por_x_preferred":[
        "Sinio"
    ],
    "name:ron_x_preferred":[
        "Sinio"
    ],
    "name:rus_x_preferred":[
        "\u0421\u0438\u043d\u0438\u043e"
    ],
    "name:scn_x_preferred":[
        "Sinio"
    ],
    "name:spa_x_preferred":[
        "Sinio"
    ],
    "name:srp_x_preferred":[
        "\u0421\u0438\u043d\u0438\u043e"
    ],
    "name:tgl_x_preferred":[
        "Sinio"
    ],
    "name:ukr_x_preferred":[
        "\u0421\u0456\u043d\u0456\u043e"
    ],
    "name:uzb_x_preferred":[
        "Sinio"
    ],
    "name:vie_x_preferred":[
        "Sinio"
    ],
    "name:vol_x_preferred":[
        "Sinio"
    ],
    "name:war_x_preferred":[
        "Sinio"
    ],
    "name:zho_x_preferred":[
        "\u897f\u5c3c\u5965"
    ],
    "wof:lang_x_official":[
        "ind"
    ],
    "wof:lang_x_spoken":[
        "ind",
        "eng"
    ],
    "wof:name":"Sinio",
    "wof:placetype":"locality"
},
  "geometry": {"coordinates":[119.73208,-1.0244],"type":"Point"}
}