{
  "type": "Feature",
  "properties": {
    "gn:admin1_code":"21.0",
    "gn:asciiname":"Sinio",
    "gn:country_code":"ID",
    "gn:dem":992,
    "gn:feature_class":"P",
    "gn:feature_code":"PPL",
    "gn:name":"Sinio",
    "gn:population":0,
    "gn:timezone":"Asia/Makassar",
    "iso:country":"ID",
    "name:ind_x_preferred":[
        "Sinio"
    ],
    "wof:name":"Sinio",
    "wof:placetype":"locality"
},
  "geometry": {"coordinates":[119.73208,-1.0244],"type":"Point"}
}