{
  "type": "Feature",
  "properties": {
    "gn:admin1_code":"30",
    "gn:asciiname":"Lemahneundeut Karet",
    "gn:country_code":"ID",
    "gn:dem":939,
    "gn:feature_class":"P",
    "gn:feature_code":"PPL",
    "gn:name":"Lemahneundeut Karet",
    "gn:population":0,
    "gn:timezone":"Asia/Jakarta",
    "iso:country":"ID",
    "name:ind_x_preferred":[
        "Lemahneundeut Karet"
    ],
    "wof:lang_x_official":[
        "ind"
    ],
    "wof:lang_x_spoken":[
        "ind",
        "eng"
    ],
    "wof:name":"Lemahneundeut Karet",
    "wof:placetype":"locality"
},
  "geometry": {"coordinates":[106.92028000000001,-6.70333],"type":"Point"}
}