{
  "type": "Feature",
  "properties": {
    "gn:admin1_code":"17.0",
    "gn:asciiname":"Kolohtiung",
    "gn:country_code":"ID",
    "gn:dem":53,
    "gn:feature_class":"P",
    "gn:feature_code":"PPL",
    "gn:name":"Kolohtiung",
    "gn:population":0,
    "gn:timezone":"Asia/Makassar",
    "iso:country":"ID",
    "name:ind_x_preferred":[
        "Kolohtiung"
    ],
    "wof:name":"Kolohtiung",
    "wof:placetype":"locality"
},
  "geometry": {"coordinates":[116.18770000000001,-8.3627],"type":"Point"}
}