{
  "type": "Feature",
  "properties": {
    "gn:admin1_code":"33.0",
    "gn:asciiname":"Moncor",
    "gn:country_code":"ID",
    "gn:dem":326,
    "gn:feature_class":"P",
    "gn:feature_code":"PPL",
    "gn:name":"Moncor",
    "gn:population":0,
    "gn:timezone":"Asia/Jakarta",
    "iso:country":"ID",
    "name:ind_x_preferred":[
        "Moncor"
    ],
    "wof:name":"Moncor",
    "wof:placetype":"locality"
},
  "geometry": {"coordinates":[105.94710000000001,-6.3397],"type":"Point"}
}