{
  "type": "Feature",
  "properties": {
    "gn:admin1_code":"7.0",
    "gn:asciiname":"Sobokarang",
    "gn:country_code":"ID",
    "gn:dem":391,
    "gn:feature_class":"P",
    "gn:feature_code":"PPL",
    "gn:name":"Sobokarang",
    "gn:population":0,
    "gn:timezone":"Asia/Jakarta",
    "iso:country":"ID",
    "wof:name":"Sobokarang",
    "wof:placetype":"locality"
},
  "geometry": {"coordinates":[110.23888999999998,-7.45083],"type":"Point"}
}