{
  "type": "Feature",
  "properties": {
    "gn:admin1_code":"8",
    "gn:asciiname":"Kerto",
    "gn:country_code":"ID",
    "gn:dem":808,
    "gn:feature_class":"P",
    "gn:feature_code":"PPL",
    "gn:name":"Kerto",
    "gn:population":0,
    "gn:timezone":"Asia/Jakarta",
    "iso:country":"ID",
    "name:ind_x_preferred":[
        "Kerto"
    ],
    "wof:name":"Kerto",
    "wof:placetype":"locality"
},
  "geometry": {"coordinates":[111.32611,-8.11861],"type":"Point"}
}