{
  "type": "Feature",
  "properties": {
    "gn:admin1_code":"12.0",
    "gn:asciiname":"Sungaidualaut",
    "gn:country_code":"ID",
    "gn:dem":4,
    "gn:feature_class":"P",
    "gn:feature_code":"PPL",
    "gn:name":"Sungaidualaut",
    "gn:population":0,
    "gn:timezone":"Asia/Makassar",
    "iso:country":"ID",
    "name:ind_x_preferred":[
        "Sungaidualaut"
    ],
    "name:und_x_variant":[
        "Soengai Doewa",
        "Soengaidoea",
        "Sungaidua"
    ],
    "wof:name":"Sungaidualaut",
    "wof:placetype":"locality"
},
  "geometry": {"coordinates":[115.7496,-3.7004],"type":"Point"}
}