{
  "type": "Feature",
  "properties": {
    "gn:admin1_code":"26",
    "gn:asciiname":"Bagasan Dua",
    "gn:country_code":"ID",
    "gn:dem":900,
    "gn:feature_class":"P",
    "gn:feature_code":"PPL",
    "gn:name":"Bagasan Dua",
    "gn:population":0,
    "gn:timezone":"Asia/Jakarta",
    "iso:country":"ID",
    "name:ind_x_preferred":[
        "Bagasan Dua"
    ],
    "name:und_x_variant":[
        "Bagasan 2"
    ],
    "wof:lang_x_official":[
        "ind"
    ],
    "wof:lang_x_spoken":[
        "ind",
        "eng"
    ],
    "wof:name":"Bagasan Dua",
    "wof:placetype":"locality"
},
  "geometry": {"coordinates":[99.0608,2.3392],"type":"Point"}
}