{
  "type": "Feature",
  "properties": {
    "gn:admin1_code":"17",
    "gn:asciiname":"Sompang",
    "gn:country_code":"ID",
    "gn:dem":481,
    "gn:feature_class":"P",
    "gn:feature_code":"PPL",
    "gn:name":"Sompang",
    "gn:population":0,
    "gn:timezone":"Asia/Makassar",
    "iso:country":"ID",
    "name:ind_x_preferred":[
        "Sompang"
    ],
    "wof:name":"Sompang",
    "wof:placetype":"locality"
},
  "geometry": {"coordinates":[116.4147,-8.5695],"type":"Point"}
}