{
  "type": "Feature",
  "properties": {
    "gn:admin1_code":"8.0",
    "gn:asciiname":"Jember",
    "gn:country_code":"ID",
    "gn:dem":68,
    "gn:feature_class":"P",
    "gn:feature_code":"PPL",
    "gn:name":"Jember",
    "gn:population":0,
    "gn:timezone":"Asia/Jakarta",
    "iso:country":"ID",
    "name:ben_x_preferred":[
        "\u099c\u09c7\u09ae\u09ac\u09c7\u09b0"
    ],
    "name:ell_x_preferred":[
        "\u03a4\u03b6\u03ad\u03bc\u03c0\u03b5\u03c1"
    ],
    "name:heb_x_preferred":[
        "\u05d2'\u05de\u05d1\u05e8"
    ],
    "name:hin_x_preferred":[
        "\u091c\u0947\u0902\u092c\u0930"
    ],
    "name:hun_x_preferred":[
        "Jember"
    ],
    "name:ind_x_preferred":[
        "Jember"
    ],
    "name:kor_x_preferred":[
        "\uc82c\ubc84"
    ],
    "name:rus_x_preferred":[
        "\u0419\u0435\u043c\u0431\u0435\u0440"
    ],
    "name:tur_x_preferred":[
        "Jember"
    ],
    "name:ukr_x_preferred":[
        "\u0414\u0436\u0435\u043c\u0431\u0435\u0440"
    ],
    "name:urd_x_preferred":[
        "\u062c\u06cc\u0645\u0628\u0631"
    ],
    "wof:lang_x_official":[
        "ind"
    ],
    "wof:lang_x_spoken":[
        "ind",
        "eng"
    ],
    "wof:name":"Jember",
    "wof:placetype":"locality"
},
  "geometry": {"coordinates":[112.1789,-7.6364],"type":"Point"}
}