{
  "type": "Feature",
  "properties": {
    "gn:admin1_code":"30",
    "gn:asciiname":"Sayatilama",
    "gn:country_code":"ID",
    "gn:dem":670,
    "gn:feature_class":"P",
    "gn:feature_code":"PPL",
    "gn:name":"Sayatilama",
    "gn:population":0,
    "gn:timezone":"Asia/Jakarta",
    "iso:country":"ID",
    "name:ind_x_preferred":[
        "Sayatilama"
    ],
    "name:und_x_variant":[
        "Sajati 1",
        "Sayati Satu"
    ],
    "wof:lang_x_official":[
        "ind"
    ],
    "wof:lang_x_spoken":[
        "ind",
        "eng"
    ],
    "wof:name":"Sayatilama",
    "wof:placetype":"locality"
},
  "geometry": {"coordinates":[107.57583,-6.97056],"type":"Point"}
}