{
  "type": "Feature",
  "properties": {
    "gn:admin1_code":"8.0",
    "gn:asciiname":"Glugur Satu",
    "gn:country_code":"ID",
    "gn:dem":84,
    "gn:feature_class":"P",
    "gn:feature_code":"PPL",
    "gn:name":"Glugur Satu",
    "gn:population":0,
    "gn:timezone":"Asia/Jakarta",
    "iso:country":"ID",
    "name:ind_x_preferred":[
        "Glugur Satu"
    ],
    "wof:name":"Glugur Satu",
    "wof:placetype":"locality"
},
  "geometry": {"coordinates":[113.4259,-7.0597],"type":"Point"}
}