{
  "type": "Feature",
  "properties": {
    "gn:admin1_code":"30",
    "gn:asciiname":"Rabu",
    "gn:country_code":"ID",
    "gn:dem":345,
    "gn:feature_class":"P",
    "gn:feature_code":"PPL",
    "gn:name":"Rabu",
    "gn:population":0,
    "gn:timezone":"Asia/Jakarta",
    "iso:country":"ID",
    "name:ind_x_preferred":[
        "Rabu"
    ],
    "wof:name":"Rabu",
    "wof:placetype":"locality"
},
  "geometry": {"coordinates":[108.28471999999999,-6.83972],"type":"Point"}
}