{
  "type": "Feature",
  "properties": {
    "gn:admin1_code":"30",
    "gn:asciiname":"Peusar",
    "gn:country_code":"ID",
    "gn:dem":519,
    "gn:feature_class":"P",
    "gn:feature_code":"PPL",
    "gn:name":"Peusar",
    "gn:population":0,
    "gn:timezone":"Asia/Jakarta",
    "iso:country":"ID",
    "name:ind_x_preferred":[
        "Peusar"
    ],
    "wof:name":"Peusar",
    "wof:placetype":"locality"
},
  "geometry": {"coordinates":[107.93472,-6.89278],"type":"Point"}
}