{
  "type": "Feature",
  "properties": {
    "gn:admin1_code":"30.0",
    "gn:asciiname":"Cimenteng",
    "gn:country_code":"ID",
    "gn:dem":19,
    "gn:feature_class":"P",
    "gn:feature_code":"PPL",
    "gn:name":"Cimenteng",
    "gn:population":0,
    "gn:timezone":"Asia/Jakarta",
    "iso:country":"ID",
    "name:ind_x_preferred":[
        "Cimenteng"
    ],
    "wof:name":"Cimenteng",
    "wof:placetype":"locality"
},
  "geometry": {"coordinates":[106.47150000000001,-7.24],"type":"Point"}
}