{
  "type": "Feature",
  "properties": {
    "gn:admin1_code":"1",
    "gn:asciiname":"Ateuklamura",
    "gn:country_code":"ID",
    "gn:dem":18,
    "gn:feature_class":"P",
    "gn:feature_code":"PPL",
    "gn:name":"Ateuklamura",
    "gn:population":0,
    "gn:timezone":"Asia/Jakarta",
    "iso:country":"ID",
    "name:ind_x_preferred":[
        "Ateuklamura"
    ],
    "wof:name":"Ateuklamura",
    "wof:placetype":"locality"
},
  "geometry": {"coordinates":[95.35209999999999,5.4814],"type":"Point"}
}