{
  "type": "Feature",
  "properties": {
    "gn:admin1_code":"8.0",
    "gn:asciiname":"Kaligandu",
    "gn:country_code":"ID",
    "gn:dem":120,
    "gn:feature_class":"P",
    "gn:feature_code":"PPL",
    "gn:name":"Kaligandu",
    "gn:population":0,
    "gn:timezone":"Asia/Jakarta",
    "iso:country":"ID",
    "name:ind_x_preferred":[
        "Kaligandu"
    ],
    "wof:name":"Kaligandu",
    "wof:placetype":"locality"
},
  "geometry": {"coordinates":[111.5915,-7.3885],"type":"Point"}
}