{
  "type": "Feature",
  "properties": {
    "gn:admin1_code":"30",
    "gn:asciiname":"Parungkuda Satu",
    "gn:country_code":"ID",
    "gn:dem":396,
    "gn:feature_class":"P",
    "gn:feature_code":"PPL",
    "gn:name":"Parungkuda Satu",
    "gn:population":0,
    "gn:timezone":"Asia/Jakarta",
    "iso:country":"ID",
    "name:ind_x_preferred":[
        "Parungkuda Satu"
    ],
    "wof:lang_x_official":[
        "ind"
    ],
    "wof:lang_x_spoken":[
        "ind",
        "eng"
    ],
    "wof:name":"Parungkuda Satu",
    "wof:placetype":"locality"
},
  "geometry": {"coordinates":[106.76000000000001,-6.845],"type":"Point"}
}