{
  "type": "Feature",
  "properties": {
    "gn:admin1_code":"34.0",
    "gn:asciiname":"Lemito Pantai",
    "gn:country_code":"ID",
    "gn:dem":5,
    "gn:feature_class":"P",
    "gn:feature_code":"PPL",
    "gn:name":"Lemito Pantai",
    "gn:population":0,
    "gn:timezone":"Asia/Makassar",
    "iso:country":"ID",
    "name:ind_x_preferred":[
        "Lemito Pantai"
    ],
    "wof:name":"Lemito Pantai",
    "wof:placetype":"locality"
},
  "geometry": {"coordinates":[121.5729,0.537],"type":"Point"}
}