{
  "type": "Feature",
  "properties": {
    "gn:admin1_code":"18.0",
    "gn:asciiname":"Loboma",
    "gn:country_code":"ID",
    "gn:dem":122,
    "gn:feature_class":"P",
    "gn:feature_code":"PPLA4",
    "gn:name":"Loboma",
    "gn:population":0,
    "gn:timezone":"Asia/Makassar",
    "iso:country":"ID",
    "name:ind_x_preferred":[
        "Loboma"
    ],
    "wof:name":"Loboma",
    "wof:placetype":"locality"
},
  "geometry": {"coordinates":[121.5749,-10.6212],"type":"Point"}
}