{
  "type": "Feature",
  "properties": {
    "gn:admin1_code":"31.0",
    "gn:asciiname":"Kisihang",
    "gn:country_code":"ID",
    "gn:dem":17,
    "gn:feature_class":"P",
    "gn:feature_code":"PPL",
    "gn:name":"Kisihang",
    "gn:population":0,
    "gn:timezone":"Asia/Makassar",
    "iso:country":"ID",
    "name:ind_x_preferred":[
        "Kisihang"
    ],
    "name:und_x_variant":[
        "Kesihan"
    ],
    "wof:name":"Kisihang",
    "wof:placetype":"locality"
},
  "geometry": {"coordinates":[125.4363,2.3188],"type":"Point"}
}