{
  "type": "Feature",
  "properties": {
    "gn:admin1_code":"30",
    "gn:asciiname":"Nempel",
    "gn:country_code":"ID",
    "gn:dem":462,
    "gn:feature_class":"P",
    "gn:feature_code":"PPL",
    "gn:name":"Nempel",
    "gn:population":0,
    "gn:timezone":"Asia/Jakarta",
    "iso:country":"ID",
    "name:ind_x_preferred":[
        "Nempel"
    ],
    "wof:name":"Nempel",
    "wof:placetype":"locality"
},
  "geometry": {"coordinates":[106.72083000000001,-6.84778],"type":"Point"}
}