{
  "type": "Feature",
  "properties": {
    "gn:admin1_code":"7.0",
    "gn:asciiname":"Cibolek Kidul",
    "gn:country_code":"ID",
    "gn:dem":15,
    "gn:feature_class":"P",
    "gn:feature_code":"PPLA4",
    "gn:name":"Cibolek Kidul",
    "gn:population":0,
    "gn:timezone":"Asia/Jakarta",
    "iso:country":"ID",
    "name:ind_x_preferred":[
        "Cibolek Kidul"
    ],
    "wof:name":"Cibolek Kidul",
    "wof:placetype":"locality"
},
  "geometry": {"coordinates":[111.06581,-6.60099],"type":"Point"}
}