{
  "type": "Feature",
  "properties": {
    "gn:admin1_code":"30",
    "gn:asciiname":"Marongge Hilir",
    "gn:country_code":"ID",
    "gn:dem":53,
    "gn:feature_class":"P",
    "gn:feature_code":"PPL",
    "gn:name":"Marongge Hilir",
    "gn:population":0,
    "gn:timezone":"Asia/Jakarta",
    "iso:country":"ID",
    "name:ind_x_preferred":[
        "Marongge Hilir"
    ],
    "wof:name":"Marongge Hilir",
    "wof:placetype":"locality"
},
  "geometry": {"coordinates":[108.16110999999999,-6.78861],"type":"Point"}
}