{
  "type": "Feature",
  "properties": {
    "gn:admin1_code":"15.0",
    "gn:asciiname":"Seleraputra Empat",
    "gn:country_code":"ID",
    "gn:dem":41,
    "gn:feature_class":"P",
    "gn:feature_code":"PPL",
    "gn:name":"Seleraputra Empat",
    "gn:population":0,
    "gn:timezone":"Asia/Jakarta",
    "iso:country":"ID",
    "name:ind_x_preferred":[
        "Seleraputra Empat"
    ],
    "name:und_x_variant":[
        "Seleraputra 4"
    ],
    "wof:lang_x_official":[
        "ind"
    ],
    "wof:lang_x_spoken":[
        "ind",
        "eng"
    ],
    "wof:name":"Seleraputra Empat",
    "wof:placetype":"locality"
},
  "geometry": {"coordinates":[105.62485,-5.11698],"type":"Point"}
}