{
  "type": "Feature",
  "properties": {
    "gn:admin1_code":"33.0",
    "gn:asciiname":"Salawi",
    "gn:country_code":"ID",
    "gn:dem":153,
    "gn:feature_class":"P",
    "gn:feature_code":"PPL",
    "gn:name":"Salawi",
    "gn:population":0,
    "gn:timezone":"Asia/Jakarta",
    "iso:country":"ID",
    "name:ind_x_preferred":[
        "Salawi"
    ],
    "wof:name":"Salawi",
    "wof:placetype":"locality"
},
  "geometry": {"coordinates":[106.0202,-6.3754],"type":"Point"}
}