{
  "type": "Feature",
  "properties": {
    "gn:admin1_code":"22",
    "gn:asciiname":"Laikambuu",
    "gn:country_code":"ID",
    "gn:dem":41,
    "gn:feature_class":"P",
    "gn:feature_code":"PPL",
    "gn:name":"Laikambuu",
    "gn:population":0,
    "gn:timezone":"Asia/Makassar",
    "iso:country":"ID",
    "name:ind_x_preferred":[
        "Laikambuu"
    ],
    "name:und_x_variant":[
        "Laekambu"
    ],
    "wof:name":"Laikambuu",
    "wof:placetype":"locality"
},
  "geometry": {"coordinates":[122.06529999999999,-3.8416],"type":"Point"}
}