{
  "type": "Feature",
  "properties": {
    "gn:admin1_code":"7.0",
    "gn:asciiname":"Ngawen",
    "gn:country_code":"ID",
    "gn:dem":640,
    "gn:feature_class":"P",
    "gn:feature_code":"PPL",
    "gn:name":"Ngawen",
    "gn:population":0,
    "gn:timezone":"Asia/Jakarta",
    "iso:country":"ID",
    "name:ind_x_preferred":[
        "Candi Ngawen"
    ],
    "name:jav_x_preferred":[
        "Candhi Ngaw\u00e8n"
    ],
    "wof:lang_x_official":[
        "ind"
    ],
    "wof:lang_x_spoken":[
        "ind",
        "eng"
    ],
    "wof:name":"Ngawen",
    "wof:placetype":"locality"
},
  "geometry": {"coordinates":[110.49417,-7.3475],"type":"Point"}
}