{
  "type": "Feature",
  "properties": {
    "gn:admin1_code":"0.0",
    "gn:asciiname":"Sumi",
    "gn:cc2":"ID",
    "gn:country_code":"ID",
    "gn:dem":-9999,
    "gn:feature_class":"P",
    "gn:feature_code":"PPL",
    "gn:name":"Sumi",
    "gn:population":0,
    "gn:timezone":"Asia/Makassar",
    "iso:country":"ID",
    "name:ceb_x_preferred":[
        "Sumi"
    ],
    "name:deu_x_preferred":[
        "Sumi"
    ],
    "name:fra_x_preferred":[
        "Sumi"
    ],
    "name:ita_x_preferred":[
        "Sumi"
    ],
    "name:swe_x_preferred":[
        "Sumi"
    ],
    "name:und_x_variant":[
        "Soemi",
        "Sumi"
    ],
    "wof:lang_x_official":[
        "ind"
    ],
    "wof:lang_x_spoken":[
        "ind",
        "eng"
    ],
    "wof:name":"Sumi",
    "wof:placetype":"locality"
},
  "geometry": {"coordinates":[119.01667,-8.58333],"type":"Point"}
}