{
  "type": "Feature",
  "properties": {
    "gn:admin1_code":"38.0",
    "gn:asciiname":"Rante Kata",
    "gn:country_code":"ID",
    "gn:dem":407,
    "gn:feature_class":"P",
    "gn:feature_code":"PPL",
    "gn:name":"Rante Kata",
    "gn:population":0,
    "gn:timezone":"Asia/Makassar",
    "iso:country":"ID",
    "name:ind_x_preferred":[
        "Rante Kata"
    ],
    "wof:name":"Rante Kata",
    "wof:placetype":"locality"
},
  "geometry": {"coordinates":[120.0381,-3.1457],"type":"Point"}
}