{
  "type": "Feature",
  "properties": {
    "gn:admin1_code":"10",
    "gn:asciiname":"Silingi",
    "gn:country_code":"ID",
    "gn:dem":225,
    "gn:feature_class":"P",
    "gn:feature_code":"PPL",
    "gn:name":"Silingi",
    "gn:population":0,
    "gn:timezone":"Asia/Jakarta",
    "iso:country":"ID",
    "name:afr_x_preferred":[
        "Silingi"
    ],
    "name:ast_x_preferred":[
        "Silingos"
    ],
    "name:bul_x_preferred":[
        "\u0421\u0438\u043b\u0438\u043d\u0433\u0438"
    ],
    "name:cat_x_preferred":[
        "Silinges"
    ],
    "name:ces_x_preferred":[
        "Silingov\u00e9"
    ],
    "name:deu_x_preferred":[
        "Silingen"
    ],
    "name:epo_x_preferred":[
        "Silingoj"
    ],
    "name:fra_x_preferred":[
        "Sillings"
    ],
    "name:fry_x_preferred":[
        "Silingen"
    ],
    "name:glg_x_preferred":[
        "Silingos"
    ],
    "name:hun_x_preferred":[
        "Naharvaliak"
    ],
    "name:ita_x_preferred":[
        "Silingi"
    ],
    "name:lat_x_preferred":[
        "Silingae"
    ],
    "name:nds_x_preferred":[
        "Silingen"
    ],
    "name:nld_x_preferred":[
        "Silingen"
    ],
    "name:nor_x_preferred":[
        "Silinger"
    ],
    "name:pol_x_preferred":[
        "Silingowie"
    ],
    "name:por_x_preferred":[
        "Silingos"
    ],
    "name:ron_x_preferred":[
        "Silingi"
    ],
    "name:rus_x_preferred":[
        "\u0421\u0438\u043b\u0438\u043d\u0433\u0438"
    ],
    "name:spa_x_preferred":[
        "Silingos"
    ],
    "name:srp_x_preferred":[
        "\u0421\u0438\u043b\u0438\u043d\u0437\u0438"
    ],
    "wof:lang_x_official":[
        "ind"
    ],
    "wof:lang_x_spoken":[
        "ind",
        "eng"
    ],
    "wof:name":"Silingi",
    "wof:placetype":"locality"
},
  "geometry": {"coordinates":[110.71611,-7.95389],"type":"Point"}
}