{
  "type": "Feature",
  "properties": {
    "gn:admin1_code":"18.0",
    "gn:asciiname":"Mnesatbubuk",
    "gn:country_code":"ID",
    "gn:dem":750,
    "gn:feature_class":"P",
    "gn:feature_code":"PPL",
    "gn:name":"Mnesatbubuk",
    "gn:population":0,
    "gn:timezone":"Asia/Makassar",
    "iso:country":"ID",
    "name:ind_x_preferred":[
        "Mnesatbubuk"
    ],
    "wof:name":"Mnesatbubuk",
    "wof:placetype":"locality"
},
  "geometry": {"coordinates":[124.3584,-9.6419],"type":"Point"}
}