{
  "type": "Feature",
  "properties": {
    "gn:admin1_code":"30",
    "gn:asciiname":"Dadap Kulon",
    "gn:cc2":"ID",
    "gn:country_code":"ID",
    "gn:dem":37,
    "gn:feature_class":"P",
    "gn:feature_code":"PPL",
    "gn:name":"Dadap Kulon",
    "gn:population":0,
    "gn:timezone":"Asia/Jakarta",
    "iso:country":"ID",
    "name:und_x_variant":[
        "Dadap Dua",
        "Dadap 2",
        "Dadap Kulon"
    ],
    "wof:name":"Dadap Kulon",
    "wof:placetype":"locality"
},
  "geometry": {"coordinates":[106.67194000000001,-6.30194],"type":"Point"}
}