{
  "type": "Feature",
  "properties": {
    "gn:admin1_code":"37.0",
    "gn:asciiname":"Bencahkelangan",
    "gn:country_code":"ID",
    "gn:dem":11,
    "gn:feature_class":"P",
    "gn:feature_code":"PPL",
    "gn:name":"Bencahkelangan",
    "gn:population":0,
    "gn:timezone":"Asia/Jakarta",
    "iso:country":"ID",
    "name:ind_x_preferred":[
        "Bencahkelangan"
    ],
    "name:und_x_variant":[
        "Bentjahkelangan"
    ],
    "wof:name":"Bencahkelangan",
    "wof:placetype":"locality"
},
  "geometry": {"coordinates":[101.30419999999999,0.5601],"type":"Point"}
}