{
  "type": "Feature",
  "properties": {
    "gn:admin1_code":"8.0",
    "gn:asciiname":"Sumurup",
    "gn:country_code":"ID",
    "gn:dem":111,
    "gn:feature_class":"P",
    "gn:feature_code":"PPL",
    "gn:name":"Sumurup",
    "gn:population":0,
    "gn:timezone":"Asia/Jakarta",
    "iso:country":"ID",
    "name:ind_x_preferred":[
        "Sumurup"
    ],
    "wof:name":"Sumurup",
    "wof:placetype":"locality"
},
  "geometry": {"coordinates":[112.1005,-8.286],"type":"Point"}
}