{
  "type": "Feature",
  "properties": {
    "gn:admin1_code":"15.0",
    "gn:asciiname":"Umbulan Jungbelabuh",
    "gn:country_code":"ID",
    "gn:dem":39,
    "gn:feature_class":"P",
    "gn:feature_code":"PPL",
    "gn:name":"Umbulan Jungbelabuh",
    "gn:population":0,
    "gn:timezone":"Asia/Jakarta",
    "iso:country":"ID",
    "name:ind_x_preferred":[
        "Umbulan Jungbelabuh"
    ],
    "name:und_x_variant":[
        "Umbulan Jungbalabuh"
    ],
    "wof:name":"Umbulan Jungbelabuh",
    "wof:placetype":"locality"
},
  "geometry": {"coordinates":[104.54557,-4.38122],"type":"Point"}
}