{
  "type": "Feature",
  "properties": {
    "gn:admin1_code":"30.0",
    "gn:asciiname":"Cileuksa Hilir",
    "gn:country_code":"ID",
    "gn:dem":524,
    "gn:feature_class":"P",
    "gn:feature_code":"PPL",
    "gn:name":"Cileuksa Hilir",
    "gn:population":0,
    "gn:timezone":"Asia/Jakarta",
    "iso:country":"ID",
    "name:ind_x_preferred":[
        "Cileuksa Hilir"
    ],
    "wof:name":"Cileuksa Hilir",
    "wof:placetype":"locality"
},
  "geometry": {"coordinates":[106.43470000000001,-6.6045],"type":"Point"}
}