{
  "type": "Feature",
  "properties": {
    "gn:admin1_code":"28.0",
    "gn:asciiname":"Ngilgof",
    "gn:country_code":"ID",
    "gn:dem":12,
    "gn:feature_class":"P",
    "gn:feature_code":"PPL",
    "gn:name":"Ngilgof",
    "gn:population":0,
    "gn:timezone":"Asia/Jayapura",
    "iso:country":"ID",
    "name:ind_x_preferred":[
        "Ngilgof"
    ],
    "wof:name":"Ngilgof",
    "wof:placetype":"locality"
},
  "geometry": {"coordinates":[132.63714999999999,-5.67302],"type":"Point"}
}