{
  "type": "Feature",
  "properties": {
    "gn:admin1_code":"38",
    "gn:asciiname":"Batulabbu",
    "gn:country_code":"ID",
    "gn:dem":362,
    "gn:feature_class":"P",
    "gn:feature_code":"PPL",
    "gn:name":"Batulabbu",
    "gn:population":0,
    "gn:timezone":"Asia/Makassar",
    "iso:country":"ID",
    "name:ind_x_preferred":[
        "Batulabbu"
    ],
    "wof:name":"Batulabbu",
    "wof:placetype":"locality"
},
  "geometry": {"coordinates":[120.0544,-5.4672],"type":"Point"}
}