{
  "type": "Feature",
  "properties": {
    "gn:admin1_code":"8",
    "gn:asciiname":"Ngerayung",
    "gn:country_code":"ID",
    "gn:dem":43,
    "gn:feature_class":"P",
    "gn:feature_code":"PPL",
    "gn:name":"Ngerayung",
    "gn:population":0,
    "gn:timezone":"Asia/Jakarta",
    "iso:country":"ID",
    "name:ind_x_preferred":[
        "Ngerayung"
    ],
    "wof:name":"Ngerayung",
    "wof:placetype":"locality"
},
  "geometry": {"coordinates":[112.4349,-7.5285],"type":"Point"}
}