{
  "type": "Feature",
  "properties": {
    "gn:admin1_code":"30.0",
    "gn:asciiname":"Cikupa",
    "gn:country_code":"ID",
    "gn:dem":186,
    "gn:feature_class":"P",
    "gn:feature_code":"PPL",
    "gn:name":"Cikupa",
    "gn:population":0,
    "gn:timezone":"Asia/Jakarta",
    "iso:country":"ID",
    "name:ind_x_preferred":[
        "Cikupa"
    ],
    "wof:name":"Cikupa",
    "wof:placetype":"locality"
},
  "geometry": {"coordinates":[106.6314,-7.3204],"type":"Point"}
}