{
  "type": "Feature",
  "properties": {
    "gn:admin1_code":"07",
    "gn:asciiname":"Ngasinan",
    "gn:country_code":"ID",
    "gn:dem":565,
    "gn:feature_class":"P",
    "gn:feature_code":"PPL",
    "gn:name":"Ngasinan",
    "gn:population":0,
    "gn:timezone":"Asia/Jakarta",
    "iso:country":"ID",
    "name:und_x_variant":[
        "Ngasinan Dua",
        "Ngasinan 2",
        "Ngasinan"
    ],
    "wof:lang_x_official":[
        "ind"
    ],
    "wof:lang_x_spoken":[
        "ind",
        "eng"
    ],
    "wof:name":"Ngasinan",
    "wof:placetype":"locality"
},
  "geometry": {"coordinates":[110.55361000000001,-7.33083],"type":"Point"}
}