{
  "type": "Feature",
  "properties": {
    "gn:admin1_code":"18.0",
    "gn:asciiname":"Daemeko",
    "gn:country_code":"ID",
    "gn:dem":74,
    "gn:feature_class":"P",
    "gn:feature_code":"PPL",
    "gn:name":"Daemeko",
    "gn:population":0,
    "gn:timezone":"Asia/Makassar",
    "iso:country":"ID",
    "name:ind_x_preferred":[
        "Daemeko"
    ],
    "wof:name":"Daemeko",
    "wof:placetype":"locality"
},
  "geometry": {"coordinates":[122.9461,-10.8556],"type":"Point"}
}