{
  "type": "Feature",
  "properties": {
    "gn:admin1_code":"38.0",
    "gn:asciiname":"Laburasseng",
    "gn:country_code":"ID",
    "gn:dem":158,
    "gn:feature_class":"P",
    "gn:feature_code":"PPL",
    "gn:name":"Laburasseng",
    "gn:population":0,
    "gn:timezone":"Asia/Makassar",
    "iso:country":"ID",
    "name:ind_x_preferred":[
        "Laburasseng"
    ],
    "wof:name":"Laburasseng",
    "wof:placetype":"locality"
},
  "geometry": {"coordinates":[120.05589999999999,-4.8732],"type":"Point"}
}