{
  "type": "Feature",
  "properties": {
    "gn:admin1_code":"35",
    "gn:asciiname":"Segembir",
    "gn:country_code":"ID",
    "gn:dem":32,
    "gn:feature_class":"P",
    "gn:feature_code":"PPL",
    "gn:name":"Segembir",
    "gn:population":0,
    "gn:timezone":"Asia/Jakarta",
    "iso:country":"ID",
    "name:ind_x_preferred":[
        "Segembir"
    ],
    "wof:name":"Segembir",
    "wof:placetype":"locality"
},
  "geometry": {"coordinates":[106.07167,-1.8903],"type":"Point"}
}