{
  "type": "Feature",
  "properties": {
    "gn:admin1_code":"32.0",
    "gn:asciiname":"Tanjungmenang",
    "gn:country_code":"ID",
    "gn:dem":348,
    "gn:feature_class":"P",
    "gn:feature_code":"PPL",
    "gn:name":"Tanjungmenang",
    "gn:population":0,
    "gn:timezone":"Asia/Jakarta",
    "iso:country":"ID",
    "name:ind_x_preferred":[
        "Tanjungmenang"
    ],
    "wof:name":"Tanjungmenang",
    "wof:placetype":"locality"
},
  "geometry": {"coordinates":[103.46810000000001,-3.976],"type":"Point"}
}