{
  "type": "Feature",
  "properties": {
    "gn:admin1_code":"30.0",
    "gn:asciiname":"Kutamandarakan",
    "gn:country_code":"ID",
    "gn:dem":155,
    "gn:feature_class":"P",
    "gn:feature_code":"PPLA4",
    "gn:name":"Kutamandarakan",
    "gn:population":0,
    "gn:timezone":"Asia/Jakarta",
    "iso:country":"ID",
    "name:ind_x_preferred":[
        "Kutamandarakan"
    ],
    "wof:name":"Kutamandarakan",
    "wof:placetype":"locality"
},
  "geometry": {"coordinates":[108.5577,-7.0277],"type":"Point"}
}