{
  "type": "Feature",
  "properties": {
    "gn:admin1_code":"00",
    "gn:asciiname":"Babakan Satu",
    "gn:cc2":"ID",
    "gn:country_code":"ID",
    "gn:dem":20,
    "gn:feature_class":"P",
    "gn:feature_code":"PPL",
    "gn:name":"Babakan Satu",
    "gn:population":0,
    "gn:timezone":"Asia/Jakarta",
    "iso:country":"ID",
    "name:und_x_variant":[
        "Babakan 1",
        "Babakan Satu"
    ],
    "wof:name":"Babakan Satu",
    "wof:placetype":"locality"
},
  "geometry": {"coordinates":[106.63222,-6.185],"type":"Point"}
}