{
  "type": "Feature",
  "properties": {
    "gn:admin1_code":"8.0",
    "gn:asciiname":"Ombul Dua",
    "gn:country_code":"ID",
    "gn:dem":6,
    "gn:feature_class":"P",
    "gn:feature_code":"PPL",
    "gn:name":"Ombul Dua",
    "gn:population":0,
    "gn:timezone":"Asia/Jakarta",
    "iso:country":"ID",
    "name:ind_x_preferred":[
        "Ombul Dua"
    ],
    "wof:name":"Ombul Dua",
    "wof:placetype":"locality"
},
  "geometry": {"coordinates":[113.3997,-7.2113],"type":"Point"}
}