{
  "type": "Feature",
  "properties": {
    "gn:admin1_code":"18.0",
    "gn:asciiname":"Lui",
    "gn:country_code":"ID",
    "gn:dem":195,
    "gn:feature_class":"P",
    "gn:feature_code":"PPL",
    "gn:name":"Lui",
    "gn:population":0,
    "gn:timezone":"Asia/Makassar",
    "iso:country":"ID",
    "name:deu_x_preferred":[
        "Lui"
    ],
    "name:est_x_preferred":[
        "Lui"
    ],
    "name:fra_x_preferred":[
        "Lui"
    ],
    "name:hun_x_preferred":[
        "Lui"
    ],
    "name:ind_x_preferred":[
        "Lui"
    ],
    "wof:lang_x_official":[
        "ind"
    ],
    "wof:lang_x_spoken":[
        "ind",
        "eng"
    ],
    "wof:name":"Lui",
    "wof:placetype":"locality"
},
  "geometry": {"coordinates":[121.2045,-8.8802],"type":"Point"}
}