{
  "type": "Feature",
  "properties": {
    "gn:admin1_code":"3.0",
    "gn:asciiname":"Tanjunglontar",
    "gn:country_code":"ID",
    "gn:dem":74,
    "gn:feature_class":"P",
    "gn:feature_code":"PPL",
    "gn:name":"Tanjunglontar",
    "gn:population":0,
    "gn:timezone":"Asia/Jakarta",
    "iso:country":"ID",
    "name:ind_x_preferred":[
        "Tanjunglontar"
    ],
    "wof:name":"Tanjunglontar",
    "wof:placetype":"locality"
},
  "geometry": {"coordinates":[103.26206000000001,-4.57106],"type":"Point"}
}