{
  "type": "Feature",
  "properties": {
    "gn:admin1_code":"08",
    "gn:asciiname":"Wonokoyo Dua",
    "gn:cc2":"ID",
    "gn:country_code":"ID",
    "gn:dem":454,
    "gn:feature_class":"P",
    "gn:feature_code":"PPL",
    "gn:name":"Wonokoyo Dua",
    "gn:population":0,
    "gn:timezone":"Asia/Jakarta",
    "iso:country":"ID",
    "name:und_x_variant":[
        "Wonokojo 2",
        "Wonokoyo Dua"
    ],
    "wof:lang_x_official":[
        "ind"
    ],
    "wof:lang_x_spoken":[
        "ind",
        "eng"
    ],
    "wof:name":"Wonokoyo Dua",
    "wof:placetype":"locality"
},
  "geometry": {"coordinates":[112.65139000000001,-8.02444],"type":"Point"}
}