{
  "type": "Feature",
  "properties": {
    "gn:admin1_code":"21",
    "gn:asciiname":"Doda",
    "gn:country_code":"ID",
    "gn:dem":752,
    "gn:feature_class":"P",
    "gn:feature_code":"PPL",
    "gn:name":"Doda",
    "gn:population":0,
    "gn:timezone":"Asia/Makassar",
    "iso:country":"ID",
    "name:ind_x_preferred":[
        "Doda"
    ],
    "wof:name":"Doda",
    "wof:placetype":"locality"
},
  "geometry": {"coordinates":[119.8039,-1.6175],"type":"Point"}
}