{
  "type": "Feature",
  "properties": {
    "gn:admin1_code":"30",
    "gn:asciiname":"Sindangreret",
    "gn:country_code":"ID",
    "gn:dem":978,
    "gn:feature_class":"P",
    "gn:feature_code":"PPL",
    "gn:name":"Sindangreret",
    "gn:population":0,
    "gn:timezone":"Asia/Jakarta",
    "iso:country":"ID",
    "name:ind_x_preferred":[
        "Sindangreret"
    ],
    "wof:name":"Sindangreret",
    "wof:placetype":"locality"
},
  "geometry": {"coordinates":[107.8301,-7.2044],"type":"Point"}
}