{
  "type": "Feature",
  "properties": {
    "gn:admin1_code":"15.0",
    "gn:asciiname":"Pematang Merbau",
    "gn:country_code":"ID",
    "gn:dem":167,
    "gn:feature_class":"P",
    "gn:feature_code":"PPL",
    "gn:name":"Pematang Merbau",
    "gn:population":0,
    "gn:timezone":"Asia/Jakarta",
    "iso:country":"ID",
    "name:ind_x_preferred":[
        "Pematang Merbau"
    ],
    "name:und_x_variant":[
        "Oemboelan P\u0115matangm\u0115rbau"
    ],
    "wof:lang_x_official":[
        "ind"
    ],
    "wof:lang_x_spoken":[
        "ind",
        "eng"
    ],
    "wof:name":"Pematang Merbau",
    "wof:placetype":"locality"
},
  "geometry": {"coordinates":[105.33446000000001,-5.45766],"type":"Point"}
}