{
  "type": "Feature",
  "properties": {
    "gn:admin1_code":"18",
    "gn:asciiname":"Lalang",
    "gn:country_code":"ID",
    "gn:dem":844,
    "gn:feature_class":"P",
    "gn:feature_code":"PPL",
    "gn:name":"Lalang",
    "gn:population":0,
    "gn:timezone":"Asia/Makassar",
    "iso:country":"ID",
    "name:ceb_x_preferred":[
        "Lalang"
    ],
    "name:ind_x_preferred":[
        "Lalang"
    ],
    "name:nld_x_preferred":[
        "Lalang"
    ],
    "name:swe_x_preferred":[
        "Lalang"
    ],
    "wof:lang_x_official":[
        "ind"
    ],
    "wof:lang_x_spoken":[
        "ind",
        "eng"
    ],
    "wof:name":"Lalang",
    "wof:placetype":"locality"
},
  "geometry": {"coordinates":[120.4986,-8.5378],"type":"Point"}
}