{
  "type": "Feature",
  "properties": {
    "gn:admin1_code":"39",
    "gn:asciiname":"Kabaro",
    "gn:country_code":"ID",
    "gn:dem":8,
    "gn:feature_class":"P",
    "gn:feature_code":"PPL",
    "gn:name":"Kabaro",
    "gn:population":0,
    "gn:timezone":"Asia/Jayapura",
    "iso:country":"ID",
    "name:ind_x_preferred":[
        "Kabaro"
    ],
    "name:und_x_variant":[
        "Kabare"
    ],
    "wof:name":"Kabaro",
    "wof:placetype":"locality"
},
  "geometry": {"coordinates":[130.98716000000002,-0.06004],"type":"Point"}
}