{
  "type": "Feature",
  "properties": {
    "gn:admin1_code":"38",
    "gn:asciiname":"Parasangngang",
    "gn:country_code":"ID",
    "gn:dem":499,
    "gn:feature_class":"P",
    "gn:feature_code":"PPL",
    "gn:name":"Parasangngang",
    "gn:population":0,
    "gn:timezone":"Asia/Makassar",
    "iso:country":"ID",
    "name:ind_x_preferred":[
        "Parasangngang"
    ],
    "wof:name":"Parasangngang",
    "wof:placetype":"locality"
},
  "geometry": {"coordinates":[119.7876,-5.4937],"type":"Point"}
}