{
  "type": "Feature",
  "properties": {
    "gn:admin1_code":"37",
    "gn:asciiname":"Nipahsendanu",
    "gn:country_code":"ID",
    "gn:dem":13,
    "gn:feature_class":"P",
    "gn:feature_code":"PPL",
    "gn:name":"Nipahsendanu",
    "gn:population":0,
    "gn:timezone":"Asia/Jakarta",
    "iso:country":"ID",
    "name:ind_x_preferred":[
        "Nipahsendanu"
    ],
    "wof:name":"Nipahsendanu",
    "wof:placetype":"locality"
},
  "geometry": {"coordinates":[103.02826,0.8756],"type":"Point"}
}