{
  "type": "Feature",
  "properties": {
    "gn:admin1_code":"30.0",
    "gn:asciiname":"Citaraje Tiga",
    "gn:country_code":"ID",
    "gn:dem":252,
    "gn:feature_class":"P",
    "gn:feature_code":"PPL",
    "gn:name":"Citaraje Tiga",
    "gn:population":0,
    "gn:timezone":"Asia/Jakarta",
    "iso:country":"ID",
    "name:ind_x_preferred":[
        "Citaraje Tiga"
    ],
    "wof:name":"Citaraje Tiga",
    "wof:placetype":"locality"
},
  "geometry": {"coordinates":[106.5962,-7.276],"type":"Point"}
}