{
  "type": "Feature",
  "properties": {
    "gn:admin1_code":"7.0",
    "gn:asciiname":"Ngargorejo",
    "gn:country_code":"ID",
    "gn:dem":113,
    "gn:feature_class":"P",
    "gn:feature_code":"PPL",
    "gn:name":"Ngargorejo",
    "gn:population":0,
    "gn:timezone":"Asia/Jakarta",
    "iso:country":"ID",
    "wof:name":"Ngargorejo",
    "wof:placetype":"locality"
},
  "geometry": {"coordinates":[110.84305999999999,-7.2925],"type":"Point"}
}