{
  "type": "Feature",
  "properties": {
    "gn:admin1_code":"34.0",
    "gn:asciiname":"Totediti",
    "gn:country_code":"ID",
    "gn:dem":13,
    "gn:feature_class":"P",
    "gn:feature_code":"PPL",
    "gn:name":"Totediti",
    "gn:population":0,
    "gn:timezone":"Asia/Makassar",
    "iso:country":"ID",
    "name:ind_x_preferred":[
        "Totediti"
    ],
    "wof:name":"Totediti",
    "wof:placetype":"locality"
},
  "geometry": {"coordinates":[123.1176,0.8911],"type":"Point"}
}