{
  "type": "Feature",
  "properties": {
    "gn:admin1_code":"08",
    "gn:asciiname":"Londuwak Dua",
    "gn:cc2":"ID",
    "gn:country_code":"ID",
    "gn:dem":127,
    "gn:feature_class":"P",
    "gn:feature_code":"PPL",
    "gn:name":"Londuwak Dua",
    "gn:population":0,
    "gn:timezone":"Asia/Jakarta",
    "iso:country":"ID",
    "name:und_x_variant":[
        "Londuwak 2",
        "Londuwak Dua"
    ],
    "wof:name":"Londuwak Dua",
    "wof:placetype":"locality"
},
  "geometry": {"coordinates":[112.97556000000002,-7.08222],"type":"Point"}
}