{
  "type": "Feature",
  "properties": {
    "gn:admin1_code":"30.0",
    "gn:asciiname":"Samanggen",
    "gn:country_code":"ID",
    "gn:dem":715,
    "gn:feature_class":"P",
    "gn:feature_code":"PPLA4",
    "gn:name":"Samanggen",
    "gn:population":0,
    "gn:timezone":"Asia/Jakarta",
    "iso:country":"ID",
    "name:ind_x_preferred":[
        "Samanggen"
    ],
    "wof:lang_x_official":[
        "ind"
    ],
    "wof:lang_x_spoken":[
        "ind",
        "eng"
    ],
    "wof:name":"Samanggen",
    "wof:placetype":"locality"
},
  "geometry": {"coordinates":[107.9838,-7.1679],"type":"Point"}
}