{
  "type": "Feature",
  "properties": {
    "gn:admin1_code":"33.0",
    "gn:asciiname":"Kubang",
    "gn:country_code":"ID",
    "gn:dem":24,
    "gn:feature_class":"P",
    "gn:feature_code":"PPL",
    "gn:name":"Kubang",
    "gn:population":0,
    "gn:timezone":"Asia/Jakarta",
    "iso:country":"ID",
    "name:ceb_x_preferred":[
        "Kubang"
    ],
    "name:ind_x_preferred":[
        "Kubang"
    ],
    "name:min_x_preferred":[
        "Kubang"
    ],
    "name:msa_x_preferred":[
        "Kubang"
    ],
    "name:nld_x_preferred":[
        "Kubang"
    ],
    "name:swe_x_preferred":[
        "Kubang"
    ],
    "wof:lang_x_official":[
        "ind"
    ],
    "wof:lang_x_spoken":[
        "ind",
        "eng"
    ],
    "wof:name":"Kubang",
    "wof:placetype":"locality"
},
  "geometry": {"coordinates":[105.8355,-6.3404],"type":"Point"}
}