{
  "type": "Feature",
  "properties": {
    "gn:admin1_code":"28.0",
    "gn:asciiname":"Sanahu",
    "gn:country_code":"ID",
    "gn:dem":8,
    "gn:feature_class":"P",
    "gn:feature_code":"PPL",
    "gn:name":"Sanahu",
    "gn:population":0,
    "gn:timezone":"Asia/Jayapura",
    "iso:country":"ID",
    "name:ind_x_preferred":[
        "Sanahu"
    ],
    "wof:name":"Sanahu",
    "wof:placetype":"locality"
},
  "geometry": {"coordinates":[128.72125,-3.31379],"type":"Point"}
}