{
  "type": "Feature",
  "properties": {
    "gn:admin1_code":"26",
    "gn:asciiname":"Sikunikan Satu",
    "gn:country_code":"ID",
    "gn:dem":1077,
    "gn:feature_class":"P",
    "gn:feature_code":"PPL",
    "gn:name":"Sikunikan Satu",
    "gn:population":0,
    "gn:timezone":"Asia/Jakarta",
    "iso:country":"ID",
    "name:ind_x_preferred":[
        "Sikunikan Satu"
    ],
    "name:und_x_variant":[
        "Sikunikan 1"
    ],
    "wof:name":"Sikunikan Satu",
    "wof:placetype":"locality"
},
  "geometry": {"coordinates":[98.41030000000001,2.7389],"type":"Point"}
}