{
  "type": "Feature",
  "properties": {
    "gn:admin1_code":"7",
    "gn:asciiname":"Babadan",
    "gn:country_code":"ID",
    "gn:dem":414,
    "gn:feature_class":"P",
    "gn:feature_code":"PPL",
    "gn:name":"Babadan",
    "gn:population":0,
    "gn:timezone":"Asia/Jakarta",
    "iso:country":"ID",
    "name:ind_x_preferred":[
        "Babadan"
    ],
    "wof:lang_x_official":[
        "ind"
    ],
    "wof:lang_x_spoken":[
        "ind",
        "eng"
    ],
    "wof:name":"Babadan",
    "wof:placetype":"locality"
},
  "geometry": {"coordinates":[110.41417,-7.16083],"type":"Point"}
}