{
  "type": "Feature",
  "properties": {
    "gn:admin1_code":"1",
    "gn:asciiname":"Lungkalamuning",
    "gn:country_code":"ID",
    "gn:dem":88,
    "gn:feature_class":"P",
    "gn:feature_code":"PPL",
    "gn:name":"Lungkalamuning",
    "gn:population":0,
    "gn:timezone":"Asia/Jakarta",
    "iso:country":"ID",
    "name:ind_x_preferred":[
        "Lungkalamuning"
    ],
    "wof:name":"Lungkalamuning",
    "wof:placetype":"locality"
},
  "geometry": {"coordinates":[97.8536,4.1898],"type":"Point"}
}