{
  "type": "Feature",
  "properties": {
    "gn:admin1_code":"1",
    "gn:asciiname":"Matang Nibong",
    "gn:country_code":"ID",
    "gn:dem":2,
    "gn:feature_class":"P",
    "gn:feature_code":"PPL",
    "gn:name":"Matang Nibong",
    "gn:population":0,
    "gn:timezone":"Asia/Jakarta",
    "iso:country":"ID",
    "name:ind_x_preferred":[
        "Matang Nibong"
    ],
    "wof:name":"Matang Nibong",
    "wof:placetype":"locality"
},
  "geometry": {"coordinates":[97.3539,5.1155],"type":"Point"}
}