{
  "type": "Feature",
  "properties": {
    "gn:admin1_code":"8.0",
    "gn:asciiname":"Genengan Kulon",
    "gn:country_code":"ID",
    "gn:dem":94,
    "gn:feature_class":"P",
    "gn:feature_code":"PPLA4",
    "gn:name":"Genengan Kulon",
    "gn:population":0,
    "gn:timezone":"Asia/Jakarta",
    "iso:country":"ID",
    "name:ind_x_preferred":[
        "Genengan Kulon"
    ],
    "wof:name":"Genengan Kulon",
    "wof:placetype":"locality"
},
  "geometry": {"coordinates":[111.83620000000001,-8.1302],"type":"Point"}
}