{
  "type": "Feature",
  "properties": {
    "gn:admin1_code":"33.0",
    "gn:asciiname":"Numpi",
    "gn:country_code":"ID",
    "gn:dem":466,
    "gn:feature_class":"P",
    "gn:feature_code":"PPL",
    "gn:name":"Numpi",
    "gn:population":0,
    "gn:timezone":"Asia/Jakarta",
    "iso:country":"ID",
    "name:ind_x_preferred":[
        "Numpi"
    ],
    "wof:name":"Numpi",
    "wof:placetype":"locality"
},
  "geometry": {"coordinates":[106.009,-6.2941],"type":"Point"}
}