{
  "type": "Feature",
  "properties": {
    "gn:admin1_code":"1",
    "gn:asciiname":"Cotpange",
    "gn:country_code":"ID",
    "gn:dem":18,
    "gn:feature_class":"P",
    "gn:feature_code":"PPL",
    "gn:name":"Cotpange",
    "gn:population":0,
    "gn:timezone":"Asia/Jakarta",
    "iso:country":"ID",
    "name:ind_x_preferred":[
        "Cotpange"
    ],
    "wof:name":"Cotpange",
    "wof:placetype":"locality"
},
  "geometry": {"coordinates":[95.5098,4.8209],"type":"Point"}
}