{
  "type": "Feature",
  "properties": {
    "gn:admin1_code":"26",
    "gn:asciiname":"Panombean Dua",
    "gn:country_code":"ID",
    "gn:dem":116,
    "gn:feature_class":"P",
    "gn:feature_code":"PPL",
    "gn:name":"Panombean Dua",
    "gn:population":0,
    "gn:timezone":"Asia/Jakarta",
    "iso:country":"ID",
    "name:ind_x_preferred":[
        "Panombean Dua"
    ],
    "name:und_x_variant":[
        "Panombean 2"
    ],
    "wof:name":"Panombean Dua",
    "wof:placetype":"locality"
},
  "geometry": {"coordinates":[99.2903,3.0088],"type":"Point"}
}