{
  "type": "Feature",
  "properties": {
    "gn:admin1_code":"8.0",
    "gn:asciiname":"Sumurpawon",
    "gn:country_code":"ID",
    "gn:dem":17,
    "gn:feature_class":"P",
    "gn:feature_code":"PPL",
    "gn:name":"Sumurpawon",
    "gn:population":0,
    "gn:timezone":"Asia/Jakarta",
    "iso:country":"ID",
    "name:ind_x_preferred":[
        "Sumurpawon"
    ],
    "wof:name":"Sumurpawon",
    "wof:placetype":"locality"
},
  "geometry": {"coordinates":[111.9708,-6.7722],"type":"Point"}
}