{
  "type": "Feature",
  "properties": {
    "gn:admin1_code":"28.0",
    "gn:asciiname":"Latu",
    "gn:country_code":"ID",
    "gn:dem":6,
    "gn:feature_class":"P",
    "gn:feature_code":"PPL",
    "gn:name":"Latu",
    "gn:population":0,
    "gn:timezone":"Asia/Jayapura",
    "iso:country":"ID",
    "name:ind_x_preferred":[
        "Latu"
    ],
    "name:und_x_variant":[
        "Latoe",
        "Latu"
    ],
    "wof:name":"Latu",
    "wof:placetype":"locality"
},
  "geometry": {"coordinates":[128.68885,-3.41972],"type":"Point"}
}