{
  "type": "Feature",
  "properties": {
    "gn:admin1_code":"36.0",
    "gn:asciiname":"Rotambrug",
    "gn:country_code":"ID",
    "gn:dem":110,
    "gn:feature_class":"P",
    "gn:feature_code":"PPL",
    "gn:name":"Rotambrug",
    "gn:population":0,
    "gn:timezone":"Asia/Jayapura",
    "iso:country":"ID",
    "name:ind_x_preferred":[
        "Rotambrug"
    ],
    "name:und_x_variant":[
        "Rotanbrug"
    ],
    "wof:name":"Rotambrug",
    "wof:placetype":"locality"
},
  "geometry": {"coordinates":[138.5256,-3.3212],"type":"Point"}
}