{
  "type": "Feature",
  "properties": {
    "gn:admin1_code":"07",
    "gn:asciiname":"Jragung",
    "gn:cc2":"ID",
    "gn:country_code":"ID",
    "gn:dem":34,
    "gn:feature_class":"P",
    "gn:feature_code":"PPL",
    "gn:name":"Jragung",
    "gn:population":0,
    "gn:timezone":"Asia/Jakarta",
    "iso:country":"ID",
    "name:und_x_variant":[
        "Djragung",
        "Jragung"
    ],
    "wof:name":"Jragung",
    "wof:placetype":"locality"
},
  "geometry": {"coordinates":[110.565,-7.11722],"type":"Point"}
}