{
  "type": "Feature",
  "properties": {
    "gn:admin1_code":"30",
    "gn:asciiname":"Wonosari",
    "gn:country_code":"ID",
    "gn:dem":74,
    "gn:feature_class":"P",
    "gn:feature_code":"PPL",
    "gn:name":"Wonosari",
    "gn:population":0,
    "gn:timezone":"Asia/Jakarta",
    "iso:country":"ID",
    "name:ceb_x_preferred":[
        "Kecamatan Wonosari"
    ],
    "name:ind_x_preferred":[
        "Wonosari"
    ],
    "name:jav_x_preferred":[
        "Wanasari"
    ],
    "name:msa_x_preferred":[
        "Wonosari"
    ],
    "name:sun_x_preferred":[
        "Wonosari"
    ],
    "name:szl_x_preferred":[
        "Wonosari"
    ],
    "wof:name":"Wonosari",
    "wof:placetype":"locality"
},
  "geometry": {"coordinates":[112.8848,-7.7512],"type":"Point"}
}