{
  "type": "Feature",
  "properties": {
    "gn:admin1_code":"08",
    "gn:asciiname":"Sidodadi",
    "gn:country_code":"ID",
    "gn:dem":460,
    "gn:feature_class":"P",
    "gn:feature_code":"PPL",
    "gn:name":"Sidodadi",
    "gn:population":0,
    "gn:timezone":"Asia/Jakarta",
    "iso:country":"ID",
    "name:ind_x_preferred":[
        "Sidodadi"
    ],
    "name:und_x_variant":[
        "Dawuhan 2",
        "Dawuhan Dua"
    ],
    "wof:lang_x_official":[
        "ind"
    ],
    "wof:lang_x_spoken":[
        "ind",
        "eng"
    ],
    "wof:name":"Sidodadi",
    "wof:placetype":"locality"
},
  "geometry": {"coordinates":[112.6833,-8.0856],"type":"Point"}
}