{
  "type": "Feature",
  "properties": {
    "gn:admin1_code":"15.0",
    "gn:asciiname":"Umbuljaya",
    "gn:country_code":"ID",
    "gn:dem":216,
    "gn:feature_class":"P",
    "gn:feature_code":"PPL",
    "gn:name":"Umbuljaya",
    "gn:population":0,
    "gn:timezone":"Asia/Jakarta",
    "iso:country":"ID",
    "name:ind_x_preferred":[
        "Umbuljaya"
    ],
    "wof:name":"Umbuljaya",
    "wof:placetype":"locality"
},
  "geometry": {"coordinates":[105.05524,-5.61223],"type":"Point"}
}