{
  "type": "Feature",
  "properties": {
    "gn:admin1_code":"10.0",
    "gn:asciiname":"Tegalmindi",
    "gn:country_code":"ID",
    "gn:dem":244,
    "gn:feature_class":"P",
    "gn:feature_code":"PPL",
    "gn:name":"Tegalmindi",
    "gn:population":0,
    "gn:timezone":"Asia/Jakarta",
    "iso:country":"ID",
    "wof:name":"Tegalmindi",
    "wof:placetype":"locality"
},
  "geometry": {"coordinates":[110.39417,-7.71639],"type":"Point"}
}