{
  "type": "Feature",
  "properties": {
    "gn:admin1_code":"38.0",
    "gn:asciiname":"Kassa",
    "gn:country_code":"ID",
    "gn:dem":112,
    "gn:feature_class":"P",
    "gn:feature_code":"PPL",
    "gn:name":"Kassa",
    "gn:population":0,
    "gn:timezone":"Asia/Makassar",
    "iso:country":"ID",
    "name:ind_x_preferred":[
        "Kassa"
    ],
    "name:und_x_variant":[
        "Kasa",
        "Kassa"
    ],
    "wof:name":"Kassa",
    "wof:placetype":"locality"
},
  "geometry": {"coordinates":[119.693,-3.5998],"type":"Point"}
}