{
  "type": "Feature",
  "properties": {
    "gn:admin1_code":"30",
    "gn:asciiname":"Kedungjumbleng",
    "gn:country_code":"ID",
    "gn:dem":99,
    "gn:feature_class":"P",
    "gn:feature_code":"PPL",
    "gn:name":"Kedungjumbleng",
    "gn:population":0,
    "gn:timezone":"Asia/Jakarta",
    "iso:country":"ID",
    "name:ind_x_preferred":[
        "Kedungjumbleng"
    ],
    "wof:lang_x_official":[
        "ind"
    ],
    "wof:lang_x_spoken":[
        "ind",
        "eng"
    ],
    "wof:name":"Kedungjumbleng",
    "wof:placetype":"locality"
},
  "geometry": {"coordinates":[108.53570000000001,-6.7829],"type":"Point"}
}