{
  "type": "Feature",
  "properties": {
    "gn:admin1_code":"2",
    "gn:asciiname":"Banjar Batudingding",
    "gn:country_code":"ID",
    "gn:dem":260,
    "gn:feature_class":"P",
    "gn:feature_code":"PPL",
    "gn:name":"Banjar Batudingding",
    "gn:population":0,
    "gn:timezone":"Asia/Makassar",
    "iso:country":"ID",
    "name:ind_x_preferred":[
        "Banjar Batudingding"
    ],
    "wof:name":"Banjar Batudingding",
    "wof:placetype":"locality"
},
  "geometry": {"coordinates":[115.1379,-8.1598],"type":"Point"}
}