{
  "type": "Feature",
  "properties": {
    "gn:admin1_code":"37.0",
    "gn:asciiname":"Muaradanau",
    "gn:country_code":"ID",
    "gn:dem":113,
    "gn:feature_class":"P",
    "gn:feature_code":"PPL",
    "gn:name":"Muaradanau",
    "gn:population":0,
    "gn:timezone":"Asia/Jakarta",
    "iso:country":"ID",
    "name:ind_x_preferred":[
        "Muaradanau"
    ],
    "wof:name":"Muaradanau",
    "wof:placetype":"locality"
},
  "geometry": {"coordinates":[102.33060999999999,-0.87103],"type":"Point"}
}