{
  "type": "Feature",
  "properties": {
    "gn:admin1_code":"34",
    "gn:asciiname":"Sukadamai",
    "gn:country_code":"ID",
    "gn:dem":49,
    "gn:feature_class":"P",
    "gn:feature_code":"PPL",
    "gn:name":"Sukadamai",
    "gn:population":0,
    "gn:timezone":"Asia/Makassar",
    "iso:country":"ID",
    "name:ind_x_preferred":[
        "Sukadamai"
    ],
    "wof:name":"Sukadamai",
    "wof:placetype":"locality"
},
  "geometry": {"coordinates":[122.4383,0.7714],"type":"Point"}
}