{
  "type": "Feature",
  "properties": {
    "gn:admin1_code":"7",
    "gn:asciiname":"Kongsi",
    "gn:country_code":"ID",
    "gn:dem":4,
    "gn:feature_class":"P",
    "gn:feature_code":"PPL",
    "gn:name":"Kongsi",
    "gn:population":0,
    "gn:timezone":"Asia/Jakarta",
    "iso:country":"ID",
    "name:fra_x_preferred":[
        "Kongsi"
    ],
    "name:ind_x_preferred":[
        "Kongsi"
    ],
    "name:nld_x_preferred":[
        "Kongsi"
    ],
    "name:zho_x_preferred":[
        "\u540c\u4e61\u4f1a\u9986"
    ],
    "wof:lang_x_official":[
        "ind"
    ],
    "wof:lang_x_spoken":[
        "ind",
        "eng"
    ],
    "wof:name":"Kongsi",
    "wof:placetype":"locality"
},
  "geometry": {"coordinates":[110.5463,-6.8253],"type":"Point"}
}