{
  "type": "Feature",
  "properties": {
    "gn:admin1_code":"38",
    "gn:asciiname":"Assorajang",
    "gn:country_code":"ID",
    "gn:dem":14,
    "gn:feature_class":"P",
    "gn:feature_code":"PPL",
    "gn:name":"Assorajang",
    "gn:population":0,
    "gn:timezone":"Asia/Makassar",
    "iso:country":"ID",
    "name:ind_x_preferred":[
        "Assorajang"
    ],
    "wof:name":"Assorajang",
    "wof:placetype":"locality"
},
  "geometry": {"coordinates":[119.5912,-4.6827],"type":"Point"}
}