{
  "type": "Feature",
  "properties": {
    "gn:admin1_code":"15.0",
    "gn:asciiname":"Umbulan Saniprancang",
    "gn:country_code":"ID",
    "gn:dem":96,
    "gn:feature_class":"P",
    "gn:feature_code":"PPL",
    "gn:name":"Umbulan Saniprancang",
    "gn:population":0,
    "gn:timezone":"Asia/Jakarta",
    "iso:country":"ID",
    "name:ind_x_preferred":[
        "Umbulan Saniprancang"
    ],
    "wof:name":"Umbulan Saniprancang",
    "wof:placetype":"locality"
},
  "geometry": {"coordinates":[104.83327,-4.99425],"type":"Point"}
}