{
  "type": "Feature",
  "properties": {
    "gn:admin1_code":"22.0",
    "gn:asciiname":"Buanakarya",
    "gn:country_code":"ID",
    "gn:dem":32,
    "gn:feature_class":"P",
    "gn:feature_code":"PPL",
    "gn:name":"Buanakarya",
    "gn:population":0,
    "gn:timezone":"Asia/Makassar",
    "iso:country":"ID",
    "name:ind_x_preferred":[
        "Buanakarya"
    ],
    "wof:name":"Buanakarya",
    "wof:placetype":"locality"
},
  "geometry": {"coordinates":[122.04430000000001,-3.8215],"type":"Point"}
}