{
  "type": "Feature",
  "properties": {
    "gn:admin1_code":"37",
    "gn:asciiname":"Batublok",
    "gn:country_code":"ID",
    "gn:dem":12,
    "gn:feature_class":"P",
    "gn:feature_code":"PPL",
    "gn:name":"Batublok",
    "gn:population":0,
    "gn:timezone":"Asia/Jakarta",
    "iso:country":"ID",
    "name:ind_x_preferred":[
        "Batublok"
    ],
    "wof:name":"Batublok",
    "wof:placetype":"locality"
},
  "geometry": {"coordinates":[101.44995,1.63241],"type":"Point"}
}