{
  "type": "Feature",
  "properties": {
    "gn:admin1_code":"26.0",
    "gn:asciiname":"Huta Ginjang Dua",
    "gn:country_code":"ID",
    "gn:dem":1378,
    "gn:feature_class":"P",
    "gn:feature_code":"PPL",
    "gn:name":"Huta Ginjang Dua",
    "gn:population":0,
    "gn:timezone":"Asia/Jakarta",
    "iso:country":"ID",
    "name:ind_x_preferred":[
        "Huta Ginjang Dua"
    ],
    "name:und_x_variant":[
        "Huta Ginjang 2"
    ],
    "wof:lang_x_official":[
        "ind"
    ],
    "wof:lang_x_spoken":[
        "ind",
        "eng"
    ],
    "wof:name":"Huta Ginjang Dua",
    "wof:placetype":"locality"
},
  "geometry": {"coordinates":[98.6801,2.1913],"type":"Point"}
}