{
  "type": "Feature",
  "properties": {
    "gn:admin1_code":"30",
    "gn:asciiname":"Ciburayut Kidul",
    "gn:country_code":"ID",
    "gn:dem":597,
    "gn:feature_class":"P",
    "gn:feature_code":"PPL",
    "gn:name":"Ciburayut Kidul",
    "gn:population":0,
    "gn:timezone":"Asia/Jakarta",
    "iso:country":"ID",
    "name:ind_x_preferred":[
        "Ciburayut Kidul"
    ],
    "wof:lang_x_official":[
        "ind"
    ],
    "wof:lang_x_spoken":[
        "ind",
        "eng"
    ],
    "wof:name":"Ciburayut Kidul",
    "wof:placetype":"locality"
},
  "geometry": {"coordinates":[106.79056,-6.72],"type":"Point"}
}