{
  "type": "Feature",
  "properties": {
    "gn:admin1_code":"8.0",
    "gn:asciiname":"Mor Laok",
    "gn:country_code":"ID",
    "gn:dem":2,
    "gn:feature_class":"P",
    "gn:feature_code":"PPL",
    "gn:name":"Mor Laok",
    "gn:population":0,
    "gn:timezone":"Asia/Jakarta",
    "iso:country":"ID",
    "name:ind_x_preferred":[
        "Mor Laok"
    ],
    "wof:name":"Mor Laok",
    "wof:placetype":"locality"
},
  "geometry": {"coordinates":[113.0724,-7.129],"type":"Point"}
}