{
  "type": "Feature",
  "properties": {
    "gn:admin1_code":"26",
    "gn:asciiname":"Kampung Mangga",
    "gn:country_code":"ID",
    "gn:dem":9,
    "gn:feature_class":"P",
    "gn:feature_code":"PPL",
    "gn:name":"Kampung Mangga",
    "gn:population":0,
    "gn:timezone":"Asia/Jakarta",
    "iso:country":"ID",
    "name:ind_x_preferred":[
        "Kampung Mangga"
    ],
    "wof:name":"Kampung Mangga",
    "wof:placetype":"locality"
},
  "geometry": {"coordinates":[98.5097,3.7765],"type":"Point"}
}