{
  "type": "Feature",
  "properties": {
    "gn:admin1_code":"07",
    "gn:asciiname":"Pandakanngaglik",
    "gn:country_code":"ID",
    "gn:dem":282,
    "gn:feature_class":"P",
    "gn:feature_code":"PPL",
    "gn:name":"Pandakanngaglik",
    "gn:population":0,
    "gn:timezone":"Asia/Jakarta",
    "iso:country":"ID",
    "wof:name":"Pandakanngaglik",
    "wof:placetype":"locality"
},
  "geometry": {"coordinates":[110.99833,-7.64639],"type":"Point"}
}