{
  "type": "Feature",
  "properties": {
    "gn:admin1_code":"7",
    "gn:asciiname":"Kedungbulus Timur",
    "gn:country_code":"ID",
    "gn:dem":87,
    "gn:feature_class":"P",
    "gn:feature_code":"PPL",
    "gn:name":"Kedungbulus Timur",
    "gn:population":0,
    "gn:timezone":"Asia/Jakarta",
    "iso:country":"ID",
    "name:ind_x_preferred":[
        "Kedungbulus Timur"
    ],
    "wof:name":"Kedungbulus Timur",
    "wof:placetype":"locality"
},
  "geometry": {"coordinates":[111.1375,-7.34944],"type":"Point"}
}