{
  "type": "Feature",
  "properties": {
    "gn:admin1_code":"38",
    "gn:asciiname":"Jira",
    "gn:country_code":"ID",
    "gn:dem":255,
    "gn:feature_class":"P",
    "gn:feature_code":"PPL",
    "gn:name":"Jira",
    "gn:population":0,
    "gn:timezone":"Asia/Makassar",
    "iso:country":"ID",
    "name:ces_x_preferred":[
        "J\u00edra"
    ],
    "name:deu_x_preferred":[
        "Jira"
    ],
    "name:ind_x_preferred":[
        "Jira"
    ],
    "name:pol_x_preferred":[
        "Jira"
    ],
    "wof:lang_x_official":[
        "ind"
    ],
    "wof:lang_x_spoken":[
        "ind",
        "eng"
    ],
    "wof:name":"Jira",
    "wof:placetype":"locality"
},
  "geometry": {"coordinates":[120.1108,-5.1676],"type":"Point"}
}