{
  "type": "Feature",
  "properties": {
    "gn:admin1_code":"01",
    "gn:asciiname":"Blangpulo",
    "gn:country_code":"ID",
    "gn:dem":10,
    "gn:feature_class":"P",
    "gn:feature_code":"PPLA3",
    "gn:name":"Blangpulo",
    "gn:population":0,
    "gn:timezone":"Asia/Jakarta",
    "iso:country":"ID",
    "name:ind_x_preferred":[
        "Blangpulo"
    ],
    "wof:name":"Blangpulo",
    "wof:placetype":"locality"
},
  "geometry": {"coordinates":[97.07743000000001,5.2068],"type":"Point"}
}