{
  "type": "Feature",
  "properties": {
    "gn:admin1_code":"26",
    "gn:asciiname":"Simarbdloluk Dua",
    "gn:country_code":"ID",
    "gn:dem":1312,
    "gn:feature_class":"P",
    "gn:feature_code":"PPL",
    "gn:name":"Simarbdloluk Dua",
    "gn:population":0,
    "gn:timezone":"Asia/Jakarta",
    "iso:country":"ID",
    "name:ind_x_preferred":[
        "Simarbdloluk Dua"
    ],
    "name:und_x_variant":[
        "Simarbdloluk 2"
    ],
    "wof:lang_x_official":[
        "ind"
    ],
    "wof:lang_x_spoken":[
        "ind",
        "eng"
    ],
    "wof:name":"Simarbdloluk Dua",
    "wof:placetype":"locality"
},
  "geometry": {"coordinates":[99.2379,2.3745],"type":"Point"}
}