{
  "type": "Feature",
  "properties": {
    "gn:admin1_code":"1",
    "gn:asciiname":"Suak Seumaseh",
    "gn:country_code":"ID",
    "gn:dem":10,
    "gn:feature_class":"P",
    "gn:feature_code":"PPL",
    "gn:name":"Suak Seumaseh",
    "gn:population":0,
    "gn:timezone":"Asia/Jakarta",
    "iso:country":"ID",
    "name:ind_x_preferred":[
        "Suak Seumaseh"
    ],
    "wof:name":"Suak Seumaseh",
    "wof:placetype":"locality"
},
  "geometry": {"coordinates":[95.9752,4.2694],"type":"Point"}
}