{
  "type": "Feature",
  "properties": {
    "gn:admin1_code":"38.0",
    "gn:asciiname":"Siapi",
    "gn:country_code":"ID",
    "gn:dem":828,
    "gn:feature_class":"P",
    "gn:feature_code":"PPL",
    "gn:name":"Siapi",
    "gn:population":0,
    "gn:timezone":"Asia/Makassar",
    "iso:country":"ID",
    "name:ind_x_preferred":[
        "Siapi"
    ],
    "wof:name":"Siapi",
    "wof:placetype":"locality"
},
  "geometry": {"coordinates":[119.4564,-3.317],"type":"Point"}
}