{
  "type": "Feature",
  "properties": {
    "gn:admin1_code":"18.0",
    "gn:asciiname":"Karai",
    "gn:country_code":"ID",
    "gn:dem":84,
    "gn:feature_class":"P",
    "gn:feature_code":"PPL",
    "gn:name":"Karai",
    "gn:population":0,
    "gn:timezone":"Asia/Makassar",
    "iso:country":"ID",
    "name:ceb_x_preferred":[
        "Karai"
    ],
    "name:deu_x_preferred":[
        "Karai"
    ],
    "name:fra_x_preferred":[
        "Karai"
    ],
    "name:ind_x_preferred":[
        "Karai"
    ],
    "wof:lang_x_official":[
        "ind"
    ],
    "wof:lang_x_spoken":[
        "ind",
        "eng"
    ],
    "wof:name":"Karai",
    "wof:placetype":"locality"
},
  "geometry": {"coordinates":[119.4492,-9.7264],"type":"Point"}
}