{
  "type": "Feature",
  "properties": {
    "gn:admin1_code":"18.0",
    "gn:asciiname":"Ayofanu",
    "gn:country_code":"ID",
    "gn:dem":987,
    "gn:feature_class":"P",
    "gn:feature_code":"PPLA4",
    "gn:name":"Ayofanu",
    "gn:population":0,
    "gn:timezone":"Asia/Makassar",
    "iso:country":"ID",
    "name:ind_x_preferred":[
        "Ayofanu"
    ],
    "wof:name":"Ayofanu",
    "wof:placetype":"locality"
},
  "geometry": {"coordinates":[124.5908,-9.8753],"type":"Point"}
}