{
  "type": "Feature",
  "properties": {
    "gn:admin1_code":"7.0",
    "gn:asciiname":"Kedungwringin",
    "gn:country_code":"ID",
    "gn:dem":102,
    "gn:feature_class":"P",
    "gn:feature_code":"PPL",
    "gn:name":"Kedungwringin",
    "gn:population":0,
    "gn:timezone":"Asia/Jakarta",
    "iso:country":"ID",
    "name:ind_x_preferred":[
        "Kedungwringin"
    ],
    "name:und_x_variant":[
        "Kedoengwringin"
    ],
    "wof:name":"Kedungwringin",
    "wof:placetype":"locality"
},
  "geometry": {"coordinates":[109.50917,-7.54528],"type":"Point"}
}