{
  "type": "Feature",
  "properties": {
    "gn:admin1_code":"1",
    "gn:asciiname":"Bulusema",
    "gn:country_code":"ID",
    "gn:dem":20,
    "gn:feature_class":"P",
    "gn:feature_code":"PPL",
    "gn:name":"Bulusema",
    "gn:population":0,
    "gn:timezone":"Asia/Jakarta",
    "iso:country":"ID",
    "name:ind_x_preferred":[
        "Bulusema"
    ],
    "wof:name":"Bulusema",
    "wof:placetype":"locality"
},
  "geometry": {"coordinates":[98.0363,2.5077],"type":"Point"}
}