{
  "type": "Feature",
  "properties": {
    "gn:admin1_code":"7.0",
    "gn:asciiname":"Sijo",
    "gn:country_code":"ID",
    "gn:dem":297,
    "gn:feature_class":"P",
    "gn:feature_code":"PPL",
    "gn:name":"Sijo",
    "gn:population":0,
    "gn:timezone":"Asia/Jakarta",
    "iso:country":"ID",
    "name:ces_x_preferred":[
        "Sid\u017eo"
    ],
    "name:deu_x_preferred":[
        "Sijo"
    ],
    "name:fra_x_preferred":[
        "Sijo"
    ],
    "name:hun_x_preferred":[
        "Sidzso"
    ],
    "name:hye_x_preferred":[
        "\u054d\u056b\u057b\u0578"
    ],
    "name:ind_x_preferred":[
        "Sijo"
    ],
    "name:ita_x_preferred":[
        "Sijo"
    ],
    "name:jav_x_preferred":[
        "Sijo"
    ],
    "name:nep_x_preferred":[
        "\u0938\u093f\u091c\u094b"
    ],
    "name:rus_x_preferred":[
        "\u0421\u0438\u0434\u0436\u043e"
    ],
    "name:spa_x_preferred":[
        "Sijo"
    ],
    "name:ukr_x_preferred":[
        "\u0421\u0456\u0434\u0436\u043e"
    ],
    "name:vie_x_preferred":[
        "Sijo"
    ],
    "name:zho_x_preferred":[
        "\u6642\u8abf"
    ],
    "wof:lang_x_official":[
        "ind"
    ],
    "wof:lang_x_spoken":[
        "ind",
        "eng"
    ],
    "wof:name":"Sijo",
    "wof:placetype":"locality"
},
  "geometry": {"coordinates":[110.06361,-7.79278],"type":"Point"}
}