{
  "type": "Feature",
  "properties": {
    "gn:admin1_code":"37",
    "gn:asciiname":"Perupuk",
    "gn:country_code":"ID",
    "gn:dem":15,
    "gn:feature_class":"P",
    "gn:feature_code":"PPL",
    "gn:name":"Perupuk",
    "gn:population":0,
    "gn:timezone":"Asia/Jakarta",
    "iso:country":"ID",
    "name:ind_x_preferred":[
        "Perupuk"
    ],
    "wof:name":"Perupuk",
    "wof:placetype":"locality"
},
  "geometry": {"coordinates":[101.4534,0.371],"type":"Point"}
}