{
  "type": "Feature",
  "properties": {
    "gn:admin1_code":"30.0",
    "gn:asciiname":"Cibangkong",
    "gn:country_code":"ID",
    "gn:dem":500,
    "gn:feature_class":"P",
    "gn:feature_code":"PPL",
    "gn:name":"Cibangkong",
    "gn:population":0,
    "gn:timezone":"Asia/Jakarta",
    "iso:country":"ID",
    "name:ind_x_preferred":[
        "Cibangkong"
    ],
    "name:und_x_variant":[
        "Tjibangkong"
    ],
    "wof:lang_x_official":[
        "ind"
    ],
    "wof:lang_x_spoken":[
        "ind",
        "eng"
    ],
    "wof:name":"Cibangkong",
    "wof:placetype":"locality"
},
  "geometry": {"coordinates":[108.48609999999999,-7.1604],"type":"Point"}
}