{
  "type": "Feature",
  "properties": {
    "gn:admin1_code":"8.0",
    "gn:asciiname":"Pandan",
    "gn:country_code":"ID",
    "gn:dem":165,
    "gn:feature_class":"P",
    "gn:feature_code":"PPL",
    "gn:name":"Pandan",
    "gn:population":0,
    "gn:timezone":"Asia/Jakarta",
    "iso:country":"ID",
    "name:ceb_x_preferred":[
        "Pandan"
    ],
    "name:deu_x_preferred":[
        "Pandan"
    ],
    "name:fra_x_preferred":[
        "Pandan"
    ],
    "name:ind_x_preferred":[
        "Pandan"
    ],
    "name:ita_x_preferred":[
        "Pandan"
    ],
    "name:msa_x_preferred":[
        "Pandan"
    ],
    "name:nld_x_preferred":[
        "Pandan"
    ],
    "name:swe_x_preferred":[
        "Pandan"
    ],
    "name:tgl_x_preferred":[
        "Pandan"
    ],
    "name:war_x_preferred":[
        "Pandan"
    ],
    "wof:lang_x_official":[
        "ind"
    ],
    "wof:lang_x_spoken":[
        "ind",
        "eng"
    ],
    "wof:name":"Pandan",
    "wof:placetype":"locality"
},
  "geometry": {"coordinates":[111.5964,-8.042],"type":"Point"}
}