{
  "type": "Feature",
  "properties": {
    "gn:admin1_code":"30",
    "gn:asciiname":"Pamayagan",
    "gn:cc2":"ID",
    "gn:country_code":"ID",
    "gn:dem":23,
    "gn:feature_class":"P",
    "gn:feature_code":"PPL",
    "gn:name":"Pamayagan",
    "gn:population":0,
    "gn:timezone":"Asia/Jakarta",
    "iso:country":"ID",
    "name:und_x_variant":[
        "Panajagan",
        "Pamayagan"
    ],
    "wof:name":"Pamayagan",
    "wof:placetype":"locality"
},
  "geometry": {"coordinates":[106.30889000000001,-6.22333],"type":"Point"}
}