{
  "type": "Feature",
  "properties": {
    "gn:admin1_code":"42.0",
    "gn:asciiname":"Tanjung Keramat Dua",
    "gn:country_code":"ID",
    "gn:dem":16,
    "gn:feature_class":"P",
    "gn:feature_code":"PPL",
    "gn:name":"Tanjung Keramat Dua",
    "gn:population":0,
    "gn:timezone":"Asia/Makassar",
    "iso:country":"ID",
    "name:ind_x_preferred":[
        "Tanjung Keramat Dua"
    ],
    "name:ind_x_variant":[
        "Tanjung Keramat 2",
        "Tanahmera",
        "Tanahmerah"
    ],
    "name:und_x_variant":[
        "Tandjungkeramat",
        "Tandjoengkeramat",
        "Tanjungkeramat"
    ],
    "wof:name":"Tanjung Keramat Dua",
    "wof:placetype":"locality"
},
  "geometry": {"coordinates":[117.52961999999999,3.66943],"type":"Point"}
}