{
  "type": "Feature",
  "properties": {
    "gn:admin1_code":"18.0",
    "gn:asciiname":"Bondokambala",
    "gn:country_code":"ID",
    "gn:dem":613,
    "gn:feature_class":"P",
    "gn:feature_code":"PPL",
    "gn:name":"Bondokambala",
    "gn:population":0,
    "gn:timezone":"Asia/Makassar",
    "iso:country":"ID",
    "name:ind_x_preferred":[
        "Bondokambala"
    ],
    "wof:name":"Bondokambala",
    "wof:placetype":"locality"
},
  "geometry": {"coordinates":[119.4479,-9.5257],"type":"Point"}
}