{
  "type": "Feature",
  "properties": {
    "gn:admin1_code":"37.0",
    "gn:asciiname":"Kebonrenahtanjungmalen",
    "gn:country_code":"ID",
    "gn:dem":267,
    "gn:feature_class":"P",
    "gn:feature_code":"PPL",
    "gn:name":"Kebonrenahtanjungmalen",
    "gn:population":0,
    "gn:timezone":"Asia/Jakarta",
    "iso:country":"ID",
    "name:ind_x_preferred":[
        "Kebonrenahtanjungmalen"
    ],
    "wof:name":"Kebonrenahtanjungmalen",
    "wof:placetype":"locality"
},
  "geometry": {"coordinates":[100.9143,-0.1286],"type":"Point"}
}