{
  "type": "Feature",
  "properties": {
    "gn:admin1_code":"38.0",
    "gn:asciiname":"Jawijawi",
    "gn:country_code":"ID",
    "gn:dem":497,
    "gn:feature_class":"P",
    "gn:feature_code":"PPL",
    "gn:name":"Jawijawi",
    "gn:population":0,
    "gn:timezone":"Asia/Makassar",
    "iso:country":"ID",
    "name:ind_x_preferred":[
        "Jawijawi"
    ],
    "name:und_x_variant":[
        "Djawidjawi"
    ],
    "wof:name":"Jawijawi",
    "wof:placetype":"locality"
},
  "geometry": {"coordinates":[119.90689999999999,-5.0285],"type":"Point"}
}