{
  "type": "Feature",
  "properties": {
    "gn:admin1_code":"8",
    "gn:asciiname":"Sokmaelang Lor",
    "gn:country_code":"ID",
    "gn:dem":638,
    "gn:feature_class":"P",
    "gn:feature_code":"PPL",
    "gn:name":"Sokmaelang Lor",
    "gn:population":0,
    "gn:timezone":"Asia/Jakarta",
    "iso:country":"ID",
    "name:ind_x_preferred":[
        "Sokmaelang Lor"
    ],
    "wof:name":"Sokmaelang Lor",
    "wof:placetype":"locality"
},
  "geometry": {"coordinates":[114.1341,-7.8935],"type":"Point"}
}