{
  "type": "Feature",
  "properties": {
    "gn:admin1_code":"18.0",
    "gn:asciiname":"Tublapa",
    "gn:country_code":"ID",
    "gn:dem":745,
    "gn:feature_class":"P",
    "gn:feature_code":"PPL",
    "gn:name":"Tublapa",
    "gn:population":0,
    "gn:timezone":"Asia/Makassar",
    "iso:country":"ID",
    "name:ind_x_preferred":[
        "Tublapa"
    ],
    "wof:name":"Tublapa",
    "wof:placetype":"locality"
},
  "geometry": {"coordinates":[124.5855,-9.7874],"type":"Point"}
}