{
  "type": "Feature",
  "properties": {
    "gn:admin1_code":"18.0",
    "gn:asciiname":"Tuamese",
    "gn:country_code":"ID",
    "gn:dem":469,
    "gn:feature_class":"P",
    "gn:feature_code":"PPLA4",
    "gn:name":"Tuamese",
    "gn:population":0,
    "gn:timezone":"Asia/Makassar",
    "iso:country":"ID",
    "name:ind_x_preferred":[
        "Tuamese"
    ],
    "name:und_x_variant":[
        "Tuamesa"
    ],
    "wof:name":"Tuamese",
    "wof:placetype":"locality"
},
  "geometry": {"coordinates":[123.8749,-10.2455],"type":"Point"}
}