{
  "type": "Feature",
  "properties": {
    "gn:admin1_code":"17.0",
    "gn:asciiname":"Kalabaru",
    "gn:country_code":"ID",
    "gn:dem":13,
    "gn:feature_class":"P",
    "gn:feature_code":"PPL",
    "gn:name":"Kalabaru",
    "gn:population":0,
    "gn:timezone":"Asia/Makassar",
    "iso:country":"ID",
    "name:ind_x_preferred":[
        "Kalabaru"
    ],
    "wof:name":"Kalabaru",
    "wof:placetype":"locality"
},
  "geometry": {"coordinates":[118.657,-8.3087],"type":"Point"}
}