{
  "type": "Feature",
  "properties": {
    "gn:admin1_code":"32.0",
    "gn:asciiname":"Pulau Layang",
    "gn:country_code":"ID",
    "gn:dem":11,
    "gn:feature_class":"P",
    "gn:feature_code":"PPL",
    "gn:name":"Pulau Layang",
    "gn:population":0,
    "gn:timezone":"Asia/Jakarta",
    "iso:country":"ID",
    "name:ind_x_preferred":[
        "Pulau Layang"
    ],
    "name:ind_x_variant":[
        "Poelaulajang"
    ],
    "name:und_x_variant":[
        "Relajang",
        "Relayang"
    ],
    "wof:lang_x_official":[
        "ind"
    ],
    "wof:lang_x_spoken":[
        "ind",
        "eng"
    ],
    "wof:name":"Pulau Layang",
    "wof:placetype":"locality"
},
  "geometry": {"coordinates":[104.95802999999999,-3.212],"type":"Point"}
}