{
  "type": "Feature",
  "properties": {
    "gn:admin1_code":"28.0",
    "gn:asciiname":"Hatta",
    "gn:country_code":"ID",
    "gn:dem":18,
    "gn:feature_class":"P",
    "gn:feature_code":"PPL",
    "gn:name":"Hatta",
    "gn:population":0,
    "gn:timezone":"Asia/Jayapura",
    "iso:country":"ID",
    "name:cat_x_preferred":[
        "Hatta"
    ],
    "name:ceb_x_preferred":[
        "Hatta"
    ],
    "name:deu_x_preferred":[
        "Hatta"
    ],
    "name:fra_x_preferred":[
        "Hatta"
    ],
    "name:ind_x_preferred":[
        "Hatta"
    ],
    "name:ita_x_preferred":[
        "Hatta"
    ],
    "name:nld_x_preferred":[
        "Hatta"
    ],
    "name:rus_x_preferred":[
        "\u0425\u0430\u0442\u0442\u0430"
    ],
    "name:spa_x_preferred":[
        "Hatta"
    ],
    "name:swe_x_preferred":[
        "Hatta"
    ],
    "name:ukr_x_preferred":[
        "\u0425\u0430\u0442\u0442\u0430"
    ],
    "name:und_x_variant":[
        "Kampoeng Rozengain",
        "Rozengain"
    ],
    "wof:lang_x_official":[
        "ind"
    ],
    "wof:lang_x_spoken":[
        "ind",
        "eng"
    ],
    "wof:name":"Hatta",
    "wof:placetype":"locality"
},
  "geometry": {"coordinates":[130.04107999999999,-4.57981],"type":"Point"}
}