{
  "type": "Feature",
  "properties": {
    "gn:admin1_code":"12.0",
    "gn:asciiname":"Cantung Kiri Hulu",
    "gn:country_code":"ID",
    "gn:dem":81,
    "gn:feature_class":"P",
    "gn:feature_code":"PPL",
    "gn:name":"Cantung Kiri Hulu",
    "gn:population":0,
    "gn:timezone":"Asia/Makassar",
    "iso:country":"ID",
    "name:ind_x_preferred":[
        "Tjantunghulu"
    ],
    "name:ind_x_variant":[
        "Cantung Kiri Hulu"
    ],
    "name:und_x_variant":[
        "Tjantoeng-hoeloe",
        "Tjantoengoeloe",
        "Tjantung-hulu",
        "Cantunghulu"
    ],
    "wof:lang_x_official":[
        "ind"
    ],
    "wof:lang_x_spoken":[
        "ind",
        "eng"
    ],
    "wof:name":"Cantung Kiri Hulu",
    "wof:placetype":"locality"
},
  "geometry": {"coordinates":[115.7422,-3.0092],"type":"Point"}
}