{
  "type": "Feature",
  "properties": {
    "gn:admin1_code":"30.0",
    "gn:asciiname":"Lebak",
    "gn:country_code":"ID",
    "gn:dem":361,
    "gn:feature_class":"P",
    "gn:feature_code":"PPL",
    "gn:name":"Lebak",
    "gn:population":0,
    "gn:timezone":"Asia/Jakarta",
    "iso:country":"ID",
    "name:ceb_x_preferred":[
        "Lebak"
    ],
    "name:fra_x_preferred":[
        "Lebak"
    ],
    "name:ind_x_preferred":[
        "Lebak"
    ],
    "name:ita_x_preferred":[
        "Lebak"
    ],
    "name:nld_x_preferred":[
        "Lebak"
    ],
    "name:sun_x_preferred":[
        "Lebak"
    ],
    "name:swe_x_preferred":[
        "Lebak"
    ],
    "wof:lang_x_official":[
        "ind"
    ],
    "wof:lang_x_spoken":[
        "ind",
        "eng"
    ],
    "wof:name":"Lebak",
    "wof:placetype":"locality"
},
  "geometry": {"coordinates":[113.9614,-7.9061],"type":"Point"}
}