{
  "type": "Feature",
  "properties": {
    "gn:admin1_code":"14.0",
    "gn:asciiname":"Sepatin",
    "gn:country_code":"ID",
    "gn:dem":2,
    "gn:feature_class":"P",
    "gn:feature_code":"PPL",
    "gn:name":"Sepatin",
    "gn:population":0,
    "gn:timezone":"Asia/Makassar",
    "iso:country":"ID",
    "name:und_x_variant":[
        "Soengaipatin",
        "Sungaipatin"
    ],
    "wof:lang_x_official":[
        "ind"
    ],
    "wof:lang_x_spoken":[
        "ind",
        "eng"
    ],
    "wof:name":"Sepatin",
    "wof:placetype":"locality"
},
  "geometry": {"coordinates":[117.59271,-0.78037],"type":"Point"}
}