{
  "type": "Feature",
  "properties": {
    "gn:admin1_code":"30",
    "gn:asciiname":"Babakankubang",
    "gn:country_code":"ID",
    "gn:dem":315,
    "gn:feature_class":"P",
    "gn:feature_code":"PPL",
    "gn:name":"Babakankubang",
    "gn:population":0,
    "gn:timezone":"Asia/Jakarta",
    "iso:country":"ID",
    "name:ind_x_preferred":[
        "Babakankubang"
    ],
    "wof:name":"Babakankubang",
    "wof:placetype":"locality"
},
  "geometry": {"coordinates":[107.19138999999998,-6.7875],"type":"Point"}
}