{
  "type": "Feature",
  "properties": {
    "gn:admin1_code":"7",
    "gn:asciiname":"Blumah",
    "gn:country_code":"ID",
    "gn:dem":938,
    "gn:feature_class":"P",
    "gn:feature_code":"PPL",
    "gn:name":"Blumah",
    "gn:population":0,
    "gn:timezone":"Asia/Jakarta",
    "iso:country":"ID",
    "name:ind_x_preferred":[
        "Blumah"
    ],
    "wof:name":"Blumah",
    "wof:placetype":"locality"
},
  "geometry": {"coordinates":[109.94361000000001,-7.14028],"type":"Point"}
}