{
  "type": "Feature",
  "properties": {
    "gn:admin1_code":"17.0",
    "gn:asciiname":"Talimung",
    "gn:country_code":"ID",
    "gn:dem":18,
    "gn:feature_class":"P",
    "gn:feature_code":"PPL",
    "gn:name":"Talimung",
    "gn:population":0,
    "gn:timezone":"Asia/Makassar",
    "iso:country":"ID",
    "name:ind_x_preferred":[
        "Talimung"
    ],
    "wof:name":"Talimung",
    "wof:placetype":"locality"
},
  "geometry": {"coordinates":[117.9952,-8.7513],"type":"Point"}
}