{
  "type": "Feature",
  "properties": {
    "gn:admin1_code":"07",
    "gn:asciiname":"Pulerejo",
    "gn:country_code":"ID",
    "gn:dem":739,
    "gn:feature_class":"P",
    "gn:feature_code":"PPL",
    "gn:name":"Pulerejo",
    "gn:population":0,
    "gn:timezone":"Asia/Jakarta",
    "iso:country":"ID",
    "wof:name":"Pulerejo",
    "wof:placetype":"locality"
},
  "geometry": {"coordinates":[110.51306,-7.58722],"type":"Point"}
}