{
  "type": "Feature",
  "properties": {
    "gn:admin1_code":"0.0",
    "gn:asciiname":"Natai Darung",
    "gn:cc2":"ID",
    "gn:country_code":"ID",
    "gn:dem":185,
    "gn:feature_class":"P",
    "gn:feature_code":"PPL",
    "gn:name":"Natai Darung",
    "gn:population":0,
    "gn:timezone":"Asia/Pontianak",
    "iso:country":"ID",
    "name:und_x_variant":[
        "Natai Daroeng",
        "Natai Darung"
    ],
    "wof:name":"Natai Darung",
    "wof:placetype":"locality"
},
  "geometry": {"coordinates":[112.88333,-0.06667],"type":"Point"}
}