{
  "type": "Feature",
  "properties": {
    "gn:admin1_code":"37",
    "gn:asciiname":"Sikiat",
    "gn:country_code":"ID",
    "gn:dem":8,
    "gn:feature_class":"P",
    "gn:feature_code":"PPL",
    "gn:name":"Sikiat",
    "gn:population":0,
    "gn:timezone":"Asia/Jakarta",
    "iso:country":"ID",
    "name:ind_x_preferred":[
        "Sikiat"
    ],
    "wof:name":"Sikiat",
    "wof:placetype":"locality"
},
  "geometry": {"coordinates":[103.16316999999999,0.63031],"type":"Point"}
}