{
  "type": "Feature",
  "properties": {
    "gn:admin1_code":"26",
    "gn:asciiname":"Pasirtuntung",
    "gn:country_code":"ID",
    "gn:dem":27,
    "gn:feature_class":"P",
    "gn:feature_code":"PPL",
    "gn:name":"Pasirtuntung",
    "gn:population":0,
    "gn:timezone":"Asia/Jakarta",
    "iso:country":"ID",
    "name:ind_x_preferred":[
        "Pasirtuntung"
    ],
    "wof:name":"Pasirtuntung",
    "wof:placetype":"locality"
},
  "geometry": {"coordinates":[100.05224,1.81907],"type":"Point"}
}