{
  "type": "Feature",
  "properties": {
    "gn:admin1_code":"7.0",
    "gn:asciiname":"Cilongkrang",
    "gn:country_code":"ID",
    "gn:dem":28,
    "gn:feature_class":"P",
    "gn:feature_code":"PPLA4",
    "gn:name":"Cilongkrang",
    "gn:population":0,
    "gn:timezone":"Asia/Jakarta",
    "iso:country":"ID",
    "name:ind_x_preferred":[
        "Cilongkrang"
    ],
    "name:und_x_variant":[
        "Tjilongkrang"
    ],
    "wof:lang_x_official":[
        "ind"
    ],
    "wof:lang_x_spoken":[
        "ind",
        "eng"
    ],
    "wof:name":"Cilongkrang",
    "wof:placetype":"locality"
},
  "geometry": {"coordinates":[108.7127,-7.4084],"type":"Point"}
}