{
  "type": "Feature",
  "properties": {
    "gn:admin1_code":"30",
    "gn:asciiname":"Rantaya Hilir",
    "gn:cc2":"ID",
    "gn:country_code":"ID",
    "gn:dem":982,
    "gn:feature_class":"P",
    "gn:feature_code":"PPL",
    "gn:name":"Rantaya Hilir",
    "gn:population":0,
    "gn:timezone":"Asia/Jakarta",
    "iso:country":"ID",
    "name:und_x_variant":[
        "Rantajan",
        "Rantayan",
        "Rantaya Hilir"
    ],
    "wof:lang_x_official":[
        "ind"
    ],
    "wof:lang_x_spoken":[
        "ind",
        "eng"
    ],
    "wof:name":"Rantaya Hilir",
    "wof:placetype":"locality"
},
  "geometry": {"coordinates":[107.54000000000001,-7.11833],"type":"Point"}
}