{
  "type": "Feature",
  "properties": {
    "gn:admin1_code":"18.0",
    "gn:asciiname":"Iungnian",
    "gn:country_code":"ID",
    "gn:dem":66,
    "gn:feature_class":"P",
    "gn:feature_code":"PPL",
    "gn:name":"Iungnian",
    "gn:population":0,
    "gn:timezone":"Asia/Makassar",
    "iso:country":"ID",
    "name:ind_x_preferred":[
        "Iungnian"
    ],
    "name:und_x_variant":[
        "Besdale 1",
        "Besdale"
    ],
    "wof:name":"Iungnian",
    "wof:placetype":"locality"
},
  "geometry": {"coordinates":[123.3511,-10.2536],"type":"Point"}
}