{
  "type": "Feature",
  "properties": {
    "gn:admin1_code":"22",
    "gn:asciiname":"Mandiri",
    "gn:country_code":"ID",
    "gn:dem":10,
    "gn:feature_class":"P",
    "gn:feature_code":"PPL",
    "gn:name":"Mandiri",
    "gn:population":0,
    "gn:timezone":"Asia/Makassar",
    "iso:country":"ID",
    "name:ind_x_preferred":[
        "Mandiri"
    ],
    "wof:name":"Mandiri",
    "wof:placetype":"locality"
},
  "geometry": {"coordinates":[121.069,-3.0932],"type":"Point"}
}