{
  "type": "Feature",
  "properties": {
    "gn:admin1_code":"15.0",
    "gn:asciiname":"Pekonlok",
    "gn:country_code":"ID",
    "gn:dem":39,
    "gn:feature_class":"P",
    "gn:feature_code":"PPL",
    "gn:name":"Pekonlok",
    "gn:population":0,
    "gn:timezone":"Asia/Jakarta",
    "iso:country":"ID",
    "name:ind_x_preferred":[
        "Pekonlok"
    ],
    "wof:name":"Pekonlok",
    "wof:placetype":"locality"
},
  "geometry": {"coordinates":[103.84801,-5.1219],"type":"Point"}
}