{
  "type": "Feature",
  "properties": {
    "gn:admin1_code":"30",
    "gn:asciiname":"Ciputat",
    "gn:country_code":"ID",
    "gn:dem":664,
    "gn:feature_class":"P",
    "gn:feature_code":"PPL",
    "gn:name":"Ciputat",
    "gn:population":0,
    "gn:timezone":"Asia/Jakarta",
    "iso:country":"ID",
    "name:ind_x_preferred":[
        "Ciputat"
    ],
    "name:und_x_variant":[
        "Tjiputat 1",
        "Ciputat Satu"
    ],
    "wof:name":"Ciputat",
    "wof:placetype":"locality"
},
  "geometry": {"coordinates":[107.67806000000002,-6.99083],"type":"Point"}
}