{
  "type": "Feature",
  "properties": {
    "gn:admin1_code":"15.0",
    "gn:asciiname":"Harjobinangun",
    "gn:country_code":"ID",
    "gn:dem":93,
    "gn:feature_class":"P",
    "gn:feature_code":"PPL",
    "gn:name":"Harjobinangun",
    "gn:population":0,
    "gn:timezone":"Asia/Jakarta",
    "iso:country":"ID",
    "name:ind_x_preferred":[
        "Harjobinangun"
    ],
    "wof:name":"Harjobinangun",
    "wof:placetype":"locality"
},
  "geometry": {"coordinates":[105.38712,-5.43743],"type":"Point"}
}