{
  "type": "Feature",
  "properties": {
    "gn:admin1_code":"36.0",
    "gn:asciiname":"Opfa",
    "gn:country_code":"ID",
    "gn:dem":122,
    "gn:feature_class":"P",
    "gn:feature_code":"PPL",
    "gn:name":"Opfa",
    "gn:population":0,
    "gn:timezone":"Asia/Jayapura",
    "iso:country":"ID",
    "name:ind_x_preferred":[
        "Opfa"
    ],
    "wof:name":"Opfa",
    "wof:placetype":"locality"
},
  "geometry": {"coordinates":[140.93716000000001,-5.61331],"type":"Point"}
}