{
  "type": "Feature",
  "properties": {
    "gn:admin1_code":"30",
    "gn:asciiname":"Sawah Empat",
    "gn:cc2":"ID",
    "gn:country_code":"ID",
    "gn:dem":120,
    "gn:feature_class":"P",
    "gn:feature_code":"PPL",
    "gn:name":"Sawah Empat",
    "gn:population":0,
    "gn:timezone":"Asia/Jakarta",
    "iso:country":"ID",
    "name:und_x_variant":[
        "Sawah 4",
        "Sawah Empat"
    ],
    "wof:name":"Sawah Empat",
    "wof:placetype":"locality"
},
  "geometry": {"coordinates":[106.84056,-6.44889],"type":"Point"}
}