{
  "type": "Feature",
  "properties": {
    "gn:admin1_code":"30",
    "gn:asciiname":"Mekarjaya",
    "gn:country_code":"ID",
    "gn:dem":245,
    "gn:feature_class":"P",
    "gn:feature_code":"PPL",
    "gn:name":"Mekarjaya",
    "gn:population":0,
    "gn:timezone":"Asia/Jakarta",
    "iso:country":"ID",
    "name:ind_x_preferred":[
        "Mekarjaya"
    ],
    "wof:name":"Mekarjaya",
    "wof:placetype":"locality"
},
  "geometry": {"coordinates":[106.56471999999999,-6.56333],"type":"Point"}
}