{
  "type": "Feature",
  "properties": {
    "gn:admin1_code":"7.0",
    "gn:asciiname":"Bondolharjo",
    "gn:country_code":"ID",
    "gn:dem":249,
    "gn:feature_class":"P",
    "gn:feature_code":"PPL",
    "gn:name":"Bondolharjo",
    "gn:population":0,
    "gn:timezone":"Asia/Jakarta",
    "iso:country":"ID",
    "name:ind_x_preferred":[
        "Bondolharjo"
    ],
    "wof:name":"Bondolharjo",
    "wof:placetype":"locality"
},
  "geometry": {"coordinates":[109.62694,-7.3625],"type":"Point"}
}