{
  "type": "Feature",
  "properties": {
    "gn:country":"ID",
    "gn:fcode":"PPL",
    "gn:pop":7,
    "iso:country":"ID",
    "qs:name":"Tempat tinggal Alfian",
    "qs:photos_9r":0,
    "qs:photos_sr":0,
    "qs:pop_sr":"1",
    "wof:name":"Tempat tinggal Alfian",
    "wof:placetype":"locality",
    "wof:population":7
},
  "geometry": {"coordinates":[107.95587,-6.36859],"type":"Point"}
}