{
  "type": "Feature",
  "properties": {
    "gn:admin1_code":"38.0",
    "gn:asciiname":"Bajoe",
    "gn:country_code":"ID",
    "gn:dem":12,
    "gn:feature_class":"P",
    "gn:feature_code":"PPL",
    "gn:name":"Bajoe",
    "gn:population":0,
    "gn:timezone":"Asia/Makassar",
    "iso:country":"ID",
    "name:ind_x_preferred":[
        "Bajoe"
    ],
    "name:und_x_variant":[
        "Bajoa",
        "Badjowe 1",
        "Badjoa",
        "Bajowe"
    ],
    "wof:name":"Bajoe",
    "wof:placetype":"locality"
},
  "geometry": {"coordinates":[120.3751,-4.547],"type":"Point"}
}