{
  "type": "Feature",
  "properties": {
    "gn:admin1_code":"7.0",
    "gn:asciiname":"Tulun",
    "gn:country_code":"ID",
    "gn:dem":208,
    "gn:feature_class":"P",
    "gn:feature_code":"PPL",
    "gn:name":"Tulun",
    "gn:population":0,
    "gn:timezone":"Asia/Jakarta",
    "iso:country":"ID",
    "name:ara_x_preferred":[
        "\u062a\u0648\u0644\u0648\u0646"
    ],
    "name:aze_x_preferred":[
        "Tulun"
    ],
    "name:bel_x_preferred":[
        "\u0422\u0443\u043b\u0443\u043d"
    ],
    "name:ben_x_preferred":[
        "\u09a4\u09c1\u09b2\u09c1\u09a8"
    ],
    "name:bul_x_preferred":[
        "\u0422\u0443\u043b\u0443\u043d"
    ],
    "name:cat_x_preferred":[
        "Tulun"
    ],
    "name:ceb_x_preferred":[
        "Tulun"
    ],
    "name:ces_x_preferred":[
        "Tulun"
    ],
    "name:che_x_preferred":[
        "\u0422\u0443\u043b\u0443\u043d"
    ],
    "name:dan_x_preferred":[
        "Tulun"
    ],
    "name:deu_x_preferred":[
        "Tulun"
    ],
    "name:ell_x_preferred":[
        "\u03a4\u03bf\u03c5\u03bb\u03bf\u03cd\u03bd"
    ],
    "name:epo_x_preferred":[
        "Tulun"
    ],
    "name:est_x_preferred":[
        "Tulun"
    ],
    "name:fas_x_preferred":[
        "\u062a\u0648\u0644\u0648\u0646"
    ],
    "name:fin_x_preferred":[
        "Tulun"
    ],
    "name:fra_x_preferred":[
        "Touloun"
    ],
    "name:heb_x_preferred":[
        "\u05d8\u05d5\u05dc\u05d5\u05df"
    ],
    "name:hin_x_preferred":[
        "\u0924\u0941\u0932\u0942\u0928"
    ],
    "name:hsb_x_preferred":[
        "Tulun"
    ],
    "name:hun_x_preferred":[
        "Tulun"
    ],
    "name:ind_x_preferred":[
        "Tulun"
    ],
    "name:ita_x_preferred":[
        "Tulun"
    ],
    "name:kor_x_preferred":[
        "\ud234\ub8ec"
    ],
    "name:lit_x_preferred":[
        "Tulunas"
    ],
    "name:nld_x_preferred":[
        "Toeloen"
    ],
    "name:nno_x_preferred":[
        "Tulun"
    ],
    "name:nor_x_preferred":[
        "Tulun"
    ],
    "name:pnb_x_preferred":[
        "\u062a\u0648\u0644\u0648\u0646"
    ],
    "name:pol_x_preferred":[
        "Tu\u0142un"
    ],
    "name:ron_x_preferred":[
        "Tulun"
    ],
    "name:rus_x_preferred":[
        "\u0422\u0443\u043b\u0443\u043d"
    ],
    "name:spa_x_preferred":[
        "Tul\u00fan"
    ],
    "name:srp_x_preferred":[
        "\u0422\u0443\u043b\u0443\u043d"
    ],
    "name:swe_x_preferred":[
        "Tulun"
    ],
    "name:szl_x_preferred":[
        "Tu\u0142un"
    ],
    "name:tat_x_preferred":[
        "\u0422\u0443\u043b\u0443\u043d"
    ],
    "name:tgl_x_preferred":[
        "Tulun"
    ],
    "name:ukr_x_preferred":[
        "\u0422\u0443\u043b\u0443\u043d"
    ],
    "name:urd_x_preferred":[
        "\u0679\u0648\u0644\u0648\u0646"
    ],
    "name:vep_x_preferred":[
        "Tulun"
    ],
    "name:vie_x_preferred":[
        "Tulun"
    ],
    "name:war_x_preferred":[
        "Tulun"
    ],
    "name:zho_x_preferred":[
        "\u56fe\u4f26"
    ],
    "wof:lang_x_official":[
        "ind"
    ],
    "wof:lang_x_spoken":[
        "ind",
        "eng"
    ],
    "wof:name":"Tulun",
    "wof:placetype":"locality"
},
  "geometry": {"coordinates":[110.95083,-7.68028],"type":"Point"}
}