{
  "type": "Feature",
  "properties": {
    "gn:admin1_code":"7.0",
    "gn:asciiname":"Tulun",
    "gn:country_code":"ID",
    "gn:dem":208,
    "gn:feature_class":"P",
    "gn:feature_code":"PPL",
    "gn:name":"Tulun",
    "gn:population":0,
    "gn:timezone":"Asia/Jakarta",
    "iso:country":"ID",
    "wof:name":"Tulun",
    "wof:placetype":"locality"
},
  "geometry": {"coordinates":[110.95083,-7.68028],"type":"Point"}
}