{
  "type": "Feature",
  "properties": {
    "gn:admin1_code":"38",
    "gn:asciiname":"Passingkalling",
    "gn:country_code":"ID",
    "gn:dem":405,
    "gn:feature_class":"P",
    "gn:feature_code":"PPL",
    "gn:name":"Passingkalling",
    "gn:population":0,
    "gn:timezone":"Asia/Makassar",
    "iso:country":"ID",
    "name:ind_x_preferred":[
        "Passingkalling"
    ],
    "wof:name":"Passingkalling",
    "wof:placetype":"locality"
},
  "geometry": {"coordinates":[119.7216,-5.0906],"type":"Point"}
}