{
  "type": "Feature",
  "properties": {
    "gn:admin1_code":"30",
    "gn:asciiname":"Haurkoneng",
    "gn:country_code":"ID",
    "gn:dem":94,
    "gn:feature_class":"P",
    "gn:feature_code":"PPL",
    "gn:name":"Haurkoneng",
    "gn:population":0,
    "gn:timezone":"Asia/Jakarta",
    "iso:country":"ID",
    "name:ind_x_preferred":[
        "Haurkoneng"
    ],
    "wof:name":"Haurkoneng",
    "wof:placetype":"locality"
},
  "geometry": {"coordinates":[107.06944,-6.46194],"type":"Point"}
}