{
  "type": "Feature",
  "properties": {
    "gn:admin1_code":"0.0",
    "gn:asciiname":"Kadundung",
    "gn:cc2":"ID",
    "gn:country_code":"ID",
    "gn:dem":801,
    "gn:feature_class":"P",
    "gn:feature_code":"PPL",
    "gn:name":"Kadundung",
    "gn:population":0,
    "gn:timezone":"Asia/Makassar",
    "iso:country":"ID",
    "name:und_x_variant":[
        "Kadoendoeng",
        "Kadundung"
    ],
    "wof:name":"Kadundung",
    "wof:placetype":"locality"
},
  "geometry": {"coordinates":[119.55,-3.41667],"type":"Point"}
}