{
  "type": "Feature",
  "properties": {
    "gn:admin1_code":"10",
    "gn:asciiname":"Troseno",
    "gn:country_code":"ID",
    "gn:dem":175,
    "gn:feature_class":"P",
    "gn:feature_code":"PPL",
    "gn:name":"Troseno",
    "gn:population":0,
    "gn:timezone":"Asia/Jakarta",
    "iso:country":"ID",
    "name:ind_x_preferred":[
        "Troseno"
    ],
    "wof:name":"Troseno",
    "wof:placetype":"locality"
},
  "geometry": {"coordinates":[110.58667,-8.00417],"type":"Point"}
}