{
  "type": "Feature",
  "properties": {
    "gn:admin1_code":"18",
    "gn:asciiname":"Potu",
    "gn:country_code":"ID",
    "gn:dem":334,
    "gn:feature_class":"P",
    "gn:feature_code":"PPL",
    "gn:name":"Potu",
    "gn:population":0,
    "gn:timezone":"Asia/Makassar",
    "iso:country":"ID",
    "name:aze_x_preferred":[
        "Potu"
    ],
    "name:ceb_x_preferred":[
        "Potu"
    ],
    "name:dan_x_preferred":[
        "Potu"
    ],
    "name:fas_x_preferred":[
        "\u067e\u0648\u062a\u0648"
    ],
    "name:ind_x_preferred":[
        "Potu"
    ],
    "name:ita_x_preferred":[
        "Potu"
    ],
    "name:kat_x_preferred":[
        "\u10e4\u10dd\u10d7\u10e3"
    ],
    "name:msa_x_preferred":[
        "Potu"
    ],
    "name:swe_x_preferred":[
        "Potu"
    ],
    "wof:name":"Potu",
    "wof:placetype":"locality"
},
  "geometry": {"coordinates":[121.9665,-8.7986],"type":"Point"}
}