{
  "type": "Feature",
  "properties": {
    "gn:admin1_code":"8.0",
    "gn:asciiname":"Ngaglik",
    "gn:country_code":"ID",
    "gn:dem":409,
    "gn:feature_class":"P",
    "gn:feature_code":"PPL",
    "gn:name":"Ngaglik",
    "gn:population":0,
    "gn:timezone":"Asia/Jakarta",
    "iso:country":"ID",
    "name:ind_x_preferred":[
        "Ngaglik"
    ],
    "wof:name":"Ngaglik",
    "wof:placetype":"locality"
},
  "geometry": {"coordinates":[111.79300000000001,-7.981],"type":"Point"}
}