{
  "type": "Feature",
  "properties": {
    "gn:admin1_code":"18.0",
    "gn:asciiname":"Tupan",
    "gn:country_code":"ID",
    "gn:dem":141,
    "gn:feature_class":"P",
    "gn:feature_code":"PPL",
    "gn:name":"Tupan",
    "gn:population":0,
    "gn:timezone":"Asia/Makassar",
    "iso:country":"ID",
    "name:ceb_x_preferred":[
        "Tupan"
    ],
    "name:deu_x_preferred":[
        "Tupan"
    ],
    "name:ind_x_preferred":[
        "Tupan"
    ],
    "name:por_x_preferred":[
        "Tupan"
    ],
    "name:rus_x_preferred":[
        "\u0422\u0443\u043f\u0430\u043d"
    ],
    "name:swe_x_preferred":[
        "Tupan"
    ],
    "wof:name":"Tupan",
    "wof:placetype":"locality"
},
  "geometry": {"coordinates":[124.12358999999999,-9.95321],"type":"Point"}
}