{
  "type": "Feature",
  "properties": {
    "gn:admin1_code":"2.0",
    "gn:asciiname":"Tunoon",
    "gn:country_code":"ID",
    "gn:dem":17,
    "gn:feature_class":"P",
    "gn:feature_code":"PPL",
    "gn:name":"Tunoon",
    "gn:population":0,
    "gn:timezone":"Asia/Makassar",
    "iso:country":"ID",
    "name:ind_x_preferred":[
        "Tunoon"
    ],
    "wof:name":"Tunoon",
    "wof:placetype":"locality"
},
  "geometry": {"coordinates":[115.15219999999999,-8.6654],"type":"Point"}
}