{
  "type": "Feature",
  "properties": {
    "gn:admin1_code":"8.0",
    "gn:asciiname":"Pandan Kidul",
    "gn:country_code":"ID",
    "gn:dem":627,
    "gn:feature_class":"P",
    "gn:feature_code":"PPL",
    "gn:name":"Pandan Kidul",
    "gn:population":0,
    "gn:timezone":"Asia/Jakarta",
    "iso:country":"ID",
    "name:ind_x_preferred":[
        "Pandan Kidul"
    ],
    "wof:name":"Pandan Kidul",
    "wof:placetype":"locality"
},
  "geometry": {"coordinates":[111.5508,-8.0186],"type":"Point"}
}