{
  "type": "Feature",
  "properties": {
    "gn:admin1_code":"29.0",
    "gn:asciiname":"Waisipang Satu",
    "gn:country_code":"ID",
    "gn:dem":6,
    "gn:feature_class":"P",
    "gn:feature_code":"PPL",
    "gn:name":"Waisipang Satu",
    "gn:population":0,
    "gn:timezone":"Asia/Jayapura",
    "iso:country":"ID",
    "name:ind_x_preferred":[
        "Waisipang Satu"
    ],
    "name:und_x_variant":[
        "Waisipang 1",
        "Waisipang"
    ],
    "wof:lang_x_official":[
        "ind"
    ],
    "wof:lang_x_spoken":[
        "ind",
        "eng"
    ],
    "wof:name":"Waisipang Satu",
    "wof:placetype":"locality"
},
  "geometry": {"coordinates":[127.41439,0.08036],"type":"Point"}
}