{
  "type": "Feature",
  "properties": {
    "gn:admin1_code":"28.0",
    "gn:asciiname":"Loroulung",
    "gn:country_code":"ID",
    "gn:dem":5,
    "gn:feature_class":"P",
    "gn:feature_code":"PPL",
    "gn:name":"Loroulung",
    "gn:population":0,
    "gn:timezone":"Asia/Jayapura",
    "iso:country":"ID",
    "name:ind_x_preferred":[
        "Loroulung"
    ],
    "wof:name":"Loroulung",
    "wof:placetype":"locality"
},
  "geometry": {"coordinates":[131.38018,-7.8519],"type":"Point"}
}