{
  "type": "Feature",
  "properties": {
    "gn:admin1_code":"30.0",
    "gn:asciiname":"Sindanglangon",
    "gn:country_code":"ID",
    "gn:dem":627,
    "gn:feature_class":"P",
    "gn:feature_code":"PPL",
    "gn:name":"Sindanglangon",
    "gn:population":0,
    "gn:timezone":"Asia/Jakarta",
    "iso:country":"ID",
    "name:ind_x_preferred":[
        "Sindanglangon"
    ],
    "name:und_x_variant":[
        "Sindanglanggong"
    ],
    "wof:lang_x_official":[
        "ind"
    ],
    "wof:lang_x_spoken":[
        "ind",
        "eng"
    ],
    "wof:name":"Sindanglangon",
    "wof:placetype":"locality"
},
  "geometry": {"coordinates":[107.94370000000001,-7.1234],"type":"Point"}
}