{
  "type": "Feature",
  "properties": {
    "gn:admin1_code":"1",
    "gn:asciiname":"Cot Patisah",
    "gn:country_code":"ID",
    "gn:dem":8,
    "gn:feature_class":"P",
    "gn:feature_code":"PPL",
    "gn:name":"Cot Patisah",
    "gn:population":0,
    "gn:timezone":"Asia/Jakarta",
    "iso:country":"ID",
    "name:ind_x_preferred":[
        "Cot Patisah"
    ],
    "name:und_x_variant":[
        "Tjotpatisah"
    ],
    "wof:name":"Cot Patisah",
    "wof:placetype":"locality"
},
  "geometry": {"coordinates":[97.3947,5.1879],"type":"Point"}
}