{
  "type": "Feature",
  "properties": {
    "gn:admin1_code":"30.0",
    "gn:asciiname":"Cibingbin",
    "gn:country_code":"ID",
    "gn:dem":994,
    "gn:feature_class":"P",
    "gn:feature_code":"PPL",
    "gn:name":"Cibingbin",
    "gn:population":0,
    "gn:timezone":"Asia/Jakarta",
    "iso:country":"ID",
    "name:ind_x_preferred":[
        "Cibingbin"
    ],
    "name:und_x_variant":[
        "Tjibingbin",
        "Cibingbin"
    ],
    "wof:lang_x_official":[
        "ind"
    ],
    "wof:lang_x_spoken":[
        "ind",
        "eng"
    ],
    "wof:name":"Cibingbin",
    "wof:placetype":"locality"
},
  "geometry": {"coordinates":[107.0716,-7.0116],"type":"Point"}
}