{
  "type": "Feature",
  "properties": {
    "gn:admin1_code":"7.0",
    "gn:asciiname":"Kedawung",
    "gn:country_code":"ID",
    "gn:dem":416,
    "gn:feature_class":"P",
    "gn:feature_code":"PPL",
    "gn:name":"Kedawung",
    "gn:population":0,
    "gn:timezone":"Asia/Jakarta",
    "iso:country":"ID",
    "name:ind_x_preferred":[
        "Kedawung"
    ],
    "wof:name":"Kedawung",
    "wof:placetype":"locality"
},
  "geometry": {"coordinates":[109.05861000000002,-7.30556],"type":"Point"}
}