{
  "type": "Feature",
  "properties": {
    "gn:admin1_code":"30.0",
    "gn:asciiname":"Cipandan",
    "gn:country_code":"ID",
    "gn:dem":29,
    "gn:feature_class":"P",
    "gn:feature_code":"PPL",
    "gn:name":"Cipandan",
    "gn:population":0,
    "gn:timezone":"Asia/Jakarta",
    "iso:country":"ID",
    "name:ind_x_preferred":[
        "Cipandan"
    ],
    "wof:name":"Cipandan",
    "wof:placetype":"locality"
},
  "geometry": {"coordinates":[107.51130000000001,-7.5344],"type":"Point"}
}