{
  "type": "Feature",
  "properties": {
    "gn:admin1_code":"30.0",
    "gn:asciiname":"Pangkalan",
    "gn:country_code":"ID",
    "gn:dem":619,
    "gn:feature_class":"P",
    "gn:feature_code":"PPLA4",
    "gn:name":"Pangkalan",
    "gn:population":0,
    "gn:timezone":"Asia/Jakarta",
    "iso:country":"ID",
    "name:ceb_x_preferred":[
        "Pangkalan"
    ],
    "name:ind_x_preferred":[
        "Pangkalan"
    ],
    "name:nld_x_preferred":[
        "Pangkalan"
    ],
    "name:swe_x_preferred":[
        "Pangkalan"
    ],
    "name:und_x_variant":[
        "Pangkalan 1"
    ],
    "wof:lang_x_official":[
        "ind"
    ],
    "wof:lang_x_spoken":[
        "ind",
        "eng"
    ],
    "wof:name":"Pangkalan",
    "wof:placetype":"locality"
},
  "geometry": {"coordinates":[108.071,-7.0211],"type":"Point"}
}