{
  "type": "Feature",
  "properties": {
    "gn:country":"ID",
    "gn:fcode":"PPL",
    "gn:pop":0,
    "iso:country":"ID",
    "name:ban_x_preferred":[
        "Terban"
    ],
    "name:ceb_x_preferred":[
        "Kelurahan Terban"
    ],
    "name:deu_x_preferred":[
        "Terban"
    ],
    "name:eng_x_preferred":[
        "Terban"
    ],
    "name:fra_x_preferred":[
        "Terban"
    ],
    "name:ind_x_preferred":[
        "Terban"
    ],
    "name:jav_x_preferred":[
        "Terban"
    ],
    "name:msa_x_preferred":[
        "Terban"
    ],
    "name:nld_x_preferred":[
        "Terban"
    ],
    "name:swe_x_preferred":[
        "Kelurahan Terban"
    ],
    "qs:name":"Terban",
    "qs:name_adm0":"Indonesia",
    "qs:name_adm1":"Daerah Istimewa Yogyakarta",
    "qs:photos_9k":1,
    "qs:photos_9r":1,
    "qs:photos_all":1,
    "qs:photos_sr":0,
    "qs:placetype":"Town",
    "qs:pop_sr":"0",
    "wof:lang_x_official":[
        "ind"
    ],
    "wof:lang_x_spoken":[
        "ind",
        "eng"
    ],
    "wof:name":"Terban",
    "wof:placetype":"locality",
    "wof:population":0
},
  "geometry": {"coordinates":[110.37389,-7.77694],"type":"Point"}
}