{
  "type": "Feature",
  "properties": {
    "gn:admin1_code":"31.0",
    "gn:asciiname":"Tonsealama",
    "gn:country_code":"ID",
    "gn:dem":704,
    "gn:feature_class":"P",
    "gn:feature_code":"PPL",
    "gn:name":"Tonsealama",
    "gn:population":0,
    "gn:timezone":"Asia/Makassar",
    "iso:country":"ID",
    "name:ind_x_preferred":[
        "Tonsealama"
    ],
    "name:und_x_variant":[
        "Tonsea Sama"
    ],
    "wof:lang_x_official":[
        "ind"
    ],
    "wof:lang_x_spoken":[
        "ind",
        "eng"
    ],
    "wof:name":"Tonsealama",
    "wof:placetype":"locality"
},
  "geometry": {"coordinates":[124.92270000000001,1.3231],"type":"Point"}
}