{
  "type": "Feature",
  "properties": {
    "gn:admin1_code":"26",
    "gn:asciiname":"Balige",
    "gn:country_code":"ID",
    "gn:dem":74,
    "gn:feature_class":"P",
    "gn:feature_code":"PPL",
    "gn:name":"Balige",
    "gn:population":0,
    "gn:timezone":"Asia/Jakarta",
    "iso:country":"ID",
    "name:ind_x_preferred":[
        "Balige"
    ],
    "name:jav_x_preferred":[
        "Balige"
    ],
    "name:min_x_preferred":[
        "Balige"
    ],
    "name:msa_x_preferred":[
        "Balige"
    ],
    "wof:lang_x_official":[
        "ind"
    ],
    "wof:lang_x_spoken":[
        "ind",
        "eng"
    ],
    "wof:name":"Balige",
    "wof:placetype":"locality"
},
  "geometry": {"coordinates":[99.2878,3.1112],"type":"Point"}
}