{
  "type": "Feature",
  "properties": {
    "gn:admin1_code":"7",
    "gn:asciiname":"Tukul",
    "gn:country_code":"ID",
    "gn:dem":162,
    "gn:feature_class":"P",
    "gn:feature_code":"PPL",
    "gn:name":"Tukul",
    "gn:population":0,
    "gn:timezone":"Asia/Jakarta",
    "iso:country":"ID",
    "name:ind_x_preferred":[
        "Tukul"
    ],
    "name:ita_x_preferred":[
        "Tucul"
    ],
    "wof:name":"Tukul",
    "wof:placetype":"locality"
},
  "geometry": {"coordinates":[110.95806,-8.02583],"type":"Point"}
}