{
  "type": "Feature",
  "properties": {
    "gn:admin1_code":"30.0",
    "gn:asciiname":"Panjiwulung",
    "gn:country_code":"ID",
    "gn:dem":718,
    "gn:feature_class":"P",
    "gn:feature_code":"PPL",
    "gn:name":"Panjiwulung",
    "gn:population":0,
    "gn:timezone":"Asia/Jakarta",
    "iso:country":"ID",
    "name:ind_x_preferred":[
        "Panjiwulung"
    ],
    "wof:name":"Panjiwulung",
    "wof:placetype":"locality"
},
  "geometry": {"coordinates":[107.9003,-7.2141],"type":"Point"}
}