{
  "type": "Feature",
  "properties": {
    "gn:admin1_code":"7",
    "gn:asciiname":"Gumelem",
    "gn:country_code":"ID",
    "gn:dem":1546,
    "gn:feature_class":"P",
    "gn:feature_code":"PPL",
    "gn:name":"Gumelem",
    "gn:population":0,
    "gn:timezone":"Asia/Jakarta",
    "iso:country":"ID",
    "name:ind_x_preferred":[
        "Gumelem"
    ],
    "wof:name":"Gumelem",
    "wof:placetype":"locality"
},
  "geometry": {"coordinates":[109.74139,-7.18861],"type":"Point"}
}