{
  "type": "Feature",
  "properties": {
    "gn:admin1_code":"8.0",
    "gn:asciiname":"Jambu",
    "gn:country_code":"ID",
    "gn:dem":16,
    "gn:feature_class":"P",
    "gn:feature_code":"PPL",
    "gn:name":"Jambu",
    "gn:population":0,
    "gn:timezone":"Asia/Jakarta",
    "iso:country":"ID",
    "name:ceb_x_preferred":[
        "Jambu"
    ],
    "name:deu_x_preferred":[
        "Jambu"
    ],
    "name:ind_x_preferred":[
        "Jambu"
    ],
    "name:nld_x_preferred":[
        "Jambu"
    ],
    "name:swe_x_preferred":[
        "Jambu"
    ],
    "wof:name":"Jambu",
    "wof:placetype":"locality"
},
  "geometry": {"coordinates":[113.9328,-7.0004],"type":"Point"}
}