{
  "type": "Feature",
  "properties": {
    "gn:admin1_code":"0.0",
    "gn:asciiname":"Ciseuseupan",
    "gn:cc2":"ID",
    "gn:country_code":"ID",
    "gn:dem":335,
    "gn:feature_class":"P",
    "gn:feature_code":"PPL",
    "gn:name":"Ciseuseupan",
    "gn:population":0,
    "gn:timezone":"Asia/Jakarta",
    "iso:country":"ID",
    "name:und_x_variant":[
        "Tjiseuseupan",
        "Ciseuseupan"
    ],
    "wof:lang_x_official":[
        "ind"
    ],
    "wof:lang_x_spoken":[
        "ind",
        "eng"
    ],
    "wof:name":"Ciseuseupan",
    "wof:placetype":"locality"
},
  "geometry": {"coordinates":[106.11667,-6.75],"type":"Point"}
}