{
  "type": "Feature",
  "properties": {
    "gn:admin1_code":"8.0",
    "gn:asciiname":"Masaran",
    "gn:country_code":"ID",
    "gn:dem":40,
    "gn:feature_class":"P",
    "gn:feature_code":"PPL",
    "gn:name":"Masaran",
    "gn:population":0,
    "gn:timezone":"Asia/Jakarta",
    "iso:country":"ID",
    "name:ind_x_preferred":[
        "Masaran"
    ],
    "wof:name":"Masaran",
    "wof:placetype":"locality"
},
  "geometry": {"coordinates":[113.02200000000001,-6.9176],"type":"Point"}
}