{
  "type": "Feature",
  "properties": {
    "gn:admin1_code":"38",
    "gn:asciiname":"Komplek Hasanuddin",
    "gn:country_code":"ID",
    "gn:dem":13,
    "gn:feature_class":"P",
    "gn:feature_code":"PPL",
    "gn:name":"Komplek Hasanuddin",
    "gn:population":0,
    "gn:timezone":"Asia/Makassar",
    "iso:country":"ID",
    "name:ind_x_preferred":[
        "Komplek Hasanuddin"
    ],
    "wof:name":"Komplek Hasanuddin",
    "wof:placetype":"locality"
},
  "geometry": {"coordinates":[119.45059999999999,-5.1956],"type":"Point"}
}