{
  "type": "Feature",
  "properties": {
    "gn:admin1_code":"30",
    "gn:asciiname":"Lemahneundeut",
    "gn:country_code":"ID",
    "gn:dem":1290,
    "gn:feature_class":"P",
    "gn:feature_code":"PPL",
    "gn:name":"Lemahneundeut",
    "gn:population":0,
    "gn:timezone":"Asia/Jakarta",
    "iso:country":"ID",
    "wof:name":"Lemahneundeut",
    "wof:placetype":"locality"
},
  "geometry": {"coordinates":[107.42694,-7.08806],"type":"Point"}
}