{
  "type": "Feature",
  "properties": {
    "gn:admin1_code":"26.0",
    "gn:asciiname":"Simanampang Satu",
    "gn:country_code":"ID",
    "gn:dem":927,
    "gn:feature_class":"P",
    "gn:feature_code":"PPL",
    "gn:name":"Simanampang Satu",
    "gn:population":0,
    "gn:timezone":"Asia/Jakarta",
    "iso:country":"ID",
    "name:ind_x_preferred":[
        "Simanampang Satu"
    ],
    "name:und_x_variant":[
        "Simanampang I"
    ],
    "wof:name":"Simanampang Satu",
    "wof:placetype":"locality"
},
  "geometry": {"coordinates":[98.6908,2.6577],"type":"Point"}
}