{
  "type": "Feature",
  "properties": {
    "gn:admin1_code":"12",
    "gn:asciiname":"Sungaibatok",
    "gn:country_code":"ID",
    "gn:dem":4,
    "gn:feature_class":"P",
    "gn:feature_code":"PPL",
    "gn:name":"Sungaibatok",
    "gn:population":0,
    "gn:timezone":"Asia/Makassar",
    "iso:country":"ID",
    "name:ind_x_preferred":[
        "Sungaibatok"
    ],
    "wof:name":"Sungaibatok",
    "wof:placetype":"locality"
},
  "geometry": {"coordinates":[114.7346,-3.0745],"type":"Point"}
}