{
  "type": "Feature",
  "properties": {
    "gn:admin1_code":"24",
    "gn:asciiname":"Simalaiming",
    "gn:country_code":"ID",
    "gn:dem":8,
    "gn:feature_class":"P",
    "gn:feature_code":"PPL",
    "gn:name":"Simalaiming",
    "gn:population":0,
    "gn:timezone":"Asia/Jakarta",
    "iso:country":"ID",
    "name:ind_x_preferred":[
        "Simalaiming"
    ],
    "wof:name":"Simalaiming",
    "wof:placetype":"locality"
},
  "geometry": {"coordinates":[99.18935,-1.74664],"type":"Point"}
}