{
  "type": "Feature",
  "properties": {
    "gn:country":"ID",
    "gn:fcode":"ADM3",
    "gn:pop":0,
    "iso:country":"ID",
    "name:ind_x_preferred":[
        "Kecamatan Pallangga"
    ],
    "name:unk_x_variant":[
        "Palangga"
    ],
    "qs:name":"Kecamatan Pallangga",
    "qs:photos_9r":0,
    "qs:photos_sr":0,
    "qs:pop_sr":"0",
    "wof:name":"Kecamatan Pallangga",
    "wof:placetype":"localadmin",
    "wof:population":0
},
  "geometry": {"coordinates":[119.45059999999999,-5.2442],"type":"Point"}
}