{
  "type": "Feature",
  "properties": {
    "gn:admin1_code":"33",
    "gn:asciiname":"Wado",
    "gn:country_code":"ID",
    "gn:dem":147,
    "gn:feature_class":"P",
    "gn:feature_code":"PPL",
    "gn:name":"Wado",
    "gn:population":0,
    "gn:timezone":"Asia/Jakarta",
    "iso:country":"ID",
    "name:ceb_x_preferred":[
        "Wado"
    ],
    "name:ind_x_preferred":[
        "Wado"
    ],
    "name:nld_x_preferred":[
        "Wado"
    ],
    "name:swe_x_preferred":[
        "Wado"
    ],
    "wof:lang_x_official":[
        "ind"
    ],
    "wof:lang_x_spoken":[
        "ind",
        "eng"
    ],
    "wof:name":"Wado",
    "wof:placetype":"locality"
},
  "geometry": {"coordinates":[106.1519,-6.2622],"type":"Point"}
}