{
  "type": "Feature",
  "properties": {
    "gn:admin1_code":"37",
    "gn:asciiname":"Kampungrampang",
    "gn:country_code":"ID",
    "gn:dem":6,
    "gn:feature_class":"P",
    "gn:feature_code":"PPL",
    "gn:name":"Kampungrampang",
    "gn:population":0,
    "gn:timezone":"Asia/Jakarta",
    "iso:country":"ID",
    "name:ind_x_preferred":[
        "Kampungrampang"
    ],
    "wof:name":"Kampungrampang",
    "wof:placetype":"locality"
},
  "geometry": {"coordinates":[101.42677,1.79268],"type":"Point"}
}