{
  "type": "Feature",
  "properties": {
    "gn:admin1_code":"8.0",
    "gn:asciiname":"Kedungpeluk",
    "gn:country_code":"ID",
    "gn:dem":256,
    "gn:feature_class":"P",
    "gn:feature_code":"PPL",
    "gn:name":"Kedungpeluk",
    "gn:population":0,
    "gn:timezone":"Asia/Jakarta",
    "iso:country":"ID",
    "name:ind_x_preferred":[
        "Kedungpeluk"
    ],
    "wof:name":"Kedungpeluk",
    "wof:placetype":"locality"
},
  "geometry": {"coordinates":[112.5377,-7.6017],"type":"Point"}
}