{
  "type": "Feature",
  "properties": {
    "gn:admin1_code":"7",
    "gn:asciiname":"Sikepyar",
    "gn:country_code":"ID",
    "gn:dem":1032,
    "gn:feature_class":"P",
    "gn:feature_code":"PPL",
    "gn:name":"Sikepyar",
    "gn:population":0,
    "gn:timezone":"Asia/Jakarta",
    "iso:country":"ID",
    "name:ind_x_preferred":[
        "Sikepyar"
    ],
    "wof:name":"Sikepyar",
    "wof:placetype":"locality"
},
  "geometry": {"coordinates":[109.54583,-7.18583],"type":"Point"}
}