{
  "type": "Feature",
  "properties": {
    "gn:admin1_code":"30",
    "gn:asciiname":"Kampungjuana",
    "gn:country_code":"ID",
    "gn:dem":214,
    "gn:feature_class":"P",
    "gn:feature_code":"PPL",
    "gn:name":"Kampungjuana",
    "gn:population":0,
    "gn:timezone":"Asia/Jakarta",
    "iso:country":"ID",
    "name:ind_x_preferred":[
        "Kampungjuana"
    ],
    "wof:name":"Kampungjuana",
    "wof:placetype":"locality"
},
  "geometry": {"coordinates":[106.79667000000001,-6.56889],"type":"Point"}
}