{
  "type": "Feature",
  "properties": {
    "gn:admin1_code":"1",
    "gn:asciiname":"Ujongbaroh",
    "gn:country_code":"ID",
    "gn:dem":13,
    "gn:feature_class":"P",
    "gn:feature_code":"PPL",
    "gn:name":"Ujongbaroh",
    "gn:population":0,
    "gn:timezone":"Asia/Jakarta",
    "iso:country":"ID",
    "name:ind_x_preferred":[
        "Ujongbaroh"
    ],
    "name:und_x_variant":[
        "Udjongbaroh"
    ],
    "wof:name":"Ujongbaroh",
    "wof:placetype":"locality"
},
  "geometry": {"coordinates":[97.25709999999999,5.0538],"type":"Point"}
}