{
  "type": "Feature",
  "properties": {
    "gn:admin1_code":"30",
    "gn:asciiname":"Pilar",
    "gn:country_code":"ID",
    "gn:dem":505,
    "gn:feature_class":"P",
    "gn:feature_code":"PPL",
    "gn:name":"Pilar",
    "gn:population":0,
    "gn:timezone":"Asia/Jakarta",
    "iso:country":"ID",
    "name:bre_x_preferred":[
        "Pilar"
    ],
    "name:cat_x_preferred":[
        "Pilar"
    ],
    "name:ceb_x_preferred":[
        "Pilar"
    ],
    "name:deu_x_preferred":[
        "Pilar"
    ],
    "name:fra_x_preferred":[
        "Pilar"
    ],
    "name:ilo_x_preferred":[
        "Pilar"
    ],
    "name:ind_x_preferred":[
        "Pilar"
    ],
    "name:ita_x_preferred":[
        "Pilar"
    ],
    "name:jpn_x_preferred":[
        "\u30d4\u30e9\u30fc\u30eb"
    ],
    "name:lit_x_preferred":[
        "Pilaras"
    ],
    "name:nld_x_preferred":[
        "Pilar"
    ],
    "name:nor_x_preferred":[
        "Pilar"
    ],
    "name:por_x_preferred":[
        "Pilar"
    ],
    "name:sco_x_preferred":[
        "Pilar"
    ],
    "name:slv_x_preferred":[
        "Pilar"
    ],
    "name:spa_x_preferred":[
        "Pilar"
    ],
    "name:swe_x_preferred":[
        "Pilar"
    ],
    "name:vie_x_preferred":[
        "Pilar"
    ],
    "name:vol_x_preferred":[
        "Pilar"
    ],
    "name:war_x_preferred":[
        "Pilar"
    ],
    "name:zho_x_preferred":[
        "\u76ae\u62c9\u723e"
    ],
    "wof:lang_x_official":[
        "ind"
    ],
    "wof:lang_x_spoken":[
        "ind",
        "eng"
    ],
    "wof:name":"Pilar",
    "wof:placetype":"locality"
},
  "geometry": {"coordinates":[106.85639,-6.66472],"type":"Point"}
}