{
  "type": "Feature",
  "properties": {
    "gn:admin1_code":"18",
    "gn:asciiname":"Donga",
    "gn:country_code":"ID",
    "gn:dem":388,
    "gn:feature_class":"P",
    "gn:feature_code":"PPL",
    "gn:name":"Donga",
    "gn:population":0,
    "gn:timezone":"Asia/Makassar",
    "iso:country":"ID",
    "name:ceb_x_preferred":[
        "Donga"
    ],
    "name:deu_x_preferred":[
        "Donga"
    ],
    "name:fas_x_preferred":[
        "\u062f\u0648\u0646\u06af\u0627"
    ],
    "name:fra_x_preferred":[
        "Donga"
    ],
    "name:heb_x_preferred":[
        "\u05d3\u05d5\u05e0\u05d2\u05d4"
    ],
    "name:ind_x_preferred":[
        "Donga"
    ],
    "name:ita_x_preferred":[
        "Donga"
    ],
    "name:jpn_x_preferred":[
        "\u30c9\u30f3\u30ac"
    ],
    "name:slk_x_preferred":[
        "Donga"
    ],
    "name:swe_x_preferred":[
        "Donga"
    ],
    "wof:lang_x_official":[
        "ind"
    ],
    "wof:lang_x_spoken":[
        "ind",
        "eng"
    ],
    "wof:name":"Donga",
    "wof:placetype":"locality"
},
  "geometry": {"coordinates":[121.57980000000001,-8.7756],"type":"Point"}
}