{
  "type": "Feature",
  "properties": {
    "gn:admin1_code":"2.0",
    "gn:asciiname":"Banjar Tengah",
    "gn:country_code":"ID",
    "gn:dem":84,
    "gn:feature_class":"P",
    "gn:feature_code":"PPL",
    "gn:name":"Banjar Tengah",
    "gn:population":0,
    "gn:timezone":"Asia/Makassar",
    "iso:country":"ID",
    "name:ind_x_preferred":[
        "Banjar Tengah"
    ],
    "wof:name":"Banjar Tengah",
    "wof:placetype":"locality"
},
  "geometry": {"coordinates":[115.16249999999999,-8.604],"type":"Point"}
}