{
  "type": "Feature",
  "properties": {
    "gn:admin1_code":"21.0",
    "gn:asciiname":"Mamu",
    "gn:country_code":"ID",
    "gn:dem":973,
    "gn:feature_class":"P",
    "gn:feature_code":"PPL",
    "gn:name":"Mamu",
    "gn:population":0,
    "gn:timezone":"Asia/Makassar",
    "iso:country":"ID",
    "name:fra_x_preferred":[
        "Mamu"
    ],
    "name:ind_x_preferred":[
        "Mamu"
    ],
    "name:und_x_variant":[
        "Mamoe"
    ],
    "wof:lang_x_official":[
        "ind"
    ],
    "wof:lang_x_spoken":[
        "ind",
        "eng"
    ],
    "wof:name":"Mamu",
    "wof:placetype":"locality"
},
  "geometry": {"coordinates":[119.96303,-1.89638],"type":"Point"}
}