{
  "type": "Feature",
  "properties": {
    "gn:admin1_code":"5.0",
    "gn:asciiname":"Tanjungpauhmudik",
    "gn:country_code":"ID",
    "gn:dem":832,
    "gn:feature_class":"P",
    "gn:feature_code":"PPL",
    "gn:name":"Tanjungpauhmudik",
    "gn:population":0,
    "gn:timezone":"Asia/Jakarta",
    "iso:country":"ID",
    "name:ind_x_preferred":[
        "Tanjungpauhmudik"
    ],
    "wof:name":"Tanjungpauhmudik",
    "wof:placetype":"locality"
},
  "geometry": {"coordinates":[101.41930000000001,-2.1048],"type":"Point"}
}