{
  "type": "Feature",
  "properties": {
    "gn:admin1_code":"18",
    "gn:asciiname":"Pogolede",
    "gn:country_code":"ID",
    "gn:dem":64,
    "gn:feature_class":"P",
    "gn:feature_code":"PPL",
    "gn:name":"Pogolede",
    "gn:population":0,
    "gn:timezone":"Asia/Makassar",
    "iso:country":"ID",
    "name:ind_x_preferred":[
        "Pogolede"
    ],
    "wof:name":"Pogolede",
    "wof:placetype":"locality"
},
  "geometry": {"coordinates":[119.1947,-9.4207],"type":"Point"}
}