{
  "type": "Feature",
  "properties": {
    "gn:admin1_code":"18",
    "gn:asciiname":"Gogojabi",
    "gn:country_code":"ID",
    "gn:dem":386,
    "gn:feature_class":"P",
    "gn:feature_code":"PPL",
    "gn:name":"Gogojabi",
    "gn:population":0,
    "gn:timezone":"Asia/Makassar",
    "iso:country":"ID",
    "name:ind_x_preferred":[
        "Gogojabi"
    ],
    "wof:name":"Gogojabi",
    "wof:placetype":"locality"
},
  "geometry": {"coordinates":[121.5557,-8.7662],"type":"Point"}
}