{
  "type": "Feature",
  "properties": {
    "gn:admin1_code":"7",
    "gn:asciiname":"Bodeh",
    "gn:country_code":"ID",
    "gn:dem":138,
    "gn:feature_class":"P",
    "gn:feature_code":"PPL",
    "gn:name":"Bodeh",
    "gn:population":0,
    "gn:timezone":"Asia/Jakarta",
    "iso:country":"ID",
    "name:ind_x_preferred":[
        "Bodeh"
    ],
    "wof:name":"Bodeh",
    "wof:placetype":"locality"
},
  "geometry": {"coordinates":[111.30444,-7.29111],"type":"Point"}
}