{
  "type": "Feature",
  "properties": {
    "gn:admin1_code":"1",
    "gn:asciiname":"Ujong Rundeng",
    "gn:country_code":"ID",
    "gn:dem":6,
    "gn:feature_class":"P",
    "gn:feature_code":"PPL",
    "gn:name":"Ujong Rundeng",
    "gn:population":0,
    "gn:timezone":"Asia/Jakarta",
    "iso:country":"ID",
    "name:ind_x_preferred":[
        "Ujong Rundeng"
    ],
    "wof:name":"Ujong Rundeng",
    "wof:placetype":"locality"
},
  "geometry": {"coordinates":[95.4738,4.8317],"type":"Point"}
}