{
  "type": "Feature",
  "properties": {
    "gn:admin1_code":"30",
    "gn:asciiname":"Karanguyah",
    "gn:country_code":"ID",
    "gn:dem":2,
    "gn:feature_class":"P",
    "gn:feature_code":"PPL",
    "gn:name":"Karanguyah",
    "gn:population":0,
    "gn:timezone":"Asia/Jakarta",
    "iso:country":"ID",
    "name:ind_x_preferred":[
        "Karanguyah"
    ],
    "wof:name":"Karanguyah",
    "wof:placetype":"locality"
},
  "geometry": {"coordinates":[108.22556000000002,-6.33056],"type":"Point"}
}