{
  "type": "Feature",
  "properties": {
    "gn:admin1_code":"26",
    "gn:asciiname":"Lobugala",
    "gn:country_code":"ID",
    "gn:dem":1130,
    "gn:feature_class":"P",
    "gn:feature_code":"PPL",
    "gn:name":"Lobugala",
    "gn:population":0,
    "gn:timezone":"Asia/Jakarta",
    "iso:country":"ID",
    "name:ind_x_preferred":[
        "Lobugala"
    ],
    "wof:name":"Lobugala",
    "wof:placetype":"locality"
},
  "geometry": {"coordinates":[99.25606000000001,1.94973],"type":"Point"}
}