{
  "type": "Feature",
  "properties": {
    "gn:admin1_code":"30",
    "gn:asciiname":"Cidahupasar",
    "gn:country_code":"ID",
    "gn:dem":595,
    "gn:feature_class":"P",
    "gn:feature_code":"PPL",
    "gn:name":"Cidahupasar",
    "gn:population":0,
    "gn:timezone":"Asia/Jakarta",
    "iso:country":"ID",
    "name:ind_x_preferred":[
        "Cidahupasar"
    ],
    "wof:lang_x_official":[
        "ind"
    ],
    "wof:lang_x_spoken":[
        "ind",
        "eng"
    ],
    "wof:name":"Cidahupasar",
    "wof:placetype":"locality"
},
  "geometry": {"coordinates":[106.75306,-6.77583],"type":"Point"}
}