{
  "type": "Feature",
  "properties": {
    "gn:admin1_code":"30",
    "gn:asciiname":"Sukalaksana",
    "gn:country_code":"ID",
    "gn:dem":474,
    "gn:feature_class":"P",
    "gn:feature_code":"PPL",
    "gn:name":"Sukalaksana",
    "gn:population":0,
    "gn:timezone":"Asia/Jakarta",
    "iso:country":"ID",
    "name:ind_x_preferred":[
        "Sukalaksana"
    ],
    "wof:name":"Sukalaksana",
    "wof:placetype":"locality"
},
  "geometry": {"coordinates":[107.94278,-6.83528],"type":"Point"}
}