{
  "type": "Feature",
  "properties": {
    "gn:admin1_code":"38.0",
    "gn:asciiname":"Lamma",
    "gn:country_code":"ID",
    "gn:dem":227,
    "gn:feature_class":"P",
    "gn:feature_code":"PPL",
    "gn:name":"Lamma",
    "gn:population":0,
    "gn:timezone":"Asia/Makassar",
    "iso:country":"ID",
    "name:deu_x_preferred":[
        "Lamma"
    ],
    "name:hun_x_preferred":[
        "Lamma"
    ],
    "name:ind_x_preferred":[
        "Lamma"
    ],
    "wof:name":"Lamma",
    "wof:placetype":"locality"
},
  "geometry": {"coordinates":[120.2424,-3.3366],"type":"Point"}
}