{
  "type": "Feature",
  "properties": {
    "gn:admin1_code":"26",
    "gn:asciiname":"Barisan",
    "gn:country_code":"ID",
    "gn:dem":894,
    "gn:feature_class":"P",
    "gn:feature_code":"PPL",
    "gn:name":"Barisan",
    "gn:population":0,
    "gn:timezone":"Asia/Jakarta",
    "iso:country":"ID",
    "name:deu_x_preferred":[
        "Barisan"
    ],
    "name:fra_x_preferred":[
        "Barisan"
    ],
    "name:ind_x_preferred":[
        "Barisan"
    ],
    "name:jpn_x_preferred":[
        "\u30d0\u30ea\u30b5\u30f3"
    ],
    "wof:lang_x_official":[
        "ind"
    ],
    "wof:lang_x_spoken":[
        "ind",
        "eng"
    ],
    "wof:name":"Barisan",
    "wof:placetype":"locality"
},
  "geometry": {"coordinates":[98.32470000000001,2.5519],"type":"Point"}
}