{
  "type": "Feature",
  "properties": {
    "gn:admin1_code":"26",
    "gn:asciiname":"Gajingtonga",
    "gn:country_code":"ID",
    "gn:dem":152,
    "gn:feature_class":"P",
    "gn:feature_code":"PPL",
    "gn:name":"Gajingtonga",
    "gn:population":0,
    "gn:timezone":"Asia/Jakarta",
    "iso:country":"ID",
    "name:ind_x_preferred":[
        "Gajingtonga"
    ],
    "name:und_x_variant":[
        "Gadjingtongahtongah"
    ],
    "wof:name":"Gajingtonga",
    "wof:placetype":"locality"
},
  "geometry": {"coordinates":[99.1747,3.0668],"type":"Point"}
}