{
  "type": "Feature",
  "properties": {
    "gn:admin1_code":"7",
    "gn:asciiname":"Kudon",
    "gn:country_code":"ID",
    "gn:dem":84,
    "gn:feature_class":"P",
    "gn:feature_code":"PPL",
    "gn:name":"Kudon",
    "gn:population":0,
    "gn:timezone":"Asia/Jakarta",
    "iso:country":"ID",
    "name:ind_x_preferred":[
        "Kudon"
    ],
    "wof:name":"Kudon",
    "wof:placetype":"locality"
},
  "geometry": {"coordinates":[111.31619999999999,-7.0281],"type":"Point"}
}