{
  "type": "Feature",
  "properties": {
    "gn:admin1_code":"30",
    "gn:asciiname":"Babakanpasirangin",
    "gn:country_code":"ID",
    "gn:dem":932,
    "gn:feature_class":"P",
    "gn:feature_code":"PPL",
    "gn:name":"Babakanpasirangin",
    "gn:population":0,
    "gn:timezone":"Asia/Jakarta",
    "iso:country":"ID",
    "name:ind_x_preferred":[
        "Babakanpasirangin"
    ],
    "wof:name":"Babakanpasirangin",
    "wof:placetype":"locality"
},
  "geometry": {"coordinates":[107.72444,-6.89444],"type":"Point"}
}