{
  "type": "Feature",
  "properties": {
    "gn:admin1_code":"18.0",
    "gn:asciiname":"Tanahmerah",
    "gn:country_code":"ID",
    "gn:dem":387,
    "gn:feature_class":"P",
    "gn:feature_code":"PPL",
    "gn:name":"Tanahmerah",
    "gn:population":0,
    "gn:timezone":"Asia/Makassar",
    "iso:country":"ID",
    "name:ind_x_preferred":[
        "Tanahmerah"
    ],
    "name:und_x_variant":[
        "Poepoet",
        "Puput"
    ],
    "wof:name":"Tanahmerah",
    "wof:placetype":"locality"
},
  "geometry": {"coordinates":[123.946,-10.0309],"type":"Point"}
}