{
  "type": "Feature",
  "properties": {
    "gn:admin1_code":"7",
    "gn:asciiname":"Ngrojo",
    "gn:country_code":"ID",
    "gn:dem":16,
    "gn:feature_class":"P",
    "gn:feature_code":"PPL",
    "gn:name":"Ngrojo",
    "gn:population":0,
    "gn:timezone":"Asia/Jakarta",
    "iso:country":"ID",
    "name:ind_x_preferred":[
        "Ngrojo"
    ],
    "wof:name":"Ngrojo",
    "wof:placetype":"locality"
},
  "geometry": {"coordinates":[110.7538,-7.0566],"type":"Point"}
}