{
  "type": "Feature",
  "properties": {
    "gn:admin1_code":"0.0",
    "gn:asciiname":"Batu-hirang",
    "gn:cc2":"ID",
    "gn:country_code":"ID",
    "gn:dem":2,
    "gn:feature_class":"P",
    "gn:feature_code":"PPL",
    "gn:name":"Batu-hirang",
    "gn:population":0,
    "gn:timezone":"Asia/Pontianak",
    "iso:country":"ID",
    "name:und_x_variant":[
        "Batoe-hirang",
        "Batu-hirang"
    ],
    "wof:name":"Batu-hirang",
    "wof:placetype":"locality"
},
  "geometry": {"coordinates":[112.40000000000001,-3.21667],"type":"Point"}
}