{
  "type": "Feature",
  "properties": {
    "gn:admin1_code":"8.0",
    "gn:asciiname":"Jate Laok",
    "gn:country_code":"ID",
    "gn:dem":63,
    "gn:feature_class":"P",
    "gn:feature_code":"PPL",
    "gn:name":"Jate Laok",
    "gn:population":0,
    "gn:timezone":"Asia/Jakarta",
    "iso:country":"ID",
    "name:ind_x_preferred":[
        "Jate Laok"
    ],
    "wof:name":"Jate Laok",
    "wof:placetype":"locality"
},
  "geometry": {"coordinates":[113.95569999999999,-7.0846],"type":"Point"}
}