{
  "type": "Feature",
  "properties": {
    "gn:admin1_code":"30.0",
    "gn:asciiname":"Citapenlandeuh",
    "gn:country_code":"ID",
    "gn:dem":324,
    "gn:feature_class":"P",
    "gn:feature_code":"PPL",
    "gn:name":"Citapenlandeuh",
    "gn:population":0,
    "gn:timezone":"Asia/Jakarta",
    "iso:country":"ID",
    "name:ind_x_preferred":[
        "Citapenlandeuh"
    ],
    "wof:name":"Citapenlandeuh",
    "wof:placetype":"locality"
},
  "geometry": {"coordinates":[108.4862,-7.1297],"type":"Point"}
}