{
  "type": "Feature",
  "properties": {
    "gn:admin1_code":"26.0",
    "gn:asciiname":"Aeknagodang",
    "gn:country_code":"ID",
    "gn:dem":901,
    "gn:feature_class":"P",
    "gn:feature_code":"PPL",
    "gn:name":"Aeknagodang",
    "gn:population":0,
    "gn:timezone":"Asia/Jakarta",
    "iso:country":"ID",
    "name:ind_x_preferred":[
        "Aeknagodang"
    ],
    "wof:name":"Aeknagodang",
    "wof:placetype":"locality"
},
  "geometry": {"coordinates":[98.5972,2.1179],"type":"Point"}
}