{
  "type": "Feature",
  "properties": {
    "gn:admin1_code":"26",
    "gn:asciiname":"Simaninggji",
    "gn:country_code":"ID",
    "gn:dem":1203,
    "gn:feature_class":"P",
    "gn:feature_code":"PPL",
    "gn:name":"Simaninggji",
    "gn:population":0,
    "gn:timezone":"Asia/Jakarta",
    "iso:country":"ID",
    "name:ind_x_preferred":[
        "Simaninggji"
    ],
    "wof:name":"Simaninggji",
    "wof:placetype":"locality"
},
  "geometry": {"coordinates":[99.15730000000001,2.0291],"type":"Point"}
}