{
  "type": "Feature",
  "properties": {
    "gn:admin1_code":"26",
    "gn:asciiname":"Bulan Baru",
    "gn:country_code":"ID",
    "gn:dem":1344,
    "gn:feature_class":"P",
    "gn:feature_code":"PPL",
    "gn:name":"Bulan Baru",
    "gn:population":0,
    "gn:timezone":"Asia/Jakarta",
    "iso:country":"ID",
    "name:ind_x_preferred":[
        "Bulan Baru"
    ],
    "wof:name":"Bulan Baru",
    "wof:placetype":"locality"
},
  "geometry": {"coordinates":[98.489,3.1603],"type":"Point"}
}