{
  "type": "Feature",
  "properties": {
    "gn:admin1_code":"7",
    "gn:asciiname":"Biron",
    "gn:country_code":"ID",
    "gn:dem":600,
    "gn:feature_class":"P",
    "gn:feature_code":"PPL",
    "gn:name":"Biron",
    "gn:population":0,
    "gn:timezone":"Asia/Jakarta",
    "iso:country":"ID",
    "name:ind_x_preferred":[
        "Biron"
    ],
    "wof:name":"Biron",
    "wof:placetype":"locality"
},
  "geometry": {"coordinates":[110.16417,-7.19583],"type":"Point"}
}