{
  "type": "Feature",
  "properties": {
    "gn:admin1_code":"7",
    "gn:asciiname":"Biron",
    "gn:country_code":"ID",
    "gn:dem":600,
    "gn:feature_class":"P",
    "gn:feature_code":"PPL",
    "gn:name":"Biron",
    "gn:population":0,
    "gn:timezone":"Asia/Jakarta",
    "iso:country":"ID",
    "name:ceb_x_preferred":[
        "Biron"
    ],
    "name:ces_x_preferred":[
        "Biron"
    ],
    "name:deu_x_preferred":[
        "Biron"
    ],
    "name:epo_x_preferred":[
        "Biron"
    ],
    "name:fra_x_preferred":[
        "Biron"
    ],
    "name:ind_x_preferred":[
        "Biron"
    ],
    "name:ita_x_preferred":[
        "Biron"
    ],
    "name:lav_x_preferred":[
        "B\u012brons"
    ],
    "name:nds_x_preferred":[
        "Biron"
    ],
    "name:nld_x_preferred":[
        "Biron"
    ],
    "name:pms_x_preferred":[
        "Biron"
    ],
    "name:pol_x_preferred":[
        "Biron"
    ],
    "name:por_x_preferred":[
        "Biron"
    ],
    "name:rus_x_preferred":[
        "\u0411\u0438\u0440\u043e\u043d"
    ],
    "name:slk_x_preferred":[
        "Biron"
    ],
    "name:spa_x_preferred":[
        "Biron"
    ],
    "name:srp_x_preferred":[
        "\u0411\u0438\u0440\u043e\u043d"
    ],
    "name:swe_x_preferred":[
        "Biron"
    ],
    "name:ukr_x_preferred":[
        "\u0411\u0456\u0440\u043e\u043d"
    ],
    "wof:lang_x_official":[
        "ind"
    ],
    "wof:lang_x_spoken":[
        "ind",
        "eng"
    ],
    "wof:name":"Biron",
    "wof:placetype":"locality"
},
  "geometry": {"coordinates":[110.16417,-7.19583],"type":"Point"}
}