{
  "type": "Feature",
  "properties": {
    "gn:admin1_code":"18.0",
    "gn:asciiname":"Saendale",
    "gn:country_code":"ID",
    "gn:dem":63,
    "gn:feature_class":"P",
    "gn:feature_code":"PPL",
    "gn:name":"Saendale",
    "gn:population":0,
    "gn:timezone":"Asia/Makassar",
    "iso:country":"ID",
    "name:ind_x_preferred":[
        "Saendale"
    ],
    "wof:name":"Saendale",
    "wof:placetype":"locality"
},
  "geometry": {"coordinates":[123.2169,-10.721],"type":"Point"}
}