{
  "type": "Feature",
  "properties": {
    "gn:admin1_code":"30",
    "gn:asciiname":"Papanggungan",
    "gn:country_code":"ID",
    "gn:dem":667,
    "gn:feature_class":"P",
    "gn:feature_code":"PPL",
    "gn:name":"Papanggungan",
    "gn:population":0,
    "gn:timezone":"Asia/Jakarta",
    "iso:country":"ID",
    "name:ind_x_preferred":[
        "Papanggungan"
    ],
    "wof:name":"Papanggungan",
    "wof:placetype":"locality"
},
  "geometry": {"coordinates":[107.76833000000001,-6.98222],"type":"Point"}
}