{
  "type": "Feature",
  "properties": {
    "gn:admin1_code":"38",
    "gn:asciiname":"Lauwa",
    "gn:country_code":"ID",
    "gn:dem":18,
    "gn:feature_class":"P",
    "gn:feature_code":"PPL",
    "gn:name":"Lauwa",
    "gn:population":0,
    "gn:timezone":"Asia/Makassar",
    "iso:country":"ID",
    "name:ind_x_preferred":[
        "Lauwa"
    ],
    "wof:name":"Lauwa",
    "wof:placetype":"locality"
},
  "geometry": {"coordinates":[120.3775,-3.3628],"type":"Point"}
}