{
  "type": "Feature",
  "properties": {
    "gn:admin1_code":"8",
    "gn:asciiname":"Curahjeru Timur",
    "gn:country_code":"ID",
    "gn:dem":31,
    "gn:feature_class":"P",
    "gn:feature_code":"PPL",
    "gn:name":"Curahjeru Timur",
    "gn:population":0,
    "gn:timezone":"Asia/Jakarta",
    "iso:country":"ID",
    "name:ind_x_preferred":[
        "Curahjeru Timur"
    ],
    "wof:name":"Curahjeru Timur",
    "wof:placetype":"locality"
},
  "geometry": {"coordinates":[114.0256,-7.6908],"type":"Point"}
}