{
  "type": "Feature",
  "properties": {
    "gn:admin1_code":"8",
    "gn:asciiname":"Trate",
    "gn:country_code":"ID",
    "gn:dem":13,
    "gn:feature_class":"P",
    "gn:feature_code":"PPL",
    "gn:name":"Trate",
    "gn:population":0,
    "gn:timezone":"Asia/Jakarta",
    "iso:country":"ID",
    "name:bos_x_preferred":[
        "Trate"
    ],
    "name:ind_x_preferred":[
        "Trate"
    ],
    "name:nld_x_preferred":[
        "Trate"
    ],
    "name:pol_x_preferred":[
        "Trate"
    ],
    "name:ron_x_preferred":[
        "Trate"
    ],
    "name:slv_x_preferred":[
        "Trate"
    ],
    "name:ukr_x_preferred":[
        "\u0422\u0440\u0430\u0442\u0435"
    ],
    "wof:lang_x_official":[
        "ind"
    ],
    "wof:lang_x_spoken":[
        "ind",
        "eng"
    ],
    "wof:name":"Trate",
    "wof:placetype":"locality"
},
  "geometry": {"coordinates":[112.6534,-7.1553],"type":"Point"}
}