{
  "type": "Feature",
  "properties": {
    "gn:admin1_code":"38.0",
    "gn:asciiname":"Pandanbau",
    "gn:country_code":"ID",
    "gn:dem":370,
    "gn:feature_class":"P",
    "gn:feature_code":"PPL",
    "gn:name":"Pandanbau",
    "gn:population":0,
    "gn:timezone":"Asia/Makassar",
    "iso:country":"ID",
    "name:ind_x_preferred":[
        "Pandanbau"
    ],
    "wof:name":"Pandanbau",
    "wof:placetype":"locality"
},
  "geometry": {"coordinates":[119.6949,-3.2754],"type":"Point"}
}