{
  "type": "Feature",
  "properties": {
    "gn:admin1_code":"26",
    "gn:asciiname":"Hutapadang Dua",
    "gn:country_code":"ID",
    "gn:dem":246,
    "gn:feature_class":"P",
    "gn:feature_code":"PPL",
    "gn:name":"Hutapadang Dua",
    "gn:population":0,
    "gn:timezone":"Asia/Jakarta",
    "iso:country":"ID",
    "name:ind_x_preferred":[
        "Hutapadang Dua"
    ],
    "name:und_x_variant":[
        "Hutapadang 2"
    ],
    "wof:name":"Hutapadang Dua",
    "wof:placetype":"locality"
},
  "geometry": {"coordinates":[99.26090000000001,2.7867],"type":"Point"}
}