{
  "type": "Feature",
  "properties": {
    "gn:admin1_code":"18",
    "gn:asciiname":"Lait",
    "gn:country_code":"ID",
    "gn:dem":739,
    "gn:feature_class":"P",
    "gn:feature_code":"PPL",
    "gn:name":"Lait",
    "gn:population":0,
    "gn:timezone":"Asia/Makassar",
    "iso:country":"ID",
    "name:ind_x_preferred":[
        "Lait"
    ],
    "wof:name":"Lait",
    "wof:placetype":"locality"
},
  "geometry": {"coordinates":[120.2651,-8.5304],"type":"Point"}
}