{
  "type": "Feature",
  "properties": {
    "gn:admin1_code":"30.0",
    "gn:asciiname":"Jayapura",
    "gn:country_code":"ID",
    "gn:dem":596,
    "gn:feature_class":"P",
    "gn:feature_code":"PPLA3",
    "gn:name":"Jayapura",
    "gn:population":0,
    "gn:timezone":"Asia/Jakarta",
    "iso:country":"ID",
    "name:ind_x_preferred":[
        "Jayapura"
    ],
    "wof:name":"Jayapura",
    "wof:placetype":"locality"
},
  "geometry": {"coordinates":[108.0322,-7.352],"type":"Point"}
}