{
  "type": "Feature",
  "properties": {
    "gn:admin1_code":"38",
    "gn:asciiname":"Dea",
    "gn:country_code":"ID",
    "gn:dem":931,
    "gn:feature_class":"P",
    "gn:feature_code":"PPL",
    "gn:name":"Dea",
    "gn:population":0,
    "gn:timezone":"Asia/Makassar",
    "iso:country":"ID",
    "name:ceb_x_preferred":[
        "Dea"
    ],
    "name:deu_x_preferred":[
        "Dea"
    ],
    "name:ind_x_preferred":[
        "Dea"
    ],
    "name:swe_x_preferred":[
        "Dea"
    ],
    "wof:lang_x_official":[
        "ind"
    ],
    "wof:lang_x_spoken":[
        "ind",
        "eng"
    ],
    "wof:name":"Dea",
    "wof:placetype":"locality"
},
  "geometry": {"coordinates":[119.7925,-3.1073],"type":"Point"}
}