{
  "type": "Feature",
  "properties": {
    "gn:admin1_code":"2.0",
    "gn:asciiname":"Kuwumtegallinggah",
    "gn:country_code":"ID",
    "gn:dem":258,
    "gn:feature_class":"P",
    "gn:feature_code":"PPL",
    "gn:name":"Kuwumtegallinggah",
    "gn:population":0,
    "gn:timezone":"Asia/Makassar",
    "iso:country":"ID",
    "name:ind_x_preferred":[
        "Kuwumtegallinggah"
    ],
    "wof:name":"Kuwumtegallinggah",
    "wof:placetype":"locality"
},
  "geometry": {"coordinates":[115.1703,-8.4812],"type":"Point"}
}