{
  "type": "Feature",
  "properties": {
    "gn:admin1_code":"8",
    "gn:asciiname":"Dangmati",
    "gn:country_code":"ID",
    "gn:dem":2,
    "gn:feature_class":"P",
    "gn:feature_code":"PPL",
    "gn:name":"Dangmati",
    "gn:population":0,
    "gn:timezone":"Asia/Jakarta",
    "iso:country":"ID",
    "name:ind_x_preferred":[
        "Dangmati"
    ],
    "wof:name":"Dangmati",
    "wof:placetype":"locality"
},
  "geometry": {"coordinates":[113.1289,-7.1612],"type":"Point"}
}