{
  "type": "Feature",
  "properties": {
    "gn:admin1_code":"0.0",
    "gn:asciiname":"Dolatanden",
    "gn:country_code":"ID",
    "gn:dem":12,
    "gn:feature_class":"P",
    "gn:feature_code":"PPL",
    "gn:name":"Dolatanden",
    "gn:population":0,
    "gn:timezone":"Asia/Jayapura",
    "iso:country":"ID",
    "wof:name":"Dolatanden",
    "wof:placetype":"locality"
},
  "geometry": {"coordinates":[138.06666999999999,-7.71667],"type":"Point"}
}