{
  "type": "Feature",
  "properties": {
    "gn:admin1_code":"7.0",
    "gn:asciiname":"Pentul Bawah",
    "gn:country_code":"ID",
    "gn:dem":352,
    "gn:feature_class":"P",
    "gn:feature_code":"PPL",
    "gn:name":"Pentul Bawah",
    "gn:population":0,
    "gn:timezone":"Asia/Jakarta",
    "iso:country":"ID",
    "name:ind_x_preferred":[
        "Pentul Bawah"
    ],
    "wof:lang_x_official":[
        "ind"
    ],
    "wof:lang_x_spoken":[
        "ind",
        "eng"
    ],
    "wof:name":"Pentul Bawah",
    "wof:placetype":"locality"
},
  "geometry": {"coordinates":[109.58360999999999,-7.29194],"type":"Point"}
}