{
  "type": "Feature",
  "properties": {
    "gn:admin1_code":"30",
    "gn:asciiname":"Cibongparang",
    "gn:cc2":"ID",
    "gn:country_code":"ID",
    "gn:dem":670,
    "gn:feature_class":"P",
    "gn:feature_code":"PPL",
    "gn:name":"Cibongparang",
    "gn:population":0,
    "gn:timezone":"Asia/Jakarta",
    "iso:country":"ID",
    "name:und_x_variant":[
        "Tjibongparang",
        "Cibongparang"
    ],
    "wof:name":"Cibongparang",
    "wof:placetype":"locality"
},
  "geometry": {"coordinates":[107.54306,-6.99833],"type":"Point"}
}