{
  "type": "Feature",
  "properties": {
    "gn:admin1_code":"30",
    "gn:asciiname":"Ciledug",
    "gn:cc2":"ID",
    "gn:country_code":"ID",
    "gn:dem":56,
    "gn:feature_class":"P",
    "gn:feature_code":"PPL",
    "gn:name":"Ciledug",
    "gn:population":0,
    "gn:timezone":"Asia/Jakarta",
    "iso:country":"ID",
    "name:und_x_variant":[
        "Cileduk-wetan",
        "Tjileduk-wetan",
        "Ciledug"
    ],
    "wof:name":"Ciledug",
    "wof:placetype":"locality"
},
  "geometry": {"coordinates":[106.72944,-6.3375],"type":"Point"}
}