{
  "type": "Feature",
  "properties": {
    "gn:admin1_code":"8",
    "gn:asciiname":"Sapulante Lor",
    "gn:country_code":"ID",
    "gn:dem":260,
    "gn:feature_class":"P",
    "gn:feature_code":"PPL",
    "gn:name":"Sapulante Lor",
    "gn:population":0,
    "gn:timezone":"Asia/Jakarta",
    "iso:country":"ID",
    "name:ind_x_preferred":[
        "Sapulante Lor"
    ],
    "wof:name":"Sapulante Lor",
    "wof:placetype":"locality"
},
  "geometry": {"coordinates":[112.82389999999999,-7.7809],"type":"Point"}
}