{
  "type": "Feature",
  "properties": {
    "gn:admin1_code":"7.0",
    "gn:asciiname":"Pakisan",
    "gn:country_code":"ID",
    "gn:dem":256,
    "gn:feature_class":"P",
    "gn:feature_code":"PPL",
    "gn:name":"Pakisan",
    "gn:population":0,
    "gn:timezone":"Asia/Jakarta",
    "iso:country":"ID",
    "wof:name":"Pakisan",
    "wof:placetype":"locality"
},
  "geometry": {"coordinates":[110.66278,-7.35972],"type":"Point"}
}