{
  "type": "Feature",
  "properties": {
    "gn:country":"ID",
    "gn:fcode":"PPL",
    "gn:pop":0,
    "iso:country":"ID",
    "name:ace_x_preferred":[
        "Mirit"
    ],
    "name:ceb_x_preferred":[
        "Desa Mirit"
    ],
    "name:deu_x_preferred":[
        "Mirit"
    ],
    "name:eng_x_preferred":[
        "Mirit"
    ],
    "name:eng_x_variant":[
        "Sukaresmi"
    ],
    "name:fra_x_preferred":[
        "Mirit"
    ],
    "name:gor_x_preferred":[
        "Mirit"
    ],
    "name:ind_x_preferred":[
        "Mirit"
    ],
    "name:jav_x_preferred":[
        "Mirit"
    ],
    "name:msa_x_preferred":[
        "Mirit"
    ],
    "name:nld_x_preferred":[
        "Mirit"
    ],
    "name:por_x_preferred":[
        "Mirit"
    ],
    "name:spa_x_preferred":[
        "Mirit"
    ],
    "name:swe_x_preferred":[
        "Desa Mirit"
    ],
    "qs:name":"Mirit",
    "qs:name_adm0":"Indonesia",
    "qs:name_adm1":"Provinsi Jawa Tengah",
    "qs:photos_9k":1,
    "qs:photos_9r":1,
    "qs:photos_all":1,
    "qs:photos_sr":0,
    "qs:placetype":"Town",
    "qs:pop_sr":"0",
    "wof:lang_x_official":[
        "ind"
    ],
    "wof:lang_x_spoken":[
        "ind",
        "eng"
    ],
    "wof:name":"Mirit",
    "wof:placetype":"locality",
    "wof:population":0
},
  "geometry": {"coordinates":[109.78417,-7.80194],"type":"Point"}
}