{
  "type": "Feature",
  "properties": {
    "gn:admin1_code":"36.0",
    "gn:asciiname":"Sawardori",
    "gn:country_code":"ID",
    "gn:dem":7,
    "gn:feature_class":"P",
    "gn:feature_code":"PPL",
    "gn:name":"Sawardori",
    "gn:population":0,
    "gn:timezone":"Asia/Jayapura",
    "iso:country":"ID",
    "name:ind_x_preferred":[
        "Sawardori"
    ],
    "name:und_x_variant":[
        "Wafordori"
    ],
    "wof:name":"Sawardori",
    "wof:placetype":"locality"
},
  "geometry": {"coordinates":[135.70400000000001,-0.71361],"type":"Point"}
}