{
  "type": "Feature",
  "properties": {
    "gn:admin1_code":"7",
    "gn:asciiname":"Gedebeg",
    "gn:country_code":"ID",
    "gn:dem":80,
    "gn:feature_class":"P",
    "gn:feature_code":"PPL",
    "gn:name":"Gedebeg",
    "gn:population":0,
    "gn:timezone":"Asia/Jakarta",
    "iso:country":"ID",
    "name:ind_x_preferred":[
        "Gedebeg"
    ],
    "wof:name":"Gedebeg",
    "wof:placetype":"locality"
},
  "geometry": {"coordinates":[111.2974,-7.0705],"type":"Point"}
}