{
  "type": "Feature",
  "properties": {
    "gn:admin1_code":"18.0",
    "gn:asciiname":"Oepuah",
    "gn:country_code":"ID",
    "gn:dem":747,
    "gn:feature_class":"P",
    "gn:feature_code":"PPL",
    "gn:name":"Oepuah",
    "gn:population":0,
    "gn:timezone":"Asia/Makassar",
    "iso:country":"ID",
    "name:ind_x_preferred":[
        "Oepuah"
    ],
    "wof:name":"Oepuah",
    "wof:placetype":"locality"
},
  "geometry": {"coordinates":[124.47645,-9.80783],"type":"Point"}
}