{
  "type": "Feature",
  "properties": {
    "gn:admin1_code":"34",
    "gn:asciiname":"Lingkungan Enam",
    "gn:country_code":"ID",
    "gn:dem":15,
    "gn:feature_class":"P",
    "gn:feature_code":"PPL",
    "gn:name":"Lingkungan Enam",
    "gn:population":0,
    "gn:timezone":"Asia/Makassar",
    "iso:country":"ID",
    "name:ind_x_preferred":[
        "Lingkungan Enam"
    ],
    "name:und_x_variant":[
        "Lingkungan 6"
    ],
    "wof:lang_x_official":[
        "ind"
    ],
    "wof:lang_x_spoken":[
        "ind",
        "eng"
    ],
    "wof:name":"Lingkungan Enam",
    "wof:placetype":"locality"
},
  "geometry": {"coordinates":[122.996,0.6218],"type":"Point"}
}