{
  "type": "Feature",
  "properties": {
    "gn:admin1_code":"2.0",
    "gn:asciiname":"Banjar Delodbaleagung",
    "gn:country_code":"ID",
    "gn:dem":12,
    "gn:feature_class":"P",
    "gn:feature_code":"PPL",
    "gn:name":"Banjar Delodbaleagung",
    "gn:population":0,
    "gn:timezone":"Asia/Makassar",
    "iso:country":"ID",
    "name:ind_x_preferred":[
        "Banjar Delodbaleagung"
    ],
    "wof:name":"Banjar Delodbaleagung",
    "wof:placetype":"locality"
},
  "geometry": {"coordinates":[114.6658,-8.3687],"type":"Point"}
}