{
  "type": "Feature",
  "properties": {
    "gn:admin1_code":"38",
    "gn:asciiname":"Padanglampe",
    "gn:country_code":"ID",
    "gn:dem":22,
    "gn:feature_class":"P",
    "gn:feature_code":"PPL",
    "gn:name":"Padanglampe",
    "gn:population":0,
    "gn:timezone":"Asia/Makassar",
    "iso:country":"ID",
    "name:ind_x_preferred":[
        "Padanglampe"
    ],
    "wof:name":"Padanglampe",
    "wof:placetype":"locality"
},
  "geometry": {"coordinates":[119.6177,-4.7152],"type":"Point"}
}