{
  "type": "Feature",
  "properties": {
    "gn:admin1_code":"14",
    "gn:asciiname":"Karangjoang Kilometer Lima Belas",
    "gn:country_code":"ID",
    "gn:dem":21,
    "gn:feature_class":"P",
    "gn:feature_code":"PPL",
    "gn:name":"Karangjoang Kilometer Lima Belas",
    "gn:population":0,
    "gn:timezone":"Asia/Makassar",
    "iso:country":"ID",
    "name:ind_x_preferred":[
        "Karangjoang Kilometer Lima Belas"
    ],
    "name:und_x_variant":[
        "Karangjoang Kilometer 15"
    ],
    "wof:lang_x_official":[
        "ind"
    ],
    "wof:lang_x_spoken":[
        "ind",
        "eng"
    ],
    "wof:name":"Karangjoang Kilometer Lima Belas",
    "wof:placetype":"locality"
},
  "geometry": {"coordinates":[116.88079999999999,-1.1377],"type":"Point"}
}