{
  "type": "Feature",
  "properties": {
    "gn:admin1_code":"30",
    "gn:asciiname":"Nusa",
    "gn:country_code":"ID",
    "gn:dem":663,
    "gn:feature_class":"P",
    "gn:feature_code":"PPL",
    "gn:name":"Nusa",
    "gn:population":0,
    "gn:timezone":"Asia/Jakarta",
    "iso:country":"ID",
    "name:ind_x_preferred":[
        "Nusa"
    ],
    "wof:name":"Nusa",
    "wof:placetype":"locality"
},
  "geometry": {"coordinates":[107.59972,-6.98778],"type":"Point"}
}