{
  "type": "Feature",
  "properties": {
    "gn:admin1_code":"38",
    "gn:asciiname":"Talumanuk",
    "gn:country_code":"ID",
    "gn:dem":830,
    "gn:feature_class":"P",
    "gn:feature_code":"PPL",
    "gn:name":"Talumanuk",
    "gn:population":0,
    "gn:timezone":"Asia/Makassar",
    "iso:country":"ID",
    "name:ind_x_preferred":[
        "Talumanuk"
    ],
    "wof:name":"Talumanuk",
    "wof:placetype":"locality"
},
  "geometry": {"coordinates":[119.77209999999999,-3.0835],"type":"Point"}
}