{
  "type": "Feature",
  "properties": {
    "gn:admin1_code":"7.0",
    "gn:asciiname":"Bunut",
    "gn:country_code":"ID",
    "gn:dem":108,
    "gn:feature_class":"P",
    "gn:feature_code":"PPL",
    "gn:name":"Bunut",
    "gn:population":0,
    "gn:timezone":"Asia/Jakarta",
    "iso:country":"ID",
    "name:ind_x_preferred":[
        "Bunut"
    ],
    "wof:name":"Bunut",
    "wof:placetype":"locality"
},
  "geometry": {"coordinates":[108.91861000000002,-7.3775],"type":"Point"}
}