{
  "type": "Feature",
  "properties": {
    "gn:admin1_code":"8",
    "gn:asciiname":"Gunungdangean",
    "gn:country_code":"ID",
    "gn:dem":261,
    "gn:feature_class":"P",
    "gn:feature_code":"PPL",
    "gn:name":"Gunungdangean",
    "gn:population":0,
    "gn:timezone":"Asia/Jakarta",
    "iso:country":"ID",
    "name:ind_x_preferred":[
        "Gunungdangean"
    ],
    "wof:name":"Gunungdangean",
    "wof:placetype":"locality"
},
  "geometry": {"coordinates":[111.5484,-7.8167],"type":"Point"}
}