{
  "type": "Feature",
  "properties": {
    "gn:admin1_code":"30",
    "gn:asciiname":"Peguyuban",
    "gn:country_code":"ID",
    "gn:dem":4,
    "gn:feature_class":"P",
    "gn:feature_code":"PPL",
    "gn:name":"Peguyuban",
    "gn:population":0,
    "gn:timezone":"Asia/Jakarta",
    "iso:country":"ID",
    "name:ind_x_preferred":[
        "Peguyuban"
    ],
    "wof:name":"Peguyuban",
    "wof:placetype":"locality"
},
  "geometry": {"coordinates":[108.5779,-6.7306],"type":"Point"}
}