{
  "type": "Feature",
  "properties": {
    "gn:admin1_code":"30.0",
    "gn:asciiname":"Haurseah",
    "gn:country_code":"ID",
    "gn:dem":696,
    "gn:feature_class":"P",
    "gn:feature_code":"PPL",
    "gn:name":"Haurseah",
    "gn:population":0,
    "gn:timezone":"Asia/Jakarta",
    "iso:country":"ID",
    "name:ind_x_preferred":[
        "Haurseah"
    ],
    "name:und_x_variant":[
        "Haoerseah"
    ],
    "wof:name":"Haurseah",
    "wof:placetype":"locality"
},
  "geometry": {"coordinates":[107.95869999999999,-7.1703],"type":"Point"}
}