{
  "type": "Feature",
  "properties": {
    "gn:admin1_code":"18.0",
    "gn:asciiname":"Teni",
    "gn:country_code":"ID",
    "gn:dem":605,
    "gn:feature_class":"P",
    "gn:feature_code":"PPL",
    "gn:name":"Teni",
    "gn:population":0,
    "gn:timezone":"Asia/Makassar",
    "iso:country":"ID",
    "name:ceb_x_preferred":[
        "Teni"
    ],
    "name:ind_x_preferred":[
        "Teni"
    ],
    "name:swe_x_preferred":[
        "Teni"
    ],
    "wof:name":"Teni",
    "wof:placetype":"locality"
},
  "geometry": {"coordinates":[120.90000000000001,-8.7943],"type":"Point"}
}