{
  "type": "Feature",
  "properties": {
    "gn:admin1_code":"30",
    "gn:asciiname":"Leuwinanggung",
    "gn:country_code":"ID",
    "gn:dem":481,
    "gn:feature_class":"P",
    "gn:feature_code":"PPL",
    "gn:name":"Leuwinanggung",
    "gn:population":0,
    "gn:timezone":"Asia/Jakarta",
    "iso:country":"ID",
    "name:ind_x_preferred":[
        "Leuwinanggung"
    ],
    "wof:name":"Leuwinanggung",
    "wof:placetype":"locality"
},
  "geometry": {"coordinates":[106.77306000000002,-6.80611],"type":"Point"}
}