{
  "type": "Feature",
  "properties": {
    "gn:admin1_code":"30",
    "gn:asciiname":"Bumisatriaraharja",
    "gn:country_code":"ID",
    "gn:dem":865,
    "gn:feature_class":"P",
    "gn:feature_code":"PPL",
    "gn:name":"Bumisatriaraharja",
    "gn:population":0,
    "gn:timezone":"Asia/Jakarta",
    "iso:country":"ID",
    "name:ind_x_preferred":[
        "Bumisatriaraharja"
    ],
    "wof:name":"Bumisatriaraharja",
    "wof:placetype":"locality"
},
  "geometry": {"coordinates":[107.81861000000001,-6.92444],"type":"Point"}
}