{
  "type": "Feature",
  "properties": {
    "gn:admin1_code":"7",
    "gn:asciiname":"Dukuhwaru",
    "gn:country_code":"ID",
    "gn:dem":31,
    "gn:feature_class":"P",
    "gn:feature_code":"PPL",
    "gn:name":"Dukuhwaru",
    "gn:population":0,
    "gn:timezone":"Asia/Jakarta",
    "iso:country":"ID",
    "name:ind_x_preferred":[
        "Dukuhwaru"
    ],
    "wof:name":"Dukuhwaru",
    "wof:placetype":"locality"
},
  "geometry": {"coordinates":[109.099,-6.9696],"type":"Point"}
}