{
  "type": "Feature",
  "properties": {
    "gn:admin1_code":"0.0",
    "gn:asciiname":"Lembobenua",
    "gn:cc2":"ID",
    "gn:country_code":"ID",
    "gn:dem":741,
    "gn:feature_class":"P",
    "gn:feature_code":"PPL",
    "gn:name":"Lembobenua",
    "gn:population":0,
    "gn:timezone":"Asia/Makassar",
    "iso:country":"ID",
    "name:und_x_variant":[
        "Lembobenoea",
        "Lembobenua"
    ],
    "wof:lang_x_official":[
        "ind"
    ],
    "wof:lang_x_spoken":[
        "ind",
        "eng"
    ],
    "wof:name":"Lembobenua",
    "wof:placetype":"locality"
},
  "geometry": {"coordinates":[120.96666999999999,-2.13333],"type":"Point"}
}