{
  "type": "Feature",
  "properties": {
    "gn:admin1_code":"1",
    "gn:asciiname":"Alue Geudong",
    "gn:country_code":"ID",
    "gn:dem":6,
    "gn:feature_class":"P",
    "gn:feature_code":"PPL",
    "gn:name":"Alue Geudong",
    "gn:population":0,
    "gn:timezone":"Asia/Jakarta",
    "iso:country":"ID",
    "name:ind_x_preferred":[
        "Alue Geudong"
    ],
    "wof:name":"Alue Geudong",
    "wof:placetype":"locality"
},
  "geometry": {"coordinates":[97.4027,5.1686],"type":"Point"}
}