{
  "type": "Feature",
  "properties": {
    "gn:admin1_code":"30.0",
    "gn:asciiname":"Sawahmanjah",
    "gn:country_code":"ID",
    "gn:dem":1009,
    "gn:feature_class":"P",
    "gn:feature_code":"PPL",
    "gn:name":"Sawahmanjah",
    "gn:population":0,
    "gn:timezone":"Asia/Jakarta",
    "iso:country":"ID",
    "name:ind_x_preferred":[
        "Sawahmanjah"
    ],
    "wof:name":"Sawahmanjah",
    "wof:placetype":"locality"
},
  "geometry": {"coordinates":[107.53060000000001,-7.3476],"type":"Point"}
}