{
  "type": "Feature",
  "properties": {
    "gn:admin1_code":"11.0",
    "gn:asciiname":"Jahumerah",
    "gn:country_code":"ID",
    "gn:dem":46,
    "gn:feature_class":"P",
    "gn:feature_code":"PPL",
    "gn:name":"Jahumerah",
    "gn:population":0,
    "gn:timezone":"Asia/Pontianak",
    "iso:country":"ID",
    "name:und_x_variant":[
        "Djahoemerah",
        "Djahumerah",
        "Jahumerah"
    ],
    "wof:name":"Jahumerah",
    "wof:placetype":"locality"
},
  "geometry": {"coordinates":[111.86667,0.36667],"type":"Point"}
}