{
  "type": "Feature",
  "properties": {
    "gn:admin1_code":"0.0",
    "gn:asciiname":"Sanoto-kecil",
    "gn:cc2":"ID",
    "gn:country_code":"ID",
    "gn:dem":24,
    "gn:feature_class":"P",
    "gn:feature_code":"PPL",
    "gn:name":"Sanoto-kecil",
    "gn:population":0,
    "gn:timezone":"Asia/Jayapura",
    "iso:country":"ID",
    "name:und_x_variant":[
        "Little Sanoto",
        "Sanoto-ketjil",
        "Sanoto-kecil"
    ],
    "wof:name":"Sanoto-kecil",
    "wof:placetype":"locality"
},
  "geometry": {"coordinates":[127.36667,0.76667],"type":"Point"}
}