{
  "type": "Feature",
  "properties": {
    "gn:admin1_code":"15.0",
    "gn:asciiname":"Sukaraja",
    "gn:country_code":"ID",
    "gn:dem":833,
    "gn:feature_class":"P",
    "gn:feature_code":"PPL",
    "gn:name":"Sukaraja",
    "gn:population":0,
    "gn:timezone":"Asia/Jakarta",
    "iso:country":"ID",
    "name:ind_x_preferred":[
        "Sukaraja"
    ],
    "wof:name":"Sukaraja",
    "wof:placetype":"locality"
},
  "geometry": {"coordinates":[104.14896,-4.99841],"type":"Point"}
}