{
  "type": "Feature",
  "properties": {
    "gn:admin1_code":"31",
    "gn:asciiname":"Dominanga Dusun Satu",
    "gn:country_code":"ID",
    "gn:dem":58,
    "gn:feature_class":"P",
    "gn:feature_code":"PPL",
    "gn:name":"Dominanga Dusun Satu",
    "gn:population":0,
    "gn:timezone":"Asia/Makassar",
    "iso:country":"ID",
    "name:ind_x_preferred":[
        "Dominanga Dusun Satu"
    ],
    "name:und_x_variant":[
        "Dominanga Dusun 1"
    ],
    "wof:lang_x_official":[
        "ind"
    ],
    "wof:lang_x_spoken":[
        "ind",
        "eng"
    ],
    "wof:name":"Dominanga Dusun Satu",
    "wof:placetype":"locality"
},
  "geometry": {"coordinates":[123.81740000000001,0.3418],"type":"Point"}
}