{
  "type": "Feature",
  "properties": {
    "gn:admin1_code":"8.0",
    "gn:asciiname":"Pelikan",
    "gn:country_code":"ID",
    "gn:dem":213,
    "gn:feature_class":"P",
    "gn:feature_code":"PPL",
    "gn:name":"Pelikan",
    "gn:population":0,
    "gn:timezone":"Asia/Jakarta",
    "iso:country":"ID",
    "name:azb_x_preferred":[
        "\u067e\u0644\u06cc\u06a9\u0627\u0646"
    ],
    "name:ces_x_preferred":[
        "Pelikan"
    ],
    "name:deu_x_preferred":[
        "Pelikan Holding"
    ],
    "name:fas_x_preferred":[
        "\u067e\u0644\u06cc\u06a9\u0627\u0646"
    ],
    "name:fra_x_preferred":[
        "Pelikan"
    ],
    "name:ind_x_preferred":[
        "Pelikan"
    ],
    "name:ita_x_preferred":[
        "Pelikan"
    ],
    "name:jpn_x_preferred":[
        "\u30da\u30ea\u30ab\u30f3"
    ],
    "name:nld_x_preferred":[
        "Pelikan"
    ],
    "name:pol_x_preferred":[
        "Pelikan Holding"
    ],
    "name:por_x_preferred":[
        "Pelikan Holding"
    ],
    "name:spa_x_preferred":[
        "Pelikan"
    ],
    "name:swe_x_preferred":[
        "Pelikan"
    ],
    "name:tur_x_preferred":[
        "Pelikan"
    ],
    "name:zho_x_preferred":[
        "\u767e\u5229\u91d1"
    ],
    "wof:lang_x_official":[
        "ind"
    ],
    "wof:lang_x_spoken":[
        "ind",
        "eng"
    ],
    "wof:name":"Pelikan",
    "wof:placetype":"locality"
},
  "geometry": {"coordinates":[111.6811,-8.206],"type":"Point"}
}