{
  "type": "Feature",
  "properties": {
    "gn:admin1_code":"8.0",
    "gn:asciiname":"Pelikan",
    "gn:country_code":"ID",
    "gn:dem":213,
    "gn:feature_class":"P",
    "gn:feature_code":"PPL",
    "gn:name":"Pelikan",
    "gn:population":0,
    "gn:timezone":"Asia/Jakarta",
    "iso:country":"ID",
    "name:ind_x_preferred":[
        "Pelikan"
    ],
    "wof:name":"Pelikan",
    "wof:placetype":"locality"
},
  "geometry": {"coordinates":[111.6811,-8.206],"type":"Point"}
}