{
  "type": "Feature",
  "properties": {
    "gn:admin1_code":"38",
    "gn:asciiname":"Tarutuk",
    "gn:country_code":"ID",
    "gn:dem":475,
    "gn:feature_class":"P",
    "gn:feature_code":"PPL",
    "gn:name":"Tarutuk",
    "gn:population":0,
    "gn:timezone":"Asia/Makassar",
    "iso:country":"ID",
    "name:ind_x_preferred":[
        "Tarutuk"
    ],
    "wof:name":"Tarutuk",
    "wof:placetype":"locality"
},
  "geometry": {"coordinates":[119.8489,-4.8324],"type":"Point"}
}