{
  "type": "Feature",
  "properties": {
    "gn:admin1_code":"32.0",
    "gn:asciiname":"Sukaraja",
    "gn:country_code":"ID",
    "gn:dem":824,
    "gn:feature_class":"P",
    "gn:feature_code":"PPL",
    "gn:name":"Sukaraja",
    "gn:population":0,
    "gn:timezone":"Asia/Jakarta",
    "iso:country":"ID",
    "name:ind_x_preferred":[
        "Sukaraja"
    ],
    "wof:name":"Sukaraja",
    "wof:placetype":"locality"
},
  "geometry": {"coordinates":[103.02119999999999,-4.1047],"type":"Point"}
}