{
  "type": "Feature",
  "properties": {
    "gn:admin1_code":"18.0",
    "gn:asciiname":"Larimehia",
    "gn:country_code":"ID",
    "gn:dem":173,
    "gn:feature_class":"P",
    "gn:feature_code":"PPL",
    "gn:name":"Larimehia",
    "gn:population":0,
    "gn:timezone":"Asia/Makassar",
    "iso:country":"ID",
    "name:ind_x_preferred":[
        "Larimehia"
    ],
    "wof:name":"Larimehia",
    "wof:placetype":"locality"
},
  "geometry": {"coordinates":[121.8922,-10.5393],"type":"Point"}
}