{
  "type": "Feature",
  "properties": {
    "gn:admin1_code":"33.0",
    "gn:asciiname":"Cilentung",
    "gn:country_code":"ID",
    "gn:dem":474,
    "gn:feature_class":"P",
    "gn:feature_code":"PPLA4",
    "gn:name":"Cilentung",
    "gn:population":0,
    "gn:timezone":"Asia/Jakarta",
    "iso:country":"ID",
    "name:ind_x_preferred":[
        "Cilentung"
    ],
    "name:und_x_variant":[
        "Tjilontung",
        "Cilontung"
    ],
    "wof:lang_x_official":[
        "ind"
    ],
    "wof:lang_x_spoken":[
        "ind",
        "eng"
    ],
    "wof:name":"Cilentung",
    "wof:placetype":"locality"
},
  "geometry": {"coordinates":[105.9563,-6.3274],"type":"Point"}
}