{
  "type": "Feature",
  "properties": {
    "gn:admin1_code":"0.0",
    "gn:asciiname":"Kedungdalem",
    "gn:cc2":"ID",
    "gn:country_code":"ID",
    "gn:dem":13,
    "gn:feature_class":"P",
    "gn:feature_code":"PPL",
    "gn:name":"Kedungdalem",
    "gn:population":0,
    "gn:timezone":"Asia/Jakarta",
    "iso:country":"ID",
    "name:und_x_variant":[
        "Kedoengdalem",
        "Kedoengbadjoel",
        "Kedungbadjung",
        "Kedoenghadjoel",
        "Kedungdalem"
    ],
    "wof:lang_x_official":[
        "ind"
    ],
    "wof:lang_x_spoken":[
        "ind",
        "eng"
    ],
    "wof:name":"Kedungdalem",
    "wof:placetype":"locality"
},
  "geometry": {"coordinates":[113.25,-7.76667],"type":"Point"}
}