{
  "type": "Feature",
  "properties": {
    "gn:admin1_code":"7",
    "gn:asciiname":"Gondosuli Kidul",
    "gn:country_code":"ID",
    "gn:dem":1599,
    "gn:feature_class":"P",
    "gn:feature_code":"PPL",
    "gn:name":"Gondosuli Kidul",
    "gn:population":0,
    "gn:timezone":"Asia/Jakarta",
    "iso:country":"ID",
    "name:ind_x_preferred":[
        "Gondosuli Kidul"
    ],
    "wof:name":"Gondosuli Kidul",
    "wof:placetype":"locality"
},
  "geometry": {"coordinates":[111.16833,-7.66889],"type":"Point"}
}