{
  "type": "Feature",
  "properties": {
    "gn:admin1_code":"7.0",
    "gn:asciiname":"Waruombo",
    "gn:country_code":"ID",
    "gn:dem":20,
    "gn:feature_class":"P",
    "gn:feature_code":"PPL",
    "gn:name":"Waruombo",
    "gn:population":0,
    "gn:timezone":"Asia/Jakarta",
    "iso:country":"ID",
    "name:ind_x_preferred":[
        "Waruombo"
    ],
    "wof:name":"Waruombo",
    "wof:placetype":"locality"
},
  "geometry": {"coordinates":[109.66667,-7.71333],"type":"Point"}
}