{
  "type": "Feature",
  "properties": {
    "gn:admin1_code":"38",
    "gn:asciiname":"Ulusalo",
    "gn:country_code":"ID",
    "gn:dem":26,
    "gn:feature_class":"P",
    "gn:feature_code":"PPL",
    "gn:name":"Ulusalo",
    "gn:population":0,
    "gn:timezone":"Asia/Makassar",
    "iso:country":"ID",
    "name:ind_x_preferred":[
        "Ulusalo"
    ],
    "wof:name":"Ulusalo",
    "wof:placetype":"locality"
},
  "geometry": {"coordinates":[120.2529,-5.1182],"type":"Point"}
}