{
  "type": "Feature",
  "properties": {
    "gn:admin1_code":"30.0",
    "gn:asciiname":"Parungkadu",
    "gn:country_code":"ID",
    "gn:dem":274,
    "gn:feature_class":"P",
    "gn:feature_code":"PPL",
    "gn:name":"Parungkadu",
    "gn:population":0,
    "gn:timezone":"Asia/Jakarta",
    "iso:country":"ID",
    "name:ind_x_preferred":[
        "Parungkadu"
    ],
    "wof:name":"Parungkadu",
    "wof:placetype":"locality"
},
  "geometry": {"coordinates":[106.83159999999999,-7.2793],"type":"Point"}
}