{
  "type": "Feature",
  "properties": {
    "gn:admin1_code":"8.0",
    "gn:asciiname":"Barat",
    "gn:country_code":"ID",
    "gn:dem":33,
    "gn:feature_class":"P",
    "gn:feature_code":"PPL",
    "gn:name":"Barat",
    "gn:population":0,
    "gn:timezone":"Asia/Jakarta",
    "iso:country":"ID",
    "name:bos_x_preferred":[
        "Barat"
    ],
    "name:ceb_x_preferred":[
        "Barat"
    ],
    "name:deu_x_preferred":[
        "Barat"
    ],
    "name:fra_x_preferred":[
        "Barat"
    ],
    "name:hrv_x_preferred":[
        "Barat"
    ],
    "name:hun_x_preferred":[
        "Barat"
    ],
    "name:ind_x_preferred":[
        "Barat"
    ],
    "name:nld_x_preferred":[
        "Barat"
    ],
    "name:slv_x_preferred":[
        "Barat"
    ],
    "name:srp_x_preferred":[
        "\u0411\u0430\u0440\u0430\u0442"
    ],
    "name:swe_x_preferred":[
        "Barat"
    ],
    "wof:name":"Barat",
    "wof:placetype":"locality"
},
  "geometry": {"coordinates":[113.44119999999999,-7.1327],"type":"Point"}
}