{
  "type": "Feature",
  "properties": {
    "gn:admin1_code":"26",
    "gn:asciiname":"Langau",
    "gn:country_code":"ID",
    "gn:dem":9,
    "gn:feature_class":"P",
    "gn:feature_code":"PPL",
    "gn:name":"Langau",
    "gn:population":0,
    "gn:timezone":"Asia/Jakarta",
    "iso:country":"ID",
    "name:ceb_x_preferred":[
        "Langau"
    ],
    "name:ces_x_preferred":[
        "Langau"
    ],
    "name:deu_x_preferred":[
        "Langau"
    ],
    "name:epo_x_preferred":[
        "Langau"
    ],
    "name:fas_x_preferred":[
        "\u0644\u0627\u0646\u06af\u0648"
    ],
    "name:fra_x_preferred":[
        "Langau"
    ],
    "name:hun_x_preferred":[
        "Langau"
    ],
    "name:ind_x_preferred":[
        "Langau"
    ],
    "name:ita_x_preferred":[
        "Langau"
    ],
    "name:kaz_x_preferred":[
        "\u0425\u0435\u0441\u0441\u0435\u043d\u0434\u043e\u0440\u0444"
    ],
    "name:nld_x_preferred":[
        "Langau"
    ],
    "name:pol_x_preferred":[
        "Langau"
    ],
    "name:por_x_preferred":[
        "Langau"
    ],
    "name:rus_x_preferred":[
        "\u041b\u0430\u043d\u0433\u0430\u0443"
    ],
    "name:slk_x_preferred":[
        "Langau"
    ],
    "name:spa_x_preferred":[
        "Langau"
    ],
    "name:swe_x_preferred":[
        "Langau"
    ],
    "name:uzb_x_preferred":[
        "Langau"
    ],
    "name:vie_x_preferred":[
        "Langau"
    ],
    "name:vol_x_preferred":[
        "Langau"
    ],
    "name:war_x_preferred":[
        "Langau"
    ],
    "wof:lang_x_official":[
        "ind"
    ],
    "wof:lang_x_spoken":[
        "ind",
        "eng"
    ],
    "wof:name":"Langau",
    "wof:placetype":"locality"
},
  "geometry": {"coordinates":[99.2384,3.3975],"type":"Point"}
}