{
  "type": "Feature",
  "properties": {
    "gn:admin1_code":"32.0",
    "gn:asciiname":"Gunungraya",
    "gn:country_code":"ID",
    "gn:dem":26,
    "gn:feature_class":"P",
    "gn:feature_code":"PPL",
    "gn:name":"Gunungraya",
    "gn:population":0,
    "gn:timezone":"Asia/Jakarta",
    "iso:country":"ID",
    "name:ind_x_preferred":[
        "Gunungraya"
    ],
    "name:ind_x_variant":[
        "Gunungraja"
    ],
    "wof:name":"Gunungraya",
    "wof:placetype":"locality"
},
  "geometry": {"coordinates":[104.40119,-3.61672],"type":"Point"}
}