{
  "type": "Feature",
  "properties": {
    "gn:admin1_code":"7",
    "gn:asciiname":"Gunungsari",
    "gn:country_code":"ID",
    "gn:dem":80,
    "gn:feature_class":"P",
    "gn:feature_code":"PPL",
    "gn:name":"Gunungsari",
    "gn:population":0,
    "gn:timezone":"Asia/Jakarta",
    "iso:country":"ID",
    "name:ind_x_preferred":[
        "Gunungsari"
    ],
    "wof:name":"Gunungsari",
    "wof:placetype":"locality"
},
  "geometry": {"coordinates":[111.00333000000001,-7.36167],"type":"Point"}
}