{
  "type": "Feature",
  "properties": {
    "gn:admin1_code":"10",
    "gn:asciiname":"Sampangan",
    "gn:country_code":"ID",
    "gn:dem":69,
    "gn:feature_class":"P",
    "gn:feature_code":"PPL",
    "gn:name":"Sampangan",
    "gn:population":0,
    "gn:timezone":"Asia/Jakarta",
    "iso:country":"ID",
    "name:ind_x_preferred":[
        "Sampangan"
    ],
    "name:jav_x_preferred":[
        "Sampangan"
    ],
    "name:nld_x_preferred":[
        "Sampangan"
    ],
    "wof:lang_x_official":[
        "ind"
    ],
    "wof:lang_x_spoken":[
        "ind",
        "eng"
    ],
    "wof:name":"Sampangan",
    "wof:placetype":"locality"
},
  "geometry": {"coordinates":[110.39749999999999,-7.85444],"type":"Point"}
}