{
  "type": "Feature",
  "properties": {
    "gn:admin1_code":"7",
    "gn:asciiname":"Bojolangu",
    "gn:country_code":"ID",
    "gn:dem":76,
    "gn:feature_class":"P",
    "gn:feature_code":"PPL",
    "gn:name":"Bojolangu",
    "gn:population":0,
    "gn:timezone":"Asia/Jakarta",
    "iso:country":"ID",
    "name:ind_x_preferred":[
        "Bojolangu"
    ],
    "wof:name":"Bojolangu",
    "wof:placetype":"locality"
},
  "geometry": {"coordinates":[110.89472000000001,-7.21111],"type":"Point"}
}