{
  "type": "Feature",
  "properties": {
    "gn:admin1_code":"2",
    "gn:asciiname":"Banjar Samageria",
    "gn:country_code":"ID",
    "gn:dem":560,
    "gn:feature_class":"P",
    "gn:feature_code":"PPL",
    "gn:name":"Banjar Samageria",
    "gn:population":0,
    "gn:timezone":"Asia/Makassar",
    "iso:country":"ID",
    "name:ind_x_preferred":[
        "Banjar Samageria"
    ],
    "wof:name":"Banjar Samageria",
    "wof:placetype":"locality"
},
  "geometry": {"coordinates":[115.3777,-8.4264],"type":"Point"}
}