{
  "type": "Feature",
  "properties": {
    "gn:admin1_code":"26.0",
    "gn:asciiname":"Sungaipelantjang",
    "gn:country_code":"ID",
    "gn:dem":4,
    "gn:feature_class":"P",
    "gn:feature_code":"PPL",
    "gn:name":"Sungaipelantjang",
    "gn:population":0,
    "gn:timezone":"Asia/Jakarta",
    "iso:country":"ID",
    "name:ind_x_preferred":[
        "Sungaipelantjang"
    ],
    "wof:name":"Sungaipelantjang",
    "wof:placetype":"locality"
},
  "geometry": {"coordinates":[100.22372,2.36715],"type":"Point"}
}