{
  "type": "Feature",
  "properties": {
    "gn:admin1_code":"17",
    "gn:asciiname":"Batman",
    "gn:country_code":"ID",
    "gn:dem":209,
    "gn:feature_class":"P",
    "gn:feature_code":"PPL",
    "gn:name":"Batman",
    "gn:population":0,
    "gn:timezone":"Asia/Makassar",
    "iso:country":"ID",
    "name:ind_x_preferred":[
        "Batman"
    ],
    "wof:name":"Batman",
    "wof:placetype":"locality"
},
  "geometry": {"coordinates":[116.59699999999999,-8.5345],"type":"Point"}
}