{
  "type": "Feature",
  "properties": {
    "gn:admin1_code":"22.0",
    "gn:asciiname":"Asambaki",
    "gn:country_code":"ID",
    "gn:dem":17,
    "gn:feature_class":"P",
    "gn:feature_code":"PPL",
    "gn:name":"Asambaki",
    "gn:population":0,
    "gn:timezone":"Asia/Makassar",
    "iso:country":"ID",
    "name:ind_x_preferred":[
        "Asambaki"
    ],
    "wof:name":"Asambaki",
    "wof:placetype":"locality"
},
  "geometry": {"coordinates":[122.5389,-4.0122],"type":"Point"}
}