{
  "type": "Feature",
  "properties": {
    "gn:admin1_code":"8",
    "gn:asciiname":"Kalongan",
    "gn:country_code":"ID",
    "gn:dem":13,
    "gn:feature_class":"P",
    "gn:feature_code":"PPL",
    "gn:name":"Kalongan",
    "gn:population":0,
    "gn:timezone":"Asia/Jakarta",
    "iso:country":"ID",
    "name:ind_x_preferred":[
        "Kalongan"
    ],
    "wof:name":"Kalongan",
    "wof:placetype":"locality"
},
  "geometry": {"coordinates":[112.16240000000001,-7.111],"type":"Point"}
}