{
  "type": "Feature",
  "properties": {
    "gn:country":"ID",
    "gn:fcode":"ADM3",
    "gn:pop":0,
    "iso:country":"ID",
    "name:ind_x_preferred":[
        "Kecamatan Singaparna"
    ],
    "name:unk_x_variant":[
        "Singaparna"
    ],
    "qs:name":"Kecamatan Singaparna",
    "qs:photos_9r":0,
    "qs:photos_sr":0,
    "qs:pop_sr":"0",
    "wd:wordcount":1319,
    "wof:name":"Kecamatan Singaparna",
    "wof:placetype":"localadmin",
    "wof:population":0
},
  "geometry": {"coordinates":[108.1172,-7.3681],"type":"Point"}
}