{
  "type": "Feature",
  "properties": {
    "gn:admin1_code":"08",
    "gn:asciiname":"Bargan",
    "gn:country_code":"ID",
    "gn:dem":11,
    "gn:feature_class":"P",
    "gn:feature_code":"PPL",
    "gn:name":"Bargan",
    "gn:population":0,
    "gn:timezone":"Asia/Jakarta",
    "iso:country":"ID",
    "name:ara_x_preferred":[
        "\u0628\u0627\u0631\u063a\u0627\u0646"
    ],
    "name:fas_x_preferred":[
        "\u0628\u0627\u0631\u06af\u0627\u0646"
    ],
    "name:ind_x_preferred":[
        "Bargan"
    ],
    "name:msa_x_preferred":[
        "Bargan"
    ],
    "wof:name":"Bargan",
    "wof:placetype":"locality"
},
  "geometry": {"coordinates":[112.7041,-7.0901],"type":"Point"}
}