{
  "type": "Feature",
  "properties": {
    "gn:admin1_code":"33",
    "gn:asciiname":"Kampungpos",
    "gn:country_code":"ID",
    "gn:dem":17,
    "gn:feature_class":"P",
    "gn:feature_code":"PPL",
    "gn:name":"Kampungpos",
    "gn:population":0,
    "gn:timezone":"Asia/Jakarta",
    "iso:country":"ID",
    "name:ind_x_preferred":[
        "Kampungpos"
    ],
    "wof:name":"Kampungpos",
    "wof:placetype":"locality"
},
  "geometry": {"coordinates":[106.1217,-6.0654],"type":"Point"}
}