{
  "type": "Feature",
  "properties": {
    "gn:admin1_code":"8.0",
    "gn:asciiname":"Tlampean",
    "gn:country_code":"ID",
    "gn:dem":46,
    "gn:feature_class":"P",
    "gn:feature_code":"PPL",
    "gn:name":"Tlampean",
    "gn:population":0,
    "gn:timezone":"Asia/Jakarta",
    "iso:country":"ID",
    "name:ind_x_preferred":[
        "Tlampean"
    ],
    "wof:name":"Tlampean",
    "wof:placetype":"locality"
},
  "geometry": {"coordinates":[113.62349,-8.29865],"type":"Point"}
}