{
  "type": "Feature",
  "properties": {
    "gn:admin1_code":"30.0",
    "gn:asciiname":"Sukajaya",
    "gn:country_code":"ID",
    "gn:dem":371,
    "gn:feature_class":"P",
    "gn:feature_code":"PPL",
    "gn:name":"Sukajaya",
    "gn:population":0,
    "gn:timezone":"Asia/Jakarta",
    "iso:country":"ID",
    "name:ind_x_preferred":[
        "Sukajaya"
    ],
    "wof:name":"Sukajaya",
    "wof:placetype":"locality"
},
  "geometry": {"coordinates":[108.2302,-7.4109],"type":"Point"}
}