{
  "type": "Feature",
  "properties": {
    "gn:admin1_code":"17.0",
    "gn:asciiname":"Kondang Barat",
    "gn:country_code":"ID",
    "gn:dem":253,
    "gn:feature_class":"P",
    "gn:feature_code":"PPL",
    "gn:name":"Kondang Barat",
    "gn:population":0,
    "gn:timezone":"Asia/Makassar",
    "iso:country":"ID",
    "name:ind_x_preferred":[
        "Kondang Barat"
    ],
    "wof:name":"Kondang Barat",
    "wof:placetype":"locality"
},
  "geometry": {"coordinates":[116.0954,-8.7788],"type":"Point"}
}