{
  "type": "Feature",
  "properties": {
    "gn:admin1_code":"7.0",
    "gn:asciiname":"Linggarsari",
    "gn:country_code":"ID",
    "gn:dem":270,
    "gn:feature_class":"P",
    "gn:feature_code":"PPL",
    "gn:name":"Linggarsari",
    "gn:population":0,
    "gn:timezone":"Asia/Jakarta",
    "iso:country":"ID",
    "name:ind_x_preferred":[
        "Linggarsari"
    ],
    "wof:name":"Linggarsari",
    "wof:placetype":"locality"
},
  "geometry": {"coordinates":[109.42833,-7.73278],"type":"Point"}
}