{
  "type": "Feature",
  "properties": {
    "gn:admin1_code":"18.0",
    "gn:asciiname":"Oenasi",
    "gn:country_code":"ID",
    "gn:dem":802,
    "gn:feature_class":"P",
    "gn:feature_code":"PPL",
    "gn:name":"Oenasi",
    "gn:population":0,
    "gn:timezone":"Asia/Makassar",
    "iso:country":"ID",
    "name:ind_x_preferred":[
        "Oenasi"
    ],
    "wof:name":"Oenasi",
    "wof:placetype":"locality"
},
  "geometry": {"coordinates":[124.2886,-9.8529],"type":"Point"}
}