{
  "type": "Feature",
  "properties": {
    "gn:admin1_code":"1.0",
    "gn:asciiname":"Kutapanjang",
    "gn:country_code":"ID",
    "gn:dem":1308,
    "gn:feature_class":"P",
    "gn:feature_code":"PPLA3",
    "gn:name":"Kutapanjang",
    "gn:population":0,
    "gn:timezone":"Asia/Jakarta",
    "iso:country":"ID",
    "name:ind_x_preferred":[
        "Kutapanjang"
    ],
    "wof:lang_x_official":[
        "ind"
    ],
    "wof:lang_x_spoken":[
        "ind",
        "eng"
    ],
    "wof:name":"Kutapanjang",
    "wof:placetype":"locality"
},
  "geometry": {"coordinates":[97.2371,4.03753],"type":"Point"}
}