{
  "type": "Feature",
  "properties": {
    "gn:admin1_code":"10.0",
    "gn:asciiname":"Kowang",
    "gn:country_code":"ID",
    "gn:dem":205,
    "gn:feature_class":"P",
    "gn:feature_code":"PPL",
    "gn:name":"Kowang",
    "gn:population":0,
    "gn:timezone":"Asia/Jakarta",
    "iso:country":"ID",
    "name:ceb_x_preferred":[
        "Kowang"
    ],
    "name:deu_x_preferred":[
        "Kowang"
    ],
    "name:dty_x_preferred":[
        "\u0915\u094b\u092c\u093e\u0919"
    ],
    "name:msa_x_preferred":[
        "Kowang"
    ],
    "name:nep_x_preferred":[
        "\u0915\u094b\u092c\u093e\u0919"
    ],
    "name:new_x_preferred":[
        "\u0915\u094b\u0935\u093e\u0919"
    ],
    "name:pol_x_preferred":[
        "Kowang"
    ],
    "name:por_x_preferred":[
        "Kowang"
    ],
    "wof:lang_x_official":[
        "ind"
    ],
    "wof:lang_x_spoken":[
        "ind",
        "eng"
    ],
    "wof:name":"Kowang",
    "wof:placetype":"locality"
},
  "geometry": {"coordinates":[110.46639,-7.72722],"type":"Point"}
}