{
  "type": "Feature",
  "properties": {
    "gn:admin1_code":"7",
    "gn:asciiname":"Karangawenkrajan",
    "gn:country_code":"ID",
    "gn:dem":17,
    "gn:feature_class":"P",
    "gn:feature_code":"PPL",
    "gn:name":"Karangawenkrajan",
    "gn:population":0,
    "gn:timezone":"Asia/Jakarta",
    "iso:country":"ID",
    "name:ind_x_preferred":[
        "Karangawenkrajan"
    ],
    "wof:name":"Karangawenkrajan",
    "wof:placetype":"locality"
},
  "geometry": {"coordinates":[110.57040000000001,-7.0414],"type":"Point"}
}