{
  "type": "Feature",
  "properties": {
    "gn:admin1_code":"17",
    "gn:asciiname":"Karya",
    "gn:country_code":"ID",
    "gn:dem":76,
    "gn:feature_class":"P",
    "gn:feature_code":"PPL",
    "gn:name":"Karya",
    "gn:population":0,
    "gn:timezone":"Asia/Makassar",
    "iso:country":"ID",
    "name:ell_x_preferred":[
        "\u039a\u03b1\u03c1\u03c5\u03ac"
    ],
    "name:fin_x_preferred":[
        "Kary\u00e1"
    ],
    "name:ind_x_preferred":[
        "Karya"
    ],
    "name:nld_x_preferred":[
        "Karya"
    ],
    "name:slk_x_preferred":[
        "Karya"
    ],
    "wof:name":"Karya",
    "wof:placetype":"locality"
},
  "geometry": {"coordinates":[117.4507,-8.6292],"type":"Point"}
}