{
  "type": "Feature",
  "properties": {
    "gn:admin1_code":"38",
    "gn:asciiname":"Celengang",
    "gn:country_code":"ID",
    "gn:dem":16,
    "gn:feature_class":"P",
    "gn:feature_code":"PPL",
    "gn:name":"Celengang",
    "gn:population":0,
    "gn:timezone":"Asia/Makassar",
    "iso:country":"ID",
    "name:ind_x_preferred":[
        "Celengang"
    ],
    "wof:name":"Celengang",
    "wof:placetype":"locality"
},
  "geometry": {"coordinates":[119.8664,-4.0271],"type":"Point"}
}