{
  "type": "Feature",
  "properties": {
    "gn:admin1_code":"17",
    "gn:asciiname":"Sikur",
    "gn:country_code":"ID",
    "gn:dem":305,
    "gn:feature_class":"P",
    "gn:feature_code":"PPLA3",
    "gn:name":"Sikur",
    "gn:population":0,
    "gn:timezone":"Asia/Makassar",
    "iso:country":"ID",
    "name:ind_x_preferred":[
        "Sikur"
    ],
    "name:jav_x_preferred":[
        "Sikur"
    ],
    "name:msa_x_preferred":[
        "Sikur"
    ],
    "name:ukr_x_preferred":[
        "\u0421\u0456\u043a\u0443\u0440"
    ],
    "wof:lang_x_official":[
        "ind"
    ],
    "wof:lang_x_spoken":[
        "ind",
        "eng"
    ],
    "wof:name":"Sikur",
    "wof:placetype":"locality"
},
  "geometry": {"coordinates":[116.44629999999999,-8.6331],"type":"Point"}
}