{
  "type": "Feature",
  "properties": {
    "gn:admin1_code":"41.0",
    "gn:asciiname":"Kai",
    "gn:country_code":"ID",
    "gn:dem":15,
    "gn:feature_class":"P",
    "gn:feature_code":"PPL",
    "gn:name":"Kai",
    "gn:population":0,
    "gn:timezone":"Asia/Makassar",
    "iso:country":"ID",
    "name:cat_x_preferred":[
        "Kai"
    ],
    "name:ceb_x_preferred":[
        "Kai"
    ],
    "name:deu_x_preferred":[
        "Kai"
    ],
    "name:ell_x_preferred":[
        "\u039a\u03b1\u03b9"
    ],
    "name:est_x_preferred":[
        "Kai"
    ],
    "name:fra_x_preferred":[
        "Kai"
    ],
    "name:hye_x_preferred":[
        "\u053f\u0561\u0575"
    ],
    "name:nld_x_preferred":[
        "Kai"
    ],
    "name:nor_x_preferred":[
        "Kai"
    ],
    "name:pol_x_preferred":[
        "Kai"
    ],
    "name:por_x_preferred":[
        "Kai"
    ],
    "name:rus_x_preferred":[
        "\u041a\u0430\u0439"
    ],
    "name:slk_x_preferred":[
        "Kai"
    ],
    "name:spa_x_preferred":[
        "Kai"
    ],
    "name:swe_x_preferred":[
        "Kai"
    ],
    "name:ukr_x_preferred":[
        "\u041a\u0430\u0439"
    ],
    "name:vie_x_preferred":[
        "Kai"
    ],
    "wof:lang_x_official":[
        "ind"
    ],
    "wof:lang_x_spoken":[
        "ind",
        "eng"
    ],
    "wof:name":"Kai",
    "wof:placetype":"locality"
},
  "geometry": {"coordinates":[118.81361,-2.85028],"type":"Point"}
}