{
  "type": "Feature",
  "properties": {
    "gn:admin1_code":"7",
    "gn:asciiname":"Sawojajar",
    "gn:country_code":"ID",
    "gn:dem":8,
    "gn:feature_class":"P",
    "gn:feature_code":"PPL",
    "gn:name":"Sawojajar",
    "gn:population":0,
    "gn:timezone":"Asia/Jakarta",
    "iso:country":"ID",
    "name:ind_x_preferred":[
        "Sawojajar"
    ],
    "wof:name":"Sawojajar",
    "wof:placetype":"locality"
},
  "geometry": {"coordinates":[109.0142,-6.8201],"type":"Point"}
}