{
  "type": "Feature",
  "properties": {
    "gn:admin1_code":"30.0",
    "gn:asciiname":"Desakolot",
    "gn:country_code":"ID",
    "gn:dem":167,
    "gn:feature_class":"P",
    "gn:feature_code":"PPL",
    "gn:name":"Desakolot",
    "gn:population":0,
    "gn:timezone":"Asia/Jakarta",
    "iso:country":"ID",
    "name:ind_x_preferred":[
        "Desakolot"
    ],
    "wof:name":"Desakolot",
    "wof:placetype":"locality"
},
  "geometry": {"coordinates":[108.1983,-7.7027],"type":"Point"}
}