{
  "type": "Feature",
  "properties": {
    "gn:admin1_code":"7.0",
    "gn:asciiname":"Cangkaraun",
    "gn:country_code":"ID",
    "gn:dem":205,
    "gn:feature_class":"P",
    "gn:feature_code":"PPL",
    "gn:name":"Cangkaraun",
    "gn:population":0,
    "gn:timezone":"Asia/Jakarta",
    "iso:country":"ID",
    "name:ind_x_preferred":[
        "Cangkaraun"
    ],
    "wof:name":"Cangkaraun",
    "wof:placetype":"locality"
},
  "geometry": {"coordinates":[109.00833,-7.30778],"type":"Point"}
}