{
  "type": "Feature",
  "properties": {
    "gn:admin1_code":"8",
    "gn:asciiname":"Sekluweng",
    "gn:country_code":"ID",
    "gn:dem":402,
    "gn:feature_class":"P",
    "gn:feature_code":"PPL",
    "gn:name":"Sekluweng",
    "gn:population":0,
    "gn:timezone":"Asia/Jakarta",
    "iso:country":"ID",
    "name:ind_x_preferred":[
        "Sekluweng"
    ],
    "wof:name":"Sekluweng",
    "wof:placetype":"locality"
},
  "geometry": {"coordinates":[111.7278,-7.6735],"type":"Point"}
}