{
  "type": "Feature",
  "properties": {
    "gn:country":"ID",
    "gn:fcode":"PPL",
    "gn:pop":0,
    "iso:country":"ID",
    "name:unk_x_variant":[
        "Pekoelonan"
    ],
    "qs:name":"Pakulonan",
    "qs:name_adm0":"Indonesia",
    "qs:name_adm1":"Banten",
    "qs:photos_9k":1,
    "qs:photos_9r":3,
    "qs:photos_all":96,
    "qs:photos_sr":0,
    "qs:placetype":"Town",
    "qs:pop_sr":"0",
    "wof:name":"Pakulonan",
    "wof:placetype":"locality",
    "wof:population":0
},
  "geometry": {"coordinates":[106.63694,-6.23222],"type":"Point"}
}