{
  "type": "Feature",
  "properties": {
    "gn:admin1_code":"26.0",
    "gn:asciiname":"Sosor Sitanggang",
    "gn:country_code":"ID",
    "gn:dem":1428,
    "gn:feature_class":"P",
    "gn:feature_code":"PPL",
    "gn:name":"Sosor Sitanggang",
    "gn:population":0,
    "gn:timezone":"Asia/Jakarta",
    "iso:country":"ID",
    "name:ind_x_preferred":[
        "Sosor Sitanggang"
    ],
    "wof:name":"Sosor Sitanggang",
    "wof:placetype":"locality"
},
  "geometry": {"coordinates":[98.76730000000001,2.5992],"type":"Point"}
}