{
  "type": "Feature",
  "properties": {
    "gn:admin1_code":"30.0",
    "gn:asciiname":"Kosambilempeng Tengah",
    "gn:country_code":"ID",
    "gn:dem":4,
    "gn:feature_class":"P",
    "gn:feature_code":"PPL",
    "gn:name":"Kosambilempeng Tengah",
    "gn:population":0,
    "gn:timezone":"Asia/Jakarta",
    "iso:country":"ID",
    "name:ind_x_preferred":[
        "Kosambilempeng Tengah"
    ],
    "name:und_x_variant":[
        "Kosambilempeng"
    ],
    "wof:lang_x_official":[
        "ind"
    ],
    "wof:lang_x_spoken":[
        "ind",
        "eng"
    ],
    "wof:name":"Kosambilempeng Tengah",
    "wof:placetype":"locality"
},
  "geometry": {"coordinates":[107.55833,-6.23056],"type":"Point"}
}