{
  "type": "Feature",
  "properties": {
    "gn:admin1_code":"30.0",
    "gn:asciiname":"Lengkob",
    "gn:country_code":"ID",
    "gn:dem":332,
    "gn:feature_class":"P",
    "gn:feature_code":"PPL",
    "gn:name":"Lengkob",
    "gn:population":0,
    "gn:timezone":"Asia/Jakarta",
    "iso:country":"ID",
    "name:ind_x_preferred":[
        "Lengkob"
    ],
    "wof:name":"Lengkob",
    "wof:placetype":"locality"
},
  "geometry": {"coordinates":[107.12690000000001,-7.2716],"type":"Point"}
}