{
  "type": "Feature",
  "properties": {
    "gn:admin1_code":"30",
    "gn:asciiname":"Ugrem",
    "gn:country_code":"ID",
    "gn:dem":658,
    "gn:feature_class":"P",
    "gn:feature_code":"PPL",
    "gn:name":"Ugrem",
    "gn:population":0,
    "gn:timezone":"Asia/Jakarta",
    "iso:country":"ID",
    "name:ind_x_preferred":[
        "Ugrem"
    ],
    "wof:name":"Ugrem",
    "wof:placetype":"locality"
},
  "geometry": {"coordinates":[107.43389000000001,-6.9625],"type":"Point"}
}