{
  "type": "Feature",
  "properties": {
    "gn:admin1_code":"30.0",
    "gn:asciiname":"Cisarua",
    "gn:country_code":"ID",
    "gn:dem":650,
    "gn:feature_class":"P",
    "gn:feature_code":"PPL",
    "gn:name":"Cisarua",
    "gn:population":0,
    "gn:timezone":"Asia/Jakarta",
    "iso:country":"ID",
    "name:ind_x_preferred":[
        "Cisarua"
    ],
    "wof:name":"Cisarua",
    "wof:placetype":"locality"
},
  "geometry": {"coordinates":[107.52030000000001,-7.4424],"type":"Point"}
}