{
  "type": "Feature",
  "properties": {
    "gn:admin1_code":"7.0",
    "gn:asciiname":"Ngandang",
    "gn:country_code":"ID",
    "gn:dem":161,
    "gn:feature_class":"P",
    "gn:feature_code":"PPLA4",
    "gn:name":"Ngandang",
    "gn:population":0,
    "gn:timezone":"Asia/Jakarta",
    "iso:country":"ID",
    "name:ind_x_preferred":[
        "Ngandang"
    ],
    "wof:lang_x_official":[
        "ind"
    ],
    "wof:lang_x_spoken":[
        "ind",
        "eng"
    ],
    "wof:name":"Ngandang",
    "wof:placetype":"locality"
},
  "geometry": {"coordinates":[111.55589999999999,-6.816],"type":"Point"}
}