{
  "type": "Feature",
  "properties": {
    "gn:admin1_code":"7.0",
    "gn:asciiname":"Kedungjambu",
    "gn:country_code":"ID",
    "gn:dem":53,
    "gn:feature_class":"P",
    "gn:feature_code":"PPL",
    "gn:name":"Kedungjambu",
    "gn:population":0,
    "gn:timezone":"Asia/Jakarta",
    "iso:country":"ID",
    "name:ind_x_preferred":[
        "Kedungjambu"
    ],
    "wof:name":"Kedungjambu",
    "wof:placetype":"locality"
},
  "geometry": {"coordinates":[111.41970000000001,-7.1917],"type":"Point"}
}