{
  "type": "Feature",
  "properties": {
    "gn:admin1_code":"18.0",
    "gn:asciiname":"Oenana",
    "gn:country_code":"ID",
    "gn:dem":274,
    "gn:feature_class":"P",
    "gn:feature_code":"PPL",
    "gn:name":"Oenana",
    "gn:population":0,
    "gn:timezone":"Asia/Makassar",
    "iso:country":"ID",
    "name:ind_x_preferred":[
        "Oenana"
    ],
    "wof:name":"Oenana",
    "wof:placetype":"locality"
},
  "geometry": {"coordinates":[124.60890000000001,-9.6243],"type":"Point"}
}