{
  "type": "Feature",
  "properties": {
    "gn:admin1_code":"1",
    "gn:asciiname":"Blang Remulek",
    "gn:country_code":"ID",
    "gn:dem":10,
    "gn:feature_class":"P",
    "gn:feature_code":"PPL",
    "gn:name":"Blang Remulek",
    "gn:population":0,
    "gn:timezone":"Asia/Jakarta",
    "iso:country":"ID",
    "name:ind_x_preferred":[
        "Blang Remulek"
    ],
    "wof:name":"Blang Remulek",
    "wof:placetype":"locality"
},
  "geometry": {"coordinates":[96.41070000000001,5.1992],"type":"Point"}
}