{
  "type": "Feature",
  "properties": {
    "gn:admin1_code":"18",
    "gn:asciiname":"Waikabubak",
    "gn:country_code":"ID",
    "gn:dem":396,
    "gn:feature_class":"P",
    "gn:feature_code":"PPL",
    "gn:name":"Waikabubak",
    "gn:population":0,
    "gn:timezone":"Asia/Makassar",
    "iso:country":"ID",
    "name:ind_x_preferred":[
        "Waikabubak"
    ],
    "wof:name":"Waikabubak",
    "wof:placetype":"locality"
},
  "geometry": {"coordinates":[119.8038,-9.5663],"type":"Point"}
}