{
  "type": "Feature",
  "properties": {
    "gn:admin1_code":"38.0",
    "gn:asciiname":"Karangkarangan",
    "gn:country_code":"ID",
    "gn:dem":13,
    "gn:feature_class":"P",
    "gn:feature_code":"PPL",
    "gn:name":"Karangkarangan",
    "gn:population":0,
    "gn:timezone":"Asia/Makassar",
    "iso:country":"ID",
    "name:ind_x_preferred":[
        "Karangkarangan"
    ],
    "wof:name":"Karangkarangan",
    "wof:placetype":"locality"
},
  "geometry": {"coordinates":[120.2551,-3.1161],"type":"Point"}
}