{
  "type": "Feature",
  "properties": {
    "gn:admin1_code":"18",
    "gn:asciiname":"Buas",
    "gn:country_code":"ID",
    "gn:dem":676,
    "gn:feature_class":"P",
    "gn:feature_code":"PPL",
    "gn:name":"Buas",
    "gn:population":0,
    "gn:timezone":"Asia/Makassar",
    "iso:country":"ID",
    "name:ind_x_preferred":[
        "Buas"
    ],
    "wof:name":"Buas",
    "wof:placetype":"locality"
},
  "geometry": {"coordinates":[120.2608,-8.6974],"type":"Point"}
}