{
  "type": "Feature",
  "properties": {
    "gn:admin1_code":"30.0",
    "gn:asciiname":"Ciawi",
    "gn:country_code":"ID",
    "gn:dem":305,
    "gn:feature_class":"P",
    "gn:feature_code":"PPL",
    "gn:name":"Ciawi",
    "gn:population":0,
    "gn:timezone":"Asia/Jakarta",
    "iso:country":"ID",
    "name:ind_x_preferred":[
        "Ciawi"
    ],
    "wof:name":"Ciawi",
    "wof:placetype":"locality"
},
  "geometry": {"coordinates":[107.68819999999999,-7.56046],"type":"Point"}
}