{
  "type": "Feature",
  "properties": {
    "gn:admin1_code":"1",
    "gn:asciiname":"Rema",
    "gn:country_code":"ID",
    "gn:dem":172,
    "gn:feature_class":"P",
    "gn:feature_code":"PPL",
    "gn:name":"Rema",
    "gn:population":0,
    "gn:timezone":"Asia/Jakarta",
    "iso:country":"ID",
    "name:ceb_x_preferred":[
        "Rema"
    ],
    "name:deu_x_preferred":[
        "Rema"
    ],
    "name:ind_x_preferred":[
        "Rema"
    ],
    "name:nld_x_preferred":[
        "Rema"
    ],
    "wof:lang_x_official":[
        "ind"
    ],
    "wof:lang_x_spoken":[
        "ind",
        "eng"
    ],
    "wof:name":"Rema",
    "wof:placetype":"locality"
},
  "geometry": {"coordinates":[97.88590000000001,3.4205],"type":"Point"}
}