{
  "type": "Feature",
  "properties": {
    "gn:admin1_code":"8",
    "gn:asciiname":"Batulawang",
    "gn:country_code":"ID",
    "gn:dem":842,
    "gn:feature_class":"P",
    "gn:feature_code":"PPL",
    "gn:name":"Batulawang",
    "gn:population":0,
    "gn:timezone":"Asia/Jakarta",
    "iso:country":"ID",
    "name:ind_x_preferred":[
        "Batulawang"
    ],
    "wof:name":"Batulawang",
    "wof:placetype":"locality"
},
  "geometry": {"coordinates":[114.1703,-7.9212],"type":"Point"}
}