{
  "type": "Feature",
  "properties": {
    "gn:admin1_code":"15.0",
    "gn:asciiname":"Umbulan Kandar",
    "gn:country_code":"ID",
    "gn:dem":111,
    "gn:feature_class":"P",
    "gn:feature_code":"PPL",
    "gn:name":"Umbulan Kandar",
    "gn:population":0,
    "gn:timezone":"Asia/Jakarta",
    "iso:country":"ID",
    "name:ind_x_preferred":[
        "Umbulan Kandar"
    ],
    "wof:name":"Umbulan Kandar",
    "wof:placetype":"locality"
},
  "geometry": {"coordinates":[104.82898,-4.98775],"type":"Point"}
}