{
  "type": "Feature",
  "properties": {
    "gn:admin1_code":"1",
    "gn:asciiname":"Pantonlasi",
    "gn:country_code":"ID",
    "gn:dem":29,
    "gn:feature_class":"P",
    "gn:feature_code":"PPL",
    "gn:name":"Pantonlasi",
    "gn:population":0,
    "gn:timezone":"Asia/Jakarta",
    "iso:country":"ID",
    "name:ind_x_preferred":[
        "Pantonlasi"
    ],
    "wof:name":"Pantonlasi",
    "wof:placetype":"locality"
},
  "geometry": {"coordinates":[96.45059999999999,4.1226],"type":"Point"}
}