{
  "type": "Feature",
  "properties": {
    "gn:admin1_code":"26",
    "gn:asciiname":"Kutakepar",
    "gn:country_code":"ID",
    "gn:dem":1215,
    "gn:feature_class":"P",
    "gn:feature_code":"PPL",
    "gn:name":"Kutakepar",
    "gn:population":0,
    "gn:timezone":"Asia/Jakarta",
    "iso:country":"ID",
    "name:ind_x_preferred":[
        "Kutakepar"
    ],
    "name:und_x_variant":[
        "Kotakeper"
    ],
    "wof:lang_x_official":[
        "ind"
    ],
    "wof:lang_x_spoken":[
        "ind",
        "eng"
    ],
    "wof:name":"Kutakepar",
    "wof:placetype":"locality"
},
  "geometry": {"coordinates":[98.5111,3.0542],"type":"Point"}
}