{
  "type": "Feature",
  "properties": {
    "gn:admin1_code":"30",
    "gn:asciiname":"Lebaksirah",
    "gn:country_code":"ID",
    "gn:dem":539,
    "gn:feature_class":"P",
    "gn:feature_code":"PPL",
    "gn:name":"Lebaksirah",
    "gn:population":0,
    "gn:timezone":"Asia/Jakarta",
    "iso:country":"ID",
    "name:ind_x_preferred":[
        "Lebaksirah"
    ],
    "wof:name":"Lebaksirah",
    "wof:placetype":"locality"
},
  "geometry": {"coordinates":[107.99861,-6.76278],"type":"Point"}
}