{
  "type": "Feature",
  "properties": {
    "gn:admin1_code":"08",
    "gn:asciiname":"Jambangan",
    "gn:country_code":"ID",
    "gn:dem":445,
    "gn:feature_class":"P",
    "gn:feature_code":"PPL",
    "gn:name":"Jambangan",
    "gn:population":0,
    "gn:timezone":"Asia/Jakarta",
    "iso:country":"ID",
    "name:ind_x_preferred":[
        "Jambangan"
    ],
    "name:und_x_variant":[
        "Djambangan"
    ],
    "wof:name":"Jambangan",
    "wof:placetype":"locality"
},
  "geometry": {"coordinates":[112.65989999999999,-7.9569],"type":"Point"}
}