{
  "type": "Feature",
  "properties": {
    "gn:admin1_code":"26",
    "gn:asciiname":"Bukittua",
    "gn:country_code":"ID",
    "gn:dem":10,
    "gn:feature_class":"P",
    "gn:feature_code":"PPL",
    "gn:name":"Bukittua",
    "gn:population":0,
    "gn:timezone":"Asia/Jakarta",
    "iso:country":"ID",
    "name:ind_x_preferred":[
        "Bukittua"
    ],
    "wof:name":"Bukittua",
    "wof:placetype":"locality"
},
  "geometry": {"coordinates":[98.3562,3.8727],"type":"Point"}
}