{
  "type": "Feature",
  "properties": {
    "gn:admin1_code":"18.0",
    "gn:asciiname":"Balauring",
    "gn:country_code":"ID",
    "gn:dem":16,
    "gn:feature_class":"P",
    "gn:feature_code":"PPLA3",
    "gn:name":"Balauring",
    "gn:population":0,
    "gn:timezone":"Asia/Makassar",
    "iso:country":"ID",
    "name:und_x_variant":[
        "Balurin",
        "Balaoerjn",
        "Baloerin",
        "Balauring",
        "Balaoerin",
        "Balaurin"
    ],
    "wof:name":"Balauring",
    "wof:placetype":"locality"
},
  "geometry": {"coordinates":[123.706,-8.2336],"type":"Point"}
}