{
  "type": "Feature",
  "properties": {
    "gn:admin1_code":"07",
    "gn:asciiname":"Pakisan",
    "gn:country_code":"ID",
    "gn:dem":379,
    "gn:feature_class":"P",
    "gn:feature_code":"PPL",
    "gn:name":"Pakisan",
    "gn:population":0,
    "gn:timezone":"Asia/Jakarta",
    "iso:country":"ID",
    "wof:name":"Pakisan",
    "wof:placetype":"locality"
},
  "geometry": {"coordinates":[110.6425,-7.39444],"type":"Point"}
}