{
  "type": "Feature",
  "properties": {
    "gn:admin1_code":"8.0",
    "gn:asciiname":"Kutorejo",
    "gn:cc2":"ID",
    "gn:country_code":"ID",
    "gn:dem":432,
    "gn:feature_class":"P",
    "gn:feature_code":"PPL",
    "gn:name":"Kutorejo",
    "gn:population":0,
    "gn:timezone":"Asia/Jakarta",
    "iso:country":"ID",
    "name:und_x_variant":[
        "Koetoredjo",
        "Kutoredjo",
        "Kotaredja",
        "Kutorejo"
    ],
    "wof:lang_x_official":[
        "ind"
    ],
    "wof:lang_x_spoken":[
        "ind",
        "eng"
    ],
    "wof:name":"Kutorejo",
    "wof:placetype":"locality"
},
  "geometry": {"coordinates":[112.64861000000001,-7.99083],"type":"Point"}
}