{
  "type": "Feature",
  "properties": {
    "gn:admin1_code":"8.0",
    "gn:asciiname":"Minggirejo",
    "gn:country_code":"ID",
    "gn:dem":48,
    "gn:feature_class":"P",
    "gn:feature_code":"PPL",
    "gn:name":"Minggirejo",
    "gn:population":0,
    "gn:timezone":"Asia/Jakarta",
    "iso:country":"ID",
    "name:ind_x_preferred":[
        "Minggirejo"
    ],
    "wof:name":"Minggirejo",
    "wof:placetype":"locality"
},
  "geometry": {"coordinates":[112.3402,-7.395],"type":"Point"}
}