{
  "type": "Feature",
  "properties": {
    "gn:admin1_code":"18",
    "gn:asciiname":"Bipaan",
    "gn:country_code":"ID",
    "gn:dem":337,
    "gn:feature_class":"P",
    "gn:feature_code":"PPL",
    "gn:name":"Bipaan",
    "gn:population":0,
    "gn:timezone":"Asia/Makassar",
    "iso:country":"ID",
    "wof:name":"Bipaan",
    "wof:placetype":"locality"
},
  "geometry": {"coordinates":[124.53111,-9.31528],"type":"Point"}
}