{
  "type": "Feature",
  "properties": {
    "gn:country":"ID",
    "gn:fcode":"PPLA4",
    "gn:pop":0,
    "iso:country":"ID",
    "name:ind_x_preferred":[
        "Utara"
    ],
    "qs:name":"Utara",
    "qs:photos_9r":0,
    "qs:photos_sr":0,
    "qs:pop_sr":"0",
    "wd:wordcount":78,
    "wof:name":"Utara",
    "wof:placetype":"locality",
    "wof:population":0
},
  "geometry": {"coordinates":[113.49657999999999,-7.19886],"type":"Point"}
}