{
  "type": "Feature",
  "properties": {
    "gn:admin1_code":"26",
    "gn:asciiname":"Jumateguh",
    "gn:country_code":"ID",
    "gn:dem":771,
    "gn:feature_class":"P",
    "gn:feature_code":"PPL",
    "gn:name":"Jumateguh",
    "gn:population":0,
    "gn:timezone":"Asia/Jakarta",
    "iso:country":"ID",
    "name:ind_x_preferred":[
        "Jumateguh"
    ],
    "name:und_x_variant":[
        "Jumateguh 1"
    ],
    "wof:lang_x_official":[
        "ind"
    ],
    "wof:lang_x_spoken":[
        "ind",
        "eng"
    ],
    "wof:name":"Jumateguh",
    "wof:placetype":"locality"
},
  "geometry": {"coordinates":[98.227,2.7938],"type":"Point"}
}