{
  "type": "Feature",
  "properties": {
    "gn:admin1_code":"07",
    "gn:asciiname":"Randusari",
    "gn:country_code":"ID",
    "gn:dem":501,
    "gn:feature_class":"P",
    "gn:feature_code":"PPL",
    "gn:name":"Randusari",
    "gn:population":0,
    "gn:timezone":"Asia/Jakarta",
    "iso:country":"ID",
    "name:und_x_variant":[
        "Randusari 2",
        "Randusari Dua",
        "Randusari"
    ],
    "wof:name":"Randusari",
    "wof:placetype":"locality"
},
  "geometry": {"coordinates":[110.58861,-7.47056],"type":"Point"}
}