{
  "type": "Feature",
  "properties": {
    "gn:admin1_code":"8",
    "gn:asciiname":"Pasaran",
    "gn:country_code":"ID",
    "gn:dem":506,
    "gn:feature_class":"P",
    "gn:feature_code":"PPL",
    "gn:name":"Pasaran",
    "gn:population":0,
    "gn:timezone":"Asia/Jakarta",
    "iso:country":"ID",
    "name:ceb_x_preferred":[
        "Pulau Pasaran"
    ],
    "name:ind_x_preferred":[
        "Pasaran"
    ],
    "name:ind_x_variant":[
        "Pulau Pasaran"
    ],
    "wof:name":"Pasaran",
    "wof:placetype":"locality"
},
  "geometry": {"coordinates":[113.92230000000001,-8.1061],"type":"Point"}
}