{
  "type": "Feature",
  "properties": {
    "gn:admin1_code":"37",
    "gn:asciiname":"Bancadanan",
    "gn:country_code":"ID",
    "gn:dem":43,
    "gn:feature_class":"P",
    "gn:feature_code":"PPL",
    "gn:name":"Bancadanan",
    "gn:population":0,
    "gn:timezone":"Asia/Jakarta",
    "iso:country":"ID",
    "name:eng_x_preferred":[
        "Bantjadanan Dua"
    ],
    "name:eng_x_variant":[
        "Bantjadanan 2"
    ],
    "name:ind_x_preferred":[
        "Bancadanan"
    ],
    "wof:lang_x_official":[
        "ind"
    ],
    "wof:lang_x_spoken":[
        "ind",
        "eng"
    ],
    "wof:name":"Bancadanan",
    "wof:placetype":"locality"
},
  "geometry": {"coordinates":[101.31189999999999,0.2975],"type":"Point"}
}