{
  "type": "Feature",
  "properties": {
    "gn:admin1_code":"8",
    "gn:asciiname":"Pancor",
    "gn:country_code":"ID",
    "gn:dem":21,
    "gn:feature_class":"P",
    "gn:feature_code":"PPL",
    "gn:name":"Pancor",
    "gn:population":0,
    "gn:timezone":"Asia/Jakarta",
    "iso:country":"ID",
    "name:ind_x_preferred":[
        "Pancor"
    ],
    "wof:name":"Pancor",
    "wof:placetype":"locality"
},
  "geometry": {"coordinates":[113.24509999999999,-7.1143],"type":"Point"}
}