{
  "type": "Feature",
  "properties": {
    "gn:admin1_code":"35",
    "gn:asciiname":"Selumar",
    "gn:country_code":"ID",
    "gn:dem":21,
    "gn:feature_class":"P",
    "gn:feature_code":"PPL",
    "gn:name":"Selumar",
    "gn:population":0,
    "gn:timezone":"Asia/Jakarta",
    "iso:country":"ID",
    "name:ind_x_preferred":[
        "Selumar"
    ],
    "wof:name":"Selumar",
    "wof:placetype":"locality"
},
  "geometry": {"coordinates":[107.76075,-2.60297],"type":"Point"}
}