{
  "type": "Feature",
  "properties": {
    "gn:country":"ID",
    "gn:fcode":"ADM4",
    "gn:pop":0,
    "iso:country":"ID",
    "name:ind_x_preferred":[
        "Kelurahan Lukluk"
    ],
    "name:unk_x_variant":[
        "Lukluk"
    ],
    "qs:name":"Kelurahan Lukluk",
    "qs:photos_9r":0,
    "qs:photos_sr":0,
    "qs:pop_sr":"0",
    "wof:name":"Kelurahan Lukluk",
    "wof:placetype":"localadmin",
    "wof:population":0
},
  "geometry": {"coordinates":[115.1947,-8.566],"type":"Point"}
}