{
  "type": "Feature",
  "properties": {
    "gn:admin1_code":"08",
    "gn:asciiname":"Soga",
    "gn:country_code":"ID",
    "gn:dem":39,
    "gn:feature_class":"P",
    "gn:feature_code":"PPL",
    "gn:name":"Soga",
    "gn:population":0,
    "gn:timezone":"Asia/Jakarta",
    "iso:country":"ID",
    "name:ceb_x_preferred":[
        "Soga"
    ],
    "name:deu_x_preferred":[
        "Soga"
    ],
    "name:fin_x_preferred":[
        "Soga"
    ],
    "name:fra_x_preferred":[
        "Soga"
    ],
    "name:pol_x_preferred":[
        "Soga"
    ],
    "name:rus_x_preferred":[
        "\u0421\u043e\u0433\u0430"
    ],
    "name:spa_x_preferred":[
        "Soga"
    ],
    "wof:lang_x_official":[
        "ind"
    ],
    "wof:lang_x_spoken":[
        "ind",
        "eng"
    ],
    "wof:name":"Soga",
    "wof:placetype":"locality"
},
  "geometry": {"coordinates":[112.79361,-7.1375],"type":"Point"}
}