{
  "type": "Feature",
  "properties": {
    "gn:admin1_code":"33",
    "gn:asciiname":"Papanggo",
    "gn:country_code":"ID",
    "gn:dem":67,
    "gn:feature_class":"P",
    "gn:feature_code":"PPL",
    "gn:name":"Papanggo",
    "gn:population":0,
    "gn:timezone":"Asia/Jakarta",
    "iso:country":"ID",
    "name:ind_x_preferred":[
        "Papanggo"
    ],
    "name:msa_x_preferred":[
        "Papanggo"
    ],
    "name:nld_x_preferred":[
        "Papanggo"
    ],
    "name:sun_x_preferred":[
        "Papango"
    ],
    "wof:lang_x_official":[
        "ind"
    ],
    "wof:lang_x_spoken":[
        "ind",
        "eng"
    ],
    "wof:name":"Papanggo",
    "wof:placetype":"locality"
},
  "geometry": {"coordinates":[106.334,-6.3428],"type":"Point"}
}