{
  "type": "Feature",
  "properties": {
    "gn:admin1_code":"30.0",
    "gn:asciiname":"Citamiang",
    "gn:country_code":"ID",
    "gn:dem":678,
    "gn:feature_class":"P",
    "gn:feature_code":"PPL",
    "gn:name":"Citamiang",
    "gn:population":0,
    "gn:timezone":"Asia/Jakarta",
    "iso:country":"ID",
    "name:ind_x_preferred":[
        "Citamiang"
    ],
    "name:und_x_variant":[
        "Tjitamiang 1"
    ],
    "wof:name":"Citamiang",
    "wof:placetype":"locality"
},
  "geometry": {"coordinates":[107.97790000000001,-7.4924],"type":"Point"}
}