{
  "type": "Feature",
  "properties": {
    "gn:admin1_code":"7",
    "gn:asciiname":"Tejo",
    "gn:country_code":"ID",
    "gn:dem":466,
    "gn:feature_class":"P",
    "gn:feature_code":"PPL",
    "gn:name":"Tejo",
    "gn:population":0,
    "gn:timezone":"Asia/Jakarta",
    "iso:country":"ID",
    "name:ben_x_preferred":[
        "\u09a4\u09c7\u099c\u09cb"
    ],
    "name:deu_x_preferred":[
        "Tejo"
    ],
    "name:epo_x_preferred":[
        "Tejo"
    ],
    "name:fra_x_preferred":[
        "Tejo"
    ],
    "name:hin_x_preferred":[
        "\u0924\u0947\u091c\u094b"
    ],
    "name:hun_x_preferred":[
        "Tejo"
    ],
    "name:ind_x_preferred":[
        "Tejo"
    ],
    "name:nld_x_preferred":[
        "Tejo"
    ],
    "name:pol_x_preferred":[
        "Tejo"
    ],
    "name:por_x_preferred":[
        "Tejo"
    ],
    "name:spa_x_preferred":[
        "Tejo"
    ],
    "name:swe_x_preferred":[
        "Tejo"
    ],
    "name:urd_x_preferred":[
        "\u062a\u06cc\u062c\u0648"
    ],
    "wof:lang_x_official":[
        "ind"
    ],
    "wof:lang_x_spoken":[
        "ind",
        "eng"
    ],
    "wof:name":"Tejo",
    "wof:placetype":"locality"
},
  "geometry": {"coordinates":[111.11,-7.5375],"type":"Point"}
}