{
  "type": "Feature",
  "properties": {
    "gn:admin1_code":"8.0",
    "gn:asciiname":"Grintingan",
    "gn:country_code":"ID",
    "gn:dem":57,
    "gn:feature_class":"P",
    "gn:feature_code":"PPL",
    "gn:name":"Grintingan",
    "gn:population":0,
    "gn:timezone":"Asia/Jakarta",
    "iso:country":"ID",
    "name:ind_x_preferred":[
        "Grintingan"
    ],
    "wof:name":"Grintingan",
    "wof:placetype":"locality"
},
  "geometry": {"coordinates":[113.2817,-7.8497],"type":"Point"}
}