{
  "type": "Feature",
  "properties": {
    "gn:admin1_code":"1.0",
    "gn:asciiname":"Buga",
    "gn:country_code":"ID",
    "gn:dem":12,
    "gn:feature_class":"P",
    "gn:feature_code":"PPL",
    "gn:name":"Buga",
    "gn:population":0,
    "gn:timezone":"Asia/Jakarta",
    "iso:country":"ID",
    "name:ceb_x_preferred":[
        "Buga"
    ],
    "name:deu_x_preferred":[
        "Buga"
    ],
    "name:ind_x_preferred":[
        "Buga"
    ],
    "name:ita_x_preferred":[
        "Buga"
    ],
    "name:lav_x_preferred":[
        "Buga"
    ],
    "name:spa_x_preferred":[
        "Buga"
    ],
    "name:und_x_variant":[
        "Boega"
    ],
    "wof:lang_x_official":[
        "ind"
    ],
    "wof:lang_x_spoken":[
        "ind",
        "eng"
    ],
    "wof:name":"Buga",
    "wof:placetype":"locality"
},
  "geometry": {"coordinates":[96.81610000000001,5.25],"type":"Point"}
}