{
  "type": "Feature",
  "properties": {
    "gn:admin1_code":"8",
    "gn:asciiname":"Jagir",
    "gn:country_code":"ID",
    "gn:dem":251,
    "gn:feature_class":"P",
    "gn:feature_code":"PPL",
    "gn:name":"Jagir",
    "gn:population":0,
    "gn:timezone":"Asia/Jakarta",
    "iso:country":"ID",
    "name:ind_x_preferred":[
        "Jagir"
    ],
    "wof:name":"Jagir",
    "wof:placetype":"locality"
},
  "geometry": {"coordinates":[111.18361000000002,-7.47194],"type":"Point"}
}