{
  "type": "Feature",
  "properties": {
    "gn:admin1_code":"8",
    "gn:asciiname":"Jagir",
    "gn:country_code":"ID",
    "gn:dem":251,
    "gn:feature_class":"P",
    "gn:feature_code":"PPL",
    "gn:name":"Jagir",
    "gn:population":0,
    "gn:timezone":"Asia/Jakarta",
    "iso:country":"ID",
    "name:bel_x_preferred":[
        "\u0414\u0436\u0430\u0433\u0456\u0440"
    ],
    "name:ben_x_preferred":[
        "\u099c\u09be\u09af\u09bc\u0997\u09c0\u09b0"
    ],
    "name:cat_x_preferred":[
        "Jagir"
    ],
    "name:ces_x_preferred":[
        "D\u017eag\u00edr"
    ],
    "name:deu_x_preferred":[
        "Jagir"
    ],
    "name:fas_x_preferred":[
        "\u062c\u0627\u06af\u06cc\u0631"
    ],
    "name:ind_x_preferred":[
        "Jagir"
    ],
    "name:ita_x_preferred":[
        "Jagir"
    ],
    "name:jpn_x_preferred":[
        "\u30b8\u30e3\u30fc\u30ae\u30fc\u30eb"
    ],
    "name:kan_x_preferred":[
        "\u0c9c\u0cb9\u0c97\u0cc0\u0cb0\u0cc1"
    ],
    "name:kat_x_preferred":[
        "\u10ef\u10d0\u10d2\u10d8\u10e0\u10d8"
    ],
    "name:nor_x_preferred":[
        "Jagir"
    ],
    "name:rus_x_preferred":[
        "\u0414\u0436\u0430\u0433\u0438\u0440"
    ],
    "name:spa_x_preferred":[
        "Jagir"
    ],
    "name:tam_x_preferred":[
        "\u0b9a\u0bbe\u0b95\u0bbf\u0bb0\u0bcd"
    ],
    "name:ukr_x_preferred":[
        "\u0414\u0436\u0430\u0491\u0456\u0440"
    ],
    "name:uzb_x_preferred":[
        "Jogir"
    ],
    "wof:name":"Jagir",
    "wof:placetype":"locality"
},
  "geometry": {"coordinates":[111.18361000000002,-7.47194],"type":"Point"}
}