{
  "type": "Feature",
  "properties": {
    "gn:admin1_code":"31.0",
    "gn:asciiname":"Liba",
    "gn:country_code":"ID",
    "gn:dem":734,
    "gn:feature_class":"P",
    "gn:feature_code":"PPL",
    "gn:name":"Liba",
    "gn:population":0,
    "gn:timezone":"Asia/Makassar",
    "iso:country":"ID",
    "name:ind_x_preferred":[
        "Liba"
    ],
    "wof:lang_x_official":[
        "ind"
    ],
    "wof:lang_x_spoken":[
        "ind",
        "eng"
    ],
    "wof:name":"Liba",
    "wof:placetype":"locality"
},
  "geometry": {"coordinates":[124.8112,1.1784],"type":"Point"}
}