{
  "type": "Feature",
  "properties": {
    "gn:admin1_code":"21.0",
    "gn:asciiname":"Tanggawas",
    "gn:country_code":"ID",
    "gn:dem":6,
    "gn:feature_class":"P",
    "gn:feature_code":"PPL",
    "gn:name":"Tanggawas",
    "gn:population":0,
    "gn:timezone":"Asia/Makassar",
    "iso:country":"ID",
    "name:ind_x_preferred":[
        "Tanggawas"
    ],
    "wof:name":"Tanggawas",
    "wof:placetype":"locality"
},
  "geometry": {"coordinates":[123.3908,-0.8963],"type":"Point"}
}