{
  "type": "Feature",
  "properties": {
    "gn:admin1_code":"1",
    "gn:asciiname":"Bandar Situhuk",
    "gn:country_code":"ID",
    "gn:dem":23,
    "gn:feature_class":"P",
    "gn:feature_code":"PPL",
    "gn:name":"Bandar Situhuk",
    "gn:population":0,
    "gn:timezone":"Asia/Jakarta",
    "iso:country":"ID",
    "name:ind_x_preferred":[
        "Bandar Situhuk"
    ],
    "wof:name":"Bandar Situhuk",
    "wof:placetype":"locality"
},
  "geometry": {"coordinates":[99.5294,2.6911],"type":"Point"}
}