{
  "type": "Feature",
  "properties": {
    "gn:admin1_code":"26",
    "gn:asciiname":"Dagang Dokah",
    "gn:country_code":"ID",
    "gn:dem":90,
    "gn:feature_class":"P",
    "gn:feature_code":"PPL",
    "gn:name":"Dagang Dokah",
    "gn:population":0,
    "gn:timezone":"Asia/Jakarta",
    "iso:country":"ID",
    "name:ind_x_preferred":[
        "Dagang Dokah"
    ],
    "wof:name":"Dagang Dokah",
    "wof:placetype":"locality"
},
  "geometry": {"coordinates":[98.9996,3.2428],"type":"Point"}
}