{
  "type": "Feature",
  "properties": {
    "gn:admin1_code":"10.0",
    "gn:asciiname":"Ngrabu",
    "gn:country_code":"ID",
    "gn:dem":456,
    "gn:feature_class":"P",
    "gn:feature_code":"PPL",
    "gn:name":"Ngrabu",
    "gn:population":0,
    "gn:timezone":"Asia/Jakarta",
    "iso:country":"ID",
    "wof:name":"Ngrabu",
    "wof:placetype":"locality"
},
  "geometry": {"coordinates":[110.20556000000001,-7.69444],"type":"Point"}
}