{
  "type": "Feature",
  "properties": {
    "gn:admin1_code":"30",
    "gn:asciiname":"Rancagede",
    "gn:cc2":"ID",
    "gn:country_code":"ID",
    "gn:dem":1488,
    "gn:feature_class":"P",
    "gn:feature_code":"PPL",
    "gn:name":"Rancagede",
    "gn:population":0,
    "gn:timezone":"Asia/Jakarta",
    "iso:country":"ID",
    "name:und_x_variant":[
        "Rantja-gede",
        "Rancagede"
    ],
    "wof:name":"Rancagede",
    "wof:placetype":"locality"
},
  "geometry": {"coordinates":[107.59222,-7.19667],"type":"Point"}
}