{
  "type": "Feature",
  "properties": {
    "gn:admin1_code":"30",
    "gn:asciiname":"Krajan Satu",
    "gn:country_code":"ID",
    "gn:dem":14,
    "gn:feature_class":"P",
    "gn:feature_code":"PPL",
    "gn:name":"Krajan Satu",
    "gn:population":0,
    "gn:timezone":"Asia/Jakarta",
    "iso:country":"ID",
    "name:ind_x_preferred":[
        "Krajan Satu"
    ],
    "name:und_x_variant":[
        "Krajan 1"
    ],
    "wof:name":"Krajan Satu",
    "wof:placetype":"locality"
},
  "geometry": {"coordinates":[107.38722,-6.29028],"type":"Point"}
}