{
  "type": "Feature",
  "properties": {
    "gn:admin1_code":"18",
    "gn:asciiname":"Orakeri",
    "gn:country_code":"ID",
    "gn:dem":664,
    "gn:feature_class":"P",
    "gn:feature_code":"PPL",
    "gn:name":"Orakeri",
    "gn:population":0,
    "gn:timezone":"Asia/Makassar",
    "iso:country":"ID",
    "name:ind_x_preferred":[
        "Orakeri"
    ],
    "wof:name":"Orakeri",
    "wof:placetype":"locality"
},
  "geometry": {"coordinates":[121.44280000000001,-8.7258],"type":"Point"}
}