{
  "type": "Feature",
  "properties": {
    "gn:admin1_code":"8.0",
    "gn:asciiname":"Sumberbuncis",
    "gn:country_code":"ID",
    "gn:dem":438,
    "gn:feature_class":"P",
    "gn:feature_code":"PPLA4",
    "gn:name":"Sumberbuncis",
    "gn:population":0,
    "gn:timezone":"Asia/Jakarta",
    "iso:country":"ID",
    "name:ind_x_preferred":[
        "Sumberbuncis"
    ],
    "name:und_x_variant":[
        "Soemberboentjis"
    ],
    "wof:name":"Sumberbuncis",
    "wof:placetype":"locality"
},
  "geometry": {"coordinates":[112.88249999999999,-8.2703],"type":"Point"}
}