{
  "type": "Feature",
  "properties": {
    "gn:admin1_code":"8.0",
    "gn:asciiname":"Kalilekso",
    "gn:country_code":"ID",
    "gn:dem":694,
    "gn:feature_class":"P",
    "gn:feature_code":"PPL",
    "gn:name":"Kalilekso",
    "gn:population":0,
    "gn:timezone":"Asia/Jakarta",
    "iso:country":"ID",
    "name:ind_x_preferred":[
        "Kalilekso"
    ],
    "wof:name":"Kalilekso",
    "wof:placetype":"locality"
},
  "geometry": {"coordinates":[112.4443,-8.0617],"type":"Point"}
}