{
  "type": "Feature",
  "properties": {
    "gn:admin1_code":"18",
    "gn:asciiname":"Watong",
    "gn:country_code":"ID",
    "gn:dem":573,
    "gn:feature_class":"P",
    "gn:feature_code":"PPL",
    "gn:name":"Watong",
    "gn:population":0,
    "gn:timezone":"Asia/Makassar",
    "iso:country":"ID",
    "name:ind_x_preferred":[
        "Watong"
    ],
    "wof:name":"Watong",
    "wof:placetype":"locality"
},
  "geometry": {"coordinates":[120.8344,-8.5795],"type":"Point"}
}