{
  "type": "Feature",
  "properties": {
    "gn:admin1_code":"8",
    "gn:asciiname":"Krajan Pokaan",
    "gn:country_code":"ID",
    "gn:dem":14,
    "gn:feature_class":"P",
    "gn:feature_code":"PPL",
    "gn:name":"Krajan Pokaan",
    "gn:population":0,
    "gn:timezone":"Asia/Jakarta",
    "iso:country":"ID",
    "name:ind_x_preferred":[
        "Krajan Pokaan"
    ],
    "name:ind_x_variant":[
        "Krajan"
    ],
    "wof:name":"Krajan Pokaan",
    "wof:placetype":"locality"
},
  "geometry": {"coordinates":[114.06359999999999,-7.6684],"type":"Point"}
}