{
  "type": "Feature",
  "properties": {
    "gn:admin1_code":"38",
    "gn:asciiname":"Kani",
    "gn:country_code":"ID",
    "gn:dem":821,
    "gn:feature_class":"P",
    "gn:feature_code":"PPL",
    "gn:name":"Kani",
    "gn:population":0,
    "gn:timezone":"Asia/Makassar",
    "iso:country":"ID",
    "name:aze_x_preferred":[
        "Kani"
    ],
    "name:ceb_x_preferred":[
        "Kani"
    ],
    "name:deu_x_preferred":[
        "Kani"
    ],
    "name:fin_x_preferred":[
        "Kani"
    ],
    "name:fra_x_preferred":[
        "Kani"
    ],
    "name:ind_x_preferred":[
        "Kani"
    ],
    "name:ita_x_preferred":[
        "Kani"
    ],
    "name:jpn_x_preferred":[
        "\u30ab\u30cb"
    ],
    "name:nld_x_preferred":[
        "Kani"
    ],
    "name:swa_x_preferred":[
        "Kani"
    ],
    "name:swe_x_preferred":[
        "Kani"
    ],
    "name:ukr_x_preferred":[
        "\u041a\u0430\u043d\u0456"
    ],
    "wof:lang_x_official":[
        "ind"
    ],
    "wof:lang_x_spoken":[
        "ind",
        "eng"
    ],
    "wof:name":"Kani",
    "wof:placetype":"locality"
},
  "geometry": {"coordinates":[119.8159,-3.0612],"type":"Point"}
}