{
  "type": "Feature",
  "properties": {
    "gn:admin1_code":"7.0",
    "gn:asciiname":"Jrakahsari",
    "gn:country_code":"ID",
    "gn:dem":65,
    "gn:feature_class":"P",
    "gn:feature_code":"PPL",
    "gn:name":"Jrakahsari",
    "gn:population":0,
    "gn:timezone":"Asia/Jakarta",
    "iso:country":"ID",
    "name:ind_x_preferred":[
        "Jrakahsari"
    ],
    "wof:name":"Jrakahsari",
    "wof:placetype":"locality"
},
  "geometry": {"coordinates":[110.7349,-6.543],"type":"Point"}
}