{
  "type": "Feature",
  "properties": {
    "gn:admin1_code":"18.0",
    "gn:asciiname":"Bodo",
    "gn:country_code":"ID",
    "gn:dem":15,
    "gn:feature_class":"P",
    "gn:feature_code":"PPL",
    "gn:name":"Bodo",
    "gn:population":0,
    "gn:timezone":"Asia/Makassar",
    "iso:country":"ID",
    "name:bih_x_preferred":[
        "\u092c\u094b\u0921\u093c\u094b \u092d\u093e\u0937\u093e"
    ],
    "name:ceb_x_preferred":[
        "Bodo"
    ],
    "name:ces_x_preferred":[
        "Bodo"
    ],
    "name:deu_x_preferred":[
        "Bodo"
    ],
    "name:fin_x_preferred":[
        "Bodo"
    ],
    "name:fra_x_preferred":[
        "Bodo"
    ],
    "name:heb_x_preferred":[
        "\u05d1\u05d5\u05d3\u05d5"
    ],
    "name:hin_x_preferred":[
        "\u092c\u094b\u0921\u094b"
    ],
    "name:ind_x_preferred":[
        "Bodo"
    ],
    "name:ita_x_preferred":[
        "Bodo"
    ],
    "name:nds_x_preferred":[
        "Bodo"
    ],
    "name:nld_x_preferred":[
        "Bodo"
    ],
    "name:pol_x_preferred":[
        "Bodo"
    ],
    "name:por_x_preferred":[
        "Bodo"
    ],
    "name:ron_x_preferred":[
        "Bodo"
    ],
    "name:rus_x_preferred":[
        "\u0411\u043e\u0434\u043e"
    ],
    "name:swe_x_preferred":[
        "Bodo"
    ],
    "name:ukr_x_preferred":[
        "\u0411\u043e\u0434\u043e"
    ],
    "name:und_x_variant":[
        "Kota Boddo"
    ],
    "wof:name":"Bodo",
    "wof:placetype":"locality"
},
  "geometry": {"coordinates":[121.82559999999999,-10.5048],"type":"Point"}
}