{
  "type": "Feature",
  "properties": {
    "gn:admin1_code":"2",
    "gn:asciiname":"Banjar Branjingan",
    "gn:country_code":"ID",
    "gn:dem":80,
    "gn:feature_class":"P",
    "gn:feature_code":"PPL",
    "gn:name":"Banjar Branjingan",
    "gn:population":0,
    "gn:timezone":"Asia/Makassar",
    "iso:country":"ID",
    "name:ind_x_preferred":[
        "Banjar Branjingan"
    ],
    "wof:name":"Banjar Branjingan",
    "wof:placetype":"locality"
},
  "geometry": {"coordinates":[115.0389,-8.5275],"type":"Point"}
}