{
  "type": "Feature",
  "properties": {
    "gn:admin1_code":"8.0",
    "gn:asciiname":"Dileman",
    "gn:country_code":"ID",
    "gn:dem":670,
    "gn:feature_class":"P",
    "gn:feature_code":"PPL",
    "gn:name":"Dileman",
    "gn:population":0,
    "gn:timezone":"Asia/Jakarta",
    "iso:country":"ID",
    "name:ind_x_preferred":[
        "Dileman"
    ],
    "wof:name":"Dileman",
    "wof:placetype":"locality"
},
  "geometry": {"coordinates":[111.87269999999999,-7.8948],"type":"Point"}
}