{
  "type": "Feature",
  "properties": {
    "gn:admin1_code":"08",
    "gn:asciiname":"Modong Satu",
    "gn:country_code":"ID",
    "gn:dem":10,
    "gn:feature_class":"P",
    "gn:feature_code":"PPL",
    "gn:name":"Modong Satu",
    "gn:population":0,
    "gn:timezone":"Asia/Jakarta",
    "iso:country":"ID",
    "name:ind_x_preferred":[
        "Modong Satu"
    ],
    "name:und_x_variant":[
        "Dojonggrinting",
        "Doyonggrinting"
    ],
    "wof:lang_x_official":[
        "ind"
    ],
    "wof:lang_x_spoken":[
        "ind",
        "eng"
    ],
    "wof:name":"Modong Satu",
    "wof:placetype":"locality"
},
  "geometry": {"coordinates":[112.65000000000001,-7.4626],"type":"Point"}
}