{
  "type": "Feature",
  "properties": {
    "gn:admin1_code":"8.0",
    "gn:asciiname":"Congaban",
    "gn:country_code":"ID",
    "gn:dem":44,
    "gn:feature_class":"P",
    "gn:feature_code":"PPL",
    "gn:name":"Congaban",
    "gn:population":0,
    "gn:timezone":"Asia/Jakarta",
    "iso:country":"ID",
    "name:ind_x_preferred":[
        "Congaban"
    ],
    "wof:name":"Congaban",
    "wof:placetype":"locality"
},
  "geometry": {"coordinates":[113.015,-7.135],"type":"Point"}
}