{
  "type": "Feature",
  "properties": {
    "gn:admin1_code":"2.0",
    "gn:asciiname":"Salang",
    "gn:country_code":"ID",
    "gn:dem":474,
    "gn:feature_class":"P",
    "gn:feature_code":"PPL",
    "gn:name":"Salang",
    "gn:population":0,
    "gn:timezone":"Asia/Makassar",
    "iso:country":"ID",
    "name:cat_x_preferred":[
        "Salang"
    ],
    "name:ceb_x_preferred":[
        "Salang"
    ],
    "name:ind_x_preferred":[
        "Salang"
    ],
    "name:new_x_preferred":[
        "\u0938\u0932\u093e\u0919"
    ],
    "name:swe_x_preferred":[
        "Salang"
    ],
    "wof:lang_x_official":[
        "ind"
    ],
    "wof:lang_x_spoken":[
        "ind",
        "eng"
    ],
    "wof:name":"Salang",
    "wof:placetype":"locality"
},
  "geometry": {"coordinates":[115.54770000000001,-8.738],"type":"Point"}
}