{
  "type": "Feature",
  "properties": {
    "gn:admin1_code":"30",
    "gn:asciiname":"Cukanggenteng",
    "gn:country_code":"ID",
    "gn:dem":934,
    "gn:feature_class":"P",
    "gn:feature_code":"PPL",
    "gn:name":"Cukanggenteng",
    "gn:population":0,
    "gn:timezone":"Asia/Jakarta",
    "iso:country":"ID",
    "name:ind_x_preferred":[
        "Cukanggenteng"
    ],
    "name:und_x_variant":[
        "Tjukanggenteng 2",
        "Cukanggenteng Dua"
    ],
    "wof:lang_x_official":[
        "ind"
    ],
    "wof:lang_x_spoken":[
        "ind",
        "eng"
    ],
    "wof:name":"Cukanggenteng",
    "wof:placetype":"locality"
},
  "geometry": {"coordinates":[107.49299999999999,-7.0658],"type":"Point"}
}