{
  "type": "Feature",
  "properties": {
    "gn:admin1_code":"31.0",
    "gn:asciiname":"Haas",
    "gn:country_code":"ID",
    "gn:dem":31,
    "gn:feature_class":"P",
    "gn:feature_code":"PPL",
    "gn:name":"Haas",
    "gn:population":0,
    "gn:timezone":"Asia/Makassar",
    "iso:country":"ID",
    "name:eng_x_preferred":[
        "Haas"
    ],
    "name:ind_x_preferred":[
        "Haasi"
    ],
    "name:und_x_variant":[
        "Ha\u00e4s"
    ],
    "wof:name":"Haas",
    "wof:placetype":"locality"
},
  "geometry": {"coordinates":[125.41911,2.32036],"type":"Point"}
}