{
  "type": "Feature",
  "properties": {
    "gn:admin1_code":"1",
    "gn:asciiname":"Dollu",
    "gn:country_code":"ID",
    "gn:dem":15,
    "gn:feature_class":"P",
    "gn:feature_code":"PPL",
    "gn:name":"Dollu",
    "gn:population":0,
    "gn:timezone":"Asia/Jakarta",
    "iso:country":"ID",
    "name:aze_x_preferred":[
        "Dollu"
    ],
    "name:ind_x_preferred":[
        "Dollu"
    ],
    "wof:name":"Dollu",
    "wof:placetype":"locality"
},
  "geometry": {"coordinates":[95.9692,2.601],"type":"Point"}
}