{
  "type": "Feature",
  "properties": {
    "gn:admin1_code":"18.0",
    "gn:asciiname":"Takai",
    "gn:country_code":"ID",
    "gn:dem":135,
    "gn:feature_class":"P",
    "gn:feature_code":"PPL",
    "gn:name":"Takai",
    "gn:population":0,
    "gn:timezone":"Asia/Makassar",
    "iso:country":"ID",
    "name:ceb_x_preferred":[
        "Takai"
    ],
    "name:fra_x_preferred":[
        "Takai"
    ],
    "name:hau_x_preferred":[
        "Takai"
    ],
    "name:ind_x_preferred":[
        "Takai"
    ],
    "name:ita_x_preferred":[
        "Takai"
    ],
    "name:spa_x_preferred":[
        "Takai"
    ],
    "wof:name":"Takai",
    "wof:placetype":"locality"
},
  "geometry": {"coordinates":[123.0429,-10.7787],"type":"Point"}
}