{
  "type": "Feature",
  "properties": {
    "gn:admin1_code":"01",
    "gn:admin2_code":"1117",
    "gn:admin3_code":"8572026.0",
    "gn:asciiname":"Buntul Kemumu",
    "gn:country_code":"ID",
    "gn:dem":1560,
    "gn:feature_class":"P",
    "gn:feature_code":"PPL",
    "gn:name":"Buntul Kemumu",
    "gn:population":0,
    "gn:timezone":"Asia/Jakarta",
    "iso:country":"ID",
    "wof:lang_x_official":[
        "ind"
    ],
    "wof:lang_x_spoken":[
        "ind",
        "eng"
    ],
    "wof:name":"Buntul Kemumu",
    "wof:placetype":"locality"
},
  "geometry": {"coordinates":[96.91373,4.82113],"type":"Point"}
}