{
  "type": "Feature",
  "properties": {
    "gn:admin1_code":"37",
    "gn:asciiname":"Pasir",
    "gn:country_code":"ID",
    "gn:dem":12,
    "gn:feature_class":"P",
    "gn:feature_code":"PPLA4",
    "gn:name":"Pasir",
    "gn:population":0,
    "gn:timezone":"Asia/Jakarta",
    "iso:country":"ID",
    "name:ind_x_preferred":[
        "Pasir"
    ],
    "wof:name":"Pasir",
    "wof:placetype":"locality"
},
  "geometry": {"coordinates":[100.80747,2.13994],"type":"Point"}
}