{
  "type": "Feature",
  "properties": {
    "gn:admin1_code":"7",
    "gn:asciiname":"Ketilang",
    "gn:country_code":"ID",
    "gn:dem":14,
    "gn:feature_class":"P",
    "gn:feature_code":"PPL",
    "gn:name":"Ketilang",
    "gn:population":0,
    "gn:timezone":"Asia/Jakarta",
    "iso:country":"ID",
    "name:ind_x_preferred":[
        "Ketilang"
    ],
    "wof:name":"Ketilang",
    "wof:placetype":"locality"
},
  "geometry": {"coordinates":[109.0966,-6.9143],"type":"Point"}
}