{
  "type": "Feature",
  "properties": {
    "gn:admin1_code":"30",
    "gn:asciiname":"Pakemitan Kaler",
    "gn:country_code":"ID",
    "gn:dem":339,
    "gn:feature_class":"P",
    "gn:feature_code":"PPL",
    "gn:name":"Pakemitan Kaler",
    "gn:population":0,
    "gn:timezone":"Asia/Jakarta",
    "iso:country":"ID",
    "name:ind_x_preferred":[
        "Pakemitan Kaler"
    ],
    "wof:name":"Pakemitan Kaler",
    "wof:placetype":"locality"
},
  "geometry": {"coordinates":[107.35083,-6.83139],"type":"Point"}
}