{
  "type": "Feature",
  "properties": {
    "gn:admin1_code":"1",
    "gn:asciiname":"Bies",
    "gn:country_code":"ID",
    "gn:dem":1205,
    "gn:feature_class":"P",
    "gn:feature_code":"PPL",
    "gn:name":"Bies",
    "gn:population":0,
    "gn:timezone":"Asia/Jakarta",
    "iso:country":"ID",
    "name:afr_x_preferred":[
        "Bjes"
    ],
    "name:ces_x_preferred":[
        "B\u011bs"
    ],
    "name:epo_x_preferred":[
        "Bjeso"
    ],
    "name:ind_x_preferred":[
        "Bies"
    ],
    "name:mkd_x_preferred":[
        "\u0411\u0435\u0441"
    ],
    "name:pol_x_preferred":[
        "Bies"
    ],
    "name:por_x_preferred":[
        "Bies"
    ],
    "name:rus_x_preferred":[
        "\u0411\u0435\u0441"
    ],
    "name:srp_x_preferred":[
        "\u0411\u0435\u0441"
    ],
    "name:ukr_x_preferred":[
        "\u0411\u0456\u0441"
    ],
    "wof:lang_x_official":[
        "ind"
    ],
    "wof:lang_x_spoken":[
        "ind",
        "eng"
    ],
    "wof:name":"Bies",
    "wof:placetype":"locality"
},
  "geometry": {"coordinates":[96.7599,4.6028],"type":"Point"}
}