{
  "type": "Feature",
  "properties": {
    "gn:admin1_code":"0.0",
    "gn:asciiname":"Marinjahan",
    "gn:cc2":"ID",
    "gn:country_code":"ID",
    "gn:dem":33,
    "gn:feature_class":"P",
    "gn:feature_code":"PPL",
    "gn:name":"Marinjahan",
    "gn:population":0,
    "gn:timezone":"Asia/Pontianak",
    "iso:country":"ID",
    "name:und_x_variant":[
        "Marindjahan",
        "Marinjahan"
    ],
    "wof:name":"Marinjahan",
    "wof:placetype":"locality"
},
  "geometry": {"coordinates":[111.36667,-2.61667],"type":"Point"}
}