{
  "type": "Feature",
  "properties": {
    "gn:admin1_code":"15.0",
    "gn:asciiname":"Batubedil",
    "gn:country_code":"ID",
    "gn:dem":393,
    "gn:feature_class":"P",
    "gn:feature_code":"PPL",
    "gn:name":"Batubedil",
    "gn:population":0,
    "gn:timezone":"Asia/Jakarta",
    "iso:country":"ID",
    "name:ind_x_preferred":[
        "Batubedil"
    ],
    "wof:name":"Batubedil",
    "wof:placetype":"locality"
},
  "geometry": {"coordinates":[104.68241,-5.30211],"type":"Point"}
}