{
  "type": "Feature",
  "properties": {
    "gn:admin1_code":"8.0",
    "gn:asciiname":"Darma",
    "gn:country_code":"ID",
    "gn:dem":22,
    "gn:feature_class":"P",
    "gn:feature_code":"PPL",
    "gn:name":"Darma",
    "gn:population":0,
    "gn:timezone":"Asia/Jakarta",
    "iso:country":"ID",
    "name:ceb_x_preferred":[
        "Darma"
    ],
    "name:ind_x_preferred":[
        "Darma"
    ],
    "name:nld_x_preferred":[
        "Darma"
    ],
    "name:swe_x_preferred":[
        "Darma"
    ],
    "wof:lang_x_official":[
        "ind"
    ],
    "wof:lang_x_spoken":[
        "ind",
        "eng"
    ],
    "wof:name":"Darma",
    "wof:placetype":"locality"
},
  "geometry": {"coordinates":[113.55092999999999,-7.13934],"type":"Point"}
}