{
  "type": "Feature",
  "properties": {
    "gn:admin1_code":"38.0",
    "gn:asciiname":"Panyula",
    "gn:country_code":"ID",
    "gn:dem":201,
    "gn:feature_class":"P",
    "gn:feature_code":"PPL",
    "gn:name":"Panyula",
    "gn:population":0,
    "gn:timezone":"Asia/Makassar",
    "iso:country":"ID",
    "name:ind_x_preferred":[
        "Panyula"
    ],
    "wof:name":"Panyula",
    "wof:placetype":"locality"
},
  "geometry": {"coordinates":[120.16419999999999,-4.5936],"type":"Point"}
}