{
  "type": "Feature",
  "properties": {
    "gn:admin1_code":"36.0",
    "gn:asciiname":"Yapero",
    "gn:cc2":"ID",
    "gn:country_code":"ID",
    "gn:dem":17,
    "gn:feature_class":"P",
    "gn:feature_code":"PPL",
    "gn:name":"Yapero",
    "gn:population":0,
    "gn:timezone":"Asia/Jayapura",
    "iso:country":"ID",
    "name:und_x_variant":[
        "Japero",
        "Yapero"
    ],
    "wof:lang_x_official":[
        "ind"
    ],
    "wof:lang_x_spoken":[
        "ind",
        "eng"
    ],
    "wof:name":"Yapero",
    "wof:placetype":"locality"
},
  "geometry": {"coordinates":[137.18333000000001,-4.98333],"type":"Point"}
}