{
  "type": "Feature",
  "properties": {
    "gn:admin1_code":"7.0",
    "gn:asciiname":"Bojongkucing",
    "gn:country_code":"ID",
    "gn:dem":47,
    "gn:feature_class":"P",
    "gn:feature_code":"PPL",
    "gn:name":"Bojongkucing",
    "gn:population":0,
    "gn:timezone":"Asia/Jakarta",
    "iso:country":"ID",
    "name:ind_x_preferred":[
        "Bojongkucing"
    ],
    "name:und_x_variant":[
        "Bodjongkantjing"
    ],
    "wof:lang_x_official":[
        "ind"
    ],
    "wof:lang_x_spoken":[
        "ind",
        "eng"
    ],
    "wof:name":"Bojongkucing",
    "wof:placetype":"locality"
},
  "geometry": {"coordinates":[108.5659,-7.2991],"type":"Point"}
}