{
  "type": "Feature",
  "properties": {
    "gn:admin1_code":"30.0",
    "gn:asciiname":"Awilega",
    "gn:country_code":"ID",
    "gn:dem":368,
    "gn:feature_class":"P",
    "gn:feature_code":"PPLA4",
    "gn:name":"Awilega",
    "gn:population":0,
    "gn:timezone":"Asia/Jakarta",
    "iso:country":"ID",
    "name:ind_x_preferred":[
        "Awilega"
    ],
    "wof:name":"Awilega",
    "wof:placetype":"locality"
},
  "geometry": {"coordinates":[108.2093,-7.3924],"type":"Point"}
}