{
  "type": "Feature",
  "properties": {
    "gn:admin1_code":"8",
    "gn:asciiname":"Pancoran",
    "gn:country_code":"ID",
    "gn:dem":378,
    "gn:feature_class":"P",
    "gn:feature_code":"PPL",
    "gn:name":"Pancoran",
    "gn:population":0,
    "gn:timezone":"Asia/Jakarta",
    "iso:country":"ID",
    "name:ind_x_preferred":[
        "Pancoran"
    ],
    "wof:name":"Pancoran",
    "wof:placetype":"locality"
},
  "geometry": {"coordinates":[113.8539,-8.0693],"type":"Point"}
}