{
  "type": "Feature",
  "properties": {
    "gn:admin1_code":"8",
    "gn:asciiname":"Alang-alang",
    "gn:country_code":"ID",
    "gn:dem":396,
    "gn:feature_class":"P",
    "gn:feature_code":"PPL",
    "gn:name":"Alang-alang",
    "gn:population":0,
    "gn:timezone":"Asia/Jakarta",
    "iso:country":"ID",
    "name:ind_x_preferred":[
        "Alang-alang"
    ],
    "name:nld_x_preferred":[
        "Alang Alang"
    ],
    "wof:name":"Alang-alang",
    "wof:placetype":"locality"
},
  "geometry": {"coordinates":[113.7244,-7.8251],"type":"Point"}
}