{
  "type": "Feature",
  "properties": {
    "gn:admin1_code":"30.0",
    "gn:asciiname":"Ciguyur",
    "gn:country_code":"ID",
    "gn:dem":23,
    "gn:feature_class":"P",
    "gn:feature_code":"PPL",
    "gn:name":"Ciguyur",
    "gn:population":0,
    "gn:timezone":"Asia/Jakarta",
    "iso:country":"ID",
    "name:ind_x_preferred":[
        "Ciguyur"
    ],
    "wof:name":"Ciguyur",
    "wof:placetype":"locality"
},
  "geometry": {"coordinates":[106.8373,-7.424],"type":"Point"}
}