{
  "type": "Feature",
  "properties": {
    "gn:admin1_code":"8.0",
    "gn:asciiname":"Panangcangka",
    "gn:country_code":"ID",
    "gn:dem":76,
    "gn:feature_class":"P",
    "gn:feature_code":"PPL",
    "gn:name":"Panangcangka",
    "gn:population":0,
    "gn:timezone":"Asia/Jakarta",
    "iso:country":"ID",
    "name:ind_x_preferred":[
        "Panangcangka"
    ],
    "wof:name":"Panangcangka",
    "wof:placetype":"locality"
},
  "geometry": {"coordinates":[113.946,-6.9551],"type":"Point"}
}