{
  "type": "Feature",
  "properties": {
    "gn:country":"ID",
    "gn:fcode":"ADM3",
    "gn:pop":0,
    "iso:country":"ID",
    "name:eng_x_preferred":[
        "Alas District"
    ],
    "name:ind_x_preferred":[
        "Kecamatan Alas"
    ],
    "qs:name":"Kecamatan Alas",
    "qs:photos_9r":0,
    "qs:photos_sr":0,
    "qs:pop_sr":"0",
    "wof:lang_x_official":[
        "ind"
    ],
    "wof:lang_x_spoken":[
        "ind",
        "eng"
    ],
    "wof:name":"Kecamatan Alas",
    "wof:placetype":"localadmin",
    "wof:population":0
},
  "geometry": {"coordinates":[117.05329999999999,-8.5493],"type":"Point"}
}