{
  "type": "Feature",
  "properties": {
    "gn:admin1_code":"30",
    "gn:asciiname":"Kesesih",
    "gn:country_code":"ID",
    "gn:dem":10,
    "gn:feature_class":"P",
    "gn:feature_code":"PPL",
    "gn:name":"Kesesih",
    "gn:population":0,
    "gn:timezone":"Asia/Jakarta",
    "iso:country":"ID",
    "name:ind_x_preferred":[
        "Kesesih"
    ],
    "wof:name":"Kesesih",
    "wof:placetype":"locality"
},
  "geometry": {"coordinates":[108.27778000000001,-6.45333],"type":"Point"}
}