{
  "type": "Feature",
  "properties": {
    "gn:admin1_code":"8",
    "gn:asciiname":"Nglogok",
    "gn:country_code":"ID",
    "gn:dem":523,
    "gn:feature_class":"P",
    "gn:feature_code":"PPL",
    "gn:name":"Nglogok",
    "gn:population":0,
    "gn:timezone":"Asia/Jakarta",
    "iso:country":"ID",
    "name:ind_x_preferred":[
        "Nglogok"
    ],
    "wof:name":"Nglogok",
    "wof:placetype":"locality"
},
  "geometry": {"coordinates":[111.21444,-8.01083],"type":"Point"}
}