{
  "type": "Feature",
  "properties": {
    "gn:admin1_code":"30.0",
    "gn:asciiname":"Cukanguncal",
    "gn:country_code":"ID",
    "gn:dem":510,
    "gn:feature_class":"P",
    "gn:feature_code":"PPLA4",
    "gn:name":"Cukanguncal",
    "gn:population":0,
    "gn:timezone":"Asia/Jakarta",
    "iso:country":"ID",
    "name:ind_x_preferred":[
        "Cukanguncal"
    ],
    "name:und_x_variant":[
        "Tjoekangoentjal"
    ],
    "wof:name":"Cukanguncal",
    "wof:placetype":"locality"
},
  "geometry": {"coordinates":[108.3155,-7.256],"type":"Point"}
}