{
  "type": "Feature",
  "properties": {
    "gn:admin1_code":"7",
    "gn:asciiname":"Sedrong Kidul",
    "gn:country_code":"ID",
    "gn:dem":92,
    "gn:feature_class":"P",
    "gn:feature_code":"PPL",
    "gn:name":"Sedrong Kidul",
    "gn:population":0,
    "gn:timezone":"Asia/Jakarta",
    "iso:country":"ID",
    "name:ind_x_preferred":[
        "Sedrong Kidul"
    ],
    "wof:name":"Sedrong Kidul",
    "wof:placetype":"locality"
},
  "geometry": {"coordinates":[110.7741,-6.6996],"type":"Point"}
}