{
  "type": "Feature",
  "properties": {
    "gn:admin1_code":"15.0",
    "gn:asciiname":"Oganjaya",
    "gn:country_code":"ID",
    "gn:dem":369,
    "gn:feature_class":"P",
    "gn:feature_code":"PPL",
    "gn:name":"Oganjaya",
    "gn:population":0,
    "gn:timezone":"Asia/Jakarta",
    "iso:country":"ID",
    "name:ind_x_preferred":[
        "Oganjaya"
    ],
    "wof:name":"Oganjaya",
    "wof:placetype":"locality"
},
  "geometry": {"coordinates":[104.42641999999999,-4.76718],"type":"Point"}
}