{
  "type": "Feature",
  "properties": {
    "gn:admin1_code":"38",
    "gn:asciiname":"Tambaksari",
    "gn:country_code":"ID",
    "gn:dem":50,
    "gn:feature_class":"P",
    "gn:feature_code":"PPL",
    "gn:name":"Tambaksari",
    "gn:population":0,
    "gn:timezone":"Asia/Makassar",
    "iso:country":"ID",
    "name:ind_x_preferred":[
        "Tambaksari"
    ],
    "name:jav_x_preferred":[
        "Tambaksari"
    ],
    "name:por_x_preferred":[
        "Tambaksari"
    ],
    "wof:name":"Tambaksari",
    "wof:placetype":"locality"
},
  "geometry": {"coordinates":[120.3801,-2.552],"type":"Point"}
}