{
  "type": "Feature",
  "properties": {
    "gn:admin1_code":"37.0",
    "gn:asciiname":"Kuat",
    "gn:country_code":"ID",
    "gn:dem":-9999,
    "gn:feature_class":"P",
    "gn:feature_code":"PPL",
    "gn:name":"Kuat",
    "gn:population":0,
    "gn:timezone":"Asia/Jakarta",
    "iso:country":"ID",
    "name:und_x_variant":[
        "Koeat",
        "Kuat"
    ],
    "wof:name":"Kuat",
    "wof:placetype":"locality"
},
  "geometry": {"coordinates":[102.23333,1.11667],"type":"Point"}
}