{
  "type": "Feature",
  "properties": {
    "gn:admin1_code":"21.0",
    "gn:asciiname":"Tiu",
    "gn:country_code":"ID",
    "gn:dem":22,
    "gn:feature_class":"P",
    "gn:feature_code":"PPL",
    "gn:name":"Tiu",
    "gn:population":0,
    "gn:timezone":"Asia/Makassar",
    "iso:country":"ID",
    "name:afr_x_preferred":[
        "Tiu"
    ],
    "name:deu_x_preferred":[
        "Tiu"
    ],
    "name:fas_x_preferred":[
        "\u062a\u06cc\u0648"
    ],
    "name:fin_x_preferred":[
        "Tiu"
    ],
    "name:ind_x_preferred":[
        "Tiu"
    ],
    "name:rus_x_preferred":[
        "\u0422\u0438\u0443"
    ],
    "wof:lang_x_official":[
        "ind"
    ],
    "wof:lang_x_spoken":[
        "ind",
        "eng"
    ],
    "wof:name":"Tiu",
    "wof:placetype":"locality"
},
  "geometry": {"coordinates":[121.2954,-2.0125],"type":"Point"}
}