{
  "type": "Feature",
  "properties": {
    "gn:admin1_code":"34.0",
    "gn:asciiname":"Potiwunduwa",
    "gn:country_code":"ID",
    "gn:dem":27,
    "gn:feature_class":"P",
    "gn:feature_code":"PPL",
    "gn:name":"Potiwunduwa",
    "gn:population":0,
    "gn:timezone":"Asia/Makassar",
    "iso:country":"ID",
    "name:ind_x_preferred":[
        "Potiwunduwa"
    ],
    "wof:name":"Potiwunduwa",
    "wof:placetype":"locality"
},
  "geometry": {"coordinates":[123.1476,0.5348],"type":"Point"}
}