{
  "type": "Feature",
  "properties": {
    "gn:admin1_code":"30",
    "gn:asciiname":"Kranggan-kulon Tiga",
    "gn:cc2":"ID",
    "gn:country_code":"ID",
    "gn:dem":57,
    "gn:feature_class":"P",
    "gn:feature_code":"PPL",
    "gn:name":"Kranggan-kulon Tiga",
    "gn:population":0,
    "gn:timezone":"Asia/Jakarta",
    "iso:country":"ID",
    "name:und_x_variant":[
        "Kranggan-kulon 3",
        "Kranggan-kulon Tiga"
    ],
    "wof:lang_x_official":[
        "ind"
    ],
    "wof:lang_x_spoken":[
        "ind",
        "eng"
    ],
    "wof:name":"Kranggan-kulon Tiga",
    "wof:placetype":"locality"
},
  "geometry": {"coordinates":[106.91943999999999,-6.34472],"type":"Point"}
}