{
  "type": "Feature",
  "properties": {
    "gn:admin1_code":"30",
    "gn:asciiname":"Cipayung",
    "gn:country_code":"ID",
    "gn:dem":85,
    "gn:feature_class":"P",
    "gn:feature_code":"PPL",
    "gn:name":"Cipayung",
    "gn:population":0,
    "gn:timezone":"Asia/Jakarta",
    "iso:country":"ID",
    "name:ceb_x_preferred":[
        "Kecamatan Cipayung"
    ],
    "name:ind_x_preferred":[
        "Cipayung"
    ],
    "name:ita_x_preferred":[
        "Cipayung"
    ],
    "name:jav_x_preferred":[
        "Cipayung"
    ],
    "name:nld_x_preferred":[
        "Cipayung"
    ],
    "name:pol_x_preferred":[
        "Cipayung"
    ],
    "name:sun_x_preferred":[
        "Cipayung"
    ],
    "name:swe_x_preferred":[
        "Kecamatan Cipayung"
    ],
    "wof:lang_x_official":[
        "ind"
    ],
    "wof:lang_x_spoken":[
        "ind",
        "eng"
    ],
    "wof:name":"Cipayung",
    "wof:placetype":"locality"
},
  "geometry": {"coordinates":[106.84721999999999,-6.39167],"type":"Point"}
}