{
  "type": "Feature",
  "properties": {
    "gn:admin1_code":"8",
    "gn:asciiname":"Kedunggelonggong",
    "gn:country_code":"ID",
    "gn:dem":22,
    "gn:feature_class":"P",
    "gn:feature_code":"PPL",
    "gn:name":"Kedunggelonggong",
    "gn:population":0,
    "gn:timezone":"Asia/Jakarta",
    "iso:country":"ID",
    "name:ind_x_preferred":[
        "Kedunggelonggong"
    ],
    "wof:name":"Kedunggelonggong",
    "wof:placetype":"locality"
},
  "geometry": {"coordinates":[112.324,-7.1707],"type":"Point"}
}