{
  "type": "Feature",
  "properties": {
    "gn:admin1_code":"08",
    "gn:asciiname":"Dadaptulis",
    "gn:country_code":"ID",
    "gn:dem":636,
    "gn:feature_class":"P",
    "gn:feature_code":"PPL",
    "gn:name":"Dadaptulis",
    "gn:population":0,
    "gn:timezone":"Asia/Jakarta",
    "iso:country":"ID",
    "wof:name":"Dadaptulis",
    "wof:placetype":"locality"
},
  "geometry": {"coordinates":[112.57056,-7.90417],"type":"Point"}
}