{
  "type": "Feature",
  "properties": {
    "gn:admin1_code":"31.0",
    "gn:asciiname":"Eris",
    "gn:country_code":"ID",
    "gn:dem":685,
    "gn:feature_class":"P",
    "gn:feature_code":"PPL",
    "gn:name":"Eris",
    "gn:population":0,
    "gn:timezone":"Asia/Makassar",
    "iso:country":"ID",
    "name:ast_x_preferred":[
        "Eris"
    ],
    "name:bre_x_preferred":[
        "Eris"
    ],
    "name:cat_x_preferred":[
        "Eris"
    ],
    "name:ceb_x_preferred":[
        "Eris"
    ],
    "name:ces_x_preferred":[
        "Eris"
    ],
    "name:cym_x_preferred":[
        "Eris"
    ],
    "name:dan_x_preferred":[
        "Eris"
    ],
    "name:deu_x_preferred":[
        "Eris"
    ],
    "name:eus_x_preferred":[
        "Eris"
    ],
    "name:fas_x_preferred":[
        "\u0627\u0631\u06cc\u0633"
    ],
    "name:fra_x_preferred":[
        "\u00c9ris"
    ],
    "name:glg_x_preferred":[
        "Eris"
    ],
    "name:heb_x_preferred":[
        "\u05d0\u05e8\u05d9\u05e1"
    ],
    "name:hrv_x_preferred":[
        "Eris"
    ],
    "name:ind_x_preferred":[
        "Eris"
    ],
    "name:isl_x_preferred":[
        "Eris"
    ],
    "name:ita_x_preferred":[
        "Eris"
    ],
    "name:jpn_x_preferred":[
        "\u30a8\u30ea\u30b9"
    ],
    "name:kat_x_preferred":[
        "\u10d4\u10e0\u10d8\u10e1\u10d8"
    ],
    "name:kor_x_preferred":[
        "\uc5d0\ub9ac\uc2a4"
    ],
    "name:lat_x_preferred":[
        "Eris"
    ],
    "name:lav_x_preferred":[
        "Er\u012bda"
    ],
    "name:msa_x_preferred":[
        "Eris"
    ],
    "name:nds_x_preferred":[
        "Eris"
    ],
    "name:nld_x_preferred":[
        "Eris"
    ],
    "name:nor_x_preferred":[
        "Eris"
    ],
    "name:pol_x_preferred":[
        "Eris"
    ],
    "name:ron_x_preferred":[
        "Eris"
    ],
    "name:rus_x_preferred":[
        "\u042d\u0440\u0438\u0434\u0430"
    ],
    "name:sco_x_preferred":[
        "Eris"
    ],
    "name:slv_x_preferred":[
        "Eris"
    ],
    "name:spa_x_preferred":[
        "Eris"
    ],
    "name:swe_x_preferred":[
        "Eris"
    ],
    "name:tur_x_preferred":[
        "Eris"
    ],
    "name:vie_x_preferred":[
        "Eris"
    ],
    "wof:lang_x_official":[
        "ind"
    ],
    "wof:lang_x_spoken":[
        "ind",
        "eng"
    ],
    "wof:name":"Eris",
    "wof:placetype":"locality"
},
  "geometry": {"coordinates":[124.9144,1.2281],"type":"Point"}
}