{
  "type": "Feature",
  "properties": {
    "gn:admin1_code":"18.0",
    "gn:asciiname":"Tasowang",
    "gn:country_code":"ID",
    "gn:dem":441,
    "gn:feature_class":"P",
    "gn:feature_code":"PPL",
    "gn:name":"Tasowang",
    "gn:population":0,
    "gn:timezone":"Asia/Makassar",
    "iso:country":"ID",
    "name:ind_x_preferred":[
        "Tasowang"
    ],
    "wof:name":"Tasowang",
    "wof:placetype":"locality"
},
  "geometry": {"coordinates":[119.4336,-9.6553],"type":"Point"}
}