{
  "type": "Feature",
  "properties": {
    "gn:admin1_code":"8",
    "gn:asciiname":"Glugur",
    "gn:country_code":"ID",
    "gn:dem":41,
    "gn:feature_class":"P",
    "gn:feature_code":"PPL",
    "gn:name":"Glugur",
    "gn:population":0,
    "gn:timezone":"Asia/Jakarta",
    "iso:country":"ID",
    "name:ind_x_preferred":[
        "Glugur"
    ],
    "wof:name":"Glugur",
    "wof:placetype":"locality"
},
  "geometry": {"coordinates":[112.813,-7.0252],"type":"Point"}
}