{
  "type": "Feature",
  "properties": {
    "gn:admin1_code":"1",
    "gn:asciiname":"Blangmerandeh",
    "gn:country_code":"ID",
    "gn:dem":549,
    "gn:feature_class":"P",
    "gn:feature_code":"PPL",
    "gn:name":"Blangmerandeh",
    "gn:population":0,
    "gn:timezone":"Asia/Jakarta",
    "iso:country":"ID",
    "name:ind_x_preferred":[
        "Blangmerandeh"
    ],
    "name:und_x_variant":[
        "Meurandeh"
    ],
    "wof:name":"Blangmerandeh",
    "wof:placetype":"locality"
},
  "geometry": {"coordinates":[96.5196,4.4582],"type":"Point"}
}