{
  "type": "Feature",
  "properties": {
    "gn:admin1_code":"26",
    "gn:asciiname":"Hutabaru",
    "gn:country_code":"ID",
    "gn:dem":80,
    "gn:feature_class":"P",
    "gn:feature_code":"PPL",
    "gn:name":"Hutabaru",
    "gn:population":0,
    "gn:timezone":"Asia/Jakarta",
    "iso:country":"ID",
    "name:ind_x_preferred":[
        "Hutabaru"
    ],
    "wof:name":"Hutabaru",
    "wof:placetype":"locality"
},
  "geometry": {"coordinates":[99.66361999999999,1.42483],"type":"Point"}
}