{
  "type": "Feature",
  "properties": {
    "gn:admin1_code":"8",
    "gn:asciiname":"Panji Tengah",
    "gn:country_code":"ID",
    "gn:dem":27,
    "gn:feature_class":"P",
    "gn:feature_code":"PPL",
    "gn:name":"Panji Tengah",
    "gn:population":0,
    "gn:timezone":"Asia/Jakarta",
    "iso:country":"ID",
    "name:ind_x_preferred":[
        "Panji Tengah"
    ],
    "wof:name":"Panji Tengah",
    "wof:placetype":"locality"
},
  "geometry": {"coordinates":[114.04510000000001,-7.7041],"type":"Point"}
}