{
  "type": "Feature",
  "properties": {
    "gn:admin1_code":"18.0",
    "gn:asciiname":"Taeneke",
    "gn:country_code":"ID",
    "gn:dem":778,
    "gn:feature_class":"P",
    "gn:feature_code":"PPL",
    "gn:name":"Taeneke",
    "gn:population":0,
    "gn:timezone":"Asia/Makassar",
    "iso:country":"ID",
    "name:ind_x_preferred":[
        "Taeneke"
    ],
    "wof:name":"Taeneke",
    "wof:placetype":"locality"
},
  "geometry": {"coordinates":[124.3126,-9.8623],"type":"Point"}
}