{
  "type": "Feature",
  "properties": {
    "gn:admin1_code":"30.0",
    "gn:asciiname":"Datarlemah",
    "gn:country_code":"ID",
    "gn:dem":908,
    "gn:feature_class":"P",
    "gn:feature_code":"PPL",
    "gn:name":"Datarlemah",
    "gn:population":0,
    "gn:timezone":"Asia/Jakarta",
    "iso:country":"ID",
    "name:ind_x_preferred":[
        "Datarlemah"
    ],
    "wof:name":"Datarlemah",
    "wof:placetype":"locality"
},
  "geometry": {"coordinates":[107.4464,-7.3189],"type":"Point"}
}