{
  "type": "Feature",
  "properties": {
    "gn:admin1_code":"38.0",
    "gn:asciiname":"Batu Tongko",
    "gn:country_code":"ID",
    "gn:dem":844,
    "gn:feature_class":"P",
    "gn:feature_code":"PPL",
    "gn:name":"Batu Tongko",
    "gn:population":0,
    "gn:timezone":"Asia/Makassar",
    "iso:country":"ID",
    "name:ind_x_preferred":[
        "Batu Tongko"
    ],
    "wof:lang_x_official":[
        "ind"
    ],
    "wof:lang_x_spoken":[
        "ind",
        "eng"
    ],
    "wof:name":"Batu Tongko",
    "wof:placetype":"locality"
},
  "geometry": {"coordinates":[119.919,-2.9213],"type":"Point"}
}