{
  "type": "Feature",
  "properties": {
    "gn:admin1_code":"7",
    "gn:asciiname":"Kaliasem",
    "gn:country_code":"ID",
    "gn:dem":777,
    "gn:feature_class":"P",
    "gn:feature_code":"PPL",
    "gn:name":"Kaliasem",
    "gn:population":0,
    "gn:timezone":"Asia/Jakarta",
    "iso:country":"ID",
    "name:ind_x_preferred":[
        "Kaliasem"
    ],
    "wof:name":"Kaliasem",
    "wof:placetype":"locality"
},
  "geometry": {"coordinates":[109.88722,-7.34778],"type":"Point"}
}