{
  "type": "Feature",
  "properties": {
    "gn:admin1_code":"18.0",
    "gn:asciiname":"Oelbiteno",
    "gn:country_code":"ID",
    "gn:dem":820,
    "gn:feature_class":"P",
    "gn:feature_code":"PPLA4",
    "gn:name":"Oelbiteno",
    "gn:population":0,
    "gn:timezone":"Asia/Makassar",
    "iso:country":"ID",
    "name:ind_x_preferred":[
        "Oelbiteno"
    ],
    "wof:name":"Oelbiteno",
    "wof:placetype":"locality"
},
  "geometry": {"coordinates":[123.84269999999999,-9.9251],"type":"Point"}
}