{
  "type": "Feature",
  "properties": {
    "gn:admin1_code":"0.0",
    "gn:asciiname":"Oebufu",
    "gn:cc2":"ID",
    "gn:country_code":"ID",
    "gn:dem":-9999,
    "gn:feature_class":"P",
    "gn:feature_code":"PPL",
    "gn:name":"Oebufu",
    "gn:population":0,
    "gn:timezone":"Asia/Makassar",
    "iso:country":"ID",
    "name:und_x_variant":[
        "O\u00ebboefoe",
        "Oebufu"
    ],
    "wof:lang_x_official":[
        "ind"
    ],
    "wof:lang_x_spoken":[
        "ind",
        "eng"
    ],
    "wof:name":"Oebufu",
    "wof:placetype":"locality"
},
  "geometry": {"coordinates":[123.61667,-1.18333],"type":"Point"}
}