{
  "type": "Feature",
  "properties": {
    "gn:admin1_code":"8",
    "gn:asciiname":"Curahsale Dua",
    "gn:country_code":"ID",
    "gn:dem":14,
    "gn:feature_class":"P",
    "gn:feature_code":"PPL",
    "gn:name":"Curahsale Dua",
    "gn:population":0,
    "gn:timezone":"Asia/Jakarta",
    "iso:country":"ID",
    "name:ind_x_preferred":[
        "Curahsale Dua"
    ],
    "wof:name":"Curahsale Dua",
    "wof:placetype":"locality"
},
  "geometry": {"coordinates":[114.0975,-7.7142],"type":"Point"}
}