{
  "type": "Feature",
  "properties": {
    "gn:admin1_code":"30.0",
    "gn:asciiname":"Pasirtamiang Tonggoh",
    "gn:country_code":"ID",
    "gn:dem":620,
    "gn:feature_class":"P",
    "gn:feature_code":"PPL",
    "gn:name":"Pasirtamiang Tonggoh",
    "gn:population":0,
    "gn:timezone":"Asia/Jakarta",
    "iso:country":"ID",
    "name:ind_x_preferred":[
        "Pasirtamiang Tonggoh"
    ],
    "wof:name":"Pasirtamiang Tonggoh",
    "wof:placetype":"locality"
},
  "geometry": {"coordinates":[108.21550000000001,-7.209],"type":"Point"}
}