{
  "type": "Feature",
  "properties": {
    "gn:admin1_code":"28.0",
    "gn:asciiname":"Wafabotir",
    "gn:country_code":"ID",
    "gn:dem":239,
    "gn:feature_class":"P",
    "gn:feature_code":"PPL",
    "gn:name":"Wafabotir",
    "gn:population":0,
    "gn:timezone":"Asia/Jayapura",
    "iso:country":"ID",
    "name:ind_x_preferred":[
        "Wafabotir"
    ],
    "name:und_x_variant":[
        "Wa Fa \u2019boti \u2019r\u2019"
    ],
    "wof:lang_x_official":[
        "ind"
    ],
    "wof:lang_x_spoken":[
        "ind",
        "eng"
    ],
    "wof:name":"Wafabotir",
    "wof:placetype":"locality"
},
  "geometry": {"coordinates":[126.7501,-3.55979],"type":"Point"}
}