{
  "type": "Feature",
  "properties": {
    "gn:admin1_code":"38",
    "gn:asciiname":"Seleng",
    "gn:country_code":"ID",
    "gn:dem":326,
    "gn:feature_class":"P",
    "gn:feature_code":"PPL",
    "gn:name":"Seleng",
    "gn:population":0,
    "gn:timezone":"Asia/Makassar",
    "iso:country":"ID",
    "name:ind_x_preferred":[
        "Seleng"
    ],
    "wof:name":"Seleng",
    "wof:placetype":"locality"
},
  "geometry": {"coordinates":[119.7607,-5.0827],"type":"Point"}
}