{
  "type": "Feature",
  "properties": {
    "gn:admin1_code":"28.0",
    "gn:asciiname":"Waapu",
    "gn:country_code":"ID",
    "gn:dem":18,
    "gn:feature_class":"P",
    "gn:feature_code":"PPL",
    "gn:name":"Waapu",
    "gn:population":0,
    "gn:timezone":"Asia/Jayapura",
    "iso:country":"ID",
    "name:ind_x_preferred":[
        "Waapu"
    ],
    "name:und_x_variant":[
        "Wa Apoe",
        "Waapu"
    ],
    "wof:name":"Waapu",
    "wof:placetype":"locality"
},
  "geometry": {"coordinates":[126.9335,-3.4385],"type":"Point"}
}