{
  "type": "Feature",
  "properties": {
    "gn:admin1_code":"26",
    "gn:asciiname":"Gereja",
    "gn:country_code":"ID",
    "gn:dem":3,
    "gn:feature_class":"P",
    "gn:feature_code":"PPL",
    "gn:name":"Gereja",
    "gn:population":0,
    "gn:timezone":"Asia/Jakarta",
    "iso:country":"ID",
    "name:ind_x_preferred":[
        "Gereja"
    ],
    "wof:name":"Gereja",
    "wof:placetype":"locality"
},
  "geometry": {"coordinates":[99.31399999999999,3.4148],"type":"Point"}
}