{
  "type": "Feature",
  "properties": {
    "gn:admin1_code":"1.0",
    "gn:asciiname":"Piyeung",
    "gn:country_code":"ID",
    "gn:dem":29,
    "gn:feature_class":"P",
    "gn:feature_code":"PPL",
    "gn:name":"Piyeung",
    "gn:population":0,
    "gn:timezone":"Asia/Jakarta",
    "iso:country":"ID",
    "name:ind_x_preferred":[
        "Piyeung"
    ],
    "name:und_x_variant":[
        "Pijeueng",
        "Piyeueng"
    ],
    "wof:name":"Piyeung",
    "wof:placetype":"locality"
},
  "geometry": {"coordinates":[95.4344,5.4512],"type":"Point"}
}