{
  "type": "Feature",
  "properties": {
    "gn:admin1_code":"30",
    "gn:asciiname":"Babakancangkudu",
    "gn:country_code":"ID",
    "gn:dem":45,
    "gn:feature_class":"P",
    "gn:feature_code":"PPL",
    "gn:name":"Babakancangkudu",
    "gn:population":0,
    "gn:timezone":"Asia/Jakarta",
    "iso:country":"ID",
    "name:ind_x_preferred":[
        "Babakancangkudu"
    ],
    "wof:name":"Babakancangkudu",
    "wof:placetype":"locality"
},
  "geometry": {"coordinates":[107.12444000000001,-6.48278],"type":"Point"}
}