{
  "type": "Feature",
  "properties": {
    "gn:admin1_code":"7.0",
    "gn:asciiname":"Watugede",
    "gn:country_code":"ID",
    "gn:dem":654,
    "gn:feature_class":"P",
    "gn:feature_code":"PPL",
    "gn:name":"Watugede",
    "gn:population":0,
    "gn:timezone":"Asia/Jakarta",
    "iso:country":"ID",
    "wof:name":"Watugede",
    "wof:placetype":"locality"
},
  "geometry": {"coordinates":[110.14806000000002,-7.28528],"type":"Point"}
}