{
  "type": "Feature",
  "properties": {
    "gn:admin1_code":"18.0",
    "gn:asciiname":"Bodoloba",
    "gn:country_code":"ID",
    "gn:dem":593,
    "gn:feature_class":"P",
    "gn:feature_code":"PPL",
    "gn:name":"Bodoloba",
    "gn:population":0,
    "gn:timezone":"Asia/Makassar",
    "iso:country":"ID",
    "name:ind_x_preferred":[
        "Bodoloba"
    ],
    "wof:name":"Bodoloba",
    "wof:placetype":"locality"
},
  "geometry": {"coordinates":[119.41970000000001,-9.577],"type":"Point"}
}