{
  "type": "Feature",
  "properties": {
    "gn:admin1_code":"30",
    "gn:asciiname":"Warunggombong",
    "gn:country_code":"ID",
    "gn:dem":408,
    "gn:feature_class":"P",
    "gn:feature_code":"PPL",
    "gn:name":"Warunggombong",
    "gn:population":0,
    "gn:timezone":"Asia/Jakarta",
    "iso:country":"ID",
    "name:ind_x_preferred":[
        "Warunggombong"
    ],
    "wof:name":"Warunggombong",
    "wof:placetype":"locality"
},
  "geometry": {"coordinates":[106.76139000000001,-6.83861],"type":"Point"}
}