{
  "type": "Feature",
  "properties": {
    "gn:admin1_code":"15.0",
    "gn:asciiname":"Lubukrukam",
    "gn:country_code":"ID",
    "gn:dem":690,
    "gn:feature_class":"P",
    "gn:feature_code":"PPL",
    "gn:name":"Lubukrukam",
    "gn:population":0,
    "gn:timezone":"Asia/Jakarta",
    "iso:country":"ID",
    "name:ind_x_preferred":[
        "Lubukrukam"
    ],
    "wof:name":"Lubukrukam",
    "wof:placetype":"locality"
},
  "geometry": {"coordinates":[104.52692999999999,-4.96352],"type":"Point"}
}