{
  "type": "Feature",
  "properties": {
    "gn:admin1_code":"7.0",
    "gn:asciiname":"Nepen",
    "gn:country_code":"ID",
    "gn:dem":280,
    "gn:feature_class":"P",
    "gn:feature_code":"PPL",
    "gn:name":"Nepen",
    "gn:population":0,
    "gn:timezone":"Asia/Jakarta",
    "iso:country":"ID",
    "wof:name":"Nepen",
    "wof:placetype":"locality"
},
  "geometry": {"coordinates":[110.63278,-7.56556],"type":"Point"}
}