{
  "type": "Feature",
  "properties": {
    "gn:admin1_code":"30.0",
    "gn:asciiname":"Rawa Satu",
    "gn:country_code":"ID",
    "gn:dem":532,
    "gn:feature_class":"P",
    "gn:feature_code":"PPLA4",
    "gn:name":"Rawa Satu",
    "gn:population":0,
    "gn:timezone":"Asia/Jakarta",
    "iso:country":"ID",
    "name:ind_x_preferred":[
        "Rawa Satu"
    ],
    "wof:name":"Rawa Satu",
    "wof:placetype":"locality"
},
  "geometry": {"coordinates":[108.3171,-7.1581],"type":"Point"}
}