{
  "type": "Feature",
  "properties": {
    "gn:admin1_code":"8",
    "gn:asciiname":"Dawung",
    "gn:country_code":"ID",
    "gn:dem":117,
    "gn:feature_class":"P",
    "gn:feature_code":"PPL",
    "gn:name":"Dawung",
    "gn:population":0,
    "gn:timezone":"Asia/Jakarta",
    "iso:country":"ID",
    "name:ind_x_preferred":[
        "Dawung"
    ],
    "wof:name":"Dawung",
    "wof:placetype":"locality"
},
  "geometry": {"coordinates":[111.37649999999999,-7.8487],"type":"Point"}
}