{
  "type": "Feature",
  "properties": {
    "gn:admin1_code":"07",
    "gn:asciiname":"Bumiharjo",
    "gn:country_code":"ID",
    "gn:dem":1061,
    "gn:feature_class":"P",
    "gn:feature_code":"PPL",
    "gn:name":"Bumiharjo",
    "gn:population":0,
    "gn:timezone":"Asia/Jakarta",
    "iso:country":"ID",
    "name:und_x_variant":[
        "Bumjhardjo",
        "Bumyharjo",
        "Bumiharjo"
    ],
    "wof:lang_x_official":[
        "ind"
    ],
    "wof:lang_x_spoken":[
        "ind",
        "eng"
    ],
    "wof:name":"Bumiharjo",
    "wof:placetype":"locality"
},
  "geometry": {"coordinates":[110.44722,-7.37667],"type":"Point"}
}