{
  "type": "Feature",
  "properties": {
    "gn:admin1_code":"8",
    "gn:asciiname":"Wonokertopasar",
    "gn:country_code":"ID",
    "gn:dem":313,
    "gn:feature_class":"P",
    "gn:feature_code":"PPL",
    "gn:name":"Wonokertopasar",
    "gn:population":0,
    "gn:timezone":"Asia/Jakarta",
    "iso:country":"ID",
    "name:ind_x_preferred":[
        "Wonokertopasar"
    ],
    "wof:name":"Wonokertopasar",
    "wof:placetype":"locality"
},
  "geometry": {"coordinates":[112.5972,-8.2238],"type":"Point"}
}