{
  "type": "Feature",
  "properties": {
    "gn:admin1_code":"08",
    "gn:asciiname":"Pluntas",
    "gn:country_code":"ID",
    "gn:dem":4,
    "gn:feature_class":"P",
    "gn:feature_code":"PPL",
    "gn:name":"Pluntas",
    "gn:population":0,
    "gn:timezone":"Asia/Jakarta",
    "iso:country":"ID",
    "name:ind_x_preferred":[
        "Pluntas"
    ],
    "wof:name":"Pluntas",
    "wof:placetype":"locality"
},
  "geometry": {"coordinates":[112.7544,-7.263],"type":"Point"}
}