{
  "type": "Feature",
  "properties": {
    "gn:admin1_code":"17",
    "gn:asciiname":"Tanakawuy",
    "gn:country_code":"ID",
    "gn:dem":258,
    "gn:feature_class":"P",
    "gn:feature_code":"PPL",
    "gn:name":"Tanakawuy",
    "gn:population":0,
    "gn:timezone":"Asia/Makassar",
    "iso:country":"ID",
    "name:ind_x_preferred":[
        "Tanakawuy"
    ],
    "wof:name":"Tanakawuy",
    "wof:placetype":"locality"
},
  "geometry": {"coordinates":[116.4593,-8.6579],"type":"Point"}
}