{
  "type": "Feature",
  "properties": {
    "gn:admin1_code":"30.0",
    "gn:asciiname":"Petakan",
    "gn:country_code":"ID",
    "gn:dem":332,
    "gn:feature_class":"P",
    "gn:feature_code":"PPL",
    "gn:name":"Petakan",
    "gn:population":0,
    "gn:timezone":"Asia/Jakarta",
    "iso:country":"ID",
    "name:ind_x_preferred":[
        "Petakan"
    ],
    "wof:name":"Petakan",
    "wof:placetype":"locality"
},
  "geometry": {"coordinates":[107.21420000000001,-7.3408],"type":"Point"}
}