{
  "type": "Feature",
  "properties": {
    "gn:admin1_code":"30.0",
    "gn:asciiname":"Kubangmanyar",
    "gn:country_code":"ID",
    "gn:dem":524,
    "gn:feature_class":"P",
    "gn:feature_code":"PPL",
    "gn:name":"Kubangmanyar",
    "gn:population":0,
    "gn:timezone":"Asia/Jakarta",
    "iso:country":"ID",
    "name:ind_x_preferred":[
        "Kubangmanyar"
    ],
    "name:und_x_variant":[
        "Kubangmanjar"
    ],
    "wof:name":"Kubangmanyar",
    "wof:placetype":"locality"
},
  "geometry": {"coordinates":[108.1296,-7.2825],"type":"Point"}
}