{
  "type": "Feature",
  "properties": {
    "gn:admin1_code":"15.0",
    "gn:asciiname":"Segalamidar",
    "gn:country_code":"ID",
    "gn:dem":89,
    "gn:feature_class":"P",
    "gn:feature_code":"PPL",
    "gn:name":"Segalamidar",
    "gn:population":0,
    "gn:timezone":"Asia/Jakarta",
    "iso:country":"ID",
    "name:ind_x_preferred":[
        "Segalamidar"
    ],
    "wof:name":"Segalamidar",
    "wof:placetype":"locality"
},
  "geometry": {"coordinates":[104.88097,-5.06843],"type":"Point"}
}