{
  "type": "Feature",
  "properties": {
    "gn:admin1_code":"21",
    "gn:asciiname":"Abajarang",
    "gn:country_code":"ID",
    "gn:dem":12,
    "gn:feature_class":"P",
    "gn:feature_code":"PPL",
    "gn:name":"Abajarang",
    "gn:population":0,
    "gn:timezone":"Asia/Makassar",
    "iso:country":"ID",
    "name:ind_x_preferred":[
        "Abajarang"
    ],
    "wof:name":"Abajarang",
    "wof:placetype":"locality"
},
  "geometry": {"coordinates":[120.1808,0.7523],"type":"Point"}
}