{
  "type": "Feature",
  "properties": {
    "gn:admin1_code":"15.0",
    "gn:asciiname":"Katimbang",
    "gn:country_code":"ID",
    "gn:dem":6,
    "gn:feature_class":"P",
    "gn:feature_code":"PPL",
    "gn:name":"Katimbang",
    "gn:population":0,
    "gn:timezone":"Asia/Jakarta",
    "iso:country":"ID",
    "name:ind_x_preferred":[
        "Katimbang"
    ],
    "wof:name":"Katimbang",
    "wof:placetype":"locality"
},
  "geometry": {"coordinates":[105.59143,-5.80952],"type":"Point"}
}