{
  "type": "Feature",
  "properties": {
    "gn:admin1_code":"26",
    "gn:asciiname":"Aek Loba Afdeling Satu",
    "gn:country_code":"ID",
    "gn:dem":34,
    "gn:feature_class":"P",
    "gn:feature_code":"PPL",
    "gn:name":"Aek Loba Afdeling Satu",
    "gn:population":0,
    "gn:timezone":"Asia/Jakarta",
    "iso:country":"ID",
    "name:ind_x_preferred":[
        "Aek Loba Afdeling Satu"
    ],
    "name:und_x_variant":[
        "Aek Loba Afdeling I"
    ],
    "wof:name":"Aek Loba Afdeling Satu",
    "wof:placetype":"locality"
},
  "geometry": {"coordinates":[99.6387,2.651],"type":"Point"}
}