{
  "type": "Feature",
  "properties": {
    "gn:admin1_code":"18.0",
    "gn:asciiname":"Pandanjara",
    "gn:country_code":"ID",
    "gn:dem":692,
    "gn:feature_class":"P",
    "gn:feature_code":"PPL",
    "gn:name":"Pandanjara",
    "gn:population":0,
    "gn:timezone":"Asia/Makassar",
    "iso:country":"ID",
    "name:ind_x_preferred":[
        "Pandanjara"
    ],
    "wof:name":"Pandanjara",
    "wof:placetype":"locality"
},
  "geometry": {"coordinates":[120.3201,-10.0857],"type":"Point"}
}