{
  "type": "Feature",
  "properties": {
    "gn:admin1_code":"17",
    "gn:asciiname":"Rasarige",
    "gn:country_code":"ID",
    "gn:dem":196,
    "gn:feature_class":"P",
    "gn:feature_code":"PPL",
    "gn:name":"Rasarige",
    "gn:population":0,
    "gn:timezone":"Asia/Makassar",
    "iso:country":"ID",
    "name:ind_x_preferred":[
        "Rasarige"
    ],
    "wof:name":"Rasarige",
    "wof:placetype":"locality"
},
  "geometry": {"coordinates":[118.9097,-8.4198],"type":"Point"}
}