{
  "type": "Feature",
  "properties": {
    "gn:admin1_code":"30",
    "gn:asciiname":"Pasirtengah",
    "gn:country_code":"ID",
    "gn:dem":353,
    "gn:feature_class":"P",
    "gn:feature_code":"PPL",
    "gn:name":"Pasirtengah",
    "gn:population":0,
    "gn:timezone":"Asia/Jakarta",
    "iso:country":"ID",
    "name:ind_x_preferred":[
        "Pasirtengah"
    ],
    "wof:name":"Pasirtengah",
    "wof:placetype":"locality"
},
  "geometry": {"coordinates":[107.20638999999998,-6.73278],"type":"Point"}
}