{
  "type": "Feature",
  "properties": {
    "gn:admin1_code":"0.0",
    "gn:asciiname":"Sihala",
    "gn:country_code":"ID",
    "gn:dem":60,
    "gn:feature_class":"P",
    "gn:feature_code":"PPL",
    "gn:name":"Sihala",
    "gn:population":0,
    "gn:timezone":"Asia/Jakarta",
    "iso:country":"ID",
    "name:fas_x_preferred":[
        "\u0633\u0647\u0627\u0644\u0647"
    ],
    "name:pnb_x_preferred":[
        "\u0633\u06c1\u0627\u0644\u06c1"
    ],
    "name:urd_x_preferred":[
        "\u0633\u06c1\u0627\u0644\u06c1"
    ],
    "wof:name":"Sihala",
    "wof:placetype":"locality"
},
  "geometry": {"coordinates":[99.65000000000001,2.41667],"type":"Point"}
}