{
  "type": "Feature",
  "properties": {
    "gn:admin1_code":"42",
    "gn:asciiname":"Sesuak",
    "gn:country_code":"ID",
    "gn:dem":8,
    "gn:feature_class":"P",
    "gn:feature_code":"PPL",
    "gn:name":"Sesuak",
    "gn:population":0,
    "gn:timezone":"Asia/Makassar",
    "iso:country":"ID",
    "name:ind_x_preferred":[
        "Sesuak"
    ],
    "wof:name":"Sesuak",
    "wof:placetype":"locality"
},
  "geometry": {"coordinates":[116.66097000000001,3.4766],"type":"Point"}
}