{
  "type": "Feature",
  "properties": {
    "gn:admin1_code":"30",
    "gn:asciiname":"Legon Wetan",
    "gn:country_code":"ID",
    "gn:dem":3,
    "gn:feature_class":"P",
    "gn:feature_code":"PPL",
    "gn:name":"Legon Wetan",
    "gn:population":0,
    "gn:timezone":"Asia/Jakarta",
    "iso:country":"ID",
    "name:ind_x_preferred":[
        "Legon Wetan"
    ],
    "wof:name":"Legon Wetan",
    "wof:placetype":"locality"
},
  "geometry": {"coordinates":[107.78389,-6.21111],"type":"Point"}
}