{
  "type": "Feature",
  "properties": {
    "gn:admin1_code":"18.0",
    "gn:asciiname":"Rura",
    "gn:country_code":"ID",
    "gn:dem":287,
    "gn:feature_class":"P",
    "gn:feature_code":"PPL",
    "gn:name":"Rura",
    "gn:population":0,
    "gn:timezone":"Asia/Makassar",
    "iso:country":"ID",
    "name:ind_x_preferred":[
        "Rura"
    ],
    "wof:name":"Rura",
    "wof:placetype":"locality"
},
  "geometry": {"coordinates":[120.3914,-8.3297],"type":"Point"}
}