{
  "type": "Feature",
  "properties": {
    "gn:admin1_code":"18.0",
    "gn:asciiname":"Rura",
    "gn:country_code":"ID",
    "gn:dem":287,
    "gn:feature_class":"P",
    "gn:feature_code":"PPL",
    "gn:name":"Rura",
    "gn:population":0,
    "gn:timezone":"Asia/Makassar",
    "iso:country":"ID",
    "name:bpy_x_preferred":[
        "\u09b0\u09c1\u09b0\u09be"
    ],
    "name:ceb_x_preferred":[
        "Rura"
    ],
    "name:hin_x_preferred":[
        "\u0930\u0942\u0930\u093e"
    ],
    "name:ind_x_preferred":[
        "Rura"
    ],
    "name:ita_x_preferred":[
        "Rura"
    ],
    "name:mlg_x_preferred":[
        "Rura"
    ],
    "name:msa_x_preferred":[
        "Rura"
    ],
    "name:nld_x_preferred":[
        "Rura"
    ],
    "name:pol_x_preferred":[
        "Rura"
    ],
    "name:por_x_preferred":[
        "Rura"
    ],
    "name:urd_x_preferred":[
        "\u0631\u0648\u0631\u0627"
    ],
    "name:vie_x_preferred":[
        "Rura"
    ],
    "wof:lang_x_official":[
        "ind"
    ],
    "wof:lang_x_spoken":[
        "ind",
        "eng"
    ],
    "wof:name":"Rura",
    "wof:placetype":"locality"
},
  "geometry": {"coordinates":[120.3914,-8.3297],"type":"Point"}
}