{
  "type": "Feature",
  "properties": {
    "gn:admin1_code":"38.0",
    "gn:asciiname":"Awakaluku",
    "gn:country_code":"ID",
    "gn:dem":28,
    "gn:feature_class":"P",
    "gn:feature_code":"PPL",
    "gn:name":"Awakaluku",
    "gn:population":0,
    "gn:timezone":"Asia/Makassar",
    "iso:country":"ID",
    "name:ind_x_preferred":[
        "Awakaluku"
    ],
    "wof:name":"Awakaluku",
    "wof:placetype":"locality"
},
  "geometry": {"coordinates":[120.0334,-3.9034],"type":"Point"}
}