{
  "type": "Feature",
  "properties": {
    "gn:admin1_code":"2",
    "gn:asciiname":"Gulingan",
    "gn:country_code":"ID",
    "gn:dem":163,
    "gn:feature_class":"P",
    "gn:feature_code":"PPL",
    "gn:name":"Gulingan",
    "gn:population":0,
    "gn:timezone":"Asia/Makassar",
    "iso:country":"ID",
    "name:ind_x_preferred":[
        "Gulingan"
    ],
    "wof:name":"Gulingan",
    "wof:placetype":"locality"
},
  "geometry": {"coordinates":[115.02119999999999,-8.4903],"type":"Point"}
}