{
  "type": "Feature",
  "properties": {
    "gn:admin1_code":"26.0",
    "gn:asciiname":"Gunung Bosar",
    "gn:country_code":"ID",
    "gn:dem":1089,
    "gn:feature_class":"P",
    "gn:feature_code":"PPL",
    "gn:name":"Gunung Bosar",
    "gn:population":0,
    "gn:timezone":"Asia/Jakarta",
    "iso:country":"ID",
    "name:ind_x_preferred":[
        "Gunung Bosar"
    ],
    "name:und_x_variant":[
        "Goenoeng Bosar"
    ],
    "wof:name":"Gunung Bosar",
    "wof:placetype":"locality"
},
  "geometry": {"coordinates":[98.87690000000001,2.8082],"type":"Point"}
}