{
  "type": "Feature",
  "properties": {
    "gn:admin1_code":"30",
    "gn:asciiname":"Pakuhaji",
    "gn:country_code":"ID",
    "gn:dem":18,
    "gn:feature_class":"P",
    "gn:feature_code":"PPL",
    "gn:name":"Pakuhaji",
    "gn:population":0,
    "gn:timezone":"Asia/Jakarta",
    "iso:country":"ID",
    "name:ind_x_preferred":[
        "Pakuhaji"
    ],
    "name:jav_x_preferred":[
        "Pakuhaji"
    ],
    "name:msa_x_preferred":[
        "Pakuhaji"
    ],
    "wof:lang_x_official":[
        "ind"
    ],
    "wof:lang_x_spoken":[
        "ind",
        "eng"
    ],
    "wof:name":"Pakuhaji",
    "wof:placetype":"locality"
},
  "geometry": {"coordinates":[106.45083,-6.18611],"type":"Point"}
}