{
  "type": "Feature",
  "properties": {
    "gn:admin1_code":"8.0",
    "gn:asciiname":"Blukotan",
    "gn:country_code":"ID",
    "gn:dem":13,
    "gn:feature_class":"P",
    "gn:feature_code":"PPL",
    "gn:name":"Blukotan",
    "gn:population":0,
    "gn:timezone":"Asia/Jakarta",
    "iso:country":"ID",
    "name:ind_x_preferred":[
        "Blukotan"
    ],
    "wof:name":"Blukotan",
    "wof:placetype":"locality"
},
  "geometry": {"coordinates":[113.6486,-6.8893],"type":"Point"}
}