{
  "type": "Feature",
  "properties": {
    "gn:admin1_code":"7.0",
    "gn:asciiname":"Masan",
    "gn:country_code":"ID",
    "gn:dem":301,
    "gn:feature_class":"P",
    "gn:feature_code":"PPL",
    "gn:name":"Masan",
    "gn:population":0,
    "gn:timezone":"Asia/Jakarta",
    "iso:country":"ID",
    "name:ind_x_preferred":[
        "Masan"
    ],
    "wof:name":"Masan",
    "wof:placetype":"locality"
},
  "geometry": {"coordinates":[110.82056,-8.09639],"type":"Point"}
}