{
  "type": "Feature",
  "properties": {
    "gn:admin1_code":"18",
    "gn:asciiname":"Wio",
    "gn:country_code":"ID",
    "gn:dem":488,
    "gn:feature_class":"P",
    "gn:feature_code":"PPL",
    "gn:name":"Wio",
    "gn:population":0,
    "gn:timezone":"Asia/Makassar",
    "iso:country":"ID",
    "name:ind_x_preferred":[
        "Wio"
    ],
    "wof:name":"Wio",
    "wof:placetype":"locality"
},
  "geometry": {"coordinates":[121.343,-8.8579],"type":"Point"}
}