{
  "type": "Feature",
  "properties": {
    "gn:admin1_code":"1",
    "gn:asciiname":"Kutatring",
    "gn:country_code":"ID",
    "gn:dem":24,
    "gn:feature_class":"P",
    "gn:feature_code":"PPL",
    "gn:name":"Kutatring",
    "gn:population":0,
    "gn:timezone":"Asia/Jakarta",
    "iso:country":"ID",
    "name:ind_x_preferred":[
        "Kutatring"
    ],
    "wof:name":"Kutatring",
    "wof:placetype":"locality"
},
  "geometry": {"coordinates":[96.4901,3.9885],"type":"Point"}
}