{
  "type": "Feature",
  "properties": {
    "gn:admin1_code":"38.0",
    "gn:asciiname":"Tandung",
    "gn:country_code":"ID",
    "gn:dem":307,
    "gn:feature_class":"P",
    "gn:feature_code":"PPL",
    "gn:name":"Tandung",
    "gn:population":0,
    "gn:timezone":"Asia/Makassar",
    "iso:country":"ID",
    "name:ind_x_preferred":[
        "Tandung"
    ],
    "name:und_x_variant":[
        "Tandjung",
        "Tandoeng"
    ],
    "wof:name":"Tandung",
    "wof:placetype":"locality"
},
  "geometry": {"coordinates":[120.0916,-2.6179],"type":"Point"}
}