{
  "type": "Feature",
  "properties": {
    "gn:admin1_code":"38",
    "gn:asciiname":"Belaka",
    "gn:country_code":"ID",
    "gn:dem":11,
    "gn:feature_class":"P",
    "gn:feature_code":"PPL",
    "gn:name":"Belaka",
    "gn:population":0,
    "gn:timezone":"Asia/Makassar",
    "iso:country":"ID",
    "name:bih_x_preferred":[
        "\u092c\u0947\u0932\u0915\u093e"
    ],
    "name:ind_x_preferred":[
        "Belaka"
    ],
    "name:nep_x_preferred":[
        "\u092c\u0947\u0932\u0915\u093e \u0928\u0917\u0930\u092a\u093e\u0932\u093f\u0915\u093e"
    ],
    "wof:lang_x_official":[
        "ind"
    ],
    "wof:lang_x_spoken":[
        "ind",
        "eng"
    ],
    "wof:name":"Belaka",
    "wof:placetype":"locality"
},
  "geometry": {"coordinates":[119.4218,-5.2112],"type":"Point"}
}