{
  "type": "Feature",
  "properties": {
    "gn:admin1_code":"30",
    "gn:asciiname":"Mawarsari",
    "gn:country_code":"ID",
    "gn:dem":784,
    "gn:feature_class":"P",
    "gn:feature_code":"PPL",
    "gn:name":"Mawarsari",
    "gn:population":0,
    "gn:timezone":"Asia/Jakarta",
    "iso:country":"ID",
    "name:ind_x_preferred":[
        "Mawarsari"
    ],
    "wof:name":"Mawarsari",
    "wof:placetype":"locality"
},
  "geometry": {"coordinates":[108.36888999999999,-6.98611],"type":"Point"}
}