{
  "type": "Feature",
  "properties": {
    "gn:admin1_code":"7.0",
    "gn:asciiname":"Singaraja",
    "gn:country_code":"ID",
    "gn:dem":359,
    "gn:feature_class":"P",
    "gn:feature_code":"PPL",
    "gn:name":"Singaraja",
    "gn:population":0,
    "gn:timezone":"Asia/Jakarta",
    "iso:country":"ID",
    "name:afr_x_preferred":[
        "Singaraja"
    ],
    "name:ara_x_preferred":[
        "\u0633\u0646\u063a\u0627\u0631\u0627\u062c\u0627"
    ],
    "name:ceb_x_preferred":[
        "Singaraja"
    ],
    "name:deu_x_preferred":[
        "Singaraja"
    ],
    "name:epo_x_preferred":[
        "Singaraja"
    ],
    "name:fas_x_preferred":[
        "\u0633\u06cc\u0646\u06af\u0631\u0627\u062c\u0627"
    ],
    "name:fra_x_preferred":[
        "Singaraja"
    ],
    "name:heb_x_preferred":[
        "\u05e1\u05d9\u05e0\u05d2\u05e8\u05d2'\u05d4"
    ],
    "name:hin_x_preferred":[
        "\u0938\u093f\u0902\u0939\u0930\u093e\u091c"
    ],
    "name:hun_x_preferred":[
        "Singaraja"
    ],
    "name:ind_x_preferred":[
        "Singaraja"
    ],
    "name:ita_x_preferred":[
        "Singaraja"
    ],
    "name:jpn_x_preferred":[
        "\u30b7\u30ac\u30e9\u30b8\u30e3"
    ],
    "name:mlg_x_preferred":[
        "Singaraja"
    ],
    "name:msa_x_preferred":[
        "Singaraja"
    ],
    "name:nld_x_preferred":[
        "Singaraja"
    ],
    "name:nor_x_preferred":[
        "Singaraja"
    ],
    "name:pol_x_preferred":[
        "Singaraja"
    ],
    "name:por_x_preferred":[
        "Singaraja"
    ],
    "name:rus_x_preferred":[
        "\u0421\u0438\u043d\u0433\u0430\u0440\u0430\u0434\u0436\u0430"
    ],
    "name:spa_x_preferred":[
        "Singaraja"
    ],
    "name:tha_x_preferred":[
        "\u0e0b\u0e35\u0e07\u0e32\u0e23\u0e32\u0e08\u0e32"
    ],
    "name:und_x_variant":[
        "Singaradja"
    ],
    "wof:lang_x_official":[
        "ind"
    ],
    "wof:lang_x_spoken":[
        "ind",
        "eng"
    ],
    "wof:name":"Singaraja",
    "wof:placetype":"locality"
},
  "geometry": {"coordinates":[108.6151,-7.209],"type":"Point"}
}