{
  "type": "Feature",
  "properties": {
    "gn:admin1_code":"7.0",
    "gn:asciiname":"Singaraja",
    "gn:country_code":"ID",
    "gn:dem":359,
    "gn:feature_class":"P",
    "gn:feature_code":"PPL",
    "gn:name":"Singaraja",
    "gn:population":0,
    "gn:timezone":"Asia/Jakarta",
    "iso:country":"ID",
    "name:ind_x_preferred":[
        "Singaraja"
    ],
    "name:und_x_variant":[
        "Singaradja"
    ],
    "wof:name":"Singaraja",
    "wof:placetype":"locality"
},
  "geometry": {"coordinates":[108.6151,-7.209],"type":"Point"}
}