{
  "type": "Feature",
  "properties": {
    "gn:admin1_code":"2",
    "gn:asciiname":"Banjar Batanyuh Kaja",
    "gn:country_code":"ID",
    "gn:dem":191,
    "gn:feature_class":"P",
    "gn:feature_code":"PPLA4",
    "gn:name":"Banjar Batanyuh Kaja",
    "gn:population":0,
    "gn:timezone":"Asia/Makassar",
    "iso:country":"ID",
    "name:ind_x_preferred":[
        "Banjar Batanyuh Kaja"
    ],
    "wof:name":"Banjar Batanyuh Kaja",
    "wof:placetype":"locality"
},
  "geometry": {"coordinates":[115.1678,-8.508],"type":"Point"}
}