{
  "type": "Feature",
  "properties": {
    "gn:admin1_code":"30",
    "gn:asciiname":"Talok",
    "gn:country_code":"ID",
    "gn:dem":12,
    "gn:feature_class":"P",
    "gn:feature_code":"PPL",
    "gn:name":"Talok",
    "gn:population":0,
    "gn:timezone":"Asia/Jakarta",
    "iso:country":"ID",
    "name:ind_x_preferred":[
        "Talok"
    ],
    "name:und_x_variant":[
        "Talak"
    ],
    "wof:name":"Talok",
    "wof:placetype":"locality"
},
  "geometry": {"coordinates":[107.14917,-6.19944],"type":"Point"}
}