{
  "type": "Feature",
  "properties": {
    "gn:admin1_code":"18.0",
    "gn:asciiname":"Oeteno",
    "gn:country_code":"ID",
    "gn:dem":143,
    "gn:feature_class":"P",
    "gn:feature_code":"PPL",
    "gn:name":"Oeteno",
    "gn:population":0,
    "gn:timezone":"Asia/Makassar",
    "iso:country":"ID",
    "name:ind_x_preferred":[
        "Oeteno"
    ],
    "wof:name":"Oeteno",
    "wof:placetype":"locality"
},
  "geometry": {"coordinates":[119.0301,-9.5865],"type":"Point"}
}