{
  "type": "Feature",
  "properties": {
    "gn:admin1_code":"18.0",
    "gn:asciiname":"Wongkolmalowi",
    "gn:country_code":"ID",
    "gn:dem":163,
    "gn:feature_class":"P",
    "gn:feature_code":"PPL",
    "gn:name":"Wongkolmalowi",
    "gn:population":0,
    "gn:timezone":"Asia/Makassar",
    "iso:country":"ID",
    "name:ind_x_preferred":[
        "Wongkolmalowi"
    ],
    "wof:name":"Wongkolmalowi",
    "wof:placetype":"locality"
},
  "geometry": {"coordinates":[120.1589,-8.7017],"type":"Point"}
}