{
  "type": "Feature",
  "properties": {
    "gn:admin1_code":"8",
    "gn:asciiname":"Gampang",
    "gn:country_code":"ID",
    "gn:dem":14,
    "gn:feature_class":"P",
    "gn:feature_code":"PPL",
    "gn:name":"Gampang",
    "gn:population":0,
    "gn:timezone":"Asia/Jakarta",
    "iso:country":"ID",
    "name:ind_x_preferred":[
        "Gampang"
    ],
    "wof:name":"Gampang",
    "wof:placetype":"locality"
},
  "geometry": {"coordinates":[112.32250000000001,-7.1436],"type":"Point"}
}