{
  "type": "Feature",
  "properties": {
    "gn:admin1_code":"30.0",
    "gn:asciiname":"Cigotong",
    "gn:country_code":"ID",
    "gn:dem":145,
    "gn:feature_class":"P",
    "gn:feature_code":"PPL",
    "gn:name":"Cigotong",
    "gn:population":0,
    "gn:timezone":"Asia/Jakarta",
    "iso:country":"ID",
    "name:ind_x_preferred":[
        "Cigotong"
    ],
    "wof:name":"Cigotong",
    "wof:placetype":"locality"
},
  "geometry": {"coordinates":[106.9427,-7.3136],"type":"Point"}
}