{
  "type": "Feature",
  "properties": {
    "gn:admin1_code":"38",
    "gn:asciiname":"Panjalingan",
    "gn:country_code":"ID",
    "gn:dem":1,
    "gn:feature_class":"P",
    "gn:feature_code":"PPL",
    "gn:name":"Panjalingan",
    "gn:population":0,
    "gn:timezone":"Asia/Makassar",
    "iso:country":"ID",
    "name:ind_x_preferred":[
        "Panjalingan"
    ],
    "wof:name":"Panjalingan",
    "wof:placetype":"locality"
},
  "geometry": {"coordinates":[119.5573,-4.936],"type":"Point"}
}