{
  "type": "Feature",
  "properties": {
    "gn:admin1_code":"7",
    "gn:asciiname":"Pulorejo",
    "gn:country_code":"ID",
    "gn:dem":53,
    "gn:feature_class":"P",
    "gn:feature_code":"PPL",
    "gn:name":"Pulorejo",
    "gn:population":0,
    "gn:timezone":"Asia/Jakarta",
    "iso:country":"ID",
    "name:ind_x_preferred":[
        "Pulorejo"
    ],
    "wof:name":"Pulorejo",
    "wof:placetype":"locality"
},
  "geometry": {"coordinates":[110.85805999999999,-7.20694],"type":"Point"}
}