{
  "type": "Feature",
  "properties": {
    "gn:admin1_code":"30",
    "gn:asciiname":"Selakopi",
    "gn:country_code":"ID",
    "gn:dem":205,
    "gn:feature_class":"P",
    "gn:feature_code":"PPL",
    "gn:name":"Selakopi",
    "gn:population":0,
    "gn:timezone":"Asia/Jakarta",
    "iso:country":"ID",
    "name:ind_x_preferred":[
        "Selakopi"
    ],
    "wof:name":"Selakopi",
    "wof:placetype":"locality"
},
  "geometry": {"coordinates":[106.76111000000002,-6.57861],"type":"Point"}
}