{
  "type": "Feature",
  "properties": {
    "gn:admin1_code":"30",
    "gn:asciiname":"Leuewungsireum",
    "gn:country_code":"ID",
    "gn:dem":10,
    "gn:feature_class":"P",
    "gn:feature_code":"PPL",
    "gn:name":"Leuewungsireum",
    "gn:population":0,
    "gn:timezone":"Asia/Jakarta",
    "iso:country":"ID",
    "name:ind_x_preferred":[
        "Leuewungsireum"
    ],
    "wof:name":"Leuewungsireum",
    "wof:placetype":"locality"
},
  "geometry": {"coordinates":[107.35639,-6.26944],"type":"Point"}
}