{
  "type": "Feature",
  "properties": {
    "gn:admin1_code":"26",
    "gn:asciiname":"Lumban Dolok",
    "gn:country_code":"ID",
    "gn:dem":938,
    "gn:feature_class":"P",
    "gn:feature_code":"PPL",
    "gn:name":"Lumban Dolok",
    "gn:population":0,
    "gn:timezone":"Asia/Jakarta",
    "iso:country":"ID",
    "name:ind_x_preferred":[
        "Lumban Dolok"
    ],
    "wof:name":"Lumban Dolok",
    "wof:placetype":"locality"
},
  "geometry": {"coordinates":[99.21339999999999,2.3814],"type":"Point"}
}