{
  "type": "Feature",
  "properties": {
    "gn:admin1_code":"22.0",
    "gn:asciiname":"Ulungkura",
    "gn:country_code":"ID",
    "gn:dem":142,
    "gn:feature_class":"P",
    "gn:feature_code":"PPL",
    "gn:name":"Ulungkura",
    "gn:population":0,
    "gn:timezone":"Asia/Makassar",
    "iso:country":"ID",
    "name:ind_x_preferred":[
        "Ulungkura"
    ],
    "wof:name":"Ulungkura",
    "wof:placetype":"locality"
},
  "geometry": {"coordinates":[121.9843,-5.2787],"type":"Point"}
}