{
  "type": "Feature",
  "properties": {
    "gn:admin1_code":"18",
    "gn:asciiname":"Wudi",
    "gn:country_code":"ID",
    "gn:dem":947,
    "gn:feature_class":"P",
    "gn:feature_code":"PPL",
    "gn:name":"Wudi",
    "gn:population":0,
    "gn:timezone":"Asia/Makassar",
    "iso:country":"ID",
    "name:ceb_x_preferred":[
        "Wudi"
    ],
    "name:ces_x_preferred":[
        "Wu-ti"
    ],
    "name:deu_x_preferred":[
        "Wudi"
    ],
    "name:fra_x_preferred":[
        "Wudi"
    ],
    "name:ind_x_preferred":[
        "Wudi"
    ],
    "name:pol_x_preferred":[
        "Wudi"
    ],
    "name:rus_x_preferred":[
        "\u0423-\u0434\u0438"
    ],
    "name:swe_x_preferred":[
        "Wudi"
    ],
    "wof:lang_x_official":[
        "ind"
    ],
    "wof:lang_x_spoken":[
        "ind",
        "eng"
    ],
    "wof:name":"Wudi",
    "wof:placetype":"locality"
},
  "geometry": {"coordinates":[120.3592,-8.7178],"type":"Point"}
}