{
  "type": "Feature",
  "properties": {
    "gn:admin1_code":"38",
    "gn:asciiname":"Tarura",
    "gn:country_code":"ID",
    "gn:dem":854,
    "gn:feature_class":"P",
    "gn:feature_code":"PPL",
    "gn:name":"Tarura",
    "gn:population":0,
    "gn:timezone":"Asia/Makassar",
    "iso:country":"ID",
    "name:ind_x_preferred":[
        "Tarura"
    ],
    "wof:name":"Tarura",
    "wof:placetype":"locality"
},
  "geometry": {"coordinates":[119.7593,-3.0471],"type":"Point"}
}