{
  "type": "Feature",
  "properties": {
    "gn:admin1_code":"30",
    "gn:asciiname":"Rahayu",
    "gn:country_code":"ID",
    "gn:dem":64,
    "gn:feature_class":"P",
    "gn:feature_code":"PPL",
    "gn:name":"Rahayu",
    "gn:population":0,
    "gn:timezone":"Asia/Jakarta",
    "iso:country":"ID",
    "name:ind_x_preferred":[
        "Rahayu"
    ],
    "wof:name":"Rahayu",
    "wof:placetype":"locality"
},
  "geometry": {"coordinates":[107.07861,-6.43667],"type":"Point"}
}