{
  "type": "Feature",
  "properties": {
    "gn:admin1_code":"30.0",
    "gn:asciiname":"Kilangpayan",
    "gn:country_code":"ID",
    "gn:dem":620,
    "gn:feature_class":"P",
    "gn:feature_code":"PPL",
    "gn:name":"Kilangpayan",
    "gn:population":0,
    "gn:timezone":"Asia/Jakarta",
    "iso:country":"ID",
    "name:ind_x_preferred":[
        "Kilangpayan"
    ],
    "wof:name":"Kilangpayan",
    "wof:placetype":"locality"
},
  "geometry": {"coordinates":[108.27370000000001,-7.2658],"type":"Point"}
}