{
  "type": "Feature",
  "properties": {
    "gn:admin1_code":"33",
    "gn:asciiname":"Rancasaat",
    "gn:country_code":"ID",
    "gn:dem":25,
    "gn:feature_class":"P",
    "gn:feature_code":"PPL",
    "gn:name":"Rancasaat",
    "gn:population":0,
    "gn:timezone":"Asia/Jakarta",
    "iso:country":"ID",
    "name:ind_x_preferred":[
        "Rancasaat"
    ],
    "name:und_x_variant":[
        "Rantjasaat Dua",
        "Rantjasaat 2",
        "Rancasaat Dua"
    ],
    "wof:lang_x_official":[
        "ind"
    ],
    "wof:lang_x_spoken":[
        "ind",
        "eng"
    ],
    "wof:name":"Rancasaat",
    "wof:placetype":"locality"
},
  "geometry": {"coordinates":[106.2773,-6.3117],"type":"Point"}
}