{
  "type": "Feature",
  "properties": {
    "gn:admin1_code":"38.0",
    "gn:asciiname":"Gilirang",
    "gn:country_code":"ID",
    "gn:dem":44,
    "gn:feature_class":"P",
    "gn:feature_code":"PPL",
    "gn:name":"Gilirang",
    "gn:population":0,
    "gn:timezone":"Asia/Makassar",
    "iso:country":"ID",
    "name:ind_x_preferred":[
        "Gilirang"
    ],
    "wof:name":"Gilirang",
    "wof:placetype":"locality"
},
  "geometry": {"coordinates":[120.1739,-3.9366],"type":"Point"}
}