{
  "type": "Feature",
  "properties": {
    "gn:admin1_code":"7.0",
    "gn:asciiname":"Galah",
    "gn:country_code":"ID",
    "gn:dem":291,
    "gn:feature_class":"P",
    "gn:feature_code":"PPL",
    "gn:name":"Galah",
    "gn:population":0,
    "gn:timezone":"Asia/Jakarta",
    "iso:country":"ID",
    "name:ara_x_preferred":[
        "\u0628\u0628\u063a\u0627\u0621 \u062c\u0627\u0644\u0627"
    ],
    "name:bel_x_preferred":[
        "\u041a\u0430\u043a\u0430\u0434\u0443 \u0440\u0443\u0436\u043e\u0432\u044b"
    ],
    "name:bre_x_preferred":[
        "Kaketou galah"
    ],
    "name:bul_x_preferred":[
        "\u0420\u043e\u0437\u043e\u0432\u043e \u043a\u0430\u043a\u0430\u0434\u0443"
    ],
    "name:cat_x_preferred":[
        "Cacatua galah"
    ],
    "name:ceb_x_preferred":[
        "Eolophus roseicapilla"
    ],
    "name:ces_x_preferred":[
        "Kakadu r\u016f\u017eov\u00fd"
    ],
    "name:cym_x_preferred":[
        "Gala"
    ],
    "name:dan_x_preferred":[
        "Rosa kakadue"
    ],
    "name:deu_x_preferred":[
        "Rosakakadu"
    ],
    "name:epo_x_preferred":[
        "Rozbrusta kakatuo"
    ],
    "name:eus_x_preferred":[
        "Eolophus roseicapilla"
    ],
    "name:fas_x_preferred":[
        "\u0637\u0648\u0637\u06cc\u200c\u06a9\u0627\u06a9\u0644\u06cc \u0633\u06cc\u0646\u0647\u200c\u0635\u0648\u0631\u062a\u06cc"
    ],
    "name:fin_x_preferred":[
        "Ruusukakadu"
    ],
    "name:fra_x_preferred":[
        "Cacato\u00e8s rosalbin"
    ],
    "name:heb_x_preferred":[
        "\u05e7\u05e7\u05d3\u05d5 \u05d5\u05e8\u05d3\u05e8\u05d3"
    ],
    "name:hrv_x_preferred":[
        "Ru\u017ei\u010dasti kakadu"
    ],
    "name:hun_x_preferred":[
        "R\u00f3zs\u00e1s kakadu"
    ],
    "name:hye_x_preferred":[
        "\u054e\u0561\u0580\u0564\u0561\u0563\u0578\u0582\u0575\u0576 \u056f\u0561\u056f\u0561\u0564\u0578\u0582"
    ],
    "name:ind_x_preferred":[
        "Kakatua galah"
    ],
    "name:ita_x_preferred":[
        "Eolophus roseicapilla"
    ],
    "name:jpn_x_preferred":[
        "\u30e2\u30e2\u30a4\u30ed\u30a4\u30f3\u30b3"
    ],
    "name:lit_x_preferred":[
        "Ro\u017ein\u0117 kakadu"
    ],
    "name:mal_x_preferred":[
        "\u0d17\u0d3e\u0d32"
    ],
    "name:mrj_x_preferred":[
        "\u041e\u0448\u0430\u043b\u0433\u044b-\u044f\u043a\u0448\u0430\u0440\u0438\u043a\u04d3 \u043a\u0430\u043a\u0430\u0434\u0443"
    ],
    "name:msa_x_preferred":[
        "Galah"
    ],
    "name:nld_x_preferred":[
        "Roze kaketoe"
    ],
    "name:nno_x_preferred":[
        "Rosenkakadu"
    ],
    "name:pnb_x_preferred":[
        "\u06af\u0644\u0627\u0628\u06cc \u0686\u06be\u0627\u062a\u06cc"
    ],
    "name:pol_x_preferred":[
        "Kakadu r\u00f3\u017cowa"
    ],
    "name:por_x_preferred":[
        "Galah"
    ],
    "name:rus_x_preferred":[
        "\u0420\u043e\u0437\u043e\u0432\u044b\u0439 \u043a\u0430\u043a\u0430\u0434\u0443"
    ],
    "name:slk_x_preferred":[
        "Eolophus"
    ],
    "name:spa_x_preferred":[
        "Eolophus roseicapilla"
    ],
    "name:swe_x_preferred":[
        "Rosenkakadua"
    ],
    "name:tur_x_preferred":[
        "Galah"
    ],
    "name:ukr_x_preferred":[
        "\u0420\u043e\u0436\u0435\u0432\u0438\u0439 \u043a\u0430\u043a\u0430\u0434\u0443"
    ],
    "name:vie_x_preferred":[
        "Eolophus roseicapilla"
    ],
    "name:war_x_preferred":[
        "Eolophus roseicapilla"
    ],
    "name:zho_x_preferred":[
        "\u7c89\u7ea2\u51e4\u5934\u9e66\u9e49"
    ],
    "wof:lang_x_official":[
        "ind"
    ],
    "wof:lang_x_spoken":[
        "ind",
        "eng"
    ],
    "wof:name":"Galah",
    "wof:placetype":"locality"
},
  "geometry": {"coordinates":[110.61221999999999,-7.61417],"type":"Point"}
}