{
  "type": "Feature",
  "properties": {
    "gn:admin1_code":"7.0",
    "gn:asciiname":"Galah",
    "gn:country_code":"ID",
    "gn:dem":291,
    "gn:feature_class":"P",
    "gn:feature_code":"PPL",
    "gn:name":"Galah",
    "gn:population":0,
    "gn:timezone":"Asia/Jakarta",
    "iso:country":"ID",
    "wof:name":"Galah",
    "wof:placetype":"locality"
},
  "geometry": {"coordinates":[110.61221999999999,-7.61417],"type":"Point"}
}