{
  "type": "Feature",
  "properties": {
    "gn:admin1_code":"38",
    "gn:asciiname":"Sabang Alau",
    "gn:country_code":"ID",
    "gn:dem":11,
    "gn:feature_class":"P",
    "gn:feature_code":"PPL",
    "gn:name":"Sabang Alau",
    "gn:population":0,
    "gn:timezone":"Asia/Makassar",
    "iso:country":"ID",
    "name:ind_x_preferred":[
        "Sabang Alau"
    ],
    "wof:name":"Sabang Alau",
    "wof:placetype":"locality"
},
  "geometry": {"coordinates":[120.095,-4.1494],"type":"Point"}
}