{
  "type": "Feature",
  "properties": {
    "gn:admin1_code":"8.0",
    "gn:asciiname":"Mendogo Lor",
    "gn:country_code":"ID",
    "gn:dem":7,
    "gn:feature_class":"P",
    "gn:feature_code":"PPLA4",
    "gn:name":"Mendogo Lor",
    "gn:population":0,
    "gn:timezone":"Asia/Jakarta",
    "iso:country":"ID",
    "name:ind_x_preferred":[
        "Mendogo Lor"
    ],
    "wof:name":"Mendogo Lor",
    "wof:placetype":"locality"
},
  "geometry": {"coordinates":[112.4924,-7.0879],"type":"Point"}
}