{
  "type": "Feature",
  "properties": {
    "gn:admin1_code":"7.0",
    "gn:asciiname":"Karangtalun",
    "gn:country_code":"ID",
    "gn:dem":1082,
    "gn:feature_class":"P",
    "gn:feature_code":"PPL",
    "gn:name":"Karangtalun",
    "gn:population":0,
    "gn:timezone":"Asia/Jakarta",
    "iso:country":"ID",
    "wof:name":"Karangtalun",
    "wof:placetype":"locality"
},
  "geometry": {"coordinates":[110.49611000000002,-7.46167],"type":"Point"}
}