{
  "type": "Feature",
  "properties": {
    "gn:admin1_code":"24",
    "gn:asciiname":"Pinang",
    "gn:country_code":"ID",
    "gn:dem":482,
    "gn:feature_class":"P",
    "gn:feature_code":"PPL",
    "gn:name":"Pinang",
    "gn:population":0,
    "gn:timezone":"Asia/Jakarta",
    "iso:country":"ID",
    "name:ceb_x_preferred":[
        "Pinang"
    ],
    "name:ind_x_preferred":[
        "Pinang"
    ],
    "name:msa_x_preferred":[
        "Pinang"
    ],
    "name:swe_x_preferred":[
        "Pinang"
    ],
    "wof:name":"Pinang",
    "wof:placetype":"locality"
},
  "geometry": {"coordinates":[100.1521,0.0247],"type":"Point"}
}