{
  "type": "Feature",
  "properties": {
    "gn:admin1_code":"7.0",
    "gn:asciiname":"Kalices",
    "gn:country_code":"ID",
    "gn:dem":760,
    "gn:feature_class":"P",
    "gn:feature_code":"PPL",
    "gn:name":"Kalices",
    "gn:population":0,
    "gn:timezone":"Asia/Jakarta",
    "iso:country":"ID",
    "wof:name":"Kalices",
    "wof:placetype":"locality"
},
  "geometry": {"coordinates":[110.35056000000002,-7.27194],"type":"Point"}
}