{
  "type": "Feature",
  "properties": {
    "gn:admin1_code":"2",
    "gn:asciiname":"Ceking",
    "gn:country_code":"ID",
    "gn:dem":47,
    "gn:feature_class":"P",
    "gn:feature_code":"PPL",
    "gn:name":"Ceking",
    "gn:population":0,
    "gn:timezone":"Asia/Makassar",
    "iso:country":"ID",
    "name:ind_x_preferred":[
        "Ceking"
    ],
    "wof:name":"Ceking",
    "wof:placetype":"locality"
},
  "geometry": {"coordinates":[115.4456,-8.1672],"type":"Point"}
}