{
  "type": "Feature",
  "properties": {
    "gn:admin1_code":"18",
    "gn:asciiname":"Palengpau",
    "gn:country_code":"ID",
    "gn:dem":920,
    "gn:feature_class":"P",
    "gn:feature_code":"PPL",
    "gn:name":"Palengpau",
    "gn:population":0,
    "gn:timezone":"Asia/Makassar",
    "iso:country":"ID",
    "name:ind_x_preferred":[
        "Palengpau"
    ],
    "wof:name":"Palengpau",
    "wof:placetype":"locality"
},
  "geometry": {"coordinates":[120.8133,-8.608],"type":"Point"}
}