{
  "type": "Feature",
  "properties": {
    "gn:admin1_code":"3.0",
    "gn:asciiname":"Lubuktanjung",
    "gn:country_code":"ID",
    "gn:dem":27,
    "gn:feature_class":"P",
    "gn:feature_code":"PPL",
    "gn:name":"Lubuktanjung",
    "gn:population":0,
    "gn:timezone":"Asia/Jakarta",
    "iso:country":"ID",
    "name:und_x_variant":[
        "Lubuktandjung",
        "Lubuktanjung"
    ],
    "wof:name":"Lubuktanjung",
    "wof:placetype":"locality"
},
  "geometry": {"coordinates":[102.1598,-3.5769],"type":"Point"}
}