{
  "type": "Feature",
  "properties": {
    "gn:admin1_code":"8.0",
    "gn:asciiname":"Sumberayu",
    "gn:country_code":"ID",
    "gn:dem":200,
    "gn:feature_class":"P",
    "gn:feature_code":"PPL",
    "gn:name":"Sumberayu",
    "gn:population":0,
    "gn:timezone":"Asia/Jakarta",
    "iso:country":"ID",
    "name:ind_x_preferred":[
        "Sumberayu"
    ],
    "wof:name":"Sumberayu",
    "wof:placetype":"locality"
},
  "geometry": {"coordinates":[111.9909,-7.4422],"type":"Point"}
}