{
  "type": "Feature",
  "properties": {
    "gn:admin1_code":"15.0",
    "gn:asciiname":"Telukdalam",
    "gn:country_code":"ID",
    "gn:dem":26,
    "gn:feature_class":"P",
    "gn:feature_code":"PPL",
    "gn:name":"Telukdalam",
    "gn:population":0,
    "gn:timezone":"Asia/Jakarta",
    "iso:country":"ID",
    "name:ind_x_preferred":[
        "Telukdalam"
    ],
    "name:ind_x_variant":[
        "Telakdalem"
    ],
    "wof:lang_x_official":[
        "ind"
    ],
    "wof:lang_x_spoken":[
        "ind",
        "eng"
    ],
    "wof:name":"Telukdalam",
    "wof:placetype":"locality"
},
  "geometry": {"coordinates":[105.47606,-4.79048],"type":"Point"}
}