{
  "type": "Feature",
  "properties": {
    "gn:admin1_code":"26",
    "gn:asciiname":"Kampung Baru",
    "gn:country_code":"ID",
    "gn:dem":323,
    "gn:feature_class":"P",
    "gn:feature_code":"PPL",
    "gn:name":"Kampung Baru",
    "gn:population":0,
    "gn:timezone":"Asia/Jakarta",
    "iso:country":"ID",
    "name:ind_x_preferred":[
        "Kampung Baru"
    ],
    "name:msa_x_preferred":[
        "Kampung baru"
    ],
    "name:nld_x_preferred":[
        "Kampung Baru"
    ],
    "wof:name":"Kampung Baru",
    "wof:placetype":"locality"
},
  "geometry": {"coordinates":[99.2002,2.8045],"type":"Point"}
}