{
  "type": "Feature",
  "properties": {
    "gn:admin1_code":"8.0",
    "gn:asciiname":"Kalirejo",
    "gn:country_code":"ID",
    "gn:dem":90,
    "gn:feature_class":"P",
    "gn:feature_code":"PPL",
    "gn:name":"Kalirejo",
    "gn:population":0,
    "gn:timezone":"Asia/Jakarta",
    "iso:country":"ID",
    "name:ind_x_preferred":[
        "Kalirejo"
    ],
    "wof:name":"Kalirejo",
    "wof:placetype":"locality"
},
  "geometry": {"coordinates":[111.7972,-8.1883],"type":"Point"}
}