{
  "type": "Feature",
  "properties": {
    "gn:admin1_code":"30",
    "gn:asciiname":"Jatirah",
    "gn:country_code":"ID",
    "gn:dem":65,
    "gn:feature_class":"P",
    "gn:feature_code":"PPL",
    "gn:name":"Jatirah",
    "gn:population":0,
    "gn:timezone":"Asia/Jakarta",
    "iso:country":"ID",
    "name:ind_x_preferred":[
        "Jatirah"
    ],
    "wof:name":"Jatirah",
    "wof:placetype":"locality"
},
  "geometry": {"coordinates":[108.6183,-6.8856],"type":"Point"}
}