{
  "type": "Feature",
  "properties": {
    "gn:admin1_code":"30",
    "gn:asciiname":"Cikokosan",
    "gn:country_code":"ID",
    "gn:dem":431,
    "gn:feature_class":"P",
    "gn:feature_code":"PPL",
    "gn:name":"Cikokosan",
    "gn:population":0,
    "gn:timezone":"Asia/Jakarta",
    "iso:country":"ID",
    "name:ind_x_preferred":[
        "Cikokosan"
    ],
    "wof:name":"Cikokosan",
    "wof:placetype":"locality"
},
  "geometry": {"coordinates":[107.39556,-6.81222],"type":"Point"}
}