{
  "type": "Feature",
  "properties": {
    "gn:admin1_code":"8.0",
    "gn:asciiname":"Kalak",
    "gn:country_code":"ID",
    "gn:dem":185,
    "gn:feature_class":"P",
    "gn:feature_code":"PPL",
    "gn:name":"Kalak",
    "gn:population":0,
    "gn:timezone":"Asia/Jakarta",
    "iso:country":"ID",
    "name:ceb_x_preferred":[
        "Kalak"
    ],
    "name:ind_x_preferred":[
        "Kalak"
    ],
    "name:swe_x_preferred":[
        "Kalak"
    ],
    "wof:name":"Kalak",
    "wof:placetype":"locality"
},
  "geometry": {"coordinates":[110.93222,-8.19333],"type":"Point"}
}