{
  "type": "Feature",
  "properties": {
    "gn:admin1_code":"38",
    "gn:asciiname":"Bokin",
    "gn:country_code":"ID",
    "gn:dem":1010,
    "gn:feature_class":"P",
    "gn:feature_code":"PPL",
    "gn:name":"Bokin",
    "gn:population":0,
    "gn:timezone":"Asia/Makassar",
    "iso:country":"ID",
    "name:fra_x_preferred":[
        "Bokin"
    ],
    "name:ind_x_preferred":[
        "Bokin"
    ],
    "wof:lang_x_official":[
        "ind"
    ],
    "wof:lang_x_spoken":[
        "ind",
        "eng"
    ],
    "wof:name":"Bokin",
    "wof:placetype":"locality"
},
  "geometry": {"coordinates":[119.9722,-3.0224],"type":"Point"}
}