{
  "type": "Feature",
  "properties": {
    "gn:admin1_code":"7.0",
    "gn:asciiname":"Tambakan",
    "gn:country_code":"ID",
    "gn:dem":470,
    "gn:feature_class":"P",
    "gn:feature_code":"PPL",
    "gn:name":"Tambakan",
    "gn:population":0,
    "gn:timezone":"Asia/Jakarta",
    "iso:country":"ID",
    "wof:name":"Tambakan",
    "wof:placetype":"locality"
},
  "geometry": {"coordinates":[110.10111000000001,-7.53194],"type":"Point"}
}