{
  "type": "Feature",
  "properties": {
    "gn:admin1_code":"30.0",
    "gn:asciiname":"Pasirtanjung 1",
    "gn:country_code":"ID",
    "gn:dem":131,
    "gn:feature_class":"P",
    "gn:feature_code":"PPL",
    "gn:name":"Pasirtanjung 1",
    "gn:population":0,
    "gn:timezone":"Asia/Jakarta",
    "iso:country":"ID",
    "name:und_x_variant":[
        "Pasirtandjung",
        "Pasirlandjoeng",
        "Pasirtandjoeng",
        "Pasirtanjung 1"
    ],
    "wof:lang_x_official":[
        "ind"
    ],
    "wof:lang_x_spoken":[
        "ind",
        "eng"
    ],
    "wof:name":"Pasirtanjung 1",
    "wof:placetype":"locality"
},
  "geometry": {"coordinates":[107.15194,-6.59833],"type":"Point"}
}