{
  "type": "Feature",
  "properties": {
    "gn:admin1_code":"26",
    "gn:asciiname":"Gunungtua",
    "gn:country_code":"ID",
    "gn:dem":194,
    "gn:feature_class":"P",
    "gn:feature_code":"PPL",
    "gn:name":"Gunungtua",
    "gn:population":0,
    "gn:timezone":"Asia/Jakarta",
    "iso:country":"ID",
    "name:ind_x_preferred":[
        "Gunungtua"
    ],
    "wof:name":"Gunungtua",
    "wof:placetype":"locality"
},
  "geometry": {"coordinates":[99.4597,1.3266],"type":"Point"}
}