{
  "type": "Feature",
  "properties": {
    "gn:admin1_code":"30",
    "gn:asciiname":"Nambo",
    "gn:country_code":"ID",
    "gn:dem":661,
    "gn:feature_class":"P",
    "gn:feature_code":"PPL",
    "gn:name":"Nambo",
    "gn:population":0,
    "gn:timezone":"Asia/Jakarta",
    "iso:country":"ID",
    "name:ceb_x_preferred":[
        "Nambo"
    ],
    "name:ind_x_preferred":[
        "Nambo"
    ],
    "name:swe_x_preferred":[
        "Nambo"
    ],
    "wof:name":"Nambo",
    "wof:placetype":"locality"
},
  "geometry": {"coordinates":[107.33667,-6.91861],"type":"Point"}
}