{
  "type": "Feature",
  "properties": {
    "gn:admin1_code":"26.0",
    "gn:asciiname":"Bahbayu",
    "gn:country_code":"ID",
    "gn:dem":102,
    "gn:feature_class":"P",
    "gn:feature_code":"PPL",
    "gn:name":"Bahbayu",
    "gn:population":0,
    "gn:timezone":"Asia/Jakarta",
    "iso:country":"ID",
    "name:ind_x_preferred":[
        "Bahbayu"
    ],
    "name:und_x_variant":[
        "Bahbaju",
        "Bahbajoe"
    ],
    "wof:lang_x_official":[
        "ind"
    ],
    "wof:lang_x_spoken":[
        "ind",
        "eng"
    ],
    "wof:name":"Bahbayu",
    "wof:placetype":"locality"
},
  "geometry": {"coordinates":[99.2628,3.0634],"type":"Point"}
}