{
  "type": "Feature",
  "properties": {
    "gn:admin1_code":"37.0",
    "gn:asciiname":"Baganpulauruku",
    "gn:country_code":"ID",
    "gn:dem":0,
    "gn:feature_class":"P",
    "gn:feature_code":"PPL",
    "gn:name":"Baganpulauruku",
    "gn:population":0,
    "gn:timezone":"Asia/Jakarta",
    "iso:country":"ID",
    "name:ind_x_preferred":[
        "Baganpulauruku"
    ],
    "wof:name":"Baganpulauruku",
    "wof:placetype":"locality"
},
  "geometry": {"coordinates":[103.3793,-0.7126],"type":"Point"}
}