{
  "type": "Feature",
  "properties": {
    "gn:admin1_code":"38.0",
    "gn:asciiname":"Totira",
    "gn:country_code":"ID",
    "gn:dem":1655,
    "gn:feature_class":"P",
    "gn:feature_code":"PPL",
    "gn:name":"Totira",
    "gn:population":0,
    "gn:timezone":"Asia/Makassar",
    "iso:country":"ID",
    "name:ind_x_preferred":[
        "Totira"
    ],
    "wof:name":"Totira",
    "wof:placetype":"locality"
},
  "geometry": {"coordinates":[119.86060000000001,-2.8467],"type":"Point"}
}