{
  "type": "Feature",
  "properties": {
    "gn:admin1_code":"24.0",
    "gn:asciiname":"Tangahpadang",
    "gn:country_code":"ID",
    "gn:dem":22,
    "gn:feature_class":"P",
    "gn:feature_code":"PPL",
    "gn:name":"Tangahpadang",
    "gn:population":0,
    "gn:timezone":"Asia/Jakarta",
    "iso:country":"ID",
    "name:ind_x_preferred":[
        "Tangahpadang"
    ],
    "wof:name":"Tangahpadang",
    "wof:placetype":"locality"
},
  "geometry": {"coordinates":[100.8891,-1.8925],"type":"Point"}
}