{
  "type": "Feature",
  "properties": {
    "gn:admin1_code":"30.0",
    "gn:asciiname":"Gintung",
    "gn:country_code":"ID",
    "gn:dem":445,
    "gn:feature_class":"P",
    "gn:feature_code":"PPL",
    "gn:name":"Gintung",
    "gn:population":0,
    "gn:timezone":"Asia/Jakarta",
    "iso:country":"ID",
    "name:ind_x_preferred":[
        "Gintung"
    ],
    "wof:name":"Gintung",
    "wof:placetype":"locality"
},
  "geometry": {"coordinates":[108.4199,-7.2072],"type":"Point"}
}