{
  "type": "Feature",
  "properties": {
    "gn:admin1_code":"8.0",
    "gn:asciiname":"Sumberjati",
    "gn:country_code":"ID",
    "gn:dem":110,
    "gn:feature_class":"P",
    "gn:feature_code":"PPL",
    "gn:name":"Sumberjati",
    "gn:population":0,
    "gn:timezone":"Asia/Jakarta",
    "iso:country":"ID",
    "name:ind_x_preferred":[
        "Sumberjati"
    ],
    "wof:name":"Sumberjati",
    "wof:placetype":"locality"
},
  "geometry": {"coordinates":[112.52330000000001,-7.5598],"type":"Point"}
}