{
  "type": "Feature",
  "properties": {
    "gn:admin1_code":"30",
    "gn:asciiname":"Selaawi",
    "gn:country_code":"ID",
    "gn:dem":765,
    "gn:feature_class":"P",
    "gn:feature_code":"PPL",
    "gn:name":"Selaawi",
    "gn:population":0,
    "gn:timezone":"Asia/Jakarta",
    "iso:country":"ID",
    "name:ind_x_preferred":[
        "Selaawi"
    ],
    "name:und_x_variant":[
        "Seldawi 1"
    ],
    "wof:lang_x_official":[
        "ind"
    ],
    "wof:lang_x_spoken":[
        "ind",
        "eng"
    ],
    "wof:name":"Selaawi",
    "wof:placetype":"locality"
},
  "geometry": {"coordinates":[107.58944,-6.69083],"type":"Point"}
}