{
  "type": "Feature",
  "properties": {
    "gn:admin1_code":"8",
    "gn:asciiname":"Karanglo",
    "gn:country_code":"ID",
    "gn:dem":468,
    "gn:feature_class":"P",
    "gn:feature_code":"PPL",
    "gn:name":"Karanglo",
    "gn:population":0,
    "gn:timezone":"Asia/Jakarta",
    "iso:country":"ID",
    "name:ind_x_preferred":[
        "Karanglo"
    ],
    "wof:name":"Karanglo",
    "wof:placetype":"locality"
},
  "geometry": {"coordinates":[111.25167,-7.55528],"type":"Point"}
}