{
  "type": "Feature",
  "properties": {
    "gn:admin1_code":"28.0",
    "gn:asciiname":"Walikun",
    "gn:country_code":"ID",
    "gn:dem":11,
    "gn:feature_class":"P",
    "gn:feature_code":"PPL",
    "gn:name":"Walikun",
    "gn:population":0,
    "gn:timezone":"Asia/Jayapura",
    "iso:country":"ID",
    "name:ind_x_preferred":[
        "Walikun"
    ],
    "name:ind_x_variant":[
        "Walikum"
    ],
    "name:und_x_variant":[
        "Wa Likoen"
    ],
    "wof:lang_x_official":[
        "ind"
    ],
    "wof:lang_x_spoken":[
        "ind",
        "eng"
    ],
    "wof:name":"Walikun",
    "wof:placetype":"locality"
},
  "geometry": {"coordinates":[126.99536000000001,-3.72599],"type":"Point"}
}