{
  "type": "Feature",
  "properties": {
    "gn:country":"ID",
    "gn:fcode":"ADM3",
    "gn:pop":0,
    "iso:country":"ID",
    "qs:name":"Kecamatan Ngawen",
    "qs:photos_9r":0,
    "qs:photos_sr":0,
    "qs:pop_sr":"0",
    "wof:name":"Kecamatan Ngawen",
    "wof:placetype":"localadmin",
    "wof:population":0
},
  "geometry": {"coordinates":[110.67944,-7.82083],"type":"Point"}
}