{
  "type": "Feature",
  "properties": {
    "gn:admin1_code":"33.0",
    "gn:asciiname":"Karag",
    "gn:country_code":"ID",
    "gn:dem":148,
    "gn:feature_class":"P",
    "gn:feature_code":"PPL",
    "gn:name":"Karag",
    "gn:population":0,
    "gn:timezone":"Asia/Jakarta",
    "iso:country":"ID",
    "name:ara_x_preferred":[
        "\u0643\u0627\u0631\u063a"
    ],
    "name:azb_x_preferred":[
        "\u0643\u0627\u0631\u06af(\u0633\u0648\u06cc\u0648\u0642\u200c\u0628\u0648\u0644\u0627\u0642)"
    ],
    "name:aze_x_preferred":[
        "K\u0259r\u0259g"
    ],
    "name:ckb_x_preferred":[
        "\u06a9\u0627\u0631\u06af"
    ],
    "name:fas_x_preferred":[
        "\u06a9\u0627\u0631\u06af"
    ],
    "name:ind_x_preferred":[
        "Karag"
    ],
    "name:kur_x_preferred":[
        "Karg"
    ],
    "name:msa_x_preferred":[
        "Karag"
    ],
    "wof:lang_x_official":[
        "ind"
    ],
    "wof:lang_x_spoken":[
        "ind",
        "eng"
    ],
    "wof:name":"Karag",
    "wof:placetype":"locality"
},
  "geometry": {"coordinates":[106.06140000000001,-6.3637],"type":"Point"}
}