{
  "type": "Feature",
  "properties": {
    "gn:admin1_code":"3.0",
    "gn:asciiname":"Padang",
    "gn:country_code":"ID",
    "gn:dem":24,
    "gn:feature_class":"P",
    "gn:feature_code":"PPL",
    "gn:name":"Padang",
    "gn:population":0,
    "gn:timezone":"Asia/Jakarta",
    "iso:country":"ID",
    "name:ace_x_preferred":[
        "Padang"
    ],
    "name:afr_x_preferred":[
        "Padang"
    ],
    "name:ara_x_preferred":[
        "\u0628\u0627\u062f\u0646\u063a"
    ],
    "name:azb_x_preferred":[
        "\u067e\u0627\u062f\u0627\u0646\u06af"
    ],
    "name:bel_x_preferred":[
        "\u041f\u0430\u0434\u0430\u043d\u0433"
    ],
    "name:bul_x_preferred":[
        "\u041f\u0430\u0434\u0430\u043d\u0433"
    ],
    "name:cat_x_preferred":[
        "Padang"
    ],
    "name:ceb_x_preferred":[
        "Padang"
    ],
    "name:ces_x_preferred":[
        "Padang"
    ],
    "name:deu_x_preferred":[
        "Padang"
    ],
    "name:epo_x_preferred":[
        "Padango"
    ],
    "name:eus_x_preferred":[
        "Padang"
    ],
    "name:fas_x_preferred":[
        "\u067e\u0627\u062f\u0646\u06af"
    ],
    "name:fin_x_preferred":[
        "Padang"
    ],
    "name:fra_x_preferred":[
        "Padang"
    ],
    "name:fry_x_preferred":[
        "Padang"
    ],
    "name:gor_x_preferred":[
        "Kota Padang"
    ],
    "name:hrv_x_preferred":[
        "Padang"
    ],
    "name:hun_x_preferred":[
        "Padang"
    ],
    "name:ind_x_preferred":[
        "Padang"
    ],
    "name:ind_x_variant":[
        "Kota Padang"
    ],
    "name:ita_x_preferred":[
        "Padang"
    ],
    "name:jav_x_preferred":[
        "Kutha Padang"
    ],
    "name:jpn_x_preferred":[
        "\u30d1\u30c0\u30f3"
    ],
    "name:lit_x_preferred":[
        "Padangas"
    ],
    "name:mal_x_preferred":[
        "\u0d2a\u0d21\u0d3e\u0d19\u0d4d"
    ],
    "name:mar_x_preferred":[
        "\u092a\u093e\u0926\u093e\u0902\u0917"
    ],
    "name:min_x_preferred":[
        "Kota Padang"
    ],
    "name:mlg_x_preferred":[
        "Kota Padang"
    ],
    "name:msa_x_preferred":[
        "Kota Padang"
    ],
    "name:nld_x_preferred":[
        "Padang"
    ],
    "name:nno_x_preferred":[
        "Padang"
    ],
    "name:nor_x_preferred":[
        "Padang"
    ],
    "name:pnb_x_preferred":[
        "\u067e\u0627\u0688\u0627\u0646\u06af"
    ],
    "name:pol_x_preferred":[
        "Padang"
    ],
    "name:por_x_preferred":[
        "Padang"
    ],
    "name:ron_x_preferred":[
        "Padang"
    ],
    "name:rus_x_preferred":[
        "\u041f\u0430\u0434\u0430\u043d\u0433"
    ],
    "name:sah_x_preferred":[
        "\u041f\u0430\u0434\u0430\u043d\u0433"
    ],
    "name:sco_x_preferred":[
        "Padang"
    ],
    "name:spa_x_preferred":[
        "Padang"
    ],
    "name:sun_x_preferred":[
        "Kota Padang"
    ],
    "name:swe_x_preferred":[
        "Padang"
    ],
    "name:tam_x_preferred":[
        "\u0baa\u0b9f\u0bbe\u0b99\u0bcd"
    ],
    "name:tha_x_preferred":[
        "\u0e1b\u0e32\u0e14\u0e31\u0e07"
    ],
    "name:tur_x_preferred":[
        "Padang"
    ],
    "name:ukr_x_preferred":[
        "\u041f\u0430\u0434\u0430\u043d\u0433"
    ],
    "name:urd_x_preferred":[
        "\u067e\u0627\u062f\u0627\u0646\u06af"
    ],
    "name:uzb_x_preferred":[
        "Padang"
    ],
    "name:vie_x_preferred":[
        "Padang"
    ],
    "name:war_x_preferred":[
        "Padang"
    ],
    "name:wuu_x_preferred":[
        "\u5df4\u6771"
    ],
    "name:zho_x_preferred":[
        "\u5df4\u4e1c"
    ],
    "wof:name":"Padang",
    "wof:placetype":"locality"
},
  "geometry": {"coordinates":[102.2664,-3.7026],"type":"Point"}
}