{
  "type": "Feature",
  "properties": {
    "gn:admin1_code":"7",
    "gn:asciiname":"Gesing",
    "gn:country_code":"ID",
    "gn:dem":659,
    "gn:feature_class":"P",
    "gn:feature_code":"PPL",
    "gn:name":"Gesing",
    "gn:population":0,
    "gn:timezone":"Asia/Jakarta",
    "iso:country":"ID",
    "name:ind_x_preferred":[
        "Gesing"
    ],
    "wof:name":"Gesing",
    "wof:placetype":"locality"
},
  "geometry": {"coordinates":[110.18138999999999,-7.24111],"type":"Point"}
}