{
  "type": "Feature",
  "properties": {
    "gn:admin1_code":"7.0",
    "gn:asciiname":"Bonorejo",
    "gn:country_code":"ID",
    "gn:dem":49,
    "gn:feature_class":"P",
    "gn:feature_code":"PPL",
    "gn:name":"Bonorejo",
    "gn:population":0,
    "gn:timezone":"Asia/Jakarta",
    "iso:country":"ID",
    "name:ind_x_preferred":[
        "Bonorejo"
    ],
    "wof:name":"Bonorejo",
    "wof:placetype":"locality"
},
  "geometry": {"coordinates":[111.0604,-6.8888],"type":"Point"}
}