{
  "type": "Feature",
  "properties": {
    "gn:admin1_code":"8",
    "gn:asciiname":"Patuh",
    "gn:country_code":"ID",
    "gn:dem":816,
    "gn:feature_class":"P",
    "gn:feature_code":"PPL",
    "gn:name":"Patuh",
    "gn:population":0,
    "gn:timezone":"Asia/Jakarta",
    "iso:country":"ID",
    "name:ind_x_preferred":[
        "Patuh"
    ],
    "wof:name":"Patuh",
    "wof:placetype":"locality"
},
  "geometry": {"coordinates":[111.30944,-7.93917],"type":"Point"}
}