{
  "type": "Feature",
  "properties": {
    "gn:admin1_code":"7",
    "gn:asciiname":"Tenggara",
    "gn:country_code":"ID",
    "gn:dem":746,
    "gn:feature_class":"P",
    "gn:feature_code":"PPL",
    "gn:name":"Tenggara",
    "gn:population":0,
    "gn:timezone":"Asia/Jakarta",
    "iso:country":"ID",
    "name:ind_x_preferred":[
        "Tenggara"
    ],
    "wof:name":"Tenggara",
    "wof:placetype":"locality"
},
  "geometry": {"coordinates":[109.91849999999999,-7.0858],"type":"Point"}
}