{
  "type": "Feature",
  "properties": {
    "gn:admin1_code":"30.0",
    "gn:asciiname":"Dawuan",
    "gn:country_code":"ID",
    "gn:dem":448,
    "gn:feature_class":"P",
    "gn:feature_code":"PPL",
    "gn:name":"Dawuan",
    "gn:population":0,
    "gn:timezone":"Asia/Jakarta",
    "iso:country":"ID",
    "name:ind_x_preferred":[
        "Dawuan"
    ],
    "wof:name":"Dawuan",
    "wof:placetype":"locality"
},
  "geometry": {"coordinates":[113.9312,-7.9721],"type":"Point"}
}