{
  "type": "Feature",
  "properties": {
    "gn:admin1_code":"38",
    "gn:asciiname":"Bollangi",
    "gn:country_code":"ID",
    "gn:dem":156,
    "gn:feature_class":"P",
    "gn:feature_code":"PPL",
    "gn:name":"Bollangi",
    "gn:population":0,
    "gn:timezone":"Asia/Makassar",
    "iso:country":"ID",
    "name:ind_x_preferred":[
        "Bollangi"
    ],
    "wof:name":"Bollangi",
    "wof:placetype":"locality"
},
  "geometry": {"coordinates":[119.5724,-5.234],"type":"Point"}
}