{
  "type": "Feature",
  "properties": {
    "gn:admin1_code":"32.0",
    "gn:asciiname":"Gunung Batu",
    "gn:country_code":"ID",
    "gn:dem":28,
    "gn:feature_class":"P",
    "gn:feature_code":"PPL",
    "gn:name":"Gunung Batu",
    "gn:population":0,
    "gn:timezone":"Asia/Jakarta",
    "iso:country":"ID",
    "name:ind_x_preferred":[
        "Gunung Batu"
    ],
    "name:ind_x_variant":[
        "Gunungatu"
    ],
    "name:und_x_variant":[
        "Goenoengbatoe",
        "Gunungbatu"
    ],
    "wof:lang_x_official":[
        "ind"
    ],
    "wof:lang_x_spoken":[
        "ind",
        "eng"
    ],
    "wof:name":"Gunung Batu",
    "wof:placetype":"locality"
},
  "geometry": {"coordinates":[104.70031,-3.6625],"type":"Point"}
}