{
  "type": "Feature",
  "properties": {
    "gn:admin1_code":"8",
    "gn:asciiname":"Pinggiran",
    "gn:country_code":"ID",
    "gn:dem":15,
    "gn:feature_class":"P",
    "gn:feature_code":"PPL",
    "gn:name":"Pinggiran",
    "gn:population":0,
    "gn:timezone":"Asia/Jakarta",
    "iso:country":"ID",
    "name:ind_x_preferred":[
        "Pinggiran"
    ],
    "wof:name":"Pinggiran",
    "wof:placetype":"locality"
},
  "geometry": {"coordinates":[112.33029999999999,-7.1515],"type":"Point"}
}