{
  "type": "Feature",
  "properties": {
    "gn:admin1_code":"7.0",
    "gn:asciiname":"Padas",
    "gn:country_code":"ID",
    "gn:dem":63,
    "gn:feature_class":"P",
    "gn:feature_code":"PPLA4",
    "gn:name":"Padas",
    "gn:population":0,
    "gn:timezone":"Asia/Jakarta",
    "iso:country":"ID",
    "name:ind_x_preferred":[
        "Padas"
    ],
    "wof:name":"Padas",
    "wof:placetype":"locality"
},
  "geometry": {"coordinates":[111.176,-6.8613],"type":"Point"}
}