{
  "type": "Feature",
  "properties": {
    "gn:admin1_code":"26",
    "gn:asciiname":"Pematangbuluh",
    "gn:country_code":"ID",
    "gn:dem":2,
    "gn:feature_class":"P",
    "gn:feature_code":"PPL",
    "gn:name":"Pematangbuluh",
    "gn:population":0,
    "gn:timezone":"Asia/Jakarta",
    "iso:country":"ID",
    "name:ind_x_preferred":[
        "Pematangbuluh"
    ],
    "wof:name":"Pematangbuluh",
    "wof:placetype":"locality"
},
  "geometry": {"coordinates":[99.229,3.4722],"type":"Point"}
}