{
  "type": "Feature",
  "properties": {
    "gn:admin1_code":"7.0",
    "gn:asciiname":"Plana",
    "gn:country_code":"ID",
    "gn:dem":48,
    "gn:feature_class":"P",
    "gn:feature_code":"PPL",
    "gn:name":"Plana",
    "gn:population":0,
    "gn:timezone":"Asia/Jakarta",
    "iso:country":"ID",
    "name:arg_x_preferred":[
        "Plana"
    ],
    "name:bos_x_preferred":[
        "Plana"
    ],
    "name:cat_x_preferred":[
        "Plana"
    ],
    "name:ceb_x_preferred":[
        "Plana"
    ],
    "name:deu_x_preferred":[
        "Plana"
    ],
    "name:fra_x_preferred":[
        "Plana"
    ],
    "name:hrv_x_preferred":[
        "Plana"
    ],
    "name:ind_x_preferred":[
        "Plana"
    ],
    "name:ita_x_preferred":[
        "Plana"
    ],
    "name:jpn_x_preferred":[
        "\u30d7\u30e9\u30ca"
    ],
    "name:lat_x_preferred":[
        "Plana"
    ],
    "name:nld_x_preferred":[
        "Plana"
    ],
    "name:por_x_preferred":[
        "Plana"
    ],
    "name:rus_x_preferred":[
        "\u041f\u043b\u0430\u043d\u0430"
    ],
    "name:slk_x_preferred":[
        "Plana"
    ],
    "name:slv_x_preferred":[
        "Plana"
    ],
    "name:srp_x_preferred":[
        "\u041f\u043b\u0430\u043d\u0430"
    ],
    "name:swe_x_preferred":[
        "Plana"
    ],
    "name:ukr_x_preferred":[
        "\u041f\u043b\u0430\u043d\u0430"
    ],
    "wof:lang_x_official":[
        "ind"
    ],
    "wof:lang_x_spoken":[
        "ind",
        "eng"
    ],
    "wof:name":"Plana",
    "wof:placetype":"locality"
},
  "geometry": {"coordinates":[109.36333,-7.49833],"type":"Point"}
}