{
  "type": "Feature",
  "properties": {
    "gn:country":"ID",
    "gn:fcode":"PPL",
    "gn:pop":0,
    "iso:country":"ID",
    "name:cat_x_preferred":[
        "Kartini"
    ],
    "name:deu_x_preferred":[
        "Kartini"
    ],
    "name:eng_x_preferred":[
        "Kartini"
    ],
    "name:fra_x_preferred":[
        "Kartini"
    ],
    "name:glg_x_preferred":[
        "Kartini"
    ],
    "name:ind_x_preferred":[
        "Kartini"
    ],
    "name:jav_x_preferred":[
        "Kartini"
    ],
    "name:jpn_x_preferred":[
        "\u30ab\u30eb\u30c6\u30a3\u30ea"
    ],
    "name:kor_x_preferred":[
        "\uce74\ub974\ud2f0\ub2c8"
    ],
    "name:msa_x_preferred":[
        "Kartini"
    ],
    "name:nan_x_preferred":[
        "Kartini"
    ],
    "name:nld_x_preferred":[
        "Kartini"
    ],
    "name:pol_x_preferred":[
        "Kartini"
    ],
    "name:rus_x_preferred":[
        "\u041a\u0430\u0440\u0442\u0438\u043d\u0438"
    ],
    "name:slv_x_preferred":[
        "Kartini"
    ],
    "name:spa_x_preferred":[
        "Kartini"
    ],
    "name:sun_x_preferred":[
        "Kartini"
    ],
    "name:swe_x_preferred":[
        "Kartini"
    ],
    "name:tgl_x_preferred":[
        "tagalod"
    ],
    "name:tha_x_preferred":[
        "\u0e01\u0e32\u0e23\u0e4c\u0e15\u0e35\u0e19\u0e35"
    ],
    "name:zho_x_preferred":[
        "\u5361\u8482\u59ae"
    ],
    "qs:name":"Kartini",
    "qs:name_adm0":"Indonesia",
    "qs:name_adm1":"Jakarta Raya",
    "qs:photos_9r":0,
    "qs:photos_sr":0,
    "qs:placetype":"Suburb",
    "qs:pop_sr":"0",
    "wd:wordcount":2327,
    "wof:name":"Kartini",
    "wof:placetype":"neighbourhood",
    "wof:population":0
},
  "geometry": {"coordinates":[106.8343,-6.1567],"type":"Point"}
}