{
  "type": "Feature",
  "properties": {
    "gn:admin1_code":"26",
    "gn:asciiname":"Lubuk Palas",
    "gn:country_code":"ID",
    "gn:dem":11,
    "gn:feature_class":"P",
    "gn:feature_code":"PPL",
    "gn:name":"Lubuk Palas",
    "gn:population":0,
    "gn:timezone":"Asia/Jakarta",
    "iso:country":"ID",
    "name:ind_x_preferred":[
        "Lubuk Palas"
    ],
    "wof:name":"Lubuk Palas",
    "wof:placetype":"locality"
},
  "geometry": {"coordinates":[99.78,3.0444],"type":"Point"}
}