{
  "type": "Feature",
  "properties": {
    "gn:admin1_code":"30",
    "gn:asciiname":"Kecokmesjid",
    "gn:country_code":"ID",
    "gn:dem":41,
    "gn:feature_class":"P",
    "gn:feature_code":"PPL",
    "gn:name":"Kecokmesjid",
    "gn:population":0,
    "gn:timezone":"Asia/Jakarta",
    "iso:country":"ID",
    "name:ind_x_preferred":[
        "Kecokmesjid"
    ],
    "name:und_x_variant":[
        "Ketjok 1",
        "Ketjok Satu",
        "Kecok Satu"
    ],
    "wof:lang_x_official":[
        "ind"
    ],
    "wof:lang_x_spoken":[
        "ind",
        "eng"
    ],
    "wof:name":"Kecokmesjid",
    "wof:placetype":"locality"
},
  "geometry": {"coordinates":[106.44694,-6.2775],"type":"Point"}
}