{
  "type": "Feature",
  "properties": {
    "gn:admin1_code":"7",
    "gn:asciiname":"Krandegan",
    "gn:country_code":"ID",
    "gn:dem":363,
    "gn:feature_class":"P",
    "gn:feature_code":"PPL",
    "gn:name":"Krandegan",
    "gn:population":0,
    "gn:timezone":"Asia/Jakarta",
    "iso:country":"ID",
    "name:ind_x_preferred":[
        "Krandegan"
    ],
    "wof:name":"Krandegan",
    "wof:placetype":"locality"
},
  "geometry": {"coordinates":[110.1448,-7.0853],"type":"Point"}
}