{
  "type": "Feature",
  "properties": {
    "gn:admin1_code":"1",
    "gn:asciiname":"Pengarapan",
    "gn:country_code":"ID",
    "gn:dem":925,
    "gn:feature_class":"P",
    "gn:feature_code":"PPL",
    "gn:name":"Pengarapan",
    "gn:population":0,
    "gn:timezone":"Asia/Jakarta",
    "iso:country":"ID",
    "name:ind_x_preferred":[
        "Pengarapan"
    ],
    "wof:name":"Pengarapan",
    "wof:placetype":"locality"
},
  "geometry": {"coordinates":[97.3612,4.0025],"type":"Point"}
}