{
  "type": "Feature",
  "properties": {
    "gn:admin1_code":"38.0",
    "gn:asciiname":"Kallan",
    "gn:country_code":"ID",
    "gn:dem":1108,
    "gn:feature_class":"P",
    "gn:feature_code":"PPL",
    "gn:name":"Kallan",
    "gn:population":0,
    "gn:timezone":"Asia/Makassar",
    "iso:country":"ID",
    "name:ind_x_preferred":[
        "Kallan"
    ],
    "wof:name":"Kallan",
    "wof:placetype":"locality"
},
  "geometry": {"coordinates":[119.9177,-2.8731],"type":"Point"}
}