{
  "type": "Feature",
  "properties": {
    "gn:admin1_code":"8",
    "gn:asciiname":"Patihan",
    "gn:country_code":"ID",
    "gn:dem":12,
    "gn:feature_class":"P",
    "gn:feature_code":"PPL",
    "gn:name":"Patihan",
    "gn:population":0,
    "gn:timezone":"Asia/Jakarta",
    "iso:country":"ID",
    "name:ind_x_preferred":[
        "Patihan"
    ],
    "wof:name":"Patihan",
    "wof:placetype":"locality"
},
  "geometry": {"coordinates":[112.13890000000001,-7.0961],"type":"Point"}
}