{
  "type": "Feature",
  "properties": {
    "gn:admin1_code":"8.0",
    "gn:asciiname":"Sumberpetung",
    "gn:country_code":"ID",
    "gn:dem":539,
    "gn:feature_class":"P",
    "gn:feature_code":"PPL",
    "gn:name":"Sumberpetung",
    "gn:population":0,
    "gn:timezone":"Asia/Jakarta",
    "iso:country":"ID",
    "name:ind_x_preferred":[
        "Sumberpetung"
    ],
    "wof:name":"Sumberpetung",
    "wof:placetype":"locality"
},
  "geometry": {"coordinates":[112.2216,-7.9433],"type":"Point"}
}