{
  "type": "Feature",
  "properties": {
    "gn:admin1_code":"10.0",
    "gn:asciiname":"Ngringin",
    "gn:country_code":"ID",
    "gn:dem":309,
    "gn:feature_class":"P",
    "gn:feature_code":"PPL",
    "gn:name":"Ngringin",
    "gn:population":0,
    "gn:timezone":"Asia/Jakarta",
    "iso:country":"ID",
    "wof:name":"Ngringin",
    "wof:placetype":"locality"
},
  "geometry": {"coordinates":[110.13167,-7.80806],"type":"Point"}
}