{
  "type": "Feature",
  "properties": {
    "gn:admin1_code":"38",
    "gn:asciiname":"Menge",
    "gn:country_code":"ID",
    "gn:dem":18,
    "gn:feature_class":"P",
    "gn:feature_code":"PPL",
    "gn:name":"Menge",
    "gn:population":0,
    "gn:timezone":"Asia/Makassar",
    "iso:country":"ID",
    "name:ceb_x_preferred":[
        "Menge"
    ],
    "name:deu_x_preferred":[
        "Menge"
    ],
    "name:fra_x_preferred":[
        "Menge"
    ],
    "name:ind_x_preferred":[
        "Menge"
    ],
    "name:ita_x_preferred":[
        "Menge"
    ],
    "name:swe_x_preferred":[
        "Menge"
    ],
    "wof:lang_x_official":[
        "ind"
    ],
    "wof:lang_x_spoken":[
        "ind",
        "eng"
    ],
    "wof:name":"Menge",
    "wof:placetype":"locality"
},
  "geometry": {"coordinates":[119.9421,-4.0042],"type":"Point"}
}