{
  "type": "Feature",
  "properties": {
    "gn:admin1_code":"7",
    "gn:asciiname":"Dlimas",
    "gn:country_code":"ID",
    "gn:dem":678,
    "gn:feature_class":"P",
    "gn:feature_code":"PPL",
    "gn:name":"Dlimas",
    "gn:population":0,
    "gn:timezone":"Asia/Jakarta",
    "iso:country":"ID",
    "name:ind_x_preferred":[
        "Dlimas"
    ],
    "wof:lang_x_official":[
        "ind"
    ],
    "wof:lang_x_spoken":[
        "ind",
        "eng"
    ],
    "wof:name":"Dlimas",
    "wof:placetype":"locality"
},
  "geometry": {"coordinates":[110.14888999999999,-7.23417],"type":"Point"}
}