{
  "type": "Feature",
  "properties": {
    "gn:admin1_code":"38.0",
    "gn:asciiname":"Birao",
    "gn:country_code":"ID",
    "gn:dem":425,
    "gn:feature_class":"P",
    "gn:feature_code":"PPL",
    "gn:name":"Birao",
    "gn:population":0,
    "gn:timezone":"Asia/Makassar",
    "iso:country":"ID",
    "name:ara_x_preferred":[
        "\u0628\u064a\u0631\u0627\u0648"
    ],
    "name:ceb_x_preferred":[
        "Birao"
    ],
    "name:deu_x_preferred":[
        "Birao"
    ],
    "name:fin_x_preferred":[
        "Birao"
    ],
    "name:fra_x_preferred":[
        "Birao"
    ],
    "name:frr_x_preferred":[
        "Birao"
    ],
    "name:hun_x_preferred":[
        "Birao"
    ],
    "name:ind_x_preferred":[
        "Birao"
    ],
    "name:ita_x_preferred":[
        "Birao"
    ],
    "name:nld_x_preferred":[
        "Birao"
    ],
    "name:pol_x_preferred":[
        "Birao"
    ],
    "name:ron_x_preferred":[
        "Birao"
    ],
    "name:rus_x_preferred":[
        "\u0411\u0438\u0440\u0430\u043e"
    ],
    "name:sag_x_preferred":[
        "Bira\u00f6"
    ],
    "name:spa_x_preferred":[
        "Birao"
    ],
    "name:sqi_x_preferred":[
        "Birao"
    ],
    "name:swe_x_preferred":[
        "Birao"
    ],
    "name:tur_x_preferred":[
        "Birao"
    ],
    "name:und_x_variant":[
        "Biraoe",
        "Birau"
    ],
    "name:urd_x_preferred":[
        "\u0628\u06cc\u0631\u0627\u0648"
    ],
    "name:xmf_x_preferred":[
        "\u10d1\u10d8\u10e0\u10d0\u10dd"
    ],
    "wof:lang_x_official":[
        "ind"
    ],
    "wof:lang_x_spoken":[
        "ind",
        "eng"
    ],
    "wof:name":"Birao",
    "wof:placetype":"locality"
},
  "geometry": {"coordinates":[119.7861,-4.8663],"type":"Point"}
}