{
  "type": "Feature",
  "properties": {
    "gn:admin1_code":"33",
    "gn:asciiname":"Blok D",
    "gn:country_code":"ID",
    "gn:dem":20,
    "gn:feature_class":"P",
    "gn:feature_code":"PPL",
    "gn:name":"Blok D",
    "gn:population":0,
    "gn:timezone":"Asia/Jakarta",
    "iso:country":"ID",
    "name:deu_x_preferred":[
        "Blok-D"
    ],
    "name:fra_x_preferred":[
        "Bloc"
    ],
    "name:hin_x_preferred":[
        "\u092c\u094d\u0932\u0949\u0915 \u0921\u0940"
    ],
    "name:hun_x_preferred":[
        "D blokk"
    ],
    "name:ind_x_preferred":[
        "Blok D"
    ],
    "name:ind_x_variant":[
        "Blok"
    ],
    "name:lav_x_preferred":[
        "Blok"
    ],
    "name:pol_x_preferred":[
        "Blok"
    ],
    "name:rus_x_preferred":[
        "\u0421\u0435\u043c\u0435\u0439\u0441\u0442\u0432\u043e \u0440\u0430\u0437\u0433\u043e\u043d\u043d\u044b\u0445 \u0431\u043b\u043e\u043a\u043e\u0432"
    ],
    "wof:lang_x_official":[
        "ind"
    ],
    "wof:lang_x_spoken":[
        "ind",
        "eng"
    ],
    "wof:name":"Blok D",
    "wof:placetype":"locality"
},
  "geometry": {"coordinates":[106.05159999999999,-6.022],"type":"Point"}
}