{
  "type": "Feature",
  "properties": {
    "gn:admin1_code":"8.0",
    "gn:asciiname":"Bluluk",
    "gn:country_code":"ID",
    "gn:dem":71,
    "gn:feature_class":"P",
    "gn:feature_code":"PPL",
    "gn:name":"Bluluk",
    "gn:population":0,
    "gn:timezone":"Asia/Jakarta",
    "iso:country":"ID",
    "name:ind_x_preferred":[
        "Bluluk"
    ],
    "wof:name":"Bluluk",
    "wof:placetype":"locality"
},
  "geometry": {"coordinates":[112.1339,-7.275],"type":"Point"}
}