{
  "type": "Feature",
  "properties": {
    "gn:admin1_code":"30.0",
    "gn:asciiname":"Talajung",
    "gn:country_code":"ID",
    "gn:dem":669,
    "gn:feature_class":"P",
    "gn:feature_code":"PPL",
    "gn:name":"Talajung",
    "gn:population":0,
    "gn:timezone":"Asia/Jakarta",
    "iso:country":"ID",
    "name:ind_x_preferred":[
        "Talajung"
    ],
    "wof:name":"Talajung",
    "wof:placetype":"locality"
},
  "geometry": {"coordinates":[108.018,-7.3346],"type":"Point"}
}