{
  "type": "Feature",
  "properties": {
    "gn:admin1_code":"8.0",
    "gn:asciiname":"Surowiti",
    "gn:country_code":"ID",
    "gn:dem":118,
    "gn:feature_class":"P",
    "gn:feature_code":"PPL",
    "gn:name":"Surowiti",
    "gn:population":0,
    "gn:timezone":"Asia/Jakarta",
    "iso:country":"ID",
    "name:ind_x_preferred":[
        "Surowiti"
    ],
    "name:und_x_variant":[
        "Soerowiti"
    ],
    "wof:lang_x_official":[
        "ind"
    ],
    "wof:lang_x_spoken":[
        "ind",
        "eng"
    ],
    "wof:name":"Surowiti",
    "wof:placetype":"locality"
},
  "geometry": {"coordinates":[112.45180000000001,-6.9328],"type":"Point"}
}