{
  "type": "Feature",
  "properties": {
    "gn:admin1_code":"21.0",
    "gn:asciiname":"Labuan",
    "gn:country_code":"ID",
    "gn:dem":23,
    "gn:feature_class":"P",
    "gn:feature_code":"PPL",
    "gn:name":"Labuan",
    "gn:population":0,
    "gn:timezone":"Asia/Makassar",
    "iso:country":"ID",
    "name:ind_x_preferred":[
        "Labuan"
    ],
    "name:und_x_variant":[
        "Laboea",
        "Labua"
    ],
    "wof:name":"Labuan",
    "wof:placetype":"locality"
},
  "geometry": {"coordinates":[119.8176,-0.6612],"type":"Point"}
}