{
  "type": "Feature",
  "properties": {
    "gn:admin1_code":"3.0",
    "gn:asciiname":"Lubukresam",
    "gn:country_code":"ID",
    "gn:dem":310,
    "gn:feature_class":"P",
    "gn:feature_code":"PPL",
    "gn:name":"Lubukresam",
    "gn:population":0,
    "gn:timezone":"Asia/Jakarta",
    "iso:country":"ID",
    "name:ind_x_preferred":[
        "Lubukresam"
    ],
    "wof:name":"Lubukresam",
    "wof:placetype":"locality"
},
  "geometry": {"coordinates":[102.5279,-3.8338],"type":"Point"}
}