{
  "type": "Feature",
  "properties": {
    "gn:admin1_code":"26.0",
    "gn:asciiname":"Simpang Raya Huluan",
    "gn:country_code":"ID",
    "gn:dem":1242,
    "gn:feature_class":"P",
    "gn:feature_code":"PPL",
    "gn:name":"Simpang Raya Huluan",
    "gn:population":0,
    "gn:timezone":"Asia/Jakarta",
    "iso:country":"ID",
    "name:ind_x_preferred":[
        "Simpang Raya Huluan"
    ],
    "wof:lang_x_official":[
        "ind"
    ],
    "wof:lang_x_spoken":[
        "ind",
        "eng"
    ],
    "wof:name":"Simpang Raya Huluan",
    "wof:placetype":"locality"
},
  "geometry": {"coordinates":[98.75920000000001,2.9037],"type":"Point"}
}