{
  "type": "Feature",
  "properties": {
    "gn:admin1_code":"8.0",
    "gn:asciiname":"Gedog Wetan",
    "gn:country_code":"ID",
    "gn:dem":372,
    "gn:feature_class":"P",
    "gn:feature_code":"PPLA4",
    "gn:name":"Gedog Wetan",
    "gn:population":0,
    "gn:timezone":"Asia/Jakarta",
    "iso:country":"ID",
    "name:ind_x_preferred":[
        "Gedog Wetan"
    ],
    "name:und_x_variant":[
        "Gedokwetan"
    ],
    "wof:lang_x_official":[
        "ind"
    ],
    "wof:lang_x_spoken":[
        "ind",
        "eng"
    ],
    "wof:name":"Gedog Wetan",
    "wof:placetype":"locality"
},
  "geometry": {"coordinates":[112.69523,-8.19965],"type":"Point"}
}