{
  "type": "Feature",
  "properties": {
    "gn:admin1_code":"38",
    "gn:asciiname":"Domenga",
    "gn:country_code":"ID",
    "gn:dem":77,
    "gn:feature_class":"P",
    "gn:feature_code":"PPL",
    "gn:name":"Domenga",
    "gn:population":0,
    "gn:timezone":"Asia/Makassar",
    "iso:country":"ID",
    "name:ind_x_preferred":[
        "Domenga"
    ],
    "wof:name":"Domenga",
    "wof:placetype":"locality"
},
  "geometry": {"coordinates":[120.36409999999999,-5.3962],"type":"Point"}
}