{
  "type": "Feature",
  "properties": {
    "gn:admin1_code":"28.0",
    "gn:asciiname":"Wair",
    "gn:country_code":"ID",
    "gn:dem":196,
    "gn:feature_class":"P",
    "gn:feature_code":"PPL",
    "gn:name":"Wair",
    "gn:population":0,
    "gn:timezone":"Asia/Jayapura",
    "iso:country":"ID",
    "name:ceb_x_preferred":[
        "Wair"
    ],
    "name:ind_x_preferred":[
        "Wair"
    ],
    "name:swe_x_preferred":[
        "Wair"
    ],
    "wof:lang_x_official":[
        "ind"
    ],
    "wof:lang_x_spoken":[
        "ind",
        "eng"
    ],
    "wof:name":"Wair",
    "wof:placetype":"locality"
},
  "geometry": {"coordinates":[133.1275,-5.3007],"type":"Point"}
}