{
  "type": "Feature",
  "properties": {
    "gn:admin1_code":"15.0",
    "gn:asciiname":"Bayas Baru",
    "gn:country_code":"ID",
    "gn:dem":408,
    "gn:feature_class":"P",
    "gn:feature_code":"PPL",
    "gn:name":"Bayas Baru",
    "gn:population":0,
    "gn:timezone":"Asia/Jakarta",
    "iso:country":"ID",
    "name:ind_x_preferred":[
        "Bayas Baru"
    ],
    "wof:name":"Bayas Baru",
    "wof:placetype":"locality"
},
  "geometry": {"coordinates":[104.99395,-5.54524],"type":"Point"}
}