{
  "type": "Feature",
  "properties": {
    "gn:admin1_code":"0.0",
    "gn:asciiname":"Bare",
    "gn:country_code":"ID",
    "gn:dem":48,
    "gn:feature_class":"P",
    "gn:feature_code":"PPL",
    "gn:name":"Bare",
    "gn:population":0,
    "gn:timezone":"Asia/Pontianak",
    "iso:country":"ID",
    "name:bos_x_preferred":[
        "Bare"
    ],
    "name:ceb_x_preferred":[
        "Bare"
    ],
    "name:deu_x_preferred":[
        "Bare"
    ],
    "name:eus_x_preferred":[
        "Bare"
    ],
    "name:fra_x_preferred":[
        "Bare"
    ],
    "name:hrv_x_preferred":[
        "Bare"
    ],
    "name:hun_x_preferred":[
        "Bare"
    ],
    "name:ita_x_preferred":[
        "Bare"
    ],
    "name:nld_x_preferred":[
        "Bare"
    ],
    "name:por_x_preferred":[
        "Bare"
    ],
    "name:slv_x_preferred":[
        "Bare"
    ],
    "name:swe_x_preferred":[
        "Bare"
    ],
    "wof:lang_x_official":[
        "ind"
    ],
    "wof:lang_x_spoken":[
        "ind",
        "eng"
    ],
    "wof:name":"Bare",
    "wof:placetype":"locality"
},
  "geometry": {"coordinates":[109.56667,0.98333],"type":"Point"}
}