{
  "type": "Feature",
  "properties": {
    "gn:admin1_code":"7.0",
    "gn:asciiname":"Gondanglegi",
    "gn:country_code":"ID",
    "gn:dem":421,
    "gn:feature_class":"P",
    "gn:feature_code":"PPL",
    "gn:name":"Gondanglegi",
    "gn:population":0,
    "gn:timezone":"Asia/Jakarta",
    "iso:country":"ID",
    "wof:name":"Gondanglegi",
    "wof:placetype":"locality"
},
  "geometry": {"coordinates":[110.34361,-7.635],"type":"Point"}
}