{
  "type": "Feature",
  "properties": {
    "gn:admin1_code":"30",
    "gn:asciiname":"Pilanghilir",
    "gn:country_code":"ID",
    "gn:dem":7,
    "gn:feature_class":"P",
    "gn:feature_code":"PPL",
    "gn:name":"Pilanghilir",
    "gn:population":0,
    "gn:timezone":"Asia/Jakarta",
    "iso:country":"ID",
    "name:ind_x_preferred":[
        "Pilanghilir"
    ],
    "wof:name":"Pilanghilir",
    "wof:placetype":"locality"
},
  "geometry": {"coordinates":[107.81972,-6.27778],"type":"Point"}
}