{
  "type": "Feature",
  "properties": {
    "gn:admin1_code":"07",
    "gn:asciiname":"Gintungan",
    "gn:country_code":"ID",
    "gn:dem":448,
    "gn:feature_class":"P",
    "gn:feature_code":"PPL",
    "gn:name":"Gintungan",
    "gn:population":0,
    "gn:timezone":"Asia/Jakarta",
    "iso:country":"ID",
    "name:ind_x_preferred":[
        "Gintungan"
    ],
    "wof:name":"Gintungan",
    "wof:placetype":"locality"
},
  "geometry": {"coordinates":[110.395,-7.16167],"type":"Point"}
}