{
  "type": "Feature",
  "properties": {
    "gn:admin1_code":"7.0",
    "gn:asciiname":"Losari",
    "gn:country_code":"ID",
    "gn:dem":1029,
    "gn:feature_class":"P",
    "gn:feature_code":"PPL",
    "gn:name":"Losari",
    "gn:population":0,
    "gn:timezone":"Asia/Jakarta",
    "iso:country":"ID",
    "wof:name":"Losari",
    "wof:placetype":"locality"
},
  "geometry": {"coordinates":[110.37166999999999,-7.36833],"type":"Point"}
}