{
  "type": "Feature",
  "properties": {
    "gn:admin1_code":"08",
    "gn:asciiname":"Tinjomoyo",
    "gn:country_code":"ID",
    "gn:dem":895,
    "gn:feature_class":"P",
    "gn:feature_code":"PPL",
    "gn:name":"Tinjomoyo",
    "gn:population":0,
    "gn:timezone":"Asia/Jakarta",
    "iso:country":"ID",
    "name:ind_x_preferred":[
        "Tinjomoyo"
    ],
    "name:und_x_variant":[
        "Tindjomojo"
    ],
    "wof:lang_x_official":[
        "ind"
    ],
    "wof:lang_x_spoken":[
        "ind",
        "eng"
    ],
    "wof:name":"Tinjomoyo",
    "wof:placetype":"locality"
},
  "geometry": {"coordinates":[112.5266,-7.8571],"type":"Point"}
}