{
  "type": "Feature",
  "properties": {
    "gn:admin1_code":"7",
    "gn:asciiname":"Kutorejo",
    "gn:country_code":"ID",
    "gn:dem":93,
    "gn:feature_class":"P",
    "gn:feature_code":"PPL",
    "gn:name":"Kutorejo",
    "gn:population":0,
    "gn:timezone":"Asia/Jakarta",
    "iso:country":"ID",
    "name:ind_x_preferred":[
        "Kutorejo"
    ],
    "wof:name":"Kutorejo",
    "wof:placetype":"locality"
},
  "geometry": {"coordinates":[111.08693999999998,-7.3425],"type":"Point"}
}