{
  "type": "Feature",
  "properties": {
    "gn:admin1_code":"34",
    "gn:asciiname":"Tembiu",
    "gn:country_code":"ID",
    "gn:dem":36,
    "gn:feature_class":"P",
    "gn:feature_code":"PPL",
    "gn:name":"Tembiu",
    "gn:population":0,
    "gn:timezone":"Asia/Makassar",
    "iso:country":"ID",
    "name:ind_x_preferred":[
        "Tembiu"
    ],
    "wof:name":"Tembiu",
    "wof:placetype":"locality"
},
  "geometry": {"coordinates":[122.48950000000001,0.7481],"type":"Point"}
}