{
  "type": "Feature",
  "properties": {
    "gn:admin1_code":"7.0",
    "gn:asciiname":"Susukan Timur Satu",
    "gn:country_code":"ID",
    "gn:dem":668,
    "gn:feature_class":"P",
    "gn:feature_code":"PPL",
    "gn:name":"Susukan Timur Satu",
    "gn:population":0,
    "gn:timezone":"Asia/Jakarta",
    "iso:country":"ID",
    "wof:name":"Susukan Timur Satu",
    "wof:placetype":"locality"
},
  "geometry": {"coordinates":[110.31083,-7.36972],"type":"Point"}
}