{
  "type": "Feature",
  "properties": {
    "gn:admin1_code":"7.0",
    "gn:asciiname":"Kedungluwuk",
    "gn:country_code":"ID",
    "gn:dem":64,
    "gn:feature_class":"P",
    "gn:feature_code":"PPL",
    "gn:name":"Kedungluwuk",
    "gn:population":0,
    "gn:timezone":"Asia/Jakarta",
    "iso:country":"ID",
    "name:ind_x_preferred":[
        "Kedungluwuk"
    ],
    "wof:name":"Kedungluwuk",
    "wof:placetype":"locality"
},
  "geometry": {"coordinates":[109.46111000000001,-7.3775],"type":"Point"}
}