{
  "type": "Feature",
  "properties": {
    "gn:country":"ID",
    "gn:fcode":"ADM3",
    "gn:pop":0,
    "iso:country":"ID",
    "name:ind_x_preferred":[
        "Kecamatan Pesanggrahan"
    ],
    "name:unk_x_variant":[
        "Pesanggrahan"
    ],
    "qs:name":"Kecamatan Pesanggrahan",
    "qs:photos_9r":0,
    "qs:photos_sr":0,
    "qs:pop_sr":"0",
    "wof:name":"Kecamatan Pesanggrahan",
    "wof:placetype":"localadmin",
    "wof:population":0
},
  "geometry": {"coordinates":[106.7565,-6.2401],"type":"Point"}
}