{
  "type": "Feature",
  "properties": {
    "gn:admin1_code":"0.0",
    "gn:asciiname":"Tewangpajangan",
    "gn:cc2":"ID",
    "gn:country_code":"ID",
    "gn:dem":38,
    "gn:feature_class":"P",
    "gn:feature_code":"PPL",
    "gn:name":"Tewangpajangan",
    "gn:population":0,
    "gn:timezone":"Asia/Pontianak",
    "iso:country":"ID",
    "name:und_x_variant":[
        "Tewangp\u0115djangan",
        "Tewangpadjangan",
        "Tewangpajangan"
    ],
    "wof:lang_x_official":[
        "ind"
    ],
    "wof:lang_x_spoken":[
        "ind",
        "eng"
    ],
    "wof:name":"Tewangpajangan",
    "wof:placetype":"locality"
},
  "geometry": {"coordinates":[113.90000000000001,-1.21667],"type":"Point"}
}