{
  "type": "Feature",
  "properties": {
    "gn:admin1_code":"8.0",
    "gn:asciiname":"Laoklorong",
    "gn:country_code":"ID",
    "gn:dem":18,
    "gn:feature_class":"P",
    "gn:feature_code":"PPL",
    "gn:name":"Laoklorong",
    "gn:population":0,
    "gn:timezone":"Asia/Jakarta",
    "iso:country":"ID",
    "name:ind_x_preferred":[
        "Laoklorong"
    ],
    "wof:name":"Laoklorong",
    "wof:placetype":"locality"
},
  "geometry": {"coordinates":[113.9808,-7.0051],"type":"Point"}
}