{
  "type": "Feature",
  "properties": {
    "gn:country":"ID",
    "gn:fcode":"PPLA3",
    "gn:pop":0,
    "iso:country":"ID",
    "name:ind_x_preferred":[
        "Utan"
    ],
    "name:unk_x_variant":[
        "Oetan"
    ],
    "qs:name":"Utan",
    "qs:photos_9r":0,
    "qs:photos_sr":0,
    "qs:pop_sr":"6",
    "wd:wordcount":200,
    "wof:name":"Utan",
    "wof:placetype":"locality",
    "wof:population":0
},
  "geometry": {"coordinates":[117.1332,-8.4129],"type":"Point"}
}