{
  "type": "Feature",
  "properties": {
    "gn:admin1_code":"11.0",
    "gn:asciiname":"Sungaisaput",
    "gn:country_code":"ID",
    "gn:dem":165,
    "gn:feature_class":"P",
    "gn:feature_code":"PPL",
    "gn:name":"Sungaisaput",
    "gn:population":0,
    "gn:timezone":"Asia/Pontianak",
    "iso:country":"ID",
    "name:ind_x_preferred":[
        "Sungaisaput"
    ],
    "wof:name":"Sungaisaput",
    "wof:placetype":"locality"
},
  "geometry": {"coordinates":[112.70352,0.43216],"type":"Point"}
}