{
  "type": "Feature",
  "properties": {
    "gn:admin1_code":"8.0",
    "gn:asciiname":"Cumpleng Kidul",
    "gn:country_code":"ID",
    "gn:dem":62,
    "gn:feature_class":"P",
    "gn:feature_code":"PPL",
    "gn:name":"Cumpleng Kidul",
    "gn:population":0,
    "gn:timezone":"Asia/Jakarta",
    "iso:country":"ID",
    "name:ind_x_preferred":[
        "Cumpleng Kidul"
    ],
    "wof:name":"Cumpleng Kidul",
    "wof:placetype":"locality"
},
  "geometry": {"coordinates":[112.1426,-7.2873],"type":"Point"}
}