{
  "type": "Feature",
  "properties": {
    "gn:admin1_code":"8.0",
    "gn:asciiname":"Puntuk",
    "gn:country_code":"ID",
    "gn:dem":96,
    "gn:feature_class":"P",
    "gn:feature_code":"PPL",
    "gn:name":"Puntuk",
    "gn:population":0,
    "gn:timezone":"Asia/Jakarta",
    "iso:country":"ID",
    "name:ind_x_preferred":[
        "Puntuk"
    ],
    "wof:name":"Puntuk",
    "wof:placetype":"locality"
},
  "geometry": {"coordinates":[111.88509999999999,-8.0196],"type":"Point"}
}