{
  "type": "Feature",
  "properties": {
    "gn:admin1_code":"0.0",
    "gn:asciiname":"Mansulan",
    "gn:cc2":"ID",
    "gn:country_code":"ID",
    "gn:dem":121,
    "gn:feature_class":"P",
    "gn:feature_code":"PPL",
    "gn:name":"Mansulan",
    "gn:population":0,
    "gn:timezone":"Asia/Pontianak",
    "iso:country":"ID",
    "name:und_x_variant":[
        "Mansoelan",
        "Mansulan"
    ],
    "wof:name":"Mansulan",
    "wof:placetype":"locality"
},
  "geometry": {"coordinates":[113.38333,-1.26667],"type":"Point"}
}