{
  "type": "Feature",
  "properties": {
    "gn:admin1_code":"7",
    "gn:asciiname":"Wonopringgo Utara",
    "gn:country_code":"ID",
    "gn:dem":23,
    "gn:feature_class":"P",
    "gn:feature_code":"PPL",
    "gn:name":"Wonopringgo Utara",
    "gn:population":0,
    "gn:timezone":"Asia/Jakarta",
    "iso:country":"ID",
    "name:ind_x_preferred":[
        "Wonopringgo Utara"
    ],
    "wof:name":"Wonopringgo Utara",
    "wof:placetype":"locality"
},
  "geometry": {"coordinates":[109.63405,-6.98422],"type":"Point"}
}