{
  "type": "Feature",
  "properties": {
    "gn:admin1_code":"7.0",
    "gn:asciiname":"Munggangsari",
    "gn:country_code":"ID",
    "gn:dem":112,
    "gn:feature_class":"P",
    "gn:feature_code":"PPL",
    "gn:name":"Munggangsari",
    "gn:population":0,
    "gn:timezone":"Asia/Jakarta",
    "iso:country":"ID",
    "name:ind_x_preferred":[
        "Munggangsari"
    ],
    "wof:name":"Munggangsari",
    "wof:placetype":"locality"
},
  "geometry": {"coordinates":[109.4575,-7.32444],"type":"Point"}
}