{
  "type": "Feature",
  "properties": {
    "gn:admin1_code":"8.0",
    "gn:asciiname":"Timurlorong",
    "gn:country_code":"ID",
    "gn:dem":133,
    "gn:feature_class":"P",
    "gn:feature_code":"PPL",
    "gn:name":"Timurlorong",
    "gn:population":0,
    "gn:timezone":"Asia/Jakarta",
    "iso:country":"ID",
    "name:ind_x_preferred":[
        "Timurlorong"
    ],
    "wof:name":"Timurlorong",
    "wof:placetype":"locality"
},
  "geometry": {"coordinates":[113.45999999999999,-7.0277],"type":"Point"}
}