{
  "type": "Feature",
  "properties": {
    "gn:admin1_code":"17",
    "gn:asciiname":"Repoktinggang",
    "gn:country_code":"ID",
    "gn:dem":29,
    "gn:feature_class":"P",
    "gn:feature_code":"PPL",
    "gn:name":"Repoktinggang",
    "gn:population":0,
    "gn:timezone":"Asia/Makassar",
    "iso:country":"ID",
    "name:ind_x_preferred":[
        "Repoktinggang"
    ],
    "wof:name":"Repoktinggang",
    "wof:placetype":"locality"
},
  "geometry": {"coordinates":[116.3703,-8.9003],"type":"Point"}
}