{
  "type": "Feature",
  "properties": {
    "gn:admin1_code":"30",
    "gn:asciiname":"Pasirleneng",
    "gn:country_code":"ID",
    "gn:dem":764,
    "gn:feature_class":"P",
    "gn:feature_code":"PPL",
    "gn:name":"Pasirleneng",
    "gn:population":0,
    "gn:timezone":"Asia/Jakarta",
    "iso:country":"ID",
    "name:ind_x_preferred":[
        "Pasirleneng"
    ],
    "wof:name":"Pasirleneng",
    "wof:placetype":"locality"
},
  "geometry": {"coordinates":[107.04389,-6.98444],"type":"Point"}
}