{
  "type": "Feature",
  "properties": {
    "gn:admin1_code":"14.0",
    "gn:asciiname":"Satuan Pemukiman IV Kaubun",
    "gn:country_code":"ID",
    "gn:dem":46,
    "gn:feature_class":"P",
    "gn:feature_code":"PPL",
    "gn:name":"Satuan Pemukiman IV Kaubun",
    "gn:population":0,
    "gn:timezone":"Asia/Makassar",
    "iso:country":"ID",
    "name:ind_x_preferred":[
        "Satuan Pemukiman IV Kaubun"
    ],
    "name:und_x_variant":[
        "SP IV Kaubun"
    ],
    "wof:lang_x_official":[
        "ind"
    ],
    "wof:lang_x_spoken":[
        "ind",
        "eng"
    ],
    "wof:name":"Satuan Pemukiman IV Kaubun",
    "wof:placetype":"locality"
},
  "geometry": {"coordinates":[117.87350000000001,0.9895],"type":"Point"}
}