{
  "type": "Feature",
  "properties": {
    "gn:admin1_code":"07",
    "gn:asciiname":"Cerme",
    "gn:country_code":"ID",
    "gn:dem":142,
    "gn:feature_class":"P",
    "gn:feature_code":"PPL",
    "gn:name":"Cerme",
    "gn:population":0,
    "gn:timezone":"Asia/Jakarta",
    "iso:country":"ID",
    "name:ind_x_preferred":[
        "Cerme"
    ],
    "name:und_x_variant":[
        "Tjerme 1",
        "Cerme Satu"
    ],
    "wof:name":"Cerme",
    "wof:placetype":"locality"
},
  "geometry": {"coordinates":[110.73111000000002,-7.16944],"type":"Point"}
}