{
  "type": "Feature",
  "properties": {
    "gn:admin1_code":"8.0",
    "gn:asciiname":"Setonorejo",
    "gn:country_code":"ID",
    "gn:dem":93,
    "gn:feature_class":"P",
    "gn:feature_code":"PPL",
    "gn:name":"Setonorejo",
    "gn:population":0,
    "gn:timezone":"Asia/Jakarta",
    "iso:country":"ID",
    "name:ind_x_preferred":[
        "Setonorejo"
    ],
    "wof:name":"Setonorejo",
    "wof:placetype":"locality"
},
  "geometry": {"coordinates":[111.9541,-7.9065],"type":"Point"}
}