{
  "type": "Feature",
  "properties": {
    "gn:admin1_code":"37.0",
    "gn:asciiname":"Parittengah",
    "gn:country_code":"ID",
    "gn:dem":6,
    "gn:feature_class":"P",
    "gn:feature_code":"PPL",
    "gn:name":"Parittengah",
    "gn:population":0,
    "gn:timezone":"Asia/Jakarta",
    "iso:country":"ID",
    "name:ind_x_preferred":[
        "Parittengah"
    ],
    "wof:name":"Parittengah",
    "wof:placetype":"locality"
},
  "geometry": {"coordinates":[103.3985,-0.456],"type":"Point"}
}