{
  "type": "Feature",
  "properties": {
    "gn:admin1_code":"17",
    "gn:asciiname":"Saung",
    "gn:country_code":"ID",
    "gn:dem":100,
    "gn:feature_class":"P",
    "gn:feature_code":"PPL",
    "gn:name":"Saung",
    "gn:population":0,
    "gn:timezone":"Asia/Makassar",
    "iso:country":"ID",
    "name:deu_x_preferred":[
        "Saung gauk"
    ],
    "name:fin_x_preferred":[
        "Saung"
    ],
    "name:fra_x_preferred":[
        "Saung"
    ],
    "name:hun_x_preferred":[
        "Szaung gauk"
    ],
    "name:ind_x_preferred":[
        "Saung"
    ],
    "name:jpn_x_preferred":[
        "\u30b5\u30a6\u30f3\u30fb\u30ac\u30a6"
    ],
    "name:mya_x_preferred":[
        "\u1005\u1031\u102c\u1004\u103a\u1038\u1000\u1031\u102c\u1000\u103a"
    ],
    "name:nld_x_preferred":[
        "Saung"
    ],
    "name:pol_x_preferred":[
        "Saung"
    ],
    "name:rus_x_preferred":[
        "\u0421\u0430\u0443\u043d\u0433"
    ],
    "name:tha_x_preferred":[
        "\u0e0b\u0e2d\u0e07\u0e40\u0e01\u0e32\u0e30"
    ],
    "name:vie_x_preferred":[
        "Saung-gauk"
    ],
    "wof:lang_x_official":[
        "ind"
    ],
    "wof:lang_x_spoken":[
        "ind",
        "eng"
    ],
    "wof:name":"Saung",
    "wof:placetype":"locality"
},
  "geometry": {"coordinates":[116.2731,-8.8104],"type":"Point"}
}