{
  "type": "Feature",
  "properties": {
    "gn:admin1_code":"30.0",
    "gn:asciiname":"Cijabar",
    "gn:country_code":"ID",
    "gn:dem":344,
    "gn:feature_class":"P",
    "gn:feature_code":"PPL",
    "gn:name":"Cijabar",
    "gn:population":0,
    "gn:timezone":"Asia/Jakarta",
    "iso:country":"ID",
    "name:ind_x_preferred":[
        "Cijabar"
    ],
    "wof:name":"Cijabar",
    "wof:placetype":"locality"
},
  "geometry": {"coordinates":[108.16500000000001,-7.4138],"type":"Point"}
}