{
  "type": "Feature",
  "properties": {
    "gn:admin1_code":"17",
    "gn:asciiname":"Merca",
    "gn:country_code":"ID",
    "gn:dem":148,
    "gn:feature_class":"P",
    "gn:feature_code":"PPL",
    "gn:name":"Merca",
    "gn:population":0,
    "gn:timezone":"Asia/Makassar",
    "iso:country":"ID",
    "name:ara_x_preferred":[
        "\u0645\u0631\u0643\u0629"
    ],
    "name:azb_x_preferred":[
        "\u0645\u0631\u06a9\u0647"
    ],
    "name:cat_x_preferred":[
        "Marka"
    ],
    "name:ceb_x_preferred":[
        "Marka"
    ],
    "name:dan_x_preferred":[
        "Merca"
    ],
    "name:deu_x_preferred":[
        "Merka"
    ],
    "name:epo_x_preferred":[
        "Merka"
    ],
    "name:fas_x_preferred":[
        "\u0645\u0631\u06a9\u0647"
    ],
    "name:fin_x_preferred":[
        "Merka"
    ],
    "name:fra_x_preferred":[
        "Merka"
    ],
    "name:ind_x_preferred":[
        "Merca"
    ],
    "name:ind_x_variant":[
        "Marka"
    ],
    "name:ita_x_preferred":[
        "Merca"
    ],
    "name:jpn_x_preferred":[
        "\u30de\u30eb\u30ab"
    ],
    "name:kat_x_preferred":[
        "\u10db\u10d0\u10e0\u10d9\u10d0"
    ],
    "name:kaz_x_preferred":[
        "\u041c\u0430\u0440\u043a\u0430 \u049b\u0430\u043b\u0430\u0441\u044b"
    ],
    "name:kor_x_preferred":[
        "\ub9c8\ub974\uce74"
    ],
    "name:lit_x_preferred":[
        "Merka"
    ],
    "name:mal_x_preferred":[
        "\u0d2e\u0d46\u0d7c\u0d15\u0d4d\u0d15"
    ],
    "name:nld_x_preferred":[
        "Marka"
    ],
    "name:nor_x_preferred":[
        "Marka"
    ],
    "name:pol_x_preferred":[
        "Marka"
    ],
    "name:por_x_preferred":[
        "Merca"
    ],
    "name:ron_x_preferred":[
        "Merca"
    ],
    "name:rus_x_preferred":[
        "\u041c\u0430\u0440\u043a\u0430"
    ],
    "name:sco_x_preferred":[
        "Merca"
    ],
    "name:som_x_preferred":[
        "Marka"
    ],
    "name:swa_x_preferred":[
        "Merka"
    ],
    "name:swe_x_preferred":[
        "Merca"
    ],
    "name:tur_x_preferred":[
        "Merka"
    ],
    "name:ukr_x_preferred":[
        "\u041c\u0430\u0440\u043a\u0430"
    ],
    "name:urd_x_preferred":[
        "\u0645\u0631\u06a9\u06c1"
    ],
    "name:war_x_preferred":[
        "Merca"
    ],
    "name:zho_x_preferred":[
        "\u9a6c\u5c14\u5361"
    ],
    "wof:name":"Merca",
    "wof:placetype":"locality"
},
  "geometry": {"coordinates":[116.2034,-8.5797],"type":"Point"}
}