{
  "type": "Feature",
  "properties": {
    "gn:admin1_code":"42",
    "gn:asciiname":"Gunung Putih",
    "gn:country_code":"ID",
    "gn:dem":6,
    "gn:feature_class":"P",
    "gn:feature_code":"PPL",
    "gn:name":"Gunung Putih",
    "gn:population":0,
    "gn:timezone":"Asia/Makassar",
    "iso:country":"ID",
    "name:ind_x_preferred":[
        "Gunung Putih"
    ],
    "wof:name":"Gunung Putih",
    "wof:placetype":"locality"
},
  "geometry": {"coordinates":[117.35366999999999,2.8372],"type":"Point"}
}