{
  "type": "Feature",
  "properties": {
    "gn:admin1_code":"30.0",
    "gn:asciiname":"Kubang",
    "gn:country_code":"ID",
    "gn:dem":428,
    "gn:feature_class":"P",
    "gn:feature_code":"PPL",
    "gn:name":"Kubang",
    "gn:population":0,
    "gn:timezone":"Asia/Jakarta",
    "iso:country":"ID",
    "name:ceb_x_preferred":[
        "Kubang"
    ],
    "name:ind_x_preferred":[
        "Kubang"
    ],
    "name:min_x_preferred":[
        "Kubang"
    ],
    "name:msa_x_preferred":[
        "Kubang"
    ],
    "name:nld_x_preferred":[
        "Kubang"
    ],
    "name:swe_x_preferred":[
        "Kubang"
    ],
    "wof:name":"Kubang",
    "wof:placetype":"locality"
},
  "geometry": {"coordinates":[108.40049999999999,-7.2046],"type":"Point"}
}