{
  "type": "Feature",
  "properties": {
    "gn:admin1_code":"7",
    "gn:asciiname":"Lembangan",
    "gn:country_code":"ID",
    "gn:dem":22,
    "gn:feature_class":"P",
    "gn:feature_code":"PPL",
    "gn:name":"Lembangan",
    "gn:population":0,
    "gn:timezone":"Asia/Jakarta",
    "iso:country":"ID",
    "name:ind_x_preferred":[
        "Lembangan"
    ],
    "wof:name":"Lembangan",
    "wof:placetype":"locality"
},
  "geometry": {"coordinates":[109.69138999999998,-6.96271],"type":"Point"}
}