{
  "type": "Feature",
  "properties": {
    "gn:admin1_code":"8",
    "gn:asciiname":"Rekesan Kulon",
    "gn:country_code":"ID",
    "gn:dem":1060,
    "gn:feature_class":"P",
    "gn:feature_code":"PPL",
    "gn:name":"Rekesan Kulon",
    "gn:population":0,
    "gn:timezone":"Asia/Jakarta",
    "iso:country":"ID",
    "name:ind_x_preferred":[
        "Rekesan Kulon"
    ],
    "wof:name":"Rekesan Kulon",
    "wof:placetype":"locality"
},
  "geometry": {"coordinates":[112.53749999999999,-7.8326],"type":"Point"}
}