{
  "type": "Feature",
  "properties": {
    "gn:admin1_code":"5.0",
    "gn:asciiname":"Pangkalanbulian",
    "gn:country_code":"ID",
    "gn:dem":35,
    "gn:feature_class":"P",
    "gn:feature_code":"PPL",
    "gn:name":"Pangkalanbulian",
    "gn:population":0,
    "gn:timezone":"Asia/Jakarta",
    "iso:country":"ID",
    "name:ind_x_preferred":[
        "Pangkalanbulian"
    ],
    "wof:name":"Pangkalanbulian",
    "wof:placetype":"locality"
},
  "geometry": {"coordinates":[102.6635,-2.1185],"type":"Point"}
}