{
  "type": "Feature",
  "properties": {
    "gn:admin1_code":"8",
    "gn:asciiname":"Ketepengan",
    "gn:country_code":"ID",
    "gn:dem":449,
    "gn:feature_class":"P",
    "gn:feature_code":"PPL",
    "gn:name":"Ketepengan",
    "gn:population":0,
    "gn:timezone":"Asia/Jakarta",
    "iso:country":"ID",
    "name:ind_x_preferred":[
        "Ketepengan"
    ],
    "wof:name":"Ketepengan",
    "wof:placetype":"locality"
},
  "geometry": {"coordinates":[112.6151,-7.9846],"type":"Point"}
}