{
  "type": "Feature",
  "properties": {
    "gn:admin1_code":"36.0",
    "gn:asciiname":"Maryendi",
    "gn:country_code":"ID",
    "gn:dem":82,
    "gn:feature_class":"P",
    "gn:feature_code":"PPL",
    "gn:name":"Maryendi",
    "gn:population":0,
    "gn:timezone":"Asia/Jayapura",
    "iso:country":"ID",
    "name:ind_x_preferred":[
        "Maryendi"
    ],
    "name:und_x_variant":[
        "Marjendi"
    ],
    "wof:name":"Maryendi",
    "wof:placetype":"locality"
},
  "geometry": {"coordinates":[136.08279999999999,-1.1435],"type":"Point"}
}