{
  "type": "Feature",
  "properties": {
    "gn:admin1_code":"8.0",
    "gn:asciiname":"Brumbung Dajah",
    "gn:country_code":"ID",
    "gn:dem":104,
    "gn:feature_class":"P",
    "gn:feature_code":"PPL",
    "gn:name":"Brumbung Dajah",
    "gn:population":0,
    "gn:timezone":"Asia/Jakarta",
    "iso:country":"ID",
    "name:ind_x_preferred":[
        "Brumbung Dajah"
    ],
    "wof:name":"Brumbung Dajah",
    "wof:placetype":"locality"
},
  "geometry": {"coordinates":[113.5206,-6.9166],"type":"Point"}
}