{
  "type": "Feature",
  "properties": {
    "gn:admin1_code":"30",
    "gn:asciiname":"Cikukulu",
    "gn:country_code":"ID",
    "gn:dem":106,
    "gn:feature_class":"P",
    "gn:feature_code":"PPL",
    "gn:name":"Cikukulu",
    "gn:population":0,
    "gn:timezone":"Asia/Jakarta",
    "iso:country":"ID",
    "name:ind_x_preferred":[
        "Cikukulu"
    ],
    "wof:name":"Cikukulu",
    "wof:placetype":"locality"
},
  "geometry": {"coordinates":[107.21167,-6.51667],"type":"Point"}
}