{
  "type": "Feature",
  "properties": {
    "gn:admin1_code":"15.0",
    "gn:asciiname":"Umbulanpenengahan",
    "gn:country_code":"ID",
    "gn:dem":881,
    "gn:feature_class":"P",
    "gn:feature_code":"PPL",
    "gn:name":"Umbulanpenengahan",
    "gn:population":0,
    "gn:timezone":"Asia/Jakarta",
    "iso:country":"ID",
    "name:ind_x_preferred":[
        "Umbulanpenengahan"
    ],
    "wof:name":"Umbulanpenengahan",
    "wof:placetype":"locality"
},
  "geometry": {"coordinates":[104.10337,-4.98128],"type":"Point"}
}