{
  "type": "Feature",
  "properties": {
    "gn:admin1_code":"7",
    "gn:asciiname":"Pengkol",
    "gn:country_code":"ID",
    "gn:dem":1162,
    "gn:feature_class":"P",
    "gn:feature_code":"PPL",
    "gn:name":"Pengkol",
    "gn:population":0,
    "gn:timezone":"Asia/Jakarta",
    "iso:country":"ID",
    "name:ind_x_preferred":[
        "Pengkol"
    ],
    "wof:name":"Pengkol",
    "wof:placetype":"locality"
},
  "geometry": {"coordinates":[111.13583,-7.69722],"type":"Point"}
}