{
  "type": "Feature",
  "properties": {
    "gn:admin1_code":"38",
    "gn:asciiname":"Popo",
    "gn:country_code":"ID",
    "gn:dem":1114,
    "gn:feature_class":"P",
    "gn:feature_code":"PPL",
    "gn:name":"Popo",
    "gn:population":0,
    "gn:timezone":"Asia/Makassar",
    "iso:country":"ID",
    "name:ceb_x_preferred":[
        "Popo"
    ],
    "name:deu_x_preferred":[
        "Popo"
    ],
    "name:epo_x_preferred":[
        "Popo"
    ],
    "name:eus_x_preferred":[
        "Popo"
    ],
    "name:fra_x_preferred":[
        "Popo"
    ],
    "name:ind_x_preferred":[
        "Popo"
    ],
    "name:ita_x_preferred":[
        "Popo"
    ],
    "name:jpn_x_preferred":[
        "\u30dd\u30dd"
    ],
    "name:pol_x_preferred":[
        "Popo"
    ],
    "name:swe_x_preferred":[
        "Popo"
    ],
    "wof:name":"Popo",
    "wof:placetype":"locality"
},
  "geometry": {"coordinates":[119.51609999999999,-3.2438],"type":"Point"}
}