{
  "type": "Feature",
  "properties": {
    "gn:admin1_code":"30",
    "gn:asciiname":"Tangkil",
    "gn:country_code":"ID",
    "gn:dem":747,
    "gn:feature_class":"P",
    "gn:feature_code":"PPL",
    "gn:name":"Tangkil",
    "gn:population":0,
    "gn:timezone":"Asia/Jakarta",
    "iso:country":"ID",
    "name:ind_x_preferred":[
        "Tangkil"
    ],
    "name:und_x_variant":[
        "Tongkil 2",
        "Tongkil Dua"
    ],
    "wof:lang_x_official":[
        "ind"
    ],
    "wof:lang_x_spoken":[
        "ind",
        "eng"
    ],
    "wof:name":"Tangkil",
    "wof:placetype":"locality"
},
  "geometry": {"coordinates":[107.55110999999999,-6.88806],"type":"Point"}
}