{
  "type": "Feature",
  "properties": {
    "gn:country":"ID",
    "gn:fcode":"PPLA4",
    "gn:pop":0,
    "iso:country":"ID",
    "name:unk_x_variant":[
        "Oesapa-besar"
    ],
    "qs:name":"Oesapa",
    "qs:photos_9r":0,
    "qs:photos_sr":0,
    "qs:pop_sr":"0",
    "wof:lang_x_official":[
        "ind"
    ],
    "wof:lang_x_spoken":[
        "ind",
        "eng"
    ],
    "wof:name":"Oesapa",
    "wof:placetype":"locality",
    "wof:population":0
},
  "geometry": {"coordinates":[123.64700000000001,-10.1485],"type":"Point"}
}