{
  "type": "Feature",
  "properties": {
    "gn:admin1_code":"8.0",
    "gn:asciiname":"Pusuh",
    "gn:country_code":"ID",
    "gn:dem":488,
    "gn:feature_class":"P",
    "gn:feature_code":"PPL",
    "gn:name":"Pusuh",
    "gn:population":0,
    "gn:timezone":"Asia/Jakarta",
    "iso:country":"ID",
    "name:ind_x_preferred":[
        "Pusuh"
    ],
    "wof:name":"Pusuh",
    "wof:placetype":"locality"
},
  "geometry": {"coordinates":[112.3053,-7.8566],"type":"Point"}
}