{
  "type": "Feature",
  "properties": {
    "gn:admin1_code":"5.0",
    "gn:asciiname":"Kotapetai",
    "gn:country_code":"ID",
    "gn:dem":797,
    "gn:feature_class":"P",
    "gn:feature_code":"PPL",
    "gn:name":"Kotapetai",
    "gn:population":0,
    "gn:timezone":"Asia/Jakarta",
    "iso:country":"ID",
    "name:ind_x_preferred":[
        "Kotapetai"
    ],
    "wof:lang_x_official":[
        "ind"
    ],
    "wof:lang_x_spoken":[
        "ind",
        "eng"
    ],
    "wof:name":"Kotapetai",
    "wof:placetype":"locality"
},
  "geometry": {"coordinates":[101.4761,-2.1171],"type":"Point"}
}