{
  "type": "Feature",
  "properties": {
    "gn:admin1_code":"1",
    "gn:asciiname":"Reueng Reueng",
    "gn:country_code":"ID",
    "gn:dem":13,
    "gn:feature_class":"P",
    "gn:feature_code":"PPL",
    "gn:name":"Reueng Reueng",
    "gn:population":0,
    "gn:timezone":"Asia/Jakarta",
    "iso:country":"ID",
    "name:ind_x_preferred":[
        "Reueng Reueng"
    ],
    "name:und_x_variant":[
        "Reueng Reueng 2"
    ],
    "wof:name":"Reueng Reueng",
    "wof:placetype":"locality"
},
  "geometry": {"coordinates":[96.0013,5.323],"type":"Point"}
}