{
  "type": "Feature",
  "properties": {
    "gn:admin1_code":"22.0",
    "gn:asciiname":"Solewatu",
    "gn:country_code":"ID",
    "gn:dem":317,
    "gn:feature_class":"P",
    "gn:feature_code":"PPL",
    "gn:name":"Solewatu",
    "gn:population":0,
    "gn:timezone":"Asia/Makassar",
    "iso:country":"ID",
    "name:und_x_variant":[
        "Solewatoe",
        "Solewatu"
    ],
    "wof:name":"Solewatu",
    "wof:placetype":"locality"
},
  "geometry": {"coordinates":[121.753,-3.93],"type":"Point"}
}