{
  "type": "Feature",
  "properties": {
    "gn:admin1_code":"38",
    "gn:asciiname":"Bayuntana",
    "gn:country_code":"ID",
    "gn:dem":31,
    "gn:feature_class":"P",
    "gn:feature_code":"PPL",
    "gn:name":"Bayuntana",
    "gn:population":0,
    "gn:timezone":"Asia/Makassar",
    "iso:country":"ID",
    "name:ind_x_preferred":[
        "Bayuntana"
    ],
    "wof:name":"Bayuntana",
    "wof:placetype":"locality"
},
  "geometry": {"coordinates":[120.8266,-2.5454],"type":"Point"}
}