{
  "type": "Feature",
  "properties": {
    "gn:admin1_code":"8",
    "gn:asciiname":"Tumpakserut",
    "gn:country_code":"ID",
    "gn:dem":257,
    "gn:feature_class":"P",
    "gn:feature_code":"PPL",
    "gn:name":"Tumpakserut",
    "gn:population":0,
    "gn:timezone":"Asia/Jakarta",
    "iso:country":"ID",
    "name:ind_x_preferred":[
        "Tumpakserut"
    ],
    "wof:name":"Tumpakserut",
    "wof:placetype":"locality"
},
  "geometry": {"coordinates":[112.3691,-8.2312],"type":"Point"}
}