{
  "type": "Feature",
  "properties": {
    "gn:admin1_code":"18.0",
    "gn:asciiname":"Dereng",
    "gn:country_code":"ID",
    "gn:dem":30,
    "gn:feature_class":"P",
    "gn:feature_code":"PPL",
    "gn:name":"Dereng",
    "gn:population":0,
    "gn:timezone":"Asia/Makassar",
    "iso:country":"ID",
    "name:ind_x_preferred":[
        "Dereng"
    ],
    "wof:name":"Dereng",
    "wof:placetype":"locality"
},
  "geometry": {"coordinates":[123.08629999999999,-8.3984],"type":"Point"}
}