{
  "type": "Feature",
  "properties": {
    "gn:admin1_code":"8.0",
    "gn:asciiname":"Palebunan",
    "gn:country_code":"ID",
    "gn:dem":5,
    "gn:feature_class":"P",
    "gn:feature_code":"PPLA4",
    "gn:name":"Palebunan",
    "gn:population":0,
    "gn:timezone":"Asia/Jakarta",
    "iso:country":"ID",
    "name:ind_x_preferred":[
        "Palebunan"
    ],
    "wof:name":"Palebunan",
    "wof:placetype":"locality"
},
  "geometry": {"coordinates":[113.87869999999999,-7.0563],"type":"Point"}
}