{
  "type": "Feature",
  "properties": {
    "gn:admin1_code":"15.0",
    "gn:asciiname":"Talang Wai Harun",
    "gn:country_code":"ID",
    "gn:dem":157,
    "gn:feature_class":"P",
    "gn:feature_code":"PPL",
    "gn:name":"Talang Wai Harun",
    "gn:population":0,
    "gn:timezone":"Asia/Jakarta",
    "iso:country":"ID",
    "name:ind_x_preferred":[
        "Talang Wai Harun"
    ],
    "wof:name":"Talang Wai Harun",
    "wof:placetype":"locality"
},
  "geometry": {"coordinates":[104.62976999999999,-4.78976],"type":"Point"}
}