{
  "type": "Feature",
  "properties": {
    "gn:admin1_code":"30.0",
    "gn:asciiname":"Gunungdamar",
    "gn:country_code":"ID",
    "gn:dem":20,
    "gn:feature_class":"P",
    "gn:feature_code":"PPL",
    "gn:name":"Gunungdamar",
    "gn:population":0,
    "gn:timezone":"Asia/Jakarta",
    "iso:country":"ID",
    "name:ind_x_preferred":[
        "Gunungdamar"
    ],
    "wof:name":"Gunungdamar",
    "wof:placetype":"locality"
},
  "geometry": {"coordinates":[108.6523,-7.4575],"type":"Point"}
}