{
  "type": "Feature",
  "properties": {
    "gn:admin1_code":"29.0",
    "gn:asciiname":"Kobe",
    "gn:country_code":"ID",
    "gn:dem":5,
    "gn:feature_class":"P",
    "gn:feature_code":"PPL",
    "gn:name":"Kobe",
    "gn:population":0,
    "gn:timezone":"Asia/Jayapura",
    "iso:country":"ID",
    "name:und_x_variant":[
        "Kobo",
        "Kobe"
    ],
    "wof:name":"Kobe",
    "wof:placetype":"locality"
},
  "geometry": {"coordinates":[127.90000999999999,0.42909],"type":"Point"}
}