{
  "type": "Feature",
  "properties": {
    "gn:admin1_code":"18",
    "gn:asciiname":"Pedang",
    "gn:country_code":"ID",
    "gn:dem":810,
    "gn:feature_class":"P",
    "gn:feature_code":"PPL",
    "gn:name":"Pedang",
    "gn:population":0,
    "gn:timezone":"Asia/Makassar",
    "iso:country":"ID",
    "name:ceb_x_preferred":[
        "Pedang"
    ],
    "name:ind_x_preferred":[
        "Pedang"
    ],
    "name:msa_x_preferred":[
        "Pedang"
    ],
    "name:nep_x_preferred":[
        "\u092a\u0947\u0926\u093e\u0919"
    ],
    "name:new_x_preferred":[
        "\u092a\u0947\u0926\u093e\u0919"
    ],
    "name:pol_x_preferred":[
        "Pedang"
    ],
    "wof:lang_x_official":[
        "ind"
    ],
    "wof:lang_x_spoken":[
        "ind",
        "eng"
    ],
    "wof:name":"Pedang",
    "wof:placetype":"locality"
},
  "geometry": {"coordinates":[120.3549,-8.6565],"type":"Point"}
}