{
  "type": "Feature",
  "properties": {
    "gn:admin1_code":"35.0",
    "gn:asciiname":"Airbatu",
    "gn:country_code":"ID",
    "gn:dem":25,
    "gn:feature_class":"P",
    "gn:feature_code":"PPL",
    "gn:name":"Airbatu",
    "gn:population":0,
    "gn:timezone":"Asia/Jakarta",
    "iso:country":"ID",
    "name:ind_x_preferred":[
        "Airbatu"
    ],
    "wof:name":"Airbatu",
    "wof:placetype":"locality"
},
  "geometry": {"coordinates":[107.89997,-2.74627],"type":"Point"}
}