{
  "type": "Feature",
  "properties": {
    "gn:admin1_code":"8.0",
    "gn:asciiname":"Jetak",
    "gn:country_code":"ID",
    "gn:dem":195,
    "gn:feature_class":"P",
    "gn:feature_code":"PPL",
    "gn:name":"Jetak",
    "gn:population":0,
    "gn:timezone":"Asia/Jakarta",
    "iso:country":"ID",
    "name:ind_x_preferred":[
        "Jetak"
    ],
    "name:und_x_variant":[
        "Djetak"
    ],
    "wof:name":"Jetak",
    "wof:placetype":"locality"
},
  "geometry": {"coordinates":[112.7039,-7.6712],"type":"Point"}
}