{
  "type": "Feature",
  "properties": {
    "gn:country":"ID",
    "gn:fcode":"PPL",
    "gn:pop":0,
    "iso:country":"ID",
    "name:unk_x_variant":[
        "Mare"
    ],
    "qs:name":"Marek",
    "qs:name_adm0":"Indonesia",
    "qs:name_adm1":"Sulawesi Selatan",
    "qs:photos_9r":0,
    "qs:photos_sr":0,
    "qs:placetype":"Town",
    "qs:pop_sr":"5",
    "wd:wordcount":198,
    "wof:name":"Marek",
    "wof:placetype":"locality",
    "wof:population":0
},
  "geometry": {"coordinates":[120.3443,-4.8062],"type":"Point"}
}