{
  "type": "Feature",
  "properties": {
    "gn:admin1_code":"26",
    "gn:asciiname":"Pasarkemis",
    "gn:country_code":"ID",
    "gn:dem":6,
    "gn:feature_class":"P",
    "gn:feature_code":"PPL",
    "gn:name":"Pasarkemis",
    "gn:population":0,
    "gn:timezone":"Asia/Jakarta",
    "iso:country":"ID",
    "name:ceb_x_preferred":[
        "Pasarkemis"
    ],
    "name:fas_x_preferred":[
        "\u067e\u0627\u0633\u0631\u06a9\u0645\u06cc\u0633"
    ],
    "name:fra_x_preferred":[
        "Pasarkemis"
    ],
    "name:ind_x_preferred":[
        "Pasarkemis"
    ],
    "name:ind_x_variant":[
        "Pasar Kemis"
    ],
    "name:jav_x_preferred":[
        "Pasarkemis"
    ],
    "name:mlg_x_preferred":[
        "Pasarkemis"
    ],
    "name:msa_x_preferred":[
        "Pasarkemis"
    ],
    "name:nld_x_preferred":[
        "Pasarkemis"
    ],
    "name:nor_x_preferred":[
        "Pasarkemis"
    ],
    "name:swe_x_preferred":[
        "Pasarkemis"
    ],
    "wof:name":"Pasarkemis",
    "wof:placetype":"locality"
},
  "geometry": {"coordinates":[98.5531,3.8109],"type":"Point"}
}