{
  "type": "Feature",
  "properties": {
    "gn:admin1_code":"17",
    "gn:asciiname":"Sangiang",
    "gn:country_code":"ID",
    "gn:dem":11,
    "gn:feature_class":"P",
    "gn:feature_code":"PPLA4",
    "gn:name":"Sangiang",
    "gn:population":0,
    "gn:timezone":"Asia/Makassar",
    "iso:country":"ID",
    "name:ind_x_preferred":[
        "Sangiang"
    ],
    "wof:name":"Sangiang",
    "wof:placetype":"locality"
},
  "geometry": {"coordinates":[118.9332,-8.2969],"type":"Point"}
}