{
  "type": "Feature",
  "properties": {
    "gn:admin1_code":"30.0",
    "gn:asciiname":"Kebonkopi",
    "gn:country_code":"ID",
    "gn:dem":483,
    "gn:feature_class":"P",
    "gn:feature_code":"PPL",
    "gn:name":"Kebonkopi",
    "gn:population":0,
    "gn:timezone":"Asia/Jakarta",
    "iso:country":"ID",
    "name:ind_x_preferred":[
        "Kebonkopi"
    ],
    "wof:name":"Kebonkopi",
    "wof:placetype":"locality"
},
  "geometry": {"coordinates":[107.0611,-7.2169],"type":"Point"}
}