{
  "type": "Feature",
  "properties": {
    "gn:admin1_code":"18.0",
    "gn:asciiname":"Oekefan",
    "gn:country_code":"ID",
    "gn:dem":831,
    "gn:feature_class":"P",
    "gn:feature_code":"PPL",
    "gn:name":"Oekefan",
    "gn:population":0,
    "gn:timezone":"Asia/Makassar",
    "iso:country":"ID",
    "name:ind_x_preferred":[
        "Oekefan"
    ],
    "wof:name":"Oekefan",
    "wof:placetype":"locality"
},
  "geometry": {"coordinates":[124.58,-9.8373],"type":"Point"}
}