{
  "type": "Feature",
  "properties": {
    "gn:admin1_code":"17.0",
    "gn:asciiname":"Kerukak",
    "gn:country_code":"ID",
    "gn:dem":91,
    "gn:feature_class":"P",
    "gn:feature_code":"PPL",
    "gn:name":"Kerukak",
    "gn:population":0,
    "gn:timezone":"Asia/Makassar",
    "iso:country":"ID",
    "name:ind_x_preferred":[
        "Kerukak"
    ],
    "wof:name":"Kerukak",
    "wof:placetype":"locality"
},
  "geometry": {"coordinates":[116.21550000000001,-8.3356],"type":"Point"}
}