{
  "type": "Feature",
  "properties": {
    "gn:admin1_code":"22.0",
    "gn:asciiname":"Rompurompu",
    "gn:country_code":"ID",
    "gn:dem":24,
    "gn:feature_class":"P",
    "gn:feature_code":"PPL",
    "gn:name":"Rompurompu",
    "gn:population":0,
    "gn:timezone":"Asia/Makassar",
    "iso:country":"ID",
    "name:ind_x_preferred":[
        "Rompurompu"
    ],
    "name:und_x_variant":[
        "Romporompo"
    ],
    "wof:name":"Rompurompu",
    "wof:placetype":"locality"
},
  "geometry": {"coordinates":[121.79089999999999,-4.7794],"type":"Point"}
}