{
  "type": "Feature",
  "properties": {
    "gn:admin1_code":"30.0",
    "gn:asciiname":"Puncak",
    "gn:country_code":"ID",
    "gn:dem":566,
    "gn:feature_class":"P",
    "gn:feature_code":"PPL",
    "gn:name":"Puncak",
    "gn:population":0,
    "gn:timezone":"Asia/Jakarta",
    "iso:country":"ID",
    "name:ara_x_preferred":[
        "\u0628\u0648\u0646\u0634\u0627\u0643"
    ],
    "name:ind_x_preferred":[
        "Puncak"
    ],
    "name:nld_x_preferred":[
        "Puncak"
    ],
    "wof:lang_x_official":[
        "ind"
    ],
    "wof:lang_x_spoken":[
        "ind",
        "eng"
    ],
    "wof:name":"Puncak",
    "wof:placetype":"locality"
},
  "geometry": {"coordinates":[107.08669999999999,-7.2905],"type":"Point"}
}