{
  "type": "Feature",
  "properties": {
    "gn:admin1_code":"14",
    "gn:asciiname":"Perkebunan Inti Rakyat Rangen Dua",
    "gn:country_code":"ID",
    "gn:dem":25,
    "gn:feature_class":"P",
    "gn:feature_code":"PPL",
    "gn:name":"Perkebunan Inti Rakyat Rangen Dua",
    "gn:population":0,
    "gn:timezone":"Asia/Makassar",
    "iso:country":"ID",
    "name:ind_x_preferred":[
        "Perkebunan Inti Rakyat Rangen Dua"
    ],
    "wof:name":"Perkebunan Inti Rakyat Rangen Dua",
    "wof:placetype":"locality"
},
  "geometry": {"coordinates":[116.09950000000001,-1.7614],"type":"Point"}
}