{
  "type": "Feature",
  "properties": {
    "gn:admin1_code":"8.0",
    "gn:asciiname":"Bugeger",
    "gn:country_code":"ID",
    "gn:dem":175,
    "gn:feature_class":"P",
    "gn:feature_code":"PPL",
    "gn:name":"Bugeger",
    "gn:population":0,
    "gn:timezone":"Asia/Jakarta",
    "iso:country":"ID",
    "name:ind_x_preferred":[
        "Bugeger"
    ],
    "wof:name":"Bugeger",
    "wof:placetype":"locality"
},
  "geometry": {"coordinates":[112.9967,-6.9754],"type":"Point"}
}