{
  "type": "Feature",
  "properties": {
    "gn:admin1_code":"30",
    "gn:asciiname":"Ciloa",
    "gn:country_code":"ID",
    "gn:dem":727,
    "gn:feature_class":"P",
    "gn:feature_code":"PPL",
    "gn:name":"Ciloa",
    "gn:population":0,
    "gn:timezone":"Asia/Jakarta",
    "iso:country":"ID",
    "wof:name":"Ciloa",
    "wof:placetype":"locality"
},
  "geometry": {"coordinates":[107.52472,-7.02361],"type":"Point"}
}