{
  "type": "Feature",
  "properties": {
    "gn:admin1_code":"30.0",
    "gn:asciiname":"Pananggungan",
    "gn:country_code":"ID",
    "gn:dem":691,
    "gn:feature_class":"P",
    "gn:feature_code":"PPL",
    "gn:name":"Pananggungan",
    "gn:population":0,
    "gn:timezone":"Asia/Jakarta",
    "iso:country":"ID",
    "name:ind_x_preferred":[
        "Pananggungan"
    ],
    "name:und_x_variant":[
        "Pananggoengan"
    ],
    "wof:lang_x_official":[
        "ind"
    ],
    "wof:lang_x_spoken":[
        "ind",
        "eng"
    ],
    "wof:name":"Pananggungan",
    "wof:placetype":"locality"
},
  "geometry": {"coordinates":[107.9252,-7.1874],"type":"Point"}
}