{
  "type": "Feature",
  "properties": {
    "gn:admin1_code":"8.0",
    "gn:asciiname":"Sukodono",
    "gn:country_code":"ID",
    "gn:dem":22,
    "gn:feature_class":"P",
    "gn:feature_code":"PPL",
    "gn:name":"Sukodono",
    "gn:population":0,
    "gn:timezone":"Asia/Jakarta",
    "iso:country":"ID",
    "name:ind_x_preferred":[
        "Sukodono"
    ],
    "wof:name":"Sukodono",
    "wof:placetype":"locality"
},
  "geometry": {"coordinates":[112.45359999999999,-7.4286],"type":"Point"}
}