{
  "type": "Feature",
  "properties": {
    "gn:admin1_code":"8",
    "gn:asciiname":"Bara'ala",
    "gn:country_code":"ID",
    "gn:dem":11,
    "gn:feature_class":"P",
    "gn:feature_code":"PPL",
    "gn:name":"Bara\u2019ala",
    "gn:population":0,
    "gn:timezone":"Asia/Jakarta",
    "iso:country":"ID",
    "name:ind_x_preferred":[
        "Bara\u2019ala"
    ],
    "wof:name":"Bara'ala",
    "wof:placetype":"locality"
},
  "geometry": {"coordinates":[113.1961,-7.1363],"type":"Point"}
}