{
  "type": "Feature",
  "properties": {
    "gn:admin1_code":"07",
    "gn:asciiname":"Candipromasan",
    "gn:country_code":"ID",
    "gn:dem":1429,
    "gn:feature_class":"P",
    "gn:feature_code":"PPL",
    "gn:name":"Candipromasan",
    "gn:population":0,
    "gn:timezone":"Asia/Jakarta",
    "iso:country":"ID",
    "name:ind_x_preferred":[
        "Candipromasan"
    ],
    "name:und_x_variant":[
        "Tjandiperglon",
        "Candiperglon"
    ],
    "wof:lang_x_official":[
        "ind"
    ],
    "wof:lang_x_spoken":[
        "ind",
        "eng"
    ],
    "wof:name":"Candipromasan",
    "wof:placetype":"locality"
},
  "geometry": {"coordinates":[110.35222,-7.17167],"type":"Point"}
}