{
  "type": "Feature",
  "properties": {
    "gn:admin1_code":"38",
    "gn:asciiname":"Tokasa",
    "gn:country_code":"ID",
    "gn:dem":65,
    "gn:feature_class":"P",
    "gn:feature_code":"PPL",
    "gn:name":"Tokasa",
    "gn:population":0,
    "gn:timezone":"Asia/Makassar",
    "iso:country":"ID",
    "name:ind_x_preferred":[
        "Tokasa"
    ],
    "wof:name":"Tokasa",
    "wof:placetype":"locality"
},
  "geometry": {"coordinates":[120.12309999999999,-4.3084],"type":"Point"}
}