{
  "type": "Feature",
  "properties": {
    "gn:admin1_code":"26",
    "gn:asciiname":"Padang Siandomang",
    "gn:country_code":"ID",
    "gn:dem":1046,
    "gn:feature_class":"P",
    "gn:feature_code":"PPL",
    "gn:name":"Padang Siandomang",
    "gn:population":0,
    "gn:timezone":"Asia/Jakarta",
    "iso:country":"ID",
    "name:ind_x_preferred":[
        "Padang Siandomang"
    ],
    "wof:name":"Padang Siandomang",
    "wof:placetype":"locality"
},
  "geometry": {"coordinates":[99.2496,2.049],"type":"Point"}
}