{
  "type": "Feature",
  "properties": {
    "gn:admin1_code":"30",
    "gn:asciiname":"Lombang",
    "gn:country_code":"ID",
    "gn:dem":8,
    "gn:feature_class":"P",
    "gn:feature_code":"PPL",
    "gn:name":"Lombang",
    "gn:population":0,
    "gn:timezone":"Asia/Jakarta",
    "iso:country":"ID",
    "name:ind_x_preferred":[
        "Lombang"
    ],
    "wof:name":"Lombang",
    "wof:placetype":"locality"
},
  "geometry": {"coordinates":[107.75611000000001,-6.29222],"type":"Point"}
}