{
  "type": "Feature",
  "properties": {
    "gn:admin1_code":"30.0",
    "gn:asciiname":"Cikarikil",
    "gn:country_code":"ID",
    "gn:dem":808,
    "gn:feature_class":"P",
    "gn:feature_code":"PPL",
    "gn:name":"Cikarikil",
    "gn:population":0,
    "gn:timezone":"Asia/Jakarta",
    "iso:country":"ID",
    "name:ind_x_preferred":[
        "Cikarikil"
    ],
    "wof:name":"Cikarikil",
    "wof:placetype":"locality"
},
  "geometry": {"coordinates":[107.76090000000001,-7.5152],"type":"Point"}
}