{
  "type": "Feature",
  "properties": {
    "gn:admin1_code":"8",
    "gn:asciiname":"Watupecah",
    "gn:country_code":"ID",
    "gn:dem":864,
    "gn:feature_class":"P",
    "gn:feature_code":"PPL",
    "gn:name":"Watupecah",
    "gn:population":0,
    "gn:timezone":"Asia/Jakarta",
    "iso:country":"ID",
    "name:ind_x_preferred":[
        "Watupecah"
    ],
    "wof:name":"Watupecah",
    "wof:placetype":"locality"
},
  "geometry": {"coordinates":[111.27806,-7.9775],"type":"Point"}
}