{
  "type": "Feature",
  "properties": {
    "gn:admin1_code":"8",
    "gn:asciiname":"Ngangkang",
    "gn:country_code":"ID",
    "gn:dem":133,
    "gn:feature_class":"P",
    "gn:feature_code":"PPL",
    "gn:name":"Ngangkang",
    "gn:population":0,
    "gn:timezone":"Asia/Jakarta",
    "iso:country":"ID",
    "name:ind_x_preferred":[
        "Ngangkang"
    ],
    "wof:name":"Ngangkang",
    "wof:placetype":"locality"
},
  "geometry": {"coordinates":[113.7529,-8.2306],"type":"Point"}
}