{
  "type": "Feature",
  "properties": {
    "gn:admin1_code":"41",
    "gn:asciiname":"Loso",
    "gn:country_code":"ID",
    "gn:dem":11,
    "gn:feature_class":"P",
    "gn:feature_code":"PPL",
    "gn:name":"Loso",
    "gn:population":0,
    "gn:timezone":"Asia/Makassar",
    "iso:country":"ID",
    "name:ces_x_preferred":[
        "Loso"
    ],
    "name:fra_x_preferred":[
        "Loso"
    ],
    "name:ind_x_preferred":[
        "Loso"
    ],
    "name:jpn_x_preferred":[
        "Loso"
    ],
    "name:nor_x_preferred":[
        "Loso"
    ],
    "name:pol_x_preferred":[
        "Loso"
    ],
    "name:spa_x_preferred":[
        "Loso"
    ],
    "name:swe_x_preferred":[
        "Loso"
    ],
    "name:tha_x_preferred":[
        "\u0e42\u0e25\u0e42\u0e0b"
    ],
    "wof:name":"Loso",
    "wof:placetype":"locality"
},
  "geometry": {"coordinates":[119.1972,-2.3218],"type":"Point"}
}