{
  "type": "Feature",
  "properties": {
    "gn:admin1_code":"40.0",
    "gn:asciiname":"Jago",
    "gn:country_code":"ID",
    "gn:dem":5,
    "gn:feature_class":"P",
    "gn:feature_code":"PPL",
    "gn:name":"Jago",
    "gn:population":0,
    "gn:timezone":"Asia/Jakarta",
    "iso:country":"ID",
    "name:deu_x_preferred":[
        "Jago"
    ],
    "name:fra_x_preferred":[
        "Jago"
    ],
    "name:swe_x_preferred":[
        "Jago"
    ],
    "name:und_x_variant":[
        "Djago",
        "Diago",
        "Jago"
    ],
    "wof:name":"Jago",
    "wof:placetype":"locality"
},
  "geometry": {"coordinates":[104.45316,-0.34541],"type":"Point"}
}