{
  "type": "Feature",
  "properties": {
    "gn:admin1_code":"10",
    "gn:asciiname":"Kedungdowo Selatan",
    "gn:country_code":"ID",
    "gn:dem":165,
    "gn:feature_class":"P",
    "gn:feature_code":"PPL",
    "gn:name":"Kedungdowo Selatan",
    "gn:population":0,
    "gn:timezone":"Asia/Jakarta",
    "iso:country":"ID",
    "wof:name":"Kedungdowo Selatan",
    "wof:placetype":"locality"
},
  "geometry": {"coordinates":[110.54472,-7.98778],"type":"Point"}
}