{
  "type": "Feature",
  "properties": {
    "gn:admin1_code":"18.0",
    "gn:asciiname":"Kamangi",
    "gn:country_code":"ID",
    "gn:dem":21,
    "gn:feature_class":"P",
    "gn:feature_code":"PPL",
    "gn:name":"Kamangi",
    "gn:population":0,
    "gn:timezone":"Asia/Makassar",
    "iso:country":"ID",
    "name:ind_x_preferred":[
        "Kamangi"
    ],
    "wof:name":"Kamangi",
    "wof:placetype":"locality"
},
  "geometry": {"coordinates":[120.73650000000001,-10.1285],"type":"Point"}
}