{
  "type": "Feature",
  "properties": {
    "gn:admin1_code":"30",
    "gn:asciiname":"Teluk",
    "gn:country_code":"ID",
    "gn:dem":17,
    "gn:feature_class":"P",
    "gn:feature_code":"PPL",
    "gn:name":"Teluk",
    "gn:population":0,
    "gn:timezone":"Asia/Jakarta",
    "iso:country":"ID",
    "name:ind_x_preferred":[
        "Teluk"
    ],
    "name:nld_x_preferred":[
        "Teluk"
    ],
    "wof:name":"Teluk",
    "wof:placetype":"locality"
},
  "geometry": {"coordinates":[108.32639,-6.54667],"type":"Point"}
}