{
  "type": "Feature",
  "properties": {
    "gn:admin1_code":"21",
    "gn:asciiname":"Molowagu",
    "gn:country_code":"ID",
    "gn:dem":56,
    "gn:feature_class":"P",
    "gn:feature_code":"PPL",
    "gn:name":"Molowagu",
    "gn:population":0,
    "gn:timezone":"Asia/Makassar",
    "iso:country":"ID",
    "name:ind_x_preferred":[
        "Molowagu"
    ],
    "wof:name":"Molowagu",
    "wof:placetype":"locality"
},
  "geometry": {"coordinates":[121.6756,-0.5513],"type":"Point"}
}