{
  "type": "Feature",
  "properties": {
    "gn:admin1_code":"38.0",
    "gn:asciiname":"Rantelimbong",
    "gn:country_code":"ID",
    "gn:dem":812,
    "gn:feature_class":"P",
    "gn:feature_code":"PPL",
    "gn:name":"Rantelimbong",
    "gn:population":0,
    "gn:timezone":"Asia/Makassar",
    "iso:country":"ID",
    "name:ind_x_preferred":[
        "Rantelimbong"
    ],
    "wof:lang_x_official":[
        "ind"
    ],
    "wof:lang_x_spoken":[
        "ind",
        "eng"
    ],
    "wof:name":"Rantelimbong",
    "wof:placetype":"locality"
},
  "geometry": {"coordinates":[119.9062,-2.9699],"type":"Point"}
}