{
  "type": "Feature",
  "properties": {
    "gn:admin1_code":"7",
    "gn:asciiname":"Ngaglik Lama",
    "gn:country_code":"ID",
    "gn:dem":35,
    "gn:feature_class":"P",
    "gn:feature_code":"PPL",
    "gn:name":"Ngaglik Lama",
    "gn:population":0,
    "gn:timezone":"Asia/Jakarta",
    "iso:country":"ID",
    "name:ind_x_preferred":[
        "Ngaglik Lama"
    ],
    "wof:name":"Ngaglik Lama",
    "wof:placetype":"locality"
},
  "geometry": {"coordinates":[110.4093,-6.9983],"type":"Point"}
}