{
  "type": "Feature",
  "properties": {
    "iso:country":"ID",
    "qs:name":"Ploeit",
    "qs:name_adm0":"Indonesia",
    "qs:name_adm1":"Jakarta Raya",
    "qs:photos":155,
    "qs:photos_1k":31,
    "qs:photos_9k":1,
    "qs:photos_9r":4,
    "qs:photos_all":155,
    "qs:photos_sr":4,
    "qs:placetype":"Suburb",
    "qs:pop_sr":"0",
    "wof:name":"Ploeit",
    "wof:placetype":"neighbourhood"
},
  "geometry": {"coordinates":[106.792945,-6.117086],"type":"Point"}
}