{
  "type": "Feature",
  "properties": {
    "gn:admin1_code":"22.0",
    "gn:asciiname":"Tedoso",
    "gn:country_code":"ID",
    "gn:dem":27,
    "gn:feature_class":"P",
    "gn:feature_code":"PPL",
    "gn:name":"Tedoso",
    "gn:population":0,
    "gn:timezone":"Asia/Makassar",
    "iso:country":"ID",
    "name:ind_x_preferred":[
        "Tedoso"
    ],
    "wof:name":"Tedoso",
    "wof:placetype":"locality"
},
  "geometry": {"coordinates":[121.589,-4.4628],"type":"Point"}
}