{
  "type": "Feature",
  "properties": {
    "gn:admin1_code":"36.0",
    "gn:asciiname":"Bad",
    "gn:country_code":"ID",
    "gn:dem":10,
    "gn:feature_class":"P",
    "gn:feature_code":"PPL",
    "gn:name":"Bad",
    "gn:population":0,
    "gn:timezone":"Asia/Jayapura",
    "iso:country":"ID",
    "name:aze_x_preferred":[
        "Bad"
    ],
    "name:ceb_x_preferred":[
        "Bad"
    ],
    "name:ces_x_preferred":[
        "Bad"
    ],
    "name:dan_x_preferred":[
        "Bad"
    ],
    "name:deu_x_preferred":[
        "Bad"
    ],
    "name:fra_x_preferred":[
        "Bad"
    ],
    "name:ind_x_preferred":[
        "Bad"
    ],
    "name:jpn_x_preferred":[
        "\u30d0\u30c3\u30c9"
    ],
    "name:kor_x_preferred":[
        "Bad"
    ],
    "name:new_x_preferred":[
        "\u092c\u093e\u0926"
    ],
    "name:nld_x_preferred":[
        "Bad"
    ],
    "name:nno_x_preferred":[
        "Bad"
    ],
    "name:pol_x_preferred":[
        "Bad"
    ],
    "name:por_x_preferred":[
        "Bad"
    ],
    "name:rus_x_preferred":[
        "Bad"
    ],
    "name:spa_x_preferred":[
        "Bad"
    ],
    "name:tha_x_preferred":[
        "\u0e41\u0e1a\u0e14"
    ],
    "name:tur_x_preferred":[
        "Bad"
    ],
    "name:und_x_variant":[
        "Bade"
    ],
    "wof:lang_x_official":[
        "ind"
    ],
    "wof:lang_x_spoken":[
        "ind",
        "eng"
    ],
    "wof:name":"Bad",
    "wof:placetype":"locality"
},
  "geometry": {"coordinates":[140.49504999999999,-8.03185],"type":"Point"}
}