{
  "type": "Feature",
  "properties": {
    "gn:country":"ID",
    "gn:fcode":"PPLA3",
    "gn:pop":0,
    "iso:country":"ID",
    "name:ind_x_preferred":[
        "Tumpang"
    ],
    "name:unk_x_variant":[
        "Toempang"
    ],
    "qs:name":"Tumpang",
    "qs:photos_9r":0,
    "qs:photos_sr":0,
    "qs:pop_sr":"0",
    "wof:lang_x_official":[
        "ind"
    ],
    "wof:lang_x_spoken":[
        "ind",
        "eng"
    ],
    "wof:name":"Tumpang",
    "wof:placetype":"locality",
    "wof:population":0
},
  "geometry": {"coordinates":[112.76390000000001,-8.0061],"type":"Point"}
}