{
  "type": "Feature",
  "properties": {
    "gn:admin1_code":"30",
    "gn:asciiname":"Blok D",
    "gn:country_code":"ID",
    "gn:dem":8,
    "gn:feature_class":"P",
    "gn:feature_code":"PPL",
    "gn:name":"Blok D",
    "gn:population":0,
    "gn:timezone":"Asia/Jakarta",
    "iso:country":"ID",
    "name:ind_x_preferred":[
        "Blok D"
    ],
    "wof:name":"Blok D",
    "wof:placetype":"locality"
},
  "geometry": {"coordinates":[108.30444,-6.37417],"type":"Point"}
}