{
  "type": "Feature",
  "properties": {
    "gn:admin1_code":"30",
    "gn:asciiname":"Parakankembang",
    "gn:country_code":"ID",
    "gn:dem":174,
    "gn:feature_class":"P",
    "gn:feature_code":"PPL",
    "gn:name":"Parakankembang",
    "gn:population":0,
    "gn:timezone":"Asia/Jakarta",
    "iso:country":"ID",
    "name:ind_x_preferred":[
        "Parakankembang"
    ],
    "wof:name":"Parakankembang",
    "wof:placetype":"locality"
},
  "geometry": {"coordinates":[106.80722,-6.53694],"type":"Point"}
}