{
  "type": "Feature",
  "properties": {
    "gn:admin1_code":"18.0",
    "gn:asciiname":"Kilimbatu",
    "gn:country_code":"ID",
    "gn:dem":21,
    "gn:feature_class":"P",
    "gn:feature_code":"PPL",
    "gn:name":"Kilimbatu",
    "gn:population":0,
    "gn:timezone":"Asia/Makassar",
    "iso:country":"ID",
    "name:ind_x_preferred":[
        "Kilimbatu"
    ],
    "wof:name":"Kilimbatu",
    "wof:placetype":"locality"
},
  "geometry": {"coordinates":[120.67234999999999,-9.93033],"type":"Point"}
}