{
  "type": "Feature",
  "properties": {
    "gn:admin1_code":"7",
    "gn:asciiname":"Karangdawa",
    "gn:country_code":"ID",
    "gn:dem":332,
    "gn:feature_class":"P",
    "gn:feature_code":"PPL",
    "gn:name":"Karangdawa",
    "gn:population":0,
    "gn:timezone":"Asia/Jakarta",
    "iso:country":"ID",
    "name:ind_x_preferred":[
        "Karangdawa"
    ],
    "wof:name":"Karangdawa",
    "wof:placetype":"locality"
},
  "geometry": {"coordinates":[109.26439999999999,-7.0804],"type":"Point"}
}