{
  "type": "Feature",
  "properties": {
    "gn:admin1_code":"14.0",
    "gn:asciiname":"Satuan Pemukiman Satu Kaliorang",
    "gn:country_code":"ID",
    "gn:dem":26,
    "gn:feature_class":"P",
    "gn:feature_code":"PPL",
    "gn:name":"Satuan Pemukiman Satu Kaliorang",
    "gn:population":0,
    "gn:timezone":"Asia/Makassar",
    "iso:country":"ID",
    "name:ind_x_preferred":[
        "Satuan Pemukiman Satu Kaliorang"
    ],
    "name:und_x_variant":[
        "SP. 1 Kaliorang"
    ],
    "wof:lang_x_official":[
        "ind"
    ],
    "wof:lang_x_spoken":[
        "ind",
        "eng"
    ],
    "wof:name":"Satuan Pemukiman Satu Kaliorang",
    "wof:placetype":"locality"
},
  "geometry": {"coordinates":[117.83450000000001,0.8895],"type":"Point"}
}