{
  "type": "Feature",
  "properties": {
    "gn:admin1_code":"31.0",
    "gn:asciiname":"Molobog",
    "gn:country_code":"ID",
    "gn:dem":20,
    "gn:feature_class":"P",
    "gn:feature_code":"PPL",
    "gn:name":"Molobog",
    "gn:population":0,
    "gn:timezone":"Asia/Makassar",
    "iso:country":"ID",
    "name:ind_x_preferred":[
        "Molobog"
    ],
    "name:und_x_variant":[
        "Boentaja",
        "Molobok",
        "Djiko",
        "Molobog",
        "Jiko"
    ],
    "wof:lang_x_official":[
        "ind"
    ],
    "wof:lang_x_spoken":[
        "ind",
        "eng"
    ],
    "wof:name":"Molobog",
    "wof:placetype":"locality"
},
  "geometry": {"coordinates":[124.5363,0.6524],"type":"Point"}
}