{
  "type": "Feature",
  "properties": {
    "gn:admin1_code":"26",
    "gn:asciiname":"Bukit Tinggi",
    "gn:country_code":"ID",
    "gn:dem":123,
    "gn:feature_class":"P",
    "gn:feature_code":"PPL",
    "gn:name":"Bukit Tinggi",
    "gn:population":0,
    "gn:timezone":"Asia/Jakarta",
    "iso:country":"ID",
    "name:ceb_x_preferred":[
        "Bukit Tinggi"
    ],
    "name:ind_x_preferred":[
        "Bukit Tinggi"
    ],
    "name:nld_x_preferred":[
        "Bukit Tinggi"
    ],
    "name:swe_x_preferred":[
        "Bukit Tinggi"
    ],
    "wof:name":"Bukit Tinggi",
    "wof:placetype":"locality"
},
  "geometry": {"coordinates":[99.67243999999999,1.82614],"type":"Point"}
}