{
  "type": "Feature",
  "properties": {
    "gn:admin1_code":"30.0",
    "gn:asciiname":"Bojongpicung",
    "gn:country_code":"ID",
    "gn:dem":591,
    "gn:feature_class":"P",
    "gn:feature_code":"PPL",
    "gn:name":"Bojongpicung",
    "gn:population":0,
    "gn:timezone":"Asia/Jakarta",
    "iso:country":"ID",
    "name:ind_x_preferred":[
        "Bojongpicung"
    ],
    "name:und_x_variant":[
        "Bodjongpitjoeng"
    ],
    "wof:name":"Bojongpicung",
    "wof:placetype":"locality"
},
  "geometry": {"coordinates":[106.9093,-7.1154],"type":"Point"}
}