{
  "type": "Feature",
  "properties": {
    "gn:admin1_code":"30.0",
    "gn:asciiname":"Pasirlinggaindah",
    "gn:country_code":"ID",
    "gn:dem":729,
    "gn:feature_class":"P",
    "gn:feature_code":"PPL",
    "gn:name":"Pasirlinggaindah",
    "gn:population":0,
    "gn:timezone":"Asia/Jakarta",
    "iso:country":"ID",
    "name:ind_x_preferred":[
        "Pasirlinggaindah"
    ],
    "wof:name":"Pasirlinggaindah",
    "wof:placetype":"locality"
},
  "geometry": {"coordinates":[107.8925,-7.1764],"type":"Point"}
}