{
  "type": "Feature",
  "properties": {
    "gn:admin1_code":"8.0",
    "gn:asciiname":"Simorukun",
    "gn:country_code":"ID",
    "gn:dem":47,
    "gn:feature_class":"P",
    "gn:feature_code":"PPL",
    "gn:name":"Simorukun",
    "gn:population":0,
    "gn:timezone":"Asia/Jakarta",
    "iso:country":"ID",
    "name:ind_x_preferred":[
        "Simorukun"
    ],
    "wof:name":"Simorukun",
    "wof:placetype":"locality"
},
  "geometry": {"coordinates":[112.3588,-7.3388],"type":"Point"}
}