{
  "type": "Feature",
  "properties": {
    "gn:admin1_code":"30",
    "gn:asciiname":"Sawahdadap",
    "gn:country_code":"ID",
    "gn:dem":690,
    "gn:feature_class":"P",
    "gn:feature_code":"PPL",
    "gn:name":"Sawahdadap",
    "gn:population":0,
    "gn:timezone":"Asia/Jakarta",
    "iso:country":"ID",
    "name:ind_x_preferred":[
        "Sawahdadap"
    ],
    "wof:name":"Sawahdadap",
    "wof:placetype":"locality"
},
  "geometry": {"coordinates":[107.80694,-6.95139],"type":"Point"}
}