{
  "type": "Feature",
  "properties": {
    "gn:admin1_code":"32.0",
    "gn:asciiname":"Tanjungbulan",
    "gn:country_code":"ID",
    "gn:dem":962,
    "gn:feature_class":"P",
    "gn:feature_code":"PPL",
    "gn:name":"Tanjungbulan",
    "gn:population":0,
    "gn:timezone":"Asia/Jakarta",
    "iso:country":"ID",
    "name:ind_x_preferred":[
        "Tanjungbulan"
    ],
    "name:ind_x_variant":[
        "Tanjung Bulan"
    ],
    "wof:name":"Tanjungbulan",
    "wof:placetype":"locality"
},
  "geometry": {"coordinates":[103.60363,-4.49276],"type":"Point"}
}