{
  "type": "Feature",
  "properties": {
    "gn:admin1_code":"38",
    "gn:asciiname":"Waetuwo",
    "gn:country_code":"ID",
    "gn:dem":125,
    "gn:feature_class":"P",
    "gn:feature_code":"PPL",
    "gn:name":"Waetuwo",
    "gn:population":0,
    "gn:timezone":"Asia/Makassar",
    "iso:country":"ID",
    "name:ind_x_preferred":[
        "Waetuwo"
    ],
    "wof:name":"Waetuwo",
    "wof:placetype":"locality"
},
  "geometry": {"coordinates":[120.1353,-5.0105],"type":"Point"}
}