{
  "type": "Feature",
  "properties": {
    "gn:admin1_code":"33.0",
    "gn:asciiname":"Bodaan",
    "gn:country_code":"ID",
    "gn:dem":335,
    "gn:feature_class":"P",
    "gn:feature_code":"PPL",
    "gn:name":"Bodaan",
    "gn:population":0,
    "gn:timezone":"Asia/Jakarta",
    "iso:country":"ID",
    "name:ind_x_preferred":[
        "Bodaan"
    ],
    "wof:name":"Bodaan",
    "wof:placetype":"locality"
},
  "geometry": {"coordinates":[106.2088,-6.6243],"type":"Point"}
}