{
  "type": "Feature",
  "properties": {
    "gn:admin1_code":"08",
    "gn:asciiname":"Angsoka",
    "gn:country_code":"ID",
    "gn:dem":89,
    "gn:feature_class":"P",
    "gn:feature_code":"PPL",
    "gn:name":"Angsoka",
    "gn:population":0,
    "gn:timezone":"Asia/Jakarta",
    "iso:country":"ID",
    "wof:name":"Angsoka",
    "wof:placetype":"locality"
},
  "geometry": {"coordinates":[112.84889,-7.04389],"type":"Point"}
}