{
  "type": "Feature",
  "properties": {
    "gn:admin1_code":"8.0",
    "gn:asciiname":"Binoloh",
    "gn:country_code":"ID",
    "gn:dem":46,
    "gn:feature_class":"P",
    "gn:feature_code":"PPL",
    "gn:name":"Binoloh",
    "gn:population":0,
    "gn:timezone":"Asia/Jakarta",
    "iso:country":"ID",
    "name:ind_x_preferred":[
        "Binoloh"
    ],
    "wof:name":"Binoloh",
    "wof:placetype":"locality"
},
  "geometry": {"coordinates":[112.9378,-6.9101],"type":"Point"}
}