{
  "type": "Feature",
  "properties": {
    "gn:admin1_code":"26",
    "gn:asciiname":"Pasar Empat Dalam",
    "gn:country_code":"ID",
    "gn:dem":11,
    "gn:feature_class":"P",
    "gn:feature_code":"PPL",
    "gn:name":"Pasar Empat Dalam",
    "gn:population":0,
    "gn:timezone":"Asia/Jakarta",
    "iso:country":"ID",
    "name:ind_x_preferred":[
        "Pasar Empat Dalam"
    ],
    "name:und_x_variant":[
        "Pasar IV Dalam"
    ],
    "wof:lang_x_official":[
        "ind"
    ],
    "wof:lang_x_spoken":[
        "ind",
        "eng"
    ],
    "wof:name":"Pasar Empat Dalam",
    "wof:placetype":"locality"
},
  "geometry": {"coordinates":[99.21939999999999,3.3914],"type":"Point"}
}