{
  "type": "Feature",
  "properties": {
    "gn:admin1_code":"30.0",
    "gn:asciiname":"Panatasan",
    "gn:country_code":"ID",
    "gn:dem":26,
    "gn:feature_class":"P",
    "gn:feature_code":"PPL",
    "gn:name":"Panatasan",
    "gn:population":0,
    "gn:timezone":"Asia/Jakarta",
    "iso:country":"ID",
    "name:ind_x_preferred":[
        "Panatasan"
    ],
    "wof:name":"Panatasan",
    "wof:placetype":"locality"
},
  "geometry": {"coordinates":[108.5715,-7.3708],"type":"Point"}
}