{
  "type": "Feature",
  "properties": {
    "gn:admin1_code":"18",
    "gn:asciiname":"Gurung",
    "gn:country_code":"ID",
    "gn:dem":1040,
    "gn:feature_class":"P",
    "gn:feature_code":"PPL",
    "gn:name":"Gurung",
    "gn:population":0,
    "gn:timezone":"Asia/Makassar",
    "iso:country":"ID",
    "name:ind_x_preferred":[
        "Gurung"
    ],
    "wof:name":"Gurung",
    "wof:placetype":"locality"
},
  "geometry": {"coordinates":[120.4006,-8.5985],"type":"Point"}
}