{
  "type": "Feature",
  "properties": {
    "gn:admin1_code":"38",
    "gn:asciiname":"Jawijawi",
    "gn:country_code":"ID",
    "gn:dem":426,
    "gn:feature_class":"P",
    "gn:feature_code":"PPL",
    "gn:name":"Jawijawi",
    "gn:population":0,
    "gn:timezone":"Asia/Makassar",
    "iso:country":"ID",
    "name:ind_x_preferred":[
        "Jawijawi"
    ],
    "wof:name":"Jawijawi",
    "wof:placetype":"locality"
},
  "geometry": {"coordinates":[120.139,-5.3321],"type":"Point"}
}