{
  "type": "Feature",
  "properties": {
    "gn:admin1_code":"30.0",
    "gn:asciiname":"Cikenod",
    "gn:country_code":"ID",
    "gn:dem":122,
    "gn:feature_class":"P",
    "gn:feature_code":"PPL",
    "gn:name":"Cikenod",
    "gn:population":0,
    "gn:timezone":"Asia/Jakarta",
    "iso:country":"ID",
    "name:ind_x_preferred":[
        "Cikenod"
    ],
    "name:und_x_variant":[
        "Tjikenoet"
    ],
    "wof:name":"Cikenod",
    "wof:placetype":"locality"
},
  "geometry": {"coordinates":[108.6036,-7.0284],"type":"Point"}
}