{
  "type": "Feature",
  "properties": {
    "gn:admin1_code":"30",
    "gn:asciiname":"Kebonjeruk",
    "gn:country_code":"ID",
    "gn:dem":341,
    "gn:feature_class":"P",
    "gn:feature_code":"PPL",
    "gn:name":"Kebonjeruk",
    "gn:population":0,
    "gn:timezone":"Asia/Jakarta",
    "iso:country":"ID",
    "name:ind_x_preferred":[
        "Kebonjeruk"
    ],
    "wof:name":"Kebonjeruk",
    "wof:placetype":"locality"
},
  "geometry": {"coordinates":[106.77167,-6.94667],"type":"Point"}
}