{
  "type": "Feature",
  "properties": {
    "gn:admin1_code":"18.0",
    "gn:asciiname":"Napoq",
    "gn:country_code":"ID",
    "gn:dem":16,
    "gn:feature_class":"P",
    "gn:feature_code":"PPL",
    "gn:name":"Napoq",
    "gn:population":0,
    "gn:timezone":"Asia/Makassar",
    "iso:country":"ID",
    "name:ind_x_preferred":[
        "Napoq"
    ],
    "wof:name":"Napoq",
    "wof:placetype":"locality"
},
  "geometry": {"coordinates":[123.8342,-8.2015],"type":"Point"}
}