{
  "type": "Feature",
  "properties": {
    "gn:admin1_code":"37",
    "gn:asciiname":"Tanjungtayas",
    "gn:country_code":"ID",
    "gn:dem":25,
    "gn:feature_class":"P",
    "gn:feature_code":"PPL",
    "gn:name":"Tanjungtayas",
    "gn:population":0,
    "gn:timezone":"Asia/Jakarta",
    "iso:country":"ID",
    "name:ind_x_preferred":[
        "Tanjungtayas"
    ],
    "wof:name":"Tanjungtayas",
    "wof:placetype":"locality"
},
  "geometry": {"coordinates":[102.2771,0.0238],"type":"Point"}
}