{
  "type": "Feature",
  "properties": {
    "gn:admin1_code":"7.0",
    "gn:asciiname":"Jurip",
    "gn:country_code":"ID",
    "gn:dem":367,
    "gn:feature_class":"P",
    "gn:feature_code":"PPL",
    "gn:name":"Jurip",
    "gn:population":0,
    "gn:timezone":"Asia/Jakarta",
    "iso:country":"ID",
    "wof:name":"Jurip",
    "wof:placetype":"locality"
},
  "geometry": {"coordinates":[110.23278000000001,-7.47111],"type":"Point"}
}