{
  "type": "Feature",
  "properties": {
    "gn:admin1_code":"8.0",
    "gn:asciiname":"Gaber",
    "gn:country_code":"ID",
    "gn:dem":210,
    "gn:feature_class":"P",
    "gn:feature_code":"PPL",
    "gn:name":"Gaber",
    "gn:population":0,
    "gn:timezone":"Asia/Jakarta",
    "iso:country":"ID",
    "name:bos_x_preferred":[
        "Gaber"
    ],
    "name:bul_x_preferred":[
        "\u0413\u0430\u0431\u0435\u0440"
    ],
    "name:ceb_x_preferred":[
        "Gaber"
    ],
    "name:deu_x_preferred":[
        "Gaber"
    ],
    "name:fra_x_preferred":[
        "Gaber"
    ],
    "name:ind_x_preferred":[
        "Gaber"
    ],
    "name:ron_x_preferred":[
        "Gaber"
    ],
    "name:rus_x_preferred":[
        "\u0413\u0430\u0431\u0435\u0440"
    ],
    "name:slv_x_preferred":[
        "Gaber"
    ],
    "name:swe_x_preferred":[
        "Gaber"
    ],
    "wof:name":"Gaber",
    "wof:placetype":"locality"
},
  "geometry": {"coordinates":[113.7167,-6.9362],"type":"Point"}
}