{
  "type": "Feature",
  "properties": {
    "gn:admin1_code":"26",
    "gn:asciiname":"Lumban Sitogu Dua",
    "gn:country_code":"ID",
    "gn:dem":1332,
    "gn:feature_class":"P",
    "gn:feature_code":"PPL",
    "gn:name":"Lumban Sitogu Dua",
    "gn:population":0,
    "gn:timezone":"Asia/Jakarta",
    "iso:country":"ID",
    "name:ind_x_preferred":[
        "Lumban Sitogu Dua"
    ],
    "name:und_x_variant":[
        "Lumban Sitogu 2"
    ],
    "wof:lang_x_official":[
        "ind"
    ],
    "wof:lang_x_spoken":[
        "ind",
        "eng"
    ],
    "wof:name":"Lumban Sitogu Dua",
    "wof:placetype":"locality"
},
  "geometry": {"coordinates":[98.9807,2.2324],"type":"Point"}
}