{
  "type": "Feature",
  "properties": {
    "gn:admin1_code":"7.0",
    "gn:asciiname":"Kedungbanteng Lor",
    "gn:country_code":"ID",
    "gn:dem":13,
    "gn:feature_class":"P",
    "gn:feature_code":"PPL",
    "gn:name":"Kedungbanteng Lor",
    "gn:population":0,
    "gn:timezone":"Asia/Jakarta",
    "iso:country":"ID",
    "name:ind_x_preferred":[
        "Kedungbanteng Lor"
    ],
    "wof:name":"Kedungbanteng Lor",
    "wof:placetype":"locality"
},
  "geometry": {"coordinates":[109.05028,-7.62417],"type":"Point"}
}