{
  "type": "Feature",
  "properties": {
    "gn:admin1_code":"7.0",
    "gn:asciiname":"Diwek",
    "gn:country_code":"ID",
    "gn:dem":391,
    "gn:feature_class":"P",
    "gn:feature_code":"PPL",
    "gn:name":"Diwek",
    "gn:population":0,
    "gn:timezone":"Asia/Jakarta",
    "iso:country":"ID",
    "name:ind_x_preferred":[
        "Diwek"
    ],
    "wof:name":"Diwek",
    "wof:placetype":"locality"
},
  "geometry": {"coordinates":[109.78583,-7.40444],"type":"Point"}
}