{
  "type": "Feature",
  "properties": {
    "gn:admin1_code":"18.0",
    "gn:asciiname":"Welaghunga",
    "gn:country_code":"ID",
    "gn:dem":220,
    "gn:feature_class":"P",
    "gn:feature_code":"PPL",
    "gn:name":"Welaghunga",
    "gn:population":0,
    "gn:timezone":"Asia/Makassar",
    "iso:country":"ID",
    "name:ind_x_preferred":[
        "Welaghunga"
    ],
    "wof:name":"Welaghunga",
    "wof:placetype":"locality"
},
  "geometry": {"coordinates":[119.42059999999999,-9.4421],"type":"Point"}
}