{
  "type": "Feature",
  "properties": {
    "gn:admin1_code":"30",
    "gn:asciiname":"Puncakraya Satu",
    "gn:cc2":"ID",
    "gn:country_code":"ID",
    "gn:dem":1453,
    "gn:feature_class":"P",
    "gn:feature_code":"PPL",
    "gn:name":"Puncakraya Satu",
    "gn:population":0,
    "gn:timezone":"Asia/Jakarta",
    "iso:country":"ID",
    "name:und_x_variant":[
        "Puncakmara Satu",
        "Puntjakmara 1",
        "Puncakraya Satu"
    ],
    "wof:lang_x_official":[
        "ind"
    ],
    "wof:lang_x_spoken":[
        "ind",
        "eng"
    ],
    "wof:name":"Puncakraya Satu",
    "wof:placetype":"locality"
},
  "geometry": {"coordinates":[107.54971999999999,-7.20889],"type":"Point"}
}