{
  "type": "Feature",
  "properties": {
    "gn:admin1_code":"30.0",
    "gn:asciiname":"Karamat",
    "gn:country_code":"ID",
    "gn:dem":511,
    "gn:feature_class":"P",
    "gn:feature_code":"PPL",
    "gn:name":"Karamat",
    "gn:population":0,
    "gn:timezone":"Asia/Jakarta",
    "iso:country":"ID",
    "name:ara_x_preferred":[
        "\u0643\u0631\u0627\u0645\u0627\u062a"
    ],
    "name:aze_x_preferred":[
        "K\u0259ram\u0259t"
    ],
    "name:ind_x_preferred":[
        "Karamat"
    ],
    "name:rus_x_preferred":[
        "\u041a\u0430\u0440\u0430\u043c\u0430\u0442"
    ],
    "name:tur_x_preferred":[
        "Keramet"
    ],
    "name:urd_x_preferred":[
        "\u06a9\u0631\u0627\u0645\u062a"
    ],
    "name:uzb_x_preferred":[
        "Karomat"
    ],
    "wof:lang_x_official":[
        "ind"
    ],
    "wof:lang_x_spoken":[
        "ind",
        "eng"
    ],
    "wof:name":"Karamat",
    "wof:placetype":"locality"
},
  "geometry": {"coordinates":[107.11239999999999,-7.1913],"type":"Point"}
}