{
  "type": "Feature",
  "properties": {
    "gn:admin1_code":"30.0",
    "gn:asciiname":"Karamat",
    "gn:country_code":"ID",
    "gn:dem":511,
    "gn:feature_class":"P",
    "gn:feature_code":"PPL",
    "gn:name":"Karamat",
    "gn:population":0,
    "gn:timezone":"Asia/Jakarta",
    "iso:country":"ID",
    "name:ind_x_preferred":[
        "Karamat"
    ],
    "wof:name":"Karamat",
    "wof:placetype":"locality"
},
  "geometry": {"coordinates":[107.11239999999999,-7.1913],"type":"Point"}
}