{
  "type": "Feature",
  "properties": {
    "gn:admin1_code":"30.0",
    "gn:asciiname":"Pasanggrahan",
    "gn:country_code":"ID",
    "gn:dem":326,
    "gn:feature_class":"P",
    "gn:feature_code":"PPLA4",
    "gn:name":"Pasanggrahan",
    "gn:population":0,
    "gn:timezone":"Asia/Jakarta",
    "iso:country":"ID",
    "name:ind_x_preferred":[
        "Pasanggrahan"
    ],
    "wof:lang_x_official":[
        "ind"
    ],
    "wof:lang_x_spoken":[
        "ind",
        "eng"
    ],
    "wof:name":"Pasanggrahan",
    "wof:placetype":"locality"
},
  "geometry": {"coordinates":[108.20399999999999,-7.3872],"type":"Point"}
}