{
  "type": "Feature",
  "properties": {
    "gn:admin1_code":"8.0",
    "gn:asciiname":"Sukomulio",
    "gn:cc2":"ID",
    "gn:country_code":"ID",
    "gn:dem":5,
    "gn:feature_class":"P",
    "gn:feature_code":"PPL",
    "gn:name":"Sukomulio",
    "gn:population":0,
    "gn:timezone":"Asia/Jakarta",
    "iso:country":"ID",
    "name:und_x_variant":[
        "Sukomuljo",
        "Sukomulio"
    ],
    "wof:lang_x_official":[
        "ind"
    ],
    "wof:lang_x_spoken":[
        "ind",
        "eng"
    ],
    "wof:name":"Sukomulio",
    "wof:placetype":"locality"
},
  "geometry": {"coordinates":[112.61528,-7.1325],"type":"Point"}
}