{
  "type": "Feature",
  "properties": {
    "gn:admin1_code":"2",
    "gn:asciiname":"Banjar Abiancalak",
    "gn:country_code":"ID",
    "gn:dem":275,
    "gn:feature_class":"P",
    "gn:feature_code":"PPL",
    "gn:name":"Banjar Abiancalak",
    "gn:population":0,
    "gn:timezone":"Asia/Makassar",
    "iso:country":"ID",
    "name:ind_x_preferred":[
        "Banjar Abiancalak"
    ],
    "wof:name":"Banjar Abiancalak",
    "wof:placetype":"locality"
},
  "geometry": {"coordinates":[115.3257,-8.4958],"type":"Point"}
}