{
  "type": "Feature",
  "properties": {
    "gn:admin1_code":"38.0",
    "gn:asciiname":"Dare",
    "gn:country_code":"ID",
    "gn:dem":45,
    "gn:feature_class":"P",
    "gn:feature_code":"PPL",
    "gn:name":"Dare",
    "gn:population":0,
    "gn:timezone":"Asia/Makassar",
    "iso:country":"ID",
    "name:ceb_x_preferred":[
        "Dare"
    ],
    "name:deu_x_preferred":[
        "Dare"
    ],
    "name:fra_x_preferred":[
        "Dare"
    ],
    "name:ind_x_preferred":[
        "Dare"
    ],
    "name:ita_x_preferred":[
        "Dare"
    ],
    "name:nld_x_preferred":[
        "Dare"
    ],
    "name:pol_x_preferred":[
        "Dare"
    ],
    "name:por_x_preferred":[
        "Dare"
    ],
    "name:rus_x_preferred":[
        "\u0414\u044d\u0439\u0440"
    ],
    "name:spa_x_preferred":[
        "Dare"
    ],
    "name:swe_x_preferred":[
        "Dare"
    ],
    "wof:lang_x_official":[
        "ind"
    ],
    "wof:lang_x_spoken":[
        "ind",
        "eng"
    ],
    "wof:name":"Dare",
    "wof:placetype":"locality"
},
  "geometry": {"coordinates":[120.2555,-3.2782],"type":"Point"}
}