{
  "type": "Feature",
  "properties": {
    "gn:admin1_code":"18",
    "gn:asciiname":"Woloara",
    "gn:country_code":"ID",
    "gn:dem":661,
    "gn:feature_class":"P",
    "gn:feature_code":"PPL",
    "gn:name":"Woloara",
    "gn:population":0,
    "gn:timezone":"Asia/Makassar",
    "iso:country":"ID",
    "name:ind_x_preferred":[
        "Woloara"
    ],
    "wof:name":"Woloara",
    "wof:placetype":"locality"
},
  "geometry": {"coordinates":[121.8556,-8.7565],"type":"Point"}
}