{
  "type": "Feature",
  "properties": {
    "gn:admin1_code":"8.0",
    "gn:asciiname":"Blubuk",
    "gn:country_code":"ID",
    "gn:dem":1129,
    "gn:feature_class":"P",
    "gn:feature_code":"PPL",
    "gn:name":"Blubuk",
    "gn:population":0,
    "gn:timezone":"Asia/Jakarta",
    "iso:country":"ID",
    "name:ind_x_preferred":[
        "Blubuk"
    ],
    "name:und_x_variant":[
        "Bloeboek"
    ],
    "wof:lang_x_official":[
        "ind"
    ],
    "wof:lang_x_spoken":[
        "ind",
        "eng"
    ],
    "wof:name":"Blubuk",
    "wof:placetype":"locality"
},
  "geometry": {"coordinates":[112.85509999999999,-8.1466],"type":"Point"}
}