{
  "type": "Feature",
  "properties": {
    "gn:admin1_code":"8.0",
    "gn:asciiname":"Gebyaran",
    "gn:country_code":"ID",
    "gn:dem":90,
    "gn:feature_class":"P",
    "gn:feature_code":"PPL",
    "gn:name":"Gebyaran",
    "gn:population":0,
    "gn:timezone":"Asia/Jakarta",
    "iso:country":"ID",
    "name:ind_x_preferred":[
        "Gebyaran"
    ],
    "wof:name":"Gebyaran",
    "wof:placetype":"locality"
},
  "geometry": {"coordinates":[112.15009999999999,-7.7299],"type":"Point"}
}