{
  "type": "Feature",
  "properties": {
    "gn:admin1_code":"30.0",
    "gn:asciiname":"Muara",
    "gn:country_code":"ID",
    "gn:dem":5,
    "gn:feature_class":"P",
    "gn:feature_code":"PPL",
    "gn:name":"Muara",
    "gn:population":0,
    "gn:timezone":"Asia/Jakarta",
    "iso:country":"ID",
    "name:ceb_x_preferred":[
        "Muara"
    ],
    "name:ind_x_preferred":[
        "Muara"
    ],
    "name:nld_x_preferred":[
        "Muara"
    ],
    "name:swe_x_preferred":[
        "Muara"
    ],
    "name:und_x_variant":[
        "Muara 1",
        "Moeara",
        "Muara Satu"
    ],
    "wof:name":"Muara",
    "wof:placetype":"locality"
},
  "geometry": {"coordinates":[107.06389,-6.10833],"type":"Point"}
}