{
  "type": "Feature",
  "properties": {
    "gn:admin1_code":"17",
    "gn:asciiname":"Bage",
    "gn:country_code":"ID",
    "gn:dem":302,
    "gn:feature_class":"P",
    "gn:feature_code":"PPL",
    "gn:name":"Bage",
    "gn:population":0,
    "gn:timezone":"Asia/Makassar",
    "iso:country":"ID",
    "name:ceb_x_preferred":[
        "Bage"
    ],
    "name:ind_x_preferred":[
        "Bage"
    ],
    "name:nld_x_preferred":[
        "Bage"
    ],
    "name:swe_x_preferred":[
        "Bage"
    ],
    "wof:lang_x_official":[
        "ind"
    ],
    "wof:lang_x_spoken":[
        "ind",
        "eng"
    ],
    "wof:name":"Bage",
    "wof:placetype":"locality"
},
  "geometry": {"coordinates":[116.32850000000001,-8.6707],"type":"Point"}
}