{
  "type": "Feature",
  "properties": {
    "gn:admin1_code":"26",
    "gn:asciiname":"Sukamulya",
    "gn:country_code":"ID",
    "gn:dem":58,
    "gn:feature_class":"P",
    "gn:feature_code":"PPL",
    "gn:name":"Sukamulya",
    "gn:population":0,
    "gn:timezone":"Asia/Jakarta",
    "iso:country":"ID",
    "name:ind_x_preferred":[
        "Sukamulya"
    ],
    "name:jav_x_preferred":[
        "Sukamulya"
    ],
    "name:msa_x_preferred":[
        "Sukamulya"
    ],
    "wof:lang_x_official":[
        "ind"
    ],
    "wof:lang_x_spoken":[
        "ind",
        "eng"
    ],
    "wof:name":"Sukamulya",
    "wof:placetype":"locality"
},
  "geometry": {"coordinates":[99.0192,3.3404],"type":"Point"}
}