{
  "type": "Feature",
  "properties": {
    "gn:admin1_code":"1",
    "gn:asciiname":"Ulee Gle",
    "gn:country_code":"ID",
    "gn:dem":474,
    "gn:feature_class":"P",
    "gn:feature_code":"PPL",
    "gn:name":"Ulee Gle",
    "gn:population":0,
    "gn:timezone":"Asia/Jakarta",
    "iso:country":"ID",
    "name:ind_x_preferred":[
        "Ulee Gle"
    ],
    "name:und_x_variant":[
        "Baleoeleegle"
    ],
    "wof:name":"Ulee Gle",
    "wof:placetype":"locality"
},
  "geometry": {"coordinates":[95.92570000000001,5.0198],"type":"Point"}
}