{
  "type": "Feature",
  "properties": {
    "gn:admin1_code":"8.0",
    "gn:asciiname":"Bakalan Dua",
    "gn:country_code":"ID",
    "gn:dem":425,
    "gn:feature_class":"P",
    "gn:feature_code":"PPL",
    "gn:name":"Bakalan Dua",
    "gn:population":0,
    "gn:timezone":"Asia/Jakarta",
    "iso:country":"ID",
    "name:ind_x_preferred":[
        "Bakalan Dua"
    ],
    "wof:name":"Bakalan Dua",
    "wof:placetype":"locality"
},
  "geometry": {"coordinates":[112.6555,-8.109],"type":"Point"}
}