{
  "type": "Feature",
  "properties": {
    "gn:admin1_code":"8",
    "gn:asciiname":"Klubuk",
    "gn:country_code":"ID",
    "gn:dem":72,
    "gn:feature_class":"P",
    "gn:feature_code":"PPL",
    "gn:name":"Klubuk",
    "gn:population":0,
    "gn:timezone":"Asia/Jakarta",
    "iso:country":"ID",
    "name:ind_x_preferred":[
        "Klubuk"
    ],
    "wof:name":"Klubuk",
    "wof:placetype":"locality"
},
  "geometry": {"coordinates":[111.6494,-7.5234],"type":"Point"}
}