{
  "type": "Feature",
  "properties": {
    "gn:admin1_code":"26",
    "gn:asciiname":"Kampung Batu Enam",
    "gn:country_code":"ID",
    "gn:dem":68,
    "gn:feature_class":"P",
    "gn:feature_code":"PPL",
    "gn:name":"Kampung Batu Enam",
    "gn:population":0,
    "gn:timezone":"Asia/Jakarta",
    "iso:country":"ID",
    "name:ind_x_preferred":[
        "Kampung Batu Enam"
    ],
    "name:und_x_variant":[
        "Kampung Batu 6"
    ],
    "wof:lang_x_official":[
        "ind"
    ],
    "wof:lang_x_spoken":[
        "ind",
        "eng"
    ],
    "wof:name":"Kampung Batu Enam",
    "wof:placetype":"locality"
},
  "geometry": {"coordinates":[99.2038,3.226],"type":"Point"}
}