{
  "type": "Feature",
  "properties": {
    "gn:admin1_code":"26.0",
    "gn:asciiname":"Pulau",
    "gn:country_code":"ID",
    "gn:dem":47,
    "gn:feature_class":"P",
    "gn:feature_code":"PPL",
    "gn:name":"Pulau",
    "gn:population":0,
    "gn:timezone":"Asia/Jakarta",
    "iso:country":"ID",
    "name:ind_x_preferred":[
        "Pulau"
    ],
    "name:und_x_variant":[
        "Poelau"
    ],
    "wof:name":"Pulau",
    "wof:placetype":"locality"
},
  "geometry": {"coordinates":[98.3164,3.5961],"type":"Point"}
}