{
  "type": "Feature",
  "properties": {
    "gn:admin1_code":"8",
    "gn:asciiname":"Batukodung",
    "gn:country_code":"ID",
    "gn:dem":165,
    "gn:feature_class":"P",
    "gn:feature_code":"PPL",
    "gn:name":"Batukodung",
    "gn:population":0,
    "gn:timezone":"Asia/Jakarta",
    "iso:country":"ID",
    "name:ind_x_preferred":[
        "Batukodung"
    ],
    "wof:name":"Batukodung",
    "wof:placetype":"locality"
},
  "geometry": {"coordinates":[114.2064,-7.8273],"type":"Point"}
}