{
  "type": "Feature",
  "properties": {
    "gn:admin1_code":"38.0",
    "gn:asciiname":"Ciro",
    "gn:country_code":"ID",
    "gn:dem":121,
    "gn:feature_class":"P",
    "gn:feature_code":"PPL",
    "gn:name":"Ciro",
    "gn:population":0,
    "gn:timezone":"Asia/Makassar",
    "iso:country":"ID",
    "name:ind_x_preferred":[
        "Ciro"
    ],
    "wof:name":"Ciro",
    "wof:placetype":"locality"
},
  "geometry": {"coordinates":[120.18210000000001,-4.6825],"type":"Point"}
}