{
  "type": "Feature",
  "properties": {
    "gn:admin1_code":"26",
    "gn:asciiname":"Paya Bakung Tiga",
    "gn:country_code":"ID",
    "gn:dem":19,
    "gn:feature_class":"P",
    "gn:feature_code":"PPL",
    "gn:name":"Paya Bakung Tiga",
    "gn:population":0,
    "gn:timezone":"Asia/Jakarta",
    "iso:country":"ID",
    "name:ind_x_preferred":[
        "Paya Bakung Tiga"
    ],
    "name:und_x_variant":[
        "Payabakung 3"
    ],
    "wof:name":"Paya Bakung Tiga",
    "wof:placetype":"locality"
},
  "geometry": {"coordinates":[98.5553,3.6296],"type":"Point"}
}