{
  "type": "Feature",
  "properties": {
    "gn:admin1_code":"30",
    "gn:asciiname":"Cigombong",
    "gn:country_code":"ID",
    "gn:dem":908,
    "gn:feature_class":"P",
    "gn:feature_code":"PPL",
    "gn:name":"Cigombong",
    "gn:population":0,
    "gn:timezone":"Asia/Jakarta",
    "iso:country":"ID",
    "name:ind_x_preferred":[
        "Cigombong"
    ],
    "name:und_x_variant":[
        "Tjigombong"
    ],
    "wof:lang_x_official":[
        "ind"
    ],
    "wof:lang_x_spoken":[
        "ind",
        "eng"
    ],
    "wof:name":"Cigombong",
    "wof:placetype":"locality"
},
  "geometry": {"coordinates":[107.4465,-7.0138],"type":"Point"}
}