{
  "type": "Feature",
  "properties": {
    "gn:admin1_code":"7.0",
    "gn:asciiname":"Depok Kidul",
    "gn:country_code":"ID",
    "gn:dem":86,
    "gn:feature_class":"P",
    "gn:feature_code":"PPL",
    "gn:name":"Depok Kidul",
    "gn:population":0,
    "gn:timezone":"Asia/Jakarta",
    "iso:country":"ID",
    "name:ind_x_preferred":[
        "Depok Kidul"
    ],
    "wof:name":"Depok Kidul",
    "wof:placetype":"locality"
},
  "geometry": {"coordinates":[109.32028,-7.39639],"type":"Point"}
}