{
  "type": "Feature",
  "properties": {
    "gn:admin1_code":"17.0",
    "gn:asciiname":"Rungis",
    "gn:country_code":"ID",
    "gn:dem":750,
    "gn:feature_class":"P",
    "gn:feature_code":"PPL",
    "gn:name":"Rungis",
    "gn:population":0,
    "gn:timezone":"Asia/Makassar",
    "iso:country":"ID",
    "name:ind_x_preferred":[
        "Rungis"
    ],
    "wof:name":"Rungis",
    "wof:placetype":"locality"
},
  "geometry": {"coordinates":[117.00757,-8.65693],"type":"Point"}
}