{
  "type": "Feature",
  "properties": {
    "gn:admin1_code":"17.0",
    "gn:asciiname":"Rungis",
    "gn:country_code":"ID",
    "gn:dem":750,
    "gn:feature_class":"P",
    "gn:feature_code":"PPL",
    "gn:name":"Rungis",
    "gn:population":0,
    "gn:timezone":"Asia/Makassar",
    "iso:country":"ID",
    "name:cat_x_preferred":[
        "Rungis"
    ],
    "name:ceb_x_preferred":[
        "Rungis"
    ],
    "name:ces_x_preferred":[
        "Rungis"
    ],
    "name:deu_x_preferred":[
        "Rungis"
    ],
    "name:epo_x_preferred":[
        "Rungis"
    ],
    "name:eus_x_preferred":[
        "Rungis"
    ],
    "name:fra_x_preferred":[
        "Rungis"
    ],
    "name:hun_x_preferred":[
        "Rungis"
    ],
    "name:ind_x_preferred":[
        "Rungis"
    ],
    "name:ita_x_preferred":[
        "Rungis"
    ],
    "name:jpn_x_preferred":[
        "\u30e9\u30f3\u30b8\u30b9"
    ],
    "name:kaz_x_preferred":[
        "\u0420\u0435\u043d\u0436\u0438"
    ],
    "name:msa_x_preferred":[
        "Rungis"
    ],
    "name:nld_x_preferred":[
        "Rungis"
    ],
    "name:nor_x_preferred":[
        "Rungis"
    ],
    "name:oci_x_preferred":[
        "Rungis"
    ],
    "name:pms_x_preferred":[
        "Rungis"
    ],
    "name:pol_x_preferred":[
        "Rungis"
    ],
    "name:por_x_preferred":[
        "Rungis"
    ],
    "name:ron_x_preferred":[
        "Rungis"
    ],
    "name:slk_x_preferred":[
        "Rungis"
    ],
    "name:spa_x_preferred":[
        "Rungis"
    ],
    "name:swe_x_preferred":[
        "Rungis"
    ],
    "name:ukr_x_preferred":[
        "\u0420\u0435\u043d\u0436\u0438\u0441"
    ],
    "name:vie_x_preferred":[
        "Rungis"
    ],
    "name:vol_x_preferred":[
        "Rungis"
    ],
    "name:war_x_preferred":[
        "Rungis"
    ],
    "name:zho_x_preferred":[
        "\u676d\u5409\u65af"
    ],
    "wof:lang_x_official":[
        "ind"
    ],
    "wof:lang_x_spoken":[
        "ind",
        "eng"
    ],
    "wof:name":"Rungis",
    "wof:placetype":"locality"
},
  "geometry": {"coordinates":[117.00757,-8.65693],"type":"Point"}
}