{
  "type": "Feature",
  "properties": {
    "gn:admin1_code":"30.0",
    "gn:asciiname":"Cipada Kaler",
    "gn:country_code":"ID",
    "gn:dem":16,
    "gn:feature_class":"P",
    "gn:feature_code":"PPL",
    "gn:name":"Cipada Kaler",
    "gn:population":0,
    "gn:timezone":"Asia/Jakarta",
    "iso:country":"ID",
    "name:ind_x_preferred":[
        "Cipada Kaler"
    ],
    "wof:name":"Cipada Kaler",
    "wof:placetype":"locality"
},
  "geometry": {"coordinates":[106.9098,-7.3898],"type":"Point"}
}