{
  "type": "Feature",
  "properties": {
    "gn:admin1_code":"30",
    "gn:asciiname":"Sarimukti",
    "gn:country_code":"ID",
    "gn:dem":10,
    "gn:feature_class":"P",
    "gn:feature_code":"PPL",
    "gn:name":"Sarimukti",
    "gn:population":0,
    "gn:timezone":"Asia/Jakarta",
    "iso:country":"ID",
    "name:ind_x_preferred":[
        "Sarimukti"
    ],
    "wof:name":"Sarimukti",
    "wof:placetype":"locality"
},
  "geometry": {"coordinates":[107.81610999999999,-6.29861],"type":"Point"}
}