{
  "type": "Feature",
  "properties": {
    "gn:admin1_code":"18.0",
    "gn:asciiname":"Ulaga",
    "gn:country_code":"ID",
    "gn:dem":21,
    "gn:feature_class":"P",
    "gn:feature_code":"PPL",
    "gn:name":"Ulaga",
    "gn:population":0,
    "gn:timezone":"Asia/Makassar",
    "iso:country":"ID",
    "name:ind_x_preferred":[
        "Ulaga"
    ],
    "wof:name":"Ulaga",
    "wof:placetype":"locality"
},
  "geometry": {"coordinates":[124.6404,-8.4007],"type":"Point"}
}