{
  "type": "Feature",
  "properties": {
    "gn:admin1_code":"1",
    "gn:asciiname":"Pondok Kalirejo",
    "gn:country_code":"ID",
    "gn:dem":24,
    "gn:feature_class":"P",
    "gn:feature_code":"PPL",
    "gn:name":"Pondok Kalirejo",
    "gn:population":0,
    "gn:timezone":"Asia/Jakarta",
    "iso:country":"ID",
    "name:ind_x_preferred":[
        "Pondok Kalirejo"
    ],
    "wof:name":"Pondok Kalirejo",
    "wof:placetype":"locality"
},
  "geometry": {"coordinates":[99.5688,2.9802],"type":"Point"}
}