{
  "type": "Feature",
  "properties": {
    "gn:admin1_code":"32.0",
    "gn:asciiname":"Talang Karet",
    "gn:country_code":"ID",
    "gn:dem":123,
    "gn:feature_class":"P",
    "gn:feature_code":"PPL",
    "gn:name":"Talang Karet",
    "gn:population":0,
    "gn:timezone":"Asia/Jakarta",
    "iso:country":"ID",
    "name:ind_x_preferred":[
        "Talang Karet"
    ],
    "name:und_x_variant":[
        "Talangkarel"
    ],
    "wof:name":"Talang Karet",
    "wof:placetype":"locality"
},
  "geometry": {"coordinates":[104.23220999999999,-4.54785],"type":"Point"}
}