{
  "type": "Feature",
  "properties": {
    "gn:admin1_code":"7",
    "gn:asciiname":"Gantiwarno",
    "gn:country_code":"ID",
    "gn:dem":297,
    "gn:feature_class":"P",
    "gn:feature_code":"PPL",
    "gn:name":"Gantiwarno",
    "gn:population":0,
    "gn:timezone":"Asia/Jakarta",
    "iso:country":"ID",
    "name:ind_x_preferred":[
        "Gantiwarno"
    ],
    "wof:name":"Gantiwarno",
    "wof:placetype":"locality"
},
  "geometry": {"coordinates":[111.00722,-7.62889],"type":"Point"}
}