{
  "type": "Feature",
  "properties": {
    "gn:admin1_code":"7.0",
    "gn:asciiname":"Sijeruk",
    "gn:country_code":"ID",
    "gn:dem":646,
    "gn:feature_class":"P",
    "gn:feature_code":"PPL",
    "gn:name":"Sijeruk",
    "gn:population":0,
    "gn:timezone":"Asia/Jakarta",
    "iso:country":"ID",
    "name:ind_x_preferred":[
        "Sijeruk"
    ],
    "name:jav_x_preferred":[
        "Sijeruk"
    ],
    "name:nld_x_preferred":[
        "Sijeruk"
    ],
    "name:sun_x_preferred":[
        "Sijeruk"
    ],
    "wof:lang_x_official":[
        "ind"
    ],
    "wof:lang_x_spoken":[
        "ind",
        "eng"
    ],
    "wof:name":"Sijeruk",
    "wof:placetype":"locality"
},
  "geometry": {"coordinates":[109.85472,-7.38472],"type":"Point"}
}