{
  "type": "Feature",
  "properties": {
    "gn:admin1_code":"8",
    "gn:asciiname":"Darmorejo Kulon",
    "gn:country_code":"ID",
    "gn:dem":116,
    "gn:feature_class":"P",
    "gn:feature_code":"PPL",
    "gn:name":"Darmorejo Kulon",
    "gn:population":0,
    "gn:timezone":"Asia/Jakarta",
    "iso:country":"ID",
    "name:ind_x_preferred":[
        "Darmorejo Kulon"
    ],
    "wof:lang_x_official":[
        "ind"
    ],
    "wof:lang_x_spoken":[
        "ind",
        "eng"
    ],
    "wof:name":"Darmorejo Kulon",
    "wof:placetype":"locality"
},
  "geometry": {"coordinates":[114.25069999999999,-8.3423],"type":"Point"}
}