{
  "type": "Feature",
  "properties": {
    "gn:admin1_code":"38",
    "gn:asciiname":"Pompengan Hilir",
    "gn:country_code":"ID",
    "gn:dem":14,
    "gn:feature_class":"P",
    "gn:feature_code":"PPL",
    "gn:name":"Pompengan Hilir",
    "gn:population":0,
    "gn:timezone":"Asia/Makassar",
    "iso:country":"ID",
    "name:ind_x_preferred":[
        "Pompengan Hilir"
    ],
    "wof:name":"Pompengan Hilir",
    "wof:placetype":"locality"
},
  "geometry": {"coordinates":[120.235,-2.8769],"type":"Point"}
}