{
  "type": "Feature",
  "properties": {
    "gn:admin1_code":"18.0",
    "gn:asciiname":"Binamotor",
    "gn:country_code":"ID",
    "gn:dem":86,
    "gn:feature_class":"P",
    "gn:feature_code":"PPL",
    "gn:name":"Binamotor",
    "gn:population":0,
    "gn:timezone":"Asia/Makassar",
    "iso:country":"ID",
    "name:ind_x_preferred":[
        "Binamotor"
    ],
    "wof:name":"Binamotor",
    "wof:placetype":"locality"
},
  "geometry": {"coordinates":[119.3467,-9.4247],"type":"Point"}
}