{
  "type": "Feature",
  "properties": {
    "gn:admin1_code":"7.0",
    "gn:asciiname":"Pundung Wetan",
    "gn:country_code":"ID",
    "gn:dem":336,
    "gn:feature_class":"P",
    "gn:feature_code":"PPL",
    "gn:name":"Pundung Wetan",
    "gn:population":0,
    "gn:timezone":"Asia/Jakarta",
    "iso:country":"ID",
    "name:ind_x_preferred":[
        "Pundung Wetan"
    ],
    "wof:name":"Pundung Wetan",
    "wof:placetype":"locality"
},
  "geometry": {"coordinates":[111.02333,-8.07278],"type":"Point"}
}