{
  "type": "Feature",
  "properties": {
    "gn:admin1_code":"1",
    "gn:asciiname":"Kilometer Empatpuluh",
    "gn:country_code":"ID",
    "gn:dem":669,
    "gn:feature_class":"P",
    "gn:feature_code":"PPL",
    "gn:name":"Kilometer Empatpuluh",
    "gn:population":0,
    "gn:timezone":"Asia/Jakarta",
    "iso:country":"ID",
    "name:ind_x_preferred":[
        "Kilometer Empatpuluh"
    ],
    "name:und_x_variant":[
        "Km. Empatpuluh"
    ],
    "wof:lang_x_official":[
        "ind"
    ],
    "wof:lang_x_spoken":[
        "ind",
        "eng"
    ],
    "wof:name":"Kilometer Empatpuluh",
    "wof:placetype":"locality"
},
  "geometry": {"coordinates":[96.7256,4.925],"type":"Point"}
}