{
  "type": "Feature",
  "properties": {
    "gn:admin1_code":"17",
    "gn:asciiname":"Tompokompoh",
    "gn:country_code":"ID",
    "gn:dem":14,
    "gn:feature_class":"P",
    "gn:feature_code":"PPL",
    "gn:name":"Tompokompoh",
    "gn:population":0,
    "gn:timezone":"Asia/Makassar",
    "iso:country":"ID",
    "name:ind_x_preferred":[
        "Tompokompoh"
    ],
    "wof:name":"Tompokompoh",
    "wof:placetype":"locality"
},
  "geometry": {"coordinates":[116.4594,-8.8694],"type":"Point"}
}