{
  "type": "Feature",
  "properties": {
    "gn:admin1_code":"32.0",
    "gn:asciiname":"Talangrakib",
    "gn:country_code":"ID",
    "gn:dem":73,
    "gn:feature_class":"P",
    "gn:feature_code":"PPL",
    "gn:name":"Talangrakib",
    "gn:population":0,
    "gn:timezone":"Asia/Jakarta",
    "iso:country":"ID",
    "name:ind_x_preferred":[
        "Talangrakib"
    ],
    "wof:name":"Talangrakib",
    "wof:placetype":"locality"
},
  "geometry": {"coordinates":[104.13120000000001,-3.7387],"type":"Point"}
}