{
  "type": "Feature",
  "properties": {
    "gn:admin1_code":"18",
    "gn:asciiname":"Leong",
    "gn:country_code":"ID",
    "gn:dem":797,
    "gn:feature_class":"P",
    "gn:feature_code":"PPL",
    "gn:name":"Leong",
    "gn:population":0,
    "gn:timezone":"Asia/Makassar",
    "iso:country":"ID",
    "name:ind_x_preferred":[
        "Leong"
    ],
    "wof:name":"Leong",
    "wof:placetype":"locality"
},
  "geometry": {"coordinates":[120.5731,-8.559],"type":"Point"}
}