{
  "type": "Feature",
  "properties": {
    "gn:admin1_code":"38.0",
    "gn:asciiname":"Rendangan",
    "gn:country_code":"ID",
    "gn:dem":60,
    "gn:feature_class":"P",
    "gn:feature_code":"PPL",
    "gn:name":"Rendangan",
    "gn:population":0,
    "gn:timezone":"Asia/Makassar",
    "iso:country":"ID",
    "name:ind_x_preferred":[
        "Rendangan"
    ],
    "wof:name":"Rendangan",
    "wof:placetype":"locality"
},
  "geometry": {"coordinates":[119.78547,-3.5563],"type":"Point"}
}