{
  "type": "Feature",
  "properties": {
    "gn:admin1_code":"30",
    "gn:asciiname":"Areng Hilir",
    "gn:country_code":"ID",
    "gn:dem":1092,
    "gn:feature_class":"P",
    "gn:feature_code":"PPL",
    "gn:name":"Areng Hilir",
    "gn:population":0,
    "gn:timezone":"Asia/Jakarta",
    "iso:country":"ID",
    "name:ind_x_preferred":[
        "Areng Hilir"
    ],
    "name:und_x_variant":[
        "Areng"
    ],
    "wof:name":"Areng Hilir",
    "wof:placetype":"locality"
},
  "geometry": {"coordinates":[107.6125,-6.84028],"type":"Point"}
}