{
  "type": "Feature",
  "properties": {
    "gn:admin1_code":"11",
    "gn:asciiname":"H. Jame",
    "gn:country_code":"ID",
    "gn:dem":33,
    "gn:feature_class":"P",
    "gn:feature_code":"PPL",
    "gn:name":"H. Jame",
    "gn:population":0,
    "gn:timezone":"Asia/Pontianak",
    "iso:country":"ID",
    "name:ind_x_preferred":[
        "H. Jame"
    ],
    "wof:name":"H. Jame",
    "wof:placetype":"locality"
},
  "geometry": {"coordinates":[109.45818,0.47001],"type":"Point"}
}