{
  "type": "Feature",
  "properties": {
    "gn:admin1_code":"30.0",
    "gn:asciiname":"Paniis",
    "gn:country_code":"ID",
    "gn:dem":655,
    "gn:feature_class":"P",
    "gn:feature_code":"PPL",
    "gn:name":"Paniis",
    "gn:population":0,
    "gn:timezone":"Asia/Jakarta",
    "iso:country":"ID",
    "name:ind_x_preferred":[
        "Paniis"
    ],
    "wof:name":"Paniis",
    "wof:placetype":"locality"
},
  "geometry": {"coordinates":[108.0527,-7.504],"type":"Point"}
}