{
  "type": "Feature",
  "properties": {
    "gn:admin1_code":"8.0",
    "gn:asciiname":"Sumberngelbet",
    "gn:country_code":"ID",
    "gn:dem":131,
    "gn:feature_class":"P",
    "gn:feature_code":"PPL",
    "gn:name":"Sumberngelbet",
    "gn:population":0,
    "gn:timezone":"Asia/Jakarta",
    "iso:country":"ID",
    "name:ind_x_preferred":[
        "Sumberngelbet"
    ],
    "wof:name":"Sumberngelbet",
    "wof:placetype":"locality"
},
  "geometry": {"coordinates":[113.70180000000001,-7.0189],"type":"Point"}
}