{
  "type": "Feature",
  "properties": {
    "gn:admin1_code":"26",
    "gn:asciiname":"Silautan",
    "gn:country_code":"ID",
    "gn:dem":1159,
    "gn:feature_class":"P",
    "gn:feature_code":"PPL",
    "gn:name":"Silautan",
    "gn:population":0,
    "gn:timezone":"Asia/Jakarta",
    "iso:country":"ID",
    "name:ind_x_preferred":[
        "Silautan"
    ],
    "wof:name":"Silautan",
    "wof:placetype":"locality"
},
  "geometry": {"coordinates":[98.43259999999999,2.6917],"type":"Point"}
}