{
  "type": "Feature",
  "properties": {
    "gn:admin1_code":"24",
    "gn:asciiname":"Padang",
    "gn:country_code":"ID",
    "gn:dem":566,
    "gn:feature_class":"P",
    "gn:feature_code":"PPL",
    "gn:name":"Padang",
    "gn:population":0,
    "gn:timezone":"Asia/Jakarta",
    "iso:country":"ID",
    "name:ind_x_preferred":[
        "Padang"
    ],
    "wof:name":"Padang",
    "wof:placetype":"locality"
},
  "geometry": {"coordinates":[100.57391,-0.25283],"type":"Point"}
}