{
  "type": "Feature",
  "properties": {
    "gn:admin1_code":"30",
    "gn:asciiname":"Sirnahurip",
    "gn:country_code":"ID",
    "gn:dem":906,
    "gn:feature_class":"P",
    "gn:feature_code":"PPL",
    "gn:name":"Sirnahurip",
    "gn:population":0,
    "gn:timezone":"Asia/Jakarta",
    "iso:country":"ID",
    "name:ind_x_preferred":[
        "Sirnahurip"
    ],
    "wof:name":"Sirnahurip",
    "wof:placetype":"locality"
},
  "geometry": {"coordinates":[107.35639,-6.98944],"type":"Point"}
}