{
  "type": "Feature",
  "properties": {
    "gn:admin1_code":"18.0",
    "gn:asciiname":"Praikaniru",
    "gn:country_code":"ID",
    "gn:dem":479,
    "gn:feature_class":"P",
    "gn:feature_code":"PPL",
    "gn:name":"Praikaniru",
    "gn:population":0,
    "gn:timezone":"Asia/Makassar",
    "iso:country":"ID",
    "name:ind_x_preferred":[
        "Praikaniru"
    ],
    "wof:name":"Praikaniru",
    "wof:placetype":"locality"
},
  "geometry": {"coordinates":[119.6448,-9.6013],"type":"Point"}
}