{
  "type": "Feature",
  "properties": {
    "gn:admin1_code":"8.0",
    "gn:asciiname":"Pandan Bara'",
    "gn:country_code":"ID",
    "gn:dem":68,
    "gn:feature_class":"P",
    "gn:feature_code":"PPL",
    "gn:name":"Pandan Bara'",
    "gn:population":0,
    "gn:timezone":"Asia/Jakarta",
    "iso:country":"ID",
    "name:ind_x_preferred":[
        "Pandan Bara'"
    ],
    "wof:name":"Pandan Bara'",
    "wof:placetype":"locality"
},
  "geometry": {"coordinates":[113.3117,-7.0772],"type":"Point"}
}