{
  "type": "Feature",
  "properties": {
    "gn:admin1_code":"5.0",
    "gn:asciiname":"Dusungenting",
    "gn:country_code":"ID",
    "gn:dem":359,
    "gn:feature_class":"P",
    "gn:feature_code":"PPL",
    "gn:name":"Dusungenting",
    "gn:population":0,
    "gn:timezone":"Asia/Jakarta",
    "iso:country":"ID",
    "name:und_x_variant":[
        "Doesoengenting",
        "Dusungenting"
    ],
    "wof:name":"Dusungenting",
    "wof:placetype":"locality"
},
  "geometry": {"coordinates":[101.7547,-1.9582],"type":"Point"}
}