{
  "type": "Feature",
  "properties": {
    "gn:admin1_code":"1",
    "gn:asciiname":"Kubu",
    "gn:country_code":"ID",
    "gn:dem":10,
    "gn:feature_class":"P",
    "gn:feature_code":"PPL",
    "gn:name":"Kubu",
    "gn:population":0,
    "gn:timezone":"Asia/Jakarta",
    "iso:country":"ID",
    "name:ceb_x_preferred":[
        "Kubu"
    ],
    "name:ind_x_preferred":[
        "Kubu"
    ],
    "name:msa_x_preferred":[
        "Kubu"
    ],
    "name:nld_x_preferred":[
        "Kubu"
    ],
    "name:rus_x_preferred":[
        "\u041a\u0443\u0431\u0443"
    ],
    "name:swe_x_preferred":[
        "Kubu"
    ],
    "name:und_x_variant":[
        "Kubuh"
    ],
    "wof:lang_x_official":[
        "ind"
    ],
    "wof:lang_x_spoken":[
        "ind",
        "eng"
    ],
    "wof:name":"Kubu",
    "wof:placetype":"locality"
},
  "geometry": {"coordinates":[95.94750000000001,4.3032],"type":"Point"}
}