{
  "type": "Feature",
  "properties": {
    "gn:admin1_code":"7",
    "gn:asciiname":"Legoksari",
    "gn:country_code":"ID",
    "gn:dem":813,
    "gn:feature_class":"P",
    "gn:feature_code":"PPL",
    "gn:name":"Legoksari",
    "gn:population":0,
    "gn:timezone":"Asia/Jakarta",
    "iso:country":"ID",
    "name:ind_x_preferred":[
        "Legoksari"
    ],
    "wof:name":"Legoksari",
    "wof:placetype":"locality"
},
  "geometry": {"coordinates":[110.37721999999999,-7.22083],"type":"Point"}
}