{
  "type": "Feature",
  "properties": {
    "gn:admin1_code":"1.0",
    "gn:asciiname":"Krueng Baro Blang Me",
    "gn:country_code":"ID",
    "gn:dem":7,
    "gn:feature_class":"P",
    "gn:feature_code":"PPL",
    "gn:name":"Krueng Baro Blang Me",
    "gn:population":0,
    "gn:timezone":"Asia/Jakarta",
    "iso:country":"ID",
    "name:ind_x_preferred":[
        "Krueng Baro Blang Me"
    ],
    "name:und_x_variant":[
        "Blangme"
    ],
    "wof:lang_x_official":[
        "ind"
    ],
    "wof:lang_x_spoken":[
        "ind",
        "eng"
    ],
    "wof:name":"Krueng Baro Blang Me",
    "wof:placetype":"locality"
},
  "geometry": {"coordinates":[97.22329999999999,5.1371],"type":"Point"}
}