{
  "type": "Feature",
  "properties": {
    "gn:admin1_code":"7",
    "gn:asciiname":"Kedawung Lor",
    "gn:country_code":"ID",
    "gn:dem":158,
    "gn:feature_class":"P",
    "gn:feature_code":"PPL",
    "gn:name":"Kedawung Lor",
    "gn:population":0,
    "gn:timezone":"Asia/Jakarta",
    "iso:country":"ID",
    "name:ind_x_preferred":[
        "Kedawung Lor"
    ],
    "wof:name":"Kedawung Lor",
    "wof:placetype":"locality"
},
  "geometry": {"coordinates":[111.0425,-7.48056],"type":"Point"}
}