{
  "type": "Feature",
  "properties": {
    "gn:admin1_code":"7.0",
    "gn:asciiname":"Keron",
    "gn:country_code":"ID",
    "gn:dem":472,
    "gn:feature_class":"P",
    "gn:feature_code":"PPL",
    "gn:name":"Keron",
    "gn:population":0,
    "gn:timezone":"Asia/Jakarta",
    "iso:country":"ID",
    "name:pol_x_preferred":[
        "Keroun"
    ],
    "wof:name":"Keron",
    "wof:placetype":"locality"
},
  "geometry": {"coordinates":[110.31833,-7.56861],"type":"Point"}
}