{
  "type": "Feature",
  "properties": {
    "gn:admin1_code":"28.0",
    "gn:asciiname":"Pillipuang",
    "gn:country_code":"ID",
    "gn:dem":14,
    "gn:feature_class":"P",
    "gn:feature_code":"PPL",
    "gn:name":"Pillipuang",
    "gn:population":0,
    "gn:timezone":"Asia/Jayapura",
    "iso:country":"ID",
    "name:und_x_variant":[
        "Pillipoeang",
        "Pillipuang"
    ],
    "wof:name":"Pillipuang",
    "wof:placetype":"locality"
},
  "geometry": {"coordinates":[126.15112000000001,-7.89762],"type":"Point"}
}