{
  "type": "Feature",
  "properties": {
    "gn:admin1_code":"30.0",
    "gn:asciiname":"Cikarang",
    "gn:country_code":"ID",
    "gn:dem":396,
    "gn:feature_class":"P",
    "gn:feature_code":"PPL",
    "gn:name":"Cikarang",
    "gn:population":0,
    "gn:timezone":"Asia/Jakarta",
    "iso:country":"ID",
    "name:fas_x_preferred":[
        "\u06a9\u06cc\u06a9\u0627\u0631\u0627\u0646\u06af"
    ],
    "name:ind_x_preferred":[
        "Cikarang"
    ],
    "name:mlg_x_preferred":[
        "Cikarang"
    ],
    "name:nld_x_preferred":[
        "Cibeber"
    ],
    "wof:lang_x_official":[
        "ind"
    ],
    "wof:lang_x_spoken":[
        "ind",
        "eng"
    ],
    "wof:name":"Cikarang",
    "wof:placetype":"locality"
},
  "geometry": {"coordinates":[106.62269999999999,-7.2208],"type":"Point"}
}