{
  "type": "Feature",
  "properties": {
    "gn:admin1_code":"30.0",
    "gn:asciiname":"Cikarang",
    "gn:country_code":"ID",
    "gn:dem":396,
    "gn:feature_class":"P",
    "gn:feature_code":"PPL",
    "gn:name":"Cikarang",
    "gn:population":0,
    "gn:timezone":"Asia/Jakarta",
    "iso:country":"ID",
    "name:ind_x_preferred":[
        "Cikarang"
    ],
    "wof:name":"Cikarang",
    "wof:placetype":"locality"
},
  "geometry": {"coordinates":[106.62269999999999,-7.2208],"type":"Point"}
}