{
  "type": "Feature",
  "properties": {
    "gn:admin1_code":"18.0",
    "gn:asciiname":"Malata",
    "gn:country_code":"ID",
    "gn:dem":95,
    "gn:feature_class":"P",
    "gn:feature_code":"PPLA4",
    "gn:name":"Malata",
    "gn:population":0,
    "gn:timezone":"Asia/Makassar",
    "iso:country":"ID",
    "name:ind_x_preferred":[
        "Malata"
    ],
    "wof:name":"Malata",
    "wof:placetype":"locality"
},
  "geometry": {"coordinates":[119.3845,-9.4466],"type":"Point"}
}