{
  "type": "Feature",
  "properties": {
    "gn:admin1_code":"26",
    "gn:asciiname":"Batangtanggaljulu",
    "gn:country_code":"ID",
    "gn:dem":138,
    "gn:feature_class":"P",
    "gn:feature_code":"PPL",
    "gn:name":"Batangtanggaljulu",
    "gn:population":0,
    "gn:timezone":"Asia/Jakarta",
    "iso:country":"ID",
    "name:ind_x_preferred":[
        "Batangtanggaljulu"
    ],
    "wof:name":"Batangtanggaljulu",
    "wof:placetype":"locality"
},
  "geometry": {"coordinates":[99.77506,1.08405],"type":"Point"}
}