{
  "type": "Feature",
  "properties": {
    "gn:admin1_code":"26",
    "gn:asciiname":"Sisir Gunting",
    "gn:country_code":"ID",
    "gn:dem":1,
    "gn:feature_class":"P",
    "gn:feature_code":"PPL",
    "gn:name":"Sisir Gunting",
    "gn:population":0,
    "gn:timezone":"Asia/Jakarta",
    "iso:country":"ID",
    "name:ind_x_preferred":[
        "Sisir Gunting"
    ],
    "wof:name":"Sisir Gunting",
    "wof:placetype":"locality"
},
  "geometry": {"coordinates":[98.64619999999999,3.8194],"type":"Point"}
}