{
  "type": "Feature",
  "properties": {
    "gn:admin1_code":"17.0",
    "gn:asciiname":"Soriutu",
    "gn:country_code":"ID",
    "gn:dem":100,
    "gn:feature_class":"P",
    "gn:feature_code":"PPLA4",
    "gn:name":"Soriutu",
    "gn:population":0,
    "gn:timezone":"Asia/Makassar",
    "iso:country":"ID",
    "name:ind_x_preferred":[
        "Soriutu"
    ],
    "wof:name":"Soriutu",
    "wof:placetype":"locality"
},
  "geometry": {"coordinates":[118.3229,-8.5191],"type":"Point"}
}