{
  "type": "Feature",
  "properties": {
    "gn:admin1_code":"17",
    "gn:asciiname":"Unit Pemukiman Transimigrasi Waworada",
    "gn:country_code":"ID",
    "gn:dem":11,
    "gn:feature_class":"P",
    "gn:feature_code":"PPL",
    "gn:name":"Unit Pemukiman Transimigrasi Waworada",
    "gn:population":0,
    "gn:timezone":"Asia/Makassar",
    "iso:country":"ID",
    "name:ind_x_preferred":[
        "Unit Pemukiman Transimigrasi Waworada"
    ],
    "name:ind_x_variant":[
        "UPT Waworada"
    ],
    "wof:name":"Unit Pemukiman Transimigrasi Waworada",
    "wof:placetype":"locality"
},
  "geometry": {"coordinates":[118.7928,-8.6979],"type":"Point"}
}