{
  "type": "Feature",
  "properties": {
    "gn:admin1_code":"30",
    "gn:asciiname":"Jangga",
    "gn:country_code":"ID",
    "gn:dem":336,
    "gn:feature_class":"P",
    "gn:feature_code":"PPL",
    "gn:name":"Jangga",
    "gn:population":0,
    "gn:timezone":"Asia/Jakarta",
    "iso:country":"ID",
    "name:ind_x_preferred":[
        "Jangga"
    ],
    "name:nld_x_preferred":[
        "Jangga"
    ],
    "name:urd_x_preferred":[
        "\u062c\u0646\u06af\u06af\u0627"
    ],
    "wof:lang_x_official":[
        "ind"
    ],
    "wof:lang_x_spoken":[
        "ind",
        "eng"
    ],
    "wof:name":"Jangga",
    "wof:placetype":"locality"
},
  "geometry": {"coordinates":[107.19667,-6.84556],"type":"Point"}
}