{
  "type": "Feature",
  "properties": {
    "gn:admin1_code":"1",
    "gn:asciiname":"Dandusijabut",
    "gn:country_code":"ID",
    "gn:dem":37,
    "gn:feature_class":"P",
    "gn:feature_code":"PPL",
    "gn:name":"Dandusijabut",
    "gn:population":0,
    "gn:timezone":"Asia/Jakarta",
    "iso:country":"ID",
    "name:ind_x_preferred":[
        "Dandusijabut"
    ],
    "name:und_x_variant":[
        "Dandusidjabut"
    ],
    "wof:name":"Dandusijabut",
    "wof:placetype":"locality"
},
  "geometry": {"coordinates":[99.6362,2.8872],"type":"Point"}
}