{
  "type": "Feature",
  "properties": {
    "gn:admin1_code":"3.0",
    "gn:asciiname":"Payangan",
    "gn:country_code":"ID",
    "gn:dem":29,
    "gn:feature_class":"P",
    "gn:feature_code":"PPL",
    "gn:name":"Payangan",
    "gn:population":0,
    "gn:timezone":"Asia/Jakarta",
    "iso:country":"ID",
    "name:ind_x_preferred":[
        "Payangan"
    ],
    "wof:name":"Payangan",
    "wof:placetype":"locality"
},
  "geometry": {"coordinates":[102.65411,-4.16428],"type":"Point"}
}