{
  "type": "Feature",
  "properties": {
    "gn:admin1_code":"38",
    "gn:asciiname":"Ujungsabang",
    "gn:country_code":"ID",
    "gn:dem":6,
    "gn:feature_class":"P",
    "gn:feature_code":"PPL",
    "gn:name":"Ujungsabang",
    "gn:population":0,
    "gn:timezone":"Asia/Makassar",
    "iso:country":"ID",
    "name:ind_x_preferred":[
        "Ujungsabang"
    ],
    "wof:name":"Ujungsabang",
    "wof:placetype":"locality"
},
  "geometry": {"coordinates":[119.62139999999999,-4.0022],"type":"Point"}
}