{
  "type": "Feature",
  "properties": {
    "gn:country":"ID",
    "gn:fcode":"PPL",
    "gn:pop":0,
    "iso:country":"ID",
    "name:ind_x_preferred":[
        "Padamara"
    ],
    "qs:name":"Padaharja",
    "qs:name_adm0":"Indonesia",
    "qs:name_adm1":"Provinsi Jawa Tengah",
    "qs:photos_9r":0,
    "qs:photos_sr":0,
    "qs:placetype":"Town",
    "qs:pop_sr":"0",
    "wof:name":"Padaharja",
    "wof:placetype":"locality",
    "wof:population":0
},
  "geometry": {"coordinates":[109.31889,-7.38194],"type":"Point"}
}