{
  "type": "Feature",
  "properties": {
    "gn:admin1_code":"18.0",
    "gn:asciiname":"Tuanese",
    "gn:country_code":"ID",
    "gn:dem":45,
    "gn:feature_class":"P",
    "gn:feature_code":"PPL",
    "gn:name":"Tuanese",
    "gn:population":0,
    "gn:timezone":"Asia/Makassar",
    "iso:country":"ID",
    "name:ind_x_preferred":[
        "Tuanese"
    ],
    "wof:name":"Tuanese",
    "wof:placetype":"locality"
},
  "geometry": {"coordinates":[123.5034,-10.2598],"type":"Point"}
}