{
  "type": "Feature",
  "properties": {
    "gn:admin1_code":"7.0",
    "gn:asciiname":"Krapyak",
    "gn:country_code":"ID",
    "gn:dem":104,
    "gn:feature_class":"P",
    "gn:feature_code":"PPL",
    "gn:name":"Krapyak",
    "gn:population":0,
    "gn:timezone":"Asia/Jakarta",
    "iso:country":"ID",
    "name:ind_x_preferred":[
        "Krapyak"
    ],
    "wof:name":"Krapyak",
    "wof:placetype":"locality"
},
  "geometry": {"coordinates":[108.98111000000002,-7.46444],"type":"Point"}
}