{
  "type": "Feature",
  "properties": {
    "gn:admin1_code":"15.0",
    "gn:asciiname":"Teluk Driyan",
    "gn:country_code":"ID",
    "gn:dem":119,
    "gn:feature_class":"P",
    "gn:feature_code":"PPL",
    "gn:name":"Teluk Driyan",
    "gn:population":0,
    "gn:timezone":"Asia/Jakarta",
    "iso:country":"ID",
    "name:ind_x_preferred":[
        "Teluk Driyan"
    ],
    "wof:name":"Teluk Driyan",
    "wof:placetype":"locality"
},
  "geometry": {"coordinates":[105.35886000000001,-5.46272],"type":"Point"}
}