{
  "type": "Feature",
  "properties": {
    "gn:admin1_code":"30.0",
    "gn:asciiname":"Pasirjaya",
    "gn:country_code":"ID",
    "gn:dem":748,
    "gn:feature_class":"P",
    "gn:feature_code":"PPL",
    "gn:name":"Pasirjaya",
    "gn:population":0,
    "gn:timezone":"Asia/Jakarta",
    "iso:country":"ID",
    "name:ind_x_preferred":[
        "Pasirjaya"
    ],
    "name:und_x_variant":[
        "Pasirdjaja"
    ],
    "wof:lang_x_official":[
        "ind"
    ],
    "wof:lang_x_spoken":[
        "ind",
        "eng"
    ],
    "wof:name":"Pasirjaya",
    "wof:placetype":"locality"
},
  "geometry": {"coordinates":[108.19410000000001,-7.0696],"type":"Point"}
}