{
  "type": "Feature",
  "properties": {
    "gn:admin1_code":"30.0",
    "gn:asciiname":"Sadananya",
    "gn:country_code":"ID",
    "gn:dem":388,
    "gn:feature_class":"P",
    "gn:feature_code":"PPLA3",
    "gn:name":"Sadananya",
    "gn:population":0,
    "gn:timezone":"Asia/Jakarta",
    "iso:country":"ID",
    "name:ind_x_preferred":[
        "Sadananya"
    ],
    "name:und_x_variant":[
        "Sadanaja",
        "Sadananja",
        "Sadananya"
    ],
    "wof:lang_x_official":[
        "ind"
    ],
    "wof:lang_x_spoken":[
        "ind",
        "eng"
    ],
    "wof:name":"Sadananya",
    "wof:placetype":"locality"
},
  "geometry": {"coordinates":[108.31489999999999,-7.2741],"type":"Point"}
}