{
  "type": "Feature",
  "properties": {
    "gn:admin1_code":"17",
    "gn:asciiname":"Oronglekok",
    "gn:country_code":"ID",
    "gn:dem":487,
    "gn:feature_class":"P",
    "gn:feature_code":"PPL",
    "gn:name":"Oronglekok",
    "gn:population":0,
    "gn:timezone":"Asia/Makassar",
    "iso:country":"ID",
    "name:ind_x_preferred":[
        "Oronglekok"
    ],
    "wof:name":"Oronglekok",
    "wof:placetype":"locality"
},
  "geometry": {"coordinates":[116.3935,-8.5718],"type":"Point"}
}