{
  "type": "Feature",
  "properties": {
    "gn:admin1_code":"2",
    "gn:asciiname":"Banjar Banyuning Selatan",
    "gn:country_code":"ID",
    "gn:dem":69,
    "gn:feature_class":"P",
    "gn:feature_code":"PPL",
    "gn:name":"Banjar Banyuning Selatan",
    "gn:population":0,
    "gn:timezone":"Asia/Makassar",
    "iso:country":"ID",
    "name:ind_x_preferred":[
        "Banjar Banyuning Selatan"
    ],
    "wof:name":"Banjar Banyuning Selatan",
    "wof:placetype":"locality"
},
  "geometry": {"coordinates":[115.1035,-8.1267],"type":"Point"}
}