{
  "type": "Feature",
  "properties": {
    "gn:admin1_code":"26",
    "gn:asciiname":"Sumbul",
    "gn:country_code":"ID",
    "gn:dem":529,
    "gn:feature_class":"P",
    "gn:feature_code":"PPL",
    "gn:name":"Sumbul",
    "gn:population":0,
    "gn:timezone":"Asia/Jakarta",
    "iso:country":"ID",
    "name:ind_x_preferred":[
        "Sumbul"
    ],
    "name:kur_x_preferred":[
        "Sumbul"
    ],
    "name:nld_x_preferred":[
        "Sumbul"
    ],
    "wof:lang_x_official":[
        "ind"
    ],
    "wof:lang_x_spoken":[
        "ind",
        "eng"
    ],
    "wof:name":"Sumbul",
    "wof:placetype":"locality"
},
  "geometry": {"coordinates":[98.4141,2.188],"type":"Point"}
}