{
  "type": "Feature",
  "properties": {
    "gn:admin1_code":"29.0",
    "gn:asciiname":"Dawongbebudo",
    "gn:country_code":"ID",
    "gn:dem":38,
    "gn:feature_class":"P",
    "gn:feature_code":"PPL",
    "gn:name":"Dawongbebudo",
    "gn:population":0,
    "gn:timezone":"Asia/Jayapura",
    "iso:country":"ID",
    "name:ind_x_preferred":[
        "Dawongbebudo"
    ],
    "name:und_x_variant":[
        "Dawongbeboedo"
    ],
    "wof:lang_x_official":[
        "ind"
    ],
    "wof:lang_x_spoken":[
        "ind",
        "eng"
    ],
    "wof:name":"Dawongbebudo",
    "wof:placetype":"locality"
},
  "geometry": {"coordinates":[127.15345000000001,-0.46825],"type":"Point"}
}