{
  "type": "Feature",
  "properties": {
    "gn:admin1_code":"7",
    "gn:asciiname":"Lekor",
    "gn:country_code":"ID",
    "gn:dem":559,
    "gn:feature_class":"P",
    "gn:feature_code":"PPL",
    "gn:name":"Lekor",
    "gn:population":0,
    "gn:timezone":"Asia/Jakarta",
    "iso:country":"ID",
    "name:ind_x_preferred":[
        "Lekor"
    ],
    "name:msa_x_preferred":[
        "Keropok lekor"
    ],
    "name:tha_x_preferred":[
        "\u0e40\u0e01\u0e42\u0e23\u0e42\u0e1b\u0e30\u0e01\u0e4c\u0e40\u0e25\u0e42\u0e01\u0e23\u0e4c"
    ],
    "wof:lang_x_official":[
        "ind"
    ],
    "wof:lang_x_spoken":[
        "ind",
        "eng"
    ],
    "wof:name":"Lekor",
    "wof:placetype":"locality"
},
  "geometry": {"coordinates":[110.0104,-7.0727],"type":"Point"}
}