{
  "type": "Feature",
  "properties": {
    "gn:admin1_code":"7",
    "gn:asciiname":"Ngilo-ilo",
    "gn:country_code":"ID",
    "gn:dem":706,
    "gn:feature_class":"P",
    "gn:feature_code":"PPL",
    "gn:name":"Ngilo-ilo",
    "gn:population":0,
    "gn:timezone":"Asia/Jakarta",
    "iso:country":"ID",
    "name:ind_x_preferred":[
        "Ngilo-ilo"
    ],
    "wof:name":"Ngilo-ilo",
    "wof:placetype":"locality"
},
  "geometry": {"coordinates":[111.09917,-7.58861],"type":"Point"}
}