{
  "type": "Feature",
  "properties": {
    "gn:admin1_code":"7.0",
    "gn:asciiname":"Karanglo",
    "gn:country_code":"ID",
    "gn:dem":679,
    "gn:feature_class":"P",
    "gn:feature_code":"PPL",
    "gn:name":"Karanglo",
    "gn:population":0,
    "gn:timezone":"Asia/Jakarta",
    "iso:country":"ID",
    "wof:name":"Karanglo",
    "wof:placetype":"locality"
},
  "geometry": {"coordinates":[110.54528000000001,-7.35417],"type":"Point"}
}