{
  "type": "Feature",
  "properties": {
    "gn:admin1_code":"30.0",
    "gn:asciiname":"Cikurantung",
    "gn:country_code":"ID",
    "gn:dem":562,
    "gn:feature_class":"P",
    "gn:feature_code":"PPL",
    "gn:name":"Cikurantung",
    "gn:population":0,
    "gn:timezone":"Asia/Jakarta",
    "iso:country":"ID",
    "name:ind_x_preferred":[
        "Cikurantung"
    ],
    "name:und_x_variant":[
        "Tjikurantoeng"
    ],
    "wof:lang_x_official":[
        "ind"
    ],
    "wof:lang_x_spoken":[
        "ind",
        "eng"
    ],
    "wof:name":"Cikurantung",
    "wof:placetype":"locality"
},
  "geometry": {"coordinates":[108.0348,-7.0073],"type":"Point"}
}