{
  "type": "Feature",
  "properties": {
    "gn:admin1_code":"17",
    "gn:asciiname":"Penumpak",
    "gn:country_code":"ID",
    "gn:dem":11,
    "gn:feature_class":"P",
    "gn:feature_code":"PPL",
    "gn:name":"Penumpak",
    "gn:population":0,
    "gn:timezone":"Asia/Makassar",
    "iso:country":"ID",
    "name:ind_x_preferred":[
        "Penumpak"
    ],
    "wof:name":"Penumpak",
    "wof:placetype":"locality"
},
  "geometry": {"coordinates":[116.4962,-8.8301],"type":"Point"}
}