{
  "type": "Feature",
  "properties": {
    "gn:admin1_code":"8",
    "gn:asciiname":"Ngepeh Satu",
    "gn:country_code":"ID",
    "gn:dem":81,
    "gn:feature_class":"P",
    "gn:feature_code":"PPL",
    "gn:name":"Ngepeh Satu",
    "gn:population":0,
    "gn:timezone":"Asia/Jakarta",
    "iso:country":"ID",
    "name:ind_x_preferred":[
        "Ngepeh Satu"
    ],
    "wof:name":"Ngepeh Satu",
    "wof:placetype":"locality"
},
  "geometry": {"coordinates":[111.6802,-7.5465],"type":"Point"}
}