{
  "type": "Feature",
  "properties": {
    "gn:admin1_code":"0.0",
    "gn:asciiname":"Mangoni",
    "gn:country_code":"ID",
    "gn:dem":3,
    "gn:feature_class":"P",
    "gn:feature_code":"PPL",
    "gn:name":"Mangoni",
    "gn:population":0,
    "gn:timezone":"Asia/Makassar",
    "iso:country":"ID",
    "wof:name":"Mangoni",
    "wof:placetype":"locality"
},
  "geometry": {"coordinates":[121.83333,-2.31667],"type":"Point"}
}