{
  "type": "Feature",
  "properties": {
    "gn:admin1_code":"18",
    "gn:asciiname":"Tanahmerah",
    "gn:country_code":"ID",
    "gn:dem":33,
    "gn:feature_class":"P",
    "gn:feature_code":"PPL",
    "gn:name":"Tanahmerah",
    "gn:population":0,
    "gn:timezone":"Asia/Makassar",
    "iso:country":"ID",
    "name:ind_x_preferred":[
        "Tanahmerah"
    ],
    "wof:name":"Tanahmerah",
    "wof:placetype":"locality"
},
  "geometry": {"coordinates":[122.02970000000001,-8.5456],"type":"Point"}
}