{
  "type": "Feature",
  "properties": {
    "gn:admin1_code":"30.0",
    "gn:asciiname":"Bebedahan",
    "gn:country_code":"ID",
    "gn:dem":497,
    "gn:feature_class":"P",
    "gn:feature_code":"PPL",
    "gn:name":"Bebedahan",
    "gn:population":0,
    "gn:timezone":"Asia/Jakarta",
    "iso:country":"ID",
    "name:ind_x_preferred":[
        "Bebedahan"
    ],
    "name:und_x_variant":[
        "B\u0115d\u0115dahan"
    ],
    "wof:lang_x_official":[
        "ind"
    ],
    "wof:lang_x_spoken":[
        "ind",
        "eng"
    ],
    "wof:name":"Bebedahan",
    "wof:placetype":"locality"
},
  "geometry": {"coordinates":[108.12820000000001,-7.2995],"type":"Point"}
}