{
  "type": "Feature",
  "properties": {
    "gn:admin1_code":"30",
    "gn:asciiname":"Cihideung",
    "gn:country_code":"ID",
    "gn:dem":250,
    "gn:feature_class":"P",
    "gn:feature_code":"PPL",
    "gn:name":"Cihideung",
    "gn:population":0,
    "gn:timezone":"Asia/Jakarta",
    "iso:country":"ID",
    "name:ind_x_preferred":[
        "Cihideung"
    ],
    "wof:name":"Cihideung",
    "wof:placetype":"locality"
},
  "geometry": {"coordinates":[108.08778,-6.91444],"type":"Point"}
}