{
  "type": "Feature",
  "properties": {
    "gn:admin1_code":"18.0",
    "gn:asciiname":"Kalembutadei",
    "gn:country_code":"ID",
    "gn:dem":479,
    "gn:feature_class":"P",
    "gn:feature_code":"PPL",
    "gn:name":"Kalembutadei",
    "gn:population":0,
    "gn:timezone":"Asia/Makassar",
    "iso:country":"ID",
    "name:ind_x_preferred":[
        "Kalembutadei"
    ],
    "wof:name":"Kalembutadei",
    "wof:placetype":"locality"
},
  "geometry": {"coordinates":[119.26260000000001,-9.5151],"type":"Point"}
}