{
  "type": "Feature",
  "properties": {
    "gn:admin1_code":"18",
    "gn:asciiname":"Marilewa",
    "gn:country_code":"ID",
    "gn:dem":16,
    "gn:feature_class":"P",
    "gn:feature_code":"PPL",
    "gn:name":"Marilewa",
    "gn:population":0,
    "gn:timezone":"Asia/Makassar",
    "iso:country":"ID",
    "name:ind_x_preferred":[
        "Marilewa"
    ],
    "wof:name":"Marilewa",
    "wof:placetype":"locality"
},
  "geometry": {"coordinates":[121.5047,-8.63],"type":"Point"}
}