{
  "type": "Feature",
  "properties": {
    "gn:admin1_code":"30",
    "gn:asciiname":"Bakungpasir",
    "gn:cc2":"ID",
    "gn:country_code":"ID",
    "gn:dem":17,
    "gn:feature_class":"P",
    "gn:feature_code":"PPL",
    "gn:name":"Bakungpasir",
    "gn:population":0,
    "gn:timezone":"Asia/Jakarta",
    "iso:country":"ID",
    "name:und_x_variant":[
        "Bakung Dua",
        "Bakunglebak",
        "Bakung 2",
        "Bakungpasir"
    ],
    "wof:name":"Bakungpasir",
    "wof:placetype":"locality"
},
  "geometry": {"coordinates":[106.37083,-6.16694],"type":"Point"}
}