{
  "type": "Feature",
  "properties": {
    "gn:admin1_code":"8",
    "gn:asciiname":"Sambirejo",
    "gn:country_code":"ID",
    "gn:dem":80,
    "gn:feature_class":"P",
    "gn:feature_code":"PPL",
    "gn:name":"Sambirejo",
    "gn:population":0,
    "gn:timezone":"Asia/Jakarta",
    "iso:country":"ID",
    "name:ind_x_preferred":[
        "Sambirejo"
    ],
    "wof:name":"Sambirejo",
    "wof:placetype":"locality"
},
  "geometry": {"coordinates":[111.5081,-7.6971],"type":"Point"}
}