{
  "type": "Feature",
  "properties": {
    "gn:admin1_code":"7",
    "gn:asciiname":"Kadalbuntung",
    "gn:country_code":"ID",
    "gn:dem":650,
    "gn:feature_class":"P",
    "gn:feature_code":"PPL",
    "gn:name":"Kadalbuntung",
    "gn:population":0,
    "gn:timezone":"Asia/Jakarta",
    "iso:country":"ID",
    "name:ind_x_preferred":[
        "Kadalbuntung"
    ],
    "wof:name":"Kadalbuntung",
    "wof:placetype":"locality"
},
  "geometry": {"coordinates":[111.10527999999999,-7.7625],"type":"Point"}
}