{
  "type": "Feature",
  "properties": {
    "gn:admin1_code":"26",
    "gn:asciiname":"Gonting Dua",
    "gn:country_code":"ID",
    "gn:dem":1422,
    "gn:feature_class":"P",
    "gn:feature_code":"PPL",
    "gn:name":"Gonting Dua",
    "gn:population":0,
    "gn:timezone":"Asia/Jakarta",
    "iso:country":"ID",
    "name:ind_x_preferred":[
        "Gonting Dua"
    ],
    "name:und_x_variant":[
        "Gonting 2"
    ],
    "wof:name":"Gonting Dua",
    "wof:placetype":"locality"
},
  "geometry": {"coordinates":[98.8579,2.1621],"type":"Point"}
}