{
  "type": "Feature",
  "properties": {
    "gn:admin1_code":"15.0",
    "gn:asciiname":"Tulungsawo",
    "gn:country_code":"ID",
    "gn:dem":61,
    "gn:feature_class":"P",
    "gn:feature_code":"PPL",
    "gn:name":"Tulungsawo",
    "gn:population":0,
    "gn:timezone":"Asia/Jakarta",
    "iso:country":"ID",
    "name:ind_x_preferred":[
        "Tulungsawo"
    ],
    "wof:name":"Tulungsawo",
    "wof:placetype":"locality"
},
  "geometry": {"coordinates":[105.2317,-5.21548],"type":"Point"}
}