{
  "type": "Feature",
  "properties": {
    "gn:admin1_code":"26",
    "gn:asciiname":"Batunadua Tonga",
    "gn:country_code":"ID",
    "gn:dem":368,
    "gn:feature_class":"P",
    "gn:feature_code":"PPL",
    "gn:name":"Batunadua Tonga",
    "gn:population":0,
    "gn:timezone":"Asia/Jakarta",
    "iso:country":"ID",
    "name:ind_x_preferred":[
        "Batunadua Tonga"
    ],
    "wof:name":"Batunadua Tonga",
    "wof:placetype":"locality"
},
  "geometry": {"coordinates":[99.28230000000001,1.4115],"type":"Point"}
}