{
  "type": "Feature",
  "properties": {
    "gn:admin1_code":"7",
    "gn:asciiname":"Plumbunganindah",
    "gn:country_code":"ID",
    "gn:dem":94,
    "gn:feature_class":"P",
    "gn:feature_code":"PPL",
    "gn:name":"Plumbunganindah",
    "gn:population":0,
    "gn:timezone":"Asia/Jakarta",
    "iso:country":"ID",
    "name:ind_x_preferred":[
        "Plumbunganindah"
    ],
    "wof:name":"Plumbunganindah",
    "wof:placetype":"locality"
},
  "geometry": {"coordinates":[111.04389,-7.43278],"type":"Point"}
}