{
  "type": "Feature",
  "properties": {
    "gn:admin1_code":"7.0",
    "gn:asciiname":"Dodog",
    "gn:country_code":"ID",
    "gn:dem":606,
    "gn:feature_class":"P",
    "gn:feature_code":"PPL",
    "gn:name":"Dodog",
    "gn:population":0,
    "gn:timezone":"Asia/Jakarta",
    "iso:country":"ID",
    "name:ind_x_preferred":[
        "Dodog"
    ],
    "wof:name":"Dodog",
    "wof:placetype":"locality"
},
  "geometry": {"coordinates":[109.41833,-7.53361],"type":"Point"}
}