{
  "type": "Feature",
  "properties": {
    "gn:admin1_code":"18.0",
    "gn:asciiname":"Kualeu",
    "gn:country_code":"ID",
    "gn:dem":1029,
    "gn:feature_class":"P",
    "gn:feature_code":"PPLA4",
    "gn:name":"Kualeu",
    "gn:population":0,
    "gn:timezone":"Asia/Makassar",
    "iso:country":"ID",
    "name:ind_x_preferred":[
        "Kualeu"
    ],
    "wof:lang_x_official":[
        "ind"
    ],
    "wof:lang_x_spoken":[
        "ind",
        "eng"
    ],
    "wof:name":"Kualeu",
    "wof:placetype":"locality"
},
  "geometry": {"coordinates":[124.6525,-9.8617],"type":"Point"}
}