{
  "type": "Feature",
  "properties": {
    "gn:admin1_code":"0.0",
    "gn:asciiname":"Labarubi",
    "gn:cc2":"ID",
    "gn:country_code":"ID",
    "gn:dem":1360,
    "gn:feature_class":"P",
    "gn:feature_code":"PPL",
    "gn:name":"Labarubi",
    "gn:population":0,
    "gn:timezone":"Asia/Makassar",
    "iso:country":"ID",
    "name:und_x_variant":[
        "Labaroebi",
        "Labarubi"
    ],
    "wof:lang_x_official":[
        "ind"
    ],
    "wof:lang_x_spoken":[
        "ind",
        "eng"
    ],
    "wof:name":"Labarubi",
    "wof:placetype":"locality"
},
  "geometry": {"coordinates":[119.76667,-0.95],"type":"Point"}
}