{
  "type": "Feature",
  "properties": {
    "gn:admin1_code":"2",
    "gn:asciiname":"Gunungina",
    "gn:country_code":"ID",
    "gn:dem":41,
    "gn:feature_class":"P",
    "gn:feature_code":"PPL",
    "gn:name":"Gunungina",
    "gn:population":0,
    "gn:timezone":"Asia/Makassar",
    "iso:country":"ID",
    "name:ind_x_preferred":[
        "Gunungina"
    ],
    "wof:name":"Gunungina",
    "wof:placetype":"locality"
},
  "geometry": {"coordinates":[114.9256,-8.2097],"type":"Point"}
}