{
  "type": "Feature",
  "properties": {
    "gn:admin1_code":"18.0",
    "gn:asciiname":"Matani",
    "gn:country_code":"ID",
    "gn:dem":70,
    "gn:feature_class":"P",
    "gn:feature_code":"PPL",
    "gn:name":"Matani",
    "gn:population":0,
    "gn:timezone":"Asia/Makassar",
    "iso:country":"ID",
    "name:che_x_preferred":[
        "\u041c\u0430\u0442\u0430\u043d\u0438"
    ],
    "name:deu_x_preferred":[
        "Matani"
    ],
    "name:hye_x_preferred":[
        "\u0544\u0561\u057f\u0561\u0576"
    ],
    "name:ind_x_preferred":[
        "Matani"
    ],
    "name:kat_x_preferred":[
        "\u10db\u10d0\u10e2\u10d0\u10dc\u10d8"
    ],
    "name:nld_x_preferred":[
        "Matani"
    ],
    "name:rus_x_preferred":[
        "\u041c\u0430\u0442\u0430\u043d\u0438"
    ],
    "wof:lang_x_official":[
        "ind"
    ],
    "wof:lang_x_spoken":[
        "ind",
        "eng"
    ],
    "wof:name":"Matani",
    "wof:placetype":"locality"
},
  "geometry": {"coordinates":[123.6818,-10.1555],"type":"Point"}
}