{
  "type": "Feature",
  "properties": {
    "gn:admin1_code":"30",
    "gn:asciiname":"Karangmalang Satu",
    "gn:country_code":"ID",
    "gn:dem":9,
    "gn:feature_class":"P",
    "gn:feature_code":"PPL",
    "gn:name":"Karangmalang Satu",
    "gn:population":0,
    "gn:timezone":"Asia/Jakarta",
    "iso:country":"ID",
    "name:ind_x_preferred":[
        "Karangmalang Satu"
    ],
    "wof:name":"Karangmalang Satu",
    "wof:placetype":"locality"
},
  "geometry": {"coordinates":[108.29667000000001,-6.42861],"type":"Point"}
}