{
  "type": "Feature",
  "properties": {
    "gn:admin1_code":"14",
    "gn:asciiname":"Girimulyo",
    "gn:country_code":"ID",
    "gn:dem":31,
    "gn:feature_class":"P",
    "gn:feature_code":"PPL",
    "gn:name":"Girimulyo",
    "gn:population":0,
    "gn:timezone":"Asia/Makassar",
    "iso:country":"ID",
    "name:ind_x_preferred":[
        "Girimulyo"
    ],
    "wof:name":"Girimulyo",
    "wof:placetype":"locality"
},
  "geometry": {"coordinates":[116.8907,-1.1552],"type":"Point"}
}