{
  "type": "Feature",
  "properties": {
    "gn:admin1_code":"30.0",
    "gn:asciiname":"Cikalapa",
    "gn:country_code":"ID",
    "gn:dem":568,
    "gn:feature_class":"P",
    "gn:feature_code":"PPL",
    "gn:name":"Cikalapa",
    "gn:population":0,
    "gn:timezone":"Asia/Jakarta",
    "iso:country":"ID",
    "name:ind_x_preferred":[
        "Cikalapa"
    ],
    "name:und_x_variant":[
        "Tjikalapa Dua"
    ],
    "wof:name":"Cikalapa",
    "wof:placetype":"locality"
},
  "geometry": {"coordinates":[108.1644,-7.2017],"type":"Point"}
}