{
  "type": "Feature",
  "properties": {
    "gn:admin1_code":"8.0",
    "gn:asciiname":"Bunul",
    "gn:cc2":"ID",
    "gn:country_code":"ID",
    "gn:dem":444,
    "gn:feature_class":"P",
    "gn:feature_code":"PPL",
    "gn:name":"Bunul",
    "gn:population":0,
    "gn:timezone":"Asia/Jakarta",
    "iso:country":"ID",
    "name:und_x_variant":[
        "Boenoel",
        "Bunul"
    ],
    "wof:name":"Bunul",
    "wof:placetype":"locality"
},
  "geometry": {"coordinates":[112.64749999999999,-7.97333],"type":"Point"}
}