{
  "type": "Feature",
  "properties": {
    "gn:admin1_code":"18.0",
    "gn:asciiname":"Danggoen",
    "gn:country_code":"ID",
    "gn:dem":8,
    "gn:feature_class":"P",
    "gn:feature_code":"PPL",
    "gn:name":"Danggoen",
    "gn:population":0,
    "gn:timezone":"Asia/Makassar",
    "iso:country":"ID",
    "name:ind_x_preferred":[
        "Danggoen"
    ],
    "wof:name":"Danggoen",
    "wof:placetype":"locality"
},
  "geometry": {"coordinates":[123.00190000000001,-10.858],"type":"Point"}
}