{
  "type": "Feature",
  "properties": {
    "gn:admin1_code":"18.0",
    "gn:asciiname":"Bandu",
    "gn:country_code":"ID",
    "gn:dem":133,
    "gn:feature_class":"P",
    "gn:feature_code":"PPL",
    "gn:name":"Bandu",
    "gn:population":0,
    "gn:timezone":"Asia/Makassar",
    "iso:country":"ID",
    "name:ceb_x_preferred":[
        "Bandu"
    ],
    "name:fas_x_preferred":[
        "\u0628\u0646\u062f\u0648"
    ],
    "name:ind_x_preferred":[
        "Bandu"
    ],
    "name:swe_x_preferred":[
        "Bandu"
    ],
    "wof:lang_x_official":[
        "ind"
    ],
    "wof:lang_x_spoken":[
        "ind",
        "eng"
    ],
    "wof:name":"Bandu",
    "wof:placetype":"locality"
},
  "geometry": {"coordinates":[123.1049,-10.807],"type":"Point"}
}