{
  "type": "Feature",
  "properties": {
    "gn:admin1_code":"1",
    "gn:asciiname":"Lileu",
    "gn:country_code":"ID",
    "gn:dem":480,
    "gn:feature_class":"P",
    "gn:feature_code":"PPL",
    "gn:name":"Lileu",
    "gn:population":0,
    "gn:timezone":"Asia/Jakarta",
    "iso:country":"ID",
    "name:ind_x_preferred":[
        "Lileu"
    ],
    "wof:name":"Lileu",
    "wof:placetype":"locality"
},
  "geometry": {"coordinates":[96.1434,4.837],"type":"Point"}
}