{
  "type": "Feature",
  "properties": {
    "gn:admin1_code":"1",
    "gn:asciiname":"Darulaman",
    "gn:country_code":"ID",
    "gn:dem":7,
    "gn:feature_class":"P",
    "gn:feature_code":"PPL",
    "gn:name":"Darulaman",
    "gn:population":0,
    "gn:timezone":"Asia/Jakarta",
    "iso:country":"ID",
    "name:fas_x_preferred":[
        "\u062f\u0627\u0631\u0627\u0644\u0627\u0645\u0627\u0646"
    ],
    "name:ind_x_preferred":[
        "Darulaman"
    ],
    "wof:name":"Darulaman",
    "wof:placetype":"locality"
},
  "geometry": {"coordinates":[97.70869999999999,5.0029],"type":"Point"}
}