{
  "type": "Feature",
  "properties": {
    "gn:admin1_code":"37.0",
    "gn:asciiname":"Telukdalam",
    "gn:country_code":"ID",
    "gn:dem":8,
    "gn:feature_class":"P",
    "gn:feature_code":"PPLA3",
    "gn:name":"Telukdalam",
    "gn:population":0,
    "gn:timezone":"Asia/Jakarta",
    "iso:country":"ID",
    "name:ind_x_preferred":[
        "Telukdalam"
    ],
    "wof:name":"Telukdalam",
    "wof:placetype":"locality"
},
  "geometry": {"coordinates":[103.26645000000001,0.53275],"type":"Point"}
}