{
  "type": "Feature",
  "properties": {
    "gn:admin1_code":"30.0",
    "gn:asciiname":"Sembahpanday",
    "gn:country_code":"ID",
    "gn:dem":867,
    "gn:feature_class":"P",
    "gn:feature_code":"PPL",
    "gn:name":"Sembahpanday",
    "gn:population":0,
    "gn:timezone":"Asia/Jakarta",
    "iso:country":"ID",
    "name:ind_x_preferred":[
        "Sembahpanday"
    ],
    "wof:name":"Sembahpanday",
    "wof:placetype":"locality"
},
  "geometry": {"coordinates":[107.9395,-7.244],"type":"Point"}
}