{
  "type": "Feature",
  "properties": {
    "gn:admin1_code":"10",
    "gn:asciiname":"Bengle Dua",
    "gn:country_code":"ID",
    "gn:dem":210,
    "gn:feature_class":"P",
    "gn:feature_code":"PPL",
    "gn:name":"Bengle Dua",
    "gn:population":0,
    "gn:timezone":"Asia/Jakarta",
    "iso:country":"ID",
    "name:ind_x_preferred":[
        "Bengle Dua"
    ],
    "wof:name":"Bengle Dua",
    "wof:placetype":"locality"
},
  "geometry": {"coordinates":[110.62194,-8.10611],"type":"Point"}
}