{
  "type": "Feature",
  "properties": {
    "gn:admin1_code":"28.0",
    "gn:asciiname":"Olilit",
    "gn:country_code":"ID",
    "gn:dem":11,
    "gn:feature_class":"P",
    "gn:feature_code":"PPL",
    "gn:name":"Olilit",
    "gn:population":0,
    "gn:timezone":"Asia/Jayapura",
    "iso:country":"ID",
    "name:eng_x_preferred":[
        "Olilit"
    ],
    "name:ind_x_preferred":[
        "Alilit"
    ],
    "wof:lang_x_official":[
        "ind"
    ],
    "wof:lang_x_spoken":[
        "ind",
        "eng"
    ],
    "wof:name":"Olilit",
    "wof:placetype":"locality"
},
  "geometry": {"coordinates":[131.32798,-7.99336],"type":"Point"}
}