{
  "type": "Feature",
  "properties": {
    "gn:admin1_code":"18.0",
    "gn:asciiname":"Umapaohi",
    "gn:country_code":"ID",
    "gn:dem":455,
    "gn:feature_class":"P",
    "gn:feature_code":"PPL",
    "gn:name":"Umapaohi",
    "gn:population":0,
    "gn:timezone":"Asia/Makassar",
    "iso:country":"ID",
    "name:ind_x_preferred":[
        "Umapaohi"
    ],
    "wof:name":"Umapaohi",
    "wof:placetype":"locality"
},
  "geometry": {"coordinates":[119.63120000000001,-9.6349],"type":"Point"}
}