{
  "type": "Feature",
  "properties": {
    "gn:admin1_code":"38",
    "gn:asciiname":"Wanuaewelado",
    "gn:country_code":"ID",
    "gn:dem":21,
    "gn:feature_class":"P",
    "gn:feature_code":"PPL",
    "gn:name":"Wanuaewelado",
    "gn:population":0,
    "gn:timezone":"Asia/Makassar",
    "iso:country":"ID",
    "name:ind_x_preferred":[
        "Wanuaewelado"
    ],
    "name:und_x_variant":[
        "Welado"
    ],
    "wof:name":"Wanuaewelado",
    "wof:placetype":"locality"
},
  "geometry": {"coordinates":[120.1811,-4.24],"type":"Point"}
}