{
  "type": "Feature",
  "properties": {
    "gn:admin1_code":"0.0",
    "gn:asciiname":"Sungaisungkai",
    "gn:country_code":"ID",
    "gn:dem":236,
    "gn:feature_class":"P",
    "gn:feature_code":"PPL",
    "gn:name":"Sungaisungkai",
    "gn:population":0,
    "gn:timezone":"Asia/Jakarta",
    "iso:country":"ID",
    "wof:name":"Sungaisungkai",
    "wof:placetype":"locality"
},
  "geometry": {"coordinates":[101.46666999999999,-1.41667],"type":"Point"}
}