{
  "type": "Feature",
  "properties": {
    "gn:admin1_code":"30.0",
    "gn:asciiname":"Gunungrasamala",
    "gn:country_code":"ID",
    "gn:dem":1050,
    "gn:feature_class":"P",
    "gn:feature_code":"PPL",
    "gn:name":"Gunungrasamala",
    "gn:population":0,
    "gn:timezone":"Asia/Jakarta",
    "iso:country":"ID",
    "name:ind_x_preferred":[
        "Gunungrasamala"
    ],
    "wof:name":"Gunungrasamala",
    "wof:placetype":"locality"
},
  "geometry": {"coordinates":[106.9894,-7.0387],"type":"Point"}
}