{
  "type": "Feature",
  "properties": {
    "gn:admin1_code":"33",
    "gn:asciiname":"Pagadungan",
    "gn:country_code":"ID",
    "gn:dem":27,
    "gn:feature_class":"P",
    "gn:feature_code":"PPL",
    "gn:name":"Pagadungan",
    "gn:population":0,
    "gn:timezone":"Asia/Jakarta",
    "iso:country":"ID",
    "name:ind_x_preferred":[
        "Pagadungan"
    ],
    "wof:name":"Pagadungan",
    "wof:placetype":"locality"
},
  "geometry": {"coordinates":[106.3678,-6.2939],"type":"Point"}
}