{
  "type": "Feature",
  "properties": {
    "gn:admin1_code":"8.0",
    "gn:asciiname":"Ngerjo",
    "gn:country_code":"ID",
    "gn:dem":472,
    "gn:feature_class":"P",
    "gn:feature_code":"PPL",
    "gn:name":"Ngerjo",
    "gn:population":0,
    "gn:timezone":"Asia/Jakarta",
    "iso:country":"ID",
    "name:ind_x_preferred":[
        "Ngerjo"
    ],
    "wof:name":"Ngerjo",
    "wof:placetype":"locality"
},
  "geometry": {"coordinates":[111.6176,-8.0043],"type":"Point"}
}