{
  "type": "Feature",
  "properties": {
    "gn:admin1_code":"38.0",
    "gn:asciiname":"Kanan",
    "gn:country_code":"ID",
    "gn:dem":1250,
    "gn:feature_class":"P",
    "gn:feature_code":"PPL",
    "gn:name":"Kanan",
    "gn:population":0,
    "gn:timezone":"Asia/Makassar",
    "iso:country":"ID",
    "name:ind_x_preferred":[
        "Kanan"
    ],
    "wof:name":"Kanan",
    "wof:placetype":"locality"
},
  "geometry": {"coordinates":[119.5688,-3.1916],"type":"Point"}
}