{
  "type": "Feature",
  "properties": {
    "gn:admin1_code":"30",
    "gn:asciiname":"Tambuntigabagian",
    "gn:country_code":"ID",
    "gn:dem":2,
    "gn:feature_class":"P",
    "gn:feature_code":"PPL",
    "gn:name":"Tambuntigabagian",
    "gn:population":0,
    "gn:timezone":"Asia/Jakarta",
    "iso:country":"ID",
    "name:ind_x_preferred":[
        "Tambuntigabagian"
    ],
    "wof:name":"Tambuntigabagian",
    "wof:placetype":"locality"
},
  "geometry": {"coordinates":[107.02,-6.12222],"type":"Point"}
}