{
  "type": "Feature",
  "properties": {
    "gn:admin1_code":"7",
    "gn:asciiname":"Petunjungan",
    "gn:country_code":"ID",
    "gn:dem":13,
    "gn:feature_class":"P",
    "gn:feature_code":"PPL",
    "gn:name":"Petunjungan",
    "gn:population":0,
    "gn:timezone":"Asia/Jakarta",
    "iso:country":"ID",
    "name:ind_x_preferred":[
        "Petunjungan"
    ],
    "wof:name":"Petunjungan",
    "wof:placetype":"locality"
},
  "geometry": {"coordinates":[108.97790000000001,-6.9147],"type":"Point"}
}