{
  "type": "Feature",
  "properties": {
    "gn:admin1_code":"17.0",
    "gn:asciiname":"Labuancarik",
    "gn:country_code":"ID",
    "gn:dem":8,
    "gn:feature_class":"P",
    "gn:feature_code":"PPL",
    "gn:name":"Labuancarik",
    "gn:population":0,
    "gn:timezone":"Asia/Makassar",
    "iso:country":"ID",
    "name:ind_x_preferred":[
        "Labuancarik"
    ],
    "name:und_x_variant":[
        "Labuhancarik",
        "Laboehantjarik",
        "Labuhantjarik",
        "Laboean Tjarik",
        "Laboean Tjari",
        "Labuhancari"
    ],
    "wof:lang_x_official":[
        "ind"
    ],
    "wof:lang_x_spoken":[
        "ind",
        "eng"
    ],
    "wof:name":"Labuancarik",
    "wof:placetype":"locality"
},
  "geometry": {"coordinates":[116.4269,-8.2227],"type":"Point"}
}