{
  "type": "Feature",
  "properties": {
    "gn:admin1_code":"8.0",
    "gn:asciiname":"Gili",
    "gn:country_code":"ID",
    "gn:dem":-9999,
    "gn:feature_class":"P",
    "gn:feature_code":"PPL",
    "gn:name":"Gili",
    "gn:population":0,
    "gn:timezone":"Asia/Jakarta",
    "iso:country":"ID",
    "name:ceb_x_preferred":[
        "Gili"
    ],
    "name:deu_x_preferred":[
        "Gili"
    ],
    "name:fra_x_preferred":[
        "Gili"
    ],
    "name:ind_x_preferred":[
        "Gili"
    ],
    "name:nld_x_preferred":[
        "Gili"
    ],
    "name:swe_x_preferred":[
        "Gili"
    ],
    "wof:lang_x_official":[
        "ind"
    ],
    "wof:lang_x_spoken":[
        "ind",
        "eng"
    ],
    "wof:name":"Gili",
    "wof:placetype":"locality"
},
  "geometry": {"coordinates":[112.76841,-5.80338],"type":"Point"}
}