{
  "type": "Feature",
  "properties": {
    "gn:admin1_code":"22.0",
    "gn:asciiname":"Purwodadi",
    "gn:country_code":"ID",
    "gn:dem":38,
    "gn:feature_class":"P",
    "gn:feature_code":"PPL",
    "gn:name":"Purwodadi",
    "gn:population":0,
    "gn:timezone":"Asia/Makassar",
    "iso:country":"ID",
    "name:ind_x_preferred":[
        "Purwodadi"
    ],
    "wof:name":"Purwodadi",
    "wof:placetype":"locality"
},
  "geometry": {"coordinates":[122.46339999999999,-4.2973],"type":"Point"}
}