{
  "type": "Feature",
  "properties": {
    "gn:admin1_code":"18.0",
    "gn:asciiname":"Galokawu",
    "gn:country_code":"ID",
    "gn:dem":508,
    "gn:feature_class":"P",
    "gn:feature_code":"PPL",
    "gn:name":"Galokawu",
    "gn:population":0,
    "gn:timezone":"Asia/Makassar",
    "iso:country":"ID",
    "name:ind_x_preferred":[
        "Galokawu"
    ],
    "wof:name":"Galokawu",
    "wof:placetype":"locality"
},
  "geometry": {"coordinates":[119.6955,-9.5239],"type":"Point"}
}