{
  "type": "Feature",
  "properties": {
    "gn:admin1_code":"33.0",
    "gn:asciiname":"Juhut",
    "gn:country_code":"ID",
    "gn:dem":290,
    "gn:feature_class":"P",
    "gn:feature_code":"PPLA4",
    "gn:name":"Juhut",
    "gn:population":0,
    "gn:timezone":"Asia/Jakarta",
    "iso:country":"ID",
    "name:ind_x_preferred":[
        "Juhut"
    ],
    "wof:name":"Juhut",
    "wof:placetype":"locality"
},
  "geometry": {"coordinates":[106.10639999999999,-6.2955],"type":"Point"}
}