{
  "type": "Feature",
  "properties": {
    "gn:admin1_code":"35",
    "gn:asciiname":"Anggas",
    "gn:country_code":"ID",
    "gn:dem":39,
    "gn:feature_class":"P",
    "gn:feature_code":"PPL",
    "gn:name":"Anggas",
    "gn:population":0,
    "gn:timezone":"Asia/Jakarta",
    "iso:country":"ID",
    "name:ind_x_preferred":[
        "Anggas"
    ],
    "wof:name":"Anggas",
    "wof:placetype":"locality"
},
  "geometry": {"coordinates":[105.77495999999999,-1.9493],"type":"Point"}
}