{
  "type": "Feature",
  "properties": {
    "gn:admin1_code":"10.0",
    "gn:asciiname":"Nogosari",
    "gn:country_code":"ID",
    "gn:dem":349,
    "gn:feature_class":"P",
    "gn:feature_code":"PPL",
    "gn:name":"Nogosari",
    "gn:population":0,
    "gn:timezone":"Asia/Jakarta",
    "iso:country":"ID",
    "wof:name":"Nogosari",
    "wof:placetype":"locality"
},
  "geometry": {"coordinates":[110.17944,-7.72278],"type":"Point"}
}