{
  "type": "Feature",
  "properties": {
    "gn:country":"ID",
    "gn:fcode":"PPLA4",
    "gn:pop":0,
    "iso:country":"ID",
    "name:ind_x_preferred":[
        "Banjarsari"
    ],
    "qs:name":"Banjarsari",
    "qs:photos_9r":0,
    "qs:photos_sr":0,
    "qs:pop_sr":"0",
    "wof:lang_x_official":[
        "ind"
    ],
    "wof:lang_x_spoken":[
        "ind",
        "eng"
    ],
    "wof:name":"Banjarsari",
    "wof:placetype":"locality",
    "wof:population":0
},
  "geometry": {"coordinates":[108.1456,-7.3152],"type":"Point"}
}