{
  "type": "Feature",
  "properties": {
    "gn:admin1_code":"8",
    "gn:asciiname":"Jago",
    "gn:country_code":"ID",
    "gn:dem":612,
    "gn:feature_class":"P",
    "gn:feature_code":"PPL",
    "gn:name":"Jago",
    "gn:population":0,
    "gn:timezone":"Asia/Jakarta",
    "iso:country":"ID",
    "name:deu_x_preferred":[
        "Jago"
    ],
    "name:fra_x_preferred":[
        "Jago"
    ],
    "name:ind_x_preferred":[
        "Jago"
    ],
    "name:swe_x_preferred":[
        "Jago"
    ],
    "wof:name":"Jago",
    "wof:placetype":"locality"
},
  "geometry": {"coordinates":[112.7632,-8.003],"type":"Point"}
}