{
  "type": "Feature",
  "properties": {
    "gn:admin1_code":"18.0",
    "gn:asciiname":"Palumu",
    "gn:country_code":"ID",
    "gn:dem":306,
    "gn:feature_class":"P",
    "gn:feature_code":"PPL",
    "gn:name":"Palumu",
    "gn:population":0,
    "gn:timezone":"Asia/Makassar",
    "iso:country":"ID",
    "name:ind_x_preferred":[
        "Palumu"
    ],
    "wof:name":"Palumu",
    "wof:placetype":"locality"
},
  "geometry": {"coordinates":[119.27679999999999,-9.455],"type":"Point"}
}