{
  "type": "Feature",
  "properties": {
    "gn:admin1_code":"38.0",
    "gn:asciiname":"Pangi",
    "gn:country_code":"ID",
    "gn:dem":8,
    "gn:feature_class":"P",
    "gn:feature_code":"PPL",
    "gn:name":"Pangi",
    "gn:population":0,
    "gn:timezone":"Asia/Makassar",
    "iso:country":"ID",
    "name:ceb_x_preferred":[
        "Pangi"
    ],
    "name:ind_x_preferred":[
        "Pangi"
    ],
    "name:nld_x_preferred":[
        "Pangi"
    ],
    "name:swe_x_preferred":[
        "Pangi"
    ],
    "wof:name":"Pangi",
    "wof:placetype":"locality"
},
  "geometry": {"coordinates":[120.959,-2.5887],"type":"Point"}
}