{
  "type": "Feature",
  "properties": {
    "gn:admin1_code":"8",
    "gn:asciiname":"Bugel",
    "gn:country_code":"ID",
    "gn:dem":445,
    "gn:feature_class":"P",
    "gn:feature_code":"PPL",
    "gn:name":"Bugel",
    "gn:population":0,
    "gn:timezone":"Asia/Jakarta",
    "iso:country":"ID",
    "name:ind_x_preferred":[
        "Bugel"
    ],
    "wof:name":"Bugel",
    "wof:placetype":"locality"
},
  "geometry": {"coordinates":[111.28749999999999,-7.59306],"type":"Point"}
}