{
  "type": "Feature",
  "properties": {
    "gn:admin1_code":"30.0",
    "gn:asciiname":"Ciroas",
    "gn:country_code":"ID",
    "gn:dem":382,
    "gn:feature_class":"P",
    "gn:feature_code":"PPL",
    "gn:name":"Ciroas",
    "gn:population":0,
    "gn:timezone":"Asia/Jakarta",
    "iso:country":"ID",
    "name:ind_x_preferred":[
        "Ciroas"
    ],
    "wof:name":"Ciroas",
    "wof:placetype":"locality"
},
  "geometry": {"coordinates":[108.47920000000001,-7.2092],"type":"Point"}
}