{
  "type": "Feature",
  "properties": {
    "gn:admin1_code":"7",
    "gn:asciiname":"Temu",
    "gn:country_code":"ID",
    "gn:dem":157,
    "gn:feature_class":"P",
    "gn:feature_code":"PPL",
    "gn:name":"Temu",
    "gn:population":0,
    "gn:timezone":"Asia/Jakarta",
    "iso:country":"ID",
    "name:ceb_x_preferred":[
        "Temu"
    ],
    "name:deu_x_preferred":[
        "Temu"
    ],
    "name:ind_x_preferred":[
        "Temu"
    ],
    "name:nld_x_preferred":[
        "Temu"
    ],
    "name:rus_x_preferred":[
        "\u0422\u0435\u043c\u0443"
    ],
    "name:spa_x_preferred":[
        "Temu"
    ],
    "name:swe_x_preferred":[
        "Temu"
    ],
    "name:ukr_x_preferred":[
        "\u0422\u0435\u043c\u0443"
    ],
    "wof:lang_x_official":[
        "ind"
    ],
    "wof:lang_x_spoken":[
        "ind",
        "eng"
    ],
    "wof:name":"Temu",
    "wof:placetype":"locality"
},
  "geometry": {"coordinates":[109.26690000000001,-7.0285],"type":"Point"}
}