{
  "type": "Feature",
  "properties": {
    "gn:admin1_code":"17.0",
    "gn:asciiname":"Dayamakmur Satu",
    "gn:country_code":"ID",
    "gn:dem":14,
    "gn:feature_class":"P",
    "gn:feature_code":"PPL",
    "gn:name":"Dayamakmur Satu",
    "gn:population":0,
    "gn:timezone":"Asia/Makassar",
    "iso:country":"ID",
    "name:ind_x_preferred":[
        "Dayamakmur Satu"
    ],
    "wof:name":"Dayamakmur Satu",
    "wof:placetype":"locality"
},
  "geometry": {"coordinates":[116.8591,-8.5483],"type":"Point"}
}