{
  "type": "Feature",
  "properties": {
    "gn:admin1_code":"2",
    "gn:asciiname":"Banjar Bantastengah Kaja",
    "gn:country_code":"ID",
    "gn:dem":149,
    "gn:feature_class":"P",
    "gn:feature_code":"PPL",
    "gn:name":"Banjar Bantastengah Kaja",
    "gn:population":0,
    "gn:timezone":"Asia/Makassar",
    "iso:country":"ID",
    "name:ind_x_preferred":[
        "Banjar Bantastengah Kaja"
    ],
    "name:und_x_variant":[
        "Bantas Tengah Kaja"
    ],
    "wof:name":"Banjar Bantastengah Kaja",
    "wof:placetype":"locality"
},
  "geometry": {"coordinates":[115.068,-8.5004],"type":"Point"}
}