{
  "type": "Feature",
  "properties": {
    "gn:admin1_code":"11.0",
    "gn:asciiname":"Nanga Badau",
    "gn:country_code":"ID",
    "gn:dem":91,
    "gn:feature_class":"P",
    "gn:feature_code":"PPL",
    "gn:name":"Nanga Badau",
    "gn:population":0,
    "gn:timezone":"Asia/Pontianak",
    "iso:country":"ID",
    "name:und_x_variant":[
        "Nangahbadau",
        "Nangabdau",
        "Nangabadau",
        "Nanga Badau",
        "Nangah Badau"
    ],
    "wof:lang_x_official":[
        "ind"
    ],
    "wof:lang_x_spoken":[
        "ind",
        "eng"
    ],
    "wof:name":"Nanga Badau",
    "wof:placetype":"locality"
},
  "geometry": {"coordinates":[111.90079,1.04399],"type":"Point"}
}