{
  "type": "Feature",
  "properties": {
    "gn:admin1_code":"18",
    "gn:asciiname":"Muli",
    "gn:country_code":"ID",
    "gn:dem":530,
    "gn:feature_class":"P",
    "gn:feature_code":"PPL",
    "gn:name":"Muli",
    "gn:population":0,
    "gn:timezone":"Asia/Makassar",
    "iso:country":"ID",
    "name:ceb_x_preferred":[
        "Muli"
    ],
    "name:deu_x_preferred":[
        "Muli"
    ],
    "name:div_x_preferred":[
        "\u0789\u07aa\u078d\u07a8"
    ],
    "name:fas_x_preferred":[
        "\u0645\u0648\u0644\u06cc"
    ],
    "name:ind_x_preferred":[
        "Muli"
    ],
    "name:nld_x_preferred":[
        "Muli"
    ],
    "name:swe_x_preferred":[
        "Muli"
    ],
    "wof:lang_x_official":[
        "ind"
    ],
    "wof:lang_x_spoken":[
        "ind",
        "eng"
    ],
    "wof:name":"Muli",
    "wof:placetype":"locality"
},
  "geometry": {"coordinates":[120.8297,-8.575],"type":"Point"}
}