{
  "type": "Feature",
  "properties": {
    "gn:admin1_code":"18.0",
    "gn:asciiname":"Pandu",
    "gn:country_code":"ID",
    "gn:dem":185,
    "gn:feature_class":"P",
    "gn:feature_code":"PPL",
    "gn:name":"Pandu",
    "gn:population":0,
    "gn:timezone":"Asia/Makassar",
    "iso:country":"ID",
    "name:ben_x_preferred":[
        "\u09aa\u09be\u09a3\u09cd\u09a1\u09c1"
    ],
    "name:deu_x_preferred":[
        "Pandu"
    ],
    "name:epo_x_preferred":[
        "Panduo"
    ],
    "name:fas_x_preferred":[
        "\u067e\u0627\u0646\u062f\u0648"
    ],
    "name:fra_x_preferred":[
        "Pandu"
    ],
    "name:guj_x_preferred":[
        "\u0aaa\u0abe\u0a82\u0aa1\u0ac1"
    ],
    "name:hin_x_preferred":[
        "\u092a\u093e\u0923\u094d\u0921\u0941"
    ],
    "name:ind_x_preferred":[
        "Pandu"
    ],
    "name:jav_x_preferred":[
        "Pandhu"
    ],
    "name:jpn_x_preferred":[
        "\u30d1\u30fc\u30f3\u30c9\u30a5"
    ],
    "name:kan_x_preferred":[
        "\u0caa\u0cbe\u0c82\u0ca1\u0cc1"
    ],
    "name:lit_x_preferred":[
        "Pandus"
    ],
    "name:mal_x_preferred":[
        "\u0d2a\u0d3e\u0d23\u0d4d\u0d21\u0d41"
    ],
    "name:mar_x_preferred":[
        "\u092a\u0902\u0921\u0942"
    ],
    "name:nep_x_preferred":[
        "\u092a\u093e\u0923\u094d\u0921\u0941"
    ],
    "name:nld_x_preferred":[
        "Pandu"
    ],
    "name:pan_x_preferred":[
        "\u0a2a\u0a3e\u0a02\u0a21\u0a42"
    ],
    "name:rus_x_preferred":[
        "\u041f\u0430\u043d\u0434\u0443"
    ],
    "name:san_x_preferred":[
        "\u092a\u093e\u0923\u094d\u0921\u0941\u0903"
    ],
    "name:spa_x_preferred":[
        "Pand\u00fa"
    ],
    "name:sun_x_preferred":[
        "Pandu"
    ],
    "name:swe_x_preferred":[
        "Pandu"
    ],
    "name:tam_x_preferred":[
        "\u0baa\u0bbe\u0ba3\u0bcd\u0b9f\u0bc1"
    ],
    "name:tel_x_preferred":[
        "\u0c2a\u0c3e\u0c02\u0c21\u0c41\u0c30\u0c3e\u0c1c\u0c41"
    ],
    "name:tha_x_preferred":[
        "\u0e17\u0e49\u0e32\u0e27\u0e1b\u0e32\u0e13\u0e11\u0e38"
    ],
    "name:ukr_x_preferred":[
        "\u041f\u0430\u043d\u0434\u0443"
    ],
    "wof:lang_x_official":[
        "ind"
    ],
    "wof:lang_x_spoken":[
        "ind",
        "eng"
    ],
    "wof:name":"Pandu",
    "wof:placetype":"locality"
},
  "geometry": {"coordinates":[120.6618,-8.7957],"type":"Point"}
}