{
  "type": "Feature",
  "properties": {
    "gn:admin1_code":"30.0",
    "gn:asciiname":"Darmabakti",
    "gn:country_code":"ID",
    "gn:dem":683,
    "gn:feature_class":"P",
    "gn:feature_code":"PPL",
    "gn:name":"Darmabakti",
    "gn:population":0,
    "gn:timezone":"Asia/Jakarta",
    "iso:country":"ID",
    "name:ind_x_preferred":[
        "Darmabakti"
    ],
    "wof:name":"Darmabakti",
    "wof:placetype":"locality"
},
  "geometry": {"coordinates":[107.46169999999999,-7.3325],"type":"Point"}
}