{
  "type": "Feature",
  "properties": {
    "gn:admin1_code":"38.0",
    "gn:asciiname":"Bontopanno",
    "gn:country_code":"ID",
    "gn:dem":241,
    "gn:feature_class":"P",
    "gn:feature_code":"PPL",
    "gn:name":"Bontopanno",
    "gn:population":0,
    "gn:timezone":"Asia/Makassar",
    "iso:country":"ID",
    "name:ind_x_preferred":[
        "Bontopanno"
    ],
    "name:und_x_variant":[
        "Bontopano 2",
        "Bontopano"
    ],
    "wof:name":"Bontopanno",
    "wof:placetype":"locality"
},
  "geometry": {"coordinates":[119.7561,-4.8318],"type":"Point"}
}