{
  "type": "Feature",
  "properties": {
    "gn:admin1_code":"15.0",
    "gn:asciiname":"Way Redak",
    "gn:country_code":"ID",
    "gn:dem":9,
    "gn:feature_class":"P",
    "gn:feature_code":"PPL",
    "gn:name":"Way Redak",
    "gn:population":0,
    "gn:timezone":"Asia/Jakarta",
    "iso:country":"ID",
    "name:ind_x_preferred":[
        "Way Redak"
    ],
    "wof:name":"Way Redak",
    "wof:placetype":"locality"
},
  "geometry": {"coordinates":[103.92364999999999,-5.20605],"type":"Point"}
}