{
  "type": "Feature",
  "properties": {
    "gn:admin1_code":"0.0",
    "gn:asciiname":"Batupayung",
    "gn:cc2":"ID",
    "gn:country_code":"ID",
    "gn:dem":3,
    "gn:feature_class":"P",
    "gn:feature_code":"PPL",
    "gn:name":"Batupayung",
    "gn:population":0,
    "gn:timezone":"Asia/Pontianak",
    "iso:country":"ID",
    "name:und_x_variant":[
        "Batoepajoeng",
        "Batupajung",
        "Batupayung"
    ],
    "wof:lang_x_official":[
        "ind"
    ],
    "wof:lang_x_spoken":[
        "ind",
        "eng"
    ],
    "wof:name":"Batupayung",
    "wof:placetype":"locality"
},
  "geometry": {"coordinates":[108.86667,0.78333],"type":"Point"}
}