{
  "type": "Feature",
  "properties": {
    "gn:admin1_code":"30.0",
    "gn:asciiname":"Cimanggu",
    "gn:country_code":"ID",
    "gn:dem":409,
    "gn:feature_class":"P",
    "gn:feature_code":"PPL",
    "gn:name":"Cimanggu",
    "gn:population":0,
    "gn:timezone":"Asia/Jakarta",
    "iso:country":"ID",
    "name:ind_x_preferred":[
        "Cimanggu"
    ],
    "name:und_x_variant":[
        "Tjimanggoe Satu"
    ],
    "wof:lang_x_official":[
        "ind"
    ],
    "wof:lang_x_spoken":[
        "ind",
        "eng"
    ],
    "wof:name":"Cimanggu",
    "wof:placetype":"locality"
},
  "geometry": {"coordinates":[108.167,-7.3391],"type":"Point"}
}