{
  "type": "Feature",
  "properties": {
    "gn:admin1_code":"30",
    "gn:asciiname":"Caringin",
    "gn:cc2":"ID",
    "gn:country_code":"ID",
    "gn:dem":714,
    "gn:feature_class":"P",
    "gn:feature_code":"PPL",
    "gn:name":"Caringin",
    "gn:population":0,
    "gn:timezone":"Asia/Jakarta",
    "iso:country":"ID",
    "name:und_x_variant":[
        "Tjingtjin 1",
        "Cingcin Satu",
        "Caringin"
    ],
    "wof:lang_x_official":[
        "ind"
    ],
    "wof:lang_x_spoken":[
        "ind",
        "eng"
    ],
    "wof:name":"Caringin",
    "wof:placetype":"locality"
},
  "geometry": {"coordinates":[107.52639000000001,-7.01833],"type":"Point"}
}