{
  "type": "Feature",
  "properties": {
    "gn:admin1_code":"7",
    "gn:asciiname":"Nogosari",
    "gn:country_code":"ID",
    "gn:dem":302,
    "gn:feature_class":"P",
    "gn:feature_code":"PPL",
    "gn:name":"Nogosari",
    "gn:population":0,
    "gn:timezone":"Asia/Jakarta",
    "iso:country":"ID",
    "name:ind_x_preferred":[
        "Nogosari"
    ],
    "wof:name":"Nogosari",
    "wof:placetype":"locality"
},
  "geometry": {"coordinates":[110.84180000000001,-6.6854],"type":"Point"}
}