{
  "type": "Feature",
  "properties": {
    "gn:admin1_code":"37",
    "gn:asciiname":"Sarangunggang",
    "gn:country_code":"ID",
    "gn:dem":66,
    "gn:feature_class":"P",
    "gn:feature_code":"PPL",
    "gn:name":"Sarangunggang",
    "gn:population":0,
    "gn:timezone":"Asia/Jakarta",
    "iso:country":"ID",
    "name:ind_x_preferred":[
        "Sarangunggang"
    ],
    "wof:name":"Sarangunggang",
    "wof:placetype":"locality"
},
  "geometry": {"coordinates":[101.7591,0.1822],"type":"Point"}
}