{
  "type": "Feature",
  "properties": {
    "gn:admin1_code":"7.0",
    "gn:asciiname":"Purbosari",
    "gn:country_code":"ID",
    "gn:dem":15,
    "gn:feature_class":"P",
    "gn:feature_code":"PPL",
    "gn:name":"Purbosari",
    "gn:population":0,
    "gn:timezone":"Asia/Jakarta",
    "iso:country":"ID",
    "name:ind_x_preferred":[
        "Purbosari"
    ],
    "wof:name":"Purbosari",
    "wof:placetype":"locality"
},
  "geometry": {"coordinates":[108.7239,-7.4351],"type":"Point"}
}