{
  "type": "Feature",
  "properties": {
    "gn:admin1_code":"17.0",
    "gn:asciiname":"Ndawa Dalam",
    "gn:country_code":"ID",
    "gn:dem":67,
    "gn:feature_class":"P",
    "gn:feature_code":"PPL",
    "gn:name":"Ndawa Dalam",
    "gn:population":0,
    "gn:timezone":"Asia/Makassar",
    "iso:country":"ID",
    "name:ind_x_preferred":[
        "Ndawa Dalam"
    ],
    "wof:name":"Ndawa Dalam",
    "wof:placetype":"locality"
},
  "geometry": {"coordinates":[118.8425,-8.3161],"type":"Point"}
}