{
  "type": "Feature",
  "properties": {
    "gn:admin1_code":"30",
    "gn:asciiname":"Pulopasir",
    "gn:country_code":"ID",
    "gn:dem":13,
    "gn:feature_class":"P",
    "gn:feature_code":"PPL",
    "gn:name":"Pulopasir",
    "gn:population":0,
    "gn:timezone":"Asia/Jakarta",
    "iso:country":"ID",
    "name:ind_x_preferred":[
        "Pulopasir"
    ],
    "name:und_x_variant":[
        "Pulopisang"
    ],
    "wof:name":"Pulopasir",
    "wof:placetype":"locality"
},
  "geometry": {"coordinates":[107.18694000000001,-6.20806],"type":"Point"}
}