{
  "type": "Feature",
  "properties": {
    "gn:admin1_code":"8.0",
    "gn:asciiname":"Kapas",
    "gn:country_code":"ID",
    "gn:dem":54,
    "gn:feature_class":"P",
    "gn:feature_code":"PPL",
    "gn:name":"Kapas",
    "gn:population":0,
    "gn:timezone":"Asia/Jakarta",
    "iso:country":"ID",
    "name:ceb_x_preferred":[
        "Kapas"
    ],
    "name:hun_x_preferred":[
        "Kap\u00e1s"
    ],
    "name:ind_x_preferred":[
        "Kapas"
    ],
    "name:nld_x_preferred":[
        "Kapas"
    ],
    "name:swe_x_preferred":[
        "Kapas"
    ],
    "wof:lang_x_official":[
        "ind"
    ],
    "wof:lang_x_spoken":[
        "ind",
        "eng"
    ],
    "wof:name":"Kapas",
    "wof:placetype":"locality"
},
  "geometry": {"coordinates":[111.92919999999999,-7.6104],"type":"Point"}
}