{
  "type": "Feature",
  "properties": {
    "gn:admin1_code":"0.0",
    "gn:asciiname":"Riang Bowu",
    "gn:cc2":"ID",
    "gn:country_code":"ID",
    "gn:dem":217,
    "gn:feature_class":"P",
    "gn:feature_code":"PPL",
    "gn:name":"Riang Bowu",
    "gn:population":0,
    "gn:timezone":"Asia/Makassar",
    "iso:country":"ID",
    "name:und_x_variant":[
        "Riang Bowoe",
        "Riang Bowu"
    ],
    "wof:lang_x_official":[
        "ind"
    ],
    "wof:lang_x_spoken":[
        "ind",
        "eng"
    ],
    "wof:name":"Riang Bowu",
    "wof:placetype":"locality"
},
  "geometry": {"coordinates":[118.88333,-8.56667],"type":"Point"}
}