{
  "type": "Feature",
  "properties": {
    "gn:admin1_code":"10",
    "gn:asciiname":"Pringwatan",
    "gn:country_code":"ID",
    "gn:dem":283,
    "gn:feature_class":"P",
    "gn:feature_code":"PPL",
    "gn:name":"Pringwatan",
    "gn:population":0,
    "gn:timezone":"Asia/Jakarta",
    "iso:country":"ID",
    "name:ind_x_preferred":[
        "Pringwatan"
    ],
    "wof:name":"Pringwatan",
    "wof:placetype":"locality"
},
  "geometry": {"coordinates":[110.44777999999999,-8.0375],"type":"Point"}
}