{
  "type": "Feature",
  "properties": {
    "gn:admin1_code":"30.0",
    "gn:asciiname":"Gandrung",
    "gn:country_code":"ID",
    "gn:dem":413,
    "gn:feature_class":"P",
    "gn:feature_code":"PPL",
    "gn:name":"Gandrung",
    "gn:population":0,
    "gn:timezone":"Asia/Jakarta",
    "iso:country":"ID",
    "name:ind_x_preferred":[
        "Gandrung"
    ],
    "name:ind_x_variant":[
        "Gandrung Banyuwangi"
    ],
    "name:und_x_variant":[
        "Gandroeng"
    ],
    "wof:name":"Gandrung",
    "wof:placetype":"locality"
},
  "geometry": {"coordinates":[108.14190000000001,-7.3452],"type":"Point"}
}