{
  "type": "Feature",
  "properties": {
    "gn:admin1_code":"30",
    "gn:asciiname":"Manggis Girang",
    "gn:country_code":"ID",
    "gn:dem":592,
    "gn:feature_class":"P",
    "gn:feature_code":"PPL",
    "gn:name":"Manggis Girang",
    "gn:population":0,
    "gn:timezone":"Asia/Jakarta",
    "iso:country":"ID",
    "name:ind_x_preferred":[
        "Manggis Girang"
    ],
    "wof:name":"Manggis Girang",
    "wof:placetype":"locality"
},
  "geometry": {"coordinates":[106.815,-6.77333],"type":"Point"}
}