{
  "type": "Feature",
  "properties": {
    "gn:admin1_code":"7",
    "gn:asciiname":"Pejambon",
    "gn:country_code":"ID",
    "gn:dem":19,
    "gn:feature_class":"P",
    "gn:feature_code":"PPL",
    "gn:name":"Pejambon",
    "gn:population":0,
    "gn:timezone":"Asia/Jakarta",
    "iso:country":"ID",
    "name:ind_x_preferred":[
        "Pejambon"
    ],
    "wof:name":"Pejambon",
    "wof:placetype":"locality"
},
  "geometry": {"coordinates":[109.65094000000001,-6.95654],"type":"Point"}
}