{
  "type": "Feature",
  "properties": {
    "gn:admin1_code":"8",
    "gn:asciiname":"Kolla",
    "gn:country_code":"ID",
    "gn:dem":36,
    "gn:feature_class":"P",
    "gn:feature_code":"PPL",
    "gn:name":"Kolla",
    "gn:population":0,
    "gn:timezone":"Asia/Jakarta",
    "iso:country":"ID",
    "name:ceb_x_preferred":[
        "Kolla"
    ],
    "name:ind_x_preferred":[
        "Kolla"
    ],
    "name:nno_x_preferred":[
        "Kolla"
    ],
    "name:nor_x_preferred":[
        "Kolla"
    ],
    "wof:name":"Kolla",
    "wof:placetype":"locality"
},
  "geometry": {"coordinates":[113.0656,-7.1019],"type":"Point"}
}