{
  "type": "Feature",
  "properties": {
    "gn:admin1_code":"17.0",
    "gn:asciiname":"Solohidek",
    "gn:country_code":"ID",
    "gn:dem":227,
    "gn:feature_class":"P",
    "gn:feature_code":"PPL",
    "gn:name":"Solohidek",
    "gn:population":0,
    "gn:timezone":"Asia/Makassar",
    "iso:country":"ID",
    "name:ind_x_preferred":[
        "Solohidek"
    ],
    "wof:name":"Solohidek",
    "wof:placetype":"locality"
},
  "geometry": {"coordinates":[116.2453,-8.3171],"type":"Point"}
}