{
  "type": "Feature",
  "properties": {
    "gn:admin1_code":"8",
    "gn:asciiname":"Losarikrajan",
    "gn:country_code":"ID",
    "gn:dem":35,
    "gn:feature_class":"P",
    "gn:feature_code":"PPL",
    "gn:name":"Losarikrajan",
    "gn:population":0,
    "gn:timezone":"Asia/Jakarta",
    "iso:country":"ID",
    "name:ind_x_preferred":[
        "Losarikrajan"
    ],
    "wof:name":"Losarikrajan",
    "wof:placetype":"locality"
},
  "geometry": {"coordinates":[112.2291,-7.4541],"type":"Point"}
}