{
  "type": "Feature",
  "properties": {
    "gn:admin1_code":"26",
    "gn:asciiname":"Tornagodang",
    "gn:country_code":"ID",
    "gn:dem":1045,
    "gn:feature_class":"P",
    "gn:feature_code":"PPL",
    "gn:name":"Tornagodang",
    "gn:population":0,
    "gn:timezone":"Asia/Jakarta",
    "iso:country":"ID",
    "name:ind_x_preferred":[
        "Tornagodang"
    ],
    "wof:name":"Tornagodang",
    "wof:placetype":"locality"
},
  "geometry": {"coordinates":[99.14100000000001,2.2988],"type":"Point"}
}