{
  "type": "Feature",
  "properties": {
    "gn:admin1_code":"7.0",
    "gn:asciiname":"Druju",
    "gn:country_code":"ID",
    "gn:dem":639,
    "gn:feature_class":"P",
    "gn:feature_code":"PPL",
    "gn:name":"Druju",
    "gn:population":0,
    "gn:timezone":"Asia/Jakarta",
    "iso:country":"ID",
    "wof:name":"Druju",
    "wof:placetype":"locality"
},
  "geometry": {"coordinates":[110.14888999999999,-7.25889],"type":"Point"}
}