{
  "type": "Feature",
  "properties": {
    "gn:admin1_code":"1.0",
    "gn:asciiname":"Lhok Jok",
    "gn:country_code":"ID",
    "gn:dem":67,
    "gn:feature_class":"P",
    "gn:feature_code":"PPL",
    "gn:name":"Lhok Jok",
    "gn:population":0,
    "gn:timezone":"Asia/Jakarta",
    "iso:country":"ID",
    "name:ind_x_preferred":[
        "Lhok Jok"
    ],
    "name:und_x_variant":[
        "Lhokdjok"
    ],
    "wof:name":"Lhok Jok",
    "wof:placetype":"locality"
},
  "geometry": {"coordinates":[96.9046,5.1292],"type":"Point"}
}