{
  "type": "Feature",
  "properties": {
    "gn:admin1_code":"30.0",
    "gn:asciiname":"Mendakak",
    "gn:country_code":"ID",
    "gn:dem":700,
    "gn:feature_class":"P",
    "gn:feature_code":"PPL",
    "gn:name":"Mendakak",
    "gn:population":0,
    "gn:timezone":"Asia/Jakarta",
    "iso:country":"ID",
    "name:ind_x_preferred":[
        "Mendakak"
    ],
    "name:und_x_variant":[
        "Mendakaki"
    ],
    "wof:lang_x_official":[
        "ind"
    ],
    "wof:lang_x_spoken":[
        "ind",
        "eng"
    ],
    "wof:name":"Mendakak",
    "wof:placetype":"locality"
},
  "geometry": {"coordinates":[108.2353,-7.0939],"type":"Point"}
}