{
  "type": "Feature",
  "properties": {
    "gn:admin1_code":"8",
    "gn:asciiname":"Krajan Satu Dawuan Wetan",
    "gn:country_code":"ID",
    "gn:dem":32,
    "gn:feature_class":"P",
    "gn:feature_code":"PPL",
    "gn:name":"Krajan Satu Dawuan Wetan",
    "gn:population":0,
    "gn:timezone":"Asia/Jakarta",
    "iso:country":"ID",
    "name:ind_x_preferred":[
        "Krajan Satu Dawuan Wetan"
    ],
    "name:ind_x_variant":[
        "Krajan Satu"
    ],
    "wof:name":"Krajan Satu Dawuan Wetan",
    "wof:placetype":"locality"
},
  "geometry": {"coordinates":[113.2795,-8.1457],"type":"Point"}
}