{
  "type": "Feature",
  "properties": {
    "gn:admin1_code":"26",
    "gn:asciiname":"Tumpatannibung Tiga",
    "gn:country_code":"ID",
    "gn:dem":13,
    "gn:feature_class":"P",
    "gn:feature_code":"PPL",
    "gn:name":"Tumpatannibung Tiga",
    "gn:population":0,
    "gn:timezone":"Asia/Jakarta",
    "iso:country":"ID",
    "name:ind_x_preferred":[
        "Tumpatannibung Tiga"
    ],
    "name:und_x_variant":[
        "Tumpatannibung 3"
    ],
    "wof:name":"Tumpatannibung Tiga",
    "wof:placetype":"locality"
},
  "geometry": {"coordinates":[98.81381,3.5929],"type":"Point"}
}