{
  "type": "Feature",
  "properties": {
    "gn:admin1_code":"30",
    "gn:asciiname":"Daraham",
    "gn:country_code":"ID",
    "gn:dem":47,
    "gn:feature_class":"P",
    "gn:feature_code":"PPL",
    "gn:name":"Daraham",
    "gn:population":0,
    "gn:timezone":"Asia/Jakarta",
    "iso:country":"ID",
    "name:ind_x_preferred":[
        "Daraham"
    ],
    "name:und_x_variant":[
        "Darakam 1",
        "Darakam Satu",
        "Darakam 2",
        "Darakam Dua"
    ],
    "wof:lang_x_official":[
        "ind"
    ],
    "wof:lang_x_spoken":[
        "ind",
        "eng"
    ],
    "wof:name":"Daraham",
    "wof:placetype":"locality"
},
  "geometry": {"coordinates":[106.48639,-6.30056],"type":"Point"}
}