{
  "type": "Feature",
  "properties": {
    "gn:admin1_code":"38",
    "gn:asciiname":"Monte",
    "gn:country_code":"ID",
    "gn:dem":822,
    "gn:feature_class":"P",
    "gn:feature_code":"PPL",
    "gn:name":"Monte",
    "gn:population":0,
    "gn:timezone":"Asia/Makassar",
    "iso:country":"ID",
    "name:ind_x_preferred":[
        "Monte"
    ],
    "wof:name":"Monte",
    "wof:placetype":"locality"
},
  "geometry": {"coordinates":[120.06319999999999,-5.3428],"type":"Point"}
}