{
  "type": "Feature",
  "properties": {
    "gn:admin1_code":"18.0",
    "gn:asciiname":"Neco",
    "gn:country_code":"ID",
    "gn:dem":506,
    "gn:feature_class":"P",
    "gn:feature_code":"PPL",
    "gn:name":"Neco",
    "gn:population":0,
    "gn:timezone":"Asia/Makassar",
    "iso:country":"ID",
    "name:ara_x_preferred":[
        "\u0646\u064a\u0643\u0648 \u0645\u0627\u0631\u062a\u064a\u0646\u064a\u0632"
    ],
    "name:cat_x_preferred":[
        "Manoel Nunes"
    ],
    "name:deu_x_preferred":[
        "Manuel Nunes"
    ],
    "name:est_x_preferred":[
        "Neco"
    ],
    "name:fas_x_preferred":[
        "\u0646\u06a9\u0648"
    ],
    "name:fra_x_preferred":[
        "Neco"
    ],
    "name:ind_x_preferred":[
        "Neco"
    ],
    "name:ita_x_preferred":[
        "Neco"
    ],
    "name:nld_x_preferred":[
        "Manuel Nunes"
    ],
    "name:pol_x_preferred":[
        "Neco"
    ],
    "name:por_x_preferred":[
        "Manuel Nunes"
    ],
    "name:rus_x_preferred":[
        "\u041d\u0435\u043a\u043e"
    ],
    "name:spa_x_preferred":[
        "Manoel Nunes"
    ],
    "name:tgk_x_preferred":[
        "\u041d\u0435\u043a\u043e"
    ],
    "wof:name":"Neco",
    "wof:placetype":"locality"
},
  "geometry": {"coordinates":[121.1811,-8.762],"type":"Point"}
}