{
  "type": "Feature",
  "properties": {
    "gn:admin1_code":"38",
    "gn:asciiname":"Kulumpa",
    "gn:country_code":"ID",
    "gn:dem":16,
    "gn:feature_class":"P",
    "gn:feature_code":"PPL",
    "gn:name":"Kulumpa",
    "gn:population":0,
    "gn:timezone":"Asia/Makassar",
    "iso:country":"ID",
    "name:ind_x_preferred":[
        "Kulumpa"
    ],
    "wof:name":"Kulumpa",
    "wof:placetype":"locality"
},
  "geometry": {"coordinates":[119.44410000000001,-5.413],"type":"Point"}
}