{
  "type": "Feature",
  "properties": {
    "gn:admin1_code":"30.0",
    "gn:asciiname":"Kampungasem",
    "gn:cc2":"ID",
    "gn:country_code":"ID",
    "gn:dem":4,
    "gn:feature_class":"P",
    "gn:feature_code":"PPL",
    "gn:name":"Kampungasem",
    "gn:population":0,
    "gn:timezone":"Asia/Jakarta",
    "iso:country":"ID",
    "name:und_x_variant":[
        "Kampoengasem 1",
        "Kampungasem Satu",
        "Kampungasem 1",
        "Kampungasem"
    ],
    "wof:name":"Kampungasem",
    "wof:placetype":"locality"
},
  "geometry": {"coordinates":[106.65667000000001,-6.0575],"type":"Point"}
}