{
  "type": "Feature",
  "properties": {
    "gn:admin1_code":"39.0",
    "gn:asciiname":"Tinduwi",
    "gn:country_code":"ID",
    "gn:dem":558,
    "gn:feature_class":"P",
    "gn:feature_code":"PPL",
    "gn:name":"Tinduwi",
    "gn:population":0,
    "gn:timezone":"Asia/Jayapura",
    "iso:country":"ID",
    "name:ind_x_preferred":[
        "Tinduwi"
    ],
    "name:und_x_variant":[
        "Tindawi"
    ],
    "wof:name":"Tinduwi",
    "wof:placetype":"locality"
},
  "geometry": {"coordinates":[133.01349999999999,-0.8082],"type":"Point"}
}