{
  "type": "Feature",
  "properties": {
    "gn:admin1_code":"8.0",
    "gn:asciiname":"Gempeng",
    "gn:country_code":"ID",
    "gn:dem":9,
    "gn:feature_class":"P",
    "gn:feature_code":"PPL",
    "gn:name":"Gempeng",
    "gn:population":0,
    "gn:timezone":"Asia/Jakarta",
    "iso:country":"ID",
    "name:ind_x_preferred":[
        "Gempeng"
    ],
    "wof:name":"Gempeng",
    "wof:placetype":"locality"
},
  "geometry": {"coordinates":[112.79089999999999,-7.5971],"type":"Point"}
}