{
  "type": "Feature",
  "properties": {
    "gn:admin1_code":"18.0",
    "gn:asciiname":"Ndapakali",
    "gn:country_code":"ID",
    "gn:dem":511,
    "gn:feature_class":"P",
    "gn:feature_code":"PPL",
    "gn:name":"Ndapakali",
    "gn:population":0,
    "gn:timezone":"Asia/Makassar",
    "iso:country":"ID",
    "name:ind_x_preferred":[
        "Ndapakali"
    ],
    "wof:name":"Ndapakali",
    "wof:placetype":"locality"
},
  "geometry": {"coordinates":[120.2248,-9.9732],"type":"Point"}
}