{
  "type": "Feature",
  "properties": {
    "gn:admin1_code":"1",
    "gn:asciiname":"Durin",
    "gn:country_code":"ID",
    "gn:dem":915,
    "gn:feature_class":"P",
    "gn:feature_code":"PPL",
    "gn:name":"Durin",
    "gn:population":0,
    "gn:timezone":"Asia/Jakarta",
    "iso:country":"ID",
    "name:ind_x_preferred":[
        "Durin"
    ],
    "wof:name":"Durin",
    "wof:placetype":"locality"
},
  "geometry": {"coordinates":[97.3432,3.9982],"type":"Point"}
}