{
  "type": "Feature",
  "properties": {
    "gn:admin1_code":"1",
    "gn:asciiname":"Durin",
    "gn:country_code":"ID",
    "gn:dem":915,
    "gn:feature_class":"P",
    "gn:feature_code":"PPL",
    "gn:name":"Durin",
    "gn:population":0,
    "gn:timezone":"Asia/Jakarta",
    "iso:country":"ID",
    "name:ces_x_preferred":[
        "Durin"
    ],
    "name:est_x_preferred":[
        "Durin"
    ],
    "name:fas_x_preferred":[
        "\u062f\u0648\u0631\u06cc\u0646"
    ],
    "name:fra_x_preferred":[
        "Durin"
    ],
    "name:ind_x_preferred":[
        "Durin"
    ],
    "name:ita_x_preferred":[
        "Durin"
    ],
    "name:kor_x_preferred":[
        "\ub450\ub9b0"
    ],
    "name:nld_x_preferred":[
        "Durin"
    ],
    "name:nor_x_preferred":[
        "Durin"
    ],
    "name:pol_x_preferred":[
        "Durin"
    ],
    "name:por_x_preferred":[
        "Durin"
    ],
    "name:ron_x_preferred":[
        "Durin"
    ],
    "name:rus_x_preferred":[
        "\u0414\u0443\u0440\u0438\u043d"
    ],
    "name:scn_x_preferred":[
        "Durin"
    ],
    "name:tha_x_preferred":[
        "\u0e14\u0e39\u0e23\u0e34\u0e19"
    ],
    "name:tur_x_preferred":[
        "Durin"
    ],
    "name:zho_x_preferred":[
        "\u90fd\u9748"
    ],
    "wof:lang_x_official":[
        "ind"
    ],
    "wof:lang_x_spoken":[
        "ind",
        "eng"
    ],
    "wof:name":"Durin",
    "wof:placetype":"locality"
},
  "geometry": {"coordinates":[97.3432,3.9982],"type":"Point"}
}