{
  "type": "Feature",
  "properties": {
    "gn:admin1_code":"21.0",
    "gn:asciiname":"Tompe",
    "gn:country_code":"ID",
    "gn:dem":10,
    "gn:feature_class":"P",
    "gn:feature_code":"PPL",
    "gn:name":"Tompe",
    "gn:population":0,
    "gn:timezone":"Asia/Makassar",
    "iso:country":"ID",
    "name:ind_x_preferred":[
        "Tompe"
    ],
    "name:und_x_variant":[
        "Tompo"
    ],
    "wof:name":"Tompe",
    "wof:placetype":"locality"
},
  "geometry": {"coordinates":[119.8109,-0.2108],"type":"Point"}
}