{
  "type": "Feature",
  "properties": {
    "gn:admin1_code":"4.0",
    "gn:asciiname":"Utanpanjang",
    "gn:country_code":"ID",
    "gn:dem":4,
    "gn:feature_class":"P",
    "gn:feature_code":"PPL",
    "gn:name":"Utanpanjang",
    "gn:population":0,
    "gn:timezone":"Asia/Jakarta",
    "iso:country":"ID",
    "name:ind_x_preferred":[
        "Utanpanjang"
    ],
    "name:und_x_variant":[
        "Oetanpandjang",
        "Utanpatang",
        "Utanpandjang"
    ],
    "wof:lang_x_official":[
        "ind"
    ],
    "wof:lang_x_spoken":[
        "ind",
        "eng"
    ],
    "wof:name":"Utanpanjang",
    "wof:placetype":"locality"
},
  "geometry": {"coordinates":[106.8549,-6.1652],"type":"Point"}
}