{
  "type": "Feature",
  "properties": {
    "gn:admin1_code":"30.0",
    "gn:asciiname":"Emblegan",
    "gn:country_code":"ID",
    "gn:dem":505,
    "gn:feature_class":"P",
    "gn:feature_code":"PPLA4",
    "gn:name":"Emblegan",
    "gn:population":0,
    "gn:timezone":"Asia/Jakarta",
    "iso:country":"ID",
    "name:ind_x_preferred":[
        "Emblegan"
    ],
    "wof:name":"Emblegan",
    "wof:placetype":"locality"
},
  "geometry": {"coordinates":[108.4212,-7.1325],"type":"Point"}
}