{
  "type": "Feature",
  "properties": {
    "gn:admin1_code":"8",
    "gn:asciiname":"Mojokopek",
    "gn:country_code":"ID",
    "gn:dem":171,
    "gn:feature_class":"P",
    "gn:feature_code":"PPL",
    "gn:name":"Mojokopek",
    "gn:population":0,
    "gn:timezone":"Asia/Jakarta",
    "iso:country":"ID",
    "name:ind_x_preferred":[
        "Mojokopek"
    ],
    "wof:name":"Mojokopek",
    "wof:placetype":"locality"
},
  "geometry": {"coordinates":[111.19306,-7.44972],"type":"Point"}
}