{
  "type": "Feature",
  "properties": {
    "gn:admin1_code":"7",
    "gn:asciiname":"Kuto",
    "gn:country_code":"ID",
    "gn:dem":325,
    "gn:feature_class":"P",
    "gn:feature_code":"PPL",
    "gn:name":"Kuto",
    "gn:population":0,
    "gn:timezone":"Asia/Jakarta",
    "iso:country":"ID",
    "name:ind_x_preferred":[
        "Kuto"
    ],
    "wof:name":"Kuto",
    "wof:placetype":"locality"
},
  "geometry": {"coordinates":[111.04917,-7.53778],"type":"Point"}
}