{
  "type": "Feature",
  "properties": {
    "gn:admin1_code":"7",
    "gn:asciiname":"Nglayapan",
    "gn:country_code":"ID",
    "gn:dem":36,
    "gn:feature_class":"P",
    "gn:feature_code":"PPL",
    "gn:name":"Nglayapan",
    "gn:population":0,
    "gn:timezone":"Asia/Jakarta",
    "iso:country":"ID",
    "name:ind_x_preferred":[
        "Nglayapan"
    ],
    "wof:name":"Nglayapan",
    "wof:placetype":"locality"
},
  "geometry": {"coordinates":[110.9806,-7.0961],"type":"Point"}
}