{
  "type": "Feature",
  "properties": {
    "gn:admin1_code":"30.0",
    "gn:asciiname":"Rancapaku",
    "gn:country_code":"ID",
    "gn:dem":596,
    "gn:feature_class":"P",
    "gn:feature_code":"PPL",
    "gn:name":"Rancapaku",
    "gn:population":0,
    "gn:timezone":"Asia/Jakarta",
    "iso:country":"ID",
    "name:ind_x_preferred":[
        "Rancapaku"
    ],
    "name:und_x_variant":[
        "Rantjapakoe"
    ],
    "wof:name":"Rancapaku",
    "wof:placetype":"locality"
},
  "geometry": {"coordinates":[107.9556,-7.0335],"type":"Point"}
}