{
  "type": "Feature",
  "properties": {
    "gn:admin1_code":"30",
    "gn:asciiname":"Tenjolaya Girang",
    "gn:country_code":"ID",
    "gn:dem":737,
    "gn:feature_class":"P",
    "gn:feature_code":"PPL",
    "gn:name":"Tenjolaya Girang",
    "gn:population":0,
    "gn:timezone":"Asia/Jakarta",
    "iso:country":"ID",
    "name:ind_x_preferred":[
        "Tenjolaya Girang"
    ],
    "wof:name":"Tenjolaya Girang",
    "wof:placetype":"locality"
},
  "geometry": {"coordinates":[106.74444,-6.75944],"type":"Point"}
}