{
  "type": "Feature",
  "properties": {
    "gn:admin1_code":"15.0",
    "gn:asciiname":"Umbulan Waisido",
    "gn:country_code":"ID",
    "gn:dem":22,
    "gn:feature_class":"P",
    "gn:feature_code":"PPL",
    "gn:name":"Umbulan Waisido",
    "gn:population":0,
    "gn:timezone":"Asia/Jakarta",
    "iso:country":"ID",
    "name:ind_x_preferred":[
        "Umbulan Waisido"
    ],
    "name:ind_x_variant":[
        "Umbulan Waysido",
        "Oemboelan Waisido",
        "Umbulanwaisido"
    ],
    "wof:lang_x_official":[
        "ind"
    ],
    "wof:lang_x_spoken":[
        "ind",
        "eng"
    ],
    "wof:name":"Umbulan Waisido",
    "wof:placetype":"locality"
},
  "geometry": {"coordinates":[105.01326,-4.63012],"type":"Point"}
}