{
  "type": "Feature",
  "properties": {
    "gn:admin1_code":"8.0",
    "gn:asciiname":"Bunder",
    "gn:country_code":"ID",
    "gn:dem":7,
    "gn:feature_class":"P",
    "gn:feature_code":"PPLA4",
    "gn:name":"Bunder",
    "gn:population":0,
    "gn:timezone":"Asia/Jakarta",
    "iso:country":"ID",
    "name:deu_x_preferred":[
        "Bunder"
    ],
    "name:fra_x_preferred":[
        "Bonnier"
    ],
    "name:ind_x_preferred":[
        "Bunder"
    ],
    "name:ita_x_preferred":[
        "Bunder"
    ],
    "name:nld_x_preferred":[
        "Bunder"
    ],
    "name:wln_x_preferred":[
        "Boun\u00ee"
    ],
    "wof:name":"Bunder",
    "wof:placetype":"locality"
},
  "geometry": {"coordinates":[113.52967,-7.1867],"type":"Point"}
}