{
  "type": "Feature",
  "properties": {
    "gn:admin1_code":"17",
    "gn:asciiname":"Pancor",
    "gn:country_code":"ID",
    "gn:dem":225,
    "gn:feature_class":"P",
    "gn:feature_code":"PPL",
    "gn:name":"Pancor",
    "gn:population":0,
    "gn:timezone":"Asia/Makassar",
    "iso:country":"ID",
    "name:ind_x_preferred":[
        "Pancor"
    ],
    "wof:name":"Pancor",
    "wof:placetype":"locality"
},
  "geometry": {"coordinates":[116.3122,-8.6834],"type":"Point"}
}