{
  "type": "Feature",
  "properties": {
    "gn:admin1_code":"24.0",
    "gn:asciiname":"Kulam",
    "gn:country_code":"ID",
    "gn:dem":78,
    "gn:feature_class":"P",
    "gn:feature_code":"PPL",
    "gn:name":"Kulam",
    "gn:population":0,
    "gn:timezone":"Asia/Jakarta",
    "iso:country":"ID",
    "name:ben_x_preferred":[
        "\u0995\u09c1\u09b2\u09be\u09ae"
    ],
    "name:ind_x_preferred":[
        "Kulam"
    ],
    "wof:lang_x_official":[
        "ind"
    ],
    "wof:lang_x_spoken":[
        "ind",
        "eng"
    ],
    "wof:name":"Kulam",
    "wof:placetype":"locality"
},
  "geometry": {"coordinates":[100.8032,-1.6508],"type":"Point"}
}