{
  "type": "Feature",
  "properties": {
    "gn:admin1_code":"7.0",
    "gn:asciiname":"Cilamat",
    "gn:country_code":"ID",
    "gn:dem":218,
    "gn:feature_class":"P",
    "gn:feature_code":"PPL",
    "gn:name":"Cilamat",
    "gn:population":0,
    "gn:timezone":"Asia/Jakarta",
    "iso:country":"ID",
    "name:ind_x_preferred":[
        "Cilamat"
    ],
    "wof:name":"Cilamat",
    "wof:placetype":"locality"
},
  "geometry": {"coordinates":[109.59972,-7.37917],"type":"Point"}
}