{
  "type": "Feature",
  "properties": {
    "gn:admin1_code":"30",
    "gn:asciiname":"Ciupih",
    "gn:country_code":"ID",
    "gn:dem":421,
    "gn:feature_class":"P",
    "gn:feature_code":"PPL",
    "gn:name":"Ciupih",
    "gn:population":0,
    "gn:timezone":"Asia/Jakarta",
    "iso:country":"ID",
    "name:ind_x_preferred":[
        "Ciupih"
    ],
    "wof:name":"Ciupih",
    "wof:placetype":"locality"
},
  "geometry": {"coordinates":[108.14388999999998,-6.94778],"type":"Point"}
}