{
  "type": "Feature",
  "properties": {
    "gn:admin1_code":"35",
    "gn:asciiname":"Sungkai",
    "gn:country_code":"ID",
    "gn:dem":20,
    "gn:feature_class":"P",
    "gn:feature_code":"PPL",
    "gn:name":"Sungkai",
    "gn:population":0,
    "gn:timezone":"Asia/Jakarta",
    "iso:country":"ID",
    "name:epo_x_preferred":[
        "Sungkai"
    ],
    "name:ind_x_preferred":[
        "Sungkai"
    ],
    "name:msa_x_preferred":[
        "Sungkai"
    ],
    "wof:lang_x_official":[
        "ind"
    ],
    "wof:lang_x_spoken":[
        "ind",
        "eng"
    ],
    "wof:name":"Sungkai",
    "wof:placetype":"locality"
},
  "geometry": {"coordinates":[106.00834,-2.03348],"type":"Point"}
}