{
  "type": "Feature",
  "properties": {
    "gn:admin1_code":"30",
    "gn:asciiname":"Pamipiran",
    "gn:country_code":"ID",
    "gn:dem":65,
    "gn:feature_class":"P",
    "gn:feature_code":"PPL",
    "gn:name":"Pamipiran",
    "gn:population":0,
    "gn:timezone":"Asia/Jakarta",
    "iso:country":"ID",
    "name:ind_x_preferred":[
        "Pamipiran"
    ],
    "wof:name":"Pamipiran",
    "wof:placetype":"locality"
},
  "geometry": {"coordinates":[107.15361,-6.48667],"type":"Point"}
}