{
  "type": "Feature",
  "properties": {
    "gn:admin1_code":"30",
    "gn:asciiname":"Rajapolah",
    "gn:country_code":"ID",
    "gn:dem":12,
    "gn:feature_class":"P",
    "gn:feature_code":"PPL",
    "gn:name":"Rajapolah",
    "gn:population":0,
    "gn:timezone":"Asia/Jakarta",
    "iso:country":"ID",
    "name:ind_x_preferred":[
        "Rajapolah"
    ],
    "name:jav_x_preferred":[
        "Rajapolah"
    ],
    "name:sun_x_preferred":[
        "Rajapolah"
    ],
    "wof:lang_x_official":[
        "ind"
    ],
    "wof:lang_x_spoken":[
        "ind",
        "eng"
    ],
    "wof:name":"Rajapolah",
    "wof:placetype":"locality"
},
  "geometry": {"coordinates":[107.67528,-6.32139],"type":"Point"}
}