{
  "type": "Feature",
  "properties": {
    "gn:admin1_code":"18.0",
    "gn:asciiname":"Kalembukalogho",
    "gn:country_code":"ID",
    "gn:dem":87,
    "gn:feature_class":"P",
    "gn:feature_code":"PPL",
    "gn:name":"Kalembukalogho",
    "gn:population":0,
    "gn:timezone":"Asia/Makassar",
    "iso:country":"ID",
    "name:ind_x_preferred":[
        "Kalembukalogho"
    ],
    "wof:name":"Kalembukalogho",
    "wof:placetype":"locality"
},
  "geometry": {"coordinates":[119.2534,-9.432],"type":"Point"}
}