{
  "type": "Feature",
  "properties": {
    "gn:admin1_code":"18.0",
    "gn:asciiname":"Rego",
    "gn:country_code":"ID",
    "gn:dem":754,
    "gn:feature_class":"P",
    "gn:feature_code":"PPLA4",
    "gn:name":"Rego",
    "gn:population":0,
    "gn:timezone":"Asia/Makassar",
    "iso:country":"ID",
    "name:ceb_x_preferred":[
        "Rego"
    ],
    "name:deu_x_preferred":[
        "Rego"
    ],
    "name:fra_x_preferred":[
        "Rego"
    ],
    "name:glg_x_preferred":[
        "Rego"
    ],
    "name:ind_x_preferred":[
        "Rego"
    ],
    "name:nld_x_preferred":[
        "Rego"
    ],
    "name:pol_x_preferred":[
        "Rego"
    ],
    "name:por_x_preferred":[
        "Rego"
    ],
    "name:rus_x_preferred":[
        "\u0420\u0435\u0433\u0443"
    ],
    "name:swe_x_preferred":[
        "Rego"
    ],
    "name:ukr_x_preferred":[
        "\u0420\u0435\u0433\u043e"
    ],
    "wof:lang_x_official":[
        "ind"
    ],
    "wof:lang_x_spoken":[
        "ind",
        "eng"
    ],
    "wof:name":"Rego",
    "wof:placetype":"locality"
},
  "geometry": {"coordinates":[120.2565,-8.4266],"type":"Point"}
}