{
  "type": "Feature",
  "properties": {
    "gn:admin1_code":"04",
    "gn:asciiname":"Rawabadakatas",
    "gn:country_code":"ID",
    "gn:dem":5,
    "gn:feature_class":"P",
    "gn:feature_code":"PPL",
    "gn:name":"Rawabadakatas",
    "gn:population":0,
    "gn:timezone":"Asia/Jakarta",
    "iso:country":"ID",
    "wof:name":"Rawabadakatas",
    "wof:placetype":"locality"
},
  "geometry": {"coordinates":[106.89888999999999,-6.11361],"type":"Point"}
}