{
  "type": "Feature",
  "properties": {
    "gn:admin1_code":"15.0",
    "gn:asciiname":"Telukdalam",
    "gn:country_code":"ID",
    "gn:dem":34,
    "gn:feature_class":"P",
    "gn:feature_code":"PPL",
    "gn:name":"Telukdalam",
    "gn:population":0,
    "gn:timezone":"Asia/Jakarta",
    "iso:country":"ID",
    "name:ind_x_preferred":[
        "Telukdalam"
    ],
    "wof:name":"Telukdalam",
    "wof:placetype":"locality"
},
  "geometry": {"coordinates":[105.73515,-5.25729],"type":"Point"}
}