{
  "type": "Feature",
  "properties": {
    "gn:admin1_code":"10",
    "gn:asciiname":"Santan",
    "gn:country_code":"ID",
    "gn:dem":120,
    "gn:feature_class":"P",
    "gn:feature_code":"PPL",
    "gn:name":"Santan",
    "gn:population":0,
    "gn:timezone":"Asia/Jakarta",
    "iso:country":"ID",
    "name:ceb_x_preferred":[
        "Santan"
    ],
    "name:swe_x_preferred":[
        "Santan"
    ],
    "name:tgl_x_preferred":[
        "Santan"
    ],
    "wof:lang_x_official":[
        "ind"
    ],
    "wof:lang_x_spoken":[
        "ind",
        "eng"
    ],
    "wof:name":"Santan",
    "wof:placetype":"locality"
},
  "geometry": {"coordinates":[110.41833,-7.78667],"type":"Point"}
}