{
  "type": "Feature",
  "properties": {
    "gn:admin1_code":"17",
    "gn:asciiname":"Gonjong",
    "gn:country_code":"ID",
    "gn:dem":116,
    "gn:feature_class":"P",
    "gn:feature_code":"PPL",
    "gn:name":"Gonjong",
    "gn:population":0,
    "gn:timezone":"Asia/Makassar",
    "iso:country":"ID",
    "name:ind_x_preferred":[
        "Gonjong"
    ],
    "wof:name":"Gonjong",
    "wof:placetype":"locality"
},
  "geometry": {"coordinates":[116.31570000000001,-8.7878],"type":"Point"}
}