{
  "type": "Feature",
  "properties": {
    "gn:admin1_code":"30.0",
    "gn:asciiname":"Sudimara",
    "gn:country_code":"ID",
    "gn:dem":383,
    "gn:feature_class":"P",
    "gn:feature_code":"PPLA4",
    "gn:name":"Sudimara",
    "gn:population":0,
    "gn:timezone":"Asia/Jakarta",
    "iso:country":"ID",
    "name:ind_x_preferred":[
        "Sudimara"
    ],
    "name:und_x_variant":[
        "Soedimara"
    ],
    "wof:name":"Sudimara",
    "wof:placetype":"locality"
},
  "geometry": {"coordinates":[108.17740000000001,-7.3626],"type":"Point"}
}