{
  "type": "Feature",
  "properties": {
    "gn:admin1_code":"17.0",
    "gn:asciiname":"Karongkeng",
    "gn:country_code":"ID",
    "gn:dem":24,
    "gn:feature_class":"P",
    "gn:feature_code":"PPL",
    "gn:name":"Karongkeng",
    "gn:population":0,
    "gn:timezone":"Asia/Makassar",
    "iso:country":"ID",
    "name:ind_x_preferred":[
        "Karongkeng"
    ],
    "wof:name":"Karongkeng",
    "wof:placetype":"locality"
},
  "geometry": {"coordinates":[118.01690000000001,-8.7389],"type":"Point"}
}