{
  "type": "Feature",
  "properties": {
    "gn:admin1_code":"33.0",
    "gn:asciiname":"Bojongjeureuk",
    "gn:country_code":"ID",
    "gn:dem":11,
    "gn:feature_class":"P",
    "gn:feature_code":"PPL",
    "gn:name":"Bojongjeureuk",
    "gn:population":0,
    "gn:timezone":"Asia/Jakarta",
    "iso:country":"ID",
    "name:ind_x_preferred":[
        "Bojongjeureuk"
    ],
    "wof:name":"Bojongjeureuk",
    "wof:placetype":"locality"
},
  "geometry": {"coordinates":[105.7465,-6.5481],"type":"Point"}
}