{
  "type": "Feature",
  "properties": {
    "gn:admin1_code":"30.0",
    "gn:asciiname":"Cipanengah",
    "gn:country_code":"ID",
    "gn:dem":795,
    "gn:feature_class":"P",
    "gn:feature_code":"PPL",
    "gn:name":"Cipanengah",
    "gn:population":0,
    "gn:timezone":"Asia/Jakarta",
    "iso:country":"ID",
    "name:ind_x_preferred":[
        "Cipanengah"
    ],
    "name:und_x_variant":[
        "Tjipanengah 4"
    ],
    "wof:name":"Cipanengah",
    "wof:placetype":"locality"
},
  "geometry": {"coordinates":[106.66370000000001,-7.1277],"type":"Point"}
}