{
  "type": "Feature",
  "properties": {
    "gn:admin1_code":"30.0",
    "gn:asciiname":"Dukujering",
    "gn:country_code":"ID",
    "gn:dem":29,
    "gn:feature_class":"P",
    "gn:feature_code":"PPL",
    "gn:name":"Dukujering",
    "gn:population":0,
    "gn:timezone":"Asia/Jakarta",
    "iso:country":"ID",
    "name:ind_x_preferred":[
        "Dukujering"
    ],
    "wof:name":"Dukujering",
    "wof:placetype":"locality"
},
  "geometry": {"coordinates":[108.45,-6.72333],"type":"Point"}
}