{
  "type": "Feature",
  "properties": {
    "gn:admin1_code":"10",
    "gn:asciiname":"Dringo",
    "gn:country_code":"ID",
    "gn:dem":232,
    "gn:feature_class":"P",
    "gn:feature_code":"PPL",
    "gn:name":"Dringo",
    "gn:population":0,
    "gn:timezone":"Asia/Jakarta",
    "iso:country":"ID",
    "wof:name":"Dringo",
    "wof:placetype":"locality"
},
  "geometry": {"coordinates":[110.71028,-7.83028],"type":"Point"}
}