{
  "type": "Feature",
  "properties": {
    "gn:admin1_code":"7.0",
    "gn:asciiname":"Pailus",
    "gn:country_code":"ID",
    "gn:dem":6,
    "gn:feature_class":"P",
    "gn:feature_code":"PPL",
    "gn:name":"Pailus",
    "gn:population":0,
    "gn:timezone":"Asia/Jakarta",
    "iso:country":"ID",
    "name:ind_x_preferred":[
        "Pailus"
    ],
    "wof:name":"Pailus",
    "wof:placetype":"locality"
},
  "geometry": {"coordinates":[110.6896,-6.5015],"type":"Point"}
}