{
  "type": "Feature",
  "properties": {
    "gn:admin1_code":"07",
    "gn:asciiname":"Jaten",
    "gn:country_code":"ID",
    "gn:dem":315,
    "gn:feature_class":"P",
    "gn:feature_code":"PPL",
    "gn:name":"Jaten",
    "gn:population":0,
    "gn:timezone":"Asia/Jakarta",
    "iso:country":"ID",
    "name:und_x_variant":[
        "Jaten Satu",
        "Djaten 1",
        "Jaten"
    ],
    "wof:name":"Jaten",
    "wof:placetype":"locality"
},
  "geometry": {"coordinates":[110.69194,-7.38167],"type":"Point"}
}