{
  "type": "Feature",
  "properties": {
    "gn:admin1_code":"18.0",
    "gn:asciiname":"Menanga",
    "gn:country_code":"ID",
    "gn:dem":61,
    "gn:feature_class":"P",
    "gn:feature_code":"PPL",
    "gn:name":"Menanga",
    "gn:population":0,
    "gn:timezone":"Asia/Makassar",
    "iso:country":"ID",
    "name:ind_x_preferred":[
        "Menanga"
    ],
    "wof:name":"Menanga",
    "wof:placetype":"locality"
},
  "geometry": {"coordinates":[122.75879999999999,-8.3705],"type":"Point"}
}