{
  "type": "Feature",
  "properties": {
    "gn:admin1_code":"2",
    "gn:asciiname":"Banjar Tanahdaa",
    "gn:country_code":"ID",
    "gn:dem":1713,
    "gn:feature_class":"P",
    "gn:feature_code":"PPL",
    "gn:name":"Banjar Tanahdaa",
    "gn:population":0,
    "gn:timezone":"Asia/Makassar",
    "iso:country":"ID",
    "name:ind_x_preferred":[
        "Banjar Tanahdaa"
    ],
    "wof:name":"Banjar Tanahdaa",
    "wof:placetype":"locality"
},
  "geometry": {"coordinates":[115.3291,-8.2076],"type":"Point"}
}