{
  "type": "Feature",
  "properties": {
    "gn:admin1_code":"8",
    "gn:asciiname":"Banci",
    "gn:country_code":"ID",
    "gn:dem":21,
    "gn:feature_class":"P",
    "gn:feature_code":"PPL",
    "gn:name":"Banci",
    "gn:population":0,
    "gn:timezone":"Asia/Jakarta",
    "iso:country":"ID",
    "name:ind_x_preferred":[
        "Banci"
    ],
    "wof:name":"Banci",
    "wof:placetype":"locality"
},
  "geometry": {"coordinates":[112.45359999999999,-7.2705],"type":"Point"}
}