{
  "type": "Feature",
  "properties": {
    "gn:admin1_code":"18.0",
    "gn:asciiname":"Baru",
    "gn:country_code":"ID",
    "gn:dem":11,
    "gn:feature_class":"P",
    "gn:feature_code":"PPLA4",
    "gn:name":"Baru",
    "gn:population":0,
    "gn:timezone":"Asia/Makassar",
    "iso:country":"ID",
    "name:ces_x_preferred":[
        "Baru"
    ],
    "name:ind_x_preferred":[
        "Baru"
    ],
    "name:nld_x_preferred":[
        "Baru"
    ],
    "name:spa_x_preferred":[
        "Baru"
    ],
    "wof:name":"Baru",
    "wof:placetype":"locality"
},
  "geometry": {"coordinates":[120.4911,-8.3072],"type":"Point"}
}