{
  "type": "Feature",
  "properties": {
    "gn:admin1_code":"18.0",
    "gn:asciiname":"Siuf",
    "gn:country_code":"ID",
    "gn:dem":51,
    "gn:feature_class":"P",
    "gn:feature_code":"PPL",
    "gn:name":"Siuf",
    "gn:population":0,
    "gn:timezone":"Asia/Makassar",
    "iso:country":"ID",
    "name:ind_x_preferred":[
        "Siuf"
    ],
    "wof:name":"Siuf",
    "wof:placetype":"locality"
},
  "geometry": {"coordinates":[124.00020000000001,-10.2193],"type":"Point"}
}