{
  "type": "Feature",
  "properties": {
    "gn:admin1_code":"38",
    "gn:asciiname":"Baddo",
    "gn:country_code":"ID",
    "gn:dem":6,
    "gn:feature_class":"P",
    "gn:feature_code":"PPL",
    "gn:name":"Baddo",
    "gn:population":0,
    "gn:timezone":"Asia/Makassar",
    "iso:country":"ID",
    "name:ind_x_preferred":[
        "Baddo"
    ],
    "wof:name":"Baddo",
    "wof:placetype":"locality"
},
  "geometry": {"coordinates":[119.45,-5.1353],"type":"Point"}
}