{
  "type": "Feature",
  "properties": {
    "gn:admin1_code":"7.0",
    "gn:asciiname":"Kabuan",
    "gn:country_code":"ID",
    "gn:dem":270,
    "gn:feature_class":"P",
    "gn:feature_code":"PPL",
    "gn:name":"Kabuan",
    "gn:population":0,
    "gn:timezone":"Asia/Jakarta",
    "iso:country":"ID",
    "wof:name":"Kabuan",
    "wof:placetype":"locality"
},
  "geometry": {"coordinates":[110.81,-7.81056],"type":"Point"}
}