{
  "type": "Feature",
  "properties": {
    "gn:admin1_code":"8",
    "gn:asciiname":"Guluran",
    "gn:country_code":"ID",
    "gn:dem":149,
    "gn:feature_class":"P",
    "gn:feature_code":"PPL",
    "gn:name":"Guluran",
    "gn:population":0,
    "gn:timezone":"Asia/Jakarta",
    "iso:country":"ID",
    "name:ind_x_preferred":[
        "Guluran"
    ],
    "wof:name":"Guluran",
    "wof:placetype":"locality"
},
  "geometry": {"coordinates":[111.55289999999999,-7.7344],"type":"Point"}
}