{
  "type": "Feature",
  "properties": {
    "gn:admin1_code":"24.0",
    "gn:asciiname":"Buahdarat",
    "gn:country_code":"ID",
    "gn:dem":714,
    "gn:feature_class":"P",
    "gn:feature_code":"PPL",
    "gn:name":"Buahdarat",
    "gn:population":0,
    "gn:timezone":"Asia/Jakarta",
    "iso:country":"ID",
    "name:ind_x_preferred":[
        "Buahdarat"
    ],
    "wof:name":"Buahdarat",
    "wof:placetype":"locality"
},
  "geometry": {"coordinates":[101.02719999999999,-1.0361],"type":"Point"}
}