{
  "type": "Feature",
  "properties": {
    "gn:admin1_code":"30",
    "gn:asciiname":"Pasirhayam",
    "gn:country_code":"ID",
    "gn:dem":354,
    "gn:feature_class":"P",
    "gn:feature_code":"PPL",
    "gn:name":"Pasirhayam",
    "gn:population":0,
    "gn:timezone":"Asia/Jakarta",
    "iso:country":"ID",
    "name:ind_x_preferred":[
        "Pasirhayam"
    ],
    "wof:name":"Pasirhayam",
    "wof:placetype":"locality"
},
  "geometry": {"coordinates":[107.18416999999999,-6.83556],"type":"Point"}
}