{
  "type": "Feature",
  "properties": {
    "gn:admin1_code":"24.0",
    "gn:asciiname":"Pematangbukaras",
    "gn:country_code":"ID",
    "gn:dem":371,
    "gn:feature_class":"P",
    "gn:feature_code":"PPL",
    "gn:name":"Pematangbukaras",
    "gn:population":0,
    "gn:timezone":"Asia/Jakarta",
    "iso:country":"ID",
    "name:ind_x_preferred":[
        "Pematangbukaras"
    ],
    "wof:name":"Pematangbukaras",
    "wof:placetype":"locality"
},
  "geometry": {"coordinates":[101.0628,-0.7598],"type":"Point"}
}