{
  "type": "Feature",
  "properties": {
    "gn:admin1_code":"8.0",
    "gn:asciiname":"Jabonrowo",
    "gn:country_code":"ID",
    "gn:dem":13,
    "gn:feature_class":"P",
    "gn:feature_code":"PPL",
    "gn:name":"Jabonrowo",
    "gn:population":0,
    "gn:timezone":"Asia/Jakarta",
    "iso:country":"ID",
    "name:ind_x_preferred":[
        "Jabonrowo"
    ],
    "wof:name":"Jabonrowo",
    "wof:placetype":"locality"
},
  "geometry": {"coordinates":[112.62350000000001,-7.5108],"type":"Point"}
}