{
  "type": "Feature",
  "properties": {
    "gn:admin1_code":"38.0",
    "gn:asciiname":"Patommo",
    "gn:country_code":"ID",
    "gn:dem":50,
    "gn:feature_class":"P",
    "gn:feature_code":"PPL",
    "gn:name":"Patommo",
    "gn:population":0,
    "gn:timezone":"Asia/Makassar",
    "iso:country":"ID",
    "name:ind_x_preferred":[
        "Patommo"
    ],
    "wof:name":"Patommo",
    "wof:placetype":"locality"
},
  "geometry": {"coordinates":[119.7527,-3.9369],"type":"Point"}
}