{
  "type": "Feature",
  "properties": {
    "gn:admin1_code":"8.0",
    "gn:asciiname":"Soko",
    "gn:country_code":"ID",
    "gn:dem":677,
    "gn:feature_class":"P",
    "gn:feature_code":"PPL",
    "gn:name":"Soko",
    "gn:population":0,
    "gn:timezone":"Asia/Jakarta",
    "iso:country":"ID",
    "name:ind_x_preferred":[
        "Soko"
    ],
    "wof:name":"Soko",
    "wof:placetype":"locality"
},
  "geometry": {"coordinates":[111.58580000000001,-8.1659],"type":"Point"}
}