{
  "type": "Feature",
  "properties": {
    "gn:admin1_code":"8.0",
    "gn:asciiname":"Soko",
    "gn:country_code":"ID",
    "gn:dem":677,
    "gn:feature_class":"P",
    "gn:feature_code":"PPL",
    "gn:name":"Soko",
    "gn:population":0,
    "gn:timezone":"Asia/Jakarta",
    "iso:country":"ID",
    "name:bos_x_preferred":[
        "Soko"
    ],
    "name:ceb_x_preferred":[
        "Soko"
    ],
    "name:fra_x_preferred":[
        "Soko"
    ],
    "name:heb_x_preferred":[
        "\u05e1\u05d5\u05e7\u05d5"
    ],
    "name:ind_x_preferred":[
        "Soko"
    ],
    "name:mlg_x_preferred":[
        "Soko"
    ],
    "name:nld_x_preferred":[
        "Soko"
    ],
    "name:pol_x_preferred":[
        "Soko"
    ],
    "name:spa_x_preferred":[
        "Soko"
    ],
    "name:swe_x_preferred":[
        "Soko"
    ],
    "wof:lang_x_official":[
        "ind"
    ],
    "wof:lang_x_spoken":[
        "ind",
        "eng"
    ],
    "wof:name":"Soko",
    "wof:placetype":"locality"
},
  "geometry": {"coordinates":[111.58580000000001,-8.1659],"type":"Point"}
}