{
  "type": "Feature",
  "properties": {
    "gn:admin1_code":"0.0",
    "gn:asciiname":"Biting",
    "gn:country_code":"ID",
    "gn:dem":193,
    "gn:feature_class":"P",
    "gn:feature_code":"PPL",
    "gn:name":"Biting",
    "gn:population":0,
    "gn:timezone":"Asia/Jakarta",
    "iso:country":"ID",
    "name:est_x_preferred":[
        "Hammustamine"
    ],
    "name:fas_x_preferred":[
        "\u06af\u0627\u0632 \u06af\u0631\u0641\u062a\u0646"
    ],
    "name:ind_x_preferred":[
        "Biting"
    ],
    "name:kan_x_preferred":[
        "\u0c95\u0c9a\u0ccd\u0c9a\u0cc1\u0cb5\u0cc1\u0ca6\u0cc1"
    ],
    "name:vie_x_preferred":[
        "C\u1eafn"
    ],
    "wof:lang_x_official":[
        "ind"
    ],
    "wof:lang_x_spoken":[
        "ind",
        "eng"
    ],
    "wof:name":"Biting",
    "wof:placetype":"locality"
},
  "geometry": {"coordinates":[111.30083,-7.86278],"type":"Point"}
}