{
  "type": "Feature",
  "properties": {
    "gn:admin1_code":"0.0",
    "gn:asciiname":"Biting",
    "gn:country_code":"ID",
    "gn:dem":193,
    "gn:feature_class":"P",
    "gn:feature_code":"PPL",
    "gn:name":"Biting",
    "gn:population":0,
    "gn:timezone":"Asia/Jakarta",
    "iso:country":"ID",
    "name:ind_x_preferred":[
        "Biting"
    ],
    "wof:name":"Biting",
    "wof:placetype":"locality"
},
  "geometry": {"coordinates":[111.30083,-7.86278],"type":"Point"}
}