{
  "type": "Feature",
  "properties": {
    "iso:country":"ID",
    "qs:name":"Abang Batu Dinding",
    "qs:name_adm0":"Indonesia",
    "qs:name_adm1":"Bali",
    "qs:photos":53,
    "qs:photos_1k":11,
    "qs:photos_9k":1,
    "qs:photos_9r":2,
    "qs:photos_all":53,
    "qs:photos_sr":2,
    "qs:placetype":"Town",
    "qs:pop_sr":"0",
    "wd:wordcount":56,
    "wof:lang_x_official":[
        "ind"
    ],
    "wof:lang_x_spoken":[
        "ind",
        "eng"
    ],
    "wof:name":"Abang Batu Dinding",
    "wof:placetype":"locality"
},
  "geometry": {"coordinates":[115.420281,-8.266874],"type":"Point"}
}