{
  "type": "Feature",
  "properties": {
    "gn:admin1_code":"8",
    "gn:asciiname":"Besuki",
    "gn:country_code":"ID",
    "gn:dem":1285,
    "gn:feature_class":"P",
    "gn:feature_code":"PPL",
    "gn:name":"Besuki",
    "gn:population":0,
    "gn:timezone":"Asia/Jakarta",
    "iso:country":"ID",
    "name:ind_x_preferred":[
        "Besuki"
    ],
    "name:jav_x_preferred":[
        "Besuki"
    ],
    "name:min_x_preferred":[
        "Besuki"
    ],
    "name:swe_x_preferred":[
        "Besuki"
    ],
    "wof:name":"Besuki",
    "wof:placetype":"locality"
},
  "geometry": {"coordinates":[112.8477,-7.9068],"type":"Point"}
}