{
  "type": "Feature",
  "properties": {
    "gn:admin1_code":"7",
    "gn:asciiname":"Brangsong",
    "gn:country_code":"ID",
    "gn:dem":5,
    "gn:feature_class":"P",
    "gn:feature_code":"PPL",
    "gn:name":"Brangsong",
    "gn:population":0,
    "gn:timezone":"Asia/Jakarta",
    "iso:country":"ID",
    "name:ind_x_preferred":[
        "Brangsong"
    ],
    "wof:name":"Brangsong",
    "wof:placetype":"locality"
},
  "geometry": {"coordinates":[110.54730000000001,-6.8812],"type":"Point"}
}