{
  "type": "Feature",
  "properties": {
    "gn:admin1_code":"7.0",
    "gn:asciiname":"Cikokol",
    "gn:country_code":"ID",
    "gn:dem":115,
    "gn:feature_class":"P",
    "gn:feature_code":"PPL",
    "gn:name":"Cikokol",
    "gn:population":0,
    "gn:timezone":"Asia/Jakarta",
    "iso:country":"ID",
    "name:ind_x_preferred":[
        "Cikokol"
    ],
    "name:und_x_variant":[
        "Tjikokol 2"
    ],
    "wof:name":"Cikokol",
    "wof:placetype":"locality"
},
  "geometry": {"coordinates":[108.83499999999999,-7.2781],"type":"Point"}
}