{
  "type": "Feature",
  "properties": {
    "gn:admin1_code":"26",
    "gn:asciiname":"Besibesi",
    "gn:country_code":"ID",
    "gn:dem":602,
    "gn:feature_class":"P",
    "gn:feature_code":"PPL",
    "gn:name":"Besibesi",
    "gn:population":0,
    "gn:timezone":"Asia/Jakarta",
    "iso:country":"ID",
    "name:ind_x_preferred":[
        "Besibesi"
    ],
    "wof:name":"Besibesi",
    "wof:placetype":"locality"
},
  "geometry": {"coordinates":[98.0894,3.3137],"type":"Point"}
}