{
  "type": "Feature",
  "properties": {
    "gn:admin1_code":"18.0",
    "gn:asciiname":"Malabai",
    "gn:country_code":"ID",
    "gn:dem":607,
    "gn:feature_class":"P",
    "gn:feature_code":"PPLA4",
    "gn:name":"Malabai",
    "gn:population":0,
    "gn:timezone":"Asia/Makassar",
    "iso:country":"ID",
    "name:ind_x_preferred":[
        "Malabai"
    ],
    "wof:lang_x_official":[
        "ind"
    ],
    "wof:lang_x_spoken":[
        "ind",
        "eng"
    ],
    "wof:name":"Malabai",
    "wof:placetype":"locality"
},
  "geometry": {"coordinates":[121.1514,-8.5605],"type":"Point"}
}