{
  "type": "Feature",
  "properties": {
    "gn:admin1_code":"30.0",
    "gn:asciiname":"Kalapadua Kaler",
    "gn:country_code":"ID",
    "gn:dem":878,
    "gn:feature_class":"P",
    "gn:feature_code":"PPL",
    "gn:name":"Kalapadua Kaler",
    "gn:population":0,
    "gn:timezone":"Asia/Jakarta",
    "iso:country":"ID",
    "name:ind_x_preferred":[
        "Kalapadua Kaler"
    ],
    "wof:name":"Kalapadua Kaler",
    "wof:placetype":"locality"
},
  "geometry": {"coordinates":[107.97029999999999,-7.2153],"type":"Point"}
}