{
  "type": "Feature",
  "properties": {
    "gn:admin1_code":"33",
    "gn:asciiname":"Bank Tabungan Negara Mandala",
    "gn:country_code":"ID",
    "gn:dem":32,
    "gn:feature_class":"P",
    "gn:feature_code":"PPL",
    "gn:name":"Bank Tabungan Negara Mandala",
    "gn:population":0,
    "gn:timezone":"Asia/Jakarta",
    "iso:country":"ID",
    "name:ind_x_preferred":[
        "Bank Tabungan Negara Mandala"
    ],
    "name:und_x_variant":[
        "BTN Mandala"
    ],
    "wof:lang_x_official":[
        "ind"
    ],
    "wof:lang_x_spoken":[
        "ind",
        "eng"
    ],
    "wof:name":"Bank Tabungan Negara Mandala",
    "wof:placetype":"locality"
},
  "geometry": {"coordinates":[106.2295,-6.3462],"type":"Point"}
}