{
  "type": "Feature",
  "properties": {
    "gn:admin1_code":"7",
    "gn:asciiname":"Tropong",
    "gn:country_code":"ID",
    "gn:dem":590,
    "gn:feature_class":"P",
    "gn:feature_code":"PPL",
    "gn:name":"Tropong",
    "gn:population":0,
    "gn:timezone":"Asia/Jakarta",
    "iso:country":"ID",
    "name:ind_x_preferred":[
        "Tropong"
    ],
    "wof:name":"Tropong",
    "wof:placetype":"locality"
},
  "geometry": {"coordinates":[109.6542,-7.1237],"type":"Point"}
}