{
  "type": "Feature",
  "properties": {
    "gn:admin1_code":"5.0",
    "gn:asciiname":"Kluru",
    "gn:country_code":"ID",
    "gn:dem":786,
    "gn:feature_class":"P",
    "gn:feature_code":"PPL",
    "gn:name":"Kluru",
    "gn:population":0,
    "gn:timezone":"Asia/Jakarta",
    "iso:country":"ID",
    "name:ind_x_preferred":[
        "Kluru"
    ],
    "wof:name":"Kluru",
    "wof:placetype":"locality"
},
  "geometry": {"coordinates":[101.5119,-2.1762],"type":"Point"}
}