{
  "type": "Feature",
  "properties": {
    "gn:admin1_code":"7.0",
    "gn:asciiname":"Sorogan",
    "gn:country_code":"ID",
    "gn:dem":28,
    "gn:feature_class":"P",
    "gn:feature_code":"PPL",
    "gn:name":"Sorogan",
    "gn:population":0,
    "gn:timezone":"Asia/Jakarta",
    "iso:country":"ID",
    "name:ind_x_preferred":[
        "Sorogan"
    ],
    "wof:name":"Sorogan",
    "wof:placetype":"locality"
},
  "geometry": {"coordinates":[109.22638999999999,-7.49222],"type":"Point"}
}