{
  "type": "Feature",
  "properties": {
    "gn:admin1_code":"21",
    "gn:asciiname":"Rogo",
    "gn:country_code":"ID",
    "gn:dem":88,
    "gn:feature_class":"P",
    "gn:feature_code":"PPL",
    "gn:name":"Rogo",
    "gn:population":0,
    "gn:timezone":"Asia/Makassar",
    "iso:country":"ID",
    "name:ceb_x_preferred":[
        "Rogo"
    ],
    "name:fra_x_preferred":[
        "Rogo"
    ],
    "name:ind_x_preferred":[
        "Rogo"
    ],
    "name:ita_x_preferred":[
        "Rogo"
    ],
    "name:por_x_preferred":[
        "Rogo"
    ],
    "name:spa_x_preferred":[
        "Rogo"
    ],
    "wof:lang_x_official":[
        "ind"
    ],
    "wof:lang_x_spoken":[
        "ind",
        "eng"
    ],
    "wof:name":"Rogo",
    "wof:placetype":"locality"
},
  "geometry": {"coordinates":[119.8875,-1.1778],"type":"Point"}
}