{
  "type": "Feature",
  "properties": {
    "gn:admin1_code":"30.0",
    "gn:asciiname":"Cipayungguyangan",
    "gn:country_code":"ID",
    "gn:dem":769,
    "gn:feature_class":"P",
    "gn:feature_code":"PPL",
    "gn:name":"Cipayungguyangan",
    "gn:population":0,
    "gn:timezone":"Asia/Jakarta",
    "iso:country":"ID",
    "name:ind_x_preferred":[
        "Cipayungguyangan"
    ],
    "name:und_x_variant":[
        "Tjipanggoejangan"
    ],
    "wof:lang_x_official":[
        "ind"
    ],
    "wof:lang_x_spoken":[
        "ind",
        "eng"
    ],
    "wof:name":"Cipayungguyangan",
    "wof:placetype":"locality"
},
  "geometry": {"coordinates":[108.01690000000001,-7.3133],"type":"Point"}
}