{
  "type": "Feature",
  "properties": {
    "gn:admin1_code":"5.0",
    "gn:asciiname":"Pungutmudik",
    "gn:country_code":"ID",
    "gn:dem":1237,
    "gn:feature_class":"P",
    "gn:feature_code":"PPL",
    "gn:name":"Pungutmudik",
    "gn:population":0,
    "gn:timezone":"Asia/Jakarta",
    "iso:country":"ID",
    "name:ind_x_preferred":[
        "Pungutmudik"
    ],
    "wof:name":"Pungutmudik",
    "wof:placetype":"locality"
},
  "geometry": {"coordinates":[101.4434,-1.9762],"type":"Point"}
}