{
  "type": "Feature",
  "properties": {
    "gn:admin1_code":"7",
    "gn:asciiname":"Ngasem",
    "gn:country_code":"ID",
    "gn:dem":72,
    "gn:feature_class":"P",
    "gn:feature_code":"PPL",
    "gn:name":"Ngasem",
    "gn:population":0,
    "gn:timezone":"Asia/Jakarta",
    "iso:country":"ID",
    "name:ind_x_preferred":[
        "Ngasem"
    ],
    "wof:name":"Ngasem",
    "wof:placetype":"locality"
},
  "geometry": {"coordinates":[111.12417000000001,-7.16944],"type":"Point"}
}