{
  "type": "Feature",
  "properties": {
    "gn:admin1_code":"30.0",
    "gn:asciiname":"Nagrag",
    "gn:country_code":"ID",
    "gn:dem":83,
    "gn:feature_class":"P",
    "gn:feature_code":"PPL",
    "gn:name":"Nagrag",
    "gn:population":0,
    "gn:timezone":"Asia/Jakarta",
    "iso:country":"ID",
    "name:ind_x_preferred":[
        "Nagrag"
    ],
    "wof:name":"Nagrag",
    "wof:placetype":"locality"
},
  "geometry": {"coordinates":[106.5552,-7.3603],"type":"Point"}
}