{
  "type": "Feature",
  "properties": {
    "gn:admin1_code":"2",
    "gn:asciiname":"Banjar Pasdalem",
    "gn:country_code":"ID",
    "gn:dem":121,
    "gn:feature_class":"P",
    "gn:feature_code":"PPL",
    "gn:name":"Banjar Pasdalem",
    "gn:population":0,
    "gn:timezone":"Asia/Makassar",
    "iso:country":"ID",
    "name:ind_x_preferred":[
        "Banjar Pasdalem"
    ],
    "wof:name":"Banjar Pasdalem",
    "wof:placetype":"locality"
},
  "geometry": {"coordinates":[115.3292,-8.545],"type":"Point"}
}