{
  "type": "Feature",
  "properties": {
    "gn:admin1_code":"30",
    "gn:asciiname":"Panaragan Pojok",
    "gn:country_code":"ID",
    "gn:dem":225,
    "gn:feature_class":"P",
    "gn:feature_code":"PPL",
    "gn:name":"Panaragan Pojok",
    "gn:population":0,
    "gn:timezone":"Asia/Jakarta",
    "iso:country":"ID",
    "name:ind_x_preferred":[
        "Panaragan Pojok"
    ],
    "wof:name":"Panaragan Pojok",
    "wof:placetype":"locality"
},
  "geometry": {"coordinates":[106.78417,-6.59583],"type":"Point"}
}