{
  "type": "Feature",
  "properties": {
    "gn:admin1_code":"29.0",
    "gn:asciiname":"Bobapaja",
    "gn:country_code":"ID",
    "gn:dem":8,
    "gn:feature_class":"P",
    "gn:feature_code":"PPL",
    "gn:name":"Bobapaja",
    "gn:population":0,
    "gn:timezone":"Asia/Jayapura",
    "iso:country":"ID",
    "name:ind_x_preferred":[
        "Bobapaja"
    ],
    "name:und_x_variant":[
        "Bobopajo",
        "Bobopayo",
        "Bobopaja"
    ],
    "wof:lang_x_official":[
        "ind"
    ],
    "wof:lang_x_spoken":[
        "ind",
        "eng"
    ],
    "wof:name":"Bobapaja",
    "wof:placetype":"locality"
},
  "geometry": {"coordinates":[127.41115000000001,1.0512],"type":"Point"}
}