{
  "type": "Feature",
  "properties": {
    "gn:admin1_code":"41",
    "gn:asciiname":"Rumbia",
    "gn:country_code":"ID",
    "gn:dem":132,
    "gn:feature_class":"P",
    "gn:feature_code":"PPL",
    "gn:name":"Rumbia",
    "gn:population":0,
    "gn:timezone":"Asia/Makassar",
    "iso:country":"ID",
    "name:ind_x_preferred":[
        "Rumbia"
    ],
    "wof:name":"Rumbia",
    "wof:placetype":"locality"
},
  "geometry": {"coordinates":[119.09910000000001,-3.4514],"type":"Point"}
}