{
  "type": "Feature",
  "properties": {
    "gn:admin1_code":"7.0",
    "gn:asciiname":"Kiteran",
    "gn:country_code":"ID",
    "gn:dem":10,
    "gn:feature_class":"P",
    "gn:feature_code":"PPL",
    "gn:name":"Kiteran",
    "gn:population":0,
    "gn:timezone":"Asia/Jakarta",
    "iso:country":"ID",
    "name:ind_x_preferred":[
        "Kiteran"
    ],
    "wof:name":"Kiteran",
    "wof:placetype":"locality"
},
  "geometry": {"coordinates":[109.53111,-7.71917],"type":"Point"}
}