{
  "type": "Feature",
  "properties": {
    "gn:admin1_code":"8.0",
    "gn:asciiname":"Babatan",
    "gn:country_code":"ID",
    "gn:dem":783,
    "gn:feature_class":"P",
    "gn:feature_code":"PPL",
    "gn:name":"Babatan",
    "gn:population":0,
    "gn:timezone":"Asia/Jakarta",
    "iso:country":"ID",
    "name:ind_x_preferred":[
        "Babatan"
    ],
    "wof:name":"Babatan",
    "wof:placetype":"locality"
},
  "geometry": {"coordinates":[112.45399999999999,-8.0348],"type":"Point"}
}