{
  "type": "Feature",
  "properties": {
    "gn:admin1_code":"26",
    "gn:asciiname":"Siduatopayan",
    "gn:country_code":"ID",
    "gn:dem":99,
    "gn:feature_class":"P",
    "gn:feature_code":"PPL",
    "gn:name":"Siduatopayan",
    "gn:population":0,
    "gn:timezone":"Asia/Jakarta",
    "iso:country":"ID",
    "name:ind_x_preferred":[
        "Siduatopayan"
    ],
    "wof:name":"Siduatopayan",
    "wof:placetype":"locality"
},
  "geometry": {"coordinates":[99.63415999999999,1.48558],"type":"Point"}
}