{
  "type": "Feature",
  "properties": {
    "gn:admin1_code":"7.0",
    "gn:asciiname":"Banaran",
    "gn:country_code":"ID",
    "gn:dem":23,
    "gn:feature_class":"P",
    "gn:feature_code":"PPL",
    "gn:name":"Banaran",
    "gn:population":0,
    "gn:timezone":"Asia/Jakarta",
    "iso:country":"ID",
    "name:ind_x_preferred":[
        "Banaran"
    ],
    "wof:name":"Banaran",
    "wof:placetype":"locality"
},
  "geometry": {"coordinates":[111.61279999999999,-6.7555],"type":"Point"}
}