{
  "type": "Feature",
  "properties": {
    "gn:admin1_code":"30",
    "gn:asciiname":"Talaga",
    "gn:country_code":"ID",
    "gn:dem":167,
    "gn:feature_class":"P",
    "gn:feature_code":"PPL",
    "gn:name":"Talaga",
    "gn:population":0,
    "gn:timezone":"Asia/Jakarta",
    "iso:country":"ID",
    "name:ind_x_preferred":[
        "Talaga"
    ],
    "wof:name":"Talaga",
    "wof:placetype":"locality"
},
  "geometry": {"coordinates":[107.45332999999999,-6.63083],"type":"Point"}
}