{
  "type": "Feature",
  "properties": {
    "gn:admin1_code":"1",
    "gn:asciiname":"Bukit Jenat Manyang",
    "gn:country_code":"ID",
    "gn:dem":17,
    "gn:feature_class":"P",
    "gn:feature_code":"PPL",
    "gn:name":"Bukit Jenat Manyang",
    "gn:population":0,
    "gn:timezone":"Asia/Jakarta",
    "iso:country":"ID",
    "name:ind_x_preferred":[
        "Bukit Jenat Manyang"
    ],
    "name:und_x_variant":[
        "Bk Jeratmanyang"
    ],
    "wof:name":"Bukit Jenat Manyang",
    "wof:placetype":"locality"
},
  "geometry": {"coordinates":[97.4679,5.0515],"type":"Point"}
}