{
  "type": "Feature",
  "properties": {
    "gn:admin1_code":"26",
    "gn:asciiname":"Sawi Rejo",
    "gn:country_code":"ID",
    "gn:dem":71,
    "gn:feature_class":"P",
    "gn:feature_code":"PPL",
    "gn:name":"Sawi Rejo",
    "gn:population":0,
    "gn:timezone":"Asia/Jakarta",
    "iso:country":"ID",
    "name:ind_x_preferred":[
        "Sawi Rejo"
    ],
    "wof:name":"Sawi Rejo",
    "wof:placetype":"locality"
},
  "geometry": {"coordinates":[98.54949999999999,3.5273],"type":"Point"}
}