{
  "type": "Feature",
  "properties": {
    "gn:admin1_code":"21",
    "gn:asciiname":"Koropu",
    "gn:country_code":"ID",
    "gn:dem":13,
    "gn:feature_class":"P",
    "gn:feature_code":"PPL",
    "gn:name":"Koropu",
    "gn:population":0,
    "gn:timezone":"Asia/Makassar",
    "iso:country":"ID",
    "name:ind_x_preferred":[
        "Koropu"
    ],
    "wof:name":"Koropu",
    "wof:placetype":"locality"
},
  "geometry": {"coordinates":[120.56780000000001,-1.169],"type":"Point"}
}