{
  "type": "Feature",
  "properties": {
    "gn:admin1_code":"21.0",
    "gn:asciiname":"Waelemo",
    "gn:country_code":"ID",
    "gn:dem":1116,
    "gn:feature_class":"P",
    "gn:feature_code":"PPL",
    "gn:name":"Waelemo",
    "gn:population":0,
    "gn:timezone":"Asia/Makassar",
    "iso:country":"ID",
    "name:ind_x_preferred":[
        "Waelemo"
    ],
    "wof:name":"Waelemo",
    "wof:placetype":"locality"
},
  "geometry": {"coordinates":[119.74638,-1.05261],"type":"Point"}
}