{
  "type": "Feature",
  "properties": {
    "gn:admin1_code":"15.0",
    "gn:asciiname":"Umbulan Patinkurat",
    "gn:country_code":"ID",
    "gn:dem":35,
    "gn:feature_class":"P",
    "gn:feature_code":"PPL",
    "gn:name":"Umbulan Patinkurat",
    "gn:population":0,
    "gn:timezone":"Asia/Jakarta",
    "iso:country":"ID",
    "name:und_x_variant":[
        "Oemboelan Patinkoerat",
        "Umbulan Patinkurat"
    ],
    "wof:name":"Umbulan Patinkurat",
    "wof:placetype":"locality"
},
  "geometry": {"coordinates":[104.86681000000002,-4.46913],"type":"Point"}
}