{
  "type": "Feature",
  "properties": {
    "gn:admin1_code":"26",
    "gn:asciiname":"Si-kapal Dua-satu",
    "gn:country_code":"ID",
    "gn:dem":771,
    "gn:feature_class":"P",
    "gn:feature_code":"PPL",
    "gn:name":"Si-kapal Dua-satu",
    "gn:population":0,
    "gn:timezone":"Asia/Jakarta",
    "iso:country":"ID",
    "name:ind_x_preferred":[
        "Si-kapal Dua-satu"
    ],
    "name:und_x_variant":[
        "Si-Kapal 2-1"
    ],
    "wof:lang_x_official":[
        "ind"
    ],
    "wof:lang_x_spoken":[
        "ind",
        "eng"
    ],
    "wof:name":"Si-kapal Dua-satu",
    "wof:placetype":"locality"
},
  "geometry": {"coordinates":[98.1944,2.7816],"type":"Point"}
}