{
  "type": "Feature",
  "properties": {
    "gn:admin1_code":"33.0",
    "gn:asciiname":"Bulakan",
    "gn:country_code":"ID",
    "gn:dem":37,
    "gn:feature_class":"P",
    "gn:feature_code":"PPL",
    "gn:name":"Bulakan",
    "gn:population":0,
    "gn:timezone":"Asia/Jakarta",
    "iso:country":"ID",
    "name:ind_x_preferred":[
        "Bulakan"
    ],
    "wof:name":"Bulakan",
    "wof:placetype":"locality"
},
  "geometry": {"coordinates":[105.7749,-6.5884],"type":"Point"}
}