{
  "type": "Feature",
  "properties": {
    "gn:admin1_code":"31",
    "gn:asciiname":"Simbel",
    "gn:country_code":"ID",
    "gn:dem":713,
    "gn:feature_class":"P",
    "gn:feature_code":"PPL",
    "gn:name":"Simbel",
    "gn:population":0,
    "gn:timezone":"Asia/Makassar",
    "iso:country":"ID",
    "name:ind_x_preferred":[
        "Simbel"
    ],
    "wof:name":"Simbel",
    "wof:placetype":"locality"
},
  "geometry": {"coordinates":[124.87260000000001,1.1429],"type":"Point"}
}