{
  "type": "Feature",
  "properties": {
    "gn:admin1_code":"7.0",
    "gn:asciiname":"Sokawera",
    "gn:country_code":"ID",
    "gn:dem":32,
    "gn:feature_class":"P",
    "gn:feature_code":"PPL",
    "gn:name":"Sokawera",
    "gn:population":0,
    "gn:timezone":"Asia/Jakarta",
    "iso:country":"ID",
    "name:ind_x_preferred":[
        "Sokawera"
    ],
    "wof:name":"Sokawera",
    "wof:placetype":"locality"
},
  "geometry": {"coordinates":[109.66333,-7.64417],"type":"Point"}
}