{
  "type": "Feature",
  "properties": {
    "gn:admin1_code":"15.0",
    "gn:asciiname":"Brajatajar",
    "gn:country_code":"ID",
    "gn:dem":13,
    "gn:feature_class":"P",
    "gn:feature_code":"PPL",
    "gn:name":"Brajatajar",
    "gn:population":0,
    "gn:timezone":"Asia/Jakarta",
    "iso:country":"ID",
    "name:ind_x_preferred":[
        "Brajatajar"
    ],
    "wof:name":"Brajatajar",
    "wof:placetype":"locality"
},
  "geometry": {"coordinates":[105.76021,-5.27044],"type":"Point"}
}