{
  "type": "Feature",
  "properties": {
    "gn:admin1_code":"30",
    "gn:asciiname":"Kukulu",
    "gn:country_code":"ID",
    "gn:dem":400,
    "gn:feature_class":"P",
    "gn:feature_code":"PPL",
    "gn:name":"Kukulu",
    "gn:population":0,
    "gn:timezone":"Asia/Jakarta",
    "iso:country":"ID",
    "name:ind_x_preferred":[
        "Kukulu"
    ],
    "wof:name":"Kukulu",
    "wof:placetype":"locality"
},
  "geometry": {"coordinates":[108.18861,-6.95833],"type":"Point"}
}