{
  "type": "Feature",
  "properties": {
    "gn:admin1_code":"30.0",
    "gn:asciiname":"Cublukkolot",
    "gn:country_code":"ID",
    "gn:dem":75,
    "gn:feature_class":"P",
    "gn:feature_code":"PPL",
    "gn:name":"Cublukkolot",
    "gn:population":0,
    "gn:timezone":"Asia/Jakarta",
    "iso:country":"ID",
    "name:und_x_variant":[
        "Tjublukkolot",
        "Cublukkolot",
        "Tjoebloek-kolot"
    ],
    "wof:lang_x_official":[
        "ind"
    ],
    "wof:lang_x_spoken":[
        "ind",
        "eng"
    ],
    "wof:name":"Cublukkolot",
    "wof:placetype":"locality"
},
  "geometry": {"coordinates":[108.55249999999999,-7.3899],"type":"Point"}
}