{
  "type": "Feature",
  "properties": {
    "gn:admin1_code":"08",
    "gn:asciiname":"Kemuning",
    "gn:country_code":"ID",
    "gn:dem":18,
    "gn:feature_class":"P",
    "gn:feature_code":"PPL",
    "gn:name":"Kemuning",
    "gn:population":0,
    "gn:timezone":"Asia/Jakarta",
    "iso:country":"ID",
    "name:ind_x_preferred":[
        "Kemuning"
    ],
    "name:und_x_variant":[
        "Kemuning 1",
        "Kemuning Satu"
    ],
    "wof:name":"Kemuning",
    "wof:placetype":"locality"
},
  "geometry": {"coordinates":[112.5248,-7.4446],"type":"Point"}
}