{
  "type": "Feature",
  "properties": {
    "gn:admin1_code":"17",
    "gn:asciiname":"Kombobau",
    "gn:country_code":"ID",
    "gn:dem":405,
    "gn:feature_class":"P",
    "gn:feature_code":"PPL",
    "gn:name":"Kombobau",
    "gn:population":0,
    "gn:timezone":"Asia/Makassar",
    "iso:country":"ID",
    "name:ind_x_preferred":[
        "Kombobau"
    ],
    "wof:name":"Kombobau",
    "wof:placetype":"locality"
},
  "geometry": {"coordinates":[118.8657,-8.5549],"type":"Point"}
}