{
  "type": "Feature",
  "properties": {
    "gn:admin1_code":"33.0",
    "gn:asciiname":"Pasir Lebak",
    "gn:country_code":"ID",
    "gn:dem":160,
    "gn:feature_class":"P",
    "gn:feature_code":"PPL",
    "gn:name":"Pasir Lebak",
    "gn:population":0,
    "gn:timezone":"Asia/Jakarta",
    "iso:country":"ID",
    "name:ind_x_preferred":[
        "Pasir Lebak"
    ],
    "wof:name":"Pasir Lebak",
    "wof:placetype":"locality"
},
  "geometry": {"coordinates":[106.1023,-6.338],"type":"Point"}
}