{
  "type": "Feature",
  "properties": {
    "gn:admin1_code":"15.0",
    "gn:asciiname":"Umbulan Titibungui Satu",
    "gn:country_code":"ID",
    "gn:dem":106,
    "gn:feature_class":"P",
    "gn:feature_code":"PPL",
    "gn:name":"Umbulan Titibungui Satu",
    "gn:population":0,
    "gn:timezone":"Asia/Jakarta",
    "iso:country":"ID",
    "name:ind_x_preferred":[
        "Umbulan Titibungui Satu"
    ],
    "name:und_x_variant":[
        "Umbulantitibungui 1"
    ],
    "wof:name":"Umbulan Titibungui Satu",
    "wof:placetype":"locality"
},
  "geometry": {"coordinates":[104.4479,-4.64035],"type":"Point"}
}