{
  "type": "Feature",
  "properties": {
    "gn:admin1_code":"30.0",
    "gn:asciiname":"Kubangkuwu",
    "gn:country_code":"ID",
    "gn:dem":525,
    "gn:feature_class":"P",
    "gn:feature_code":"PPL",
    "gn:name":"Kubangkuwu",
    "gn:population":0,
    "gn:timezone":"Asia/Jakarta",
    "iso:country":"ID",
    "name:ind_x_preferred":[
        "Kubangkuwu"
    ],
    "wof:name":"Kubangkuwu",
    "wof:placetype":"locality"
},
  "geometry": {"coordinates":[108.12050000000001,-7.2938],"type":"Point"}
}