{
  "type": "Feature",
  "properties": {
    "gn:admin1_code":"8.0",
    "gn:asciiname":"Glagahan",
    "gn:country_code":"ID",
    "gn:dem":18,
    "gn:feature_class":"P",
    "gn:feature_code":"PPLA4",
    "gn:name":"Glagahan",
    "gn:population":0,
    "gn:timezone":"Asia/Jakarta",
    "iso:country":"ID",
    "name:ind_x_preferred":[
        "Glagahan"
    ],
    "wof:name":"Glagahan",
    "wof:placetype":"locality"
},
  "geometry": {"coordinates":[112.9528,-8.2969],"type":"Point"}
}