{
  "type": "Feature",
  "properties": {
    "gn:admin1_code":"08",
    "gn:asciiname":"Nanasan",
    "gn:country_code":"ID",
    "gn:dem":763,
    "gn:feature_class":"P",
    "gn:feature_code":"PPL",
    "gn:name":"Nanasan",
    "gn:population":0,
    "gn:timezone":"Asia/Jakarta",
    "iso:country":"ID",
    "name:ind_x_preferred":[
        "Nanasan"
    ],
    "wof:name":"Nanasan",
    "wof:placetype":"locality"
},
  "geometry": {"coordinates":[112.5106,-8.0301],"type":"Point"}
}