{
  "type": "Feature",
  "properties": {
    "gn:admin1_code":"08",
    "gn:asciiname":"Sumberrejo Satu",
    "gn:cc2":"ID",
    "gn:country_code":"ID",
    "gn:dem":301,
    "gn:feature_class":"P",
    "gn:feature_code":"PPL",
    "gn:name":"Sumberrejo Satu",
    "gn:population":0,
    "gn:timezone":"Asia/Jakarta",
    "iso:country":"ID",
    "name:und_x_variant":[
        "Sumberredjo 1",
        "Sumberrejo Satu"
    ],
    "wof:name":"Sumberrejo Satu",
    "wof:placetype":"locality"
},
  "geometry": {"coordinates":[112.55777999999999,-8.19583],"type":"Point"}
}