{
  "type": "Feature",
  "properties": {
    "gn:admin1_code":"8.0",
    "gn:asciiname":"Cerme",
    "gn:country_code":"ID",
    "gn:dem":71,
    "gn:feature_class":"P",
    "gn:feature_code":"PPL",
    "gn:name":"Cerme",
    "gn:population":0,
    "gn:timezone":"Asia/Jakarta",
    "iso:country":"ID",
    "name:ind_x_preferred":[
        "Cerme"
    ],
    "wof:name":"Cerme",
    "wof:placetype":"locality"
},
  "geometry": {"coordinates":[112.1606,-7.2964],"type":"Point"}
}