{
  "type": "Feature",
  "properties": {
    "gn:admin1_code":"30",
    "gn:asciiname":"Melayupeuntas",
    "gn:country_code":"ID",
    "gn:dem":874,
    "gn:feature_class":"P",
    "gn:feature_code":"PPL",
    "gn:name":"Melayupeuntas",
    "gn:population":0,
    "gn:timezone":"Asia/Jakarta",
    "iso:country":"ID",
    "name:ind_x_preferred":[
        "Melayupeuntas"
    ],
    "wof:name":"Melayupeuntas",
    "wof:placetype":"locality"
},
  "geometry": {"coordinates":[107.86190000000001,-7.213],"type":"Point"}
}