{
  "type": "Feature",
  "properties": {
    "gn:admin1_code":"33",
    "gn:asciiname":"Tegalmangun",
    "gn:country_code":"ID",
    "gn:dem":67,
    "gn:feature_class":"P",
    "gn:feature_code":"PPL",
    "gn:name":"Tegalmangun",
    "gn:population":0,
    "gn:timezone":"Asia/Jakarta",
    "iso:country":"ID",
    "name:ind_x_preferred":[
        "Tegalmangun"
    ],
    "wof:name":"Tegalmangun",
    "wof:placetype":"locality"
},
  "geometry": {"coordinates":[106.0718,-6.081],"type":"Point"}
}