{
  "type": "Feature",
  "properties": {
    "gn:admin1_code":"8",
    "gn:asciiname":"Bulabugunong",
    "gn:country_code":"ID",
    "gn:dem":146,
    "gn:feature_class":"P",
    "gn:feature_code":"PPL",
    "gn:name":"Bulabugunong",
    "gn:population":0,
    "gn:timezone":"Asia/Jakarta",
    "iso:country":"ID",
    "name:ind_x_preferred":[
        "Bulabugunong"
    ],
    "wof:name":"Bulabugunong",
    "wof:placetype":"locality"
},
  "geometry": {"coordinates":[113.1708,-7.1025],"type":"Point"}
}