{
  "type": "Feature",
  "properties": {
    "gn:admin1_code":"33",
    "gn:asciiname":"Kaliwadas",
    "gn:country_code":"ID",
    "gn:dem":22,
    "gn:feature_class":"P",
    "gn:feature_code":"PPL",
    "gn:name":"Kaliwadas",
    "gn:population":0,
    "gn:timezone":"Asia/Jakarta",
    "iso:country":"ID",
    "name:ind_x_preferred":[
        "Kaliwadas"
    ],
    "wof:name":"Kaliwadas",
    "wof:placetype":"locality"
},
  "geometry": {"coordinates":[106.1669,-6.1064],"type":"Point"}
}