{
  "type": "Feature",
  "properties": {
    "gn:admin1_code":"08",
    "gn:asciiname":"Ragunan",
    "gn:country_code":"ID",
    "gn:dem":362,
    "gn:feature_class":"P",
    "gn:feature_code":"PPL",
    "gn:name":"Ragunan",
    "gn:population":0,
    "gn:timezone":"Asia/Jakarta",
    "iso:country":"ID",
    "wof:name":"Ragunan",
    "wof:placetype":"locality"
},
  "geometry": {"coordinates":[112.66222,-8.19],"type":"Point"}
}