{
  "type": "Feature",
  "properties": {
    "gn:admin1_code":"30.0",
    "gn:asciiname":"Gardu",
    "gn:country_code":"ID",
    "gn:dem":51,
    "gn:feature_class":"P",
    "gn:feature_code":"PPL",
    "gn:name":"Gardu",
    "gn:population":0,
    "gn:timezone":"Asia/Jakarta",
    "iso:country":"ID",
    "name:ind_x_preferred":[
        "Gardu"
    ],
    "wof:name":"Gardu",
    "wof:placetype":"locality"
},
  "geometry": {"coordinates":[108.51609999999999,-7.3736],"type":"Point"}
}