{
  "type": "Feature",
  "properties": {
    "gn:admin1_code":"8.0",
    "gn:asciiname":"Klaten",
    "gn:country_code":"ID",
    "gn:dem":101,
    "gn:feature_class":"P",
    "gn:feature_code":"PPL",
    "gn:name":"Klaten",
    "gn:population":0,
    "gn:timezone":"Asia/Jakarta",
    "iso:country":"ID",
    "name:ind_x_preferred":[
        "Klaten"
    ],
    "wof:name":"Klaten",
    "wof:placetype":"locality"
},
  "geometry": {"coordinates":[111.96729999999999,-8.0524],"type":"Point"}
}