{
  "type": "Feature",
  "properties": {
    "gn:admin1_code":"00",
    "gn:asciiname":"Tjengkareng Dua",
    "gn:cc2":"ID",
    "gn:country_code":"ID",
    "gn:dem":3,
    "gn:feature_class":"P",
    "gn:feature_code":"PPL",
    "gn:name":"Tjengkareng Dua",
    "gn:population":0,
    "gn:timezone":"Asia/Jakarta",
    "iso:country":"ID",
    "name:und_x_variant":[
        "Tjengkareng 2",
        "Tjengkareng Dua"
    ],
    "wof:lang_x_official":[
        "ind"
    ],
    "wof:lang_x_spoken":[
        "ind",
        "eng"
    ],
    "wof:name":"Tjengkareng Dua",
    "wof:placetype":"locality"
},
  "geometry": {"coordinates":[106.7325,-6.13417],"type":"Point"}
}