{
  "type": "Feature",
  "properties": {
    "gn:admin1_code":"1",
    "gn:asciiname":"Cot Dulang",
    "gn:country_code":"ID",
    "gn:dem":11,
    "gn:feature_class":"P",
    "gn:feature_code":"PPL",
    "gn:name":"Cot Dulang",
    "gn:population":0,
    "gn:timezone":"Asia/Jakarta",
    "iso:country":"ID",
    "name:ind_x_preferred":[
        "Cot Dulang"
    ],
    "name:und_x_variant":[
        "Tjotdulang",
        "Catdulang"
    ],
    "wof:name":"Cot Dulang",
    "wof:placetype":"locality"
},
  "geometry": {"coordinates":[95.3747,5.0825],"type":"Point"}
}