{
  "type": "Feature",
  "properties": {
    "gn:admin1_code":"24",
    "gn:asciiname":"Airjernih",
    "gn:country_code":"ID",
    "gn:dem":1126,
    "gn:feature_class":"P",
    "gn:feature_code":"PPL",
    "gn:name":"Airjernih",
    "gn:population":0,
    "gn:timezone":"Asia/Jakarta",
    "iso:country":"ID",
    "name:ind_x_preferred":[
        "Airjernih"
    ],
    "wof:name":"Airjernih",
    "wof:placetype":"locality"
},
  "geometry": {"coordinates":[100.86458,-1.22511],"type":"Point"}
}