{
  "type": "Feature",
  "properties": {
    "gn:admin1_code":"0.0",
    "gn:asciiname":"Parhebangan",
    "gn:country_code":"ID",
    "gn:dem":1412,
    "gn:feature_class":"P",
    "gn:feature_code":"PPL",
    "gn:name":"Parhebangan",
    "gn:population":0,
    "gn:timezone":"Asia/Jakarta",
    "iso:country":"ID",
    "name:ind_x_preferred":[
        "Parhebangan"
    ],
    "wof:name":"Parhebangan",
    "wof:placetype":"locality"
},
  "geometry": {"coordinates":[98.74648999999999,2.25743],"type":"Point"}
}