{
  "type": "Feature",
  "properties": {
    "gn:admin1_code":"8.0",
    "gn:asciiname":"Sambirojo",
    "gn:country_code":"ID",
    "gn:dem":11,
    "gn:feature_class":"P",
    "gn:feature_code":"PPL",
    "gn:name":"Sambirojo",
    "gn:population":0,
    "gn:timezone":"Asia/Jakarta",
    "iso:country":"ID",
    "name:ind_x_preferred":[
        "Sambirojo"
    ],
    "name:und_x_variant":[
        "Sambiredjo"
    ],
    "wof:name":"Sambirojo",
    "wof:placetype":"locality"
},
  "geometry": {"coordinates":[113.3612,-8.3415],"type":"Point"}
}