{
  "type": "Feature",
  "properties": {
    "gn:admin1_code":"2",
    "gn:asciiname":"Banjar Besakih Kangin",
    "gn:country_code":"ID",
    "gn:dem":847,
    "gn:feature_class":"P",
    "gn:feature_code":"PPL",
    "gn:name":"Banjar Besakih Kangin",
    "gn:population":0,
    "gn:timezone":"Asia/Makassar",
    "iso:country":"ID",
    "name:ind_x_preferred":[
        "Banjar Besakih Kangin"
    ],
    "wof:name":"Banjar Besakih Kangin",
    "wof:placetype":"locality"
},
  "geometry": {"coordinates":[115.4462,-8.3797],"type":"Point"}
}