{
  "type": "Feature",
  "properties": {
    "gn:admin1_code":"30",
    "gn:asciiname":"Mandaling",
    "gn:country_code":"ID",
    "gn:dem":346,
    "gn:feature_class":"P",
    "gn:feature_code":"PPL",
    "gn:name":"Mandaling",
    "gn:population":0,
    "gn:timezone":"Asia/Jakarta",
    "iso:country":"ID",
    "name:ind_x_preferred":[
        "Mandaling"
    ],
    "wof:name":"Mandaling",
    "wof:placetype":"locality"
},
  "geometry": {"coordinates":[106.79111,-6.98833],"type":"Point"}
}