{
  "type": "Feature",
  "properties": {
    "gn:admin1_code":"35.0",
    "gn:asciiname":"Tokoi",
    "gn:country_code":"ID",
    "gn:dem":14,
    "gn:feature_class":"P",
    "gn:feature_code":"PPL",
    "gn:name":"Tokoi",
    "gn:population":0,
    "gn:timezone":"Asia/Jakarta",
    "iso:country":"ID",
    "name:ind_x_preferred":[
        "Tokoi"
    ],
    "wof:name":"Tokoi",
    "wof:placetype":"locality"
},
  "geometry": {"coordinates":[106.72017,-3.03483],"type":"Point"}
}