{
  "type": "Feature",
  "properties": {
    "gn:admin1_code":"7",
    "gn:asciiname":"Mejasem Kidul",
    "gn:country_code":"ID",
    "gn:dem":12,
    "gn:feature_class":"P",
    "gn:feature_code":"PPL",
    "gn:name":"Mejasem Kidul",
    "gn:population":0,
    "gn:timezone":"Asia/Jakarta",
    "iso:country":"ID",
    "name:ind_x_preferred":[
        "Mejasem Kidul"
    ],
    "wof:name":"Mejasem Kidul",
    "wof:placetype":"locality"
},
  "geometry": {"coordinates":[109.563,-6.9217],"type":"Point"}
}