{
  "type": "Feature",
  "properties": {
    "gn:admin1_code":"2",
    "gn:asciiname":"Banjar Bongkang",
    "gn:country_code":"ID",
    "gn:dem":161,
    "gn:feature_class":"P",
    "gn:feature_code":"PPL",
    "gn:name":"Banjar Bongkang",
    "gn:population":0,
    "gn:timezone":"Asia/Makassar",
    "iso:country":"ID",
    "name:ind_x_preferred":[
        "Banjar Bongkang"
    ],
    "wof:name":"Banjar Bongkang",
    "wof:placetype":"locality"
},
  "geometry": {"coordinates":[115.1739,-8.1193],"type":"Point"}
}