{
  "type": "Feature",
  "properties": {
    "gn:admin1_code":"7",
    "gn:asciiname":"Palelesan",
    "gn:country_code":"ID",
    "gn:dem":10,
    "gn:feature_class":"P",
    "gn:feature_code":"PPL",
    "gn:name":"Palelesan",
    "gn:population":0,
    "gn:timezone":"Asia/Jakarta",
    "iso:country":"ID",
    "name:ind_x_preferred":[
        "Palelesan"
    ],
    "wof:name":"Palelesan",
    "wof:placetype":"locality"
},
  "geometry": {"coordinates":[110.94670000000001,-6.8175],"type":"Point"}
}