{
  "type": "Feature",
  "properties": {
    "gn:admin1_code":"15.0",
    "gn:asciiname":"Srikaton",
    "gn:country_code":"ID",
    "gn:dem":104,
    "gn:feature_class":"P",
    "gn:feature_code":"PPL",
    "gn:name":"Srikaton",
    "gn:population":0,
    "gn:timezone":"Asia/Jakarta",
    "iso:country":"ID",
    "name:ind_x_preferred":[
        "Srikaton"
    ],
    "wof:name":"Srikaton",
    "wof:placetype":"locality"
},
  "geometry": {"coordinates":[105.20217,-5.31066],"type":"Point"}
}