{
  "type": "Feature",
  "properties": {
    "gn:admin1_code":"7.0",
    "gn:asciiname":"Pasirpalam",
    "gn:country_code":"ID",
    "gn:dem":283,
    "gn:feature_class":"P",
    "gn:feature_code":"PPL",
    "gn:name":"Pasirpalam",
    "gn:population":0,
    "gn:timezone":"Asia/Jakarta",
    "iso:country":"ID",
    "name:ind_x_preferred":[
        "Pasirpalam"
    ],
    "wof:name":"Pasirpalam",
    "wof:placetype":"locality"
},
  "geometry": {"coordinates":[108.81829999999999,-7.1021],"type":"Point"}
}