{
  "type": "Feature",
  "properties": {
    "gn:admin1_code":"30.0",
    "gn:asciiname":"Sumadra",
    "gn:country_code":"ID",
    "gn:dem":1226,
    "gn:feature_class":"P",
    "gn:feature_code":"PPL",
    "gn:name":"Sumadra",
    "gn:population":0,
    "gn:timezone":"Asia/Jakarta",
    "iso:country":"ID",
    "name:ind_x_preferred":[
        "Sumadra"
    ],
    "name:und_x_variant":[
        "Soemadra",
        "Sumadra"
    ],
    "wof:name":"Sumadra",
    "wof:placetype":"locality"
},
  "geometry": {"coordinates":[107.7251,-7.3786],"type":"Point"}
}