{
  "type": "Feature",
  "properties": {
    "gn:admin1_code":"08",
    "gn:asciiname":"Penarukan",
    "gn:country_code":"ID",
    "gn:dem":343,
    "gn:feature_class":"P",
    "gn:feature_code":"PPLA4",
    "gn:name":"Penarukan",
    "gn:population":0,
    "gn:timezone":"Asia/Jakarta",
    "iso:country":"ID",
    "name:ind_x_preferred":[
        "Penarukan"
    ],
    "wof:lang_x_official":[
        "ind"
    ],
    "wof:lang_x_spoken":[
        "ind",
        "eng"
    ],
    "wof:name":"Penarukan",
    "wof:placetype":"locality"
},
  "geometry": {"coordinates":[112.5791,-8.1354],"type":"Point"}
}