{
  "type": "Feature",
  "properties": {
    "gn:admin1_code":"30.0",
    "gn:asciiname":"Lame",
    "gn:country_code":"ID",
    "gn:dem":544,
    "gn:feature_class":"P",
    "gn:feature_code":"PPL",
    "gn:name":"Lame",
    "gn:population":0,
    "gn:timezone":"Asia/Jakarta",
    "iso:country":"ID",
    "name:ceb_x_preferred":[
        "Lame"
    ],
    "name:deu_x_preferred":[
        "Lame"
    ],
    "name:fra_x_preferred":[
        "Lame"
    ],
    "name:ind_x_preferred":[
        "Lame"
    ],
    "name:rus_x_preferred":[
        "\u041b\u0430\u043c\u0435"
    ],
    "name:srp_x_preferred":[
        "Lame"
    ],
    "name:swe_x_preferred":[
        "Lame"
    ],
    "wof:name":"Lame",
    "wof:placetype":"locality"
},
  "geometry": {"coordinates":[108.0171,-7.0147],"type":"Point"}
}