{
  "type": "Feature",
  "properties": {
    "gn:admin1_code":"39.0",
    "gn:asciiname":"Rewanggi",
    "gn:country_code":"ID",
    "gn:dem":27,
    "gn:feature_class":"P",
    "gn:feature_code":"PPL",
    "gn:name":"Rewanggi",
    "gn:population":0,
    "gn:timezone":"Asia/Jayapura",
    "iso:country":"ID",
    "name:ind_x_preferred":[
        "Rewanggi"
    ],
    "wof:name":"Rewanggi",
    "wof:placetype":"locality"
},
  "geometry": {"coordinates":[133.02763999999999,-2.15385],"type":"Point"}
}