{
  "type": "Feature",
  "properties": {
    "gn:admin1_code":"30",
    "gn:asciiname":"Rawataal",
    "gn:country_code":"ID",
    "gn:dem":227,
    "gn:feature_class":"P",
    "gn:feature_code":"PPL",
    "gn:name":"Rawataal",
    "gn:population":0,
    "gn:timezone":"Asia/Jakarta",
    "iso:country":"ID",
    "name:ind_x_preferred":[
        "Rawataal"
    ],
    "wof:name":"Rawataal",
    "wof:placetype":"locality"
},
  "geometry": {"coordinates":[107.30249999999999,-6.72],"type":"Point"}
}