{
  "type": "Feature",
  "properties": {
    "gn:admin1_code":"30",
    "gn:asciiname":"Cibinong",
    "gn:country_code":"ID",
    "gn:dem":420,
    "gn:feature_class":"P",
    "gn:feature_code":"PPL",
    "gn:name":"Cibinong",
    "gn:population":0,
    "gn:timezone":"Asia/Jakarta",
    "iso:country":"ID",
    "name:fas_x_preferred":[
        "\u0633\u06cc\u0628\u06cc\u200c\u0646\u0648\u0646\u06af"
    ],
    "name:fra_x_preferred":[
        "Cibinong"
    ],
    "name:ind_x_preferred":[
        "Cibinong"
    ],
    "name:jav_x_preferred":[
        "Cibinong"
    ],
    "name:mlg_x_preferred":[
        "Cibinong"
    ],
    "name:nor_x_preferred":[
        "Cibinong"
    ],
    "name:spa_x_preferred":[
        "Cibinong"
    ],
    "name:sun_x_preferred":[
        "Cibinong"
    ],
    "wof:lang_x_official":[
        "ind"
    ],
    "wof:lang_x_spoken":[
        "ind",
        "eng"
    ],
    "wof:name":"Cibinong",
    "wof:placetype":"locality"
},
  "geometry": {"coordinates":[107.87972000000001,-6.70722],"type":"Point"}
}