{
  "type": "Feature",
  "properties": {
    "gn:admin1_code":"31.0",
    "gn:asciiname":"Pangueng",
    "gn:country_code":"ID",
    "gn:dem":140,
    "gn:feature_class":"P",
    "gn:feature_code":"PPL",
    "gn:name":"Pangueng",
    "gn:population":0,
    "gn:timezone":"Asia/Makassar",
    "iso:country":"ID",
    "name:ind_x_preferred":[
        "Pangueng"
    ],
    "wof:name":"Pangueng",
    "wof:placetype":"locality"
},
  "geometry": {"coordinates":[125.5284,3.4224],"type":"Point"}
}