{
  "type": "Feature",
  "properties": {
    "gn:admin1_code":"2",
    "gn:asciiname":"Banjar Kejanan",
    "gn:country_code":"ID",
    "gn:dem":634,
    "gn:feature_class":"P",
    "gn:feature_code":"PPL",
    "gn:name":"Banjar Kejanan",
    "gn:population":0,
    "gn:timezone":"Asia/Makassar",
    "iso:country":"ID",
    "name:ind_x_preferred":[
        "Banjar Kejanan"
    ],
    "wof:name":"Banjar Kejanan",
    "wof:placetype":"locality"
},
  "geometry": {"coordinates":[115.3082,-8.1521],"type":"Point"}
}