{
  "type": "Feature",
  "properties": {
    "gn:country":"ID",
    "gn:fcode":"ADM3",
    "gn:pop":0,
    "iso:country":"ID",
    "name:ind_x_preferred":[
        "Kecamatan Wonokromo"
    ],
    "name:unk_x_variant":[
        "Wonokromo"
    ],
    "qs:name":"Kecamatan Wonokromo",
    "qs:photos_9r":0,
    "qs:photos_sr":0,
    "qs:pop_sr":"0",
    "wof:lang_x_official":[
        "ind"
    ],
    "wof:lang_x_spoken":[
        "ind",
        "eng"
    ],
    "wof:name":"Kecamatan Wonokromo",
    "wof:placetype":"localadmin",
    "wof:population":0
},
  "geometry": {"coordinates":[112.7363,-7.2987],"type":"Point"}
}