{
  "type": "Feature",
  "properties": {
    "gn:admin1_code":"26",
    "gn:asciiname":"Hampungsibodak",
    "gn:country_code":"ID",
    "gn:dem":3,
    "gn:feature_class":"P",
    "gn:feature_code":"PPL",
    "gn:name":"Hampungsibodak",
    "gn:population":0,
    "gn:timezone":"Asia/Jakarta",
    "iso:country":"ID",
    "name:ind_x_preferred":[
        "Hampungsibodak"
    ],
    "wof:name":"Hampungsibodak",
    "wof:placetype":"locality"
},
  "geometry": {"coordinates":[98.94889999999999,1.0507],"type":"Point"}
}