{
  "type": "Feature",
  "properties": {
    "gn:admin1_code":"28.0",
    "gn:asciiname":"Lata",
    "gn:country_code":"ID",
    "gn:dem":28,
    "gn:feature_class":"P",
    "gn:feature_code":"PPL",
    "gn:name":"Lata",
    "gn:population":0,
    "gn:timezone":"Asia/Jayapura",
    "iso:country":"ID",
    "name:heb_x_preferred":[
        "\u05dc\u05d0\u05d8\u05d4"
    ],
    "name:hun_x_preferred":[
        "Lata"
    ],
    "name:ind_x_preferred":[
        "Lata"
    ],
    "wof:lang_x_official":[
        "ind"
    ],
    "wof:lang_x_spoken":[
        "ind",
        "eng"
    ],
    "wof:name":"Lata",
    "wof:placetype":"locality"
},
  "geometry": {"coordinates":[128.22828000000001,-3.65357],"type":"Point"}
}