{
  "type": "Feature",
  "properties": {
    "gn:admin1_code":"2",
    "gn:asciiname":"Banjar Umadiwang Kawan",
    "gn:country_code":"ID",
    "gn:dem":185,
    "gn:feature_class":"P",
    "gn:feature_code":"PPL",
    "gn:name":"Banjar Umadiwang Kawan",
    "gn:population":0,
    "gn:timezone":"Asia/Makassar",
    "iso:country":"ID",
    "name:ind_x_preferred":[
        "Banjar Umadiwang Kawan"
    ],
    "wof:name":"Banjar Umadiwang Kawan",
    "wof:placetype":"locality"
},
  "geometry": {"coordinates":[115.16679999999999,-8.511],"type":"Point"}
}