{
  "type": "Feature",
  "properties": {
    "gn:admin1_code":"33.0",
    "gn:asciiname":"Cilandak",
    "gn:country_code":"ID",
    "gn:dem":52,
    "gn:feature_class":"P",
    "gn:feature_code":"PPL",
    "gn:name":"Cilandak",
    "gn:population":0,
    "gn:timezone":"Asia/Jakarta",
    "iso:country":"ID",
    "name:ind_x_preferred":[
        "Cilandak"
    ],
    "name:ita_x_preferred":[
        "Cilandak"
    ],
    "name:jav_x_preferred":[
        "Cilandhak"
    ],
    "name:msa_x_preferred":[
        "Cilandak"
    ],
    "name:nld_x_preferred":[
        "Cilandak"
    ],
    "name:pol_x_preferred":[
        "Cilandak"
    ],
    "name:spa_x_preferred":[
        "Cilandak"
    ],
    "name:sun_x_preferred":[
        "Cilandak"
    ],
    "wof:lang_x_official":[
        "ind"
    ],
    "wof:lang_x_spoken":[
        "ind",
        "eng"
    ],
    "wof:name":"Cilandak",
    "wof:placetype":"locality"
},
  "geometry": {"coordinates":[106.11799999999999,-6.4833],"type":"Point"}
}