{
  "type": "Feature",
  "properties": {
    "gn:admin1_code":"18.0",
    "gn:asciiname":"Rango",
    "gn:country_code":"ID",
    "gn:dem":144,
    "gn:feature_class":"P",
    "gn:feature_code":"PPL",
    "gn:name":"Rango",
    "gn:population":0,
    "gn:timezone":"Asia/Makassar",
    "iso:country":"ID",
    "name:ceb_x_preferred":[
        "Rango"
    ],
    "name:ces_x_preferred":[
        "Rango"
    ],
    "name:deu_x_preferred":[
        "Rango"
    ],
    "name:epo_x_preferred":[
        "Rango"
    ],
    "name:eus_x_preferred":[
        "Rango"
    ],
    "name:fin_x_preferred":[
        "Rango"
    ],
    "name:fra_x_preferred":[
        "Rango"
    ],
    "name:ind_x_preferred":[
        "Rango"
    ],
    "name:ita_x_preferred":[
        "Rango"
    ],
    "name:msa_x_preferred":[
        "Rango"
    ],
    "name:nld_x_preferred":[
        "Rango"
    ],
    "name:spa_x_preferred":[
        "Rango"
    ],
    "name:swe_x_preferred":[
        "Rango"
    ],
    "name:uzb_x_preferred":[
        "Rango"
    ],
    "wof:name":"Rango",
    "wof:placetype":"locality"
},
  "geometry": {"coordinates":[119.3484,-9.7237],"type":"Point"}
}