{
  "type": "Feature",
  "properties": {
    "gn:admin1_code":"1",
    "gn:asciiname":"Kruengkalee",
    "gn:country_code":"ID",
    "gn:dem":12,
    "gn:feature_class":"P",
    "gn:feature_code":"PPL",
    "gn:name":"Kruengkalee",
    "gn:population":0,
    "gn:timezone":"Asia/Jakarta",
    "iso:country":"ID",
    "name:ind_x_preferred":[
        "Kruengkalee"
    ],
    "wof:name":"Kruengkalee",
    "wof:placetype":"locality"
},
  "geometry": {"coordinates":[95.4053,5.5798],"type":"Point"}
}