{
  "type": "Feature",
  "properties": {
    "gn:admin1_code":"30.0",
    "gn:asciiname":"Cinyawar",
    "gn:country_code":"ID",
    "gn:dem":1046,
    "gn:feature_class":"P",
    "gn:feature_code":"PPLA4",
    "gn:name":"Cinyawar",
    "gn:population":0,
    "gn:timezone":"Asia/Jakarta",
    "iso:country":"ID",
    "name:ind_x_preferred":[
        "Cinyawar"
    ],
    "wof:lang_x_official":[
        "ind"
    ],
    "wof:lang_x_spoken":[
        "ind",
        "eng"
    ],
    "wof:name":"Cinyawar",
    "wof:placetype":"locality"
},
  "geometry": {"coordinates":[107.9241,-7.3325],"type":"Point"}
}