{
  "type": "Feature",
  "properties": {
    "gn:admin1_code":"7.0",
    "gn:asciiname":"Kalisalak",
    "gn:country_code":"ID",
    "gn:dem":705,
    "gn:feature_class":"P",
    "gn:feature_code":"PPL",
    "gn:name":"Kalisalak",
    "gn:population":0,
    "gn:timezone":"Asia/Jakarta",
    "iso:country":"ID",
    "wof:name":"Kalisalak",
    "wof:placetype":"locality"
},
  "geometry": {"coordinates":[110.32889,-7.38083],"type":"Point"}
}