{
  "type": "Feature",
  "properties": {
    "gn:admin1_code":"30.0",
    "gn:asciiname":"Cicayurtonggoh",
    "gn:country_code":"ID",
    "gn:dem":1169,
    "gn:feature_class":"P",
    "gn:feature_code":"PPL",
    "gn:name":"Cicayurtonggoh",
    "gn:population":0,
    "gn:timezone":"Asia/Jakarta",
    "iso:country":"ID",
    "name:ind_x_preferred":[
        "Cicayurtonggoh"
    ],
    "wof:name":"Cicayurtonggoh",
    "wof:placetype":"locality"
},
  "geometry": {"coordinates":[107.819,-7.2953],"type":"Point"}
}