{
  "type": "Feature",
  "properties": {
    "gn:admin1_code":"40.0",
    "gn:asciiname":"Sambu",
    "gn:country_code":"ID",
    "gn:dem":21,
    "gn:feature_class":"P",
    "gn:feature_code":"PPL",
    "gn:name":"Sambu",
    "gn:population":0,
    "gn:timezone":"Asia/Pontianak",
    "iso:country":"ID",
    "name:ceb_x_preferred":[
        "Pulau Sambu"
    ],
    "name:fra_x_preferred":[
        "Sambu"
    ],
    "name:ind_x_preferred":[
        "Pulau Sambu"
    ],
    "name:jav_x_preferred":[
        "Pulo Sambu"
    ],
    "name:swe_x_preferred":[
        "Pulau Sambu"
    ],
    "name:und_x_variant":[
        "Poelausamboe",
        "Sambo",
        "Samboe",
        "Sambu"
    ],
    "name:zho_x_preferred":[
        "\u6851\u5e03\u5c9b"
    ],
    "wof:lang_x_official":[
        "ind"
    ],
    "wof:lang_x_spoken":[
        "ind",
        "eng"
    ],
    "wof:name":"Sambu",
    "wof:placetype":"locality"
},
  "geometry": {"coordinates":[103.90158,1.15679],"type":"Point"}
}