{
  "type": "Feature",
  "properties": {
    "gn:admin1_code":"40.0",
    "gn:asciiname":"Sambu",
    "gn:country_code":"ID",
    "gn:dem":21,
    "gn:feature_class":"P",
    "gn:feature_code":"PPL",
    "gn:name":"Sambu",
    "gn:population":0,
    "gn:timezone":"Asia/Pontianak",
    "iso:country":"ID",
    "name:und_x_variant":[
        "Poelausamboe",
        "Sambo",
        "Samboe",
        "Sambu"
    ],
    "wof:name":"Sambu",
    "wof:placetype":"locality"
},
  "geometry": {"coordinates":[103.90158,1.15679],"type":"Point"}
}