{
  "type": "Feature",
  "properties": {
    "gn:admin1_code":"17",
    "gn:asciiname":"Gubukpande",
    "gn:country_code":"ID",
    "gn:dem":42,
    "gn:feature_class":"P",
    "gn:feature_code":"PPL",
    "gn:name":"Gubukpande",
    "gn:population":0,
    "gn:timezone":"Asia/Makassar",
    "iso:country":"ID",
    "name:ind_x_preferred":[
        "Gubukpande"
    ],
    "wof:name":"Gubukpande",
    "wof:placetype":"locality"
},
  "geometry": {"coordinates":[116.6078,-8.6211],"type":"Point"}
}