{
  "type": "Feature",
  "properties": {
    "gn:admin1_code":"26",
    "gn:asciiname":"Pondok Empat",
    "gn:country_code":"ID",
    "gn:dem":93,
    "gn:feature_class":"P",
    "gn:feature_code":"PPL",
    "gn:name":"Pondok Empat",
    "gn:population":0,
    "gn:timezone":"Asia/Jakarta",
    "iso:country":"ID",
    "name:ind_x_preferred":[
        "Pondok Empat"
    ],
    "name:und_x_variant":[
        "Pondok 4"
    ],
    "wof:name":"Pondok Empat",
    "wof:placetype":"locality"
},
  "geometry": {"coordinates":[99.00620000000001,3.2377],"type":"Point"}
}