{
  "type": "Feature",
  "properties": {
    "gn:admin1_code":"22.0",
    "gn:asciiname":"Lamilai",
    "gn:country_code":"ID",
    "gn:dem":54,
    "gn:feature_class":"P",
    "gn:feature_code":"PPL",
    "gn:name":"Lamilai",
    "gn:population":0,
    "gn:timezone":"Asia/Makassar",
    "iso:country":"ID",
    "name:ind_x_preferred":[
        "Lamilai"
    ],
    "wof:name":"Lamilai",
    "wof:placetype":"locality"
},
  "geometry": {"coordinates":[122.0254,-3.8858],"type":"Point"}
}