{
  "type": "Feature",
  "properties": {
    "gn:admin1_code":"33.0",
    "gn:asciiname":"Sukadiri",
    "gn:country_code":"ID",
    "gn:dem":229,
    "gn:feature_class":"P",
    "gn:feature_code":"PPL",
    "gn:name":"Sukadiri",
    "gn:population":0,
    "gn:timezone":"Asia/Jakarta",
    "iso:country":"ID",
    "name:ind_x_preferred":[
        "Sukadiri"
    ],
    "wof:name":"Sukadiri",
    "wof:placetype":"locality"
},
  "geometry": {"coordinates":[106.1088,-6.2344],"type":"Point"}
}