{
  "type": "Feature",
  "properties": {
    "gn:admin1_code":"08",
    "gn:asciiname":"Duren",
    "gn:country_code":"ID",
    "gn:dem":440,
    "gn:feature_class":"P",
    "gn:feature_code":"PPL",
    "gn:name":"Duren",
    "gn:population":0,
    "gn:timezone":"Asia/Jakarta",
    "iso:country":"ID",
    "name:ind_x_preferred":[
        "Duren"
    ],
    "name:und_x_variant":[
        "Ardjosari",
        "Arjosari"
    ],
    "wof:lang_x_official":[
        "ind"
    ],
    "wof:lang_x_spoken":[
        "ind",
        "eng"
    ],
    "wof:name":"Duren",
    "wof:placetype":"locality"
},
  "geometry": {"coordinates":[112.6079,-8.0083],"type":"Point"}
}