{
  "type": "Feature",
  "properties": {
    "gn:admin1_code":"7",
    "gn:asciiname":"Craken",
    "gn:country_code":"ID",
    "gn:dem":664,
    "gn:feature_class":"P",
    "gn:feature_code":"PPL",
    "gn:name":"Craken",
    "gn:population":0,
    "gn:timezone":"Asia/Jakarta",
    "iso:country":"ID",
    "name:ind_x_preferred":[
        "Craken"
    ],
    "wof:name":"Craken",
    "wof:placetype":"locality"
},
  "geometry": {"coordinates":[110.14833,-7.24361],"type":"Point"}
}