{
  "type": "Feature",
  "properties": {
    "gn:admin1_code":"30.0",
    "gn:asciiname":"Cibanten",
    "gn:country_code":"ID",
    "gn:dem":157,
    "gn:feature_class":"P",
    "gn:feature_code":"PPLA4",
    "gn:name":"Cibanten",
    "gn:population":0,
    "gn:timezone":"Asia/Jakarta",
    "iso:country":"ID",
    "name:ind_x_preferred":[
        "Cibanten"
    ],
    "name:und_x_variant":[
        "Tjibanten",
        "Cibanten"
    ],
    "wof:lang_x_official":[
        "ind"
    ],
    "wof:lang_x_spoken":[
        "ind",
        "eng"
    ],
    "wof:name":"Cibanten",
    "wof:placetype":"locality"
},
  "geometry": {"coordinates":[108.4029,-7.6941],"type":"Point"}
}