{
  "type": "Feature",
  "properties": {
    "gn:admin1_code":"8",
    "gn:asciiname":"Ngablak",
    "gn:country_code":"ID",
    "gn:dem":14,
    "gn:feature_class":"P",
    "gn:feature_code":"PPL",
    "gn:name":"Ngablak",
    "gn:population":0,
    "gn:timezone":"Asia/Jakarta",
    "iso:country":"ID",
    "name:ind_x_preferred":[
        "Ngablak"
    ],
    "wof:name":"Ngablak",
    "wof:placetype":"locality"
},
  "geometry": {"coordinates":[112.24169999999999,-7.0972],"type":"Point"}
}