{
  "type": "Feature",
  "properties": {
    "gn:admin1_code":"18.0",
    "gn:asciiname":"Tamping",
    "gn:country_code":"ID",
    "gn:dem":15,
    "gn:feature_class":"P",
    "gn:feature_code":"PPL",
    "gn:name":"Tamping",
    "gn:population":0,
    "gn:timezone":"Asia/Makassar",
    "iso:country":"ID",
    "name:ind_x_preferred":[
        "Tamping"
    ],
    "wof:name":"Tamping",
    "wof:placetype":"locality"
},
  "geometry": {"coordinates":[120.84569999999999,-8.3559],"type":"Point"}
}