{
  "type": "Feature",
  "properties": {
    "gn:admin1_code":"26",
    "gn:asciiname":"Simarloting",
    "gn:country_code":"ID",
    "gn:dem":325,
    "gn:feature_class":"P",
    "gn:feature_code":"PPL",
    "gn:name":"Simarloting",
    "gn:population":0,
    "gn:timezone":"Asia/Jakarta",
    "iso:country":"ID",
    "name:ind_x_preferred":[
        "Simarloting"
    ],
    "wof:name":"Simarloting",
    "wof:placetype":"locality"
},
  "geometry": {"coordinates":[99.41506,1.4449],"type":"Point"}
}