{
  "type": "Feature",
  "properties": {
    "gn:admin1_code":"26",
    "gn:asciiname":"Selingkar",
    "gn:country_code":"ID",
    "gn:dem":3,
    "gn:feature_class":"P",
    "gn:feature_code":"PPL",
    "gn:name":"Selingkar",
    "gn:population":0,
    "gn:timezone":"Asia/Jakarta",
    "iso:country":"ID",
    "name:ind_x_preferred":[
        "Selingkar"
    ],
    "wof:name":"Selingkar",
    "wof:placetype":"locality"
},
  "geometry": {"coordinates":[98.3978,3.999],"type":"Point"}
}