{
  "type": "Feature",
  "properties": {
    "gn:admin1_code":"18.0",
    "gn:asciiname":"Paubuku",
    "gn:country_code":"ID",
    "gn:dem":706,
    "gn:feature_class":"P",
    "gn:feature_code":"PPL",
    "gn:name":"Paubuku",
    "gn:population":0,
    "gn:timezone":"Asia/Makassar",
    "iso:country":"ID",
    "name:ind_x_preferred":[
        "Paubuku"
    ],
    "wof:name":"Paubuku",
    "wof:placetype":"locality"
},
  "geometry": {"coordinates":[121.1172,-8.7916],"type":"Point"}
}