{
  "type": "Feature",
  "properties": {
    "gn:admin1_code":"38",
    "gn:asciiname":"Bulutosompo",
    "gn:country_code":"ID",
    "gn:dem":14,
    "gn:feature_class":"P",
    "gn:feature_code":"PPL",
    "gn:name":"Bulutosompo",
    "gn:population":0,
    "gn:timezone":"Asia/Makassar",
    "iso:country":"ID",
    "name:ind_x_preferred":[
        "Bulutosompo"
    ],
    "wof:name":"Bulutosompo",
    "wof:placetype":"locality"
},
  "geometry": {"coordinates":[120.1478,-4.1227],"type":"Point"}
}