{
  "type": "Feature",
  "properties": {
    "gn:admin1_code":"38",
    "gn:asciiname":"Pangoki",
    "gn:country_code":"ID",
    "gn:dem":166,
    "gn:feature_class":"P",
    "gn:feature_code":"PPL",
    "gn:name":"Pangoki",
    "gn:population":0,
    "gn:timezone":"Asia/Makassar",
    "iso:country":"ID",
    "name:ind_x_preferred":[
        "Pangoki"
    ],
    "wof:name":"Pangoki",
    "wof:placetype":"locality"
},
  "geometry": {"coordinates":[120.40470000000001,-5.415],"type":"Point"}
}