{
  "type": "Feature",
  "properties": {
    "gn:admin1_code":"1",
    "gn:asciiname":"Air Halim Rambung",
    "gn:country_code":"ID",
    "gn:dem":35,
    "gn:feature_class":"P",
    "gn:feature_code":"PPL",
    "gn:name":"Air Halim Rambung",
    "gn:population":0,
    "gn:timezone":"Asia/Jakarta",
    "iso:country":"ID",
    "name:ind_x_preferred":[
        "Air Halim Rambung"
    ],
    "wof:name":"Air Halim Rambung",
    "wof:placetype":"locality"
},
  "geometry": {"coordinates":[99.6185,2.8587],"type":"Point"}
}