{
  "type": "Feature",
  "properties": {
    "gn:admin1_code":"08",
    "gn:asciiname":"Bendomungal",
    "gn:country_code":"ID",
    "gn:dem":16,
    "gn:feature_class":"P",
    "gn:feature_code":"PPL",
    "gn:name":"Bendomungal",
    "gn:population":0,
    "gn:timezone":"Asia/Jakarta",
    "iso:country":"ID",
    "name:ind_x_preferred":[
        "Bendomungal"
    ],
    "name:und_x_variant":[
        "Kedungmungol"
    ],
    "wof:name":"Bendomungal",
    "wof:placetype":"locality"
},
  "geometry": {"coordinates":[112.58839999999999,-7.4971],"type":"Point"}
}