{
  "type": "Feature",
  "properties": {
    "gn:admin1_code":"8.0",
    "gn:asciiname":"Ngrancang",
    "gn:country_code":"ID",
    "gn:dem":62,
    "gn:feature_class":"P",
    "gn:feature_code":"PPL",
    "gn:name":"Ngrancang",
    "gn:population":0,
    "gn:timezone":"Asia/Jakarta",
    "iso:country":"ID",
    "name:ind_x_preferred":[
        "Ngrancang"
    ],
    "wof:name":"Ngrancang",
    "wof:placetype":"locality"
},
  "geometry": {"coordinates":[111.60209999999999,-7.2815],"type":"Point"}
}