{
  "type": "Feature",
  "properties": {
    "gn:admin1_code":"26",
    "gn:asciiname":"Lumbabuntu",
    "gn:country_code":"ID",
    "gn:dem":248,
    "gn:feature_class":"P",
    "gn:feature_code":"PPL",
    "gn:name":"Lumbabuntu",
    "gn:population":0,
    "gn:timezone":"Asia/Jakarta",
    "iso:country":"ID",
    "name:ind_x_preferred":[
        "Lumbabuntu"
    ],
    "wof:name":"Lumbabuntu",
    "wof:placetype":"locality"
},
  "geometry": {"coordinates":[99.13590000000001,2.9816],"type":"Point"}
}