{
  "type": "Feature",
  "properties": {
    "gn:admin1_code":"34",
    "gn:asciiname":"Makmurbersama",
    "gn:country_code":"ID",
    "gn:dem":30,
    "gn:feature_class":"P",
    "gn:feature_code":"PPL",
    "gn:name":"Makmurbersama",
    "gn:population":0,
    "gn:timezone":"Asia/Makassar",
    "iso:country":"ID",
    "name:ind_x_preferred":[
        "Makmurbersama"
    ],
    "wof:name":"Makmurbersama",
    "wof:placetype":"locality"
},
  "geometry": {"coordinates":[122.56100000000001,0.7013],"type":"Point"}
}