{
  "type": "Feature",
  "properties": {
    "gn:admin1_code":"7",
    "gn:asciiname":"Tlogowarno",
    "gn:country_code":"ID",
    "gn:dem":29,
    "gn:feature_class":"P",
    "gn:feature_code":"PPL",
    "gn:name":"Tlogowarno",
    "gn:population":0,
    "gn:timezone":"Asia/Jakarta",
    "iso:country":"ID",
    "name:ind_x_preferred":[
        "Tlogowarno"
    ],
    "wof:name":"Tlogowarno",
    "wof:placetype":"locality"
},
  "geometry": {"coordinates":[109.77278,-7.70667],"type":"Point"}
}