{
  "type": "Feature",
  "properties": {
    "gn:admin1_code":"8.0",
    "gn:asciiname":"Sukowati",
    "gn:country_code":"ID",
    "gn:dem":6,
    "gn:feature_class":"P",
    "gn:feature_code":"PPL",
    "gn:name":"Sukowati",
    "gn:population":0,
    "gn:timezone":"Asia/Jakarta",
    "iso:country":"ID",
    "name:ind_x_preferred":[
        "Sukowati"
    ],
    "wof:name":"Sukowati",
    "wof:placetype":"locality"
},
  "geometry": {"coordinates":[112.39579999999999,-6.8758],"type":"Point"}
}