{
  "type": "Feature",
  "properties": {
    "gn:admin1_code":"15.0",
    "gn:asciiname":"Bumbon",
    "gn:country_code":"ID",
    "gn:dem":855,
    "gn:feature_class":"P",
    "gn:feature_code":"PPL",
    "gn:name":"Bumbon",
    "gn:population":0,
    "gn:timezone":"Asia/Jakarta",
    "iso:country":"ID",
    "name:ind_x_preferred":[
        "Bumbon"
    ],
    "wof:name":"Bumbon",
    "wof:placetype":"locality"
},
  "geometry": {"coordinates":[104.16057000000001,-5.07906],"type":"Point"}
}