{
  "type": "Feature",
  "properties": {
    "gn:admin1_code":"18.0",
    "gn:asciiname":"Waikabolor",
    "gn:country_code":"ID",
    "gn:dem":530,
    "gn:feature_class":"P",
    "gn:feature_code":"PPL",
    "gn:name":"Waikabolor",
    "gn:population":0,
    "gn:timezone":"Asia/Makassar",
    "iso:country":"ID",
    "name:ind_x_preferred":[
        "Waikabolor"
    ],
    "wof:name":"Waikabolor",
    "wof:placetype":"locality"
},
  "geometry": {"coordinates":[119.527,-9.5822],"type":"Point"}
}