{
  "type": "Feature",
  "properties": {
    "gn:admin1_code":"18.0",
    "gn:asciiname":"Tumu",
    "gn:country_code":"ID",
    "gn:dem":495,
    "gn:feature_class":"P",
    "gn:feature_code":"PPL",
    "gn:name":"Tumu",
    "gn:population":0,
    "gn:timezone":"Asia/Makassar",
    "iso:country":"ID",
    "name:ceb_x_preferred":[
        "Tumu"
    ],
    "name:deu_x_preferred":[
        "Tumu"
    ],
    "name:ind_x_preferred":[
        "Tumu"
    ],
    "name:nld_x_preferred":[
        "Tumu"
    ],
    "name:swe_x_preferred":[
        "Tumu"
    ],
    "wof:lang_x_official":[
        "ind"
    ],
    "wof:lang_x_spoken":[
        "ind",
        "eng"
    ],
    "wof:name":"Tumu",
    "wof:placetype":"locality"
},
  "geometry": {"coordinates":[124.70650000000001,-9.6908],"type":"Point"}
}