{
  "type": "Feature",
  "properties": {
    "gn:admin1_code":"33.0",
    "gn:asciiname":"Babakancisoka",
    "gn:country_code":"ID",
    "gn:dem":397,
    "gn:feature_class":"P",
    "gn:feature_code":"PPL",
    "gn:name":"Babakancisoka",
    "gn:population":0,
    "gn:timezone":"Asia/Jakarta",
    "iso:country":"ID",
    "name:ind_x_preferred":[
        "Babakancisoka"
    ],
    "wof:name":"Babakancisoka",
    "wof:placetype":"locality"
},
  "geometry": {"coordinates":[106.4029,-6.6253],"type":"Point"}
}