{
  "type": "Feature",
  "properties": {
    "gn:admin1_code":"0.0",
    "gn:asciiname":"Udjungtandjung",
    "gn:country_code":"ID",
    "gn:dem":43,
    "gn:feature_class":"P",
    "gn:feature_code":"PPL",
    "gn:name":"Udjungtandjung",
    "gn:population":0,
    "gn:timezone":"Asia/Jakarta",
    "iso:country":"ID",
    "name:ind_x_preferred":[
        "Udjungtandjung"
    ],
    "wof:name":"Udjungtandjung",
    "wof:placetype":"locality"
},
  "geometry": {"coordinates":[99.60549,0.25844],"type":"Point"}
}