{
  "type": "Feature",
  "properties": {
    "gn:admin1_code":"41",
    "gn:asciiname":"Sikatuang",
    "gn:country_code":"ID",
    "gn:dem":108,
    "gn:feature_class":"P",
    "gn:feature_code":"PPL",
    "gn:name":"Sikatuang",
    "gn:population":0,
    "gn:timezone":"Asia/Makassar",
    "iso:country":"ID",
    "name:ind_x_preferred":[
        "Sikatuang"
    ],
    "wof:name":"Sikatuang",
    "wof:placetype":"locality"
},
  "geometry": {"coordinates":[119.09229999999999,-3.3308],"type":"Point"}
}