{
  "type": "Feature",
  "properties": {
    "gn:admin1_code":"30.0",
    "gn:asciiname":"Putrajawa",
    "gn:country_code":"ID",
    "gn:dem":565,
    "gn:feature_class":"P",
    "gn:feature_code":"PPLA4",
    "gn:name":"Putrajawa",
    "gn:population":0,
    "gn:timezone":"Asia/Jakarta",
    "iso:country":"ID",
    "name:ind_x_preferred":[
        "Putrajawa"
    ],
    "name:und_x_variant":[
        "Poetradjawa"
    ],
    "wof:name":"Putrajawa",
    "wof:placetype":"locality"
},
  "geometry": {"coordinates":[108.01090000000001,-7.0054],"type":"Point"}
}