{
  "type": "Feature",
  "properties": {
    "gn:admin1_code":"8",
    "gn:asciiname":"Tawangsari",
    "gn:country_code":"ID",
    "gn:dem":50,
    "gn:feature_class":"P",
    "gn:feature_code":"PPL",
    "gn:name":"Tawangsari",
    "gn:population":0,
    "gn:timezone":"Asia/Jakarta",
    "iso:country":"ID",
    "name:ind_x_preferred":[
        "Tawangsari"
    ],
    "wof:name":"Tawangsari",
    "wof:placetype":"locality"
},
  "geometry": {"coordinates":[111.88079999999999,-7.0927],"type":"Point"}
}