{
  "type": "Feature",
  "properties": {
    "gn:admin1_code":"0.0",
    "gn:asciiname":"Pamulawan",
    "gn:cc2":"ID",
    "gn:country_code":"ID",
    "gn:dem":46,
    "gn:feature_class":"P",
    "gn:feature_code":"PPL",
    "gn:name":"Pamulawan",
    "gn:population":0,
    "gn:timezone":"Asia/Makassar",
    "iso:country":"ID",
    "name:und_x_variant":[
        "Pamoelawan",
        "Pamulawan"
    ],
    "wof:lang_x_official":[
        "ind"
    ],
    "wof:lang_x_spoken":[
        "ind",
        "eng"
    ],
    "wof:name":"Pamulawan",
    "wof:placetype":"locality"
},
  "geometry": {"coordinates":[115.68333,-3.36667],"type":"Point"}
}