{
  "type": "Feature",
  "properties": {
    "gn:admin1_code":"26",
    "gn:asciiname":"Rinangolngolan",
    "gn:country_code":"ID",
    "gn:dem":1201,
    "gn:feature_class":"P",
    "gn:feature_code":"PPL",
    "gn:name":"Rinangolngolan",
    "gn:population":0,
    "gn:timezone":"Asia/Jakarta",
    "iso:country":"ID",
    "name:ind_x_preferred":[
        "Rinangolngolan"
    ],
    "wof:name":"Rinangolngolan",
    "wof:placetype":"locality"
},
  "geometry": {"coordinates":[99.1534,2.0235],"type":"Point"}
}