{
  "type": "Feature",
  "properties": {
    "gn:admin1_code":"7.0",
    "gn:asciiname":"Doplang",
    "gn:country_code":"ID",
    "gn:dem":82,
    "gn:feature_class":"P",
    "gn:feature_code":"PPL",
    "gn:name":"Doplang",
    "gn:population":0,
    "gn:timezone":"Asia/Jakarta",
    "iso:country":"ID",
    "name:ind_x_preferred":[
        "Doplang"
    ],
    "name:und_x_variant":[
        "Djati",
        "Jati"
    ],
    "wof:name":"Doplang",
    "wof:placetype":"locality"
},
  "geometry": {"coordinates":[111.28943999999998,-7.18472],"type":"Point"}
}