{
  "type": "Feature",
  "properties": {
    "gn:admin1_code":"7.0",
    "gn:asciiname":"Moncongos",
    "gn:country_code":"ID",
    "gn:dem":614,
    "gn:feature_class":"P",
    "gn:feature_code":"PPL",
    "gn:name":"Moncongos",
    "gn:population":0,
    "gn:timezone":"Asia/Jakarta",
    "iso:country":"ID",
    "name:ind_x_preferred":[
        "Moncongos"
    ],
    "name:und_x_variant":[
        "Mentjongos"
    ],
    "wof:lang_x_official":[
        "ind"
    ],
    "wof:lang_x_spoken":[
        "ind",
        "eng"
    ],
    "wof:name":"Moncongos",
    "wof:placetype":"locality"
},
  "geometry": {"coordinates":[108.7441,-7.1813],"type":"Point"}
}