{
  "type": "Feature",
  "properties": {
    "gn:admin1_code":"1.0",
    "gn:asciiname":"Birim-rayeu",
    "gn:country_code":"ID",
    "gn:dem":1,
    "gn:feature_class":"P",
    "gn:feature_code":"PPL",
    "gn:name":"Birim-rayeu",
    "gn:population":0,
    "gn:timezone":"Asia/Jakarta",
    "iso:country":"ID",
    "name:ind_x_preferred":[
        "Birim-rayeu"
    ],
    "name:und_x_variant":[
        "Birimrajeu",
        "Birem Rajeu"
    ],
    "wof:lang_x_official":[
        "ind"
    ],
    "wof:lang_x_spoken":[
        "ind",
        "eng"
    ],
    "wof:name":"Birim-rayeu",
    "wof:placetype":"locality"
},
  "geometry": {"coordinates":[97.94,4.5391],"type":"Point"}
}