{
  "type": "Feature",
  "properties": {
    "gn:admin1_code":"8.0",
    "gn:asciiname":"Karuk",
    "gn:country_code":"ID",
    "gn:dem":21,
    "gn:feature_class":"P",
    "gn:feature_code":"PPL",
    "gn:name":"Karuk",
    "gn:population":0,
    "gn:timezone":"Asia/Jakarta",
    "iso:country":"ID",
    "name:bul_x_preferred":[
        "\u041a\u0430\u0440\u0443\u043a"
    ],
    "name:cat_x_preferred":[
        "Karuks"
    ],
    "name:ces_x_preferred":[
        "Karukov\u00e9"
    ],
    "name:deu_x_preferred":[
        "Karok"
    ],
    "name:hrv_x_preferred":[
        "Karok Indijanci"
    ],
    "name:ind_x_preferred":[
        "Karuk"
    ],
    "name:nld_x_preferred":[
        "Karok"
    ],
    "name:spa_x_preferred":[
        "Karok"
    ],
    "name:ukr_x_preferred":[
        "\u041a\u0430\u0440\u0443\u043a"
    ],
    "wof:name":"Karuk",
    "wof:placetype":"locality"
},
  "geometry": {"coordinates":[113.494,-8.2897],"type":"Point"}
}