{
  "type": "Feature",
  "properties": {
    "gn:admin1_code":"24",
    "gn:asciiname":"Puncakkota",
    "gn:country_code":"ID",
    "gn:dem":553,
    "gn:feature_class":"P",
    "gn:feature_code":"PPL",
    "gn:name":"Puncakkota",
    "gn:population":0,
    "gn:timezone":"Asia/Jakarta",
    "iso:country":"ID",
    "name:ind_x_preferred":[
        "Puncakkota"
    ],
    "wof:name":"Puncakkota",
    "wof:placetype":"locality"
},
  "geometry": {"coordinates":[100.55383999999999,-0.52498],"type":"Point"}
}