{
  "type": "Feature",
  "properties": {
    "gn:admin1_code":"1",
    "gn:asciiname":"Peundawa Puntong",
    "gn:country_code":"ID",
    "gn:dem":9,
    "gn:feature_class":"P",
    "gn:feature_code":"PPL",
    "gn:name":"Peundawa Puntong",
    "gn:population":0,
    "gn:timezone":"Asia/Jakarta",
    "iso:country":"ID",
    "name:ind_x_preferred":[
        "Peundawa Puntong"
    ],
    "name:und_x_variant":[
        "Peudawapuntong"
    ],
    "wof:lang_x_official":[
        "ind"
    ],
    "wof:lang_x_spoken":[
        "ind",
        "eng"
    ],
    "wof:name":"Peundawa Puntong",
    "wof:placetype":"locality"
},
  "geometry": {"coordinates":[97.7931,4.9267],"type":"Point"}
}