{
  "type": "Feature",
  "properties": {
    "gn:admin1_code":"1",
    "gn:asciiname":"Palohawe",
    "gn:country_code":"ID",
    "gn:dem":13,
    "gn:feature_class":"P",
    "gn:feature_code":"PPL",
    "gn:name":"Palohawe",
    "gn:population":0,
    "gn:timezone":"Asia/Jakarta",
    "iso:country":"ID",
    "name:ind_x_preferred":[
        "Palohawe"
    ],
    "wof:name":"Palohawe",
    "wof:placetype":"locality"
},
  "geometry": {"coordinates":[96.96680000000001,5.2351],"type":"Point"}
}