{
  "type": "Feature",
  "properties": {
    "gn:admin1_code":"8",
    "gn:asciiname":"Sedudut",
    "gn:country_code":"ID",
    "gn:dem":475,
    "gn:feature_class":"P",
    "gn:feature_code":"PPL",
    "gn:name":"Sedudut",
    "gn:population":0,
    "gn:timezone":"Asia/Jakarta",
    "iso:country":"ID",
    "name:ind_x_preferred":[
        "Sedudut"
    ],
    "wof:name":"Sedudut",
    "wof:placetype":"locality"
},
  "geometry": {"coordinates":[112.59690000000001,-7.9908],"type":"Point"}
}