{
  "type": "Feature",
  "properties": {
    "gn:admin1_code":"15.0",
    "gn:asciiname":"Brajadewa",
    "gn:country_code":"ID",
    "gn:dem":14,
    "gn:feature_class":"P",
    "gn:feature_code":"PPL",
    "gn:name":"Brajadewa",
    "gn:population":0,
    "gn:timezone":"Asia/Jakarta",
    "iso:country":"ID",
    "name:ind_x_preferred":[
        "Brajadewa"
    ],
    "wof:name":"Brajadewa",
    "wof:placetype":"locality"
},
  "geometry": {"coordinates":[105.74323,-5.22958],"type":"Point"}
}