{
  "type": "Feature",
  "properties": {
    "gn:admin1_code":"32.0",
    "gn:asciiname":"Umbulan Simpangampat",
    "gn:country_code":"ID",
    "gn:dem":24,
    "gn:feature_class":"P",
    "gn:feature_code":"PPL",
    "gn:name":"Umbulan Simpangampat",
    "gn:population":0,
    "gn:timezone":"Asia/Jakarta",
    "iso:country":"ID",
    "name:ind_x_preferred":[
        "Umbulan Simpangampat"
    ],
    "wof:name":"Umbulan Simpangampat",
    "wof:placetype":"locality"
},
  "geometry": {"coordinates":[105.20381999999999,-3.75376],"type":"Point"}
}