{
  "type": "Feature",
  "properties": {
    "iso:country":"ID",
    "qs:name":"Tegal Mengkeb",
    "qs:name_adm0":"Indonesia",
    "qs:name_adm1":"Bali",
    "qs:photos":55,
    "qs:photos_1k":11,
    "qs:photos_9k":1,
    "qs:photos_9r":2,
    "qs:photos_all":55,
    "qs:photos_sr":2,
    "qs:placetype":"Town",
    "qs:pop_sr":"0",
    "wof:lang_x_official":[
        "ind"
    ],
    "wof:lang_x_spoken":[
        "ind",
        "eng"
    ],
    "wof:name":"Tegal Mengkeb",
    "wof:placetype":"locality"
},
  "geometry": {"coordinates":[115.00979599999999,-8.536207],"type":"Point"}
}