{
  "type": "Feature",
  "properties": {
    "gn:admin1_code":"17",
    "gn:asciiname":"Padangbai",
    "gn:country_code":"ID",
    "gn:dem":563,
    "gn:feature_class":"P",
    "gn:feature_code":"PPL",
    "gn:name":"Padangbai",
    "gn:population":0,
    "gn:timezone":"Asia/Makassar",
    "iso:country":"ID",
    "name:deu_x_preferred":[
        "Padang Bai"
    ],
    "name:fra_x_preferred":[
        "Padangbai"
    ],
    "name:ind_x_preferred":[
        "Padangbai"
    ],
    "name:jav_x_preferred":[
        "Padangbai"
    ],
    "name:jpn_x_preferred":[
        "\u30d1\u30c0\u30f3\u30d0\u30a4"
    ],
    "name:msa_x_preferred":[
        "Padangbai"
    ],
    "name:nld_x_preferred":[
        "Padangbai"
    ],
    "wof:lang_x_official":[
        "ind"
    ],
    "wof:lang_x_spoken":[
        "ind",
        "eng"
    ],
    "wof:name":"Padangbai",
    "wof:placetype":"locality"
},
  "geometry": {"coordinates":[116.5115,-8.5236],"type":"Point"}
}