{
  "type": "Feature",
  "properties": {
    "gn:admin1_code":"33",
    "gn:asciiname":"Sabrang Kidul",
    "gn:country_code":"ID",
    "gn:dem":35,
    "gn:feature_class":"P",
    "gn:feature_code":"PPL",
    "gn:name":"Sabrang Kidul",
    "gn:population":0,
    "gn:timezone":"Asia/Jakarta",
    "iso:country":"ID",
    "name:ind_x_preferred":[
        "Sabrang Kidul"
    ],
    "wof:name":"Sabrang Kidul",
    "wof:placetype":"locality"
},
  "geometry": {"coordinates":[106.3433,-6.3043],"type":"Point"}
}