{
  "type": "Feature",
  "properties": {
    "gn:admin1_code":"30",
    "gn:asciiname":"Pamoyanan",
    "gn:country_code":"ID",
    "gn:dem":690,
    "gn:feature_class":"P",
    "gn:feature_code":"PPL",
    "gn:name":"Pamoyanan",
    "gn:population":0,
    "gn:timezone":"Asia/Jakarta",
    "iso:country":"ID",
    "name:ind_x_preferred":[
        "Pamoyanan"
    ],
    "wof:name":"Pamoyanan",
    "wof:placetype":"locality"
},
  "geometry": {"coordinates":[107.37917,-6.95472],"type":"Point"}
}