{
  "type": "Feature",
  "properties": {
    "gn:admin1_code":"1",
    "gn:asciiname":"Seununddon",
    "gn:country_code":"ID",
    "gn:dem":2,
    "gn:feature_class":"P",
    "gn:feature_code":"PPL",
    "gn:name":"Seununddon",
    "gn:population":0,
    "gn:timezone":"Asia/Jakarta",
    "iso:country":"ID",
    "name:ind_x_preferred":[
        "Seununddon"
    ],
    "wof:name":"Seununddon",
    "wof:placetype":"locality"
},
  "geometry": {"coordinates":[97.43989999999999,5.1804],"type":"Point"}
}