{
  "type": "Feature",
  "properties": {
    "gn:admin1_code":"18.0",
    "gn:asciiname":"Oesoot",
    "gn:country_code":"ID",
    "gn:dem":310,
    "gn:feature_class":"P",
    "gn:feature_code":"PPLA4",
    "gn:name":"Oesoot",
    "gn:population":0,
    "gn:timezone":"Asia/Makassar",
    "iso:country":"ID",
    "name:ind_x_preferred":[
        "Oesoot"
    ],
    "wof:name":"Oesoot",
    "wof:placetype":"locality"
},
  "geometry": {"coordinates":[124.7223,-9.7259],"type":"Point"}
}