{
  "type": "Feature",
  "properties": {
    "gn:admin1_code":"30.0",
    "gn:asciiname":"Cihuni",
    "gn:country_code":"ID",
    "gn:dem":647,
    "gn:feature_class":"P",
    "gn:feature_code":"PPL",
    "gn:name":"Cihuni",
    "gn:population":0,
    "gn:timezone":"Asia/Jakarta",
    "iso:country":"ID",
    "name:ind_x_preferred":[
        "Cihuni"
    ],
    "name:und_x_variant":[
        "Tjihoeni"
    ],
    "wof:lang_x_official":[
        "ind"
    ],
    "wof:lang_x_spoken":[
        "ind",
        "eng"
    ],
    "wof:name":"Cihuni",
    "wof:placetype":"locality"
},
  "geometry": {"coordinates":[107.91070000000001,-7.457],"type":"Point"}
}