{
  "type": "Feature",
  "properties": {
    "gn:admin1_code":"30.0",
    "gn:asciiname":"Ciherang Girang",
    "gn:country_code":"ID",
    "gn:dem":1013,
    "gn:feature_class":"P",
    "gn:feature_code":"PPL",
    "gn:name":"Ciherang Girang",
    "gn:population":0,
    "gn:timezone":"Asia/Jakarta",
    "iso:country":"ID",
    "name:ind_x_preferred":[
        "Ciherang Girang"
    ],
    "wof:name":"Ciherang Girang",
    "wof:placetype":"locality"
},
  "geometry": {"coordinates":[107.2133,-7.077],"type":"Point"}
}