{
  "type": "Feature",
  "properties": {
    "gn:admin1_code":"0.0",
    "gn:asciiname":"Glen Nevis",
    "gn:country_code":"ID",
    "gn:dem":416,
    "gn:feature_class":"P",
    "gn:feature_code":"PPL",
    "gn:name":"Glen Nevis",
    "gn:population":0,
    "gn:timezone":"Asia/Jakarta",
    "iso:country":"ID",
    "name:ceb_x_preferred":[
        "Glen Nevis"
    ],
    "name:deu_x_preferred":[
        "Glen Nevis"
    ],
    "name:eus_x_preferred":[
        "Glen Nevis"
    ],
    "name:fra_x_preferred":[
        "Glen Nevis"
    ],
    "name:gla_x_preferred":[
        "Gleann Nibheis"
    ],
    "name:pol_x_preferred":[
        "Glen Nevis"
    ],
    "name:sco_x_preferred":[
        "Glen Nevis"
    ],
    "wof:lang_x_official":[
        "ind"
    ],
    "wof:lang_x_spoken":[
        "ind",
        "eng"
    ],
    "wof:name":"Glen Nevis",
    "wof:placetype":"locality"
},
  "geometry": {"coordinates":[113.96666999999999,-8.31667],"type":"Point"}
}