{
  "type": "Feature",
  "properties": {
    "gn:admin1_code":"8.0",
    "gn:asciiname":"Cengglong",
    "gn:country_code":"ID",
    "gn:dem":636,
    "gn:feature_class":"P",
    "gn:feature_code":"PPL",
    "gn:name":"Cengglong",
    "gn:population":0,
    "gn:timezone":"Asia/Jakarta",
    "iso:country":"ID",
    "name:ind_x_preferred":[
        "Cengglong"
    ],
    "wof:name":"Cengglong",
    "wof:placetype":"locality"
},
  "geometry": {"coordinates":[112.2547,-7.9079],"type":"Point"}
}