{
  "type": "Feature",
  "properties": {
    "gn:admin1_code":"7",
    "gn:asciiname":"Tlogocino Timur",
    "gn:country_code":"ID",
    "gn:dem":10,
    "gn:feature_class":"P",
    "gn:feature_code":"PPL",
    "gn:name":"Tlogocino Timur",
    "gn:population":0,
    "gn:timezone":"Asia/Jakarta",
    "iso:country":"ID",
    "name:ind_x_preferred":[
        "Tlogocino Timur"
    ],
    "wof:name":"Tlogocino Timur",
    "wof:placetype":"locality"
},
  "geometry": {"coordinates":[110.5818,-6.8496],"type":"Point"}
}