{
  "type": "Feature",
  "properties": {
    "gn:admin1_code":"18.0",
    "gn:asciiname":"Kolouju",
    "gn:country_code":"ID",
    "gn:dem":12,
    "gn:feature_class":"P",
    "gn:feature_code":"PPL",
    "gn:name":"Kolouju",
    "gn:population":0,
    "gn:timezone":"Asia/Makassar",
    "iso:country":"ID",
    "name:ind_x_preferred":[
        "Kolouju"
    ],
    "wof:name":"Kolouju",
    "wof:placetype":"locality"
},
  "geometry": {"coordinates":[121.8477,-10.4543],"type":"Point"}
}