{
  "type": "Feature",
  "properties": {
    "gn:admin1_code":"17",
    "gn:asciiname":"Montongmacan",
    "gn:country_code":"ID",
    "gn:dem":24,
    "gn:feature_class":"P",
    "gn:feature_code":"PPL",
    "gn:name":"Montongmacan",
    "gn:population":0,
    "gn:timezone":"Asia/Makassar",
    "iso:country":"ID",
    "name:ind_x_preferred":[
        "Montongmacan"
    ],
    "wof:name":"Montongmacan",
    "wof:placetype":"locality"
},
  "geometry": {"coordinates":[116.50069999999999,-8.7728],"type":"Point"}
}