{
  "type": "Feature",
  "properties": {
    "gn:admin1_code":"07",
    "gn:asciiname":"Lendoh Atas",
    "gn:country_code":"ID",
    "gn:dem":715,
    "gn:feature_class":"P",
    "gn:feature_code":"PPL",
    "gn:name":"Lendoh Atas",
    "gn:population":0,
    "gn:timezone":"Asia/Jakarta",
    "iso:country":"ID",
    "name:und_x_variant":[
        "Lendoh",
        "Lendoh Atas"
    ],
    "wof:lang_x_official":[
        "ind"
    ],
    "wof:lang_x_spoken":[
        "ind",
        "eng"
    ],
    "wof:name":"Lendoh Atas",
    "wof:placetype":"locality"
},
  "geometry": {"coordinates":[110.34472,-7.30667],"type":"Point"}
}