{
  "type": "Feature",
  "properties": {
    "gn:admin1_code":"8.0",
    "gn:asciiname":"Watupelen",
    "gn:country_code":"ID",
    "gn:dem":162,
    "gn:feature_class":"P",
    "gn:feature_code":"PPL",
    "gn:name":"Watupelen",
    "gn:population":0,
    "gn:timezone":"Asia/Jakarta",
    "iso:country":"ID",
    "name:ind_x_preferred":[
        "Watupelen"
    ],
    "wof:name":"Watupelen",
    "wof:placetype":"locality"
},
  "geometry": {"coordinates":[111.4096,-7.6575],"type":"Point"}
}