{
  "type": "Feature",
  "properties": {
    "gn:admin1_code":"26",
    "gn:asciiname":"Simatorkis Pandalu",
    "gn:country_code":"ID",
    "gn:dem":561,
    "gn:feature_class":"P",
    "gn:feature_code":"PPL",
    "gn:name":"Simatorkis Pandalu",
    "gn:population":0,
    "gn:timezone":"Asia/Jakarta",
    "iso:country":"ID",
    "name:ind_x_preferred":[
        "Simatorkis Pandalu"
    ],
    "wof:lang_x_official":[
        "ind"
    ],
    "wof:lang_x_spoken":[
        "ind",
        "eng"
    ],
    "wof:name":"Simatorkis Pandalu",
    "wof:placetype":"locality"
},
  "geometry": {"coordinates":[99.23945000000001,1.43476],"type":"Point"}
}