{
  "type": "Feature",
  "properties": {
    "gn:admin1_code":"22",
    "gn:asciiname":"Tomulipu",
    "gn:country_code":"ID",
    "gn:dem":28,
    "gn:feature_class":"P",
    "gn:feature_code":"PPL",
    "gn:name":"Tomulipu",
    "gn:population":0,
    "gn:timezone":"Asia/Makassar",
    "iso:country":"ID",
    "name:ind_x_preferred":[
        "Tomulipu"
    ],
    "name:und_x_variant":[
        "Tamulipu"
    ],
    "wof:name":"Tomulipu",
    "wof:placetype":"locality"
},
  "geometry": {"coordinates":[122.16840000000001,-3.9195],"type":"Point"}
}