{
  "type": "Feature",
  "properties": {
    "gn:admin1_code":"7",
    "gn:asciiname":"Beji",
    "gn:country_code":"ID",
    "gn:dem":8,
    "gn:feature_class":"P",
    "gn:feature_code":"PPL",
    "gn:name":"Beji",
    "gn:population":0,
    "gn:timezone":"Asia/Jakarta",
    "iso:country":"ID",
    "name:bjn_x_preferred":[
        "Beji"
    ],
    "name:ind_x_preferred":[
        "Beji"
    ],
    "name:jav_x_preferred":[
        "B\u00e8ji"
    ],
    "name:sun_x_preferred":[
        "Beji"
    ],
    "wof:lang_x_official":[
        "ind"
    ],
    "wof:lang_x_spoken":[
        "ind",
        "eng"
    ],
    "wof:name":"Beji",
    "wof:placetype":"locality"
},
  "geometry": {"coordinates":[110.6464,-6.8824],"type":"Point"}
}