{
  "type": "Feature",
  "properties": {
    "gn:admin1_code":"8",
    "gn:asciiname":"Dander",
    "gn:country_code":"ID",
    "gn:dem":50,
    "gn:feature_class":"P",
    "gn:feature_code":"PPL",
    "gn:name":"Dander",
    "gn:population":0,
    "gn:timezone":"Asia/Jakarta",
    "iso:country":"ID",
    "name:ara_x_preferred":[
        "\u0648\u0628\u063a"
    ],
    "name:ind_x_preferred":[
        "Dander"
    ],
    "wof:name":"Dander",
    "wof:placetype":"locality"
},
  "geometry": {"coordinates":[112.2474,-7.3997],"type":"Point"}
}