{
  "type": "Feature",
  "properties": {
    "gn:admin1_code":"26",
    "gn:asciiname":"Tandem Hilir",
    "gn:country_code":"ID",
    "gn:dem":15,
    "gn:feature_class":"P",
    "gn:feature_code":"PPL",
    "gn:name":"Tandem Hilir",
    "gn:population":0,
    "gn:timezone":"Asia/Jakarta",
    "iso:country":"ID",
    "name:ind_x_preferred":[
        "Tandem Hilir"
    ],
    "wof:name":"Tandem Hilir",
    "wof:placetype":"locality"
},
  "geometry": {"coordinates":[98.5097,3.7118],"type":"Point"}
}