{
  "type": "Feature",
  "properties": {
    "gn:admin1_code":"18.0",
    "gn:asciiname":"Karing",
    "gn:country_code":"ID",
    "gn:dem":307,
    "gn:feature_class":"P",
    "gn:feature_code":"PPL",
    "gn:name":"Karing",
    "gn:population":0,
    "gn:timezone":"Asia/Makassar",
    "iso:country":"ID",
    "name:ind_x_preferred":[
        "Karing"
    ],
    "wof:name":"Karing",
    "wof:placetype":"locality"
},
  "geometry": {"coordinates":[123.21210000000001,-8.342],"type":"Point"}
}