{
  "type": "Feature",
  "properties": {
    "gn:admin1_code":"7",
    "gn:asciiname":"Laban",
    "gn:country_code":"ID",
    "gn:dem":704,
    "gn:feature_class":"P",
    "gn:feature_code":"PPL",
    "gn:name":"Laban",
    "gn:population":0,
    "gn:timezone":"Asia/Jakarta",
    "iso:country":"ID",
    "name:ind_x_preferred":[
        "Laban"
    ],
    "wof:name":"Laban",
    "wof:placetype":"locality"
},
  "geometry": {"coordinates":[109.39333000000001,-7.21361],"type":"Point"}
}