{
  "type": "Feature",
  "properties": {
    "gn:admin1_code":"30",
    "gn:asciiname":"Cinangsih",
    "gn:country_code":"ID",
    "gn:dem":302,
    "gn:feature_class":"P",
    "gn:feature_code":"PPL",
    "gn:name":"Cinangsih",
    "gn:population":0,
    "gn:timezone":"Asia/Jakarta",
    "iso:country":"ID",
    "name:ind_x_preferred":[
        "Cinangsih"
    ],
    "wof:name":"Cinangsih",
    "wof:placetype":"locality"
},
  "geometry": {"coordinates":[108.5488,-6.9549],"type":"Point"}
}