{
  "type": "Feature",
  "properties": {
    "gn:admin1_code":"24",
    "gn:asciiname":"Ambungkapu",
    "gn:country_code":"ID",
    "gn:dem":171,
    "gn:feature_class":"P",
    "gn:feature_code":"PPL",
    "gn:name":"Ambungkapu",
    "gn:population":0,
    "gn:timezone":"Asia/Jakarta",
    "iso:country":"ID",
    "name:ind_x_preferred":[
        "Ambungkapu"
    ],
    "wof:name":"Ambungkapu",
    "wof:placetype":"locality"
},
  "geometry": {"coordinates":[100.21414,-0.53719],"type":"Point"}
}