{
  "type": "Feature",
  "properties": {
    "gn:admin1_code":"18.0",
    "gn:asciiname":"Lianglolong",
    "gn:country_code":"ID",
    "gn:dem":22,
    "gn:feature_class":"P",
    "gn:feature_code":"PPL",
    "gn:name":"Lianglolong",
    "gn:population":0,
    "gn:timezone":"Asia/Makassar",
    "iso:country":"ID",
    "name:ind_x_preferred":[
        "Lianglolong"
    ],
    "wof:name":"Lianglolong",
    "wof:placetype":"locality"
},
  "geometry": {"coordinates":[124.3233,-8.1909],"type":"Point"}
}