{
  "type": "Feature",
  "properties": {
    "gn:admin1_code":"7.0",
    "gn:asciiname":"Kemojing",
    "gn:country_code":"ID",
    "gn:dem":326,
    "gn:feature_class":"P",
    "gn:feature_code":"PPL",
    "gn:name":"Kemojing",
    "gn:population":0,
    "gn:timezone":"Asia/Jakarta",
    "iso:country":"ID",
    "name:ind_x_preferred":[
        "Kemojing"
    ],
    "wof:name":"Kemojing",
    "wof:placetype":"locality"
},
  "geometry": {"coordinates":[109.34305999999999,-7.26889],"type":"Point"}
}