{
  "type": "Feature",
  "properties": {
    "gn:admin1_code":"8.0",
    "gn:asciiname":"Kemiri",
    "gn:country_code":"ID",
    "gn:dem":280,
    "gn:feature_class":"P",
    "gn:feature_code":"PPLA4",
    "gn:name":"Kemiri",
    "gn:population":0,
    "gn:timezone":"Asia/Jakarta",
    "iso:country":"ID",
    "name:ind_x_preferred":[
        "Kemiri"
    ],
    "wof:lang_x_official":[
        "ind"
    ],
    "wof:lang_x_spoken":[
        "ind",
        "eng"
    ],
    "wof:name":"Kemiri",
    "wof:placetype":"locality"
},
  "geometry": {"coordinates":[111.9113,-8.2267],"type":"Point"}
}