{
  "type": "Feature",
  "properties": {
    "gn:admin1_code":"26",
    "gn:asciiname":"Jumatorop",
    "gn:country_code":"ID",
    "gn:dem":585,
    "gn:feature_class":"P",
    "gn:feature_code":"PPL",
    "gn:name":"Jumatorop",
    "gn:population":0,
    "gn:timezone":"Asia/Jakarta",
    "iso:country":"ID",
    "name:ind_x_preferred":[
        "Jumatorop"
    ],
    "wof:name":"Jumatorop",
    "wof:placetype":"locality"
},
  "geometry": {"coordinates":[98.25879999999999,2.864],"type":"Point"}
}