{
  "type": "Feature",
  "properties": {
    "gn:country":"ID",
    "gn:fcode":"ADM3",
    "gn:pop":0,
    "iso:country":"ID",
    "name:eng_x_preferred":[
        "Districts of Jakarta"
    ],
    "name:ind_x_preferred":[
        "Kecamatan Cilandak"
    ],
    "name:unk_x_variant":[
        "Cilandak"
    ],
    "qs:name":"Kecamatan Cilandak",
    "qs:photos_9r":0,
    "qs:photos_sr":0,
    "qs:pop_sr":"0",
    "wd:wordcount":195,
    "wof:name":"Kecamatan Cilandak",
    "wof:placetype":"localadmin",
    "wof:population":0
},
  "geometry": {"coordinates":[106.7945,-6.2924],"type":"Point"}
}