{
  "type": "Feature",
  "properties": {
    "gn:admin1_code":"8.0",
    "gn:asciiname":"Baran Tegaron",
    "gn:country_code":"ID",
    "gn:dem":573,
    "gn:feature_class":"P",
    "gn:feature_code":"PPL",
    "gn:name":"Baran Tegaron",
    "gn:population":0,
    "gn:timezone":"Asia/Jakarta",
    "iso:country":"ID",
    "name:ind_x_preferred":[
        "Baran Tegaron"
    ],
    "name:und_x_variant":[
        "Barantegaran"
    ],
    "wof:lang_x_official":[
        "ind"
    ],
    "wof:lang_x_spoken":[
        "ind",
        "eng"
    ],
    "wof:name":"Baran Tegaron",
    "wof:placetype":"locality"
},
  "geometry": {"coordinates":[112.6681,-8.0017],"type":"Point"}
}