{
  "type": "Feature",
  "properties": {
    "gn:admin1_code":"34.0",
    "gn:asciiname":"Serayu",
    "gn:country_code":"ID",
    "gn:dem":55,
    "gn:feature_class":"P",
    "gn:feature_code":"PPL",
    "gn:name":"Serayu",
    "gn:population":0,
    "gn:timezone":"Asia/Makassar",
    "iso:country":"ID",
    "name:ind_x_preferred":[
        "Serayu"
    ],
    "wof:name":"Serayu",
    "wof:placetype":"locality"
},
  "geometry": {"coordinates":[122.5355,0.7571],"type":"Point"}
}