{
  "type": "Feature",
  "properties": {
    "gn:gn_country":"ID",
    "gn:gn_fcode":"PPL",
    "gn:gn_pop":0,
    "iso:country":"ID",
    "qs_pg:aaroncc":"ID",
    "qs_pg:gn_country":"ID",
    "qs_pg:gn_fcode":"PPL",
    "qs_pg:gn_pop":0,
    "qs_pg:name":"Susukan",
    "qs_pg:name_adm0":"Indonesia",
    "qs_pg:name_adm1":"Jawa Barat",
    "qs_pg:photos_9r":0,
    "qs_pg:photos_sr":0,
    "qs_pg:pop_sr":0,
    "qs_pg:qs_pg_placetype":"neighbourhood",
    "qs_pg:qs_pg_placetype_gp":"Suburb",
    "qs_pg:woe_adm0":23424846,
    "woe:adm0_id":23424846,
    "woe:name_adm0":"Indonesia",
    "woe:name_adm1":"Jawa Barat",
    "woe:placetype":"Suburb",
    "wof:name":"Susukan",
    "wof:placetype":"neighbourhood"
},
  "geometry": {"coordinates":[106.86750000000001,-6.31278],"type":"Point"}
}