{
  "type": "Feature",
  "properties": {
    "gn:admin1_code":"24",
    "gn:asciiname":"Mangingging",
    "gn:country_code":"ID",
    "gn:dem":258,
    "gn:feature_class":"P",
    "gn:feature_code":"PPL",
    "gn:name":"Mangingging",
    "gn:population":0,
    "gn:timezone":"Asia/Jakarta",
    "iso:country":"ID",
    "name:ind_x_preferred":[
        "Mangingging"
    ],
    "wof:name":"Mangingging",
    "wof:placetype":"locality"
},
  "geometry": {"coordinates":[100.09099999999999,0.0301],"type":"Point"}
}