{
  "type": "Feature",
  "properties": {
    "gn:admin1_code":"8.0",
    "gn:asciiname":"Paobulan",
    "gn:country_code":"ID",
    "gn:dem":25,
    "gn:feature_class":"P",
    "gn:feature_code":"PPLA4",
    "gn:name":"Paobulan",
    "gn:population":0,
    "gn:timezone":"Asia/Jakarta",
    "iso:country":"ID",
    "name:ind_x_preferred":[
        "Paobulan"
    ],
    "wof:name":"Paobulan",
    "wof:placetype":"locality"
},
  "geometry": {"coordinates":[112.8419,-6.9967],"type":"Point"}
}