{
  "type": "Feature",
  "properties": {
    "gn:admin1_code":"17.0",
    "gn:asciiname":"Ekas",
    "gn:country_code":"ID",
    "gn:dem":6,
    "gn:feature_class":"P",
    "gn:feature_code":"PPL",
    "gn:name":"Ekas",
    "gn:population":0,
    "gn:timezone":"Asia/Makassar",
    "iso:country":"ID",
    "name:ind_x_preferred":[
        "Ekas"
    ],
    "wof:name":"Ekas",
    "wof:placetype":"locality"
},
  "geometry": {"coordinates":[116.45569999999999,-8.8735],"type":"Point"}
}