{
  "type": "Feature",
  "properties": {
    "gn:admin1_code":"7",
    "gn:asciiname":"Josari",
    "gn:country_code":"ID",
    "gn:dem":944,
    "gn:feature_class":"P",
    "gn:feature_code":"PPL",
    "gn:name":"Josari",
    "gn:population":0,
    "gn:timezone":"Asia/Jakarta",
    "iso:country":"ID",
    "name:ind_x_preferred":[
        "Josari"
    ],
    "wof:name":"Josari",
    "wof:placetype":"locality"
},
  "geometry": {"coordinates":[111.11056000000001,-7.71167],"type":"Point"}
}