{
  "type": "Feature",
  "properties": {
    "gn:admin1_code":"15.0",
    "gn:asciiname":"Umbulan Gelabek",
    "gn:country_code":"ID",
    "gn:dem":17,
    "gn:feature_class":"P",
    "gn:feature_code":"PPL",
    "gn:name":"Umbulan Gelabek",
    "gn:population":0,
    "gn:timezone":"Asia/Jakarta",
    "iso:country":"ID",
    "name:ind_x_preferred":[
        "Umbulan Gelabek"
    ],
    "name:ind_x_variant":[
        "Umbulangalabek",
        "Oemboelan G\u0115lab\u0115k"
    ],
    "wof:lang_x_official":[
        "ind"
    ],
    "wof:lang_x_spoken":[
        "ind",
        "eng"
    ],
    "wof:name":"Umbulan Gelabek",
    "wof:placetype":"locality"
},
  "geometry": {"coordinates":[105.20343,-4.49211],"type":"Point"}
}