{
  "type": "Feature",
  "properties": {
    "gn:admin1_code":"33.0",
    "gn:asciiname":"Cigadog Kidul",
    "gn:country_code":"ID",
    "gn:dem":33,
    "gn:feature_class":"P",
    "gn:feature_code":"PPL",
    "gn:name":"Cigadog Kidul",
    "gn:population":0,
    "gn:timezone":"Asia/Jakarta",
    "iso:country":"ID",
    "name:ind_x_preferred":[
        "Cigadog Kidul"
    ],
    "wof:name":"Cigadog Kidul",
    "wof:placetype":"locality"
},
  "geometry": {"coordinates":[105.7841,-6.8381],"type":"Point"}
}