{
  "type": "Feature",
  "properties": {
    "gn:admin1_code":"18.0",
    "gn:asciiname":"Namolein",
    "gn:country_code":"ID",
    "gn:dem":25,
    "gn:feature_class":"P",
    "gn:feature_code":"PPL",
    "gn:name":"Namolein",
    "gn:population":0,
    "gn:timezone":"Asia/Makassar",
    "iso:country":"ID",
    "name:ind_x_preferred":[
        "Namolein"
    ],
    "wof:name":"Namolein",
    "wof:placetype":"locality"
},
  "geometry": {"coordinates":[123.48878000000001,-8.24507],"type":"Point"}
}