{
  "type": "Feature",
  "properties": {
    "gn:admin1_code":"30",
    "gn:asciiname":"Bojong",
    "gn:country_code":"ID",
    "gn:dem":42,
    "gn:feature_class":"P",
    "gn:feature_code":"PPL",
    "gn:name":"Bojong",
    "gn:population":0,
    "gn:timezone":"Asia/Jakarta",
    "iso:country":"ID",
    "name:ind_x_preferred":[
        "Bojong"
    ],
    "name:und_x_variant":[
        "Bojong 3",
        "Bojong Tiga"
    ],
    "wof:name":"Bojong",
    "wof:placetype":"locality"
},
  "geometry": {"coordinates":[106.42306000000001,-6.28667],"type":"Point"}
}