{
  "type": "Feature",
  "properties": {
    "gn:admin1_code":"33",
    "gn:asciiname":"Walukon",
    "gn:country_code":"ID",
    "gn:dem":93,
    "gn:feature_class":"P",
    "gn:feature_code":"PPL",
    "gn:name":"Walukon",
    "gn:population":0,
    "gn:timezone":"Asia/Jakarta",
    "iso:country":"ID",
    "name:ind_x_preferred":[
        "Walukon"
    ],
    "wof:name":"Walukon",
    "wof:placetype":"locality"
},
  "geometry": {"coordinates":[105.997,-6.0524],"type":"Point"}
}