{
  "type": "Feature",
  "properties": {
    "gn:admin1_code":"30.0",
    "gn:asciiname":"Pasarmunding",
    "gn:country_code":"ID",
    "gn:dem":300,
    "gn:feature_class":"P",
    "gn:feature_code":"PPL",
    "gn:name":"Pasarmunding",
    "gn:population":0,
    "gn:timezone":"Asia/Jakarta",
    "iso:country":"ID",
    "name:ind_x_preferred":[
        "Pasarmunding"
    ],
    "wof:name":"Pasarmunding",
    "wof:placetype":"locality"
},
  "geometry": {"coordinates":[108.2945,-7.3512],"type":"Point"}
}