{
  "type": "Feature",
  "properties": {
    "gn:admin1_code":"7.0",
    "gn:asciiname":"Ledok",
    "gn:country_code":"ID",
    "gn:dem":46,
    "gn:feature_class":"P",
    "gn:feature_code":"PPL",
    "gn:name":"Ledok",
    "gn:population":0,
    "gn:timezone":"Asia/Jakarta",
    "iso:country":"ID",
    "name:ind_x_preferred":[
        "Ledok"
    ],
    "name:jav_x_preferred":[
        "Ledhok"
    ],
    "name:nld_x_preferred":[
        "Ledok"
    ],
    "wof:lang_x_official":[
        "ind"
    ],
    "wof:lang_x_spoken":[
        "ind",
        "eng"
    ],
    "wof:name":"Ledok",
    "wof:placetype":"locality"
},
  "geometry": {"coordinates":[111.0919,-7.0724],"type":"Point"}
}