{
  "type": "Feature",
  "properties": {
    "gn:country":"ID",
    "gn:fcode":"PPL",
    "gn:pop":0,
    "iso:country":"ID",
    "name:unk_x_variant":[
        "Ketaoen"
    ],
    "qs:name":"Ketaun",
    "qs:name_adm0":"Indonesia",
    "qs:name_adm1":"Bengkulu",
    "qs:photos_9r":0,
    "qs:photos_sr":0,
    "qs:placetype":"Town",
    "qs:pop_sr":"4",
    "wof:name":"Ketaun",
    "wof:placetype":"locality",
    "wof:population":0
},
  "geometry": {"coordinates":[101.81667,-3.38333],"type":"Point"}
}