{
  "type": "Feature",
  "properties": {
    "gn:admin1_code":"7.0",
    "gn:asciiname":"Aren",
    "gn:country_code":"ID",
    "gn:dem":766,
    "gn:feature_class":"P",
    "gn:feature_code":"PPL",
    "gn:name":"Aren",
    "gn:population":0,
    "gn:timezone":"Asia/Jakarta",
    "iso:country":"ID",
    "name:ind_x_preferred":[
        "Aren"
    ],
    "wof:name":"Aren",
    "wof:placetype":"locality"
},
  "geometry": {"coordinates":[109.06917,-7.23333],"type":"Point"}
}