{
  "type": "Feature",
  "properties": {
    "gn:admin1_code":"30.0",
    "gn:asciiname":"Garunggang",
    "gn:country_code":"ID",
    "gn:dem":416,
    "gn:feature_class":"P",
    "gn:feature_code":"PPLA4",
    "gn:name":"Garunggang",
    "gn:population":0,
    "gn:timezone":"Asia/Jakarta",
    "iso:country":"ID",
    "name:ind_x_preferred":[
        "Garunggang"
    ],
    "name:und_x_variant":[
        "Garoenggang"
    ],
    "wof:name":"Garunggang",
    "wof:placetype":"locality"
},
  "geometry": {"coordinates":[108.4423,-7.2046],"type":"Point"}
}