{
  "type": "Feature",
  "properties": {
    "gn:admin1_code":"15.0",
    "gn:asciiname":"Umbulan Tinggi",
    "gn:country_code":"ID",
    "gn:dem":26,
    "gn:feature_class":"P",
    "gn:feature_code":"PPL",
    "gn:name":"Umbulan Tinggi",
    "gn:population":0,
    "gn:timezone":"Asia/Jakarta",
    "iso:country":"ID",
    "name:ind_x_preferred":[
        "Umbulan Tinggi"
    ],
    "name:ind_x_variant":[
        "Oemboelan Tinggi",
        "Umbulantinggi"
    ],
    "wof:name":"Umbulan Tinggi",
    "wof:placetype":"locality"
},
  "geometry": {"coordinates":[105.73649,-4.60529],"type":"Point"}
}