{
  "type": "Feature",
  "properties": {
    "gn:admin1_code":"30.0",
    "gn:asciiname":"Nanggoh",
    "gn:country_code":"ID",
    "gn:dem":466,
    "gn:feature_class":"P",
    "gn:feature_code":"PPL",
    "gn:name":"Nanggoh",
    "gn:population":0,
    "gn:timezone":"Asia/Jakarta",
    "iso:country":"ID",
    "name:ind_x_preferred":[
        "Nanggoh"
    ],
    "name:und_x_variant":[
        "Nangoh"
    ],
    "wof:name":"Nanggoh",
    "wof:placetype":"locality"
},
  "geometry": {"coordinates":[108.1815,-7.2388],"type":"Point"}
}