{
  "type": "Feature",
  "properties": {
    "gn:admin1_code":"07",
    "gn:asciiname":"Mrisen",
    "gn:country_code":"ID",
    "gn:dem":254,
    "gn:feature_class":"P",
    "gn:feature_code":"PPL",
    "gn:name":"Mrisen",
    "gn:population":0,
    "gn:timezone":"Asia/Jakarta",
    "iso:country":"ID",
    "wof:name":"Mrisen",
    "wof:placetype":"locality"
},
  "geometry": {"coordinates":[110.52139,-7.69583],"type":"Point"}
}