{
  "type": "Feature",
  "properties": {
    "gn:admin1_code":"38",
    "gn:asciiname":"Amunge Satu",
    "gn:country_code":"ID",
    "gn:dem":208,
    "gn:feature_class":"P",
    "gn:feature_code":"PPL",
    "gn:name":"Amunge Satu",
    "gn:population":0,
    "gn:timezone":"Asia/Makassar",
    "iso:country":"ID",
    "name:ind_x_preferred":[
        "Amunge Satu"
    ],
    "name:und_x_variant":[
        "Amunge 1"
    ],
    "wof:name":"Amunge Satu",
    "wof:placetype":"locality"
},
  "geometry": {"coordinates":[119.87649999999999,-4.3739],"type":"Point"}
}