{
  "type": "Feature",
  "properties": {
    "gn:admin1_code":"26",
    "gn:asciiname":"Poalan",
    "gn:country_code":"ID",
    "gn:dem":109,
    "gn:feature_class":"P",
    "gn:feature_code":"PPL",
    "gn:name":"Poalan",
    "gn:population":0,
    "gn:timezone":"Asia/Jakarta",
    "iso:country":"ID",
    "name:ind_x_preferred":[
        "Poalan"
    ],
    "wof:name":"Poalan",
    "wof:placetype":"locality"
},
  "geometry": {"coordinates":[98.468,3.4786],"type":"Point"}
}