{
  "type": "Feature",
  "properties": {
    "gn:admin1_code":"30.0",
    "gn:asciiname":"Pasirgebang",
    "gn:country_code":"ID",
    "gn:dem":322,
    "gn:feature_class":"P",
    "gn:feature_code":"PPL",
    "gn:name":"Pasirgebang",
    "gn:population":0,
    "gn:timezone":"Asia/Jakarta",
    "iso:country":"ID",
    "name:ind_x_preferred":[
        "Pasirgebang"
    ],
    "wof:name":"Pasirgebang",
    "wof:placetype":"locality"
},
  "geometry": {"coordinates":[107.215,-7.3862],"type":"Point"}
}