{
  "type": "Feature",
  "properties": {
    "gn:admin1_code":"18.0",
    "gn:asciiname":"Horodawu",
    "gn:country_code":"ID",
    "gn:dem":27,
    "gn:feature_class":"P",
    "gn:feature_code":"PPL",
    "gn:name":"Horodawu",
    "gn:population":0,
    "gn:timezone":"Asia/Makassar",
    "iso:country":"ID",
    "name:ind_x_preferred":[
        "Horodawu"
    ],
    "wof:name":"Horodawu",
    "wof:placetype":"locality"
},
  "geometry": {"coordinates":[121.7852,-10.524],"type":"Point"}
}