{
  "type": "Feature",
  "properties": {
    "gn:admin1_code":"1",
    "gn:asciiname":"Ampa Kolak",
    "gn:country_code":"ID",
    "gn:dem":849,
    "gn:feature_class":"P",
    "gn:feature_code":"PPL",
    "gn:name":"Ampa Kolak",
    "gn:population":0,
    "gn:timezone":"Asia/Jakarta",
    "iso:country":"ID",
    "name:ind_x_preferred":[
        "Ampa Kolak"
    ],
    "name:und_x_variant":[
        "Ampankolak"
    ],
    "wof:lang_x_official":[
        "ind"
    ],
    "wof:lang_x_spoken":[
        "ind",
        "eng"
    ],
    "wof:name":"Ampa Kolak",
    "wof:placetype":"locality"
},
  "geometry": {"coordinates":[97.2664,4.0986],"type":"Point"}
}