{
  "type": "Feature",
  "properties": {
    "gn:admin1_code":"30.0",
    "gn:asciiname":"Cikuda",
    "gn:country_code":"ID",
    "gn:dem":645,
    "gn:feature_class":"P",
    "gn:feature_code":"PPL",
    "gn:name":"Cikuda",
    "gn:population":0,
    "gn:timezone":"Asia/Jakarta",
    "iso:country":"ID",
    "name:ind_x_preferred":[
        "Cikuda"
    ],
    "name:und_x_variant":[
        "Tjikuda",
        "Cikuda"
    ],
    "wof:name":"Cikuda",
    "wof:placetype":"locality"
},
  "geometry": {"coordinates":[106.6786,-7.0801],"type":"Point"}
}