{
  "type": "Feature",
  "properties": {
    "gn:admin1_code":"7.0",
    "gn:asciiname":"Demangan",
    "gn:country_code":"ID",
    "gn:dem":58,
    "gn:feature_class":"P",
    "gn:feature_code":"PPL",
    "gn:name":"Demangan",
    "gn:population":0,
    "gn:timezone":"Asia/Jakarta",
    "iso:country":"ID",
    "name:ind_x_preferred":[
        "Demangan"
    ],
    "wof:name":"Demangan",
    "wof:placetype":"locality"
},
  "geometry": {"coordinates":[111.01300000000001,-6.7151],"type":"Point"}
}