{
  "type": "Feature",
  "properties": {
    "gn:admin1_code":"7.0",
    "gn:asciiname":"Semingkir",
    "gn:country_code":"ID",
    "gn:dem":16,
    "gn:feature_class":"P",
    "gn:feature_code":"PPL",
    "gn:name":"Semingkir",
    "gn:population":0,
    "gn:timezone":"Asia/Jakarta",
    "iso:country":"ID",
    "name:ind_x_preferred":[
        "Semingkir"
    ],
    "wof:name":"Semingkir",
    "wof:placetype":"locality"
},
  "geometry": {"coordinates":[109.59556000000001,-7.71889],"type":"Point"}
}