{
  "type": "Feature",
  "properties": {
    "gn:admin1_code":"30.0",
    "gn:asciiname":"Kebonkai",
    "gn:country_code":"ID",
    "gn:dem":852,
    "gn:feature_class":"P",
    "gn:feature_code":"PPLA3",
    "gn:name":"Kebonkai",
    "gn:population":0,
    "gn:timezone":"Asia/Jakarta",
    "iso:country":"ID",
    "name:ind_x_preferred":[
        "Kebonkai"
    ],
    "wof:lang_x_official":[
        "ind"
    ],
    "wof:lang_x_spoken":[
        "ind",
        "eng"
    ],
    "wof:name":"Kebonkai",
    "wof:placetype":"locality"
},
  "geometry": {"coordinates":[107.967,-7.5025],"type":"Point"}
}