{
  "type": "Feature",
  "properties": {
    "gn:admin1_code":"30",
    "gn:asciiname":"Kancanunggal",
    "gn:country_code":"ID",
    "gn:dem":7,
    "gn:feature_class":"P",
    "gn:feature_code":"PPL",
    "gn:name":"Kancanunggal",
    "gn:population":0,
    "gn:timezone":"Asia/Jakarta",
    "iso:country":"ID",
    "name:ind_x_preferred":[
        "Kancanunggal"
    ],
    "wof:name":"Kancanunggal",
    "wof:placetype":"locality"
},
  "geometry": {"coordinates":[107.40194,-6.10611],"type":"Point"}
}