{
  "type": "Feature",
  "properties": {
    "gn:admin1_code":"7.0",
    "gn:asciiname":"Gedan",
    "gn:country_code":"ID",
    "gn:dem":465,
    "gn:feature_class":"P",
    "gn:feature_code":"PPL",
    "gn:name":"Gedan",
    "gn:population":0,
    "gn:timezone":"Asia/Jakarta",
    "iso:country":"ID",
    "wof:name":"Gedan",
    "wof:placetype":"locality"
},
  "geometry": {"coordinates":[110.61360999999999,-7.40472],"type":"Point"}
}