{
  "type": "Feature",
  "properties": {
    "gn:admin1_code":"08",
    "gn:asciiname":"Wonokerso",
    "gn:country_code":"ID",
    "gn:dem":392,
    "gn:feature_class":"P",
    "gn:feature_code":"PPLA4",
    "gn:name":"Wonokerso",
    "gn:population":0,
    "gn:timezone":"Asia/Jakarta",
    "iso:country":"ID",
    "name:ind_x_preferred":[
        "Wonokerso"
    ],
    "name:und_x_variant":[
        "Wonokenso"
    ],
    "wof:name":"Wonokerso",
    "wof:placetype":"locality"
},
  "geometry": {"coordinates":[112.6113,-8.0765],"type":"Point"}
}