{
  "type": "Feature",
  "properties": {
    "gn:admin1_code":"1.0",
    "gn:asciiname":"Janka",
    "gn:country_code":"ID",
    "gn:dem":10,
    "gn:feature_class":"P",
    "gn:feature_code":"PPL",
    "gn:name":"Janka",
    "gn:population":0,
    "gn:timezone":"Asia/Jakarta",
    "iso:country":"ID",
    "name:deu_x_preferred":[
        "Janka"
    ],
    "name:fra_x_preferred":[
        "Janka"
    ],
    "name:hun_x_preferred":[
        "Janka"
    ],
    "name:srp_x_preferred":[
        "\u0408\u0430\u043d\u043a\u0430"
    ],
    "wof:lang_x_official":[
        "ind"
    ],
    "wof:lang_x_spoken":[
        "ind",
        "eng"
    ],
    "wof:name":"Janka",
    "wof:placetype":"locality"
},
  "geometry": {"coordinates":[96.80833,5.26056],"type":"Point"}
}