{
  "type": "Feature",
  "properties": {
    "gn:admin1_code":"30.0",
    "gn:asciiname":"Cibojong Dua",
    "gn:country_code":"ID",
    "gn:dem":290,
    "gn:feature_class":"P",
    "gn:feature_code":"PPL",
    "gn:name":"Cibojong Dua",
    "gn:population":0,
    "gn:timezone":"Asia/Jakarta",
    "iso:country":"ID",
    "name:ind_x_preferred":[
        "Cibojong Dua"
    ],
    "wof:name":"Cibojong Dua",
    "wof:placetype":"locality"
},
  "geometry": {"coordinates":[106.57429999999999,-7.2407],"type":"Point"}
}