{
  "type": "Feature",
  "properties": {
    "gn:admin1_code":"26",
    "gn:asciiname":"Aeksori",
    "gn:country_code":"ID",
    "gn:dem":1392,
    "gn:feature_class":"P",
    "gn:feature_code":"PPL",
    "gn:name":"Aeksori",
    "gn:population":0,
    "gn:timezone":"Asia/Jakarta",
    "iso:country":"ID",
    "name:ind_x_preferred":[
        "Aeksori"
    ],
    "wof:name":"Aeksori",
    "wof:placetype":"locality"
},
  "geometry": {"coordinates":[98.7871,2.2116],"type":"Point"}
}