{
  "type": "Feature",
  "properties": {
    "gn:admin1_code":"1",
    "gn:asciiname":"Padang Mancang",
    "gn:country_code":"ID",
    "gn:dem":11,
    "gn:feature_class":"P",
    "gn:feature_code":"PPL",
    "gn:name":"Padang Mancang",
    "gn:population":0,
    "gn:timezone":"Asia/Jakarta",
    "iso:country":"ID",
    "name:ind_x_preferred":[
        "Padang Mancang"
    ],
    "name:und_x_variant":[
        "Padamantjang"
    ],
    "wof:name":"Padang Mancang",
    "wof:placetype":"locality"
},
  "geometry": {"coordinates":[96.16079999999999,4.2248],"type":"Point"}
}