{
  "type": "Feature",
  "properties": {
    "gn:admin1_code":"21.0",
    "gn:asciiname":"Kinta",
    "gn:country_code":"ID",
    "gn:dem":773,
    "gn:feature_class":"P",
    "gn:feature_code":"PPL",
    "gn:name":"Kinta",
    "gn:population":0,
    "gn:timezone":"Asia/Makassar",
    "iso:country":"ID",
    "name:ind_x_preferred":[
        "Kinta"
    ],
    "wof:name":"Kinta",
    "wof:placetype":"locality"
},
  "geometry": {"coordinates":[120.0312,-1.5114],"type":"Point"}
}