{
  "type": "Feature",
  "properties": {
    "gn:admin1_code":"8",
    "gn:asciiname":"Watukaras",
    "gn:country_code":"ID",
    "gn:dem":64,
    "gn:feature_class":"P",
    "gn:feature_code":"PPL",
    "gn:name":"Watukaras",
    "gn:population":0,
    "gn:timezone":"Asia/Jakarta",
    "iso:country":"ID",
    "name:ind_x_preferred":[
        "Watukaras"
    ],
    "wof:name":"Watukaras",
    "wof:placetype":"locality"
},
  "geometry": {"coordinates":[111.34332999999999,-7.37611],"type":"Point"}
}