{
  "type": "Feature",
  "properties": {
    "gn:admin1_code":"29.0",
    "gn:asciiname":"Benawa",
    "gn:country_code":"ID",
    "gn:dem":22,
    "gn:feature_class":"P",
    "gn:feature_code":"PPL",
    "gn:name":"Benawa",
    "gn:population":0,
    "gn:timezone":"Asia/Jayapura",
    "iso:country":"ID",
    "name:ind_x_preferred":[
        "Benawa"
    ],
    "name:msa_x_preferred":[
        "Benawa"
    ],
    "wof:name":"Benawa",
    "wof:placetype":"locality"
},
  "geometry": {"coordinates":[127.3724,0.6411],"type":"Point"}
}