{
  "type": "Feature",
  "properties": {
    "gn:admin1_code":"1",
    "gn:asciiname":"Lhogkase",
    "gn:country_code":"ID",
    "gn:dem":30,
    "gn:feature_class":"P",
    "gn:feature_code":"PPL",
    "gn:name":"Lhogkase",
    "gn:population":0,
    "gn:timezone":"Asia/Jakarta",
    "iso:country":"ID",
    "name:ind_x_preferred":[
        "Lhogkase"
    ],
    "wof:name":"Lhogkase",
    "wof:placetype":"locality"
},
  "geometry": {"coordinates":[97.08159999999999,3.4242],"type":"Point"}
}