{
  "type": "Feature",
  "properties": {
    "gn:admin1_code":"33.0",
    "gn:asciiname":"Anyar",
    "gn:country_code":"ID",
    "gn:dem":7,
    "gn:feature_class":"P",
    "gn:feature_code":"PPL",
    "gn:name":"Anyar",
    "gn:population":0,
    "gn:timezone":"Asia/Jakarta",
    "iso:country":"ID",
    "name:deu_x_preferred":[
        "Anyer"
    ],
    "name:fra_x_preferred":[
        "Anyer"
    ],
    "name:fry_x_preferred":[
        "Anjer"
    ],
    "name:ind_x_preferred":[
        "Anyar"
    ],
    "name:jav_x_preferred":[
        "Anyar"
    ],
    "name:msa_x_preferred":[
        "Anyar"
    ],
    "name:nld_x_preferred":[
        "Anyer"
    ],
    "name:por_x_preferred":[
        "Anyer"
    ],
    "name:sun_x_preferred":[
        "Anyar"
    ],
    "name:und_x_variant":[
        "Old Anjer",
        "Anjer-lor",
        "Anyer-Lor"
    ],
    "wof:name":"Anyar",
    "wof:placetype":"locality"
},
  "geometry": {"coordinates":[105.92207000000001,-6.05297],"type":"Point"}
}