{
  "type": "Feature",
  "properties": {
    "gn:admin1_code":"38.0",
    "gn:asciiname":"Kanung",
    "gn:country_code":"ID",
    "gn:dem":30,
    "gn:feature_class":"P",
    "gn:feature_code":"PPL",
    "gn:name":"Kanung",
    "gn:population":0,
    "gn:timezone":"Asia/Makassar",
    "iso:country":"ID",
    "name:ind_x_preferred":[
        "Kanung"
    ],
    "wof:name":"Kanung",
    "wof:placetype":"locality"
},
  "geometry": {"coordinates":[120.01009999999999,-3.8727],"type":"Point"}
}