{
  "type": "Feature",
  "properties": {
    "gn:admin1_code":"18.0",
    "gn:asciiname":"Kefakole",
    "gn:country_code":"ID",
    "gn:dem":365,
    "gn:feature_class":"P",
    "gn:feature_code":"PPL",
    "gn:name":"Kefakole",
    "gn:population":0,
    "gn:timezone":"Asia/Makassar",
    "iso:country":"ID",
    "name:ind_x_preferred":[
        "Kefakole"
    ],
    "wof:name":"Kefakole",
    "wof:placetype":"locality"
},
  "geometry": {"coordinates":[124.53400000000001,-9.576],"type":"Point"}
}