{
  "type": "Feature",
  "properties": {
    "gn:admin1_code":"8",
    "gn:asciiname":"Nujung",
    "gn:country_code":"ID",
    "gn:dem":45,
    "gn:feature_class":"P",
    "gn:feature_code":"PPL",
    "gn:name":"Nujung",
    "gn:population":0,
    "gn:timezone":"Asia/Jakarta",
    "iso:country":"ID",
    "name:ind_x_preferred":[
        "Nujung"
    ],
    "wof:name":"Nujung",
    "wof:placetype":"locality"
},
  "geometry": {"coordinates":[112.8306,-7.696],"type":"Point"}
}