{
  "type": "Feature",
  "properties": {
    "gn:admin1_code":"30",
    "gn:asciiname":"Jawa-kulon",
    "gn:cc2":"ID",
    "gn:country_code":"ID",
    "gn:dem":691,
    "gn:feature_class":"P",
    "gn:feature_code":"PPL",
    "gn:name":"Jawa-kulon",
    "gn:population":0,
    "gn:timezone":"Asia/Jakarta",
    "iso:country":"ID",
    "name:und_x_variant":[
        "Djawa-kulon",
        "Jawa-kulon"
    ],
    "wof:lang_x_official":[
        "ind"
    ],
    "wof:lang_x_spoken":[
        "ind",
        "eng"
    ],
    "wof:name":"Jawa-kulon",
    "wof:placetype":"locality"
},
  "geometry": {"coordinates":[107.72833,-6.93417],"type":"Point"}
}