{
  "type": "Feature",
  "properties": {
    "gn:admin1_code":"30",
    "gn:asciiname":"Kemuning",
    "gn:country_code":"ID",
    "gn:dem":355,
    "gn:feature_class":"P",
    "gn:feature_code":"PPL",
    "gn:name":"Kemuning",
    "gn:population":0,
    "gn:timezone":"Asia/Jakarta",
    "iso:country":"ID",
    "name:ind_x_preferred":[
        "Kemuning"
    ],
    "wof:name":"Kemuning",
    "wof:placetype":"locality"
},
  "geometry": {"coordinates":[107.19306,-6.90417],"type":"Point"}
}