{
  "type": "Feature",
  "properties": {
    "gn:admin1_code":"18.0",
    "gn:asciiname":"Parun",
    "gn:country_code":"ID",
    "gn:dem":384,
    "gn:feature_class":"P",
    "gn:feature_code":"PPL",
    "gn:name":"Parun",
    "gn:population":0,
    "gn:timezone":"Asia/Makassar",
    "iso:country":"ID",
    "name:cat_x_preferred":[
        "Parun"
    ],
    "name:ceb_x_preferred":[
        "P\u0101r\u016bn"
    ],
    "name:deu_x_preferred":[
        "Parun"
    ],
    "name:epo_x_preferred":[
        "Parun"
    ],
    "name:fas_x_preferred":[
        "\u067e\u0627\u0631\u0648\u0646"
    ],
    "name:hin_x_preferred":[
        "\u092a\u093e\u0930\u0942\u0928"
    ],
    "name:ind_x_preferred":[
        "Parun"
    ],
    "name:nld_x_preferred":[
        "Parun"
    ],
    "name:pol_x_preferred":[
        "Parun"
    ],
    "name:por_x_preferred":[
        "Parun"
    ],
    "name:pus_x_preferred":[
        "\u067e\u0627\u0631\u0648\u0646"
    ],
    "name:spa_x_preferred":[
        "Parun"
    ],
    "name:swe_x_preferred":[
        "P\u0101r\u016bn"
    ],
    "name:tur_x_preferred":[
        "Parun"
    ],
    "name:war_x_preferred":[
        "Parun"
    ],
    "wof:lang_x_official":[
        "ind"
    ],
    "wof:lang_x_spoken":[
        "ind",
        "eng"
    ],
    "wof:name":"Parun",
    "wof:placetype":"locality"
},
  "geometry": {"coordinates":[119.58029999999999,-9.5017],"type":"Point"}
}