{
  "type": "Feature",
  "properties": {
    "gn:admin1_code":"8",
    "gn:asciiname":"Miraan Tengah",
    "gn:country_code":"ID",
    "gn:dem":51,
    "gn:feature_class":"P",
    "gn:feature_code":"PPL",
    "gn:name":"Miraan Tengah",
    "gn:population":0,
    "gn:timezone":"Asia/Jakarta",
    "iso:country":"ID",
    "name:ind_x_preferred":[
        "Miraan Tengah"
    ],
    "wof:name":"Miraan Tengah",
    "wof:placetype":"locality"
},
  "geometry": {"coordinates":[112.87269999999999,-7.7323],"type":"Point"}
}