{
  "type": "Feature",
  "properties": {
    "gn:admin1_code":"30.0",
    "gn:asciiname":"Bunter",
    "gn:country_code":"ID",
    "gn:dem":600,
    "gn:feature_class":"P",
    "gn:feature_code":"PPL",
    "gn:name":"Bunter",
    "gn:population":0,
    "gn:timezone":"Asia/Jakarta",
    "iso:country":"ID",
    "name:ind_x_preferred":[
        "Bunter"
    ],
    "wof:name":"Bunter",
    "wof:placetype":"locality"
},
  "geometry": {"coordinates":[108.2709,-7.0277],"type":"Point"}
}