{
  "type": "Feature",
  "properties": {
    "gn:admin1_code":"0.0",
    "gn:asciiname":"Atinowaniwa",
    "gn:country_code":"ID",
    "gn:dem":106,
    "gn:feature_class":"P",
    "gn:feature_code":"PPL",
    "gn:name":"Atinowaniwa",
    "gn:population":0,
    "gn:timezone":"Asia/Jayapura",
    "iso:country":"ID",
    "wof:name":"Atinowaniwa",
    "wof:placetype":"locality"
},
  "geometry": {"coordinates":[138.41666999999998,-1.91667],"type":"Point"}
}