{
  "type": "Feature",
  "properties": {
    "gn:admin1_code":"15.0",
    "gn:asciiname":"Umbulan Pedada Udik",
    "gn:country_code":"ID",
    "gn:dem":53,
    "gn:feature_class":"P",
    "gn:feature_code":"PPL",
    "gn:name":"Umbulan Pedada Udik",
    "gn:population":0,
    "gn:timezone":"Asia/Jakarta",
    "iso:country":"ID",
    "name:ind_x_preferred":[
        "Umbulan Pedada Udik"
    ],
    "name:ind_x_variant":[
        "Umbulan Pedada-udik",
        "Umbulanpedadaudik"
    ],
    "wof:lang_x_official":[
        "ind"
    ],
    "wof:lang_x_spoken":[
        "ind",
        "eng"
    ],
    "wof:name":"Umbulan Pedada Udik",
    "wof:placetype":"locality"
},
  "geometry": {"coordinates":[105.0412,-4.2811],"type":"Point"}
}