{
  "type": "Feature",
  "properties": {
    "gn:admin1_code":"30",
    "gn:asciiname":"Tanjunggalur",
    "gn:country_code":"ID",
    "gn:dem":12,
    "gn:feature_class":"P",
    "gn:feature_code":"PPL",
    "gn:name":"Tanjunggalur",
    "gn:population":0,
    "gn:timezone":"Asia/Jakarta",
    "iso:country":"ID",
    "name:ind_x_preferred":[
        "Tanjunggalur"
    ],
    "wof:name":"Tanjunggalur",
    "wof:placetype":"locality"
},
  "geometry": {"coordinates":[107.41361000000001,-6.24944],"type":"Point"}
}