{
  "type": "Feature",
  "properties": {
    "gn:admin1_code":"21.0",
    "gn:asciiname":"Batuampas",
    "gn:cc2":"ID",
    "gn:country_code":"ID",
    "gn:dem":11,
    "gn:feature_class":"P",
    "gn:feature_code":"PPL",
    "gn:name":"Batuampas",
    "gn:population":0,
    "gn:timezone":"Asia/Makassar",
    "iso:country":"ID",
    "name:und_x_variant":[
        "Batoeampas",
        "Batuampas"
    ],
    "wof:name":"Batuampas",
    "wof:placetype":"locality"
},
  "geometry": {"coordinates":[122.16777999999999,-0.81972],"type":"Point"}
}