{
  "type": "Feature",
  "properties": {
    "gn:admin1_code":"1",
    "gn:asciiname":"Lelhop",
    "gn:country_code":"ID",
    "gn:dem":18,
    "gn:feature_class":"P",
    "gn:feature_code":"PPL",
    "gn:name":"Lelhop",
    "gn:population":0,
    "gn:timezone":"Asia/Jakarta",
    "iso:country":"ID",
    "name:ind_x_preferred":[
        "Lelhop"
    ],
    "wof:name":"Lelhop",
    "wof:placetype":"locality"
},
  "geometry": {"coordinates":[96.8981,3.6831],"type":"Point"}
}