{
  "type": "Feature",
  "properties": {
    "gn:admin1_code":"8",
    "gn:asciiname":"Plabuhan",
    "gn:country_code":"ID",
    "gn:dem":35,
    "gn:feature_class":"P",
    "gn:feature_code":"PPL",
    "gn:name":"Plabuhan",
    "gn:population":0,
    "gn:timezone":"Asia/Jakarta",
    "iso:country":"ID",
    "name:ind_x_preferred":[
        "Plabuhan"
    ],
    "wof:name":"Plabuhan",
    "wof:placetype":"locality"
},
  "geometry": {"coordinates":[112.40170000000001,-7.2802],"type":"Point"}
}