{
  "type": "Feature",
  "properties": {
    "gn:admin1_code":"26",
    "gn:asciiname":"Damak Matio",
    "gn:country_code":"ID",
    "gn:dem":216,
    "gn:feature_class":"P",
    "gn:feature_code":"PPL",
    "gn:name":"Damak Matio",
    "gn:population":0,
    "gn:timezone":"Asia/Jakarta",
    "iso:country":"ID",
    "name:ind_x_preferred":[
        "Damak Matio"
    ],
    "wof:name":"Damak Matio",
    "wof:placetype":"locality"
},
  "geometry": {"coordinates":[99.2186,2.8791],"type":"Point"}
}