{
  "type": "Feature",
  "properties": {
    "gn:admin1_code":"8.0",
    "gn:asciiname":"Tlogowaru",
    "gn:country_code":"ID",
    "gn:dem":39,
    "gn:feature_class":"P",
    "gn:feature_code":"PPL",
    "gn:name":"Tlogowaru",
    "gn:population":0,
    "gn:timezone":"Asia/Jakarta",
    "iso:country":"ID",
    "name:ind_x_preferred":[
        "Tlogowaru"
    ],
    "wof:name":"Tlogowaru",
    "wof:placetype":"locality"
},
  "geometry": {"coordinates":[112.51990000000001,-6.9148],"type":"Point"}
}