{
  "type": "Feature",
  "properties": {
    "gn:admin1_code":"7",
    "gn:asciiname":"Bangkle",
    "gn:country_code":"ID",
    "gn:dem":22,
    "gn:feature_class":"P",
    "gn:feature_code":"PPL",
    "gn:name":"Bangkle",
    "gn:population":0,
    "gn:timezone":"Asia/Jakarta",
    "iso:country":"ID",
    "name:ind_x_preferred":[
        "Bangkle"
    ],
    "name:und_x_variant":[
        "Bangle"
    ],
    "wof:name":"Bangkle",
    "wof:placetype":"locality"
},
  "geometry": {"coordinates":[110.75109999999999,-7.0834],"type":"Point"}
}