{
  "type": "Feature",
  "properties": {
    "gn:admin1_code":"30",
    "gn:asciiname":"Babakantapos Empat",
    "gn:country_code":"ID",
    "gn:dem":495,
    "gn:feature_class":"P",
    "gn:feature_code":"PPL",
    "gn:name":"Babakantapos Empat",
    "gn:population":0,
    "gn:timezone":"Asia/Jakarta",
    "iso:country":"ID",
    "name:ind_x_preferred":[
        "Babakantapos Empat"
    ],
    "wof:name":"Babakantapos Empat",
    "wof:placetype":"locality"
},
  "geometry": {"coordinates":[106.68971999999999,-6.64389],"type":"Point"}
}