{
  "type": "Feature",
  "properties": {
    "gn:admin1_code":"05",
    "gn:asciiname":"Sungaigurun",
    "gn:country_code":"ID",
    "gn:dem":52,
    "gn:feature_class":"P",
    "gn:feature_code":"PPL",
    "gn:name":"Sungaigurun",
    "gn:population":0,
    "gn:timezone":"Asia/Jakarta",
    "iso:country":"ID",
    "name:ind_x_preferred":[
        "Sungaigurun"
    ],
    "wof:name":"Sungaigurun",
    "wof:placetype":"locality"
},
  "geometry": {"coordinates":[102.1635,-1.6558],"type":"Point"}
}