{
  "type": "Feature",
  "properties": {
    "gn:admin1_code":"30",
    "gn:asciiname":"Amis Satu",
    "gn:country_code":"ID",
    "gn:dem":16,
    "gn:feature_class":"P",
    "gn:feature_code":"PPL",
    "gn:name":"Amis Satu",
    "gn:population":0,
    "gn:timezone":"Asia/Jakarta",
    "iso:country":"ID",
    "name:ind_x_preferred":[
        "Amis Satu"
    ],
    "wof:name":"Amis Satu",
    "wof:placetype":"locality"
},
  "geometry": {"coordinates":[108.175,-6.51889],"type":"Point"}
}