{
  "type": "Feature",
  "properties": {
    "gn:admin1_code":"17",
    "gn:asciiname":"Baratorong",
    "gn:country_code":"ID",
    "gn:dem":168,
    "gn:feature_class":"P",
    "gn:feature_code":"PPL",
    "gn:name":"Baratorong",
    "gn:population":0,
    "gn:timezone":"Asia/Makassar",
    "iso:country":"ID",
    "name:ind_x_preferred":[
        "Baratorong"
    ],
    "wof:name":"Baratorong",
    "wof:placetype":"locality"
},
  "geometry": {"coordinates":[116.57340000000001,-8.5693],"type":"Point"}
}