{
  "type": "Feature",
  "properties": {
    "gn:admin1_code":"10.0",
    "gn:asciiname":"Weru",
    "gn:country_code":"ID",
    "gn:dem":317,
    "gn:feature_class":"P",
    "gn:feature_code":"PPL",
    "gn:name":"Weru",
    "gn:population":0,
    "gn:timezone":"Asia/Jakarta",
    "iso:country":"ID",
    "name:ind_x_preferred":[
        "Weru"
    ],
    "wof:name":"Weru",
    "wof:placetype":"locality"
},
  "geometry": {"coordinates":[110.72194,-8.08917],"type":"Point"}
}