{
  "type": "Feature",
  "properties": {
    "gn:admin1_code":"17",
    "gn:asciiname":"Trengwalis",
    "gn:country_code":"ID",
    "gn:dem":679,
    "gn:feature_class":"P",
    "gn:feature_code":"PPL",
    "gn:name":"Trengwalis",
    "gn:population":0,
    "gn:timezone":"Asia/Makassar",
    "iso:country":"ID",
    "name:ind_x_preferred":[
        "Trengwalis"
    ],
    "wof:name":"Trengwalis",
    "wof:placetype":"locality"
},
  "geometry": {"coordinates":[116.3811,-8.5356],"type":"Point"}
}