{
  "type": "Feature",
  "properties": {
    "gn:admin1_code":"30.0",
    "gn:asciiname":"Menol",
    "gn:country_code":"ID",
    "gn:dem":239,
    "gn:feature_class":"P",
    "gn:feature_code":"PPLA4",
    "gn:name":"Menol",
    "gn:population":0,
    "gn:timezone":"Asia/Jakarta",
    "iso:country":"ID",
    "name:ind_x_preferred":[
        "Menol"
    ],
    "wof:name":"Menol",
    "wof:placetype":"locality"
},
  "geometry": {"coordinates":[108.0879,-7.643],"type":"Point"}
}