{
  "type": "Feature",
  "properties": {
    "gn:admin1_code":"26",
    "gn:asciiname":"Gungpinto",
    "gn:country_code":"ID",
    "gn:dem":1407,
    "gn:feature_class":"P",
    "gn:feature_code":"PPL",
    "gn:name":"Gungpinto",
    "gn:population":0,
    "gn:timezone":"Asia/Jakarta",
    "iso:country":"ID",
    "name:ind_x_preferred":[
        "Gungpinto"
    ],
    "name:und_x_variant":[
        "Gungpintau"
    ],
    "wof:lang_x_official":[
        "ind"
    ],
    "wof:lang_x_spoken":[
        "ind",
        "eng"
    ],
    "wof:name":"Gungpinto",
    "wof:placetype":"locality"
},
  "geometry": {"coordinates":[98.43917999999999,3.20788],"type":"Point"}
}