{
  "type": "Feature",
  "properties": {
    "gn:admin1_code":"21",
    "gn:asciiname":"Uetangko",
    "gn:country_code":"ID",
    "gn:dem":286,
    "gn:feature_class":"P",
    "gn:feature_code":"PPL",
    "gn:name":"Uetangko",
    "gn:population":0,
    "gn:timezone":"Asia/Makassar",
    "iso:country":"ID",
    "name:ind_x_preferred":[
        "Uetangko"
    ],
    "wof:name":"Uetangko",
    "wof:placetype":"locality"
},
  "geometry": {"coordinates":[121.8173,-1.2953],"type":"Point"}
}