{
  "type": "Feature",
  "properties": {
    "gn:admin1_code":"26",
    "gn:asciiname":"Janji-bilang",
    "gn:country_code":"ID",
    "gn:dem":1013,
    "gn:feature_class":"P",
    "gn:feature_code":"PPL",
    "gn:name":"Janji-bilang",
    "gn:population":0,
    "gn:timezone":"Asia/Jakarta",
    "iso:country":"ID",
    "name:ind_x_preferred":[
        "Janji-bilang"
    ],
    "wof:name":"Janji-bilang",
    "wof:placetype":"locality"
},
  "geometry": {"coordinates":[98.9813,1.981],"type":"Point"}
}