{
  "type": "Feature",
  "properties": {
    "gn:admin1_code":"34.0",
    "gn:asciiname":"Aladi",
    "gn:country_code":"ID",
    "gn:dem":23,
    "gn:feature_class":"P",
    "gn:feature_code":"PPL",
    "gn:name":"Aladi",
    "gn:population":0,
    "gn:timezone":"Asia/Makassar",
    "iso:country":"ID",
    "name:ind_x_preferred":[
        "Aladi"
    ],
    "wof:name":"Aladi",
    "wof:placetype":"locality"
},
  "geometry": {"coordinates":[123.2162,0.3856],"type":"Point"}
}