{
  "type": "Feature",
  "properties": {
    "gn:admin1_code":"04",
    "gn:asciiname":"Pondokranggon",
    "gn:country_code":"ID",
    "gn:dem":63,
    "gn:feature_class":"P",
    "gn:feature_code":"PPL",
    "gn:name":"Pondokranggon",
    "gn:population":0,
    "gn:timezone":"Asia/Jakarta",
    "iso:country":"ID",
    "name:ind_x_preferred":[
        "Pondokranggon"
    ],
    "name:und_x_variant":[
        "Pondokranggon 1",
        "Pondokranggon Satu"
    ],
    "wof:lang_x_official":[
        "ind"
    ],
    "wof:lang_x_spoken":[
        "ind",
        "eng"
    ],
    "wof:name":"Pondokranggon",
    "wof:placetype":"locality"
},
  "geometry": {"coordinates":[106.9128,-6.3472],"type":"Point"}
}