{
  "type": "Feature",
  "properties": {
    "gn:admin1_code":"18.0",
    "gn:asciiname":"Tumu",
    "gn:country_code":"ID",
    "gn:dem":874,
    "gn:feature_class":"P",
    "gn:feature_code":"PPLA4",
    "gn:name":"Tumu",
    "gn:population":0,
    "gn:timezone":"Asia/Makassar",
    "iso:country":"ID",
    "name:ceb_x_preferred":[
        "Tumu"
    ],
    "name:deu_x_preferred":[
        "Tumu"
    ],
    "name:ind_x_preferred":[
        "Tumu"
    ],
    "name:nld_x_preferred":[
        "Tumu"
    ],
    "name:swe_x_preferred":[
        "Tumu"
    ],
    "wof:name":"Tumu",
    "wof:placetype":"locality"
},
  "geometry": {"coordinates":[124.4967,-9.8883],"type":"Point"}
}