{
  "type": "Feature",
  "properties": {
    "gn:admin1_code":"7.0",
    "gn:asciiname":"Mrebet",
    "gn:country_code":"ID",
    "gn:dem":169,
    "gn:feature_class":"P",
    "gn:feature_code":"PPL",
    "gn:name":"Mrebet",
    "gn:population":0,
    "gn:timezone":"Asia/Jakarta",
    "iso:country":"ID",
    "name:ind_x_preferred":[
        "Mrebet"
    ],
    "wof:name":"Mrebet",
    "wof:placetype":"locality"
},
  "geometry": {"coordinates":[109.34917,-7.31917],"type":"Point"}
}