{
  "type": "Feature",
  "properties": {
    "gn:admin1_code":"30",
    "gn:asciiname":"Sukawama",
    "gn:country_code":"ID",
    "gn:dem":70,
    "gn:feature_class":"P",
    "gn:feature_code":"PPL",
    "gn:name":"Sukawama",
    "gn:population":0,
    "gn:timezone":"Asia/Jakarta",
    "iso:country":"ID",
    "wof:name":"Sukawama",
    "wof:placetype":"locality"
},
  "geometry": {"coordinates":[106.62972000000001,-6.38722],"type":"Point"}
}