{
  "type": "Feature",
  "properties": {
    "gn:admin1_code":"22.0",
    "gn:asciiname":"Bende",
    "gn:country_code":"ID",
    "gn:dem":21,
    "gn:feature_class":"P",
    "gn:feature_code":"PPL",
    "gn:name":"Bende",
    "gn:population":0,
    "gn:timezone":"Asia/Makassar",
    "iso:country":"ID",
    "name:ceb_x_preferred":[
        "Bende"
    ],
    "name:deu_x_preferred":[
        "Bende"
    ],
    "name:fra_x_preferred":[
        "Bende"
    ],
    "name:ind_x_preferred":[
        "Bende"
    ],
    "name:ita_x_preferred":[
        "Bende"
    ],
    "name:nld_x_preferred":[
        "Bende"
    ],
    "name:swe_x_preferred":[
        "Bende"
    ],
    "wof:lang_x_official":[
        "ind"
    ],
    "wof:lang_x_spoken":[
        "ind",
        "eng"
    ],
    "wof:name":"Bende",
    "wof:placetype":"locality"
},
  "geometry": {"coordinates":[121.658,-4.1217],"type":"Point"}
}