{
  "type": "Feature",
  "properties": {
    "gn:admin1_code":"33",
    "gn:asciiname":"Pasirkembang Wetan",
    "gn:country_code":"ID",
    "gn:dem":41,
    "gn:feature_class":"P",
    "gn:feature_code":"PPL",
    "gn:name":"Pasirkembang Wetan",
    "gn:population":0,
    "gn:timezone":"Asia/Jakarta",
    "iso:country":"ID",
    "name:ind_x_preferred":[
        "Pasirkembang Wetan"
    ],
    "wof:name":"Pasirkembang Wetan",
    "wof:placetype":"locality"
},
  "geometry": {"coordinates":[106.3556,-6.3444],"type":"Point"}
}