{
  "type": "Feature",
  "properties": {
    "gn:admin1_code":"30.0",
    "gn:asciiname":"Beringin",
    "gn:country_code":"ID",
    "gn:dem":9,
    "gn:feature_class":"P",
    "gn:feature_code":"PPL",
    "gn:name":"Beringin",
    "gn:population":0,
    "gn:timezone":"Asia/Jakarta",
    "iso:country":"ID",
    "name:ind_x_preferred":[
        "Beringin"
    ],
    "name:und_x_variant":[
        "Bringin"
    ],
    "wof:name":"Beringin",
    "wof:placetype":"locality"
},
  "geometry": {"coordinates":[108.6525,-6.8158],"type":"Point"}
}