{
  "type": "Feature",
  "properties": {
    "gn:admin1_code":"30",
    "gn:asciiname":"Nyalindung",
    "gn:country_code":"ID",
    "gn:dem":42,
    "gn:feature_class":"P",
    "gn:feature_code":"PPL",
    "gn:name":"Nyalindung",
    "gn:population":0,
    "gn:timezone":"Asia/Jakarta",
    "iso:country":"ID",
    "name:ind_x_preferred":[
        "Nyalindung"
    ],
    "wof:name":"Nyalindung",
    "wof:placetype":"locality"
},
  "geometry": {"coordinates":[108.12166999999999,-6.73278],"type":"Point"}
}