{
  "type": "Feature",
  "properties": {
    "gn:admin1_code":"22",
    "gn:asciiname":"Ingot",
    "gn:country_code":"ID",
    "gn:dem":6,
    "gn:feature_class":"P",
    "gn:feature_code":"PPL",
    "gn:name":"Ingot",
    "gn:population":0,
    "gn:timezone":"Asia/Makassar",
    "iso:country":"ID",
    "name:ara_x_preferred":[
        "\u0635\u0628\u0629"
    ],
    "name:bel_x_preferred":[
        "\u0417\u043b\u0456\u0442\u0430\u043a"
    ],
    "name:bos_x_preferred":[
        "Ingot"
    ],
    "name:cat_x_preferred":[
        "Lingot"
    ],
    "name:ces_x_preferred":[
        "Ingot"
    ],
    "name:dan_x_preferred":[
        "Barre"
    ],
    "name:deu_x_preferred":[
        "Barren"
    ],
    "name:epo_x_preferred":[
        "Ingoto"
    ],
    "name:est_x_preferred":[
        "Toorik"
    ],
    "name:eus_x_preferred":[
        "Lingote"
    ],
    "name:fas_x_preferred":[
        "\u0634\u0645\u0634"
    ],
    "name:fra_x_preferred":[
        "Lingot"
    ],
    "name:glg_x_preferred":[
        "Lingote"
    ],
    "name:hrv_x_preferred":[
        "Ingot"
    ],
    "name:ido_x_preferred":[
        "Lingoto"
    ],
    "name:ind_x_preferred":[
        "Ingot"
    ],
    "name:ita_x_preferred":[
        "Lingotto"
    ],
    "name:lit_x_preferred":[
        "Liejinys"
    ],
    "name:msa_x_preferred":[
        "Jongkong"
    ],
    "name:nld_x_preferred":[
        "Lingot"
    ],
    "name:nor_x_preferred":[
        "Barre"
    ],
    "name:oci_x_preferred":[
        "Ling\u00f2t"
    ],
    "name:oss_x_preferred":[
        "\u0417\u0433\u044a\u00e6\u0440\u0442\u0430\u0434"
    ],
    "name:pol_x_preferred":[
        "Sztaba"
    ],
    "name:por_x_preferred":[
        "Lingote"
    ],
    "name:rus_x_preferred":[
        "\u0421\u043b\u0438\u0442\u043e\u043a"
    ],
    "name:slk_x_preferred":[
        "Ingot"
    ],
    "name:sna_x_preferred":[
        "Honha"
    ],
    "name:spa_x_preferred":[
        "Lingote"
    ],
    "name:srp_x_preferred":[
        "\u0418\u043d\u0433\u043e\u0442"
    ],
    "name:swe_x_preferred":[
        "Tacka"
    ],
    "name:ukr_x_preferred":[
        "\u0417\u043b\u0438\u0432\u043e\u043a"
    ],
    "name:uzb_x_preferred":[
        "Yombi"
    ],
    "wof:lang_x_official":[
        "ind"
    ],
    "wof:lang_x_spoken":[
        "ind",
        "eng"
    ],
    "wof:name":"Ingot",
    "wof:placetype":"locality"
},
  "geometry": {"coordinates":[121.6016,-4.1957],"type":"Point"}
}