{
  "type": "Feature",
  "properties": {
    "gn:admin1_code":"30",
    "gn:asciiname":"Walini",
    "gn:country_code":"ID",
    "gn:dem":664,
    "gn:feature_class":"P",
    "gn:feature_code":"PPL",
    "gn:name":"Walini",
    "gn:population":0,
    "gn:timezone":"Asia/Jakarta",
    "iso:country":"ID",
    "name:ind_x_preferred":[
        "Walini"
    ],
    "wof:name":"Walini",
    "wof:placetype":"locality"
},
  "geometry": {"coordinates":[107.75861,-6.98361],"type":"Point"}
}