{
  "type": "Feature",
  "properties": {
    "gn:admin1_code":"30",
    "gn:asciiname":"Bangsasuta",
    "gn:country_code":"ID",
    "gn:dem":25,
    "gn:feature_class":"P",
    "gn:feature_code":"PPL",
    "gn:name":"Bangsasuta",
    "gn:population":0,
    "gn:timezone":"Asia/Jakarta",
    "iso:country":"ID",
    "name:ind_x_preferred":[
        "Bangsasuta"
    ],
    "wof:name":"Bangsasuta",
    "wof:placetype":"locality"
},
  "geometry": {"coordinates":[107.55389,-6.34],"type":"Point"}
}