{
  "type": "Feature",
  "properties": {
    "gn:admin1_code":"18.0",
    "gn:asciiname":"Modu",
    "gn:country_code":"ID",
    "gn:dem":427,
    "gn:feature_class":"P",
    "gn:feature_code":"PPL",
    "gn:name":"Modu",
    "gn:population":0,
    "gn:timezone":"Asia/Makassar",
    "iso:country":"ID",
    "name:heb_x_preferred":[
        "\u05de\u05d5\u05d3\u05d5"
    ],
    "name:ind_x_preferred":[
        "Modu"
    ],
    "wof:lang_x_official":[
        "ind"
    ],
    "wof:lang_x_spoken":[
        "ind",
        "eng"
    ],
    "wof:name":"Modu",
    "wof:placetype":"locality"
},
  "geometry": {"coordinates":[119.4456,-9.631],"type":"Point"}
}