{
  "type": "Feature",
  "properties": {
    "gn:admin1_code":"1",
    "gn:asciiname":"Ramean",
    "gn:country_code":"ID",
    "gn:dem":25,
    "gn:feature_class":"P",
    "gn:feature_code":"PPL",
    "gn:name":"Ramean",
    "gn:population":0,
    "gn:timezone":"Asia/Jakarta",
    "iso:country":"ID",
    "name:ind_x_preferred":[
        "Ramean"
    ],
    "name:und_x_variant":[
        "Ramaan"
    ],
    "wof:name":"Ramean",
    "wof:placetype":"locality"
},
  "geometry": {"coordinates":[96.3091,4.1933],"type":"Point"}
}