{
  "type": "Feature",
  "properties": {
    "gn:admin1_code":"30.0",
    "gn:asciiname":"Pasirdalem",
    "gn:country_code":"ID",
    "gn:dem":339,
    "gn:feature_class":"P",
    "gn:feature_code":"PPLA4",
    "gn:name":"Pasirdalem",
    "gn:population":0,
    "gn:timezone":"Asia/Jakarta",
    "iso:country":"ID",
    "name:ind_x_preferred":[
        "Pasirdalem"
    ],
    "wof:name":"Pasirdalem",
    "wof:placetype":"locality"
},
  "geometry": {"coordinates":[106.6037,-7.2181],"type":"Point"}
}