{
  "type": "Feature",
  "properties": {
    "gn:admin1_code":"38.0",
    "gn:asciiname":"Sampa",
    "gn:country_code":"ID",
    "gn:dem":40,
    "gn:feature_class":"P",
    "gn:feature_code":"PPL",
    "gn:name":"Sampa",
    "gn:population":0,
    "gn:timezone":"Asia/Makassar",
    "iso:country":"ID",
    "name:bre_x_preferred":[
        "Sampa"
    ],
    "name:ceb_x_preferred":[
        "Sampa"
    ],
    "name:fra_x_preferred":[
        "Sampa"
    ],
    "name:ind_x_preferred":[
        "Sampa"
    ],
    "name:por_x_preferred":[
        "Sampa"
    ],
    "name:spa_x_preferred":[
        "Sampa"
    ],
    "name:swe_x_preferred":[
        "Sampa"
    ],
    "wof:lang_x_official":[
        "ind"
    ],
    "wof:lang_x_spoken":[
        "ind",
        "eng"
    ],
    "wof:name":"Sampa",
    "wof:placetype":"locality"
},
  "geometry": {"coordinates":[120.31789999999999,-3.3596],"type":"Point"}
}