{
  "type": "Feature",
  "properties": {
    "gn:admin1_code":"26.0",
    "gn:asciiname":"Parmonangan",
    "gn:country_code":"ID",
    "gn:dem":1078,
    "gn:feature_class":"P",
    "gn:feature_code":"PPL",
    "gn:name":"Parmonangan",
    "gn:population":0,
    "gn:timezone":"Asia/Jakarta",
    "iso:country":"ID",
    "name:ind_x_preferred":[
        "Parmonangan"
    ],
    "wof:name":"Parmonangan",
    "wof:placetype":"locality"
},
  "geometry": {"coordinates":[98.7544,2.7335],"type":"Point"}
}