{
  "type": "Feature",
  "properties": {
    "gn:admin1_code":"38",
    "gn:asciiname":"Cempae",
    "gn:country_code":"ID",
    "gn:dem":26,
    "gn:feature_class":"P",
    "gn:feature_code":"PPL",
    "gn:name":"Cempae",
    "gn:population":0,
    "gn:timezone":"Asia/Makassar",
    "iso:country":"ID",
    "name:ind_x_preferred":[
        "Cempae"
    ],
    "wof:name":"Cempae",
    "wof:placetype":"locality"
},
  "geometry": {"coordinates":[120.3258,-4.768],"type":"Point"}
}