{
  "type": "Feature",
  "properties": {
    "gn:admin1_code":"30",
    "gn:asciiname":"Cisomang Kaler",
    "gn:country_code":"ID",
    "gn:dem":683,
    "gn:feature_class":"P",
    "gn:feature_code":"PPL",
    "gn:name":"Cisomang Kaler",
    "gn:population":0,
    "gn:timezone":"Asia/Jakarta",
    "iso:country":"ID",
    "name:ind_x_preferred":[
        "Cisomang Kaler"
    ],
    "wof:name":"Cisomang Kaler",
    "wof:placetype":"locality"
},
  "geometry": {"coordinates":[107.45999999999999,-6.71611],"type":"Point"}
}