{
  "type": "Feature",
  "properties": {
    "gn:admin1_code":"8.0",
    "gn:asciiname":"Dukonangka",
    "gn:country_code":"ID",
    "gn:dem":36,
    "gn:feature_class":"P",
    "gn:feature_code":"PPL",
    "gn:name":"Dukonangka",
    "gn:population":0,
    "gn:timezone":"Asia/Jakarta",
    "iso:country":"ID",
    "name:ind_x_preferred":[
        "Dukonangka"
    ],
    "wof:name":"Dukonangka",
    "wof:placetype":"locality"
},
  "geometry": {"coordinates":[112.90260000000001,-6.9457],"type":"Point"}
}