{
  "type": "Feature",
  "properties": {
    "gn:admin1_code":"37",
    "gn:asciiname":"Kota-dalam",
    "gn:country_code":"ID",
    "gn:dem":82,
    "gn:feature_class":"P",
    "gn:feature_code":"PPL",
    "gn:name":"Kota-dalam",
    "gn:population":0,
    "gn:timezone":"Asia/Jakarta",
    "iso:country":"ID",
    "name:eng_x_preferred":[
        "Kota-dalam"
    ],
    "wof:lang_x_official":[
        "ind"
    ],
    "wof:lang_x_spoken":[
        "ind",
        "eng"
    ],
    "wof:name":"Kota-dalam",
    "wof:placetype":"locality"
},
  "geometry": {"coordinates":[100.64239999999999,0.3447],"type":"Point"}
}