{
  "type": "Feature",
  "properties": {
    "gn:admin1_code":"29.0",
    "gn:asciiname":"Gamkonora",
    "gn:country_code":"ID",
    "gn:dem":17,
    "gn:feature_class":"P",
    "gn:feature_code":"PPL",
    "gn:name":"Gamkonora",
    "gn:population":0,
    "gn:timezone":"Asia/Jayapura",
    "iso:country":"ID",
    "name:und_x_variant":[
        "Gumkonora",
        "Gamkonora"
    ],
    "wof:name":"Gamkonora",
    "wof:placetype":"locality"
},
  "geometry": {"coordinates":[127.53385,1.43526],"type":"Point"}
}