{
  "type": "Feature",
  "properties": {
    "gn:admin1_code":"29.0",
    "gn:asciiname":"Gamkonora",
    "gn:country_code":"ID",
    "gn:dem":17,
    "gn:feature_class":"P",
    "gn:feature_code":"PPL",
    "gn:name":"Gamkonora",
    "gn:population":0,
    "gn:timezone":"Asia/Jayapura",
    "iso:country":"ID",
    "name:ceb_x_preferred":[
        "Gunung Gamkonora"
    ],
    "name:deu_x_preferred":[
        "Gamkonora"
    ],
    "name:fra_x_preferred":[
        "Mont Gamkonora"
    ],
    "name:ind_x_preferred":[
        "Gunung Gamkonora"
    ],
    "name:jav_x_preferred":[
        "Gunung Gamkonora"
    ],
    "name:nno_x_preferred":[
        "Gamkonora"
    ],
    "name:por_x_preferred":[
        "Monte Gamkonora"
    ],
    "name:rus_x_preferred":[
        "\u0413\u0430\u043c\u043a\u043e\u043d\u043e\u0440\u0430"
    ],
    "name:slk_x_preferred":[
        "Gamkonora"
    ],
    "name:spa_x_preferred":[
        "Monte Gamkonora"
    ],
    "name:sun_x_preferred":[
        "Gunung Gamkonora"
    ],
    "name:swe_x_preferred":[
        "Gunung Gamkonora"
    ],
    "name:und_x_variant":[
        "Gumkonora",
        "Gamkonora"
    ],
    "name:zho_x_preferred":[
        "\u7518\u79d1\u8afe\u62c9\u706b\u5c71"
    ],
    "wof:lang_x_official":[
        "ind"
    ],
    "wof:lang_x_spoken":[
        "ind",
        "eng"
    ],
    "wof:name":"Gamkonora",
    "wof:placetype":"locality"
},
  "geometry": {"coordinates":[127.53385,1.43526],"type":"Point"}
}