{
  "type": "Feature",
  "properties": {
    "gn:admin1_code":"26.0",
    "gn:asciiname":"Lancang",
    "gn:country_code":"ID",
    "gn:dem":1013,
    "gn:feature_class":"P",
    "gn:feature_code":"PPL",
    "gn:name":"Lancang",
    "gn:population":0,
    "gn:timezone":"Asia/Jakarta",
    "iso:country":"ID",
    "name:fra_x_preferred":[
        "Lancang"
    ],
    "name:ind_x_preferred":[
        "Lancang"
    ],
    "name:nld_x_preferred":[
        "Lancang"
    ],
    "name:nor_x_preferred":[
        "Lancang"
    ],
    "name:und_x_variant":[
        "Lantjang"
    ],
    "wof:name":"Lancang",
    "wof:placetype":"locality"
},
  "geometry": {"coordinates":[99.2123,2.3407],"type":"Point"}
}