{
  "type": "Feature",
  "properties": {
    "gn:admin1_code":"7.0",
    "gn:asciiname":"Sempu",
    "gn:country_code":"ID",
    "gn:dem":418,
    "gn:feature_class":"P",
    "gn:feature_code":"PPL",
    "gn:name":"Sempu",
    "gn:population":0,
    "gn:timezone":"Asia/Jakarta",
    "iso:country":"ID",
    "name:ceb_x_preferred":[
        "Sempu"
    ],
    "name:fra_x_preferred":[
        "Sempu"
    ],
    "name:ind_x_preferred":[
        "Sempu"
    ],
    "name:nld_x_preferred":[
        "Sempu"
    ],
    "name:swe_x_preferred":[
        "Sempu"
    ],
    "wof:lang_x_official":[
        "ind"
    ],
    "wof:lang_x_spoken":[
        "ind",
        "eng"
    ],
    "wof:name":"Sempu",
    "wof:placetype":"locality"
},
  "geometry": {"coordinates":[110.23222,-7.41222],"type":"Point"}
}