{
  "type": "Feature",
  "properties": {
    "gn:admin1_code":"26",
    "gn:asciiname":"Bandar Aceh",
    "gn:country_code":"ID",
    "gn:dem":25,
    "gn:feature_class":"P",
    "gn:feature_code":"PPL",
    "gn:name":"Bandar Aceh",
    "gn:population":0,
    "gn:timezone":"Asia/Jakarta",
    "iso:country":"ID",
    "name:ind_x_preferred":[
        "Bandar Aceh"
    ],
    "wof:name":"Bandar Aceh",
    "wof:placetype":"locality"
},
  "geometry": {"coordinates":[98.417,2.0306],"type":"Point"}
}