{
  "type": "Feature",
  "properties": {
    "gn:admin1_code":"7.0",
    "gn:asciiname":"Kalimenyawak",
    "gn:country_code":"ID",
    "gn:dem":193,
    "gn:feature_class":"P",
    "gn:feature_code":"PPL",
    "gn:name":"Kalimenyawak",
    "gn:population":0,
    "gn:timezone":"Asia/Jakarta",
    "iso:country":"ID",
    "name:ind_x_preferred":[
        "Kalimenyawak"
    ],
    "wof:name":"Kalimenyawak",
    "wof:placetype":"locality"
},
  "geometry": {"coordinates":[108.99556,-7.43028],"type":"Point"}
}