{
  "type": "Feature",
  "properties": {
    "gn:admin1_code":"7",
    "gn:asciiname":"Leles",
    "gn:country_code":"ID",
    "gn:dem":204,
    "gn:feature_class":"P",
    "gn:feature_code":"PPL",
    "gn:name":"Leles",
    "gn:population":0,
    "gn:timezone":"Asia/Jakarta",
    "iso:country":"ID",
    "name:cat_x_preferred":[
        "Leles"
    ],
    "name:ces_x_preferred":[
        "Leles"
    ],
    "name:deu_x_preferred":[
        "Leles"
    ],
    "name:epo_x_preferred":[
        "Leles"
    ],
    "name:eus_x_preferred":[
        "Leles"
    ],
    "name:fra_x_preferred":[
        "Leles"
    ],
    "name:hun_x_preferred":[
        "Lelesz"
    ],
    "name:ind_x_preferred":[
        "Leles"
    ],
    "name:ita_x_preferred":[
        "Leles"
    ],
    "name:msa_x_preferred":[
        "Leles"
    ],
    "name:nld_x_preferred":[
        "Leles"
    ],
    "name:pol_x_preferred":[
        "Leles"
    ],
    "name:ron_x_preferred":[
        "Leles"
    ],
    "name:rue_x_preferred":[
        "\u041b\u0435\u043b\u0435\u0441"
    ],
    "name:slk_x_preferred":[
        "Leles"
    ],
    "name:spa_x_preferred":[
        "Leles"
    ],
    "name:srp_x_preferred":[
        "\u0409\u0435\u0459\u0435\u0441"
    ],
    "name:tur_x_preferred":[
        "Leles"
    ],
    "name:ukr_x_preferred":[
        "\u041b\u0435\u043b\u0435\u0441"
    ],
    "name:war_x_preferred":[
        "Leles"
    ],
    "wof:lang_x_official":[
        "ind"
    ],
    "wof:lang_x_spoken":[
        "ind",
        "eng"
    ],
    "wof:name":"Leles",
    "wof:placetype":"locality"
},
  "geometry": {"coordinates":[109.5089,-7.0933],"type":"Point"}
}