{
  "type": "Feature",
  "properties": {
    "gn:admin1_code":"30",
    "gn:asciiname":"Cinangneng Satu",
    "gn:country_code":"ID",
    "gn:dem":173,
    "gn:feature_class":"P",
    "gn:feature_code":"PPL",
    "gn:name":"Cinangneng Satu",
    "gn:population":0,
    "gn:timezone":"Asia/Jakarta",
    "iso:country":"ID",
    "name:ind_x_preferred":[
        "Cinangneng Satu"
    ],
    "name:und_x_variant":[
        "Cinangneng 1"
    ],
    "wof:lang_x_official":[
        "ind"
    ],
    "wof:lang_x_spoken":[
        "ind",
        "eng"
    ],
    "wof:name":"Cinangneng Satu",
    "wof:placetype":"locality"
},
  "geometry": {"coordinates":[106.71083,-6.56194],"type":"Point"}
}