{
  "type": "Feature",
  "properties": {
    "gn:admin1_code":"26",
    "gn:asciiname":"Raja",
    "gn:country_code":"ID",
    "gn:dem":6,
    "gn:feature_class":"P",
    "gn:feature_code":"PPL",
    "gn:name":"Raja",
    "gn:population":0,
    "gn:timezone":"Asia/Jakarta",
    "iso:country":"ID",
    "name:ind_x_preferred":[
        "Raja"
    ],
    "name:und_x_variant":[
        "Radja"
    ],
    "wof:name":"Raja",
    "wof:placetype":"locality"
},
  "geometry": {"coordinates":[99.5826,3.1811],"type":"Point"}
}