{
  "type": "Feature",
  "properties": {
    "gn:admin1_code":"30.0",
    "gn:asciiname":"Datarlega",
    "gn:country_code":"ID",
    "gn:dem":14,
    "gn:feature_class":"P",
    "gn:feature_code":"PPL",
    "gn:name":"Datarlega",
    "gn:population":0,
    "gn:timezone":"Asia/Jakarta",
    "iso:country":"ID",
    "name:ind_x_preferred":[
        "Datarlega"
    ],
    "wof:name":"Datarlega",
    "wof:placetype":"locality"
},
  "geometry": {"coordinates":[106.9948,-7.4394],"type":"Point"}
}