{
  "type": "Feature",
  "properties": {
    "gn:admin1_code":"38",
    "gn:asciiname":"Kalindu",
    "gn:country_code":"ID",
    "gn:dem":6,
    "gn:feature_class":"P",
    "gn:feature_code":"PPL",
    "gn:name":"Kalindu",
    "gn:population":0,
    "gn:timezone":"Asia/Makassar",
    "iso:country":"ID",
    "name:ind_x_preferred":[
        "Kalindu"
    ],
    "wof:name":"Kalindu",
    "wof:placetype":"locality"
},
  "geometry": {"coordinates":[119.3048,-1.4172],"type":"Point"}
}