{
  "type": "Feature",
  "properties": {
    "gn:admin1_code":"7",
    "gn:asciiname":"Suru",
    "gn:country_code":"ID",
    "gn:dem":48,
    "gn:feature_class":"P",
    "gn:feature_code":"PPL",
    "gn:name":"Suru",
    "gn:population":0,
    "gn:timezone":"Asia/Jakarta",
    "iso:country":"ID",
    "name:ceb_x_preferred":[
        "Suru"
    ],
    "name:hye_x_preferred":[
        "\u054d\u0578\u0582\u057c\u0578\u0582"
    ],
    "name:ind_x_preferred":[
        "Suru"
    ],
    "name:nld_x_preferred":[
        "Suru"
    ],
    "name:rus_x_preferred":[
        "\u0421\u0443\u0440\u0443"
    ],
    "name:swe_x_preferred":[
        "Suru"
    ],
    "name:ukr_x_preferred":[
        "\u0421\u0443\u0440\u0443"
    ],
    "wof:lang_x_official":[
        "ind"
    ],
    "wof:lang_x_spoken":[
        "ind",
        "eng"
    ],
    "wof:name":"Suru",
    "wof:placetype":"locality"
},
  "geometry": {"coordinates":[110.84083,-7.19833],"type":"Point"}
}