{
  "type": "Feature",
  "properties": {
    "gn:admin1_code":"37.0",
    "gn:asciiname":"Gambir",
    "gn:country_code":"ID",
    "gn:dem":49,
    "gn:feature_class":"P",
    "gn:feature_code":"PPL",
    "gn:name":"Gambir",
    "gn:population":0,
    "gn:timezone":"Asia/Jakarta",
    "iso:country":"ID",
    "name:ceb_x_preferred":[
        "Gambir"
    ],
    "name:ind_x_preferred":[
        "Gambir"
    ],
    "name:nld_x_preferred":[
        "Gambir"
    ],
    "name:swe_x_preferred":[
        "Gambir"
    ],
    "wof:lang_x_official":[
        "ind"
    ],
    "wof:lang_x_spoken":[
        "ind",
        "eng"
    ],
    "wof:name":"Gambir",
    "wof:placetype":"locality"
},
  "geometry": {"coordinates":[102.1039,-0.4246],"type":"Point"}
}