{
  "type": "Feature",
  "properties": {
    "gn:admin1_code":"14.0",
    "gn:asciiname":"Rajancandung",
    "gn:country_code":"ID",
    "gn:dem":553,
    "gn:feature_class":"P",
    "gn:feature_code":"PPL",
    "gn:name":"Rajancandung",
    "gn:population":0,
    "gn:timezone":"Asia/Makassar",
    "iso:country":"ID",
    "name:und_x_variant":[
        "Radjantjandoeng",
        "Radjantjandung",
        "Rajancandung"
    ],
    "wof:lang_x_official":[
        "ind"
    ],
    "wof:lang_x_spoken":[
        "ind",
        "eng"
    ],
    "wof:name":"Rajancandung",
    "wof:placetype":"locality"
},
  "geometry": {"coordinates":[117.41667,1.63333],"type":"Point"}
}