{
  "type": "Feature",
  "properties": {
    "gn:admin1_code":"18.0",
    "gn:asciiname":"Puuletena",
    "gn:country_code":"ID",
    "gn:dem":486,
    "gn:feature_class":"P",
    "gn:feature_code":"PPL",
    "gn:name":"Puuletena",
    "gn:population":0,
    "gn:timezone":"Asia/Makassar",
    "iso:country":"ID",
    "name:ind_x_preferred":[
        "Puuletena"
    ],
    "wof:name":"Puuletena",
    "wof:placetype":"locality"
},
  "geometry": {"coordinates":[119.3691,-9.5711],"type":"Point"}
}