{
  "type": "Feature",
  "properties": {
    "gn:admin1_code":"42",
    "gn:asciiname":"Kendari",
    "gn:country_code":"ID",
    "gn:dem":10,
    "gn:feature_class":"P",
    "gn:feature_code":"PPL",
    "gn:name":"Kendari",
    "gn:population":0,
    "gn:timezone":"Asia/Makassar",
    "iso:country":"ID",
    "name:afr_x_preferred":[
        "Kendari"
    ],
    "name:ara_x_preferred":[
        "\u0643\u0646\u062f\u0627\u0631\u064a"
    ],
    "name:ast_x_preferred":[
        "Kendari"
    ],
    "name:azb_x_preferred":[
        "\u06a9\u0626\u0646\u062f\u0627\u0631\u06cc"
    ],
    "name:bel_x_preferred":[
        "\u041a\u0435\u043d\u0434\u0430\u0440\u044b"
    ],
    "name:ceb_x_preferred":[
        "Kendari"
    ],
    "name:deu_x_preferred":[
        "Kendari"
    ],
    "name:eus_x_preferred":[
        "Kendari"
    ],
    "name:fas_x_preferred":[
        "\u06a9\u0646\u062f\u0631\u06cc"
    ],
    "name:fin_x_preferred":[
        "Kendari"
    ],
    "name:fra_x_preferred":[
        "Kendari"
    ],
    "name:gor_x_preferred":[
        "Kota Kendari"
    ],
    "name:hun_x_preferred":[
        "Kendari"
    ],
    "name:ind_x_preferred":[
        "Kendari"
    ],
    "name:ind_x_variant":[
        "Kota Kendari"
    ],
    "name:ita_x_preferred":[
        "Kendari"
    ],
    "name:jav_x_preferred":[
        "Kutha Kendhari"
    ],
    "name:jpn_x_preferred":[
        "\u30b1\u30f3\u30c0\u30ea"
    ],
    "name:kor_x_preferred":[
        "\ud070\ub2e4\ub9ac"
    ],
    "name:lit_x_preferred":[
        "Kendaris"
    ],
    "name:mlg_x_preferred":[
        "Kota Kendari"
    ],
    "name:msa_x_preferred":[
        "Kota Kendari"
    ],
    "name:nld_x_preferred":[
        "Kendari"
    ],
    "name:nor_x_preferred":[
        "Kendari"
    ],
    "name:pnb_x_preferred":[
        "\u06a9\u0646\u062f\u0627\u0631\u06cc"
    ],
    "name:pol_x_preferred":[
        "Kendari"
    ],
    "name:por_x_preferred":[
        "Kendari"
    ],
    "name:ron_x_preferred":[
        "Kendari"
    ],
    "name:rus_x_preferred":[
        "\u041a\u0435\u043d\u0434\u0430\u0440\u0438"
    ],
    "name:spa_x_preferred":[
        "Kendari"
    ],
    "name:swe_x_preferred":[
        "Kendari"
    ],
    "name:tha_x_preferred":[
        "\u0e40\u0e01\u0e34\u0e19\u0e14\u0e32\u0e23\u0e35"
    ],
    "name:tur_x_preferred":[
        "Kendari"
    ],
    "name:ukr_x_preferred":[
        "\u041a\u0435\u043d\u0434\u0430\u0440\u0456"
    ],
    "name:urd_x_preferred":[
        "\u06a9\u0646\u062f\u0627\u0631\u06cc"
    ],
    "name:war_x_preferred":[
        "Kendari"
    ],
    "name:zho_x_preferred":[
        "\u80af\u9054\u91cc"
    ],
    "wof:lang_x_official":[
        "ind"
    ],
    "wof:lang_x_spoken":[
        "ind",
        "eng"
    ],
    "wof:name":"Kendari",
    "wof:placetype":"locality"
},
  "geometry": {"coordinates":[117.15487,3.26016],"type":"Point"}
}