{
  "type": "Feature",
  "properties": {
    "gn:admin1_code":"37",
    "gn:asciiname":"Aursat",
    "gn:country_code":"ID",
    "gn:dem":21,
    "gn:feature_class":"P",
    "gn:feature_code":"PPL",
    "gn:name":"Aursat",
    "gn:population":0,
    "gn:timezone":"Asia/Jakarta",
    "iso:country":"ID",
    "name:ind_x_preferred":[
        "Aursat"
    ],
    "wof:name":"Aursat",
    "wof:placetype":"locality"
},
  "geometry": {"coordinates":[101.2542,0.354],"type":"Point"}
}