{
  "type": "Feature",
  "properties": {
    "gn:admin1_code":"31.0",
    "gn:asciiname":"Sompini",
    "gn:country_code":"ID",
    "gn:dem":6,
    "gn:feature_class":"P",
    "gn:feature_code":"PPL",
    "gn:name":"Sompini",
    "gn:population":0,
    "gn:timezone":"Asia/Makassar",
    "iso:country":"ID",
    "name:ind_x_preferred":[
        "Sompini"
    ],
    "wof:name":"Sompini",
    "wof:placetype":"locality"
},
  "geometry": {"coordinates":[124.88339999999999,0.9904],"type":"Point"}
}