{
  "type": "Feature",
  "properties": {
    "gn:admin1_code":"30.0",
    "gn:asciiname":"Cibungur",
    "gn:country_code":"ID",
    "gn:dem":265,
    "gn:feature_class":"P",
    "gn:feature_code":"PPL",
    "gn:name":"Cibungur",
    "gn:population":0,
    "gn:timezone":"Asia/Jakarta",
    "iso:country":"ID",
    "name:ind_x_preferred":[
        "Cibungur"
    ],
    "wof:name":"Cibungur",
    "wof:placetype":"locality"
},
  "geometry": {"coordinates":[108.1409,-7.4601],"type":"Point"}
}