{
  "type": "Feature",
  "properties": {
    "gn:admin1_code":"26",
    "gn:asciiname":"Pagarantonga",
    "gn:country_code":"ID",
    "gn:dem":37,
    "gn:feature_class":"P",
    "gn:feature_code":"PPL",
    "gn:name":"Pagarantonga",
    "gn:population":0,
    "gn:timezone":"Asia/Jakarta",
    "iso:country":"ID",
    "name:ind_x_preferred":[
        "Pagarantonga"
    ],
    "wof:name":"Pagarantonga",
    "wof:placetype":"locality"
},
  "geometry": {"coordinates":[100.00118000000001,1.55132],"type":"Point"}
}