{
  "type": "Feature",
  "properties": {
    "gn:admin1_code":"30",
    "gn:asciiname":"Mujit",
    "gn:country_code":"ID",
    "gn:dem":491,
    "gn:feature_class":"P",
    "gn:feature_code":"PPL",
    "gn:name":"Mujit",
    "gn:population":0,
    "gn:timezone":"Asia/Jakarta",
    "iso:country":"ID",
    "name:ind_x_preferred":[
        "Mujit"
    ],
    "wof:name":"Mujit",
    "wof:placetype":"locality"
},
  "geometry": {"coordinates":[107.28306000000001,-6.90056],"type":"Point"}
}