{
  "type": "Feature",
  "properties": {
    "gn:admin1_code":"18.0",
    "gn:asciiname":"Benbesi",
    "gn:country_code":"ID",
    "gn:dem":493,
    "gn:feature_class":"P",
    "gn:feature_code":"PPL",
    "gn:name":"Benbesi",
    "gn:population":0,
    "gn:timezone":"Asia/Makassar",
    "iso:country":"ID",
    "name:ind_x_preferred":[
        "Benbesi"
    ],
    "wof:name":"Benbesi",
    "wof:placetype":"locality"
},
  "geometry": {"coordinates":[124.3359,-9.9941],"type":"Point"}
}