{
  "type": "Feature",
  "properties": {
    "gn:admin1_code":"22.0",
    "gn:asciiname":"Kadeadea",
    "gn:country_code":"ID",
    "gn:dem":198,
    "gn:feature_class":"P",
    "gn:feature_code":"PPL",
    "gn:name":"Kadeadea",
    "gn:population":0,
    "gn:timezone":"Asia/Makassar",
    "iso:country":"ID",
    "name:ind_x_preferred":[
        "Kadeadea"
    ],
    "name:und_x_variant":[
        "Lahadeadea"
    ],
    "wof:lang_x_official":[
        "ind"
    ],
    "wof:lang_x_spoken":[
        "ind",
        "eng"
    ],
    "wof:name":"Kadeadea",
    "wof:placetype":"locality"
},
  "geometry": {"coordinates":[122.616,-5.0073],"type":"Point"}
}