{
  "type": "Feature",
  "properties": {
    "gn:admin1_code":"37.0",
    "gn:asciiname":"Telukempas",
    "gn:country_code":"ID",
    "gn:dem":1,
    "gn:feature_class":"P",
    "gn:feature_code":"PPL",
    "gn:name":"Telukempas",
    "gn:population":0,
    "gn:timezone":"Asia/Jakarta",
    "iso:country":"ID",
    "name:ind_x_preferred":[
        "Telukempas"
    ],
    "wof:name":"Telukempas",
    "wof:placetype":"locality"
},
  "geometry": {"coordinates":[102.846,-0.5327],"type":"Point"}
}