{
  "type": "Feature",
  "properties": {
    "gn:admin1_code":"07",
    "gn:asciiname":"Pandak",
    "gn:country_code":"ID",
    "gn:dem":558,
    "gn:feature_class":"P",
    "gn:feature_code":"PPL",
    "gn:name":"Pandak",
    "gn:population":0,
    "gn:timezone":"Asia/Jakarta",
    "iso:country":"ID",
    "name:ceb_x_preferred":[
        "Pandak"
    ],
    "name:ind_x_preferred":[
        "Pandak"
    ],
    "name:nld_x_preferred":[
        "Pandak"
    ],
    "name:swe_x_preferred":[
        "Pandak"
    ],
    "name:und_x_variant":[
        "Pandak-kulon",
        "Pandak"
    ],
    "wof:lang_x_official":[
        "ind"
    ],
    "wof:lang_x_spoken":[
        "ind",
        "eng"
    ],
    "wof:name":"Pandak",
    "wof:placetype":"locality"
},
  "geometry": {"coordinates":[110.29443999999999,-7.42778],"type":"Point"}
}