{
  "type": "Feature",
  "properties": {
    "gn:admin1_code":"26",
    "gn:asciiname":"Siporka",
    "gn:country_code":"ID",
    "gn:dem":916,
    "gn:feature_class":"P",
    "gn:feature_code":"PPL",
    "gn:name":"Siporka",
    "gn:population":0,
    "gn:timezone":"Asia/Jakarta",
    "iso:country":"ID",
    "name:ind_x_preferred":[
        "Siporka"
    ],
    "wof:name":"Siporka",
    "wof:placetype":"locality"
},
  "geometry": {"coordinates":[98.85209999999999,3.0186],"type":"Point"}
}