{
  "type": "Feature",
  "properties": {
    "gn:admin1_code":"26",
    "gn:asciiname":"Tondang",
    "gn:country_code":"ID",
    "gn:dem":967,
    "gn:feature_class":"P",
    "gn:feature_code":"PPL",
    "gn:name":"Tondang",
    "gn:population":0,
    "gn:timezone":"Asia/Jakarta",
    "iso:country":"ID",
    "name:ind_x_preferred":[
        "Tondang"
    ],
    "wof:name":"Tondang",
    "wof:placetype":"locality"
},
  "geometry": {"coordinates":[98.8737,3.0061],"type":"Point"}
}