{
  "type": "Feature",
  "properties": {
    "gn:admin1_code":"14",
    "gn:asciiname":"Gunungbakaran",
    "gn:country_code":"ID",
    "gn:dem":28,
    "gn:feature_class":"P",
    "gn:feature_code":"PPL",
    "gn:name":"Gunungbakaran",
    "gn:population":0,
    "gn:timezone":"Asia/Makassar",
    "iso:country":"ID",
    "name:ind_x_preferred":[
        "Gunungbakaran"
    ],
    "wof:name":"Gunungbakaran",
    "wof:placetype":"locality"
},
  "geometry": {"coordinates":[116.8755,-1.2655],"type":"Point"}
}