{
  "type": "Feature",
  "properties": {
    "gn:admin1_code":"15.0",
    "gn:asciiname":"Talang Bojong",
    "gn:country_code":"ID",
    "gn:dem":39,
    "gn:feature_class":"P",
    "gn:feature_code":"PPL",
    "gn:name":"Talang Bojong",
    "gn:population":0,
    "gn:timezone":"Asia/Jakarta",
    "iso:country":"ID",
    "name:ind_x_preferred":[
        "Talang Bojong"
    ],
    "name:und_x_variant":[
        "Talangbojong"
    ],
    "wof:name":"Talang Bojong",
    "wof:placetype":"locality"
},
  "geometry": {"coordinates":[104.83847,-4.83664],"type":"Point"}
}