{
  "type": "Feature",
  "properties": {
    "gn:admin1_code":"15.0",
    "gn:asciiname":"Panjirejo",
    "gn:country_code":"ID",
    "gn:dem":100,
    "gn:feature_class":"P",
    "gn:feature_code":"PPL",
    "gn:name":"Panjirejo",
    "gn:population":0,
    "gn:timezone":"Asia/Jakarta",
    "iso:country":"ID",
    "name:ind_x_preferred":[
        "Panjirejo"
    ],
    "wof:name":"Panjirejo",
    "wof:placetype":"locality"
},
  "geometry": {"coordinates":[104.99782999999999,-5.38174],"type":"Point"}
}