{
  "type": "Feature",
  "properties": {
    "gn:admin1_code":"7",
    "gn:asciiname":"Karanganyar",
    "gn:country_code":"ID",
    "gn:dem":17,
    "gn:feature_class":"P",
    "gn:feature_code":"PPL",
    "gn:name":"Karanganyar",
    "gn:population":0,
    "gn:timezone":"Asia/Jakarta",
    "iso:country":"ID",
    "name:ind_x_preferred":[
        "Karanganyar"
    ],
    "wof:name":"Karanganyar",
    "wof:placetype":"locality"
},
  "geometry": {"coordinates":[110.75960000000001,-7.0236],"type":"Point"}
}