{
  "type": "Feature",
  "properties": {
    "gn:admin1_code":"8.0",
    "gn:asciiname":"Temenggungan",
    "gn:country_code":"ID",
    "gn:dem":425,
    "gn:feature_class":"P",
    "gn:feature_code":"PPL",
    "gn:name":"Temenggungan",
    "gn:population":0,
    "gn:timezone":"Asia/Jakarta",
    "iso:country":"ID",
    "name:ind_x_preferred":[
        "Temenggungan"
    ],
    "name:und_x_variant":[
        "Temenggoongan",
        "Temenggoengan"
    ],
    "wof:name":"Temenggungan",
    "wof:placetype":"locality"
},
  "geometry": {"coordinates":[112.63979999999999,-7.9856],"type":"Point"}
}