{
  "type": "Feature",
  "properties": {
    "gn:admin1_code":"30",
    "gn:asciiname":"Tutupan",
    "gn:country_code":"ID",
    "gn:dem":42,
    "gn:feature_class":"P",
    "gn:feature_code":"PPL",
    "gn:name":"Tutupan",
    "gn:population":0,
    "gn:timezone":"Asia/Jakarta",
    "iso:country":"ID",
    "name:ind_x_preferred":[
        "Tutupan"
    ],
    "wof:name":"Tutupan",
    "wof:placetype":"locality"
},
  "geometry": {"coordinates":[107.82444,-6.49667],"type":"Point"}
}