{
  "type": "Feature",
  "properties": {
    "gn:admin1_code":"30.0",
    "gn:asciiname":"Timbangwindu",
    "gn:country_code":"ID",
    "gn:dem":144,
    "gn:feature_class":"P",
    "gn:feature_code":"PPL",
    "gn:name":"Timbangwindu",
    "gn:population":0,
    "gn:timezone":"Asia/Jakarta",
    "iso:country":"ID",
    "name:ind_x_preferred":[
        "Timbangwindu"
    ],
    "wof:name":"Timbangwindu",
    "wof:placetype":"locality"
},
  "geometry": {"coordinates":[108.39409999999999,-7.3246],"type":"Point"}
}