{
  "type": "Feature",
  "properties": {
    "gn:admin1_code":"17",
    "gn:asciiname":"Bagikrebak",
    "gn:country_code":"ID",
    "gn:dem":260,
    "gn:feature_class":"P",
    "gn:feature_code":"PPL",
    "gn:name":"Bagikrebak",
    "gn:population":0,
    "gn:timezone":"Asia/Makassar",
    "iso:country":"ID",
    "name:ind_x_preferred":[
        "Bagikrebak"
    ],
    "wof:name":"Bagikrebak",
    "wof:placetype":"locality"
},
  "geometry": {"coordinates":[116.548,-8.5615],"type":"Point"}
}