{
  "type": "Feature",
  "properties": {
    "gn:admin1_code":"18",
    "gn:asciiname":"Mandatar",
    "gn:country_code":"ID",
    "gn:dem":522,
    "gn:feature_class":"P",
    "gn:feature_code":"PPL",
    "gn:name":"Mandatar",
    "gn:population":0,
    "gn:timezone":"Asia/Makassar",
    "iso:country":"ID",
    "name:ind_x_preferred":[
        "Mandatar"
    ],
    "wof:name":"Mandatar",
    "wof:placetype":"locality"
},
  "geometry": {"coordinates":[119.8617,-9.6383],"type":"Point"}
}