{
  "type": "Feature",
  "properties": {
    "gn:admin1_code":"7",
    "gn:asciiname":"Wangantengah",
    "gn:country_code":"ID",
    "gn:dem":7,
    "gn:feature_class":"P",
    "gn:feature_code":"PPL",
    "gn:name":"Wangantengah",
    "gn:population":0,
    "gn:timezone":"Asia/Jakarta",
    "iso:country":"ID",
    "name:ind_x_preferred":[
        "Wangantengah"
    ],
    "wof:name":"Wangantengah",
    "wof:placetype":"locality"
},
  "geometry": {"coordinates":[109.095,-6.9005],"type":"Point"}
}