{
  "type": "Feature",
  "properties": {
    "gn:admin1_code":"8.0",
    "gn:asciiname":"Sumberjo",
    "gn:country_code":"ID",
    "gn:dem":124,
    "gn:feature_class":"P",
    "gn:feature_code":"PPL",
    "gn:name":"Sumberjo",
    "gn:population":0,
    "gn:timezone":"Asia/Jakarta",
    "iso:country":"ID",
    "name:ind_x_preferred":[
        "Sumberjo"
    ],
    "wof:name":"Sumberjo",
    "wof:placetype":"locality"
},
  "geometry": {"coordinates":[112.02930000000001,-7.9509],"type":"Point"}
}