{
  "type": "Feature",
  "properties": {
    "gn:admin1_code":"7",
    "gn:asciiname":"Guntur",
    "gn:country_code":"ID",
    "gn:dem":600,
    "gn:feature_class":"P",
    "gn:feature_code":"PPL",
    "gn:name":"Guntur",
    "gn:population":0,
    "gn:timezone":"Asia/Jakarta",
    "iso:country":"ID",
    "name:ind_x_preferred":[
        "Guntur"
    ],
    "wof:name":"Guntur",
    "wof:placetype":"locality"
},
  "geometry": {"coordinates":[111.12917,-7.53694],"type":"Point"}
}