{
  "type": "Feature",
  "properties": {
    "gn:admin1_code":"7.0",
    "gn:asciiname":"Ngadipiro Lor",
    "gn:country_code":"ID",
    "gn:dem":247,
    "gn:feature_class":"P",
    "gn:feature_code":"PPL",
    "gn:name":"Ngadipiro Lor",
    "gn:population":0,
    "gn:timezone":"Asia/Jakarta",
    "iso:country":"ID",
    "wof:name":"Ngadipiro Lor",
    "wof:placetype":"locality"
},
  "geometry": {"coordinates":[110.77167,-7.84889],"type":"Point"}
}