{
  "type": "Feature",
  "properties": {
    "gn:admin1_code":"30.0",
    "gn:asciiname":"Pulau Ceger",
    "gn:country_code":"ID",
    "gn:dem":25,
    "gn:feature_class":"P",
    "gn:feature_code":"PPL",
    "gn:name":"Pulau Ceger",
    "gn:population":0,
    "gn:timezone":"Asia/Jakarta",
    "iso:country":"ID",
    "name:ind_x_preferred":[
        "Pulau Ceger"
    ],
    "name:und_x_variant":[
        "Tjeger",
        "Ceger Satu",
        "Ceger"
    ],
    "wof:name":"Pulau Ceger",
    "wof:placetype":"locality"
},
  "geometry": {"coordinates":[106.9682,-6.2552],"type":"Point"}
}