{
  "type": "Feature",
  "properties": {
    "gn:admin1_code":"8.0",
    "gn:asciiname":"Tugurejo Dua",
    "gn:country_code":"ID",
    "gn:dem":438,
    "gn:feature_class":"P",
    "gn:feature_code":"PPL",
    "gn:name":"Tugurejo Dua",
    "gn:population":0,
    "gn:timezone":"Asia/Jakarta",
    "iso:country":"ID",
    "name:ind_x_preferred":[
        "Tugurejo Dua"
    ],
    "name:und_x_variant":[
        "Toegoeredjo 2"
    ],
    "wof:lang_x_official":[
        "ind"
    ],
    "wof:lang_x_spoken":[
        "ind",
        "eng"
    ],
    "wof:name":"Tugurejo Dua",
    "wof:placetype":"locality"
},
  "geometry": {"coordinates":[112.3827,-8.2786],"type":"Point"}
}