{
  "type": "Feature",
  "properties": {
    "gn:admin1_code":"7",
    "gn:asciiname":"Kuning",
    "gn:country_code":"ID",
    "gn:dem":168,
    "gn:feature_class":"P",
    "gn:feature_code":"PPL",
    "gn:name":"Kuning",
    "gn:population":0,
    "gn:timezone":"Asia/Jakarta",
    "iso:country":"ID",
    "name:ind_x_preferred":[
        "Kuning"
    ],
    "wof:name":"Kuning",
    "wof:placetype":"locality"
},
  "geometry": {"coordinates":[111.0775,-7.48889],"type":"Point"}
}