{
  "type": "Feature",
  "properties": {
    "gn:admin1_code":"18.0",
    "gn:asciiname":"Bodo",
    "gn:country_code":"ID",
    "gn:dem":749,
    "gn:feature_class":"P",
    "gn:feature_code":"PPL",
    "gn:name":"Bodo",
    "gn:population":0,
    "gn:timezone":"Asia/Makassar",
    "iso:country":"ID",
    "name:ind_x_preferred":[
        "Bodo"
    ],
    "wof:name":"Bodo",
    "wof:placetype":"locality"
},
  "geometry": {"coordinates":[121.11490000000001,-8.8015],"type":"Point"}
}