{
  "type": "Feature",
  "properties": {
    "gn:admin1_code":"26.0",
    "gn:asciiname":"Hutaduru",
    "gn:country_code":"ID",
    "gn:dem":335,
    "gn:feature_class":"P",
    "gn:feature_code":"PPL",
    "gn:name":"Hutaduru",
    "gn:population":0,
    "gn:timezone":"Asia/Jakarta",
    "iso:country":"ID",
    "name:ind_x_preferred":[
        "Hutaduru"
    ],
    "name:und_x_variant":[
        "Hoetadoeroe"
    ],
    "wof:name":"Hutaduru",
    "wof:placetype":"locality"
},
  "geometry": {"coordinates":[98.1819,2.492],"type":"Point"}
}