{
  "type": "Feature",
  "properties": {
    "iso:country":"ID",
    "qs:name":"Beresela",
    "qs:name_adm0":"Indonesia",
    "qs:name_adm1":"Bali",
    "qs:photos":223,
    "qs:photos_1k":45,
    "qs:photos_9k":1,
    "qs:photos_9r":4,
    "qs:photos_all":223,
    "qs:photos_sr":4,
    "qs:placetype":"Town",
    "qs:pop_sr":"0",
    "wof:lang_x_official":[
        "ind"
    ],
    "wof:lang_x_spoken":[
        "ind",
        "eng"
    ],
    "wof:name":"Beresela",
    "wof:placetype":"locality"
},
  "geometry": {"coordinates":[115.278667,-8.433248],"type":"Point"}
}