{
  "type": "Feature",
  "properties": {
    "gn:admin1_code":"26",
    "gn:asciiname":"Guriahan",
    "gn:country_code":"ID",
    "gn:dem":138,
    "gn:feature_class":"P",
    "gn:feature_code":"PPL",
    "gn:name":"Guriahan",
    "gn:population":0,
    "gn:timezone":"Asia/Jakarta",
    "iso:country":"ID",
    "name:ind_x_preferred":[
        "Guriahan"
    ],
    "wof:name":"Guriahan",
    "wof:placetype":"locality"
},
  "geometry": {"coordinates":[98.7897,3.36],"type":"Point"}
}