{
  "type": "Feature",
  "properties": {
    "gn:admin1_code":"7",
    "gn:asciiname":"Kliti",
    "gn:country_code":"ID",
    "gn:dem":269,
    "gn:feature_class":"P",
    "gn:feature_code":"PPL",
    "gn:name":"Kliti",
    "gn:population":0,
    "gn:timezone":"Asia/Jakarta",
    "iso:country":"ID",
    "name:ind_x_preferred":[
        "Kliti"
    ],
    "wof:name":"Kliti",
    "wof:placetype":"locality"
},
  "geometry": {"coordinates":[111.25722,-7.90083],"type":"Point"}
}