{
  "type": "Feature",
  "properties": {
    "gn:admin1_code":"7.0",
    "gn:asciiname":"Pringamba",
    "gn:country_code":"ID",
    "gn:dem":834,
    "gn:feature_class":"P",
    "gn:feature_code":"PPL",
    "gn:name":"Pringamba",
    "gn:population":0,
    "gn:timezone":"Asia/Jakarta",
    "iso:country":"ID",
    "name:ind_x_preferred":[
        "Pringamba"
    ],
    "wof:name":"Pringamba",
    "wof:placetype":"locality"
},
  "geometry": {"coordinates":[109.75583,-7.33722],"type":"Point"}
}