{
  "type": "Feature",
  "properties": {
    "gn:admin1_code":"24",
    "gn:asciiname":"Kotatua Tiga",
    "gn:country_code":"ID",
    "gn:dem":508,
    "gn:feature_class":"P",
    "gn:feature_code":"PPL",
    "gn:name":"Kotatua Tiga",
    "gn:population":0,
    "gn:timezone":"Asia/Jakarta",
    "iso:country":"ID",
    "name:ind_x_preferred":[
        "Kotatua Tiga"
    ],
    "name:und_x_variant":[
        "Kotatua 3"
    ],
    "wof:lang_x_official":[
        "ind"
    ],
    "wof:lang_x_spoken":[
        "ind",
        "eng"
    ],
    "wof:name":"Kotatua Tiga",
    "wof:placetype":"locality"
},
  "geometry": {"coordinates":[100.62452,-0.60984],"type":"Point"}
}