{
  "type": "Feature",
  "properties": {
    "gn:admin1_code":"30.0",
    "gn:asciiname":"Palawija",
    "gn:country_code":"ID",
    "gn:dem":749,
    "gn:feature_class":"P",
    "gn:feature_code":"PPL",
    "gn:name":"Palawija",
    "gn:population":0,
    "gn:timezone":"Asia/Jakarta",
    "iso:country":"ID",
    "name:ind_x_preferred":[
        "Palawija"
    ],
    "wof:name":"Palawija",
    "wof:placetype":"locality"
},
  "geometry": {"coordinates":[107.9392,-7.4789],"type":"Point"}
}