{
  "type": "Feature",
  "properties": {
    "gn:admin1_code":"8.0",
    "gn:asciiname":"Purboyo",
    "gn:country_code":"ID",
    "gn:dem":349,
    "gn:feature_class":"P",
    "gn:feature_code":"PPL",
    "gn:name":"Purboyo",
    "gn:population":0,
    "gn:timezone":"Asia/Jakarta",
    "iso:country":"ID",
    "name:ind_x_preferred":[
        "Purboyo"
    ],
    "name:und_x_variant":[
        "Purbojo",
        "Purboyo",
        "Poerbojo"
    ],
    "wof:lang_x_official":[
        "ind"
    ],
    "wof:lang_x_spoken":[
        "ind",
        "eng"
    ],
    "wof:name":"Purboyo",
    "wof:placetype":"locality"
},
  "geometry": {"coordinates":[112.5423,-8.3104],"type":"Point"}
}