{
  "type": "Feature",
  "properties": {
    "gn:admin1_code":"17.0",
    "gn:asciiname":"Kolo",
    "gn:country_code":"ID",
    "gn:dem":14,
    "gn:feature_class":"P",
    "gn:feature_code":"PPLA4",
    "gn:name":"Kolo",
    "gn:population":0,
    "gn:timezone":"Asia/Makassar",
    "iso:country":"ID",
    "name:ind_x_preferred":[
        "Kolo"
    ],
    "name:und_x_variant":[
        "Nae",
        "Nanganae"
    ],
    "wof:name":"Kolo",
    "wof:placetype":"locality"
},
  "geometry": {"coordinates":[118.7193,-8.3722],"type":"Point"}
}