{
  "type": "Feature",
  "properties": {
    "gn:admin1_code":"33.0",
    "gn:asciiname":"Pasirhantap",
    "gn:country_code":"ID",
    "gn:dem":12,
    "gn:feature_class":"P",
    "gn:feature_code":"PPL",
    "gn:name":"Pasirhantap",
    "gn:population":0,
    "gn:timezone":"Asia/Jakarta",
    "iso:country":"ID",
    "name:ind_x_preferred":[
        "Pasirhantap"
    ],
    "wof:name":"Pasirhantap",
    "wof:placetype":"locality"
},
  "geometry": {"coordinates":[105.9302,-6.471],"type":"Point"}
}