{
  "type": "Feature",
  "properties": {
    "gn:admin1_code":"18.0",
    "gn:asciiname":"Minggitimbi Satu",
    "gn:country_code":"ID",
    "gn:dem":8,
    "gn:feature_class":"P",
    "gn:feature_code":"PPL",
    "gn:name":"Minggitimbi Satu",
    "gn:population":0,
    "gn:timezone":"Asia/Makassar",
    "iso:country":"ID",
    "name:ind_x_preferred":[
        "Minggitimbi Satu"
    ],
    "wof:name":"Minggitimbi Satu",
    "wof:placetype":"locality"
},
  "geometry": {"coordinates":[120.4954,-9.6802],"type":"Point"}
}