{
  "type": "Feature",
  "properties": {
    "gn:admin1_code":"18.0",
    "gn:asciiname":"Mio",
    "gn:country_code":"ID",
    "gn:dem":111,
    "gn:feature_class":"P",
    "gn:feature_code":"PPL",
    "gn:name":"Mio",
    "gn:population":0,
    "gn:timezone":"Asia/Makassar",
    "iso:country":"ID",
    "name:ceb_x_preferred":[
        "Mio"
    ],
    "name:deu_x_preferred":[
        "Mio"
    ],
    "name:fra_x_preferred":[
        "Mio"
    ],
    "name:ind_x_preferred":[
        "Mio"
    ],
    "name:nld_x_preferred":[
        "Mio"
    ],
    "name:swe_x_preferred":[
        "Mio"
    ],
    "wof:lang_x_official":[
        "ind"
    ],
    "wof:lang_x_spoken":[
        "ind",
        "eng"
    ],
    "wof:name":"Mio",
    "wof:placetype":"locality"
},
  "geometry": {"coordinates":[124.1555,-9.9932],"type":"Point"}
}