{
  "type": "Feature",
  "properties": {
    "gn:admin1_code":"18.0",
    "gn:asciiname":"Mio",
    "gn:country_code":"ID",
    "gn:dem":111,
    "gn:feature_class":"P",
    "gn:feature_code":"PPL",
    "gn:name":"Mio",
    "gn:population":0,
    "gn:timezone":"Asia/Makassar",
    "iso:country":"ID",
    "name:ceb_x_preferred":[
        "Mio"
    ],
    "name:deu_x_preferred":[
        "Mio"
    ],
    "name:ell_x_preferred":[
        "\u039c\u03af\u03bf"
    ],
    "name:fra_x_preferred":[
        "Mio"
    ],
    "name:heb_x_preferred":[
        "\u05d4\u05d0\u05d9 \u05de\u05d9\u05e7\u05dc\u05d5\u05df"
    ],
    "name:hin_x_preferred":[
        "\u092e\u093e\u092f\u0913"
    ],
    "name:ind_x_preferred":[
        "Mio"
    ],
    "name:nld_x_preferred":[
        "Mio"
    ],
    "name:swe_x_preferred":[
        "Mio"
    ],
    "name:tur_x_preferred":[
        "Mio"
    ],
    "name:urd_x_preferred":[
        "\u0645\u06cc\u0648"
    ],
    "name:vie_x_preferred":[
        "S\u00f4ng Mio"
    ],
    "wof:lang_x_official":[
        "ind"
    ],
    "wof:lang_x_spoken":[
        "ind",
        "eng"
    ],
    "wof:name":"Mio",
    "wof:placetype":"locality"
},
  "geometry": {"coordinates":[124.1555,-9.9932],"type":"Point"}
}