{
  "type": "Feature",
  "properties": {
    "gn:admin1_code":"18.0",
    "gn:asciiname":"Gero",
    "gn:country_code":"ID",
    "gn:dem":303,
    "gn:feature_class":"P",
    "gn:feature_code":"PPLA4",
    "gn:name":"Gero",
    "gn:population":0,
    "gn:timezone":"Asia/Makassar",
    "iso:country":"ID",
    "name:bul_x_preferred":[
        "\u0413\u0435\u0440\u043e"
    ],
    "name:cat_x_preferred":[
        "Ger\u00f3"
    ],
    "name:deu_x_preferred":[
        "Gero"
    ],
    "name:fra_x_preferred":[
        "Gero"
    ],
    "name:ind_x_preferred":[
        "Gero"
    ],
    "name:ita_x_preferred":[
        "Gero"
    ],
    "name:jpn_x_preferred":[
        "\u30b2\u30ed"
    ],
    "name:mlg_x_preferred":[
        "Gero"
    ],
    "name:nld_x_preferred":[
        "Gero"
    ],
    "name:pol_x_preferred":[
        "Gero"
    ],
    "name:ron_x_preferred":[
        "Gero"
    ],
    "name:swe_x_preferred":[
        "Gero"
    ],
    "wof:name":"Gero",
    "wof:placetype":"locality"
},
  "geometry": {"coordinates":[121.18810000000001,-8.7039],"type":"Point"}
}