{
  "type": "Feature",
  "properties": {
    "gn:admin1_code":"18.0",
    "gn:asciiname":"Lalu",
    "gn:country_code":"ID",
    "gn:dem":344,
    "gn:feature_class":"P",
    "gn:feature_code":"PPL",
    "gn:name":"Lalu",
    "gn:population":0,
    "gn:timezone":"Asia/Makassar",
    "iso:country":"ID",
    "name:ceb_x_preferred":[
        "Lalu"
    ],
    "name:ind_x_preferred":[
        "Lalu"
    ],
    "name:swe_x_preferred":[
        "Lalu"
    ],
    "wof:lang_x_official":[
        "ind"
    ],
    "wof:lang_x_spoken":[
        "ind",
        "eng"
    ],
    "wof:name":"Lalu",
    "wof:placetype":"locality"
},
  "geometry": {"coordinates":[124.0853,-9.7452],"type":"Point"}
}