{
  "type": "Feature",
  "properties": {
    "gn:admin1_code":"7.0",
    "gn:asciiname":"Cibiros",
    "gn:country_code":"ID",
    "gn:dem":532,
    "gn:feature_class":"P",
    "gn:feature_code":"PPL",
    "gn:name":"Cibiros",
    "gn:population":0,
    "gn:timezone":"Asia/Jakarta",
    "iso:country":"ID",
    "name:ind_x_preferred":[
        "Cibiros"
    ],
    "name:und_x_variant":[
        "Tjibiroes"
    ],
    "wof:name":"Cibiros",
    "wof:placetype":"locality"
},
  "geometry": {"coordinates":[108.82810000000001,-7.2071],"type":"Point"}
}