{
  "type": "Feature",
  "properties": {
    "gn:admin1_code":"30",
    "gn:asciiname":"Tegalpadung",
    "gn:country_code":"ID",
    "gn:dem":1634,
    "gn:feature_class":"P",
    "gn:feature_code":"PPL",
    "gn:name":"Tegalpadung",
    "gn:population":0,
    "gn:timezone":"Asia/Jakarta",
    "iso:country":"ID",
    "wof:name":"Tegalpadung",
    "wof:placetype":"locality"
},
  "geometry": {"coordinates":[107.66167,-7.24556],"type":"Point"}
}