{
  "type": "Feature",
  "properties": {
    "gn:admin1_code":"8",
    "gn:asciiname":"Patuk Tengah",
    "gn:country_code":"ID",
    "gn:dem":387,
    "gn:feature_class":"P",
    "gn:feature_code":"PPL",
    "gn:name":"Patuk Tengah",
    "gn:population":0,
    "gn:timezone":"Asia/Jakarta",
    "iso:country":"ID",
    "name:ind_x_preferred":[
        "Patuk Tengah"
    ],
    "wof:name":"Patuk Tengah",
    "wof:placetype":"locality"
},
  "geometry": {"coordinates":[111.5942,-7.8263],"type":"Point"}
}