{
  "type": "Feature",
  "properties": {
    "gn:admin1_code":"10",
    "gn:asciiname":"Pakel",
    "gn:country_code":"ID",
    "gn:dem":126,
    "gn:feature_class":"P",
    "gn:feature_code":"PPL",
    "gn:name":"Pakel",
    "gn:population":0,
    "gn:timezone":"Asia/Jakarta",
    "iso:country":"ID",
    "name:ind_x_preferred":[
        "Pakel"
    ],
    "wof:name":"Pakel",
    "wof:placetype":"locality"
},
  "geometry": {"coordinates":[110.54528000000001,-8.10444],"type":"Point"}
}