{
  "type": "Feature",
  "properties": {
    "gn:admin1_code":"18.0",
    "gn:asciiname":"Nepo",
    "gn:country_code":"ID",
    "gn:dem":1383,
    "gn:feature_class":"P",
    "gn:feature_code":"PPL",
    "gn:name":"Nepo",
    "gn:population":0,
    "gn:timezone":"Asia/Makassar",
    "iso:country":"ID",
    "name:ind_x_preferred":[
        "Nepo"
    ],
    "wof:name":"Nepo",
    "wof:placetype":"locality"
},
  "geometry": {"coordinates":[124.2055,-9.5939],"type":"Point"}
}