{
  "type": "Feature",
  "properties": {
    "gn:admin1_code":"30",
    "gn:asciiname":"Sumurkawung",
    "gn:country_code":"ID",
    "gn:dem":682,
    "gn:feature_class":"P",
    "gn:feature_code":"PPL",
    "gn:name":"Sumurkawung",
    "gn:population":0,
    "gn:timezone":"Asia/Jakarta",
    "iso:country":"ID",
    "name:ind_x_preferred":[
        "Sumurkawung"
    ],
    "wof:name":"Sumurkawung",
    "wof:placetype":"locality"
},
  "geometry": {"coordinates":[107.79694000000001,-6.95361],"type":"Point"}
}