{
  "type": "Feature",
  "properties": {
    "gn:admin1_code":"18.0",
    "gn:asciiname":"Kamaru Satu",
    "gn:country_code":"ID",
    "gn:dem":17,
    "gn:feature_class":"P",
    "gn:feature_code":"PPL",
    "gn:name":"Kamaru Satu",
    "gn:population":0,
    "gn:timezone":"Asia/Makassar",
    "iso:country":"ID",
    "name:ind_x_preferred":[
        "Kamaru Satu"
    ],
    "name:und_x_variant":[
        "Kamaru 1"
    ],
    "wof:name":"Kamaru Satu",
    "wof:placetype":"locality"
},
  "geometry": {"coordinates":[120.3242,-9.6914],"type":"Point"}
}