{
  "type": "Feature",
  "properties": {
    "gn:admin1_code":"8",
    "gn:asciiname":"Semadar",
    "gn:country_code":"ID",
    "gn:dem":159,
    "gn:feature_class":"P",
    "gn:feature_code":"PPL",
    "gn:name":"Semadar",
    "gn:population":0,
    "gn:timezone":"Asia/Jakarta",
    "iso:country":"ID",
    "name:ind_x_preferred":[
        "Semadar"
    ],
    "wof:name":"Semadar",
    "wof:placetype":"locality"
},
  "geometry": {"coordinates":[111.31556,-7.87472],"type":"Point"}
}