{
  "type": "Feature",
  "properties": {
    "gn:admin1_code":"8.0",
    "gn:asciiname":"Nguluh",
    "gn:country_code":"ID",
    "gn:dem":32,
    "gn:feature_class":"P",
    "gn:feature_code":"PPL",
    "gn:name":"Nguluh",
    "gn:population":0,
    "gn:timezone":"Asia/Jakarta",
    "iso:country":"ID",
    "name:ind_x_preferred":[
        "Nguluh"
    ],
    "wof:name":"Nguluh",
    "wof:placetype":"locality"
},
  "geometry": {"coordinates":[112.2025,-7.1456],"type":"Point"}
}