{
  "type": "Feature",
  "properties": {
    "gn:admin1_code":"30.0",
    "gn:asciiname":"Kiarapandak",
    "gn:country_code":"ID",
    "gn:dem":485,
    "gn:feature_class":"P",
    "gn:feature_code":"PPL",
    "gn:name":"Kiarapandak",
    "gn:population":0,
    "gn:timezone":"Asia/Jakarta",
    "iso:country":"ID",
    "name:ind_x_preferred":[
        "Kiarapandak"
    ],
    "wof:name":"Kiarapandak",
    "wof:placetype":"locality"
},
  "geometry": {"coordinates":[108.17910000000001,-7.1338],"type":"Point"}
}