{
  "type": "Feature",
  "properties": {
    "gn:admin1_code":"28.0",
    "gn:asciiname":"Seriholu",
    "gn:country_code":"ID",
    "gn:dem":20,
    "gn:feature_class":"P",
    "gn:feature_code":"PPL",
    "gn:name":"Seriholu",
    "gn:population":0,
    "gn:timezone":"Asia/Jayapura",
    "iso:country":"ID",
    "name:und_x_variant":[
        "Seriholoe",
        "Seriholu"
    ],
    "wof:name":"Seriholu",
    "wof:placetype":"locality"
},
  "geometry": {"coordinates":[128.67320000000001,-3.3577],"type":"Point"}
}