{
  "type": "Feature",
  "properties": {
    "gn:admin1_code":"8",
    "gn:asciiname":"Pilangrejo",
    "gn:country_code":"ID",
    "gn:dem":23,
    "gn:feature_class":"P",
    "gn:feature_code":"PPL",
    "gn:name":"Pilangrejo",
    "gn:population":0,
    "gn:timezone":"Asia/Jakarta",
    "iso:country":"ID",
    "name:ind_x_preferred":[
        "Pilangrejo"
    ],
    "wof:name":"Pilangrejo",
    "wof:placetype":"locality"
},
  "geometry": {"coordinates":[112.4392,-7.2755],"type":"Point"}
}