{
  "type": "Feature",
  "properties": {
    "gn:admin1_code":"8.0",
    "gn:asciiname":"Sumbersalam Selatan",
    "gn:country_code":"ID",
    "gn:dem":304,
    "gn:feature_class":"P",
    "gn:feature_code":"PPL",
    "gn:name":"Sumbersalam Selatan",
    "gn:population":0,
    "gn:timezone":"Asia/Jakarta",
    "iso:country":"ID",
    "name:ind_x_preferred":[
        "Sumbersalam Selatan"
    ],
    "wof:name":"Sumbersalam Selatan",
    "wof:placetype":"locality"
},
  "geometry": {"coordinates":[113.84520000000001,-7.9605],"type":"Point"}
}