{
  "type": "Feature",
  "properties": {
    "gn:admin1_code":"7.0",
    "gn:asciiname":"Kayunan Lor",
    "gn:country_code":"ID",
    "gn:dem":297,
    "gn:feature_class":"P",
    "gn:feature_code":"PPL",
    "gn:name":"Kayunan Lor",
    "gn:population":0,
    "gn:timezone":"Asia/Jakarta",
    "iso:country":"ID",
    "name:ind_x_preferred":[
        "Kayunan Lor"
    ],
    "wof:name":"Kayunan Lor",
    "wof:placetype":"locality"
},
  "geometry": {"coordinates":[109.67111,-7.35722],"type":"Point"}
}