{
  "type": "Feature",
  "properties": {
    "gn:admin1_code":"30",
    "gn:asciiname":"Pulogandang Ujung",
    "gn:country_code":"ID",
    "gn:dem":7,
    "gn:feature_class":"P",
    "gn:feature_code":"PPL",
    "gn:name":"Pulogandang Ujung",
    "gn:population":0,
    "gn:timezone":"Asia/Jakarta",
    "iso:country":"ID",
    "name:ind_x_preferred":[
        "Pulogandang Ujung"
    ],
    "name:und_x_variant":[
        "Pulopandjang",
        "Pulopanjang"
    ],
    "wof:lang_x_official":[
        "ind"
    ],
    "wof:lang_x_spoken":[
        "ind",
        "eng"
    ],
    "wof:name":"Pulogandang Ujung",
    "wof:placetype":"locality"
},
  "geometry": {"coordinates":[107.14472000000001,-6.08833],"type":"Point"}
}