{
  "type": "Feature",
  "properties": {
    "gn:admin1_code":"15.0",
    "gn:asciiname":"Pujosari",
    "gn:country_code":"ID",
    "gn:dem":116,
    "gn:feature_class":"P",
    "gn:feature_code":"PPL",
    "gn:name":"Pujosari",
    "gn:population":0,
    "gn:timezone":"Asia/Jakarta",
    "iso:country":"ID",
    "name:ind_x_preferred":[
        "Pujosari"
    ],
    "wof:name":"Pujosari",
    "wof:placetype":"locality"
},
  "geometry": {"coordinates":[105.05625999999999,-5.32872],"type":"Point"}
}