{
  "type": "Feature",
  "properties": {
    "gn:admin1_code":"30.0",
    "gn:asciiname":"Cipurut",
    "gn:country_code":"ID",
    "gn:dem":225,
    "gn:feature_class":"P",
    "gn:feature_code":"PPL",
    "gn:name":"Cipurut",
    "gn:population":0,
    "gn:timezone":"Asia/Jakarta",
    "iso:country":"ID",
    "name:ind_x_preferred":[
        "Cipurut"
    ],
    "name:und_x_variant":[
        "Tjipoeroet 2"
    ],
    "wof:name":"Cipurut",
    "wof:placetype":"locality"
},
  "geometry": {"coordinates":[108.1862,-7.6565],"type":"Point"}
}