{
  "type": "Feature",
  "properties": {
    "gn:admin1_code":"30.0",
    "gn:asciiname":"Kertapura",
    "gn:country_code":"ID",
    "gn:dem":1131,
    "gn:feature_class":"P",
    "gn:feature_code":"PPLA4",
    "gn:name":"Kertapura",
    "gn:population":0,
    "gn:timezone":"Asia/Jakarta",
    "iso:country":"ID",
    "name:ind_x_preferred":[
        "Kertapura"
    ],
    "wof:name":"Kertapura",
    "wof:placetype":"locality"
},
  "geometry": {"coordinates":[108.0183,-7.2345],"type":"Point"}
}