{
  "type": "Feature",
  "properties": {
    "gn:admin1_code":"08",
    "gn:asciiname":"Princi",
    "gn:cc2":"ID",
    "gn:country_code":"ID",
    "gn:dem":1013,
    "gn:feature_class":"P",
    "gn:feature_code":"PPL",
    "gn:name":"Princi",
    "gn:population":0,
    "gn:timezone":"Asia/Jakarta",
    "iso:country":"ID",
    "name:und_x_variant":[
        "Printji",
        "Princi"
    ],
    "wof:name":"Princi",
    "wof:placetype":"locality"
},
  "geometry": {"coordinates":[112.52889,-7.92583],"type":"Point"}
}