{
  "type": "Feature",
  "properties": {
    "gn:admin1_code":"11.0",
    "gn:asciiname":"Sedua",
    "gn:country_code":"ID",
    "gn:dem":62,
    "gn:feature_class":"P",
    "gn:feature_code":"PPL",
    "gn:name":"Sedua",
    "gn:population":0,
    "gn:timezone":"Asia/Pontianak",
    "iso:country":"ID",
    "name:und_x_variant":[
        "Sedoea",
        "Sedua"
    ],
    "wof:name":"Sedua",
    "wof:placetype":"locality"
},
  "geometry": {"coordinates":[110.59999999999999,0.38333],"type":"Point"}
}