{
  "type": "Feature",
  "properties": {
    "gn:admin1_code":"30.0",
    "gn:asciiname":"Sukahening",
    "gn:country_code":"ID",
    "gn:dem":480,
    "gn:feature_class":"P",
    "gn:feature_code":"PPL",
    "gn:name":"Sukahening",
    "gn:population":0,
    "gn:timezone":"Asia/Jakarta",
    "iso:country":"ID",
    "name:ind_x_preferred":[
        "Sukahening"
    ],
    "wof:name":"Sukahening",
    "wof:placetype":"locality"
},
  "geometry": {"coordinates":[108.1743,-7.1363],"type":"Point"}
}