{
  "type": "Feature",
  "properties": {
    "gn:admin1_code":"26",
    "gn:asciiname":"Pondok Siujung Raja",
    "gn:country_code":"ID",
    "gn:dem":393,
    "gn:feature_class":"P",
    "gn:feature_code":"PPL",
    "gn:name":"Pondok Siujung Raja",
    "gn:population":0,
    "gn:timezone":"Asia/Jakarta",
    "iso:country":"ID",
    "name:ind_x_preferred":[
        "Pondok Siujung Raja"
    ],
    "wof:name":"Pondok Siujung Raja",
    "wof:placetype":"locality"
},
  "geometry": {"coordinates":[99.0806,2.8992],"type":"Point"}
}