{
  "type": "Feature",
  "properties": {
    "gn:admin1_code":"30.0",
    "gn:asciiname":"Kertayasa",
    "gn:country_code":"ID",
    "gn:dem":18,
    "gn:feature_class":"P",
    "gn:feature_code":"PPL",
    "gn:name":"Kertayasa",
    "gn:population":0,
    "gn:timezone":"Asia/Jakarta",
    "iso:country":"ID",
    "name:ind_x_preferred":[
        "Kertayasa"
    ],
    "wof:name":"Kertayasa",
    "wof:placetype":"locality"
},
  "geometry": {"coordinates":[108.46472,-6.68944],"type":"Point"}
}