{
  "type": "Feature",
  "properties": {
    "gn:admin1_code":"41",
    "gn:asciiname":"Kanari",
    "gn:country_code":"ID",
    "gn:dem":15,
    "gn:feature_class":"P",
    "gn:feature_code":"PPL",
    "gn:name":"Kanari",
    "gn:population":0,
    "gn:timezone":"Asia/Makassar",
    "iso:country":"ID",
    "name:ind_x_preferred":[
        "Kanari"
    ],
    "wof:name":"Kanari",
    "wof:placetype":"locality"
},
  "geometry": {"coordinates":[119.18559999999999,-3.4482],"type":"Point"}
}