{
  "type": "Feature",
  "properties": {
    "gn:admin1_code":"1",
    "gn:asciiname":"Blang Dalam",
    "gn:country_code":"ID",
    "gn:dem":39,
    "gn:feature_class":"P",
    "gn:feature_code":"PPL",
    "gn:name":"Blang Dalam",
    "gn:population":0,
    "gn:timezone":"Asia/Jakarta",
    "iso:country":"ID",
    "name:ind_x_preferred":[
        "Blang Dalam"
    ],
    "wof:name":"Blang Dalam",
    "wof:placetype":"locality"
},
  "geometry": {"coordinates":[96.1413,4.4568],"type":"Point"}
}