{
  "type": "Feature",
  "properties": {
    "gn:admin1_code":"18",
    "gn:asciiname":"Guna",
    "gn:country_code":"ID",
    "gn:dem":75,
    "gn:feature_class":"P",
    "gn:feature_code":"PPL",
    "gn:name":"Guna",
    "gn:population":0,
    "gn:timezone":"Asia/Makassar",
    "iso:country":"ID",
    "name:ind_x_preferred":[
        "Guna"
    ],
    "wof:name":"Guna",
    "wof:placetype":"locality"
},
  "geometry": {"coordinates":[121.49930000000001,-8.7681],"type":"Point"}
}