{
  "type": "Feature",
  "properties": {
    "gn:admin1_code":"30.0",
    "gn:asciiname":"Ciroyom",
    "gn:country_code":"ID",
    "gn:dem":704,
    "gn:feature_class":"P",
    "gn:feature_code":"PPLA4",
    "gn:name":"Ciroyom",
    "gn:population":0,
    "gn:timezone":"Asia/Jakarta",
    "iso:country":"ID",
    "name:ind_x_preferred":[
        "Ciroyom"
    ],
    "name:und_x_variant":[
        "Tjirojom",
        "Ciroyom"
    ],
    "wof:lang_x_official":[
        "ind"
    ],
    "wof:lang_x_spoken":[
        "ind",
        "eng"
    ],
    "wof:name":"Ciroyom",
    "wof:placetype":"locality"
},
  "geometry": {"coordinates":[107.9704,-7.4916],"type":"Point"}
}