{
  "type": "Feature",
  "properties": {
    "gn:admin1_code":"7.0",
    "gn:asciiname":"Tenjo",
    "gn:country_code":"ID",
    "gn:dem":665,
    "gn:feature_class":"P",
    "gn:feature_code":"PPL",
    "gn:name":"Tenjo",
    "gn:population":0,
    "gn:timezone":"Asia/Jakarta",
    "iso:country":"ID",
    "name:ceb_x_preferred":[
        "Tenjo"
    ],
    "name:deu_x_preferred":[
        "Tenjo"
    ],
    "name:epo_x_preferred":[
        "Tenjo"
    ],
    "name:fin_x_preferred":[
        "Tenjo"
    ],
    "name:fra_x_preferred":[
        "Tenjo"
    ],
    "name:ind_x_preferred":[
        "Tenjo"
    ],
    "name:ita_x_preferred":[
        "Tenjo"
    ],
    "name:kat_x_preferred":[
        "\u10e2\u10d4\u10dc\u10ee\u10dd"
    ],
    "name:msa_x_preferred":[
        "Tenjo"
    ],
    "name:nld_x_preferred":[
        "Tenjo"
    ],
    "name:spa_x_preferred":[
        "Tenjo"
    ],
    "name:swe_x_preferred":[
        "Tenjo"
    ],
    "name:tgl_x_preferred":[
        "Tenjo"
    ],
    "name:vie_x_preferred":[
        "Tenjo"
    ],
    "name:war_x_preferred":[
        "Tenjo"
    ],
    "wof:lang_x_official":[
        "ind"
    ],
    "wof:lang_x_spoken":[
        "ind",
        "eng"
    ],
    "wof:name":"Tenjo",
    "wof:placetype":"locality"
},
  "geometry": {"coordinates":[109.09917,-7.15861],"type":"Point"}
}