{
  "type": "Feature",
  "properties": {
    "gn:admin1_code":"30.0",
    "gn:asciiname":"Blandongan Dua",
    "gn:country_code":"ID",
    "gn:dem":441,
    "gn:feature_class":"P",
    "gn:feature_code":"PPL",
    "gn:name":"Blandongan Dua",
    "gn:population":0,
    "gn:timezone":"Asia/Jakarta",
    "iso:country":"ID",
    "name:ind_x_preferred":[
        "Blandongan Dua"
    ],
    "wof:name":"Blandongan Dua",
    "wof:placetype":"locality"
},
  "geometry": {"coordinates":[108.60850000000001,-7.1167],"type":"Point"}
}