{
  "type": "Feature",
  "properties": {
    "gn:admin1_code":"30.0",
    "gn:asciiname":"Cibodaspasar",
    "gn:country_code":"ID",
    "gn:dem":429,
    "gn:feature_class":"P",
    "gn:feature_code":"PPL",
    "gn:name":"Cibodaspasar",
    "gn:population":0,
    "gn:timezone":"Asia/Jakarta",
    "iso:country":"ID",
    "name:ind_x_preferred":[
        "Cibodaspasar"
    ],
    "name:und_x_variant":[
        "Tjibodas"
    ],
    "wof:lang_x_official":[
        "ind"
    ],
    "wof:lang_x_spoken":[
        "ind",
        "eng"
    ],
    "wof:name":"Cibodaspasar",
    "wof:placetype":"locality"
},
  "geometry": {"coordinates":[108.1861,-7.259],"type":"Point"}
}