{
  "type": "Feature",
  "properties": {
    "gn:admin1_code":"33.0",
    "gn:asciiname":"Kadumeong",
    "gn:country_code":"ID",
    "gn:dem":155,
    "gn:feature_class":"P",
    "gn:feature_code":"PPL",
    "gn:name":"Kadumeong",
    "gn:population":0,
    "gn:timezone":"Asia/Jakarta",
    "iso:country":"ID",
    "name:ind_x_preferred":[
        "Kadumeong"
    ],
    "wof:name":"Kadumeong",
    "wof:placetype":"locality"
},
  "geometry": {"coordinates":[105.9217,-6.3588],"type":"Point"}
}