{
  "type": "Feature",
  "properties": {
    "gn:country":"ID",
    "gn:fcode":"PPL",
    "gn:pop":0,
    "iso:country":"ID",
    "name:eng_x_preferred":[
        "Selong"
    ],
    "name:ind_x_preferred":[
        "Selong"
    ],
    "qs:name":"Selong",
    "qs:name_adm0":"Indonesia",
    "qs:name_adm1":"Nusa Tenggara Barat",
    "qs:photos_9k":1,
    "qs:photos_9r":1,
    "qs:photos_all":5,
    "qs:photos_sr":0,
    "qs:placetype":"Town",
    "qs:pop_sr":"0",
    "wd:wordcount":25,
    "wof:lang_x_official":[
        "ind"
    ],
    "wof:lang_x_spoken":[
        "ind",
        "eng"
    ],
    "wof:name":"Selong",
    "wof:placetype":"locality",
    "wof:population":0
},
  "geometry": {"coordinates":[116.3626,-8.8252],"type":"Point"}
}