{
  "type": "Feature",
  "properties": {
    "gn:admin1_code":"22",
    "gn:asciiname":"Eeea",
    "gn:country_code":"ID",
    "gn:dem":123,
    "gn:feature_class":"P",
    "gn:feature_code":"PPL",
    "gn:name":"Eeea",
    "gn:population":0,
    "gn:timezone":"Asia/Makassar",
    "iso:country":"ID",
    "name:ind_x_preferred":[
        "Erea"
    ],
    "name:ind_x_variant":[
        "Eeea"
    ],
    "wof:name":"Eeea",
    "wof:placetype":"locality"
},
  "geometry": {"coordinates":[121.9499,-4.7261],"type":"Point"}
}