{
  "type": "Feature",
  "properties": {
    "gn:admin1_code":"30.0",
    "gn:asciiname":"Ciaren",
    "gn:country_code":"ID",
    "gn:dem":45,
    "gn:feature_class":"P",
    "gn:feature_code":"PPL",
    "gn:name":"Ciaren",
    "gn:population":0,
    "gn:timezone":"Asia/Jakarta",
    "iso:country":"ID",
    "name:ind_x_preferred":[
        "Ciaren"
    ],
    "name:und_x_variant":[
        "Tjiaren"
    ],
    "wof:name":"Ciaren",
    "wof:placetype":"locality"
},
  "geometry": {"coordinates":[108.5633,-7.4176],"type":"Point"}
}