{
  "type": "Feature",
  "properties": {
    "gn:country":"ID",
    "gn:fcode":"PPLA4",
    "gn:pop":0,
    "iso:country":"ID",
    "name:ace_x_preferred":[
        "Kelungkung"
    ],
    "name:cat_x_preferred":[
        "Kelungkung"
    ],
    "name:ces_x_preferred":[
        "Kelungkung"
    ],
    "name:dan_x_preferred":[
        "Kelungkung"
    ],
    "name:deu_x_preferred":[
        "Kelungkung"
    ],
    "name:eng_x_preferred":[
        "Kelungkung"
    ],
    "name:eus_x_preferred":[
        "Kelungkung"
    ],
    "name:fin_x_preferred":[
        "Kelungkung"
    ],
    "name:hrv_x_preferred":[
        "Kelungkung"
    ],
    "name:ind_x_preferred":[
        "Kelungkung"
    ],
    "name:ita_x_preferred":[
        "Kelungkung"
    ],
    "name:msa_x_preferred":[
        "Kelungkung"
    ],
    "name:nld_x_preferred":[
        "Kelungkung"
    ],
    "name:nno_x_preferred":[
        "Kelungkung"
    ],
    "name:nob_x_preferred":[
        "Kelungkung"
    ],
    "name:pol_x_preferred":[
        "Kelungkung"
    ],
    "name:por_x_preferred":[
        "Kelungkung"
    ],
    "name:ron_x_preferred":[
        "Kelungkung"
    ],
    "name:sco_x_preferred":[
        "Kelungkung"
    ],
    "name:slk_x_preferred":[
        "Kelungkung"
    ],
    "name:slv_x_preferred":[
        "Kelungkung"
    ],
    "name:spa_x_preferred":[
        "Kelungkung"
    ],
    "name:swe_x_preferred":[
        "Kelungkung"
    ],
    "name:tur_x_preferred":[
        "Kelungkung"
    ],
    "name:war_x_preferred":[
        "Kelungkung"
    ],
    "qs:name":"Kelungkung",
    "qs:photos_9r":0,
    "qs:photos_sr":0,
    "qs:pop_sr":"0",
    "wof:name":"Kelungkung",
    "wof:placetype":"locality",
    "wof:population":0
},
  "geometry": {"coordinates":[117.3368,-8.5518],"type":"Point"}
}