{
  "type": "Feature",
  "properties": {
    "gn:admin1_code":"26",
    "gn:asciiname":"Klambir Tiga",
    "gn:country_code":"ID",
    "gn:dem":5,
    "gn:feature_class":"P",
    "gn:feature_code":"PPL",
    "gn:name":"Klambir Tiga",
    "gn:population":0,
    "gn:timezone":"Asia/Jakarta",
    "iso:country":"ID",
    "name:ind_x_preferred":[
        "Klambir Tiga"
    ],
    "name:und_x_variant":[
        "Klambir 3"
    ],
    "wof:name":"Klambir Tiga",
    "wof:placetype":"locality"
},
  "geometry": {"coordinates":[98.85250000000001,3.6769],"type":"Point"}
}