{
  "type": "Feature",
  "properties": {
    "gn:admin1_code":"30.0",
    "gn:asciiname":"Rancabungur",
    "gn:country_code":"ID",
    "gn:dem":525,
    "gn:feature_class":"P",
    "gn:feature_code":"PPL",
    "gn:name":"Rancabungur",
    "gn:population":0,
    "gn:timezone":"Asia/Jakarta",
    "iso:country":"ID",
    "name:ind_x_preferred":[
        "Rancabungur"
    ],
    "name:und_x_variant":[
        "Rantjaboengoer"
    ],
    "wof:lang_x_official":[
        "ind"
    ],
    "wof:lang_x_spoken":[
        "ind",
        "eng"
    ],
    "wof:name":"Rancabungur",
    "wof:placetype":"locality"
},
  "geometry": {"coordinates":[108.04989999999999,-7.5157],"type":"Point"}
}