{
  "type": "Feature",
  "properties": {
    "gn:admin1_code":"15.0",
    "gn:asciiname":"Talang Soban",
    "gn:country_code":"ID",
    "gn:dem":78,
    "gn:feature_class":"P",
    "gn:feature_code":"PPL",
    "gn:name":"Talang Soban",
    "gn:population":0,
    "gn:timezone":"Asia/Jakarta",
    "iso:country":"ID",
    "name:ind_x_preferred":[
        "Talang Soban"
    ],
    "wof:name":"Talang Soban",
    "wof:placetype":"locality"
},
  "geometry": {"coordinates":[104.51900999999999,-4.62988],"type":"Point"}
}