{
  "type": "Feature",
  "properties": {
    "gn:admin1_code":"07",
    "gn:asciiname":"Srebeg Gede",
    "gn:country_code":"ID",
    "gn:dem":119,
    "gn:feature_class":"P",
    "gn:feature_code":"PPL",
    "gn:name":"Srebeg Gede",
    "gn:population":0,
    "gn:timezone":"Asia/Jakarta",
    "iso:country":"ID",
    "wof:name":"Srebeg Gede",
    "wof:placetype":"locality"
},
  "geometry": {"coordinates":[110.66167,-7.7225],"type":"Point"}
}