{
  "type": "Feature",
  "properties": {
    "gn:admin1_code":"26",
    "gn:asciiname":"Godungparsingguran",
    "gn:country_code":"ID",
    "gn:dem":1412,
    "gn:feature_class":"P",
    "gn:feature_code":"PPL",
    "gn:name":"Godungparsingguran",
    "gn:population":0,
    "gn:timezone":"Asia/Jakarta",
    "iso:country":"ID",
    "name:ind_x_preferred":[
        "Godungparsingguran"
    ],
    "wof:lang_x_official":[
        "ind"
    ],
    "wof:lang_x_spoken":[
        "ind",
        "eng"
    ],
    "wof:name":"Godungparsingguran",
    "wof:placetype":"locality"
},
  "geometry": {"coordinates":[98.76600000000001,2.3531],"type":"Point"}
}