{
  "type": "Feature",
  "properties": {
    "gn:admin1_code":"38.0",
    "gn:asciiname":"Bulete",
    "gn:country_code":"ID",
    "gn:dem":14,
    "gn:feature_class":"P",
    "gn:feature_code":"PPL",
    "gn:name":"Bulete",
    "gn:population":0,
    "gn:timezone":"Asia/Makassar",
    "iso:country":"ID",
    "name:ind_x_preferred":[
        "Bulete"
    ],
    "name:und_x_variant":[
        "Boelete",
        "Buletto",
        "Boelette",
        "Bulette",
        "Bulete"
    ],
    "wof:lang_x_official":[
        "ind"
    ],
    "wof:lang_x_spoken":[
        "ind",
        "eng"
    ],
    "wof:name":"Bulete",
    "wof:placetype":"locality"
},
  "geometry": {"coordinates":[120.38760000000001,-3.733],"type":"Point"}
}