{
  "type": "Feature",
  "properties": {
    "gn:admin1_code":"18",
    "gn:asciiname":"Watumbelar",
    "gn:country_code":"ID",
    "gn:dem":266,
    "gn:feature_class":"P",
    "gn:feature_code":"PPL",
    "gn:name":"Watumbelar",
    "gn:population":0,
    "gn:timezone":"Asia/Makassar",
    "iso:country":"ID",
    "name:ind_x_preferred":[
        "Watumbelar"
    ],
    "wof:name":"Watumbelar",
    "wof:placetype":"locality"
},
  "geometry": {"coordinates":[120.0159,-9.9169],"type":"Point"}
}