{
  "type": "Feature",
  "properties": {
    "gn:admin1_code":"38",
    "gn:asciiname":"Passapa",
    "gn:country_code":"ID",
    "gn:dem":128,
    "gn:feature_class":"P",
    "gn:feature_code":"PPL",
    "gn:name":"Passapa",
    "gn:population":0,
    "gn:timezone":"Asia/Makassar",
    "iso:country":"ID",
    "name:ind_x_preferred":[
        "Passapa"
    ],
    "wof:name":"Passapa",
    "wof:placetype":"locality"
},
  "geometry": {"coordinates":[120.1861,-2.6219],"type":"Point"}
}