{
  "type": "Feature",
  "properties": {
    "gn:admin1_code":"38",
    "gn:asciiname":"Tondon",
    "gn:country_code":"ID",
    "gn:dem":795,
    "gn:feature_class":"P",
    "gn:feature_code":"PPL",
    "gn:name":"Tondon",
    "gn:population":0,
    "gn:timezone":"Asia/Makassar",
    "iso:country":"ID",
    "name:ceb_x_preferred":[
        "Tondon"
    ],
    "name:fra_x_preferred":[
        "Tondon"
    ],
    "name:ind_x_preferred":[
        "Tondon"
    ],
    "name:ita_x_preferred":[
        "Tondon"
    ],
    "name:jav_x_preferred":[
        "Tondon"
    ],
    "name:msa_x_preferred":[
        "Tondon"
    ],
    "name:pol_x_preferred":[
        "Tondon"
    ],
    "name:spa_x_preferred":[
        "Tondon"
    ],
    "name:swe_x_preferred":[
        "Tondon"
    ],
    "wof:lang_x_official":[
        "ind"
    ],
    "wof:lang_x_spoken":[
        "ind",
        "eng"
    ],
    "wof:name":"Tondon",
    "wof:placetype":"locality"
},
  "geometry": {"coordinates":[119.8571,-3.1023],"type":"Point"}
}