{
  "type": "Feature",
  "properties": {
    "gn:admin1_code":"17.0",
    "gn:asciiname":"Ncera",
    "gn:country_code":"ID",
    "gn:dem":50,
    "gn:feature_class":"P",
    "gn:feature_code":"PPLA4",
    "gn:name":"Ncera",
    "gn:population":0,
    "gn:timezone":"Asia/Makassar",
    "iso:country":"ID",
    "name:ind_x_preferred":[
        "Ncera"
    ],
    "wof:name":"Ncera",
    "wof:placetype":"locality"
},
  "geometry": {"coordinates":[118.74460000000001,-8.6349],"type":"Point"}
}