{
  "type": "Feature",
  "properties": {
    "gn:admin1_code":"0.0",
    "gn:asciiname":"Gunungcampaka",
    "gn:country_code":"ID",
    "gn:dem":1096,
    "gn:feature_class":"P",
    "gn:feature_code":"PPL",
    "gn:name":"Gunungcampaka",
    "gn:population":0,
    "gn:timezone":"Asia/Jakarta",
    "iso:country":"ID",
    "name:und_x_variant":[
        "Gunungtjampaka",
        "Gunungcampaka"
    ],
    "wof:name":"Gunungcampaka",
    "wof:placetype":"locality"
},
  "geometry": {"coordinates":[107.10791,-7.07216],"type":"Point"}
}