{
  "type": "Feature",
  "properties": {
    "gn:admin1_code":"08",
    "gn:asciiname":"Tamanriakenjeran",
    "gn:country_code":"ID",
    "gn:dem":5,
    "gn:feature_class":"P",
    "gn:feature_code":"PPL",
    "gn:name":"Tamanriakenjeran",
    "gn:population":0,
    "gn:timezone":"Asia/Jakarta",
    "iso:country":"ID",
    "name:ind_x_preferred":[
        "Tamanriakenjeran"
    ],
    "name:und_x_variant":[
        "Tamannakenjeran"
    ],
    "wof:lang_x_official":[
        "ind"
    ],
    "wof:lang_x_spoken":[
        "ind",
        "eng"
    ],
    "wof:name":"Tamanriakenjeran",
    "wof:placetype":"locality"
},
  "geometry": {"coordinates":[112.8038,-7.2533],"type":"Point"}
}