{
  "type": "Feature",
  "properties": {
    "gn:admin1_code":"30",
    "gn:asciiname":"Babakantalaga",
    "gn:country_code":"ID",
    "gn:dem":1176,
    "gn:feature_class":"P",
    "gn:feature_code":"PPL",
    "gn:name":"Babakantalaga",
    "gn:population":0,
    "gn:timezone":"Asia/Jakarta",
    "iso:country":"ID",
    "name:ind_x_preferred":[
        "Babakantalaga"
    ],
    "wof:name":"Babakantalaga",
    "wof:placetype":"locality"
},
  "geometry": {"coordinates":[107.7834,-7.2242],"type":"Point"}
}