{
  "type": "Feature",
  "properties": {
    "gn:admin1_code":"0.0",
    "gn:asciiname":"Masni",
    "gn:cc2":"ID",
    "gn:country_code":"ID",
    "gn:dem":43,
    "gn:feature_class":"P",
    "gn:feature_code":"PPL",
    "gn:name":"Masni",
    "gn:population":0,
    "gn:timezone":"Asia/Jayapura",
    "iso:country":"ID",
    "name:und_x_variant":[
        "Maseni",
        "Masni"
    ],
    "wof:name":"Masni",
    "wof:placetype":"locality"
},
  "geometry": {"coordinates":[133.75,-0.73333],"type":"Point"}
}