{
  "type": "Feature",
  "properties": {
    "gn:admin1_code":"41",
    "gn:asciiname":"Kalena",
    "gn:country_code":"ID",
    "gn:dem":11,
    "gn:feature_class":"P",
    "gn:feature_code":"PPL",
    "gn:name":"Kalena",
    "gn:population":0,
    "gn:timezone":"Asia/Makassar",
    "iso:country":"ID",
    "name:ceb_x_preferred":[
        "Kalena"
    ],
    "name:fra_x_preferred":[
        "Kalena"
    ],
    "name:ind_x_preferred":[
        "Kalena"
    ],
    "name:mai_x_preferred":[
        "\u0915\u0932\u0947\u0928\u093e"
    ],
    "name:msa_x_preferred":[
        "Kalena"
    ],
    "name:nep_x_preferred":[
        "\u0915\u0932\u0947\u0928\u093e"
    ],
    "name:new_x_preferred":[
        "\u0915\u0932\u0947\u0928\u093e"
    ],
    "name:pol_x_preferred":[
        "Kalena"
    ],
    "wof:lang_x_official":[
        "ind"
    ],
    "wof:lang_x_spoken":[
        "ind",
        "eng"
    ],
    "wof:name":"Kalena",
    "wof:placetype":"locality"
},
  "geometry": {"coordinates":[119.21339999999999,-3.4271],"type":"Point"}
}