{
  "type": "Feature",
  "properties": {
    "gn:admin1_code":"8",
    "gn:asciiname":"Kapur",
    "gn:country_code":"ID",
    "gn:dem":23,
    "gn:feature_class":"P",
    "gn:feature_code":"PPL",
    "gn:name":"Kapur",
    "gn:population":0,
    "gn:timezone":"Asia/Jakarta",
    "iso:country":"ID",
    "name:ind_x_preferred":[
        "Kapur"
    ],
    "wof:name":"Kapur",
    "wof:placetype":"locality"
},
  "geometry": {"coordinates":[113.06359999999999,-7.7113],"type":"Point"}
}