{
  "type": "Feature",
  "properties": {
    "gn:admin1_code":"22.0",
    "gn:asciiname":"Mertajaya",
    "gn:country_code":"ID",
    "gn:dem":57,
    "gn:feature_class":"P",
    "gn:feature_code":"PPL",
    "gn:name":"Mertajaya",
    "gn:population":0,
    "gn:timezone":"Asia/Makassar",
    "iso:country":"ID",
    "name:ind_x_preferred":[
        "Mertajaya"
    ],
    "wof:name":"Mertajaya",
    "wof:placetype":"locality"
},
  "geometry": {"coordinates":[121.88760000000001,-4.0929],"type":"Point"}
}