{
  "type": "Feature",
  "properties": {
    "gn:admin1_code":"30.0",
    "gn:asciiname":"Ancol",
    "gn:country_code":"ID",
    "gn:dem":209,
    "gn:feature_class":"P",
    "gn:feature_code":"PPLA4",
    "gn:name":"Ancol",
    "gn:population":0,
    "gn:timezone":"Asia/Jakarta",
    "iso:country":"ID",
    "name:ceb_x_preferred":[
        "Kelurahan Ancol"
    ],
    "name:ind_x_preferred":[
        "Ancol"
    ],
    "name:msa_x_preferred":[
        "Ancol"
    ],
    "name:nld_x_preferred":[
        "Ancol"
    ],
    "name:sun_x_preferred":[
        "Ancol"
    ],
    "name:und_x_variant":[
        "Antjol"
    ],
    "wof:lang_x_official":[
        "ind"
    ],
    "wof:lang_x_spoken":[
        "ind",
        "eng"
    ],
    "wof:name":"Ancol",
    "wof:placetype":"locality"
},
  "geometry": {"coordinates":[108.3871,-7.3651],"type":"Point"}
}