{
  "type": "Feature",
  "properties": {
    "gn:admin1_code":"30.0",
    "gn:asciiname":"Ciporeang",
    "gn:country_code":"ID",
    "gn:dem":22,
    "gn:feature_class":"P",
    "gn:feature_code":"PPL",
    "gn:name":"Ciporeang",
    "gn:population":0,
    "gn:timezone":"Asia/Jakarta",
    "iso:country":"ID",
    "name:ind_x_preferred":[
        "Ciporeang"
    ],
    "wof:name":"Ciporeang",
    "wof:placetype":"locality"
},
  "geometry": {"coordinates":[106.4953,-7.2373],"type":"Point"}
}