{
  "type": "Feature",
  "properties": {
    "gn:admin1_code":"38",
    "gn:asciiname":"Baraya",
    "gn:country_code":"ID",
    "gn:dem":781,
    "gn:feature_class":"P",
    "gn:feature_code":"PPL",
    "gn:name":"Baraya",
    "gn:population":0,
    "gn:timezone":"Asia/Makassar",
    "iso:country":"ID",
    "name:ind_x_preferred":[
        "Baraya"
    ],
    "wof:name":"Baraya",
    "wof:placetype":"locality"
},
  "geometry": {"coordinates":[119.9785,-5.1946],"type":"Point"}
}