{
  "type": "Feature",
  "properties": {
    "gn:admin1_code":"38",
    "gn:asciiname":"Baraya",
    "gn:country_code":"ID",
    "gn:dem":781,
    "gn:feature_class":"P",
    "gn:feature_code":"PPL",
    "gn:name":"Baraya",
    "gn:population":0,
    "gn:timezone":"Asia/Makassar",
    "iso:country":"ID",
    "name:ceb_x_preferred":[
        "Baraya"
    ],
    "name:fra_x_preferred":[
        "Baraya"
    ],
    "name:ind_x_preferred":[
        "Baraya"
    ],
    "name:ita_x_preferred":[
        "Baraya"
    ],
    "name:kat_x_preferred":[
        "\u10d1\u10d0\u10e0\u10d0\u10d8\u10d0"
    ],
    "name:msa_x_preferred":[
        "Baraya"
    ],
    "name:nld_x_preferred":[
        "Baraya"
    ],
    "name:por_x_preferred":[
        "Baraya"
    ],
    "name:sco_x_preferred":[
        "Baraya"
    ],
    "name:spa_x_preferred":[
        "Baraya"
    ],
    "name:swe_x_preferred":[
        "Baraya"
    ],
    "name:tgl_x_preferred":[
        "Baraya"
    ],
    "name:vie_x_preferred":[
        "Baraya"
    ],
    "name:war_x_preferred":[
        "Baraya"
    ],
    "name:zho_x_preferred":[
        "\u5df4\u62c9\u4e9e"
    ],
    "wof:lang_x_official":[
        "ind"
    ],
    "wof:lang_x_spoken":[
        "ind",
        "eng"
    ],
    "wof:name":"Baraya",
    "wof:placetype":"locality"
},
  "geometry": {"coordinates":[119.9785,-5.1946],"type":"Point"}
}