{
  "type": "Feature",
  "properties": {
    "gn:admin1_code":"17",
    "gn:asciiname":"Waka",
    "gn:country_code":"ID",
    "gn:dem":113,
    "gn:feature_class":"P",
    "gn:feature_code":"PPL",
    "gn:name":"Waka",
    "gn:population":0,
    "gn:timezone":"Asia/Makassar",
    "iso:country":"ID",
    "name:arg_x_preferred":[
        "Waka"
    ],
    "name:bul_x_preferred":[
        "\u0412\u0430\u043a\u0430"
    ],
    "name:ceb_x_preferred":[
        "Waka"
    ],
    "name:deu_x_preferred":[
        "Waka"
    ],
    "name:fra_x_preferred":[
        "Waka"
    ],
    "name:heb_x_preferred":[
        "\u05d5\u05d0\u05e7\u05d4"
    ],
    "name:ind_x_preferred":[
        "Waka"
    ],
    "name:mri_x_preferred":[
        "Waka"
    ],
    "name:nds_x_preferred":[
        "Waka"
    ],
    "name:nld_x_preferred":[
        "Waka"
    ],
    "name:nor_x_preferred":[
        "Waka"
    ],
    "name:pol_x_preferred":[
        "Waka"
    ],
    "name:por_x_preferred":[
        "Waka"
    ],
    "name:rus_x_preferred":[
        "\u0412\u0430\u043a\u0430"
    ],
    "name:spa_x_preferred":[
        "Waka"
    ],
    "name:swe_x_preferred":[
        "Waka"
    ],
    "name:ukr_x_preferred":[
        "\u0412\u0430\u043a\u0430"
    ],
    "wof:lang_x_official":[
        "ind"
    ],
    "wof:lang_x_spoken":[
        "ind",
        "eng"
    ],
    "wof:name":"Waka",
    "wof:placetype":"locality"
},
  "geometry": {"coordinates":[116.26430000000001,-8.691],"type":"Point"}
}