{
  "type": "Feature",
  "properties": {
    "gn:admin1_code":"17",
    "gn:asciiname":"Waka",
    "gn:country_code":"ID",
    "gn:dem":113,
    "gn:feature_class":"P",
    "gn:feature_code":"PPL",
    "gn:name":"Waka",
    "gn:population":0,
    "gn:timezone":"Asia/Makassar",
    "iso:country":"ID",
    "name:ind_x_preferred":[
        "Waka"
    ],
    "wof:name":"Waka",
    "wof:placetype":"locality"
},
  "geometry": {"coordinates":[116.26430000000001,-8.691],"type":"Point"}
}