{
  "type": "Feature",
  "properties": {
    "gn:admin1_code":"29.0",
    "gn:asciiname":"Dowongikokotu",
    "gn:country_code":"ID",
    "gn:dem":20,
    "gn:feature_class":"P",
    "gn:feature_code":"PPL",
    "gn:name":"Dowongikokotu",
    "gn:population":0,
    "gn:timezone":"Asia/Jayapura",
    "iso:country":"ID",
    "name:und_x_variant":[
        "Kampoeng Dowongi Kokotoe",
        "Dowongikokotoe",
        "Dowongi Kokatoe",
        "Dowongikokote",
        "Dowongikokotu",
        "Galo Galo"
    ],
    "wof:name":"Dowongikokotu",
    "wof:placetype":"locality"
},
  "geometry": {"coordinates":[128.24839,2.12706],"type":"Point"}
}