{
  "type": "Feature",
  "properties": {
    "gn:admin1_code":"33",
    "gn:asciiname":"Saronge Lor",
    "gn:country_code":"ID",
    "gn:dem":49,
    "gn:feature_class":"P",
    "gn:feature_code":"PPL",
    "gn:name":"Saronge Lor",
    "gn:population":0,
    "gn:timezone":"Asia/Jakarta",
    "iso:country":"ID",
    "name:ind_x_preferred":[
        "Saronge Lor"
    ],
    "wof:name":"Saronge Lor",
    "wof:placetype":"locality"
},
  "geometry": {"coordinates":[106.3716,-6.3495],"type":"Point"}
}