{
  "type": "Feature",
  "properties": {
    "gn:admin1_code":"30.0",
    "gn:asciiname":"Balapulang",
    "gn:country_code":"ID",
    "gn:dem":675,
    "gn:feature_class":"P",
    "gn:feature_code":"PPL",
    "gn:name":"Balapulang",
    "gn:population":0,
    "gn:timezone":"Asia/Jakarta",
    "iso:country":"ID",
    "name:ind_x_preferred":[
        "Balapulang"
    ],
    "name:und_x_variant":[
        "Balapoelang"
    ],
    "wof:name":"Balapulang",
    "wof:placetype":"locality"
},
  "geometry": {"coordinates":[108.24850000000001,-7.1458],"type":"Point"}
}