{
  "type": "Feature",
  "properties": {
    "gn:admin1_code":"18",
    "gn:asciiname":"Ninu",
    "gn:country_code":"ID",
    "gn:dem":1064,
    "gn:feature_class":"P",
    "gn:feature_code":"PPL",
    "gn:name":"Ninu",
    "gn:population":0,
    "gn:timezone":"Asia/Makassar",
    "iso:country":"ID",
    "name:ind_x_preferred":[
        "Ninu"
    ],
    "wof:name":"Ninu",
    "wof:placetype":"locality"
},
  "geometry": {"coordinates":[120.7496,-8.5548],"type":"Point"}
}