{
  "type": "Feature",
  "properties": {
    "gn:admin1_code":"38.0",
    "gn:asciiname":"Paladan",
    "gn:country_code":"ID",
    "gn:dem":333,
    "gn:feature_class":"P",
    "gn:feature_code":"PPL",
    "gn:name":"Paladan",
    "gn:population":0,
    "gn:timezone":"Asia/Makassar",
    "iso:country":"ID",
    "name:ind_x_preferred":[
        "Paladan"
    ],
    "wof:name":"Paladan",
    "wof:placetype":"locality"
},
  "geometry": {"coordinates":[119.8629,-3.63771],"type":"Point"}
}