{
  "type": "Feature",
  "properties": {
    "gn:admin1_code":"17",
    "gn:asciiname":"Jegguar",
    "gn:country_code":"ID",
    "gn:dem":375,
    "gn:feature_class":"P",
    "gn:feature_code":"PPL",
    "gn:name":"Jegguar",
    "gn:population":0,
    "gn:timezone":"Asia/Makassar",
    "iso:country":"ID",
    "name:ind_x_preferred":[
        "Jegguar"
    ],
    "wof:name":"Jegguar",
    "wof:placetype":"locality"
},
  "geometry": {"coordinates":[116.3185,-8.577],"type":"Point"}
}