{
  "type": "Feature",
  "properties": {
    "gn:admin1_code":"37.0",
    "gn:asciiname":"Enok",
    "gn:country_code":"ID",
    "gn:dem":2,
    "gn:feature_class":"P",
    "gn:feature_code":"PPLA3",
    "gn:name":"Enok",
    "gn:population":0,
    "gn:timezone":"Asia/Jakarta",
    "iso:country":"ID",
    "name:ind_x_preferred":[
        "Enok"
    ],
    "wof:name":"Enok",
    "wof:placetype":"locality"
},
  "geometry": {"coordinates":[103.1985,-0.5149],"type":"Point"}
}