{
  "type": "Feature",
  "properties": {
    "gn:admin1_code":"30",
    "gn:asciiname":"Makam",
    "gn:country_code":"ID",
    "gn:dem":1056,
    "gn:feature_class":"P",
    "gn:feature_code":"PPL",
    "gn:name":"Makam",
    "gn:population":0,
    "gn:timezone":"Asia/Jakarta",
    "iso:country":"ID",
    "name:ind_x_preferred":[
        "Makam"
    ],
    "wof:name":"Makam",
    "wof:placetype":"locality"
},
  "geometry": {"coordinates":[107.8223,-7.1885],"type":"Point"}
}