{
  "type": "Feature",
  "properties": {
    "gn:admin1_code":"38",
    "gn:asciiname":"Lokae",
    "gn:country_code":"ID",
    "gn:dem":53,
    "gn:feature_class":"P",
    "gn:feature_code":"PPL",
    "gn:name":"Lokae",
    "gn:population":0,
    "gn:timezone":"Asia/Makassar",
    "iso:country":"ID",
    "name:ind_x_preferred":[
        "Lokae"
    ],
    "wof:name":"Lokae",
    "wof:placetype":"locality"
},
  "geometry": {"coordinates":[119.9293,-4.3592],"type":"Point"}
}