{
  "type": "Feature",
  "properties": {
    "gn:admin1_code":"7",
    "gn:asciiname":"Suru Wetan",
    "gn:country_code":"ID",
    "gn:dem":44,
    "gn:feature_class":"P",
    "gn:feature_code":"PPL",
    "gn:name":"Suru Wetan",
    "gn:population":0,
    "gn:timezone":"Asia/Jakarta",
    "iso:country":"ID",
    "name:ind_x_preferred":[
        "Suru Wetan"
    ],
    "wof:name":"Suru Wetan",
    "wof:placetype":"locality"
},
  "geometry": {"coordinates":[110.84361,-7.19722],"type":"Point"}
}