{
  "type": "Feature",
  "properties": {
    "gn:country":"ID",
    "gn:fcode":"ADM3",
    "gn:pop":0,
    "iso:country":"ID",
    "name:ind_x_preferred":[
        "Kecamatan Cikarang"
    ],
    "name:unk_x_variant":[
        "Cikarang"
    ],
    "qs:name":"Kecamatan Cikarang",
    "qs:photos_9r":0,
    "qs:photos_sr":0,
    "qs:pop_sr":"0",
    "wof:name":"Kecamatan Cikarang",
    "wof:placetype":"localadmin",
    "wof:population":0
},
  "geometry": {"coordinates":[107.17778,-6.21861],"type":"Point"}
}