{
  "type": "Feature",
  "properties": {
    "gn:admin1_code":"30",
    "gn:asciiname":"Sindanganom",
    "gn:country_code":"ID",
    "gn:dem":828,
    "gn:feature_class":"P",
    "gn:feature_code":"PPL",
    "gn:name":"Sindanganom",
    "gn:population":0,
    "gn:timezone":"Asia/Jakarta",
    "iso:country":"ID",
    "name:ind_x_preferred":[
        "Sindanganom"
    ],
    "wof:name":"Sindanganom",
    "wof:placetype":"locality"
},
  "geometry": {"coordinates":[108.11556000000002,-6.99889],"type":"Point"}
}