{
  "type": "Feature",
  "properties": {
    "gn:admin1_code":"30",
    "gn:asciiname":"Pasirparos",
    "gn:cc2":"ID",
    "gn:country_code":"ID",
    "gn:dem":672,
    "gn:feature_class":"P",
    "gn:feature_code":"PPL",
    "gn:name":"Pasirparos",
    "gn:population":0,
    "gn:timezone":"Asia/Jakarta",
    "iso:country":"ID",
    "name:und_x_variant":[
        "Pasirparos Satu",
        "Pasirparos 1",
        "Pasirparos"
    ],
    "wof:lang_x_official":[
        "ind"
    ],
    "wof:lang_x_spoken":[
        "ind",
        "eng"
    ],
    "wof:name":"Pasirparos",
    "wof:placetype":"locality"
},
  "geometry": {"coordinates":[107.62306,-7.01111],"type":"Point"}
}