{
  "type": "Feature",
  "properties": {
    "gn:admin1_code":"22.0",
    "gn:asciiname":"Lapangan Watubangga",
    "gn:country_code":"ID",
    "gn:dem":9,
    "gn:feature_class":"P",
    "gn:feature_code":"PPL",
    "gn:name":"Lapangan Watubangga",
    "gn:population":0,
    "gn:timezone":"Asia/Makassar",
    "iso:country":"ID",
    "name:ind_x_preferred":[
        "Watubangga"
    ],
    "name:und_x_variant":[
        "Watoebangga",
        "Watubanga"
    ],
    "wof:name":"Lapangan Watubangga",
    "wof:placetype":"locality"
},
  "geometry": {"coordinates":[121.51479999999999,-4.4827],"type":"Point"}
}