{
  "type": "Feature",
  "properties": {
    "gn:admin1_code":"0.0",
    "gn:asciiname":"Ledung",
    "gn:cc2":"ID",
    "gn:country_code":"ID",
    "gn:dem":-9999,
    "gn:feature_class":"P",
    "gn:feature_code":"PPL",
    "gn:name":"Ledung",
    "gn:population":0,
    "gn:timezone":"Asia/Jakarta",
    "iso:country":"ID",
    "name:und_x_variant":[
        "Ledoeng",
        "Ledung"
    ],
    "wof:name":"Ledung",
    "wof:placetype":"locality"
},
  "geometry": {"coordinates":[99.98333,2.75],"type":"Point"}
}