{
  "type": "Feature",
  "properties": {
    "gn:admin1_code":"18",
    "gn:asciiname":"Takojak",
    "gn:country_code":"ID",
    "gn:dem":427,
    "gn:feature_class":"P",
    "gn:feature_code":"PPL",
    "gn:name":"Takojak",
    "gn:population":0,
    "gn:timezone":"Asia/Makassar",
    "iso:country":"ID",
    "name:ind_x_preferred":[
        "Takojak"
    ],
    "wof:lang_x_official":[
        "ind"
    ],
    "wof:lang_x_spoken":[
        "ind",
        "eng"
    ],
    "wof:name":"Takojak",
    "wof:placetype":"locality"
},
  "geometry": {"coordinates":[119.7962,-9.6545],"type":"Point"}
}