{
  "type": "Feature",
  "properties": {
    "gn:admin1_code":"30.0",
    "gn:asciiname":"Kampunganyar",
    "gn:cc2":"ID",
    "gn:country_code":"ID",
    "gn:dem":4,
    "gn:feature_class":"P",
    "gn:feature_code":"PPL",
    "gn:name":"Kampunganyar",
    "gn:population":0,
    "gn:timezone":"Asia/Jakarta",
    "iso:country":"ID",
    "name:und_x_variant":[
        "Kampoenganjar",
        "Kampunganjar",
        "Kampunganyar"
    ],
    "wof:lang_x_official":[
        "ind"
    ],
    "wof:lang_x_spoken":[
        "ind",
        "eng"
    ],
    "wof:name":"Kampunganyar",
    "wof:placetype":"locality"
},
  "geometry": {"coordinates":[107.06778,-5.99028],"type":"Point"}
}