{
  "type": "Feature",
  "properties": {
    "gn:admin1_code":"30",
    "gn:asciiname":"Cipeuteuy",
    "gn:country_code":"ID",
    "gn:dem":689,
    "gn:feature_class":"P",
    "gn:feature_code":"PPL",
    "gn:name":"Cipeuteuy",
    "gn:population":0,
    "gn:timezone":"Asia/Jakarta",
    "iso:country":"ID",
    "name:ind_x_preferred":[
        "Cipeuteuy"
    ],
    "name:und_x_variant":[
        "Tjipeuteuj"
    ],
    "wof:lang_x_official":[
        "ind"
    ],
    "wof:lang_x_spoken":[
        "ind",
        "eng"
    ],
    "wof:name":"Cipeuteuy",
    "wof:placetype":"locality"
},
  "geometry": {"coordinates":[107.38222,-6.91056],"type":"Point"}
}