{
  "type": "Feature",
  "properties": {
    "gn:admin1_code":"38.0",
    "gn:asciiname":"Sapewalie",
    "gn:country_code":"ID",
    "gn:dem":17,
    "gn:feature_class":"P",
    "gn:feature_code":"PPL",
    "gn:name":"Sapewalie",
    "gn:population":0,
    "gn:timezone":"Asia/Makassar",
    "iso:country":"ID",
    "name:ind_x_preferred":[
        "Sapewalie"
    ],
    "wof:name":"Sapewalie",
    "wof:placetype":"locality"
},
  "geometry": {"coordinates":[120.3699,-3.78],"type":"Point"}
}