{
  "type": "Feature",
  "properties": {
    "gn:admin1_code":"38",
    "gn:asciiname":"Kaccaning",
    "gn:country_code":"ID",
    "gn:dem":28,
    "gn:feature_class":"P",
    "gn:feature_code":"PPL",
    "gn:name":"Kaccaning",
    "gn:population":0,
    "gn:timezone":"Asia/Makassar",
    "iso:country":"ID",
    "name:ind_x_preferred":[
        "Kaccaning"
    ],
    "name:und_x_variant":[
        "Kacaning"
    ],
    "wof:lang_x_official":[
        "ind"
    ],
    "wof:lang_x_spoken":[
        "ind",
        "eng"
    ],
    "wof:name":"Kaccaning",
    "wof:placetype":"locality"
},
  "geometry": {"coordinates":[120.31140000000001,-3.2681],"type":"Point"}
}