{
  "type": "Feature",
  "properties": {
    "gn:admin1_code":"26",
    "gn:asciiname":"Lumban Gurning",
    "gn:country_code":"ID",
    "gn:dem":935,
    "gn:feature_class":"P",
    "gn:feature_code":"PPL",
    "gn:name":"Lumban Gurning",
    "gn:population":0,
    "gn:timezone":"Asia/Jakarta",
    "iso:country":"ID",
    "name:ind_x_preferred":[
        "Lambang Gurning"
    ],
    "wof:name":"Lumban Gurning",
    "wof:placetype":"locality"
},
  "geometry": {"coordinates":[99.17310000000001,2.4724],"type":"Point"}
}