{
  "type": "Feature",
  "properties": {
    "gn:admin1_code":"7.0",
    "gn:asciiname":"Sirengge",
    "gn:country_code":"ID",
    "gn:dem":366,
    "gn:feature_class":"P",
    "gn:feature_code":"PPL",
    "gn:name":"Sirengge",
    "gn:population":0,
    "gn:timezone":"Asia/Jakarta",
    "iso:country":"ID",
    "name:ind_x_preferred":[
        "Sirengge"
    ],
    "wof:name":"Sirengge",
    "wof:placetype":"locality"
},
  "geometry": {"coordinates":[109.12639,-7.36417],"type":"Point"}
}