{
  "type": "Feature",
  "properties": {
    "gn:admin1_code":"1",
    "gn:asciiname":"Pajar Harapan",
    "gn:country_code":"ID",
    "gn:dem":1131,
    "gn:feature_class":"P",
    "gn:feature_code":"PPL",
    "gn:name":"Pajar Harapan",
    "gn:population":0,
    "gn:timezone":"Asia/Jakarta",
    "iso:country":"ID",
    "name:ind_x_preferred":[
        "Pajar Harapan"
    ],
    "wof:name":"Pajar Harapan",
    "wof:placetype":"locality"
},
  "geometry": {"coordinates":[96.78530000000001,4.7385],"type":"Point"}
}