{
  "type": "Feature",
  "properties": {
    "gn:admin1_code":"30",
    "gn:asciiname":"Saargenggong",
    "gn:country_code":"ID",
    "gn:dem":667,
    "gn:feature_class":"P",
    "gn:feature_code":"PPL",
    "gn:name":"Saargenggong",
    "gn:population":0,
    "gn:timezone":"Asia/Jakarta",
    "iso:country":"ID",
    "name:ind_x_preferred":[
        "Saargenggong"
    ],
    "wof:name":"Saargenggong",
    "wof:placetype":"locality"
},
  "geometry": {"coordinates":[107.47306,-6.9375],"type":"Point"}
}