{
  "type": "Feature",
  "properties": {
    "gn:country":"ID",
    "gn:fcode":"PPLA4",
    "gn:pop":0,
    "iso:country":"ID",
    "name:ind_x_preferred":[
        "Bojong"
    ],
    "name:unk_x_variant":[
        "Bodjong"
    ],
    "qs:name":"Bojong",
    "qs:photos_9r":0,
    "qs:photos_sr":0,
    "qs:pop_sr":"0",
    "wd:wordcount":128,
    "wof:name":"Bojong",
    "wof:placetype":"locality",
    "wof:population":0
},
  "geometry": {"coordinates":[107.73545,-7.59638],"type":"Point"}
}