{
  "type": "Feature",
  "properties": {
    "gn:country":"ID",
    "gn:fcode":"PPLA4",
    "gn:pop":0,
    "iso:country":"ID",
    "name:ast_x_preferred":[
        "Bojong"
    ],
    "name:eng_x_preferred":[
        "Bojong"
    ],
    "name:ind_x_preferred":[
        "Bojong"
    ],
    "name:jpn_x_preferred":[
        "\u5b9d\u5b97"
    ],
    "name:kor_x_preferred":[
        "\ubcf4\uc885"
    ],
    "name:nld_x_preferred":[
        "Bojong"
    ],
    "name:spa_x_preferred":[
        "Bojong"
    ],
    "name:sun_x_preferred":[
        "Bojong"
    ],
    "name:unk_x_variant":[
        "Bodjong"
    ],
    "name:zho_x_preferred":[
        "\u5bf6\u5b97"
    ],
    "qs:name":"Bojong",
    "qs:photos_9r":0,
    "qs:photos_sr":0,
    "qs:pop_sr":"0",
    "wd:wordcount":128,
    "wof:lang_x_official":[
        "ind"
    ],
    "wof:lang_x_spoken":[
        "ind",
        "eng"
    ],
    "wof:name":"Bojong",
    "wof:placetype":"locality",
    "wof:population":0
},
  "geometry": {"coordinates":[107.73545,-7.59638],"type":"Point"}
}