{
  "type": "Feature",
  "properties": {
    "gn:admin1_code":"37",
    "gn:asciiname":"Perhentianmarapuyan",
    "gn:country_code":"ID",
    "gn:dem":35,
    "gn:feature_class":"P",
    "gn:feature_code":"PPL",
    "gn:name":"Perhentianmarapuyan",
    "gn:population":0,
    "gn:timezone":"Asia/Jakarta",
    "iso:country":"ID",
    "name:eng_x_preferred":[
        "Perhentianmarapujan"
    ],
    "name:ind_x_preferred":[
        "Pantaimarpuyan"
    ],
    "name:ind_x_variant":[
        "Perhentianmarapuyan"
    ],
    "wof:lang_x_official":[
        "ind"
    ],
    "wof:lang_x_spoken":[
        "ind",
        "eng"
    ],
    "wof:name":"Perhentianmarapuyan",
    "wof:placetype":"locality"
},
  "geometry": {"coordinates":[101.44880000000001,0.4407],"type":"Point"}
}