{
  "type": "Feature",
  "properties": {
    "gn:admin1_code":"8.0",
    "gn:asciiname":"Galihrejo",
    "gn:country_code":"ID",
    "gn:dem":214,
    "gn:feature_class":"P",
    "gn:feature_code":"PPL",
    "gn:name":"Galihrejo",
    "gn:population":0,
    "gn:timezone":"Asia/Jakarta",
    "iso:country":"ID",
    "name:ind_x_preferred":[
        "Galihrejo"
    ],
    "wof:name":"Galihrejo",
    "wof:placetype":"locality"
},
  "geometry": {"coordinates":[111.9152,-8.2432],"type":"Point"}
}