{
  "type": "Feature",
  "properties": {
    "gn:admin1_code":"17",
    "gn:asciiname":"Sekayu",
    "gn:country_code":"ID",
    "gn:dem":50,
    "gn:feature_class":"P",
    "gn:feature_code":"PPL",
    "gn:name":"Sekayu",
    "gn:population":0,
    "gn:timezone":"Asia/Makassar",
    "iso:country":"ID",
    "name:ind_x_preferred":[
        "Sekayu"
    ],
    "wof:name":"Sekayu",
    "wof:placetype":"locality"
},
  "geometry": {"coordinates":[117.5757,-8.6424],"type":"Point"}
}