{
  "type": "Feature",
  "properties": {
    "gn:admin1_code":"37",
    "gn:asciiname":"Bangsal Aceh",
    "gn:country_code":"ID",
    "gn:dem":4,
    "gn:feature_class":"P",
    "gn:feature_code":"PPLA4",
    "gn:name":"Bangsal Aceh",
    "gn:population":0,
    "gn:timezone":"Asia/Jakarta",
    "iso:country":"ID",
    "name:ind_x_preferred":[
        "Bangsal Aceh"
    ],
    "wof:name":"Bangsal Aceh",
    "wof:placetype":"locality"
},
  "geometry": {"coordinates":[101.37614000000001,1.73202],"type":"Point"}
}