{
  "type": "Feature",
  "properties": {
    "gn:admin1_code":"38",
    "gn:asciiname":"Bontongan",
    "gn:country_code":"ID",
    "gn:dem":885,
    "gn:feature_class":"P",
    "gn:feature_code":"PPL",
    "gn:name":"Bontongan",
    "gn:population":0,
    "gn:timezone":"Asia/Makassar",
    "iso:country":"ID",
    "name:ind_x_preferred":[
        "Bontongan"
    ],
    "wof:name":"Bontongan",
    "wof:placetype":"locality"
},
  "geometry": {"coordinates":[119.90300000000001,-3.429],"type":"Point"}
}