{
  "type": "Feature",
  "properties": {
    "iso:country":"ID",
    "name:ban_x_preferred":[
        "Kartasura"
    ],
    "name:ceb_x_preferred":[
        "Kecamatan Kartasura"
    ],
    "name:deu_x_preferred":[
        "Kartasura"
    ],
    "name:eng_x_preferred":[
        "Kartasura"
    ],
    "name:fra_x_preferred":[
        "Kartasura"
    ],
    "name:ind_x_preferred":[
        "Kartasura"
    ],
    "name:jav_x_preferred":[
        "Kartasura"
    ],
    "name:jpn_x_preferred":[
        "\u30ab\u30eb\u30bf\u30b9\u30e9"
    ],
    "name:nan_x_preferred":[
        "Kartasura"
    ],
    "name:nld_x_preferred":[
        "Kartasura"
    ],
    "name:rus_x_preferred":[
        "\u041a\u0430\u0440\u0442\u0430\u0441\u0443\u0440\u0430"
    ],
    "name:spa_x_preferred":[
        "Kartasura"
    ],
    "name:swe_x_preferred":[
        "Bangunharjo"
    ],
    "name:swe_x_variant":[
        "Kecamatan Kartasura"
    ],
    "name:zho_x_preferred":[
        "\u5361\u723e\u5854\u8607\u62c9"
    ],
    "qs:name":"Kartosuro",
    "qs:name_adm0":"Indonesia",
    "qs:name_adm1":"Provinsi Jawa Tengah",
    "qs:photos":15,
    "qs:photos_1k":3,
    "qs:photos_9k":1,
    "qs:photos_9r":1,
    "qs:photos_all":15,
    "qs:photos_sr":1,
    "qs:placetype":"Town",
    "qs:pop_sr":"0",
    "wd:wordcount":282,
    "wof:lang_x_official":[
        "ind"
    ],
    "wof:lang_x_spoken":[
        "ind",
        "eng"
    ],
    "wof:name":"Kartosuro",
    "wof:placetype":"locality"
},
  "geometry": {"coordinates":[110.7397,-7.551399],"type":"Point"}
}