{
  "type": "Feature",
  "properties": {
    "gn:admin1_code":"33.0",
    "gn:asciiname":"Cikala",
    "gn:country_code":"ID",
    "gn:dem":326,
    "gn:feature_class":"P",
    "gn:feature_code":"PPL",
    "gn:name":"Cikala",
    "gn:population":0,
    "gn:timezone":"Asia/Jakarta",
    "iso:country":"ID",
    "name:ind_x_preferred":[
        "Cikala"
    ],
    "wof:name":"Cikala",
    "wof:placetype":"locality"
},
  "geometry": {"coordinates":[105.9115,-6.2413],"type":"Point"}
}