{
  "type": "Feature",
  "properties": {
    "gn:admin1_code":"8",
    "gn:asciiname":"Sambo",
    "gn:country_code":"ID",
    "gn:dem":559,
    "gn:feature_class":"P",
    "gn:feature_code":"PPL",
    "gn:name":"Sambo",
    "gn:population":0,
    "gn:timezone":"Asia/Jakarta",
    "iso:country":"ID",
    "name:ceb_x_preferred":[
        "Sambo"
    ],
    "name:dan_x_preferred":[
        "Sambo"
    ],
    "name:deu_x_preferred":[
        "Sambo"
    ],
    "name:epo_x_preferred":[
        "Sambo"
    ],
    "name:heb_x_preferred":[
        "\u05e1\u05de\u05d1\u05d5"
    ],
    "name:ind_x_preferred":[
        "Sambo"
    ],
    "name:ita_x_preferred":[
        "Sambo"
    ],
    "name:jpn_x_preferred":[
        "\u30b5\u30f3\u30dc"
    ],
    "name:nor_x_preferred":[
        "Sambo"
    ],
    "name:pol_x_preferred":[
        "Sambo"
    ],
    "name:por_x_preferred":[
        "Sambo"
    ],
    "name:rus_x_preferred":[
        "\u0421\u0430\u043c\u0431\u043e"
    ],
    "name:slk_x_preferred":[
        "Sambo"
    ],
    "name:swe_x_preferred":[
        "Sambo"
    ],
    "name:ukr_x_preferred":[
        "\u0421\u0430\u043c\u0431\u043e"
    ],
    "wof:lang_x_official":[
        "ind"
    ],
    "wof:lang_x_spoken":[
        "ind",
        "eng"
    ],
    "wof:name":"Sambo",
    "wof:placetype":"locality"
},
  "geometry": {"coordinates":[111.15278000000001,-7.53167],"type":"Point"}
}