{
  "type": "Feature",
  "properties": {
    "gn:admin1_code":"1",
    "gn:asciiname":"Urung Pane Tiga",
    "gn:country_code":"ID",
    "gn:dem":33,
    "gn:feature_class":"P",
    "gn:feature_code":"PPL",
    "gn:name":"Urung Pane Tiga",
    "gn:population":0,
    "gn:timezone":"Asia/Jakarta",
    "iso:country":"ID",
    "name:ind_x_preferred":[
        "Urung Pane Tiga"
    ],
    "name:und_x_variant":[
        "Urung Pane 3"
    ],
    "wof:lang_x_official":[
        "ind"
    ],
    "wof:lang_x_spoken":[
        "ind",
        "eng"
    ],
    "wof:name":"Urung Pane Tiga",
    "wof:placetype":"locality"
},
  "geometry": {"coordinates":[99.5253,2.9556],"type":"Point"}
}