{
  "type": "Feature",
  "properties": {
    "gn:admin1_code":"7.0",
    "gn:asciiname":"Tluko",
    "gn:country_code":"ID",
    "gn:dem":784,
    "gn:feature_class":"P",
    "gn:feature_code":"PPL",
    "gn:name":"Tluko",
    "gn:population":0,
    "gn:timezone":"Asia/Jakarta",
    "iso:country":"ID",
    "wof:name":"Tluko",
    "wof:placetype":"locality"
},
  "geometry": {"coordinates":[110.50943999999998,-7.40194],"type":"Point"}
}