{
  "type": "Feature",
  "properties": {
    "gn:admin1_code":"22.0",
    "gn:asciiname":"Lalowulo",
    "gn:country_code":"ID",
    "gn:dem":15,
    "gn:feature_class":"P",
    "gn:feature_code":"PPL",
    "gn:name":"Lalowulo",
    "gn:population":0,
    "gn:timezone":"Asia/Makassar",
    "iso:country":"ID",
    "name:ind_x_preferred":[
        "Lalowulo"
    ],
    "wof:name":"Lalowulo",
    "wof:placetype":"locality"
},
  "geometry": {"coordinates":[122.7022,-4.3018],"type":"Point"}
}