{
  "type": "Feature",
  "properties": {
    "gn:admin1_code":"7",
    "gn:asciiname":"Glinggang",
    "gn:country_code":"ID",
    "gn:dem":62,
    "gn:feature_class":"P",
    "gn:feature_code":"PPL",
    "gn:name":"Glinggang",
    "gn:population":0,
    "gn:timezone":"Asia/Jakarta",
    "iso:country":"ID",
    "name:ind_x_preferred":[
        "Glinggang"
    ],
    "wof:name":"Glinggang",
    "wof:placetype":"locality"
},
  "geometry": {"coordinates":[110.89778,-7.21611],"type":"Point"}
}