{
  "type": "Feature",
  "properties": {
    "gn:admin1_code":"26",
    "gn:asciiname":"Pondok Limapuluh",
    "gn:country_code":"ID",
    "gn:dem":35,
    "gn:feature_class":"P",
    "gn:feature_code":"PPL",
    "gn:name":"Pondok Limapuluh",
    "gn:population":0,
    "gn:timezone":"Asia/Jakarta",
    "iso:country":"ID",
    "name:ind_x_preferred":[
        "Pondok Limapuluh"
    ],
    "wof:name":"Pondok Limapuluh",
    "wof:placetype":"locality"
},
  "geometry": {"coordinates":[99.41289999999999,3.1751],"type":"Point"}
}