{
  "type": "Feature",
  "properties": {
    "gn:admin1_code":"32.0",
    "gn:asciiname":"Talang Tebat",
    "gn:country_code":"ID",
    "gn:dem":22,
    "gn:feature_class":"P",
    "gn:feature_code":"PPL",
    "gn:name":"Talang Tebat",
    "gn:population":0,
    "gn:timezone":"Asia/Jakarta",
    "iso:country":"ID",
    "name:ind_x_preferred":[
        "Talang Tebat"
    ],
    "wof:name":"Talang Tebat",
    "wof:placetype":"locality"
},
  "geometry": {"coordinates":[103.678,-2.73],"type":"Point"}
}