{
  "type": "Feature",
  "properties": {
    "gn:admin1_code":"17.0",
    "gn:asciiname":"Maria",
    "gn:country_code":"ID",
    "gn:dem":387,
    "gn:feature_class":"P",
    "gn:feature_code":"PPLA3",
    "gn:name":"Maria",
    "gn:population":0,
    "gn:timezone":"Asia/Makassar",
    "iso:country":"ID",
    "name:ind_x_preferred":[
        "Maria"
    ],
    "name:und_x_variant":[
        "Maria 1"
    ],
    "wof:name":"Maria",
    "wof:placetype":"locality"
},
  "geometry": {"coordinates":[118.84293999999998,-8.52388],"type":"Point"}
}