{
  "type": "Feature",
  "properties": {
    "gn:admin1_code":"21.0",
    "gn:asciiname":"Bega",
    "gn:country_code":"ID",
    "gn:dem":4,
    "gn:feature_class":"P",
    "gn:feature_code":"PPL",
    "gn:name":"Bega",
    "gn:population":0,
    "gn:timezone":"Asia/Makassar",
    "iso:country":"ID",
    "name:cat_x_preferred":[
        "Bega"
    ],
    "name:ceb_x_preferred":[
        "Bega"
    ],
    "name:deu_x_preferred":[
        "Bega"
    ],
    "name:fra_x_preferred":[
        "Bega"
    ],
    "name:glg_x_preferred":[
        "Bega"
    ],
    "name:ind_x_preferred":[
        "Bega"
    ],
    "name:ita_x_preferred":[
        "Bega"
    ],
    "name:nld_x_preferred":[
        "Bega"
    ],
    "name:pol_x_preferred":[
        "Bega"
    ],
    "name:ron_x_preferred":[
        "Bega"
    ],
    "name:rus_x_preferred":[
        "\u0411\u0435\u0433\u0430"
    ],
    "name:sqi_x_preferred":[
        "Bega"
    ],
    "name:swe_x_preferred":[
        "Bega"
    ],
    "name:ukr_x_preferred":[
        "\u0411\u0435\u0433\u0430"
    ],
    "wof:name":"Bega",
    "wof:placetype":"locality"
},
  "geometry": {"coordinates":[120.66549999999999,-1.4163],"type":"Point"}
}