{
  "type": "Feature",
  "properties": {
    "gn:admin1_code":"38.0",
    "gn:asciiname":"Tolo",
    "gn:country_code":"ID",
    "gn:dem":207,
    "gn:feature_class":"P",
    "gn:feature_code":"PPL",
    "gn:name":"Tolo",
    "gn:population":0,
    "gn:timezone":"Asia/Makassar",
    "iso:country":"ID",
    "name:ceb_x_preferred":[
        "Tolo"
    ],
    "name:deu_x_preferred":[
        "Tolo"
    ],
    "name:fin_x_preferred":[
        "Tolo"
    ],
    "name:fra_x_preferred":[
        "Tolo"
    ],
    "name:ind_x_preferred":[
        "Tolo"
    ],
    "name:ita_x_preferred":[
        "Tolo"
    ],
    "name:por_x_preferred":[
        "Tolo"
    ],
    "name:srp_x_preferred":[
        "Tolo"
    ],
    "name:swe_x_preferred":[
        "Tolo"
    ],
    "wof:lang_x_official":[
        "ind"
    ],
    "wof:lang_x_spoken":[
        "ind",
        "eng"
    ],
    "wof:name":"Tolo",
    "wof:placetype":"locality"
},
  "geometry": {"coordinates":[119.8053,-5.5618],"type":"Point"}
}