{
  "type": "Feature",
  "properties": {
    "gn:admin1_code":"8.0",
    "gn:asciiname":"Wilisindah Satu",
    "gn:country_code":"ID",
    "gn:dem":80,
    "gn:feature_class":"P",
    "gn:feature_code":"PPL",
    "gn:name":"Wilisindah Satu",
    "gn:population":0,
    "gn:timezone":"Asia/Jakarta",
    "iso:country":"ID",
    "name:ind_x_preferred":[
        "Wilisindah Satu"
    ],
    "wof:name":"Wilisindah Satu",
    "wof:placetype":"locality"
},
  "geometry": {"coordinates":[111.9866,-7.8195],"type":"Point"}
}