{
  "type": "Feature",
  "properties": {
    "gn:admin1_code":"41.0",
    "gn:asciiname":"Kako",
    "gn:country_code":"ID",
    "gn:dem":897,
    "gn:feature_class":"P",
    "gn:feature_code":"PPL",
    "gn:name":"Kako",
    "gn:population":0,
    "gn:timezone":"Asia/Makassar",
    "iso:country":"ID",
    "name:ind_x_preferred":[
        "Kako"
    ],
    "wof:name":"Kako",
    "wof:placetype":"locality"
},
  "geometry": {"coordinates":[119.372,-3.2595],"type":"Point"}
}