{
  "type": "Feature",
  "properties": {
    "gn:admin1_code":"2",
    "gn:asciiname":"Dajanceking",
    "gn:country_code":"ID",
    "gn:dem":681,
    "gn:feature_class":"P",
    "gn:feature_code":"PPL",
    "gn:name":"Dajanceking",
    "gn:population":0,
    "gn:timezone":"Asia/Makassar",
    "iso:country":"ID",
    "name:ind_x_preferred":[
        "Dajanceking"
    ],
    "wof:name":"Dajanceking",
    "wof:placetype":"locality"
},
  "geometry": {"coordinates":[114.9401,-8.3826],"type":"Point"}
}