{
  "type": "Feature",
  "properties": {
    "gn:admin1_code":"14",
    "gn:asciiname":"Transmigrasi Kayungo Satu B",
    "gn:country_code":"ID",
    "gn:dem":36,
    "gn:feature_class":"P",
    "gn:feature_code":"PPL",
    "gn:name":"Transmigrasi Kayungo Satu B",
    "gn:population":0,
    "gn:timezone":"Asia/Makassar",
    "iso:country":"ID",
    "name:ind_x_preferred":[
        "Transmigrasi Kayungo Satu B"
    ],
    "wof:name":"Transmigrasi Kayungo Satu B",
    "wof:placetype":"locality"
},
  "geometry": {"coordinates":[116.199,-1.564],"type":"Point"}
}