{
  "type": "Feature",
  "properties": {
    "gn:admin1_code":"18.0",
    "gn:asciiname":"Yabakalewa",
    "gn:country_code":"ID",
    "gn:dem":492,
    "gn:feature_class":"P",
    "gn:feature_code":"PPL",
    "gn:name":"Yabakalewa",
    "gn:population":0,
    "gn:timezone":"Asia/Makassar",
    "iso:country":"ID",
    "name:ind_x_preferred":[
        "Yabakalewa"
    ],
    "wof:name":"Yabakalewa",
    "wof:placetype":"locality"
},
  "geometry": {"coordinates":[119.3623,-9.5733],"type":"Point"}
}