{
  "type": "Feature",
  "properties": {
    "gn:country":"ID",
    "gn:fcode":"PPL",
    "gn:pop":0,
    "iso:country":"ID",
    "name:ind_x_preferred":[
        "Lateng"
    ],
    "qs:name":"Lelateng",
    "qs:name_adm0":"Indonesia",
    "qs:name_adm1":"Bali",
    "qs:photos_9r":0,
    "qs:photos_sr":0,
    "qs:placetype":"Town",
    "qs:pop_sr":"0",
    "wof:name":"Lelateng",
    "wof:placetype":"locality",
    "wof:population":0
},
  "geometry": {"coordinates":[114.28879999999999,-8.3284],"type":"Point"}
}