{
  "type": "Feature",
  "properties": {
    "gn:admin1_code":"30.0",
    "gn:asciiname":"Sudi",
    "gn:country_code":"ID",
    "gn:dem":484,
    "gn:feature_class":"P",
    "gn:feature_code":"PPL",
    "gn:name":"Sudi",
    "gn:population":0,
    "gn:timezone":"Asia/Jakarta",
    "iso:country":"ID",
    "name:ceb_x_preferred":[
        "S\u016bdi"
    ],
    "name:deu_x_preferred":[
        "Sudi"
    ],
    "name:hin_x_preferred":[
        "\u0938\u0941\u0926\u0940"
    ],
    "name:ind_x_preferred":[
        "Sudi"
    ],
    "name:kan_x_preferred":[
        "\u0cb8\u0cc2\u0ca1\u0cbf"
    ],
    "name:swe_x_preferred":[
        "S\u016bdi"
    ],
    "name:und_x_variant":[
        "Soedi"
    ],
    "wof:lang_x_official":[
        "ind"
    ],
    "wof:lang_x_spoken":[
        "ind",
        "eng"
    ],
    "wof:name":"Sudi",
    "wof:placetype":"locality"
},
  "geometry": {"coordinates":[108.0774,-7.4707],"type":"Point"}
}