{
  "type": "Feature",
  "properties": {
    "gn:admin1_code":"30.0",
    "gn:asciiname":"Sudi",
    "gn:country_code":"ID",
    "gn:dem":484,
    "gn:feature_class":"P",
    "gn:feature_code":"PPL",
    "gn:name":"Sudi",
    "gn:population":0,
    "gn:timezone":"Asia/Jakarta",
    "iso:country":"ID",
    "name:ind_x_preferred":[
        "Sudi"
    ],
    "name:und_x_variant":[
        "Soedi"
    ],
    "wof:name":"Sudi",
    "wof:placetype":"locality"
},
  "geometry": {"coordinates":[108.0774,-7.4707],"type":"Point"}
}