{
  "type": "Feature",
  "properties": {
    "gn:admin1_code":"18",
    "gn:asciiname":"Halifehan",
    "gn:country_code":"ID",
    "gn:dem":169,
    "gn:feature_class":"P",
    "gn:feature_code":"PPL",
    "gn:name":"Halifehan",
    "gn:population":0,
    "gn:timezone":"Asia/Makassar",
    "iso:country":"ID",
    "wof:name":"Halifehan",
    "wof:placetype":"locality"
},
  "geometry": {"coordinates":[125.00360999999999,-9.46139],"type":"Point"}
}