{
  "type": "Feature",
  "properties": {
    "gn:admin1_code":"24",
    "gn:asciiname":"Tabat",
    "gn:country_code":"ID",
    "gn:dem":214,
    "gn:feature_class":"P",
    "gn:feature_code":"PPL",
    "gn:name":"Tabat",
    "gn:population":0,
    "gn:timezone":"Asia/Jakarta",
    "iso:country":"ID",
    "name:ind_x_preferred":[
        "Tabat"
    ],
    "wof:name":"Tabat",
    "wof:placetype":"locality"
},
  "geometry": {"coordinates":[100.07250000000001,0.4994],"type":"Point"}
}