{
  "type": "Feature",
  "properties": {
    "gn:admin1_code":"41",
    "gn:asciiname":"Ujung Satu",
    "gn:country_code":"ID",
    "gn:dem":16,
    "gn:feature_class":"P",
    "gn:feature_code":"PPL",
    "gn:name":"Ujung Satu",
    "gn:population":0,
    "gn:timezone":"Asia/Makassar",
    "iso:country":"ID",
    "name:ind_x_preferred":[
        "Ujung Satu"
    ],
    "name:und_x_variant":[
        "Ujung 1"
    ],
    "wof:name":"Ujung Satu",
    "wof:placetype":"locality"
},
  "geometry": {"coordinates":[119.1863,-3.4488],"type":"Point"}
}