{
  "type": "Feature",
  "properties": {
    "gn:country":"ID",
    "gn:fcode":"PPL",
    "gn:pop":0,
    "iso:country":"ID",
    "name:deu_x_preferred":[
        "Menggala"
    ],
    "name:eng_x_preferred":[
        "Menggala"
    ],
    "name:fra_x_preferred":[
        "Menggala"
    ],
    "name:ind_x_preferred":[
        "Menggala"
    ],
    "name:nld_x_preferred":[
        "Menggala"
    ],
    "name:sun_x_preferred":[
        "Menggala"
    ],
    "name:swe_x_preferred":[
        "Kasomalang Kulon"
    ],
    "qs:name":"Menggala",
    "qs:name_adm0":"Indonesia",
    "qs:name_adm1":"Lampung",
    "qs:photos_9k":1,
    "qs:photos_9r":1,
    "qs:photos_all":4,
    "qs:photos_sr":0,
    "qs:placetype":"Town",
    "qs:pop_sr":"0",
    "wof:lang_x_official":[
        "ind"
    ],
    "wof:lang_x_spoken":[
        "ind",
        "eng"
    ],
    "wof:name":"Menggala",
    "wof:placetype":"locality",
    "wof:population":0
},
  "geometry": {"coordinates":[104.69156,-5.50823],"type":"Point"}
}