{
  "type": "Feature",
  "properties": {
    "gn:admin1_code":"7.0",
    "gn:asciiname":"Prumbanan",
    "gn:country_code":"ID",
    "gn:dem":947,
    "gn:feature_class":"P",
    "gn:feature_code":"PPL",
    "gn:name":"Prumbanan",
    "gn:population":0,
    "gn:timezone":"Asia/Jakarta",
    "iso:country":"ID",
    "name:ind_x_preferred":[
        "Prumbanan"
    ],
    "name:und_x_variant":[
        "Proembanan",
        "Proemboen",
        "Prambanan"
    ],
    "wof:lang_x_official":[
        "ind"
    ],
    "wof:lang_x_spoken":[
        "ind",
        "eng"
    ],
    "wof:name":"Prumbanan",
    "wof:placetype":"locality"
},
  "geometry": {"coordinates":[109.97167,-7.37694],"type":"Point"}
}