{
  "type": "Feature",
  "properties": {
    "gn:admin1_code":"30.0",
    "gn:asciiname":"Pabuaran",
    "gn:country_code":"ID",
    "gn:dem":51,
    "gn:feature_class":"P",
    "gn:feature_code":"PPL",
    "gn:name":"Pabuaran",
    "gn:population":0,
    "gn:timezone":"Asia/Jakarta",
    "iso:country":"ID",
    "name:ind_x_preferred":[
        "Pabuaran"
    ],
    "name:und_x_variant":[
        "Pabuwaran",
        "Paboewaran Satu"
    ],
    "wof:name":"Pabuaran",
    "wof:placetype":"locality"
},
  "geometry": {"coordinates":[108.5779,-7.4164],"type":"Point"}
}