{
  "type": "Feature",
  "properties": {
    "gn:admin1_code":"22.0",
    "gn:asciiname":"Topa",
    "gn:country_code":"ID",
    "gn:dem":9,
    "gn:feature_class":"P",
    "gn:feature_code":"PPL",
    "gn:name":"Topa",
    "gn:population":0,
    "gn:timezone":"Asia/Makassar",
    "iso:country":"ID",
    "name:ind_x_preferred":[
        "Topa"
    ],
    "wof:name":"Topa",
    "wof:placetype":"locality"
},
  "geometry": {"coordinates":[122.55929999999999,-5.5041],"type":"Point"}
}