{
  "type": "Feature",
  "properties": {
    "gn:admin1_code":"22.0",
    "gn:asciiname":"Topa",
    "gn:country_code":"ID",
    "gn:dem":9,
    "gn:feature_class":"P",
    "gn:feature_code":"PPL",
    "gn:name":"Topa",
    "gn:population":0,
    "gn:timezone":"Asia/Makassar",
    "iso:country":"ID",
    "name:bih_x_preferred":[
        "\u0924\u094b\u092a\u093e"
    ],
    "name:bpy_x_preferred":[
        "\u09a4\u09cb\u09aa\u09be"
    ],
    "name:ind_x_preferred":[
        "Topa"
    ],
    "name:ita_x_preferred":[
        "Topa"
    ],
    "name:msa_x_preferred":[
        "Topa"
    ],
    "name:nld_x_preferred":[
        "Topa"
    ],
    "name:por_x_preferred":[
        "Topa"
    ],
    "name:spa_x_preferred":[
        "Topa"
    ],
    "name:vie_x_preferred":[
        "Topa"
    ],
    "wof:lang_x_official":[
        "ind"
    ],
    "wof:lang_x_spoken":[
        "ind",
        "eng"
    ],
    "wof:name":"Topa",
    "wof:placetype":"locality"
},
  "geometry": {"coordinates":[122.55929999999999,-5.5041],"type":"Point"}
}