{
  "type": "Feature",
  "properties": {
    "gn:admin1_code":"18.0",
    "gn:asciiname":"Terdamo",
    "gn:country_code":"ID",
    "gn:dem":18,
    "gn:feature_class":"P",
    "gn:feature_code":"PPL",
    "gn:name":"Terdamo",
    "gn:population":0,
    "gn:timezone":"Asia/Makassar",
    "iso:country":"ID",
    "name:ind_x_preferred":[
        "Terdamo"
    ],
    "wof:name":"Terdamo",
    "wof:placetype":"locality"
},
  "geometry": {"coordinates":[121.85080000000001,-10.4909],"type":"Point"}
}