{
  "type": "Feature",
  "properties": {
    "gn:admin1_code":"18.0",
    "gn:asciiname":"Tubropo",
    "gn:country_code":"ID",
    "gn:dem":453,
    "gn:feature_class":"P",
    "gn:feature_code":"PPL",
    "gn:name":"Tubropo",
    "gn:population":0,
    "gn:timezone":"Asia/Makassar",
    "iso:country":"ID",
    "name:ind_x_preferred":[
        "Tubropo"
    ],
    "wof:name":"Tubropo",
    "wof:placetype":"locality"
},
  "geometry": {"coordinates":[123.70823,-10.29228],"type":"Point"}
}