{
  "type": "Feature",
  "properties": {
    "gn:admin1_code":"8.0",
    "gn:asciiname":"Ngenden",
    "gn:country_code":"ID",
    "gn:dem":18,
    "gn:feature_class":"P",
    "gn:feature_code":"PPL",
    "gn:name":"Ngenden",
    "gn:population":0,
    "gn:timezone":"Asia/Jakarta",
    "iso:country":"ID",
    "name:ind_x_preferred":[
        "Ngenden"
    ],
    "wof:name":"Ngenden",
    "wof:placetype":"locality"
},
  "geometry": {"coordinates":[111.99281999999999,-7.16888],"type":"Point"}
}