{
  "type": "Feature",
  "properties": {
    "gn:admin1_code":"7.0",
    "gn:asciiname":"Wonosari",
    "gn:country_code":"ID",
    "gn:dem":98,
    "gn:feature_class":"P",
    "gn:feature_code":"PPLA4",
    "gn:name":"Wonosari",
    "gn:population":0,
    "gn:timezone":"Asia/Jakarta",
    "iso:country":"ID",
    "name:ind_x_preferred":[
        "Wonosari"
    ],
    "wof:name":"Wonosari",
    "wof:placetype":"locality"
},
  "geometry": {"coordinates":[111.4335,-6.9516],"type":"Point"}
}