{
  "type": "Feature",
  "properties": {
    "gn:admin1_code":"18",
    "gn:asciiname":"Boazea",
    "gn:country_code":"ID",
    "gn:dem":448,
    "gn:feature_class":"P",
    "gn:feature_code":"PPL",
    "gn:name":"Boazea",
    "gn:population":0,
    "gn:timezone":"Asia/Makassar",
    "iso:country":"ID",
    "name:ind_x_preferred":[
        "Boazea"
    ],
    "wof:name":"Boazea",
    "wof:placetype":"locality"
},
  "geometry": {"coordinates":[121.3107,-8.6898],"type":"Point"}
}