{
  "type": "Feature",
  "properties": {
    "gn:admin1_code":"8",
    "gn:asciiname":"Dukutan",
    "gn:country_code":"ID",
    "gn:dem":1037,
    "gn:feature_class":"P",
    "gn:feature_code":"PPL",
    "gn:name":"Dukutan",
    "gn:population":0,
    "gn:timezone":"Asia/Jakarta",
    "iso:country":"ID",
    "name:ind_x_preferred":[
        "Dukutan"
    ],
    "wof:name":"Dukutan",
    "wof:placetype":"locality"
},
  "geometry": {"coordinates":[112.7953,-7.9042],"type":"Point"}
}