{
  "type": "Feature",
  "properties": {
    "gn:admin1_code":"8.0",
    "gn:asciiname":"Kalimanas",
    "gn:country_code":"ID",
    "gn:dem":283,
    "gn:feature_class":"P",
    "gn:feature_code":"PPL",
    "gn:name":"Kalimanas",
    "gn:population":0,
    "gn:timezone":"Asia/Jakarta",
    "iso:country":"ID",
    "name:ind_x_preferred":[
        "Kalimanas"
    ],
    "wof:name":"Kalimanas",
    "wof:placetype":"locality"
},
  "geometry": {"coordinates":[111.8991,-7.7778],"type":"Point"}
}