{
  "type": "Feature",
  "properties": {
    "gn:admin1_code":"18.0",
    "gn:asciiname":"Lewomadoleren",
    "gn:country_code":"ID",
    "gn:dem":571,
    "gn:feature_class":"P",
    "gn:feature_code":"PPL",
    "gn:name":"Lewomadoleren",
    "gn:population":0,
    "gn:timezone":"Asia/Makassar",
    "iso:country":"ID",
    "name:ind_x_preferred":[
        "Lewomadoleren"
    ],
    "wof:name":"Lewomadoleren",
    "wof:placetype":"locality"
},
  "geometry": {"coordinates":[122.6412,-8.4164],"type":"Point"}
}