{
  "type": "Feature",
  "properties": {
    "gn:admin1_code":"7.0",
    "gn:asciiname":"Gunungsari",
    "gn:country_code":"ID",
    "gn:dem":637,
    "gn:feature_class":"P",
    "gn:feature_code":"PPL",
    "gn:name":"Gunungsari",
    "gn:population":0,
    "gn:timezone":"Asia/Jakarta",
    "iso:country":"ID",
    "wof:name":"Gunungsari",
    "wof:placetype":"locality"
},
  "geometry": {"coordinates":[110.30167,-7.37444],"type":"Point"}
}