{
  "type": "Feature",
  "properties": {
    "gn:admin1_code":"38.0",
    "gn:asciiname":"Ussu",
    "gn:country_code":"ID",
    "gn:dem":6,
    "gn:feature_class":"P",
    "gn:feature_code":"PPL",
    "gn:name":"Ussu",
    "gn:population":0,
    "gn:timezone":"Asia/Makassar",
    "iso:country":"ID",
    "name:ind_x_preferred":[
        "Ussu"
    ],
    "name:und_x_variant":[
        "Oesoe",
        "Usu"
    ],
    "wof:name":"Ussu",
    "wof:placetype":"locality"
},
  "geometry": {"coordinates":[121.09180000000001,-2.5922],"type":"Point"}
}