{
  "type": "Feature",
  "properties": {
    "gn:admin1_code":"2",
    "gn:asciiname":"Pasut",
    "gn:country_code":"ID",
    "gn:dem":556,
    "gn:feature_class":"P",
    "gn:feature_code":"PPL",
    "gn:name":"Pasut",
    "gn:population":0,
    "gn:timezone":"Asia/Makassar",
    "iso:country":"ID",
    "name:ind_x_preferred":[
        "Pasut"
    ],
    "wof:name":"Pasut",
    "wof:placetype":"locality"
},
  "geometry": {"coordinates":[114.91459999999999,-8.3839],"type":"Point"}
}