{
  "type": "Feature",
  "properties": {
    "gn:admin1_code":"11.0",
    "gn:asciiname":"Setawan",
    "gn:country_code":"ID",
    "gn:dem":24,
    "gn:feature_class":"P",
    "gn:feature_code":"PPL",
    "gn:name":"Setawan",
    "gn:population":0,
    "gn:timezone":"Asia/Pontianak",
    "iso:country":"ID",
    "name:ind_x_preferred":[
        "Setawan"
    ],
    "wof:name":"Setawan",
    "wof:placetype":"locality"
},
  "geometry": {"coordinates":[110.09406,0.3964],"type":"Point"}
}