{
  "type": "Feature",
  "properties": {
    "gn:admin1_code":"33.0",
    "gn:asciiname":"Ranca",
    "gn:country_code":"ID",
    "gn:dem":277,
    "gn:feature_class":"P",
    "gn:feature_code":"PPL",
    "gn:name":"Ranca",
    "gn:population":0,
    "gn:timezone":"Asia/Jakarta",
    "iso:country":"ID",
    "name:ind_x_preferred":[
        "Ranca"
    ],
    "wof:name":"Ranca",
    "wof:placetype":"locality"
},
  "geometry": {"coordinates":[105.91200000000001,-6.3199],"type":"Point"}
}