{
  "type": "Feature",
  "properties": {
    "gn:admin1_code":"30.0",
    "gn:asciiname":"Cipetir",
    "gn:country_code":"ID",
    "gn:dem":506,
    "gn:feature_class":"P",
    "gn:feature_code":"PPL",
    "gn:name":"Cipetir",
    "gn:population":0,
    "gn:timezone":"Asia/Jakarta",
    "iso:country":"ID",
    "name:ind_x_preferred":[
        "Cipetir"
    ],
    "wof:name":"Cipetir",
    "wof:placetype":"locality"
},
  "geometry": {"coordinates":[108.2367,-7.1299],"type":"Point"}
}