{
  "type": "Feature",
  "properties": {
    "gn:admin1_code":"8.0",
    "gn:asciiname":"Tambaksari",
    "gn:country_code":"ID",
    "gn:dem":29,
    "gn:feature_class":"P",
    "gn:feature_code":"PPL",
    "gn:name":"Tambaksari",
    "gn:population":0,
    "gn:timezone":"Asia/Jakarta",
    "iso:country":"ID",
    "name:ind_x_preferred":[
        "Tambaksari"
    ],
    "name:jav_x_preferred":[
        "Tambaksari"
    ],
    "name:por_x_preferred":[
        "Tambaksari"
    ],
    "wof:lang_x_official":[
        "ind"
    ],
    "wof:lang_x_spoken":[
        "ind",
        "eng"
    ],
    "wof:name":"Tambaksari",
    "wof:placetype":"locality"
},
  "geometry": {"coordinates":[112.5972,-7.3389],"type":"Point"}
}