{
  "type": "Feature",
  "properties": {
    "gn:admin1_code":"08",
    "gn:asciiname":"Dukuhrejo",
    "gn:country_code":"ID",
    "gn:dem":6,
    "gn:feature_class":"P",
    "gn:feature_code":"PPL",
    "gn:name":"Dukuhrejo",
    "gn:population":0,
    "gn:timezone":"Asia/Jakarta",
    "iso:country":"ID",
    "name:ind_x_preferred":[
        "Dukuhrejo"
    ],
    "name:und_x_variant":[
        "Djokolojo",
        "Jokoloyo"
    ],
    "wof:name":"Dukuhrejo",
    "wof:placetype":"locality"
},
  "geometry": {"coordinates":[112.5119,-7.0796],"type":"Point"}
}