{
  "type": "Feature",
  "properties": {
    "gn:admin1_code":"26.0",
    "gn:asciiname":"Sosornapa Satu",
    "gn:country_code":"ID",
    "gn:dem":1471,
    "gn:feature_class":"P",
    "gn:feature_code":"PPL",
    "gn:name":"Sosornapa Satu",
    "gn:population":0,
    "gn:timezone":"Asia/Jakarta",
    "iso:country":"ID",
    "name:ind_x_preferred":[
        "Sosornapa Satu"
    ],
    "name:und_x_variant":[
        "Sosornapa 1"
    ],
    "wof:lang_x_official":[
        "ind"
    ],
    "wof:lang_x_spoken":[
        "ind",
        "eng"
    ],
    "wof:name":"Sosornapa Satu",
    "wof:placetype":"locality"
},
  "geometry": {"coordinates":[98.7132,2.2316],"type":"Point"}
}