{
  "type": "Feature",
  "properties": {
    "gn:admin1_code":"38",
    "gn:asciiname":"Bakke",
    "gn:country_code":"ID",
    "gn:dem":57,
    "gn:feature_class":"P",
    "gn:feature_code":"PPL",
    "gn:name":"Bakke",
    "gn:population":0,
    "gn:timezone":"Asia/Makassar",
    "iso:country":"ID",
    "name:dan_x_preferred":[
        "Bakke"
    ],
    "name:deu_x_preferred":[
        "Bakke"
    ],
    "name:fra_x_preferred":[
        "Bakke"
    ],
    "name:ind_x_preferred":[
        "Bakke"
    ],
    "name:ita_x_preferred":[
        "Bakke"
    ],
    "name:nld_x_preferred":[
        "Bakke"
    ],
    "name:nor_x_preferred":[
        "Bakke"
    ],
    "name:rus_x_preferred":[
        "\u0411\u0430\u043a\u043a\u0438"
    ],
    "wof:name":"Bakke",
    "wof:placetype":"locality"
},
  "geometry": {"coordinates":[120.2808,-4.5981],"type":"Point"}
}