{
  "type": "Feature",
  "properties": {
    "gn:admin1_code":"8",
    "gn:asciiname":"Tegalsari",
    "gn:country_code":"ID",
    "gn:dem":29,
    "gn:feature_class":"P",
    "gn:feature_code":"PPLA4",
    "gn:name":"Tegalsari",
    "gn:population":0,
    "gn:timezone":"Asia/Jakarta",
    "iso:country":"ID",
    "name:ind_x_preferred":[
        "Tegalsari"
    ],
    "wof:name":"Tegalsari",
    "wof:placetype":"locality"
},
  "geometry": {"coordinates":[113.2865,-8.1863],"type":"Point"}
}