{
  "type": "Feature",
  "properties": {
    "gn:admin1_code":"7",
    "gn:asciiname":"Simbarejo",
    "gn:country_code":"ID",
    "gn:dem":225,
    "gn:feature_class":"P",
    "gn:feature_code":"PPL",
    "gn:name":"Simbarejo",
    "gn:population":0,
    "gn:timezone":"Asia/Jakarta",
    "iso:country":"ID",
    "name:ind_x_preferred":[
        "Simbarejo"
    ],
    "wof:name":"Simbarejo",
    "wof:placetype":"locality"
},
  "geometry": {"coordinates":[111.04833000000001,-7.50056],"type":"Point"}
}