{
  "type": "Feature",
  "properties": {
    "gn:admin1_code":"32.0",
    "gn:asciiname":"Talangsungaipening",
    "gn:country_code":"ID",
    "gn:dem":58,
    "gn:feature_class":"P",
    "gn:feature_code":"PPL",
    "gn:name":"Talangsungaipening",
    "gn:population":0,
    "gn:timezone":"Asia/Jakarta",
    "iso:country":"ID",
    "name:ind_x_preferred":[
        "Talangsungaipening"
    ],
    "wof:name":"Talangsungaipening",
    "wof:placetype":"locality"
},
  "geometry": {"coordinates":[103.9577,-3.3631],"type":"Point"}
}