{
  "type": "Feature",
  "properties": {
    "gn:admin1_code":"38",
    "gn:asciiname":"Padange",
    "gn:country_code":"ID",
    "gn:dem":7,
    "gn:feature_class":"P",
    "gn:feature_code":"PPL",
    "gn:name":"Padange",
    "gn:population":0,
    "gn:timezone":"Asia/Makassar",
    "iso:country":"ID",
    "name:ind_x_preferred":[
        "Padange"
    ],
    "wof:name":"Padange",
    "wof:placetype":"locality"
},
  "geometry": {"coordinates":[119.63200000000001,-4.3389],"type":"Point"}
}