{
  "type": "Feature",
  "properties": {
    "gn:admin1_code":"32.0",
    "gn:asciiname":"Talangipuh",
    "gn:country_code":"ID",
    "gn:dem":22,
    "gn:feature_class":"P",
    "gn:feature_code":"PPL",
    "gn:name":"Talangipuh",
    "gn:population":0,
    "gn:timezone":"Asia/Jakarta",
    "iso:country":"ID",
    "name:ind_x_preferred":[
        "Talangipuh"
    ],
    "wof:name":"Talangipuh",
    "wof:placetype":"locality"
},
  "geometry": {"coordinates":[103.6953,-2.8901],"type":"Point"}
}