{
  "type": "Feature",
  "properties": {
    "gn:admin1_code":"7",
    "gn:asciiname":"Gatak",
    "gn:country_code":"ID",
    "gn:dem":5,
    "gn:feature_class":"P",
    "gn:feature_code":"PPL",
    "gn:name":"Gatak",
    "gn:population":0,
    "gn:timezone":"Asia/Jakarta",
    "iso:country":"ID",
    "name:ind_x_preferred":[
        "Gatak"
    ],
    "wof:name":"Gatak",
    "wof:placetype":"locality"
},
  "geometry": {"coordinates":[110.60890000000001,-6.8898],"type":"Point"}
}