{
  "type": "Feature",
  "properties": {
    "gn:admin1_code":"07",
    "gn:asciiname":"Purworejo",
    "gn:cc2":"ID",
    "gn:country_code":"ID",
    "gn:dem":490,
    "gn:feature_class":"P",
    "gn:feature_code":"PPL",
    "gn:name":"Purworejo",
    "gn:population":0,
    "gn:timezone":"Asia/Jakarta",
    "iso:country":"ID",
    "name:und_x_variant":[
        "Purworedjo",
        "Purworejo"
    ],
    "wof:lang_x_official":[
        "ind"
    ],
    "wof:lang_x_spoken":[
        "ind",
        "eng"
    ],
    "wof:name":"Purworejo",
    "wof:placetype":"locality"
},
  "geometry": {"coordinates":[110.28333000000001,-7.47417],"type":"Point"}
}