{
  "type": "Feature",
  "properties": {
    "gn:admin1_code":"8.0",
    "gn:asciiname":"Punten",
    "gn:country_code":"ID",
    "gn:dem":1002,
    "gn:feature_class":"P",
    "gn:feature_code":"PPL",
    "gn:name":"Punten",
    "gn:population":0,
    "gn:timezone":"Asia/Jakarta",
    "iso:country":"ID",
    "name:ind_x_preferred":[
        "Punten"
    ],
    "name:und_x_variant":[
        "Poehten",
        "Poenten"
    ],
    "wof:lang_x_official":[
        "ind"
    ],
    "wof:lang_x_spoken":[
        "ind",
        "eng"
    ],
    "wof:name":"Punten",
    "wof:placetype":"locality"
},
  "geometry": {"coordinates":[112.5283,-7.8363],"type":"Point"}
}