{
  "type": "Feature",
  "properties": {
    "gn:admin1_code":"26",
    "gn:asciiname":"Lubuk Cemara Tiga",
    "gn:country_code":"ID",
    "gn:dem":12,
    "gn:feature_class":"P",
    "gn:feature_code":"PPL",
    "gn:name":"Lubuk Cemara Tiga",
    "gn:population":0,
    "gn:timezone":"Asia/Jakarta",
    "iso:country":"ID",
    "name:ind_x_preferred":[
        "Lubuk Cemara Tiga"
    ],
    "name:und_x_variant":[
        "Lubukcemara 3"
    ],
    "wof:lang_x_official":[
        "ind"
    ],
    "wof:lang_x_spoken":[
        "ind",
        "eng"
    ],
    "wof:name":"Lubuk Cemara Tiga",
    "wof:placetype":"locality"
},
  "geometry": {"coordinates":[98.9687,3.58868],"type":"Point"}
}