{
  "type": "Feature",
  "properties": {
    "gn:admin1_code":"36.0",
    "gn:asciiname":"Sota",
    "gn:country_code":"ID",
    "gn:dem":23,
    "gn:feature_class":"P",
    "gn:feature_code":"PPL",
    "gn:name":"Sota",
    "gn:population":0,
    "gn:timezone":"Asia/Jayapura",
    "iso:country":"ID",
    "name:ceb_x_preferred":[
        "Sota"
    ],
    "name:deu_x_preferred":[
        "Sota"
    ],
    "name:ind_x_preferred":[
        "Sota"
    ],
    "name:swe_x_preferred":[
        "Sota"
    ],
    "wof:lang_x_official":[
        "ind"
    ],
    "wof:lang_x_spoken":[
        "ind",
        "eng"
    ],
    "wof:name":"Sota",
    "wof:placetype":"locality"
},
  "geometry": {"coordinates":[140.99350999999999,-8.48851],"type":"Point"}
}