{
  "type": "Feature",
  "properties": {
    "gn:admin1_code":"26",
    "gn:asciiname":"Medan Krio Dua",
    "gn:country_code":"ID",
    "gn:dem":29,
    "gn:feature_class":"P",
    "gn:feature_code":"PPL",
    "gn:name":"Medan Krio Dua",
    "gn:population":0,
    "gn:timezone":"Asia/Jakarta",
    "iso:country":"ID",
    "name:ind_x_preferred":[
        "Medan Krio Dua"
    ],
    "name:und_x_variant":[
        "Medankrio 2"
    ],
    "wof:name":"Medan Krio Dua",
    "wof:placetype":"locality"
},
  "geometry": {"coordinates":[98.59099999999999,3.5822],"type":"Point"}
}