{
  "type": "Feature",
  "properties": {
    "gn:admin1_code":"17",
    "gn:asciiname":"Sondosia Satu",
    "gn:country_code":"ID",
    "gn:dem":11,
    "gn:feature_class":"P",
    "gn:feature_code":"PPL",
    "gn:name":"Sondosia Satu",
    "gn:population":0,
    "gn:timezone":"Asia/Makassar",
    "iso:country":"ID",
    "name:ind_x_preferred":[
        "Sondosia Satu"
    ],
    "wof:name":"Sondosia Satu",
    "wof:placetype":"locality"
},
  "geometry": {"coordinates":[118.65315,-8.51904],"type":"Point"}
}