{
  "type": "Feature",
  "properties": {
    "gn:admin1_code":"0.0",
    "gn:asciiname":"Sindangjawa",
    "gn:cc2":"ID",
    "gn:country_code":"ID",
    "gn:dem":96,
    "gn:feature_class":"P",
    "gn:feature_code":"PPL",
    "gn:name":"Sindangjawa",
    "gn:population":0,
    "gn:timezone":"Asia/Jakarta",
    "iso:country":"ID",
    "name:und_x_variant":[
        "Sindangdjawa",
        "Sindangjawa"
    ],
    "wof:name":"Sindangjawa",
    "wof:placetype":"locality"
},
  "geometry": {"coordinates":[108.43333,-6.76667],"type":"Point"}
}