{
  "type": "Feature",
  "properties": {
    "gn:admin1_code":"2",
    "gn:asciiname":"Banjar Kedui",
    "gn:country_code":"ID",
    "gn:dem":604,
    "gn:feature_class":"P",
    "gn:feature_code":"PPL",
    "gn:name":"Banjar Kedui",
    "gn:population":0,
    "gn:timezone":"Asia/Makassar",
    "iso:country":"ID",
    "name:ind_x_preferred":[
        "Banjar Kedui"
    ],
    "wof:name":"Banjar Kedui",
    "wof:placetype":"locality"
},
  "geometry": {"coordinates":[115.3817,-8.4172],"type":"Point"}
}