{
  "type": "Feature",
  "properties": {
    "gn:admin1_code":"18.0",
    "gn:asciiname":"Oefatu",
    "gn:country_code":"ID",
    "gn:dem":657,
    "gn:feature_class":"P",
    "gn:feature_code":"PPL",
    "gn:name":"Oefatu",
    "gn:population":0,
    "gn:timezone":"Asia/Makassar",
    "iso:country":"ID",
    "name:ind_x_preferred":[
        "Oefatu"
    ],
    "wof:name":"Oefatu",
    "wof:placetype":"locality"
},
  "geometry": {"coordinates":[124.33329999999999,-9.9175],"type":"Point"}
}