{
  "type": "Feature",
  "properties": {
    "gn:admin1_code":"8",
    "gn:asciiname":"Tlogosari Kidul",
    "gn:country_code":"ID",
    "gn:dem":578,
    "gn:feature_class":"P",
    "gn:feature_code":"PPL",
    "gn:name":"Tlogosari Kidul",
    "gn:population":0,
    "gn:timezone":"Asia/Jakarta",
    "iso:country":"ID",
    "name:ind_x_preferred":[
        "Tlogosari Kidul"
    ],
    "wof:lang_x_official":[
        "ind"
    ],
    "wof:lang_x_spoken":[
        "ind",
        "eng"
    ],
    "wof:name":"Tlogosari Kidul",
    "wof:placetype":"locality"
},
  "geometry": {"coordinates":[112.83799999999999,-8.2393],"type":"Point"}
}