{
  "type": "Feature",
  "properties": {
    "gn:admin1_code":"30",
    "gn:asciiname":"Sukabirus",
    "gn:country_code":"ID",
    "gn:dem":667,
    "gn:feature_class":"P",
    "gn:feature_code":"PPL",
    "gn:name":"Sukabirus",
    "gn:population":0,
    "gn:timezone":"Asia/Jakarta",
    "iso:country":"ID",
    "name:ind_x_preferred":[
        "Sukabirus"
    ],
    "name:und_x_variant":[
        "Sukabirus 2",
        "Sukabirus Dua"
    ],
    "wof:lang_x_official":[
        "ind"
    ],
    "wof:lang_x_spoken":[
        "ind",
        "eng"
    ],
    "wof:name":"Sukabirus",
    "wof:placetype":"locality"
},
  "geometry": {"coordinates":[107.63139,-6.97944],"type":"Point"}
}