{
  "type": "Feature",
  "properties": {
    "gn:admin1_code":"30",
    "gn:asciiname":"Sahang",
    "gn:country_code":"ID",
    "gn:dem":590,
    "gn:feature_class":"P",
    "gn:feature_code":"PPL",
    "gn:name":"Sahang",
    "gn:population":0,
    "gn:timezone":"Asia/Jakarta",
    "iso:country":"ID",
    "name:fas_x_preferred":[
        "\u0633\u0627\u0647\u0646\u06af"
    ],
    "name:ind_x_preferred":[
        "Sahang"
    ],
    "name:pnb_x_preferred":[
        "\u0633\u0627\u0647\u0646\u06af"
    ],
    "name:urd_x_preferred":[
        "\u0633\u0627\u06c1\u0646\u06af"
    ],
    "wof:name":"Sahang",
    "wof:placetype":"locality"
},
  "geometry": {"coordinates":[107.98806,-6.88778],"type":"Point"}
}