{
  "type": "Feature",
  "properties": {
    "gn:admin1_code":"1",
    "gn:asciiname":"Tangsilama Satu",
    "gn:country_code":"ID",
    "gn:dem":5,
    "gn:feature_class":"P",
    "gn:feature_code":"PPL",
    "gn:name":"Tangsilama Satu",
    "gn:population":0,
    "gn:timezone":"Asia/Jakarta",
    "iso:country":"ID",
    "name:ind_x_preferred":[
        "Tangsilama Satu"
    ],
    "name:und_x_variant":[
        "Tangsilama 1"
    ],
    "wof:lang_x_official":[
        "ind"
    ],
    "wof:lang_x_spoken":[
        "ind",
        "eng"
    ],
    "wof:name":"Tangsilama Satu",
    "wof:placetype":"locality"
},
  "geometry": {"coordinates":[98.17829999999999,4.3575],"type":"Point"}
}