{
  "type": "Feature",
  "properties": {
    "gn:admin1_code":"18.0",
    "gn:asciiname":"Olatimo",
    "gn:country_code":"ID",
    "gn:dem":1131,
    "gn:feature_class":"P",
    "gn:feature_code":"PPL",
    "gn:name":"Olatimo",
    "gn:population":0,
    "gn:timezone":"Asia/Makassar",
    "iso:country":"ID",
    "name:ind_x_preferred":[
        "Olatimo"
    ],
    "wof:name":"Olatimo",
    "wof:placetype":"locality"
},
  "geometry": {"coordinates":[124.31310000000001,-9.547],"type":"Point"}
}