{
  "type": "Feature",
  "properties": {
    "gn:admin1_code":"18.0",
    "gn:asciiname":"Fatufafi",
    "gn:country_code":"ID",
    "gn:dem":339,
    "gn:feature_class":"P",
    "gn:feature_code":"PPL",
    "gn:name":"Fatufafi",
    "gn:population":0,
    "gn:timezone":"Asia/Makassar",
    "iso:country":"ID",
    "name:ind_x_preferred":[
        "Fatufafi"
    ],
    "wof:name":"Fatufafi",
    "wof:placetype":"locality"
},
  "geometry": {"coordinates":[124.56780000000001,-9.5389],"type":"Point"}
}