{
  "type": "Feature",
  "properties": {
    "gn:admin1_code":"7.0",
    "gn:asciiname":"Ngembul",
    "gn:country_code":"ID",
    "gn:dem":146,
    "gn:feature_class":"P",
    "gn:feature_code":"PPL",
    "gn:name":"Ngembul",
    "gn:population":0,
    "gn:timezone":"Asia/Jakarta",
    "iso:country":"ID",
    "wof:name":"Ngembul",
    "wof:placetype":"locality"
},
  "geometry": {"coordinates":[110.83194,-7.42389],"type":"Point"}
}