{
  "type": "Feature",
  "properties": {
    "gn:admin1_code":"33.0",
    "gn:asciiname":"Pancanagara",
    "gn:country_code":"ID",
    "gn:dem":135,
    "gn:feature_class":"P",
    "gn:feature_code":"PPLA4",
    "gn:name":"Pancanagara",
    "gn:population":0,
    "gn:timezone":"Asia/Jakarta",
    "iso:country":"ID",
    "name:ind_x_preferred":[
        "Pancanagara"
    ],
    "wof:lang_x_official":[
        "ind"
    ],
    "wof:lang_x_spoken":[
        "ind",
        "eng"
    ],
    "wof:name":"Pancanagara",
    "wof:placetype":"locality"
},
  "geometry": {"coordinates":[106.0877,-6.1919],"type":"Point"}
}