{
  "type": "Feature",
  "properties": {
    "gn:admin1_code":"1.0",
    "gn:asciiname":"Tanjung Bintah",
    "gn:country_code":"ID",
    "gn:dem":10,
    "gn:feature_class":"P",
    "gn:feature_code":"PPL",
    "gn:name":"Tanjung Bintah",
    "gn:population":0,
    "gn:timezone":"Asia/Jakarta",
    "iso:country":"ID",
    "name:ind_x_preferred":[
        "Tanjung Bintah"
    ],
    "name:und_x_variant":[
        "Bintah"
    ],
    "wof:name":"Tanjung Bintah",
    "wof:placetype":"locality"
},
  "geometry": {"coordinates":[97.4802,5.1296],"type":"Point"}
}