{
  "type": "Feature",
  "properties": {
    "gn:admin1_code":"33",
    "gn:asciiname":"Kemanden",
    "gn:country_code":"ID",
    "gn:dem":138,
    "gn:feature_class":"P",
    "gn:feature_code":"PPL",
    "gn:name":"Kemanden",
    "gn:population":0,
    "gn:timezone":"Asia/Jakarta",
    "iso:country":"ID",
    "name:ind_x_preferred":[
        "Kemanden"
    ],
    "wof:name":"Kemanden",
    "wof:placetype":"locality"
},
  "geometry": {"coordinates":[106.0067,-6.0895],"type":"Point"}
}