{
  "type": "Feature",
  "properties": {
    "gn:admin1_code":"10.0",
    "gn:asciiname":"Sugotamu",
    "gn:country_code":"ID",
    "gn:dem":580,
    "gn:feature_class":"P",
    "gn:feature_code":"PPL",
    "gn:name":"Sugotamu",
    "gn:population":0,
    "gn:timezone":"Asia/Jakarta",
    "iso:country":"ID",
    "wof:name":"Sugotamu",
    "wof:placetype":"locality"
},
  "geometry": {"coordinates":[110.12582999999999,-7.76278],"type":"Point"}
}