{
  "type": "Feature",
  "properties": {
    "gn:admin1_code":"21.0",
    "gn:asciiname":"Tokala Atas",
    "gn:country_code":"ID",
    "gn:dem":14,
    "gn:feature_class":"P",
    "gn:feature_code":"PPL",
    "gn:name":"Tokala Atas",
    "gn:population":0,
    "gn:timezone":"Asia/Makassar",
    "iso:country":"ID",
    "name:ind_x_preferred":[
        "Tokala Atas"
    ],
    "name:und_x_variant":[
        "Benedan Tokala",
        "Tokala"
    ],
    "wof:name":"Tokala Atas",
    "wof:placetype":"locality"
},
  "geometry": {"coordinates":[121.7436,-1.7899],"type":"Point"}
}