{
  "type": "Feature",
  "properties": {
    "gn:admin1_code":"37.0",
    "gn:asciiname":"Inuman",
    "gn:country_code":"ID",
    "gn:dem":77,
    "gn:feature_class":"P",
    "gn:feature_code":"PPL",
    "gn:name":"Inuman",
    "gn:population":0,
    "gn:timezone":"Asia/Jakarta",
    "iso:country":"ID",
    "name:ind_x_preferred":[
        "Inuman"
    ],
    "wof:name":"Inuman",
    "wof:placetype":"locality"
},
  "geometry": {"coordinates":[101.36879999999999,-0.5845],"type":"Point"}
}