{
  "type": "Feature",
  "properties": {
    "gn:admin1_code":"26",
    "gn:asciiname":"Ujungdolok",
    "gn:country_code":"ID",
    "gn:dem":915,
    "gn:feature_class":"P",
    "gn:feature_code":"PPL",
    "gn:name":"Ujungdolok",
    "gn:population":0,
    "gn:timezone":"Asia/Jakarta",
    "iso:country":"ID",
    "name:ind_x_preferred":[
        "Ujungdolok"
    ],
    "name:und_x_variant":[
        "Udjungdolok"
    ],
    "wof:name":"Ujungdolok",
    "wof:placetype":"locality"
},
  "geometry": {"coordinates":[98.7527,3.03],"type":"Point"}
}