{
  "type": "Feature",
  "properties": {
    "gn:admin1_code":"22.0",
    "gn:asciiname":"Liasa",
    "gn:country_code":"ID",
    "gn:dem":337,
    "gn:feature_class":"P",
    "gn:feature_code":"PPL",
    "gn:name":"Liasa",
    "gn:population":0,
    "gn:timezone":"Asia/Makassar",
    "iso:country":"ID",
    "name:ind_x_preferred":[
        "Liasa"
    ],
    "wof:name":"Liasa",
    "wof:placetype":"locality"
},
  "geometry": {"coordinates":[121.6288,-2.9366],"type":"Point"}
}