{
  "type": "Feature",
  "properties": {
    "gn:admin1_code":"24",
    "gn:asciiname":"Sungailandir",
    "gn:country_code":"ID",
    "gn:dem":1064,
    "gn:feature_class":"P",
    "gn:feature_code":"PPL",
    "gn:name":"Sungailandir",
    "gn:population":0,
    "gn:timezone":"Asia/Jakarta",
    "iso:country":"ID",
    "name:ind_x_preferred":[
        "Sungailandir"
    ],
    "wof:lang_x_official":[
        "ind"
    ],
    "wof:lang_x_spoken":[
        "ind",
        "eng"
    ],
    "wof:name":"Sungailandir",
    "wof:placetype":"locality"
},
  "geometry": {"coordinates":[100.29909000000001,-0.31353],"type":"Point"}
}