{
  "type": "Feature",
  "properties": {
    "gn:admin1_code":"30.0",
    "gn:asciiname":"Jodang",
    "gn:country_code":"ID",
    "gn:dem":19,
    "gn:feature_class":"P",
    "gn:feature_code":"PPL",
    "gn:name":"Jodang",
    "gn:population":0,
    "gn:timezone":"Asia/Jakarta",
    "iso:country":"ID",
    "name:ind_x_preferred":[
        "Jodang"
    ],
    "wof:name":"Jodang",
    "wof:placetype":"locality"
},
  "geometry": {"coordinates":[108.15949999999999,-7.7657],"type":"Point"}
}