{
  "type": "Feature",
  "properties": {
    "gn:admin1_code":"2",
    "gn:asciiname":"Subuk",
    "gn:country_code":"ID",
    "gn:dem":299,
    "gn:feature_class":"P",
    "gn:feature_code":"PPLA4",
    "gn:name":"Subuk",
    "gn:population":0,
    "gn:timezone":"Asia/Makassar",
    "iso:country":"ID",
    "name:ind_x_preferred":[
        "Subuk"
    ],
    "wof:name":"Subuk",
    "wof:placetype":"locality"
},
  "geometry": {"coordinates":[114.97629999999999,-8.2871],"type":"Point"}
}