{
  "type": "Feature",
  "properties": {
    "gn:admin1_code":"17.0",
    "gn:asciiname":"Karama",
    "gn:country_code":"ID",
    "gn:dem":8,
    "gn:feature_class":"P",
    "gn:feature_code":"PPL",
    "gn:name":"Karama",
    "gn:population":0,
    "gn:timezone":"Asia/Makassar",
    "iso:country":"ID",
    "name:ceb_x_preferred":[
        "Karama"
    ],
    "name:fra_x_preferred":[
        "Karama"
    ],
    "name:ind_x_preferred":[
        "Karama"
    ],
    "name:ita_x_preferred":[
        "Karama"
    ],
    "name:swe_x_preferred":[
        "Karama"
    ],
    "wof:lang_x_official":[
        "ind"
    ],
    "wof:lang_x_spoken":[
        "ind",
        "eng"
    ],
    "wof:name":"Karama",
    "wof:placetype":"locality"
},
  "geometry": {"coordinates":[118.2342,-8.5545],"type":"Point"}
}