{
  "type": "Feature",
  "properties": {
    "gn:admin1_code":"41",
    "gn:asciiname":"Salunata",
    "gn:country_code":"ID",
    "gn:dem":1004,
    "gn:feature_class":"P",
    "gn:feature_code":"PPL",
    "gn:name":"Salunata",
    "gn:population":0,
    "gn:timezone":"Asia/Makassar",
    "iso:country":"ID",
    "name:ind_x_preferred":[
        "Salunata"
    ],
    "wof:name":"Salunata",
    "wof:placetype":"locality"
},
  "geometry": {"coordinates":[119.31619999999999,-3.0164],"type":"Point"}
}