{
  "type": "Feature",
  "properties": {
    "gn:admin1_code":"17.0",
    "gn:asciiname":"Lantungteloh",
    "gn:country_code":"ID",
    "gn:dem":14,
    "gn:feature_class":"P",
    "gn:feature_code":"PPL",
    "gn:name":"Lantungteloh",
    "gn:population":0,
    "gn:timezone":"Asia/Makassar",
    "iso:country":"ID",
    "name:ind_x_preferred":[
        "Lantungteloh"
    ],
    "wof:name":"Lantungteloh",
    "wof:placetype":"locality"
},
  "geometry": {"coordinates":[116.1908,-8.328],"type":"Point"}
}