{
  "type": "Feature",
  "properties": {
    "gn:admin1_code":"17.0",
    "gn:asciiname":"Seliyuran",
    "gn:country_code":"ID",
    "gn:dem":658,
    "gn:feature_class":"P",
    "gn:feature_code":"PPL",
    "gn:name":"Seliyuran",
    "gn:population":0,
    "gn:timezone":"Asia/Makassar",
    "iso:country":"ID",
    "name:ind_x_preferred":[
        "Seliyuran"
    ],
    "wof:name":"Seliyuran",
    "wof:placetype":"locality"
},
  "geometry": {"coordinates":[116.59699999999999,-8.477],"type":"Point"}
}