{
  "type": "Feature",
  "properties": {
    "gn:admin1_code":"26",
    "gn:asciiname":"Padang-baru",
    "gn:country_code":"ID",
    "gn:dem":53,
    "gn:feature_class":"P",
    "gn:feature_code":"PPL",
    "gn:name":"Padang-baru",
    "gn:population":0,
    "gn:timezone":"Asia/Jakarta",
    "iso:country":"ID",
    "name:ind_x_preferred":[
        "Padang-baru"
    ],
    "wof:name":"Padang-baru",
    "wof:placetype":"locality"
},
  "geometry": {"coordinates":[99.0043,3.3669],"type":"Point"}
}