{
  "type": "Feature",
  "properties": {
    "gn:admin1_code":"18.0",
    "gn:asciiname":"Fatukusi",
    "gn:country_code":"ID",
    "gn:dem":483,
    "gn:feature_class":"P",
    "gn:feature_code":"PPL",
    "gn:name":"Fatukusi",
    "gn:population":0,
    "gn:timezone":"Asia/Makassar",
    "iso:country":"ID",
    "name:ind_x_preferred":[
        "Fatukusi"
    ],
    "wof:name":"Fatukusi",
    "wof:placetype":"locality"
},
  "geometry": {"coordinates":[124.5206,-9.7543],"type":"Point"}
}