{
  "type": "Feature",
  "properties": {
    "gn:admin1_code":"38",
    "gn:asciiname":"Paselloreng",
    "gn:country_code":"ID",
    "gn:dem":54,
    "gn:feature_class":"P",
    "gn:feature_code":"PPL",
    "gn:name":"Paselloreng",
    "gn:population":0,
    "gn:timezone":"Asia/Makassar",
    "iso:country":"ID",
    "name:ind_x_preferred":[
        "Paselloreng"
    ],
    "wof:name":"Paselloreng",
    "wof:placetype":"locality"
},
  "geometry": {"coordinates":[120.1677,-3.8688],"type":"Point"}
}