{
  "type": "Feature",
  "properties": {
    "gn:admin1_code":"10.0",
    "gn:asciiname":"Sogo",
    "gn:country_code":"ID",
    "gn:dem":188,
    "gn:feature_class":"P",
    "gn:feature_code":"PPL",
    "gn:name":"Sogo",
    "gn:population":0,
    "gn:timezone":"Asia/Jakarta",
    "iso:country":"ID",
    "name:deu_x_preferred":[
        "Sog\u014d"
    ],
    "name:ind_x_preferred":[
        "Sogo"
    ],
    "name:jpn_x_preferred":[
        "\u305d\u3054\u3046"
    ],
    "name:kor_x_preferred":[
        "\uc18c\uace0"
    ],
    "name:msa_x_preferred":[
        "Sogo"
    ],
    "name:nld_x_preferred":[
        "Sogo"
    ],
    "name:zho_x_preferred":[
        "\u5d07\u5149\u767e\u8ca8"
    ],
    "wof:lang_x_official":[
        "ind"
    ],
    "wof:lang_x_spoken":[
        "ind",
        "eng"
    ],
    "wof:name":"Sogo",
    "wof:placetype":"locality"
},
  "geometry": {"coordinates":[110.64722,-8.03472],"type":"Point"}
}