{
  "type": "Feature",
  "properties": {
    "gn:admin1_code":"10.0",
    "gn:asciiname":"Sogo",
    "gn:country_code":"ID",
    "gn:dem":188,
    "gn:feature_class":"P",
    "gn:feature_code":"PPL",
    "gn:name":"Sogo",
    "gn:population":0,
    "gn:timezone":"Asia/Jakarta",
    "iso:country":"ID",
    "name:ind_x_preferred":[
        "Sogo"
    ],
    "wof:name":"Sogo",
    "wof:placetype":"locality"
},
  "geometry": {"coordinates":[110.64722,-8.03472],"type":"Point"}
}