{
  "type": "Feature",
  "properties": {
    "gn:admin1_code":"33",
    "gn:asciiname":"Cikubang Dua",
    "gn:country_code":"ID",
    "gn:dem":28,
    "gn:feature_class":"P",
    "gn:feature_code":"PPL",
    "gn:name":"Cikubang Dua",
    "gn:population":0,
    "gn:timezone":"Asia/Jakarta",
    "iso:country":"ID",
    "name:ind_x_preferred":[
        "Cikubang Dua"
    ],
    "wof:name":"Cikubang Dua",
    "wof:placetype":"locality"
},
  "geometry": {"coordinates":[106.0911,-5.9477],"type":"Point"}
}