{
  "type": "Feature",
  "properties": {
    "gn:admin1_code":"8.0",
    "gn:asciiname":"Jagung Bawah",
    "gn:country_code":"ID",
    "gn:dem":193,
    "gn:feature_class":"P",
    "gn:feature_code":"PPL",
    "gn:name":"Jagung Bawah",
    "gn:population":0,
    "gn:timezone":"Asia/Jakarta",
    "iso:country":"ID",
    "name:ind_x_preferred":[
        "Jagung Bawah"
    ],
    "wof:name":"Jagung Bawah",
    "wof:placetype":"locality"
},
  "geometry": {"coordinates":[113.629,-6.9339],"type":"Point"}
}