{
  "type": "Feature",
  "properties": {
    "gn:admin1_code":"30.0",
    "gn:asciiname":"Gadobangkong",
    "gn:country_code":"ID",
    "gn:dem":578,
    "gn:feature_class":"P",
    "gn:feature_code":"PPL",
    "gn:name":"Gadobangkong",
    "gn:population":0,
    "gn:timezone":"Asia/Jakarta",
    "iso:country":"ID",
    "name:ind_x_preferred":[
        "Gadobangkong"
    ],
    "wof:name":"Gadobangkong",
    "wof:placetype":"locality"
},
  "geometry": {"coordinates":[107.46639999999999,-7.3206],"type":"Point"}
}