{
  "type": "Feature",
  "properties": {
    "gn:admin1_code":"7",
    "gn:asciiname":"Kedungwadas",
    "gn:country_code":"ID",
    "gn:dem":9,
    "gn:feature_class":"P",
    "gn:feature_code":"PPL",
    "gn:name":"Kedungwadas",
    "gn:population":0,
    "gn:timezone":"Asia/Jakarta",
    "iso:country":"ID",
    "name:ind_x_preferred":[
        "Kedungwadas"
    ],
    "wof:name":"Kedungwadas",
    "wof:placetype":"locality"
},
  "geometry": {"coordinates":[109.03360000000001,-6.9299],"type":"Point"}
}