{
  "type": "Feature",
  "properties": {
    "gn:admin1_code":"7",
    "gn:asciiname":"Serang",
    "gn:country_code":"ID",
    "gn:dem":85,
    "gn:feature_class":"P",
    "gn:feature_code":"PPL",
    "gn:name":"Serang",
    "gn:population":0,
    "gn:timezone":"Asia/Jakarta",
    "iso:country":"ID",
    "name:ind_x_preferred":[
        "Serang"
    ],
    "wof:name":"Serang",
    "wof:placetype":"locality"
},
  "geometry": {"coordinates":[110.8473,-6.7509],"type":"Point"}
}