{
  "type": "Feature",
  "properties": {
    "gn:admin1_code":"7.0",
    "gn:asciiname":"Menganti",
    "gn:country_code":"ID",
    "gn:dem":18,
    "gn:feature_class":"P",
    "gn:feature_code":"PPLA4",
    "gn:name":"Menganti",
    "gn:population":0,
    "gn:timezone":"Asia/Jakarta",
    "iso:country":"ID",
    "name:ind_x_preferred":[
        "Menganti"
    ],
    "name:und_x_variant":[
        "Meganti"
    ],
    "wof:name":"Menganti",
    "wof:placetype":"locality"
},
  "geometry": {"coordinates":[109.15639,-7.54917],"type":"Point"}
}