{
  "type": "Feature",
  "properties": {
    "gn:admin1_code":"2.0",
    "gn:asciiname":"Banjar Sangkaragung",
    "gn:country_code":"ID",
    "gn:dem":11,
    "gn:feature_class":"P",
    "gn:feature_code":"PPL",
    "gn:name":"Banjar Sangkaragung",
    "gn:population":0,
    "gn:timezone":"Asia/Makassar",
    "iso:country":"ID",
    "name:ind_x_preferred":[
        "Banjar Sangkaragung"
    ],
    "wof:name":"Banjar Sangkaragung",
    "wof:placetype":"locality"
},
  "geometry": {"coordinates":[114.6495,-8.3748],"type":"Point"}
}