{
  "type": "Feature",
  "properties": {
    "gn:admin1_code":"38",
    "gn:asciiname":"Paranggi",
    "gn:country_code":"ID",
    "gn:dem":9,
    "gn:feature_class":"P",
    "gn:feature_code":"PPL",
    "gn:name":"Paranggi",
    "gn:population":0,
    "gn:timezone":"Asia/Makassar",
    "iso:country":"ID",
    "name:ind_x_preferred":[
        "Paranggi"
    ],
    "wof:name":"Paranggi",
    "wof:placetype":"locality"
},
  "geometry": {"coordinates":[119.63039999999999,-4.9908],"type":"Point"}
}