{
  "type": "Feature",
  "properties": {
    "gn:admin1_code":"29.0",
    "gn:asciiname":"Mamin",
    "gn:country_code":"ID",
    "gn:dem":80,
    "gn:feature_class":"P",
    "gn:feature_code":"PPL",
    "gn:name":"Mamin",
    "gn:population":0,
    "gn:timezone":"Asia/Jayapura",
    "iso:country":"ID",
    "name:deu_x_preferred":[
        "Mamin"
    ],
    "name:nds_x_preferred":[
        "Mamin"
    ],
    "wof:lang_x_official":[
        "ind"
    ],
    "wof:lang_x_spoken":[
        "ind",
        "eng"
    ],
    "wof:name":"Mamin",
    "wof:placetype":"locality"
},
  "geometry": {"coordinates":[127.71608000000001,0.84621],"type":"Point"}
}