{
  "type": "Feature",
  "properties": {
    "gn:admin1_code":"41",
    "gn:asciiname":"Ratte",
    "gn:country_code":"ID",
    "gn:dem":1029,
    "gn:feature_class":"P",
    "gn:feature_code":"PPL",
    "gn:name":"Ratte",
    "gn:population":0,
    "gn:timezone":"Asia/Makassar",
    "iso:country":"ID",
    "name:deu_x_preferred":[
        "Ratte"
    ],
    "name:fra_x_preferred":[
        "Ratte"
    ],
    "name:ind_x_preferred":[
        "Ratte"
    ],
    "name:ita_x_preferred":[
        "Ratte"
    ],
    "name:nld_x_preferred":[
        "Ratte"
    ],
    "name:vls_x_preferred":[
        "Ratte"
    ],
    "wof:lang_x_official":[
        "ind"
    ],
    "wof:lang_x_spoken":[
        "ind",
        "eng"
    ],
    "wof:name":"Ratte",
    "wof:placetype":"locality"
},
  "geometry": {"coordinates":[119.3591,-3.1715],"type":"Point"}
}