{
  "type": "Feature",
  "properties": {
    "gn:admin1_code":"18",
    "gn:asciiname":"Bonga",
    "gn:country_code":"ID",
    "gn:dem":423,
    "gn:feature_class":"P",
    "gn:feature_code":"PPL",
    "gn:name":"Bonga",
    "gn:population":0,
    "gn:timezone":"Asia/Makassar",
    "iso:country":"ID",
    "name:ind_x_preferred":[
        "Bonga"
    ],
    "wof:name":"Bonga",
    "wof:placetype":"locality"
},
  "geometry": {"coordinates":[119.8263,-9.6477],"type":"Point"}
}