{
  "type": "Feature",
  "properties": {
    "gn:admin1_code":"7",
    "gn:asciiname":"Karangtalun",
    "gn:country_code":"ID",
    "gn:dem":712,
    "gn:feature_class":"P",
    "gn:feature_code":"PPL",
    "gn:name":"Karangtalun",
    "gn:population":0,
    "gn:timezone":"Asia/Jakarta",
    "iso:country":"ID",
    "name:ind_x_preferred":[
        "Karangtalun"
    ],
    "wof:name":"Karangtalun",
    "wof:placetype":"locality"
},
  "geometry": {"coordinates":[110.38972,-7.22139],"type":"Point"}
}