{
  "type": "Feature",
  "properties": {
    "gn:admin1_code":"38",
    "gn:asciiname":"Lapara",
    "gn:country_code":"ID",
    "gn:dem":1007,
    "gn:feature_class":"P",
    "gn:feature_code":"PPL",
    "gn:name":"Lapara",
    "gn:population":0,
    "gn:timezone":"Asia/Makassar",
    "iso:country":"ID",
    "name:azb_x_preferred":[
        "\u0644\u0627\u067e\u0627\u0631\u0627"
    ],
    "name:fas_x_preferred":[
        "\u0644\u0627\u067e\u0627\u0631\u0627"
    ],
    "name:fra_x_preferred":[
        "Lapara"
    ],
    "name:ind_x_preferred":[
        "Lapara"
    ],
    "name:urd_x_preferred":[
        "\u0644\u0627\u067e\u0627\u0631\u0627"
    ],
    "wof:lang_x_official":[
        "ind"
    ],
    "wof:lang_x_spoken":[
        "ind",
        "eng"
    ],
    "wof:name":"Lapara",
    "wof:placetype":"locality"
},
  "geometry": {"coordinates":[119.9093,-5.4613],"type":"Point"}
}