{
  "type": "Feature",
  "properties": {
    "gn:admin1_code":"30.0",
    "gn:asciiname":"Citake",
    "gn:country_code":"ID",
    "gn:dem":740,
    "gn:feature_class":"P",
    "gn:feature_code":"PPL",
    "gn:name":"Citake",
    "gn:population":0,
    "gn:timezone":"Asia/Jakarta",
    "iso:country":"ID",
    "name:ind_x_preferred":[
        "Citake"
    ],
    "wof:name":"Citake",
    "wof:placetype":"locality"
},
  "geometry": {"coordinates":[107.84350000000001,-7.4975],"type":"Point"}
}