{
  "type": "Feature",
  "properties": {
    "gn:admin1_code":"30",
    "gn:asciiname":"Grahapemda",
    "gn:country_code":"ID",
    "gn:dem":15,
    "gn:feature_class":"P",
    "gn:feature_code":"PPL",
    "gn:name":"Grahapemda",
    "gn:population":0,
    "gn:timezone":"Asia/Jakarta",
    "iso:country":"ID",
    "name:ind_x_preferred":[
        "Grahapemda"
    ],
    "wof:name":"Grahapemda",
    "wof:placetype":"locality"
},
  "geometry": {"coordinates":[107.18138999999999,-6.27306],"type":"Point"}
}