{
  "type": "Feature",
  "properties": {
    "gn:admin1_code":"8.0",
    "gn:asciiname":"Kemlaten",
    "gn:country_code":"ID",
    "gn:dem":31,
    "gn:feature_class":"P",
    "gn:feature_code":"PPL",
    "gn:name":"Kemlaten",
    "gn:population":0,
    "gn:timezone":"Asia/Jakarta",
    "iso:country":"ID",
    "name:ind_x_preferred":[
        "Kemlaten"
    ],
    "wof:name":"Kemlaten",
    "wof:placetype":"locality"
},
  "geometry": {"coordinates":[112.35129999999999,-7.4193],"type":"Point"}
}