{
  "type": "Feature",
  "properties": {
    "gn:admin1_code":"38",
    "gn:asciiname":"Batangkaluku",
    "gn:country_code":"ID",
    "gn:dem":15,
    "gn:feature_class":"P",
    "gn:feature_code":"PPL",
    "gn:name":"Batangkaluku",
    "gn:population":0,
    "gn:timezone":"Asia/Makassar",
    "iso:country":"ID",
    "name:ind_x_preferred":[
        "Batangkaluku"
    ],
    "wof:name":"Batangkaluku",
    "wof:placetype":"locality"
},
  "geometry": {"coordinates":[119.4616,-5.2144],"type":"Point"}
}