{
  "type": "Feature",
  "properties": {
    "gn:admin1_code":"8.0",
    "gn:asciiname":"Maron",
    "gn:country_code":"ID",
    "gn:dem":126,
    "gn:feature_class":"P",
    "gn:feature_code":"PPL",
    "gn:name":"Maron",
    "gn:population":0,
    "gn:timezone":"Asia/Jakarta",
    "iso:country":"ID",
    "name:ara_x_preferred":[
        "\u0645\u0627\u0631\u0648\u0646"
    ],
    "name:arg_x_preferred":[
        "Sant Mar\u00f3n"
    ],
    "name:arz_x_preferred":[
        "\u0627\u0644\u0642\u062f\u064a\u0633 \u0645\u0627\u0631\u0648\u0646"
    ],
    "name:ces_x_preferred":[
        "Svat\u00fd Maron"
    ],
    "name:epo_x_preferred":[
        "Sankta Marono"
    ],
    "name:fra_x_preferred":[
        "Maron"
    ],
    "name:ind_x_preferred":[
        "Maron"
    ],
    "name:ita_x_preferred":[
        "San Marone"
    ],
    "name:lat_x_preferred":[
        "Maron"
    ],
    "name:nld_x_preferred":[
        "Maron"
    ],
    "name:pol_x_preferred":[
        "\u015awi\u0119ty Maron"
    ],
    "name:rus_x_preferred":[
        "\u041c\u0430\u0440\u043e\u043d"
    ],
    "name:swa_x_preferred":[
        "Maroni"
    ],
    "name:swe_x_preferred":[
        "Johannes Maron"
    ],
    "name:ukr_x_preferred":[
        "\u0421\u0432\u044f\u0442\u0438\u0439 \u041c\u0430\u0440\u043e\u043d"
    ],
    "wof:lang_x_official":[
        "ind"
    ],
    "wof:lang_x_spoken":[
        "ind",
        "eng"
    ],
    "wof:name":"Maron",
    "wof:placetype":"locality"
},
  "geometry": {"coordinates":[112.0844,-8.1022],"type":"Point"}
}