{
  "type": "Feature",
  "properties": {
    "gn:admin1_code":"7.0",
    "gn:asciiname":"Sadabumi",
    "gn:country_code":"ID",
    "gn:dem":528,
    "gn:feature_class":"P",
    "gn:feature_code":"PPLA4",
    "gn:name":"Sadabumi",
    "gn:population":0,
    "gn:timezone":"Asia/Jakarta",
    "iso:country":"ID",
    "name:ind_x_preferred":[
        "Sadabumi"
    ],
    "name:und_x_variant":[
        "Sadaboemi"
    ],
    "wof:name":"Sadabumi",
    "wof:placetype":"locality"
},
  "geometry": {"coordinates":[108.7505,-7.2137],"type":"Point"}
}