{
  "type": "Feature",
  "properties": {
    "gn:admin1_code":"0.0",
    "gn:asciiname":"Lauru",
    "gn:cc2":"ID",
    "gn:country_code":"ID",
    "gn:dem":253,
    "gn:feature_class":"P",
    "gn:feature_code":"PPL",
    "gn:name":"Lauru",
    "gn:population":0,
    "gn:timezone":"Asia/Jakarta",
    "iso:country":"ID",
    "name:und_x_variant":[
        "Lelewua",
        "Lauru"
    ],
    "wof:name":"Lauru",
    "wof:placetype":"locality"
},
  "geometry": {"coordinates":[97.56667,1.21667],"type":"Point"}
}