{
  "type": "Feature",
  "properties": {
    "gn:admin1_code":"7.0",
    "gn:asciiname":"Rangkah",
    "gn:country_code":"ID",
    "gn:dem":17,
    "gn:feature_class":"P",
    "gn:feature_code":"PPL",
    "gn:name":"Rangkah",
    "gn:population":0,
    "gn:timezone":"Asia/Jakarta",
    "iso:country":"ID",
    "name:ind_x_preferred":[
        "Rangkah"
    ],
    "wof:name":"Rangkah",
    "wof:placetype":"locality"
},
  "geometry": {"coordinates":[111.4633,-6.6818],"type":"Point"}
}