{
  "type": "Feature",
  "properties": {
    "gn:admin1_code":"7",
    "gn:asciiname":"Dungguwak",
    "gn:country_code":"ID",
    "gn:dem":22,
    "gn:feature_class":"P",
    "gn:feature_code":"PPL",
    "gn:name":"Dungguwak",
    "gn:population":0,
    "gn:timezone":"Asia/Jakarta",
    "iso:country":"ID",
    "name:ind_x_preferred":[
        "Dungguwak"
    ],
    "wof:name":"Dungguwak",
    "wof:placetype":"locality"
},
  "geometry": {"coordinates":[110.82980000000001,-7.0288],"type":"Point"}
}