{
  "type": "Feature",
  "properties": {
    "gn:admin1_code":"30.0",
    "gn:asciiname":"Kebonkalapa",
    "gn:country_code":"ID",
    "gn:dem":201,
    "gn:feature_class":"P",
    "gn:feature_code":"PPL",
    "gn:name":"Kebonkalapa",
    "gn:population":0,
    "gn:timezone":"Asia/Jakarta",
    "iso:country":"ID",
    "name:ind_x_preferred":[
        "Kebonkalapa"
    ],
    "wof:name":"Kebonkalapa",
    "wof:placetype":"locality"
},
  "geometry": {"coordinates":[107.19589999999999,-7.3368],"type":"Point"}
}