{
  "type": "Feature",
  "properties": {
    "gn:admin1_code":"0.0",
    "gn:asciiname":"Sopolongat-jae",
    "gn:cc2":"ID",
    "gn:country_code":"ID",
    "gn:dem":621,
    "gn:feature_class":"P",
    "gn:feature_code":"PPL",
    "gn:name":"Sopolongat-jae",
    "gn:population":0,
    "gn:timezone":"Asia/Jakarta",
    "iso:country":"ID",
    "name:und_x_variant":[
        "Sopolongat-djae",
        "Sopolongat-jae"
    ],
    "wof:lang_x_official":[
        "ind"
    ],
    "wof:lang_x_spoken":[
        "ind",
        "eng"
    ],
    "wof:name":"Sopolongat-jae",
    "wof:placetype":"locality"
},
  "geometry": {"coordinates":[99.58333,2.03333],"type":"Point"}
}