{
  "type": "Feature",
  "properties": {
    "gn:admin1_code":"30",
    "gn:asciiname":"Pasirangin",
    "gn:country_code":"ID",
    "gn:dem":711,
    "gn:feature_class":"P",
    "gn:feature_code":"PPL",
    "gn:name":"Pasirangin",
    "gn:population":0,
    "gn:timezone":"Asia/Jakarta",
    "iso:country":"ID",
    "name:ind_x_preferred":[
        "Pasirangin"
    ],
    "wof:name":"Pasirangin",
    "wof:placetype":"locality"
},
  "geometry": {"coordinates":[106.92556,-6.89306],"type":"Point"}
}