{
  "type": "Feature",
  "properties": {
    "gn:admin1_code":"30.0",
    "gn:asciiname":"Tarisi",
    "gn:country_code":"ID",
    "gn:dem":245,
    "gn:feature_class":"P",
    "gn:feature_code":"PPL",
    "gn:name":"Tarisi",
    "gn:population":0,
    "gn:timezone":"Asia/Jakarta",
    "iso:country":"ID",
    "name:ind_x_preferred":[
        "Tarisi"
    ],
    "wof:name":"Tarisi",
    "wof:placetype":"locality"
},
  "geometry": {"coordinates":[107.6459,-7.4802],"type":"Point"}
}