{
  "type": "Feature",
  "properties": {
    "gn:admin1_code":"8.0",
    "gn:asciiname":"Tegar Barat",
    "gn:country_code":"ID",
    "gn:dem":68,
    "gn:feature_class":"P",
    "gn:feature_code":"PPL",
    "gn:name":"Tegar Barat",
    "gn:population":0,
    "gn:timezone":"Asia/Jakarta",
    "iso:country":"ID",
    "name:ind_x_preferred":[
        "Tegar Barat"
    ],
    "wof:name":"Tegar Barat",
    "wof:placetype":"locality"
},
  "geometry": {"coordinates":[112.8676,-6.9914],"type":"Point"}
}