{
  "type": "Feature",
  "properties": {
    "gn:admin1_code":"30.0",
    "gn:asciiname":"Pasirgombong",
    "gn:country_code":"ID",
    "gn:dem":262,
    "gn:feature_class":"P",
    "gn:feature_code":"PPL",
    "gn:name":"Pasirgombong",
    "gn:population":0,
    "gn:timezone":"Asia/Jakarta",
    "iso:country":"ID",
    "name:ind_x_preferred":[
        "Pasirgombong"
    ],
    "wof:name":"Pasirgombong",
    "wof:placetype":"locality"
},
  "geometry": {"coordinates":[108.503,-7.4948],"type":"Point"}
}