{
  "type": "Feature",
  "properties": {
    "gn:admin1_code":"7.0",
    "gn:asciiname":"Asinan",
    "gn:country_code":"ID",
    "gn:dem":48,
    "gn:feature_class":"P",
    "gn:feature_code":"PPL",
    "gn:name":"Asinan",
    "gn:population":0,
    "gn:timezone":"Asia/Jakarta",
    "iso:country":"ID",
    "name:ind_x_preferred":[
        "Asinan"
    ],
    "wof:name":"Asinan",
    "wof:placetype":"locality"
},
  "geometry": {"coordinates":[109.43611,-7.39389],"type":"Point"}
}