{
  "type": "Feature",
  "properties": {
    "gn:admin1_code":"7.0",
    "gn:asciiname":"Asinan",
    "gn:country_code":"ID",
    "gn:dem":48,
    "gn:feature_class":"P",
    "gn:feature_code":"PPL",
    "gn:name":"Asinan",
    "gn:population":0,
    "gn:timezone":"Asia/Jakarta",
    "iso:country":"ID",
    "name:fas_x_preferred":[
        "\u0622\u0633\u06cc\u0646\u0627\u0646"
    ],
    "name:fra_x_preferred":[
        "Asinan"
    ],
    "name:ind_x_preferred":[
        "Asinan"
    ],
    "name:spa_x_preferred":[
        "Asinan"
    ],
    "name:sun_x_preferred":[
        "Asinan"
    ],
    "name:tha_x_preferred":[
        "\u0e2d\u0e32\u0e0b\u0e35\u0e19\u0e31\u0e19"
    ],
    "wof:name":"Asinan",
    "wof:placetype":"locality"
},
  "geometry": {"coordinates":[109.43611,-7.39389],"type":"Point"}
}