{
  "type": "Feature",
  "properties": {
    "gn:admin1_code":"38.0",
    "gn:asciiname":"Temban",
    "gn:country_code":"ID",
    "gn:dem":81,
    "gn:feature_class":"P",
    "gn:feature_code":"PPL",
    "gn:name":"Temban",
    "gn:population":0,
    "gn:timezone":"Asia/Makassar",
    "iso:country":"ID",
    "name:ind_x_preferred":[
        "Temban"
    ],
    "wof:name":"Temban",
    "wof:placetype":"locality"
},
  "geometry": {"coordinates":[119.7287,-3.4997],"type":"Point"}
}