{
  "type": "Feature",
  "properties": {
    "gn:admin1_code":"7.0",
    "gn:asciiname":"Banyuurip",
    "gn:country_code":"ID",
    "gn:dem":124,
    "gn:feature_class":"P",
    "gn:feature_code":"PPL",
    "gn:name":"Banyuurip",
    "gn:population":0,
    "gn:timezone":"Asia/Jakarta",
    "iso:country":"ID",
    "name:ind_x_preferred":[
        "Banyuurip"
    ],
    "wof:name":"Banyuurip",
    "wof:placetype":"locality"
},
  "geometry": {"coordinates":[111.3707,-6.8592],"type":"Point"}
}