{
  "type": "Feature",
  "properties": {
    "gn:admin1_code":"30",
    "gn:asciiname":"Gunungsanggar",
    "gn:country_code":"ID",
    "gn:dem":659,
    "gn:feature_class":"P",
    "gn:feature_code":"PPL",
    "gn:name":"Gunungsanggar",
    "gn:population":0,
    "gn:timezone":"Asia/Jakarta",
    "iso:country":"ID",
    "name:ind_x_preferred":[
        "Gunungsanggar"
    ],
    "name:und_x_variant":[
        "Gunungsanggar 1",
        "Gunungsanggar Dua",
        "Gunungsanggar 2",
        "Gunungsanggar Satu"
    ],
    "wof:lang_x_official":[
        "ind"
    ],
    "wof:lang_x_spoken":[
        "ind",
        "eng"
    ],
    "wof:name":"Gunungsanggar",
    "wof:placetype":"locality"
},
  "geometry": {"coordinates":[107.42111,-6.97083],"type":"Point"}
}