{
  "type": "Feature",
  "properties": {
    "gn:admin1_code":"33",
    "gn:asciiname":"Kaduembe",
    "gn:country_code":"ID",
    "gn:dem":177,
    "gn:feature_class":"P",
    "gn:feature_code":"PPL",
    "gn:name":"Kaduembe",
    "gn:population":0,
    "gn:timezone":"Asia/Jakarta",
    "iso:country":"ID",
    "name:ind_x_preferred":[
        "Kaduembe"
    ],
    "wof:name":"Kaduembe",
    "wof:placetype":"locality"
},
  "geometry": {"coordinates":[105.9867,-6.1074],"type":"Point"}
}