{
  "type": "Feature",
  "properties": {
    "gn:admin1_code":"1",
    "gn:asciiname":"Cotteunom",
    "gn:country_code":"ID",
    "gn:dem":8,
    "gn:feature_class":"P",
    "gn:feature_code":"PPL",
    "gn:name":"Cotteunom",
    "gn:population":0,
    "gn:timezone":"Asia/Jakarta",
    "iso:country":"ID",
    "name:ind_x_preferred":[
        "Cotteunom"
    ],
    "wof:name":"Cotteunom",
    "wof:placetype":"locality"
},
  "geometry": {"coordinates":[95.9584,5.3672],"type":"Point"}
}