{
  "type": "Feature",
  "properties": {
    "gn:country":"ID",
    "gn:fcode":"PPLA4",
    "gn:pop":0,
    "iso:country":"ID",
    "name:ace_x_preferred":[
        "Padangbai"
    ],
    "name:ban_x_preferred":[
        "Padangbai"
    ],
    "name:ceb_x_preferred":[
        "Desa Padangbai"
    ],
    "name:deu_x_preferred":[
        "Padang Bai"
    ],
    "name:eng_x_preferred":[
        "Padangbai"
    ],
    "name:fra_x_preferred":[
        "Padangbai"
    ],
    "name:ind_x_preferred":[
        "Padangbai"
    ],
    "name:jav_x_preferred":[
        "Padangbai"
    ],
    "name:jpn_x_preferred":[
        "\u30d1\u30c0\u30f3\u30d0\u30a4"
    ],
    "name:msa_x_preferred":[
        "Padangbai"
    ],
    "name:nld_x_preferred":[
        "Padangbai"
    ],
    "name:por_x_preferred":[
        "Padangbai"
    ],
    "name:rus_x_preferred":[
        "\u041f\u0430\u0434\u0430\u043d\u0433\u0431\u0430\u0439"
    ],
    "name:spa_x_preferred":[
        "Padangbai"
    ],
    "name:swe_x_preferred":[
        "Desa Padangbai"
    ],
    "name:unk_x_variant":[
        "Padang"
    ],
    "qs:name":"Padangbai",
    "qs:photos_9r":0,
    "qs:photos_sr":0,
    "qs:pop_sr":"0",
    "wd:wordcount":828,
    "wof:lang_x_official":[
        "ind"
    ],
    "wof:lang_x_spoken":[
        "ind",
        "eng"
    ],
    "wof:name":"Padangbai",
    "wof:placetype":"locality",
    "wof:population":0
},
  "geometry": {"coordinates":[115.5072,-8.5317],"type":"Point"}
}