{
  "type": "Feature",
  "properties": {
    "gn:admin1_code":"8",
    "gn:asciiname":"Penanggungan",
    "gn:country_code":"ID",
    "gn:dem":20,
    "gn:feature_class":"P",
    "gn:feature_code":"PPL",
    "gn:name":"Penanggungan",
    "gn:population":0,
    "gn:timezone":"Asia/Jakarta",
    "iso:country":"ID",
    "name:ind_x_preferred":[
        "Penanggungan"
    ],
    "wof:name":"Penanggungan",
    "wof:placetype":"locality"
},
  "geometry": {"coordinates":[113.06570000000001,-7.6814],"type":"Point"}
}