{
  "type": "Feature",
  "properties": {
    "gn:admin1_code":"7.0",
    "gn:asciiname":"Bangunrejo",
    "gn:country_code":"ID",
    "gn:dem":81,
    "gn:feature_class":"P",
    "gn:feature_code":"PPLA4",
    "gn:name":"Bangunrejo",
    "gn:population":0,
    "gn:timezone":"Asia/Jakarta",
    "iso:country":"ID",
    "name:ind_x_preferred":[
        "Bangunrejo"
    ],
    "wof:name":"Bangunrejo",
    "wof:placetype":"locality"
},
  "geometry": {"coordinates":[111.515,-6.7751],"type":"Point"}
}