{
  "type": "Feature",
  "properties": {
    "gn:admin1_code":"8.0",
    "gn:asciiname":"Toro",
    "gn:country_code":"ID",
    "gn:dem":712,
    "gn:feature_class":"P",
    "gn:feature_code":"PPL",
    "gn:name":"Toro",
    "gn:population":0,
    "gn:timezone":"Asia/Jakarta",
    "iso:country":"ID",
    "name:bre_x_preferred":[
        "Toro"
    ],
    "name:bul_x_preferred":[
        "\u0422\u043e\u0440\u043e"
    ],
    "name:cat_x_preferred":[
        "Toro"
    ],
    "name:ceb_x_preferred":[
        "Toro"
    ],
    "name:ces_x_preferred":[
        "Toro"
    ],
    "name:deu_x_preferred":[
        "Toro"
    ],
    "name:epo_x_preferred":[
        "Toro"
    ],
    "name:eus_x_preferred":[
        "Toro"
    ],
    "name:fin_x_preferred":[
        "Toro"
    ],
    "name:fra_x_preferred":[
        "Toro"
    ],
    "name:glg_x_preferred":[
        "Toro"
    ],
    "name:heb_x_preferred":[
        "\u05d8\u05d5\u05e8\u05d5"
    ],
    "name:hun_x_preferred":[
        "Toro"
    ],
    "name:ido_x_preferred":[
        "Toro"
    ],
    "name:ind_x_preferred":[
        "Toro"
    ],
    "name:ita_x_preferred":[
        "Toro"
    ],
    "name:jpn_x_preferred":[
        "\u30c8\u30ed"
    ],
    "name:nld_x_preferred":[
        "Toro"
    ],
    "name:pnb_x_preferred":[
        "\u0679\u0648\u0631\u0648"
    ],
    "name:pol_x_preferred":[
        "Toro"
    ],
    "name:por_x_preferred":[
        "Toro"
    ],
    "name:ron_x_preferred":[
        "Toro"
    ],
    "name:rus_x_preferred":[
        "\u0422\u043e\u0440\u043e"
    ],
    "name:scn_x_preferred":[
        "Toru"
    ],
    "name:spa_x_preferred":[
        "Toro"
    ],
    "name:srp_x_preferred":[
        "\u0422\u043e\u0440\u043e"
    ],
    "name:swe_x_preferred":[
        "Toro"
    ],
    "name:tgl_x_preferred":[
        "Toro"
    ],
    "name:ukr_x_preferred":[
        "\u0422\u043e\u0440\u043e"
    ],
    "name:war_x_preferred":[
        "Toro"
    ],
    "wof:name":"Toro",
    "wof:placetype":"locality"
},
  "geometry": {"coordinates":[111.75879999999999,-7.9491],"type":"Point"}
}