{
  "type": "Feature",
  "properties": {
    "gn:admin1_code":"26",
    "gn:asciiname":"Benteng",
    "gn:country_code":"ID",
    "gn:dem":3,
    "gn:feature_class":"P",
    "gn:feature_code":"PPL",
    "gn:name":"Benteng",
    "gn:population":0,
    "gn:timezone":"Asia/Jakarta",
    "iso:country":"ID",
    "name:ceb_x_preferred":[
        "Benteng"
    ],
    "name:ind_x_preferred":[
        "Benteng"
    ],
    "name:nld_x_preferred":[
        "Benteng"
    ],
    "name:swe_x_preferred":[
        "Benteng"
    ],
    "wof:name":"Benteng",
    "wof:placetype":"locality"
},
  "geometry": {"coordinates":[99.3027,3.421],"type":"Point"}
}