{
  "type": "Feature",
  "properties": {
    "gn:admin1_code":"18.0",
    "gn:asciiname":"Puuluda",
    "gn:country_code":"ID",
    "gn:dem":356,
    "gn:feature_class":"P",
    "gn:feature_code":"PPL",
    "gn:name":"Puuluda",
    "gn:population":0,
    "gn:timezone":"Asia/Makassar",
    "iso:country":"ID",
    "name:ind_x_preferred":[
        "Puuluda"
    ],
    "wof:name":"Puuluda",
    "wof:placetype":"locality"
},
  "geometry": {"coordinates":[119.4419,-9.6618],"type":"Point"}
}