{
  "type": "Feature",
  "properties": {
    "gn:admin1_code":"18.0",
    "gn:asciiname":"Kili",
    "gn:country_code":"ID",
    "gn:dem":225,
    "gn:feature_class":"P",
    "gn:feature_code":"PPL",
    "gn:name":"Kili",
    "gn:population":0,
    "gn:timezone":"Asia/Makassar",
    "iso:country":"ID",
    "name:ceb_x_preferred":[
        "Kili"
    ],
    "name:deu_x_preferred":[
        "Kili"
    ],
    "name:fin_x_preferred":[
        "Kili"
    ],
    "name:heb_x_preferred":[
        "\u05e7\u05d9\u05dc\u05d9"
    ],
    "name:hun_x_preferred":[
        "Kili"
    ],
    "name:ind_x_preferred":[
        "Kili"
    ],
    "name:pol_x_preferred":[
        "Kili"
    ],
    "name:spa_x_preferred":[
        "Kili"
    ],
    "name:swe_x_preferred":[
        "Kili"
    ],
    "wof:lang_x_official":[
        "ind"
    ],
    "wof:lang_x_spoken":[
        "ind",
        "eng"
    ],
    "wof:name":"Kili",
    "wof:placetype":"locality"
},
  "geometry": {"coordinates":[121.80119999999999,-10.5885],"type":"Point"}
}