{
  "type": "Feature",
  "properties": {
    "gn:admin1_code":"30",
    "gn:asciiname":"Lojipasar",
    "gn:country_code":"ID",
    "gn:dem":114,
    "gn:feature_class":"P",
    "gn:feature_code":"PPL",
    "gn:name":"Lojipasar",
    "gn:population":0,
    "gn:timezone":"Asia/Jakarta",
    "iso:country":"ID",
    "name:ind_x_preferred":[
        "Lojipasar"
    ],
    "wof:name":"Lojipasar",
    "wof:placetype":"locality"
},
  "geometry": {"coordinates":[107.23111000000002,-6.51611],"type":"Point"}
}