{
  "type": "Feature",
  "properties": {
    "gn:admin1_code":"8.0",
    "gn:asciiname":"Sodo",
    "gn:country_code":"ID",
    "gn:dem":740,
    "gn:feature_class":"P",
    "gn:feature_code":"PPL",
    "gn:name":"Sodo",
    "gn:population":0,
    "gn:timezone":"Asia/Jakarta",
    "iso:country":"ID",
    "name:ceb_x_preferred":[
        "Sodo"
    ],
    "name:deu_x_preferred":[
        "Soddo"
    ],
    "name:fra_x_preferred":[
        "Sodo"
    ],
    "name:heb_x_preferred":[
        "\u05e1\u05d5\u05d3\u05d5"
    ],
    "name:hrv_x_preferred":[
        "Sodo"
    ],
    "name:hun_x_preferred":[
        "Sodo"
    ],
    "name:ind_x_preferred":[
        "Sodo"
    ],
    "name:ita_x_preferred":[
        "Soddo"
    ],
    "name:jav_x_preferred":[
        "Sodo"
    ],
    "name:nld_x_preferred":[
        "Sodo"
    ],
    "name:pol_x_preferred":[
        "Soddo"
    ],
    "name:rus_x_preferred":[
        "\u0421\u043e\u0434\u0434\u043e"
    ],
    "name:srp_x_preferred":[
        "\u0421\u043e\u0434\u043e"
    ],
    "wof:lang_x_official":[
        "ind"
    ],
    "wof:lang_x_spoken":[
        "ind",
        "eng"
    ],
    "wof:name":"Sodo",
    "wof:placetype":"locality"
},
  "geometry": {"coordinates":[111.4726,-8.1784],"type":"Point"}
}