{
  "type": "Feature",
  "properties": {
    "gn:admin1_code":"21.0",
    "gn:asciiname":"Lenggetan",
    "gn:country_code":"ID",
    "gn:dem":-9999,
    "gn:feature_class":"P",
    "gn:feature_code":"PPL",
    "gn:name":"Lenggetan",
    "gn:population":0,
    "gn:timezone":"Asia/Makassar",
    "iso:country":"ID",
    "name:ind_x_preferred":[
        "Lenggetan"
    ],
    "wof:name":"Lenggetan",
    "wof:placetype":"locality"
},
  "geometry": {"coordinates":[123.057,-1.8094],"type":"Point"}
}