{
  "type": "Feature",
  "properties": {
    "gn:admin1_code":"8.0",
    "gn:asciiname":"Gajahbiru",
    "gn:country_code":"ID",
    "gn:dem":105,
    "gn:feature_class":"P",
    "gn:feature_code":"PPL",
    "gn:name":"Gajahbiru",
    "gn:population":0,
    "gn:timezone":"Asia/Jakarta",
    "iso:country":"ID",
    "name:ind_x_preferred":[
        "Gajahbiru"
    ],
    "wof:name":"Gajahbiru",
    "wof:placetype":"locality"
},
  "geometry": {"coordinates":[111.4421,-7.9463],"type":"Point"}
}