{
  "type": "Feature",
  "properties": {
    "gn:admin1_code":"18",
    "gn:asciiname":"Kengga",
    "gn:country_code":"ID",
    "gn:dem":410,
    "gn:feature_class":"P",
    "gn:feature_code":"PPLA4",
    "gn:name":"Kengga",
    "gn:population":0,
    "gn:timezone":"Asia/Makassar",
    "iso:country":"ID",
    "name:ind_x_preferred":[
        "Kengga"
    ],
    "wof:name":"Kengga",
    "wof:placetype":"locality"
},
  "geometry": {"coordinates":[121.71380000000001,-8.7596],"type":"Point"}
}