{
  "type": "Feature",
  "properties": {
    "gn:admin1_code":"1.0",
    "gn:asciiname":"Uten Pulo",
    "gn:country_code":"ID",
    "gn:dem":46,
    "gn:feature_class":"P",
    "gn:feature_code":"PPL",
    "gn:name":"Uten Pulo",
    "gn:population":0,
    "gn:timezone":"Asia/Jakarta",
    "iso:country":"ID",
    "name:ind_x_preferred":[
        "Uten Pulo"
    ],
    "name:und_x_variant":[
        "Oeteuenpoelo",
        "Uteunpulo",
        "Uteuenpulo"
    ],
    "wof:name":"Uten Pulo",
    "wof:placetype":"locality"
},
  "geometry": {"coordinates":[96.3544,4.273],"type":"Point"}
}