{
  "type": "Feature",
  "properties": {
    "gn:admin1_code":"7",
    "gn:asciiname":"Bruno Wetan",
    "gn:country_code":"ID",
    "gn:dem":215,
    "gn:feature_class":"P",
    "gn:feature_code":"PPL",
    "gn:name":"Bruno Wetan",
    "gn:population":0,
    "gn:timezone":"Asia/Jakarta",
    "iso:country":"ID",
    "name:ind_x_preferred":[
        "Bruno Wetan"
    ],
    "wof:name":"Bruno Wetan",
    "wof:placetype":"locality"
},
  "geometry": {"coordinates":[109.93222,-7.56889],"type":"Point"}
}