{
  "type": "Feature",
  "properties": {
    "gn:admin1_code":"30",
    "gn:asciiname":"Pulosari",
    "gn:country_code":"ID",
    "gn:dem":35,
    "gn:feature_class":"P",
    "gn:feature_code":"PPL",
    "gn:name":"Pulosari",
    "gn:population":0,
    "gn:timezone":"Asia/Jakarta",
    "iso:country":"ID",
    "name:ind_x_preferred":[
        "Pulosari"
    ],
    "wof:name":"Pulosari",
    "wof:placetype":"locality"
},
  "geometry": {"coordinates":[107.71666999999999,-6.4325],"type":"Point"}
}