{
  "type": "Feature",
  "properties": {
    "gn:admin1_code":"26",
    "gn:asciiname":"Bakaran Batu",
    "gn:country_code":"ID",
    "gn:dem":13,
    "gn:feature_class":"P",
    "gn:feature_code":"PPL",
    "gn:name":"Bakaran Batu",
    "gn:population":0,
    "gn:timezone":"Asia/Jakarta",
    "iso:country":"ID",
    "name:ind_x_preferred":[
        "Bakaran Batu"
    ],
    "wof:name":"Bakaran Batu",
    "wof:placetype":"locality"
},
  "geometry": {"coordinates":[98.86941,3.5715],"type":"Point"}
}