{
  "type": "Feature",
  "properties": {
    "gn:admin1_code":"30",
    "gn:asciiname":"Pasirtanjung",
    "gn:cc2":"ID",
    "gn:country_code":"ID",
    "gn:dem":15,
    "gn:feature_class":"P",
    "gn:feature_code":"PPL",
    "gn:name":"Pasirtanjung",
    "gn:population":0,
    "gn:timezone":"Asia/Jakarta",
    "iso:country":"ID",
    "name:und_x_variant":[
        "Tandjung",
        "Pasirtanjung"
    ],
    "wof:name":"Pasirtanjung",
    "wof:placetype":"locality"
},
  "geometry": {"coordinates":[106.38443999999998,-6.17944],"type":"Point"}
}