{
  "type": "Feature",
  "properties": {
    "gn:admin1_code":"8",
    "gn:asciiname":"Aristengah",
    "gn:country_code":"ID",
    "gn:dem":383,
    "gn:feature_class":"P",
    "gn:feature_code":"PPL",
    "gn:name":"Aristengah",
    "gn:population":0,
    "gn:timezone":"Asia/Jakarta",
    "iso:country":"ID",
    "name:ind_x_preferred":[
        "Aristengah"
    ],
    "wof:name":"Aristengah",
    "wof:placetype":"locality"
},
  "geometry": {"coordinates":[113.0754,-8.1506],"type":"Point"}
}