{
  "type": "Feature",
  "properties": {
    "gn:admin1_code":"30",
    "gn:asciiname":"Gunungtangkil Kulon",
    "gn:country_code":"ID",
    "gn:dem":193,
    "gn:feature_class":"P",
    "gn:feature_code":"PPL",
    "gn:name":"Gunungtangkil Kulon",
    "gn:population":0,
    "gn:timezone":"Asia/Jakarta",
    "iso:country":"ID",
    "name:ind_x_preferred":[
        "Gunungtangkil Kulon"
    ],
    "wof:name":"Gunungtangkil Kulon",
    "wof:placetype":"locality"
},
  "geometry": {"coordinates":[106.61278,-6.57056],"type":"Point"}
}