{
  "type": "Feature",
  "properties": {
    "gn:admin1_code":"38.0",
    "gn:asciiname":"Lagundi",
    "gn:country_code":"ID",
    "gn:dem":10,
    "gn:feature_class":"P",
    "gn:feature_code":"PPL",
    "gn:name":"Lagundi",
    "gn:population":0,
    "gn:timezone":"Asia/Makassar",
    "iso:country":"ID",
    "name:ind_x_preferred":[
        "Lagundi"
    ],
    "wof:name":"Lagundi",
    "wof:placetype":"locality"
},
  "geometry": {"coordinates":[121.0928,-7.3917],"type":"Point"}
}