{
  "type": "Feature",
  "properties": {
    "gn:admin1_code":"2",
    "gn:asciiname":"Banjar Temukuaya",
    "gn:country_code":"ID",
    "gn:dem":67,
    "gn:feature_class":"P",
    "gn:feature_code":"PPL",
    "gn:name":"Banjar Temukuaya",
    "gn:population":0,
    "gn:timezone":"Asia/Makassar",
    "iso:country":"ID",
    "name:ind_x_preferred":[
        "Banjar Temukuaya"
    ],
    "wof:name":"Banjar Temukuaya",
    "wof:placetype":"locality"
},
  "geometry": {"coordinates":[115.05029999999999,-8.5382],"type":"Point"}
}