{
  "type": "Feature",
  "properties": {
    "gn:admin1_code":"26",
    "gn:asciiname":"Tanjung Morawa B Empat",
    "gn:country_code":"ID",
    "gn:dem":19,
    "gn:feature_class":"P",
    "gn:feature_code":"PPL",
    "gn:name":"Tanjung Morawa B Empat",
    "gn:population":0,
    "gn:timezone":"Asia/Jakarta",
    "iso:country":"ID",
    "name:ind_x_preferred":[
        "Tanjung Morawa B Empat"
    ],
    "name:und_x_variant":[
        "Tanjungmorawa B 4"
    ],
    "wof:lang_x_official":[
        "ind"
    ],
    "wof:lang_x_spoken":[
        "ind",
        "eng"
    ],
    "wof:name":"Tanjung Morawa B Empat",
    "wof:placetype":"locality"
},
  "geometry": {"coordinates":[98.8146,3.5464],"type":"Point"}
}