{
  "type": "Feature",
  "properties": {
    "gn:admin1_code":"10",
    "gn:asciiname":"Kaneman",
    "gn:country_code":"ID",
    "gn:dem":33,
    "gn:feature_class":"P",
    "gn:feature_code":"PPL",
    "gn:name":"Kaneman",
    "gn:population":0,
    "gn:timezone":"Asia/Jakarta",
    "iso:country":"ID",
    "wof:name":"Kaneman",
    "wof:placetype":"locality"
},
  "geometry": {"coordinates":[110.38527999999999,-7.92722],"type":"Point"}
}