{
  "type": "Feature",
  "properties": {
    "gn:admin1_code":"17.0",
    "gn:asciiname":"Dasangelumpang",
    "gn:country_code":"ID",
    "gn:dem":101,
    "gn:feature_class":"P",
    "gn:feature_code":"PPL",
    "gn:name":"Dasangelumpang",
    "gn:population":0,
    "gn:timezone":"Asia/Makassar",
    "iso:country":"ID",
    "name:ind_x_preferred":[
        "Dasangelumpang"
    ],
    "wof:name":"Dasangelumpang",
    "wof:placetype":"locality"
},
  "geometry": {"coordinates":[116.36750000000001,-8.2436],"type":"Point"}
}