{
  "type": "Feature",
  "properties": {
    "gn:admin1_code":"7",
    "gn:asciiname":"Bleder",
    "gn:country_code":"ID",
    "gn:dem":24,
    "gn:feature_class":"P",
    "gn:feature_code":"PPL",
    "gn:name":"Bleder",
    "gn:population":0,
    "gn:timezone":"Asia/Jakarta",
    "iso:country":"ID",
    "name:ind_x_preferred":[
        "Bleder"
    ],
    "wof:name":"Bleder",
    "wof:placetype":"locality"
},
  "geometry": {"coordinates":[109.71810000000001,-6.9536],"type":"Point"}
}