{
  "type": "Feature",
  "properties": {
    "gn:admin1_code":"30",
    "gn:asciiname":"Jatironyok Dua",
    "gn:cc2":"ID",
    "gn:country_code":"ID",
    "gn:dem":87,
    "gn:feature_class":"P",
    "gn:feature_code":"PPL",
    "gn:name":"Jatironyok Dua",
    "gn:population":0,
    "gn:timezone":"Asia/Jakarta",
    "iso:country":"ID",
    "name:und_x_variant":[
        "Djatironjok 2",
        "Djatironjok Dua",
        "Jatironyok Dua"
    ],
    "wof:lang_x_official":[
        "ind"
    ],
    "wof:lang_x_spoken":[
        "ind",
        "eng"
    ],
    "wof:name":"Jatironyok Dua",
    "wof:placetype":"locality"
},
  "geometry": {"coordinates":[106.85472,-6.38472],"type":"Point"}
}