{
  "type": "Feature",
  "properties": {
    "gn:admin1_code":"17",
    "gn:asciiname":"Kombo",
    "gn:country_code":"ID",
    "gn:dem":420,
    "gn:feature_class":"P",
    "gn:feature_code":"PPL",
    "gn:name":"Kombo",
    "gn:population":0,
    "gn:timezone":"Asia/Makassar",
    "iso:country":"ID",
    "name:cat_x_preferred":[
        "Combo"
    ],
    "name:deu_x_preferred":[
        "Kombo"
    ],
    "name:ind_x_preferred":[
        "Kombo"
    ],
    "wof:lang_x_official":[
        "ind"
    ],
    "wof:lang_x_spoken":[
        "ind",
        "eng"
    ],
    "wof:name":"Kombo",
    "wof:placetype":"locality"
},
  "geometry": {"coordinates":[118.8574,-8.554],"type":"Point"}
}