{
  "type": "Feature",
  "properties": {
    "gn:admin1_code":"38.0",
    "gn:asciiname":"Lamikomiko",
    "gn:country_code":"ID",
    "gn:dem":6,
    "gn:feature_class":"P",
    "gn:feature_code":"PPL",
    "gn:name":"Lamikomiko",
    "gn:population":0,
    "gn:timezone":"Asia/Makassar",
    "iso:country":"ID",
    "name:ind_x_preferred":[
        "Lamikomiko"
    ],
    "wof:name":"Lamikomiko",
    "wof:placetype":"locality"
},
  "geometry": {"coordinates":[120.32729999999999,-2.8831],"type":"Point"}
}