{
  "type": "Feature",
  "properties": {
    "gn:admin1_code":"26",
    "gn:asciiname":"Rimaukayu",
    "gn:country_code":"ID",
    "gn:dem":213,
    "gn:feature_class":"P",
    "gn:feature_code":"PPL",
    "gn:name":"Rimaukayu",
    "gn:population":0,
    "gn:timezone":"Asia/Jakarta",
    "iso:country":"ID",
    "name:ind_x_preferred":[
        "Rimaukayu"
    ],
    "name:und_x_variant":[
        "Rimaukaju"
    ],
    "wof:name":"Rimaukayu",
    "wof:placetype":"locality"
},
  "geometry": {"coordinates":[98.3065,3.3989],"type":"Point"}
}