{
  "type": "Feature",
  "properties": {
    "gn:admin1_code":"8.0",
    "gn:asciiname":"Jatijejer Dua",
    "gn:country_code":"ID",
    "gn:dem":287,
    "gn:feature_class":"P",
    "gn:feature_code":"PPL",
    "gn:name":"Jatijejer Dua",
    "gn:population":0,
    "gn:timezone":"Asia/Jakarta",
    "iso:country":"ID",
    "name:ind_x_preferred":[
        "Jatijejer Dua"
    ],
    "name:und_x_variant":[
        "Djatidjedjer",
        "Jatijejer"
    ],
    "wof:name":"Jatijejer Dua",
    "wof:placetype":"locality"
},
  "geometry": {"coordinates":[112.5613,-7.5972],"type":"Point"}
}