{
  "type": "Feature",
  "properties": {
    "gn:admin1_code":"0.0",
    "gn:asciiname":"Cimenga",
    "gn:cc2":"ID",
    "gn:country_code":"ID",
    "gn:dem":491,
    "gn:feature_class":"P",
    "gn:feature_code":"PPL",
    "gn:name":"Cimenga",
    "gn:population":0,
    "gn:timezone":"Asia/Jakarta",
    "iso:country":"ID",
    "name:und_x_variant":[
        "Tjimenga",
        "Cimenga"
    ],
    "wof:name":"Cimenga",
    "wof:placetype":"locality"
},
  "geometry": {"coordinates":[108.38333,-7.06667],"type":"Point"}
}