{
  "type": "Feature",
  "properties": {
    "gn:admin1_code":"17.0",
    "gn:asciiname":"Legamba",
    "gn:country_code":"ID",
    "gn:dem":123,
    "gn:feature_class":"P",
    "gn:feature_code":"PPL",
    "gn:name":"Legamba",
    "gn:population":0,
    "gn:timezone":"Asia/Makassar",
    "iso:country":"ID",
    "name:ind_x_preferred":[
        "Legamba"
    ],
    "wof:name":"Legamba",
    "wof:placetype":"locality"
},
  "geometry": {"coordinates":[117.7577,-8.2567],"type":"Point"}
}