{
  "type": "Feature",
  "properties": {
    "gn:admin1_code":"30",
    "gn:asciiname":"Cipada Girang",
    "gn:country_code":"ID",
    "gn:dem":917,
    "gn:feature_class":"P",
    "gn:feature_code":"PPL",
    "gn:name":"Cipada Girang",
    "gn:population":0,
    "gn:timezone":"Asia/Jakarta",
    "iso:country":"ID",
    "name:ind_x_preferred":[
        "Cipada Girang"
    ],
    "name:und_x_variant":[
        "Tjipada-girang"
    ],
    "wof:lang_x_official":[
        "ind"
    ],
    "wof:lang_x_spoken":[
        "ind",
        "eng"
    ],
    "wof:name":"Cipada Girang",
    "wof:placetype":"locality"
},
  "geometry": {"coordinates":[107.49222,-6.77889],"type":"Point"}
}