{
  "type": "Feature",
  "properties": {
    "gn:admin1_code":"1",
    "gn:asciiname":"Cerihcot",
    "gn:country_code":"ID",
    "gn:dem":16,
    "gn:feature_class":"P",
    "gn:feature_code":"PPL",
    "gn:name":"Cerihcot",
    "gn:population":0,
    "gn:timezone":"Asia/Jakarta",
    "iso:country":"ID",
    "name:ind_x_preferred":[
        "Cerihcot"
    ],
    "wof:name":"Cerihcot",
    "wof:placetype":"locality"
},
  "geometry": {"coordinates":[95.9144,5.3477],"type":"Point"}
}