{
  "type": "Feature",
  "properties": {
    "gn:admin1_code":"8.0",
    "gn:asciiname":"Bugis",
    "gn:country_code":"ID",
    "gn:dem":141,
    "gn:feature_class":"P",
    "gn:feature_code":"PPLA4",
    "gn:name":"Bugis",
    "gn:population":0,
    "gn:timezone":"Asia/Jakarta",
    "iso:country":"ID",
    "name:ind_x_preferred":[
        "Bugis"
    ],
    "wof:name":"Bugis",
    "wof:placetype":"locality"
},
  "geometry": {"coordinates":[111.44410000000001,-8.0198],"type":"Point"}
}