{
  "type": "Feature",
  "properties": {
    "gn:admin1_code":"8",
    "gn:asciiname":"Pathi",
    "gn:country_code":"ID",
    "gn:dem":62,
    "gn:feature_class":"P",
    "gn:feature_code":"PPL",
    "gn:name":"Pathi",
    "gn:population":0,
    "gn:timezone":"Asia/Jakarta",
    "iso:country":"ID",
    "name:ind_x_preferred":[
        "Pathi"
    ],
    "wof:name":"Pathi",
    "wof:placetype":"locality"
},
  "geometry": {"coordinates":[112.10899999999999,-7.707],"type":"Point"}
}