{
  "type": "Feature",
  "properties": {
    "gn:admin1_code":"38.0",
    "gn:asciiname":"Kotaintan",
    "gn:country_code":"ID",
    "gn:dem":47,
    "gn:feature_class":"P",
    "gn:feature_code":"PPL",
    "gn:name":"Kotaintan",
    "gn:population":0,
    "gn:timezone":"Asia/Makassar",
    "iso:country":"ID",
    "name:ind_x_preferred":[
        "Kotaintan"
    ],
    "wof:name":"Kotaintan",
    "wof:placetype":"locality"
},
  "geometry": {"coordinates":[120.7358,-7.1282],"type":"Point"}
}