{
  "type": "Feature",
  "properties": {
    "gn:admin1_code":"26",
    "gn:asciiname":"Lebuhinggris",
    "gn:country_code":"ID",
    "gn:dem":406,
    "gn:feature_class":"P",
    "gn:feature_code":"PPL",
    "gn:name":"Lebuhinggris",
    "gn:population":0,
    "gn:timezone":"Asia/Jakarta",
    "iso:country":"ID",
    "name:ind_x_preferred":[
        "Lebuhinggris"
    ],
    "wof:name":"Lebuhinggris",
    "wof:placetype":"locality"
},
  "geometry": {"coordinates":[98.2756,2.4108],"type":"Point"}
}