{
  "type": "Feature",
  "properties": {
    "gn:admin1_code":"7",
    "gn:asciiname":"Laban",
    "gn:country_code":"ID",
    "gn:dem":450,
    "gn:feature_class":"P",
    "gn:feature_code":"PPL",
    "gn:name":"Laban",
    "gn:population":0,
    "gn:timezone":"Asia/Jakarta",
    "iso:country":"ID",
    "name:bel_x_preferred":[
        "\u041b\u0430\u0432\u0430\u043d"
    ],
    "name:ceb_x_preferred":[
        "Laban"
    ],
    "name:ces_x_preferred":[
        "Laban"
    ],
    "name:dan_x_preferred":[
        "Laban"
    ],
    "name:deu_x_preferred":[
        "Laban"
    ],
    "name:fra_x_preferred":[
        "Laban"
    ],
    "name:ind_x_preferred":[
        "Laban"
    ],
    "name:jpn_x_preferred":[
        "\u30e9\u30d0\u30f3"
    ],
    "name:nld_x_preferred":[
        "Laban"
    ],
    "name:rus_x_preferred":[
        "\u041b\u0430\u0432\u0430\u043d"
    ],
    "name:swe_x_preferred":[
        "Laban"
    ],
    "wof:name":"Laban",
    "wof:placetype":"locality"
},
  "geometry": {"coordinates":[110.03149999999999,-7.04],"type":"Point"}
}