{
  "type": "Feature",
  "properties": {
    "gn:admin1_code":"8.0",
    "gn:asciiname":"Tempel",
    "gn:country_code":"ID",
    "gn:dem":16,
    "gn:feature_class":"P",
    "gn:feature_code":"PPL",
    "gn:name":"Tempel",
    "gn:population":0,
    "gn:timezone":"Asia/Jakarta",
    "iso:country":"ID",
    "name:ceb_x_preferred":[
        "Tempel"
    ],
    "name:deu_x_preferred":[
        "Tempel"
    ],
    "name:fra_x_preferred":[
        "Tempel"
    ],
    "name:ind_x_preferred":[
        "Tempel"
    ],
    "name:jpn_x_preferred":[
        "\u30c6\u30f3\u30da\u30eb"
    ],
    "name:lav_x_preferred":[
        "Tempels"
    ],
    "name:nds_x_preferred":[
        "Tempel"
    ],
    "name:nld_x_preferred":[
        "Tempel"
    ],
    "name:pol_x_preferred":[
        "Tempel"
    ],
    "name:slk_x_preferred":[
        "Tempel"
    ],
    "name:swe_x_preferred":[
        "Tempel"
    ],
    "name:und_x_variant":[
        "Tempel Satu",
        "Tempel 1"
    ],
    "wof:lang_x_official":[
        "ind"
    ],
    "wof:lang_x_spoken":[
        "ind",
        "eng"
    ],
    "wof:name":"Tempel",
    "wof:placetype":"locality"
},
  "geometry": {"coordinates":[112.5796,-7.3854],"type":"Point"}
}