{
  "type": "Feature",
  "properties": {
    "gn:admin1_code":"34.0",
    "gn:asciiname":"Bubaa",
    "gn:country_code":"ID",
    "gn:dem":4,
    "gn:feature_class":"P",
    "gn:feature_code":"PPL",
    "gn:name":"Bubaa",
    "gn:population":0,
    "gn:timezone":"Asia/Makassar",
    "iso:country":"ID",
    "name:ind_x_preferred":[
        "Bubaa"
    ],
    "name:und_x_variant":[
        "Boeba\u00e4",
        "Boba\u00e4"
    ],
    "wof:name":"Bubaa",
    "wof:placetype":"locality"
},
  "geometry": {"coordinates":[122.5556,0.5158],"type":"Point"}
}