{
  "type": "Feature",
  "properties": {
    "gn:admin1_code":"18.0",
    "gn:asciiname":"Mirumairo",
    "gn:country_code":"ID",
    "gn:dem":646,
    "gn:feature_class":"P",
    "gn:feature_code":"PPL",
    "gn:name":"Mirumairo",
    "gn:population":0,
    "gn:timezone":"Asia/Makassar",
    "iso:country":"ID",
    "name:ind_x_preferred":[
        "Mirumairo"
    ],
    "wof:lang_x_official":[
        "ind"
    ],
    "wof:lang_x_spoken":[
        "ind",
        "eng"
    ],
    "wof:name":"Mirumairo",
    "wof:placetype":"locality"
},
  "geometry": {"coordinates":[119.3537,-9.553],"type":"Point"}
}