{
  "type": "Feature",
  "properties": {
    "gn:admin1_code":"30.0",
    "gn:asciiname":"Palangpang",
    "gn:country_code":"ID",
    "gn:dem":-5,
    "gn:feature_class":"P",
    "gn:feature_code":"PPL",
    "gn:name":"Palangpang",
    "gn:population":0,
    "gn:timezone":"Asia/Jakarta",
    "iso:country":"ID",
    "name:ind_x_preferred":[
        "Palangpang"
    ],
    "wof:name":"Palangpang",
    "wof:placetype":"locality"
},
  "geometry": {"coordinates":[106.4551,-7.187],"type":"Point"}
}