{
  "type": "Feature",
  "properties": {
    "gn:admin1_code":"7",
    "gn:asciiname":"Kajang",
    "gn:country_code":"ID",
    "gn:dem":449,
    "gn:feature_class":"P",
    "gn:feature_code":"PPL",
    "gn:name":"Kajang",
    "gn:population":0,
    "gn:timezone":"Asia/Jakarta",
    "iso:country":"ID",
    "name:ind_x_preferred":[
        "Kajang"
    ],
    "wof:name":"Kajang",
    "wof:placetype":"locality"
},
  "geometry": {"coordinates":[110.9049,-6.5543],"type":"Point"}
}