{
  "type": "Feature",
  "properties": {
    "gn:admin1_code":"5.0",
    "gn:asciiname":"Dusunbaru",
    "gn:country_code":"ID",
    "gn:dem":38,
    "gn:feature_class":"P",
    "gn:feature_code":"PPL",
    "gn:name":"Dusunbaru",
    "gn:population":0,
    "gn:timezone":"Asia/Jakarta",
    "iso:country":"ID",
    "name:ind_x_preferred":[
        "Dusunbaru"
    ],
    "wof:name":"Dusunbaru",
    "wof:placetype":"locality"
},
  "geometry": {"coordinates":[102.7467,-2.0362],"type":"Point"}
}