{
  "type": "Feature",
  "properties": {
    "gn:admin1_code":"30.0",
    "gn:asciiname":"Peundeuy",
    "gn:country_code":"ID",
    "gn:dem":653,
    "gn:feature_class":"P",
    "gn:feature_code":"PPL",
    "gn:name":"Peundeuy",
    "gn:population":0,
    "gn:timezone":"Asia/Jakarta",
    "iso:country":"ID",
    "name:ind_x_preferred":[
        "Peundeuy"
    ],
    "wof:name":"Peundeuy",
    "wof:placetype":"locality"
},
  "geometry": {"coordinates":[107.9575,-7.1413],"type":"Point"}
}