{
  "type": "Feature",
  "properties": {
    "gn:country":"ID",
    "gn:fcode":"PPLA3",
    "gn:pop":0,
    "iso:country":"ID",
    "name:ceb_x_preferred":[
        "Kediri"
    ],
    "name:deu_x_preferred":[
        "Kediri"
    ],
    "name:heb_x_preferred":[
        "\u05e7\u05d3\u05d9\u05e8\u05d9"
    ],
    "name:hun_x_preferred":[
        "Kediri"
    ],
    "name:ind_x_preferred":[
        "Kediri"
    ],
    "name:jav_x_preferred":[
        "Kadhiri"
    ],
    "name:kat_x_preferred":[
        "\u10d9\u10d4\u10d3\u10d8\u10e0\u10d8"
    ],
    "name:mal_x_preferred":[
        "\u0d15\u0d46\u0d26\u0d3f\u0d30\u0d3f"
    ],
    "name:mlg_x_preferred":[
        "Kediri"
    ],
    "name:nld_x_preferred":[
        "Kediri"
    ],
    "name:rus_x_preferred":[
        "\u041a\u0435\u0434\u0438\u0440\u0438"
    ],
    "name:swe_x_preferred":[
        "Kediri"
    ],
    "name:vie_x_preferred":[
        "Kediri"
    ],
    "qs:name":"Kediri",
    "qs:photos_9r":0,
    "qs:photos_sr":0,
    "qs:pop_sr":"0",
    "wd:wordcount":80,
    "wof:lang_x_official":[
        "ind"
    ],
    "wof:lang_x_spoken":[
        "ind",
        "eng"
    ],
    "wof:name":"Kediri",
    "wof:placetype":"locality",
    "wof:population":0
},
  "geometry": {"coordinates":[116.1515,-8.6343],"type":"Point"}
}