{
  "type": "Feature",
  "properties": {
    "gn:country":"ID",
    "gn:fcode":"PPLA3",
    "gn:pop":0,
    "iso:country":"ID",
    "name:ind_x_preferred":[
        "Kediri"
    ],
    "qs:name":"Kediri",
    "qs:photos_9r":0,
    "qs:photos_sr":0,
    "qs:pop_sr":"0",
    "wd:wordcount":80,
    "wof:name":"Kediri",
    "wof:placetype":"locality",
    "wof:population":0
},
  "geometry": {"coordinates":[116.1515,-8.6343],"type":"Point"}
}