{
  "type": "Feature",
  "properties": {
    "gn:admin1_code":"07",
    "gn:asciiname":"Glondong Dua",
    "gn:cc2":"ID",
    "gn:country_code":"ID",
    "gn:dem":222,
    "gn:feature_class":"P",
    "gn:feature_code":"PPL",
    "gn:name":"Glondong Dua",
    "gn:population":0,
    "gn:timezone":"Asia/Jakarta",
    "iso:country":"ID",
    "name:und_x_variant":[
        "Glondong 2",
        "Glondong Dua"
    ],
    "wof:name":"Glondong Dua",
    "wof:placetype":"locality"
},
  "geometry": {"coordinates":[110.68111,-7.25528],"type":"Point"}
}