{
  "type": "Feature",
  "properties": {
    "gn:admin1_code":"08",
    "gn:asciiname":"Sooko",
    "gn:country_code":"ID",
    "gn:dem":51,
    "gn:feature_class":"P",
    "gn:feature_code":"PPL",
    "gn:name":"Sooko",
    "gn:population":0,
    "gn:timezone":"Asia/Jakarta",
    "iso:country":"ID",
    "name:ind_x_preferred":[
        "Sooko"
    ],
    "name:und_x_variant":[
        "Suka"
    ],
    "wof:name":"Sooko",
    "wof:placetype":"locality"
},
  "geometry": {"coordinates":[112.52030000000001,-7.3532],"type":"Point"}
}