{
  "type": "Feature",
  "properties": {
    "gn:admin1_code":"38",
    "gn:asciiname":"Marana",
    "gn:country_code":"ID",
    "gn:dem":5,
    "gn:feature_class":"P",
    "gn:feature_code":"PPL",
    "gn:name":"Marana",
    "gn:population":0,
    "gn:timezone":"Asia/Makassar",
    "iso:country":"ID",
    "name:ind_x_preferred":[
        "Marana"
    ],
    "wof:name":"Marana",
    "wof:placetype":"locality"
},
  "geometry": {"coordinates":[119.56189999999999,-4.9592],"type":"Point"}
}