{
  "type": "Feature",
  "properties": {
    "gn:admin1_code":"7.0",
    "gn:asciiname":"Cilempuyang",
    "gn:country_code":"ID",
    "gn:dem":43,
    "gn:feature_class":"P",
    "gn:feature_code":"PPLA4",
    "gn:name":"Cilempuyang",
    "gn:population":0,
    "gn:timezone":"Asia/Jakarta",
    "iso:country":"ID",
    "name:ind_x_preferred":[
        "Cilempuyang"
    ],
    "wof:name":"Cilempuyang",
    "wof:placetype":"locality"
},
  "geometry": {"coordinates":[108.83329999999999,-7.3421],"type":"Point"}
}