{
  "type": "Feature",
  "properties": {
    "gn:admin1_code":"30",
    "gn:asciiname":"Cicarita",
    "gn:country_code":"ID",
    "gn:dem":947,
    "gn:feature_class":"P",
    "gn:feature_code":"PPL",
    "gn:name":"Cicarita",
    "gn:population":0,
    "gn:timezone":"Asia/Jakarta",
    "iso:country":"ID",
    "name:ind_x_preferred":[
        "Cicarita"
    ],
    "name:und_x_variant":[
        "Tjitjarita"
    ],
    "wof:name":"Cicarita",
    "wof:placetype":"locality"
},
  "geometry": {"coordinates":[107.58583,-6.85444],"type":"Point"}
}