{
  "type": "Feature",
  "properties": {
    "gn:admin1_code":"30.0",
    "gn:asciiname":"Lengoremok",
    "gn:country_code":"ID",
    "gn:dem":23,
    "gn:feature_class":"P",
    "gn:feature_code":"PPL",
    "gn:name":"Lengoremok",
    "gn:population":0,
    "gn:timezone":"Asia/Jakarta",
    "iso:country":"ID",
    "name:ind_x_preferred":[
        "Lengoremok"
    ],
    "wof:name":"Lengoremok",
    "wof:placetype":"locality"
},
  "geometry": {"coordinates":[108.6117,-7.3502],"type":"Point"}
}