{
  "type": "Feature",
  "properties": {
    "gn:admin1_code":"18.0",
    "gn:asciiname":"Nangakeo",
    "gn:country_code":"ID",
    "gn:dem":21,
    "gn:feature_class":"P",
    "gn:feature_code":"PPLA4",
    "gn:name":"Nangakeo",
    "gn:population":0,
    "gn:timezone":"Asia/Makassar",
    "iso:country":"ID",
    "name:ind_x_preferred":[
        "Nangakeo"
    ],
    "wof:name":"Nangakeo",
    "wof:placetype":"locality"
},
  "geometry": {"coordinates":[121.5676,-8.7946],"type":"Point"}
}