{
  "type": "Feature",
  "properties": {
    "gn:admin1_code":"8.0",
    "gn:asciiname":"Medayun Lor",
    "gn:country_code":"ID",
    "gn:dem":23,
    "gn:feature_class":"P",
    "gn:feature_code":"PPL",
    "gn:name":"Medayun Lor",
    "gn:population":0,
    "gn:timezone":"Asia/Jakarta",
    "iso:country":"ID",
    "name:ind_x_preferred":[
        "Medayun Lor"
    ],
    "wof:name":"Medayun Lor",
    "wof:placetype":"locality"
},
  "geometry": {"coordinates":[111.97933,-7.18637],"type":"Point"}
}