{
  "type": "Feature",
  "properties": {
    "gn:admin1_code":"30",
    "gn:asciiname":"Cimuncang",
    "gn:cc2":"ID",
    "gn:country_code":"ID",
    "gn:dem":677,
    "gn:feature_class":"P",
    "gn:feature_code":"PPL",
    "gn:name":"Cimuncang",
    "gn:population":0,
    "gn:timezone":"Asia/Jakarta",
    "iso:country":"ID",
    "name:und_x_variant":[
        "Tjimuntjang",
        "Cimuncang"
    ],
    "wof:lang_x_official":[
        "ind"
    ],
    "wof:lang_x_spoken":[
        "ind",
        "eng"
    ],
    "wof:name":"Cimuncang",
    "wof:placetype":"locality"
},
  "geometry": {"coordinates":[107.65083,-7.02167],"type":"Point"}
}