{
  "type": "Feature",
  "properties": {
    "gn:admin1_code":"21",
    "gn:asciiname":"Bonebuya",
    "gn:country_code":"ID",
    "gn:dem":519,
    "gn:feature_class":"P",
    "gn:feature_code":"PPL",
    "gn:name":"Bonebuya",
    "gn:population":0,
    "gn:timezone":"Asia/Makassar",
    "iso:country":"ID",
    "name:ind_x_preferred":[
        "Bonebuya"
    ],
    "wof:name":"Bonebuya",
    "wof:placetype":"locality"
},
  "geometry": {"coordinates":[120.6925,-2.0674],"type":"Point"}
}