{
  "type": "Feature",
  "properties": {
    "gn:admin1_code":"26",
    "gn:asciiname":"Lumban Greja",
    "gn:country_code":"ID",
    "gn:dem":1222,
    "gn:feature_class":"P",
    "gn:feature_code":"PPL",
    "gn:name":"Lumban Greja",
    "gn:population":0,
    "gn:timezone":"Asia/Jakarta",
    "iso:country":"ID",
    "name:ind_x_preferred":[
        "Lumban Greja"
    ],
    "wof:name":"Lumban Greja",
    "wof:placetype":"locality"
},
  "geometry": {"coordinates":[99.10120999999999,1.97273],"type":"Point"}
}