{
  "type": "Feature",
  "properties": {
    "gn:admin1_code":"30.0",
    "gn:asciiname":"Curug Hilir",
    "gn:country_code":"ID",
    "gn:dem":279,
    "gn:feature_class":"P",
    "gn:feature_code":"PPL",
    "gn:name":"Curug Hilir",
    "gn:population":0,
    "gn:timezone":"Asia/Jakarta",
    "iso:country":"ID",
    "name:ind_x_preferred":[
        "Curug Hilir"
    ],
    "wof:name":"Curug Hilir",
    "wof:placetype":"locality"
},
  "geometry": {"coordinates":[106.6392,-7.2814],"type":"Point"}
}