{
  "type": "Feature",
  "properties": {
    "gn:admin1_code":"8.0",
    "gn:asciiname":"Bengkokomere",
    "gn:country_code":"ID",
    "gn:dem":159,
    "gn:feature_class":"P",
    "gn:feature_code":"PPL",
    "gn:name":"Bengkokomere",
    "gn:population":0,
    "gn:timezone":"Asia/Jakarta",
    "iso:country":"ID",
    "name:ind_x_preferred":[
        "Bengkokomere"
    ],
    "wof:name":"Bengkokomere",
    "wof:placetype":"locality"
},
  "geometry": {"coordinates":[114.05,-7.8199],"type":"Point"}
}