{
  "type": "Feature",
  "properties": {
    "gn:country":"ID",
    "gn:fcode":"PPL",
    "gn:pop":0,
    "iso:country":"ID",
    "name:ara_x_preferred":[
        "\u062a\u064a\u0645\u0628\u0648\u0631\u0627"
    ],
    "name:ast_x_preferred":[
        "Tenpura"
    ],
    "name:cat_x_preferred":[
        "tempura"
    ],
    "name:ces_x_preferred":[
        "Tempura"
    ],
    "name:dan_x_preferred":[
        "Tempura"
    ],
    "name:deu_x_preferred":[
        "Tempura"
    ],
    "name:ell_x_preferred":[
        "\u03a4\u03b5\u03bc\u03c0\u03bf\u03cd\u03c1\u03b1"
    ],
    "name:eng_x_preferred":[
        "tempura"
    ],
    "name:epo_x_preferred":[
        "tempuro"
    ],
    "name:fas_x_preferred":[
        "\u062a\u0645\u067e\u0648\u0631\u0627"
    ],
    "name:fin_x_preferred":[
        "Tempura"
    ],
    "name:fra_x_preferred":[
        "tempura"
    ],
    "name:heb_x_preferred":[
        "\u05d8\u05de\u05e4\u05d5\u05e8\u05d4"
    ],
    "name:hrv_x_preferred":[
        "Tenpura"
    ],
    "name:hun_x_preferred":[
        "Tempura"
    ],
    "name:ind_x_preferred":[
        "Tempuran"
    ],
    "name:ind_x_variant":[
        "Tempura"
    ],
    "name:ita_x_preferred":[
        "tempura"
    ],
    "name:jav_x_preferred":[
        "Tempura"
    ],
    "name:jpn_x_preferred":[
        "\u5929\u3077\u3089"
    ],
    "name:kaz_x_preferred":[
        "\u0422\u0435\u043c\u043f\u0443\u0440\u0430"
    ],
    "name:kor_x_preferred":[
        "\ub374\ud478\ub77c"
    ],
    "name:mkd_x_preferred":[
        "\u0442\u0435\u043c\u043f\u0443\u0440\u0430"
    ],
    "name:msa_x_preferred":[
        "Tempura"
    ],
    "name:nan_x_preferred":[
        "Ten-p\u00fa-lah"
    ],
    "name:nep_x_preferred":[
        "\u0924\u0930\u0941\u0935\u093e"
    ],
    "name:nld_x_preferred":[
        "Tempura"
    ],
    "name:nob_x_preferred":[
        "Tempura"
    ],
    "name:pol_x_preferred":[
        "Tempura"
    ],
    "name:por_x_preferred":[
        "tempura"
    ],
    "name:rus_x_preferred":[
        "\u0422\u044d\u043c\u043f\u0443\u0440\u0430"
    ],
    "name:spa_x_preferred":[
        "tempura"
    ],
    "name:swe_x_preferred":[
        "Tempura"
    ],
    "name:tgl_x_preferred":[
        "Tempura"
    ],
    "name:tha_x_preferred":[
        "\u0e40\u0e17\u0e47\u0e21\u0e1b\u0e39\u0e23\u0e30"
    ],
    "name:tur_x_preferred":[
        "Tempura"
    ],
    "name:ukr_x_preferred":[
        "\u0422\u0435\u043c\u043f\u0443\u0440\u0430"
    ],
    "name:vie_x_preferred":[
        "Tempura"
    ],
    "name:wuu_x_preferred":[
        "\u5929\u5987\u7f57"
    ],
    "name:yue_x_preferred":[
        "\u5929\u9ea9\u7f85"
    ],
    "name:zho_x_preferred":[
        "\u5929\u5a66\u7f85"
    ],
    "qs:name":"Tempura",
    "qs:name_adm0":"Indonesia",
    "qs:name_adm1":"Jawa Barat",
    "qs:photos_9r":0,
    "qs:photos_sr":0,
    "qs:placetype":"Town",
    "qs:pop_sr":"0",
    "wd:wordcount":1830,
    "wof:name":"Tempura",
    "wof:placetype":"locality",
    "wof:population":0
},
  "geometry": {"coordinates":[107.12667,-6.43611],"type":"Point"}
}