{
  "type": "Feature",
  "properties": {
    "gn:admin1_code":"18.0",
    "gn:asciiname":"Rekamade",
    "gn:country_code":"ID",
    "gn:dem":235,
    "gn:feature_class":"P",
    "gn:feature_code":"PPL",
    "gn:name":"Rekamade",
    "gn:population":0,
    "gn:timezone":"Asia/Makassar",
    "iso:country":"ID",
    "name:ind_x_preferred":[
        "Rekamade"
    ],
    "wof:name":"Rekamade",
    "wof:placetype":"locality"
},
  "geometry": {"coordinates":[121.6973,-8.304],"type":"Point"}
}