{
  "type": "Feature",
  "properties": {
    "gn:admin1_code":"18.0",
    "gn:asciiname":"Patamanunu",
    "gn:country_code":"ID",
    "gn:dem":198,
    "gn:feature_class":"P",
    "gn:feature_code":"PPL",
    "gn:name":"Patamanunu",
    "gn:population":0,
    "gn:timezone":"Asia/Makassar",
    "iso:country":"ID",
    "name:ind_x_preferred":[
        "Patamanunu"
    ],
    "wof:name":"Patamanunu",
    "wof:placetype":"locality"
},
  "geometry": {"coordinates":[119.3082,-9.7225],"type":"Point"}
}