{
  "type": "Feature",
  "properties": {
    "gn:admin1_code":"30.0",
    "gn:asciiname":"Cukanggaleuh",
    "gn:country_code":"ID",
    "gn:dem":329,
    "gn:feature_class":"P",
    "gn:feature_code":"PPL",
    "gn:name":"Cukanggaleuh",
    "gn:population":0,
    "gn:timezone":"Asia/Jakarta",
    "iso:country":"ID",
    "name:ind_x_preferred":[
        "Cukanggaleuh"
    ],
    "wof:name":"Cukanggaleuh",
    "wof:placetype":"locality"
},
  "geometry": {"coordinates":[107.0347,-7.2884],"type":"Point"}
}