{
  "type": "Feature",
  "properties": {
    "gn:admin1_code":"21.0",
    "gn:asciiname":"Bangkalan",
    "gn:country_code":"ID",
    "gn:dem":7,
    "gn:feature_class":"P",
    "gn:feature_code":"PPL",
    "gn:name":"Bangkalan",
    "gn:population":0,
    "gn:timezone":"Asia/Makassar",
    "iso:country":"ID",
    "name:ind_x_preferred":[
        "Bangkalan"
    ],
    "name:jav_x_preferred":[
        "Bangkalan"
    ],
    "name:mlg_x_preferred":[
        "Bangkalan"
    ],
    "name:nld_x_preferred":[
        "Bangkalan"
    ],
    "wof:lang_x_official":[
        "ind"
    ],
    "wof:lang_x_spoken":[
        "ind",
        "eng"
    ],
    "wof:name":"Bangkalan",
    "wof:placetype":"locality"
},
  "geometry": {"coordinates":[123.16459999999999,-1.1508],"type":"Point"}
}