{
  "type": "Feature",
  "properties": {
    "gn:admin1_code":"30",
    "gn:asciiname":"Sijan",
    "gn:country_code":"ID",
    "gn:dem":36,
    "gn:feature_class":"P",
    "gn:feature_code":"PPL",
    "gn:name":"Sijan",
    "gn:population":0,
    "gn:timezone":"Asia/Jakarta",
    "iso:country":"ID",
    "name:ceb_x_preferred":[
        "Sijan"
    ],
    "name:ind_x_preferred":[
        "Sijan"
    ],
    "name:rus_x_preferred":[
        "\u0428\u0438\u044f\u043d"
    ],
    "name:swe_x_preferred":[
        "Sijan"
    ],
    "name:ukr_x_preferred":[
        "\u0428\u0438\u044f\u043d"
    ],
    "wof:name":"Sijan",
    "wof:placetype":"locality"
},
  "geometry": {"coordinates":[107.93528000000001,-6.51472],"type":"Point"}
}