{
  "type": "Feature",
  "properties": {
    "gn:admin1_code":"38.0",
    "gn:asciiname":"Bunbun",
    "gn:country_code":"ID",
    "gn:dem":635,
    "gn:feature_class":"P",
    "gn:feature_code":"PPL",
    "gn:name":"Bunbun",
    "gn:population":0,
    "gn:timezone":"Asia/Makassar",
    "iso:country":"ID",
    "name:ind_x_preferred":[
        "Bunbun"
    ],
    "wof:name":"Bunbun",
    "wof:placetype":"locality"
},
  "geometry": {"coordinates":[119.89960000000001,-3.3224],"type":"Point"}
}