{
  "type": "Feature",
  "properties": {
    "gn:admin1_code":"8.0",
    "gn:asciiname":"Karkar",
    "gn:country_code":"ID",
    "gn:dem":290,
    "gn:feature_class":"P",
    "gn:feature_code":"PPL",
    "gn:name":"Karkar",
    "gn:population":0,
    "gn:timezone":"Asia/Jakarta",
    "iso:country":"ID",
    "name:ceb_x_preferred":[
        "Karkar"
    ],
    "name:fra_x_preferred":[
        "Karkar"
    ],
    "name:ind_x_preferred":[
        "Karkar"
    ],
    "name:ita_x_preferred":[
        "Karkar"
    ],
    "name:pol_x_preferred":[
        "Karkar"
    ],
    "name:swe_x_preferred":[
        "Karkar"
    ],
    "wof:lang_x_official":[
        "ind"
    ],
    "wof:lang_x_spoken":[
        "ind",
        "eng"
    ],
    "wof:name":"Karkar",
    "wof:placetype":"locality"
},
  "geometry": {"coordinates":[113.5401,-7.055],"type":"Point"}
}