{
  "type": "Feature",
  "properties": {
    "gn:admin1_code":"8.0",
    "gn:asciiname":"Karkar",
    "gn:country_code":"ID",
    "gn:dem":290,
    "gn:feature_class":"P",
    "gn:feature_code":"PPL",
    "gn:name":"Karkar",
    "gn:population":0,
    "gn:timezone":"Asia/Jakarta",
    "iso:country":"ID",
    "name:ara_x_preferred":[
        "\u0643\u0631\u0643\u0631"
    ],
    "name:ben_x_preferred":[
        "\u0995\u09be\u09b0\u0995\u09be\u09b0"
    ],
    "name:ceb_x_preferred":[
        "Karkar"
    ],
    "name:deu_x_preferred":[
        "Karkar"
    ],
    "name:ell_x_preferred":[
        "\u039a\u03b1\u03c1\u03ba\u03ac\u03c1"
    ],
    "name:eng_x_preferred":[
        "Karkar"
    ],
    "name:fas_x_preferred":[
        "\u06a9\u0627\u0631\u06a9\u0627\u0631"
    ],
    "name:fra_x_preferred":[
        "Dchar Karkar"
    ],
    "name:fra_x_variant":[
        "Karkar"
    ],
    "name:heb_x_preferred":[
        "\u05d4\u05d0\u05d9 \u05e7\u05e8\u05e7\u05d0\u05e8"
    ],
    "name:hin_x_preferred":[
        "\u0915\u0930\u0915\u0930"
    ],
    "name:hun_x_preferred":[
        "Karkar"
    ],
    "name:ind_x_preferred":[
        "Karkar"
    ],
    "name:ita_x_preferred":[
        "Karkar"
    ],
    "name:jpn_x_preferred":[
        "\u30ab\u30eb\u30ab\u30eb\u5cf6"
    ],
    "name:kor_x_preferred":[
        "\uce74\ub974\uce74\ub974"
    ],
    "name:nld_x_preferred":[
        "Karkar"
    ],
    "name:pol_x_preferred":[
        "Karkar"
    ],
    "name:por_x_preferred":[
        "Karkar"
    ],
    "name:rus_x_preferred":[
        "\u043e\u0441\u0442\u0440\u043e\u0432 \u041a\u0430\u043a\u0440\u043a\u0430\u0440"
    ],
    "name:spa_x_preferred":[
        "Karkar"
    ],
    "name:swe_x_preferred":[
        "Karkar"
    ],
    "name:tur_x_preferred":[
        "Karkar"
    ],
    "name:ukr_x_preferred":[
        "\u041a\u0430\u0440\u043a\u0430\u0440"
    ],
    "name:urd_x_preferred":[
        "\u06a9\u0627\u0631\u06a9\u0627\u0631"
    ],
    "name:vie_x_preferred":[
        "\u0110\u1ea3o Karkar"
    ],
    "name:zho_cn_x_preferred":[
        "\u5361\u5c14\u5361\u5c14\u5c9b"
    ],
    "name:zho_tw_x_preferred":[
        "\u5361\u723e\u5361\u723e\u5cf6"
    ],
    "wof:lang_x_official":[
        "ind"
    ],
    "wof:lang_x_spoken":[
        "ind",
        "eng"
    ],
    "wof:name":"Karkar",
    "wof:placetype":"locality"
},
  "geometry": {"coordinates":[113.5401,-7.055],"type":"Point"}
}