{
  "type": "Feature",
  "properties": {
    "gn:admin1_code":"18",
    "gn:asciiname":"Dapajami",
    "gn:country_code":"ID",
    "gn:dem":418,
    "gn:feature_class":"P",
    "gn:feature_code":"PPL",
    "gn:name":"Dapajami",
    "gn:population":0,
    "gn:timezone":"Asia/Makassar",
    "iso:country":"ID",
    "name:ind_x_preferred":[
        "Dapajami"
    ],
    "wof:name":"Dapajami",
    "wof:placetype":"locality"
},
  "geometry": {"coordinates":[120.1146,-9.6341],"type":"Point"}
}