{
  "type": "Feature",
  "properties": {
    "gn:admin1_code":"30",
    "gn:asciiname":"Kukun",
    "gn:country_code":"ID",
    "gn:dem":18,
    "gn:feature_class":"P",
    "gn:feature_code":"PPL",
    "gn:name":"Kukun",
    "gn:population":0,
    "gn:timezone":"Asia/Jakarta",
    "iso:country":"ID",
    "name:ind_x_preferred":[
        "Kukun"
    ],
    "wof:name":"Kukun",
    "wof:placetype":"locality"
},
  "geometry": {"coordinates":[107.28167000000001,-6.33917],"type":"Point"}
}