{
  "type": "Feature",
  "properties": {
    "gn:admin1_code":"05",
    "gn:asciiname":"Pulauairhitam",
    "gn:country_code":"ID",
    "gn:dem":3,
    "gn:feature_class":"P",
    "gn:feature_code":"PPL",
    "gn:name":"Pulauairhitam",
    "gn:population":0,
    "gn:timezone":"Asia/Jakarta",
    "iso:country":"ID",
    "name:ind_x_preferred":[
        "Pulauairhitam"
    ],
    "wof:name":"Pulauairhitam",
    "wof:placetype":"locality"
},
  "geometry": {"coordinates":[104.11982999999999,-1.24381],"type":"Point"}
}