{
  "type": "Feature",
  "properties": {
    "gn:admin1_code":"18.0",
    "gn:asciiname":"Homara Satu",
    "gn:country_code":"ID",
    "gn:dem":22,
    "gn:feature_class":"P",
    "gn:feature_code":"PPL",
    "gn:name":"Homara Satu",
    "gn:population":0,
    "gn:timezone":"Asia/Makassar",
    "iso:country":"ID",
    "name:ind_x_preferred":[
        "Homara Satu"
    ],
    "name:und_x_variant":[
        "Homara 1"
    ],
    "wof:name":"Homara Satu",
    "wof:placetype":"locality"
},
  "geometry": {"coordinates":[120.28660000000001,-9.6912],"type":"Point"}
}