{
  "type": "Feature",
  "properties": {
    "gn:admin1_code":"7.0",
    "gn:asciiname":"Pucungroto",
    "gn:country_code":"ID",
    "gn:dem":623,
    "gn:feature_class":"P",
    "gn:feature_code":"PPL",
    "gn:name":"Pucungroto",
    "gn:population":0,
    "gn:timezone":"Asia/Jakarta",
    "iso:country":"ID",
    "wof:name":"Pucungroto",
    "wof:placetype":"locality"
},
  "geometry": {"coordinates":[110.06305999999999,-7.51083],"type":"Point"}
}