{
  "type": "Feature",
  "properties": {
    "gn:admin1_code":"10",
    "gn:asciiname":"Kembangan",
    "gn:country_code":"ID",
    "gn:dem":32,
    "gn:feature_class":"P",
    "gn:feature_code":"PPL",
    "gn:name":"Kembangan",
    "gn:population":0,
    "gn:timezone":"Asia/Jakarta",
    "iso:country":"ID",
    "name:ceb_x_preferred":[
        "Kembangan"
    ],
    "name:ind_x_preferred":[
        "Kembangan"
    ],
    "name:nld_x_preferred":[
        "Kembangan"
    ],
    "name:swe_x_preferred":[
        "Kembangan"
    ],
    "wof:name":"Kembangan",
    "wof:placetype":"locality"
},
  "geometry": {"coordinates":[110.31332999999999,-7.94083],"type":"Point"}
}