{
  "type": "Feature",
  "properties": {
    "gn:admin1_code":"18.0",
    "gn:asciiname":"Wiri",
    "gn:country_code":"ID",
    "gn:dem":19,
    "gn:feature_class":"P",
    "gn:feature_code":"PPL",
    "gn:name":"Wiri",
    "gn:population":0,
    "gn:timezone":"Asia/Makassar",
    "iso:country":"ID",
    "name:ind_x_preferred":[
        "Wiri"
    ],
    "name:sco_x_preferred":[
        "Wiri"
    ],
    "wof:name":"Wiri",
    "wof:placetype":"locality"
},
  "geometry": {"coordinates":[120.62139999999999,-10.2124],"type":"Point"}
}