{
  "type": "Feature",
  "properties": {
    "gn:admin1_code":"26",
    "gn:asciiname":"Aek Korsik",
    "gn:country_code":"ID",
    "gn:dem":31,
    "gn:feature_class":"P",
    "gn:feature_code":"PPL",
    "gn:name":"Aek Korsik",
    "gn:population":0,
    "gn:timezone":"Asia/Jakarta",
    "iso:country":"ID",
    "name:ind_x_preferred":[
        "Aek Korsik"
    ],
    "wof:name":"Aek Korsik",
    "wof:placetype":"locality"
},
  "geometry": {"coordinates":[99.6656,2.6138],"type":"Point"}
}