{
  "type": "Feature",
  "properties": {
    "gn:admin1_code":"26.0",
    "gn:asciiname":"Huta Bolon",
    "gn:country_code":"ID",
    "gn:dem":1092,
    "gn:feature_class":"P",
    "gn:feature_code":"PPL",
    "gn:name":"Huta Bolon",
    "gn:population":0,
    "gn:timezone":"Asia/Jakarta",
    "iso:country":"ID",
    "name:ind_x_preferred":[
        "Huta Bolon"
    ],
    "wof:name":"Huta Bolon",
    "wof:placetype":"locality"
},
  "geometry": {"coordinates":[98.8639,2.6287],"type":"Point"}
}