{
  "type": "Feature",
  "properties": {
    "gn:admin1_code":"30",
    "gn:asciiname":"Imbangan",
    "gn:country_code":"ID",
    "gn:dem":604,
    "gn:feature_class":"P",
    "gn:feature_code":"PPL",
    "gn:name":"Imbangan",
    "gn:population":0,
    "gn:timezone":"Asia/Jakarta",
    "iso:country":"ID",
    "name:ind_x_preferred":[
        "Imbangan"
    ],
    "wof:name":"Imbangan",
    "wof:placetype":"locality"
},
  "geometry": {"coordinates":[107.09833,-6.82083],"type":"Point"}
}