{
  "type": "Feature",
  "properties": {
    "gn:admin1_code":"30",
    "gn:asciiname":"Kebonkolot Timur",
    "gn:country_code":"ID",
    "gn:dem":90,
    "gn:feature_class":"P",
    "gn:feature_code":"PPL",
    "gn:name":"Kebonkolot Timur",
    "gn:population":0,
    "gn:timezone":"Asia/Jakarta",
    "iso:country":"ID",
    "name:ind_x_preferred":[
        "Kebonkolot Timur"
    ],
    "wof:name":"Kebonkolot Timur",
    "wof:placetype":"locality"
},
  "geometry": {"coordinates":[107.44556,-6.53417],"type":"Point"}
}