{
  "type": "Feature",
  "properties": {
    "gn:admin1_code":"36.0",
    "gn:asciiname":"Barito",
    "gn:country_code":"ID",
    "gn:dem":732,
    "gn:feature_class":"P",
    "gn:feature_code":"PPL",
    "gn:name":"Barito",
    "gn:population":0,
    "gn:timezone":"Asia/Jayapura",
    "iso:country":"ID",
    "name:ben_x_preferred":[
        "\u09ac\u09be\u09b0\u09bf\u09a4\u09cb"
    ],
    "name:deu_x_preferred":[
        "Barito"
    ],
    "name:ell_x_preferred":[
        "\u039c\u03c0\u03b1\u03c1\u03af\u03c4\u03bf"
    ],
    "name:fas_x_preferred":[
        "\u0628\u0627\u0631\u06cc\u062a\u0648"
    ],
    "name:fra_x_preferred":[
        "Barito"
    ],
    "name:heb_x_preferred":[
        "\u05d1\u05d0\u05e8\u05d9\u05d8\u05d5"
    ],
    "name:hun_x_preferred":[
        "Barito"
    ],
    "name:ind_x_preferred":[
        "Barito"
    ],
    "name:kor_x_preferred":[
        "\ubc14\ub9ac\ud1a0"
    ],
    "name:tur_x_preferred":[
        "Barito"
    ],
    "name:urd_x_preferred":[
        "\u0628\u0627\u0631\u06cc\u0679\u0648"
    ],
    "name:vie_x_preferred":[
        "S\u00f4ng Barito"
    ],
    "wof:lang_x_official":[
        "ind"
    ],
    "wof:lang_x_spoken":[
        "ind",
        "eng"
    ],
    "wof:name":"Barito",
    "wof:placetype":"locality"
},
  "geometry": {"coordinates":[139.68950000000001,-2.9548],"type":"Point"}
}