{
  "type": "Feature",
  "properties": {
    "gn:admin1_code":"36.0",
    "gn:asciiname":"Barito",
    "gn:country_code":"ID",
    "gn:dem":732,
    "gn:feature_class":"P",
    "gn:feature_code":"PPL",
    "gn:name":"Barito",
    "gn:population":0,
    "gn:timezone":"Asia/Jayapura",
    "iso:country":"ID",
    "name:ind_x_preferred":[
        "Barito"
    ],
    "wof:name":"Barito",
    "wof:placetype":"locality"
},
  "geometry": {"coordinates":[139.68950000000001,-2.9548],"type":"Point"}
}