{
  "type": "Feature",
  "properties": {
    "gn:admin1_code":"7",
    "gn:asciiname":"Andung",
    "gn:country_code":"ID",
    "gn:dem":120,
    "gn:feature_class":"P",
    "gn:feature_code":"PPL",
    "gn:name":"Andung",
    "gn:population":0,
    "gn:timezone":"Asia/Jakarta",
    "iso:country":"ID",
    "name:ind_x_preferred":[
        "Andung"
    ],
    "wof:name":"Andung",
    "wof:placetype":"locality"
},
  "geometry": {"coordinates":[109.76222,-7.64917],"type":"Point"}
}