{
  "type": "Feature",
  "properties": {
    "gn:admin1_code":"18.0",
    "gn:asciiname":"Balango",
    "gn:country_code":"ID",
    "gn:dem":50,
    "gn:feature_class":"P",
    "gn:feature_code":"PPL",
    "gn:name":"Balango",
    "gn:population":0,
    "gn:timezone":"Asia/Makassar",
    "iso:country":"ID",
    "name:ind_x_preferred":[
        "Balango"
    ],
    "wof:name":"Balango",
    "wof:placetype":"locality"
},
  "geometry": {"coordinates":[119.00620000000001,-9.612],"type":"Point"}
}