{
  "type": "Feature",
  "properties": {
    "gn:admin1_code":"17.0",
    "gn:asciiname":"Kondek",
    "gn:country_code":"ID",
    "gn:dem":167,
    "gn:feature_class":"P",
    "gn:feature_code":"PPL",
    "gn:name":"Kondek",
    "gn:population":0,
    "gn:timezone":"Asia/Makassar",
    "iso:country":"ID",
    "name:ind_x_preferred":[
        "Kondek"
    ],
    "wof:name":"Kondek",
    "wof:placetype":"locality"
},
  "geometry": {"coordinates":[116.48860000000001,-8.7148],"type":"Point"}
}