{
  "type": "Feature",
  "properties": {
    "gn:admin1_code":"30.0",
    "gn:asciiname":"Cipandak Dua",
    "gn:country_code":"ID",
    "gn:dem":409,
    "gn:feature_class":"P",
    "gn:feature_code":"PPL",
    "gn:name":"Cipandak Dua",
    "gn:population":0,
    "gn:timezone":"Asia/Jakarta",
    "iso:country":"ID",
    "name:ind_x_preferred":[
        "Cipandak Dua"
    ],
    "wof:lang_x_official":[
        "ind"
    ],
    "wof:lang_x_spoken":[
        "ind",
        "eng"
    ],
    "wof:name":"Cipandak Dua",
    "wof:placetype":"locality"
},
  "geometry": {"coordinates":[107.1499,-7.2626],"type":"Point"}
}