{
  "type": "Feature",
  "properties": {
    "gn:admin1_code":"26",
    "gn:asciiname":"Bajarongge",
    "gn:country_code":"ID",
    "gn:dem":59,
    "gn:feature_class":"P",
    "gn:feature_code":"PPL",
    "gn:name":"Bajarongge",
    "gn:population":0,
    "gn:timezone":"Asia/Jakarta",
    "iso:country":"ID",
    "name:ind_x_preferred":[
        "Bajarongge"
    ],
    "wof:name":"Bajarongge",
    "wof:placetype":"locality"
},
  "geometry": {"coordinates":[98.9696,3.3778],"type":"Point"}
}