{
  "type": "Feature",
  "properties": {
    "gn:admin1_code":"36.0",
    "gn:asciiname":"Ghaito",
    "gn:country_code":"ID",
    "gn:dem":8,
    "gn:feature_class":"P",
    "gn:feature_code":"PPL",
    "gn:name":"Ghaito",
    "gn:population":0,
    "gn:timezone":"Asia/Jayapura",
    "iso:country":"ID",
    "name:ind_x_preferred":[
        "Ghaito"
    ],
    "wof:name":"Ghaito",
    "wof:placetype":"locality"
},
  "geometry": {"coordinates":[139.23548,-6.25024],"type":"Point"}
}