{
  "type": "Feature",
  "properties": {
    "gn:admin1_code":"7.0",
    "gn:asciiname":"Kahuripan",
    "gn:country_code":"ID",
    "gn:dem":24,
    "gn:feature_class":"P",
    "gn:feature_code":"PPL",
    "gn:name":"Kahuripan",
    "gn:population":0,
    "gn:timezone":"Asia/Jakarta",
    "iso:country":"ID",
    "name:fra_x_preferred":[
        "Kahuripan"
    ],
    "name:ind_x_preferred":[
        "Kerajaan Kahuripan"
    ],
    "name:jav_x_preferred":[
        "Karajan Kahuripan"
    ],
    "name:sun_x_preferred":[
        "Karajaan Kahuripan"
    ],
    "name:swe_x_preferred":[
        "Kungariket Kahuripan"
    ],
    "name:zho_x_preferred":[
        "\u56fa\u91cc\u73ed"
    ],
    "wof:name":"Kahuripan",
    "wof:placetype":"locality"
},
  "geometry": {"coordinates":[110.02194,-7.80611],"type":"Point"}
}