{
  "type": "Feature",
  "properties": {
    "gn:admin1_code":"41",
    "gn:asciiname":"Kota",
    "gn:country_code":"ID",
    "gn:dem":537,
    "gn:feature_class":"P",
    "gn:feature_code":"PPL",
    "gn:name":"Kota",
    "gn:population":0,
    "gn:timezone":"Asia/Makassar",
    "iso:country":"ID",
    "name:bih_x_preferred":[
        "\u0915\u094b\u091f\u093e"
    ],
    "name:bpy_x_preferred":[
        "\u0995\u09cb\u09a4\u09be"
    ],
    "name:cat_x_preferred":[
        "Kota"
    ],
    "name:ceb_x_preferred":[
        "Kota"
    ],
    "name:deu_x_preferred":[
        "Kota"
    ],
    "name:fas_x_preferred":[
        "\u06a9\u0648\u062a\u0627"
    ],
    "name:fra_x_preferred":[
        "Kota"
    ],
    "name:hun_x_preferred":[
        "Kota"
    ],
    "name:ind_x_preferred":[
        "Kota"
    ],
    "name:ita_x_preferred":[
        "Kota"
    ],
    "name:lav_x_preferred":[
        "Kota"
    ],
    "name:msa_x_preferred":[
        "Kota"
    ],
    "name:new_x_preferred":[
        "\u0915\u094b\u0924\u093e"
    ],
    "name:nld_x_preferred":[
        "Kota"
    ],
    "name:pol_x_preferred":[
        "Kota"
    ],
    "name:pus_x_preferred":[
        "\u06a9\u0648\u062a\u0627"
    ],
    "name:rus_x_preferred":[
        "\u041a\u043e\u0442\u0430"
    ],
    "name:spa_x_preferred":[
        "Kota"
    ],
    "name:swe_x_preferred":[
        "Kota"
    ],
    "name:ukr_x_preferred":[
        "\u041a\u043e\u0442\u0430"
    ],
    "name:vie_x_preferred":[
        "Kota"
    ],
    "wof:lang_x_official":[
        "ind"
    ],
    "wof:lang_x_spoken":[
        "ind",
        "eng"
    ],
    "wof:name":"Kota",
    "wof:placetype":"locality"
},
  "geometry": {"coordinates":[118.962,-3.1826],"type":"Point"}
}