{
  "type": "Feature",
  "properties": {
    "gn:admin1_code":"08",
    "gn:asciiname":"Sumberayu",
    "gn:country_code":"ID",
    "gn:dem":421,
    "gn:feature_class":"P",
    "gn:feature_code":"PPL",
    "gn:name":"Sumberayu",
    "gn:population":0,
    "gn:timezone":"Asia/Jakarta",
    "iso:country":"ID",
    "name:ind_x_preferred":[
        "Sumberayu"
    ],
    "name:und_x_variant":[
        "Sumberaju 2",
        "Sumberayu Dua"
    ],
    "wof:lang_x_official":[
        "ind"
    ],
    "wof:lang_x_spoken":[
        "ind",
        "eng"
    ],
    "wof:name":"Sumberayu",
    "wof:placetype":"locality"
},
  "geometry": {"coordinates":[112.74135,-8.21291],"type":"Point"}
}