{
  "type": "Feature",
  "properties": {
    "gn:admin1_code":"31",
    "gn:asciiname":"Weerot",
    "gn:country_code":"ID",
    "gn:dem":24,
    "gn:feature_class":"P",
    "gn:feature_code":"PPL",
    "gn:name":"Weerot",
    "gn:population":0,
    "gn:timezone":"Asia/Makassar",
    "iso:country":"ID",
    "name:ind_x_preferred":[
        "Weerot"
    ],
    "name:und_x_variant":[
        "Werot"
    ],
    "wof:name":"Weerot",
    "wof:placetype":"locality"
},
  "geometry": {"coordinates":[124.99889,1.65101],"type":"Point"}
}