{
  "type": "Feature",
  "properties": {
    "gn:admin1_code":"14",
    "gn:asciiname":"Semarang",
    "gn:country_code":"ID",
    "gn:dem":23,
    "gn:feature_class":"P",
    "gn:feature_code":"PPL",
    "gn:name":"Semarang",
    "gn:population":0,
    "gn:timezone":"Asia/Makassar",
    "iso:country":"ID",
    "name:ind_x_preferred":[
        "Semarang"
    ],
    "wof:name":"Semarang",
    "wof:placetype":"locality"
},
  "geometry": {"coordinates":[116.8907,-1.1528],"type":"Point"}
}