{
  "type": "Feature",
  "properties": {
    "gn:admin1_code":"7.0",
    "gn:asciiname":"Juwen",
    "gn:country_code":"ID",
    "gn:dem":57,
    "gn:feature_class":"P",
    "gn:feature_code":"PPLA4",
    "gn:name":"Juwen",
    "gn:population":0,
    "gn:timezone":"Asia/Jakarta",
    "iso:country":"ID",
    "name:ind_x_preferred":[
        "Juwen"
    ],
    "wof:name":"Juwen",
    "wof:placetype":"locality"
},
  "geometry": {"coordinates":[111.5659,-6.7099],"type":"Point"}
}