{
  "type": "Feature",
  "properties": {
    "gn:admin1_code":"18.0",
    "gn:asciiname":"Denge",
    "gn:country_code":"ID",
    "gn:dem":501,
    "gn:feature_class":"P",
    "gn:feature_code":"PPL",
    "gn:name":"Denge",
    "gn:population":0,
    "gn:timezone":"Asia/Makassar",
    "iso:country":"ID",
    "name:ceb_x_preferred":[
        "Denge"
    ],
    "name:deu_x_preferred":[
        "Denge"
    ],
    "name:ind_x_preferred":[
        "Denge"
    ],
    "name:swe_x_preferred":[
        "Denge"
    ],
    "name:tur_x_preferred":[
        "Denge"
    ],
    "wof:lang_x_official":[
        "ind"
    ],
    "wof:lang_x_spoken":[
        "ind",
        "eng"
    ],
    "wof:name":"Denge",
    "wof:placetype":"locality"
},
  "geometry": {"coordinates":[120.30249999999999,-8.8068],"type":"Point"}
}