{
  "type": "Feature",
  "properties": {
    "gn:admin1_code":"38",
    "gn:asciiname":"Sunggumanai",
    "gn:country_code":"ID",
    "gn:dem":160,
    "gn:feature_class":"P",
    "gn:feature_code":"PPL",
    "gn:name":"Sunggumanai",
    "gn:population":0,
    "gn:timezone":"Asia/Makassar",
    "iso:country":"ID",
    "name:ind_x_preferred":[
        "Sunggumanai"
    ],
    "wof:name":"Sunggumanai",
    "wof:placetype":"locality"
},
  "geometry": {"coordinates":[119.7881,-5.5837],"type":"Point"}
}