{
  "type": "Feature",
  "properties": {
    "gn:admin1_code":"01",
    "gn:admin2_code":"1117",
    "gn:admin3_code":"8572026.0",
    "gn:asciiname":"Dsn. Sara Ate",
    "gn:country_code":"ID",
    "gn:dem":1542,
    "gn:feature_class":"P",
    "gn:feature_code":"PPL",
    "gn:name":"Dsn. Sara Ate",
    "gn:population":0,
    "gn:timezone":"Asia/Jakarta",
    "iso:country":"ID",
    "wof:name":"Dsn. Sara Ate",
    "wof:placetype":"locality"
},
  "geometry": {"coordinates":[96.91746999999999,4.81788],"type":"Point"}
}