{
  "type": "Feature",
  "properties": {
    "gn:country":"ID",
    "gn:fcode":"PPL",
    "gn:pop":0,
    "iso:country":"ID",
    "name:ind_x_preferred":[
        "Gerdu"
    ],
    "name:nld_x_preferred":[
        "Gerdu"
    ],
    "qs:name":"Gerdu",
    "qs:name_adm0":"Indonesia",
    "qs:name_adm1":"Provinsi Jawa Tengah",
    "qs:photos":152,
    "qs:photos_1k":31,
    "qs:photos_9k":1,
    "qs:photos_9r":4,
    "qs:photos_all":152,
    "qs:photos_sr":4,
    "qs:placetype":"Town",
    "qs:pop_sr":"0",
    "wd:wordcount":33,
    "wof:lang_x_official":[
        "ind"
    ],
    "wof:lang_x_spoken":[
        "ind",
        "eng"
    ],
    "wof:name":"Gerdu",
    "wof:placetype":"locality",
    "wof:population":0
},
  "geometry": {"coordinates":[111.0975,-7.63361],"type":"Point"}
}