{
  "type": "Feature",
  "properties": {
    "gn:admin1_code":"30",
    "gn:asciiname":"Kajangan",
    "gn:cc2":"ID",
    "gn:country_code":"ID",
    "gn:dem":8,
    "gn:feature_class":"P",
    "gn:feature_code":"PPL",
    "gn:name":"Kajangan",
    "gn:population":0,
    "gn:timezone":"Asia/Jakarta",
    "iso:country":"ID",
    "name:und_x_variant":[
        "Pekadjangan",
        "Pekajangan",
        "Kajangan"
    ],
    "wof:name":"Kajangan",
    "wof:placetype":"locality"
},
  "geometry": {"coordinates":[106.63417,-6.08111],"type":"Point"}
}