{
  "type": "Feature",
  "properties": {
    "gn:admin1_code":"33",
    "gn:asciiname":"Eurih",
    "gn:country_code":"ID",
    "gn:dem":29,
    "gn:feature_class":"P",
    "gn:feature_code":"PPL",
    "gn:name":"Eurih",
    "gn:population":0,
    "gn:timezone":"Asia/Jakarta",
    "iso:country":"ID",
    "name:ind_x_preferred":[
        "Eurih"
    ],
    "wof:name":"Eurih",
    "wof:placetype":"locality"
},
  "geometry": {"coordinates":[105.89530000000001,-6.0924],"type":"Point"}
}