{
  "type": "Feature",
  "properties": {
    "gn:admin1_code":"39.0",
    "gn:asciiname":"Winusi",
    "gn:country_code":"ID",
    "gn:dem":142,
    "gn:feature_class":"P",
    "gn:feature_code":"PPL",
    "gn:name":"Winusi",
    "gn:population":0,
    "gn:timezone":"Asia/Jayapura",
    "iso:country":"ID",
    "name:ind_x_preferred":[
        "Winusi"
    ],
    "wof:name":"Winusi",
    "wof:placetype":"locality"
},
  "geometry": {"coordinates":[133.30000000000001,-0.667],"type":"Point"}
}