{
  "type": "Feature",
  "properties": {
    "gn:admin1_code":"8",
    "gn:asciiname":"Ngepring",
    "gn:country_code":"ID",
    "gn:dem":1000,
    "gn:feature_class":"P",
    "gn:feature_code":"PPL",
    "gn:name":"Ngepring",
    "gn:population":0,
    "gn:timezone":"Asia/Jakarta",
    "iso:country":"ID",
    "name:ind_x_preferred":[
        "Ngepring"
    ],
    "wof:name":"Ngepring",
    "wof:placetype":"locality"
},
  "geometry": {"coordinates":[112.7921,-7.8957],"type":"Point"}
}