{
  "type": "Feature",
  "properties": {
    "gn:admin1_code":"7",
    "gn:asciiname":"Jumblang",
    "gn:country_code":"ID",
    "gn:dem":140,
    "gn:feature_class":"P",
    "gn:feature_code":"PPL",
    "gn:name":"Jumblang",
    "gn:population":0,
    "gn:timezone":"Asia/Jakarta",
    "iso:country":"ID",
    "name:ind_x_preferred":[
        "Jumblang"
    ],
    "wof:name":"Jumblang",
    "wof:placetype":"locality"
},
  "geometry": {"coordinates":[111.5913,-7.0103],"type":"Point"}
}