{
  "type": "Feature",
  "properties": {
    "gn:admin1_code":"36.0",
    "gn:asciiname":"Dedifu",
    "gn:country_code":"ID",
    "gn:dem":79,
    "gn:feature_class":"P",
    "gn:feature_code":"PPL",
    "gn:name":"Dedifu",
    "gn:population":0,
    "gn:timezone":"Asia/Jayapura",
    "iso:country":"ID",
    "name:ind_x_preferred":[
        "Dedifu"
    ],
    "name:und_x_variant":[
        "Dedifo",
        "Dedifoe",
        "Dedifu"
    ],
    "wof:name":"Dedifu",
    "wof:placetype":"locality"
},
  "geometry": {"coordinates":[135.83529999999999,-1.0399],"type":"Point"}
}