{
  "type": "Feature",
  "properties": {
    "gn:admin1_code":"24.0",
    "gn:asciiname":"Tanjungbalit",
    "gn:country_code":"ID",
    "gn:dem":85,
    "gn:feature_class":"P",
    "gn:feature_code":"PPL",
    "gn:name":"Tanjungbalit",
    "gn:population":0,
    "gn:timezone":"Asia/Jakarta",
    "iso:country":"ID",
    "name:ind_x_preferred":[
        "Tanjungbalit"
    ],
    "name:und_x_variant":[
        "Tandjoengbalik",
        "Tandjungbalik",
        "Tanjungbalik"
    ],
    "wof:lang_x_official":[
        "ind"
    ],
    "wof:lang_x_spoken":[
        "ind",
        "eng"
    ],
    "wof:name":"Tanjungbalit",
    "wof:placetype":"locality"
},
  "geometry": {"coordinates":[100.77419999999999,0.151],"type":"Point"}
}