{
  "type": "Feature",
  "properties": {
    "gn:admin1_code":"36.0",
    "gn:asciiname":"Sawendidori",
    "gn:country_code":"ID",
    "gn:dem":11,
    "gn:feature_class":"P",
    "gn:feature_code":"PPL",
    "gn:name":"Sawendidori",
    "gn:population":0,
    "gn:timezone":"Asia/Jayapura",
    "iso:country":"ID",
    "name:ind_x_preferred":[
        "Sawendidori"
    ],
    "name:und_x_variant":[
        "Sawendidor",
        "Sawendidori",
        "Suwendidori"
    ],
    "wof:lang_x_official":[
        "ind"
    ],
    "wof:lang_x_spoken":[
        "ind",
        "eng"
    ],
    "wof:name":"Sawendidori",
    "wof:placetype":"locality"
},
  "geometry": {"coordinates":[135.46534,-0.78787],"type":"Point"}
}