{
  "type": "Feature",
  "properties": {
    "gn:admin1_code":"30.0",
    "gn:asciiname":"Cikalapa",
    "gn:country_code":"ID",
    "gn:dem":31,
    "gn:feature_class":"P",
    "gn:feature_code":"PPL",
    "gn:name":"Cikalapa",
    "gn:population":0,
    "gn:timezone":"Asia/Jakarta",
    "iso:country":"ID",
    "name:ind_x_preferred":[
        "Cikalapa"
    ],
    "wof:name":"Cikalapa",
    "wof:placetype":"locality"
},
  "geometry": {"coordinates":[106.46469999999999,-7.3581],"type":"Point"}
}