{
  "type": "Feature",
  "properties": {
    "gn:admin1_code":"7",
    "gn:asciiname":"Susuk",
    "gn:country_code":"ID",
    "gn:dem":14,
    "gn:feature_class":"P",
    "gn:feature_code":"PPL",
    "gn:name":"Susuk",
    "gn:population":0,
    "gn:timezone":"Asia/Jakarta",
    "iso:country":"ID",
    "name:ind_x_preferred":[
        "Susuk"
    ],
    "wof:name":"Susuk",
    "wof:placetype":"locality"
},
  "geometry": {"coordinates":[109.94611,-7.8175],"type":"Point"}
}