{
  "type": "Feature",
  "properties": {
    "gn:admin1_code":"26",
    "gn:asciiname":"Timbang Langkat",
    "gn:country_code":"ID",
    "gn:dem":37,
    "gn:feature_class":"P",
    "gn:feature_code":"PPL",
    "gn:name":"Timbang Langkat",
    "gn:population":0,
    "gn:timezone":"Asia/Jakarta",
    "iso:country":"ID",
    "name:ind_x_preferred":[
        "Timbang Langkat"
    ],
    "wof:name":"Timbang Langkat",
    "wof:placetype":"locality"
},
  "geometry": {"coordinates":[98.4922,3.5966],"type":"Point"}
}