{
  "type": "Feature",
  "properties": {
    "gn:admin1_code":"8.0",
    "gn:asciiname":"Cobaan",
    "gn:country_code":"ID",
    "gn:dem":26,
    "gn:feature_class":"P",
    "gn:feature_code":"PPL",
    "gn:name":"Cobaan",
    "gn:population":0,
    "gn:timezone":"Asia/Jakarta",
    "iso:country":"ID",
    "name:ind_x_preferred":[
        "Cobaan"
    ],
    "wof:name":"Cobaan",
    "wof:placetype":"locality"
},
  "geometry": {"coordinates":[111.82980000000001,-7.114],"type":"Point"}
}