{
  "type": "Feature",
  "properties": {
    "gn:admin1_code":"07",
    "gn:asciiname":"Sukerejo",
    "gn:country_code":"ID",
    "gn:dem":129,
    "gn:feature_class":"P",
    "gn:feature_code":"PPL",
    "gn:name":"Sukerejo",
    "gn:population":0,
    "gn:timezone":"Asia/Jakarta",
    "iso:country":"ID",
    "wof:name":"Sukerejo",
    "wof:placetype":"locality"
},
  "geometry": {"coordinates":[110.60111000000001,-7.76167],"type":"Point"}
}