{
  "type": "Feature",
  "properties": {
    "gn:admin1_code":"26",
    "gn:asciiname":"Sosorsaba",
    "gn:country_code":"ID",
    "gn:dem":911,
    "gn:feature_class":"P",
    "gn:feature_code":"PPL",
    "gn:name":"Sosorsaba",
    "gn:population":0,
    "gn:timezone":"Asia/Jakarta",
    "iso:country":"ID",
    "name:ind_x_preferred":[
        "Sosorsaba"
    ],
    "name:und_x_variant":[
        "Sosorsaba 5"
    ],
    "wof:name":"Sosorsaba",
    "wof:placetype":"locality"
},
  "geometry": {"coordinates":[99.1237,2.4364],"type":"Point"}
}