{
  "type": "Feature",
  "properties": {
    "gn:admin1_code":"26",
    "gn:asciiname":"Pulerejo",
    "gn:country_code":"ID",
    "gn:dem":31,
    "gn:feature_class":"P",
    "gn:feature_code":"PPL",
    "gn:name":"Pulerejo",
    "gn:population":0,
    "gn:timezone":"Asia/Jakarta",
    "iso:country":"ID",
    "name:ind_x_preferred":[
        "Pulerejo"
    ],
    "wof:name":"Pulerejo",
    "wof:placetype":"locality"
},
  "geometry": {"coordinates":[98.55459999999999,3.5963],"type":"Point"}
}