{
  "type": "Feature",
  "properties": {
    "gn:admin1_code":"0.0",
    "gn:asciiname":"Pajaumbun",
    "gn:country_code":"ID",
    "gn:dem":645,
    "gn:feature_class":"P",
    "gn:feature_code":"PPL",
    "gn:name":"Pajaumbun",
    "gn:population":0,
    "gn:timezone":"Asia/Jakarta",
    "iso:country":"ID",
    "name:ind_x_preferred":[
        "Pajaumbun"
    ],
    "wof:lang_x_official":[
        "ind"
    ],
    "wof:lang_x_spoken":[
        "ind",
        "eng"
    ],
    "wof:name":"Pajaumbun",
    "wof:placetype":"locality"
},
  "geometry": {"coordinates":[99.45162000000001,1.97858],"type":"Point"}
}