{
  "type": "Feature",
  "properties": {
    "gn:admin1_code":"38",
    "gn:asciiname":"Papasangtiangotere",
    "gn:country_code":"ID",
    "gn:dem":288,
    "gn:feature_class":"P",
    "gn:feature_code":"PPL",
    "gn:name":"Papasangtiangotere",
    "gn:population":0,
    "gn:timezone":"Asia/Makassar",
    "iso:country":"ID",
    "name:ind_x_preferred":[
        "Papasangtiangotere"
    ],
    "wof:name":"Papasangtiangotere",
    "wof:placetype":"locality"
},
  "geometry": {"coordinates":[119.7547,-5.5182],"type":"Point"}
}