{
  "type": "Feature",
  "properties": {
    "gn:admin1_code":"8.0",
    "gn:asciiname":"Balongpanggang",
    "gn:country_code":"ID",
    "gn:dem":131,
    "gn:feature_class":"P",
    "gn:feature_code":"PPL",
    "gn:name":"Balongpanggang",
    "gn:population":0,
    "gn:timezone":"Asia/Jakarta",
    "iso:country":"ID",
    "name:ind_x_preferred":[
        "Balongpanggang"
    ],
    "wof:name":"Balongpanggang",
    "wof:placetype":"locality"
},
  "geometry": {"coordinates":[111.8207,-7.2988],"type":"Point"}
}