{
  "type": "Feature",
  "properties": {
    "gn:admin1_code":"33",
    "gn:asciiname":"Kubangkemiri",
    "gn:country_code":"ID",
    "gn:dem":19,
    "gn:feature_class":"P",
    "gn:feature_code":"PPL",
    "gn:name":"Kubangkemiri",
    "gn:population":0,
    "gn:timezone":"Asia/Jakarta",
    "iso:country":"ID",
    "name:ind_x_preferred":[
        "Kubangkemiri"
    ],
    "wof:name":"Kubangkemiri",
    "wof:placetype":"locality"
},
  "geometry": {"coordinates":[106.1918,-6.106],"type":"Point"}
}