{
  "type": "Feature",
  "properties": {
    "gn:admin1_code":"33.0",
    "gn:asciiname":"Langensari",
    "gn:country_code":"ID",
    "gn:dem":90,
    "gn:feature_class":"P",
    "gn:feature_code":"PPLA4",
    "gn:name":"Langensari",
    "gn:population":0,
    "gn:timezone":"Asia/Jakarta",
    "iso:country":"ID",
    "name:ind_x_preferred":[
        "Langensari"
    ],
    "wof:name":"Langensari",
    "wof:placetype":"locality"
},
  "geometry": {"coordinates":[105.9425,-6.4222],"type":"Point"}
}