{
  "type": "Feature",
  "properties": {
    "gn:admin1_code":"30",
    "gn:asciiname":"Cihalimun Kulon",
    "gn:country_code":"ID",
    "gn:dem":725,
    "gn:feature_class":"P",
    "gn:feature_code":"PPL",
    "gn:name":"Cihalimun Kulon",
    "gn:population":0,
    "gn:timezone":"Asia/Jakarta",
    "iso:country":"ID",
    "name:ind_x_preferred":[
        "Cihalimun Kulon"
    ],
    "name:und_x_variant":[
        "Tjihalimun",
        "Cihalimun"
    ],
    "wof:name":"Cihalimun Kulon",
    "wof:placetype":"locality"
},
  "geometry": {"coordinates":[107.43805999999999,-6.85361],"type":"Point"}
}