{
  "type": "Feature",
  "properties": {
    "gn:admin1_code":"0.0",
    "gn:asciiname":"Rua",
    "gn:cc2":"ID",
    "gn:country_code":"ID",
    "gn:dem":828,
    "gn:feature_class":"P",
    "gn:feature_code":"PPL",
    "gn:name":"Rua",
    "gn:population":0,
    "gn:timezone":"Asia/Makassar",
    "iso:country":"ID",
    "name:ceb_x_preferred":[
        "Rua"
    ],
    "name:deu_x_preferred":[
        "Rua"
    ],
    "name:fra_x_preferred":[
        "Rua"
    ],
    "name:nld_x_preferred":[
        "Rua"
    ],
    "name:por_x_preferred":[
        "Rua"
    ],
    "name:spa_x_preferred":[
        "Rua"
    ],
    "name:swe_x_preferred":[
        "Rua"
    ],
    "name:und_x_variant":[
        "Roea",
        "Rua"
    ],
    "wof:name":"Rua",
    "wof:placetype":"locality"
},
  "geometry": {"coordinates":[120.25,-8.78333],"type":"Point"}
}