{
  "type": "Feature",
  "properties": {
    "gn:admin1_code":"30",
    "gn:asciiname":"Jambudipa",
    "gn:country_code":"ID",
    "gn:dem":634,
    "gn:feature_class":"P",
    "gn:feature_code":"PPL",
    "gn:name":"Jambudipa",
    "gn:population":0,
    "gn:timezone":"Asia/Jakarta",
    "iso:country":"ID",
    "name:ind_x_preferred":[
        "Jambudipa"
    ],
    "wof:name":"Jambudipa",
    "wof:placetype":"locality"
},
  "geometry": {"coordinates":[107.06861000000001,-6.88],"type":"Point"}
}