{
  "type": "Feature",
  "properties": {
    "gn:admin1_code":"26",
    "gn:asciiname":"Bonggung",
    "gn:country_code":"ID",
    "gn:dem":1286,
    "gn:feature_class":"P",
    "gn:feature_code":"PPL",
    "gn:name":"Bonggung",
    "gn:population":0,
    "gn:timezone":"Asia/Jakarta",
    "iso:country":"ID",
    "name:ind_x_preferred":[
        "Bonggung"
    ],
    "wof:name":"Bonggung",
    "wof:placetype":"locality"
},
  "geometry": {"coordinates":[99.114,2.5399],"type":"Point"}
}