{
  "type": "Feature",
  "properties": {
    "gn:gn_country":"ID",
    "gn:gn_fcode":"ADM4",
    "gn:gn_pop":0,
    "iso:country":"ID",
    "name:ind_x_preferred":[
        "Kelurahan Pandeglang"
    ],
    "name:unk_x_variant":[
        "Pandeglang"
    ],
    "qs_pg:aaroncc":"ID",
    "qs_pg:gn_country":"ID",
    "qs_pg:gn_fcode":"ADM4",
    "qs_pg:gn_pop":0,
    "qs_pg:name":"Kelurahan Pandeglang",
    "qs_pg:photos_9r":0,
    "qs_pg:photos_sr":0,
    "qs_pg:pop_sr":0,
    "qs_pg:qs_pg_placetype":"localadmin",
    "wof:lang_x_official":[
        "ind"
    ],
    "wof:lang_x_spoken":[
        "ind",
        "eng"
    ],
    "wof:name":"Kelurahan Pandeglang",
    "wof:placetype":"localadmin"
},
  "geometry": {"coordinates":[106.10469999999999,-6.3047],"type":"Point"}
}