{
  "type": "Feature",
  "properties": {
    "gn:admin1_code":"38",
    "gn:asciiname":"Sangngisangngi",
    "gn:country_code":"ID",
    "gn:dem":17,
    "gn:feature_class":"P",
    "gn:feature_code":"PPL",
    "gn:name":"Sangngisangngi",
    "gn:population":0,
    "gn:timezone":"Asia/Makassar",
    "iso:country":"ID",
    "name:ind_x_preferred":[
        "Sangngisangngi"
    ],
    "wof:name":"Sangngisangngi",
    "wof:placetype":"locality"
},
  "geometry": {"coordinates":[119.55759999999999,-5.2097],"type":"Point"}
}