{
  "type": "Feature",
  "properties": {
    "gn:admin1_code":"7.0",
    "gn:asciiname":"Airmancur",
    "gn:country_code":"ID",
    "gn:dem":5,
    "gn:feature_class":"P",
    "gn:feature_code":"PPL",
    "gn:name":"Airmancur",
    "gn:population":0,
    "gn:timezone":"Asia/Jakarta",
    "iso:country":"ID",
    "name:ind_x_preferred":[
        "Airmancur"
    ],
    "wof:name":"Airmancur",
    "wof:placetype":"locality"
},
  "geometry": {"coordinates":[111.3882,-6.7034],"type":"Point"}
}