{
  "type": "Feature",
  "properties": {
    "gn:admin1_code":"7.0",
    "gn:asciiname":"Legok Kidul",
    "gn:country_code":"ID",
    "gn:dem":25,
    "gn:feature_class":"P",
    "gn:feature_code":"PPL",
    "gn:name":"Legok Kidul",
    "gn:population":0,
    "gn:timezone":"Asia/Jakarta",
    "iso:country":"ID",
    "name:ind_x_preferred":[
        "Legok Kidul"
    ],
    "wof:name":"Legok Kidul",
    "wof:placetype":"locality"
},
  "geometry": {"coordinates":[109.65333,-7.67528],"type":"Point"}
}