{
  "type": "Feature",
  "properties": {
    "gn:admin1_code":"7",
    "gn:asciiname":"Kaligung",
    "gn:country_code":"ID",
    "gn:dem":950,
    "gn:feature_class":"P",
    "gn:feature_code":"PPL",
    "gn:name":"Kaligung",
    "gn:population":0,
    "gn:timezone":"Asia/Jakarta",
    "iso:country":"ID",
    "name:ind_x_preferred":[
        "Kaligung"
    ],
    "wof:name":"Kaligung",
    "wof:placetype":"locality"
},
  "geometry": {"coordinates":[110.37111000000002,-7.20806],"type":"Point"}
}