{
  "type": "Feature",
  "properties": {
    "gn:admin1_code":"8",
    "gn:asciiname":"Angsanah",
    "gn:country_code":"ID",
    "gn:dem":73,
    "gn:feature_class":"P",
    "gn:feature_code":"PPL",
    "gn:name":"Angsanah",
    "gn:population":0,
    "gn:timezone":"Asia/Jakarta",
    "iso:country":"ID",
    "name:ind_x_preferred":[
        "Angsanah"
    ],
    "wof:name":"Angsanah",
    "wof:placetype":"locality"
},
  "geometry": {"coordinates":[113.093,-7.0532],"type":"Point"}
}