{
  "type": "Feature",
  "properties": {
    "gn:admin1_code":"30.0",
    "gn:asciiname":"Sirnajaya",
    "gn:country_code":"ID",
    "gn:dem":819,
    "gn:feature_class":"P",
    "gn:feature_code":"PPL",
    "gn:name":"Sirnajaya",
    "gn:population":0,
    "gn:timezone":"Asia/Jakarta",
    "iso:country":"ID",
    "name:ind_x_preferred":[
        "Sirnajaya"
    ],
    "wof:name":"Sirnajaya",
    "wof:placetype":"locality"
},
  "geometry": {"coordinates":[107.9799,-7.3948],"type":"Point"}
}