{
  "type": "Feature",
  "properties": {
    "gn:admin1_code":"17",
    "gn:asciiname":"Petetek",
    "gn:country_code":"ID",
    "gn:dem":45,
    "gn:feature_class":"P",
    "gn:feature_code":"PPL",
    "gn:name":"Petetek",
    "gn:population":0,
    "gn:timezone":"Asia/Makassar",
    "iso:country":"ID",
    "name:ind_x_preferred":[
        "Petetek"
    ],
    "wof:name":"Petetek",
    "wof:placetype":"locality"
},
  "geometry": {"coordinates":[116.18049999999999,-8.7535],"type":"Point"}
}