{
  "type": "Feature",
  "properties": {
    "gn:admin1_code":"41",
    "gn:asciiname":"Batubira",
    "gn:country_code":"ID",
    "gn:dem":19,
    "gn:feature_class":"P",
    "gn:feature_code":"PPL",
    "gn:name":"Batubira",
    "gn:population":0,
    "gn:timezone":"Asia/Makassar",
    "iso:country":"ID",
    "name:ind_x_preferred":[
        "Batubira"
    ],
    "wof:name":"Batubira",
    "wof:placetype":"locality"
},
  "geometry": {"coordinates":[118.8818,-2.644],"type":"Point"}
}