{
  "type": "Feature",
  "properties": {
    "gn:admin1_code":"31.0",
    "gn:asciiname":"Matole",
    "gn:country_code":"ID",
    "gn:dem":17,
    "gn:feature_class":"P",
    "gn:feature_code":"PPL",
    "gn:name":"Matole",
    "gn:population":0,
    "gn:timezone":"Asia/Makassar",
    "iso:country":"ID",
    "name:ind_x_preferred":[
        "Matole"
    ],
    "wof:name":"Matole",
    "wof:placetype":"locality"
},
  "geometry": {"coordinates":[125.45050000000001,2.6776],"type":"Point"}
}