{
  "type": "Feature",
  "properties": {
    "gn:admin1_code":"15.0",
    "gn:asciiname":"Bahadakh",
    "gn:country_code":"ID",
    "gn:dem":1046,
    "gn:feature_class":"P",
    "gn:feature_code":"PPL",
    "gn:name":"Bahadakh",
    "gn:population":0,
    "gn:timezone":"Asia/Jakarta",
    "iso:country":"ID",
    "name:ind_x_preferred":[
        "Bahadakh"
    ],
    "wof:name":"Bahadakh",
    "wof:placetype":"locality"
},
  "geometry": {"coordinates":[104.20694,-4.92755],"type":"Point"}
}