{
  "type": "Feature",
  "properties": {
    "gn:admin1_code":"40",
    "gn:asciiname":"Sanglang",
    "gn:country_code":"ID",
    "gn:dem":19,
    "gn:feature_class":"P",
    "gn:feature_code":"PPL",
    "gn:name":"Sanglang",
    "gn:population":0,
    "gn:timezone":"Asia/Jakarta",
    "iso:country":"ID",
    "name:epo_x_preferred":[
        "Sanglang"
    ],
    "name:ind_x_preferred":[
        "Sanglang"
    ],
    "name:msa_x_preferred":[
        "Sanglang"
    ],
    "wof:lang_x_official":[
        "ind"
    ],
    "wof:lang_x_spoken":[
        "ind",
        "eng"
    ],
    "wof:name":"Sanglang",
    "wof:placetype":"locality"
},
  "geometry": {"coordinates":[103.41497,0.77867],"type":"Point"}
}