{
  "type": "Feature",
  "properties": {
    "gn:admin1_code":"30",
    "gn:asciiname":"Bojongduren",
    "gn:country_code":"ID",
    "gn:dem":673,
    "gn:feature_class":"P",
    "gn:feature_code":"PPL",
    "gn:name":"Bojongduren",
    "gn:population":0,
    "gn:timezone":"Asia/Jakarta",
    "iso:country":"ID",
    "name:ind_x_preferred":[
        "Bojongduren"
    ],
    "wof:name":"Bojongduren",
    "wof:placetype":"locality"
},
  "geometry": {"coordinates":[106.92306000000001,-6.89083],"type":"Point"}
}