{
  "type": "Feature",
  "properties": {
    "gn:admin1_code":"30",
    "gn:asciiname":"Cidadap",
    "gn:country_code":"ID",
    "gn:dem":1305,
    "gn:feature_class":"P",
    "gn:feature_code":"PPL",
    "gn:name":"Cidadap",
    "gn:population":0,
    "gn:timezone":"Asia/Jakarta",
    "iso:country":"ID",
    "name:ind_x_preferred":[
        "Cidadap"
    ],
    "wof:name":"Cidadap",
    "wof:placetype":"locality"
},
  "geometry": {"coordinates":[107.38930000000001,-7.0702],"type":"Point"}
}