{
  "type": "Feature",
  "properties": {
    "gn:admin1_code":"2",
    "gn:asciiname":"Banjar Simpangan",
    "gn:country_code":"ID",
    "gn:dem":50,
    "gn:feature_class":"P",
    "gn:feature_code":"PPL",
    "gn:name":"Banjar Simpangan",
    "gn:population":0,
    "gn:timezone":"Asia/Makassar",
    "iso:country":"ID",
    "name:ind_x_preferred":[
        "Banjar Simpangan"
    ],
    "wof:name":"Banjar Simpangan",
    "wof:placetype":"locality"
},
  "geometry": {"coordinates":[115.10120000000001,-8.5806],"type":"Point"}
}