{
  "type": "Feature",
  "properties": {
    "gn:admin1_code":"18.0",
    "gn:asciiname":"Hautimu",
    "gn:country_code":"ID",
    "gn:dem":789,
    "gn:feature_class":"P",
    "gn:feature_code":"PPL",
    "gn:name":"Hautimu",
    "gn:population":0,
    "gn:timezone":"Asia/Makassar",
    "iso:country":"ID",
    "name:ind_x_preferred":[
        "Hautimu"
    ],
    "wof:name":"Hautimu",
    "wof:placetype":"locality"
},
  "geometry": {"coordinates":[124.43859999999999,-10.0492],"type":"Point"}
}