{
  "type": "Feature",
  "properties": {
    "gn:admin1_code":"18.0",
    "gn:asciiname":"Mana",
    "gn:country_code":"ID",
    "gn:dem":714,
    "gn:feature_class":"P",
    "gn:feature_code":"PPL",
    "gn:name":"Mana",
    "gn:population":0,
    "gn:timezone":"Asia/Makassar",
    "iso:country":"ID",
    "name:afr_x_preferred":[
        "Mana"
    ],
    "name:ara_x_preferred":[
        "\u0645\u0627\u0646\u0627"
    ],
    "name:ben_x_preferred":[
        "\u09ae\u09be\u09a8\u09be"
    ],
    "name:cat_x_preferred":[
        "Mana"
    ],
    "name:ces_x_preferred":[
        "Mana"
    ],
    "name:dan_x_preferred":[
        "Mana"
    ],
    "name:deu_x_preferred":[
        "Mana"
    ],
    "name:ell_x_preferred":[
        "\u039c\u03ac\u03bd\u03b1"
    ],
    "name:fas_x_preferred":[
        "\u0645\u0627\u0646\u0627"
    ],
    "name:fin_x_preferred":[
        "Mana"
    ],
    "name:fra_x_preferred":[
        "Mana"
    ],
    "name:heb_x_preferred":[
        "\u05de\u05e0\u05e4\u05d5\u05d5\u05d4"
    ],
    "name:hin_x_preferred":[
        "\u092e\u093e\u0928\u093e"
    ],
    "name:hun_x_preferred":[
        "Mana"
    ],
    "name:ind_x_preferred":[
        "Mana"
    ],
    "name:ita_x_preferred":[
        "Mana"
    ],
    "name:kor_x_preferred":[
        "\ub9c8\ub098"
    ],
    "name:lat_x_preferred":[
        "Mana"
    ],
    "name:lit_x_preferred":[
        "Magin\u0117 energija"
    ],
    "name:mkd_x_preferred":[
        "\u041c\u0430\u043d\u0430"
    ],
    "name:nld_x_preferred":[
        "Mana"
    ],
    "name:pol_x_preferred":[
        "Mana"
    ],
    "name:por_x_preferred":[
        "Mana"
    ],
    "name:rus_x_preferred":[
        "\u041c\u0430\u043d\u0430"
    ],
    "name:slk_x_preferred":[
        "Mana"
    ],
    "name:spa_x_preferred":[
        "Mana"
    ],
    "name:swe_x_preferred":[
        "Mana"
    ],
    "name:tur_x_preferred":[
        "Mana"
    ],
    "name:ukr_x_preferred":[
        "\u041c\u0430\u043d\u0430"
    ],
    "name:urd_x_preferred":[
        "\u0645\u0627\u0646\u0627"
    ],
    "name:vie_x_preferred":[
        "S\u00f4ng Mana"
    ],
    "wof:lang_x_official":[
        "ind"
    ],
    "wof:lang_x_spoken":[
        "ind",
        "eng"
    ],
    "wof:name":"Mana",
    "wof:placetype":"locality"
},
  "geometry": {"coordinates":[124.30070000000001,-9.895],"type":"Point"}
}