{
  "type": "Feature",
  "properties": {
    "gn:admin1_code":"14",
    "gn:asciiname":"Kertabuana",
    "gn:country_code":"ID",
    "gn:dem":10,
    "gn:feature_class":"P",
    "gn:feature_code":"PPL",
    "gn:name":"Kertabuana",
    "gn:population":0,
    "gn:timezone":"Asia/Makassar",
    "iso:country":"ID",
    "name:ind_x_preferred":[
        "Kertabuana"
    ],
    "wof:name":"Kertabuana",
    "wof:placetype":"locality"
},
  "geometry": {"coordinates":[117.1045,-0.3074],"type":"Point"}
}