{
  "type": "Feature",
  "properties": {
    "gn:admin1_code":"18.0",
    "gn:asciiname":"Janggameha",
    "gn:country_code":"ID",
    "gn:dem":567,
    "gn:feature_class":"P",
    "gn:feature_code":"PPL",
    "gn:name":"Janggameha",
    "gn:population":0,
    "gn:timezone":"Asia/Makassar",
    "iso:country":"ID",
    "name:ind_x_preferred":[
        "Janggameha"
    ],
    "wof:name":"Janggameha",
    "wof:placetype":"locality"
},
  "geometry": {"coordinates":[120.4452,-10.1355],"type":"Point"}
}