{
  "type": "Feature",
  "properties": {
    "gn:admin1_code":"26",
    "gn:asciiname":"Songkop",
    "gn:country_code":"ID",
    "gn:dem":75,
    "gn:feature_class":"P",
    "gn:feature_code":"PPL",
    "gn:name":"Songkop",
    "gn:population":0,
    "gn:timezone":"Asia/Jakarta",
    "iso:country":"ID",
    "name:ind_x_preferred":[
        "Songkop"
    ],
    "wof:name":"Songkop",
    "wof:placetype":"locality"
},
  "geometry": {"coordinates":[99.66030000000001,1.40047],"type":"Point"}
}