{
  "type": "Feature",
  "properties": {
    "gn:admin1_code":"38.0",
    "gn:asciiname":"Rama",
    "gn:country_code":"ID",
    "gn:dem":735,
    "gn:feature_class":"P",
    "gn:feature_code":"PPL",
    "gn:name":"Rama",
    "gn:population":0,
    "gn:timezone":"Asia/Makassar",
    "iso:country":"ID",
    "name:ind_x_preferred":[
        "Rama"
    ],
    "wof:name":"Rama",
    "wof:placetype":"locality"
},
  "geometry": {"coordinates":[120.04859999999999,-3.0813],"type":"Point"}
}