{
  "type": "Feature",
  "properties": {
    "gn:admin1_code":"38",
    "gn:asciiname":"Rantepasang",
    "gn:country_code":"ID",
    "gn:dem":28,
    "gn:feature_class":"P",
    "gn:feature_code":"PPL",
    "gn:name":"Rantepasang",
    "gn:population":0,
    "gn:timezone":"Asia/Makassar",
    "iso:country":"ID",
    "name:ind_x_preferred":[
        "Rantepasang"
    ],
    "wof:name":"Rantepasang",
    "wof:placetype":"locality"
},
  "geometry": {"coordinates":[120.2015,-2.703],"type":"Point"}
}