{
  "type": "Feature",
  "properties": {
    "gn:admin1_code":"38",
    "gn:asciiname":"Birupaya",
    "gn:country_code":"ID",
    "gn:dem":277,
    "gn:feature_class":"P",
    "gn:feature_code":"PPL",
    "gn:name":"Birupaya",
    "gn:population":0,
    "gn:timezone":"Asia/Makassar",
    "iso:country":"ID",
    "name:ind_x_preferred":[
        "Birupaya"
    ],
    "wof:name":"Birupaya",
    "wof:placetype":"locality"
},
  "geometry": {"coordinates":[119.6862,-5.3531],"type":"Point"}
}