{
  "type": "Feature",
  "properties": {
    "gn:country":"ID",
    "gn:fcode":"PPLA3",
    "gn:pop":50541,
    "iso:country":"ID",
    "name:ind_x_preferred":[
        "Kawalu"
    ],
    "name:unk_x_variant":[
        "Kawaloe"
    ],
    "qs:name":"Kawalu",
    "qs:photos_9r":0,
    "qs:photos_sr":0,
    "qs:pop_sr":"8",
    "wof:lang_x_official":[
        "ind"
    ],
    "wof:lang_x_spoken":[
        "ind",
        "eng"
    ],
    "wof:name":"Kawalu",
    "wof:placetype":"locality",
    "wof:population":50541
},
  "geometry": {"coordinates":[108.20820000000001,-7.3817],"type":"Point"}
}