{
  "type": "Feature",
  "properties": {
    "gn:admin1_code":"15.0",
    "gn:asciiname":"Burus Bawang",
    "gn:country_code":"ID",
    "gn:dem":16,
    "gn:feature_class":"P",
    "gn:feature_code":"PPL",
    "gn:name":"Burus Bawang",
    "gn:population":0,
    "gn:timezone":"Asia/Jakarta",
    "iso:country":"ID",
    "name:ind_x_preferred":[
        "Burus Bawang"
    ],
    "wof:name":"Burus Bawang",
    "wof:placetype":"locality"
},
  "geometry": {"coordinates":[104.95818,-4.41562],"type":"Point"}
}