{
  "type": "Feature",
  "properties": {
    "gn:admin1_code":"18",
    "gn:asciiname":"Kunion",
    "gn:country_code":"ID",
    "gn:dem":872,
    "gn:feature_class":"P",
    "gn:feature_code":"PPL",
    "gn:name":"Kunion",
    "gn:population":0,
    "gn:timezone":"Asia/Makassar",
    "iso:country":"ID",
    "wof:name":"Kunion",
    "wof:placetype":"locality"
},
  "geometry": {"coordinates":[124.53722,-9.35389],"type":"Point"}
}