{
  "type": "Feature",
  "properties": {
    "gn:admin1_code":"30",
    "gn:asciiname":"Nakula",
    "gn:country_code":"ID",
    "gn:dem":56,
    "gn:feature_class":"P",
    "gn:feature_code":"PPL",
    "gn:name":"Nakula",
    "gn:population":0,
    "gn:timezone":"Asia/Jakarta",
    "iso:country":"ID",
    "name:ben_x_preferred":[
        "\u09a8\u0995\u09c1\u09b2"
    ],
    "name:bre_x_preferred":[
        "Nakula"
    ],
    "name:fra_x_preferred":[
        "Nakula"
    ],
    "name:guj_x_preferred":[
        "\u0aa8\u0a95\u0ac1\u0ab2"
    ],
    "name:hin_x_preferred":[
        "\u0928\u0915\u0941\u0932"
    ],
    "name:ind_x_preferred":[
        "Nakula"
    ],
    "name:jav_x_preferred":[
        "Nakula"
    ],
    "name:jpn_x_preferred":[
        "\u30ca\u30af\u30e9"
    ],
    "name:kan_x_preferred":[
        "\u0ca8\u0c95\u0cc1\u0cb2"
    ],
    "name:mai_x_preferred":[
        "\u0928\u0915\u0941\u0932"
    ],
    "name:mal_x_preferred":[
        "\u0d28\u0d15\u0d41\u0d32\u0d7b"
    ],
    "name:mar_x_preferred":[
        "\u0928\u0915\u0941\u0932"
    ],
    "name:nep_x_preferred":[
        "\u0928\u0915\u0941\u0932"
    ],
    "name:new_x_preferred":[
        "\u0928\u0915\u0941\u0932"
    ],
    "name:rus_x_preferred":[
        "\u041d\u0430\u043a\u0443\u043b\u0430"
    ],
    "name:san_x_preferred":[
        "\u0928\u0915\u0941\u0932\u0903"
    ],
    "name:spa_x_preferred":[
        "Nakula"
    ],
    "name:sun_x_preferred":[
        "Nakula"
    ],
    "name:tam_x_preferred":[
        "\u0ba8\u0b95\u0bc1\u0bb2\u0ba9\u0bcd"
    ],
    "name:tel_x_preferred":[
        "\u0c28\u0c15\u0c41\u0c32\u0c41\u0c21\u0c41"
    ],
    "wof:name":"Nakula",
    "wof:placetype":"locality"
},
  "geometry": {"coordinates":[108.23,-6.76583],"type":"Point"}
}