{
  "type": "Feature",
  "properties": {
    "gn:admin1_code":"30",
    "gn:asciiname":"Nakula",
    "gn:country_code":"ID",
    "gn:dem":56,
    "gn:feature_class":"P",
    "gn:feature_code":"PPL",
    "gn:name":"Nakula",
    "gn:population":0,
    "gn:timezone":"Asia/Jakarta",
    "iso:country":"ID",
    "name:ind_x_preferred":[
        "Nakula"
    ],
    "wof:name":"Nakula",
    "wof:placetype":"locality"
},
  "geometry": {"coordinates":[108.23,-6.76583],"type":"Point"}
}