{
  "type": "Feature",
  "properties": {
    "gn:admin1_code":"30",
    "gn:asciiname":"Pejaten",
    "gn:country_code":"ID",
    "gn:dem":48,
    "gn:feature_class":"P",
    "gn:feature_code":"PPL",
    "gn:name":"Pejaten",
    "gn:population":0,
    "gn:timezone":"Asia/Jakarta",
    "iso:country":"ID",
    "name:ind_x_preferred":[
        "Pejaten"
    ],
    "wof:name":"Pejaten",
    "wof:placetype":"locality"
},
  "geometry": {"coordinates":[108.46972,-6.74694],"type":"Point"}
}