{
  "type": "Feature",
  "properties": {
    "gn:admin1_code":"30.0",
    "gn:asciiname":"Jurangmanggu",
    "gn:cc2":"ID",
    "gn:country_code":"ID",
    "gn:dem":33,
    "gn:feature_class":"P",
    "gn:feature_code":"PPL",
    "gn:name":"Jurangmanggu",
    "gn:population":0,
    "gn:timezone":"Asia/Jakarta",
    "iso:country":"ID",
    "name:und_x_variant":[
        "Djurangmanggu",
        "Djoerangmanggoe 1",
        "Jurangmanggu"
    ],
    "wof:lang_x_official":[
        "ind"
    ],
    "wof:lang_x_spoken":[
        "ind",
        "eng"
    ],
    "wof:name":"Jurangmanggu",
    "wof:placetype":"locality"
},
  "geometry": {"coordinates":[106.72889000000001,-6.27278],"type":"Point"}
}