{
  "type": "Feature",
  "properties": {
    "gn:admin1_code":"38",
    "gn:asciiname":"Soreang",
    "gn:country_code":"ID",
    "gn:dem":12,
    "gn:feature_class":"P",
    "gn:feature_code":"PPL",
    "gn:name":"Soreang",
    "gn:population":0,
    "gn:timezone":"Asia/Makassar",
    "iso:country":"ID",
    "name:fas_x_preferred":[
        "\u0633\u0648\u0631\u06cc\u0646\u06af"
    ],
    "name:fra_x_preferred":[
        "Soreang"
    ],
    "name:ind_x_preferred":[
        "Soreang"
    ],
    "name:jav_x_preferred":[
        "Sor\u00e8ang"
    ],
    "name:mlg_x_preferred":[
        "Soreang"
    ],
    "name:nor_x_preferred":[
        "Soreang"
    ],
    "name:sun_x_preferred":[
        "Sor\u00e9ang"
    ],
    "wof:name":"Soreang",
    "wof:placetype":"locality"
},
  "geometry": {"coordinates":[119.62130000000001,-4.469],"type":"Point"}
}