{
  "type": "Feature",
  "properties": {
    "gn:admin1_code":"8.0",
    "gn:asciiname":"Jlumbang",
    "gn:country_code":"ID",
    "gn:dem":210,
    "gn:feature_class":"P",
    "gn:feature_code":"PPL",
    "gn:name":"Jlumbang",
    "gn:population":0,
    "gn:timezone":"Asia/Jakarta",
    "iso:country":"ID",
    "name:ind_x_preferred":[
        "Jlumbang"
    ],
    "wof:name":"Jlumbang",
    "wof:placetype":"locality"
},
  "geometry": {"coordinates":[112.3022,-7.7307],"type":"Point"}
}