{
  "type": "Feature",
  "properties": {
    "gn:admin1_code":"34",
    "gn:asciiname":"Pasalaangi",
    "gn:country_code":"ID",
    "gn:dem":58,
    "gn:feature_class":"P",
    "gn:feature_code":"PPL",
    "gn:name":"Pasalaangi",
    "gn:population":0,
    "gn:timezone":"Asia/Makassar",
    "iso:country":"ID",
    "name:ind_x_preferred":[
        "Pasalaangi"
    ],
    "wof:name":"Pasalaangi",
    "wof:placetype":"locality"
},
  "geometry": {"coordinates":[122.65600000000001,0.6784],"type":"Point"}
}