{
  "type": "Feature",
  "properties": {
    "gn:admin1_code":"7",
    "gn:asciiname":"Menjanganan",
    "gn:country_code":"ID",
    "gn:dem":27,
    "gn:feature_class":"P",
    "gn:feature_code":"PPL",
    "gn:name":"Menjanganan",
    "gn:population":0,
    "gn:timezone":"Asia/Jakarta",
    "iso:country":"ID",
    "name:ind_x_preferred":[
        "Menjanganan"
    ],
    "wof:name":"Menjanganan",
    "wof:placetype":"locality"
},
  "geometry": {"coordinates":[110.8746,-7.0581],"type":"Point"}
}