{
  "type": "Feature",
  "properties": {
    "gn:admin1_code":"15.0",
    "gn:asciiname":"Umbulan Ratubagus",
    "gn:country_code":"ID",
    "gn:dem":21,
    "gn:feature_class":"P",
    "gn:feature_code":"PPL",
    "gn:name":"Umbulan Ratubagus",
    "gn:population":0,
    "gn:timezone":"Asia/Jakarta",
    "iso:country":"ID",
    "name:ind_x_preferred":[
        "Umbulan Ratubagus"
    ],
    "name:ind_x_variant":[
        "Umbulanratubagus"
    ],
    "wof:name":"Umbulan Ratubagus",
    "wof:placetype":"locality"
},
  "geometry": {"coordinates":[105.41256,-4.282],"type":"Point"}
}