{
  "type": "Feature",
  "properties": {
    "gn:admin1_code":"21",
    "gn:asciiname":"Bunga",
    "gn:country_code":"ID",
    "gn:dem":645,
    "gn:feature_class":"P",
    "gn:feature_code":"PPL",
    "gn:name":"Bunga",
    "gn:population":0,
    "gn:timezone":"Asia/Makassar",
    "iso:country":"ID",
    "name:ceb_x_preferred":[
        "Bunga"
    ],
    "name:ind_x_preferred":[
        "Bunga"
    ],
    "name:swe_x_preferred":[
        "Bunga"
    ],
    "name:tgl_x_preferred":[
        "Bunga"
    ],
    "wof:name":"Bunga",
    "wof:placetype":"locality"
},
  "geometry": {"coordinates":[120.0162,-1.1212],"type":"Point"}
}