{
  "type": "Feature",
  "properties": {
    "gn:admin1_code":"32.0",
    "gn:asciiname":"Jua-jua",
    "gn:country_code":"ID",
    "gn:dem":15,
    "gn:feature_class":"P",
    "gn:feature_code":"PPL",
    "gn:name":"Jua-jua",
    "gn:population":0,
    "gn:timezone":"Asia/Jakarta",
    "iso:country":"ID",
    "name:ind_x_preferred":[
        "Jua-jua"
    ],
    "name:ind_x_variant":[
        "Juo-juo",
        "Diuadiua",
        "Djoea Djoea"
    ],
    "wof:lang_x_official":[
        "ind"
    ],
    "wof:lang_x_spoken":[
        "ind",
        "eng"
    ],
    "wof:name":"Jua-jua",
    "wof:placetype":"locality"
},
  "geometry": {"coordinates":[104.83517000000001,-3.40115],"type":"Point"}
}