{
  "type": "Feature",
  "properties": {
    "gn:admin1_code":"33",
    "gn:asciiname":"Tanggul",
    "gn:country_code":"ID",
    "gn:dem":24,
    "gn:feature_class":"P",
    "gn:feature_code":"PPL",
    "gn:name":"Tanggul",
    "gn:population":0,
    "gn:timezone":"Asia/Jakarta",
    "iso:country":"ID",
    "name:ind_x_preferred":[
        "Tanggul"
    ],
    "wof:name":"Tanggul",
    "wof:placetype":"locality"
},
  "geometry": {"coordinates":[106.1647,-6.1092],"type":"Point"}
}