{
  "type": "Feature",
  "properties": {
    "gn:admin1_code":"0.0",
    "gn:asciiname":"Tanjakan",
    "gn:cc2":"ID",
    "gn:country_code":"ID",
    "gn:dem":7,
    "gn:feature_class":"P",
    "gn:feature_code":"PPL",
    "gn:name":"Tanjakan",
    "gn:population":0,
    "gn:timezone":"Asia/Jakarta",
    "iso:country":"ID",
    "name:und_x_variant":[
        "Tandjakan",
        "Tanjakan"
    ],
    "wof:name":"Tanjakan",
    "wof:placetype":"locality"
},
  "geometry": {"coordinates":[106.66639000000001,-6.10611],"type":"Point"}
}