{
  "type": "Feature",
  "properties": {
    "gn:admin1_code":"15.0",
    "gn:asciiname":"Umbulan Karangagung",
    "gn:country_code":"ID",
    "gn:dem":49,
    "gn:feature_class":"P",
    "gn:feature_code":"PPL",
    "gn:name":"Umbulan Karangagung",
    "gn:population":0,
    "gn:timezone":"Asia/Jakarta",
    "iso:country":"ID",
    "name:ind_x_preferred":[
        "Umbulan Karangagung"
    ],
    "name:und_x_variant":[
        "Umbulankarangagung"
    ],
    "wof:name":"Umbulan Karangagung",
    "wof:placetype":"locality"
},
  "geometry": {"coordinates":[104.51625,-4.48254],"type":"Point"}
}