{
  "type": "Feature",
  "properties": {
    "gn:admin1_code":"8",
    "gn:asciiname":"Sono",
    "gn:country_code":"ID",
    "gn:dem":263,
    "gn:feature_class":"P",
    "gn:feature_code":"PPL",
    "gn:name":"Sono",
    "gn:population":0,
    "gn:timezone":"Asia/Jakarta",
    "iso:country":"ID",
    "name:ind_x_preferred":[
        "Sono"
    ],
    "wof:name":"Sono",
    "wof:placetype":"locality"
},
  "geometry": {"coordinates":[111.35611000000002,-7.63639],"type":"Point"}
}