{
  "type": "Feature",
  "properties": {
    "gn:admin1_code":"30",
    "gn:asciiname":"Cirabu",
    "gn:country_code":"ID",
    "gn:dem":58,
    "gn:feature_class":"P",
    "gn:feature_code":"PPL",
    "gn:name":"Cirabu",
    "gn:population":0,
    "gn:timezone":"Asia/Jakarta",
    "iso:country":"ID",
    "name:ind_x_preferred":[
        "Cirabu"
    ],
    "wof:name":"Cirabu",
    "wof:placetype":"locality"
},
  "geometry": {"coordinates":[106.4978,-6.4039],"type":"Point"}
}