{
  "type": "Feature",
  "properties": {
    "gn:admin1_code":"1",
    "gn:asciiname":"Alue Batee",
    "gn:country_code":"ID",
    "gn:dem":13,
    "gn:feature_class":"P",
    "gn:feature_code":"PPL",
    "gn:name":"Alue Batee",
    "gn:population":0,
    "gn:timezone":"Asia/Jakarta",
    "iso:country":"ID",
    "name:ind_x_preferred":[
        "Alue Batee"
    ],
    "wof:name":"Alue Batee",
    "wof:placetype":"locality"
},
  "geometry": {"coordinates":[95.9796,4.3269],"type":"Point"}
}