{
  "type": "Feature",
  "properties": {
    "gn:admin1_code":"18.0",
    "gn:asciiname":"Bilesi",
    "gn:country_code":"ID",
    "gn:dem":259,
    "gn:feature_class":"P",
    "gn:feature_code":"PPL",
    "gn:name":"Bilesi",
    "gn:population":0,
    "gn:timezone":"Asia/Makassar",
    "iso:country":"ID",
    "name:ind_x_preferred":[
        "Bilesi"
    ],
    "wof:name":"Bilesi",
    "wof:placetype":"locality"
},
  "geometry": {"coordinates":[124.0528,-9.8576],"type":"Point"}
}