{
  "type": "Feature",
  "properties": {
    "gn:admin1_code":"7",
    "gn:asciiname":"Tawangsari",
    "gn:country_code":"ID",
    "gn:dem":264,
    "gn:feature_class":"P",
    "gn:feature_code":"PPL",
    "gn:name":"Tawangsari",
    "gn:population":0,
    "gn:timezone":"Asia/Jakarta",
    "iso:country":"ID",
    "name:ind_x_preferred":[
        "Tawangsari"
    ],
    "wof:name":"Tawangsari",
    "wof:placetype":"locality"
},
  "geometry": {"coordinates":[111.12056,-7.4975],"type":"Point"}
}