{
  "type": "Feature",
  "properties": {
    "gn:admin1_code":"24.0",
    "gn:asciiname":"Silabo",
    "gn:country_code":"ID",
    "gn:dem":305,
    "gn:feature_class":"P",
    "gn:feature_code":"PPL",
    "gn:name":"Silabo",
    "gn:population":0,
    "gn:timezone":"Asia/Jakarta",
    "iso:country":"ID",
    "name:ind_x_preferred":[
        "Silabo"
    ],
    "wof:name":"Silabo",
    "wof:placetype":"locality"
},
  "geometry": {"coordinates":[101.07380000000001,-0.6836],"type":"Point"}
}