{
  "type": "Feature",
  "properties": {
    "gn:admin1_code":"17",
    "gn:asciiname":"Batumulut",
    "gn:country_code":"ID",
    "gn:dem":80,
    "gn:feature_class":"P",
    "gn:feature_code":"PPL",
    "gn:name":"Batumulut",
    "gn:population":0,
    "gn:timezone":"Asia/Makassar",
    "iso:country":"ID",
    "name:ind_x_preferred":[
        "Batumulut"
    ],
    "wof:name":"Batumulut",
    "wof:placetype":"locality"
},
  "geometry": {"coordinates":[116.23220000000001,-8.7616],"type":"Point"}
}