{
  "type": "Feature",
  "properties": {
    "gn:admin1_code":"7.0",
    "gn:asciiname":"Budengan",
    "gn:country_code":"ID",
    "gn:dem":59,
    "gn:feature_class":"P",
    "gn:feature_code":"PPL",
    "gn:name":"Budengan",
    "gn:population":0,
    "gn:timezone":"Asia/Jakarta",
    "iso:country":"ID",
    "name:ind_x_preferred":[
        "Budengan"
    ],
    "wof:name":"Budengan",
    "wof:placetype":"locality"
},
  "geometry": {"coordinates":[111.17440000000001,-6.8553],"type":"Point"}
}