{
  "type": "Feature",
  "properties": {
    "gn:admin1_code":"7.0",
    "gn:asciiname":"Cibodas",
    "gn:country_code":"ID",
    "gn:dem":63,
    "gn:feature_class":"P",
    "gn:feature_code":"PPL",
    "gn:name":"Cibodas",
    "gn:population":0,
    "gn:timezone":"Asia/Jakarta",
    "iso:country":"ID",
    "name:ind_x_preferred":[
        "Cibodas"
    ],
    "wof:name":"Cibodas",
    "wof:placetype":"locality"
},
  "geometry": {"coordinates":[109.06638999999998,-7.45028],"type":"Point"}
}