{
  "type": "Feature",
  "properties": {
    "gn:admin1_code":"1.0",
    "gn:asciiname":"Lubuk Badak",
    "gn:country_code":"ID",
    "gn:dem":29,
    "gn:feature_class":"P",
    "gn:feature_code":"PPL",
    "gn:name":"Lubuk Badak",
    "gn:population":0,
    "gn:timezone":"Asia/Jakarta",
    "iso:country":"ID",
    "name:ind_x_preferred":[
        "Lubuk Badak"
    ],
    "wof:name":"Lubuk Badak",
    "wof:placetype":"locality"
},
  "geometry": {"coordinates":[97.211,4.9491],"type":"Point"}
}