{
  "type": "Feature",
  "properties": {
    "gn:admin1_code":"37.0",
    "gn:asciiname":"Sungaikundur",
    "gn:country_code":"ID",
    "gn:dem":11,
    "gn:feature_class":"P",
    "gn:feature_code":"PPL",
    "gn:name":"Sungaikundur",
    "gn:population":0,
    "gn:timezone":"Asia/Jakarta",
    "iso:country":"ID",
    "name:ind_x_preferred":[
        "Sungaikundur"
    ],
    "name:und_x_variant":[
        "Soengaikoendoer"
    ],
    "wof:name":"Sungaikundur",
    "wof:placetype":"locality"
},
  "geometry": {"coordinates":[101.65389999999999,0.58],"type":"Point"}
}