{
  "type": "Feature",
  "properties": {
    "gn:admin1_code":"05",
    "gn:asciiname":"Tanjungberingin",
    "gn:country_code":"ID",
    "gn:dem":35,
    "gn:feature_class":"P",
    "gn:feature_code":"PPL",
    "gn:name":"Tanjungberingin",
    "gn:population":0,
    "gn:timezone":"Asia/Jakarta",
    "iso:country":"ID",
    "name:ind_x_preferred":[
        "Tanjungberingin"
    ],
    "wof:name":"Tanjungberingin",
    "wof:placetype":"locality"
},
  "geometry": {"coordinates":[102.9478,-1.2707],"type":"Point"}
}