{
  "type": "Feature",
  "properties": {
    "gn:admin1_code":"30",
    "gn:asciiname":"Babakanolong",
    "gn:country_code":"ID",
    "gn:dem":4,
    "gn:feature_class":"P",
    "gn:feature_code":"PPL",
    "gn:name":"Babakanolong",
    "gn:population":0,
    "gn:timezone":"Asia/Jakarta",
    "iso:country":"ID",
    "name:ind_x_preferred":[
        "Babakanolong"
    ],
    "wof:name":"Babakanolong",
    "wof:placetype":"locality"
},
  "geometry": {"coordinates":[107.43333,-6.27361],"type":"Point"}
}