{
  "type": "Feature",
  "properties": {
    "gn:admin1_code":"30",
    "gn:asciiname":"Burandul",
    "gn:country_code":"ID",
    "gn:dem":14,
    "gn:feature_class":"P",
    "gn:feature_code":"PPL",
    "gn:name":"Burandul",
    "gn:population":0,
    "gn:timezone":"Asia/Jakarta",
    "iso:country":"ID",
    "name:ind_x_preferred":[
        "Burandul"
    ],
    "wof:name":"Burandul",
    "wof:placetype":"locality"
},
  "geometry": {"coordinates":[107.3925,-6.22944],"type":"Point"}
}