{
  "type": "Feature",
  "properties": {
    "gn:admin1_code":"38",
    "gn:asciiname":"Balla",
    "gn:country_code":"ID",
    "gn:dem":1465,
    "gn:feature_class":"P",
    "gn:feature_code":"PPL",
    "gn:name":"Balla",
    "gn:population":0,
    "gn:timezone":"Asia/Makassar",
    "iso:country":"ID",
    "name:ceb_x_preferred":[
        "Balla"
    ],
    "name:ces_x_preferred":[
        "Balla"
    ],
    "name:deu_x_preferred":[
        "Balla"
    ],
    "name:fra_x_preferred":[
        "Balla"
    ],
    "name:hun_x_preferred":[
        "Balla"
    ],
    "name:ind_x_preferred":[
        "Balla"
    ],
    "name:ita_x_preferred":[
        "Balla"
    ],
    "name:nld_x_preferred":[
        "Balla"
    ],
    "name:pol_x_preferred":[
        "Balla"
    ],
    "name:rus_x_preferred":[
        "\u0411\u0430\u043b\u043b\u0430"
    ],
    "name:srp_x_preferred":[
        "Balla"
    ],
    "name:swe_x_preferred":[
        "Balla"
    ],
    "name:ukr_x_preferred":[
        "\u0411\u0430\u043b\u043b\u0430"
    ],
    "wof:lang_x_official":[
        "ind"
    ],
    "wof:lang_x_spoken":[
        "ind",
        "eng"
    ],
    "wof:name":"Balla",
    "wof:placetype":"locality"
},
  "geometry": {"coordinates":[119.67010000000001,-2.9514],"type":"Point"}
}