{
  "type": "Feature",
  "properties": {
    "gn:admin1_code":"30.0",
    "gn:asciiname":"Tamanjaya Satu",
    "gn:country_code":"ID",
    "gn:dem":323,
    "gn:feature_class":"P",
    "gn:feature_code":"PPLA4",
    "gn:name":"Tamanjaya Satu",
    "gn:population":0,
    "gn:timezone":"Asia/Jakarta",
    "iso:country":"ID",
    "name:ind_x_preferred":[
        "Tamanjaya Satu"
    ],
    "wof:lang_x_official":[
        "ind"
    ],
    "wof:lang_x_spoken":[
        "ind",
        "eng"
    ],
    "wof:name":"Tamanjaya Satu",
    "wof:placetype":"locality"
},
  "geometry": {"coordinates":[106.5283,-7.2262],"type":"Point"}
}