{
  "type": "Feature",
  "properties": {
    "gn:admin1_code":"7.0",
    "gn:asciiname":"Palagunting",
    "gn:country_code":"ID",
    "gn:dem":75,
    "gn:feature_class":"P",
    "gn:feature_code":"PPL",
    "gn:name":"Palagunting",
    "gn:population":0,
    "gn:timezone":"Asia/Jakarta",
    "iso:country":"ID",
    "name:ind_x_preferred":[
        "Palagunting"
    ],
    "wof:name":"Palagunting",
    "wof:placetype":"locality"
},
  "geometry": {"coordinates":[109.48083,-7.47333],"type":"Point"}
}