{
  "type": "Feature",
  "properties": {
    "gn:admin1_code":"38.0",
    "gn:asciiname":"Cabia",
    "gn:country_code":"ID",
    "gn:dem":23,
    "gn:feature_class":"P",
    "gn:feature_code":"PPL",
    "gn:name":"Cabia",
    "gn:population":0,
    "gn:timezone":"Asia/Makassar",
    "iso:country":"ID",
    "name:ceb_x_preferred":[
        "Cabia"
    ],
    "name:fur_x_preferred":[
        "Cjabie"
    ],
    "name:ind_x_preferred":[
        "Cabia"
    ],
    "name:ita_x_preferred":[
        "Cabia"
    ],
    "name:srp_x_preferred":[
        "\u041a\u0430\u0431\u0438\u0458\u0430"
    ],
    "wof:lang_x_official":[
        "ind"
    ],
    "wof:lang_x_spoken":[
        "ind",
        "eng"
    ],
    "wof:name":"Cabia",
    "wof:placetype":"locality"
},
  "geometry": {"coordinates":[120.36060000000001,-3.266],"type":"Point"}
}