{
  "type": "Feature",
  "properties": {
    "gn:admin1_code":"30",
    "gn:asciiname":"Wates",
    "gn:country_code":"ID",
    "gn:dem":423,
    "gn:feature_class":"P",
    "gn:feature_code":"PPL",
    "gn:name":"Wates",
    "gn:population":0,
    "gn:timezone":"Asia/Jakarta",
    "iso:country":"ID",
    "name:ceb_x_preferred":[
        "Wates"
    ],
    "name:ind_x_preferred":[
        "Wates"
    ],
    "name:nld_x_preferred":[
        "Wates"
    ],
    "name:swe_x_preferred":[
        "Wates"
    ],
    "wof:name":"Wates",
    "wof:placetype":"locality"
},
  "geometry": {"coordinates":[106.55056,-6.60861],"type":"Point"}
}