{
  "type": "Feature",
  "properties": {
    "gn:admin1_code":"7.0",
    "gn:asciiname":"Bonang",
    "gn:country_code":"ID",
    "gn:dem":6,
    "gn:feature_class":"P",
    "gn:feature_code":"PPL",
    "gn:name":"Bonang",
    "gn:population":0,
    "gn:timezone":"Asia/Jakarta",
    "iso:country":"ID",
    "name:bul_x_preferred":[
        "\u0411\u043e\u043d\u0430\u043d\u0433"
    ],
    "name:cat_x_preferred":[
        "Bonang"
    ],
    "name:deu_x_preferred":[
        "Bonang"
    ],
    "name:ind_x_preferred":[
        "Bonang"
    ],
    "name:jav_x_preferred":[
        "Bonang"
    ],
    "name:rus_x_preferred":[
        "\u0411\u043e\u043d\u0430\u043d\u0433"
    ],
    "name:sun_x_preferred":[
        "Bonang"
    ],
    "name:und_x_variant":[
        "Bonangredjo"
    ],
    "wof:lang_x_official":[
        "ind"
    ],
    "wof:lang_x_spoken":[
        "ind",
        "eng"
    ],
    "wof:name":"Bonang",
    "wof:placetype":"locality"
},
  "geometry": {"coordinates":[110.5941,-6.8519],"type":"Point"}
}