{
  "type": "Feature",
  "properties": {
    "gn:admin1_code":"2.0",
    "gn:asciiname":"Sakti",
    "gn:country_code":"ID",
    "gn:dem":153,
    "gn:feature_class":"P",
    "gn:feature_code":"PPLA4",
    "gn:name":"Sakti",
    "gn:population":0,
    "gn:timezone":"Asia/Makassar",
    "iso:country":"ID",
    "name:ind_x_preferred":[
        "Sakti"
    ],
    "wof:name":"Sakti",
    "wof:placetype":"locality"
},
  "geometry": {"coordinates":[115.48220000000001,-8.706],"type":"Point"}
}