{
  "type": "Feature",
  "properties": {
    "gn:admin1_code":"30.0",
    "gn:asciiname":"Lemahbeureum",
    "gn:country_code":"ID",
    "gn:dem":643,
    "gn:feature_class":"P",
    "gn:feature_code":"PPL",
    "gn:name":"Lemahbeureum",
    "gn:population":0,
    "gn:timezone":"Asia/Jakarta",
    "iso:country":"ID",
    "name:ind_x_preferred":[
        "Lemahbeureum"
    ],
    "wof:name":"Lemahbeureum",
    "wof:placetype":"locality"
},
  "geometry": {"coordinates":[108.0566,-7.5039],"type":"Point"}
}