{
  "type": "Feature",
  "properties": {
    "gn:admin1_code":"34",
    "gn:asciiname":"Dulupia Selatan",
    "gn:country_code":"ID",
    "gn:dem":64,
    "gn:feature_class":"P",
    "gn:feature_code":"PPL",
    "gn:name":"Dulupia Selatan",
    "gn:population":0,
    "gn:timezone":"Asia/Makassar",
    "iso:country":"ID",
    "name:ind_x_preferred":[
        "Dulupia Selatan"
    ],
    "name:und_x_variant":[
        "Dulupia"
    ],
    "wof:name":"Dulupia Selatan",
    "wof:placetype":"locality"
},
  "geometry": {"coordinates":[122.854,0.5642],"type":"Point"}
}