{
  "type": "Feature",
  "properties": {
    "gn:admin1_code":"7.0",
    "gn:asciiname":"Lemiring",
    "gn:country_code":"ID",
    "gn:dem":424,
    "gn:feature_class":"P",
    "gn:feature_code":"PPL",
    "gn:name":"Lemiring",
    "gn:population":0,
    "gn:timezone":"Asia/Jakarta",
    "iso:country":"ID",
    "name:ind_x_preferred":[
        "Lemiring"
    ],
    "wof:name":"Lemiring",
    "wof:placetype":"locality"
},
  "geometry": {"coordinates":[109.82250000000001,-7.51722],"type":"Point"}
}