{
  "type": "Feature",
  "properties": {
    "gn:admin1_code":"7.0",
    "gn:asciiname":"Kedungagung Kulon",
    "gn:country_code":"ID",
    "gn:dem":353,
    "gn:feature_class":"P",
    "gn:feature_code":"PPL",
    "gn:name":"Kedungagung Kulon",
    "gn:population":0,
    "gn:timezone":"Asia/Jakarta",
    "iso:country":"ID",
    "name:ind_x_preferred":[
        "Kedungagung Kulon"
    ],
    "wof:name":"Kedungagung Kulon",
    "wof:placetype":"locality"
},
  "geometry": {"coordinates":[109.04139000000001,-7.33722],"type":"Point"}
}