{
  "type": "Feature",
  "properties": {
    "gn:admin1_code":"8.0",
    "gn:asciiname":"Rembang",
    "gn:country_code":"ID",
    "gn:dem":324,
    "gn:feature_class":"P",
    "gn:feature_code":"PPL",
    "gn:name":"Rembang",
    "gn:population":0,
    "gn:timezone":"Asia/Jakarta",
    "iso:country":"ID",
    "name:ind_x_preferred":[
        "Rembang"
    ],
    "wof:name":"Rembang",
    "wof:placetype":"locality"
},
  "geometry": {"coordinates":[112.38549999999999,-8.1006],"type":"Point"}
}