{
  "type": "Feature",
  "properties": {
    "gn:admin1_code":"0.0",
    "gn:asciiname":"Mangunharjo",
    "gn:cc2":"ID",
    "gn:country_code":"ID",
    "gn:dem":372,
    "gn:feature_class":"P",
    "gn:feature_code":"PPL",
    "gn:name":"Mangunharjo",
    "gn:population":0,
    "gn:timezone":"Asia/Jakarta",
    "iso:country":"ID",
    "name:und_x_variant":[
        "Mangunhardja",
        "Mangunhardjo",
        "Mangoenhardjo",
        "Mangunharjo"
    ],
    "wof:lang_x_official":[
        "ind"
    ],
    "wof:lang_x_spoken":[
        "ind",
        "eng"
    ],
    "wof:name":"Mangunharjo",
    "wof:placetype":"locality"
},
  "geometry": {"coordinates":[111.21666999999999,-8.08333],"type":"Point"}
}