{
  "type": "Feature",
  "properties": {
    "gn:admin1_code":"8",
    "gn:asciiname":"Mojogulung",
    "gn:country_code":"ID",
    "gn:dem":36,
    "gn:feature_class":"P",
    "gn:feature_code":"PPL",
    "gn:name":"Mojogulung",
    "gn:population":0,
    "gn:timezone":"Asia/Jakarta",
    "iso:country":"ID",
    "name:ind_x_preferred":[
        "Mojogulung"
    ],
    "wof:name":"Mojogulung",
    "wof:placetype":"locality"
},
  "geometry": {"coordinates":[112.2013,-7.4741],"type":"Point"}
}