{
  "type": "Feature",
  "properties": {
    "gn:country":"ID",
    "gn:fcode":"PPL",
    "gn:pop":0,
    "iso:country":"ID",
    "name:ceb_x_preferred":[
        "Mojo"
    ],
    "name:ces_x_preferred":[
        "Mojo"
    ],
    "name:deu_x_preferred":[
        "Mojo"
    ],
    "name:fra_x_preferred":[
        "Mojo"
    ],
    "name:hun_x_preferred":[
        "Mojo"
    ],
    "name:ind_x_preferred":[
        "Mojo"
    ],
    "name:ita_x_preferred":[
        "Mojo"
    ],
    "name:jpn_x_preferred":[
        "\u30e2\u30b8\u30e7"
    ],
    "name:msa_x_preferred":[
        "Mojo"
    ],
    "name:nld_x_preferred":[
        "Mojo"
    ],
    "name:pol_x_preferred":[
        "Mojo"
    ],
    "name:por_x_preferred":[
        "Mojo"
    ],
    "name:rus_x_preferred":[
        "Mojo"
    ],
    "name:spa_x_preferred":[
        "Mojo"
    ],
    "name:swe_x_preferred":[
        "Mojo"
    ],
    "name:unk_x_variant":[
        "Modjo"
    ],
    "qs:name":"Mojo",
    "qs:name_adm0":"Indonesia",
    "qs:name_adm1":"Jawa Timur",
    "qs:photos_9k":1,
    "qs:photos_9r":1,
    "qs:photos_all":13,
    "qs:photos_sr":0,
    "qs:placetype":"Town",
    "qs:pop_sr":"0",
    "wd:wordcount":428,
    "wof:name":"Mojo",
    "wof:placetype":"locality",
    "wof:population":0
},
  "geometry": {"coordinates":[111.9645,-7.8945],"type":"Point"}
}