{
  "type": "Feature",
  "properties": {
    "gn:admin1_code":"7",
    "gn:asciiname":"Pejaggan",
    "gn:country_code":"ID",
    "gn:dem":1221,
    "gn:feature_class":"P",
    "gn:feature_code":"PPL",
    "gn:name":"Pejaggan",
    "gn:population":0,
    "gn:timezone":"Asia/Jakarta",
    "iso:country":"ID",
    "name:ind_x_preferred":[
        "Pejaggan"
    ],
    "wof:lang_x_official":[
        "ind"
    ],
    "wof:lang_x_spoken":[
        "ind",
        "eng"
    ],
    "wof:name":"Pejaggan",
    "wof:placetype":"locality"
},
  "geometry": {"coordinates":[109.29111,-7.22028],"type":"Point"}
}