{
  "type": "Feature",
  "properties": {
    "gn:admin1_code":"15.0",
    "gn:asciiname":"Talang Manik",
    "gn:country_code":"ID",
    "gn:dem":54,
    "gn:feature_class":"P",
    "gn:feature_code":"PPL",
    "gn:name":"Talang Manik",
    "gn:population":0,
    "gn:timezone":"Asia/Jakarta",
    "iso:country":"ID",
    "name:ind_x_preferred":[
        "Talang Manik"
    ],
    "name:und_x_variant":[
        "Talangmanik"
    ],
    "wof:name":"Talang Manik",
    "wof:placetype":"locality"
},
  "geometry": {"coordinates":[104.78243000000001,-4.92877],"type":"Point"}
}