{
  "type": "Feature",
  "properties": {
    "gn:admin1_code":"08",
    "gn:asciiname":"Karanganyar",
    "gn:country_code":"ID",
    "gn:dem":24,
    "gn:feature_class":"P",
    "gn:feature_code":"PPL",
    "gn:name":"Karanganyar",
    "gn:population":0,
    "gn:timezone":"Asia/Jakarta",
    "iso:country":"ID",
    "name:ceb_x_preferred":[
        "Karanganyar"
    ],
    "name:ind_x_preferred":[
        "Karanganyar"
    ],
    "name:jav_x_preferred":[
        "Karanganyar"
    ],
    "name:nld_x_preferred":[
        "Karanganyar"
    ],
    "name:swe_x_preferred":[
        "Karanganyar"
    ],
    "name:und_x_variant":[
        "Karanganjar"
    ],
    "wof:lang_x_official":[
        "ind"
    ],
    "wof:lang_x_spoken":[
        "ind",
        "eng"
    ],
    "wof:name":"Karanganyar",
    "wof:placetype":"locality"
},
  "geometry": {"coordinates":[114.30670000000001,-7.7755],"type":"Point"}
}