{
  "type": "Feature",
  "properties": {
    "gn:country":"ID",
    "gn:fcode":"PPL",
    "gn:pop":0,
    "iso:country":"ID",
    "name:ceb_x_preferred":[
        "Taman"
    ],
    "name:deu_x_preferred":[
        "Taman"
    ],
    "name:fra_x_preferred":[
        "Taman"
    ],
    "name:heb_x_preferred":[
        "\u05d8\u05d0\u05de\u05d0\u05df"
    ],
    "name:ind_x_preferred":[
        "Taman"
    ],
    "name:jpn_x_preferred":[
        "\u30bf\u30de\u30f3"
    ],
    "name:nld_x_preferred":[
        "Taman"
    ],
    "name:nor_x_preferred":[
        "Taman"
    ],
    "name:por_x_preferred":[
        "Taman"
    ],
    "name:swe_x_preferred":[
        "Taman"
    ],
    "name:zho_x_preferred":[
        "Taman"
    ],
    "qs:name":"Taman",
    "qs:name_adm0":"Indonesia",
    "qs:name_adm1":"Jawa Timur",
    "qs:photos_9k":1,
    "qs:photos_9r":1,
    "qs:photos_all":1,
    "qs:photos_sr":0,
    "qs:placetype":"Town",
    "qs:pop_sr":"0",
    "wd:wordcount":140,
    "wof:lang_x_official":[
        "ind"
    ],
    "wof:lang_x_spoken":[
        "ind",
        "eng"
    ],
    "wof:name":"Taman",
    "wof:placetype":"locality",
    "wof:population":0
},
  "geometry": {"coordinates":[112.699,-7.3522],"type":"Point"}
}