{
  "type": "Feature",
  "properties": {
    "gn:admin1_code":"7",
    "gn:asciiname":"Sibedug",
    "gn:country_code":"ID",
    "gn:dem":34,
    "gn:feature_class":"P",
    "gn:feature_code":"PPL",
    "gn:name":"Sibedug",
    "gn:population":0,
    "gn:timezone":"Asia/Jakarta",
    "iso:country":"ID",
    "name:ind_x_preferred":[
        "Sibedug"
    ],
    "wof:name":"Sibedug",
    "wof:placetype":"locality"
},
  "geometry": {"coordinates":[109.58,-7.0259],"type":"Point"}
}