{
  "type": "Feature",
  "properties": {
    "gn:admin1_code":"30.0",
    "gn:asciiname":"Kampungdesa",
    "gn:country_code":"ID",
    "gn:dem":391,
    "gn:feature_class":"P",
    "gn:feature_code":"PPLA4",
    "gn:name":"Kampungdesa",
    "gn:population":0,
    "gn:timezone":"Asia/Jakarta",
    "iso:country":"ID",
    "name:ind_x_preferred":[
        "Kampungdesa"
    ],
    "name:und_x_variant":[
        "Tjikondang",
        "Cikondang"
    ],
    "wof:lang_x_official":[
        "ind"
    ],
    "wof:lang_x_spoken":[
        "ind",
        "eng"
    ],
    "wof:name":"Kampungdesa",
    "wof:placetype":"locality"
},
  "geometry": {"coordinates":[107.86001,-7.57187],"type":"Point"}
}