{
  "type": "Feature",
  "properties": {
    "gn:admin1_code":"21.0",
    "gn:asciiname":"Bangunemo",
    "gn:country_code":"ID",
    "gn:dem":16,
    "gn:feature_class":"P",
    "gn:feature_code":"PPL",
    "gn:name":"Bangunemo",
    "gn:population":0,
    "gn:timezone":"Asia/Makassar",
    "iso:country":"ID",
    "name:ind_x_preferred":[
        "Bangunemo"
    ],
    "wof:name":"Bangunemo",
    "wof:placetype":"locality"
},
  "geometry": {"coordinates":[123.13930000000001,-1.2623],"type":"Point"}
}