{
  "type": "Feature",
  "properties": {
    "gn:admin1_code":"18.0",
    "gn:asciiname":"Waekekik",
    "gn:country_code":"ID",
    "gn:dem":804,
    "gn:feature_class":"P",
    "gn:feature_code":"PPL",
    "gn:name":"Waekekik",
    "gn:population":0,
    "gn:timezone":"Asia/Makassar",
    "iso:country":"ID",
    "name:ind_x_preferred":[
        "Waekekik"
    ],
    "wof:name":"Waekekik",
    "wof:placetype":"locality"
},
  "geometry": {"coordinates":[120.7188,-8.7616],"type":"Point"}
}