{
  "type": "Feature",
  "properties": {
    "gn:admin1_code":"30",
    "gn:asciiname":"Cikacapi",
    "gn:country_code":"ID",
    "gn:dem":67,
    "gn:feature_class":"P",
    "gn:feature_code":"PPL",
    "gn:name":"Cikacapi",
    "gn:population":0,
    "gn:timezone":"Asia/Jakarta",
    "iso:country":"ID",
    "name:ind_x_preferred":[
        "Cikacapi"
    ],
    "wof:name":"Cikacapi",
    "wof:placetype":"locality"
},
  "geometry": {"coordinates":[106.4605,-6.4191],"type":"Point"}
}