{
  "type": "Feature",
  "properties": {
    "gn:country":"ID",
    "gn:fcode":"PPL",
    "gn:pop":0,
    "iso:country":"ID",
    "name:eng_x_preferred":[
        "Merdeka"
    ],
    "name:fas_x_preferred":[
        "\u0645\u0631\u062f\u06a9\u0627"
    ],
    "name:ind_x_preferred":[
        "Merdeka"
    ],
    "name:tha_x_preferred":[
        "\u0e40\u0e21\u0e2d\u0e23\u0e4c\u0e40\u0e14\u0e01\u0e32"
    ],
    "qs:name":"Merdeka",
    "qs:name_adm0":"Indonesia",
    "qs:name_adm1":"Jawa Barat",
    "qs:photos_9k":1,
    "qs:photos_9r":1,
    "qs:photos_all":1,
    "qs:photos_sr":0,
    "qs:placetype":"Town",
    "qs:pop_sr":"0",
    "wd:wordcount":1703,
    "wof:lang_x_official":[
        "ind"
    ],
    "wof:lang_x_spoken":[
        "ind",
        "eng"
    ],
    "wof:name":"Merdeka",
    "wof:placetype":"locality",
    "wof:population":0
},
  "geometry": {"coordinates":[108.2261,-7.3261],"type":"Point"}
}