{
  "type": "Feature",
  "properties": {
    "gn:admin1_code":"30",
    "gn:asciiname":"Kaliabangbahagia",
    "gn:country_code":"ID",
    "gn:dem":11,
    "gn:feature_class":"P",
    "gn:feature_code":"PPL",
    "gn:name":"Kaliabangbahagia",
    "gn:population":0,
    "gn:timezone":"Asia/Jakarta",
    "iso:country":"ID",
    "name:ind_x_preferred":[
        "Kaliabangbahagia"
    ],
    "name:und_x_variant":[
        "Kaliabangbahagiabaru"
    ],
    "wof:lang_x_official":[
        "ind"
    ],
    "wof:lang_x_spoken":[
        "ind",
        "eng"
    ],
    "wof:name":"Kaliabangbahagia",
    "wof:placetype":"locality"
},
  "geometry": {"coordinates":[106.9885,-6.1944],"type":"Point"}
}