{
  "type": "Feature",
  "properties": {
    "gn:admin1_code":"38",
    "gn:asciiname":"Labata",
    "gn:country_code":"ID",
    "gn:dem":11,
    "gn:feature_class":"P",
    "gn:feature_code":"PPL",
    "gn:name":"Labata",
    "gn:population":0,
    "gn:timezone":"Asia/Makassar",
    "iso:country":"ID",
    "name:ind_x_preferred":[
        "Labata"
    ],
    "wof:name":"Labata",
    "wof:placetype":"locality"
},
  "geometry": {"coordinates":[120.35299999999999,-4.1651],"type":"Point"}
}