{
  "type": "Feature",
  "properties": {
    "gn:admin1_code":"7.0",
    "gn:asciiname":"Tambakrejo",
    "gn:country_code":"ID",
    "gn:dem":173,
    "gn:feature_class":"P",
    "gn:feature_code":"PPL",
    "gn:name":"Tambakrejo",
    "gn:population":0,
    "gn:timezone":"Asia/Jakarta",
    "iso:country":"ID",
    "name:ind_x_preferred":[
        "Tambakrejo"
    ],
    "wof:name":"Tambakrejo",
    "wof:placetype":"locality"
},
  "geometry": {"coordinates":[110.8325,-8.03306],"type":"Point"}
}