{
  "type": "Feature",
  "properties": {
    "gn:admin1_code":"8",
    "gn:asciiname":"Jabon",
    "gn:country_code":"ID",
    "gn:dem":5,
    "gn:feature_class":"P",
    "gn:feature_code":"PPL",
    "gn:name":"Jabon",
    "gn:population":0,
    "gn:timezone":"Asia/Jakarta",
    "iso:country":"ID",
    "name:ind_x_preferred":[
        "Jabon"
    ],
    "wof:name":"Jabon",
    "wof:placetype":"locality"
},
  "geometry": {"coordinates":[112.72499999999999,-7.4539],"type":"Point"}
}