{
  "type": "Feature",
  "properties": {
    "gn:admin1_code":"32.0",
    "gn:asciiname":"Trimaharjo Satu",
    "gn:country_code":"ID",
    "gn:dem":46,
    "gn:feature_class":"P",
    "gn:feature_code":"PPL",
    "gn:name":"Trimaharjo Satu",
    "gn:population":0,
    "gn:timezone":"Asia/Jakarta",
    "iso:country":"ID",
    "name:ind_x_preferred":[
        "Trimaharjo Satu"
    ],
    "name:und_x_variant":[
        "Trimaharjo 1"
    ],
    "wof:lang_x_official":[
        "ind"
    ],
    "wof:lang_x_spoken":[
        "ind",
        "eng"
    ],
    "wof:name":"Trimaharjo Satu",
    "wof:placetype":"locality"
},
  "geometry": {"coordinates":[104.71196,-4.02648],"type":"Point"}
}