{
  "type": "Feature",
  "properties": {
    "gn:admin1_code":"7",
    "gn:asciiname":"Gemborwirun",
    "gn:country_code":"ID",
    "gn:dem":29,
    "gn:feature_class":"P",
    "gn:feature_code":"PPL",
    "gn:name":"Gemborwirun",
    "gn:population":0,
    "gn:timezone":"Asia/Jakarta",
    "iso:country":"ID",
    "name:ind_x_preferred":[
        "Gemborwirun"
    ],
    "wof:name":"Gemborwirun",
    "wof:placetype":"locality"
},
  "geometry": {"coordinates":[109.92139,-7.67472],"type":"Point"}
}