{
  "type": "Feature",
  "properties": {
    "gn:admin1_code":"14.0",
    "gn:asciiname":"Muaramaau",
    "gn:country_code":"ID",
    "gn:dem":47,
    "gn:feature_class":"P",
    "gn:feature_code":"PPL",
    "gn:name":"Muaramaau",
    "gn:population":0,
    "gn:timezone":"Asia/Makassar",
    "iso:country":"ID",
    "name:und_x_variant":[
        "Muaramadu",
        "Moearama\u00e4u",
        "Muaramaau"
    ],
    "wof:name":"Muaramaau",
    "wof:placetype":"locality"
},
  "geometry": {"coordinates":[117.25,0.98333],"type":"Point"}
}