{
  "type": "Feature",
  "properties": {
    "gn:admin1_code":"30",
    "gn:asciiname":"Jahi",
    "gn:country_code":"ID",
    "gn:dem":378,
    "gn:feature_class":"P",
    "gn:feature_code":"PPL",
    "gn:name":"Jahi",
    "gn:population":0,
    "gn:timezone":"Asia/Jakarta",
    "iso:country":"ID",
    "name:fas_x_preferred":[
        "\u062c\u0647\u06cc"
    ],
    "name:ind_x_preferred":[
        "Jahi"
    ],
    "name:jpn_x_preferred":[
        "\u30b8\u30e3\u30d2\u30fc"
    ],
    "wof:lang_x_official":[
        "ind"
    ],
    "wof:lang_x_spoken":[
        "ind",
        "eng"
    ],
    "wof:name":"Jahi",
    "wof:placetype":"locality"
},
  "geometry": {"coordinates":[107.19110999999999,-6.7425],"type":"Point"}
}