{
  "type": "Feature",
  "properties": {
    "gn:admin1_code":"26.0",
    "gn:asciiname":"Pangasean Dua",
    "gn:country_code":"ID",
    "gn:dem":1193,
    "gn:feature_class":"P",
    "gn:feature_code":"PPL",
    "gn:name":"Pangasean Dua",
    "gn:population":0,
    "gn:timezone":"Asia/Jakarta",
    "iso:country":"ID",
    "name:ind_x_preferred":[
        "Pangasean Dua"
    ],
    "name:und_x_variant":[
        "Pangasean 2"
    ],
    "wof:name":"Pangasean Dua",
    "wof:placetype":"locality"
},
  "geometry": {"coordinates":[98.9572,2.5056],"type":"Point"}
}