{
  "type": "Feature",
  "properties": {
    "gn:admin1_code":"26.0",
    "gn:asciiname":"Suhut Maraja",
    "gn:country_code":"ID",
    "gn:dem":1207,
    "gn:feature_class":"P",
    "gn:feature_code":"PPL",
    "gn:name":"Suhut Maraja",
    "gn:population":0,
    "gn:timezone":"Asia/Jakarta",
    "iso:country":"ID",
    "name:ind_x_preferred":[
        "Suhut Maraja"
    ],
    "wof:name":"Suhut Maraja",
    "wof:placetype":"locality"
},
  "geometry": {"coordinates":[98.9863,2.631],"type":"Point"}
}