{
  "type": "Feature",
  "properties": {
    "gn:admin1_code":"18.0",
    "gn:asciiname":"Oebaki",
    "gn:country_code":"ID",
    "gn:dem":585,
    "gn:feature_class":"P",
    "gn:feature_code":"PPL",
    "gn:name":"Oebaki",
    "gn:population":0,
    "gn:timezone":"Asia/Makassar",
    "iso:country":"ID",
    "name:ind_x_preferred":[
        "Oebaki"
    ],
    "wof:name":"Oebaki",
    "wof:placetype":"locality"
},
  "geometry": {"coordinates":[123.83199999999999,-10.2536],"type":"Point"}
}