{
  "type": "Feature",
  "properties": {
    "gn:admin1_code":"30",
    "gn:asciiname":"Selacau",
    "gn:country_code":"ID",
    "gn:dem":888,
    "gn:feature_class":"P",
    "gn:feature_code":"PPL",
    "gn:name":"Selacau",
    "gn:population":0,
    "gn:timezone":"Asia/Jakarta",
    "iso:country":"ID",
    "name:ind_x_preferred":[
        "Selacau"
    ],
    "name:und_x_variant":[
        "Seloe"
    ],
    "wof:name":"Selacau",
    "wof:placetype":"locality"
},
  "geometry": {"coordinates":[107.80889000000001,-6.88611],"type":"Point"}
}