{
  "type": "Feature",
  "properties": {
    "gn:admin1_code":"30.0",
    "gn:asciiname":"Panyinangan",
    "gn:country_code":"ID",
    "gn:dem":671,
    "gn:feature_class":"P",
    "gn:feature_code":"PPL",
    "gn:name":"Panyinangan",
    "gn:population":0,
    "gn:timezone":"Asia/Jakarta",
    "iso:country":"ID",
    "name:ind_x_preferred":[
        "Panyinangan"
    ],
    "name:und_x_variant":[
        "Panjingkiran 1"
    ],
    "wof:lang_x_official":[
        "ind"
    ],
    "wof:lang_x_spoken":[
        "ind",
        "eng"
    ],
    "wof:name":"Panyinangan",
    "wof:placetype":"locality"
},
  "geometry": {"coordinates":[107.9314,-7.0625],"type":"Point"}
}