{
  "type": "Feature",
  "properties": {
    "gn:admin1_code":"0.0",
    "gn:asciiname":"Kongapatalabata",
    "gn:cc2":"ID",
    "gn:country_code":"ID",
    "gn:dem":19,
    "gn:feature_class":"P",
    "gn:feature_code":"PPL",
    "gn:name":"Kongapatalabata",
    "gn:population":0,
    "gn:timezone":"Asia/Jayapura",
    "iso:country":"ID",
    "name:und_x_variant":[
        "Patalabala",
        "Konga Patalabala",
        "Kongapatalabata"
    ],
    "wof:name":"Kongapatalabata",
    "wof:placetype":"locality"
},
  "geometry": {"coordinates":[134.43333000000001,-6.53333],"type":"Point"}
}