{
  "type": "Feature",
  "properties": {
    "gn:admin1_code":"38.0",
    "gn:asciiname":"Salongko",
    "gn:country_code":"ID",
    "gn:dem":14,
    "gn:feature_class":"P",
    "gn:feature_code":"PPL",
    "gn:name":"Salongko",
    "gn:population":0,
    "gn:timezone":"Asia/Makassar",
    "iso:country":"ID",
    "name:ind_x_preferred":[
        "Salongko"
    ],
    "wof:name":"Salongko",
    "wof:placetype":"locality"
},
  "geometry": {"coordinates":[120.25069999999999,-3.1632],"type":"Point"}
}