{
  "type": "Feature",
  "properties": {
    "gn:admin1_code":"7.0",
    "gn:asciiname":"Karangkemiri Kidul",
    "gn:country_code":"ID",
    "gn:dem":189,
    "gn:feature_class":"P",
    "gn:feature_code":"PPL",
    "gn:name":"Karangkemiri Kidul",
    "gn:population":0,
    "gn:timezone":"Asia/Jakarta",
    "iso:country":"ID",
    "name:ind_x_preferred":[
        "Karangkemiri Kidul"
    ],
    "wof:name":"Karangkemiri Kidul",
    "wof:placetype":"locality"
},
  "geometry": {"coordinates":[109.45305999999999,-7.29306],"type":"Point"}
}