{
  "type": "Feature",
  "properties": {
    "gn:admin1_code":"30",
    "gn:asciiname":"Majasem",
    "gn:country_code":"ID",
    "gn:dem":36,
    "gn:feature_class":"P",
    "gn:feature_code":"PPL",
    "gn:name":"Majasem",
    "gn:population":0,
    "gn:timezone":"Asia/Jakarta",
    "iso:country":"ID",
    "name:ind_x_preferred":[
        "Majasem"
    ],
    "wof:name":"Majasem",
    "wof:placetype":"locality"
},
  "geometry": {"coordinates":[108.52209999999999,-6.7437],"type":"Point"}
}