{
  "type": "Feature",
  "properties": {
    "gn:admin1_code":"8.0",
    "gn:asciiname":"Wonodadi",
    "gn:country_code":"ID",
    "gn:dem":564,
    "gn:feature_class":"P",
    "gn:feature_code":"PPLA4",
    "gn:name":"Wonodadi",
    "gn:population":0,
    "gn:timezone":"Asia/Jakarta",
    "iso:country":"ID",
    "name:ind_x_preferred":[
        "Wonodadi"
    ],
    "wof:name":"Wonodadi",
    "wof:placetype":"locality"
},
  "geometry": {"coordinates":[111.455,-8.1593],"type":"Point"}
}