{
  "type": "Feature",
  "properties": {
    "gn:admin1_code":"07",
    "gn:asciiname":"Gambang Waluh",
    "gn:country_code":"ID",
    "gn:dem":976,
    "gn:feature_class":"P",
    "gn:feature_code":"PPL",
    "gn:name":"Gambang Waluh",
    "gn:population":0,
    "gn:timezone":"Asia/Jakarta",
    "iso:country":"ID",
    "wof:name":"Gambang Waluh",
    "wof:placetype":"locality"
},
  "geometry": {"coordinates":[110.29361000000002,-7.26194],"type":"Point"}
}