{
  "type": "Feature",
  "properties": {
    "gn:admin1_code":"1",
    "gn:asciiname":"Lamlubak",
    "gn:country_code":"ID",
    "gn:dem":25,
    "gn:feature_class":"P",
    "gn:feature_code":"PPL",
    "gn:name":"Lamlubak",
    "gn:population":0,
    "gn:timezone":"Asia/Jakarta",
    "iso:country":"ID",
    "name:ind_x_preferred":[
        "Lamlubak"
    ],
    "wof:name":"Lamlubak",
    "wof:placetype":"locality"
},
  "geometry": {"coordinates":[95.45180000000001,5.4248],"type":"Point"}
}