{
  "type": "Feature",
  "properties": {
    "gn:admin1_code":"30",
    "gn:asciiname":"Palalangon",
    "gn:country_code":"ID",
    "gn:dem":296,
    "gn:feature_class":"P",
    "gn:feature_code":"PPL",
    "gn:name":"Palalangon",
    "gn:population":0,
    "gn:timezone":"Asia/Jakarta",
    "iso:country":"ID",
    "name:ind_x_preferred":[
        "Palalangon"
    ],
    "wof:name":"Palalangon",
    "wof:placetype":"locality"
},
  "geometry": {"coordinates":[107.30638999999999,-6.82417],"type":"Point"}
}