{
  "type": "Feature",
  "properties": {
    "gn:admin1_code":"14",
    "gn:asciiname":"Bakungannular",
    "gn:country_code":"ID",
    "gn:dem":17,
    "gn:feature_class":"P",
    "gn:feature_code":"PPL",
    "gn:name":"Bakungannular",
    "gn:population":0,
    "gn:timezone":"Asia/Makassar",
    "iso:country":"ID",
    "name:ind_x_preferred":[
        "Bakungannular"
    ],
    "wof:name":"Bakungannular",
    "wof:placetype":"locality"
},
  "geometry": {"coordinates":[117.03897000000001,-0.59779],"type":"Point"}
}