{
  "type": "Feature",
  "properties": {
    "gn:admin1_code":"38.0",
    "gn:asciiname":"Salubone",
    "gn:country_code":"ID",
    "gn:dem":10,
    "gn:feature_class":"P",
    "gn:feature_code":"PPL",
    "gn:name":"Salubone",
    "gn:population":0,
    "gn:timezone":"Asia/Makassar",
    "iso:country":"ID",
    "name:ind_x_preferred":[
        "Salubone"
    ],
    "wof:name":"Salubone",
    "wof:placetype":"locality"
},
  "geometry": {"coordinates":[119.5406,-3.5928],"type":"Point"}
}