{
  "type": "Feature",
  "properties": {
    "gn:admin1_code":"30",
    "gn:asciiname":"Mekarlaksana",
    "gn:country_code":"ID",
    "gn:dem":499,
    "gn:feature_class":"P",
    "gn:feature_code":"PPL",
    "gn:name":"Mekarlaksana",
    "gn:population":0,
    "gn:timezone":"Asia/Jakarta",
    "iso:country":"ID",
    "name:ind_x_preferred":[
        "Mekarlaksana"
    ],
    "wof:name":"Mekarlaksana",
    "wof:placetype":"locality"
},
  "geometry": {"coordinates":[107.60778000000001,-6.64306],"type":"Point"}
}