{
  "type": "Feature",
  "properties": {
    "gn:admin1_code":"18.0",
    "gn:asciiname":"Tanarara Timur",
    "gn:country_code":"ID",
    "gn:dem":893,
    "gn:feature_class":"P",
    "gn:feature_code":"PPLA4",
    "gn:name":"Tanarara Timur",
    "gn:population":0,
    "gn:timezone":"Asia/Makassar",
    "iso:country":"ID",
    "name:ind_x_preferred":[
        "Tanarara Timur"
    ],
    "wof:name":"Tanarara Timur",
    "wof:placetype":"locality"
},
  "geometry": {"coordinates":[120.2949,-10.0106],"type":"Point"}
}