{
  "type": "Feature",
  "properties": {
    "gn:admin1_code":"07",
    "gn:asciiname":"Ujung-ujung",
    "gn:country_code":"ID",
    "gn:dem":657,
    "gn:feature_class":"P",
    "gn:feature_code":"PPL",
    "gn:name":"Ujung-ujung",
    "gn:population":0,
    "gn:timezone":"Asia/Jakarta",
    "iso:country":"ID",
    "name:und_x_variant":[
        "Udjungudjung",
        "Ujung-ujung"
    ],
    "wof:name":"Ujung-ujung",
    "wof:placetype":"locality"
},
  "geometry": {"coordinates":[110.53471999999999,-7.34389],"type":"Point"}
}