{
  "type": "Feature",
  "properties": {
    "gn:admin1_code":"18.0",
    "gn:asciiname":"Praimatuku",
    "gn:country_code":"ID",
    "gn:dem":425,
    "gn:feature_class":"P",
    "gn:feature_code":"PPL",
    "gn:name":"Praimatuku",
    "gn:population":0,
    "gn:timezone":"Asia/Makassar",
    "iso:country":"ID",
    "name:ind_x_preferred":[
        "Praimatuku"
    ],
    "wof:name":"Praimatuku",
    "wof:placetype":"locality"
},
  "geometry": {"coordinates":[119.5535,-9.5108],"type":"Point"}
}