{
  "type": "Feature",
  "properties": {
    "gn:admin1_code":"30",
    "gn:asciiname":"Sriasih",
    "gn:country_code":"ID",
    "gn:dem":290,
    "gn:feature_class":"P",
    "gn:feature_code":"PPL",
    "gn:name":"Sriasih",
    "gn:population":0,
    "gn:timezone":"Asia/Jakarta",
    "iso:country":"ID",
    "name:ind_x_preferred":[
        "Sriasih"
    ],
    "wof:name":"Sriasih",
    "wof:placetype":"locality"
},
  "geometry": {"coordinates":[106.77110999999999,-6.61806],"type":"Point"}
}