{
  "type": "Feature",
  "properties": {
    "gn:admin1_code":"8.0",
    "gn:asciiname":"Songkolrejo",
    "gn:country_code":"ID",
    "gn:dem":611,
    "gn:feature_class":"P",
    "gn:feature_code":"PPL",
    "gn:name":"Songkolrejo",
    "gn:population":0,
    "gn:timezone":"Asia/Jakarta",
    "iso:country":"ID",
    "name:ind_x_preferred":[
        "Songkolrejo"
    ],
    "wof:name":"Songkolrejo",
    "wof:placetype":"locality"
},
  "geometry": {"coordinates":[112.36960000000001,-7.8169],"type":"Point"}
}