{
  "type": "Feature",
  "properties": {
    "gn:admin1_code":"41.0",
    "gn:asciiname":"Ampelas",
    "gn:country_code":"ID",
    "gn:dem":7,
    "gn:feature_class":"P",
    "gn:feature_code":"PPL",
    "gn:name":"Ampelas",
    "gn:population":0,
    "gn:timezone":"Asia/Makassar",
    "iso:country":"ID",
    "name:ind_x_preferred":[
        "Ampelas"
    ],
    "name:und_x_variant":[
        "Ampalas"
    ],
    "wof:name":"Ampelas",
    "wof:placetype":"locality"
},
  "geometry": {"coordinates":[118.9769,-2.6376],"type":"Point"}
}