{
  "type": "Feature",
  "properties": {
    "gn:admin1_code":"26",
    "gn:asciiname":"Mariabandar",
    "gn:country_code":"ID",
    "gn:dem":66,
    "gn:feature_class":"P",
    "gn:feature_code":"PPL",
    "gn:name":"Mariabandar",
    "gn:population":0,
    "gn:timezone":"Asia/Jakarta",
    "iso:country":"ID",
    "name:ind_x_preferred":[
        "Mariabandar"
    ],
    "name:und_x_variant":[
        "Mariahbandar"
    ],
    "wof:name":"Mariabandar",
    "wof:placetype":"locality"
},
  "geometry": {"coordinates":[99.0401,3.3001],"type":"Point"}
}