{
  "type": "Feature",
  "properties": {
    "gn:admin1_code":"31.0",
    "gn:asciiname":"Kaiya",
    "gn:country_code":"ID",
    "gn:dem":2,
    "gn:feature_class":"P",
    "gn:feature_code":"PPL",
    "gn:name":"Kaiya",
    "gn:population":0,
    "gn:timezone":"Asia/Makassar",
    "iso:country":"ID",
    "name:ind_x_preferred":[
        "Kaiya"
    ],
    "wof:name":"Kaiya",
    "wof:placetype":"locality"
},
  "geometry": {"coordinates":[124.08920000000001,0.9087],"type":"Point"}
}