{
  "type": "Feature",
  "properties": {
    "gn:admin1_code":"8.0",
    "gn:asciiname":"Wadungasri",
    "gn:country_code":"ID",
    "gn:dem":5,
    "gn:feature_class":"P",
    "gn:feature_code":"PPLA4",
    "gn:name":"Wadungasri",
    "gn:population":0,
    "gn:timezone":"Asia/Jakarta",
    "iso:country":"ID",
    "name:ind_x_preferred":[
        "Wadungasri"
    ],
    "name:und_x_variant":[
        "Wadungsari"
    ],
    "wof:name":"Wadungasri",
    "wof:placetype":"locality"
},
  "geometry": {"coordinates":[112.7683,-7.3451],"type":"Point"}
}