{
  "type": "Feature",
  "properties": {
    "gn:admin1_code":"05",
    "gn:asciiname":"Semabu",
    "gn:country_code":"ID",
    "gn:dem":43,
    "gn:feature_class":"P",
    "gn:feature_code":"PPL",
    "gn:name":"Semabu",
    "gn:population":0,
    "gn:timezone":"Asia/Jakarta",
    "iso:country":"ID",
    "name:ind_x_preferred":[
        "Semabu"
    ],
    "wof:name":"Semabu",
    "wof:placetype":"locality"
},
  "geometry": {"coordinates":[102.48390000000001,-1.4738],"type":"Point"}
}