{
  "type": "Feature",
  "properties": {
    "gn:admin1_code":"7.0",
    "gn:asciiname":"Karangjoso",
    "gn:country_code":"ID",
    "gn:dem":14,
    "gn:feature_class":"P",
    "gn:feature_code":"PPL",
    "gn:name":"Karangjoso",
    "gn:population":0,
    "gn:timezone":"Asia/Jakarta",
    "iso:country":"ID",
    "name:ind_x_preferred":[
        "Karangjoso"
    ],
    "wof:name":"Karangjoso",
    "wof:placetype":"locality"
},
  "geometry": {"coordinates":[109.86694,-7.76528],"type":"Point"}
}