{
  "type": "Feature",
  "properties": {
    "gn:admin1_code":"38",
    "gn:asciiname":"Campagatinggia",
    "gn:country_code":"ID",
    "gn:dem":850,
    "gn:feature_class":"P",
    "gn:feature_code":"PPL",
    "gn:name":"Campagatinggia",
    "gn:population":0,
    "gn:timezone":"Asia/Makassar",
    "iso:country":"ID",
    "name:ind_x_preferred":[
        "Campagatinggia"
    ],
    "wof:name":"Campagatinggia",
    "wof:placetype":"locality"
},
  "geometry": {"coordinates":[119.8702,-5.4404],"type":"Point"}
}