{
  "type": "Feature",
  "properties": {
    "gn:admin1_code":"7",
    "gn:asciiname":"Bungkul",
    "gn:country_code":"ID",
    "gn:dem":79,
    "gn:feature_class":"P",
    "gn:feature_code":"PPL",
    "gn:name":"Bungkul",
    "gn:population":0,
    "gn:timezone":"Asia/Jakarta",
    "iso:country":"ID",
    "name:ind_x_preferred":[
        "Bungkul"
    ],
    "wof:name":"Bungkul",
    "wof:placetype":"locality"
},
  "geometry": {"coordinates":[111.2907,-7.0867],"type":"Point"}
}