{
  "type": "Feature",
  "properties": {
    "gn:admin1_code":"34",
    "gn:asciiname":"Sukamekar",
    "gn:country_code":"ID",
    "gn:dem":90,
    "gn:feature_class":"P",
    "gn:feature_code":"PPL",
    "gn:name":"Sukamekar",
    "gn:population":0,
    "gn:timezone":"Asia/Makassar",
    "iso:country":"ID",
    "name:ind_x_preferred":[
        "Sukamekar"
    ],
    "wof:name":"Sukamekar",
    "wof:placetype":"locality"
},
  "geometry": {"coordinates":[122.6763,0.6979],"type":"Point"}
}