{
  "type": "Feature",
  "properties": {
    "gn:admin1_code":"8.0",
    "gn:asciiname":"Dembo",
    "gn:country_code":"ID",
    "gn:dem":49,
    "gn:feature_class":"P",
    "gn:feature_code":"PPL",
    "gn:name":"Dembo",
    "gn:population":0,
    "gn:timezone":"Asia/Jakarta",
    "iso:country":"ID",
    "name:ind_x_preferred":[
        "Dembo"
    ],
    "name:ita_x_preferred":[
        "Dembo"
    ],
    "wof:name":"Dembo",
    "wof:placetype":"locality"
},
  "geometry": {"coordinates":[111.12278000000001,-8.11917],"type":"Point"}
}