{
  "type": "Feature",
  "properties": {
    "gn:admin1_code":"26.0",
    "gn:asciiname":"Bunga Sampang",
    "gn:country_code":"ID",
    "gn:dem":1376,
    "gn:elevation":"1379.0",
    "gn:feature_class":"P",
    "gn:feature_code":"PPL",
    "gn:name":"Bunga Sampang",
    "gn:population":0,
    "gn:timezone":"Asia/Jakarta",
    "iso:country":"ID",
    "name:ind_x_preferred":[
        "Bunga Sampang"
    ],
    "wof:name":"Bunga Sampang",
    "wof:placetype":"locality"
},
  "geometry": {"coordinates":[98.6611,2.9174],"type":"Point"}
}