{
  "type": "Feature",
  "properties": {
    "gn:admin1_code":"8.0",
    "gn:asciiname":"Guciputih",
    "gn:country_code":"ID",
    "gn:dem":21,
    "gn:feature_class":"P",
    "gn:feature_code":"PPL",
    "gn:name":"Guciputih",
    "gn:population":0,
    "gn:timezone":"Asia/Jakarta",
    "iso:country":"ID",
    "name:ind_x_preferred":[
        "Guciputih"
    ],
    "wof:name":"Guciputih",
    "wof:placetype":"locality"
},
  "geometry": {"coordinates":[113.6695,-8.4101],"type":"Point"}
}