{
  "type": "Feature",
  "properties": {
    "gn:admin1_code":"38",
    "gn:asciiname":"Lette",
    "gn:country_code":"ID",
    "gn:dem":7,
    "gn:feature_class":"P",
    "gn:feature_code":"PPL",
    "gn:name":"Lette",
    "gn:population":0,
    "gn:timezone":"Asia/Makassar",
    "iso:country":"ID",
    "name:deu_x_preferred":[
        "Lette"
    ],
    "name:ind_x_preferred":[
        "Lette"
    ],
    "name:nld_x_preferred":[
        "Lette"
    ],
    "wof:lang_x_official":[
        "ind"
    ],
    "wof:lang_x_spoken":[
        "ind",
        "eng"
    ],
    "wof:name":"Lette",
    "wof:placetype":"locality"
},
  "geometry": {"coordinates":[119.4088,-5.155],"type":"Point"}
}