{
  "type": "Feature",
  "properties": {
    "gn:admin1_code":"30",
    "gn:asciiname":"Tegalbaru",
    "gn:cc2":"ID",
    "gn:country_code":"ID",
    "gn:dem":42,
    "gn:feature_class":"P",
    "gn:feature_code":"PPL",
    "gn:name":"Tegalbaru",
    "gn:population":0,
    "gn:timezone":"Asia/Jakarta",
    "iso:country":"ID",
    "name:und_x_variant":[
        "Tegal",
        "Tegalbaru"
    ],
    "wof:name":"Tegalbaru",
    "wof:placetype":"locality"
},
  "geometry": {"coordinates":[106.56638999999998,-6.26694],"type":"Point"}
}