{
  "type": "Feature",
  "properties": {
    "gn:admin1_code":"21",
    "gn:asciiname":"Taipa",
    "gn:country_code":"ID",
    "gn:dem":95,
    "gn:feature_class":"P",
    "gn:feature_code":"PPL",
    "gn:name":"Taipa",
    "gn:population":0,
    "gn:timezone":"Asia/Makassar",
    "iso:country":"ID",
    "name:aze_x_preferred":[
        "Taypa adas\u0131"
    ],
    "name:deu_x_preferred":[
        "Taipa"
    ],
    "name:fra_x_preferred":[
        "Taipa"
    ],
    "name:heb_x_preferred":[
        "\u05d8\u05d9\u05d9\u05e4\u05d4"
    ],
    "name:ita_x_preferred":[
        "Taipa"
    ],
    "name:jpn_x_preferred":[
        "\u30bf\u30a4\u30d1\u5cf6"
    ],
    "name:kor_x_preferred":[
        "\ud0c0\uc774\ud30c\uc12c"
    ],
    "name:nld_x_preferred":[
        "Taipa"
    ],
    "name:nor_x_preferred":[
        "Taipa"
    ],
    "name:pol_x_preferred":[
        "Taipa"
    ],
    "name:por_x_preferred":[
        "Taipa"
    ],
    "name:rus_x_preferred":[
        "\u0422\u0430\u0439\u043f\u0430"
    ],
    "name:sco_x_preferred":[
        "Taipa"
    ],
    "name:spa_x_preferred":[
        "Taipa"
    ],
    "name:swe_x_preferred":[
        "Taipa"
    ],
    "name:ukr_x_preferred":[
        "\u0422\u0430\u0439\u043f\u0430"
    ],
    "name:urd_x_preferred":[
        "\u062a\u0627\u0626\u06cc\u067e\u0627"
    ],
    "name:vie_x_preferred":[
        "\u0110\u00e3ng T\u1ec3"
    ],
    "wof:lang_x_official":[
        "ind"
    ],
    "wof:lang_x_spoken":[
        "ind",
        "eng"
    ],
    "wof:name":"Taipa",
    "wof:placetype":"locality"
},
  "geometry": {"coordinates":[123.28556,-1.36056],"type":"Point"}
}