{
  "type": "Feature",
  "properties": {
    "gn:admin1_code":"7.0",
    "gn:asciiname":"Ngeglek",
    "gn:country_code":"ID",
    "gn:dem":1052,
    "gn:feature_class":"P",
    "gn:feature_code":"PPL",
    "gn:name":"Ngeglek",
    "gn:population":0,
    "gn:timezone":"Asia/Jakarta",
    "iso:country":"ID",
    "wof:name":"Ngeglek",
    "wof:placetype":"locality"
},
  "geometry": {"coordinates":[110.4975,-7.45806],"type":"Point"}
}