{
  "type": "Feature",
  "properties": {
    "gn:admin1_code":"30",
    "gn:asciiname":"Cantilancurug",
    "gn:country_code":"ID",
    "gn:dem":17,
    "gn:feature_class":"P",
    "gn:feature_code":"PPL",
    "gn:name":"Cantilancurug",
    "gn:population":0,
    "gn:timezone":"Asia/Jakarta",
    "iso:country":"ID",
    "name:ind_x_preferred":[
        "Cantilancurug"
    ],
    "wof:name":"Cantilancurug",
    "wof:placetype":"locality"
},
  "geometry": {"coordinates":[108.65219999999999,-6.8531],"type":"Point"}
}