{
  "type": "Feature",
  "properties": {
    "gn:country":"ID",
    "gn:fcode":"PPL",
    "gn:pop":0,
    "iso:country":"ID",
    "name:ind_x_preferred":[
        "Sukaram"
    ],
    "name:unk_x_variant":[
        "Soekarami"
    ],
    "qs:name":"Sukarami",
    "qs:name_adm0":"Indonesia",
    "qs:name_adm1":"Sumatera Selatan",
    "qs:photos_9k":1,
    "qs:photos_9r":2,
    "qs:photos_all":53,
    "qs:photos_sr":0,
    "qs:placetype":"Town",
    "qs:pop_sr":"0",
    "wof:lang_x_official":[
        "ind"
    ],
    "wof:lang_x_spoken":[
        "ind",
        "eng"
    ],
    "wof:name":"Sukarami",
    "wof:placetype":"locality",
    "wof:population":0
},
  "geometry": {"coordinates":[104.75,-2.93333],"type":"Point"}
}