{
  "type": "Feature",
  "properties": {
    "gn:admin1_code":"30.0",
    "gn:asciiname":"Cilangkap",
    "gn:country_code":"ID",
    "gn:dem":23,
    "gn:feature_class":"P",
    "gn:feature_code":"PPLA4",
    "gn:name":"Cilangkap",
    "gn:population":0,
    "gn:timezone":"Asia/Jakarta",
    "iso:country":"ID",
    "name:ind_x_preferred":[
        "Cilangkap"
    ],
    "wof:name":"Cilangkap",
    "wof:placetype":"locality"
},
  "geometry": {"coordinates":[106.5633,-7.0358],"type":"Point"}
}