{
  "type": "Feature",
  "properties": {
    "gn:admin1_code":"30.0",
    "gn:asciiname":"Sukamanah",
    "gn:country_code":"ID",
    "gn:dem":463,
    "gn:feature_class":"P",
    "gn:feature_code":"PPL",
    "gn:name":"Sukamanah",
    "gn:population":0,
    "gn:timezone":"Asia/Jakarta",
    "iso:country":"ID",
    "name:ind_x_preferred":[
        "Sukamanah"
    ],
    "name:und_x_variant":[
        "Soekamana 2"
    ],
    "wof:name":"Sukamanah",
    "wof:placetype":"locality"
},
  "geometry": {"coordinates":[108.1567,-7.308],"type":"Point"}
}