{
  "type": "Feature",
  "properties": {
    "gn:admin1_code":"18.0",
    "gn:asciiname":"Lewotobi",
    "gn:country_code":"ID",
    "gn:dem":20,
    "gn:feature_class":"P",
    "gn:feature_code":"PPLA4",
    "gn:name":"Lewotobi",
    "gn:population":0,
    "gn:timezone":"Asia/Makassar",
    "iso:country":"ID",
    "name:cat_x_preferred":[
        "Lewotobi"
    ],
    "name:fra_x_preferred":[
        "Lewotobi"
    ],
    "name:ind_x_preferred":[
        "Gunung Lewotobi"
    ],
    "name:jpn_x_preferred":[
        "\u30ec\u30a6\u30a9\u30c8\u30d3\u5c71"
    ],
    "name:kat_x_preferred":[
        "\u10da\u10d4\u10d5\u10dd\u10e2\u10dd\u10d1\u10d8"
    ],
    "name:nld_x_preferred":[
        "Lewotobi"
    ],
    "name:slk_x_preferred":[
        "Lewotobi"
    ],
    "name:spa_x_preferred":[
        "Lewotobi"
    ],
    "name:ukr_x_preferred":[
        "\u041b\u0435\u0432\u043e\u0442\u043e\u0431\u0456"
    ],
    "name:und_x_variant":[
        "Lobetobi",
        "Lewotobi"
    ],
    "name:zho_x_preferred":[
        "\u52d2\u6c83\u6258\u6bd4\u706b\u5c71"
    ],
    "wof:lang_x_official":[
        "ind"
    ],
    "wof:lang_x_spoken":[
        "ind",
        "eng"
    ],
    "wof:name":"Lewotobi",
    "wof:placetype":"locality"
},
  "geometry": {"coordinates":[122.836,-8.576],"type":"Point"}
}