{
  "type": "Feature",
  "properties": {
    "gn:admin1_code":"18.0",
    "gn:asciiname":"Lewotobi",
    "gn:country_code":"ID",
    "gn:dem":20,
    "gn:feature_class":"P",
    "gn:feature_code":"PPLA4",
    "gn:name":"Lewotobi",
    "gn:population":0,
    "gn:timezone":"Asia/Makassar",
    "iso:country":"ID",
    "name:und_x_variant":[
        "Lobetobi",
        "Lewotobi"
    ],
    "wof:name":"Lewotobi",
    "wof:placetype":"locality"
},
  "geometry": {"coordinates":[122.836,-8.576],"type":"Point"}
}