{
  "type": "Feature",
  "properties": {
    "gn:admin1_code":"30.0",
    "gn:asciiname":"Cipicung",
    "gn:country_code":"ID",
    "gn:dem":224,
    "gn:feature_class":"P",
    "gn:feature_code":"PPL",
    "gn:name":"Cipicung",
    "gn:population":0,
    "gn:timezone":"Asia/Jakarta",
    "iso:country":"ID",
    "name:ind_x_preferred":[
        "Cipicung"
    ],
    "name:und_x_variant":[
        "Tjipitjung"
    ],
    "wof:name":"Cipicung",
    "wof:placetype":"locality"
},
  "geometry": {"coordinates":[107.38361,-6.60722],"type":"Point"}
}