{
  "type": "Feature",
  "properties": {
    "gn:admin1_code":"30",
    "gn:asciiname":"Kebonmanggu",
    "gn:country_code":"ID",
    "gn:dem":303,
    "gn:feature_class":"P",
    "gn:feature_code":"PPL",
    "gn:name":"Kebonmanggu",
    "gn:population":0,
    "gn:timezone":"Asia/Jakarta",
    "iso:country":"ID",
    "name:ind_x_preferred":[
        "Kebonmanggu"
    ],
    "wof:name":"Kebonmanggu",
    "wof:placetype":"locality"
},
  "geometry": {"coordinates":[107.19693999999998,-6.77861],"type":"Point"}
}