{
  "type": "Feature",
  "properties": {
    "gn:admin1_code":"30",
    "gn:asciiname":"Nyalindung",
    "gn:country_code":"ID",
    "gn:dem":850,
    "gn:feature_class":"P",
    "gn:feature_code":"PPL",
    "gn:name":"Nyalindung",
    "gn:population":0,
    "gn:timezone":"Asia/Jakarta",
    "iso:country":"ID",
    "name:ind_x_preferred":[
        "Nyalindung"
    ],
    "wof:name":"Nyalindung",
    "wof:placetype":"locality"
},
  "geometry": {"coordinates":[107.8663,-7.0086],"type":"Point"}
}