{
  "type": "Feature",
  "properties": {
    "gn:admin1_code":"37",
    "gn:asciiname":"Kampungbaru",
    "gn:country_code":"ID",
    "gn:dem":23,
    "gn:feature_class":"P",
    "gn:feature_code":"PPL",
    "gn:name":"Kampungbaru",
    "gn:population":0,
    "gn:timezone":"Asia/Jakarta",
    "iso:country":"ID",
    "name:ind_x_preferred":[
        "Kampungbaru"
    ],
    "wof:name":"Kampungbaru",
    "wof:placetype":"locality"
},
  "geometry": {"coordinates":[101.65545,1.08871],"type":"Point"}
}