{
  "type": "Feature",
  "properties": {
    "gn:country":"ID",
    "gn:fcode":"ADM3",
    "gn:pop":0,
    "iso:country":"ID",
    "name:eng_x_preferred":[
        "Districts of West Java"
    ],
    "name:ind_x_preferred":[
        "Kecamatan Cilaku"
    ],
    "name:unk_x_variant":[
        "Cilaku"
    ],
    "qs:name":"Kecamatan Cilaku",
    "qs:photos_9r":0,
    "qs:photos_sr":0,
    "qs:pop_sr":"0",
    "wd:wordcount":1319,
    "wof:name":"Kecamatan Cilaku",
    "wof:placetype":"localadmin",
    "wof:population":0
},
  "geometry": {"coordinates":[107.14639,-6.87278],"type":"Point"}
}