{
  "type": "Feature",
  "properties": {
    "gn:admin1_code":"18.0",
    "gn:asciiname":"Kejopomadopa",
    "gn:country_code":"ID",
    "gn:dem":110,
    "gn:feature_class":"P",
    "gn:feature_code":"PPL",
    "gn:name":"Kejopomadopa",
    "gn:population":0,
    "gn:timezone":"Asia/Makassar",
    "iso:country":"ID",
    "name:ind_x_preferred":[
        "Kejopomadopa"
    ],
    "wof:name":"Kejopomadopa",
    "wof:placetype":"locality"
},
  "geometry": {"coordinates":[121.7702,-10.5979],"type":"Point"}
}