{
  "type": "Feature",
  "properties": {
    "gn:admin1_code":"38",
    "gn:asciiname":"Ulugalung",
    "gn:country_code":"ID",
    "gn:dem":496,
    "gn:feature_class":"P",
    "gn:feature_code":"PPL",
    "gn:name":"Ulugalung",
    "gn:population":0,
    "gn:timezone":"Asia/Makassar",
    "iso:country":"ID",
    "name:ind_x_preferred":[
        "Ulugalung"
    ],
    "wof:name":"Ulugalung",
    "wof:placetype":"locality"
},
  "geometry": {"coordinates":[120.0857,-5.0933],"type":"Point"}
}