{
  "type": "Feature",
  "properties": {
    "gn:admin1_code":"26",
    "gn:asciiname":"Tunggorono Tiga Belas",
    "gn:country_code":"ID",
    "gn:dem":42,
    "gn:feature_class":"P",
    "gn:feature_code":"PPL",
    "gn:name":"Tunggorono Tiga Belas",
    "gn:population":0,
    "gn:timezone":"Asia/Jakarta",
    "iso:country":"ID",
    "name:ind_x_preferred":[
        "Tunggorono Tiga Belas"
    ],
    "name:und_x_variant":[
        "Tunggorono 13"
    ],
    "wof:name":"Tunggorono Tiga Belas",
    "wof:placetype":"locality"
},
  "geometry": {"coordinates":[98.5184,3.5862],"type":"Point"}
}