{
  "type": "Feature",
  "properties": {
    "gn:admin1_code":"30",
    "gn:asciiname":"Tangkil Dua",
    "gn:cc2":"ID",
    "gn:country_code":"ID",
    "gn:dem":14,
    "gn:feature_class":"P",
    "gn:feature_code":"PPL",
    "gn:name":"Tangkil Dua",
    "gn:population":0,
    "gn:timezone":"Asia/Jakarta",
    "iso:country":"ID",
    "name:und_x_variant":[
        "Tangkil 2",
        "Tangkil Dua"
    ],
    "wof:name":"Tangkil Dua",
    "wof:placetype":"locality"
},
  "geometry": {"coordinates":[106.30972,-6.16806],"type":"Point"}
}