{
  "type": "Feature",
  "properties": {
    "gn:admin1_code":"37",
    "gn:asciiname":"Sungailuar",
    "gn:country_code":"ID",
    "gn:dem":9,
    "gn:feature_class":"P",
    "gn:feature_code":"PPL",
    "gn:name":"Sungailuar",
    "gn:population":0,
    "gn:timezone":"Asia/Jakarta",
    "iso:country":"ID",
    "name:ind_x_preferred":[
        "Sungailuar"
    ],
    "wof:name":"Sungailuar",
    "wof:placetype":"locality"
},
  "geometry": {"coordinates":[103.55388000000001,-0.10214],"type":"Point"}
}