{
  "type": "Feature",
  "properties": {
    "gn:admin1_code":"30.0",
    "gn:asciiname":"Bagung",
    "gn:country_code":"ID",
    "gn:dem":22,
    "gn:feature_class":"P",
    "gn:feature_code":"PPL",
    "gn:name":"Bagung",
    "gn:population":0,
    "gn:timezone":"Asia/Jakarta",
    "iso:country":"ID",
    "name:ind_x_preferred":[
        "Bagung"
    ],
    "wof:name":"Bagung",
    "wof:placetype":"locality"
},
  "geometry": {"coordinates":[108.26972000000001,-6.65861],"type":"Point"}
}