{
  "type": "Feature",
  "properties": {
    "gn:admin1_code":"18.0",
    "gn:asciiname":"Ufhau",
    "gn:country_code":"ID",
    "gn:dem":124,
    "gn:feature_class":"P",
    "gn:feature_code":"PPL",
    "gn:name":"Ufhau",
    "gn:population":0,
    "gn:timezone":"Asia/Makassar",
    "iso:country":"ID",
    "name:ind_x_preferred":[
        "Ufhau"
    ],
    "wof:name":"Ufhau",
    "wof:placetype":"locality"
},
  "geometry": {"coordinates":[124.1636,-9.9735],"type":"Point"}
}