{
  "type": "Feature",
  "properties": {
    "gn:admin1_code":"26",
    "gn:asciiname":"Hutapardomuan",
    "gn:country_code":"ID",
    "gn:dem":191,
    "gn:feature_class":"P",
    "gn:feature_code":"PPL",
    "gn:name":"Hutapardomuan",
    "gn:population":0,
    "gn:timezone":"Asia/Jakarta",
    "iso:country":"ID",
    "name:ind_x_preferred":[
        "Hutapardomuan"
    ],
    "wof:name":"Hutapardomuan",
    "wof:placetype":"locality"
},
  "geometry": {"coordinates":[99.44329999999999,1.12234],"type":"Point"}
}