{
  "type": "Feature",
  "properties": {
    "gn:admin1_code":"21",
    "gn:asciiname":"Abo",
    "gn:country_code":"ID",
    "gn:dem":28,
    "gn:feature_class":"P",
    "gn:feature_code":"PPL",
    "gn:name":"Abo",
    "gn:population":0,
    "gn:timezone":"Asia/Makassar",
    "iso:country":"ID",
    "name:ceb_x_preferred":[
        "Abo"
    ],
    "name:ces_x_preferred":[
        "Abo"
    ],
    "name:deu_x_preferred":[
        "Abo"
    ],
    "name:fin_x_preferred":[
        "Abo"
    ],
    "name:fra_x_preferred":[
        "Abo"
    ],
    "name:hye_x_preferred":[
        "\u0531\u0562\u0578"
    ],
    "name:ind_x_preferred":[
        "Abo"
    ],
    "name:nld_x_preferred":[
        "Abo"
    ],
    "name:rus_x_preferred":[
        "\u0410\u0431\u043e"
    ],
    "name:swe_x_preferred":[
        "Abo"
    ],
    "name:tgl_x_preferred":[
        "Abo"
    ],
    "name:uzb_x_preferred":[
        "Abo"
    ],
    "wof:name":"Abo",
    "wof:placetype":"locality"
},
  "geometry": {"coordinates":[119.8496,-0.1029],"type":"Point"}
}