{
  "type": "Feature",
  "properties": {
    "gn:admin1_code":"30.0",
    "gn:asciiname":"Cintawangi",
    "gn:country_code":"ID",
    "gn:dem":169,
    "gn:feature_class":"P",
    "gn:feature_code":"PPL",
    "gn:name":"Cintawangi",
    "gn:population":0,
    "gn:timezone":"Asia/Jakarta",
    "iso:country":"ID",
    "name:ind_x_preferred":[
        "Cintawangi"
    ],
    "wof:name":"Cintawangi",
    "wof:placetype":"locality"
},
  "geometry": {"coordinates":[108.1918,-7.6124],"type":"Point"}
}