{
  "type": "Feature",
  "properties": {
    "gn:admin1_code":"33.0",
    "gn:asciiname":"Batuhideung",
    "gn:country_code":"ID",
    "gn:dem":147,
    "gn:feature_class":"P",
    "gn:feature_code":"PPL",
    "gn:name":"Batuhideung",
    "gn:population":0,
    "gn:timezone":"Asia/Jakarta",
    "iso:country":"ID",
    "name:ind_x_preferred":[
        "Batuhideung"
    ],
    "name:und_x_variant":[
        "Batuhid\u00f6ng",
        "Batoehideung",
        "Batuhideung"
    ],
    "wof:name":"Batuhideung",
    "wof:placetype":"locality"
},
  "geometry": {"coordinates":[105.6545,-6.7846],"type":"Point"}
}