{
  "type": "Feature",
  "properties": {
    "gn:admin1_code":"37.0",
    "gn:asciiname":"Kubu",
    "gn:country_code":"ID",
    "gn:dem":45,
    "gn:feature_class":"P",
    "gn:feature_code":"PPL",
    "gn:name":"Kubu",
    "gn:population":0,
    "gn:timezone":"Asia/Jakarta",
    "iso:country":"ID",
    "name:ceb_x_preferred":[
        "Kubu"
    ],
    "name:ind_x_preferred":[
        "Kubu"
    ],
    "name:msa_x_preferred":[
        "Kubu"
    ],
    "name:nld_x_preferred":[
        "Kubu"
    ],
    "name:rus_x_preferred":[
        "\u041a\u0443\u0431\u0443"
    ],
    "name:swe_x_preferred":[
        "Kubu"
    ],
    "wof:name":"Kubu",
    "wof:placetype":"locality"
},
  "geometry": {"coordinates":[101.59086000000001,-0.50487],"type":"Point"}
}