{
  "type": "Feature",
  "properties": {
    "gn:admin1_code":"24.0",
    "gn:asciiname":"Limaukambing",
    "gn:country_code":"ID",
    "gn:dem":499,
    "gn:feature_class":"P",
    "gn:feature_code":"PPL",
    "gn:name":"Limaukambing",
    "gn:population":0,
    "gn:timezone":"Asia/Jakarta",
    "iso:country":"ID",
    "name:ind_x_preferred":[
        "Limaukambing"
    ],
    "wof:name":"Limaukambing",
    "wof:placetype":"locality"
},
  "geometry": {"coordinates":[100.7971,-0.7501],"type":"Point"}
}