{
  "type": "Feature",
  "properties": {
    "gn:admin1_code":"24",
    "gn:asciiname":"Kotagadang",
    "gn:country_code":"ID",
    "gn:dem":290,
    "gn:feature_class":"P",
    "gn:feature_code":"PPL",
    "gn:name":"Kotagadang",
    "gn:population":0,
    "gn:timezone":"Asia/Jakarta",
    "iso:country":"ID",
    "name:ind_x_preferred":[
        "Kotogadang"
    ],
    "name:ind_x_variant":[
        "Kotagadang"
    ],
    "wof:name":"Kotagadang",
    "wof:placetype":"locality"
},
  "geometry": {"coordinates":[100.51000000000001,0.0157],"type":"Point"}
}