{
  "type": "Feature",
  "properties": {
    "gn:admin1_code":"30.0",
    "gn:asciiname":"Cibodas",
    "gn:country_code":"ID",
    "gn:dem":233,
    "gn:feature_class":"P",
    "gn:feature_code":"PPL",
    "gn:name":"Cibodas",
    "gn:population":0,
    "gn:timezone":"Asia/Jakarta",
    "iso:country":"ID",
    "name:ind_x_preferred":[
        "Cibodas"
    ],
    "name:jav_x_preferred":[
        "Cibodas"
    ],
    "name:msa_x_preferred":[
        "Cibodas"
    ],
    "name:sun_x_preferred":[
        "Cibodas"
    ],
    "wof:lang_x_official":[
        "ind"
    ],
    "wof:lang_x_spoken":[
        "ind",
        "eng"
    ],
    "wof:name":"Cibodas",
    "wof:placetype":"locality"
},
  "geometry": {"coordinates":[108.36620000000001,-7.3635],"type":"Point"}
}