{
  "type": "Feature",
  "properties": {
    "gn:admin1_code":"8.0",
    "gn:asciiname":"Dawuhan",
    "gn:country_code":"ID",
    "gn:dem":18,
    "gn:feature_class":"P",
    "gn:feature_code":"PPL",
    "gn:name":"Dawuhan",
    "gn:population":0,
    "gn:timezone":"Asia/Jakarta",
    "iso:country":"ID",
    "name:ind_x_preferred":[
        "Dawuhan"
    ],
    "name:und_x_variant":[
        "Dawoehan"
    ],
    "wof:name":"Dawuhan",
    "wof:placetype":"locality"
},
  "geometry": {"coordinates":[111.4438,-8.2472],"type":"Point"}
}