{
  "type": "Feature",
  "properties": {
    "gn:admin1_code":"26",
    "gn:asciiname":"Negerimalela",
    "gn:country_code":"ID",
    "gn:dem":155,
    "gn:feature_class":"P",
    "gn:feature_code":"PPL",
    "gn:name":"Negerimalela",
    "gn:population":0,
    "gn:timezone":"Asia/Jakarta",
    "iso:country":"ID",
    "name:ind_x_preferred":[
        "Negerimalela"
    ],
    "wof:name":"Negerimalela",
    "wof:placetype":"locality"
},
  "geometry": {"coordinates":[99.18210000000001,3.0428],"type":"Point"}
}