{
  "type": "Feature",
  "properties": {
    "gn:admin1_code":"7.0",
    "gn:asciiname":"Karangwuni",
    "gn:country_code":"ID",
    "gn:dem":18,
    "gn:feature_class":"P",
    "gn:feature_code":"PPL",
    "gn:name":"Karangwuni",
    "gn:population":0,
    "gn:timezone":"Asia/Jakarta",
    "iso:country":"ID",
    "name:ind_x_preferred":[
        "Karangwuni"
    ],
    "wof:name":"Karangwuni",
    "wof:placetype":"locality"
},
  "geometry": {"coordinates":[109.58111,-7.65472],"type":"Point"}
}