{
  "type": "Feature",
  "properties": {
    "gn:admin1_code":"24",
    "gn:asciiname":"Pamatanggugung",
    "gn:country_code":"ID",
    "gn:dem":475,
    "gn:feature_class":"P",
    "gn:feature_code":"PPL",
    "gn:name":"Pamatanggugung",
    "gn:population":0,
    "gn:timezone":"Asia/Jakarta",
    "iso:country":"ID",
    "name:ind_x_preferred":[
        "Pamatanggugung"
    ],
    "wof:name":"Pamatanggugung",
    "wof:placetype":"locality"
},
  "geometry": {"coordinates":[100.04510000000001,0.0506],"type":"Point"}
}