{
  "type": "Feature",
  "properties": {
    "gn:admin1_code":"38",
    "gn:asciiname":"Tonasa",
    "gn:country_code":"ID",
    "gn:dem":482,
    "gn:feature_class":"P",
    "gn:feature_code":"PPL",
    "gn:name":"Tonasa",
    "gn:population":0,
    "gn:timezone":"Asia/Makassar",
    "iso:country":"ID",
    "name:ind_x_preferred":[
        "Tonasa"
    ],
    "wof:name":"Tonasa",
    "wof:placetype":"locality"
},
  "geometry": {"coordinates":[119.7214,-5.3363],"type":"Point"}
}