{
  "type": "Feature",
  "properties": {
    "gn:admin1_code":"7.0",
    "gn:asciiname":"Beskal",
    "gn:country_code":"ID",
    "gn:dem":8,
    "gn:feature_class":"P",
    "gn:feature_code":"PPL",
    "gn:name":"Beskal",
    "gn:population":0,
    "gn:timezone":"Asia/Jakarta",
    "iso:country":"ID",
    "name:ind_x_preferred":[
        "Beskal"
    ],
    "name:und_x_variant":[
        "Biskal"
    ],
    "wof:name":"Beskal",
    "wof:placetype":"locality"
},
  "geometry": {"coordinates":[108.9358,-6.8748],"type":"Point"}
}