{
  "type": "Feature",
  "properties": {
    "gn:admin1_code":"40.0",
    "gn:asciiname":"Bulungkor",
    "gn:country_code":"ID",
    "gn:dem":8,
    "gn:feature_class":"P",
    "gn:feature_code":"PPL",
    "gn:name":"Bulungkor",
    "gn:population":0,
    "gn:timezone":"Asia/Pontianak",
    "iso:country":"ID",
    "name:und_x_variant":[
        "Belangkor",
        "Bulungkor"
    ],
    "wof:name":"Bulungkor",
    "wof:placetype":"locality"
},
  "geometry": {"coordinates":[104.94959,-0.28838],"type":"Point"}
}