{
  "type": "Feature",
  "properties": {
    "gn:admin1_code":"30",
    "gn:asciiname":"Kamis",
    "gn:country_code":"ID",
    "gn:dem":335,
    "gn:feature_class":"P",
    "gn:feature_code":"PPL",
    "gn:name":"Kamis",
    "gn:population":0,
    "gn:timezone":"Asia/Jakarta",
    "iso:country":"ID",
    "name:deu_x_preferred":[
        "Kamis"
    ],
    "name:ind_x_preferred":[
        "Kamis"
    ],
    "name:pol_x_preferred":[
        "McCormick Polska"
    ],
    "wof:name":"Kamis",
    "wof:placetype":"locality"
},
  "geometry": {"coordinates":[108.28306000000001,-6.84139],"type":"Point"}
}