{
  "type": "Feature",
  "properties": {
    "gn:admin1_code":"18.0",
    "gn:asciiname":"Oeue",
    "gn:country_code":"ID",
    "gn:dem":407,
    "gn:feature_class":"P",
    "gn:feature_code":"PPL",
    "gn:name":"Oeue",
    "gn:population":0,
    "gn:timezone":"Asia/Makassar",
    "iso:country":"ID",
    "name:ind_x_preferred":[
        "Oeue"
    ],
    "wof:name":"Oeue",
    "wof:placetype":"locality"
},
  "geometry": {"coordinates":[124.53360000000001,-9.7228],"type":"Point"}
}