{
  "type": "Feature",
  "properties": {
    "gn:admin1_code":"26.0",
    "gn:asciiname":"Rantojior",
    "gn:country_code":"ID",
    "gn:dem":49,
    "gn:feature_class":"P",
    "gn:feature_code":"PPL",
    "gn:name":"Rantojior",
    "gn:population":0,
    "gn:timezone":"Asia/Jakarta",
    "iso:country":"ID",
    "name:ind_x_preferred":[
        "Rantaudjiur"
    ],
    "name:ind_x_variant":[
        "Rantojior"
    ],
    "wof:lang_x_official":[
        "ind"
    ],
    "wof:lang_x_spoken":[
        "ind",
        "eng"
    ],
    "wof:name":"Rantojior",
    "wof:placetype":"locality"
},
  "geometry": {"coordinates":[99.91619,1.73367],"type":"Point"}
}