{
  "type": "Feature",
  "properties": {
    "gn:admin1_code":"18.0",
    "gn:asciiname":"Sonapolen",
    "gn:country_code":"ID",
    "gn:dem":736,
    "gn:feature_class":"P",
    "gn:feature_code":"PPL",
    "gn:name":"Sonapolen",
    "gn:population":0,
    "gn:timezone":"Asia/Makassar",
    "iso:country":"ID",
    "name:ind_x_preferred":[
        "Sonapolen"
    ],
    "wof:name":"Sonapolen",
    "wof:placetype":"locality"
},
  "geometry": {"coordinates":[124.26779999999999,-9.8739],"type":"Point"}
}