{
  "type": "Feature",
  "properties": {
    "gn:admin1_code":"33",
    "gn:asciiname":"Lebaksalak",
    "gn:country_code":"ID",
    "gn:dem":129,
    "gn:feature_class":"P",
    "gn:feature_code":"PPL",
    "gn:name":"Lebaksalak",
    "gn:population":0,
    "gn:timezone":"Asia/Jakarta",
    "iso:country":"ID",
    "name:ind_x_preferred":[
        "Lebaksalak"
    ],
    "wof:name":"Lebaksalak",
    "wof:placetype":"locality"
},
  "geometry": {"coordinates":[106.00239999999999,-6.0795],"type":"Point"}
}