{
  "type": "Feature",
  "properties": {
    "gn:admin1_code":"30",
    "gn:asciiname":"Cidarangdan",
    "gn:cc2":"ID",
    "gn:country_code":"ID",
    "gn:dem":900,
    "gn:feature_class":"P",
    "gn:feature_code":"PPL",
    "gn:name":"Cidarangdan",
    "gn:population":0,
    "gn:timezone":"Asia/Jakarta",
    "iso:country":"ID",
    "name:und_x_variant":[
        "Tjidarangdang",
        "Cidarangdang",
        "Cidarangdan"
    ],
    "wof:lang_x_official":[
        "ind"
    ],
    "wof:lang_x_spoken":[
        "ind",
        "eng"
    ],
    "wof:name":"Cidarangdan",
    "wof:placetype":"locality"
},
  "geometry": {"coordinates":[107.62528,-7.06778],"type":"Point"}
}