{
  "type": "Feature",
  "properties": {
    "gn:admin1_code":"18.0",
    "gn:asciiname":"Lairudi",
    "gn:country_code":"ID",
    "gn:dem":267,
    "gn:feature_class":"P",
    "gn:feature_code":"PPL",
    "gn:name":"Lairudi",
    "gn:population":0,
    "gn:timezone":"Asia/Makassar",
    "iso:country":"ID",
    "name:ind_x_preferred":[
        "Lairudi"
    ],
    "wof:name":"Lairudi",
    "wof:placetype":"locality"
},
  "geometry": {"coordinates":[120.2679,-9.8204],"type":"Point"}
}