{
  "type": "Feature",
  "properties": {
    "gn:admin1_code":"17",
    "gn:asciiname":"Sukamulya",
    "gn:country_code":"ID",
    "gn:dem":73,
    "gn:feature_class":"P",
    "gn:feature_code":"PPL",
    "gn:name":"Sukamulya",
    "gn:population":0,
    "gn:timezone":"Asia/Makassar",
    "iso:country":"ID",
    "name:ind_x_preferred":[
        "Sukamulya"
    ],
    "name:jav_x_preferred":[
        "Sukamulya"
    ],
    "name:msa_x_preferred":[
        "Sukamulya"
    ],
    "wof:name":"Sukamulya",
    "wof:placetype":"locality"
},
  "geometry": {"coordinates":[117.7358,-8.1797],"type":"Point"}
}