{
  "type": "Feature",
  "properties": {
    "gn:admin1_code":"7.0",
    "gn:asciiname":"Pasarlawas",
    "gn:country_code":"ID",
    "gn:dem":1150,
    "gn:feature_class":"P",
    "gn:feature_code":"PPL",
    "gn:name":"Pasarlawas",
    "gn:population":0,
    "gn:timezone":"Asia/Jakarta",
    "iso:country":"ID",
    "name:ind_x_preferred":[
        "Pasarlawas"
    ],
    "wof:name":"Pasarlawas",
    "wof:placetype":"locality"
},
  "geometry": {"coordinates":[109.85111000000001,-7.28806],"type":"Point"}
}