{
  "type": "Feature",
  "properties": {
    "gn:admin1_code":"30.0",
    "gn:asciiname":"Sasaksaat Lebak",
    "gn:country_code":"ID",
    "gn:dem":528,
    "gn:feature_class":"P",
    "gn:feature_code":"PPL",
    "gn:name":"Sasaksaat Lebak",
    "gn:population":0,
    "gn:timezone":"Asia/Jakarta",
    "iso:country":"ID",
    "name:ind_x_preferred":[
        "Sasaksaat Lebak"
    ],
    "name:und_x_variant":[
        "Sasaksaat"
    ],
    "wof:lang_x_official":[
        "ind"
    ],
    "wof:lang_x_spoken":[
        "ind",
        "eng"
    ],
    "wof:name":"Sasaksaat Lebak",
    "wof:placetype":"locality"
},
  "geometry": {"coordinates":[107.43389000000001,-6.78389],"type":"Point"}
}