{
  "type": "Feature",
  "properties": {
    "gn:admin1_code":"2",
    "gn:asciiname":"Tunasmekar",
    "gn:country_code":"ID",
    "gn:dem":116,
    "gn:feature_class":"P",
    "gn:feature_code":"PPL",
    "gn:name":"Tunasmekar",
    "gn:population":0,
    "gn:timezone":"Asia/Makassar",
    "iso:country":"ID",
    "name:ind_x_preferred":[
        "Tunasmekar"
    ],
    "wof:name":"Tunasmekar",
    "wof:placetype":"locality"
},
  "geometry": {"coordinates":[114.5865,-8.3037],"type":"Point"}
}