{
  "type": "Feature",
  "properties": {
    "gn:admin1_code":"15.0",
    "gn:asciiname":"Damarlega",
    "gn:country_code":"ID",
    "gn:dem":53,
    "gn:feature_class":"P",
    "gn:feature_code":"PPL",
    "gn:name":"Damarlega",
    "gn:population":0,
    "gn:timezone":"Asia/Jakarta",
    "iso:country":"ID",
    "name:ind_x_preferred":[
        "Damarlega"
    ],
    "wof:name":"Damarlega",
    "wof:placetype":"locality"
},
  "geometry": {"coordinates":[105.483,-5.59849],"type":"Point"}
}