{
  "type": "Feature",
  "properties": {
    "gn:admin1_code":"22.0",
    "gn:asciiname":"Putemata",
    "gn:country_code":"ID",
    "gn:dem":46,
    "gn:feature_class":"P",
    "gn:feature_code":"PPL",
    "gn:name":"Putemata",
    "gn:population":0,
    "gn:timezone":"Asia/Makassar",
    "iso:country":"ID",
    "name:ind_x_preferred":[
        "Putemata"
    ],
    "wof:name":"Putemata",
    "wof:placetype":"locality"
},
  "geometry": {"coordinates":[122.6127,-4.3869],"type":"Point"}
}