{
  "type": "Feature",
  "properties": {
    "gn:admin1_code":"7",
    "gn:asciiname":"Sukodono",
    "gn:country_code":"ID",
    "gn:dem":100,
    "gn:feature_class":"P",
    "gn:feature_code":"PPL",
    "gn:name":"Sukodono",
    "gn:population":0,
    "gn:timezone":"Asia/Jakarta",
    "iso:country":"ID",
    "name:ind_x_preferred":[
        "Sukodono"
    ],
    "wof:name":"Sukodono",
    "wof:placetype":"locality"
},
  "geometry": {"coordinates":[111.05028,-7.44083],"type":"Point"}
}