{
  "type": "Feature",
  "properties": {
    "gn:admin1_code":"30",
    "gn:asciiname":"Pasirayu",
    "gn:country_code":"ID",
    "gn:dem":398,
    "gn:feature_class":"P",
    "gn:feature_code":"PPL",
    "gn:name":"Pasirayu",
    "gn:population":0,
    "gn:timezone":"Asia/Jakarta",
    "iso:country":"ID",
    "name:ind_x_preferred":[
        "Pasirayu"
    ],
    "wof:name":"Pasirayu",
    "wof:placetype":"locality"
},
  "geometry": {"coordinates":[108.30972,-6.84667],"type":"Point"}
}