{
  "type": "Feature",
  "properties": {
    "gn:admin1_code":"30.0",
    "gn:asciiname":"Pamotong",
    "gn:country_code":"ID",
    "gn:dem":30,
    "gn:feature_class":"P",
    "gn:feature_code":"PPL",
    "gn:name":"Pamotong",
    "gn:population":0,
    "gn:timezone":"Asia/Jakarta",
    "iso:country":"ID",
    "name:ind_x_preferred":[
        "Pamotong"
    ],
    "wof:name":"Pamotong",
    "wof:placetype":"locality"
},
  "geometry": {"coordinates":[107.67529999999999,-7.6176],"type":"Point"}
}