{
  "type": "Feature",
  "properties": {
    "gn:admin1_code":"24",
    "gn:asciiname":"Lubuklimpata",
    "gn:country_code":"ID",
    "gn:dem":725,
    "gn:feature_class":"P",
    "gn:feature_code":"PPL",
    "gn:name":"Lubuklimpata",
    "gn:population":0,
    "gn:timezone":"Asia/Jakarta",
    "iso:country":"ID",
    "name:ind_x_preferred":[
        "Lubuklimpata"
    ],
    "wof:name":"Lubuklimpata",
    "wof:placetype":"locality"
},
  "geometry": {"coordinates":[100.6653,-0.10684],"type":"Point"}
}