{
  "type": "Feature",
  "properties": {
    "gn:admin1_code":"30",
    "gn:asciiname":"Babakanbandung",
    "gn:country_code":"ID",
    "gn:dem":678,
    "gn:feature_class":"P",
    "gn:feature_code":"PPL",
    "gn:name":"Babakanbandung",
    "gn:population":0,
    "gn:timezone":"Asia/Jakarta",
    "iso:country":"ID",
    "name:ind_x_preferred":[
        "Babakanbandung"
    ],
    "name:und_x_variant":[
        "Bandung 2",
        "Bandung Dua"
    ],
    "wof:lang_x_official":[
        "ind"
    ],
    "wof:lang_x_spoken":[
        "ind",
        "eng"
    ],
    "wof:name":"Babakanbandung",
    "wof:placetype":"locality"
},
  "geometry": {"coordinates":[107.38249999999999,-6.91167],"type":"Point"}
}