{
  "type": "Feature",
  "properties": {
    "gn:admin1_code":"7.0",
    "gn:asciiname":"Rawagembol",
    "gn:country_code":"ID",
    "gn:dem":49,
    "gn:feature_class":"P",
    "gn:feature_code":"PPL",
    "gn:name":"Rawagembol",
    "gn:population":0,
    "gn:timezone":"Asia/Jakarta",
    "iso:country":"ID",
    "name:ind_x_preferred":[
        "Rawagembol"
    ],
    "wof:name":"Rawagembol",
    "wof:placetype":"locality"
},
  "geometry": {"coordinates":[109.4225,-7.47222],"type":"Point"}
}