{
  "type": "Feature",
  "properties": {
    "gn:admin1_code":"30.0",
    "gn:asciiname":"Tunggalrahayu",
    "gn:country_code":"ID",
    "gn:dem":120,
    "gn:feature_class":"P",
    "gn:feature_code":"PPL",
    "gn:name":"Tunggalrahayu",
    "gn:population":0,
    "gn:timezone":"Asia/Jakarta",
    "iso:country":"ID",
    "name:ind_x_preferred":[
        "Tunggalrahayu"
    ],
    "wof:name":"Tunggalrahayu",
    "wof:placetype":"locality"
},
  "geometry": {"coordinates":[108.45399999999999,-7.368],"type":"Point"}
}