{
  "type": "Feature",
  "properties": {
    "gn:admin1_code":"32.0",
    "gn:asciiname":"Sidarahayu",
    "gn:country_code":"ID",
    "gn:dem":62,
    "gn:feature_class":"P",
    "gn:feature_code":"PPL",
    "gn:name":"Sidarahayu",
    "gn:population":0,
    "gn:timezone":"Asia/Jakarta",
    "iso:country":"ID",
    "name:ind_x_preferred":[
        "Sidarahayu"
    ],
    "wof:name":"Sidarahayu",
    "wof:placetype":"locality"
},
  "geometry": {"coordinates":[104.60543,-4.18264],"type":"Point"}
}