{
  "type": "Feature",
  "properties": {
    "gn:admin1_code":"2.0",
    "gn:asciiname":"Banjar Yehpoh",
    "gn:country_code":"ID",
    "gn:dem":97,
    "gn:feature_class":"P",
    "gn:feature_code":"PPL",
    "gn:name":"Banjar Yehpoh",
    "gn:population":0,
    "gn:timezone":"Asia/Makassar",
    "iso:country":"ID",
    "name:ind_x_preferred":[
        "Banjar Yehpoh"
    ],
    "name:und_x_variant":[
        "Jah Poetek",
        "Jehpoh",
        "Yehpoh"
    ],
    "wof:name":"Banjar Yehpoh",
    "wof:placetype":"locality"
},
  "geometry": {"coordinates":[115.515,-8.4784],"type":"Point"}
}