{
  "type": "Feature",
  "properties": {
    "gn:admin1_code":"26.0",
    "gn:asciiname":"Pintusona",
    "gn:country_code":"ID",
    "gn:dem":919,
    "gn:feature_class":"P",
    "gn:feature_code":"PPL",
    "gn:name":"Pintusona",
    "gn:population":0,
    "gn:timezone":"Asia/Jakarta",
    "iso:country":"ID",
    "name:ind_x_preferred":[
        "Pintusona"
    ],
    "wof:name":"Pintusona",
    "wof:placetype":"locality"
},
  "geometry": {"coordinates":[98.70650000000001,2.5982],"type":"Point"}
}