{
  "type": "Feature",
  "properties": {
    "gn:admin1_code":"37",
    "gn:asciiname":"Pulaukampung",
    "gn:country_code":"ID",
    "gn:dem":27,
    "gn:feature_class":"P",
    "gn:feature_code":"PPL",
    "gn:name":"Pulaukampung",
    "gn:population":0,
    "gn:timezone":"Asia/Jakarta",
    "iso:country":"ID",
    "name:ind_x_preferred":[
        "Pulaukampung"
    ],
    "wof:name":"Pulaukampung",
    "wof:placetype":"locality"
},
  "geometry": {"coordinates":[101.188,0.3545],"type":"Point"}
}