{
  "type": "Feature",
  "properties": {
    "gn:admin1_code":"8",
    "gn:asciiname":"Singodiwongso",
    "gn:country_code":"ID",
    "gn:dem":21,
    "gn:feature_class":"P",
    "gn:feature_code":"PPL",
    "gn:name":"Singodiwongso",
    "gn:population":0,
    "gn:timezone":"Asia/Jakarta",
    "iso:country":"ID",
    "name:ind_x_preferred":[
        "Singodiwongso"
    ],
    "wof:name":"Singodiwongso",
    "wof:placetype":"locality"
},
  "geometry": {"coordinates":[114.3737,-8.1993],"type":"Point"}
}