{
  "type": "Feature",
  "properties": {
    "gn:admin1_code":"15.0",
    "gn:asciiname":"Kejadian",
    "gn:country_code":"ID",
    "gn:dem":180,
    "gn:feature_class":"P",
    "gn:feature_code":"PPL",
    "gn:name":"Kejadian",
    "gn:population":0,
    "gn:timezone":"Asia/Jakarta",
    "iso:country":"ID",
    "name:ind_x_preferred":[
        "Kejadian"
    ],
    "name:und_x_variant":[
        "K\u0115djadian"
    ],
    "wof:name":"Kejadian",
    "wof:placetype":"locality"
},
  "geometry": {"coordinates":[105.19373,-5.37571],"type":"Point"}
}