{
  "type": "Feature",
  "properties": {
    "gn:admin1_code":"15.0",
    "gn:asciiname":"Linggarjati",
    "gn:country_code":"ID",
    "gn:dem":109,
    "gn:feature_class":"P",
    "gn:feature_code":"PPL",
    "gn:name":"Linggarjati",
    "gn:population":0,
    "gn:timezone":"Asia/Jakarta",
    "iso:country":"ID",
    "name:ind_x_preferred":[
        "Linggarjati"
    ],
    "wof:name":"Linggarjati",
    "wof:placetype":"locality"
},
  "geometry": {"coordinates":[105.36096000000001,-5.44689],"type":"Point"}
}