{
  "type": "Feature",
  "properties": {
    "gn:admin1_code":"30.0",
    "gn:asciiname":"Cikareo",
    "gn:country_code":"ID",
    "gn:dem":437,
    "gn:feature_class":"P",
    "gn:feature_code":"PPL",
    "gn:name":"Cikareo",
    "gn:population":0,
    "gn:timezone":"Asia/Jakarta",
    "iso:country":"ID",
    "name:ind_x_preferred":[
        "Cikareo"
    ],
    "name:und_x_variant":[
        "Tjikareo",
        "Cikareo",
        "Tjikareo Tiga"
    ],
    "wof:name":"Cikareo",
    "wof:placetype":"locality"
},
  "geometry": {"coordinates":[108.3254,-7.4077],"type":"Point"}
}