{
  "type": "Feature",
  "properties": {
    "gn:admin1_code":"8",
    "gn:asciiname":"Kebunkoong",
    "gn:country_code":"ID",
    "gn:dem":538,
    "gn:feature_class":"P",
    "gn:feature_code":"PPL",
    "gn:name":"Kebunkoong",
    "gn:population":0,
    "gn:timezone":"Asia/Jakarta",
    "iso:country":"ID",
    "name:ind_x_preferred":[
        "Kebunkoong"
    ],
    "wof:name":"Kebunkoong",
    "wof:placetype":"locality"
},
  "geometry": {"coordinates":[113.9259,-8.1111],"type":"Point"}
}