{
  "type": "Feature",
  "properties": {
    "gn:admin1_code":"18.0",
    "gn:asciiname":"Mehanggalu",
    "gn:country_code":"ID",
    "gn:dem":43,
    "gn:feature_class":"P",
    "gn:feature_code":"PPL",
    "gn:name":"Mehanggalu",
    "gn:population":0,
    "gn:timezone":"Asia/Makassar",
    "iso:country":"ID",
    "name:ind_x_preferred":[
        "Mehanggalu"
    ],
    "wof:name":"Mehanggalu",
    "wof:placetype":"locality"
},
  "geometry": {"coordinates":[119.45650000000001,-9.6917],"type":"Point"}
}