{
  "type": "Feature",
  "properties": {
    "gn:admin1_code":"30",
    "gn:asciiname":"Dangdeur",
    "gn:country_code":"ID",
    "gn:dem":696,
    "gn:feature_class":"P",
    "gn:feature_code":"PPL",
    "gn:name":"Dangdeur",
    "gn:population":0,
    "gn:timezone":"Asia/Jakarta",
    "iso:country":"ID",
    "wof:name":"Dangdeur",
    "wof:placetype":"locality"
},
  "geometry": {"coordinates":[107.56194000000001,-7.05306],"type":"Point"}
}