{
  "type": "Feature",
  "properties": {
    "gn:admin1_code":"18.0",
    "gn:asciiname":"Melo",
    "gn:country_code":"ID",
    "gn:dem":108,
    "gn:feature_class":"P",
    "gn:feature_code":"PPL",
    "gn:name":"Melo",
    "gn:population":0,
    "gn:timezone":"Asia/Makassar",
    "iso:country":"ID",
    "name:bul_x_preferred":[
        "\u041c\u0435\u043b\u043e"
    ],
    "name:cat_x_preferred":[
        "Melo"
    ],
    "name:ceb_x_preferred":[
        "Melo"
    ],
    "name:deu_x_preferred":[
        "Melo"
    ],
    "name:fin_x_preferred":[
        "Melo"
    ],
    "name:fra_x_preferred":[
        "Melo"
    ],
    "name:glg_x_preferred":[
        "Melo"
    ],
    "name:heb_x_preferred":[
        "\u05de\u05dc\u05d5"
    ],
    "name:hun_x_preferred":[
        "Melo"
    ],
    "name:hye_x_preferred":[
        "\u0544\u0565\u056c\u0578"
    ],
    "name:ind_x_preferred":[
        "Melo"
    ],
    "name:ita_x_preferred":[
        "Melo"
    ],
    "name:lit_x_preferred":[
        "Melo"
    ],
    "name:mlg_x_preferred":[
        "Melo"
    ],
    "name:nld_x_preferred":[
        "Melo"
    ],
    "name:pol_x_preferred":[
        "Melo"
    ],
    "name:por_x_preferred":[
        "Melo"
    ],
    "name:rus_x_preferred":[
        "\u041c\u0435\u043b\u043e"
    ],
    "name:spa_x_preferred":[
        "Melo"
    ],
    "name:swe_x_preferred":[
        "Melo"
    ],
    "name:ukr_x_preferred":[
        "\u041c\u0435\u043b\u043e"
    ],
    "wof:lang_x_official":[
        "ind"
    ],
    "wof:lang_x_spoken":[
        "ind",
        "eng"
    ],
    "wof:name":"Melo",
    "wof:placetype":"locality"
},
  "geometry": {"coordinates":[120.39830000000001,-8.7974],"type":"Point"}
}