{
  "type": "Feature",
  "properties": {
    "gn:admin1_code":"18.0",
    "gn:asciiname":"Kawaliok",
    "gn:country_code":"ID",
    "gn:dem":502,
    "gn:feature_class":"P",
    "gn:feature_code":"PPL",
    "gn:name":"Kawaliok",
    "gn:population":0,
    "gn:timezone":"Asia/Makassar",
    "iso:country":"ID",
    "name:ind_x_preferred":[
        "Kawaliok"
    ],
    "wof:name":"Kawaliok",
    "wof:placetype":"locality"
},
  "geometry": {"coordinates":[120.76439999999999,-8.7727],"type":"Point"}
}