{
  "type": "Feature",
  "properties": {
    "gn:admin1_code":"8",
    "gn:asciiname":"Sundulrejo",
    "gn:country_code":"ID",
    "gn:dem":217,
    "gn:feature_class":"P",
    "gn:feature_code":"PPL",
    "gn:name":"Sundulrejo",
    "gn:population":0,
    "gn:timezone":"Asia/Jakarta",
    "iso:country":"ID",
    "name:ind_x_preferred":[
        "Sundulrejo"
    ],
    "wof:name":"Sundulrejo",
    "wof:placetype":"locality"
},
  "geometry": {"coordinates":[111.36861,-7.70806],"type":"Point"}
}