{
  "type": "Feature",
  "properties": {
    "gn:admin1_code":"24",
    "gn:asciiname":"Sawah",
    "gn:country_code":"ID",
    "gn:dem":397,
    "gn:feature_class":"P",
    "gn:feature_code":"PPL",
    "gn:name":"Sawah",
    "gn:population":0,
    "gn:timezone":"Asia/Jakarta",
    "iso:country":"ID",
    "name:ind_x_preferred":[
        "Sawah"
    ],
    "wof:name":"Sawah",
    "wof:placetype":"locality"
},
  "geometry": {"coordinates":[99.92400000000001,0.1522],"type":"Point"}
}