{
  "type": "Feature",
  "properties": {
    "gn:admin1_code":"30",
    "gn:asciiname":"Leungis Kidul",
    "gn:country_code":"ID",
    "gn:dem":483,
    "gn:feature_class":"P",
    "gn:feature_code":"PPL",
    "gn:name":"Leungis Kidul",
    "gn:population":0,
    "gn:timezone":"Asia/Jakarta",
    "iso:country":"ID",
    "name:ind_x_preferred":[
        "Leungis Kidul"
    ],
    "wof:name":"Leungis Kidul",
    "wof:placetype":"locality"
},
  "geometry": {"coordinates":[106.80444,-6.70861],"type":"Point"}
}