{
  "type": "Feature",
  "properties": {
    "gn:admin1_code":"7.0",
    "gn:asciiname":"Capar",
    "gn:country_code":"ID",
    "gn:dem":804,
    "gn:feature_class":"P",
    "gn:feature_code":"PPLA4",
    "gn:name":"Capar",
    "gn:population":0,
    "gn:timezone":"Asia/Jakarta",
    "iso:country":"ID",
    "name:ind_x_preferred":[
        "Capar"
    ],
    "name:und_x_variant":[
        "Tjapar",
        "Capar"
    ],
    "wof:lang_x_official":[
        "ind"
    ],
    "wof:lang_x_spoken":[
        "ind",
        "eng"
    ],
    "wof:name":"Capar",
    "wof:placetype":"locality"
},
  "geometry": {"coordinates":[108.7338,-7.1192],"type":"Point"}
}