{
  "type": "Feature",
  "properties": {
    "gn:admin1_code":"17.0",
    "gn:asciiname":"Wingku",
    "gn:country_code":"ID",
    "gn:dem":180,
    "gn:feature_class":"P",
    "gn:feature_code":"PPL",
    "gn:name":"Wingku",
    "gn:population":0,
    "gn:timezone":"Asia/Makassar",
    "iso:country":"ID",
    "name:ind_x_preferred":[
        "Wingku"
    ],
    "name:und_x_variant":[
        "Wingkoe"
    ],
    "wof:lang_x_official":[
        "ind"
    ],
    "wof:lang_x_spoken":[
        "ind",
        "eng"
    ],
    "wof:name":"Wingku",
    "wof:placetype":"locality"
},
  "geometry": {"coordinates":[118.62238000000001,-8.70511],"type":"Point"}
}