{
  "type": "Feature",
  "properties": {
    "gn:admin1_code":"7",
    "gn:asciiname":"Condong",
    "gn:country_code":"ID",
    "gn:dem":307,
    "gn:feature_class":"P",
    "gn:feature_code":"PPL",
    "gn:name":"Condong",
    "gn:population":0,
    "gn:timezone":"Asia/Jakarta",
    "iso:country":"ID",
    "name:ara_x_preferred":[
        "\u0631\u0642\u0635\u0629 \u0634\u0646\u062f\u0648\u0646\u063a"
    ],
    "name:ind_x_preferred":[
        "Condong"
    ],
    "wof:lang_x_official":[
        "ind"
    ],
    "wof:lang_x_spoken":[
        "ind",
        "eng"
    ],
    "wof:name":"Condong",
    "wof:placetype":"locality"
},
  "geometry": {"coordinates":[109.7846,-7.0172],"type":"Point"}
}