{
  "type": "Feature",
  "properties": {
    "gn:admin1_code":"10",
    "gn:asciiname":"Plasan",
    "gn:country_code":"ID",
    "gn:dem":149,
    "gn:feature_class":"P",
    "gn:feature_code":"PPL",
    "gn:name":"Plasan",
    "gn:population":0,
    "gn:timezone":"Asia/Jakarta",
    "iso:country":"ID",
    "name:ara_x_preferred":[
        "\u0628\u0644\u0633\u0627\u0646 \u0633\u0627\u0633\u0627"
    ],
    "name:azb_x_preferred":[
        "\u067e\u0644\u0627\u0633\u0627\u0646"
    ],
    "name:deu_x_preferred":[
        "Plasan Sasa"
    ],
    "name:fas_x_preferred":[
        "\u067e\u0644\u0627\u0633\u0627\u0646"
    ],
    "name:heb_x_preferred":[
        "\u05e4\u05dc\u05e1\u05df \u05e1\u05d0\u05e1\u05d0"
    ],
    "name:nor_x_preferred":[
        "Plasan"
    ],
    "wof:name":"Plasan",
    "wof:placetype":"locality"
},
  "geometry": {"coordinates":[110.59028000000001,-7.80833],"type":"Point"}
}