{
  "type": "Feature",
  "properties": {
    "gn:admin1_code":"10",
    "gn:asciiname":"Pengkol Tiga",
    "gn:country_code":"ID",
    "gn:dem":173,
    "gn:feature_class":"P",
    "gn:feature_code":"PPL",
    "gn:name":"Pengkol Tiga",
    "gn:population":0,
    "gn:timezone":"Asia/Jakarta",
    "iso:country":"ID",
    "wof:name":"Pengkol Tiga",
    "wof:placetype":"locality"
},
  "geometry": {"coordinates":[110.68416999999999,-7.92],"type":"Point"}
}