{
  "type": "Feature",
  "properties": {
    "gn:admin1_code":"11.0",
    "gn:asciiname":"Miyapa",
    "gn:country_code":"ID",
    "gn:dem":34,
    "gn:feature_class":"P",
    "gn:feature_code":"PPL",
    "gn:name":"Miyapa",
    "gn:population":0,
    "gn:timezone":"Asia/Pontianak",
    "iso:country":"ID",
    "name:ind_x_preferred":[
        "Miyapa"
    ],
    "wof:name":"Miyapa",
    "wof:placetype":"locality"
},
  "geometry": {"coordinates":[112.82787,0.79629],"type":"Point"}
}