{
  "type": "Feature",
  "properties": {
    "gn:admin1_code":"8.0",
    "gn:asciiname":"Telagapule",
    "gn:country_code":"ID",
    "gn:dem":160,
    "gn:feature_class":"P",
    "gn:feature_code":"PPL",
    "gn:name":"Telagapule",
    "gn:population":0,
    "gn:timezone":"Asia/Jakarta",
    "iso:country":"ID",
    "name:ind_x_preferred":[
        "Telagapule"
    ],
    "wof:name":"Telagapule",
    "wof:placetype":"locality"
},
  "geometry": {"coordinates":[112.0211,-6.9467],"type":"Point"}
}