{
  "type": "Feature",
  "properties": {
    "gn:admin1_code":"2",
    "gn:asciiname":"Banjar Pegeringsingan",
    "gn:country_code":"ID",
    "gn:dem":91,
    "gn:feature_class":"P",
    "gn:feature_code":"PPLA4",
    "gn:name":"Banjar Pegeringsingan",
    "gn:population":0,
    "gn:timezone":"Asia/Makassar",
    "iso:country":"ID",
    "name:ind_x_preferred":[
        "Banjar Pegeringsingan"
    ],
    "wof:name":"Banjar Pegeringsingan",
    "wof:placetype":"locality"
},
  "geometry": {"coordinates":[115.5671,-8.4758],"type":"Point"}
}