{
  "type": "Feature",
  "properties": {
    "gn:admin1_code":"30.0",
    "gn:asciiname":"Sukamerna",
    "gn:country_code":"ID",
    "gn:dem":12,
    "gn:feature_class":"P",
    "gn:feature_code":"PPL",
    "gn:name":"Sukamerna",
    "gn:population":0,
    "gn:timezone":"Asia/Jakarta",
    "iso:country":"ID",
    "name:ind_x_preferred":[
        "Sukamerna"
    ],
    "wof:name":"Sukamerna",
    "wof:placetype":"locality"
},
  "geometry": {"coordinates":[108.49778000000001,-6.69194],"type":"Point"}
}