{
  "type": "Feature",
  "properties": {
    "gn:admin1_code":"30.0",
    "gn:asciiname":"Bantarmunding",
    "gn:country_code":"ID",
    "gn:dem":173,
    "gn:feature_class":"P",
    "gn:feature_code":"PPLA4",
    "gn:name":"Bantarmunding",
    "gn:population":0,
    "gn:timezone":"Asia/Jakarta",
    "iso:country":"ID",
    "name:ind_x_preferred":[
        "Bantarmunding"
    ],
    "wof:name":"Bantarmunding",
    "wof:placetype":"locality"
},
  "geometry": {"coordinates":[107.42870000000001,-7.4796],"type":"Point"}
}