{
  "type": "Feature",
  "properties": {
    "gn:admin1_code":"8.0",
    "gn:asciiname":"Penjaitan",
    "gn:cc2":"ID",
    "gn:country_code":"ID",
    "gn:dem":211,
    "gn:feature_class":"P",
    "gn:feature_code":"PPL",
    "gn:name":"Penjaitan",
    "gn:population":0,
    "gn:timezone":"Asia/Jakarta",
    "iso:country":"ID",
    "name:und_x_variant":[
        "Pendjaitan",
        "Penjaitan"
    ],
    "wof:lang_x_official":[
        "ind"
    ],
    "wof:lang_x_spoken":[
        "ind",
        "eng"
    ],
    "wof:name":"Penjaitan",
    "wof:placetype":"locality"
},
  "geometry": {"coordinates":[114.32167,-7.88278],"type":"Point"}
}