{
  "type": "Feature",
  "properties": {
    "gn:admin1_code":"1",
    "gn:asciiname":"Jamburkulam",
    "gn:country_code":"ID",
    "gn:dem":1361,
    "gn:feature_class":"P",
    "gn:feature_code":"PPL",
    "gn:name":"Jamburkulam",
    "gn:population":0,
    "gn:timezone":"Asia/Jakarta",
    "iso:country":"ID",
    "name:ind_x_preferred":[
        "Jamburkulam"
    ],
    "name:und_x_variant":[
        "Djamburkulam"
    ],
    "wof:name":"Jamburkulam",
    "wof:placetype":"locality"
},
  "geometry": {"coordinates":[96.655,4.4388],"type":"Point"}
}