{
  "type": "Feature",
  "properties": {
    "gn:admin1_code":"18",
    "gn:asciiname":"Kawau",
    "gn:country_code":"ID",
    "gn:dem":501,
    "gn:feature_class":"P",
    "gn:feature_code":"PPL",
    "gn:name":"Kawau",
    "gn:population":0,
    "gn:timezone":"Asia/Makassar",
    "iso:country":"ID",
    "name:ind_x_preferred":[
        "Kawau"
    ],
    "wof:name":"Kawau",
    "wof:placetype":"locality"
},
  "geometry": {"coordinates":[120.0766,-9.7992],"type":"Point"}
}