{
  "type": "Feature",
  "properties": {
    "gn:admin1_code":"7.0",
    "gn:asciiname":"Blado",
    "gn:country_code":"ID",
    "gn:dem":545,
    "gn:feature_class":"P",
    "gn:feature_code":"PPL",
    "gn:name":"Blado",
    "gn:population":0,
    "gn:timezone":"Asia/Jakarta",
    "iso:country":"ID",
    "name:ind_x_preferred":[
        "Blado"
    ],
    "wof:name":"Blado",
    "wof:placetype":"locality"
},
  "geometry": {"coordinates":[109.83410000000001,-7.0707],"type":"Point"}
}