{
  "type": "Feature",
  "properties": {
    "gn:admin1_code":"31",
    "gn:asciiname":"Matalibaru",
    "gn:country_code":"ID",
    "gn:dem":252,
    "gn:feature_class":"P",
    "gn:feature_code":"PPL",
    "gn:name":"Matalibaru",
    "gn:population":0,
    "gn:timezone":"Asia/Makassar",
    "iso:country":"ID",
    "name:ind_x_preferred":[
        "Matalibaru"
    ],
    "wof:name":"Matalibaru",
    "wof:placetype":"locality"
},
  "geometry": {"coordinates":[124.2701,0.5803],"type":"Point"}
}