{
  "type": "Feature",
  "properties": {
    "gn:admin1_code":"30",
    "gn:asciiname":"Cilastari Dua",
    "gn:cc2":"ID",
    "gn:country_code":"ID",
    "gn:dem":1220,
    "gn:feature_class":"P",
    "gn:feature_code":"PPL",
    "gn:name":"Cilastari Dua",
    "gn:population":0,
    "gn:timezone":"Asia/Jakarta",
    "iso:country":"ID",
    "name:und_x_variant":[
        "Tjilastari 2",
        "Cilastari Dua"
    ],
    "wof:lang_x_official":[
        "ind"
    ],
    "wof:lang_x_spoken":[
        "ind",
        "eng"
    ],
    "wof:name":"Cilastari Dua",
    "wof:placetype":"locality"
},
  "geometry": {"coordinates":[107.56444,-6.79528],"type":"Point"}
}