{
  "type": "Feature",
  "properties": {
    "gn:admin1_code":"8.0",
    "gn:asciiname":"Siding",
    "gn:country_code":"ID",
    "gn:dem":31,
    "gn:feature_class":"P",
    "gn:feature_code":"PPLA4",
    "gn:name":"Siding",
    "gn:population":0,
    "gn:timezone":"Asia/Jakarta",
    "iso:country":"ID",
    "name:deu_x_preferred":[
        "Holzfassade"
    ],
    "name:fra_x_preferred":[
        "Bardage"
    ],
    "name:ind_x_preferred":[
        "Siding"
    ],
    "name:pol_x_preferred":[
        "Siding"
    ],
    "name:rus_x_preferred":[
        "\u0421\u0430\u0439\u0434\u0438\u043d\u0433"
    ],
    "name:tat_x_preferred":[
        "\u0421\u0430\u0439\u0434\u0438\u043d\u0433"
    ],
    "wof:lang_x_official":[
        "ind"
    ],
    "wof:lang_x_spoken":[
        "ind",
        "eng"
    ],
    "wof:name":"Siding",
    "wof:placetype":"locality"
},
  "geometry": {"coordinates":[111.73099999999999,-6.799],"type":"Point"}
}