{
  "type": "Feature",
  "properties": {
    "gn:admin1_code":"7",
    "gn:asciiname":"Clorong",
    "gn:country_code":"ID",
    "gn:dem":294,
    "gn:feature_class":"P",
    "gn:feature_code":"PPL",
    "gn:name":"Clorong",
    "gn:population":0,
    "gn:timezone":"Asia/Jakarta",
    "iso:country":"ID",
    "name:ind_x_preferred":[
        "Clorong"
    ],
    "wof:name":"Clorong",
    "wof:placetype":"locality"
},
  "geometry": {"coordinates":[109.98917,-7.62472],"type":"Point"}
}