{
  "type": "Feature",
  "properties": {
    "gn:admin1_code":"15.0",
    "gn:asciiname":"Probolinggo",
    "gn:country_code":"ID",
    "gn:dem":133,
    "gn:feature_class":"P",
    "gn:feature_code":"PPL",
    "gn:name":"Probolinggo",
    "gn:population":0,
    "gn:timezone":"Asia/Jakarta",
    "iso:country":"ID",
    "name:afr_x_preferred":[
        "Probolinggo"
    ],
    "name:ara_x_preferred":[
        "\u0628\u0631\u0648\u0628\u0648\u0644\u064a\u0646\u063a\u0648"
    ],
    "name:ceb_x_preferred":[
        "Probolinggo"
    ],
    "name:deu_x_preferred":[
        "Probolinggo"
    ],
    "name:fas_x_preferred":[
        "\u067e\u0631\u0648\u0628\u0648\u0644\u06cc\u0646\u06af\u0648"
    ],
    "name:fin_x_preferred":[
        "Probolinggo"
    ],
    "name:fra_x_preferred":[
        "Probolinggo"
    ],
    "name:fry_x_preferred":[
        "Probolinggo"
    ],
    "name:heb_x_preferred":[
        "\u05e4\u05e8\u05d5\u05d1\u05d5\u05dc\u05d9\u05e0\u05d2\u05d5"
    ],
    "name:hin_x_preferred":[
        "\u092a\u094d\u0930\u094b\u092c\u094b\u0932\u093f\u0902\u0917\u094b"
    ],
    "name:hun_x_preferred":[
        "Probolinggo"
    ],
    "name:ind_x_preferred":[
        "Probolinggo"
    ],
    "name:ind_x_variant":[
        "Kota Probolinggo"
    ],
    "name:ita_x_preferred":[
        "Probolinggo"
    ],
    "name:jav_x_preferred":[
        "Kutha Prabalingga"
    ],
    "name:jpn_x_preferred":[
        "\u30d7\u30ed\u30dc\u30ea\u30f3\u30b4"
    ],
    "name:kat_x_preferred":[
        "\u10de\u10e0\u10dd\u10d1\u10dd\u10da\u10d8\u10dc\u10d2\u10dd"
    ],
    "name:kor_x_preferred":[
        "\ud504\ub85c\ubcfc\ub9c1\uace0"
    ],
    "name:mlg_x_preferred":[
        "Kota Probolinggo"
    ],
    "name:nld_x_preferred":[
        "Probolinggo"
    ],
    "name:nor_x_preferred":[
        "Probolinggo"
    ],
    "name:pol_x_preferred":[
        "Probolinggo"
    ],
    "name:ron_x_preferred":[
        "Probolinggo"
    ],
    "name:rus_x_preferred":[
        "\u041f\u0440\u043e\u0431\u043e\u043b\u0438\u043d\u0433\u043e"
    ],
    "name:sun_x_preferred":[
        "Kota Probolinggo"
    ],
    "name:swe_x_preferred":[
        "Probolinggo"
    ],
    "name:tam_x_preferred":[
        "\u0baa\u0bc1\u0bb0\u0bca\u0baa\u0bcb\u0bb2\u0bbf\u0b99\u0bcd\u0b95\u0bcb"
    ],
    "name:war_x_preferred":[
        "Probolinggo"
    ],
    "wof:lang_x_official":[
        "ind"
    ],
    "wof:lang_x_spoken":[
        "ind",
        "eng"
    ],
    "wof:name":"Probolinggo",
    "wof:placetype":"locality"
},
  "geometry": {"coordinates":[104.55916999999999,-4.61969],"type":"Point"}
}