{
  "type": "Feature",
  "properties": {
    "gn:admin1_code":"30.0",
    "gn:asciiname":"Kaum Kidul",
    "gn:country_code":"ID",
    "gn:dem":470,
    "gn:feature_class":"P",
    "gn:feature_code":"PPL",
    "gn:name":"Kaum Kidul",
    "gn:population":0,
    "gn:timezone":"Asia/Jakarta",
    "iso:country":"ID",
    "name:ind_x_preferred":[
        "Kaum Kidul"
    ],
    "wof:name":"Kaum Kidul",
    "wof:placetype":"locality"
},
  "geometry": {"coordinates":[108.188,-7.2206],"type":"Point"}
}