{
  "type": "Feature",
  "properties": {
    "gn:admin1_code":"33",
    "gn:asciiname":"Bugel",
    "gn:country_code":"ID",
    "gn:dem":26,
    "gn:feature_class":"P",
    "gn:feature_code":"PPL",
    "gn:name":"Bugel",
    "gn:population":0,
    "gn:timezone":"Asia/Jakarta",
    "iso:country":"ID",
    "name:ind_x_preferred":[
        "Bugel"
    ],
    "name:und_x_variant":[
        "Bugel 1",
        "Bugel Satu"
    ],
    "wof:name":"Bugel",
    "wof:placetype":"locality"
},
  "geometry": {"coordinates":[106.3185,-6.2514],"type":"Point"}
}