{
  "type": "Feature",
  "properties": {
    "gn:admin1_code":"30.0",
    "gn:asciiname":"Cinyiruan",
    "gn:cc2":"ID",
    "gn:country_code":"ID",
    "gn:dem":1567,
    "gn:feature_class":"P",
    "gn:feature_code":"PPL",
    "gn:name":"Cinyiruan",
    "gn:population":0,
    "gn:timezone":"Asia/Jakarta",
    "iso:country":"ID",
    "name:und_x_variant":[
        "Tjinjiruan",
        "Cinyiruan"
    ],
    "wof:lang_x_official":[
        "ind"
    ],
    "wof:lang_x_spoken":[
        "ind",
        "eng"
    ],
    "wof:name":"Cinyiruan",
    "wof:placetype":"locality"
},
  "geometry": {"coordinates":[107.60083,-7.17389],"type":"Point"}
}