{
  "type": "Feature",
  "properties": {
    "gn:admin1_code":"28.0",
    "gn:asciiname":"Tuni",
    "gn:country_code":"ID",
    "gn:dem":261,
    "gn:feature_class":"P",
    "gn:feature_code":"PPL",
    "gn:name":"Tuni",
    "gn:population":0,
    "gn:timezone":"Asia/Jayapura",
    "iso:country":"ID",
    "name:bpy_x_preferred":[
        "\u09a4\u09c1\u09a8\u09bf"
    ],
    "name:ceb_x_preferred":[
        "Tuni"
    ],
    "name:ind_x_preferred":[
        "Tuni"
    ],
    "name:ita_x_preferred":[
        "Tuni"
    ],
    "name:msa_x_preferred":[
        "Tuni"
    ],
    "name:new_x_preferred":[
        "\u0924\u0941\u0928\u093f \u092e\u0923\u094d\u0921\u0932"
    ],
    "name:por_x_preferred":[
        "Tuni"
    ],
    "name:swe_x_preferred":[
        "Tuni"
    ],
    "name:tel_x_preferred":[
        "\u0c24\u0c41\u0c28\u0c3f"
    ],
    "name:tgl_x_preferred":[
        "Tuni"
    ],
    "name:und_x_variant":[
        "Toeni"
    ],
    "name:urd_x_preferred":[
        "\u062a\u0648\u0646\u06cc"
    ],
    "name:vie_x_preferred":[
        "Tuni"
    ],
    "wof:lang_x_official":[
        "ind"
    ],
    "wof:lang_x_spoken":[
        "ind",
        "eng"
    ],
    "wof:name":"Tuni",
    "wof:placetype":"locality"
},
  "geometry": {"coordinates":[128.20515,-3.73094],"type":"Point"}
}