{
  "type": "Feature",
  "properties": {
    "gn:admin1_code":"28.0",
    "gn:asciiname":"Tuni",
    "gn:country_code":"ID",
    "gn:dem":261,
    "gn:feature_class":"P",
    "gn:feature_code":"PPL",
    "gn:name":"Tuni",
    "gn:population":0,
    "gn:timezone":"Asia/Jayapura",
    "iso:country":"ID",
    "name:ind_x_preferred":[
        "Tuni"
    ],
    "name:und_x_variant":[
        "Toeni"
    ],
    "wof:name":"Tuni",
    "wof:placetype":"locality"
},
  "geometry": {"coordinates":[128.20515,-3.73094],"type":"Point"}
}