{
  "type": "Feature",
  "properties": {
    "gn:admin1_code":"8.0",
    "gn:asciiname":"Jerukgulung",
    "gn:country_code":"ID",
    "gn:dem":44,
    "gn:feature_class":"P",
    "gn:feature_code":"PPL",
    "gn:name":"Jerukgulung",
    "gn:population":0,
    "gn:timezone":"Asia/Jakarta",
    "iso:country":"ID",
    "name:ind_x_preferred":[
        "Jerukgulung"
    ],
    "wof:name":"Jerukgulung",
    "wof:placetype":"locality"
},
  "geometry": {"coordinates":[112.0652,-6.973],"type":"Point"}
}