{
  "type": "Feature",
  "properties": {
    "gn:admin1_code":"7.0",
    "gn:asciiname":"Dares",
    "gn:country_code":"ID",
    "gn:dem":293,
    "gn:feature_class":"P",
    "gn:feature_code":"PPL",
    "gn:name":"Dares",
    "gn:population":0,
    "gn:timezone":"Asia/Jakarta",
    "iso:country":"ID",
    "name:ind_x_preferred":[
        "Dares"
    ],
    "wof:name":"Dares",
    "wof:placetype":"locality"
},
  "geometry": {"coordinates":[109.40555999999999,-7.52056],"type":"Point"}
}