{
  "type": "Feature",
  "properties": {
    "gn:admin1_code":"30",
    "gn:asciiname":"Pulo",
    "gn:country_code":"ID",
    "gn:dem":135,
    "gn:feature_class":"P",
    "gn:feature_code":"PPL",
    "gn:name":"Pulo",
    "gn:population":0,
    "gn:timezone":"Asia/Jakarta",
    "iso:country":"ID",
    "name:ceb_x_preferred":[
        "Pulo"
    ],
    "name:ind_x_preferred":[
        "Pulo"
    ],
    "name:ita_x_preferred":[
        "Pulo"
    ],
    "name:nld_x_preferred":[
        "Pulo"
    ],
    "name:swe_x_preferred":[
        "Pulo"
    ],
    "wof:lang_x_official":[
        "ind"
    ],
    "wof:lang_x_spoken":[
        "ind",
        "eng"
    ],
    "wof:name":"Pulo",
    "wof:placetype":"locality"
},
  "geometry": {"coordinates":[106.8075,-6.48361],"type":"Point"}
}