{
  "type": "Feature",
  "properties": {
    "gn:admin1_code":"26",
    "gn:asciiname":"Kebonbaru",
    "gn:country_code":"ID",
    "gn:dem":5,
    "gn:feature_class":"P",
    "gn:feature_code":"PPL",
    "gn:name":"Kebonbaru",
    "gn:population":0,
    "gn:timezone":"Asia/Jakarta",
    "iso:country":"ID",
    "name:ind_x_preferred":[
        "Kebonbaru"
    ],
    "wof:name":"Kebonbaru",
    "wof:placetype":"locality"
},
  "geometry": {"coordinates":[98.6234,3.7088],"type":"Point"}
}