{
  "type": "Feature",
  "properties": {
    "gn:admin1_code":"0.0",
    "gn:asciiname":"Gandasoli",
    "gn:country_code":"ID",
    "gn:dem":823,
    "gn:feature_class":"P",
    "gn:feature_code":"PPL",
    "gn:name":"Gandasoli",
    "gn:population":0,
    "gn:timezone":"Asia/Jakarta",
    "iso:country":"ID",
    "wof:name":"Gandasoli",
    "wof:placetype":"locality"
},
  "geometry": {"coordinates":[108.45,-6.93333],"type":"Point"}
}