{
  "type": "Feature",
  "properties": {
    "gn:admin1_code":"7",
    "gn:asciiname":"Tengger",
    "gn:country_code":"ID",
    "gn:dem":72,
    "gn:feature_class":"P",
    "gn:feature_code":"PPL",
    "gn:name":"Tengger",
    "gn:population":0,
    "gn:timezone":"Asia/Jakarta",
    "iso:country":"ID",
    "name:ind_x_preferred":[
        "Tengger"
    ],
    "wof:name":"Tengger",
    "wof:placetype":"locality"
},
  "geometry": {"coordinates":[111.18306,-7.15389],"type":"Point"}
}