{
  "type": "Feature",
  "properties": {
    "gn:admin1_code":"18.0",
    "gn:asciiname":"Olin",
    "gn:country_code":"ID",
    "gn:dem":556,
    "gn:feature_class":"P",
    "gn:feature_code":"PPLA4",
    "gn:name":"Olin",
    "gn:population":0,
    "gn:timezone":"Asia/Makassar",
    "iso:country":"ID",
    "name:ceb_x_preferred":[
        "Olin"
    ],
    "name:deu_x_preferred":[
        "Olin"
    ],
    "name:fra_x_preferred":[
        "Olin"
    ],
    "name:ind_x_preferred":[
        "Olin"
    ],
    "name:ita_x_preferred":[
        "Olin"
    ],
    "name:jpn_x_preferred":[
        "\u30aa\u30ea\u30f3"
    ],
    "name:pol_x_preferred":[
        "Olin"
    ],
    "name:rus_x_preferred":[
        "\u041e\u043b\u0438\u043d"
    ],
    "wof:lang_x_official":[
        "ind"
    ],
    "wof:lang_x_spoken":[
        "ind",
        "eng"
    ],
    "wof:name":"Olin",
    "wof:placetype":"locality"
},
  "geometry": {"coordinates":[124.5989,-9.9613],"type":"Point"}
}