{
  "type": "Feature",
  "properties": {
    "gn:admin1_code":"18.0",
    "gn:asciiname":"Olin",
    "gn:country_code":"ID",
    "gn:dem":556,
    "gn:feature_class":"P",
    "gn:feature_code":"PPLA4",
    "gn:name":"Olin",
    "gn:population":0,
    "gn:timezone":"Asia/Makassar",
    "iso:country":"ID",
    "name:ind_x_preferred":[
        "Olin"
    ],
    "wof:name":"Olin",
    "wof:placetype":"locality"
},
  "geometry": {"coordinates":[124.5989,-9.9613],"type":"Point"}
}