{
  "type": "Feature",
  "properties": {
    "gn:admin1_code":"26",
    "gn:asciiname":"Kualasawa",
    "gn:country_code":"ID",
    "gn:dem":214,
    "gn:feature_class":"P",
    "gn:feature_code":"PPL",
    "gn:name":"Kualasawa",
    "gn:population":0,
    "gn:timezone":"Asia/Jakarta",
    "iso:country":"ID",
    "name:ind_x_preferred":[
        "Kualasawa"
    ],
    "wof:name":"Kualasawa",
    "wof:placetype":"locality"
},
  "geometry": {"coordinates":[99.20569999999999,2.8981],"type":"Point"}
}