{
  "type": "Feature",
  "properties": {
    "gn:admin1_code":"38",
    "gn:asciiname":"Baruttung",
    "gn:country_code":"ID",
    "gn:dem":87,
    "gn:feature_class":"P",
    "gn:feature_code":"PPL",
    "gn:name":"Baruttung",
    "gn:population":0,
    "gn:timezone":"Asia/Makassar",
    "iso:country":"ID",
    "name:ind_x_preferred":[
        "Baruttung"
    ],
    "wof:name":"Baruttung",
    "wof:placetype":"locality"
},
  "geometry": {"coordinates":[120.20059999999999,-5.1103],"type":"Point"}
}