{
  "type": "Feature",
  "properties": {
    "gn:admin1_code":"41",
    "gn:asciiname":"Garogo",
    "gn:country_code":"ID",
    "gn:dem":31,
    "gn:feature_class":"P",
    "gn:feature_code":"PPL",
    "gn:name":"Garogo",
    "gn:population":0,
    "gn:timezone":"Asia/Makassar",
    "iso:country":"ID",
    "name:ind_x_preferred":[
        "Garogo"
    ],
    "wof:name":"Garogo",
    "wof:placetype":"locality"
},
  "geometry": {"coordinates":[118.9572,-3.5476],"type":"Point"}
}