{
  "type": "Feature",
  "properties": {
    "gn:admin1_code":"30.0",
    "gn:asciiname":"Tambun",
    "gn:country_code":"ID",
    "gn:dem":22,
    "gn:feature_class":"P",
    "gn:feature_code":"PPL",
    "gn:name":"Tambun",
    "gn:population":0,
    "gn:timezone":"Asia/Jakarta",
    "iso:country":"ID",
    "name:ind_x_preferred":[
        "Tambun"
    ],
    "name:und_x_variant":[
        "Tambun-bodjongrongkong",
        "Tamboen-bodjongrongkong",
        "Tambun-bojongrongkong"
    ],
    "wof:name":"Tambun",
    "wof:placetype":"locality"
},
  "geometry": {"coordinates":[106.947,-6.24],"type":"Point"}
}