{
  "type": "Feature",
  "properties": {
    "gn:admin1_code":"32.0",
    "gn:asciiname":"Talangtebingtinggi",
    "gn:country_code":"ID",
    "gn:dem":47,
    "gn:feature_class":"P",
    "gn:feature_code":"PPL",
    "gn:name":"Talangtebingtinggi",
    "gn:population":0,
    "gn:timezone":"Asia/Jakarta",
    "iso:country":"ID",
    "name:ind_x_preferred":[
        "Talangtebingtinggi"
    ],
    "wof:name":"Talangtebingtinggi",
    "wof:placetype":"locality"
},
  "geometry": {"coordinates":[103.0436,-2.526],"type":"Point"}
}