{
  "type": "Feature",
  "properties": {
    "gn:admin1_code":"36.0",
    "gn:asciiname":"Erma",
    "gn:country_code":"ID",
    "gn:dem":5,
    "gn:feature_class":"P",
    "gn:feature_code":"PPL",
    "gn:name":"Erma",
    "gn:population":0,
    "gn:timezone":"Asia/Jayapura",
    "iso:country":"ID",
    "name:ceb_x_preferred":[
        "Erma"
    ],
    "name:deu_x_preferred":[
        "Erma"
    ],
    "name:ind_x_preferred":[
        "Erma"
    ],
    "name:ind_x_variant":[
        "Erna"
    ],
    "name:ita_x_preferred":[
        "Erma"
    ],
    "name:nld_x_preferred":[
        "Erma"
    ],
    "wof:lang_x_official":[
        "ind"
    ],
    "wof:lang_x_spoken":[
        "ind",
        "eng"
    ],
    "wof:name":"Erma",
    "wof:placetype":"locality"
},
  "geometry": {"coordinates":[138.21749,-5.15839],"type":"Point"}
}