{
  "type": "Feature",
  "properties": {
    "gn:admin1_code":"37.0",
    "gn:asciiname":"Kotaintan",
    "gn:country_code":"ID",
    "gn:dem":50,
    "gn:feature_class":"P",
    "gn:feature_code":"PPL",
    "gn:name":"Kotaintan",
    "gn:population":0,
    "gn:timezone":"Asia/Jakarta",
    "iso:country":"ID",
    "name:ind_x_preferred":[
        "Kotaintan"
    ],
    "name:und_x_variant":[
        "Kotainten"
    ],
    "wof:name":"Kotaintan",
    "wof:placetype":"locality"
},
  "geometry": {"coordinates":[100.58459999999999,0.8044],"type":"Point"}
}