{
  "type": "Feature",
  "properties": {
    "gn:admin1_code":"38",
    "gn:asciiname":"Kassikassi",
    "gn:country_code":"ID",
    "gn:dem":220,
    "gn:feature_class":"P",
    "gn:feature_code":"PPL",
    "gn:name":"Kassikassi",
    "gn:population":0,
    "gn:timezone":"Asia/Makassar",
    "iso:country":"ID",
    "name:ind_x_preferred":[
        "Kassikassi"
    ],
    "wof:name":"Kassikassi",
    "wof:placetype":"locality"
},
  "geometry": {"coordinates":[119.7715,-5.1241],"type":"Point"}
}