{
  "type": "Feature",
  "properties": {
    "gn:admin1_code":"8",
    "gn:asciiname":"Jaddih Selatan Dua",
    "gn:country_code":"ID",
    "gn:dem":40,
    "gn:feature_class":"P",
    "gn:feature_code":"PPL",
    "gn:name":"Jaddih Selatan Dua",
    "gn:population":0,
    "gn:timezone":"Asia/Jakarta",
    "iso:country":"ID",
    "name:ind_x_preferred":[
        "Jaddih Selatan Dua"
    ],
    "wof:name":"Jaddih Selatan Dua",
    "wof:placetype":"locality"
},
  "geometry": {"coordinates":[112.7394,-7.0862],"type":"Point"}
}