{
  "type": "Feature",
  "properties": {
    "gn:admin1_code":"38",
    "gn:asciiname":"Matajang",
    "gn:country_code":"ID",
    "gn:dem":351,
    "gn:feature_class":"P",
    "gn:feature_code":"PPL",
    "gn:name":"Matajang",
    "gn:population":0,
    "gn:timezone":"Asia/Makassar",
    "iso:country":"ID",
    "name:ind_x_preferred":[
        "Matajang"
    ],
    "wof:name":"Matajang",
    "wof:placetype":"locality"
},
  "geometry": {"coordinates":[119.8115,-4.952],"type":"Point"}
}