{
  "type": "Feature",
  "properties": {
    "gn:admin1_code":"17",
    "gn:asciiname":"Laukrurung",
    "gn:country_code":"ID",
    "gn:dem":252,
    "gn:feature_class":"P",
    "gn:feature_code":"PPLA4",
    "gn:name":"Laukrurung",
    "gn:population":0,
    "gn:timezone":"Asia/Makassar",
    "iso:country":"ID",
    "name:ind_x_preferred":[
        "Laukrurung"
    ],
    "wof:name":"Laukrurung",
    "wof:placetype":"locality"
},
  "geometry": {"coordinates":[116.476,-8.6393],"type":"Point"}
}