{
  "type": "Feature",
  "properties": {
    "gn:admin1_code":"30",
    "gn:asciiname":"Panaruban",
    "gn:country_code":"ID",
    "gn:dem":878,
    "gn:feature_class":"P",
    "gn:feature_code":"PPL",
    "gn:name":"Panaruban",
    "gn:population":0,
    "gn:timezone":"Asia/Jakarta",
    "iso:country":"ID",
    "name:ind_x_preferred":[
        "Panaruban"
    ],
    "wof:name":"Panaruban",
    "wof:placetype":"locality"
},
  "geometry": {"coordinates":[107.63806,-6.71444],"type":"Point"}
}