{
  "type": "Feature",
  "properties": {
    "gn:admin1_code":"18.0",
    "gn:asciiname":"Kiuhala",
    "gn:country_code":"ID",
    "gn:dem":338,
    "gn:feature_class":"P",
    "gn:feature_code":"PPL",
    "gn:name":"Kiuhala",
    "gn:population":0,
    "gn:timezone":"Asia/Makassar",
    "iso:country":"ID",
    "name:ind_x_preferred":[
        "Kiuhala"
    ],
    "wof:name":"Kiuhala",
    "wof:placetype":"locality"
},
  "geometry": {"coordinates":[124.40300000000001,-9.9968],"type":"Point"}
}