{
  "type": "Feature",
  "properties": {
    "gn:admin1_code":"30",
    "gn:asciiname":"Labuhan",
    "gn:country_code":"ID",
    "gn:dem":30,
    "gn:feature_class":"P",
    "gn:feature_code":"PPL",
    "gn:name":"Labuhan",
    "gn:population":0,
    "gn:timezone":"Asia/Jakarta",
    "iso:country":"ID",
    "name:ind_x_preferred":[
        "Labuhan"
    ],
    "wof:name":"Labuhan",
    "wof:placetype":"locality"
},
  "geometry": {"coordinates":[107.92417,-6.49222],"type":"Point"}
}