{
  "type": "Feature",
  "properties": {
    "gn:admin1_code":"0.0",
    "gn:asciiname":"Rukua",
    "gn:country_code":"ID",
    "gn:dem":17,
    "gn:feature_class":"P",
    "gn:feature_code":"PPL",
    "gn:name":"Rukua",
    "gn:population":0,
    "gn:timezone":"Asia/Makassar",
    "iso:country":"ID",
    "name:und_x_variant":[
        "Rukus",
        "Roekoea",
        "Rukuwa",
        "Rukua"
    ],
    "wof:name":"Rukua",
    "wof:placetype":"locality"
},
  "geometry": {"coordinates":[124.03264,-5.90414],"type":"Point"}
}