{
  "type": "Feature",
  "properties": {
    "gn:admin1_code":"10.0",
    "gn:asciiname":"Melengan",
    "gn:country_code":"ID",
    "gn:dem":244,
    "gn:feature_class":"P",
    "gn:feature_code":"PPL",
    "gn:name":"Melengan",
    "gn:population":0,
    "gn:timezone":"Asia/Jakarta",
    "iso:country":"ID",
    "name:ind_x_preferred":[
        "Melengan"
    ],
    "wof:name":"Melengan",
    "wof:placetype":"locality"
},
  "geometry": {"coordinates":[110.63778000000001,-8.10611],"type":"Point"}
}