{
  "type": "Feature",
  "properties": {
    "gn:admin1_code":"26",
    "gn:asciiname":"Afdeling Sembilan",
    "gn:country_code":"ID",
    "gn:dem":108,
    "gn:feature_class":"P",
    "gn:feature_code":"PPL",
    "gn:name":"Afdeling Sembilan",
    "gn:population":0,
    "gn:timezone":"Asia/Jakarta",
    "iso:country":"ID",
    "name:ind_x_preferred":[
        "Afdeling Sembilan"
    ],
    "name:und_x_variant":[
        "Afdeling 9"
    ],
    "wof:lang_x_official":[
        "ind"
    ],
    "wof:lang_x_spoken":[
        "ind",
        "eng"
    ],
    "wof:name":"Afdeling Sembilan",
    "wof:placetype":"locality"
},
  "geometry": {"coordinates":[99.2067,3.1372],"type":"Point"}
}