{
  "type": "Feature",
  "properties": {
    "gn:admin1_code":"1",
    "gn:asciiname":"Lamcok",
    "gn:country_code":"ID",
    "gn:dem":11,
    "gn:feature_class":"P",
    "gn:feature_code":"PPL",
    "gn:name":"Lamcok",
    "gn:population":0,
    "gn:timezone":"Asia/Jakarta",
    "iso:country":"ID",
    "name:ind_x_preferred":[
        "Lamcok"
    ],
    "wof:name":"Lamcok",
    "wof:placetype":"locality"
},
  "geometry": {"coordinates":[95.26090000000001,5.4923],"type":"Point"}
}