{
  "type": "Feature",
  "properties": {
    "gn:admin1_code":"30",
    "gn:asciiname":"Sawah",
    "gn:country_code":"ID",
    "gn:dem":137,
    "gn:feature_class":"P",
    "gn:feature_code":"PPL",
    "gn:name":"Sawah",
    "gn:population":0,
    "gn:timezone":"Asia/Jakarta",
    "iso:country":"ID",
    "name:ara_x_preferred":[
        "\u0633\u0648\u0627\u062d"
    ],
    "name:arz_x_preferred":[
        "\u0633\u0648\u0627\u062d"
    ],
    "name:bul_x_preferred":[
        "\u0425\u0430\u0431\u0438\u0431\u0438"
    ],
    "wof:lang_x_official":[
        "ind"
    ],
    "wof:lang_x_spoken":[
        "ind",
        "eng"
    ],
    "wof:name":"Sawah",
    "wof:placetype":"locality"
},
  "geometry": {"coordinates":[106.79861,-6.485],"type":"Point"}
}