{
  "type": "Feature",
  "properties": {
    "gn:admin1_code":"36",
    "gn:asciiname":"Wania",
    "gn:country_code":"ID",
    "gn:dem":23,
    "gn:feature_class":"P",
    "gn:feature_code":"PPL",
    "gn:name":"Wania",
    "gn:population":0,
    "gn:timezone":"Asia/Jayapura",
    "iso:country":"ID",
    "name:ind_x_preferred":[
        "Wania"
    ],
    "wof:name":"Wania",
    "wof:placetype":"locality"
},
  "geometry": {"coordinates":[136.75290000000001,-4.6929],"type":"Point"}
}