{
  "type": "Feature",
  "properties": {
    "gn:admin1_code":"7",
    "gn:asciiname":"Sidengkeng",
    "gn:country_code":"ID",
    "gn:dem":487,
    "gn:feature_class":"P",
    "gn:feature_code":"PPL",
    "gn:name":"Sidengkeng",
    "gn:population":0,
    "gn:timezone":"Asia/Jakarta",
    "iso:country":"ID",
    "name:ind_x_preferred":[
        "Sidengkeng"
    ],
    "wof:name":"Sidengkeng",
    "wof:placetype":"locality"
},
  "geometry": {"coordinates":[109.9892,-7.0491],"type":"Point"}
}