{
  "type": "Feature",
  "properties": {
    "gn:country":"ID",
    "gn:fcode":"PPL",
    "gn:pop":0,
    "iso:country":"ID",
    "name:ceb_x_preferred":[
        "Kecamatan Matraman"
    ],
    "name:deu_x_preferred":[
        "Matraman"
    ],
    "name:eng_x_preferred":[
        "Matraman"
    ],
    "name:fra_x_preferred":[
        "Matraman"
    ],
    "name:ind_x_preferred":[
        "Matraman"
    ],
    "name:ita_x_preferred":[
        "Matraman"
    ],
    "name:jav_x_preferred":[
        "Matraman"
    ],
    "name:jpn_x_preferred":[
        "\u30de\u30c8\u30e9\u30de\u30f3"
    ],
    "name:nld_x_preferred":[
        "Matraman"
    ],
    "name:pol_x_preferred":[
        "Matraman"
    ],
    "name:sin_x_preferred":[
        "\u0db8\u0dad\u0dca\u200d\u0dbb\u0db8\u0dcf\u0db1\u0dca"
    ],
    "name:sun_x_preferred":[
        "Matraman"
    ],
    "name:swe_x_preferred":[
        "Kecamatan Matraman"
    ],
    "name:tam_x_preferred":[
        "\u0bae\u0ba4\u0bcd\u0bb0\u0bae\u0bbe\u0ba9\u0bcd"
    ],
    "qs:name":"Matraman",
    "qs:name_adm0":"Indonesia",
    "qs:name_adm1":"Jakarta Raya",
    "qs:photos":1,
    "qs:photos_1k":1,
    "qs:photos_9k":1,
    "qs:photos_9r":1,
    "qs:photos_all":1,
    "qs:photos_sr":1,
    "qs:placetype":"Suburb",
    "qs:pop_sr":"0",
    "wd:wordcount":122,
    "wof:name":"Matraman",
    "wof:placetype":"neighbourhood",
    "wof:population":0
},
  "geometry": {"coordinates":[106.86194,-6.20694],"type":"Point"}
}