{
  "type": "Feature",
  "properties": {
    "gn:admin1_code":"33.0",
    "gn:asciiname":"Cikaroya",
    "gn:country_code":"ID",
    "gn:dem":249,
    "gn:feature_class":"P",
    "gn:feature_code":"PPL",
    "gn:name":"Cikaroya",
    "gn:population":0,
    "gn:timezone":"Asia/Jakarta",
    "iso:country":"ID",
    "name:ind_x_preferred":[
        "Cikaroya"
    ],
    "wof:name":"Cikaroya",
    "wof:placetype":"locality"
},
  "geometry": {"coordinates":[105.94,-6.3475],"type":"Point"}
}