{
  "type": "Feature",
  "properties": {
    "gn:admin1_code":"18",
    "gn:asciiname":"Karekakakara",
    "gn:country_code":"ID",
    "gn:dem":391,
    "gn:feature_class":"P",
    "gn:feature_code":"PPL",
    "gn:name":"Karekakakara",
    "gn:population":0,
    "gn:timezone":"Asia/Makassar",
    "iso:country":"ID",
    "name:ind_x_preferred":[
        "Karekakakara"
    ],
    "wof:name":"Karekakakara",
    "wof:placetype":"locality"
},
  "geometry": {"coordinates":[119.15989999999999,-9.4733],"type":"Point"}
}