{
  "type": "Feature",
  "properties": {
    "gn:admin1_code":"8",
    "gn:asciiname":"Perumahan Kamal",
    "gn:country_code":"ID",
    "gn:dem":28,
    "gn:feature_class":"P",
    "gn:feature_code":"PPL",
    "gn:name":"Perumahan Kamal",
    "gn:population":0,
    "gn:timezone":"Asia/Jakarta",
    "iso:country":"ID",
    "name:ind_x_preferred":[
        "Perumahan Kamal"
    ],
    "wof:name":"Perumahan Kamal",
    "wof:placetype":"locality"
},
  "geometry": {"coordinates":[112.7196,-7.1566],"type":"Point"}
}