{
  "type": "Feature",
  "properties": {
    "gn:admin1_code":"13.0",
    "gn:asciiname":"Tungka",
    "gn:country_code":"ID",
    "gn:dem":86,
    "gn:feature_class":"P",
    "gn:feature_code":"PPL",
    "gn:name":"Tungka",
    "gn:population":0,
    "gn:timezone":"Asia/Pontianak",
    "iso:country":"ID",
    "name:ind_x_preferred":[
        "Tungka"
    ],
    "wof:name":"Tungka",
    "wof:placetype":"locality"
},
  "geometry": {"coordinates":[115.25348,-1.23743],"type":"Point"}
}