{
  "type": "Feature",
  "properties": {
    "gn:admin1_code":"26",
    "gn:asciiname":"Tahun Dua Puluh Enam",
    "gn:country_code":"ID",
    "gn:dem":71,
    "gn:feature_class":"P",
    "gn:feature_code":"PPL",
    "gn:name":"Tahun Dua Puluh Enam",
    "gn:population":0,
    "gn:timezone":"Asia/Jakarta",
    "iso:country":"ID",
    "name:ind_x_preferred":[
        "Tahun Dua Puluh Enam"
    ],
    "name:und_x_variant":[
        "Tahun 26"
    ],
    "wof:lang_x_official":[
        "ind"
    ],
    "wof:lang_x_spoken":[
        "ind",
        "eng"
    ],
    "wof:name":"Tahun Dua Puluh Enam",
    "wof:placetype":"locality"
},
  "geometry": {"coordinates":[98.3231,3.5303],"type":"Point"}
}