{
  "type": "Feature",
  "properties": {
    "gn:admin1_code":"7.0",
    "gn:asciiname":"Nglebeng",
    "gn:country_code":"ID",
    "gn:dem":354,
    "gn:feature_class":"P",
    "gn:feature_code":"PPL",
    "gn:name":"Nglebeng",
    "gn:population":0,
    "gn:timezone":"Asia/Jakarta",
    "iso:country":"ID",
    "wof:name":"Nglebeng",
    "wof:placetype":"locality"
},
  "geometry": {"coordinates":[110.34139,-7.65583],"type":"Point"}
}