{
  "type": "Feature",
  "properties": {
    "gn:admin1_code":"18",
    "gn:asciiname":"Pinukalumbang",
    "gn:country_code":"ID",
    "gn:dem":62,
    "gn:feature_class":"P",
    "gn:feature_code":"PPL",
    "gn:name":"Pinukalumbang",
    "gn:population":0,
    "gn:timezone":"Asia/Makassar",
    "iso:country":"ID",
    "name:ind_x_preferred":[
        "Pinukalumbang"
    ],
    "wof:name":"Pinukalumbang",
    "wof:placetype":"locality"
},
  "geometry": {"coordinates":[120.7859,-10.0332],"type":"Point"}
}