{
  "type": "Feature",
  "properties": {
    "gn:admin1_code":"21",
    "gn:asciiname":"Pujimulyo",
    "gn:country_code":"ID",
    "gn:dem":14,
    "gn:feature_class":"P",
    "gn:feature_code":"PPL",
    "gn:name":"Pujimulyo",
    "gn:population":0,
    "gn:timezone":"Asia/Makassar",
    "iso:country":"ID",
    "name:ind_x_preferred":[
        "Pujimulyo"
    ],
    "wof:name":"Pujimulyo",
    "wof:placetype":"locality"
},
  "geometry": {"coordinates":[121.38290000000001,1.0985],"type":"Point"}
}