{
  "type": "Feature",
  "properties": {
    "gn:admin1_code":"15.0",
    "gn:asciiname":"Umbulan Negaramulia",
    "gn:country_code":"ID",
    "gn:dem":23,
    "gn:feature_class":"P",
    "gn:feature_code":"PPL",
    "gn:name":"Umbulan Negaramulia",
    "gn:population":0,
    "gn:timezone":"Asia/Jakarta",
    "iso:country":"ID",
    "name:ind_x_preferred":[
        "Umbulan Negaramulia"
    ],
    "wof:name":"Umbulan Negaramulia",
    "wof:placetype":"locality"
},
  "geometry": {"coordinates":[104.87156,-4.38804],"type":"Point"}
}