{
  "type": "Feature",
  "properties": {
    "gn:admin1_code":"7.0",
    "gn:asciiname":"Ngrawan",
    "gn:country_code":"ID",
    "gn:dem":153,
    "gn:feature_class":"P",
    "gn:feature_code":"PPL",
    "gn:name":"Ngrawan",
    "gn:population":0,
    "gn:timezone":"Asia/Jakarta",
    "iso:country":"ID",
    "wof:name":"Ngrawan",
    "wof:placetype":"locality"
},
  "geometry": {"coordinates":[110.84667,-7.94917],"type":"Point"}
}