{
  "type": "Feature",
  "properties": {
    "gn:admin1_code":"26.0",
    "gn:asciiname":"Tanjung Pasir",
    "gn:country_code":"ID",
    "gn:dem":14,
    "gn:feature_class":"P",
    "gn:feature_code":"PPL",
    "gn:name":"Tanjung Pasir",
    "gn:population":0,
    "gn:timezone":"Asia/Jakarta",
    "iso:country":"ID",
    "name:ind_x_preferred":[
        "Tanjung Pasir"
    ],
    "name:und_x_variant":[
        "Tandjoengpasir",
        "Tandjungpasir"
    ],
    "wof:name":"Tanjung Pasir",
    "wof:placetype":"locality"
},
  "geometry": {"coordinates":[99.72880000000001,2.5134],"type":"Point"}
}