{
  "type": "Feature",
  "properties": {
    "gn:admin1_code":"8.0",
    "gn:asciiname":"Sanggrahan Dua",
    "gn:country_code":"ID",
    "gn:dem":126,
    "gn:feature_class":"P",
    "gn:feature_code":"PPL",
    "gn:name":"Sanggrahan Dua",
    "gn:population":0,
    "gn:timezone":"Asia/Jakarta",
    "iso:country":"ID",
    "name:ind_x_preferred":[
        "Sanggrahan Dua"
    ],
    "wof:name":"Sanggrahan Dua",
    "wof:placetype":"locality"
},
  "geometry": {"coordinates":[111.6447,-8.0386],"type":"Point"}
}