{
  "type": "Feature",
  "properties": {
    "gn:admin1_code":"38",
    "gn:asciiname":"Makitta",
    "gn:country_code":"ID",
    "gn:dem":6,
    "gn:feature_class":"P",
    "gn:feature_code":"PPL",
    "gn:name":"Makitta",
    "gn:population":0,
    "gn:timezone":"Asia/Makassar",
    "iso:country":"ID",
    "name:ind_x_preferred":[
        "Makitta"
    ],
    "wof:name":"Makitta",
    "wof:placetype":"locality"
},
  "geometry": {"coordinates":[120.47029999999999,-2.7564],"type":"Point"}
}