{
  "type": "Feature",
  "properties": {
    "gn:admin1_code":"38.0",
    "gn:asciiname":"Jampue",
    "gn:country_code":"ID",
    "gn:dem":11,
    "gn:feature_class":"P",
    "gn:feature_code":"PPL",
    "gn:name":"Jampue",
    "gn:population":0,
    "gn:timezone":"Asia/Makassar",
    "iso:country":"ID",
    "name:ind_x_preferred":[
        "Jampue"
    ],
    "name:und_x_variant":[
        "Djampue",
        "Jampua",
        "Djampoe\u00c3",
        "Jampue"
    ],
    "wof:name":"Jampue",
    "wof:placetype":"locality"
},
  "geometry": {"coordinates":[119.5427,-3.907],"type":"Point"}
}