{
  "type": "Feature",
  "properties": {
    "gn:admin1_code":"30",
    "gn:asciiname":"Kendayakan",
    "gn:country_code":"ID",
    "gn:dem":7,
    "gn:feature_class":"P",
    "gn:feature_code":"PPL",
    "gn:name":"Kendayakan",
    "gn:population":0,
    "gn:timezone":"Asia/Jakarta",
    "iso:country":"ID",
    "name:ind_x_preferred":[
        "Kendayakan"
    ],
    "name:und_x_variant":[
        "Kendajakan"
    ],
    "wof:name":"Kendayakan",
    "wof:placetype":"locality"
},
  "geometry": {"coordinates":[107.19389,-6.1375],"type":"Point"}
}