{
  "type": "Feature",
  "properties": {
    "gn:admin1_code":"30.0",
    "gn:asciiname":"Ciderma",
    "gn:country_code":"ID",
    "gn:dem":602,
    "gn:feature_class":"P",
    "gn:feature_code":"PPL",
    "gn:name":"Ciderma",
    "gn:population":0,
    "gn:timezone":"Asia/Jakarta",
    "iso:country":"ID",
    "name:ind_x_preferred":[
        "Ciderma"
    ],
    "wof:name":"Ciderma",
    "wof:placetype":"locality"
},
  "geometry": {"coordinates":[107.71120000000001,-7.4492],"type":"Point"}
}