{
  "type": "Feature",
  "properties": {
    "gn:admin1_code":"18.0",
    "gn:asciiname":"Rawuk",
    "gn:country_code":"ID",
    "gn:dem":852,
    "gn:feature_class":"P",
    "gn:feature_code":"PPLA4",
    "gn:name":"Rawuk",
    "gn:population":0,
    "gn:timezone":"Asia/Makassar",
    "iso:country":"ID",
    "name:ind_x_preferred":[
        "Rawuk"
    ],
    "wof:lang_x_official":[
        "ind"
    ],
    "wof:lang_x_spoken":[
        "ind",
        "eng"
    ],
    "wof:name":"Rawuk",
    "wof:placetype":"locality"
},
  "geometry": {"coordinates":[120.23690000000001,-8.5625],"type":"Point"}
}