{
  "type": "Feature",
  "properties": {
    "gn:admin1_code":"8",
    "gn:asciiname":"Jawar",
    "gn:country_code":"ID",
    "gn:dem":409,
    "gn:feature_class":"P",
    "gn:feature_code":"PPL",
    "gn:name":"Jawar",
    "gn:population":0,
    "gn:timezone":"Asia/Jakarta",
    "iso:country":"ID",
    "name:ben_x_preferred":[
        "\u099c\u09be\u0993\u09af\u09bc\u09be\u09b0"
    ],
    "name:bpy_x_preferred":[
        "\u099c\u09be\u09f1\u09be\u09b0"
    ],
    "name:ceb_x_preferred":[
        "Jawar"
    ],
    "name:ind_x_preferred":[
        "Jawar"
    ],
    "name:ita_x_preferred":[
        "Jawar"
    ],
    "name:mlg_x_preferred":[
        "Jawar"
    ],
    "name:msa_x_preferred":[
        "Jawar"
    ],
    "name:new_x_preferred":[
        "\u091c\u0935\u093e\u0930"
    ],
    "name:nld_x_preferred":[
        "Jawar"
    ],
    "name:por_x_preferred":[
        "Jawar"
    ],
    "name:vie_x_preferred":[
        "Jawar"
    ],
    "name:zho_x_preferred":[
        "\u8d3e\u74e6\u5c14"
    ],
    "wof:lang_x_official":[
        "ind"
    ],
    "wof:lang_x_spoken":[
        "ind",
        "eng"
    ],
    "wof:name":"Jawar",
    "wof:placetype":"locality"
},
  "geometry": {"coordinates":[111.31999999999999,-7.66111],"type":"Point"}
}