{
  "type": "Feature",
  "properties": {
    "gn:admin1_code":"8",
    "gn:asciiname":"Jawar",
    "gn:country_code":"ID",
    "gn:dem":409,
    "gn:feature_class":"P",
    "gn:feature_code":"PPL",
    "gn:name":"Jawar",
    "gn:population":0,
    "gn:timezone":"Asia/Jakarta",
    "iso:country":"ID",
    "name:ind_x_preferred":[
        "Jawar"
    ],
    "wof:name":"Jawar",
    "wof:placetype":"locality"
},
  "geometry": {"coordinates":[111.31999999999999,-7.66111],"type":"Point"}
}