{
  "type": "Feature",
  "properties": {
    "gn:admin1_code":"30.0",
    "gn:asciiname":"Cikacang",
    "gn:country_code":"ID",
    "gn:dem":309,
    "gn:feature_class":"P",
    "gn:feature_code":"PPL",
    "gn:name":"Cikacang",
    "gn:population":0,
    "gn:timezone":"Asia/Jakarta",
    "iso:country":"ID",
    "name:ind_x_preferred":[
        "Cikacang"
    ],
    "name:und_x_variant":[
        "Tjikatjang"
    ],
    "wof:name":"Cikacang",
    "wof:placetype":"locality"
},
  "geometry": {"coordinates":[108.3497,-7.2705],"type":"Point"}
}