{
  "type": "Feature",
  "properties": {
    "gn:admin1_code":"26",
    "gn:asciiname":"Kutaklentong",
    "gn:country_code":"ID",
    "gn:dem":604,
    "gn:feature_class":"P",
    "gn:feature_code":"PPL",
    "gn:name":"Kutaklentong",
    "gn:population":0,
    "gn:timezone":"Asia/Jakarta",
    "iso:country":"ID",
    "name:ind_x_preferred":[
        "Kutaklentong"
    ],
    "wof:name":"Kutaklentong",
    "wof:placetype":"locality"
},
  "geometry": {"coordinates":[98.20829999999999,3.1192],"type":"Point"}
}