{
  "type": "Feature",
  "properties": {
    "gn:admin1_code":"36.0",
    "gn:asciiname":"Samsre",
    "gn:country_code":"ID",
    "gn:dem":45,
    "gn:feature_class":"P",
    "gn:feature_code":"PPL",
    "gn:name":"Samsre",
    "gn:population":0,
    "gn:timezone":"Asia/Jayapura",
    "iso:country":"ID",
    "name:ind_x_preferred":[
        "Samsre"
    ],
    "wof:name":"Samsre",
    "wof:placetype":"locality"
},
  "geometry": {"coordinates":[138.77799999999999,-2.0498],"type":"Point"}
}