{
  "type": "Feature",
  "properties": {
    "gn:admin1_code":"31.0",
    "gn:asciiname":"Kiawang",
    "gn:country_code":"ID",
    "gn:dem":91,
    "gn:feature_class":"P",
    "gn:feature_code":"PPL",
    "gn:name":"Kiawang",
    "gn:population":0,
    "gn:timezone":"Asia/Makassar",
    "iso:country":"ID",
    "name:ind_x_preferred":[
        "Kiawang"
    ],
    "name:und_x_variant":[
        "Kawiang"
    ],
    "wof:name":"Kiawang",
    "wof:placetype":"locality"
},
  "geometry": {"coordinates":[125.37649999999999,2.7962],"type":"Point"}
}