{
  "type": "Feature",
  "properties": {
    "gn:country":"ID",
    "gn:fcode":"ADM3",
    "gn:pop":0,
    "iso:country":"ID",
    "name:ind_x_preferred":[
        "Kecamatan Ajibarang"
    ],
    "name:unk_x_variant":[
        "Ajibarang"
    ],
    "qs:name":"Kecamatan Ajibarang",
    "qs:photos_9r":0,
    "qs:photos_sr":0,
    "qs:pop_sr":"0",
    "wof:name":"Kecamatan Ajibarang",
    "wof:placetype":"localadmin",
    "wof:population":0
},
  "geometry": {"coordinates":[109.09111,-7.42444],"type":"Point"}
}