{
  "type": "Feature",
  "properties": {
    "gn:admin1_code":"17.0",
    "gn:asciiname":"Bangunurip",
    "gn:country_code":"ID",
    "gn:dem":143,
    "gn:feature_class":"P",
    "gn:feature_code":"PPL",
    "gn:name":"Bangunurip",
    "gn:population":0,
    "gn:timezone":"Asia/Makassar",
    "iso:country":"ID",
    "name:ind_x_preferred":[
        "Bangunurip"
    ],
    "wof:name":"Bangunurip",
    "wof:placetype":"locality"
},
  "geometry": {"coordinates":[118.309,-8.4679],"type":"Point"}
}