{
  "type": "Feature",
  "properties": {
    "gn:admin1_code":"30",
    "gn:asciiname":"Pancol",
    "gn:country_code":"ID",
    "gn:dem":88,
    "gn:feature_class":"P",
    "gn:feature_code":"PPL",
    "gn:name":"Pancol",
    "gn:population":0,
    "gn:timezone":"Asia/Jakarta",
    "iso:country":"ID",
    "name:ind_x_preferred":[
        "Pancol"
    ],
    "wof:name":"Pancol",
    "wof:placetype":"locality"
},
  "geometry": {"coordinates":[107.09417000000001,-6.46806],"type":"Point"}
}