{
  "type": "Feature",
  "properties": {
    "gn:admin1_code":"15.0",
    "gn:asciiname":"Umbulan Tedungngeram",
    "gn:country_code":"ID",
    "gn:dem":9,
    "gn:feature_class":"P",
    "gn:feature_code":"PPL",
    "gn:name":"Umbulan Tedungngeram",
    "gn:population":0,
    "gn:timezone":"Asia/Jakarta",
    "iso:country":"ID",
    "name:ind_x_preferred":[
        "Umbulan Tedungngeram"
    ],
    "name:ind_x_variant":[
        "Umbulantedungngeram",
        "Umbulan Tedungngerem"
    ],
    "name:und_x_variant":[
        "Umbulan Tedungeram"
    ],
    "wof:lang_x_official":[
        "ind"
    ],
    "wof:lang_x_spoken":[
        "ind",
        "eng"
    ],
    "wof:name":"Umbulan Tedungngeram",
    "wof:placetype":"locality"
},
  "geometry": {"coordinates":[105.20305,-3.97755],"type":"Point"}
}