{
  "type": "Feature",
  "properties": {
    "gn:admin1_code":"26.0",
    "gn:asciiname":"Sanggaran Satu",
    "gn:country_code":"ID",
    "gn:dem":788,
    "gn:feature_class":"P",
    "gn:feature_code":"PPL",
    "gn:name":"Sanggaran Satu",
    "gn:population":0,
    "gn:timezone":"Asia/Jakarta",
    "iso:country":"ID",
    "name:ind_x_preferred":[
        "Sanggaran Satu"
    ],
    "name:und_x_variant":[
        "Sanggaran 1"
    ],
    "wof:name":"Sanggaran Satu",
    "wof:placetype":"locality"
},
  "geometry": {"coordinates":[98.6581,2.07815],"type":"Point"}
}