{
  "type": "Feature",
  "properties": {
    "gn:admin1_code":"30.0",
    "gn:asciiname":"Cibodas",
    "gn:country_code":"ID",
    "gn:dem":145,
    "gn:feature_class":"P",
    "gn:feature_code":"PPL",
    "gn:name":"Cibodas",
    "gn:population":0,
    "gn:timezone":"Asia/Jakarta",
    "iso:country":"ID",
    "name:ind_x_preferred":[
        "Cibodas"
    ],
    "name:und_x_variant":[
        "Tjibodas Satu"
    ],
    "wof:name":"Cibodas",
    "wof:placetype":"locality"
},
  "geometry": {"coordinates":[108.4148,-7.6946],"type":"Point"}
}