{
  "type": "Feature",
  "properties": {
    "gn:admin1_code":"33",
    "gn:asciiname":"Cikoret",
    "gn:country_code":"ID",
    "gn:dem":42,
    "gn:feature_class":"P",
    "gn:feature_code":"PPL",
    "gn:name":"Cikoret",
    "gn:population":0,
    "gn:timezone":"Asia/Jakarta",
    "iso:country":"ID",
    "name:ind_x_preferred":[
        "Cikoret"
    ],
    "wof:name":"Cikoret",
    "wof:placetype":"locality"
},
  "geometry": {"coordinates":[106.1344,-6.4405],"type":"Point"}
}