{
  "type": "Feature",
  "properties": {
    "gn:admin1_code":"7.0",
    "gn:asciiname":"Pamijenkrajan",
    "gn:country_code":"ID",
    "gn:dem":102,
    "gn:feature_class":"P",
    "gn:feature_code":"PPL",
    "gn:name":"Pamijenkrajan",
    "gn:population":0,
    "gn:timezone":"Asia/Jakarta",
    "iso:country":"ID",
    "name:ind_x_preferred":[
        "Pamijenkrajan"
    ],
    "wof:name":"Pamijenkrajan",
    "wof:placetype":"locality"
},
  "geometry": {"coordinates":[108.97389,-7.26083],"type":"Point"}
}