{
  "type": "Feature",
  "properties": {
    "gn:admin1_code":"7.0",
    "gn:asciiname":"Mandala",
    "gn:country_code":"ID",
    "gn:dem":1070,
    "gn:feature_class":"P",
    "gn:feature_code":"PPL",
    "gn:name":"Mandala",
    "gn:population":0,
    "gn:timezone":"Asia/Jakarta",
    "iso:country":"ID",
    "name:ind_x_preferred":[
        "Mandala"
    ],
    "wof:name":"Mandala",
    "wof:placetype":"locality"
},
  "geometry": {"coordinates":[109.69389,-7.25917],"type":"Point"}
}