{
  "type": "Feature",
  "properties": {
    "gn:admin1_code":"15.0",
    "gn:asciiname":"Pandan",
    "gn:country_code":"ID",
    "gn:dem":499,
    "gn:feature_class":"P",
    "gn:feature_code":"PPL",
    "gn:name":"Pandan",
    "gn:population":0,
    "gn:timezone":"Asia/Jakarta",
    "iso:country":"ID",
    "name:ceb_x_preferred":[
        "Pandan"
    ],
    "name:deu_x_preferred":[
        "Pandan"
    ],
    "name:fra_x_preferred":[
        "Pandan"
    ],
    "name:ind_x_preferred":[
        "Pandan"
    ],
    "name:ita_x_preferred":[
        "Pandan"
    ],
    "name:msa_x_preferred":[
        "Pandan"
    ],
    "name:nld_x_preferred":[
        "Pandan"
    ],
    "name:swe_x_preferred":[
        "Pandan"
    ],
    "name:tgl_x_preferred":[
        "Pandan"
    ],
    "name:war_x_preferred":[
        "Pandan"
    ],
    "wof:name":"Pandan",
    "wof:placetype":"locality"
},
  "geometry": {"coordinates":[105.64816,-5.76007],"type":"Point"}
}