{
  "type": "Feature",
  "properties": {
    "gn:admin1_code":"30",
    "gn:asciiname":"Babakanjakarta",
    "gn:country_code":"ID",
    "gn:dem":110,
    "gn:feature_class":"P",
    "gn:feature_code":"PPL",
    "gn:name":"Babakanjakarta",
    "gn:population":0,
    "gn:timezone":"Asia/Jakarta",
    "iso:country":"ID",
    "name:ind_x_preferred":[
        "Babakanjakarta"
    ],
    "wof:name":"Babakanjakarta",
    "wof:placetype":"locality"
},
  "geometry": {"coordinates":[107.66028,-6.51556],"type":"Point"}
}