{
  "type": "Feature",
  "properties": {
    "gn:admin1_code":"2",
    "gn:asciiname":"Banjar Pengambangan",
    "gn:country_code":"ID",
    "gn:dem":62,
    "gn:feature_class":"P",
    "gn:feature_code":"PPL",
    "gn:name":"Banjar Pengambangan",
    "gn:population":0,
    "gn:timezone":"Asia/Makassar",
    "iso:country":"ID",
    "name:ind_x_preferred":[
        "Banjar Pengambangan"
    ],
    "wof:name":"Banjar Pengambangan",
    "wof:placetype":"locality"
},
  "geometry": {"coordinates":[115.25449999999999,-8.613],"type":"Point"}
}