{
  "type": "Feature",
  "properties": {
    "gn:admin1_code":"38.0",
    "gn:asciiname":"Soreang",
    "gn:country_code":"ID",
    "gn:dem":6,
    "gn:feature_class":"P",
    "gn:feature_code":"PPL",
    "gn:name":"Soreang",
    "gn:population":0,
    "gn:timezone":"Asia/Makassar",
    "iso:country":"ID",
    "name:ind_x_preferred":[
        "Soreang"
    ],
    "wof:name":"Soreang",
    "wof:placetype":"locality"
},
  "geometry": {"coordinates":[119.58459999999999,-4.8725],"type":"Point"}
}