{
  "type": "Feature",
  "properties": {
    "gn:admin1_code":"11",
    "gn:asciiname":"Nangka",
    "gn:country_code":"ID",
    "gn:dem":46,
    "gn:feature_class":"P",
    "gn:feature_code":"PPL",
    "gn:name":"Nangka",
    "gn:population":0,
    "gn:timezone":"Asia/Pontianak",
    "iso:country":"ID",
    "name:ind_x_preferred":[
        "Nangka"
    ],
    "wof:name":"Nangka",
    "wof:placetype":"locality"
},
  "geometry": {"coordinates":[110.50184,-0.93787],"type":"Point"}
}