{
  "type": "Feature",
  "properties": {
    "gn:admin1_code":"22",
    "gn:asciiname":"Bahutara",
    "gn:country_code":"ID",
    "gn:dem":36,
    "gn:feature_class":"P",
    "gn:feature_code":"PPL",
    "gn:name":"Bahutara",
    "gn:population":0,
    "gn:timezone":"Asia/Makassar",
    "iso:country":"ID",
    "name:ind_x_preferred":[
        "Bahutara"
    ],
    "wof:name":"Bahutara",
    "wof:placetype":"locality"
},
  "geometry": {"coordinates":[122.4747,-4.9607],"type":"Point"}
}