{
  "type": "Feature",
  "properties": {
    "gn:admin1_code":"0.0",
    "gn:asciiname":"Paropean",
    "gn:country_code":"ID",
    "gn:dem":762,
    "gn:feature_class":"P",
    "gn:feature_code":"PPL",
    "gn:name":"Paropean",
    "gn:population":0,
    "gn:timezone":"Asia/Makassar",
    "iso:country":"ID",
    "wof:name":"Paropean",
    "wof:placetype":"locality"
},
  "geometry": {"coordinates":[119.71666999999999,-2.31667],"type":"Point"}
}