{
  "type": "Feature",
  "properties": {
    "gn:admin1_code":"33",
    "gn:asciiname":"Ciawetpasir",
    "gn:country_code":"ID",
    "gn:dem":40,
    "gn:feature_class":"P",
    "gn:feature_code":"PPL",
    "gn:name":"Ciawetpasir",
    "gn:population":0,
    "gn:timezone":"Asia/Jakarta",
    "iso:country":"ID",
    "name:ind_x_preferred":[
        "Ciawetpasir"
    ],
    "name:und_x_variant":[
        "Tiawet"
    ],
    "wof:name":"Ciawetpasir",
    "wof:placetype":"locality"
},
  "geometry": {"coordinates":[106.3464,-6.2726],"type":"Point"}
}