{
  "type": "Feature",
  "properties": {
    "gn:admin1_code":"3.0",
    "gn:asciiname":"Lubuklagan",
    "gn:country_code":"ID",
    "gn:dem":77,
    "gn:feature_class":"P",
    "gn:feature_code":"PPL",
    "gn:name":"Lubuklagan",
    "gn:population":0,
    "gn:timezone":"Asia/Jakarta",
    "iso:country":"ID",
    "name:ind_x_preferred":[
        "Lubuklagan"
    ],
    "wof:name":"Lubuklagan",
    "wof:placetype":"locality"
},
  "geometry": {"coordinates":[102.73569999999999,-4.1674],"type":"Point"}
}