{
  "type": "Feature",
  "properties": {
    "gn:admin1_code":"15.0",
    "gn:asciiname":"Tangkitserdang Satu",
    "gn:country_code":"ID",
    "gn:dem":220,
    "gn:feature_class":"P",
    "gn:feature_code":"PPL",
    "gn:name":"Tangkitserdang Satu",
    "gn:population":0,
    "gn:timezone":"Asia/Jakarta",
    "iso:country":"ID",
    "name:ind_x_preferred":[
        "Tangkitserdang Satu"
    ],
    "name:und_x_variant":[
        "Tangkitserdang 1"
    ],
    "wof:name":"Tangkitserdang Satu",
    "wof:placetype":"locality"
},
  "geometry": {"coordinates":[104.80161,-5.32821],"type":"Point"}
}