{
  "type": "Feature",
  "properties": {
    "gn:admin1_code":"8",
    "gn:asciiname":"Batu",
    "gn:country_code":"ID",
    "gn:dem":409,
    "gn:feature_class":"P",
    "gn:feature_code":"PPL",
    "gn:name":"Batu",
    "gn:population":0,
    "gn:timezone":"Asia/Jakarta",
    "iso:country":"ID",
    "name:cat_x_preferred":[
        "Batu"
    ],
    "name:ceb_x_preferred":[
        "Batu"
    ],
    "name:deu_x_preferred":[
        "Batu"
    ],
    "name:fin_x_preferred":[
        "Batu"
    ],
    "name:fra_x_preferred":[
        "Batu"
    ],
    "name:hrv_x_preferred":[
        "Batu"
    ],
    "name:ind_x_preferred":[
        "Batu"
    ],
    "name:kor_x_preferred":[
        "\ubc14\ud22c"
    ],
    "name:msa_x_preferred":[
        "Batu"
    ],
    "name:nld_x_preferred":[
        "Batu"
    ],
    "name:pol_x_preferred":[
        "Batu"
    ],
    "name:por_x_preferred":[
        "Batu"
    ],
    "name:spa_x_preferred":[
        "Batu"
    ],
    "name:swe_x_preferred":[
        "Batu"
    ],
    "wof:name":"Batu",
    "wof:placetype":"locality"
},
  "geometry": {"coordinates":[110.99944000000001,-8.10222],"type":"Point"}
}