{
  "type": "Feature",
  "properties": {
    "gn:admin1_code":"3.0",
    "gn:asciiname":"Rantaukenida",
    "gn:country_code":"ID",
    "gn:dem":437,
    "gn:feature_class":"P",
    "gn:feature_code":"PPL",
    "gn:name":"Rantaukenida",
    "gn:population":0,
    "gn:timezone":"Asia/Jakarta",
    "iso:country":"ID",
    "name:ind_x_preferred":[
        "Rantaukenida"
    ],
    "name:ind_x_variant":[
        "Rantaukenidai"
    ],
    "wof:lang_x_official":[
        "ind"
    ],
    "wof:lang_x_spoken":[
        "ind",
        "eng"
    ],
    "wof:name":"Rantaukenida",
    "wof:placetype":"locality"
},
  "geometry": {"coordinates":[103.54698999999999,-4.76159],"type":"Point"}
}