{
  "type": "Feature",
  "properties": {
    "gn:admin1_code":"24",
    "gn:asciiname":"Sikapak",
    "gn:country_code":"ID",
    "gn:dem":49,
    "gn:feature_class":"P",
    "gn:feature_code":"PPL",
    "gn:name":"Sikapak",
    "gn:population":0,
    "gn:timezone":"Asia/Jakarta",
    "iso:country":"ID",
    "name:ind_x_preferred":[
        "Sikapak"
    ],
    "wof:name":"Sikapak",
    "wof:placetype":"locality"
},
  "geometry": {"coordinates":[100.13481,-0.58108],"type":"Point"}
}