{
  "type": "Feature",
  "properties": {
    "gn:admin1_code":"17",
    "gn:asciiname":"Ambung",
    "gn:country_code":"ID",
    "gn:dem":247,
    "gn:feature_class":"P",
    "gn:feature_code":"PPL",
    "gn:name":"Ambung",
    "gn:population":0,
    "gn:timezone":"Asia/Makassar",
    "iso:country":"ID",
    "name:ceb_x_preferred":[
        "Ambung"
    ],
    "name:fas_x_preferred":[
        "\u0627\u0645\u0628\u0627\u0646\u06af"
    ],
    "name:ind_x_preferred":[
        "Ambung"
    ],
    "name:msa_x_preferred":[
        "Ambung"
    ],
    "name:nep_x_preferred":[
        "\u0906\u092e\u094d\u0935\u0941\u0919"
    ],
    "name:new_x_preferred":[
        "\u0906\u092e\u094d\u092c\u0941\u0919"
    ],
    "name:pol_x_preferred":[
        "Ambung"
    ],
    "wof:name":"Ambung",
    "wof:placetype":"locality"
},
  "geometry": {"coordinates":[116.4885,-8.6119],"type":"Point"}
}