{
  "type": "Feature",
  "properties": {
    "gn:admin1_code":"36",
    "gn:asciiname":"Sugapa",
    "gn:country_code":"ID",
    "gn:dem":2144,
    "gn:feature_class":"P",
    "gn:feature_code":"PPLA2",
    "gn:name":"Sugapa",
    "gn:population":0,
    "gn:timezone":"Asia/Jayapura",
    "iso:country":"ID",
    "name:ind_x_preferred":[
        "Sugapa"
    ],
    "wof:lang_x_official":[
        "ind"
    ],
    "wof:lang_x_spoken":[
        "ind",
        "eng"
    ],
    "wof:name":"Sugapa",
    "wof:placetype":"locality"
},
  "geometry": {"coordinates":[137.05000000000001,-3.74306],"type":"Point"}
}