{
  "type": "Feature",
  "properties": {
    "gn:admin1_code":"7",
    "gn:asciiname":"Candi",
    "gn:country_code":"ID",
    "gn:dem":583,
    "gn:feature_class":"P",
    "gn:feature_code":"PPL",
    "gn:name":"Candi",
    "gn:population":0,
    "gn:timezone":"Asia/Jakarta",
    "iso:country":"ID",
    "name:ceb_x_preferred":[
        "Candi"
    ],
    "name:deu_x_preferred":[
        "Candi"
    ],
    "name:fra_x_preferred":[
        "Candi"
    ],
    "name:ind_x_preferred":[
        "Candi"
    ],
    "name:ita_x_preferred":[
        "Candi"
    ],
    "name:nld_x_preferred":[
        "Candi"
    ],
    "name:swe_x_preferred":[
        "Candi"
    ],
    "wof:lang_x_official":[
        "ind"
    ],
    "wof:lang_x_spoken":[
        "ind",
        "eng"
    ],
    "wof:name":"Candi",
    "wof:placetype":"locality"
},
  "geometry": {"coordinates":[110.4175,-7.23111],"type":"Point"}
}