{
  "type": "Feature",
  "properties": {
    "gn:country":"ID",
    "gn:fcode":"PPLA3",
    "gn:pop":0,
    "iso:country":"ID",
    "name:ind_x_preferred":[
        "Sukasada"
    ],
    "name:unk_x_variant":[
        "Soekasade"
    ],
    "qs:name":"Sukasada",
    "qs:photos_9r":0,
    "qs:photos_sr":0,
    "qs:pop_sr":"0",
    "wof:name":"Sukasada",
    "wof:placetype":"locality",
    "wof:population":0
},
  "geometry": {"coordinates":[115.1031,-8.1395],"type":"Point"}
}