{
  "type": "Feature",
  "properties": {
    "gn:admin1_code":"30.0",
    "gn:asciiname":"Cikaso",
    "gn:country_code":"ID",
    "gn:dem":1001,
    "gn:feature_class":"P",
    "gn:feature_code":"PPL",
    "gn:name":"Cikaso",
    "gn:population":0,
    "gn:timezone":"Asia/Jakarta",
    "iso:country":"ID",
    "name:ind_x_preferred":[
        "Cikaso"
    ],
    "wof:name":"Cikaso",
    "wof:placetype":"locality"
},
  "geometry": {"coordinates":[106.9922,-7.0742],"type":"Point"}
}