{
  "type": "Feature",
  "properties": {
    "gn:admin1_code":"32.0",
    "gn:asciiname":"Pangkalanbulian",
    "gn:country_code":"ID",
    "gn:dem":31,
    "gn:feature_class":"P",
    "gn:feature_code":"PPL",
    "gn:name":"Pangkalanbulian",
    "gn:population":0,
    "gn:timezone":"Asia/Jakarta",
    "iso:country":"ID",
    "name:und_x_variant":[
        "Pangkalanboelian",
        "Pangkalanbulian"
    ],
    "wof:name":"Pangkalanbulian",
    "wof:placetype":"locality"
},
  "geometry": {"coordinates":[103.5449,-2.5192],"type":"Point"}
}