{
  "type": "Feature",
  "properties": {
    "gn:admin1_code":"07",
    "gn:asciiname":"Jebug",
    "gn:country_code":"ID",
    "gn:dem":717,
    "gn:feature_class":"P",
    "gn:feature_code":"PPL",
    "gn:name":"Jebug",
    "gn:population":0,
    "gn:timezone":"Asia/Jakarta",
    "iso:country":"ID",
    "name:und_x_variant":[
        "Jubug",
        "Djubug",
        "Jebug"
    ],
    "wof:name":"Jebug",
    "wof:placetype":"locality"
},
  "geometry": {"coordinates":[110.52916999999999,-7.37278],"type":"Point"}
}