{
  "type": "Feature",
  "properties": {
    "gn:admin1_code":"7.0",
    "gn:asciiname":"Pasarpaing",
    "gn:country_code":"ID",
    "gn:dem":8,
    "gn:feature_class":"P",
    "gn:feature_code":"PPL",
    "gn:name":"Pasarpaing",
    "gn:population":0,
    "gn:timezone":"Asia/Jakarta",
    "iso:country":"ID",
    "name:ind_x_preferred":[
        "Pasarpaing"
    ],
    "wof:name":"Pasarpaing",
    "wof:placetype":"locality"
},
  "geometry": {"coordinates":[109.15139000000001,-7.62028],"type":"Point"}
}