{
  "type": "Feature",
  "properties": {
    "gn:admin1_code":"7.0",
    "gn:asciiname":"Pangul",
    "gn:country_code":"ID",
    "gn:dem":315,
    "gn:feature_class":"P",
    "gn:feature_code":"PPL",
    "gn:name":"Pangul",
    "gn:population":0,
    "gn:timezone":"Asia/Jakarta",
    "iso:country":"ID",
    "wof:name":"Pangul",
    "wof:placetype":"locality"
},
  "geometry": {"coordinates":[110.6375,-7.50694],"type":"Point"}
}