{
  "type": "Feature",
  "properties": {
    "gn:admin1_code":"17",
    "gn:asciiname":"Kumbaq",
    "gn:country_code":"ID",
    "gn:dem":515,
    "gn:feature_class":"P",
    "gn:feature_code":"PPL",
    "gn:name":"Kumbaq",
    "gn:population":0,
    "gn:timezone":"Asia/Makassar",
    "iso:country":"ID",
    "name:ind_x_preferred":[
        "Kumbaq"
    ],
    "wof:name":"Kumbaq",
    "wof:placetype":"locality"
},
  "geometry": {"coordinates":[116.3661,-8.5624],"type":"Point"}
}