{
  "type": "Feature",
  "properties": {
    "gn:admin1_code":"15.0",
    "gn:asciiname":"Pedamaran",
    "gn:country_code":"ID",
    "gn:dem":117,
    "gn:feature_class":"P",
    "gn:feature_code":"PPL",
    "gn:name":"Pedamaran",
    "gn:population":0,
    "gn:timezone":"Asia/Jakarta",
    "iso:country":"ID",
    "name:ind_x_preferred":[
        "Pedamaran"
    ],
    "wof:name":"Pedamaran",
    "wof:placetype":"locality"
},
  "geometry": {"coordinates":[104.57496999999999,-5.61756],"type":"Point"}
}