{
  "type": "Feature",
  "properties": {
    "gn:admin1_code":"1",
    "gn:asciiname":"Meunasah Dayah",
    "gn:country_code":"ID",
    "gn:dem":19,
    "gn:feature_class":"P",
    "gn:feature_code":"PPL",
    "gn:name":"Meunasah Dayah",
    "gn:population":0,
    "gn:timezone":"Asia/Jakarta",
    "iso:country":"ID",
    "name:ind_x_preferred":[
        "Meunasah Dayah"
    ],
    "wof:name":"Meunasah Dayah",
    "wof:placetype":"locality"
},
  "geometry": {"coordinates":[96.48439999999999,5.1663],"type":"Point"}
}