{
  "type": "Feature",
  "properties": {
    "gn:admin1_code":"30",
    "gn:asciiname":"Ciseke",
    "gn:country_code":"ID",
    "gn:dem":648,
    "gn:feature_class":"P",
    "gn:feature_code":"PPL",
    "gn:name":"Ciseke",
    "gn:population":0,
    "gn:timezone":"Asia/Jakarta",
    "iso:country":"ID",
    "name:ind_x_preferred":[
        "Ciseke"
    ],
    "wof:name":"Ciseke",
    "wof:placetype":"locality"
},
  "geometry": {"coordinates":[106.74028,-6.7725],"type":"Point"}
}