{
  "type": "Feature",
  "properties": {
    "gn:admin1_code":"38",
    "gn:asciiname":"Tono",
    "gn:country_code":"ID",
    "gn:dem":15,
    "gn:feature_class":"P",
    "gn:feature_code":"PPL",
    "gn:name":"Tono",
    "gn:population":0,
    "gn:timezone":"Asia/Makassar",
    "iso:country":"ID",
    "name:ceb_x_preferred":[
        "Tono"
    ],
    "name:deu_x_preferred":[
        "Tono"
    ],
    "name:ido_x_preferred":[
        "Tono"
    ],
    "name:ind_x_preferred":[
        "Tono"
    ],
    "name:ita_x_preferred":[
        "Tono"
    ],
    "name:nds_x_preferred":[
        "Tono"
    ],
    "name:nld_x_preferred":[
        "Tono"
    ],
    "name:spa_x_preferred":[
        "Tono"
    ],
    "name:swe_x_preferred":[
        "Tono"
    ],
    "name:tgl_x_preferred":[
        "Tono"
    ],
    "name:ukr_x_preferred":[
        "\u0422\u043e\u043d\u043e"
    ],
    "wof:name":"Tono",
    "wof:placetype":"locality"
},
  "geometry": {"coordinates":[120.24979999999999,-4.3206],"type":"Point"}
}