{
  "type": "Feature",
  "properties": {
    "gn:admin1_code":"18",
    "gn:asciiname":"Leda",
    "gn:country_code":"ID",
    "gn:dem":804,
    "gn:feature_class":"P",
    "gn:feature_code":"PPL",
    "gn:name":"Leda",
    "gn:population":0,
    "gn:timezone":"Asia/Makassar",
    "iso:country":"ID",
    "name:ind_x_preferred":[
        "Leda"
    ],
    "wof:name":"Leda",
    "wof:placetype":"locality"
},
  "geometry": {"coordinates":[120.27500000000001,-8.5523],"type":"Point"}
}