{
  "type": "Feature",
  "properties": {
    "gn:admin1_code":"18.0",
    "gn:asciiname":"Bokeka",
    "gn:country_code":"ID",
    "gn:dem":1253,
    "gn:feature_class":"P",
    "gn:feature_code":"PPL",
    "gn:name":"Bokeka",
    "gn:population":0,
    "gn:timezone":"Asia/Makassar",
    "iso:country":"ID",
    "name:ind_x_preferred":[
        "Bokeka"
    ],
    "wof:name":"Bokeka",
    "wof:placetype":"locality"
},
  "geometry": {"coordinates":[121.05500000000001,-8.8722],"type":"Point"}
}