{
  "type": "Feature",
  "properties": {
    "gn:admin1_code":"8.0",
    "gn:asciiname":"Bruno",
    "gn:country_code":"ID",
    "gn:dem":815,
    "gn:feature_class":"P",
    "gn:feature_code":"PPL",
    "gn:name":"Bruno",
    "gn:population":0,
    "gn:timezone":"Asia/Jakarta",
    "iso:country":"ID",
    "name:ara_x_preferred":[
        "\u0628\u0631\u0648\u0646\u0648"
    ],
    "name:ceb_x_preferred":[
        "Bruno"
    ],
    "name:ces_x_preferred":[
        "Bruno"
    ],
    "name:deu_x_preferred":[
        "Bruno"
    ],
    "name:ell_x_preferred":[
        "\u039c\u03c0\u03c1\u03bf\u03cd\u03bd\u03bf"
    ],
    "name:epo_x_preferred":[
        "Bruno"
    ],
    "name:est_x_preferred":[
        "Bruno"
    ],
    "name:fra_x_preferred":[
        "Bruno"
    ],
    "name:heb_x_preferred":[
        "\u05d1\u05e8\u05d5\u05e0\u05d5"
    ],
    "name:hye_x_preferred":[
        "\u0532\u0580\u0578\u0582\u0576\u0578"
    ],
    "name:ind_x_preferred":[
        "Bruno"
    ],
    "name:ita_x_preferred":[
        "Bruno"
    ],
    "name:jav_x_preferred":[
        "Bruno"
    ],
    "name:jpn_x_preferred":[
        "\u30d6\u30eb\u30fc\u30ce"
    ],
    "name:kor_x_preferred":[
        "\ube0c\ub8e8\ub178"
    ],
    "name:lav_x_preferred":[
        "Bruno"
    ],
    "name:nld_x_preferred":[
        "Bruno"
    ],
    "name:pol_x_preferred":[
        "Bruno"
    ],
    "name:por_x_preferred":[
        "Bruno"
    ],
    "name:rus_x_preferred":[
        "\u0411\u0440\u0443\u043d\u043e"
    ],
    "name:slv_x_preferred":[
        "Bruno"
    ],
    "name:spa_x_preferred":[
        "Bruno"
    ],
    "name:srp_x_preferred":[
        "\u0411\u0440\u0443\u043d\u043e"
    ],
    "name:swe_x_preferred":[
        "Bruno"
    ],
    "name:tur_x_preferred":[
        "Bruno"
    ],
    "name:ukr_x_preferred":[
        "\u0411\u0440\u0443\u043d\u043e"
    ],
    "name:vol_x_preferred":[
        "Bruno"
    ],
    "name:zho_x_preferred":[
        "\u5e03\u9c81\u8bfa"
    ],
    "wof:lang_x_official":[
        "ind"
    ],
    "wof:lang_x_spoken":[
        "ind",
        "eng"
    ],
    "wof:name":"Bruno",
    "wof:placetype":"locality"
},
  "geometry": {"coordinates":[111.7593,-7.7531],"type":"Point"}
}