{
  "type": "Feature",
  "properties": {
    "gn:admin1_code":"8.0",
    "gn:asciiname":"Bruno",
    "gn:country_code":"ID",
    "gn:dem":815,
    "gn:feature_class":"P",
    "gn:feature_code":"PPL",
    "gn:name":"Bruno",
    "gn:population":0,
    "gn:timezone":"Asia/Jakarta",
    "iso:country":"ID",
    "name:ind_x_preferred":[
        "Bruno"
    ],
    "wof:name":"Bruno",
    "wof:placetype":"locality"
},
  "geometry": {"coordinates":[111.7593,-7.7531],"type":"Point"}
}