{
  "type": "Feature",
  "properties": {
    "gn:admin1_code":"7",
    "gn:asciiname":"Kemantren Lor",
    "gn:country_code":"ID",
    "gn:dem":47,
    "gn:feature_class":"P",
    "gn:feature_code":"PPL",
    "gn:name":"Kemantren Lor",
    "gn:population":0,
    "gn:timezone":"Asia/Jakarta",
    "iso:country":"ID",
    "name:ind_x_preferred":[
        "Kemantren Lor"
    ],
    "wof:name":"Kemantren Lor",
    "wof:placetype":"locality"
},
  "geometry": {"coordinates":[109.995,-7.65611],"type":"Point"}
}