{
  "type": "Feature",
  "properties": {
    "gn:admin1_code":"30.0",
    "gn:asciiname":"Cikoleang",
    "gn:country_code":"ID",
    "gn:dem":229,
    "gn:feature_class":"P",
    "gn:feature_code":"PPL",
    "gn:name":"Cikoleang",
    "gn:population":0,
    "gn:timezone":"Asia/Jakarta",
    "iso:country":"ID",
    "name:ind_x_preferred":[
        "Cikoleang"
    ],
    "name:und_x_variant":[
        "Tjikoleang"
    ],
    "wof:name":"Cikoleang",
    "wof:placetype":"locality"
},
  "geometry": {"coordinates":[107.0154,-7.2343],"type":"Point"}
}