{
  "type": "Feature",
  "properties": {
    "gn:admin1_code":"7",
    "gn:asciiname":"Dogleg",
    "gn:country_code":"ID",
    "gn:dem":251,
    "gn:feature_class":"P",
    "gn:feature_code":"PPL",
    "gn:name":"Dogleg",
    "gn:population":0,
    "gn:timezone":"Asia/Jakarta",
    "iso:country":"ID",
    "name:ind_x_preferred":[
        "Dogleg"
    ],
    "wof:name":"Dogleg",
    "wof:placetype":"locality"
},
  "geometry": {"coordinates":[109.91861000000002,-7.5825],"type":"Point"}
}