{
  "type": "Feature",
  "properties": {
    "gn:admin1_code":"26",
    "gn:asciiname":"Pondok Tanjung Rejo",
    "gn:country_code":"ID",
    "gn:dem":20,
    "gn:feature_class":"P",
    "gn:feature_code":"PPL",
    "gn:name":"Pondok Tanjung Rejo",
    "gn:population":0,
    "gn:timezone":"Asia/Jakarta",
    "iso:country":"ID",
    "name:ind_x_preferred":[
        "Pondok Tanjung Rejo"
    ],
    "wof:name":"Pondok Tanjung Rejo",
    "wof:placetype":"locality"
},
  "geometry": {"coordinates":[99.5578,3.0428],"type":"Point"}
}