{
  "type": "Feature",
  "properties": {
    "gn:admin1_code":"5.0",
    "gn:asciiname":"Lubuklawas",
    "gn:country_code":"ID",
    "gn:dem":55,
    "gn:feature_class":"P",
    "gn:feature_code":"PPL",
    "gn:name":"Lubuklawas",
    "gn:population":0,
    "gn:timezone":"Asia/Jakarta",
    "iso:country":"ID",
    "name:ind_x_preferred":[
        "Lubuklawas"
    ],
    "wof:name":"Lubuklawas",
    "wof:placetype":"locality"
},
  "geometry": {"coordinates":[102.94410999999999,-1.14359],"type":"Point"}
}