{
  "type": "Feature",
  "properties": {
    "gn:admin1_code":"7",
    "gn:asciiname":"Dukuhtengah",
    "gn:country_code":"ID",
    "gn:dem":864,
    "gn:feature_class":"P",
    "gn:feature_code":"PPL",
    "gn:name":"Dukuhtengah",
    "gn:population":0,
    "gn:timezone":"Asia/Jakarta",
    "iso:country":"ID",
    "name:ind_x_preferred":[
        "Dukuhtengah"
    ],
    "wof:name":"Dukuhtengah",
    "wof:placetype":"locality"
},
  "geometry": {"coordinates":[109.24167,-7.16556],"type":"Point"}
}