{
  "type": "Feature",
  "properties": {
    "gn:admin1_code":"33.0",
    "gn:asciiname":"Kampungsawah Landeuh",
    "gn:country_code":"ID",
    "gn:dem":432,
    "gn:feature_class":"P",
    "gn:feature_code":"PPLA4",
    "gn:name":"Kampungsawah Landeuh",
    "gn:population":0,
    "gn:timezone":"Asia/Jakarta",
    "iso:country":"ID",
    "name:ind_x_preferred":[
        "Kampungsawah Landeuh"
    ],
    "name:und_x_variant":[
        "Kampungsawah"
    ],
    "wof:name":"Kampungsawah Landeuh",
    "wof:placetype":"locality"
},
  "geometry": {"coordinates":[106.01000000000001,-6.2485],"type":"Point"}
}