{
  "type": "Feature",
  "properties": {
    "gn:admin1_code":"33.0",
    "gn:asciiname":"Barugbug",
    "gn:country_code":"ID",
    "gn:dem":22,
    "gn:feature_class":"P",
    "gn:feature_code":"PPL",
    "gn:name":"Barugbug",
    "gn:population":0,
    "gn:timezone":"Asia/Jakarta",
    "iso:country":"ID",
    "name:ind_x_preferred":[
        "Barugbug"
    ],
    "wof:name":"Barugbug",
    "wof:placetype":"locality"
},
  "geometry": {"coordinates":[105.90940000000001,-6.609],"type":"Point"}
}