{
  "type": "Feature",
  "properties": {
    "gn:admin1_code":"0.0",
    "gn:asciiname":"Manngan",
    "gn:cc2":"ID",
    "gn:country_code":"ID",
    "gn:dem":16,
    "gn:feature_class":"P",
    "gn:feature_code":"PPL",
    "gn:name":"Manngan",
    "gn:population":0,
    "gn:timezone":"Asia/Jayapura",
    "iso:country":"ID",
    "name:und_x_variant":[
        "Mannoan",
        "Mangan",
        "Manngan"
    ],
    "wof:name":"Manngan",
    "wof:placetype":"locality"
},
  "geometry": {"coordinates":[139.33333000000002,-8.03333],"type":"Point"}
}