{
  "type": "Feature",
  "properties": {
    "gn:admin1_code":"30",
    "gn:asciiname":"Angsana Dua",
    "gn:country_code":"ID",
    "gn:dem":548,
    "gn:feature_class":"P",
    "gn:feature_code":"PPL",
    "gn:name":"Angsana Dua",
    "gn:population":0,
    "gn:timezone":"Asia/Jakarta",
    "iso:country":"ID",
    "name:ind_x_preferred":[
        "Angsana Dua"
    ],
    "wof:name":"Angsana Dua",
    "wof:placetype":"locality"
},
  "geometry": {"coordinates":[106.605,-6.60917],"type":"Point"}
}