{
  "type": "Feature",
  "properties": {
    "gn:admin1_code":"30.0",
    "gn:asciiname":"Pasarkolot",
    "gn:country_code":"ID",
    "gn:dem":246,
    "gn:feature_class":"P",
    "gn:feature_code":"PPL",
    "gn:name":"Pasarkolot",
    "gn:population":0,
    "gn:timezone":"Asia/Jakarta",
    "iso:country":"ID",
    "name:ind_x_preferred":[
        "Pasarkolot"
    ],
    "wof:name":"Pasarkolot",
    "wof:placetype":"locality"
},
  "geometry": {"coordinates":[108.18819999999999,-7.4504],"type":"Point"}
}