{
  "type": "Feature",
  "properties": {
    "gn:admin1_code":"18.0",
    "gn:asciiname":"Pretana",
    "gn:country_code":"ID",
    "gn:dem":480,
    "gn:feature_class":"P",
    "gn:feature_code":"PPLA4",
    "gn:name":"Pretana",
    "gn:population":0,
    "gn:timezone":"Asia/Makassar",
    "iso:country":"ID",
    "name:ind_x_preferred":[
        "Parewatana"
    ],
    "wof:lang_x_official":[
        "ind"
    ],
    "wof:lang_x_spoken":[
        "ind",
        "eng"
    ],
    "wof:name":"Pretana",
    "wof:placetype":"locality"
},
  "geometry": {"coordinates":[119.64409999999999,-9.6161],"type":"Point"}
}