{
  "type": "Feature",
  "properties": {
    "gn:admin1_code":"1.0",
    "gn:asciiname":"Ujungbungo",
    "gn:country_code":"ID",
    "gn:dem":10,
    "gn:feature_class":"P",
    "gn:feature_code":"PPL",
    "gn:name":"Ujungbungo",
    "gn:population":0,
    "gn:timezone":"Asia/Jakarta",
    "iso:country":"ID",
    "name:ind_x_preferred":[
        "Ujungbungo"
    ],
    "name:und_x_variant":[
        "Udjungbungo",
        "Bunga"
    ],
    "wof:name":"Ujungbungo",
    "wof:placetype":"locality"
},
  "geometry": {"coordinates":[95.9242,2.6083],"type":"Point"}
}