{
  "type": "Feature",
  "properties": {
    "gn:admin1_code":"07",
    "gn:asciiname":"Tegalkatak",
    "gn:country_code":"ID",
    "gn:dem":306,
    "gn:feature_class":"P",
    "gn:feature_code":"PPL",
    "gn:name":"Tegalkatak",
    "gn:population":0,
    "gn:timezone":"Asia/Jakarta",
    "iso:country":"ID",
    "name:ind_x_preferred":[
        "Tegalkatak"
    ],
    "wof:name":"Tegalkatak",
    "wof:placetype":"locality"
},
  "geometry": {"coordinates":[111.00028,-7.73806],"type":"Point"}
}