{
  "type": "Feature",
  "properties": {
    "gn:admin1_code":"18",
    "gn:asciiname":"Aijauka Lama",
    "gn:country_code":"ID",
    "gn:dem":540,
    "gn:feature_class":"P",
    "gn:feature_code":"PPL",
    "gn:name":"Aijauka Lama",
    "gn:population":0,
    "gn:timezone":"Asia/Makassar",
    "iso:country":"ID",
    "wof:name":"Aijauka Lama",
    "wof:placetype":"locality"
},
  "geometry": {"coordinates":[124.42667,-9.46972],"type":"Point"}
}