{
  "type": "Feature",
  "properties": {
    "gn:admin1_code":"32.0",
    "gn:asciiname":"Talang Pakualan",
    "gn:country_code":"ID",
    "gn:dem":400,
    "gn:feature_class":"P",
    "gn:feature_code":"PPL",
    "gn:name":"Talang Pakualan",
    "gn:population":0,
    "gn:timezone":"Asia/Jakarta",
    "iso:country":"ID",
    "name:ind_x_preferred":[
        "Talang Pakualan"
    ],
    "wof:name":"Talang Pakualan",
    "wof:placetype":"locality"
},
  "geometry": {"coordinates":[104.06756,-4.67897],"type":"Point"}
}