{
  "type": "Feature",
  "properties": {
    "gn:admin1_code":"30.0",
    "gn:asciiname":"Cilowa",
    "gn:country_code":"ID",
    "gn:dem":10,
    "gn:feature_class":"P",
    "gn:feature_code":"PPL",
    "gn:name":"Cilowa",
    "gn:population":0,
    "gn:timezone":"Asia/Jakarta",
    "iso:country":"ID",
    "name:und_x_variant":[
        "Tjilowa",
        "Cilowa"
    ],
    "wof:name":"Cilowa",
    "wof:placetype":"locality"
},
  "geometry": {"coordinates":[106.48049,-7.19163],"type":"Point"}
}