{
  "type": "Feature",
  "properties": {
    "gn:admin1_code":"7",
    "gn:asciiname":"Dera",
    "gn:country_code":"ID",
    "gn:dem":1087,
    "gn:feature_class":"P",
    "gn:feature_code":"PPL",
    "gn:name":"Dera",
    "gn:population":0,
    "gn:timezone":"Asia/Jakarta",
    "iso:country":"ID",
    "name:fra_x_preferred":[
        "Dera"
    ],
    "name:ind_x_preferred":[
        "Dera"
    ],
    "name:snd_x_preferred":[
        "\u062f\u064a\u0631\u0648"
    ],
    "name:urd_x_preferred":[
        "\u0688\u06cc\u0631\u06c1"
    ],
    "wof:name":"Dera",
    "wof:placetype":"locality"
},
  "geometry": {"coordinates":[109.87528,-7.29417],"type":"Point"}
}