{
  "type": "Feature",
  "properties": {
    "gn:admin1_code":"30",
    "gn:asciiname":"Pabuwaran Sembilan",
    "gn:cc2":"ID",
    "gn:country_code":"ID",
    "gn:dem":33,
    "gn:feature_class":"P",
    "gn:feature_code":"PPL",
    "gn:name":"Pabuwaran Sembilan",
    "gn:population":0,
    "gn:timezone":"Asia/Jakarta",
    "iso:country":"ID",
    "name:und_x_variant":[
        "Pabuwaran 9",
        "Pabuwaran Sembilan"
    ],
    "wof:lang_x_official":[
        "ind"
    ],
    "wof:lang_x_spoken":[
        "ind",
        "eng"
    ],
    "wof:name":"Pabuwaran Sembilan",
    "wof:placetype":"locality"
},
  "geometry": {"coordinates":[106.37889,-6.28917],"type":"Point"}
}