{
  "type": "Feature",
  "properties": {
    "gn:admin1_code":"18.0",
    "gn:asciiname":"Waisumar",
    "gn:country_code":"ID",
    "gn:dem":468,
    "gn:feature_class":"P",
    "gn:feature_code":"PPL",
    "gn:name":"Waisumar",
    "gn:population":0,
    "gn:timezone":"Asia/Makassar",
    "iso:country":"ID",
    "name:ind_x_preferred":[
        "Waisumar"
    ],
    "wof:name":"Waisumar",
    "wof:placetype":"locality"
},
  "geometry": {"coordinates":[119.5262,-9.6107],"type":"Point"}
}