{
  "type": "Feature",
  "properties": {
    "gn:admin1_code":"7",
    "gn:asciiname":"Jatirokeh Lor",
    "gn:country_code":"ID",
    "gn:dem":26,
    "gn:feature_class":"P",
    "gn:feature_code":"PPL",
    "gn:name":"Jatirokeh Lor",
    "gn:population":0,
    "gn:timezone":"Asia/Jakarta",
    "iso:country":"ID",
    "name:ind_x_preferred":[
        "Jatirokeh Lor"
    ],
    "wof:name":"Jatirokeh Lor",
    "wof:placetype":"locality"
},
  "geometry": {"coordinates":[109.0213,-6.993],"type":"Point"}
}