{
  "type": "Feature",
  "properties": {
    "gn:admin1_code":"7.0",
    "gn:asciiname":"Banteng",
    "gn:country_code":"ID",
    "gn:dem":80,
    "gn:feature_class":"P",
    "gn:feature_code":"PPLA4",
    "gn:name":"Banteng",
    "gn:population":0,
    "gn:timezone":"Asia/Jakarta",
    "iso:country":"ID",
    "name:ind_x_preferred":[
        "Banteng"
    ],
    "wof:name":"Banteng",
    "wof:placetype":"locality"
},
  "geometry": {"coordinates":[111.0157,-6.5966],"type":"Point"}
}