{
  "type": "Feature",
  "properties": {
    "gn:admin1_code":"10.0",
    "gn:asciiname":"Gebang",
    "gn:country_code":"ID",
    "gn:dem":104,
    "gn:feature_class":"P",
    "gn:feature_code":"PPL",
    "gn:name":"Gebang",
    "gn:population":0,
    "gn:timezone":"Asia/Jakarta",
    "iso:country":"ID",
    "name:ind_x_preferred":[
        "Gebang"
    ],
    "name:und_x_variant":[
        "Gebang 2"
    ],
    "wof:name":"Gebang",
    "wof:placetype":"locality"
},
  "geometry": {"coordinates":[110.51694000000001,-8.10361],"type":"Point"}
}