{
  "type": "Feature",
  "properties": {
    "gn:admin1_code":"30",
    "gn:asciiname":"Tiparmesjid",
    "gn:country_code":"ID",
    "gn:dem":45,
    "gn:feature_class":"P",
    "gn:feature_code":"PPL",
    "gn:name":"Tiparmesjid",
    "gn:population":0,
    "gn:timezone":"Asia/Jakarta",
    "iso:country":"ID",
    "name:ind_x_preferred":[
        "Tiparmesjid"
    ],
    "name:und_x_variant":[
        "Tipar"
    ],
    "wof:name":"Tiparmesjid",
    "wof:placetype":"locality"
},
  "geometry": {"coordinates":[106.49111000000001,-6.31611],"type":"Point"}
}