{
  "type": "Feature",
  "properties": {
    "gn:admin1_code":"26",
    "gn:asciiname":"Panombean Baru Dua",
    "gn:country_code":"ID",
    "gn:dem":44,
    "gn:feature_class":"P",
    "gn:feature_code":"PPL",
    "gn:name":"Panombean Baru Dua",
    "gn:population":0,
    "gn:timezone":"Asia/Jakarta",
    "iso:country":"ID",
    "name:ind_x_preferred":[
        "Panombean Baru Dua"
    ],
    "name:und_x_variant":[
        "Penombeansada",
        "Panombean Baru 2"
    ],
    "wof:name":"Panombean Baru Dua",
    "wof:placetype":"locality"
},
  "geometry": {"coordinates":[99.2987,3.206],"type":"Point"}
}