{
  "type": "Feature",
  "properties": {
    "gn:admin1_code":"30",
    "gn:asciiname":"Karanggantung",
    "gn:country_code":"ID",
    "gn:dem":845,
    "gn:feature_class":"P",
    "gn:feature_code":"PPL",
    "gn:name":"Karanggantung",
    "gn:population":0,
    "gn:timezone":"Asia/Jakarta",
    "iso:country":"ID",
    "name:ind_x_preferred":[
        "Karanggantung"
    ],
    "wof:name":"Karanggantung",
    "wof:placetype":"locality"
},
  "geometry": {"coordinates":[107.01111000000002,-6.62556],"type":"Point"}
}