{
  "type": "Feature",
  "properties": {
    "gn:admin1_code":"7",
    "gn:asciiname":"Slimpyak",
    "gn:country_code":"ID",
    "gn:dem":59,
    "gn:feature_class":"P",
    "gn:feature_code":"PPL",
    "gn:name":"Slimpyak",
    "gn:population":0,
    "gn:timezone":"Asia/Jakarta",
    "iso:country":"ID",
    "name:ind_x_preferred":[
        "Slimpyak"
    ],
    "wof:name":"Slimpyak",
    "wof:placetype":"locality"
},
  "geometry": {"coordinates":[110.1028,-7.0395],"type":"Point"}
}