{
  "type": "Feature",
  "properties": {
    "gn:admin1_code":"18.0",
    "gn:asciiname":"Lau",
    "gn:country_code":"ID",
    "gn:dem":782,
    "gn:feature_class":"P",
    "gn:feature_code":"PPL",
    "gn:name":"Lau",
    "gn:population":0,
    "gn:timezone":"Asia/Makassar",
    "iso:country":"ID",
    "name:ceb_x_preferred":[
        "Lau"
    ],
    "name:ces_x_preferred":[
        "Lau"
    ],
    "name:deu_x_preferred":[
        "Lau"
    ],
    "name:fra_x_preferred":[
        "Lau"
    ],
    "name:heb_x_preferred":[
        "\u05dc\u05d0\u05d5"
    ],
    "name:ind_x_preferred":[
        "Lau"
    ],
    "name:nld_x_preferred":[
        "Lau"
    ],
    "name:swe_x_preferred":[
        "Lau"
    ],
    "name:ukr_x_preferred":[
        "LAU"
    ],
    "wof:lang_x_official":[
        "ind"
    ],
    "wof:lang_x_spoken":[
        "ind",
        "eng"
    ],
    "wof:name":"Lau",
    "wof:placetype":"locality"
},
  "geometry": {"coordinates":[124.5949,-9.8107],"type":"Point"}
}