{
  "type": "Feature",
  "properties": {
    "gn:admin1_code":"38",
    "gn:asciiname":"Boda",
    "gn:country_code":"ID",
    "gn:dem":29,
    "gn:feature_class":"P",
    "gn:feature_code":"PPL",
    "gn:name":"Boda",
    "gn:population":0,
    "gn:timezone":"Asia/Makassar",
    "iso:country":"ID",
    "name:ben_x_preferred":[
        "\u09ac\u09cb\u09a6"
    ],
    "name:bpy_x_preferred":[
        "\u09ac\u09cb\u09a6"
    ],
    "name:ceb_x_preferred":[
        "Boda"
    ],
    "name:deu_x_preferred":[
        "Boda"
    ],
    "name:fin_x_preferred":[
        "Boda"
    ],
    "name:fra_x_preferred":[
        "Boda"
    ],
    "name:ind_x_preferred":[
        "Boda"
    ],
    "name:ita_x_preferred":[
        "Boda"
    ],
    "name:nld_x_preferred":[
        "Boda"
    ],
    "name:oci_x_preferred":[
        "Boda"
    ],
    "name:pol_x_preferred":[
        "Boda"
    ],
    "name:por_x_preferred":[
        "Boda"
    ],
    "name:rus_x_preferred":[
        "\u0411\u043e\u0434\u0430"
    ],
    "name:spa_x_preferred":[
        "Boda"
    ],
    "name:swe_x_preferred":[
        "Boda"
    ],
    "wof:lang_x_official":[
        "ind"
    ],
    "wof:lang_x_spoken":[
        "ind",
        "eng"
    ],
    "wof:name":"Boda",
    "wof:placetype":"locality"
},
  "geometry": {"coordinates":[120.3047,-4.4914],"type":"Point"}
}