{
  "type": "Feature",
  "properties": {
    "gn:admin1_code":"7",
    "gn:asciiname":"Karanglo",
    "gn:country_code":"ID",
    "gn:dem":290,
    "gn:feature_class":"P",
    "gn:feature_code":"PPL",
    "gn:name":"Karanglo",
    "gn:population":0,
    "gn:timezone":"Asia/Jakarta",
    "iso:country":"ID",
    "name:ind_x_preferred":[
        "Karanglo"
    ],
    "wof:name":"Karanglo",
    "wof:placetype":"locality"
},
  "geometry": {"coordinates":[111.26416999999999,-7.85222],"type":"Point"}
}