{
  "type": "Feature",
  "properties": {
    "gn:admin1_code":"15.0",
    "gn:asciiname":"Umbulan Tebing Tinggi",
    "gn:country_code":"ID",
    "gn:dem":19,
    "gn:feature_class":"P",
    "gn:feature_code":"PPL",
    "gn:name":"Umbulan Tebing Tinggi",
    "gn:population":0,
    "gn:timezone":"Asia/Jakarta",
    "iso:country":"ID",
    "name:ind_x_preferred":[
        "Umbulan Tebing Tinggi"
    ],
    "name:ind_x_variant":[
        "Umbulantebingtinggi"
    ],
    "wof:lang_x_official":[
        "ind"
    ],
    "wof:lang_x_spoken":[
        "ind",
        "eng"
    ],
    "wof:name":"Umbulan Tebing Tinggi",
    "wof:placetype":"locality"
},
  "geometry": {"coordinates":[105.16804999999999,-4.52474],"type":"Point"}
}