{
  "type": "Feature",
  "properties": {
    "gn:admin1_code":"7.0",
    "gn:asciiname":"Nolobangsan Barat",
    "gn:country_code":"ID",
    "gn:dem":613,
    "gn:feature_class":"P",
    "gn:feature_code":"PPL",
    "gn:name":"Nolobangsan Barat",
    "gn:population":0,
    "gn:timezone":"Asia/Jakarta",
    "iso:country":"ID",
    "wof:name":"Nolobangsan Barat",
    "wof:placetype":"locality"
},
  "geometry": {"coordinates":[110.17778,-7.35944],"type":"Point"}
}