{
  "type": "Feature",
  "properties": {
    "gn:admin1_code":"30.0",
    "gn:asciiname":"Legok",
    "gn:country_code":"ID",
    "gn:dem":424,
    "gn:feature_class":"P",
    "gn:feature_code":"PPL",
    "gn:name":"Legok",
    "gn:population":0,
    "gn:timezone":"Asia/Jakarta",
    "iso:country":"ID",
    "name:ind_x_preferred":[
        "Legok"
    ],
    "name:jav_x_preferred":[
        "Legok"
    ],
    "name:msa_x_preferred":[
        "Legok"
    ],
    "wof:lang_x_official":[
        "ind"
    ],
    "wof:lang_x_spoken":[
        "ind",
        "eng"
    ],
    "wof:name":"Legok",
    "wof:placetype":"locality"
},
  "geometry": {"coordinates":[108.16419999999999,-7.3354],"type":"Point"}
}