{
  "type": "Feature",
  "properties": {
    "gn:admin1_code":"18.0",
    "gn:asciiname":"Koli",
    "gn:country_code":"ID",
    "gn:dem":685,
    "gn:feature_class":"P",
    "gn:feature_code":"PPL",
    "gn:name":"Koli",
    "gn:population":0,
    "gn:timezone":"Asia/Makassar",
    "iso:country":"ID",
    "name:ind_x_preferred":[
        "Koli"
    ],
    "wof:name":"Koli",
    "wof:placetype":"locality"
},
  "geometry": {"coordinates":[121.0864,-8.7877],"type":"Point"}
}