{
  "type": "Feature",
  "properties": {
    "gn:admin1_code":"30.0",
    "gn:asciiname":"Gambarsari",
    "gn:country_code":"ID",
    "gn:dem":32,
    "gn:feature_class":"P",
    "gn:feature_code":"PPL",
    "gn:name":"Gambarsari",
    "gn:population":0,
    "gn:timezone":"Asia/Jakarta",
    "iso:country":"ID",
    "name:ind_x_preferred":[
        "Gambarsari"
    ],
    "name:und_x_variant":[
        "Gambarsar"
    ],
    "wof:name":"Gambarsari",
    "wof:placetype":"locality"
},
  "geometry": {"coordinates":[107.78722,-6.44472],"type":"Point"}
}