{
  "type": "Feature",
  "properties": {
    "gn:admin1_code":"15.0",
    "gn:asciiname":"Pulau Kangkung",
    "gn:country_code":"ID",
    "gn:dem":56,
    "gn:feature_class":"P",
    "gn:feature_code":"PPL",
    "gn:name":"Pulau Kangkung",
    "gn:population":0,
    "gn:timezone":"Asia/Jakarta",
    "iso:country":"ID",
    "name:ind_x_preferred":[
        "Pulau Kangkung"
    ],
    "wof:name":"Pulau Kangkung",
    "wof:placetype":"locality"
},
  "geometry": {"coordinates":[105.16414,-5.12595],"type":"Point"}
}