{
  "type": "Feature",
  "properties": {
    "gn:admin1_code":"08",
    "gn:asciiname":"Langlang Satu",
    "gn:country_code":"ID",
    "gn:dem":539,
    "gn:feature_class":"P",
    "gn:feature_code":"PPL",
    "gn:name":"Langlang Satu",
    "gn:population":0,
    "gn:timezone":"Asia/Jakarta",
    "iso:country":"ID",
    "name:ind_x_preferred":[
        "Langlang Satu"
    ],
    "name:und_x_variant":[
        "Lahglang"
    ],
    "wof:name":"Langlang Satu",
    "wof:placetype":"locality"
},
  "geometry": {"coordinates":[112.63249999999999,-7.8956],"type":"Point"}
}