{
  "type": "Feature",
  "properties": {
    "gn:admin1_code":"30",
    "gn:asciiname":"Babakansirna",
    "gn:country_code":"ID",
    "gn:dem":34,
    "gn:feature_class":"P",
    "gn:feature_code":"PPL",
    "gn:name":"Babakansirna",
    "gn:population":0,
    "gn:timezone":"Asia/Jakarta",
    "iso:country":"ID",
    "name:ind_x_preferred":[
        "Babakansirna"
    ],
    "wof:name":"Babakansirna",
    "wof:placetype":"locality"
},
  "geometry": {"coordinates":[106.52167,-6.96389],"type":"Point"}
}