{
  "type": "Feature",
  "properties": {
    "gn:admin1_code":"11.0",
    "gn:asciiname":"Kubu",
    "gn:country_code":"ID",
    "gn:dem":83,
    "gn:feature_class":"P",
    "gn:feature_code":"PPL",
    "gn:name":"Kubu",
    "gn:population":0,
    "gn:timezone":"Asia/Pontianak",
    "iso:country":"ID",
    "name:ind_x_preferred":[
        "Kubu"
    ],
    "name:und_x_variant":[
        "Koeboe"
    ],
    "wof:name":"Kubu",
    "wof:placetype":"locality"
},
  "geometry": {"coordinates":[111.39252,0.84614],"type":"Point"}
}