{
  "type": "Feature",
  "properties": {
    "gn:admin1_code":"8.0",
    "gn:asciiname":"Kasri",
    "gn:country_code":"ID",
    "gn:dem":244,
    "gn:feature_class":"P",
    "gn:feature_code":"PPL",
    "gn:name":"Kasri",
    "gn:population":0,
    "gn:timezone":"Asia/Jakarta",
    "iso:country":"ID",
    "name:ind_x_preferred":[
        "Kasri"
    ],
    "wof:name":"Kasri",
    "wof:placetype":"locality"
},
  "geometry": {"coordinates":[111.30110999999999,-8.195],"type":"Point"}
}