{
  "type": "Feature",
  "properties": {
    "gn:admin1_code":"24",
    "gn:asciiname":"Campago",
    "gn:country_code":"ID",
    "gn:dem":980,
    "gn:feature_class":"P",
    "gn:feature_code":"PPL",
    "gn:name":"Campago",
    "gn:population":0,
    "gn:timezone":"Asia/Jakarta",
    "iso:country":"ID",
    "name:ind_x_preferred":[
        "Campago"
    ],
    "wof:name":"Campago",
    "wof:placetype":"locality"
},
  "geometry": {"coordinates":[100.26878000000001,-0.38072],"type":"Point"}
}