{
  "type": "Feature",
  "properties": {
    "gn:admin1_code":"17.0",
    "gn:asciiname":"Gubukbaru",
    "gn:country_code":"ID",
    "gn:dem":95,
    "gn:feature_class":"P",
    "gn:feature_code":"PPL",
    "gn:name":"Gubukbaru",
    "gn:population":0,
    "gn:timezone":"Asia/Makassar",
    "iso:country":"ID",
    "name:ind_x_preferred":[
        "Gubukbaru"
    ],
    "wof:name":"Gubukbaru",
    "wof:placetype":"locality"
},
  "geometry": {"coordinates":[116.63630000000001,-8.2996],"type":"Point"}
}