{
  "type": "Feature",
  "properties": {
    "gn:admin1_code":"37.0",
    "gn:asciiname":"Paritjalangaung",
    "gn:country_code":"ID",
    "gn:dem":8,
    "gn:feature_class":"P",
    "gn:feature_code":"PPL",
    "gn:name":"Paritjalangaung",
    "gn:population":0,
    "gn:timezone":"Asia/Jakarta",
    "iso:country":"ID",
    "name:ind_x_preferred":[
        "Paritjalangaung"
    ],
    "wof:name":"Paritjalangaung",
    "wof:placetype":"locality"
},
  "geometry": {"coordinates":[103.23220000000001,-0.1304],"type":"Point"}
}