{
  "type": "Feature",
  "properties": {
    "gn:admin1_code":"7",
    "gn:asciiname":"Kedungmojo",
    "gn:country_code":"ID",
    "gn:dem":40,
    "gn:feature_class":"P",
    "gn:feature_code":"PPL",
    "gn:name":"Kedungmojo",
    "gn:population":0,
    "gn:timezone":"Asia/Jakarta",
    "iso:country":"ID",
    "name:ind_x_preferred":[
        "Kedungmojo"
    ],
    "wof:name":"Kedungmojo",
    "wof:placetype":"locality"
},
  "geometry": {"coordinates":[110.9191,-6.778],"type":"Point"}
}