{
  "type": "Feature",
  "properties": {
    "gn:admin1_code":"7.0",
    "gn:asciiname":"Ingasrejo",
    "gn:country_code":"ID",
    "gn:dem":114,
    "gn:feature_class":"P",
    "gn:feature_code":"PPL",
    "gn:name":"Ingasrejo",
    "gn:population":0,
    "gn:timezone":"Asia/Jakarta",
    "iso:country":"ID",
    "wof:name":"Ingasrejo",
    "wof:placetype":"locality"
},
  "geometry": {"coordinates":[110.86556000000002,-7.53528],"type":"Point"}
}