{
  "type": "Feature",
  "properties": {
    "gn:admin1_code":"41.0",
    "gn:asciiname":"Kurrak",
    "gn:country_code":"ID",
    "gn:dem":436,
    "gn:feature_class":"P",
    "gn:feature_code":"PPL",
    "gn:name":"Kurrak",
    "gn:population":0,
    "gn:timezone":"Asia/Makassar",
    "iso:country":"ID",
    "name:ind_x_preferred":[
        "Kurrak"
    ],
    "wof:name":"Kurrak",
    "wof:placetype":"locality"
},
  "geometry": {"coordinates":[119.3124,-3.2916],"type":"Point"}
}