{
  "type": "Feature",
  "properties": {
    "gn:admin1_code":"18.0",
    "gn:asciiname":"Tanah Merah",
    "gn:country_code":"ID",
    "gn:dem":16,
    "gn:feature_class":"P",
    "gn:feature_code":"PPL",
    "gn:name":"Tanah Merah",
    "gn:population":0,
    "gn:timezone":"Asia/Makassar",
    "iso:country":"ID",
    "name:ceb_x_preferred":[
        "Tanah Merah"
    ],
    "name:ind_x_preferred":[
        "Tanah Merah"
    ],
    "name:nld_x_preferred":[
        "Tanah Merah"
    ],
    "name:swe_x_preferred":[
        "Tanah Merah"
    ],
    "wof:lang_x_official":[
        "ind"
    ],
    "wof:lang_x_spoken":[
        "ind",
        "eng"
    ],
    "wof:name":"Tanah Merah",
    "wof:placetype":"locality"
},
  "geometry": {"coordinates":[123.029,-8.3162],"type":"Point"}
}