{
  "type": "Feature",
  "properties": {
    "gn:admin1_code":"38",
    "gn:asciiname":"Sopa",
    "gn:country_code":"ID",
    "gn:dem":92,
    "gn:feature_class":"P",
    "gn:feature_code":"PPL",
    "gn:name":"Sopa",
    "gn:population":0,
    "gn:timezone":"Asia/Makassar",
    "iso:country":"ID",
    "name:ind_x_preferred":[
        "Sopa"
    ],
    "wof:name":"Sopa",
    "wof:placetype":"locality"
},
  "geometry": {"coordinates":[120.15649999999999,-5.4966],"type":"Point"}
}