{
  "type": "Feature",
  "properties": {
    "gn:admin1_code":"38",
    "gn:asciiname":"Bululonrong",
    "gn:country_code":"ID",
    "gn:dem":48,
    "gn:feature_class":"P",
    "gn:feature_code":"PPL",
    "gn:name":"Bululonrong",
    "gn:population":0,
    "gn:timezone":"Asia/Makassar",
    "iso:country":"ID",
    "name:ind_x_preferred":[
        "Bululonrong"
    ],
    "wof:name":"Bululonrong",
    "wof:placetype":"locality"
},
  "geometry": {"coordinates":[120.2454,-5.4593],"type":"Point"}
}