{
  "type": "Feature",
  "properties": {
    "gn:admin1_code":"30.0",
    "gn:asciiname":"Pondokcempaka",
    "gn:country_code":"ID",
    "gn:dem":26,
    "gn:feature_class":"P",
    "gn:feature_code":"PPL",
    "gn:name":"Pondokcempaka",
    "gn:population":0,
    "gn:timezone":"Asia/Jakarta",
    "iso:country":"ID",
    "name:ind_x_preferred":[
        "Pondokcempaka"
    ],
    "name:und_x_variant":[
        "Pondoktjempaka",
        "Pondokcempaca"
    ],
    "wof:name":"Pondokcempaka",
    "wof:placetype":"locality"
},
  "geometry": {"coordinates":[106.91240000000001,-6.2604],"type":"Point"}
}