{
  "type": "Feature",
  "properties": {
    "gn:admin1_code":"8.0",
    "gn:asciiname":"Malangsari",
    "gn:country_code":"ID",
    "gn:dem":609,
    "gn:feature_class":"P",
    "gn:feature_code":"PPL",
    "gn:name":"Malangsari",
    "gn:population":0,
    "gn:timezone":"Asia/Jakarta",
    "iso:country":"ID",
    "name:ind_x_preferred":[
        "Malangsari"
    ],
    "wof:name":"Malangsari",
    "wof:placetype":"locality"
},
  "geometry": {"coordinates":[113.9556,-8.3637],"type":"Point"}
}