{
  "type": "Feature",
  "properties": {
    "gn:country":"ID",
    "gn:fcode":"PPL",
    "gn:pop":0,
    "iso:country":"ID",
    "name:ace_x_preferred":[
        "Sicincin"
    ],
    "name:deu_x_preferred":[
        "Sicincin"
    ],
    "name:eng_x_preferred":[
        "Sicincin"
    ],
    "name:fra_x_preferred":[
        "Sicincin"
    ],
    "name:ind_x_preferred":[
        "Sicincin"
    ],
    "name:min_x_preferred":[
        "Sicincin"
    ],
    "name:msa_x_preferred":[
        "Sicincin"
    ],
    "name:nld_x_preferred":[
        "Sicincin"
    ],
    "name:spa_x_preferred":[
        "Sicincin"
    ],
    "name:unk_x_variant":[
        "Pasarsitjintjin"
    ],
    "qs:name":"Sicincin",
    "qs:name_adm0":"Indonesia",
    "qs:name_adm1":"Sumatera Barat",
    "qs:photos_9r":0,
    "qs:photos_sr":0,
    "qs:placetype":"Town",
    "qs:pop_sr":"0",
    "wof:name":"Sicincin",
    "wof:placetype":"locality",
    "wof:population":0
},
  "geometry": {"coordinates":[100.27225,-0.57586],"type":"Point"}
}