{
  "type": "Feature",
  "properties": {
    "gn:admin1_code":"26",
    "gn:asciiname":"Bungajulu",
    "gn:country_code":"ID",
    "gn:dem":536,
    "gn:feature_class":"P",
    "gn:feature_code":"PPL",
    "gn:name":"Bungajulu",
    "gn:population":0,
    "gn:timezone":"Asia/Jakarta",
    "iso:country":"ID",
    "name:ind_x_preferred":[
        "Bungajulu"
    ],
    "name:und_x_variant":[
        "Bungadjulu"
    ],
    "wof:lang_x_official":[
        "ind"
    ],
    "wof:lang_x_spoken":[
        "ind",
        "eng"
    ],
    "wof:name":"Bungajulu",
    "wof:placetype":"locality"
},
  "geometry": {"coordinates":[98.2139,2.58],"type":"Point"}
}