{
  "type": "Feature",
  "properties": {
    "gn:admin1_code":"21.0",
    "gn:asciiname":"Matanga",
    "gn:country_code":"ID",
    "gn:dem":1,
    "gn:feature_class":"P",
    "gn:feature_code":"PPL",
    "gn:name":"Matanga",
    "gn:population":0,
    "gn:timezone":"Asia/Makassar",
    "iso:country":"ID",
    "name:ceb_x_preferred":[
        "Matanga"
    ],
    "name:ind_x_preferred":[
        "Matanga"
    ],
    "name:swe_x_preferred":[
        "Matanga"
    ],
    "wof:lang_x_official":[
        "ind"
    ],
    "wof:lang_x_spoken":[
        "ind",
        "eng"
    ],
    "wof:name":"Matanga",
    "wof:placetype":"locality"
},
  "geometry": {"coordinates":[123.5872,-1.7131],"type":"Point"}
}