{
  "type": "Feature",
  "properties": {
    "gn:admin1_code":"24",
    "gn:asciiname":"Sungaitanuk",
    "gn:country_code":"ID",
    "gn:dem":36,
    "gn:feature_class":"P",
    "gn:feature_code":"PPL",
    "gn:name":"Sungaitanuk",
    "gn:population":0,
    "gn:timezone":"Asia/Jakarta",
    "iso:country":"ID",
    "name:ind_x_preferred":[
        "Sungaitanuk"
    ],
    "wof:name":"Sungaitanuk",
    "wof:placetype":"locality"
},
  "geometry": {"coordinates":[100.50432000000001,-1.1531],"type":"Point"}
}