{
  "type": "Feature",
  "properties": {
    "gn:admin1_code":"26",
    "gn:asciiname":"Petuaranulu",
    "gn:country_code":"ID",
    "gn:dem":21,
    "gn:feature_class":"P",
    "gn:feature_code":"PPL",
    "gn:name":"Petuaranulu",
    "gn:population":0,
    "gn:timezone":"Asia/Jakarta",
    "iso:country":"ID",
    "name:ind_x_preferred":[
        "Petuaranulu"
    ],
    "wof:name":"Petuaranulu",
    "wof:placetype":"locality"
},
  "geometry": {"coordinates":[99.00449999999999,3.4951],"type":"Point"}
}