{
  "type": "Feature",
  "properties": {
    "gn:admin1_code":"30.0",
    "gn:asciiname":"Cisantri",
    "gn:country_code":"ID",
    "gn:dem":348,
    "gn:feature_class":"P",
    "gn:feature_code":"PPL",
    "gn:name":"Cisantri",
    "gn:population":0,
    "gn:timezone":"Asia/Jakarta",
    "iso:country":"ID",
    "name:ind_x_preferred":[
        "Cisantri"
    ],
    "wof:name":"Cisantri",
    "wof:placetype":"locality"
},
  "geometry": {"coordinates":[107.20569999999999,-7.3184],"type":"Point"}
}