{
  "type": "Feature",
  "properties": {
    "gn:admin1_code":"0.0",
    "gn:asciiname":"Banameha",
    "gn:country_code":"ID",
    "gn:dem":171,
    "gn:feature_class":"P",
    "gn:feature_code":"PPL",
    "gn:name":"Banameha",
    "gn:population":0,
    "gn:timezone":"Asia/Makassar",
    "iso:country":"ID",
    "wof:name":"Banameha",
    "wof:placetype":"locality"
},
  "geometry": {"coordinates":[119.93333,-9.45],"type":"Point"}
}