{
  "type": "Feature",
  "properties": {
    "gn:admin1_code":"18",
    "gn:asciiname":"Halibot",
    "gn:country_code":"ID",
    "gn:dem":59,
    "gn:feature_class":"P",
    "gn:feature_code":"PPL",
    "gn:name":"Halibot",
    "gn:population":0,
    "gn:timezone":"Asia/Makassar",
    "iso:country":"ID",
    "wof:name":"Halibot",
    "wof:placetype":"locality"
},
  "geometry": {"coordinates":[125.01083,-9.4725],"type":"Point"}
}