{
  "type": "Feature",
  "properties": {
    "gn:admin1_code":"38.0",
    "gn:asciiname":"Patappo",
    "gn:country_code":"ID",
    "gn:dem":1247,
    "gn:feature_class":"P",
    "gn:feature_code":"PPL",
    "gn:name":"Patappo",
    "gn:population":0,
    "gn:timezone":"Asia/Makassar",
    "iso:country":"ID",
    "name:ind_x_preferred":[
        "Patappo"
    ],
    "wof:name":"Patappo",
    "wof:placetype":"locality"
},
  "geometry": {"coordinates":[119.74209999999999,-3.0819],"type":"Point"}
}