{
  "type": "Feature",
  "properties": {
    "gn:admin1_code":"38",
    "gn:asciiname":"Paria",
    "gn:country_code":"ID",
    "gn:dem":168,
    "gn:feature_class":"P",
    "gn:feature_code":"PPL",
    "gn:name":"Paria",
    "gn:population":0,
    "gn:timezone":"Asia/Makassar",
    "iso:country":"ID",
    "name:ces_x_preferred":[
        "Paria"
    ],
    "name:deu_x_preferred":[
        "Paria"
    ],
    "name:fra_x_preferred":[
        "Paria"
    ],
    "name:hrv_x_preferred":[
        "Paria"
    ],
    "name:ind_x_preferred":[
        "Paria"
    ],
    "name:ita_x_preferred":[
        "Paria"
    ],
    "name:kor_x_preferred":[
        "\ud30c\ub9ac\uc544"
    ],
    "name:nld_x_preferred":[
        "Paria"
    ],
    "name:pol_x_preferred":[
        "Paria"
    ],
    "name:spa_x_preferred":[
        "Paria"
    ],
    "name:swe_x_preferred":[
        "Paria"
    ],
    "wof:name":"Paria",
    "wof:placetype":"locality"
},
  "geometry": {"coordinates":[120.17610000000001,-5.0863],"type":"Point"}
}