{
  "type": "Feature",
  "properties": {
    "gn:admin1_code":"8.0",
    "gn:asciiname":"Blumbur",
    "gn:country_code":"ID",
    "gn:dem":563,
    "gn:feature_class":"P",
    "gn:feature_code":"PPL",
    "gn:name":"Blumbur",
    "gn:population":0,
    "gn:timezone":"Asia/Jakarta",
    "iso:country":"ID",
    "name:ind_x_preferred":[
        "Blumbur"
    ],
    "wof:name":"Blumbur",
    "wof:placetype":"locality"
},
  "geometry": {"coordinates":[111.4415,-8.0712],"type":"Point"}
}