{
  "type": "Feature",
  "properties": {
    "gn:admin1_code":"07",
    "gn:asciiname":"Kalibanyu",
    "gn:cc2":"ID",
    "gn:country_code":"ID",
    "gn:dem":23,
    "gn:feature_class":"P",
    "gn:feature_code":"PPL",
    "gn:name":"Kalibanyu",
    "gn:population":0,
    "gn:timezone":"Asia/Jakarta",
    "iso:country":"ID",
    "name:und_x_variant":[
        "Kalibanju",
        "Kalibanyu"
    ],
    "wof:name":"Kalibanyu",
    "wof:placetype":"locality"
},
  "geometry": {"coordinates":[110.70778,-7.10833],"type":"Point"}
}