{
  "type": "Feature",
  "properties": {
    "gn:admin1_code":"8.0",
    "gn:asciiname":"Karangwaru",
    "gn:country_code":"ID",
    "gn:dem":16,
    "gn:feature_class":"P",
    "gn:feature_code":"PPL",
    "gn:name":"Karangwaru",
    "gn:population":0,
    "gn:timezone":"Asia/Jakarta",
    "iso:country":"ID",
    "name:ind_x_preferred":[
        "Karangwaru"
    ],
    "wof:name":"Karangwaru",
    "wof:placetype":"locality"
},
  "geometry": {"coordinates":[112.0539,-6.9043],"type":"Point"}
}