{
  "type": "Feature",
  "properties": {
    "gn:admin1_code":"15.0",
    "gn:asciiname":"Singgaruga",
    "gn:country_code":"ID",
    "gn:dem":8,
    "gn:feature_class":"P",
    "gn:feature_code":"PPL",
    "gn:name":"Singgaruga",
    "gn:population":0,
    "gn:timezone":"Asia/Jakarta",
    "iso:country":"ID",
    "name:ind_x_preferred":[
        "Singgaruga"
    ],
    "name:und_x_variant":[
        "Singgaroega",
        "Singgaruga",
        "Singgaraga"
    ],
    "wof:lang_x_official":[
        "ind"
    ],
    "wof:lang_x_spoken":[
        "ind",
        "eng"
    ],
    "wof:name":"Singgaruga",
    "wof:placetype":"locality"
},
  "geometry": {"coordinates":[103.82693999999999,-5.05711],"type":"Point"}
}