{
  "type": "Feature",
  "properties": {
    "gn:admin1_code":"10.0",
    "gn:asciiname":"Tegalrejo",
    "gn:country_code":"ID",
    "gn:dem":221,
    "gn:feature_class":"P",
    "gn:feature_code":"PPL",
    "gn:name":"Tegalrejo",
    "gn:population":0,
    "gn:timezone":"Asia/Jakarta",
    "iso:country":"ID",
    "wof:name":"Tegalrejo",
    "wof:placetype":"locality"
},
  "geometry": {"coordinates":[110.10138999999999,-7.815],"type":"Point"}
}