{
  "type": "Feature",
  "properties": {
    "gn:admin1_code":"7",
    "gn:asciiname":"Gandu",
    "gn:country_code":"ID",
    "gn:dem":71,
    "gn:feature_class":"P",
    "gn:feature_code":"PPL",
    "gn:name":"Gandu",
    "gn:population":0,
    "gn:timezone":"Asia/Jakarta",
    "iso:country":"ID",
    "name:bpy_x_preferred":[
        "\u0997\u09be\u09a8\u09cd\u09a1\u09c1"
    ],
    "name:epo_x_preferred":[
        "Gandu"
    ],
    "name:fra_x_preferred":[
        "Gandu"
    ],
    "name:hye_x_preferred":[
        "\u0533\u0561\u0576\u0564\u0578\u0582"
    ],
    "name:ind_x_preferred":[
        "Gandu"
    ],
    "name:ita_x_preferred":[
        "Gandu"
    ],
    "name:kat_x_preferred":[
        "\u10d2\u10d0\u10dc\u10d3\u10e3"
    ],
    "name:kaz_x_preferred":[
        "\u0413\u0430\u043d\u0434\u0443"
    ],
    "name:mlg_x_preferred":[
        "Gandu"
    ],
    "name:nld_x_preferred":[
        "Gandu"
    ],
    "name:nor_x_preferred":[
        "Gandu"
    ],
    "name:pol_x_preferred":[
        "Gandu"
    ],
    "name:por_x_preferred":[
        "Gandu"
    ],
    "name:ron_x_preferred":[
        "Gandu"
    ],
    "name:rus_x_preferred":[
        "\u0413\u0430\u043d\u0434\u0443"
    ],
    "name:spa_x_preferred":[
        "Gandu"
    ],
    "name:vie_x_preferred":[
        "Gandu"
    ],
    "name:vol_x_preferred":[
        "Gandu"
    ],
    "name:war_x_preferred":[
        "Gandu"
    ],
    "wof:name":"Gandu",
    "wof:placetype":"locality"
},
  "geometry": {"coordinates":[111.3034,-7.0625],"type":"Point"}
}