{
  "type": "Feature",
  "properties": {
    "gn:admin1_code":"26",
    "gn:asciiname":"Kuala",
    "gn:country_code":"ID",
    "gn:dem":563,
    "gn:feature_class":"P",
    "gn:feature_code":"PPL",
    "gn:name":"Kuala",
    "gn:population":0,
    "gn:timezone":"Asia/Jakarta",
    "iso:country":"ID",
    "name:ind_x_preferred":[
        "Kuala"
    ],
    "name:und_x_variant":[
        "Kwala"
    ],
    "wof:name":"Kuala",
    "wof:placetype":"locality"
},
  "geometry": {"coordinates":[98.2289,3.0715],"type":"Point"}
}