{
  "type": "Feature",
  "properties": {
    "gn:admin1_code":"26",
    "gn:asciiname":"Dolok Siduadua",
    "gn:country_code":"ID",
    "gn:dem":1241,
    "gn:feature_class":"P",
    "gn:feature_code":"PPL",
    "gn:name":"Dolok Siduadua",
    "gn:population":0,
    "gn:timezone":"Asia/Jakarta",
    "iso:country":"ID",
    "name:ind_x_preferred":[
        "Dolok Siduadua"
    ],
    "wof:name":"Dolok Siduadua",
    "wof:placetype":"locality"
},
  "geometry": {"coordinates":[99.13226,1.95777],"type":"Point"}
}