{
  "type": "Feature",
  "properties": {
    "gn:admin1_code":"38.0",
    "gn:asciiname":"Bocikoro",
    "gn:country_code":"ID",
    "gn:dem":257,
    "gn:feature_class":"P",
    "gn:feature_code":"PPL",
    "gn:name":"Bocikoro",
    "gn:population":0,
    "gn:timezone":"Asia/Makassar",
    "iso:country":"ID",
    "name:ind_x_preferred":[
        "Bocikoro"
    ],
    "name:und_x_variant":[
        "Batjikoro",
        "Bacikoro"
    ],
    "wof:lang_x_official":[
        "ind"
    ],
    "wof:lang_x_spoken":[
        "ind",
        "eng"
    ],
    "wof:name":"Bocikoro",
    "wof:placetype":"locality"
},
  "geometry": {"coordinates":[120.10720000000001,-5.2019],"type":"Point"}
}