{
  "type": "Feature",
  "properties": {
    "gn:admin1_code":"1",
    "gn:asciiname":"Blok Lima Belas",
    "gn:country_code":"ID",
    "gn:dem":43,
    "gn:feature_class":"P",
    "gn:feature_code":"PPL",
    "gn:name":"Blok Lima Belas",
    "gn:population":0,
    "gn:timezone":"Asia/Jakarta",
    "iso:country":"ID",
    "name:ind_x_preferred":[
        "Blok Lima Belas"
    ],
    "name:und_x_variant":[
        "Blok-15"
    ],
    "wof:name":"Blok Lima Belas",
    "wof:placetype":"locality"
},
  "geometry": {"coordinates":[97.9867,2.3999],"type":"Point"}
}