{
  "type": "Feature",
  "properties": {
    "gn:admin1_code":"17",
    "gn:asciiname":"Karangbaru Barat",
    "gn:country_code":"ID",
    "gn:dem":97,
    "gn:feature_class":"P",
    "gn:feature_code":"PPL",
    "gn:name":"Karangbaru Barat",
    "gn:population":0,
    "gn:timezone":"Asia/Makassar",
    "iso:country":"ID",
    "name:ind_x_preferred":[
        "Karangbaru Barat"
    ],
    "wof:name":"Karangbaru Barat",
    "wof:placetype":"locality"
},
  "geometry": {"coordinates":[116.25709999999999,-8.7388],"type":"Point"}
}