{
  "type": "Feature",
  "properties": {
    "gn:admin1_code":"15.0",
    "gn:asciiname":"Talang Kasi Raja",
    "gn:country_code":"ID",
    "gn:dem":1192,
    "gn:feature_class":"P",
    "gn:feature_code":"PPL",
    "gn:name":"Talang Kasi Raja",
    "gn:population":0,
    "gn:timezone":"Asia/Jakarta",
    "iso:country":"ID",
    "name:ind_x_preferred":[
        "Talang Kasi Raja"
    ],
    "wof:name":"Talang Kasi Raja",
    "wof:placetype":"locality"
},
  "geometry": {"coordinates":[103.96587,-4.9555],"type":"Point"}
}