{
  "type": "Feature",
  "properties": {
    "gn:admin1_code":"7.0",
    "gn:asciiname":"Sirkandi",
    "gn:country_code":"ID",
    "gn:dem":74,
    "gn:feature_class":"P",
    "gn:feature_code":"PPL",
    "gn:name":"Sirkandi",
    "gn:population":0,
    "gn:timezone":"Asia/Jakarta",
    "iso:country":"ID",
    "name:ind_x_preferred":[
        "Sirkandi"
    ],
    "wof:name":"Sirkandi",
    "wof:placetype":"locality"
},
  "geometry": {"coordinates":[109.45444000000001,-7.49306],"type":"Point"}
}