{
  "type": "Feature",
  "properties": {
    "gn:admin1_code":"36.0",
    "gn:asciiname":"Banda",
    "gn:country_code":"ID",
    "gn:dem":509,
    "gn:feature_class":"P",
    "gn:feature_code":"PPLA3",
    "gn:name":"Banda",
    "gn:population":0,
    "gn:timezone":"Asia/Jayapura",
    "iso:country":"ID",
    "name:ast_x_preferred":[
        "Banda"
    ],
    "name:bel_x_preferred":[
        "\u0411\u0430\u043d\u0434\u0430"
    ],
    "name:ben_x_preferred":[
        "\u09ac\u09be\u09a8\u09cd\u09a6\u09be"
    ],
    "name:bih_x_preferred":[
        "\u092c\u093e\u0901\u0926\u093e"
    ],
    "name:bos_x_preferred":[
        "Banda"
    ],
    "name:bpy_x_preferred":[
        "\u09ac\u09be\u09a8\u09cd\u09a6\u09be"
    ],
    "name:bul_x_preferred":[
        "\u0411\u0430\u043d\u0434\u0430"
    ],
    "name:cat_x_preferred":[
        "Banda"
    ],
    "name:ceb_x_preferred":[
        "Banda"
    ],
    "name:deu_x_preferred":[
        "Banda"
    ],
    "name:fra_x_preferred":[
        "Banda"
    ],
    "name:glg_x_preferred":[
        "Banda"
    ],
    "name:heb_x_preferred":[
        "\u05d1\u05d0\u05e0\u05d3\u05d4"
    ],
    "name:hrv_x_preferred":[
        "Banda"
    ],
    "name:ind_x_preferred":[
        "Banda"
    ],
    "name:ita_x_preferred":[
        "Banda"
    ],
    "name:jpn_x_preferred":[
        "\u30d0\u30f3\u30c0"
    ],
    "name:kat_x_preferred":[
        "\u10d1\u10d0\u10dc\u10d3\u10d0"
    ],
    "name:kaz_x_preferred":[
        "\u0411\u0430\u043d\u0434\u0430"
    ],
    "name:lit_x_preferred":[
        "Banda"
    ],
    "name:new_x_preferred":[
        "\u092c\u093e\u0928\u094d\u0926\u093e"
    ],
    "name:nld_x_preferred":[
        "Banda"
    ],
    "name:pnb_x_preferred":[
        "\u0628\u0646\u062f\u06c1"
    ],
    "name:pol_x_preferred":[
        "Banda"
    ],
    "name:por_x_preferred":[
        "Banda"
    ],
    "name:rus_x_preferred":[
        "\u0411\u0430\u043d\u0434\u0430"
    ],
    "name:slk_x_preferred":[
        "Banda"
    ],
    "name:spa_x_preferred":[
        "Banda"
    ],
    "name:swe_x_preferred":[
        "Banda"
    ],
    "name:ukr_x_preferred":[
        "\u0411\u0430\u043d\u0434\u0430"
    ],
    "wof:lang_x_official":[
        "ind"
    ],
    "wof:lang_x_spoken":[
        "ind",
        "eng"
    ],
    "wof:name":"Banda",
    "wof:placetype":"locality"
},
  "geometry": {"coordinates":[140.9419,-3.1796],"type":"Point"}
}