{
  "type": "Feature",
  "properties": {
    "gn:admin1_code":"36.0",
    "gn:asciiname":"Banda",
    "gn:country_code":"ID",
    "gn:dem":509,
    "gn:feature_class":"P",
    "gn:feature_code":"PPLA3",
    "gn:name":"Banda",
    "gn:population":0,
    "gn:timezone":"Asia/Jayapura",
    "iso:country":"ID",
    "name:ind_x_preferred":[
        "Banda"
    ],
    "wof:name":"Banda",
    "wof:placetype":"locality"
},
  "geometry": {"coordinates":[140.9419,-3.1796],"type":"Point"}
}