{
  "type": "Feature",
  "properties": {
    "gn:country":"ID",
    "gn:fcode":"PPLA3",
    "gn:pop":0,
    "iso:country":"ID",
    "name:ind_x_preferred":[
        "Sedan"
    ],
    "name:unk_x_variant":[
        "Saden"
    ],
    "qs:name":"Sedan",
    "qs:photos_9r":0,
    "qs:photos_sr":0,
    "qs:pop_sr":"3",
    "wd:wordcount":144,
    "wof:name":"Sedan",
    "wof:placetype":"locality",
    "wof:population":0
},
  "geometry": {"coordinates":[111.5744,-6.7668],"type":"Point"}
}