{
  "type": "Feature",
  "properties": {
    "gn:admin1_code":"30",
    "gn:asciiname":"Sukarapih",
    "gn:country_code":"ID",
    "gn:dem":766,
    "gn:feature_class":"P",
    "gn:feature_code":"PPL",
    "gn:name":"Sukarapih",
    "gn:population":0,
    "gn:timezone":"Asia/Jakarta",
    "iso:country":"ID",
    "name:ind_x_preferred":[
        "Sukarapih"
    ],
    "wof:name":"Sukarapih",
    "wof:placetype":"locality"
},
  "geometry": {"coordinates":[107.50388999999998,-6.71556],"type":"Point"}
}