{
  "type": "Feature",
  "properties": {
    "gn:admin1_code":"18.0",
    "gn:asciiname":"Deere",
    "gn:country_code":"ID",
    "gn:dem":357,
    "gn:feature_class":"P",
    "gn:feature_code":"PPL",
    "gn:name":"Deere",
    "gn:population":0,
    "gn:timezone":"Asia/Makassar",
    "iso:country":"ID",
    "name:ind_x_preferred":[
        "Deere"
    ],
    "wof:name":"Deere",
    "wof:placetype":"locality"
},
  "geometry": {"coordinates":[124.56829999999999,-8.1645],"type":"Point"}
}