{
  "type": "Feature",
  "properties": {
    "gn:admin1_code":"38.0",
    "gn:asciiname":"Duri",
    "gn:country_code":"ID",
    "gn:dem":830,
    "gn:feature_class":"P",
    "gn:feature_code":"PPL",
    "gn:name":"Duri",
    "gn:population":0,
    "gn:timezone":"Asia/Makassar",
    "iso:country":"ID",
    "name:ind_x_preferred":[
        "Duri"
    ],
    "wof:name":"Duri",
    "wof:placetype":"locality"
},
  "geometry": {"coordinates":[119.4701,-3.3196],"type":"Point"}
}