{
  "type": "Feature",
  "properties": {
    "gn:admin1_code":"17",
    "gn:asciiname":"Talun",
    "gn:country_code":"ID",
    "gn:dem":332,
    "gn:feature_class":"P",
    "gn:feature_code":"PPL",
    "gn:name":"Talun",
    "gn:population":0,
    "gn:timezone":"Asia/Makassar",
    "iso:country":"ID",
    "name:ceb_x_preferred":[
        "T\u0101l\u016bn"
    ],
    "name:fas_x_preferred":[
        "\u0637\u0627\u0644\u0648\u0646"
    ],
    "name:ind_x_preferred":[
        "Talun"
    ],
    "name:swe_x_preferred":[
        "T\u0101l\u016bn"
    ],
    "wof:name":"Talun",
    "wof:placetype":"locality"
},
  "geometry": {"coordinates":[116.4246,-8.6321],"type":"Point"}
}