{
  "type": "Feature",
  "properties": {
    "gn:admin1_code":"35",
    "gn:asciiname":"Tuatunu",
    "gn:country_code":"ID",
    "gn:dem":17,
    "gn:feature_class":"P",
    "gn:feature_code":"PPL",
    "gn:name":"Tuatunu",
    "gn:population":0,
    "gn:timezone":"Asia/Jakarta",
    "iso:country":"ID",
    "name:ind_x_preferred":[
        "Tuatunu"
    ],
    "wof:name":"Tuatunu",
    "wof:placetype":"locality"
},
  "geometry": {"coordinates":[106.06733,-2.10294],"type":"Point"}
}