{
  "type": "Feature",
  "properties": {
    "gn:admin1_code":"17",
    "gn:asciiname":"Bangkong",
    "gn:country_code":"ID",
    "gn:dem":47,
    "gn:feature_class":"P",
    "gn:feature_code":"PPL",
    "gn:name":"Bangkong",
    "gn:population":0,
    "gn:timezone":"Asia/Makassar",
    "iso:country":"ID",
    "name:ind_x_preferred":[
        "Bangkong"
    ],
    "wof:name":"Bangkong",
    "wof:placetype":"locality"
},
  "geometry": {"coordinates":[117.3593,-8.5002],"type":"Point"}
}