{
  "type": "Feature",
  "properties": {
    "gn:admin1_code":"8.0",
    "gn:asciiname":"Pao",
    "gn:country_code":"ID",
    "gn:dem":14,
    "gn:feature_class":"P",
    "gn:feature_code":"PPL",
    "gn:name":"Pao",
    "gn:population":0,
    "gn:timezone":"Asia/Jakarta",
    "iso:country":"ID",
    "name:ceb_x_preferred":[
        "Pao"
    ],
    "name:deu_x_preferred":[
        "Pao"
    ],
    "name:ind_x_preferred":[
        "Pao"
    ],
    "name:spa_x_preferred":[
        "Pao"
    ],
    "name:swe_x_preferred":[
        "Pao"
    ],
    "wof:lang_x_official":[
        "ind"
    ],
    "wof:lang_x_spoken":[
        "ind",
        "eng"
    ],
    "wof:name":"Pao",
    "wof:placetype":"locality"
},
  "geometry": {"coordinates":[113.44515,-7.76776],"type":"Point"}
}