{
  "type": "Feature",
  "properties": {
    "gn:admin1_code":"17",
    "gn:asciiname":"Sadah",
    "gn:country_code":"ID",
    "gn:dem":318,
    "gn:feature_class":"P",
    "gn:feature_code":"PPL",
    "gn:name":"Sadah",
    "gn:population":0,
    "gn:timezone":"Asia/Makassar",
    "iso:country":"ID",
    "name:hun_x_preferred":[
        "Sadah"
    ],
    "name:ind_x_preferred":[
        "Sadah"
    ],
    "wof:lang_x_official":[
        "ind"
    ],
    "wof:lang_x_spoken":[
        "ind",
        "eng"
    ],
    "wof:name":"Sadah",
    "wof:placetype":"locality"
},
  "geometry": {"coordinates":[116.39449999999999,-8.6873],"type":"Point"}
}