{
  "type": "Feature",
  "properties": {
    "gn:admin1_code":"38",
    "gn:asciiname":"Batukede",
    "gn:country_code":"ID",
    "gn:dem":1382,
    "gn:feature_class":"P",
    "gn:feature_code":"PPL",
    "gn:name":"Batukede",
    "gn:population":0,
    "gn:timezone":"Asia/Makassar",
    "iso:country":"ID",
    "name:ind_x_preferred":[
        "Batukede"
    ],
    "wof:name":"Batukede",
    "wof:placetype":"locality"
},
  "geometry": {"coordinates":[119.7757,-3.3033],"type":"Point"}
}