{
  "type": "Feature",
  "properties": {
    "gn:admin1_code":"38",
    "gn:asciiname":"Boddong",
    "gn:country_code":"ID",
    "gn:dem":114,
    "gn:feature_class":"P",
    "gn:feature_code":"PPL",
    "gn:name":"Boddong",
    "gn:population":0,
    "gn:timezone":"Asia/Makassar",
    "iso:country":"ID",
    "name:ind_x_preferred":[
        "Boddong"
    ],
    "wof:name":"Boddong",
    "wof:placetype":"locality"
},
  "geometry": {"coordinates":[119.6641,-4.9096],"type":"Point"}
}