{
  "type": "Feature",
  "properties": {
    "gn:admin1_code":"30",
    "gn:asciiname":"Gandasoli",
    "gn:country_code":"ID",
    "gn:dem":501,
    "gn:feature_class":"P",
    "gn:feature_code":"PPL",
    "gn:name":"Gandasoli",
    "gn:population":0,
    "gn:timezone":"Asia/Jakarta",
    "iso:country":"ID",
    "name:ind_x_preferred":[
        "Gandasoli"
    ],
    "wof:name":"Gandasoli",
    "wof:placetype":"locality"
},
  "geometry": {"coordinates":[107.95083,-6.82806],"type":"Point"}
}