{
  "type": "Feature",
  "properties": {
    "gn:admin1_code":"30",
    "gn:asciiname":"Ciparay",
    "gn:country_code":"ID",
    "gn:dem":1439,
    "gn:feature_class":"P",
    "gn:feature_code":"PPL",
    "gn:name":"Ciparay",
    "gn:population":0,
    "gn:timezone":"Asia/Jakarta",
    "iso:country":"ID",
    "name:ind_x_preferred":[
        "Ciparay"
    ],
    "wof:name":"Ciparay",
    "wof:placetype":"locality"
},
  "geometry": {"coordinates":[107.3412,-7.1265],"type":"Point"}
}