{
  "type": "Feature",
  "properties": {
    "gn:admin1_code":"30.0",
    "gn:asciiname":"Bulakan",
    "gn:country_code":"ID",
    "gn:dem":54,
    "gn:feature_class":"P",
    "gn:feature_code":"PPL",
    "gn:name":"Bulakan",
    "gn:population":0,
    "gn:timezone":"Asia/Jakarta",
    "iso:country":"ID",
    "name:bcl_x_preferred":[
        "Bulacan"
    ],
    "name:ceb_x_preferred":[
        "Bulacan"
    ],
    "name:deu_x_preferred":[
        "Bulacan"
    ],
    "name:fra_x_preferred":[
        "Bulac\u00e1n"
    ],
    "name:ilo_x_preferred":[
        "Bulacan"
    ],
    "name:ind_x_preferred":[
        "Bulakan"
    ],
    "name:ind_x_variant":[
        "Bulacan"
    ],
    "name:ita_x_preferred":[
        "Bulacan"
    ],
    "name:nld_x_preferred":[
        "Bulacan"
    ],
    "name:nor_x_preferred":[
        "Bulacan"
    ],
    "name:pag_x_preferred":[
        "Bulacan"
    ],
    "name:pam_x_preferred":[
        "Bulacan"
    ],
    "name:spa_x_preferred":[
        "Bulac\u00e1n"
    ],
    "name:swe_x_preferred":[
        "Bulacan"
    ],
    "name:tgl_x_preferred":[
        "Bulakan"
    ],
    "name:war_x_preferred":[
        "Bulakan"
    ],
    "wof:lang_x_official":[
        "ind"
    ],
    "wof:lang_x_spoken":[
        "ind",
        "eng"
    ],
    "wof:name":"Bulakan",
    "wof:placetype":"locality"
},
  "geometry": {"coordinates":[111.4335,-7.4659],"type":"Point"}
}