{
  "type": "Feature",
  "properties": {
    "gn:admin1_code":"8.0",
    "gn:asciiname":"Kebonagung",
    "gn:country_code":"ID",
    "gn:dem":248,
    "gn:feature_class":"P",
    "gn:feature_code":"PPL",
    "gn:name":"Kebonagung",
    "gn:population":0,
    "gn:timezone":"Asia/Jakarta",
    "iso:country":"ID",
    "name:ind_x_preferred":[
        "Kebonagung"
    ],
    "wof:name":"Kebonagung",
    "wof:placetype":"locality"
},
  "geometry": {"coordinates":[112.29000000000001,-7.7975],"type":"Point"}
}