{
  "type": "Feature",
  "properties": {
    "gn:admin1_code":"8",
    "gn:asciiname":"Kopenbayah Kulon",
    "gn:country_code":"ID",
    "gn:dem":171,
    "gn:feature_class":"P",
    "gn:feature_code":"PPL",
    "gn:name":"Kopenbayah Kulon",
    "gn:population":0,
    "gn:timezone":"Asia/Jakarta",
    "iso:country":"ID",
    "name:ind_x_preferred":[
        "Kopenbayah Kulon"
    ],
    "wof:name":"Kopenbayah Kulon",
    "wof:placetype":"locality"
},
  "geometry": {"coordinates":[114.34139999999999,-8.1793],"type":"Point"}
}