{
  "type": "Feature",
  "properties": {
    "gn:admin1_code":"8.0",
    "gn:asciiname":"Temorleke",
    "gn:country_code":"ID",
    "gn:dem":20,
    "gn:feature_class":"P",
    "gn:feature_code":"PPL",
    "gn:name":"Temorleke",
    "gn:population":0,
    "gn:timezone":"Asia/Jakarta",
    "iso:country":"ID",
    "name:ind_x_preferred":[
        "Temorleke"
    ],
    "wof:name":"Temorleke",
    "wof:placetype":"locality"
},
  "geometry": {"coordinates":[113.8873,-6.999],"type":"Point"}
}