{
  "type": "Feature",
  "properties": {
    "gn:admin1_code":"31",
    "gn:asciiname":"Aloga",
    "gn:country_code":"ID",
    "gn:dem":409,
    "gn:feature_class":"P",
    "gn:feature_code":"PPL",
    "gn:name":"Aloga",
    "gn:population":0,
    "gn:timezone":"Asia/Makassar",
    "iso:country":"ID",
    "name:ind_x_preferred":[
        "Aloga"
    ],
    "wof:lang_x_official":[
        "ind"
    ],
    "wof:lang_x_spoken":[
        "ind",
        "eng"
    ],
    "wof:name":"Aloga",
    "wof:placetype":"locality"
},
  "geometry": {"coordinates":[124.51349999999999,0.6817],"type":"Point"}
}