{
  "type": "Feature",
  "properties": {
    "gn:country":"ID",
    "gn:fcode":"PPL",
    "gn:pop":0,
    "iso:country":"ID",
    "name:ind_x_preferred":[
        "Palengkong"
    ],
    "qs:name":"Plengkung",
    "qs:name_adm0":"Indonesia",
    "qs:name_adm1":"Jawa Timur",
    "qs:photos":65,
    "qs:photos_1k":13,
    "qs:photos_9k":1,
    "qs:photos_9r":2,
    "qs:photos_all":65,
    "qs:photos_sr":2,
    "qs:placetype":"Town",
    "qs:pop_sr":"0",
    "wof:lang_x_official":[
        "ind"
    ],
    "wof:lang_x_spoken":[
        "ind",
        "eng"
    ],
    "wof:name":"Plengkung",
    "wof:placetype":"locality",
    "wof:population":0
},
  "geometry": {"coordinates":[114.5813,-8.1514],"type":"Point"}
}