{
  "type": "Feature",
  "properties": {
    "gn:admin1_code":"14.0",
    "gn:asciiname":"Pakotlaburan",
    "gn:country_code":"ID",
    "gn:dem":41,
    "gn:feature_class":"P",
    "gn:feature_code":"PPL",
    "gn:name":"Pakotlaburan",
    "gn:population":0,
    "gn:timezone":"Asia/Makassar",
    "iso:country":"ID",
    "name:ind_x_preferred":[
        "Pakotlaburan"
    ],
    "wof:name":"Pakotlaburan",
    "wof:placetype":"locality"
},
  "geometry": {"coordinates":[116.35347,-1.98579],"type":"Point"}
}