{
  "type": "Feature",
  "properties": {
    "gn:admin1_code":"7.0",
    "gn:asciiname":"Banyuasin",
    "gn:country_code":"ID",
    "gn:dem":163,
    "gn:feature_class":"P",
    "gn:feature_code":"PPL",
    "gn:name":"Banyuasin",
    "gn:population":0,
    "gn:timezone":"Asia/Jakarta",
    "iso:country":"ID",
    "name:ind_x_preferred":[
        "Banyuasin"
    ],
    "name:und_x_variant":[
        "Banjuasin",
        "Banjoeasin"
    ],
    "wof:name":"Banyuasin",
    "wof:placetype":"locality"
},
  "geometry": {"coordinates":[111.4205,-7.0857],"type":"Point"}
}