{
  "type": "Feature",
  "properties": {
    "gn:admin1_code":"30",
    "gn:asciiname":"Girisuka",
    "gn:country_code":"ID",
    "gn:dem":370,
    "gn:feature_class":"P",
    "gn:feature_code":"PPL",
    "gn:name":"Girisuka",
    "gn:population":0,
    "gn:timezone":"Asia/Jakarta",
    "iso:country":"ID",
    "name:ind_x_preferred":[
        "Girisuka"
    ],
    "wof:name":"Girisuka",
    "wof:placetype":"locality"
},
  "geometry": {"coordinates":[107.20193999999999,-6.89472],"type":"Point"}
}