{
  "type": "Feature",
  "properties": {
    "gn:admin1_code":"7.0",
    "gn:asciiname":"Bawang",
    "gn:country_code":"ID",
    "gn:dem":629,
    "gn:feature_class":"P",
    "gn:feature_code":"PPL",
    "gn:name":"Bawang",
    "gn:population":0,
    "gn:timezone":"Asia/Jakarta",
    "iso:country":"ID",
    "wof:name":"Bawang",
    "wof:placetype":"locality"
},
  "geometry": {"coordinates":[110.23583000000001,-7.26944],"type":"Point"}
}