{
  "type": "Feature",
  "properties": {
    "gn:admin1_code":"0.0",
    "gn:asciiname":"Tokunyi",
    "gn:cc2":"ID",
    "gn:country_code":"ID",
    "gn:dem":1710,
    "gn:feature_class":"P",
    "gn:feature_code":"PPL",
    "gn:name":"Tokunyi",
    "gn:population":0,
    "gn:timezone":"Asia/Makassar",
    "iso:country":"ID",
    "name:und_x_variant":[
        "Tokoenji",
        "Tokunji",
        "Tokunyi"
    ],
    "wof:lang_x_official":[
        "ind"
    ],
    "wof:lang_x_spoken":[
        "ind",
        "eng"
    ],
    "wof:name":"Tokunyi",
    "wof:placetype":"locality"
},
  "geometry": {"coordinates":[120.33333,-2.25],"type":"Point"}
}