{
  "type": "Feature",
  "properties": {
    "gn:admin1_code":"13.0",
    "gn:asciiname":"Kruing",
    "gn:country_code":"ID",
    "gn:dem":19,
    "gn:feature_class":"P",
    "gn:feature_code":"PPL",
    "gn:name":"Kruing",
    "gn:population":0,
    "gn:timezone":"Asia/Pontianak",
    "iso:country":"ID",
    "name:und_x_variant":[
        "Kroeing",
        "Kruing"
    ],
    "wof:name":"Kruing",
    "wof:placetype":"locality"
},
  "geometry": {"coordinates":[113.3758,-2.3961],"type":"Point"}
}