{
  "type": "Feature",
  "properties": {
    "gn:admin1_code":"2.0",
    "gn:asciiname":"Jepun",
    "gn:country_code":"ID",
    "gn:dem":23,
    "gn:feature_class":"P",
    "gn:feature_code":"PPL",
    "gn:name":"Jepun",
    "gn:population":0,
    "gn:timezone":"Asia/Makassar",
    "iso:country":"ID",
    "name:ind_x_preferred":[
        "Jepun"
    ],
    "wof:name":"Jepun",
    "wof:placetype":"locality"
},
  "geometry": {"coordinates":[115.57429999999999,-8.6836],"type":"Point"}
}