{
  "type": "Feature",
  "properties": {
    "gn:admin1_code":"7",
    "gn:asciiname":"Plosokerep",
    "gn:country_code":"ID",
    "gn:dem":85,
    "gn:feature_class":"P",
    "gn:feature_code":"PPL",
    "gn:name":"Plosokerep",
    "gn:population":0,
    "gn:timezone":"Asia/Jakarta",
    "iso:country":"ID",
    "name:ind_x_preferred":[
        "Plosokerep"
    ],
    "wof:name":"Plosokerep",
    "wof:placetype":"locality"
},
  "geometry": {"coordinates":[111.04111,-7.39472],"type":"Point"}
}