{
  "type": "Feature",
  "properties": {
    "gn:admin1_code":"30.0",
    "gn:asciiname":"Karangpaningal Kaler",
    "gn:country_code":"ID",
    "gn:dem":19,
    "gn:feature_class":"P",
    "gn:feature_code":"PPL",
    "gn:name":"Karangpaningal Kaler",
    "gn:population":0,
    "gn:timezone":"Asia/Jakarta",
    "iso:country":"ID",
    "name:ind_x_preferred":[
        "Karangpaningal Kaler"
    ],
    "wof:name":"Karangpaningal Kaler",
    "wof:placetype":"locality"
},
  "geometry": {"coordinates":[108.66549999999999,-7.4324],"type":"Point"}
}