{
  "type": "Feature",
  "properties": {
    "gn:admin1_code":"38",
    "gn:asciiname":"Mananti Satu",
    "gn:country_code":"ID",
    "gn:dem":163,
    "gn:feature_class":"P",
    "gn:feature_code":"PPL",
    "gn:name":"Mananti Satu",
    "gn:population":0,
    "gn:timezone":"Asia/Makassar",
    "iso:country":"ID",
    "name:ind_x_preferred":[
        "Mananti Satu"
    ],
    "name:und_x_variant":[
        "Mananti 1"
    ],
    "wof:lang_x_official":[
        "ind"
    ],
    "wof:lang_x_spoken":[
        "ind",
        "eng"
    ],
    "wof:name":"Mananti Satu",
    "wof:placetype":"locality"
},
  "geometry": {"coordinates":[120.2591,-5.2619],"type":"Point"}
}