{
  "type": "Feature",
  "properties": {
    "gn:admin1_code":"18.0",
    "gn:asciiname":"Trikora",
    "gn:country_code":"ID",
    "gn:dem":1204,
    "gn:feature_class":"P",
    "gn:feature_code":"PPLA4",
    "gn:name":"Trikora",
    "gn:population":0,
    "gn:timezone":"Asia/Makassar",
    "iso:country":"ID",
    "name:ind_x_preferred":[
        "Trikora"
    ],
    "wof:lang_x_official":[
        "ind"
    ],
    "wof:lang_x_spoken":[
        "ind",
        "eng"
    ],
    "wof:name":"Trikora",
    "wof:placetype":"locality"
},
  "geometry": {"coordinates":[120.97150000000001,-8.7865],"type":"Point"}
}