{
  "type": "Feature",
  "properties": {
    "gn:admin1_code":"33.0",
    "gn:asciiname":"Bukitpasau",
    "gn:country_code":"ID",
    "gn:dem":7,
    "gn:feature_class":"P",
    "gn:feature_code":"PPL",
    "gn:name":"Bukitpasau",
    "gn:population":0,
    "gn:timezone":"Asia/Jakarta",
    "iso:country":"ID",
    "name:ind_x_preferred":[
        "Bukitpasau"
    ],
    "wof:name":"Bukitpasau",
    "wof:placetype":"locality"
},
  "geometry": {"coordinates":[105.8325,-6.2116],"type":"Point"}
}