{
  "type": "Feature",
  "properties": {
    "gn:admin1_code":"30",
    "gn:asciiname":"Ciliulumpang",
    "gn:country_code":"ID",
    "gn:dem":288,
    "gn:feature_class":"P",
    "gn:feature_code":"PPL",
    "gn:name":"Ciliulumpang",
    "gn:population":0,
    "gn:timezone":"Asia/Jakarta",
    "iso:country":"ID",
    "name:ind_x_preferred":[
        "Ciliulumpang"
    ],
    "wof:name":"Ciliulumpang",
    "wof:placetype":"locality"
},
  "geometry": {"coordinates":[107.32167,-6.69167],"type":"Point"}
}