{
  "type": "Feature",
  "properties": {
    "gn:admin1_code":"18.0",
    "gn:asciiname":"Palapang",
    "gn:country_code":"ID",
    "gn:dem":71,
    "gn:feature_class":"P",
    "gn:feature_code":"PPL",
    "gn:name":"Palapang",
    "gn:population":0,
    "gn:timezone":"Asia/Makassar",
    "iso:country":"ID",
    "name:ind_x_preferred":[
        "Palapang"
    ],
    "wof:name":"Palapang",
    "wof:placetype":"locality"
},
  "geometry": {"coordinates":[120.4974,-10.1558],"type":"Point"}
}