{
  "type": "Feature",
  "properties": {
    "gn:admin1_code":"07",
    "gn:asciiname":"Cemoro",
    "gn:country_code":"ID",
    "gn:dem":681,
    "gn:feature_class":"P",
    "gn:feature_code":"PPL",
    "gn:name":"Cemoro",
    "gn:population":0,
    "gn:timezone":"Asia/Jakarta",
    "iso:country":"ID",
    "name:und_x_variant":[
        "Tjemoro",
        "Cemoro"
    ],
    "wof:name":"Cemoro",
    "wof:placetype":"locality"
},
  "geometry": {"coordinates":[110.31722000000001,-7.46833],"type":"Point"}
}