{
  "type": "Feature",
  "properties": {
    "gn:admin1_code":"7",
    "gn:asciiname":"Sedran",
    "gn:country_code":"ID",
    "gn:dem":37,
    "gn:feature_class":"P",
    "gn:feature_code":"PPL",
    "gn:name":"Sedran",
    "gn:population":0,
    "gn:timezone":"Asia/Jakarta",
    "iso:country":"ID",
    "name:ind_x_preferred":[
        "Sedran"
    ],
    "wof:name":"Sedran",
    "wof:placetype":"locality"
},
  "geometry": {"coordinates":[109.6422,-7.0049],"type":"Point"}
}