{
  "type": "Feature",
  "properties": {
    "gn:admin1_code":"7",
    "gn:asciiname":"Karangtempel",
    "gn:country_code":"ID",
    "gn:dem":24,
    "gn:feature_class":"P",
    "gn:feature_code":"PPL",
    "gn:name":"Karangtempel",
    "gn:population":0,
    "gn:timezone":"Asia/Jakarta",
    "iso:country":"ID",
    "name:ind_x_preferred":[
        "Karangtempel"
    ],
    "wof:name":"Karangtempel",
    "wof:placetype":"locality"
},
  "geometry": {"coordinates":[110.58750000000001,-7.0737],"type":"Point"}
}