{
  "type": "Feature",
  "properties": {
    "gn:admin1_code":"10.0",
    "gn:asciiname":"Gupakan",
    "gn:country_code":"ID",
    "gn:dem":271,
    "gn:feature_class":"P",
    "gn:feature_code":"PPL",
    "gn:name":"Gupakan",
    "gn:population":0,
    "gn:timezone":"Asia/Jakarta",
    "iso:country":"ID",
    "name:ind_x_preferred":[
        "Gupakan"
    ],
    "wof:name":"Gupakan",
    "wof:placetype":"locality"
},
  "geometry": {"coordinates":[110.68667000000001,-8.12222],"type":"Point"}
}