{
  "type": "Feature",
  "properties": {
    "gn:admin1_code":"1",
    "gn:asciiname":"Meudang Ghon",
    "gn:country_code":"ID",
    "gn:dem":8,
    "gn:feature_class":"P",
    "gn:feature_code":"PPL",
    "gn:name":"Meudang Ghon",
    "gn:population":0,
    "gn:timezone":"Asia/Jakarta",
    "iso:country":"ID",
    "name:ind_x_preferred":[
        "Meudang Ghon"
    ],
    "wof:name":"Meudang Ghon",
    "wof:placetype":"locality"
},
  "geometry": {"coordinates":[95.3814,5.0166],"type":"Point"}
}