{
  "type": "Feature",
  "properties": {
    "gn:admin1_code":"30",
    "gn:asciiname":"Lembang",
    "gn:country_code":"ID",
    "gn:dem":867,
    "gn:feature_class":"P",
    "gn:feature_code":"PPL",
    "gn:name":"Lembang",
    "gn:population":0,
    "gn:timezone":"Asia/Jakarta",
    "iso:country":"ID",
    "name:ceb_x_preferred":[
        "Lembang"
    ],
    "name:fra_x_preferred":[
        "Lembang"
    ],
    "name:ind_x_preferred":[
        "Lembang"
    ],
    "name:mlg_x_preferred":[
        "Lembang"
    ],
    "name:msa_x_preferred":[
        "Lembang"
    ],
    "name:nld_x_preferred":[
        "Lembang"
    ],
    "wof:lang_x_official":[
        "ind"
    ],
    "wof:lang_x_spoken":[
        "ind",
        "eng"
    ],
    "wof:name":"Lembang",
    "wof:placetype":"locality"
},
  "geometry": {"coordinates":[107.83194,-6.91806],"type":"Point"}
}