{
  "type": "Feature",
  "properties": {
    "gn:admin1_code":"30",
    "gn:asciiname":"Cijawura Girang",
    "gn:country_code":"ID",
    "gn:dem":677,
    "gn:feature_class":"P",
    "gn:feature_code":"PPL",
    "gn:name":"Cijawura Girang",
    "gn:population":0,
    "gn:timezone":"Asia/Jakarta",
    "iso:country":"ID",
    "name:ind_x_preferred":[
        "Cijawura Girang"
    ],
    "name:und_x_variant":[
        "Tjidjawura 1",
        "Cijawura Satu"
    ],
    "wof:lang_x_official":[
        "ind"
    ],
    "wof:lang_x_spoken":[
        "ind",
        "eng"
    ],
    "wof:name":"Cijawura Girang",
    "wof:placetype":"locality"
},
  "geometry": {"coordinates":[107.64944,-6.94667],"type":"Point"}
}