{
  "type": "Feature",
  "properties": {
    "gn:admin1_code":"8",
    "gn:asciiname":"Kedaleman Wetan",
    "gn:country_code":"ID",
    "gn:dem":158,
    "gn:feature_class":"P",
    "gn:feature_code":"PPL",
    "gn:name":"Kedaleman Wetan",
    "gn:population":0,
    "gn:timezone":"Asia/Jakarta",
    "iso:country":"ID",
    "name:ind_x_preferred":[
        "Kedaleman Wetan"
    ],
    "wof:name":"Kedaleman Wetan",
    "wof:placetype":"locality"
},
  "geometry": {"coordinates":[114.3272,-8.2099],"type":"Point"}
}