{
  "type": "Feature",
  "properties": {
    "gn:admin1_code":"5.0",
    "gn:asciiname":"Singkawang",
    "gn:country_code":"ID",
    "gn:dem":31,
    "gn:feature_class":"P",
    "gn:feature_code":"PPL",
    "gn:name":"Singkawang",
    "gn:population":0,
    "gn:timezone":"Asia/Jakarta",
    "iso:country":"ID",
    "name:ind_x_preferred":[
        "Singkawang"
    ],
    "wof:name":"Singkawang",
    "wof:placetype":"locality"
},
  "geometry": {"coordinates":[103.25597,-1.7814],"type":"Point"}
}