{
  "type": "Feature",
  "properties": {
    "gn:admin1_code":"5.0",
    "gn:asciiname":"Singkawang",
    "gn:country_code":"ID",
    "gn:dem":31,
    "gn:feature_class":"P",
    "gn:feature_code":"PPL",
    "gn:name":"Singkawang",
    "gn:population":0,
    "gn:timezone":"Asia/Jakarta",
    "iso:country":"ID",
    "name:ara_x_preferred":[
        "\u0633\u064a\u0646\u063a\u0643\u0648\u0627\u0646\u063a"
    ],
    "name:bjn_x_preferred":[
        "Kuta Singkawang"
    ],
    "name:bug_x_preferred":[
        "Singkawang"
    ],
    "name:ceb_x_preferred":[
        "Singkawang"
    ],
    "name:fas_x_preferred":[
        "\u0633\u06cc\u0646\u06af\u200c\u06a9\u0648\u0627\u0646\u06af"
    ],
    "name:fra_x_preferred":[
        "Singkawang"
    ],
    "name:heb_x_preferred":[
        "\u05e1\u05d9\u05e0\u05d2\u05e7\u05d5\u05d5\u05d0\u05e0\u05d2"
    ],
    "name:hun_x_preferred":[
        "Singkawang"
    ],
    "name:ind_x_preferred":[
        "Singkawang"
    ],
    "name:ind_x_variant":[
        "Kota Singkawang"
    ],
    "name:ita_x_preferred":[
        "Singkawang"
    ],
    "name:jav_x_preferred":[
        "Kutha Singkawang"
    ],
    "name:jpn_x_preferred":[
        "\u30b7\u30f3\u30ab\u30ef\u30f3"
    ],
    "name:kor_x_preferred":[
        "\uc2f1\uce74\uc655"
    ],
    "name:lit_x_preferred":[
        "Sinkavangas"
    ],
    "name:mlg_x_preferred":[
        "Kota Singkawang"
    ],
    "name:msa_x_preferred":[
        "Kota Singkawang"
    ],
    "name:nor_x_preferred":[
        "Singkawang"
    ],
    "name:pol_x_preferred":[
        "Singkawang"
    ],
    "name:rus_x_preferred":[
        "\u0421\u0438\u043d\u043a\u0430\u0432\u0430\u043d\u0433"
    ],
    "name:sun_x_preferred":[
        "Kota Singkawang"
    ],
    "name:swe_x_preferred":[
        "Singkawang"
    ],
    "name:tha_x_preferred":[
        "\u0e0b\u0e34\u0e07\u0e01\u0e32\u0e27\u0e31\u0e07"
    ],
    "name:tur_x_preferred":[
        "Singkawang"
    ],
    "name:urd_x_preferred":[
        "\u0633\u0646\u06af\u06a9\u0627\u0648\u0627\u0646\u06af"
    ],
    "name:vie_x_preferred":[
        "Singkawang"
    ],
    "name:zho_x_preferred":[
        "\u5c71\u53e3\u6d0b"
    ],
    "wof:lang_x_official":[
        "ind"
    ],
    "wof:lang_x_spoken":[
        "ind",
        "eng"
    ],
    "wof:name":"Singkawang",
    "wof:placetype":"locality"
},
  "geometry": {"coordinates":[103.25597,-1.7814],"type":"Point"}
}