{
  "type": "Feature",
  "properties": {
    "gn:admin1_code":"30",
    "gn:asciiname":"Cihejo",
    "gn:cc2":"ID",
    "gn:country_code":"ID",
    "gn:dem":1306,
    "gn:feature_class":"P",
    "gn:feature_code":"PPL",
    "gn:name":"Cihejo",
    "gn:population":0,
    "gn:timezone":"Asia/Jakarta",
    "iso:country":"ID",
    "name:und_x_variant":[
        "Tjihedro",
        "Cihedro",
        "Cihejo"
    ],
    "wof:lang_x_official":[
        "ind"
    ],
    "wof:lang_x_spoken":[
        "ind",
        "eng"
    ],
    "wof:name":"Cihejo",
    "wof:placetype":"locality"
},
  "geometry": {"coordinates":[107.68306,-7.15611],"type":"Point"}
}