{
  "type": "Feature",
  "properties": {
    "gn:admin1_code":"33.0",
    "gn:asciiname":"Bojongdatar",
    "gn:country_code":"ID",
    "gn:dem":107,
    "gn:feature_class":"P",
    "gn:feature_code":"PPL",
    "gn:name":"Bojongdatar",
    "gn:population":0,
    "gn:timezone":"Asia/Jakarta",
    "iso:country":"ID",
    "name:ind_x_preferred":[
        "Bojongdatar"
    ],
    "wof:name":"Bojongdatar",
    "wof:placetype":"locality"
},
  "geometry": {"coordinates":[106.02160000000001,-6.4466],"type":"Point"}
}