{
  "type": "Feature",
  "properties": {
    "gn:country":"ID",
    "gn:fcode":"ADM4",
    "gn:pop":0,
    "iso:country":"ID",
    "name:ind_x_preferred":[
        "Kelurahan Maospati"
    ],
    "name:unk_x_variant":[
        "Maospati"
    ],
    "qs:name":"Kelurahan Maospati",
    "qs:photos_9r":0,
    "qs:photos_sr":0,
    "qs:pop_sr":"0",
    "wof:name":"Kelurahan Maospati",
    "wof:placetype":"localadmin",
    "wof:population":0
},
  "geometry": {"coordinates":[111.43470000000001,-7.5953],"type":"Point"}
}