{
  "type": "Feature",
  "properties": {
    "gn:admin1_code":"29.0",
    "gn:asciiname":"Soanmaitik",
    "gn:country_code":"ID",
    "gn:dem":36,
    "gn:feature_class":"P",
    "gn:feature_code":"PPL",
    "gn:name":"Soanmaitik",
    "gn:population":0,
    "gn:timezone":"Asia/Jayapura",
    "iso:country":"ID",
    "wof:name":"Soanmaitik",
    "wof:placetype":"locality"
},
  "geometry": {"coordinates":[127.83620999999999,1.42441],"type":"Point"}
}