{
  "type": "Feature",
  "properties": {
    "gn:admin1_code":"7",
    "gn:asciiname":"Mijen",
    "gn:country_code":"ID",
    "gn:dem":617,
    "gn:feature_class":"P",
    "gn:feature_code":"PPL",
    "gn:name":"Mijen",
    "gn:population":0,
    "gn:timezone":"Asia/Jakarta",
    "iso:country":"ID",
    "name:ind_x_preferred":[
        "Mijen"
    ],
    "wof:name":"Mijen",
    "wof:placetype":"locality"
},
  "geometry": {"coordinates":[109.22028,-7.13694],"type":"Point"}
}