{
  "type": "Feature",
  "properties": {
    "gn:admin1_code":"18.0",
    "gn:asciiname":"Fauthanin",
    "gn:country_code":"ID",
    "gn:dem":397,
    "gn:feature_class":"P",
    "gn:feature_code":"PPLA4",
    "gn:name":"Fauthanin",
    "gn:population":0,
    "gn:timezone":"Asia/Makassar",
    "iso:country":"ID",
    "name:ind_x_preferred":[
        "Fauthanin"
    ],
    "wof:name":"Fauthanin",
    "wof:placetype":"locality"
},
  "geometry": {"coordinates":[124.43940000000001,-10.0218],"type":"Point"}
}