{
  "type": "Feature",
  "properties": {
    "gn:admin1_code":"33.0",
    "gn:asciiname":"Sukawaris",
    "gn:country_code":"ID",
    "gn:dem":403,
    "gn:feature_class":"P",
    "gn:feature_code":"PPL",
    "gn:name":"Sukawaris",
    "gn:population":0,
    "gn:timezone":"Asia/Jakarta",
    "iso:country":"ID",
    "name:ind_x_preferred":[
        "Sukawaris"
    ],
    "wof:name":"Sukawaris",
    "wof:placetype":"locality"
},
  "geometry": {"coordinates":[106.2432,-6.7908],"type":"Point"}
}