{
  "type": "Feature",
  "properties": {
    "gn:admin1_code":"7",
    "gn:asciiname":"Boni",
    "gn:country_code":"ID",
    "gn:dem":46,
    "gn:feature_class":"P",
    "gn:feature_code":"PPL",
    "gn:name":"Boni",
    "gn:population":0,
    "gn:timezone":"Asia/Jakarta",
    "iso:country":"ID",
    "name:ind_x_preferred":[
        "Boni"
    ],
    "wof:name":"Boni",
    "wof:placetype":"locality"
},
  "geometry": {"coordinates":[109.91139,-7.66333],"type":"Point"}
}