{
  "type": "Feature",
  "properties": {
    "gn:admin1_code":"7",
    "gn:asciiname":"Boni",
    "gn:country_code":"ID",
    "gn:dem":46,
    "gn:feature_class":"P",
    "gn:feature_code":"PPL",
    "gn:name":"Boni",
    "gn:population":0,
    "gn:timezone":"Asia/Jakarta",
    "iso:country":"ID",
    "name:ceb_x_preferred":[
        "Boni"
    ],
    "name:deu_x_preferred":[
        "Boni"
    ],
    "name:fas_x_preferred":[
        "\u0628\u0648\u0646\u06cc"
    ],
    "name:fra_x_preferred":[
        "Boni"
    ],
    "name:ind_x_preferred":[
        "Boni"
    ],
    "name:ita_x_preferred":[
        "Boni"
    ],
    "name:nld_x_preferred":[
        "Boni"
    ],
    "name:pol_x_preferred":[
        "Boni"
    ],
    "name:por_x_preferred":[
        "Boni"
    ],
    "name:rus_x_preferred":[
        "\u0411\u043e\u043d\u0438"
    ],
    "name:srp_x_preferred":[
        "\u0411\u043e\u043d\u0438"
    ],
    "name:swe_x_preferred":[
        "Boni"
    ],
    "wof:lang_x_official":[
        "ind"
    ],
    "wof:lang_x_spoken":[
        "ind",
        "eng"
    ],
    "wof:name":"Boni",
    "wof:placetype":"locality"
},
  "geometry": {"coordinates":[109.91139,-7.66333],"type":"Point"}
}