{
  "type": "Feature",
  "properties": {
    "gn:admin1_code":"30",
    "gn:asciiname":"Cideungkluk",
    "gn:cc2":"ID",
    "gn:country_code":"ID",
    "gn:dem":967,
    "gn:feature_class":"P",
    "gn:feature_code":"PPL",
    "gn:name":"Cideungkluk",
    "gn:population":0,
    "gn:timezone":"Asia/Jakarta",
    "iso:country":"ID",
    "name:und_x_variant":[
        "Tjideungkleung",
        "Cideungkleung",
        "Cideungkluk"
    ],
    "wof:lang_x_official":[
        "ind"
    ],
    "wof:lang_x_spoken":[
        "ind",
        "eng"
    ],
    "wof:name":"Cideungkluk",
    "wof:placetype":"locality"
},
  "geometry": {"coordinates":[107.57361,-7.1075],"type":"Point"}
}