{
  "type": "Feature",
  "properties": {
    "gn:admin1_code":"33.0",
    "gn:asciiname":"Legon",
    "gn:country_code":"ID",
    "gn:dem":153,
    "gn:feature_class":"P",
    "gn:feature_code":"PPL",
    "gn:name":"Legon",
    "gn:population":0,
    "gn:timezone":"Asia/Jakarta",
    "iso:country":"ID",
    "name:deu_x_preferred":[
        "Legon"
    ],
    "name:ind_x_preferred":[
        "Legon"
    ],
    "name:spa_x_preferred":[
        "Legon"
    ],
    "wof:name":"Legon",
    "wof:placetype":"locality"
},
  "geometry": {"coordinates":[106.0449,-6.3724],"type":"Point"}
}