{
  "type": "Feature",
  "properties": {
    "gn:country":"ID",
    "gn:fcode":"ADM4",
    "gn:pop":0,
    "iso:country":"ID",
    "name:ind_x_preferred":[
        "Desa Paiton"
    ],
    "name:unk_x_variant":[
        "Paiton"
    ],
    "qs:name":"Desa Paiton",
    "qs:photos_9r":0,
    "qs:photos_sr":0,
    "qs:pop_sr":"0",
    "wof:lang_x_official":[
        "ind"
    ],
    "wof:lang_x_spoken":[
        "ind",
        "eng"
    ],
    "wof:name":"Desa Paiton",
    "wof:placetype":"localadmin",
    "wof:population":0
},
  "geometry": {"coordinates":[113.51649999999999,-7.7255],"type":"Point"}
}