{
  "type": "Feature",
  "properties": {
    "gn:admin1_code":"33.0",
    "gn:asciiname":"Sengir",
    "gn:country_code":"ID",
    "gn:dem":127,
    "gn:feature_class":"P",
    "gn:feature_code":"PPL",
    "gn:name":"Sengir",
    "gn:population":0,
    "gn:timezone":"Asia/Jakarta",
    "iso:country":"ID",
    "name:ind_x_preferred":[
        "Sengir"
    ],
    "wof:name":"Sengir",
    "wof:placetype":"locality"
},
  "geometry": {"coordinates":[106.1242,-6.2166],"type":"Point"}
}