{
  "type": "Feature",
  "properties": {
    "gn:admin1_code":"8.0",
    "gn:asciiname":"Wangun",
    "gn:country_code":"ID",
    "gn:dem":11,
    "gn:feature_class":"P",
    "gn:feature_code":"PPLA4",
    "gn:name":"Wangun",
    "gn:population":0,
    "gn:timezone":"Asia/Jakarta",
    "iso:country":"ID",
    "name:ind_x_preferred":[
        "Wangun"
    ],
    "name:und_x_variant":[
        "Wangoen"
    ],
    "wof:name":"Wangun",
    "wof:placetype":"locality"
},
  "geometry": {"coordinates":[112.16630000000001,-6.929],"type":"Point"}
}