{
  "type": "Feature",
  "properties": {
    "gn:admin1_code":"8",
    "gn:asciiname":"Mojo Kidul",
    "gn:country_code":"ID",
    "gn:dem":9,
    "gn:feature_class":"P",
    "gn:feature_code":"PPL",
    "gn:name":"Mojo Kidul",
    "gn:population":0,
    "gn:timezone":"Asia/Jakarta",
    "iso:country":"ID",
    "name:ind_x_preferred":[
        "Mojo Kidul"
    ],
    "wof:name":"Mojo Kidul",
    "wof:placetype":"locality"
},
  "geometry": {"coordinates":[112.6611,-7.4354],"type":"Point"}
}