{
  "type": "Feature",
  "properties": {
    "gn:admin1_code":"8",
    "gn:asciiname":"Pelle",
    "gn:country_code":"ID",
    "gn:dem":27,
    "gn:feature_class":"P",
    "gn:feature_code":"PPL",
    "gn:name":"Pelle",
    "gn:population":0,
    "gn:timezone":"Asia/Jakarta",
    "iso:country":"ID",
    "name:deu_x_preferred":[
        "Pelle"
    ],
    "name:fra_x_preferred":[
        "Pelle"
    ],
    "name:ind_x_preferred":[
        "Pelle"
    ],
    "name:ita_x_preferred":[
        "Pelle"
    ],
    "name:nld_x_preferred":[
        "Pelle"
    ],
    "name:swe_x_preferred":[
        "Pelles"
    ],
    "wof:lang_x_official":[
        "ind"
    ],
    "wof:lang_x_spoken":[
        "ind",
        "eng"
    ],
    "wof:name":"Pelle",
    "wof:placetype":"locality"
},
  "geometry": {"coordinates":[113.2051,-7.2023],"type":"Point"}
}