{
  "type": "Feature",
  "properties": {
    "gn:admin1_code":"8.0",
    "gn:asciiname":"Miagan",
    "gn:country_code":"ID",
    "gn:dem":40,
    "gn:feature_class":"P",
    "gn:feature_code":"PPL",
    "gn:name":"Miagan",
    "gn:population":0,
    "gn:timezone":"Asia/Jakarta",
    "iso:country":"ID",
    "name:ind_x_preferred":[
        "Miagan"
    ],
    "wof:name":"Miagan",
    "wof:placetype":"locality"
},
  "geometry": {"coordinates":[112.3584,-7.5686],"type":"Point"}
}