{
  "type": "Feature",
  "properties": {
    "gn:admin1_code":"15.0",
    "gn:asciiname":"Tanjungpinang",
    "gn:country_code":"ID",
    "gn:dem":61,
    "gn:feature_class":"P",
    "gn:feature_code":"PPL",
    "gn:name":"Tanjungpinang",
    "gn:population":0,
    "gn:timezone":"Asia/Jakarta",
    "iso:country":"ID",
    "name:hun_x_preferred":[
        "Tanjungpinang"
    ],
    "name:ind_x_preferred":[
        "Tanjungpinang"
    ],
    "name:por_x_preferred":[
        "Tanjung Pinang"
    ],
    "wof:lang_x_official":[
        "ind"
    ],
    "wof:lang_x_spoken":[
        "ind",
        "eng"
    ],
    "wof:name":"Tanjungpinang",
    "wof:placetype":"locality"
},
  "geometry": {"coordinates":[105.21286000000001,-5.63612],"type":"Point"}
}