{
  "type": "Feature",
  "properties": {
    "gn:admin1_code":"1",
    "gn:asciiname":"Teubingpanah",
    "gn:country_code":"ID",
    "gn:dem":21,
    "gn:feature_class":"P",
    "gn:feature_code":"PPL",
    "gn:name":"Teubingpanah",
    "gn:population":0,
    "gn:timezone":"Asia/Jakarta",
    "iso:country":"ID",
    "name:ind_x_preferred":[
        "Teubingpanah"
    ],
    "wof:name":"Teubingpanah",
    "wof:placetype":"locality"
},
  "geometry": {"coordinates":[96.22839999999999,4.2817],"type":"Point"}
}