{
  "type": "Feature",
  "properties": {
    "gn:admin1_code":"12.0",
    "gn:asciiname":"Batakan",
    "gn:country_code":"ID",
    "gn:dem":58,
    "gn:feature_class":"P",
    "gn:feature_code":"PPL",
    "gn:name":"Batakan",
    "gn:population":0,
    "gn:timezone":"Asia/Makassar",
    "iso:country":"ID",
    "name:und_x_variant":[
        "Babakan",
        "Batakan"
    ],
    "wof:name":"Batakan",
    "wof:placetype":"locality"
},
  "geometry": {"coordinates":[114.6262,-4.0803],"type":"Point"}
}