{
  "type": "Feature",
  "properties": {
    "gn:admin1_code":"7.0",
    "gn:asciiname":"Karangnongko",
    "gn:country_code":"ID",
    "gn:dem":689,
    "gn:feature_class":"P",
    "gn:feature_code":"PPL",
    "gn:name":"Karangnongko",
    "gn:population":0,
    "gn:timezone":"Asia/Jakarta",
    "iso:country":"ID",
    "name:ind_x_preferred":[
        "Karangnongko"
    ],
    "name:jav_x_preferred":[
        "Karangnangka"
    ],
    "name:nld_x_preferred":[
        "Karangnongko"
    ],
    "wof:name":"Karangnongko",
    "wof:placetype":"locality"
},
  "geometry": {"coordinates":[110.54639,-7.45139],"type":"Point"}
}