{
  "type": "Feature",
  "properties": {
    "gn:admin1_code":"14",
    "gn:asciiname":"Selobatu",
    "gn:country_code":"ID",
    "gn:dem":4,
    "gn:feature_class":"P",
    "gn:feature_code":"PPL",
    "gn:name":"Selobatu",
    "gn:population":0,
    "gn:timezone":"Asia/Makassar",
    "iso:country":"ID",
    "name:ind_x_preferred":[
        "Selobatu"
    ],
    "wof:name":"Selobatu",
    "wof:placetype":"locality"
},
  "geometry": {"coordinates":[116.4115,-1.8878],"type":"Point"}
}