{
  "type": "Feature",
  "properties": {
    "gn:admin1_code":"41.0",
    "gn:asciiname":"Paopao",
    "gn:country_code":"ID",
    "gn:dem":61,
    "gn:feature_class":"P",
    "gn:feature_code":"PPL",
    "gn:name":"Paopao",
    "gn:population":0,
    "gn:timezone":"Asia/Makassar",
    "iso:country":"ID",
    "name:ind_x_preferred":[
        "Paopao"
    ],
    "wof:name":"Paopao",
    "wof:placetype":"locality"
},
  "geometry": {"coordinates":[118.98779999999999,-3.3969],"type":"Point"}
}