{
  "type": "Feature",
  "properties": {
    "gn:admin1_code":"33.0",
    "gn:asciiname":"Bojongkoneng",
    "gn:country_code":"ID",
    "gn:dem":40,
    "gn:feature_class":"P",
    "gn:feature_code":"PPL",
    "gn:name":"Bojongkoneng",
    "gn:population":0,
    "gn:timezone":"Asia/Jakarta",
    "iso:country":"ID",
    "name:ind_x_preferred":[
        "Bojongkoneng"
    ],
    "name:und_x_variant":[
        "Bodjongkoneng",
        "Bojongkoneng"
    ],
    "wof:name":"Bojongkoneng",
    "wof:placetype":"locality"
},
  "geometry": {"coordinates":[105.84529999999999,-6.6106],"type":"Point"}
}