{
  "type": "Feature",
  "properties": {
    "gn:admin1_code":"10",
    "gn:asciiname":"Nglaos",
    "gn:country_code":"ID",
    "gn:dem":203,
    "gn:feature_class":"P",
    "gn:feature_code":"PPL",
    "gn:name":"Nglaos",
    "gn:population":0,
    "gn:timezone":"Asia/Jakarta",
    "iso:country":"ID",
    "name:ind_x_preferred":[
        "Nglaos"
    ],
    "wof:name":"Nglaos",
    "wof:placetype":"locality"
},
  "geometry": {"coordinates":[110.44693999999998,-8.07528],"type":"Point"}
}