{
  "type": "Feature",
  "properties": {
    "gn:admin1_code":"26",
    "gn:asciiname":"Siolip",
    "gn:country_code":"ID",
    "gn:dem":156,
    "gn:feature_class":"P",
    "gn:feature_code":"PPL",
    "gn:name":"Siolip",
    "gn:population":0,
    "gn:timezone":"Asia/Jakarta",
    "iso:country":"ID",
    "name:ind_x_preferred":[
        "Siolip"
    ],
    "wof:name":"Siolip",
    "wof:placetype":"locality"
},
  "geometry": {"coordinates":[99.71117,1.07139],"type":"Point"}
}