{
  "type": "Feature",
  "properties": {
    "gn:admin1_code":"7",
    "gn:asciiname":"Bongso Lor",
    "gn:country_code":"ID",
    "gn:dem":901,
    "gn:feature_class":"P",
    "gn:feature_code":"PPL",
    "gn:name":"Bongso Lor",
    "gn:population":0,
    "gn:timezone":"Asia/Jakarta",
    "iso:country":"ID",
    "name:ind_x_preferred":[
        "Bongso Lor"
    ],
    "wof:lang_x_official":[
        "ind"
    ],
    "wof:lang_x_spoken":[
        "ind",
        "eng"
    ],
    "wof:name":"Bongso Lor",
    "wof:placetype":"locality"
},
  "geometry": {"coordinates":[110.03306000000001,-7.2125],"type":"Point"}
}