{
  "type": "Feature",
  "properties": {
    "gn:country":"ID",
    "gn:fcode":"PPL",
    "gn:pop":0,
    "iso:country":"ID",
    "name:ind_x_preferred":[
        "Tanjungsari"
    ],
    "qs:name":"Tanjung Sari",
    "qs:name_adm0":"Indonesia",
    "qs:name_adm1":"Jawa Barat",
    "qs:photos_9r":0,
    "qs:photos_sr":0,
    "qs:placetype":"Town",
    "qs:pop_sr":"0",
    "wof:name":"Tanjung Sari",
    "wof:placetype":"locality",
    "wof:population":0
},
  "geometry": {"coordinates":[106.91333,-6.91278],"type":"Point"}
}