{
  "type": "Feature",
  "properties": {
    "gn:admin1_code":"11",
    "gn:asciiname":"Belang",
    "gn:country_code":"ID",
    "gn:dem":6,
    "gn:feature_class":"P",
    "gn:feature_code":"PPL",
    "gn:name":"Belang",
    "gn:population":0,
    "gn:timezone":"Asia/Pontianak",
    "iso:country":"ID",
    "name:ind_x_preferred":[
        "Belang"
    ],
    "wof:name":"Belang",
    "wof:placetype":"locality"
},
  "geometry": {"coordinates":[110.06310999999999,-0.05354],"type":"Point"}
}