{
  "type": "Feature",
  "properties": {
    "gn:admin1_code":"0.0",
    "gn:asciiname":"Mangani",
    "gn:cc2":"ID",
    "gn:country_code":"ID",
    "gn:dem":649,
    "gn:feature_class":"P",
    "gn:feature_code":"PPL",
    "gn:name":"Mangani",
    "gn:population":0,
    "gn:timezone":"Asia/Jakarta",
    "iso:country":"ID",
    "name:fra_x_preferred":[
        "Langue grand-singe"
    ],
    "name:und_x_variant":[
        "Manggani",
        "Mangani"
    ],
    "wof:lang_x_official":[
        "ind"
    ],
    "wof:lang_x_spoken":[
        "ind",
        "eng"
    ],
    "wof:name":"Mangani",
    "wof:placetype":"locality"
},
  "geometry": {"coordinates":[100.25,-0.01667],"type":"Point"}
}