{
  "type": "Feature",
  "properties": {
    "gn:country":"ID",
    "gn:fcode":"PPL",
    "gn:pop":0,
    "iso:country":"ID",
    "name:ind_x_preferred":[
        "Kiaracondong"
    ],
    "name:unk_x_variant":[
        "Kiaratjondong"
    ],
    "qs:name":"Kiaracondong",
    "qs:name_adm0":"Indonesia",
    "qs:name_adm1":"Jawa Barat",
    "qs:photos_9k":1,
    "qs:photos_9r":4,
    "qs:photos_all":190,
    "qs:photos_sr":0,
    "qs:placetype":"Town",
    "qs:pop_sr":"0",
    "wof:lang_x_official":[
        "ind"
    ],
    "wof:lang_x_spoken":[
        "ind",
        "eng"
    ],
    "wof:name":"Kiaracondong",
    "wof:placetype":"locality",
    "wof:population":0
},
  "geometry": {"coordinates":[107.64528,-6.92889],"type":"Point"}
}