{
  "type": "Feature",
  "properties": {
    "gn:admin1_code":"7",
    "gn:asciiname":"Lempayan",
    "gn:country_code":"ID",
    "gn:dem":800,
    "gn:feature_class":"P",
    "gn:feature_code":"PPL",
    "gn:name":"Lempayan",
    "gn:population":0,
    "gn:timezone":"Asia/Jakarta",
    "iso:country":"ID",
    "name:ind_x_preferred":[
        "Lempayan"
    ],
    "wof:name":"Lempayan",
    "wof:placetype":"locality"
},
  "geometry": {"coordinates":[109.41694,-7.19806],"type":"Point"}
}