{
  "type": "Feature",
  "properties": {
    "gn:admin1_code":"30.0",
    "gn:asciiname":"Datarjeuruk",
    "gn:country_code":"ID",
    "gn:dem":711,
    "gn:feature_class":"P",
    "gn:feature_code":"PPL",
    "gn:name":"Datarjeuruk",
    "gn:population":0,
    "gn:timezone":"Asia/Jakarta",
    "iso:country":"ID",
    "name:ind_x_preferred":[
        "Datarjeuruk"
    ],
    "wof:name":"Datarjeuruk",
    "wof:placetype":"locality"
},
  "geometry": {"coordinates":[108.05880000000001,-7.4894],"type":"Point"}
}