{
  "type": "Feature",
  "properties": {
    "gn:admin1_code":"1",
    "gn:asciiname":"Rikitbur",
    "gn:country_code":"ID",
    "gn:dem":188,
    "gn:feature_class":"P",
    "gn:feature_code":"PPL",
    "gn:name":"Rikitbur",
    "gn:population":0,
    "gn:timezone":"Asia/Jakarta",
    "iso:country":"ID",
    "name:ind_x_preferred":[
        "Rikitbur"
    ],
    "wof:name":"Rikitbur",
    "wof:placetype":"locality"
},
  "geometry": {"coordinates":[97.8835,3.4307],"type":"Point"}
}