{
  "type": "Feature",
  "properties": {
    "gn:admin1_code":"5.0",
    "gn:asciiname":"Renahmangus",
    "gn:country_code":"ID",
    "gn:dem":195,
    "gn:feature_class":"P",
    "gn:feature_code":"PPL",
    "gn:name":"Renahmangus",
    "gn:population":0,
    "gn:timezone":"Asia/Jakarta",
    "iso:country":"ID",
    "name:ind_x_preferred":[
        "Renahmangus"
    ],
    "wof:name":"Renahmangus",
    "wof:placetype":"locality"
},
  "geometry": {"coordinates":[102.21514999999999,-2.25176],"type":"Point"}
}