{
  "type": "Feature",
  "properties": {
    "gn:admin1_code":"21",
    "gn:asciiname":"Dimpalon",
    "gn:country_code":"ID",
    "gn:dem":12,
    "gn:feature_class":"P",
    "gn:feature_code":"PPL",
    "gn:name":"Dimpalon",
    "gn:population":0,
    "gn:timezone":"Asia/Makassar",
    "iso:country":"ID",
    "name:ind_x_preferred":[
        "Dimpalon"
    ],
    "wof:name":"Dimpalon",
    "wof:placetype":"locality"
},
  "geometry": {"coordinates":[122.66800000000001,-1.1375],"type":"Point"}
}