{
  "type": "Feature",
  "properties": {
    "gn:admin1_code":"15.0",
    "gn:asciiname":"Labuhanratu Pasar",
    "gn:country_code":"ID",
    "gn:dem":65,
    "gn:feature_class":"P",
    "gn:feature_code":"PPL",
    "gn:name":"Labuhanratu Pasar",
    "gn:population":0,
    "gn:timezone":"Asia/Jakarta",
    "iso:country":"ID",
    "name:ind_x_preferred":[
        "Labuhanratu Pasar"
    ],
    "wof:name":"Labuhanratu Pasar",
    "wof:placetype":"locality"
},
  "geometry": {"coordinates":[104.77584,-4.73532],"type":"Point"}
}