{
  "type": "Feature",
  "properties": {
    "gn:admin1_code":"30.0",
    "gn:asciiname":"Ciwangi",
    "gn:country_code":"ID",
    "gn:dem":1125,
    "gn:feature_class":"P",
    "gn:feature_code":"PPL",
    "gn:name":"Ciwangi",
    "gn:population":0,
    "gn:timezone":"Asia/Jakarta",
    "iso:country":"ID",
    "name:ind_x_preferred":[
        "Ciwangi"
    ],
    "name:und_x_variant":[
        "Tjiwangi",
        "Ciwangi"
    ],
    "wof:lang_x_official":[
        "ind"
    ],
    "wof:lang_x_spoken":[
        "ind",
        "eng"
    ],
    "wof:name":"Ciwangi",
    "wof:placetype":"locality"
},
  "geometry": {"coordinates":[107.0398,-7.0661],"type":"Point"}
}