{
  "type": "Feature",
  "properties": {
    "gn:admin1_code":"7.0",
    "gn:asciiname":"Palur Kulon",
    "gn:country_code":"ID",
    "gn:dem":99,
    "gn:feature_class":"P",
    "gn:feature_code":"PPL",
    "gn:name":"Palur Kulon",
    "gn:population":0,
    "gn:timezone":"Asia/Jakarta",
    "iso:country":"ID",
    "wof:name":"Palur Kulon",
    "wof:placetype":"locality"
},
  "geometry": {"coordinates":[110.87139000000001,-7.56972],"type":"Point"}
}