{
  "type": "Feature",
  "properties": {
    "gn:admin1_code":"2.0",
    "gn:asciiname":"Kampungislamkepaon",
    "gn:country_code":"ID",
    "gn:dem":11,
    "gn:feature_class":"P",
    "gn:feature_code":"PPL",
    "gn:name":"Kampungislamkepaon",
    "gn:population":0,
    "gn:timezone":"Asia/Makassar",
    "iso:country":"ID",
    "name:ind_x_preferred":[
        "Kampungislamkepaon"
    ],
    "wof:name":"Kampungislamkepaon",
    "wof:placetype":"locality"
},
  "geometry": {"coordinates":[115.18989999999999,-8.7004],"type":"Point"}
}