{
  "type": "Feature",
  "properties": {
    "gn:admin1_code":"15",
    "gn:asciiname":"Tridadi",
    "gn:country_code":"ID",
    "gn:dem":58,
    "gn:feature_class":"P",
    "gn:feature_code":"PPL",
    "gn:name":"Tridadi",
    "gn:population":0,
    "gn:timezone":"Asia/Jakarta",
    "iso:country":"ID",
    "name:ind_x_preferred":[
        "Tridadi"
    ],
    "wof:name":"Tridadi",
    "wof:placetype":"locality"
},
  "geometry": {"coordinates":[105.15222,-5.14194],"type":"Point"}
}