{
  "type": "Feature",
  "properties": {
    "gn:admin1_code":"36.0",
    "gn:asciiname":"Wainap",
    "gn:country_code":"ID",
    "gn:dem":1,
    "gn:feature_class":"P",
    "gn:feature_code":"PPL",
    "gn:name":"Wainap",
    "gn:population":0,
    "gn:timezone":"Asia/Jayapura",
    "iso:country":"ID",
    "name:und_x_variant":[
        "Wainapi"
    ],
    "wof:name":"Wainap",
    "wof:placetype":"locality"
},
  "geometry": {"coordinates":[135.46530000000001,-1.6359],"type":"Point"}
}