{
  "type": "Feature",
  "properties": {
    "gn:admin1_code":"24.0",
    "gn:asciiname":"Kotagunung",
    "gn:country_code":"ID",
    "gn:dem":19,
    "gn:feature_class":"P",
    "gn:feature_code":"PPL",
    "gn:name":"Kotagunung",
    "gn:population":0,
    "gn:timezone":"Asia/Jakarta",
    "iso:country":"ID",
    "name:ind_x_preferred":[
        "Kotagunung"
    ],
    "wof:name":"Kotagunung",
    "wof:placetype":"locality"
},
  "geometry": {"coordinates":[100.6579,-1.4352],"type":"Point"}
}