{
  "type": "Feature",
  "properties": {
    "gn:admin1_code":"7.0",
    "gn:asciiname":"Kebogelo",
    "gn:country_code":"ID",
    "gn:dem":64,
    "gn:feature_class":"P",
    "gn:feature_code":"PPL",
    "gn:name":"Kebogelo",
    "gn:population":0,
    "gn:timezone":"Asia/Jakarta",
    "iso:country":"ID",
    "name:ind_x_preferred":[
        "Kebogelo"
    ],
    "wof:name":"Kebogelo",
    "wof:placetype":"locality"
},
  "geometry": {"coordinates":[109.33806,-7.40722],"type":"Point"}
}