{
  "type": "Feature",
  "properties": {
    "gn:admin1_code":"07",
    "gn:asciiname":"Ginung",
    "gn:country_code":"ID",
    "gn:dem":119,
    "gn:feature_class":"P",
    "gn:feature_code":"PPL",
    "gn:name":"Ginung",
    "gn:population":0,
    "gn:timezone":"Asia/Jakarta",
    "iso:country":"ID",
    "wof:name":"Ginung",
    "wof:placetype":"locality"
},
  "geometry": {"coordinates":[110.75749999999999,-7.54639],"type":"Point"}
}