{
  "type": "Feature",
  "properties": {
    "gn:admin1_code":"8.0",
    "gn:asciiname":"Soo",
    "gn:country_code":"ID",
    "gn:dem":290,
    "gn:feature_class":"P",
    "gn:feature_code":"PPL",
    "gn:name":"Soo",
    "gn:population":0,
    "gn:timezone":"Asia/Jakarta",
    "iso:country":"ID",
    "name:ceb_x_preferred":[
        "Soo"
    ],
    "name:deu_x_preferred":[
        "Soo"
    ],
    "name:est_x_preferred":[
        "Soo"
    ],
    "name:fra_x_preferred":[
        "Soo"
    ],
    "name:ind_x_preferred":[
        "Soo"
    ],
    "name:nld_x_preferred":[
        "Soo"
    ],
    "name:pol_x_preferred":[
        "Soo"
    ],
    "name:swe_x_preferred":[
        "Soo"
    ],
    "wof:name":"Soo",
    "wof:placetype":"locality"
},
  "geometry": {"coordinates":[111.687,-8.2149],"type":"Point"}
}