{
  "type": "Feature",
  "properties": {
    "gn:admin1_code":"8.0",
    "gn:asciiname":"Kliteh",
    "gn:country_code":"ID",
    "gn:dem":64,
    "gn:feature_class":"P",
    "gn:feature_code":"PPL",
    "gn:name":"Kliteh",
    "gn:population":0,
    "gn:timezone":"Asia/Jakarta",
    "iso:country":"ID",
    "name:ind_x_preferred":[
        "Kliteh"
    ],
    "wof:name":"Kliteh",
    "wof:placetype":"locality"
},
  "geometry": {"coordinates":[111.71720000000001,-7.2551],"type":"Point"}
}