{
  "type": "Feature",
  "properties": {
    "gn:admin1_code":"7",
    "gn:asciiname":"Lahar",
    "gn:country_code":"ID",
    "gn:dem":204,
    "gn:feature_class":"P",
    "gn:feature_code":"PPLA4",
    "gn:name":"Lahar",
    "gn:population":0,
    "gn:timezone":"Asia/Jakarta",
    "iso:country":"ID",
    "name:ara_x_preferred":[
        "\u0644\u0627\u0647\u0627\u0631"
    ],
    "name:aze_x_preferred":[
        "Laxar"
    ],
    "name:bel_x_preferred":[
        "\u041b\u0430\u0445\u0430\u0440"
    ],
    "name:bul_x_preferred":[
        "\u041b\u0430\u0445\u0430\u0440"
    ],
    "name:cat_x_preferred":[
        "Lahar"
    ],
    "name:ces_x_preferred":[
        "Lahar"
    ],
    "name:dan_x_preferred":[
        "Lahar"
    ],
    "name:deu_x_preferred":[
        "Lahar"
    ],
    "name:ell_x_preferred":[
        "\u039b\u03b1\u03c7\u03ac\u03c1"
    ],
    "name:epo_x_preferred":[
        "Laharo"
    ],
    "name:est_x_preferred":[
        "Lahaar"
    ],
    "name:eus_x_preferred":[
        "Lahar"
    ],
    "name:fas_x_preferred":[
        "\u06af\u0644\u200c\u0631\u0648\u062f"
    ],
    "name:fin_x_preferred":[
        "Lahari"
    ],
    "name:fra_x_preferred":[
        "Lahar"
    ],
    "name:glg_x_preferred":[
        "Lahar"
    ],
    "name:heb_x_preferred":[
        "\u05dc\u05d4\u05d0\u05e8"
    ],
    "name:hrv_x_preferred":[
        "Lahar"
    ],
    "name:hun_x_preferred":[
        "Iszap\u00e1r"
    ],
    "name:ind_x_preferred":[
        "Lahar"
    ],
    "name:ita_x_preferred":[
        "Lahar"
    ],
    "name:jav_x_preferred":[
        "Wlahar"
    ],
    "name:jpn_x_preferred":[
        "\u30e9\u30cf\u30fc\u30eb"
    ],
    "name:kaz_x_preferred":[
        "\u041b\u0430\u0445\u0430\u0440"
    ],
    "name:kor_x_preferred":[
        "\ud654\uc0b0\uc774\ub958"
    ],
    "name:lit_x_preferred":[
        "Laharas"
    ],
    "name:mkd_x_preferred":[
        "\u041b\u0430\u0445\u0430\u0440"
    ],
    "name:nld_x_preferred":[
        "Lahar"
    ],
    "name:nor_x_preferred":[
        "Gj\u00f8rmestr\u00f8m"
    ],
    "name:oci_x_preferred":[
        "Lahar"
    ],
    "name:pol_x_preferred":[
        "Lahar"
    ],
    "name:por_x_preferred":[
        "Lahar"
    ],
    "name:ron_x_preferred":[
        "Lahar"
    ],
    "name:rus_x_preferred":[
        "\u041b\u0430\u0445\u0430\u0440"
    ],
    "name:slk_x_preferred":[
        "Lah\u00e1r"
    ],
    "name:slv_x_preferred":[
        "Lahar"
    ],
    "name:spa_x_preferred":[
        "Lahar"
    ],
    "name:srp_x_preferred":[
        "\u041b\u0430\u0445\u0430\u0440"
    ],
    "name:swe_x_preferred":[
        "Lahar"
    ],
    "name:tur_x_preferred":[
        "Lahar"
    ],
    "name:ukr_x_preferred":[
        "\u041b\u0430\u0445\u0430\u0440\u0438"
    ],
    "name:wuu_x_preferred":[
        "\u706b\u5c71\u6ce5\u6d41"
    ],
    "name:zho_x_preferred":[
        "\u706b\u5c71\u6ce5\u6d41"
    ],
    "wof:name":"Lahar",
    "wof:placetype":"locality"
},
  "geometry": {"coordinates":[110.9935,-6.645],"type":"Point"}
}