{
  "type": "Feature",
  "properties": {
    "gn:admin1_code":"7",
    "gn:asciiname":"Lahar",
    "gn:country_code":"ID",
    "gn:dem":204,
    "gn:feature_class":"P",
    "gn:feature_code":"PPLA4",
    "gn:name":"Lahar",
    "gn:population":0,
    "gn:timezone":"Asia/Jakarta",
    "iso:country":"ID",
    "name:ind_x_preferred":[
        "Lahar"
    ],
    "wof:name":"Lahar",
    "wof:placetype":"locality"
},
  "geometry": {"coordinates":[110.9935,-6.645],"type":"Point"}
}