{
  "type": "Feature",
  "properties": {
    "gn:admin1_code":"30",
    "gn:asciiname":"Mang`ad",
    "gn:country_code":"ID",
    "gn:dem":52,
    "gn:feature_class":"P",
    "gn:feature_code":"PPL",
    "gn:name":"Mang\u2018ad",
    "gn:population":0,
    "gn:timezone":"Asia/Jakarta",
    "iso:country":"ID",
    "name:ind_x_preferred":[
        "Mang\u2018ad"
    ],
    "wof:name":"Mang`ad",
    "wof:placetype":"locality"
},
  "geometry": {"coordinates":[107.11360999999999,-6.42111],"type":"Point"}
}