{
  "type": "Feature",
  "properties": {
    "gn:admin1_code":"8.0",
    "gn:asciiname":"Krajan Dua",
    "gn:country_code":"ID",
    "gn:dem":38,
    "gn:feature_class":"P",
    "gn:feature_code":"PPL",
    "gn:name":"Krajan Dua",
    "gn:population":0,
    "gn:timezone":"Asia/Jakarta",
    "iso:country":"ID",
    "name:ind_x_preferred":[
        "Krajan Dua"
    ],
    "wof:name":"Krajan Dua",
    "wof:placetype":"locality"
},
  "geometry": {"coordinates":[113.23990000000001,-7.8278],"type":"Point"}
}