{
  "type": "Feature",
  "properties": {
    "gn:admin1_code":"8",
    "gn:asciiname":"Beluk",
    "gn:country_code":"ID",
    "gn:dem":282,
    "gn:feature_class":"P",
    "gn:feature_code":"PPL",
    "gn:name":"Beluk",
    "gn:population":0,
    "gn:timezone":"Asia/Jakarta",
    "iso:country":"ID",
    "name:ind_x_preferred":[
        "Beluk"
    ],
    "wof:name":"Beluk",
    "wof:placetype":"locality"
},
  "geometry": {"coordinates":[111.5676,-7.7979],"type":"Point"}
}