{
  "type": "Feature",
  "properties": {
    "gn:admin1_code":"26",
    "gn:asciiname":"Tanjungmbelang",
    "gn:country_code":"ID",
    "gn:dem":757,
    "gn:feature_class":"P",
    "gn:feature_code":"PPL",
    "gn:name":"Tanjungmbelang",
    "gn:population":0,
    "gn:timezone":"Asia/Jakarta",
    "iso:country":"ID",
    "name:ind_x_preferred":[
        "Tanjungmbelang"
    ],
    "name:und_x_variant":[
        "Tandjungbelang"
    ],
    "wof:lang_x_official":[
        "ind"
    ],
    "wof:lang_x_spoken":[
        "ind",
        "eng"
    ],
    "wof:name":"Tanjungmbelang",
    "wof:placetype":"locality"
},
  "geometry": {"coordinates":[98.3021,3.1451],"type":"Point"}
}