{
  "type": "Feature",
  "properties": {
    "gn:admin1_code":"21",
    "gn:asciiname":"Pangalasiang",
    "gn:country_code":"ID",
    "gn:dem":7,
    "gn:feature_class":"P",
    "gn:feature_code":"PPL",
    "gn:name":"Pangalasiang",
    "gn:population":0,
    "gn:timezone":"Asia/Makassar",
    "iso:country":"ID",
    "name:ind_x_preferred":[
        "Pangalasiang"
    ],
    "wof:name":"Pangalasiang",
    "wof:placetype":"locality"
},
  "geometry": {"coordinates":[119.90600000000001,0.4827],"type":"Point"}
}