{
  "type": "Feature",
  "properties": {
    "gn:admin1_code":"36.0",
    "gn:asciiname":"Kaokanao",
    "gn:country_code":"ID",
    "gn:dem":8,
    "gn:feature_class":"P",
    "gn:feature_code":"PPL",
    "gn:name":"Kaokanao",
    "gn:population":0,
    "gn:timezone":"Asia/Jayapura",
    "iso:country":"ID",
    "name:und_x_variant":[
        "Kakenau",
        "Kaukonau",
        "Kokonoa",
        "Kaokanao",
        "Kokonau",
        "Kokenau"
    ],
    "wof:name":"Kaokanao",
    "wof:placetype":"locality"
},
  "geometry": {"coordinates":[136.44144,-4.7136],"type":"Point"}
}