{
  "type": "Feature",
  "properties": {
    "gn:admin1_code":"18",
    "gn:asciiname":"Hobea",
    "gn:country_code":"ID",
    "gn:dem":512,
    "gn:feature_class":"P",
    "gn:feature_code":"PPL",
    "gn:name":"Hobea",
    "gn:population":0,
    "gn:timezone":"Asia/Makassar",
    "iso:country":"ID",
    "wof:name":"Hobea",
    "wof:placetype":"locality"
},
  "geometry": {"coordinates":[124.54000000000001,-9.46],"type":"Point"}
}