{
  "type": "Feature",
  "properties": {
    "gn:admin1_code":"07",
    "gn:asciiname":"Wonolelo",
    "gn:country_code":"ID",
    "gn:dem":1097,
    "gn:feature_class":"P",
    "gn:feature_code":"PPL",
    "gn:name":"Wonolelo",
    "gn:population":0,
    "gn:timezone":"Asia/Jakarta",
    "iso:country":"ID",
    "name:und_x_variant":[
        "Wonoleto 1",
        "Wonoleto Satu",
        "Wonolelo"
    ],
    "wof:lang_x_official":[
        "ind"
    ],
    "wof:lang_x_spoken":[
        "ind",
        "eng"
    ],
    "wof:name":"Wonolelo",
    "wof:placetype":"locality"
},
  "geometry": {"coordinates":[110.39139,-7.49611],"type":"Point"}
}