{
  "type": "Feature",
  "properties": {
    "gn:admin1_code":"17",
    "gn:asciiname":"Kedungpaok",
    "gn:country_code":"ID",
    "gn:dem":133,
    "gn:feature_class":"P",
    "gn:feature_code":"PPL",
    "gn:name":"Kedungpaok",
    "gn:population":0,
    "gn:timezone":"Asia/Makassar",
    "iso:country":"ID",
    "name:ind_x_preferred":[
        "Kedungpaok"
    ],
    "wof:name":"Kedungpaok",
    "wof:placetype":"locality"
},
  "geometry": {"coordinates":[116.3518,-8.753],"type":"Point"}
}