{
  "type": "Feature",
  "properties": {
    "gn:admin1_code":"32.0",
    "gn:asciiname":"Talanghulutekom",
    "gn:country_code":"ID",
    "gn:dem":165,
    "gn:feature_class":"P",
    "gn:feature_code":"PPL",
    "gn:name":"Talanghulutekom",
    "gn:population":0,
    "gn:timezone":"Asia/Jakarta",
    "iso:country":"ID",
    "name:ind_x_preferred":[
        "Talanghulutekom"
    ],
    "wof:name":"Talanghulutekom",
    "wof:placetype":"locality"
},
  "geometry": {"coordinates":[102.83459999999999,-3.2639],"type":"Point"}
}