{
  "type": "Feature",
  "properties": {
    "gn:admin1_code":"21.0",
    "gn:asciiname":"Lai",
    "gn:country_code":"ID",
    "gn:dem":15,
    "gn:feature_class":"P",
    "gn:feature_code":"PPL",
    "gn:name":"Lai",
    "gn:population":0,
    "gn:timezone":"Asia/Makassar",
    "iso:country":"ID",
    "name:deu_x_preferred":[
        "Lai"
    ],
    "name:est_x_preferred":[
        "Lai"
    ],
    "name:fra_x_preferred":[
        "Lai"
    ],
    "name:ind_x_preferred":[
        "Lai"
    ],
    "name:nld_x_preferred":[
        "Lai"
    ],
    "name:nor_x_preferred":[
        "Lai"
    ],
    "name:por_x_preferred":[
        "Lai"
    ],
    "name:rus_x_preferred":[
        "\u041b\u0430\u0439"
    ],
    "name:spa_x_preferred":[
        "Lai"
    ],
    "wof:lang_x_official":[
        "ind"
    ],
    "wof:lang_x_spoken":[
        "ind",
        "eng"
    ],
    "wof:name":"Lai",
    "wof:placetype":"locality"
},
  "geometry": {"coordinates":[119.8596,-0.7659],"type":"Point"}
}