{
  "type": "Feature",
  "properties": {
    "gn:admin1_code":"18.0",
    "gn:asciiname":"Homibela",
    "gn:country_code":"ID",
    "gn:dem":79,
    "gn:feature_class":"P",
    "gn:feature_code":"PPL",
    "gn:name":"Homibela",
    "gn:population":0,
    "gn:timezone":"Asia/Makassar",
    "iso:country":"ID",
    "name:ind_x_preferred":[
        "Homibela"
    ],
    "wof:name":"Homibela",
    "wof:placetype":"locality"
},
  "geometry": {"coordinates":[119.0112,-9.5559],"type":"Point"}
}