{
  "type": "Feature",
  "properties": {
    "gn:admin1_code":"31.0",
    "gn:asciiname":"Malapintu",
    "gn:country_code":"ID",
    "gn:dem":19,
    "gn:feature_class":"P",
    "gn:feature_code":"PPL",
    "gn:name":"Malapintu",
    "gn:population":0,
    "gn:timezone":"Asia/Makassar",
    "iso:country":"ID",
    "name:ind_x_preferred":[
        "Malapintu"
    ],
    "wof:name":"Malapintu",
    "wof:placetype":"locality"
},
  "geometry": {"coordinates":[125.4614,3.6164],"type":"Point"}
}