{
  "type": "Feature",
  "properties": {
    "gn:admin1_code":"30",
    "gn:asciiname":"Kemasar",
    "gn:cc2":"ID",
    "gn:country_code":"ID",
    "gn:dem":14,
    "gn:feature_class":"P",
    "gn:feature_code":"PPL",
    "gn:name":"Kemasar",
    "gn:population":0,
    "gn:timezone":"Asia/Jakarta",
    "iso:country":"ID",
    "name:und_x_variant":[
        "Kinasar",
        "Kemasar"
    ],
    "wof:name":"Kemasar",
    "wof:placetype":"locality"
},
  "geometry": {"coordinates":[106.32861,-6.11972],"type":"Point"}
}