{
  "type": "Feature",
  "properties": {
    "gn:admin1_code":"30.0",
    "gn:asciiname":"Sorok Tonggoh",
    "gn:country_code":"ID",
    "gn:dem":588,
    "gn:feature_class":"P",
    "gn:feature_code":"PPL",
    "gn:name":"Sorok Tonggoh",
    "gn:population":0,
    "gn:timezone":"Asia/Jakarta",
    "iso:country":"ID",
    "name:ind_x_preferred":[
        "Sorok Tonggoh"
    ],
    "wof:name":"Sorok Tonggoh",
    "wof:placetype":"locality"
},
  "geometry": {"coordinates":[108.2696,-7.2661],"type":"Point"}
}