{
  "type": "Feature",
  "properties": {
    "gn:admin1_code":"30",
    "gn:asciiname":"Cileuit",
    "gn:country_code":"ID",
    "gn:dem":460,
    "gn:feature_class":"P",
    "gn:feature_code":"PPL",
    "gn:name":"Cileuit",
    "gn:population":0,
    "gn:timezone":"Asia/Jakarta",
    "iso:country":"ID",
    "name:ind_x_preferred":[
        "Cileuit"
    ],
    "wof:name":"Cileuit",
    "wof:placetype":"locality"
},
  "geometry": {"coordinates":[107.78943999999998,-6.64778],"type":"Point"}
}