{
  "type": "Feature",
  "properties": {
    "gn:admin1_code":"26",
    "gn:asciiname":"Gunung Merlawan",
    "gn:country_code":"ID",
    "gn:dem":185,
    "gn:feature_class":"P",
    "gn:feature_code":"PPL",
    "gn:name":"Gunung Merlawan",
    "gn:population":0,
    "gn:timezone":"Asia/Jakarta",
    "iso:country":"ID",
    "name:ind_x_preferred":[
        "Gunung Merlawan"
    ],
    "wof:name":"Gunung Merlawan",
    "wof:placetype":"locality"
},
  "geometry": {"coordinates":[98.47239999999999,3.4349],"type":"Point"}
}