{
  "type": "Feature",
  "properties": {
    "gn:admin1_code":"15.0",
    "gn:asciiname":"Kebon Empat",
    "gn:country_code":"ID",
    "gn:dem":42,
    "gn:feature_class":"P",
    "gn:feature_code":"PPL",
    "gn:name":"Kebon Empat",
    "gn:population":0,
    "gn:timezone":"Asia/Jakarta",
    "iso:country":"ID",
    "name:ind_x_preferred":[
        "Kebon Empat"
    ],
    "name:und_x_variant":[
        "Kebon 4"
    ],
    "wof:name":"Kebon Empat",
    "wof:placetype":"locality"
},
  "geometry": {"coordinates":[104.89198,-4.86048],"type":"Point"}
}