{
  "type": "Feature",
  "properties": {
    "gn:admin1_code":"30",
    "gn:asciiname":"Pangkalan",
    "gn:country_code":"ID",
    "gn:dem":662,
    "gn:feature_class":"P",
    "gn:feature_code":"PPL",
    "gn:name":"Pangkalan",
    "gn:population":0,
    "gn:timezone":"Asia/Jakarta",
    "iso:country":"ID",
    "name:ind_x_preferred":[
        "Pangkalan"
    ],
    "wof:name":"Pangkalan",
    "wof:placetype":"locality"
},
  "geometry": {"coordinates":[107.49250000000001,-6.85917],"type":"Point"}
}