{
  "type": "Feature",
  "properties": {
    "gn:admin1_code":"08",
    "gn:asciiname":"Bumiayu Satu",
    "gn:cc2":"ID",
    "gn:country_code":"ID",
    "gn:dem":865,
    "gn:feature_class":"P",
    "gn:feature_code":"PPL",
    "gn:name":"Bumiayu Satu",
    "gn:population":0,
    "gn:timezone":"Asia/Jakarta",
    "iso:country":"ID",
    "name:und_x_variant":[
        "Bumiaju 1",
        "Bumiayu Satu"
    ],
    "wof:lang_x_official":[
        "ind"
    ],
    "wof:lang_x_spoken":[
        "ind",
        "eng"
    ],
    "wof:name":"Bumiayu Satu",
    "wof:placetype":"locality"
},
  "geometry": {"coordinates":[112.54277999999999,-7.85333],"type":"Point"}
}