{
  "type": "Feature",
  "properties": {
    "gn:admin1_code":"31.0",
    "gn:asciiname":"Sinuian",
    "gn:country_code":"ID",
    "gn:dem":713,
    "gn:feature_class":"P",
    "gn:feature_code":"PPL",
    "gn:name":"Sinuian",
    "gn:population":0,
    "gn:timezone":"Asia/Makassar",
    "iso:country":"ID",
    "name:ind_x_preferred":[
        "Sinuian"
    ],
    "wof:name":"Sinuian",
    "wof:placetype":"locality"
},
  "geometry": {"coordinates":[124.8575,1.2209],"type":"Point"}
}