{
  "type": "Feature",
  "properties": {
    "gn:admin1_code":"26",
    "gn:asciiname":"Tinggiada",
    "gn:country_code":"ID",
    "gn:dem":601,
    "gn:feature_class":"P",
    "gn:feature_code":"PPL",
    "gn:name":"Tinggiada",
    "gn:population":0,
    "gn:timezone":"Asia/Jakarta",
    "iso:country":"ID",
    "name:ind_x_preferred":[
        "Tinggiada"
    ],
    "wof:name":"Tinggiada",
    "wof:placetype":"locality"
},
  "geometry": {"coordinates":[98.3832,2.3537],"type":"Point"}
}