{
  "type": "Feature",
  "properties": {
    "gn:admin1_code":"7.0",
    "gn:asciiname":"Siketi Lebak",
    "gn:country_code":"ID",
    "gn:dem":1006,
    "gn:feature_class":"P",
    "gn:feature_code":"PPL",
    "gn:name":"Siketi Lebak",
    "gn:population":0,
    "gn:timezone":"Asia/Jakarta",
    "iso:country":"ID",
    "name:ind_x_preferred":[
        "Siketi Lebak"
    ],
    "wof:name":"Siketi Lebak",
    "wof:placetype":"locality"
},
  "geometry": {"coordinates":[109.10693999999999,-7.20472],"type":"Point"}
}