{
  "type": "Feature",
  "properties": {
    "gn:admin1_code":"5.0",
    "gn:asciiname":"Arangarang",
    "gn:country_code":"ID",
    "gn:dem":10,
    "gn:feature_class":"P",
    "gn:feature_code":"PPL",
    "gn:name":"Arangarang",
    "gn:population":0,
    "gn:timezone":"Asia/Jakarta",
    "iso:country":"ID",
    "name:ind_x_preferred":[
        "Arangarang"
    ],
    "wof:name":"Arangarang",
    "wof:placetype":"locality"
},
  "geometry": {"coordinates":[103.80343000000001,-1.61028],"type":"Point"}
}