{
  "type": "Feature",
  "properties": {
    "gn:admin1_code":"14.0",
    "gn:asciiname":"Long Muruh",
    "gn:country_code":"ID",
    "gn:dem":72,
    "gn:feature_class":"P",
    "gn:feature_code":"PPL",
    "gn:name":"Long Muruh",
    "gn:population":0,
    "gn:timezone":"Asia/Makassar",
    "iso:country":"ID",
    "name:und_x_variant":[
        "Long Moeroeh",
        "Long Muruh"
    ],
    "wof:name":"Long Muruh",
    "wof:placetype":"locality"
},
  "geometry": {"coordinates":[115.26667,0.51667],"type":"Point"}
}