{
  "type": "Feature",
  "properties": {
    "gn:admin1_code":"8.0",
    "gn:asciiname":"Weden",
    "gn:country_code":"ID",
    "gn:dem":73,
    "gn:feature_class":"P",
    "gn:feature_code":"PPLA4",
    "gn:name":"Weden",
    "gn:population":0,
    "gn:timezone":"Asia/Jakarta",
    "iso:country":"ID",
    "name:ind_x_preferred":[
        "Weden"
    ],
    "wof:name":"Weden",
    "wof:placetype":"locality"
},
  "geometry": {"coordinates":[111.6786,-6.8295],"type":"Point"}
}