{
  "type": "Feature",
  "properties": {
    "gn:admin1_code":"7.0",
    "gn:asciiname":"Danasari Wetan",
    "gn:country_code":"ID",
    "gn:dem":13,
    "gn:feature_class":"P",
    "gn:feature_code":"PPL",
    "gn:name":"Danasari Wetan",
    "gn:population":0,
    "gn:timezone":"Asia/Jakarta",
    "iso:country":"ID",
    "name:ind_x_preferred":[
        "Danasari Wetan"
    ],
    "wof:name":"Danasari Wetan",
    "wof:placetype":"locality"
},
  "geometry": {"coordinates":[109.53806000000002,-7.66833],"type":"Point"}
}