{
  "type": "Feature",
  "properties": {
    "gn:admin1_code":"18.0",
    "gn:asciiname":"Kabuni",
    "gn:country_code":"ID",
    "gn:dem":200,
    "gn:feature_class":"P",
    "gn:feature_code":"PPL",
    "gn:name":"Kabuni",
    "gn:population":0,
    "gn:timezone":"Asia/Makassar",
    "iso:country":"ID",
    "name:ind_x_preferred":[
        "Kabuni"
    ],
    "name:pol_x_preferred":[
        "Kabuni"
    ],
    "name:sqi_x_preferred":[
        "Kabunia"
    ],
    "wof:lang_x_official":[
        "ind"
    ],
    "wof:lang_x_spoken":[
        "ind",
        "eng"
    ],
    "wof:name":"Kabuni",
    "wof:placetype":"locality"
},
  "geometry": {"coordinates":[119.3139,-9.4448],"type":"Point"}
}