{
  "type": "Feature",
  "properties": {
    "gn:admin1_code":"30",
    "gn:asciiname":"Salamanik",
    "gn:country_code":"ID",
    "gn:dem":756,
    "gn:feature_class":"P",
    "gn:feature_code":"PPL",
    "gn:name":"Salamanik",
    "gn:population":0,
    "gn:timezone":"Asia/Jakarta",
    "iso:country":"ID",
    "name:ind_x_preferred":[
        "Salamanik"
    ],
    "wof:name":"Salamanik",
    "wof:placetype":"locality"
},
  "geometry": {"coordinates":[107.11944,-6.98167],"type":"Point"}
}