{
  "type": "Feature",
  "properties": {
    "gn:admin1_code":"8.0",
    "gn:asciiname":"Paridoplang",
    "gn:country_code":"ID",
    "gn:dem":385,
    "gn:feature_class":"P",
    "gn:feature_code":"PPL",
    "gn:name":"Paridoplang",
    "gn:population":0,
    "gn:timezone":"Asia/Jakarta",
    "iso:country":"ID",
    "name:ind_x_preferred":[
        "Paridoplang"
    ],
    "wof:name":"Paridoplang",
    "wof:placetype":"locality"
},
  "geometry": {"coordinates":[112.3699,-8.0644],"type":"Point"}
}