{
  "type": "Feature",
  "properties": {
    "gn:admin1_code":"8.0",
    "gn:asciiname":"Morjadah",
    "gn:country_code":"ID",
    "gn:dem":15,
    "gn:feature_class":"P",
    "gn:feature_code":"PPL",
    "gn:name":"Morjadah",
    "gn:population":0,
    "gn:timezone":"Asia/Jakarta",
    "iso:country":"ID",
    "name:ind_x_preferred":[
        "Morjadah"
    ],
    "wof:name":"Morjadah",
    "wof:placetype":"locality"
},
  "geometry": {"coordinates":[113.066,-6.8956],"type":"Point"}
}