{
  "type": "Feature",
  "properties": {
    "gn:admin1_code":"17",
    "gn:asciiname":"Jambik Satu",
    "gn:country_code":"ID",
    "gn:dem":94,
    "gn:feature_class":"P",
    "gn:feature_code":"PPL",
    "gn:name":"Jambik Satu",
    "gn:population":0,
    "gn:timezone":"Asia/Makassar",
    "iso:country":"ID",
    "name:ind_x_preferred":[
        "Jambik Satu"
    ],
    "wof:name":"Jambik Satu",
    "wof:placetype":"locality"
},
  "geometry": {"coordinates":[116.2722,-8.7978],"type":"Point"}
}