{
  "type": "Feature",
  "properties": {
    "gn:admin1_code":"18.0",
    "gn:asciiname":"Hone",
    "gn:country_code":"ID",
    "gn:dem":695,
    "gn:feature_class":"P",
    "gn:feature_code":"PPL",
    "gn:name":"Hone",
    "gn:population":0,
    "gn:timezone":"Asia/Makassar",
    "iso:country":"ID",
    "name:ceb_x_preferred":[
        "Hone"
    ],
    "name:deu_x_preferred":[
        "Hone"
    ],
    "name:fra_x_preferred":[
        "Hone"
    ],
    "name:ind_x_preferred":[
        "Hone"
    ],
    "name:nld_x_preferred":[
        "Hone"
    ],
    "name:rus_x_preferred":[
        "\u0425\u043e\u043d\u0435"
    ],
    "name:swe_x_preferred":[
        "Hone"
    ],
    "wof:lang_x_official":[
        "ind"
    ],
    "wof:lang_x_spoken":[
        "ind",
        "eng"
    ],
    "wof:name":"Hone",
    "wof:placetype":"locality"
},
  "geometry": {"coordinates":[123.1476,-8.3399],"type":"Point"}
}