{
  "type": "Feature",
  "properties": {
    "gn:admin1_code":"8.0",
    "gn:asciiname":"Karangrejo",
    "gn:country_code":"ID",
    "gn:dem":427,
    "gn:feature_class":"P",
    "gn:feature_code":"PPL",
    "gn:name":"Karangrejo",
    "gn:population":0,
    "gn:timezone":"Asia/Jakarta",
    "iso:country":"ID",
    "name:ind_x_preferred":[
        "Karangrejo"
    ],
    "wof:name":"Karangrejo",
    "wof:placetype":"locality"
},
  "geometry": {"coordinates":[113.1105,-8.075],"type":"Point"}
}