{
  "type": "Feature",
  "properties": {
    "gn:admin1_code":"7",
    "gn:asciiname":"Kaligenteng",
    "gn:country_code":"ID",
    "gn:dem":1020,
    "gn:feature_class":"P",
    "gn:feature_code":"PPL",
    "gn:name":"Kaligenteng",
    "gn:population":0,
    "gn:timezone":"Asia/Jakarta",
    "iso:country":"ID",
    "name:ind_x_preferred":[
        "Kaligenteng"
    ],
    "wof:lang_x_official":[
        "ind"
    ],
    "wof:lang_x_spoken":[
        "ind",
        "eng"
    ],
    "wof:name":"Kaligenteng",
    "wof:placetype":"locality"
},
  "geometry": {"coordinates":[109.61611000000001,-7.19611],"type":"Point"}
}