{
  "type": "Feature",
  "properties": {
    "gn:admin1_code":"30.0",
    "gn:asciiname":"Wantilan",
    "gn:country_code":"ID",
    "gn:dem":13,
    "gn:feature_class":"P",
    "gn:feature_code":"PPL",
    "gn:name":"Wantilan",
    "gn:population":0,
    "gn:timezone":"Asia/Jakarta",
    "iso:country":"ID",
    "name:fra_x_preferred":[
        "Wantilan"
    ],
    "name:ind_x_preferred":[
        "Wantilan"
    ],
    "name:por_x_preferred":[
        "Wantilan"
    ],
    "wof:name":"Wantilan",
    "wof:placetype":"locality"
},
  "geometry": {"coordinates":[108.6737,-7.4247],"type":"Point"}
}