{
  "type": "Feature",
  "properties": {
    "gn:admin1_code":"2",
    "gn:asciiname":"Banjar Sanda",
    "gn:country_code":"ID",
    "gn:dem":1304,
    "gn:feature_class":"P",
    "gn:feature_code":"PPL",
    "gn:name":"Banjar Sanda",
    "gn:population":0,
    "gn:timezone":"Asia/Makassar",
    "iso:country":"ID",
    "name:ind_x_preferred":[
        "Banjar Sanda"
    ],
    "wof:name":"Banjar Sanda",
    "wof:placetype":"locality"
},
  "geometry": {"coordinates":[115.2848,-8.2151],"type":"Point"}
}