{
  "type": "Feature",
  "properties": {
    "gn:admin1_code":"8",
    "gn:asciiname":"Punjul",
    "gn:country_code":"ID",
    "gn:dem":114,
    "gn:feature_class":"P",
    "gn:feature_code":"PPL",
    "gn:name":"Punjul",
    "gn:population":0,
    "gn:timezone":"Asia/Jakarta",
    "iso:country":"ID",
    "name:ind_x_preferred":[
        "Punjul"
    ],
    "wof:name":"Punjul",
    "wof:placetype":"locality"
},
  "geometry": {"coordinates":[111.5158,-7.7487],"type":"Point"}
}