{
  "type": "Feature",
  "properties": {
    "gn:admin1_code":"33.0",
    "gn:asciiname":"Cikalil",
    "gn:country_code":"ID",
    "gn:dem":98,
    "gn:feature_class":"P",
    "gn:feature_code":"PPL",
    "gn:name":"Cikalil",
    "gn:population":0,
    "gn:timezone":"Asia/Jakarta",
    "iso:country":"ID",
    "name:ind_x_preferred":[
        "Cikalil"
    ],
    "wof:name":"Cikalil",
    "wof:placetype":"locality"
},
  "geometry": {"coordinates":[106.08240000000001,-6.83476],"type":"Point"}
}