{
  "type": "Feature",
  "properties": {
    "gn:admin1_code":"18.0",
    "gn:asciiname":"Lemus",
    "gn:country_code":"ID",
    "gn:dem":514,
    "gn:feature_class":"P",
    "gn:feature_code":"PPL",
    "gn:name":"Lemus",
    "gn:population":0,
    "gn:timezone":"Asia/Makassar",
    "iso:country":"ID",
    "name:ind_x_preferred":[
        "Lemus"
    ],
    "wof:name":"Lemus",
    "wof:placetype":"locality"
},
  "geometry": {"coordinates":[120.5976,-8.7051],"type":"Point"}
}