{
  "type": "Feature",
  "properties": {
    "gn:admin1_code":"30",
    "gn:asciiname":"Ciwiru",
    "gn:country_code":"ID",
    "gn:dem":28,
    "gn:feature_class":"P",
    "gn:feature_code":"PPL",
    "gn:name":"Ciwiru",
    "gn:population":0,
    "gn:timezone":"Asia/Jakarta",
    "iso:country":"ID",
    "name:ind_x_preferred":[
        "Ciwiru"
    ],
    "wof:name":"Ciwiru",
    "wof:placetype":"locality"
},
  "geometry": {"coordinates":[107.38639000000001,-6.44028],"type":"Point"}
}