{
  "type": "Feature",
  "properties": {
    "gn:admin1_code":"26.0",
    "gn:asciiname":"Aek Nabara",
    "gn:country_code":"ID",
    "gn:dem":1025,
    "gn:feature_class":"P",
    "gn:feature_code":"PPL",
    "gn:name":"Aek Nabara",
    "gn:population":0,
    "gn:timezone":"Asia/Jakarta",
    "iso:country":"ID",
    "name:ind_x_preferred":[
        "Aek Nabara"
    ],
    "name:und_x_variant":[
        "Aeknabara"
    ],
    "wof:name":"Aek Nabara",
    "wof:placetype":"locality"
},
  "geometry": {"coordinates":[99.44275,1.69147],"type":"Point"}
}