{
  "type": "Feature",
  "properties": {
    "gn:admin1_code":"2",
    "gn:asciiname":"Banjar Wanasari",
    "gn:country_code":"ID",
    "gn:dem":1173,
    "gn:feature_class":"P",
    "gn:feature_code":"PPL",
    "gn:name":"Banjar Wanasari",
    "gn:population":0,
    "gn:timezone":"Asia/Makassar",
    "iso:country":"ID",
    "name:ind_x_preferred":[
        "Banjar Wanasari"
    ],
    "wof:name":"Banjar Wanasari",
    "wof:placetype":"locality"
},
  "geometry": {"coordinates":[115.3244,-8.2852],"type":"Point"}
}