{
  "type": "Feature",
  "properties": {
    "gn:admin1_code":"30.0",
    "gn:asciiname":"Bebedahan",
    "gn:country_code":"ID",
    "gn:dem":869,
    "gn:feature_class":"P",
    "gn:feature_code":"PPL",
    "gn:name":"Bebedahan",
    "gn:population":0,
    "gn:timezone":"Asia/Jakarta",
    "iso:country":"ID",
    "name:ind_x_preferred":[
        "Bebedahan"
    ],
    "wof:name":"Bebedahan",
    "wof:placetype":"locality"
},
  "geometry": {"coordinates":[107.88890000000001,-7.0068],"type":"Point"}
}