{
  "type": "Feature",
  "properties": {
    "gn:admin1_code":"17",
    "gn:asciiname":"Gersik",
    "gn:country_code":"ID",
    "gn:dem":35,
    "gn:feature_class":"P",
    "gn:feature_code":"PPL",
    "gn:name":"Gersik",
    "gn:population":0,
    "gn:timezone":"Asia/Makassar",
    "iso:country":"ID",
    "name:ind_x_preferred":[
        "Gersik"
    ],
    "wof:name":"Gersik",
    "wof:placetype":"locality"
},
  "geometry": {"coordinates":[116.13939999999999,-8.6376],"type":"Point"}
}