{
  "type": "Feature",
  "properties": {
    "gn:admin1_code":"10.0",
    "gn:asciiname":"Prigen",
    "gn:country_code":"ID",
    "gn:dem":267,
    "gn:feature_class":"P",
    "gn:feature_code":"PPL",
    "gn:name":"Prigen",
    "gn:population":0,
    "gn:timezone":"Asia/Jakarta",
    "iso:country":"ID",
    "name:ind_x_preferred":[
        "Prigen"
    ],
    "name:jav_x_preferred":[
        "Prig\u00e8n"
    ],
    "wof:name":"Prigen",
    "wof:placetype":"locality"
},
  "geometry": {"coordinates":[110.4525,-7.70667],"type":"Point"}
}