{
  "type": "Feature",
  "properties": {
    "gn:admin1_code":"30.0",
    "gn:asciiname":"Citengah Satu",
    "gn:country_code":"ID",
    "gn:dem":603,
    "gn:feature_class":"P",
    "gn:feature_code":"PPL",
    "gn:name":"Citengah Satu",
    "gn:population":0,
    "gn:timezone":"Asia/Jakarta",
    "iso:country":"ID",
    "name:ind_x_preferred":[
        "Citengah Satu"
    ],
    "wof:name":"Citengah Satu",
    "wof:placetype":"locality"
},
  "geometry": {"coordinates":[106.5633,-7.1337],"type":"Point"}
}