{
  "type": "Feature",
  "properties": {
    "gn:admin1_code":"38",
    "gn:asciiname":"Sumpangsalo",
    "gn:country_code":"ID",
    "gn:dem":35,
    "gn:feature_class":"P",
    "gn:feature_code":"PPL",
    "gn:name":"Sumpangsalo",
    "gn:population":0,
    "gn:timezone":"Asia/Makassar",
    "iso:country":"ID",
    "name:ind_x_preferred":[
        "Sumpangsalo"
    ],
    "wof:name":"Sumpangsalo",
    "wof:placetype":"locality"
},
  "geometry": {"coordinates":[119.9663,-4.3615],"type":"Point"}
}