{
  "type": "Feature",
  "properties": {
    "gn:admin1_code":"7.0",
    "gn:asciiname":"Dayu",
    "gn:country_code":"ID",
    "gn:dem":478,
    "gn:feature_class":"P",
    "gn:feature_code":"PPL",
    "gn:name":"Dayu",
    "gn:population":0,
    "gn:timezone":"Asia/Jakarta",
    "iso:country":"ID",
    "name:ceb_x_preferred":[
        "Dayu"
    ],
    "name:deu_x_preferred":[
        "Dayu"
    ],
    "name:ind_x_preferred":[
        "Dayu"
    ],
    "name:nld_x_preferred":[
        "Dayu"
    ],
    "name:swe_x_preferred":[
        "Dayu"
    ],
    "wof:name":"Dayu",
    "wof:placetype":"locality"
},
  "geometry": {"coordinates":[111.04277999999999,-8.05028],"type":"Point"}
}