{
  "type": "Feature",
  "properties": {
    "gn:admin1_code":"33.0",
    "gn:asciiname":"Simpang",
    "gn:country_code":"ID",
    "gn:dem":246,
    "gn:feature_class":"P",
    "gn:feature_code":"PPL",
    "gn:name":"Simpang",
    "gn:population":0,
    "gn:timezone":"Asia/Jakarta",
    "iso:country":"ID",
    "name:ind_x_preferred":[
        "Simpang"
    ],
    "name:mlg_x_preferred":[
        "Simpang"
    ],
    "wof:name":"Simpang",
    "wof:placetype":"locality"
},
  "geometry": {"coordinates":[106.1808,-6.5611],"type":"Point"}
}