{
  "type": "Feature",
  "properties": {
    "gn:admin1_code":"18.0",
    "gn:asciiname":"Goluwawi Dua",
    "gn:country_code":"ID",
    "gn:dem":569,
    "gn:feature_class":"P",
    "gn:feature_code":"PPL",
    "gn:name":"Goluwawi Dua",
    "gn:population":0,
    "gn:timezone":"Asia/Makassar",
    "iso:country":"ID",
    "name:ind_x_preferred":[
        "Goluwawi Dua"
    ],
    "name:und_x_variant":[
        "Goluwawi 2"
    ],
    "wof:lang_x_official":[
        "ind"
    ],
    "wof:lang_x_spoken":[
        "ind",
        "eng"
    ],
    "wof:name":"Goluwawi Dua",
    "wof:placetype":"locality"
},
  "geometry": {"coordinates":[119.255,-9.5765],"type":"Point"}
}