{
  "type": "Feature",
  "properties": {
    "gn:admin1_code":"30",
    "gn:asciiname":"Sindangasih",
    "gn:country_code":"ID",
    "gn:dem":669,
    "gn:feature_class":"P",
    "gn:feature_code":"PPL",
    "gn:name":"Sindangasih",
    "gn:population":0,
    "gn:timezone":"Asia/Jakarta",
    "iso:country":"ID",
    "wof:lang_x_official":[
        "ind"
    ],
    "wof:lang_x_spoken":[
        "ind",
        "eng"
    ],
    "wof:name":"Sindangasih",
    "wof:placetype":"locality"
},
  "geometry": {"coordinates":[107.54694000000001,-7.00778],"type":"Point"}
}