{
  "type": "Feature",
  "properties": {
    "gn:admin1_code":"30.0",
    "gn:asciiname":"Cisepan",
    "gn:country_code":"ID",
    "gn:dem":1116,
    "gn:feature_class":"P",
    "gn:feature_code":"PPL",
    "gn:name":"Cisepan",
    "gn:population":0,
    "gn:timezone":"Asia/Jakarta",
    "iso:country":"ID",
    "name:ind_x_preferred":[
        "Cisepan"
    ],
    "wof:name":"Cisepan",
    "wof:placetype":"locality"
},
  "geometry": {"coordinates":[107.229,-7.0687],"type":"Point"}
}