{
  "type": "Feature",
  "properties": {
    "gn:admin1_code":"18.0",
    "gn:asciiname":"Noekele",
    "gn:country_code":"ID",
    "gn:dem":658,
    "gn:feature_class":"P",
    "gn:feature_code":"PPL",
    "gn:name":"Noekele",
    "gn:population":0,
    "gn:timezone":"Asia/Makassar",
    "iso:country":"ID",
    "name:ind_x_preferred":[
        "Noekele"
    ],
    "wof:name":"Noekele",
    "wof:placetype":"locality"
},
  "geometry": {"coordinates":[124.255,-9.8933],"type":"Point"}
}