{
  "type": "Feature",
  "properties": {
    "gn:admin1_code":"14.0",
    "gn:asciiname":"Longbeleh",
    "gn:cc2":"ID",
    "gn:country_code":"ID",
    "gn:dem":25,
    "gn:feature_class":"P",
    "gn:feature_code":"PPL",
    "gn:name":"Longbeleh",
    "gn:population":0,
    "gn:timezone":"Asia/Makassar",
    "iso:country":"ID",
    "name:und_x_variant":[
        "Longbleh",
        "Long Bele",
        "Longbeleh"
    ],
    "wof:name":"Longbeleh",
    "wof:placetype":"locality"
},
  "geometry": {"coordinates":[116.18333,0.26667],"type":"Point"}
}