{
  "type": "Feature",
  "properties": {
    "gn:admin1_code":"30",
    "gn:asciiname":"Tangkele",
    "gn:country_code":"ID",
    "gn:dem":34,
    "gn:feature_class":"P",
    "gn:feature_code":"PPL",
    "gn:name":"Tangkele",
    "gn:population":0,
    "gn:timezone":"Asia/Jakarta",
    "iso:country":"ID",
    "name:ind_x_preferred":[
        "Tangkele"
    ],
    "name:und_x_variant":[
        "Tangkele 2",
        "Tangkele Dua"
    ],
    "wof:name":"Tangkele",
    "wof:placetype":"locality"
},
  "geometry": {"coordinates":[106.39943999999998,-6.29583],"type":"Point"}
}