{
  "type": "Feature",
  "properties": {
    "gn:admin1_code":"30",
    "gn:asciiname":"Desa Kutajaya",
    "gn:country_code":"ID",
    "gn:dem":1487,
    "gn:feature_class":"P",
    "gn:feature_code":"PPL",
    "gn:name":"Desa Kutajaya",
    "gn:population":0,
    "gn:timezone":"Asia/Jakarta",
    "iso:country":"ID",
    "name:ind_x_preferred":[
        "Desa Kutajaya"
    ],
    "name:und_x_variant":[
        "Kutajaya"
    ],
    "wof:name":"Desa Kutajaya",
    "wof:placetype":"locality"
},
  "geometry": {"coordinates":[106.74361,-6.72639],"type":"Point"}
}