{
  "type": "Feature",
  "properties": {
    "gn:admin1_code":"38",
    "gn:asciiname":"Tikkao",
    "gn:country_code":"ID",
    "gn:dem":204,
    "gn:feature_class":"P",
    "gn:feature_code":"PPL",
    "gn:name":"Tikkao",
    "gn:population":0,
    "gn:timezone":"Asia/Makassar",
    "iso:country":"ID",
    "name:ind_x_preferred":[
        "Tikkao"
    ],
    "wof:name":"Tikkao",
    "wof:placetype":"locality"
},
  "geometry": {"coordinates":[119.8892,-4.4099],"type":"Point"}
}