{
  "type": "Feature",
  "properties": {
    "gn:admin1_code":"17.0",
    "gn:asciiname":"Dasanledang",
    "gn:country_code":"ID",
    "gn:dem":35,
    "gn:feature_class":"P",
    "gn:feature_code":"PPL",
    "gn:name":"Dasanledang",
    "gn:population":0,
    "gn:timezone":"Asia/Makassar",
    "iso:country":"ID",
    "name:ind_x_preferred":[
        "Dasanledang"
    ],
    "wof:name":"Dasanledang",
    "wof:placetype":"locality"
},
  "geometry": {"coordinates":[116.4217,-8.2288],"type":"Point"}
}