{
  "type": "Feature",
  "properties": {
    "gn:admin1_code":"30.0",
    "gn:asciiname":"Cibuni",
    "gn:country_code":"ID",
    "gn:dem":1332,
    "gn:feature_class":"P",
    "gn:feature_code":"PPL",
    "gn:name":"Cibuni",
    "gn:population":0,
    "gn:timezone":"Asia/Jakarta",
    "iso:country":"ID",
    "name:ind_x_preferred":[
        "Cibuni"
    ],
    "name:und_x_variant":[
        "Tjibuni"
    ],
    "wof:name":"Cibuni",
    "wof:placetype":"locality"
},
  "geometry": {"coordinates":[107.333,-7.1898],"type":"Point"}
}