{
  "type": "Feature",
  "properties": {
    "gn:admin1_code":"7.0",
    "gn:asciiname":"Plosorejo",
    "gn:country_code":"ID",
    "gn:dem":121,
    "gn:feature_class":"P",
    "gn:feature_code":"PPL",
    "gn:name":"Plosorejo",
    "gn:population":0,
    "gn:timezone":"Asia/Jakarta",
    "iso:country":"ID",
    "name:ind_x_preferred":[
        "Plosorejo"
    ],
    "wof:name":"Plosorejo",
    "wof:placetype":"locality"
},
  "geometry": {"coordinates":[111.41719999999999,-6.9187],"type":"Point"}
}