{
  "type": "Feature",
  "properties": {
    "gn:admin1_code":"30",
    "gn:asciiname":"Palsigunung Dua",
    "gn:cc2":"ID",
    "gn:country_code":"ID",
    "gn:dem":74,
    "gn:feature_class":"P",
    "gn:feature_code":"PPL",
    "gn:name":"Palsigunung Dua",
    "gn:population":0,
    "gn:timezone":"Asia/Jakarta",
    "iso:country":"ID",
    "name:und_x_variant":[
        "Palsigunung 2",
        "Palsigunung Dua"
    ],
    "wof:name":"Palsigunung Dua",
    "wof:placetype":"locality"
},
  "geometry": {"coordinates":[106.85972,-6.36306],"type":"Point"}
}