{
  "type": "Feature",
  "properties": {
    "gn:admin1_code":"7.0",
    "gn:asciiname":"Sembir Kidul",
    "gn:country_code":"ID",
    "gn:dem":380,
    "gn:feature_class":"P",
    "gn:feature_code":"PPL",
    "gn:name":"Sembir Kidul",
    "gn:population":0,
    "gn:timezone":"Asia/Jakarta",
    "iso:country":"ID",
    "wof:name":"Sembir Kidul",
    "wof:placetype":"locality"
},
  "geometry": {"coordinates":[110.48111000000002,-7.66944],"type":"Point"}
}