{
  "type": "Feature",
  "properties": {
    "gn:admin1_code":"7",
    "gn:asciiname":"Bangsari",
    "gn:country_code":"ID",
    "gn:dem":944,
    "gn:feature_class":"P",
    "gn:feature_code":"PPL",
    "gn:name":"Bangsari",
    "gn:population":0,
    "gn:timezone":"Asia/Jakarta",
    "iso:country":"ID",
    "name:ind_x_preferred":[
        "Bangsari"
    ],
    "wof:name":"Bangsari",
    "wof:placetype":"locality"
},
  "geometry": {"coordinates":[109.98999999999999,-7.41194],"type":"Point"}
}