{
  "type": "Feature",
  "properties": {
    "gn:admin1_code":"18.0",
    "gn:asciiname":"Mude",
    "gn:country_code":"ID",
    "gn:dem":124,
    "gn:feature_class":"P",
    "gn:feature_code":"PPL",
    "gn:name":"Mude",
    "gn:population":0,
    "gn:timezone":"Asia/Makassar",
    "iso:country":"ID",
    "name:ind_x_preferred":[
        "Mude"
    ],
    "wof:name":"Mude",
    "wof:placetype":"locality"
},
  "geometry": {"coordinates":[119.3473,-9.7389],"type":"Point"}
}