{
  "type": "Feature",
  "properties": {
    "gn:admin1_code":"8",
    "gn:asciiname":"Sijar",
    "gn:country_code":"ID",
    "gn:dem":42,
    "gn:feature_class":"P",
    "gn:feature_code":"PPL",
    "gn:name":"Sijar",
    "gn:population":0,
    "gn:timezone":"Asia/Jakarta",
    "iso:country":"ID",
    "name:ind_x_preferred":[
        "Sijar"
    ],
    "wof:name":"Sijar",
    "wof:placetype":"locality"
},
  "geometry": {"coordinates":[112.81270000000001,-7.6736],"type":"Point"}
}