{
  "type": "Feature",
  "properties": {
    "gn:admin1_code":"0.0",
    "gn:asciiname":"Kayi",
    "gn:cc2":"ID",
    "gn:country_code":"ID",
    "gn:dem":672,
    "gn:feature_class":"P",
    "gn:feature_code":"PPL",
    "gn:name":"Kayi",
    "gn:population":0,
    "gn:timezone":"Asia/Jayapura",
    "iso:country":"ID",
    "name:und_x_variant":[
        "Kaji",
        "Kayi"
    ],
    "wof:name":"Kayi",
    "wof:placetype":"locality"
},
  "geometry": {"coordinates":[132.63333,-0.93333],"type":"Point"}
}