{
  "type": "Feature",
  "properties": {
    "gn:admin1_code":"08",
    "gn:asciiname":"Bunton",
    "gn:country_code":"ID",
    "gn:dem":17,
    "gn:feature_class":"P",
    "gn:feature_code":"PPL",
    "gn:name":"Bunton",
    "gn:population":0,
    "gn:timezone":"Asia/Jakarta",
    "iso:country":"ID",
    "name:ceb_x_preferred":[
        "Bunton"
    ],
    "name:deu_x_preferred":[
        "Bunton"
    ],
    "name:ind_x_preferred":[
        "Bunton"
    ],
    "name:swe_x_preferred":[
        "Bunton"
    ],
    "name:und_x_variant":[
        "Turiredjo",
        "Turirejo"
    ],
    "wof:lang_x_official":[
        "ind"
    ],
    "wof:lang_x_spoken":[
        "ind",
        "eng"
    ],
    "wof:name":"Bunton",
    "wof:placetype":"locality"
},
  "geometry": {"coordinates":[112.54085000000001,-7.3054],"type":"Point"}
}