{
  "type": "Feature",
  "properties": {
    "gn:admin1_code":"17.0",
    "gn:asciiname":"Jatibaru",
    "gn:country_code":"ID",
    "gn:dem":45,
    "gn:feature_class":"P",
    "gn:feature_code":"PPL",
    "gn:name":"Jatibaru",
    "gn:population":0,
    "gn:timezone":"Asia/Makassar",
    "iso:country":"ID",
    "name:ind_x_preferred":[
        "Jatibaru"
    ],
    "wof:name":"Jatibaru",
    "wof:placetype":"locality"
},
  "geometry": {"coordinates":[118.76690000000001,-8.4336],"type":"Point"}
}