{
  "type": "Feature",
  "properties": {
    "gn:admin1_code":"7",
    "gn:asciiname":"Golok",
    "gn:country_code":"ID",
    "gn:dem":32,
    "gn:feature_class":"P",
    "gn:feature_code":"PPL",
    "gn:name":"Golok",
    "gn:population":0,
    "gn:timezone":"Asia/Jakarta",
    "iso:country":"ID",
    "name:deu_x_preferred":[
        "Golok"
    ],
    "name:ind_x_preferred":[
        "Golok"
    ],
    "name:ita_x_preferred":[
        "Golok"
    ],
    "name:jav_x_preferred":[
        "Golok"
    ],
    "name:lit_x_preferred":[
        "Golokas"
    ],
    "name:spa_x_preferred":[
        "Golok"
    ],
    "name:sun_x_preferred":[
        "Bedog"
    ],
    "wof:lang_x_official":[
        "ind"
    ],
    "wof:lang_x_spoken":[
        "ind",
        "eng"
    ],
    "wof:name":"Golok",
    "wof:placetype":"locality"
},
  "geometry": {"coordinates":[109.95806,-7.73833],"type":"Point"}
}