{
  "type": "Feature",
  "properties": {
    "gn:admin1_code":"30",
    "gn:asciiname":"Legokbitung",
    "gn:country_code":"ID",
    "gn:dem":852,
    "gn:feature_class":"P",
    "gn:feature_code":"PPL",
    "gn:name":"Legokbitung",
    "gn:population":0,
    "gn:timezone":"Asia/Jakarta",
    "iso:country":"ID",
    "name:ind_x_preferred":[
        "Legokbitung"
    ],
    "wof:name":"Legokbitung",
    "wof:placetype":"locality"
},
  "geometry": {"coordinates":[107.84889,-6.96],"type":"Point"}
}