{
  "type": "Feature",
  "properties": {
    "gn:admin1_code":"7.0",
    "gn:asciiname":"Karangbendo",
    "gn:country_code":"ID",
    "gn:dem":801,
    "gn:feature_class":"P",
    "gn:feature_code":"PPL",
    "gn:name":"Karangbendo",
    "gn:population":0,
    "gn:timezone":"Asia/Jakarta",
    "iso:country":"ID",
    "wof:name":"Karangbendo",
    "wof:placetype":"locality"
},
  "geometry": {"coordinates":[110.08638999999999,-7.26556],"type":"Point"}
}