{
  "type": "Feature",
  "properties": {
    "gn:admin1_code":"7",
    "gn:asciiname":"Dukuhjambe",
    "gn:country_code":"ID",
    "gn:dem":11,
    "gn:feature_class":"P",
    "gn:feature_code":"PPL",
    "gn:name":"Dukuhjambe",
    "gn:population":0,
    "gn:timezone":"Asia/Jakarta",
    "iso:country":"ID",
    "name:ind_x_preferred":[
        "Dukuhjambe"
    ],
    "wof:name":"Dukuhjambe",
    "wof:placetype":"locality"
},
  "geometry": {"coordinates":[108.89239999999999,-6.9084],"type":"Point"}
}