{
  "type": "Feature",
  "properties": {
    "gn:admin1_code":"30.0",
    "gn:asciiname":"Binangun",
    "gn:country_code":"ID",
    "gn:dem":35,
    "gn:feature_class":"P",
    "gn:feature_code":"PPL",
    "gn:name":"Binangun",
    "gn:population":0,
    "gn:timezone":"Asia/Jakarta",
    "iso:country":"ID",
    "name:und_x_variant":[
        "Binangoen"
    ],
    "wof:name":"Binangun",
    "wof:placetype":"locality"
},
  "geometry": {"coordinates":[108.52312000000001,-7.42427],"type":"Point"}
}