{
  "type": "Feature",
  "properties": {
    "gn:admin1_code":"30",
    "gn:asciiname":"Grang Haji Bin Ali",
    "gn:country_code":"ID",
    "gn:dem":230,
    "gn:feature_class":"P",
    "gn:feature_code":"PPL",
    "gn:name":"Grang Haji Bin Ali",
    "gn:population":0,
    "gn:timezone":"Asia/Jakarta",
    "iso:country":"ID",
    "name:ind_x_preferred":[
        "Grang Haji Bin Ali"
    ],
    "name:und_x_variant":[
        "Grang H. Bin Ali"
    ],
    "wof:lang_x_official":[
        "ind"
    ],
    "wof:lang_x_spoken":[
        "ind",
        "eng"
    ],
    "wof:name":"Grang Haji Bin Ali",
    "wof:placetype":"locality"
},
  "geometry": {"coordinates":[106.79194,-6.58389],"type":"Point"}
}