{
  "type": "Feature",
  "properties": {
    "gn:admin1_code":"14",
    "gn:asciiname":"Lokasi Satu C",
    "gn:country_code":"ID",
    "gn:dem":18,
    "gn:feature_class":"P",
    "gn:feature_code":"PPL",
    "gn:name":"Lokasi Satu C",
    "gn:population":0,
    "gn:timezone":"Asia/Makassar",
    "iso:country":"ID",
    "name:ind_x_preferred":[
        "Lokasi Satu C"
    ],
    "wof:name":"Lokasi Satu C",
    "wof:placetype":"locality"
},
  "geometry": {"coordinates":[117.07170000000001,-0.4095],"type":"Point"}
}