{
  "type": "Feature",
  "properties": {
    "gn:admin1_code":"7.0",
    "gn:asciiname":"Wonokerto",
    "gn:country_code":"ID",
    "gn:dem":251,
    "gn:feature_class":"P",
    "gn:feature_code":"PPL",
    "gn:name":"Wonokerto",
    "gn:population":0,
    "gn:timezone":"Asia/Jakarta",
    "iso:country":"ID",
    "name:ind_x_preferred":[
        "Wonokerto"
    ],
    "wof:name":"Wonokerto",
    "wof:placetype":"locality"
},
  "geometry": {"coordinates":[110.82971999999999,-8.07472],"type":"Point"}
}