{
  "type": "Feature",
  "properties": {
    "gn:admin1_code":"26",
    "gn:asciiname":"Jatinegara",
    "gn:country_code":"ID",
    "gn:dem":36,
    "gn:feature_class":"P",
    "gn:feature_code":"PPL",
    "gn:name":"Jatinegara",
    "gn:population":0,
    "gn:timezone":"Asia/Jakarta",
    "iso:country":"ID",
    "name:ceb_x_preferred":[
        "Kelurahan Jatinegara"
    ],
    "name:deu_x_preferred":[
        "Jatinegara"
    ],
    "name:fra_x_preferred":[
        "Jatinegara"
    ],
    "name:ind_x_preferred":[
        "Jatinegara"
    ],
    "name:ita_x_preferred":[
        "Jatinegara"
    ],
    "name:jav_x_preferred":[
        "Jatinegara"
    ],
    "name:nld_x_preferred":[
        "Jatinegara"
    ],
    "name:pol_x_preferred":[
        "Jatinegara"
    ],
    "name:sun_x_preferred":[
        "Jatinegara"
    ],
    "name:swe_x_preferred":[
        "Kelurahan Jatinegara"
    ],
    "wof:lang_x_official":[
        "ind"
    ],
    "wof:lang_x_spoken":[
        "ind",
        "eng"
    ],
    "wof:name":"Jatinegara",
    "wof:placetype":"locality"
},
  "geometry": {"coordinates":[98.48260000000001,3.617],"type":"Point"}
}