{
  "type": "Feature",
  "properties": {
    "gn:admin1_code":"18",
    "gn:asciiname":"Mombok",
    "gn:country_code":"ID",
    "gn:dem":802,
    "gn:feature_class":"P",
    "gn:feature_code":"PPLA4",
    "gn:name":"Mombok",
    "gn:population":0,
    "gn:timezone":"Asia/Makassar",
    "iso:country":"ID",
    "name:ind_x_preferred":[
        "Mombok"
    ],
    "wof:lang_x_official":[
        "ind"
    ],
    "wof:lang_x_spoken":[
        "ind",
        "eng"
    ],
    "wof:name":"Mombok",
    "wof:placetype":"locality"
},
  "geometry": {"coordinates":[120.72929999999999,-8.5271],"type":"Point"}
}