{
  "type": "Feature",
  "properties": {
    "gn:admin1_code":"26",
    "gn:asciiname":"Simpang Empat",
    "gn:country_code":"ID",
    "gn:dem":4,
    "gn:feature_class":"P",
    "gn:feature_code":"PPL",
    "gn:name":"Simpang Empat",
    "gn:population":0,
    "gn:timezone":"Asia/Jakarta",
    "iso:country":"ID",
    "name:ind_x_preferred":[
        "Simpang Empat"
    ],
    "name:msa_x_preferred":[
        "Simpang Empat"
    ],
    "name:nld_x_preferred":[
        "Simpang Empat"
    ],
    "name:und_x_variant":[
        "Simpang 4"
    ],
    "wof:lang_x_official":[
        "ind"
    ],
    "wof:lang_x_spoken":[
        "ind",
        "eng"
    ],
    "wof:name":"Simpang Empat",
    "wof:placetype":"locality"
},
  "geometry": {"coordinates":[99.3125,3.4041],"type":"Point"}
}