{
  "type": "Feature",
  "properties": {
    "gn:admin1_code":"7.0",
    "gn:asciiname":"Ngawinan",
    "gn:country_code":"ID",
    "gn:dem":555,
    "gn:feature_class":"P",
    "gn:feature_code":"PPL",
    "gn:name":"Ngawinan",
    "gn:population":0,
    "gn:timezone":"Asia/Jakarta",
    "iso:country":"ID",
    "wof:name":"Ngawinan",
    "wof:placetype":"locality"
},
  "geometry": {"coordinates":[110.15472,-7.47333],"type":"Point"}
}