{
  "type": "Feature",
  "properties": {
    "gn:admin1_code":"8",
    "gn:asciiname":"Dongjati",
    "gn:country_code":"ID",
    "gn:dem":92,
    "gn:feature_class":"P",
    "gn:feature_code":"PPL",
    "gn:name":"Dongjati",
    "gn:population":0,
    "gn:timezone":"Asia/Jakarta",
    "iso:country":"ID",
    "name:ind_x_preferred":[
        "Dongjati"
    ],
    "wof:name":"Dongjati",
    "wof:placetype":"locality"
},
  "geometry": {"coordinates":[111.61490000000001,-7.0353],"type":"Point"}
}