{
  "type": "Feature",
  "properties": {
    "gn:admin1_code":"8.0",
    "gn:asciiname":"Gedangsewu Utara",
    "gn:country_code":"ID",
    "gn:dem":89,
    "gn:feature_class":"P",
    "gn:feature_code":"PPL",
    "gn:name":"Gedangsewu Utara",
    "gn:population":0,
    "gn:timezone":"Asia/Jakarta",
    "iso:country":"ID",
    "name:ind_x_preferred":[
        "Gedangsewu Utara"
    ],
    "wof:name":"Gedangsewu Utara",
    "wof:placetype":"locality"
},
  "geometry": {"coordinates":[111.8888,-8.0735],"type":"Point"}
}