{
  "type": "Feature",
  "properties": {
    "gn:admin1_code":"17",
    "gn:asciiname":"Batubodak",
    "gn:country_code":"ID",
    "gn:dem":85,
    "gn:feature_class":"P",
    "gn:feature_code":"PPL",
    "gn:name":"Batubodak",
    "gn:population":0,
    "gn:timezone":"Asia/Makassar",
    "iso:country":"ID",
    "name:ind_x_preferred":[
        "Batubodak"
    ],
    "wof:name":"Batubodak",
    "wof:placetype":"locality"
},
  "geometry": {"coordinates":[116.23220000000001,-8.7806],"type":"Point"}
}