{
  "type": "Feature",
  "properties": {
    "gn:admin1_code":"8.0",
    "gn:asciiname":"Panji",
    "gn:country_code":"ID",
    "gn:dem":192,
    "gn:feature_class":"P",
    "gn:feature_code":"PPL",
    "gn:name":"Panji",
    "gn:population":0,
    "gn:timezone":"Asia/Jakarta",
    "iso:country":"ID",
    "name:ceb_x_preferred":[
        "Panji"
    ],
    "name:fra_x_preferred":[
        "Panji"
    ],
    "name:ind_x_preferred":[
        "Panji"
    ],
    "name:nld_x_preferred":[
        "Panji"
    ],
    "name:swe_x_preferred":[
        "Panji"
    ],
    "wof:lang_x_official":[
        "ind"
    ],
    "wof:lang_x_spoken":[
        "ind",
        "eng"
    ],
    "wof:name":"Panji",
    "wof:placetype":"locality"
},
  "geometry": {"coordinates":[114.01730000000001,-7.8391],"type":"Point"}
}