{
  "type": "Feature",
  "properties": {
    "gn:admin1_code":"15.0",
    "gn:asciiname":"Rantaujaya Hilir",
    "gn:country_code":"ID",
    "gn:dem":16,
    "gn:feature_class":"P",
    "gn:feature_code":"PPL",
    "gn:name":"Rantaujaya Hilir",
    "gn:population":0,
    "gn:timezone":"Asia/Jakarta",
    "iso:country":"ID",
    "name:ind_x_preferred":[
        "Rantaujaya Hilir"
    ],
    "name:ind_x_variant":[
        "Rantaudjaja Hilir"
    ],
    "name:und_x_variant":[
        "Rantaudjaja-hilir",
        "Rantaujaya-hilir"
    ],
    "wof:lang_x_official":[
        "ind"
    ],
    "wof:lang_x_spoken":[
        "ind",
        "eng"
    ],
    "wof:name":"Rantaujaya Hilir",
    "wof:placetype":"locality"
},
  "geometry": {"coordinates":[105.60671000000001,-4.8504],"type":"Point"}
}