{
  "type": "Feature",
  "properties": {
    "gn:admin1_code":"30.0",
    "gn:asciiname":"Ganea",
    "gn:country_code":"ID",
    "gn:dem":541,
    "gn:feature_class":"P",
    "gn:feature_code":"PPL",
    "gn:name":"Ganea",
    "gn:population":0,
    "gn:timezone":"Asia/Jakarta",
    "iso:country":"ID",
    "name:deu_x_preferred":[
        "Ganea"
    ],
    "name:ind_x_preferred":[
        "Ganea"
    ],
    "name:ron_x_preferred":[
        "Ganea"
    ],
    "name:ukr_x_preferred":[
        "\u0413\u0430\u043d\u044f"
    ],
    "wof:lang_x_official":[
        "ind"
    ],
    "wof:lang_x_spoken":[
        "ind",
        "eng"
    ],
    "wof:name":"Ganea",
    "wof:placetype":"locality"
},
  "geometry": {"coordinates":[107.6183,-7.4342],"type":"Point"}
}