{
  "type": "Feature",
  "properties": {
    "gn:admin1_code":"28.0",
    "gn:asciiname":"Bina",
    "gn:country_code":"ID",
    "gn:dem":11,
    "gn:feature_class":"P",
    "gn:feature_code":"PPL",
    "gn:name":"Bina",
    "gn:population":0,
    "gn:timezone":"Asia/Jayapura",
    "iso:country":"ID",
    "name:ceb_x_preferred":[
        "Bina"
    ],
    "name:deu_x_preferred":[
        "Bina"
    ],
    "name:heb_x_preferred":[
        "\u05d1\u05d9\u05e0\u05d4"
    ],
    "name:hin_x_preferred":[
        "\u092c\u0940\u0928\u093e"
    ],
    "name:ind_x_preferred":[
        "Bina"
    ],
    "name:ita_x_preferred":[
        "Bina"
    ],
    "name:por_x_preferred":[
        "Bina"
    ],
    "name:srp_x_preferred":[
        "\u0411\u0438\u043d\u0430"
    ],
    "name:swe_x_preferred":[
        "Bina"
    ],
    "name:tur_x_preferred":[
        "Bina"
    ],
    "wof:lang_x_official":[
        "ind"
    ],
    "wof:lang_x_spoken":[
        "ind",
        "eng"
    ],
    "wof:name":"Bina",
    "wof:placetype":"locality"
},
  "geometry": {"coordinates":[127.03568,-3.40128],"type":"Point"}
}