{
  "type": "Feature",
  "properties": {
    "gn:admin1_code":"8.0",
    "gn:asciiname":"Kokembang",
    "gn:country_code":"ID",
    "gn:dem":168,
    "gn:feature_class":"P",
    "gn:feature_code":"PPLA4",
    "gn:name":"Kokembang",
    "gn:population":0,
    "gn:timezone":"Asia/Jakarta",
    "iso:country":"ID",
    "name:ind_x_preferred":[
        "Kokembang"
    ],
    "wof:name":"Kokembang",
    "wof:placetype":"locality"
},
  "geometry": {"coordinates":[113.64870000000001,-6.9524],"type":"Point"}
}