{
  "type": "Feature",
  "properties": {
    "gn:admin1_code":"15.0",
    "gn:asciiname":"Kayuabun",
    "gn:country_code":"ID",
    "gn:dem":196,
    "gn:feature_class":"P",
    "gn:feature_code":"PPL",
    "gn:name":"Kayuabun",
    "gn:population":0,
    "gn:timezone":"Asia/Jakarta",
    "iso:country":"ID",
    "name:ind_x_preferred":[
        "Kayuabun"
    ],
    "name:und_x_variant":[
        "Kajoeamboen"
    ],
    "wof:name":"Kayuabun",
    "wof:placetype":"locality"
},
  "geometry": {"coordinates":[104.8169,-5.3339],"type":"Point"}
}