{
  "type": "Feature",
  "properties": {
    "gn:admin1_code":"38",
    "gn:asciiname":"Otting",
    "gn:country_code":"ID",
    "gn:dem":59,
    "gn:feature_class":"P",
    "gn:feature_code":"PPL",
    "gn:name":"Otting",
    "gn:population":0,
    "gn:timezone":"Asia/Makassar",
    "iso:country":"ID",
    "name:als_x_preferred":[
        "Otting"
    ],
    "name:ceb_x_preferred":[
        "Otting"
    ],
    "name:deu_x_preferred":[
        "Otting"
    ],
    "name:epo_x_preferred":[
        "Otting"
    ],
    "name:eus_x_preferred":[
        "Otting"
    ],
    "name:fra_x_preferred":[
        "Otting"
    ],
    "name:hun_x_preferred":[
        "Otting"
    ],
    "name:hye_x_preferred":[
        "\u0555\u0569\u056b\u0576\u0563"
    ],
    "name:ind_x_preferred":[
        "Otting"
    ],
    "name:ita_x_preferred":[
        "Otting"
    ],
    "name:jpn_x_preferred":[
        "\u30aa\u30c3\u30c6\u30a3\u30f3\u30b0"
    ],
    "name:kaz_x_preferred":[
        "\u041e\u0442\u0442\u0438\u043d\u0433"
    ],
    "name:kir_x_preferred":[
        "\u041e\u0442\u0442\u0438\u043d\u0433"
    ],
    "name:lmo_x_preferred":[
        "Otting"
    ],
    "name:msa_x_preferred":[
        "Otting"
    ],
    "name:nld_x_preferred":[
        "Otting"
    ],
    "name:pol_x_preferred":[
        "Otting"
    ],
    "name:por_x_preferred":[
        "Otting"
    ],
    "name:ron_x_preferred":[
        "Otting"
    ],
    "name:rus_x_preferred":[
        "\u041e\u0442\u0442\u0438\u043d\u0433"
    ],
    "name:spa_x_preferred":[
        "Otting"
    ],
    "name:srp_x_preferred":[
        "\u041e\u0442\u0438\u043d\u0433"
    ],
    "name:ukr_x_preferred":[
        "\u041e\u0442\u0442\u0456\u043d\u0433"
    ],
    "name:uzb_x_preferred":[
        "Otting"
    ],
    "name:vie_x_preferred":[
        "Otting"
    ],
    "name:vol_x_preferred":[
        "Otting"
    ],
    "name:war_x_preferred":[
        "Otting"
    ],
    "wof:lang_x_official":[
        "ind"
    ],
    "wof:lang_x_spoken":[
        "ind",
        "eng"
    ],
    "wof:name":"Otting",
    "wof:placetype":"locality"
},
  "geometry": {"coordinates":[120.248,-4.4153],"type":"Point"}
}