{
  "type": "Feature",
  "properties": {
    "gn:admin1_code":"18.0",
    "gn:asciiname":"Sawah",
    "gn:country_code":"ID",
    "gn:dem":61,
    "gn:feature_class":"P",
    "gn:feature_code":"PPL",
    "gn:name":"Sawah",
    "gn:population":0,
    "gn:timezone":"Asia/Makassar",
    "iso:country":"ID",
    "name:ind_x_preferred":[
        "Sawah"
    ],
    "wof:name":"Sawah",
    "wof:placetype":"locality"
},
  "geometry": {"coordinates":[123.09180000000001,-8.2871],"type":"Point"}
}