{
  "type": "Feature",
  "properties": {
    "gn:admin1_code":"08",
    "gn:asciiname":"Pancor",
    "gn:cc2":"ID",
    "gn:country_code":"ID",
    "gn:dem":19,
    "gn:feature_class":"P",
    "gn:feature_code":"PPL",
    "gn:name":"Pancor",
    "gn:population":0,
    "gn:timezone":"Asia/Jakarta",
    "iso:country":"ID",
    "name:und_x_variant":[
        "Pantjor",
        "Pancor"
    ],
    "wof:name":"Pancor",
    "wof:placetype":"locality"
},
  "geometry": {"coordinates":[112.81999999999999,-7.07278],"type":"Point"}
}