{
  "type": "Feature",
  "properties": {
    "gn:admin1_code":"33.0",
    "gn:asciiname":"Cibarengkok",
    "gn:country_code":"ID",
    "gn:dem":21,
    "gn:feature_class":"P",
    "gn:feature_code":"PPL",
    "gn:name":"Cibarengkok",
    "gn:population":0,
    "gn:timezone":"Asia/Jakarta",
    "iso:country":"ID",
    "name:ind_x_preferred":[
        "Cibarengkok"
    ],
    "wof:name":"Cibarengkok",
    "wof:placetype":"locality"
},
  "geometry": {"coordinates":[105.9361,-6.4761],"type":"Point"}
}