{
  "type": "Feature",
  "properties": {
    "gn:admin1_code":"30.0",
    "gn:asciiname":"Cikarang Satu",
    "gn:country_code":"ID",
    "gn:dem":967,
    "gn:feature_class":"P",
    "gn:feature_code":"PPL",
    "gn:name":"Cikarang Satu",
    "gn:population":0,
    "gn:timezone":"Asia/Jakarta",
    "iso:country":"ID",
    "name:ind_x_preferred":[
        "Cikarang Satu"
    ],
    "name:und_x_variant":[
        "Tjikarang",
        "Cikarang"
    ],
    "wof:lang_x_official":[
        "ind"
    ],
    "wof:lang_x_spoken":[
        "ind",
        "eng"
    ],
    "wof:name":"Cikarang Satu",
    "wof:placetype":"locality"
},
  "geometry": {"coordinates":[106.98180000000001,-7.0905],"type":"Point"}
}