{
  "type": "Feature",
  "properties": {
    "gn:admin1_code":"17.0",
    "gn:asciiname":"Orongluk",
    "gn:country_code":"ID",
    "gn:dem":33,
    "gn:feature_class":"P",
    "gn:feature_code":"PPL",
    "gn:name":"Orongluk",
    "gn:population":0,
    "gn:timezone":"Asia/Makassar",
    "iso:country":"ID",
    "name:ind_x_preferred":[
        "Orongluk"
    ],
    "wof:name":"Orongluk",
    "wof:placetype":"locality"
},
  "geometry": {"coordinates":[116.1828,-8.3634],"type":"Point"}
}