{
  "type": "Feature",
  "properties": {
    "gn:admin1_code":"30.0",
    "gn:asciiname":"Nangela",
    "gn:country_code":"ID",
    "gn:dem":854,
    "gn:feature_class":"P",
    "gn:feature_code":"PPL",
    "gn:name":"Nangela",
    "gn:population":0,
    "gn:timezone":"Asia/Jakarta",
    "iso:country":"ID",
    "name:ind_x_preferred":[
        "Nangela"
    ],
    "name:und_x_variant":[
        "Nanggela"
    ],
    "wof:name":"Nangela",
    "wof:placetype":"locality"
},
  "geometry": {"coordinates":[108.2924,-7.1655],"type":"Point"}
}