{
  "type": "Feature",
  "properties": {
    "gn:admin1_code":"18.0",
    "gn:asciiname":"Loko",
    "gn:country_code":"ID",
    "gn:dem":520,
    "gn:feature_class":"P",
    "gn:feature_code":"PPL",
    "gn:name":"Loko",
    "gn:population":0,
    "gn:timezone":"Asia/Makassar",
    "iso:country":"ID",
    "name:ceb_x_preferred":[
        "Loko"
    ],
    "name:deu_x_preferred":[
        "Loko"
    ],
    "name:fra_x_preferred":[
        "Loko"
    ],
    "name:ind_x_preferred":[
        "Loko"
    ],
    "name:kaz_x_preferred":[
        "\u041b\u043e\u043a\u043e"
    ],
    "name:por_x_preferred":[
        "Loko"
    ],
    "name:ron_x_preferred":[
        "Loko"
    ],
    "name:rus_x_preferred":[
        "\u041b\u043e\u043a\u043e"
    ],
    "name:swe_x_preferred":[
        "Loko"
    ],
    "wof:lang_x_official":[
        "ind"
    ],
    "wof:lang_x_spoken":[
        "ind",
        "eng"
    ],
    "wof:name":"Loko",
    "wof:placetype":"locality"
},
  "geometry": {"coordinates":[119.3605,-9.5549],"type":"Point"}
}