{
  "type": "Feature",
  "properties": {
    "gn:admin1_code":"37.0",
    "gn:asciiname":"Paritudang",
    "gn:country_code":"ID",
    "gn:dem":5,
    "gn:feature_class":"P",
    "gn:feature_code":"PPL",
    "gn:name":"Paritudang",
    "gn:population":0,
    "gn:timezone":"Asia/Jakarta",
    "iso:country":"ID",
    "name:ind_x_preferred":[
        "Paritudang"
    ],
    "wof:name":"Paritudang",
    "wof:placetype":"locality"
},
  "geometry": {"coordinates":[103.33450000000001,-0.1197],"type":"Point"}
}