{
  "type": "Feature",
  "properties": {
    "gn:admin1_code":"30.0",
    "gn:asciiname":"Nangka",
    "gn:country_code":"ID",
    "gn:dem":557,
    "gn:feature_class":"P",
    "gn:feature_code":"PPL",
    "gn:name":"Nangka",
    "gn:population":0,
    "gn:timezone":"Asia/Jakarta",
    "iso:country":"ID",
    "name:ind_x_preferred":[
        "Nangka"
    ],
    "wof:name":"Nangka",
    "wof:placetype":"locality"
},
  "geometry": {"coordinates":[108.0658,-7.434],"type":"Point"}
}