{
  "type": "Feature",
  "properties": {
    "gn:admin1_code":"00",
    "gn:asciiname":"Bojongbrod",
    "gn:cc2":"ID",
    "gn:country_code":"ID",
    "gn:dem":56,
    "gn:feature_class":"P",
    "gn:feature_code":"PPL",
    "gn:name":"Bojongbrod",
    "gn:population":0,
    "gn:timezone":"Asia/Jakarta",
    "iso:country":"ID",
    "name:und_x_variant":[
        "Bodjongbrod",
        "Bojongbrod"
    ],
    "wof:name":"Bojongbrod",
    "wof:placetype":"locality"
},
  "geometry": {"coordinates":[106.53694,-6.35611],"type":"Point"}
}