{
  "type": "Feature",
  "properties": {
    "gn:admin1_code":"26.0",
    "gn:asciiname":"Si Ngali-ngali",
    "gn:country_code":"ID",
    "gn:dem":1329,
    "gn:feature_class":"P",
    "gn:feature_code":"PPL",
    "gn:name":"Si Ngali-ngali",
    "gn:population":0,
    "gn:timezone":"Asia/Jakarta",
    "iso:country":"ID",
    "name:ind_x_preferred":[
        "Si Ngali-ngali"
    ],
    "name:und_x_variant":[
        "Ngalingali"
    ],
    "wof:lang_x_official":[
        "ind"
    ],
    "wof:lang_x_spoken":[
        "ind",
        "eng"
    ],
    "wof:name":"Si Ngali-ngali",
    "wof:placetype":"locality"
},
  "geometry": {"coordinates":[98.9096,2.5173],"type":"Point"}
}