{
  "type": "Feature",
  "properties": {
    "gn:admin1_code":"26",
    "gn:asciiname":"Lingga Julu",
    "gn:country_code":"ID",
    "gn:dem":1346,
    "gn:feature_class":"P",
    "gn:feature_code":"PPL",
    "gn:name":"Lingga Julu",
    "gn:population":0,
    "gn:timezone":"Asia/Jakarta",
    "iso:country":"ID",
    "name:ind_x_preferred":[
        "Lingga Julu"
    ],
    "name:und_x_variant":[
        "Linggadjulu"
    ],
    "wof:lang_x_official":[
        "ind"
    ],
    "wof:lang_x_spoken":[
        "ind",
        "eng"
    ],
    "wof:name":"Lingga Julu",
    "wof:placetype":"locality"
},
  "geometry": {"coordinates":[98.4936,3.1604],"type":"Point"}
}