{
  "type": "Feature",
  "properties": {
    "gn:admin1_code":"30",
    "gn:asciiname":"Sarijem Satu",
    "gn:country_code":"ID",
    "gn:dem":7,
    "gn:feature_class":"P",
    "gn:feature_code":"PPL",
    "gn:name":"Sarijem Satu",
    "gn:population":0,
    "gn:timezone":"Asia/Jakarta",
    "iso:country":"ID",
    "name:ind_x_preferred":[
        "Sarijem Satu"
    ],
    "wof:name":"Sarijem Satu",
    "wof:placetype":"locality"
},
  "geometry": {"coordinates":[108.42417,-6.43278],"type":"Point"}
}