{
  "type": "Feature",
  "properties": {
    "gn:admin1_code":"2",
    "gn:asciiname":"Banjar Benbiyu",
    "gn:country_code":"ID",
    "gn:dem":78,
    "gn:feature_class":"P",
    "gn:feature_code":"PPL",
    "gn:name":"Banjar Benbiyu",
    "gn:population":0,
    "gn:timezone":"Asia/Makassar",
    "iso:country":"ID",
    "name:ind_x_preferred":[
        "Banjar Benbiyu"
    ],
    "wof:name":"Banjar Benbiyu",
    "wof:placetype":"locality"
},
  "geometry": {"coordinates":[115.2191,-8.6061],"type":"Point"}
}