{
  "type": "Feature",
  "properties": {
    "gn:admin1_code":"30.0",
    "gn:asciiname":"Cikolak",
    "gn:country_code":"ID",
    "gn:dem":588,
    "gn:feature_class":"P",
    "gn:feature_code":"PPL",
    "gn:name":"Cikolak",
    "gn:population":0,
    "gn:timezone":"Asia/Jakarta",
    "iso:country":"ID",
    "name:ind_x_preferred":[
        "Cikolak"
    ],
    "name:und_x_variant":[
        "Tjikolak"
    ],
    "wof:name":"Cikolak",
    "wof:placetype":"locality"
},
  "geometry": {"coordinates":[107.9118,-7.5298],"type":"Point"}
}