{
  "type": "Feature",
  "properties": {
    "gn:admin1_code":"18.0",
    "gn:asciiname":"Eymadaiki",
    "gn:country_code":"ID",
    "gn:dem":115,
    "gn:feature_class":"P",
    "gn:feature_code":"PPL",
    "gn:name":"Eymadaiki",
    "gn:population":0,
    "gn:timezone":"Asia/Makassar",
    "iso:country":"ID",
    "name:ind_x_preferred":[
        "Eymadaiki"
    ],
    "wof:name":"Eymadaiki",
    "wof:placetype":"locality"
},
  "geometry": {"coordinates":[121.93389999999999,-10.4775],"type":"Point"}
}