{
  "type": "Feature",
  "properties": {
    "gn:admin1_code":"10.0",
    "gn:asciiname":"Juwak",
    "gn:country_code":"ID",
    "gn:dem":275,
    "gn:feature_class":"P",
    "gn:feature_code":"PPL",
    "gn:name":"Juwak",
    "gn:population":0,
    "gn:timezone":"Asia/Jakarta",
    "iso:country":"ID",
    "name:ind_x_preferred":[
        "Juwak"
    ],
    "wof:name":"Juwak",
    "wof:placetype":"locality"
},
  "geometry": {"coordinates":[110.65639,-8.08972],"type":"Point"}
}