{
  "type": "Feature",
  "properties": {
    "gn:admin1_code":"8.0",
    "gn:asciiname":"Selatan",
    "gn:country_code":"ID",
    "gn:dem":172,
    "gn:feature_class":"P",
    "gn:feature_code":"PPL",
    "gn:name":"Selatan",
    "gn:population":0,
    "gn:timezone":"Asia/Jakarta",
    "iso:country":"ID",
    "name:ind_x_preferred":[
        "Selatan"
    ],
    "wof:name":"Selatan",
    "wof:placetype":"locality"
},
  "geometry": {"coordinates":[113.49079999999999,-7.0685],"type":"Point"}
}