{
  "type": "Feature",
  "properties": {
    "gn:country":"ID",
    "gn:fcode":"ADM3",
    "gn:pop":0,
    "iso:country":"ID",
    "name:ban_x_preferred":[
        "Kecamatan lan kelurahan ring Lampung"
    ],
    "name:eng_x_preferred":[
        "Districts of Lampung"
    ],
    "name:ind_x_preferred":[
        "Kecamatan Teluk Betung Barat"
    ],
    "name:unk_x_variant":[
        "Teluk Betung Barat"
    ],
    "qs:name":"Kecamatan Teluk Betung Barat",
    "qs:photos_9r":0,
    "qs:photos_sr":0,
    "qs:pop_sr":"0",
    "wd:wordcount":669,
    "wof:lang_x_official":[
        "ind"
    ],
    "wof:lang_x_spoken":[
        "ind",
        "eng"
    ],
    "wof:name":"Kecamatan Teluk Betung Barat",
    "wof:placetype":"localadmin",
    "wof:population":0
},
  "geometry": {"coordinates":[105.23898,-5.45646],"type":"Point"}
}