{
  "type": "Feature",
  "properties": {
    "gn:admin1_code":"36.0",
    "gn:asciiname":"Skaumaba",
    "gn:country_code":"ID",
    "gn:dem":7,
    "gn:feature_class":"P",
    "gn:feature_code":"PPL",
    "gn:name":"Skaumaba",
    "gn:population":0,
    "gn:timezone":"Asia/Jayapura",
    "iso:country":"ID",
    "name:ind_x_preferred":[
        "Skaumaba"
    ],
    "name:und_x_variant":[
        "Seko",
        "Mabo",
        "Sko",
        "Skomabo"
    ],
    "wof:lang_x_official":[
        "ind"
    ],
    "wof:lang_x_spoken":[
        "ind",
        "eng"
    ],
    "wof:name":"Skaumaba",
    "wof:placetype":"locality"
},
  "geometry": {"coordinates":[140.8638,-2.6132],"type":"Point"}
}