{
  "type": "Feature",
  "properties": {
    "gn:admin1_code":"28.0",
    "gn:asciiname":"Haya",
    "gn:country_code":"ID",
    "gn:dem":13,
    "gn:feature_class":"P",
    "gn:feature_code":"PPL",
    "gn:name":"Haya",
    "gn:population":0,
    "gn:timezone":"Asia/Jayapura",
    "iso:country":"ID",
    "name:ceb_x_preferred":[
        "Haya"
    ],
    "name:deu_x_preferred":[
        "Haya"
    ],
    "name:fra_x_preferred":[
        "Haya"
    ],
    "name:ind_x_preferred":[
        "Haya"
    ],
    "name:ita_x_preferred":[
        "Haya"
    ],
    "name:kor_x_preferred":[
        "\ud558\uc57c"
    ],
    "name:pol_x_preferred":[
        "Haya"
    ],
    "name:que_x_preferred":[
        "Haya"
    ],
    "name:rus_x_preferred":[
        "\u0425\u0430\u0439\u044f"
    ],
    "name:spa_x_preferred":[
        "Haya"
    ],
    "name:swe_x_preferred":[
        "Haya"
    ],
    "name:und_x_variant":[
        "Haja"
    ],
    "wof:name":"Haya",
    "wof:placetype":"locality"
},
  "geometry": {"coordinates":[127.83351,-3.15561],"type":"Point"}
}