{
  "type": "Feature",
  "properties": {
    "gn:admin1_code":"8.0",
    "gn:asciiname":"Pucangan",
    "gn:country_code":"ID",
    "gn:dem":183,
    "gn:feature_class":"P",
    "gn:feature_code":"PPLA4",
    "gn:name":"Pucangan",
    "gn:population":0,
    "gn:timezone":"Asia/Jakarta",
    "iso:country":"ID",
    "name:ind_x_preferred":[
        "Pucangan"
    ],
    "name:und_x_variant":[
        "Poetjangan"
    ],
    "wof:lang_x_official":[
        "ind"
    ],
    "wof:lang_x_spoken":[
        "ind",
        "eng"
    ],
    "wof:name":"Pucangan",
    "wof:placetype":"locality"
},
  "geometry": {"coordinates":[111.90049999999999,-6.9442],"type":"Point"}
}