{
  "type": "Feature",
  "properties": {
    "gn:admin1_code":"30.0",
    "gn:asciiname":"Pasirganas",
    "gn:country_code":"ID",
    "gn:dem":216,
    "gn:feature_class":"P",
    "gn:feature_code":"PPL",
    "gn:name":"Pasirganas",
    "gn:population":0,
    "gn:timezone":"Asia/Jakarta",
    "iso:country":"ID",
    "name:ind_x_preferred":[
        "Pasirganas"
    ],
    "wof:name":"Pasirganas",
    "wof:placetype":"locality"
},
  "geometry": {"coordinates":[108.25109999999999,-7.7133],"type":"Point"}
}