{
  "type": "Feature",
  "properties": {
    "gn:admin1_code":"30.0",
    "gn:asciiname":"Kranggan",
    "gn:country_code":"ID",
    "gn:dem":54,
    "gn:feature_class":"P",
    "gn:feature_code":"PPL",
    "gn:name":"Kranggan",
    "gn:population":0,
    "gn:timezone":"Asia/Jakarta",
    "iso:country":"ID",
    "name:ind_x_preferred":[
        "Kranggan"
    ],
    "wof:name":"Kranggan",
    "wof:placetype":"locality"
},
  "geometry": {"coordinates":[111.4402,-7.4077],"type":"Point"}
}