{
  "type": "Feature",
  "properties": {
    "gn:admin1_code":"26",
    "gn:asciiname":"Gundaling Dua",
    "gn:country_code":"ID",
    "gn:dem":581,
    "gn:feature_class":"P",
    "gn:feature_code":"PPL",
    "gn:name":"Gundaling Dua",
    "gn:population":0,
    "gn:timezone":"Asia/Jakarta",
    "iso:country":"ID",
    "name:ind_x_preferred":[
        "Gundaling Dua"
    ],
    "name:und_x_variant":[
        "Gundaling 2"
    ],
    "wof:name":"Gundaling Dua",
    "wof:placetype":"locality"
},
  "geometry": {"coordinates":[98.14449999999999,2.9485],"type":"Point"}
}