{
  "type": "Feature",
  "properties": {
    "gn:admin1_code":"30",
    "gn:asciiname":"Dukuhgambar",
    "gn:country_code":"ID",
    "gn:dem":570,
    "gn:feature_class":"P",
    "gn:feature_code":"PPL",
    "gn:name":"Dukuhgambar",
    "gn:population":0,
    "gn:timezone":"Asia/Jakarta",
    "iso:country":"ID",
    "name:ind_x_preferred":[
        "Dukuhgambar"
    ],
    "wof:name":"Dukuhgambar",
    "wof:placetype":"locality"
},
  "geometry": {"coordinates":[108.31694,-6.8625],"type":"Point"}
}