{
  "type": "Feature",
  "properties": {
    "gn:country":"ID",
    "gn:fcode":"ADM4",
    "gn:pop":0,
    "iso:country":"ID",
    "name:ind_x_preferred":[
        "Desa Peguyangan Kaja"
    ],
    "name:unk_x_variant":[
        "Peguyangan Kaja"
    ],
    "qs:name":"Desa Peguyangan Kaja",
    "qs:photos_9r":0,
    "qs:photos_sr":0,
    "qs:pop_sr":"0",
    "wof:name":"Desa Peguyangan Kaja",
    "wof:placetype":"localadmin",
    "wof:population":0
},
  "geometry": {"coordinates":[115.2123,-8.6045],"type":"Point"}
}