{
  "type": "Feature",
  "properties": {
    "gn:admin1_code":"18.0",
    "gn:asciiname":"Mbang",
    "gn:country_code":"ID",
    "gn:dem":317,
    "gn:feature_class":"P",
    "gn:feature_code":"PPL",
    "gn:name":"Mbang",
    "gn:population":0,
    "gn:timezone":"Asia/Makassar",
    "iso:country":"ID",
    "name:ceb_x_preferred":[
        "Mbang"
    ],
    "name:deu_x_preferred":[
        "Mbang"
    ],
    "name:fra_x_preferred":[
        "Mbang"
    ],
    "name:ind_x_preferred":[
        "Mbang"
    ],
    "name:swe_x_preferred":[
        "Mbang"
    ],
    "wof:name":"Mbang",
    "wof:placetype":"locality"
},
  "geometry": {"coordinates":[120.2945,-8.4262],"type":"Point"}
}