{
  "type": "Feature",
  "properties": {
    "gn:admin1_code":"30",
    "gn:asciiname":"Cipari",
    "gn:country_code":"ID",
    "gn:dem":734,
    "gn:feature_class":"P",
    "gn:feature_code":"PPL",
    "gn:name":"Cipari",
    "gn:population":0,
    "gn:timezone":"Asia/Jakarta",
    "iso:country":"ID",
    "name:ind_x_preferred":[
        "Cipari"
    ],
    "name:msa_x_preferred":[
        "Cipari"
    ],
    "name:nld_x_preferred":[
        "Cipari"
    ],
    "name:sun_x_preferred":[
        "Cipari"
    ],
    "wof:name":"Cipari",
    "wof:placetype":"locality"
},
  "geometry": {"coordinates":[107.90361,-6.89389],"type":"Point"}
}