{
  "type": "Feature",
  "properties": {
    "gn:admin1_code":"30",
    "gn:asciiname":"Nagrog",
    "gn:country_code":"ID",
    "gn:dem":728,
    "gn:feature_class":"P",
    "gn:feature_code":"PPL",
    "gn:name":"Nagrog",
    "gn:population":0,
    "gn:timezone":"Asia/Jakarta",
    "iso:country":"ID",
    "name:ind_x_preferred":[
        "Nagrog"
    ],
    "wof:name":"Nagrog",
    "wof:placetype":"locality"
},
  "geometry": {"coordinates":[107.70806,-6.90639],"type":"Point"}
}