{
  "type": "Feature",
  "properties": {
    "gn:admin1_code":"30",
    "gn:asciiname":"Sindangkasih",
    "gn:country_code":"ID",
    "gn:dem":29,
    "gn:feature_class":"P",
    "gn:feature_code":"PPL",
    "gn:name":"Sindangkasih",
    "gn:population":0,
    "gn:timezone":"Asia/Jakarta",
    "iso:country":"ID",
    "name:ind_x_preferred":[
        "Sindangkasih"
    ],
    "wof:name":"Sindangkasih",
    "wof:placetype":"locality"
},
  "geometry": {"coordinates":[107.815,-6.45306],"type":"Point"}
}