{
  "type": "Feature",
  "properties": {
    "gn:admin1_code":"30.0",
    "gn:asciiname":"Babakanmuncang",
    "gn:country_code":"ID",
    "gn:dem":362,
    "gn:feature_class":"P",
    "gn:feature_code":"PPL",
    "gn:name":"Babakanmuncang",
    "gn:population":0,
    "gn:timezone":"Asia/Jakarta",
    "iso:country":"ID",
    "name:ind_x_preferred":[
        "Babakanmuncang"
    ],
    "name:und_x_variant":[
        "Babakan Moentjang"
    ],
    "wof:lang_x_official":[
        "ind"
    ],
    "wof:lang_x_spoken":[
        "ind",
        "eng"
    ],
    "wof:name":"Babakanmuncang",
    "wof:placetype":"locality"
},
  "geometry": {"coordinates":[108.2216,-7.3634],"type":"Point"}
}