{
  "type": "Feature",
  "properties": {
    "gn:admin1_code":"38",
    "gn:asciiname":"Parapa",
    "gn:country_code":"ID",
    "gn:dem":698,
    "gn:feature_class":"P",
    "gn:feature_code":"PPL",
    "gn:name":"Parapa",
    "gn:population":0,
    "gn:timezone":"Asia/Makassar",
    "iso:country":"ID",
    "name:ind_x_preferred":[
        "Parapa"
    ],
    "wof:name":"Parapa",
    "wof:placetype":"locality"
},
  "geometry": {"coordinates":[119.571,-2.9729],"type":"Point"}
}