{
  "type": "Feature",
  "properties": {
    "gn:admin1_code":"22.0",
    "gn:asciiname":"Mabodo",
    "gn:country_code":"ID",
    "gn:dem":155,
    "gn:feature_class":"P",
    "gn:feature_code":"PPL",
    "gn:name":"Mabodo",
    "gn:population":0,
    "gn:timezone":"Asia/Makassar",
    "iso:country":"ID",
    "name:ind_x_preferred":[
        "Mabodo"
    ],
    "name:und_x_variant":[
        "Malabo\u00f2do",
        "Nabodo"
    ],
    "wof:name":"Mabodo",
    "wof:placetype":"locality"
},
  "geometry": {"coordinates":[122.66800000000001,-4.8642],"type":"Point"}
}