{
  "type": "Feature",
  "properties": {
    "gn:admin1_code":"7.0",
    "gn:asciiname":"Gandoang",
    "gn:country_code":"ID",
    "gn:dem":273,
    "gn:feature_class":"P",
    "gn:feature_code":"PPLA4",
    "gn:name":"Gandoang",
    "gn:population":0,
    "gn:timezone":"Asia/Jakarta",
    "iso:country":"ID",
    "name:ind_x_preferred":[
        "Gandoang"
    ],
    "wof:lang_x_official":[
        "ind"
    ],
    "wof:lang_x_spoken":[
        "ind",
        "eng"
    ],
    "wof:name":"Gandoang",
    "wof:placetype":"locality"
},
  "geometry": {"coordinates":[108.8436,-7.1668],"type":"Point"}
}