{
  "type": "Feature",
  "properties": {
    "gn:admin1_code":"30.0",
    "gn:asciiname":"Gegernoong",
    "gn:country_code":"ID",
    "gn:dem":374,
    "gn:feature_class":"P",
    "gn:feature_code":"PPLA4",
    "gn:name":"Gegernoong",
    "gn:population":0,
    "gn:timezone":"Asia/Jakarta",
    "iso:country":"ID",
    "name:ind_x_preferred":[
        "Gegernoong"
    ],
    "wof:name":"Gegernoong",
    "wof:placetype":"locality"
},
  "geometry": {"coordinates":[108.2323,-7.3862],"type":"Point"}
}