{
  "type": "Feature",
  "properties": {
    "gn:admin1_code":"26",
    "gn:asciiname":"Bandarrawan",
    "gn:country_code":"ID",
    "gn:dem":97,
    "gn:feature_class":"P",
    "gn:feature_code":"PPL",
    "gn:name":"Bandarrawan",
    "gn:population":0,
    "gn:timezone":"Asia/Jakarta",
    "iso:country":"ID",
    "name:ind_x_preferred":[
        "Bandarrawan"
    ],
    "wof:name":"Bandarrawan",
    "wof:placetype":"locality"
},
  "geometry": {"coordinates":[99.0668,3.1748],"type":"Point"}
}