{
  "type": "Feature",
  "properties": {
    "gn:admin1_code":"30",
    "gn:asciiname":"Mekarbakti",
    "gn:country_code":"ID",
    "gn:dem":696,
    "gn:feature_class":"P",
    "gn:feature_code":"PPL",
    "gn:name":"Mekarbakti",
    "gn:population":0,
    "gn:timezone":"Asia/Jakarta",
    "iso:country":"ID",
    "name:ind_x_preferred":[
        "Mekarbakti"
    ],
    "wof:name":"Mekarbakti",
    "wof:placetype":"locality"
},
  "geometry": {"coordinates":[107.53972,-6.92417],"type":"Point"}
}