{
  "type": "Feature",
  "properties": {
    "gn:admin1_code":"38.0",
    "gn:asciiname":"Boronjong",
    "gn:country_code":"ID",
    "gn:dem":822,
    "gn:feature_class":"P",
    "gn:feature_code":"PPL",
    "gn:name":"Boronjong",
    "gn:population":0,
    "gn:timezone":"Asia/Makassar",
    "iso:country":"ID",
    "name:ind_x_preferred":[
        "Boronjong"
    ],
    "wof:name":"Boronjong",
    "wof:placetype":"locality"
},
  "geometry": {"coordinates":[119.9329,-2.9564],"type":"Point"}
}