{
  "type": "Feature",
  "properties": {
    "gn:admin1_code":"38.0",
    "gn:asciiname":"Setange Dua",
    "gn:country_code":"ID",
    "gn:dem":24,
    "gn:feature_class":"P",
    "gn:feature_code":"PPL",
    "gn:name":"Setange Dua",
    "gn:population":0,
    "gn:timezone":"Asia/Makassar",
    "iso:country":"ID",
    "name:ind_x_preferred":[
        "Setange Dua"
    ],
    "name:und_x_variant":[
        "Setange 2"
    ],
    "wof:name":"Setange Dua",
    "wof:placetype":"locality"
},
  "geometry": {"coordinates":[120.3265,-3.7241],"type":"Point"}
}