{
  "type": "Feature",
  "properties": {
    "gn:admin1_code":"07",
    "gn:asciiname":"Tarukan",
    "gn:country_code":"ID",
    "gn:dem":946,
    "gn:feature_class":"P",
    "gn:feature_code":"PPL",
    "gn:name":"Tarukan",
    "gn:population":0,
    "gn:timezone":"Asia/Jakarta",
    "iso:country":"ID",
    "name:ind_x_preferred":[
        "Tarukan"
    ],
    "name:und_x_variant":[
        "Taruan"
    ],
    "wof:name":"Tarukan",
    "wof:placetype":"locality"
},
  "geometry": {"coordinates":[110.34639,-7.23],"type":"Point"}
}