{
  "type": "Feature",
  "properties": {
    "gn:admin1_code":"30",
    "gn:asciiname":"Pulokukun",
    "gn:country_code":"ID",
    "gn:dem":6,
    "gn:feature_class":"P",
    "gn:feature_code":"PPL",
    "gn:name":"Pulokukun",
    "gn:population":0,
    "gn:timezone":"Asia/Jakarta",
    "iso:country":"ID",
    "name:ind_x_preferred":[
        "Pulokukun"
    ],
    "wof:name":"Pulokukun",
    "wof:placetype":"locality"
},
  "geometry": {"coordinates":[107.18556,-6.15528],"type":"Point"}
}