{
  "type": "Feature",
  "properties": {
    "gn:admin1_code":"8.0",
    "gn:asciiname":"Klabang Selatan",
    "gn:country_code":"ID",
    "gn:dem":277,
    "gn:feature_class":"P",
    "gn:feature_code":"PPL",
    "gn:name":"Klabang Selatan",
    "gn:population":0,
    "gn:timezone":"Asia/Jakarta",
    "iso:country":"ID",
    "name:ind_x_preferred":[
        "Klabang Selatan"
    ],
    "wof:name":"Klabang Selatan",
    "wof:placetype":"locality"
},
  "geometry": {"coordinates":[113.8216,-7.8759],"type":"Point"}
}