{
  "type": "Feature",
  "properties": {
    "gn:admin1_code":"8",
    "gn:asciiname":"Swarubuluroto",
    "gn:country_code":"ID",
    "gn:dem":446,
    "gn:feature_class":"P",
    "gn:feature_code":"PPL",
    "gn:name":"Swarubuluroto",
    "gn:population":0,
    "gn:timezone":"Asia/Jakarta",
    "iso:country":"ID",
    "name:ind_x_preferred":[
        "Swarubuluroto"
    ],
    "wof:name":"Swarubuluroto",
    "wof:placetype":"locality"
},
  "geometry": {"coordinates":[112.2474,-8.0142],"type":"Point"}
}