{
  "type": "Feature",
  "properties": {
    "gn:admin1_code":"8.0",
    "gn:asciiname":"Sonogunting",
    "gn:country_code":"ID",
    "gn:dem":262,
    "gn:feature_class":"P",
    "gn:feature_code":"PPLA4",
    "gn:name":"Sonogunting",
    "gn:population":0,
    "gn:timezone":"Asia/Jakarta",
    "iso:country":"ID",
    "name:ind_x_preferred":[
        "Sonogunting"
    ],
    "wof:name":"Sonogunting",
    "wof:placetype":"locality"
},
  "geometry": {"coordinates":[112.26049999999999,-8.0839],"type":"Point"}
}