{
  "type": "Feature",
  "properties": {
    "gn:admin1_code":"8.0",
    "gn:asciiname":"Madenan",
    "gn:country_code":"ID",
    "gn:dem":50,
    "gn:feature_class":"P",
    "gn:feature_code":"PPL",
    "gn:name":"Madenan",
    "gn:population":0,
    "gn:timezone":"Asia/Jakarta",
    "iso:country":"ID",
    "name:ind_x_preferred":[
        "Madenan"
    ],
    "wof:name":"Madenan",
    "wof:placetype":"locality"
},
  "geometry": {"coordinates":[112.2555,-7.3994],"type":"Point"}
}