{
  "type": "Feature",
  "properties": {
    "gn:admin1_code":"24.0",
    "gn:asciiname":"Air Bangis",
    "gn:country_code":"ID",
    "gn:dem":7,
    "gn:feature_class":"P",
    "gn:feature_code":"PPLA3",
    "gn:name":"Air Bangis",
    "gn:population":0,
    "gn:timezone":"Asia/Jakarta",
    "iso:country":"ID",
    "name:ind_x_preferred":[
        "Air Bangis"
    ],
    "name:und_x_variant":[
        "Ayerbangis",
        "Aibangis",
        "Ajerbangis"
    ],
    "wof:name":"Air Bangis",
    "wof:placetype":"locality"
},
  "geometry": {"coordinates":[99.37985,0.2018],"type":"Point"}
}