{
  "type": "Feature",
  "properties": {
    "gn:admin1_code":"30",
    "gn:asciiname":"Cigangsa",
    "gn:country_code":"ID",
    "gn:dem":306,
    "gn:feature_class":"P",
    "gn:feature_code":"PPL",
    "gn:name":"Cigangsa",
    "gn:population":0,
    "gn:timezone":"Asia/Jakarta",
    "iso:country":"ID",
    "name:ind_x_preferred":[
        "Cigangsa"
    ],
    "name:und_x_variant":[
        "Tjigangsa"
    ],
    "wof:lang_x_official":[
        "ind"
    ],
    "wof:lang_x_spoken":[
        "ind",
        "eng"
    ],
    "wof:name":"Cigangsa",
    "wof:placetype":"locality"
},
  "geometry": {"coordinates":[107.35250000000001,-6.78556],"type":"Point"}
}