{
  "type": "Feature",
  "properties": {
    "gn:admin1_code":"30",
    "gn:asciiname":"Keladi Satu",
    "gn:country_code":"ID",
    "gn:dem":661,
    "gn:feature_class":"P",
    "gn:feature_code":"PPL",
    "gn:name":"Keladi Satu",
    "gn:population":0,
    "gn:timezone":"Asia/Jakarta",
    "iso:country":"ID",
    "name:ind_x_preferred":[
        "Keladi Satu"
    ],
    "wof:name":"Keladi Satu",
    "wof:placetype":"locality"
},
  "geometry": {"coordinates":[106.62194,-6.81833],"type":"Point"}
}