{
  "type": "Feature",
  "properties": {
    "gn:admin1_code":"26",
    "gn:asciiname":"Pondok Ujung Raja",
    "gn:country_code":"ID",
    "gn:dem":438,
    "gn:feature_class":"P",
    "gn:feature_code":"PPL",
    "gn:name":"Pondok Ujung Raja",
    "gn:population":0,
    "gn:timezone":"Asia/Jakarta",
    "iso:country":"ID",
    "name:ind_x_preferred":[
        "Pondok Ujung Raja"
    ],
    "name:und_x_variant":[
        "Udjungradja"
    ],
    "wof:name":"Pondok Ujung Raja",
    "wof:placetype":"locality"
},
  "geometry": {"coordinates":[99.06789999999999,2.8902],"type":"Point"}
}