{
  "type": "Feature",
  "properties": {
    "gn:admin1_code":"7.0",
    "gn:asciiname":"Pagedangan",
    "gn:country_code":"ID",
    "gn:dem":1176,
    "gn:feature_class":"P",
    "gn:feature_code":"PPL",
    "gn:name":"Pagedangan",
    "gn:population":0,
    "gn:timezone":"Asia/Jakarta",
    "iso:country":"ID",
    "name:ind_x_preferred":[
        "Pagedangan"
    ],
    "wof:name":"Pagedangan",
    "wof:placetype":"locality"
},
  "geometry": {"coordinates":[109.85833,-7.28778],"type":"Point"}
}