{
  "type": "Feature",
  "properties": {
    "gn:admin1_code":"7.0",
    "gn:asciiname":"Beran",
    "gn:country_code":"ID",
    "gn:dem":698,
    "gn:feature_class":"P",
    "gn:feature_code":"PPL",
    "gn:name":"Beran",
    "gn:population":0,
    "gn:timezone":"Asia/Jakarta",
    "iso:country":"ID",
    "name:ind_x_preferred":[
        "Beran"
    ],
    "wof:name":"Beran",
    "wof:placetype":"locality"
},
  "geometry": {"coordinates":[109.78028,-7.43222],"type":"Point"}
}