{
  "type": "Feature",
  "properties": {
    "gn:admin1_code":"30.0",
    "gn:asciiname":"Ciherang Satu",
    "gn:country_code":"ID",
    "gn:dem":895,
    "gn:feature_class":"P",
    "gn:feature_code":"PPL",
    "gn:name":"Ciherang Satu",
    "gn:population":0,
    "gn:timezone":"Asia/Jakarta",
    "iso:country":"ID",
    "name:ind_x_preferred":[
        "Ciherang Satu"
    ],
    "wof:name":"Ciherang Satu",
    "wof:placetype":"locality"
},
  "geometry": {"coordinates":[106.965,-7.0158],"type":"Point"}
}