{
  "type": "Feature",
  "properties": {
    "gn:admin1_code":"30",
    "gn:asciiname":"Cigeureung",
    "gn:cc2":"ID",
    "gn:country_code":"ID",
    "gn:dem":19,
    "gn:feature_class":"P",
    "gn:feature_code":"PPL",
    "gn:name":"Cigeureung",
    "gn:population":0,
    "gn:timezone":"Asia/Jakarta",
    "iso:country":"ID",
    "name:und_x_variant":[
        "Tjigeureung",
        "Cigeureung"
    ],
    "wof:name":"Cigeureung",
    "wof:placetype":"locality"
},
  "geometry": {"coordinates":[106.41278,-6.1875],"type":"Point"}
}