{
  "type": "Feature",
  "properties": {
    "gn:admin1_code":"18.0",
    "gn:asciiname":"Rote",
    "gn:country_code":"ID",
    "gn:dem":154,
    "gn:feature_class":"P",
    "gn:feature_code":"PPL",
    "gn:name":"Rote",
    "gn:population":0,
    "gn:timezone":"Asia/Makassar",
    "iso:country":"ID",
    "name:ind_x_preferred":[
        "Rote"
    ],
    "wof:name":"Rote",
    "wof:placetype":"locality"
},
  "geometry": {"coordinates":[124.1268,-9.9415],"type":"Point"}
}