{
  "type": "Feature",
  "properties": {
    "gn:admin1_code":"07",
    "gn:asciiname":"Kedungdowo",
    "gn:country_code":"ID",
    "gn:dem":182,
    "gn:feature_class":"P",
    "gn:feature_code":"PPL",
    "gn:name":"Kedungdowo",
    "gn:population":0,
    "gn:timezone":"Asia/Jakarta",
    "iso:country":"ID",
    "name:und_x_variant":[
        "Kedungdowo 2",
        "Kedungdowo Dua",
        "Kedungdowo"
    ],
    "wof:name":"Kedungdowo",
    "wof:placetype":"locality"
},
  "geometry": {"coordinates":[110.69306,-7.45083],"type":"Point"}
}