{
  "type": "Feature",
  "properties": {
    "gn:admin1_code":"38",
    "gn:asciiname":"Mattanru",
    "gn:country_code":"ID",
    "gn:dem":27,
    "gn:feature_class":"P",
    "gn:feature_code":"PPL",
    "gn:name":"Mattanru",
    "gn:population":0,
    "gn:timezone":"Asia/Makassar",
    "iso:country":"ID",
    "name:ind_x_preferred":[
        "Mattanru"
    ],
    "wof:name":"Mattanru",
    "wof:placetype":"locality"
},
  "geometry": {"coordinates":[119.9832,-4.2926],"type":"Point"}
}