{
  "type": "Feature",
  "properties": {
    "gn:admin1_code":"7.0",
    "gn:asciiname":"Nabin Kulon",
    "gn:country_code":"ID",
    "gn:dem":483,
    "gn:feature_class":"P",
    "gn:feature_code":"PPL",
    "gn:name":"Nabin Kulon",
    "gn:population":0,
    "gn:timezone":"Asia/Jakarta",
    "iso:country":"ID",
    "wof:name":"Nabin Kulon",
    "wof:placetype":"locality"
},
  "geometry": {"coordinates":[110.28028,-7.47583],"type":"Point"}
}