{
  "type": "Feature",
  "properties": {
    "gn:admin1_code":"30",
    "gn:asciiname":"Pondokcing Dua",
    "gn:cc2":"ID",
    "gn:country_code":"ID",
    "gn:dem":75,
    "gn:feature_class":"P",
    "gn:feature_code":"PPL",
    "gn:name":"Pondokcing Dua",
    "gn:population":0,
    "gn:timezone":"Asia/Jakarta",
    "iso:country":"ID",
    "name:und_x_variant":[
        "Pondoktjing Dua",
        "Pondoktjina 2",
        "Pondokcing Dua"
    ],
    "wof:lang_x_official":[
        "ind"
    ],
    "wof:lang_x_spoken":[
        "ind",
        "eng"
    ],
    "wof:name":"Pondokcing Dua",
    "wof:placetype":"locality"
},
  "geometry": {"coordinates":[106.82250000000001,-6.365],"type":"Point"}
}