{
  "type": "Feature",
  "properties": {
    "gn:admin1_code":"7",
    "gn:asciiname":"Kaliurip",
    "gn:country_code":"ID",
    "gn:dem":44,
    "gn:feature_class":"P",
    "gn:feature_code":"PPL",
    "gn:name":"Kaliurip",
    "gn:population":0,
    "gn:timezone":"Asia/Jakarta",
    "iso:country":"ID",
    "name:ind_x_preferred":[
        "Kaliurip"
    ],
    "wof:name":"Kaliurip",
    "wof:placetype":"locality"
},
  "geometry": {"coordinates":[109.89610999999999,-7.65778],"type":"Point"}
}