{
  "type": "Feature",
  "properties": {
    "gn:country":"ID",
    "gn:fcode":"ADM4",
    "gn:pop":0,
    "iso:country":"ID",
    "name:ind_x_preferred":[
        "Desa Rancaputat"
    ],
    "name:unk_x_variant":[
        "Rancaputat"
    ],
    "qs:name":"Desa Rancaputat",
    "qs:photos_9r":0,
    "qs:photos_sr":0,
    "qs:pop_sr":"0",
    "wof:name":"Desa Rancaputat",
    "wof:placetype":"localadmin",
    "wof:population":0
},
  "geometry": {"coordinates":[108.34889,-6.70083],"type":"Point"}
}