{
  "type": "Feature",
  "properties": {
    "gn:admin1_code":"24",
    "gn:asciiname":"Cibadakjambu",
    "gn:country_code":"ID",
    "gn:dem":667,
    "gn:feature_class":"P",
    "gn:feature_code":"PPL",
    "gn:name":"Cibadakjambu",
    "gn:population":0,
    "gn:timezone":"Asia/Jakarta",
    "iso:country":"ID",
    "name:ind_x_preferred":[
        "Cibadakjambu"
    ],
    "wof:name":"Cibadakjambu",
    "wof:placetype":"locality"
},
  "geometry": {"coordinates":[99.9696,0.3241],"type":"Point"}
}