{
  "type": "Feature",
  "properties": {
    "gn:admin1_code":"31.0",
    "gn:asciiname":"Lia",
    "gn:country_code":"ID",
    "gn:dem":50,
    "gn:feature_class":"P",
    "gn:feature_code":"PPL",
    "gn:name":"Lia",
    "gn:population":0,
    "gn:timezone":"Asia/Makassar",
    "iso:country":"ID",
    "name:ces_x_preferred":[
        "Lia"
    ],
    "name:deu_x_preferred":[
        "Lia"
    ],
    "name:est_x_preferred":[
        "Lia"
    ],
    "name:ind_x_preferred":[
        "Lia"
    ],
    "name:ita_x_preferred":[
        "Lia"
    ],
    "name:nor_x_preferred":[
        "Lia"
    ],
    "name:ron_x_preferred":[
        "Lia"
    ],
    "name:swe_x_preferred":[
        "Lia"
    ],
    "wof:lang_x_official":[
        "ind"
    ],
    "wof:lang_x_spoken":[
        "ind",
        "eng"
    ],
    "wof:name":"Lia",
    "wof:placetype":"locality"
},
  "geometry": {"coordinates":[125.4464,2.7871],"type":"Point"}
}