{
  "type": "Feature",
  "properties": {
    "gn:admin1_code":"36",
    "gn:asciiname":"Testega",
    "gn:country_code":"ID",
    "gn:dem":1893,
    "gn:feature_class":"P",
    "gn:feature_code":"PPL",
    "gn:name":"Testega",
    "gn:population":0,
    "gn:timezone":"Asia/Jayapura",
    "iso:country":"ID",
    "wof:name":"Testega",
    "wof:placetype":"locality"
},
  "geometry": {"coordinates":[133.94085000000001,-1.38071],"type":"Point"}
}