{
  "type": "Feature",
  "properties": {
    "gn:admin1_code":"18.0",
    "gn:asciiname":"Ledekenjaka",
    "gn:country_code":"ID",
    "gn:dem":177,
    "gn:feature_class":"P",
    "gn:feature_code":"PPL",
    "gn:name":"Ledekenjaka",
    "gn:population":0,
    "gn:timezone":"Asia/Makassar",
    "iso:country":"ID",
    "name:ind_x_preferred":[
        "Ledekenjaka"
    ],
    "wof:name":"Ledekenjaka",
    "wof:placetype":"locality"
},
  "geometry": {"coordinates":[121.8807,-10.5284],"type":"Point"}
}