{
  "type": "Feature",
  "properties": {
    "gn:admin1_code":"7",
    "gn:asciiname":"Turus Timur",
    "gn:country_code":"ID",
    "gn:dem":122,
    "gn:feature_class":"P",
    "gn:feature_code":"PPL",
    "gn:name":"Turus Timur",
    "gn:population":0,
    "gn:timezone":"Asia/Jakarta",
    "iso:country":"ID",
    "name:ind_x_preferred":[
        "Turus Timur"
    ],
    "wof:name":"Turus Timur",
    "wof:placetype":"locality"
},
  "geometry": {"coordinates":[109.95056,-7.64778],"type":"Point"}
}