{
  "type": "Feature",
  "properties": {
    "gn:admin1_code":"7.0",
    "gn:asciiname":"Ngadirejo",
    "gn:country_code":"ID",
    "gn:dem":264,
    "gn:feature_class":"P",
    "gn:feature_code":"PPL",
    "gn:name":"Ngadirejo",
    "gn:population":0,
    "gn:timezone":"Asia/Jakarta",
    "iso:country":"ID",
    "wof:name":"Ngadirejo",
    "wof:placetype":"locality"
},
  "geometry": {"coordinates":[110.98667,-7.65028],"type":"Point"}
}