{
  "type": "Feature",
  "properties": {
    "gn:admin1_code":"21",
    "gn:asciiname":"Sayambongin",
    "gn:country_code":"ID",
    "gn:dem":7,
    "gn:feature_class":"P",
    "gn:feature_code":"PPL",
    "gn:name":"Sayambongin",
    "gn:population":0,
    "gn:timezone":"Asia/Makassar",
    "iso:country":"ID",
    "name:ind_x_preferred":[
        "Sayambongin"
    ],
    "wof:name":"Sayambongin",
    "wof:placetype":"locality"
},
  "geometry": {"coordinates":[122.71550000000001,-1.1115],"type":"Point"}
}