{
  "type": "Feature",
  "properties": {
    "gn:admin1_code":"7",
    "gn:asciiname":"Legundi",
    "gn:country_code":"ID",
    "gn:dem":40,
    "gn:feature_class":"P",
    "gn:feature_code":"PPL",
    "gn:name":"Legundi",
    "gn:population":0,
    "gn:timezone":"Asia/Jakarta",
    "iso:country":"ID",
    "name:ind_x_preferred":[
        "Legundi"
    ],
    "wof:name":"Legundi",
    "wof:placetype":"locality"
},
  "geometry": {"coordinates":[110.99222,-7.125],"type":"Point"}
}