{
  "type": "Feature",
  "properties": {
    "gn:admin1_code":"15.0",
    "gn:asciiname":"Negeri Batin",
    "gn:country_code":"ID",
    "gn:dem":142,
    "gn:feature_class":"P",
    "gn:feature_code":"PPL",
    "gn:name":"Negeri Batin",
    "gn:population":0,
    "gn:timezone":"Asia/Jakarta",
    "iso:country":"ID",
    "name:ind_x_preferred":[
        "Negeri Batin"
    ],
    "wof:name":"Negeri Batin",
    "wof:placetype":"locality"
},
  "geometry": {"coordinates":[104.4971,-4.62306],"type":"Point"}
}