{
  "type": "Feature",
  "properties": {
    "gn:admin1_code":"7.0",
    "gn:asciiname":"Gatak",
    "gn:country_code":"ID",
    "gn:dem":289,
    "gn:feature_class":"P",
    "gn:feature_code":"PPL",
    "gn:name":"Gatak",
    "gn:population":0,
    "gn:timezone":"Asia/Jakarta",
    "iso:country":"ID",
    "wof:name":"Gatak",
    "wof:placetype":"locality"
},
  "geometry": {"coordinates":[110.61917,-7.60417],"type":"Point"}
}