{
  "type": "Feature",
  "properties": {
    "gn:admin1_code":"30",
    "gn:asciiname":"Depok",
    "gn:country_code":"ID",
    "gn:dem":464,
    "gn:feature_class":"P",
    "gn:feature_code":"PPL",
    "gn:name":"Depok",
    "gn:population":0,
    "gn:timezone":"Asia/Jakarta",
    "iso:country":"ID",
    "name:ind_x_preferred":[
        "Depok"
    ],
    "wof:name":"Depok",
    "wof:placetype":"locality"
},
  "geometry": {"coordinates":[106.73972000000001,-6.81861],"type":"Point"}
}