{
  "type": "Feature",
  "properties": {
    "gn:admin1_code":"17.0",
    "gn:asciiname":"Montongserubuh",
    "gn:country_code":"ID",
    "gn:dem":235,
    "gn:feature_class":"P",
    "gn:feature_code":"PPL",
    "gn:name":"Montongserubuh",
    "gn:population":0,
    "gn:timezone":"Asia/Makassar",
    "iso:country":"ID",
    "name:ind_x_preferred":[
        "Montongserubuh"
    ],
    "wof:name":"Montongserubuh",
    "wof:placetype":"locality"
},
  "geometry": {"coordinates":[116.438,-8.2694],"type":"Point"}
}