{
  "type": "Feature",
  "properties": {
    "gn:admin1_code":"30",
    "gn:asciiname":"Pojok Selatan",
    "gn:country_code":"ID",
    "gn:dem":745,
    "gn:feature_class":"P",
    "gn:feature_code":"PPL",
    "gn:name":"Pojok Selatan",
    "gn:population":0,
    "gn:timezone":"Asia/Jakarta",
    "iso:country":"ID",
    "name:ind_x_preferred":[
        "Pojok Selatan"
    ],
    "wof:name":"Pojok Selatan",
    "wof:placetype":"locality"
},
  "geometry": {"coordinates":[107.53417,-6.87833],"type":"Point"}
}