{
  "type": "Feature",
  "properties": {
    "gn:admin1_code":"8.0",
    "gn:asciiname":"Panggungpucung Timur",
    "gn:country_code":"ID",
    "gn:dem":187,
    "gn:feature_class":"P",
    "gn:feature_code":"PPL",
    "gn:name":"Panggungpucung Timur",
    "gn:population":0,
    "gn:timezone":"Asia/Jakarta",
    "iso:country":"ID",
    "name:ind_x_preferred":[
        "Panggungpucung Timur"
    ],
    "name:und_x_variant":[
        "Panggoengpoetjoeng"
    ],
    "wof:lang_x_official":[
        "ind"
    ],
    "wof:lang_x_spoken":[
        "ind",
        "eng"
    ],
    "wof:name":"Panggungpucung Timur",
    "wof:placetype":"locality"
},
  "geometry": {"coordinates":[112.0179,-8.2801],"type":"Point"}
}