{
  "type": "Feature",
  "properties": {
    "gn:admin1_code":"07",
    "gn:asciiname":"Wonodadi",
    "gn:country_code":"ID",
    "gn:dem":827,
    "gn:feature_class":"P",
    "gn:feature_code":"PPL",
    "gn:name":"Wonodadi",
    "gn:population":0,
    "gn:timezone":"Asia/Jakarta",
    "iso:country":"ID",
    "wof:name":"Wonodadi",
    "wof:placetype":"locality"
},
  "geometry": {"coordinates":[110.52,-7.56167],"type":"Point"}
}