{
  "type": "Feature",
  "properties": {
    "gn:admin1_code":"8",
    "gn:asciiname":"Wates Lor",
    "gn:country_code":"ID",
    "gn:dem":30,
    "gn:feature_class":"P",
    "gn:feature_code":"PPL",
    "gn:name":"Wates Lor",
    "gn:population":0,
    "gn:timezone":"Asia/Jakarta",
    "iso:country":"ID",
    "name:ind_x_preferred":[
        "Wates Lor"
    ],
    "wof:name":"Wates Lor",
    "wof:placetype":"locality"
},
  "geometry": {"coordinates":[112.3793,-7.5001],"type":"Point"}
}