{
  "type": "Feature",
  "properties": {
    "gn:admin1_code":"38.0",
    "gn:asciiname":"Kanna",
    "gn:country_code":"ID",
    "gn:dem":501,
    "gn:feature_class":"P",
    "gn:feature_code":"PPL",
    "gn:name":"Kanna",
    "gn:population":0,
    "gn:timezone":"Asia/Makassar",
    "iso:country":"ID",
    "name:ind_x_preferred":[
        "Kanna"
    ],
    "wof:name":"Kanna",
    "wof:placetype":"locality"
},
  "geometry": {"coordinates":[120.0566,-3.2326],"type":"Point"}
}