{
  "type": "Feature",
  "properties": {
    "gn:admin1_code":"38.0",
    "gn:asciiname":"Kanna",
    "gn:country_code":"ID",
    "gn:dem":501,
    "gn:feature_class":"P",
    "gn:feature_code":"PPL",
    "gn:name":"Kanna",
    "gn:population":0,
    "gn:timezone":"Asia/Makassar",
    "iso:country":"ID",
    "name:ceb_x_preferred":[
        "Kanna"
    ],
    "name:est_x_preferred":[
        "Kanna"
    ],
    "name:ind_x_preferred":[
        "Kanna"
    ],
    "name:ita_x_preferred":[
        "Kanna"
    ],
    "name:jpn_x_preferred":[
        "\u304b\u3093\u306a"
    ],
    "name:kat_x_preferred":[
        "\u10d9\u10d0\u10dc\u10d0"
    ],
    "name:kaz_x_preferred":[
        "\u041a\u0430\u043d\u043d\u0430"
    ],
    "name:nld_x_preferred":[
        "Kanna"
    ],
    "name:rus_x_preferred":[
        "\u041a\u0430\u043d\u043d\u0430"
    ],
    "name:spa_x_preferred":[
        "Kanna"
    ],
    "name:swe_x_preferred":[
        "Kanna"
    ],
    "name:ukr_x_preferred":[
        "\u041a\u0430\u043d\u043d\u0430"
    ],
    "wof:name":"Kanna",
    "wof:placetype":"locality"
},
  "geometry": {"coordinates":[120.0566,-3.2326],"type":"Point"}
}