{
  "type": "Feature",
  "properties": {
    "gn:admin1_code":"30.0",
    "gn:asciiname":"Cikancra",
    "gn:country_code":"ID",
    "gn:dem":78,
    "gn:feature_class":"P",
    "gn:feature_code":"PPLA4",
    "gn:name":"Cikancra",
    "gn:population":0,
    "gn:timezone":"Asia/Jakarta",
    "iso:country":"ID",
    "name:ind_x_preferred":[
        "Cikancra"
    ],
    "name:und_x_variant":[
        "Tjikantjra 3"
    ],
    "wof:name":"Cikancra",
    "wof:placetype":"locality"
},
  "geometry": {"coordinates":[108.211,-7.7527],"type":"Point"}
}