{
  "type": "Feature",
  "properties": {
    "gn:admin1_code":"30.0",
    "gn:asciiname":"Ciawitali",
    "gn:country_code":"ID",
    "gn:dem":452,
    "gn:feature_class":"P",
    "gn:feature_code":"PPL",
    "gn:name":"Ciawitali",
    "gn:population":0,
    "gn:timezone":"Asia/Jakarta",
    "iso:country":"ID",
    "name:ind_x_preferred":[
        "Ciawitali"
    ],
    "name:und_x_variant":[
        "Tjiawitali"
    ],
    "wof:lang_x_official":[
        "ind"
    ],
    "wof:lang_x_spoken":[
        "ind",
        "eng"
    ],
    "wof:name":"Ciawitali",
    "wof:placetype":"locality"
},
  "geometry": {"coordinates":[108.4165,-7.0828],"type":"Point"}
}