{
  "type": "Feature",
  "properties": {
    "gn:admin1_code":"8.0",
    "gn:asciiname":"Bibit",
    "gn:country_code":"ID",
    "gn:dem":310,
    "gn:feature_class":"P",
    "gn:feature_code":"PPL",
    "gn:name":"Bibit",
    "gn:population":0,
    "gn:timezone":"Asia/Jakarta",
    "iso:country":"ID",
    "name:ind_x_preferred":[
        "Bibit"
    ],
    "wof:name":"Bibit",
    "wof:placetype":"locality"
},
  "geometry": {"coordinates":[111.15083,-8.25694],"type":"Point"}
}