{
  "type": "Feature",
  "properties": {
    "gn:admin1_code":"1",
    "gn:asciiname":"Suak Tring",
    "gn:country_code":"ID",
    "gn:dem":14,
    "gn:feature_class":"P",
    "gn:feature_code":"PPL",
    "gn:name":"Suak Tring",
    "gn:population":0,
    "gn:timezone":"Asia/Jakarta",
    "iso:country":"ID",
    "name:ind_x_preferred":[
        "Suak Tring"
    ],
    "wof:name":"Suak Tring",
    "wof:placetype":"locality"
},
  "geometry": {"coordinates":[96.09569999999999,4.3489],"type":"Point"}
}