{
  "type": "Feature",
  "properties": {
    "gn:admin1_code":"26",
    "gn:asciiname":"Parandolok",
    "gn:country_code":"ID",
    "gn:dem":748,
    "gn:feature_class":"P",
    "gn:feature_code":"PPL",
    "gn:name":"Parandolok",
    "gn:population":0,
    "gn:timezone":"Asia/Jakarta",
    "iso:country":"ID",
    "name:ind_x_preferred":[
        "Parandolok"
    ],
    "wof:name":"Parandolok",
    "wof:placetype":"locality"
},
  "geometry": {"coordinates":[99.24827000000001,1.47997],"type":"Point"}
}