{
  "type": "Feature",
  "properties": {
    "gn:admin1_code":"8.0",
    "gn:asciiname":"Buwek",
    "gn:country_code":"ID",
    "gn:dem":209,
    "gn:feature_class":"P",
    "gn:feature_code":"PPL",
    "gn:name":"Buwek",
    "gn:population":0,
    "gn:timezone":"Asia/Jakarta",
    "iso:country":"ID",
    "name:ind_x_preferred":[
        "Buwek"
    ],
    "name:und_x_variant":[
        "Boewek"
    ],
    "wof:lang_x_official":[
        "ind"
    ],
    "wof:lang_x_spoken":[
        "ind",
        "eng"
    ],
    "wof:name":"Buwek",
    "wof:placetype":"locality"
},
  "geometry": {"coordinates":[113.2734,-8.014],"type":"Point"}
}