{
  "type": "Feature",
  "properties": {
    "gn:admin1_code":"07",
    "gn:asciiname":"Soko",
    "gn:country_code":"ID",
    "gn:dem":706,
    "gn:feature_class":"P",
    "gn:feature_code":"PPL",
    "gn:name":"Soko",
    "gn:population":0,
    "gn:timezone":"Asia/Jakarta",
    "iso:country":"ID",
    "name:bos_x_preferred":[
        "Soko"
    ],
    "name:ceb_x_preferred":[
        "Soko"
    ],
    "name:fra_x_preferred":[
        "Soko"
    ],
    "name:heb_x_preferred":[
        "\u05e1\u05d5\u05e7\u05d5"
    ],
    "name:mlg_x_preferred":[
        "Soko"
    ],
    "name:nld_x_preferred":[
        "Soko"
    ],
    "name:pol_x_preferred":[
        "Soko"
    ],
    "name:spa_x_preferred":[
        "Soko"
    ],
    "name:swe_x_preferred":[
        "Soko"
    ],
    "name:und_x_variant":[
        "Soka",
        "Soko"
    ],
    "wof:name":"Soko",
    "wof:placetype":"locality"
},
  "geometry": {"coordinates":[110.34332999999999,-7.35694],"type":"Point"}
}