{
  "type": "Feature",
  "properties": {
    "gn:admin1_code":"38",
    "gn:asciiname":"Komba",
    "gn:country_code":"ID",
    "gn:dem":1116,
    "gn:feature_class":"P",
    "gn:feature_code":"PPL",
    "gn:name":"Komba",
    "gn:population":0,
    "gn:timezone":"Asia/Makassar",
    "iso:country":"ID",
    "name:ceb_x_preferred":[
        "Komba"
    ],
    "name:ces_x_preferred":[
        "Komba"
    ],
    "name:deu_x_preferred":[
        "Komba"
    ],
    "name:fra_x_preferred":[
        "Komba"
    ],
    "name:ind_x_preferred":[
        "Komba"
    ],
    "name:nld_x_preferred":[
        "Komba"
    ],
    "name:spa_x_preferred":[
        "Komba"
    ],
    "name:swe_x_preferred":[
        "Komba"
    ],
    "wof:lang_x_official":[
        "ind"
    ],
    "wof:lang_x_spoken":[
        "ind",
        "eng"
    ],
    "wof:name":"Komba",
    "wof:placetype":"locality"
},
  "geometry": {"coordinates":[119.9679,-2.5637],"type":"Point"}
}