{
  "type": "Feature",
  "properties": {
    "gn:admin1_code":"22.0",
    "gn:asciiname":"Wawowonua",
    "gn:country_code":"ID",
    "gn:dem":28,
    "gn:feature_class":"P",
    "gn:feature_code":"PPL",
    "gn:name":"Wawowonua",
    "gn:population":0,
    "gn:timezone":"Asia/Makassar",
    "iso:country":"ID",
    "name:ind_x_preferred":[
        "Wawowonua"
    ],
    "wof:name":"Wawowonua",
    "wof:placetype":"locality"
},
  "geometry": {"coordinates":[122.44,-4.3073],"type":"Point"}
}