{
  "type": "Feature",
  "properties": {
    "gn:admin1_code":"7",
    "gn:asciiname":"Bulakrejo",
    "gn:country_code":"ID",
    "gn:dem":546,
    "gn:feature_class":"P",
    "gn:feature_code":"PPL",
    "gn:name":"Bulakrejo",
    "gn:population":0,
    "gn:timezone":"Asia/Jakarta",
    "iso:country":"ID",
    "name:ind_x_preferred":[
        "Bulakrejo"
    ],
    "wof:name":"Bulakrejo",
    "wof:placetype":"locality"
},
  "geometry": {"coordinates":[111.14749999999999,-7.53333],"type":"Point"}
}