{
  "type": "Feature",
  "properties": {
    "gn:admin1_code":"33.0",
    "gn:asciiname":"Cigoler",
    "gn:country_code":"ID",
    "gn:dem":560,
    "gn:feature_class":"P",
    "gn:feature_code":"PPL",
    "gn:name":"Cigoler",
    "gn:population":0,
    "gn:timezone":"Asia/Jakarta",
    "iso:country":"ID",
    "name:ind_x_preferred":[
        "Cigoler"
    ],
    "wof:name":"Cigoler",
    "wof:placetype":"locality"
},
  "geometry": {"coordinates":[106.1555,-6.6764],"type":"Point"}
}