{
  "type": "Feature",
  "properties": {
    "gn:admin1_code":"18",
    "gn:asciiname":"Nanu",
    "gn:country_code":"ID",
    "gn:dem":389,
    "gn:feature_class":"P",
    "gn:feature_code":"PPL",
    "gn:name":"Nanu",
    "gn:population":0,
    "gn:timezone":"Asia/Makassar",
    "iso:country":"ID",
    "name:deu_x_preferred":[
        "Nanu"
    ],
    "name:ind_x_preferred":[
        "Nanu"
    ],
    "wof:lang_x_official":[
        "ind"
    ],
    "wof:lang_x_spoken":[
        "ind",
        "eng"
    ],
    "wof:name":"Nanu",
    "wof:placetype":"locality"
},
  "geometry": {"coordinates":[120.38039999999999,-8.418],"type":"Point"}
}