{
  "type": "Feature",
  "properties": {
    "gn:admin1_code":"30",
    "gn:asciiname":"Sukamenak Kaler",
    "gn:cc2":"ID",
    "gn:country_code":"ID",
    "gn:dem":1447,
    "gn:feature_class":"P",
    "gn:feature_code":"PPL",
    "gn:name":"Sukamenak Kaler",
    "gn:population":0,
    "gn:timezone":"Asia/Jakarta",
    "iso:country":"ID",
    "name:und_x_variant":[
        "Sukamenak",
        "Sukamenak Kaler"
    ],
    "wof:lang_x_official":[
        "ind"
    ],
    "wof:lang_x_spoken":[
        "ind",
        "eng"
    ],
    "wof:name":"Sukamenak Kaler",
    "wof:placetype":"locality"
},
  "geometry": {"coordinates":[107.58056000000001,-7.18417],"type":"Point"}
}