{
  "type": "Feature",
  "properties": {
    "gn:admin1_code":"24",
    "gn:asciiname":"Bukit",
    "gn:country_code":"ID",
    "gn:dem":869,
    "gn:feature_class":"P",
    "gn:feature_code":"PPL",
    "gn:name":"Bukit",
    "gn:population":0,
    "gn:timezone":"Asia/Jakarta",
    "iso:country":"ID",
    "name:ind_x_preferred":[
        "Bukit"
    ],
    "wof:name":"Bukit",
    "wof:placetype":"locality"
},
  "geometry": {"coordinates":[100.27656,-0.40692],"type":"Point"}
}