{
  "type": "Feature",
  "properties": {
    "gn:admin1_code":"26",
    "gn:asciiname":"Lumbansibohot",
    "gn:country_code":"ID",
    "gn:dem":536,
    "gn:feature_class":"P",
    "gn:feature_code":"PPL",
    "gn:name":"Lumbansibohot",
    "gn:population":0,
    "gn:timezone":"Asia/Jakarta",
    "iso:country":"ID",
    "name:ind_x_preferred":[
        "Lumbansibohot"
    ],
    "wof:name":"Lumbansibohot",
    "wof:placetype":"locality"
},
  "geometry": {"coordinates":[99.0378,2.8721],"type":"Point"}
}