{
  "type": "Feature",
  "properties": {
    "gn:admin1_code":"38",
    "gn:asciiname":"Kampungtenga",
    "gn:country_code":"ID",
    "gn:dem":6,
    "gn:feature_class":"P",
    "gn:feature_code":"PPL",
    "gn:name":"Kampungtenga",
    "gn:population":0,
    "gn:timezone":"Asia/Makassar",
    "iso:country":"ID",
    "name:ind_x_preferred":[
        "Kampungtenga"
    ],
    "wof:name":"Kampungtenga",
    "wof:placetype":"locality"
},
  "geometry": {"coordinates":[120.36369999999999,-5.3287],"type":"Point"}
}