{
  "type": "Feature",
  "properties": {
    "gn:admin1_code":"30",
    "gn:asciiname":"Cibuyutan",
    "gn:country_code":"ID",
    "gn:dem":279,
    "gn:feature_class":"P",
    "gn:feature_code":"PPL",
    "gn:name":"Cibuyutan",
    "gn:population":0,
    "gn:timezone":"Asia/Jakarta",
    "iso:country":"ID",
    "name:ind_x_preferred":[
        "Cibuyutan"
    ],
    "wof:name":"Cibuyutan",
    "wof:placetype":"locality"
},
  "geometry": {"coordinates":[107.15000000000001,-6.66778],"type":"Point"}
}