{
  "type": "Feature",
  "properties": {
    "gn:admin1_code":"26",
    "gn:asciiname":"Terjun Tiga",
    "gn:country_code":"ID",
    "gn:dem":7,
    "gn:feature_class":"P",
    "gn:feature_code":"PPL",
    "gn:name":"Terjun Tiga",
    "gn:population":0,
    "gn:timezone":"Asia/Jakarta",
    "iso:country":"ID",
    "name:ind_x_preferred":[
        "Terjun Tiga"
    ],
    "name:und_x_variant":[
        "Terdjun 3"
    ],
    "wof:name":"Terjun Tiga",
    "wof:placetype":"locality"
},
  "geometry": {"coordinates":[98.6386,3.6973],"type":"Point"}
}