{
  "type": "Feature",
  "properties": {
    "gn:admin1_code":"26",
    "gn:asciiname":"Sinapunapu",
    "gn:country_code":"ID",
    "gn:dem":1405,
    "gn:feature_class":"P",
    "gn:feature_code":"PPL",
    "gn:name":"Sinapunapu",
    "gn:population":0,
    "gn:timezone":"Asia/Jakarta",
    "iso:country":"ID",
    "name:ind_x_preferred":[
        "Sinapunapu"
    ],
    "wof:name":"Sinapunapu",
    "wof:placetype":"locality"
},
  "geometry": {"coordinates":[98.87260000000001,2.1311],"type":"Point"}
}