{
  "type": "Feature",
  "properties": {
    "gn:admin1_code":"7.0",
    "gn:asciiname":"Palemgede",
    "gn:country_code":"ID",
    "gn:dem":42,
    "gn:feature_class":"P",
    "gn:feature_code":"PPLA4",
    "gn:name":"Palemgede",
    "gn:population":0,
    "gn:timezone":"Asia/Jakarta",
    "iso:country":"ID",
    "name:ind_x_preferred":[
        "Palemgede"
    ],
    "wof:name":"Palemgede",
    "wof:placetype":"locality"
},
  "geometry": {"coordinates":[111.17919999999999,-6.8314],"type":"Point"}
}