{
  "type": "Feature",
  "properties": {
    "gn:admin1_code":"08",
    "gn:asciiname":"Jatirejoso",
    "gn:cc2":"ID",
    "gn:country_code":"ID",
    "gn:dem":359,
    "gn:feature_class":"P",
    "gn:feature_code":"PPL",
    "gn:name":"Jatirejoso",
    "gn:population":0,
    "gn:timezone":"Asia/Jakarta",
    "iso:country":"ID",
    "name:und_x_variant":[
        "Djatiredjoso",
        "Jatirejoso"
    ],
    "wof:lang_x_official":[
        "ind"
    ],
    "wof:lang_x_spoken":[
        "ind",
        "eng"
    ],
    "wof:name":"Jatirejoso",
    "wof:placetype":"locality"
},
  "geometry": {"coordinates":[112.57444,-8.10694],"type":"Point"}
}