{
  "type": "Feature",
  "properties": {
    "gn:admin1_code":"8",
    "gn:asciiname":"Tiron",
    "gn:country_code":"ID",
    "gn:dem":61,
    "gn:feature_class":"P",
    "gn:feature_code":"PPL",
    "gn:name":"Tiron",
    "gn:population":0,
    "gn:timezone":"Asia/Jakarta",
    "iso:country":"ID",
    "name:deu_x_preferred":[
        "Tiron"
    ],
    "name:fra_x_preferred":[
        "Tiron"
    ],
    "name:ind_x_preferred":[
        "Tiron"
    ],
    "name:nld_x_preferred":[
        "Tiron"
    ],
    "name:ron_x_preferred":[
        "Tiron"
    ],
    "name:spa_x_preferred":[
        "Tir\u00f3n"
    ],
    "wof:lang_x_official":[
        "ind"
    ],
    "wof:lang_x_spoken":[
        "ind",
        "eng"
    ],
    "wof:name":"Tiron",
    "wof:placetype":"locality"
},
  "geometry": {"coordinates":[111.5416,-7.5836],"type":"Point"}
}