{
  "type": "Feature",
  "properties": {
    "gn:admin1_code":"8.0",
    "gn:asciiname":"Ngijo",
    "gn:country_code":"ID",
    "gn:dem":112,
    "gn:feature_class":"P",
    "gn:feature_code":"PPL",
    "gn:name":"Ngijo",
    "gn:population":0,
    "gn:timezone":"Asia/Jakarta",
    "iso:country":"ID",
    "name:ind_x_preferred":[
        "Ngijo"
    ],
    "wof:name":"Ngijo",
    "wof:placetype":"locality"
},
  "geometry": {"coordinates":[111.4743,-7.9768],"type":"Point"}
}