{
  "type": "Feature",
  "properties": {
    "gn:admin1_code":"33.0",
    "gn:asciiname":"Cicurug",
    "gn:country_code":"ID",
    "gn:dem":208,
    "gn:feature_class":"P",
    "gn:feature_code":"PPL",
    "gn:name":"Cicurug",
    "gn:population":0,
    "gn:timezone":"Asia/Jakarta",
    "iso:country":"ID",
    "name:ind_x_preferred":[
        "Cicurug"
    ],
    "name:jav_x_preferred":[
        "Cicurug"
    ],
    "name:mlg_x_preferred":[
        "Cicurug"
    ],
    "name:nld_x_preferred":[
        "Cicurug"
    ],
    "name:sun_x_preferred":[
        "Cicurug"
    ],
    "wof:name":"Cicurug",
    "wof:placetype":"locality"
},
  "geometry": {"coordinates":[105.6524,-6.7373],"type":"Point"}
}