{
  "type": "Feature",
  "properties": {
    "gn:admin1_code":"15.0",
    "gn:asciiname":"Ketapang",
    "gn:country_code":"ID",
    "gn:dem":48,
    "gn:feature_class":"P",
    "gn:feature_code":"PPLA3",
    "gn:name":"Ketapang",
    "gn:population":0,
    "gn:timezone":"Asia/Jakarta",
    "iso:country":"ID",
    "name:ind_x_preferred":[
        "Ketapang"
    ],
    "name:und_x_variant":[
        "Umbulan Ketapang",
        "Umbulanketibung"
    ],
    "wof:name":"Ketapang",
    "wof:placetype":"locality"
},
  "geometry": {"coordinates":[104.79953999999999,-4.71335],"type":"Point"}
}