{
  "type": "Feature",
  "properties": {
    "gn:admin1_code":"15.0",
    "gn:asciiname":"Ketapang",
    "gn:country_code":"ID",
    "gn:dem":48,
    "gn:feature_class":"P",
    "gn:feature_code":"PPLA3",
    "gn:name":"Ketapang",
    "gn:population":0,
    "gn:timezone":"Asia/Jakarta",
    "iso:country":"ID",
    "name:ara_x_preferred":[
        "\u0643\u064a\u062a\u0627\u0628\u0627\u0646\u063a"
    ],
    "name:fas_x_preferred":[
        "\u06a9\u062a\u0627\u067e\u0646\u06af"
    ],
    "name:fra_x_preferred":[
        "Ketapang"
    ],
    "name:ind_x_preferred":[
        "Ketapang"
    ],
    "name:lit_x_preferred":[
        "Ketapangas"
    ],
    "name:nor_x_preferred":[
        "Ketapang"
    ],
    "name:rus_x_preferred":[
        "\u041a\u0435\u0442\u0430\u043f\u0430\u043d\u0433"
    ],
    "name:und_x_variant":[
        "Umbulan Ketapang",
        "Umbulanketibung"
    ],
    "name:vie_x_preferred":[
        "Ketapang"
    ],
    "wof:lang_x_official":[
        "ind"
    ],
    "wof:lang_x_spoken":[
        "ind",
        "eng"
    ],
    "wof:name":"Ketapang",
    "wof:placetype":"locality"
},
  "geometry": {"coordinates":[104.79953999999999,-4.71335],"type":"Point"}
}