{
  "type": "Feature",
  "properties": {
    "gn:admin1_code":"1",
    "gn:asciiname":"Jurong",
    "gn:country_code":"ID",
    "gn:dem":15,
    "gn:feature_class":"P",
    "gn:feature_code":"PPL",
    "gn:name":"Jurong",
    "gn:population":0,
    "gn:timezone":"Asia/Jakarta",
    "iso:country":"ID",
    "name:deu_x_preferred":[
        "Jurong"
    ],
    "name:hin_x_preferred":[
        "\u091c\u094d\u092f\u0942\u0930\u0949\u0902\u0917"
    ],
    "name:ind_x_preferred":[
        "Jurong"
    ],
    "name:ita_x_preferred":[
        "Jurong"
    ],
    "name:jpn_x_preferred":[
        "\u30b8\u30e5\u30ed\u30f3"
    ],
    "name:mar_x_preferred":[
        "\u091c\u0941\u0930\u093e\u0901\u0917"
    ],
    "name:msa_x_preferred":[
        "Jurong"
    ],
    "name:por_x_preferred":[
        "Jurong"
    ],
    "name:tgl_x_preferred":[
        "Jurong"
    ],
    "name:tha_x_preferred":[
        "\u0e08\u0e39\u0e23\u0e07"
    ],
    "wof:lang_x_official":[
        "ind"
    ],
    "wof:lang_x_spoken":[
        "ind",
        "eng"
    ],
    "wof:name":"Jurong",
    "wof:placetype":"locality"
},
  "geometry": {"coordinates":[95.9524,5.3345],"type":"Point"}
}