{
  "type": "Feature",
  "properties": {
    "gn:admin1_code":"1",
    "gn:asciiname":"Rot Teungoh",
    "gn:country_code":"ID",
    "gn:dem":14,
    "gn:feature_class":"P",
    "gn:feature_code":"PPL",
    "gn:name":"Rot Teungoh",
    "gn:population":0,
    "gn:timezone":"Asia/Jakarta",
    "iso:country":"ID",
    "name:ind_x_preferred":[
        "Rot Teungoh"
    ],
    "wof:name":"Rot Teungoh",
    "wof:placetype":"locality"
},
  "geometry": {"coordinates":[97.0558,3.4841],"type":"Point"}
}