{
  "type": "Feature",
  "properties": {
    "gn:admin1_code":"30",
    "gn:asciiname":"Lebak Bitung",
    "gn:country_code":"ID",
    "gn:dem":916,
    "gn:feature_class":"P",
    "gn:feature_code":"PPL",
    "gn:name":"Lebak Bitung",
    "gn:population":0,
    "gn:timezone":"Asia/Jakarta",
    "iso:country":"ID",
    "name:ind_x_preferred":[
        "Lebak Bitung"
    ],
    "wof:name":"Lebak Bitung",
    "wof:placetype":"locality"
},
  "geometry": {"coordinates":[108.36221999999999,-6.84806],"type":"Point"}
}