{
  "type": "Feature",
  "properties": {
    "gn:admin1_code":"30.0",
    "gn:asciiname":"Wangun",
    "gn:country_code":"ID",
    "gn:dem":1055,
    "gn:feature_class":"P",
    "gn:feature_code":"PPLA4",
    "gn:name":"Wangun",
    "gn:population":0,
    "gn:timezone":"Asia/Jakarta",
    "iso:country":"ID",
    "name:ind_x_preferred":[
        "Wangun"
    ],
    "wof:name":"Wangun",
    "wof:placetype":"locality"
},
  "geometry": {"coordinates":[107.0933,-7.0308],"type":"Point"}
}