{
  "type": "Feature",
  "properties": {
    "gn:admin1_code":"8.0",
    "gn:asciiname":"Dungan",
    "gn:country_code":"ID",
    "gn:dem":7,
    "gn:feature_class":"P",
    "gn:feature_code":"PPL",
    "gn:name":"Dungan",
    "gn:population":0,
    "gn:timezone":"Asia/Jakarta",
    "iso:country":"ID",
    "name:ceb_x_preferred":[
        "Dungan"
    ],
    "name:deu_x_preferred":[
        "Dungan"
    ],
    "name:ind_x_preferred":[
        "Dungan"
    ],
    "name:rus_x_preferred":[
        "\u0414\u0443\u043d\u0433\u0430\u043d"
    ],
    "name:tur_x_preferred":[
        "Dungan"
    ],
    "wof:lang_x_official":[
        "ind"
    ],
    "wof:lang_x_spoken":[
        "ind",
        "eng"
    ],
    "wof:name":"Dungan",
    "wof:placetype":"locality"
},
  "geometry": {"coordinates":[112.37730000000001,-7.0419],"type":"Point"}
}