{
  "type": "Feature",
  "properties": {
    "gn:admin1_code":"18.0",
    "gn:asciiname":"Wuilari",
    "gn:country_code":"ID",
    "gn:dem":132,
    "gn:feature_class":"P",
    "gn:feature_code":"PPL",
    "gn:name":"Wuilari",
    "gn:population":0,
    "gn:timezone":"Asia/Makassar",
    "iso:country":"ID",
    "name:ind_x_preferred":[
        "Wuilari"
    ],
    "wof:name":"Wuilari",
    "wof:placetype":"locality"
},
  "geometry": {"coordinates":[121.9028,-10.548],"type":"Point"}
}