{
  "type": "Feature",
  "properties": {
    "gn:admin1_code":"30.0",
    "gn:asciiname":"Genjreng",
    "gn:country_code":"ID",
    "gn:dem":706,
    "gn:feature_class":"P",
    "gn:feature_code":"PPL",
    "gn:name":"Genjreng",
    "gn:population":0,
    "gn:timezone":"Asia/Jakarta",
    "iso:country":"ID",
    "name:ind_x_preferred":[
        "Genjreng"
    ],
    "name:und_x_variant":[
        "Gendjreng"
    ],
    "wof:name":"Genjreng",
    "wof:placetype":"locality"
},
  "geometry": {"coordinates":[107.93452000000001,-7.46717],"type":"Point"}
}