{
  "type": "Feature",
  "properties": {
    "gn:admin1_code":"8.0",
    "gn:asciiname":"Patalan",
    "gn:country_code":"ID",
    "gn:dem":107,
    "gn:feature_class":"P",
    "gn:feature_code":"PPL",
    "gn:name":"Patalan",
    "gn:population":0,
    "gn:timezone":"Asia/Jakarta",
    "iso:country":"ID",
    "name:ind_x_preferred":[
        "Patalan"
    ],
    "name:und_x_variant":[
        "Pantalan"
    ],
    "wof:name":"Patalan",
    "wof:placetype":"locality"
},
  "geometry": {"coordinates":[113.1502,-7.8339],"type":"Point"}
}