{
  "type": "Feature",
  "properties": {
    "gn:admin1_code":"15.0",
    "gn:asciiname":"Talang Sabuk Ulu",
    "gn:country_code":"ID",
    "gn:dem":126,
    "gn:feature_class":"P",
    "gn:feature_code":"PPL",
    "gn:name":"Talang Sabuk Ulu",
    "gn:population":0,
    "gn:timezone":"Asia/Jakarta",
    "iso:country":"ID",
    "name:ind_x_preferred":[
        "Talang Sabuk Ulu"
    ],
    "wof:name":"Talang Sabuk Ulu",
    "wof:placetype":"locality"
},
  "geometry": {"coordinates":[104.70149000000001,-4.88367],"type":"Point"}
}