{
  "type": "Feature",
  "properties": {
    "gn:admin1_code":"18",
    "gn:asciiname":"Kambureti",
    "gn:country_code":"ID",
    "gn:dem":523,
    "gn:feature_class":"P",
    "gn:feature_code":"PPL",
    "gn:name":"Kambureti",
    "gn:population":0,
    "gn:timezone":"Asia/Makassar",
    "iso:country":"ID",
    "name:ind_x_preferred":[
        "Kambureti"
    ],
    "wof:name":"Kambureti",
    "wof:placetype":"locality"
},
  "geometry": {"coordinates":[119.8626,-9.6434],"type":"Point"}
}