{
  "type": "Feature",
  "properties": {
    "gn:admin1_code":"12",
    "gn:asciiname":"Mihangit",
    "gn:country_code":"ID",
    "gn:dem":233,
    "gn:feature_class":"P",
    "gn:feature_code":"PPL",
    "gn:name":"Mihangit",
    "gn:population":0,
    "gn:timezone":"Asia/Makassar",
    "iso:country":"ID",
    "name:ind_x_preferred":[
        "Mihangit"
    ],
    "wof:name":"Mihangit",
    "wof:placetype":"locality"
},
  "geometry": {"coordinates":[115.8913,-2.6985],"type":"Point"}
}