{
  "type": "Feature",
  "properties": {
    "gn:admin1_code":"0.0",
    "gn:asciiname":"Regola",
    "gn:country_code":"ID",
    "gn:dem":180,
    "gn:feature_class":"P",
    "gn:feature_code":"PPL",
    "gn:name":"Regola",
    "gn:population":0,
    "gn:timezone":"Asia/Jayapura",
    "iso:country":"ID",
    "name:und_x_variant":[
        "Regoha",
        "Regola"
    ],
    "wof:name":"Regola",
    "wof:placetype":"locality"
},
  "geometry": {"coordinates":[129.012,-8.2404],"type":"Point"}
}