{
  "type": "Feature",
  "properties": {
    "gn:admin1_code":"0.0",
    "gn:asciiname":"Regola",
    "gn:country_code":"ID",
    "gn:dem":180,
    "gn:feature_class":"P",
    "gn:feature_code":"PPL",
    "gn:name":"Regola",
    "gn:population":0,
    "gn:timezone":"Asia/Jayapura",
    "iso:country":"ID",
    "name:ces_x_preferred":[
        "Regola"
    ],
    "name:deu_x_preferred":[
        "Regola"
    ],
    "name:eus_x_preferred":[
        "Regola"
    ],
    "name:fin_x_preferred":[
        "Regola"
    ],
    "name:heb_x_preferred":[
        "\u05e8\u05d2\u05d5\u05dc\u05d4"
    ],
    "name:nor_x_preferred":[
        "Regola"
    ],
    "name:pol_x_preferred":[
        "Regola"
    ],
    "name:rus_x_preferred":[
        "\u0420\u0435\u0433\u043e\u043b\u0430"
    ],
    "name:spa_x_preferred":[
        "Regola"
    ],
    "name:swe_x_preferred":[
        "Regola"
    ],
    "name:ukr_x_preferred":[
        "\u0420\u0435\u0491\u043e\u043b\u0430"
    ],
    "name:und_x_variant":[
        "Regoha",
        "Regola"
    ],
    "name:zho_x_preferred":[
        "\u96f7\u6208\u62c9"
    ],
    "wof:name":"Regola",
    "wof:placetype":"locality"
},
  "geometry": {"coordinates":[129.012,-8.2404],"type":"Point"}
}