{
  "type": "Feature",
  "properties": {
    "gn:admin1_code":"8.0",
    "gn:asciiname":"Jabur",
    "gn:country_code":"ID",
    "gn:dem":133,
    "gn:feature_class":"P",
    "gn:feature_code":"PPL",
    "gn:name":"Jabur",
    "gn:population":0,
    "gn:timezone":"Asia/Jakarta",
    "iso:country":"ID",
    "name:ind_x_preferred":[
        "Jabur"
    ],
    "wof:name":"Jabur",
    "wof:placetype":"locality"
},
  "geometry": {"coordinates":[113.9312,-6.9289],"type":"Point"}
}