{
  "type": "Feature",
  "properties": {
    "gn:admin1_code":"30.0",
    "gn:asciiname":"Nagertengah",
    "gn:country_code":"ID",
    "gn:dem":905,
    "gn:feature_class":"P",
    "gn:feature_code":"PPL",
    "gn:name":"Nagertengah",
    "gn:population":0,
    "gn:timezone":"Asia/Jakarta",
    "iso:country":"ID",
    "name:ind_x_preferred":[
        "Nagertengah"
    ],
    "name:und_x_variant":[
        "Garatengah"
    ],
    "wof:lang_x_official":[
        "ind"
    ],
    "wof:lang_x_spoken":[
        "ind",
        "eng"
    ],
    "wof:name":"Nagertengah",
    "wof:placetype":"locality"
},
  "geometry": {"coordinates":[108.04430000000001,-7.152],"type":"Point"}
}