{
  "type": "Feature",
  "properties": {
    "gn:admin1_code":"30",
    "gn:asciiname":"Cimurah",
    "gn:country_code":"ID",
    "gn:dem":621,
    "gn:feature_class":"P",
    "gn:feature_code":"PPL",
    "gn:name":"Cimurah",
    "gn:population":0,
    "gn:timezone":"Asia/Jakarta",
    "iso:country":"ID",
    "name:ind_x_preferred":[
        "Cimurah"
    ],
    "name:und_x_variant":[
        "Tjimurah 2",
        "Cimurah Dua"
    ],
    "wof:lang_x_official":[
        "ind"
    ],
    "wof:lang_x_spoken":[
        "ind",
        "eng"
    ],
    "wof:name":"Cimurah",
    "wof:placetype":"locality"
},
  "geometry": {"coordinates":[107.26528,-6.905],"type":"Point"}
}