{
  "type": "Feature",
  "properties": {
    "gn:admin1_code":"30",
    "gn:asciiname":"Sareuni",
    "gn:country_code":"ID",
    "gn:dem":655,
    "gn:feature_class":"P",
    "gn:feature_code":"PPL",
    "gn:name":"Sareuni",
    "gn:population":0,
    "gn:timezone":"Asia/Jakarta",
    "iso:country":"ID",
    "name:ind_x_preferred":[
        "Sareuni"
    ],
    "name:und_x_variant":[
        "Sareuri"
    ],
    "wof:name":"Sareuni",
    "wof:placetype":"locality"
},
  "geometry": {"coordinates":[107.43971999999999,-6.91028],"type":"Point"}
}