{
  "type": "Feature",
  "properties": {
    "gn:admin1_code":"08",
    "gn:asciiname":"Petis",
    "gn:country_code":"ID",
    "gn:dem":6,
    "gn:feature_class":"P",
    "gn:feature_code":"PPL",
    "gn:name":"Petis",
    "gn:population":0,
    "gn:timezone":"Asia/Jakarta",
    "iso:country":"ID",
    "name:ind_x_preferred":[
        "Petis"
    ],
    "wof:name":"Petis",
    "wof:placetype":"locality"
},
  "geometry": {"coordinates":[112.52500000000001,-7.1465],"type":"Point"}
}