{
  "type": "Feature",
  "properties": {
    "gn:admin1_code":"18",
    "gn:asciiname":"Jamawara",
    "gn:country_code":"ID",
    "gn:dem":526,
    "gn:feature_class":"P",
    "gn:feature_code":"PPL",
    "gn:name":"Jamawara",
    "gn:population":0,
    "gn:timezone":"Asia/Makassar",
    "iso:country":"ID",
    "name:ind_x_preferred":[
        "Jamawara"
    ],
    "wof:name":"Jamawara",
    "wof:placetype":"locality"
},
  "geometry": {"coordinates":[119.8937,-9.6943],"type":"Point"}
}