{
  "type": "Feature",
  "properties": {
    "gn:admin1_code":"36.0",
    "gn:asciiname":"Masipawe",
    "gn:country_code":"ID",
    "gn:dem":1,
    "gn:feature_class":"P",
    "gn:feature_code":"PPL",
    "gn:name":"Masipawe",
    "gn:population":0,
    "gn:timezone":"Asia/Jayapura",
    "iso:country":"ID",
    "name:und_x_variant":[
        "Rooewianoel",
        "Masipawe"
    ],
    "wof:name":"Masipawe",
    "wof:placetype":"locality"
},
  "geometry": {"coordinates":[135.74226999999999,-3.05322],"type":"Point"}
}