{
  "type": "Feature",
  "properties": {
    "gn:admin1_code":"26",
    "gn:asciiname":"Janji Matogu",
    "gn:country_code":"ID",
    "gn:dem":1103,
    "gn:feature_class":"P",
    "gn:feature_code":"PPL",
    "gn:name":"Janji Matogu",
    "gn:population":0,
    "gn:timezone":"Asia/Jakarta",
    "iso:country":"ID",
    "name:ind_x_preferred":[
        "Janji Matogu"
    ],
    "wof:name":"Janji Matogu",
    "wof:placetype":"locality"
},
  "geometry": {"coordinates":[98.9785,1.9773],"type":"Point"}
}