{
  "type": "Feature",
  "properties": {
    "gn:admin1_code":"30",
    "gn:asciiname":"Balekambang",
    "gn:country_code":"ID",
    "gn:dem":58,
    "gn:feature_class":"P",
    "gn:feature_code":"PPL",
    "gn:name":"Balekambang",
    "gn:population":0,
    "gn:timezone":"Asia/Jakarta",
    "iso:country":"ID",
    "name:ind_x_preferred":[
        "Balekambang"
    ],
    "wof:name":"Balekambang",
    "wof:placetype":"locality"
},
  "geometry": {"coordinates":[107.02943999999999,-6.36722],"type":"Point"}
}