{
  "type": "Feature",
  "properties": {
    "gn:admin1_code":"1",
    "gn:asciiname":"Alur Geutah",
    "gn:country_code":"ID",
    "gn:dem":36,
    "gn:feature_class":"P",
    "gn:feature_code":"PPL",
    "gn:name":"Alur Geutah",
    "gn:population":0,
    "gn:timezone":"Asia/Jakarta",
    "iso:country":"ID",
    "name:ind_x_preferred":[
        "Alur Getah"
    ],
    "wof:name":"Alur Geutah",
    "wof:placetype":"locality"
},
  "geometry": {"coordinates":[96.5629,4.0099],"type":"Point"}
}