{
  "type": "Feature",
  "properties": {
    "gn:admin1_code":"30",
    "gn:asciiname":"Salado",
    "gn:country_code":"ID",
    "gn:dem":636,
    "gn:feature_class":"P",
    "gn:feature_code":"PPL",
    "gn:name":"Salado",
    "gn:population":0,
    "gn:timezone":"Asia/Jakarta",
    "iso:country":"ID",
    "name:ceb_x_preferred":[
        "Salado"
    ],
    "name:ces_x_preferred":[
        "Salado"
    ],
    "name:deu_x_preferred":[
        "Salado"
    ],
    "name:ind_x_preferred":[
        "Salado"
    ],
    "name:ita_x_preferred":[
        "Salado"
    ],
    "name:nld_x_preferred":[
        "Salado"
    ],
    "name:pol_x_preferred":[
        "Salado"
    ],
    "name:rus_x_preferred":[
        "\u0420\u0438\u043e-\u0421\u0430\u043b\u0430\u0434\u043e"
    ],
    "name:spa_x_preferred":[
        "Salado"
    ],
    "name:swe_x_preferred":[
        "Salado"
    ],
    "wof:lang_x_official":[
        "ind"
    ],
    "wof:lang_x_spoken":[
        "ind",
        "eng"
    ],
    "wof:name":"Salado",
    "wof:placetype":"locality"
},
  "geometry": {"coordinates":[108.32693999999999,-6.98667],"type":"Point"}
}