{
  "type": "Feature",
  "properties": {
    "gn:admin1_code":"30",
    "gn:asciiname":"Salado",
    "gn:country_code":"ID",
    "gn:dem":636,
    "gn:feature_class":"P",
    "gn:feature_code":"PPL",
    "gn:name":"Salado",
    "gn:population":0,
    "gn:timezone":"Asia/Jakarta",
    "iso:country":"ID",
    "name:ceb_x_preferred":[
        "Salado"
    ],
    "name:ces_x_preferred":[
        "Salado"
    ],
    "name:deu_x_preferred":[
        "Salado"
    ],
    "name:ind_x_preferred":[
        "Salado"
    ],
    "name:ita_x_preferred":[
        "Salado"
    ],
    "name:nld_x_preferred":[
        "Salado"
    ],
    "name:pol_x_preferred":[
        "Salado"
    ],
    "name:rus_x_preferred":[
        "\u0440\u0435\u043a\u0430 \u0420\u0438\u043e-\u0421\u0430\u043b\u0430\u0434\u043e"
    ],
    "name:rus_x_variant":[
        "\u0420\u0438\u043e-\u0421\u0430\u043b\u0430\u0434\u043e"
    ],
    "name:spa_x_preferred":[
        "Salado"
    ],
    "name:swe_x_preferred":[
        "Salado"
    ],
    "name:tur_x_preferred":[
        "Salado"
    ],
    "name:ukr_x_preferred":[
        "\u0421\u0430\u043b\u0430\u0434\u043e"
    ],
    "name:urd_x_preferred":[
        "\u0633\u0627\u0644\u0627\u062f\u0648"
    ],
    "name:vie_x_preferred":[
        "S\u00f4ng Salado"
    ],
    "name:zho_cn_x_preferred":[
        "\u8428\u62c9\u591a\u6cb3"
    ],
    "name:zho_tw_x_preferred":[
        "\u96a1\u62c9\u591a\u6cb3"
    ],
    "wof:lang_x_official":[
        "ind"
    ],
    "wof:lang_x_spoken":[
        "ind",
        "eng"
    ],
    "wof:name":"Salado",
    "wof:placetype":"locality"
},
  "geometry": {"coordinates":[108.32693999999999,-6.98667],"type":"Point"}
}