{
  "type": "Feature",
  "properties": {
    "gn:admin1_code":"18",
    "gn:asciiname":"Orong",
    "gn:country_code":"ID",
    "gn:dem":734,
    "gn:feature_class":"P",
    "gn:feature_code":"PPL",
    "gn:name":"Orong",
    "gn:population":0,
    "gn:timezone":"Asia/Makassar",
    "iso:country":"ID",
    "name:ind_x_preferred":[
        "Orong"
    ],
    "wof:name":"Orong",
    "wof:placetype":"locality"
},
  "geometry": {"coordinates":[120.6467,-8.4858],"type":"Point"}
}