{
  "type": "Feature",
  "properties": {
    "gn:admin1_code":"8",
    "gn:asciiname":"Sumbersari Kulon",
    "gn:country_code":"ID",
    "gn:dem":90,
    "gn:feature_class":"P",
    "gn:feature_code":"PPL",
    "gn:name":"Sumbersari Kulon",
    "gn:population":0,
    "gn:timezone":"Asia/Jakarta",
    "iso:country":"ID",
    "name:ind_x_preferred":[
        "Sumbersari Kulon"
    ],
    "wof:name":"Sumbersari Kulon",
    "wof:placetype":"locality"
},
  "geometry": {"coordinates":[113.709,-8.1784],"type":"Point"}
}