{
  "type": "Feature",
  "properties": {
    "gn:admin1_code":"18.0",
    "gn:asciiname":"Raidao",
    "gn:country_code":"ID",
    "gn:dem":42,
    "gn:feature_class":"P",
    "gn:feature_code":"PPL",
    "gn:name":"Raidao",
    "gn:population":0,
    "gn:timezone":"Asia/Makassar",
    "iso:country":"ID",
    "name:ind_x_preferred":[
        "Raidao"
    ],
    "wof:name":"Raidao",
    "wof:placetype":"locality"
},
  "geometry": {"coordinates":[121.84990000000001,-10.5267],"type":"Point"}
}