{
  "type": "Feature",
  "properties": {
    "gn:admin1_code":"30",
    "gn:asciiname":"Legokwaru Kulon",
    "gn:country_code":"ID",
    "gn:dem":303,
    "gn:feature_class":"P",
    "gn:feature_code":"PPL",
    "gn:name":"Legokwaru Kulon",
    "gn:population":0,
    "gn:timezone":"Asia/Jakarta",
    "iso:country":"ID",
    "name:ind_x_preferred":[
        "Legokwaru Kulon"
    ],
    "wof:name":"Legokwaru Kulon",
    "wof:placetype":"locality"
},
  "geometry": {"coordinates":[107.39111,-6.68028],"type":"Point"}
}