{
  "type": "Feature",
  "properties": {
    "gn:admin1_code":"30",
    "gn:asciiname":"Pabuaran",
    "gn:country_code":"ID",
    "gn:dem":99,
    "gn:feature_class":"P",
    "gn:feature_code":"PPL",
    "gn:name":"Pabuaran",
    "gn:population":0,
    "gn:timezone":"Asia/Jakarta",
    "iso:country":"ID",
    "name:ind_x_preferred":[
        "Pabuaran"
    ],
    "wof:name":"Pabuaran",
    "wof:placetype":"locality"
},
  "geometry": {"coordinates":[107.12222,-6.50639],"type":"Point"}
}