{
  "type": "Feature",
  "properties": {
    "gn:admin1_code":"15.0",
    "gn:asciiname":"Surabaya",
    "gn:country_code":"ID",
    "gn:dem":23,
    "gn:feature_class":"P",
    "gn:feature_code":"PPLA3",
    "gn:name":"Surabaya",
    "gn:population":0,
    "gn:timezone":"Asia/Jakarta",
    "iso:country":"ID",
    "name:ind_x_preferred":[
        "Surabaya Ilir"
    ],
    "name:rus_x_preferred":[
        "\u0421\u0443\u0440\u0430\u0431\u0430\u0439\u0430"
    ],
    "name:und_x_variant":[
        "Soerabaja",
        "Surabaja",
        "Surabaya"
    ],
    "wof:name":"Surabaya",
    "wof:placetype":"locality"
},
  "geometry": {"coordinates":[105.72571000000001,-4.67122],"type":"Point"}
}