{
  "type": "Feature",
  "properties": {
    "gn:admin1_code":"30.0",
    "gn:asciiname":"Citamiang",
    "gn:country_code":"ID",
    "gn:dem":970,
    "gn:feature_class":"P",
    "gn:feature_code":"PPLA4",
    "gn:name":"Citamiang",
    "gn:population":0,
    "gn:timezone":"Asia/Jakarta",
    "iso:country":"ID",
    "name:ind_x_preferred":[
        "Citamiang"
    ],
    "wof:name":"Citamiang",
    "wof:placetype":"locality"
},
  "geometry": {"coordinates":[107.20359999999999,-7.0714],"type":"Point"}
}