{
  "type": "Feature",
  "properties": {
    "gn:admin1_code":"07",
    "gn:asciiname":"Pagertoyo",
    "gn:country_code":"ID",
    "gn:dem":516,
    "gn:feature_class":"P",
    "gn:feature_code":"PPL",
    "gn:name":"Pagertoyo",
    "gn:population":0,
    "gn:timezone":"Asia/Jakarta",
    "iso:country":"ID",
    "name:ind_x_preferred":[
        "Pagertoyo"
    ],
    "name:und_x_variant":[
        "Pagertoja",
        "Pagertoya"
    ],
    "wof:lang_x_official":[
        "ind"
    ],
    "wof:lang_x_spoken":[
        "ind",
        "eng"
    ],
    "wof:name":"Pagertoyo",
    "wof:placetype":"locality"
},
  "geometry": {"coordinates":[110.29806000000001,-7.15417],"type":"Point"}
}