{
  "type": "Feature",
  "properties": {
    "gn:admin1_code":"26",
    "gn:asciiname":"Gelunggung",
    "gn:country_code":"ID",
    "gn:dem":121,
    "gn:feature_class":"P",
    "gn:feature_code":"PPL",
    "gn:name":"Gelunggung",
    "gn:population":0,
    "gn:timezone":"Asia/Jakarta",
    "iso:country":"ID",
    "name:ind_x_preferred":[
        "Gelunggung"
    ],
    "wof:name":"Gelunggung",
    "wof:placetype":"locality"
},
  "geometry": {"coordinates":[98.6046,3.454],"type":"Point"}
}