{
  "type": "Feature",
  "properties": {
    "gn:admin1_code":"32.0",
    "gn:asciiname":"Tanjungkarang",
    "gn:country_code":"ID",
    "gn:dem":55,
    "gn:feature_class":"P",
    "gn:feature_code":"PPL",
    "gn:name":"Tanjungkarang",
    "gn:population":0,
    "gn:timezone":"Asia/Jakarta",
    "iso:country":"ID",
    "name:ind_x_preferred":[
        "Tanjungkarang"
    ],
    "wof:name":"Tanjungkarang",
    "wof:placetype":"locality"
},
  "geometry": {"coordinates":[104.10711999999999,-4.09654],"type":"Point"}
}