{
  "type": "Feature",
  "properties": {
    "gn:admin1_code":"35.0",
    "gn:asciiname":"Airduren",
    "gn:country_code":"ID",
    "gn:dem":26,
    "gn:feature_class":"P",
    "gn:feature_code":"PPL",
    "gn:name":"Airduren",
    "gn:population":0,
    "gn:timezone":"Asia/Jakarta",
    "iso:country":"ID",
    "name:ind_x_preferred":[
        "Airduren"
    ],
    "wof:name":"Airduren",
    "wof:placetype":"locality"
},
  "geometry": {"coordinates":[106.04707000000001,-1.90476],"type":"Point"}
}