{
  "type": "Feature",
  "properties": {
    "gn:admin1_code":"8.0",
    "gn:asciiname":"Ngorodowo",
    "gn:country_code":"ID",
    "gn:dem":331,
    "gn:feature_class":"P",
    "gn:feature_code":"PPL",
    "gn:name":"Ngorodowo",
    "gn:population":0,
    "gn:timezone":"Asia/Jakarta",
    "iso:country":"ID",
    "name:ind_x_preferred":[
        "Ngorodowo"
    ],
    "wof:name":"Ngorodowo",
    "wof:placetype":"locality"
},
  "geometry": {"coordinates":[110.94417,-8.13556],"type":"Point"}
}