{
  "type": "Feature",
  "properties": {
    "gn:admin1_code":"38.0",
    "gn:asciiname":"Dengen",
    "gn:country_code":"ID",
    "gn:dem":470,
    "gn:feature_class":"P",
    "gn:feature_code":"PPL",
    "gn:name":"Dengen",
    "gn:population":0,
    "gn:timezone":"Asia/Makassar",
    "iso:country":"ID",
    "name:ind_x_preferred":[
        "Dengen"
    ],
    "wof:name":"Dengen",
    "wof:placetype":"locality"
},
  "geometry": {"coordinates":[120.03400000000001,-3.0665],"type":"Point"}
}