{
  "type": "Feature",
  "properties": {
    "gn:admin1_code":"37",
    "gn:asciiname":"Sibumbung",
    "gn:country_code":"ID",
    "gn:dem":16,
    "gn:feature_class":"P",
    "gn:feature_code":"PPL",
    "gn:name":"Sibumbung",
    "gn:population":0,
    "gn:timezone":"Asia/Jakarta",
    "iso:country":"ID",
    "name:ind_x_preferred":[
        "Sibumbung"
    ],
    "wof:name":"Sibumbung",
    "wof:placetype":"locality"
},
  "geometry": {"coordinates":[102.06894,0.01229],"type":"Point"}
}