{
  "type": "Feature",
  "properties": {
    "gn:admin1_code":"18.0",
    "gn:asciiname":"Hapalukoke",
    "gn:country_code":"ID",
    "gn:dem":68,
    "gn:feature_class":"P",
    "gn:feature_code":"PPL",
    "gn:name":"Hapalukoke",
    "gn:population":0,
    "gn:timezone":"Asia/Makassar",
    "iso:country":"ID",
    "name:ind_x_preferred":[
        "Hapalukoke"
    ],
    "wof:name":"Hapalukoke",
    "wof:placetype":"locality"
},
  "geometry": {"coordinates":[118.99460000000001,-9.5402],"type":"Point"}
}