{
  "type": "Feature",
  "properties": {
    "gn:admin1_code":"30",
    "gn:asciiname":"Cijerah",
    "gn:country_code":"ID",
    "gn:dem":740,
    "gn:feature_class":"P",
    "gn:feature_code":"PPL",
    "gn:name":"Cijerah",
    "gn:population":0,
    "gn:timezone":"Asia/Jakarta",
    "iso:country":"ID",
    "name:ind_x_preferred":[
        "Cijerah"
    ],
    "name:und_x_variant":[
        "Tjidjerah 2",
        "Cijerah Dua"
    ],
    "wof:lang_x_official":[
        "ind"
    ],
    "wof:lang_x_spoken":[
        "ind",
        "eng"
    ],
    "wof:name":"Cijerah",
    "wof:placetype":"locality"
},
  "geometry": {"coordinates":[107.52222,-6.86278],"type":"Point"}
}