{
  "type": "Feature",
  "properties": {
    "gn:admin1_code":"8.0",
    "gn:asciiname":"Pandaringan Barat",
    "gn:country_code":"ID",
    "gn:dem":21,
    "gn:feature_class":"P",
    "gn:feature_code":"PPLA4",
    "gn:name":"Pandaringan Barat",
    "gn:population":0,
    "gn:timezone":"Asia/Jakarta",
    "iso:country":"ID",
    "name:ind_x_preferred":[
        "Pandaringan Barat"
    ],
    "name:und_x_variant":[
        "Padaringan Barat"
    ],
    "wof:name":"Pandaringan Barat",
    "wof:placetype":"locality"
},
  "geometry": {"coordinates":[113.89060000000001,-6.9991],"type":"Point"}
}