{
  "type": "Feature",
  "properties": {
    "gn:admin1_code":"18.0",
    "gn:asciiname":"Muri",
    "gn:country_code":"ID",
    "gn:dem":718,
    "gn:feature_class":"P",
    "gn:feature_code":"PPL",
    "gn:name":"Muri",
    "gn:population":0,
    "gn:timezone":"Asia/Makassar",
    "iso:country":"ID",
    "name:ind_x_preferred":[
        "Muri"
    ],
    "wof:name":"Muri",
    "wof:placetype":"locality"
},
  "geometry": {"coordinates":[120.4648,-8.7273],"type":"Point"}
}