{
  "type": "Feature",
  "properties": {
    "gn:admin1_code":"18.0",
    "gn:asciiname":"Muri",
    "gn:country_code":"ID",
    "gn:dem":718,
    "gn:feature_class":"P",
    "gn:feature_code":"PPL",
    "gn:name":"Muri",
    "gn:population":0,
    "gn:timezone":"Asia/Makassar",
    "iso:country":"ID",
    "name:als_x_preferred":[
        "Muri"
    ],
    "name:ceb_x_preferred":[
        "Muri"
    ],
    "name:ces_x_preferred":[
        "Muri"
    ],
    "name:deu_x_preferred":[
        "Muri"
    ],
    "name:epo_x_preferred":[
        "Muri"
    ],
    "name:est_x_preferred":[
        "Muri"
    ],
    "name:eus_x_preferred":[
        "Muri"
    ],
    "name:fra_x_preferred":[
        "Muri"
    ],
    "name:ind_x_preferred":[
        "Muri"
    ],
    "name:ita_x_preferred":[
        "Muri"
    ],
    "name:lat_x_preferred":[
        "Muri"
    ],
    "name:nld_x_preferred":[
        "Muri"
    ],
    "name:swe_x_preferred":[
        "Muri"
    ],
    "name:vol_x_preferred":[
        "Muri"
    ],
    "wof:lang_x_official":[
        "ind"
    ],
    "wof:lang_x_spoken":[
        "ind",
        "eng"
    ],
    "wof:name":"Muri",
    "wof:placetype":"locality"
},
  "geometry": {"coordinates":[120.4648,-8.7273],"type":"Point"}
}