{
  "type": "Feature",
  "properties": {
    "gn:admin1_code":"7.0",
    "gn:asciiname":"Tegalonyam",
    "gn:country_code":"ID",
    "gn:dem":342,
    "gn:feature_class":"P",
    "gn:feature_code":"PPL",
    "gn:name":"Tegalonyam",
    "gn:population":0,
    "gn:timezone":"Asia/Jakarta",
    "iso:country":"ID",
    "name:ind_x_preferred":[
        "Tegalonyam"
    ],
    "name:und_x_variant":[
        "Tegalonjam"
    ],
    "wof:name":"Tegalonyam",
    "wof:placetype":"locality"
},
  "geometry": {"coordinates":[108.801,-7.1405],"type":"Point"}
}