{
  "type": "Feature",
  "properties": {
    "gn:admin1_code":"32.0",
    "gn:asciiname":"Gunungmeraksa",
    "gn:country_code":"ID",
    "gn:dem":220,
    "gn:feature_class":"P",
    "gn:feature_code":"PPL",
    "gn:name":"Gunungmeraksa",
    "gn:population":0,
    "gn:timezone":"Asia/Jakarta",
    "iso:country":"ID",
    "name:ind_x_preferred":[
        "Gunungmeraksa"
    ],
    "wof:name":"Gunungmeraksa",
    "wof:placetype":"locality"
},
  "geometry": {"coordinates":[102.9194,-3.7807],"type":"Point"}
}