{
  "type": "Feature",
  "properties": {
    "gn:admin1_code":"17",
    "gn:asciiname":"Selak",
    "gn:country_code":"ID",
    "gn:dem":112,
    "gn:feature_class":"P",
    "gn:feature_code":"PPL",
    "gn:name":"Selak",
    "gn:population":0,
    "gn:timezone":"Asia/Makassar",
    "iso:country":"ID",
    "name:ind_x_preferred":[
        "Selak"
    ],
    "wof:name":"Selak",
    "wof:placetype":"locality"
},
  "geometry": {"coordinates":[116.29430000000001,-8.8394],"type":"Point"}
}