{
  "type": "Feature",
  "properties": {
    "gn:admin1_code":"38",
    "gn:asciiname":"Bau",
    "gn:country_code":"ID",
    "gn:dem":353,
    "gn:feature_class":"P",
    "gn:feature_code":"PPL",
    "gn:name":"Bau",
    "gn:population":0,
    "gn:timezone":"Asia/Makassar",
    "iso:country":"ID",
    "name:ind_x_preferred":[
        "Bau"
    ],
    "wof:name":"Bau",
    "wof:placetype":"locality"
},
  "geometry": {"coordinates":[120.0757,-2.6138],"type":"Point"}
}