{
  "type": "Feature",
  "properties": {
    "gn:admin1_code":"30.0",
    "gn:asciiname":"Cirungkang",
    "gn:country_code":"ID",
    "gn:dem":716,
    "gn:feature_class":"P",
    "gn:feature_code":"PPL",
    "gn:name":"Cirungkang",
    "gn:population":0,
    "gn:timezone":"Asia/Jakarta",
    "iso:country":"ID",
    "name:ind_x_preferred":[
        "Cirungkang"
    ],
    "name:und_x_variant":[
        "Tjiroengkang"
    ],
    "wof:lang_x_official":[
        "ind"
    ],
    "wof:lang_x_spoken":[
        "ind",
        "eng"
    ],
    "wof:name":"Cirungkang",
    "wof:placetype":"locality"
},
  "geometry": {"coordinates":[108.0996,-7.0029],"type":"Point"}
}