{
  "type": "Feature",
  "properties": {
    "gn:admin1_code":"26",
    "gn:asciiname":"Kelapa",
    "gn:country_code":"ID",
    "gn:dem":12,
    "gn:feature_class":"P",
    "gn:feature_code":"PPL",
    "gn:name":"Kelapa",
    "gn:population":0,
    "gn:timezone":"Asia/Jakarta",
    "iso:country":"ID",
    "name:ind_x_preferred":[
        "Kelapa"
    ],
    "wof:name":"Kelapa",
    "wof:placetype":"locality"
},
  "geometry": {"coordinates":[99.4046,3.272],"type":"Point"}
}