{
  "type": "Feature",
  "properties": {
    "gn:admin1_code":"30",
    "gn:asciiname":"Pamulihan",
    "gn:country_code":"ID",
    "gn:dem":789,
    "gn:feature_class":"P",
    "gn:feature_code":"PPL",
    "gn:name":"Pamulihan",
    "gn:population":0,
    "gn:timezone":"Asia/Jakarta",
    "iso:country":"ID",
    "name:ind_x_preferred":[
        "Pamulihan"
    ],
    "wof:name":"Pamulihan",
    "wof:placetype":"locality"
},
  "geometry": {"coordinates":[108.30861000000002,-6.93361],"type":"Point"}
}