{
  "type": "Feature",
  "properties": {
    "gn:admin1_code":"30",
    "gn:asciiname":"Cikawalu",
    "gn:country_code":"ID",
    "gn:dem":1043,
    "gn:feature_class":"P",
    "gn:feature_code":"PPL",
    "gn:name":"Cikawalu",
    "gn:population":0,
    "gn:timezone":"Asia/Jakarta",
    "iso:country":"ID",
    "wof:name":"Cikawalu",
    "wof:placetype":"locality"
},
  "geometry": {"coordinates":[107.63139,-7.07833],"type":"Point"}
}