{
  "type": "Feature",
  "properties": {
    "gn:admin1_code":"38",
    "gn:asciiname":"Galang",
    "gn:country_code":"ID",
    "gn:dem":893,
    "gn:feature_class":"P",
    "gn:feature_code":"PPL",
    "gn:name":"Galang",
    "gn:population":0,
    "gn:timezone":"Asia/Makassar",
    "iso:country":"ID",
    "name:ceb_x_preferred":[
        "Galang"
    ],
    "name:ind_x_preferred":[
        "Galang"
    ],
    "name:swe_x_preferred":[
        "Galang"
    ],
    "wof:lang_x_official":[
        "ind"
    ],
    "wof:lang_x_spoken":[
        "ind",
        "eng"
    ],
    "wof:name":"Galang",
    "wof:placetype":"locality"
},
  "geometry": {"coordinates":[119.85080000000001,-5.3094],"type":"Point"}
}