{
  "type": "Feature",
  "properties": {
    "gn:admin1_code":"18.0",
    "gn:asciiname":"Tenda",
    "gn:country_code":"ID",
    "gn:dem":1082,
    "gn:feature_class":"P",
    "gn:feature_code":"PPL",
    "gn:name":"Tenda",
    "gn:population":0,
    "gn:timezone":"Asia/Makassar",
    "iso:country":"ID",
    "name:ceb_x_preferred":[
        "Tenda"
    ],
    "name:deu_x_preferred":[
        "Tenda"
    ],
    "name:fra_x_preferred":[
        "Tenda"
    ],
    "name:ind_x_preferred":[
        "Tenda"
    ],
    "name:ita_x_preferred":[
        "Tenda"
    ],
    "name:swe_x_preferred":[
        "Tenda"
    ],
    "name:zho_x_preferred":[
        "Tenda"
    ],
    "wof:name":"Tenda",
    "wof:placetype":"locality"
},
  "geometry": {"coordinates":[120.6675,-8.6907],"type":"Point"}
}