{
  "type": "Feature",
  "properties": {
    "gn:admin1_code":"21.0",
    "gn:asciiname":"Matano",
    "gn:country_code":"ID",
    "gn:dem":5,
    "gn:feature_class":"P",
    "gn:feature_code":"PPL",
    "gn:name":"Matano",
    "gn:population":0,
    "gn:timezone":"Asia/Makassar",
    "iso:country":"ID",
    "name:ind_x_preferred":[
        "Matano"
    ],
    "wof:name":"Matano",
    "wof:placetype":"locality"
},
  "geometry": {"coordinates":[122.4241,-3.2018],"type":"Point"}
}