{
  "type": "Feature",
  "properties": {
    "gn:admin1_code":"8",
    "gn:asciiname":"Gambang",
    "gn:country_code":"ID",
    "gn:dem":995,
    "gn:feature_class":"P",
    "gn:feature_code":"PPL",
    "gn:name":"Gambang",
    "gn:population":0,
    "gn:timezone":"Asia/Jakarta",
    "iso:country":"ID",
    "name:bel_x_preferred":[
        "\u0413\u0430\u043c\u0431\u0430\u043d\u0433"
    ],
    "name:bul_x_preferred":[
        "\u0413\u0430\u043c\u0431\u0430\u043d\u0433"
    ],
    "name:cat_x_preferred":[
        "Gambang"
    ],
    "name:ind_x_preferred":[
        "Gambang"
    ],
    "name:jav_x_preferred":[
        "Gambang"
    ],
    "name:msa_x_preferred":[
        "Gambang"
    ],
    "name:rus_x_preferred":[
        "\u0413\u0430\u043c\u0431\u0430\u043d\u0433"
    ],
    "name:sun_x_preferred":[
        "Gambang"
    ],
    "name:tgl_x_preferred":[
        "Gambang"
    ],
    "wof:name":"Gambang",
    "wof:placetype":"locality"
},
  "geometry": {"coordinates":[113.1561,-7.9736],"type":"Point"}
}