{
  "type": "Feature",
  "properties": {
    "gn:admin1_code":"35",
    "gn:asciiname":"Serdang",
    "gn:country_code":"ID",
    "gn:dem":40,
    "gn:feature_class":"P",
    "gn:feature_code":"PPL",
    "gn:name":"Serdang",
    "gn:population":0,
    "gn:timezone":"Asia/Jakarta",
    "iso:country":"ID",
    "name:ceb_x_preferred":[
        "Serdang"
    ],
    "name:ind_x_preferred":[
        "Serdang"
    ],
    "name:msa_x_preferred":[
        "Serdang"
    ],
    "name:nld_x_preferred":[
        "Serdang"
    ],
    "name:swe_x_preferred":[
        "Serdang"
    ],
    "wof:name":"Serdang",
    "wof:placetype":"locality"
},
  "geometry": {"coordinates":[106.24845999999999,-2.73848],"type":"Point"}
}