{
  "type": "Feature",
  "properties": {
    "gn:admin1_code":"1",
    "gn:asciiname":"Bithak",
    "gn:country_code":"ID",
    "gn:dem":36,
    "gn:feature_class":"P",
    "gn:feature_code":"PPL",
    "gn:name":"Bithak",
    "gn:population":0,
    "gn:timezone":"Asia/Jakarta",
    "iso:country":"ID",
    "name:ind_x_preferred":[
        "Bithak"
    ],
    "wof:name":"Bithak",
    "wof:placetype":"locality"
},
  "geometry": {"coordinates":[95.53060000000001,5.3743],"type":"Point"}
}