{
  "type": "Feature",
  "properties": {
    "gn:admin1_code":"30.0",
    "gn:asciiname":"Gombong",
    "gn:country_code":"ID",
    "gn:dem":507,
    "gn:feature_class":"P",
    "gn:feature_code":"PPL",
    "gn:name":"Gombong",
    "gn:population":0,
    "gn:timezone":"Asia/Jakarta",
    "iso:country":"ID",
    "name:ind_x_preferred":[
        "Gombong"
    ],
    "wof:name":"Gombong",
    "wof:placetype":"locality"
},
  "geometry": {"coordinates":[108.0222,-7.0351],"type":"Point"}
}