{
  "type": "Feature",
  "properties": {
    "gn:admin1_code":"30",
    "gn:asciiname":"Leuwikopo",
    "gn:cc2":"ID",
    "gn:country_code":"ID",
    "gn:dem":82,
    "gn:feature_class":"P",
    "gn:feature_code":"PPL",
    "gn:name":"Leuwikopo",
    "gn:population":0,
    "gn:timezone":"Asia/Jakarta",
    "iso:country":"ID",
    "name:und_x_variant":[
        "Leuwikapa",
        "Leuwikopo"
    ],
    "wof:name":"Leuwikopo",
    "wof:placetype":"locality"
},
  "geometry": {"coordinates":[106.56083,-6.40556],"type":"Point"}
}