{
  "type": "Feature",
  "properties": {
    "gn:admin1_code":"28.0",
    "gn:asciiname":"Masarete",
    "gn:country_code":"ID",
    "gn:dem":9,
    "gn:feature_class":"P",
    "gn:feature_code":"PPL",
    "gn:name":"Masarete",
    "gn:population":0,
    "gn:timezone":"Asia/Jayapura",
    "iso:country":"ID",
    "name:ind_x_preferred":[
        "Masarete"
    ],
    "name:und_x_variant":[
        "Masar\u00e9te"
    ],
    "wof:name":"Masarete",
    "wof:placetype":"locality"
},
  "geometry": {"coordinates":[127.11126000000002,-3.38407],"type":"Point"}
}