{
  "type": "Feature",
  "properties": {
    "gn:admin1_code":"26",
    "gn:asciiname":"Sakusaku",
    "gn:country_code":"ID",
    "gn:dem":0,
    "gn:feature_class":"P",
    "gn:feature_code":"PPL",
    "gn:name":"Sakusaku",
    "gn:population":0,
    "gn:timezone":"Asia/Jakarta",
    "iso:country":"ID",
    "name:ind_x_preferred":[
        "Sakusaku"
    ],
    "wof:name":"Sakusaku",
    "wof:placetype":"locality"
},
  "geometry": {"coordinates":[97.37949999999999,0.8561],"type":"Point"}
}