{
  "type": "Feature",
  "properties": {
    "gn:admin1_code":"30",
    "gn:asciiname":"Sukahurip",
    "gn:country_code":"ID",
    "gn:dem":348,
    "gn:feature_class":"P",
    "gn:feature_code":"PPL",
    "gn:name":"Sukahurip",
    "gn:population":0,
    "gn:timezone":"Asia/Jakarta",
    "iso:country":"ID",
    "name:ind_x_preferred":[
        "Sukahurip"
    ],
    "wof:name":"Sukahurip",
    "wof:placetype":"locality"
},
  "geometry": {"coordinates":[108.06778,-6.92972],"type":"Point"}
}