{
  "type": "Feature",
  "properties": {
    "gn:admin1_code":"30",
    "gn:asciiname":"Parungareuy",
    "gn:cc2":"ID",
    "gn:country_code":"ID",
    "gn:dem":111,
    "gn:feature_class":"P",
    "gn:feature_code":"PPL",
    "gn:name":"Parungareuy",
    "gn:population":0,
    "gn:timezone":"Asia/Jakarta",
    "iso:country":"ID",
    "name:und_x_variant":[
        "Parungareuj",
        "Parungareuy"
    ],
    "wof:name":"Parungareuy",
    "wof:placetype":"locality"
},
  "geometry": {"coordinates":[106.67389,-6.47417],"type":"Point"}
}