{
  "type": "Feature",
  "properties": {
    "gn:admin1_code":"1",
    "gn:asciiname":"Pajabege",
    "gn:country_code":"ID",
    "gn:dem":1349,
    "gn:feature_class":"P",
    "gn:feature_code":"PPL",
    "gn:name":"Pajabege",
    "gn:population":0,
    "gn:timezone":"Asia/Jakarta",
    "iso:country":"ID",
    "name:ind_x_preferred":[
        "Pajabege"
    ],
    "wof:name":"Pajabege",
    "wof:placetype":"locality"
},
  "geometry": {"coordinates":[97.01609999999999,4.573],"type":"Point"}
}