{
  "type": "Feature",
  "properties": {
    "gn:admin1_code":"14",
    "gn:asciiname":"Jembaring",
    "gn:country_code":"ID",
    "gn:dem":10,
    "gn:feature_class":"P",
    "gn:feature_code":"PPL",
    "gn:name":"Jembaring",
    "gn:population":0,
    "gn:timezone":"Asia/Makassar",
    "iso:country":"ID",
    "name:ind_x_preferred":[
        "Jembaring"
    ],
    "wof:name":"Jembaring",
    "wof:placetype":"locality"
},
  "geometry": {"coordinates":[116.2597,-1.5607],"type":"Point"}
}