{
  "type": "Feature",
  "properties": {
    "gn:admin1_code":"2",
    "gn:asciiname":"Banjar Sedang",
    "gn:country_code":"ID",
    "gn:dem":111,
    "gn:feature_class":"P",
    "gn:feature_code":"PPLA4",
    "gn:name":"Banjar Sedang",
    "gn:population":0,
    "gn:timezone":"Asia/Makassar",
    "iso:country":"ID",
    "name:ind_x_preferred":[
        "Banjar Sedang"
    ],
    "wof:name":"Banjar Sedang",
    "wof:placetype":"locality"
},
  "geometry": {"coordinates":[115.2389,-8.5707],"type":"Point"}
}