{
  "type": "Feature",
  "properties": {
    "gn:admin1_code":"07",
    "gn:asciiname":"Salatiga",
    "gn:country_code":"ID",
    "gn:dem":583,
    "gn:feature_class":"P",
    "gn:feature_code":"PPL",
    "gn:name":"Salatiga",
    "gn:population":0,
    "gn:timezone":"Asia/Jakarta",
    "iso:country":"ID",
    "wof:name":"Salatiga",
    "wof:placetype":"locality"
},
  "geometry": {"coordinates":[110.50778,-7.32139],"type":"Point"}
}