{
  "type": "Feature",
  "properties": {
    "gn:admin1_code":"2",
    "gn:asciiname":"Banjar Pasekan",
    "gn:country_code":"ID",
    "gn:dem":80,
    "gn:feature_class":"P",
    "gn:feature_code":"PPL",
    "gn:name":"Banjar Pasekan",
    "gn:population":0,
    "gn:timezone":"Asia/Makassar",
    "iso:country":"ID",
    "name:ind_x_preferred":[
        "Banjar Pasekan"
    ],
    "wof:name":"Banjar Pasekan",
    "wof:placetype":"locality"
},
  "geometry": {"coordinates":[115.16070000000001,-8.6065],"type":"Point"}
}