{
  "type": "Feature",
  "properties": {
    "gn:admin1_code":"30.0",
    "gn:asciiname":"Ciharalang",
    "gn:country_code":"ID",
    "gn:dem":172,
    "gn:feature_class":"P",
    "gn:feature_code":"PPLA4",
    "gn:name":"Ciharalang",
    "gn:population":0,
    "gn:timezone":"Asia/Jakarta",
    "iso:country":"ID",
    "name:ind_x_preferred":[
        "Ciharalang"
    ],
    "name:und_x_variant":[
        "Tjiharalang Satu"
    ],
    "wof:lang_x_official":[
        "ind"
    ],
    "wof:lang_x_spoken":[
        "ind",
        "eng"
    ],
    "wof:name":"Ciharalang",
    "wof:placetype":"locality"
},
  "geometry": {"coordinates":[108.4113,-7.3503],"type":"Point"}
}