{
  "type": "Feature",
  "properties": {
    "gn:admin1_code":"38",
    "gn:asciiname":"Tanaeja",
    "gn:country_code":"ID",
    "gn:dem":215,
    "gn:feature_class":"P",
    "gn:feature_code":"PPL",
    "gn:name":"Tanaeja",
    "gn:population":0,
    "gn:timezone":"Asia/Makassar",
    "iso:country":"ID",
    "name:ind_x_preferred":[
        "Tanaeja"
    ],
    "wof:name":"Tanaeja",
    "wof:placetype":"locality"
},
  "geometry": {"coordinates":[120.1956,-5.2662],"type":"Point"}
}