{
  "type": "Feature",
  "properties": {
    "gn:admin1_code":"08",
    "gn:asciiname":"Krukah Lama",
    "gn:country_code":"ID",
    "gn:dem":6,
    "gn:feature_class":"P",
    "gn:feature_code":"PPL",
    "gn:name":"Krukah Lama",
    "gn:population":0,
    "gn:timezone":"Asia/Jakarta",
    "iso:country":"ID",
    "name:ind_x_preferred":[
        "Krukah Lama"
    ],
    "wof:name":"Krukah Lama",
    "wof:placetype":"locality"
},
  "geometry": {"coordinates":[112.7547,-7.2954],"type":"Point"}
}