{
  "type": "Feature",
  "properties": {
    "gn:admin1_code":"7",
    "gn:asciiname":"Tobo",
    "gn:country_code":"ID",
    "gn:dem":92,
    "gn:feature_class":"P",
    "gn:feature_code":"PPL",
    "gn:name":"Tobo",
    "gn:population":0,
    "gn:timezone":"Asia/Jakarta",
    "iso:country":"ID",
    "name:ceb_x_preferred":[
        "Tobo"
    ],
    "name:epo_x_preferred":[
        "Tobo"
    ],
    "name:ind_x_preferred":[
        "Tobo"
    ],
    "name:ita_x_preferred":[
        "Tobo"
    ],
    "name:nld_x_preferred":[
        "Tobo"
    ],
    "name:nno_x_preferred":[
        "Tobo"
    ],
    "name:nor_x_preferred":[
        "Tobo"
    ],
    "name:swe_x_preferred":[
        "Tobo"
    ],
    "wof:lang_x_official":[
        "ind"
    ],
    "wof:lang_x_spoken":[
        "ind",
        "eng"
    ],
    "wof:name":"Tobo",
    "wof:placetype":"locality"
},
  "geometry": {"coordinates":[111.31111,-7.16944],"type":"Point"}
}