{
  "type": "Feature",
  "properties": {
    "gn:admin1_code":"7.0",
    "gn:asciiname":"Kalibata",
    "gn:country_code":"ID",
    "gn:dem":168,
    "gn:feature_class":"P",
    "gn:feature_code":"PPL",
    "gn:name":"Kalibata",
    "gn:population":0,
    "gn:timezone":"Asia/Jakarta",
    "iso:country":"ID",
    "name:ceb_x_preferred":[
        "Kelurahan Kalibata"
    ],
    "name:ind_x_preferred":[
        "Kalibata"
    ],
    "name:jav_x_preferred":[
        "Kalibata"
    ],
    "name:msa_x_preferred":[
        "Kalibata"
    ],
    "name:nld_x_preferred":[
        "Kalibata"
    ],
    "name:sun_x_preferred":[
        "Kalibata"
    ],
    "name:swe_x_preferred":[
        "Kelurahan Kalibata"
    ],
    "wof:name":"Kalibata",
    "wof:placetype":"locality"
},
  "geometry": {"coordinates":[109.00888999999999,-7.27111],"type":"Point"}
}