{
  "type": "Feature",
  "properties": {
    "gn:admin1_code":"8",
    "gn:asciiname":"Malabang",
    "gn:country_code":"ID",
    "gn:dem":28,
    "gn:feature_class":"P",
    "gn:feature_code":"PPL",
    "gn:name":"Malabang",
    "gn:population":0,
    "gn:timezone":"Asia/Jakarta",
    "iso:country":"ID",
    "name:bcl_x_preferred":[
        "Malabang"
    ],
    "name:ceb_x_preferred":[
        "Malabang"
    ],
    "name:deu_x_preferred":[
        "Malabang"
    ],
    "name:fra_x_preferred":[
        "Malabang"
    ],
    "name:ilo_x_preferred":[
        "Malabang"
    ],
    "name:ind_x_preferred":[
        "Malabang"
    ],
    "name:ita_x_preferred":[
        "Malabang"
    ],
    "name:nld_x_preferred":[
        "Malabang"
    ],
    "name:pag_x_preferred":[
        "Malabang"
    ],
    "name:pam_x_preferred":[
        "Malabang"
    ],
    "name:swe_x_preferred":[
        "Malabang"
    ],
    "name:tgl_x_preferred":[
        "Malabang"
    ],
    "name:urd_x_preferred":[
        "\u0645\u0627\u0644\u0627\u0628\u0627\u0646\u06af"
    ],
    "name:vie_x_preferred":[
        "Malabang"
    ],
    "name:war_x_preferred":[
        "Malabang"
    ],
    "wof:name":"Malabang",
    "wof:placetype":"locality"
},
  "geometry": {"coordinates":[113.0968,-7.0835],"type":"Point"}
}