{
  "type": "Feature",
  "properties": {
    "gn:admin1_code":"8",
    "gn:asciiname":"Malabang",
    "gn:country_code":"ID",
    "gn:dem":28,
    "gn:feature_class":"P",
    "gn:feature_code":"PPL",
    "gn:name":"Malabang",
    "gn:population":0,
    "gn:timezone":"Asia/Jakarta",
    "iso:country":"ID",
    "name:ind_x_preferred":[
        "Malabang"
    ],
    "wof:name":"Malabang",
    "wof:placetype":"locality"
},
  "geometry": {"coordinates":[113.0968,-7.0835],"type":"Point"}
}