{
  "type": "Feature",
  "properties": {
    "gn:admin1_code":"7.0",
    "gn:asciiname":"Gentan",
    "gn:country_code":"ID",
    "gn:dem":521,
    "gn:feature_class":"P",
    "gn:feature_code":"PPL",
    "gn:name":"Gentan",
    "gn:population":0,
    "gn:timezone":"Asia/Jakarta",
    "iso:country":"ID",
    "wof:name":"Gentan",
    "wof:placetype":"locality"
},
  "geometry": {"coordinates":[110.44499999999999,-7.33639],"type":"Point"}
}