{
  "type": "Feature",
  "properties": {
    "gn:admin1_code":"26",
    "gn:asciiname":"Batu Tiga Belas",
    "gn:country_code":"ID",
    "gn:dem":36,
    "gn:feature_class":"P",
    "gn:feature_code":"PPL",
    "gn:name":"Batu Tiga Belas",
    "gn:population":0,
    "gn:timezone":"Asia/Jakarta",
    "iso:country":"ID",
    "name:ind_x_preferred":[
        "Batu Tiga Belas"
    ],
    "name:und_x_variant":[
        "Batu XIII"
    ],
    "wof:lang_x_official":[
        "ind"
    ],
    "wof:lang_x_spoken":[
        "ind",
        "eng"
    ],
    "wof:name":"Batu Tiga Belas",
    "wof:placetype":"locality"
},
  "geometry": {"coordinates":[99.06959999999999,3.3461],"type":"Point"}
}