{
  "type": "Feature",
  "properties": {
    "gn:admin1_code":"7.0",
    "gn:asciiname":"Kandangsengkar",
    "gn:country_code":"ID",
    "gn:dem":597,
    "gn:feature_class":"P",
    "gn:feature_code":"PPL",
    "gn:name":"Kandangsengkar",
    "gn:population":0,
    "gn:timezone":"Asia/Jakarta",
    "iso:country":"ID",
    "name:ind_x_preferred":[
        "Kandangsengkar"
    ],
    "wof:name":"Kandangsengkar",
    "wof:placetype":"locality"
},
  "geometry": {"coordinates":[109.29667000000001,-7.28444],"type":"Point"}
}