{
  "type": "Feature",
  "properties": {
    "gn:admin1_code":"30",
    "gn:asciiname":"Rawabolang",
    "gn:country_code":"ID",
    "gn:dem":77,
    "gn:feature_class":"P",
    "gn:feature_code":"PPL",
    "gn:name":"Rawabolang",
    "gn:population":0,
    "gn:timezone":"Asia/Jakarta",
    "iso:country":"ID",
    "name:ind_x_preferred":[
        "Rawabolang"
    ],
    "wof:name":"Rawabolang",
    "wof:placetype":"locality"
},
  "geometry": {"coordinates":[107.43056,-6.5225],"type":"Point"}
}