{
  "type": "Feature",
  "properties": {
    "gn:admin1_code":"35",
    "gn:asciiname":"Gumba",
    "gn:country_code":"ID",
    "gn:dem":10,
    "gn:feature_class":"P",
    "gn:feature_code":"PPL",
    "gn:name":"Gumba",
    "gn:population":0,
    "gn:timezone":"Asia/Jakarta",
    "iso:country":"ID",
    "name:ceb_x_preferred":[
        "Gumba"
    ],
    "name:deu_x_preferred":[
        "Gumba"
    ],
    "name:fra_x_preferred":[
        "Gumba"
    ],
    "name:ind_x_preferred":[
        "Gumba"
    ],
    "name:pol_x_preferred":[
        "Gumba"
    ],
    "name:swe_x_preferred":[
        "Gumba"
    ],
    "wof:lang_x_official":[
        "ind"
    ],
    "wof:lang_x_spoken":[
        "ind",
        "eng"
    ],
    "wof:name":"Gumba",
    "wof:placetype":"locality"
},
  "geometry": {"coordinates":[106.63437,-2.75626],"type":"Point"}
}