{
  "type": "Feature",
  "properties": {
    "gn:admin1_code":"30",
    "gn:asciiname":"Gunungsantri",
    "gn:country_code":"ID",
    "gn:dem":118,
    "gn:feature_class":"P",
    "gn:feature_code":"PPL",
    "gn:name":"Gunungsantri",
    "gn:population":0,
    "gn:timezone":"Asia/Jakarta",
    "iso:country":"ID",
    "name:ind_x_preferred":[
        "Gunungsantri"
    ],
    "wof:name":"Gunungsantri",
    "wof:placetype":"locality"
},
  "geometry": {"coordinates":[108.40555999999999,-6.73722],"type":"Point"}
}