{
  "type": "Feature",
  "properties": {
    "gn:admin1_code":"30.0",
    "gn:asciiname":"Cihaur Kuning",
    "gn:country_code":"ID",
    "gn:dem":144,
    "gn:feature_class":"P",
    "gn:feature_code":"PPL",
    "gn:name":"Cihaur Kuning",
    "gn:population":0,
    "gn:timezone":"Asia/Jakarta",
    "iso:country":"ID",
    "name:ind_x_preferred":[
        "Cihaur Kuning"
    ],
    "wof:name":"Cihaur Kuning",
    "wof:placetype":"locality"
},
  "geometry": {"coordinates":[106.5502,-7.3174],"type":"Point"}
}