{
  "type": "Feature",
  "properties": {
    "gn:admin1_code":"15.0",
    "gn:asciiname":"Tanjungan Dua",
    "gn:country_code":"ID",
    "gn:dem":861,
    "gn:feature_class":"P",
    "gn:feature_code":"PPL",
    "gn:name":"Tanjungan Dua",
    "gn:population":0,
    "gn:timezone":"Asia/Jakarta",
    "iso:country":"ID",
    "name:ind_x_preferred":[
        "Tanjungan Dua"
    ],
    "name:und_x_variant":[
        "Tanjungan 2"
    ],
    "wof:lang_x_official":[
        "ind"
    ],
    "wof:lang_x_spoken":[
        "ind",
        "eng"
    ],
    "wof:name":"Tanjungan Dua",
    "wof:placetype":"locality"
},
  "geometry": {"coordinates":[104.07931000000001,-4.95621],"type":"Point"}
}