{
  "type": "Feature",
  "properties": {
    "gn:admin1_code":"30",
    "gn:asciiname":"Nampel",
    "gn:country_code":"ID",
    "gn:dem":1201,
    "gn:feature_class":"P",
    "gn:feature_code":"PPL",
    "gn:name":"Nampel",
    "gn:population":0,
    "gn:timezone":"Asia/Jakarta",
    "iso:country":"ID",
    "wof:name":"Nampel",
    "wof:placetype":"locality"
},
  "geometry": {"coordinates":[107.69444,-7.15],"type":"Point"}
}