{
  "type": "Feature",
  "properties": {
    "gn:admin1_code":"8",
    "gn:asciiname":"Buntasan",
    "gn:country_code":"ID",
    "gn:dem":298,
    "gn:feature_class":"P",
    "gn:feature_code":"PPL",
    "gn:name":"Buntasan",
    "gn:population":0,
    "gn:timezone":"Asia/Jakarta",
    "iso:country":"ID",
    "name:ind_x_preferred":[
        "Buntasan"
    ],
    "wof:name":"Buntasan",
    "wof:placetype":"locality"
},
  "geometry": {"coordinates":[111.98099999999999,-7.0317],"type":"Point"}
}