{
  "type": "Feature",
  "properties": {
    "gn:admin1_code":"30.0",
    "gn:asciiname":"Cirompang",
    "gn:country_code":"ID",
    "gn:dem":435,
    "gn:feature_class":"P",
    "gn:feature_code":"PPL",
    "gn:name":"Cirompang",
    "gn:population":0,
    "gn:timezone":"Asia/Jakarta",
    "iso:country":"ID",
    "name:ind_x_preferred":[
        "Cirompang"
    ],
    "wof:lang_x_official":[
        "ind"
    ],
    "wof:lang_x_spoken":[
        "ind",
        "eng"
    ],
    "wof:name":"Cirompang",
    "wof:placetype":"locality"
},
  "geometry": {"coordinates":[107.6075,-7.4515],"type":"Point"}
}