{
  "type": "Feature",
  "properties": {
    "gn:admin1_code":"15.0",
    "gn:asciiname":"Kubugajah",
    "gn:country_code":"ID",
    "gn:dem":103,
    "gn:feature_class":"P",
    "gn:feature_code":"PPL",
    "gn:name":"Kubugajah",
    "gn:population":0,
    "gn:timezone":"Asia/Jakarta",
    "iso:country":"ID",
    "name:ind_x_preferred":[
        "Kubugajah"
    ],
    "name:und_x_variant":[
        "Koeboegadjah"
    ],
    "wof:name":"Kubugajah",
    "wof:placetype":"locality"
},
  "geometry": {"coordinates":[104.59529999999999,-5.8242],"type":"Point"}
}