{
  "type": "Feature",
  "properties": {
    "gn:admin1_code":"32.0",
    "gn:asciiname":"Umbulan Haropan",
    "gn:country_code":"ID",
    "gn:dem":57,
    "gn:feature_class":"P",
    "gn:feature_code":"PPL",
    "gn:name":"Umbulan Haropan",
    "gn:population":0,
    "gn:timezone":"Asia/Jakarta",
    "iso:country":"ID",
    "name:ind_x_preferred":[
        "Umbulan Haropan"
    ],
    "wof:name":"Umbulan Haropan",
    "wof:placetype":"locality"
},
  "geometry": {"coordinates":[104.49874,-4.08901],"type":"Point"}
}