{
  "type": "Feature",
  "properties": {
    "gn:admin1_code":"1.0",
    "gn:asciiname":"Lhokuenan",
    "gn:country_code":"ID",
    "gn:dem":950,
    "gn:feature_class":"P",
    "gn:feature_code":"PPL",
    "gn:name":"Lhokuenan",
    "gn:population":0,
    "gn:timezone":"Asia/Jakarta",
    "iso:country":"ID",
    "name:ind_x_preferred":[
        "Lhokuenan"
    ],
    "name:und_x_variant":[
        "Lhokoe\u00ebnam",
        "Lho\u2019oe\u00ebnan",
        "Lhokuenam"
    ],
    "wof:lang_x_official":[
        "ind"
    ],
    "wof:lang_x_spoken":[
        "ind",
        "eng"
    ],
    "wof:name":"Lhokuenan",
    "wof:placetype":"locality"
},
  "geometry": {"coordinates":[97.69029999999999,3.7013],"type":"Point"}
}