{
  "type": "Feature",
  "properties": {
    "gn:admin1_code":"07",
    "gn:asciiname":"Kuwarasan",
    "gn:country_code":"ID",
    "gn:dem":639,
    "gn:feature_class":"P",
    "gn:feature_code":"PPL",
    "gn:name":"Kuwarasan",
    "gn:population":0,
    "gn:timezone":"Asia/Jakarta",
    "iso:country":"ID",
    "wof:name":"Kuwarasan",
    "wof:placetype":"locality"
},
  "geometry": {"coordinates":[110.35972,-7.2725],"type":"Point"}
}