{
  "type": "Feature",
  "properties": {
    "gn:admin1_code":"18",
    "gn:asciiname":"Keling",
    "gn:country_code":"ID",
    "gn:dem":624,
    "gn:feature_class":"P",
    "gn:feature_code":"PPL",
    "gn:name":"Keling",
    "gn:population":0,
    "gn:timezone":"Asia/Makassar",
    "iso:country":"ID",
    "name:ind_x_preferred":[
        "Keling"
    ],
    "name:msa_x_preferred":[
        "Keling"
    ],
    "name:tam_x_preferred":[
        "\u0b9a\u0b9e\u0bcd\u0b9a\u0bbf\u0b95\u0bcd\u0b95\u0bc2\u0bb2\u0bbf"
    ],
    "wof:name":"Keling",
    "wof:placetype":"locality"
},
  "geometry": {"coordinates":[120.42440000000001,-8.3826],"type":"Point"}
}