{
  "type": "Feature",
  "properties": {
    "gn:admin1_code":"1",
    "gn:asciiname":"Paya Dua",
    "gn:country_code":"ID",
    "gn:dem":18,
    "gn:feature_class":"P",
    "gn:feature_code":"PPL",
    "gn:name":"Paya Dua",
    "gn:population":0,
    "gn:timezone":"Asia/Jakarta",
    "iso:country":"ID",
    "name:ind_x_preferred":[
        "Paya Dua"
    ],
    "wof:name":"Paya Dua",
    "wof:placetype":"locality"
},
  "geometry": {"coordinates":[96.0702,4.3766],"type":"Point"}
}