{
  "type": "Feature",
  "properties": {
    "gn:admin1_code":"7.0",
    "gn:asciiname":"Dukuh Kidul",
    "gn:country_code":"ID",
    "gn:dem":118,
    "gn:feature_class":"P",
    "gn:feature_code":"PPL",
    "gn:name":"Dukuh Kidul",
    "gn:population":0,
    "gn:timezone":"Asia/Jakarta",
    "iso:country":"ID",
    "name:ind_x_preferred":[
        "Dukuh Kidul"
    ],
    "wof:name":"Dukuh Kidul",
    "wof:placetype":"locality"
},
  "geometry": {"coordinates":[109.41167,-7.35639],"type":"Point"}
}