{
  "type": "Feature",
  "properties": {
    "gn:admin1_code":"30",
    "gn:asciiname":"Pulogadung Satu",
    "gn:country_code":"ID",
    "gn:dem":4,
    "gn:feature_class":"P",
    "gn:feature_code":"PPL",
    "gn:name":"Pulogadung Satu",
    "gn:population":0,
    "gn:timezone":"Asia/Jakarta",
    "iso:country":"ID",
    "name:ind_x_preferred":[
        "Pulogadung Satu"
    ],
    "name:und_x_variant":[
        "Pulogadung 1"
    ],
    "wof:name":"Pulogadung Satu",
    "wof:placetype":"locality"
},
  "geometry": {"coordinates":[107.44693999999998,-6.25333],"type":"Point"}
}