{
  "type": "Feature",
  "properties": {
    "gn:admin1_code":"26",
    "gn:asciiname":"Siborutorop",
    "gn:country_code":"ID",
    "gn:dem":929,
    "gn:feature_class":"P",
    "gn:feature_code":"PPL",
    "gn:name":"Siborutorop",
    "gn:population":0,
    "gn:timezone":"Asia/Jakarta",
    "iso:country":"ID",
    "name:ind_x_preferred":[
        "Siborutorop"
    ],
    "wof:name":"Siborutorop",
    "wof:placetype":"locality"
},
  "geometry": {"coordinates":[98.9288,2.3527],"type":"Point"}
}