{
  "type": "Feature",
  "properties": {
    "gn:admin1_code":"30",
    "gn:asciiname":"Parungseah Kidul",
    "gn:country_code":"ID",
    "gn:dem":667,
    "gn:feature_class":"P",
    "gn:feature_code":"PPL",
    "gn:name":"Parungseah Kidul",
    "gn:population":0,
    "gn:timezone":"Asia/Jakarta",
    "iso:country":"ID",
    "name:ind_x_preferred":[
        "Parungseah Kidul"
    ],
    "wof:name":"Parungseah Kidul",
    "wof:placetype":"locality"
},
  "geometry": {"coordinates":[106.92055999999999,-6.89861],"type":"Point"}
}