{
  "type": "Feature",
  "properties": {
    "gn:admin1_code":"26",
    "gn:asciiname":"Hinaikiri",
    "gn:country_code":"ID",
    "gn:dem":9,
    "gn:feature_class":"P",
    "gn:feature_code":"PPL",
    "gn:name":"Hinaikiri",
    "gn:population":0,
    "gn:timezone":"Asia/Jakarta",
    "iso:country":"ID",
    "name:ind_x_preferred":[
        "Hinaikiri"
    ],
    "wof:name":"Hinaikiri",
    "wof:placetype":"locality"
},
  "geometry": {"coordinates":[98.47620000000001,3.8507],"type":"Point"}
}