{
  "type": "Feature",
  "properties": {
    "gn:admin1_code":"8.0",
    "gn:asciiname":"Prapatan",
    "gn:country_code":"ID",
    "gn:dem":546,
    "gn:feature_class":"P",
    "gn:feature_code":"PPL",
    "gn:name":"Prapatan",
    "gn:population":0,
    "gn:timezone":"Asia/Jakarta",
    "iso:country":"ID",
    "name:ind_x_preferred":[
        "Prapatan"
    ],
    "wof:name":"Prapatan",
    "wof:placetype":"locality"
},
  "geometry": {"coordinates":[113.0609,-8.1089],"type":"Point"}
}