{
  "type": "Feature",
  "properties": {
    "gn:admin1_code":"41.0",
    "gn:asciiname":"Banggo",
    "gn:country_code":"ID",
    "gn:dem":1174,
    "gn:feature_class":"P",
    "gn:feature_code":"PPL",
    "gn:name":"Banggo",
    "gn:population":0,
    "gn:timezone":"Asia/Makassar",
    "iso:country":"ID",
    "name:ind_x_preferred":[
        "Banggo"
    ],
    "wof:name":"Banggo",
    "wof:placetype":"locality"
},
  "geometry": {"coordinates":[119.377,-2.9447],"type":"Point"}
}