{
  "type": "Feature",
  "properties": {
    "gn:admin1_code":"26",
    "gn:asciiname":"Kampung Batu Tiga",
    "gn:country_code":"ID",
    "gn:dem":250,
    "gn:feature_class":"P",
    "gn:feature_code":"PPL",
    "gn:name":"Kampung Batu Tiga",
    "gn:population":0,
    "gn:timezone":"Asia/Jakarta",
    "iso:country":"ID",
    "name:ind_x_preferred":[
        "Kampung Batu Tiga"
    ],
    "name:und_x_variant":[
        "Kampung Batu 3"
    ],
    "wof:lang_x_official":[
        "ind"
    ],
    "wof:lang_x_spoken":[
        "ind",
        "eng"
    ],
    "wof:name":"Kampung Batu Tiga",
    "wof:placetype":"locality"
},
  "geometry": {"coordinates":[99.1433,2.9642],"type":"Point"}
}