{
  "type": "Feature",
  "properties": {
    "gn:admin1_code":"18",
    "gn:asciiname":"Lema",
    "gn:country_code":"ID",
    "gn:dem":207,
    "gn:feature_class":"P",
    "gn:feature_code":"PPL",
    "gn:name":"Lema",
    "gn:population":0,
    "gn:timezone":"Asia/Makassar",
    "iso:country":"ID",
    "name:cat_x_preferred":[
        "Lema"
    ],
    "name:ceb_x_preferred":[
        "Lema"
    ],
    "name:deu_x_preferred":[
        "Lema"
    ],
    "name:eus_x_preferred":[
        "Lema"
    ],
    "name:glg_x_preferred":[
        "Lema"
    ],
    "name:ind_x_preferred":[
        "Lema"
    ],
    "name:ita_x_preferred":[
        "Lema"
    ],
    "name:por_x_preferred":[
        "Lema"
    ],
    "name:spa_x_preferred":[
        "Lema"
    ],
    "name:swe_x_preferred":[
        "Lema"
    ],
    "wof:lang_x_official":[
        "ind"
    ],
    "wof:lang_x_spoken":[
        "ind",
        "eng"
    ],
    "wof:name":"Lema",
    "wof:placetype":"locality"
},
  "geometry": {"coordinates":[121.9314,-8.8168],"type":"Point"}
}