{
  "type": "Feature",
  "properties": {
    "gn:admin1_code":"7.0",
    "gn:asciiname":"Jogodayah",
    "gn:country_code":"ID",
    "gn:dem":234,
    "gn:feature_class":"P",
    "gn:feature_code":"PPL",
    "gn:name":"Jogodayah",
    "gn:population":0,
    "gn:timezone":"Asia/Jakarta",
    "iso:country":"ID",
    "wof:name":"Jogodayah",
    "wof:placetype":"locality"
},
  "geometry": {"coordinates":[110.63861,-7.605],"type":"Point"}
}