{
  "type": "Feature",
  "properties": {
    "gn:admin1_code":"8",
    "gn:asciiname":"Sawur",
    "gn:country_code":"ID",
    "gn:dem":517,
    "gn:feature_class":"P",
    "gn:feature_code":"PPL",
    "gn:name":"Sawur",
    "gn:population":0,
    "gn:timezone":"Asia/Jakarta",
    "iso:country":"ID",
    "name:ind_x_preferred":[
        "Sawur"
    ],
    "wof:name":"Sawur",
    "wof:placetype":"locality"
},
  "geometry": {"coordinates":[111.63379999999999,-7.8867],"type":"Point"}
}