{
  "type": "Feature",
  "properties": {
    "gn:admin1_code":"33.0",
    "gn:asciiname":"Kaduronyok",
    "gn:country_code":"ID",
    "gn:dem":221,
    "gn:feature_class":"P",
    "gn:feature_code":"PPLA4",
    "gn:name":"Kaduronyok",
    "gn:population":0,
    "gn:timezone":"Asia/Jakarta",
    "iso:country":"ID",
    "name:ind_x_preferred":[
        "Kaduronyok"
    ],
    "wof:lang_x_official":[
        "ind"
    ],
    "wof:lang_x_spoken":[
        "ind",
        "eng"
    ],
    "wof:name":"Kaduronyok",
    "wof:placetype":"locality"
},
  "geometry": {"coordinates":[105.9607,-6.3731],"type":"Point"}
}