{
  "type": "Feature",
  "properties": {
    "gn:admin1_code":"1",
    "gn:asciiname":"Pajaujok",
    "gn:country_code":"ID",
    "gn:dem":4,
    "gn:feature_class":"P",
    "gn:feature_code":"PPL",
    "gn:name":"Pajaujok",
    "gn:population":0,
    "gn:timezone":"Asia/Jakarta",
    "iso:country":"ID",
    "name:ind_x_preferred":[
        "Pajaujok"
    ],
    "wof:name":"Pajaujok",
    "wof:placetype":"locality"
},
  "geometry": {"coordinates":[98.0184,4.4461],"type":"Point"}
}