{
  "type": "Feature",
  "properties": {
    "gn:admin1_code":"38",
    "gn:asciiname":"Kombe",
    "gn:country_code":"ID",
    "gn:dem":196,
    "gn:feature_class":"P",
    "gn:feature_code":"PPL",
    "gn:name":"Kombe",
    "gn:population":0,
    "gn:timezone":"Asia/Makassar",
    "iso:country":"ID",
    "name:ceb_x_preferred":[
        "Kombe"
    ],
    "name:deu_x_preferred":[
        "Kombe"
    ],
    "name:ind_x_preferred":[
        "Kombe"
    ],
    "name:swe_x_preferred":[
        "Kombe"
    ],
    "wof:lang_x_official":[
        "ind"
    ],
    "wof:lang_x_spoken":[
        "ind",
        "eng"
    ],
    "wof:name":"Kombe",
    "wof:placetype":"locality"
},
  "geometry": {"coordinates":[120.5198,-6.0602],"type":"Point"}
}