{
  "type": "Feature",
  "properties": {
    "gn:admin1_code":"0.0",
    "gn:asciiname":"Parbakalan",
    "gn:country_code":"ID",
    "gn:dem":1478,
    "gn:feature_class":"P",
    "gn:feature_code":"PPL",
    "gn:name":"Parbakalan",
    "gn:population":0,
    "gn:timezone":"Asia/Jakarta",
    "iso:country":"ID",
    "name:ind_x_preferred":[
        "Parbakalan"
    ],
    "wof:lang_x_official":[
        "ind"
    ],
    "wof:lang_x_spoken":[
        "ind",
        "eng"
    ],
    "wof:name":"Parbakalan",
    "wof:placetype":"locality"
},
  "geometry": {"coordinates":[98.46185,2.63705],"type":"Point"}
}