{
  "type": "Feature",
  "properties": {
    "gn:admin1_code":"18",
    "gn:asciiname":"Watuturan",
    "gn:country_code":"ID",
    "gn:dem":44,
    "gn:feature_class":"P",
    "gn:feature_code":"PPL",
    "gn:name":"Watuturan",
    "gn:population":0,
    "gn:timezone":"Asia/Makassar",
    "iso:country":"ID",
    "name:ind_x_preferred":[
        "Watuturan"
    ],
    "wof:name":"Watuturan",
    "wof:placetype":"locality"
},
  "geometry": {"coordinates":[122.1752,-8.5817],"type":"Point"}
}