{
  "type": "Feature",
  "properties": {
    "gn:admin1_code":"7",
    "gn:asciiname":"Karanggedang",
    "gn:country_code":"ID",
    "gn:dem":121,
    "gn:feature_class":"P",
    "gn:feature_code":"PPL",
    "gn:name":"Karanggedang",
    "gn:population":0,
    "gn:timezone":"Asia/Jakarta",
    "iso:country":"ID",
    "name:ind_x_preferred":[
        "Karanggedang"
    ],
    "wof:name":"Karanggedang",
    "wof:placetype":"locality"
},
  "geometry": {"coordinates":[109.3707,-7.0981],"type":"Point"}
}