{
  "type": "Feature",
  "properties": {
    "gn:admin1_code":"37",
    "gn:asciiname":"Parit Tengah Tiga",
    "gn:country_code":"ID",
    "gn:dem":5,
    "gn:feature_class":"P",
    "gn:feature_code":"PPL",
    "gn:name":"Parit Tengah Tiga",
    "gn:population":0,
    "gn:timezone":"Asia/Jakarta",
    "iso:country":"ID",
    "name:ind_x_preferred":[
        "Parit Tengah Tiga"
    ],
    "wof:name":"Parit Tengah Tiga",
    "wof:placetype":"locality"
},
  "geometry": {"coordinates":[103.30177,-0.48968],"type":"Point"}
}