{
  "type": "Feature",
  "properties": {
    "gn:admin1_code":"7",
    "gn:asciiname":"Bego",
    "gn:country_code":"ID",
    "gn:dem":67,
    "gn:feature_class":"P",
    "gn:feature_code":"PPL",
    "gn:name":"Bego",
    "gn:population":0,
    "gn:timezone":"Asia/Jakarta",
    "iso:country":"ID",
    "name:ceb_x_preferred":[
        "Bego"
    ],
    "name:deu_x_preferred":[
        "Bego"
    ],
    "name:ind_x_preferred":[
        "Bego"
    ],
    "name:swe_x_preferred":[
        "Bego"
    ],
    "wof:lang_x_official":[
        "ind"
    ],
    "wof:lang_x_spoken":[
        "ind",
        "eng"
    ],
    "wof:name":"Bego",
    "wof:placetype":"locality"
},
  "geometry": {"coordinates":[110.7484,-6.7027],"type":"Point"}
}