{
  "type": "Feature",
  "properties": {
    "gn:admin1_code":"26.0",
    "gn:asciiname":"Dano",
    "gn:country_code":"ID",
    "gn:dem":172,
    "gn:feature_class":"P",
    "gn:feature_code":"PPL",
    "gn:name":"Dano",
    "gn:population":0,
    "gn:timezone":"Asia/Jakarta",
    "iso:country":"ID",
    "name:ceb_x_preferred":[
        "Dano"
    ],
    "name:deu_x_preferred":[
        "Dano"
    ],
    "name:fra_x_preferred":[
        "Dano"
    ],
    "name:ind_x_preferred":[
        "Dano"
    ],
    "name:nld_x_preferred":[
        "Dano"
    ],
    "name:por_x_preferred":[
        "Dano"
    ],
    "name:slk_x_preferred":[
        "Dano"
    ],
    "name:swe_x_preferred":[
        "Dano"
    ],
    "wof:name":"Dano",
    "wof:placetype":"locality"
},
  "geometry": {"coordinates":[98.69410000000001,2.0133],"type":"Point"}
}