{
  "type": "Feature",
  "properties": {
    "gn:admin1_code":"38.0",
    "gn:asciiname":"Masiku",
    "gn:country_code":"ID",
    "gn:dem":405,
    "gn:feature_class":"P",
    "gn:feature_code":"PPL",
    "gn:name":"Masiku",
    "gn:population":0,
    "gn:timezone":"Asia/Makassar",
    "iso:country":"ID",
    "name:ind_x_preferred":[
        "Masiku"
    ],
    "wof:name":"Masiku",
    "wof:placetype":"locality"
},
  "geometry": {"coordinates":[121.6083,-2.8729],"type":"Point"}
}