{
  "type": "Feature",
  "properties": {
    "gn:admin1_code":"7.0",
    "gn:asciiname":"Situ",
    "gn:country_code":"ID",
    "gn:dem":516,
    "gn:feature_class":"P",
    "gn:feature_code":"PPL",
    "gn:name":"Situ",
    "gn:population":0,
    "gn:timezone":"Asia/Jakarta",
    "iso:country":"ID",
    "name:ceb_x_preferred":[
        "Situ"
    ],
    "name:ind_x_preferred":[
        "Situ"
    ],
    "name:swe_x_preferred":[
        "Situ"
    ],
    "wof:lang_x_official":[
        "ind"
    ],
    "wof:lang_x_spoken":[
        "ind",
        "eng"
    ],
    "wof:name":"Situ",
    "wof:placetype":"locality"
},
  "geometry": {"coordinates":[108.6452,-7.2559],"type":"Point"}
}