{
  "type": "Feature",
  "properties": {
    "gn:admin1_code":"34",
    "gn:asciiname":"Balangga Utara",
    "gn:country_code":"ID",
    "gn:dem":16,
    "gn:feature_class":"P",
    "gn:feature_code":"PPL",
    "gn:name":"Balangga Utara",
    "gn:population":0,
    "gn:timezone":"Asia/Makassar",
    "iso:country":"ID",
    "name:ind_x_preferred":[
        "Balangga Utara"
    ],
    "wof:name":"Balangga Utara",
    "wof:placetype":"locality"
},
  "geometry": {"coordinates":[122.9554,0.5651],"type":"Point"}
}