{
  "type": "Feature",
  "properties": {
    "gn:admin1_code":"7.0",
    "gn:asciiname":"Ratambulu",
    "gn:country_code":"ID",
    "gn:dem":142,
    "gn:feature_class":"P",
    "gn:feature_code":"PPL",
    "gn:name":"Ratambulu",
    "gn:population":0,
    "gn:timezone":"Asia/Jakarta",
    "iso:country":"ID",
    "name:ind_x_preferred":[
        "Ratambulu"
    ],
    "wof:name":"Ratambulu",
    "wof:placetype":"locality"
},
  "geometry": {"coordinates":[109.40833000000001,-7.32028],"type":"Point"}
}