{
  "type": "Feature",
  "properties": {
    "gn:admin1_code":"1.0",
    "gn:asciiname":"Matang Sijuk Barat",
    "gn:country_code":"ID",
    "gn:dem":11,
    "gn:feature_class":"P",
    "gn:feature_code":"PPL",
    "gn:name":"Matang Sijuk Barat",
    "gn:population":0,
    "gn:timezone":"Asia/Jakarta",
    "iso:country":"ID",
    "name:ind_x_preferred":[
        "Matang Sijuk Barat"
    ],
    "name:und_x_variant":[
        "Matangseusiju-barat",
        "Matangseusidju-barat"
    ],
    "wof:name":"Matang Sijuk Barat",
    "wof:placetype":"locality"
},
  "geometry": {"coordinates":[97.3356,5.112],"type":"Point"}
}