{
  "type": "Feature",
  "properties": {
    "gn:admin1_code":"18",
    "gn:asciiname":"Noefmuti",
    "gn:country_code":"ID",
    "gn:dem":522,
    "gn:feature_class":"P",
    "gn:feature_code":"PPL",
    "gn:name":"Noefmuti",
    "gn:population":0,
    "gn:timezone":"Asia/Makassar",
    "iso:country":"ID",
    "wof:name":"Noefmuti",
    "wof:placetype":"locality"
},
  "geometry": {"coordinates":[124.78583,-9.29417],"type":"Point"}
}