{
  "type": "Feature",
  "properties": {
    "gn:admin1_code":"32.0",
    "gn:asciiname":"Nusobakti",
    "gn:country_code":"ID",
    "gn:dem":67,
    "gn:feature_class":"P",
    "gn:feature_code":"PPL",
    "gn:name":"Nusobakti",
    "gn:population":0,
    "gn:timezone":"Asia/Jakarta",
    "iso:country":"ID",
    "name:ind_x_preferred":[
        "Nusobakti"
    ],
    "wof:name":"Nusobakti",
    "wof:placetype":"locality"
},
  "geometry": {"coordinates":[104.60675000000001,-4.20575],"type":"Point"}
}