{
  "type": "Feature",
  "properties": {
    "gn:admin1_code":"26",
    "gn:asciiname":"Perkampungan Syekh Ismail Abdul Wahab",
    "gn:country_code":"ID",
    "gn:dem":12,
    "gn:feature_class":"P",
    "gn:feature_code":"PPL",
    "gn:name":"Perkampungan Syekh Ismail Abdul Wahab",
    "gn:population":0,
    "gn:timezone":"Asia/Jakarta",
    "iso:country":"ID",
    "name:ind_x_preferred":[
        "Perkampungan Syekh Ismail Abdul Wahab"
    ],
    "name:und_x_variant":[
        "Perkampungan Syech Ismail Abdul Wahab"
    ],
    "wof:name":"Perkampungan Syekh Ismail Abdul Wahab",
    "wof:placetype":"locality"
},
  "geometry": {"coordinates":[99.59699999999999,3.0961],"type":"Point"}
}