{
  "type": "Feature",
  "properties": {
    "gn:admin1_code":"18.0",
    "gn:asciiname":"Nualeta",
    "gn:country_code":"ID",
    "gn:dem":1273,
    "gn:feature_class":"P",
    "gn:feature_code":"PPL",
    "gn:name":"Nualeta",
    "gn:population":0,
    "gn:timezone":"Asia/Makassar",
    "iso:country":"ID",
    "name:ind_x_preferred":[
        "Nualeta"
    ],
    "wof:name":"Nualeta",
    "wof:placetype":"locality"
},
  "geometry": {"coordinates":[121.87260000000001,-8.7076],"type":"Point"}
}