{
  "type": "Feature",
  "properties": {
    "gn:admin1_code":"10",
    "gn:asciiname":"Jebresan",
    "gn:country_code":"ID",
    "gn:dem":117,
    "gn:feature_class":"P",
    "gn:feature_code":"PPL",
    "gn:name":"Jebresan",
    "gn:population":0,
    "gn:timezone":"Asia/Jakarta",
    "iso:country":"ID",
    "wof:name":"Jebresan",
    "wof:placetype":"locality"
},
  "geometry": {"coordinates":[110.46611,-7.78806],"type":"Point"}
}