{
  "type": "Feature",
  "properties": {
    "gn:admin1_code":"33.0",
    "gn:asciiname":"Cimangpang",
    "gn:country_code":"ID",
    "gn:dem":7,
    "gn:feature_class":"P",
    "gn:feature_code":"PPL",
    "gn:name":"Cimangpang",
    "gn:population":0,
    "gn:timezone":"Asia/Jakarta",
    "iso:country":"ID",
    "name:ind_x_preferred":[
        "Cimangpang"
    ],
    "wof:name":"Cimangpang",
    "wof:placetype":"locality"
},
  "geometry": {"coordinates":[106.22,-6.91946],"type":"Point"}
}