{
  "type": "Feature",
  "properties": {
    "gn:admin1_code":"21",
    "gn:asciiname":"Labea",
    "gn:country_code":"ID",
    "gn:dem":13,
    "gn:feature_class":"P",
    "gn:feature_code":"PPL",
    "gn:name":"Labea",
    "gn:population":0,
    "gn:timezone":"Asia/Makassar",
    "iso:country":"ID",
    "name:ind_x_preferred":[
        "Labea"
    ],
    "wof:name":"Labea",
    "wof:placetype":"locality"
},
  "geometry": {"coordinates":[119.66972,-0.77417],"type":"Point"}
}