{
  "type": "Feature",
  "properties": {
    "gn:admin1_code":"0.0",
    "gn:asciiname":"Bagankayuara",
    "gn:cc2":"ID",
    "gn:country_code":"ID",
    "gn:dem":10,
    "gn:feature_class":"P",
    "gn:feature_code":"PPL",
    "gn:name":"Bagankayuara",
    "gn:population":0,
    "gn:timezone":"Asia/Jakarta",
    "iso:country":"ID",
    "name:und_x_variant":[
        "Bagankajuara",
        "Bagankajoeara",
        "Bagankayuara"
    ],
    "wof:lang_x_official":[
        "ind"
    ],
    "wof:lang_x_spoken":[
        "ind",
        "eng"
    ],
    "wof:name":"Bagankayuara",
    "wof:placetype":"locality"
},
  "geometry": {"coordinates":[105.65000000000001,-3.53333],"type":"Point"}
}