{
  "type": "Feature",
  "properties": {
    "gn:admin1_code":"18",
    "gn:asciiname":"Marobatong",
    "gn:country_code":"ID",
    "gn:dem":808,
    "gn:feature_class":"P",
    "gn:feature_code":"PPL",
    "gn:name":"Marobatong",
    "gn:population":0,
    "gn:timezone":"Asia/Makassar",
    "iso:country":"ID",
    "name:ind_x_preferred":[
        "Marobatong"
    ],
    "wof:name":"Marobatong",
    "wof:placetype":"locality"
},
  "geometry": {"coordinates":[120.8978,-8.5056],"type":"Point"}
}