{
  "type": "Feature",
  "properties": {
    "gn:admin1_code":"7",
    "gn:asciiname":"Sukadana",
    "gn:country_code":"ID",
    "gn:dem":77,
    "gn:feature_class":"P",
    "gn:feature_code":"PPL",
    "gn:name":"Sukadana",
    "gn:population":0,
    "gn:timezone":"Asia/Jakarta",
    "iso:country":"ID",
    "name:ind_x_preferred":[
        "Sukadana"
    ],
    "wof:name":"Sukadana",
    "wof:placetype":"locality"
},
  "geometry": {"coordinates":[109.76806000000001,-7.65361],"type":"Point"}
}