{
  "type": "Feature",
  "properties": {
    "gn:admin1_code":"11.0",
    "gn:asciiname":"Puduk",
    "gn:country_code":"ID",
    "gn:dem":2,
    "gn:feature_class":"P",
    "gn:feature_code":"PPL",
    "gn:name":"Puduk",
    "gn:population":0,
    "gn:timezone":"Asia/Pontianak",
    "iso:country":"ID",
    "name:ind_x_preferred":[
        "Puduk"
    ],
    "wof:name":"Puduk",
    "wof:placetype":"locality"
},
  "geometry": {"coordinates":[109.16531000000001,1.53888],"type":"Point"}
}