{
  "type": "Feature",
  "properties": {
    "gn:admin1_code":"07",
    "gn:asciiname":"Sukabumi",
    "gn:country_code":"ID",
    "gn:dem":972,
    "gn:feature_class":"P",
    "gn:feature_code":"PPL",
    "gn:name":"Sukabumi",
    "gn:population":0,
    "gn:timezone":"Asia/Jakarta",
    "iso:country":"ID",
    "wof:name":"Sukabumi",
    "wof:placetype":"locality"
},
  "geometry": {"coordinates":[110.51582999999999,-7.515],"type":"Point"}
}