{
  "type": "Feature",
  "properties": {
    "gn:admin1_code":"07",
    "gn:asciiname":"Sukabumi",
    "gn:country_code":"ID",
    "gn:dem":972,
    "gn:feature_class":"P",
    "gn:feature_code":"PPL",
    "gn:name":"Sukabumi",
    "gn:population":0,
    "gn:timezone":"Asia/Jakarta",
    "iso:country":"ID",
    "name:afr_x_preferred":[
        "Sukabumi"
    ],
    "name:ara_x_preferred":[
        "\u0633\u0648\u0643\u0627\u0628\u0648\u0645\u064a"
    ],
    "name:azb_x_preferred":[
        "\u0633\u0648\u06a9\u0627\u0628\u0648\u0645\u06cc"
    ],
    "name:aze_x_preferred":[
        "Sukabumi"
    ],
    "name:ceb_x_preferred":[
        "Sukabumi"
    ],
    "name:deu_x_preferred":[
        "Sukabumi"
    ],
    "name:fas_x_preferred":[
        "\u0633\u0648\u06a9\u0627\u0628\u0648\u0645\u06cc"
    ],
    "name:fra_x_preferred":[
        "Sukabumi"
    ],
    "name:heb_x_preferred":[
        "\u05e1\u05d5\u05e7\u05d1\u05d5\u05de\u05d9"
    ],
    "name:hun_x_preferred":[
        "Sukabumi"
    ],
    "name:ind_x_preferred":[
        "Kota Sukabumi"
    ],
    "name:ita_x_preferred":[
        "Sukabumi"
    ],
    "name:jav_x_preferred":[
        "Kutha Sukabumi"
    ],
    "name:jpn_x_preferred":[
        "\u30b9\u30ab\u30d6\u30df"
    ],
    "name:kat_x_preferred":[
        "\u10e1\u10e3\u10d9\u10d0\u10d1\u10e3\u10db\u10d8"
    ],
    "name:kor_x_preferred":[
        "\uc218\uce74\ubd80\ubbf8"
    ],
    "name:mal_x_preferred":[
        "\u0d38\u0d41\u0d15\u0d2c\u0d41\u0d2e\u0d3f"
    ],
    "name:mlg_x_preferred":[
        "Kota Sukabumi"
    ],
    "name:nld_x_preferred":[
        "Sukabumi"
    ],
    "name:nor_x_preferred":[
        "Sukabumi"
    ],
    "name:pol_x_preferred":[
        "Sukabumi"
    ],
    "name:ron_x_preferred":[
        "Sukabumi"
    ],
    "name:rus_x_preferred":[
        "\u0421\u0443\u043a\u0430\u0431\u0443\u043c\u0438"
    ],
    "name:sun_x_preferred":[
        "Kota Sukabumi"
    ],
    "name:swe_x_preferred":[
        "Sukabumi"
    ],
    "name:tam_x_preferred":[
        "\u0b9a\u0bc1\u0b95\u0bcd\u0b95\u0bbe\u0baa\u0bc2\u0bae\u0bbf"
    ],
    "name:tur_x_preferred":[
        "Sukabumi"
    ],
    "name:ukr_x_preferred":[
        "\u0421\u0443\u043a\u0430\u0431\u0443\u043c\u0456"
    ],
    "name:urd_x_preferred":[
        "\u0633\u0648\u06a9\u0627\u0628\u0648\u0645\u06cc"
    ],
    "name:war_x_preferred":[
        "Sukabumi"
    ],
    "name:zho_x_preferred":[
        "\u8607\u52a0\u6b66\u7709"
    ],
    "wof:lang_x_official":[
        "ind"
    ],
    "wof:lang_x_spoken":[
        "ind",
        "eng"
    ],
    "wof:name":"Sukabumi",
    "wof:placetype":"locality"
},
  "geometry": {"coordinates":[110.51582999999999,-7.515],"type":"Point"}
}