{
  "type": "Feature",
  "properties": {
    "gn:admin1_code":"7",
    "gn:asciiname":"Senet",
    "gn:country_code":"ID",
    "gn:dem":933,
    "gn:feature_class":"P",
    "gn:feature_code":"PPL",
    "gn:name":"Senet",
    "gn:population":0,
    "gn:timezone":"Asia/Jakarta",
    "iso:country":"ID",
    "name:ara_x_preferred":[
        "\u0633\u064a\u0646\u064a\u062a"
    ],
    "name:aze_x_preferred":[
        "Senet"
    ],
    "name:bre_x_preferred":[
        "Senet"
    ],
    "name:bul_x_preferred":[
        "\u0421\u0435\u043d\u0435\u0442"
    ],
    "name:cat_x_preferred":[
        "Senet"
    ],
    "name:ces_x_preferred":[
        "Senet"
    ],
    "name:deu_x_preferred":[
        "Senet"
    ],
    "name:ell_x_preferred":[
        "\u03a3\u03ad\u03bd\u03b5\u03c4"
    ],
    "name:epo_x_preferred":[
        "Seneto"
    ],
    "name:fas_x_preferred":[
        "\u0633\u06cc\u0646\u06cc\u062a"
    ],
    "name:fin_x_preferred":[
        "Senet"
    ],
    "name:fra_x_preferred":[
        "Senet"
    ],
    "name:heb_x_preferred":[
        "\u05e1\u05e0\u05ea"
    ],
    "name:hun_x_preferred":[
        "Szenet"
    ],
    "name:ind_x_preferred":[
        "Senet"
    ],
    "name:ita_x_preferred":[
        "Senet"
    ],
    "name:jpn_x_preferred":[
        "\u30bb\u30cd\u30c8"
    ],
    "name:nld_x_preferred":[
        "Senet"
    ],
    "name:oci_x_preferred":[
        "Senet"
    ],
    "name:pol_x_preferred":[
        "Senet"
    ],
    "name:por_x_preferred":[
        "Senet"
    ],
    "name:ron_x_preferred":[
        "Senet"
    ],
    "name:rus_x_preferred":[
        "\u0421\u0435\u043d\u0435\u0442"
    ],
    "name:sin_x_preferred":[
        "\u0dc3\u0dd3\u0db1\u0dd9\u0da7\u0dca"
    ],
    "name:slk_x_preferred":[
        "Senet"
    ],
    "name:spa_x_preferred":[
        "Senet"
    ],
    "name:swe_x_preferred":[
        "Senet"
    ],
    "name:tur_x_preferred":[
        "Senet"
    ],
    "name:vie_x_preferred":[
        "Senet"
    ],
    "name:zho_x_preferred":[
        "\u585e\u5c3c\u7279"
    ],
    "wof:name":"Senet",
    "wof:placetype":"locality"
},
  "geometry": {"coordinates":[110.02528,-7.21806],"type":"Point"}
}