{
  "type": "Feature",
  "properties": {
    "gn:admin1_code":"7",
    "gn:asciiname":"Senet",
    "gn:country_code":"ID",
    "gn:dem":933,
    "gn:feature_class":"P",
    "gn:feature_code":"PPL",
    "gn:name":"Senet",
    "gn:population":0,
    "gn:timezone":"Asia/Jakarta",
    "iso:country":"ID",
    "name:ind_x_preferred":[
        "Senet"
    ],
    "wof:name":"Senet",
    "wof:placetype":"locality"
},
  "geometry": {"coordinates":[110.02528,-7.21806],"type":"Point"}
}