{
  "type": "Feature",
  "properties": {
    "gn:admin1_code":"8",
    "gn:asciiname":"Tumpakasri",
    "gn:country_code":"ID",
    "gn:dem":454,
    "gn:feature_class":"P",
    "gn:feature_code":"PPL",
    "gn:name":"Tumpakasri",
    "gn:population":0,
    "gn:timezone":"Asia/Jakarta",
    "iso:country":"ID",
    "name:ind_x_preferred":[
        "Tumpakasri"
    ],
    "wof:name":"Tumpakasri",
    "wof:placetype":"locality"
},
  "geometry": {"coordinates":[111.7401,-7.684],"type":"Point"}
}