{
  "type": "Feature",
  "properties": {
    "gn:admin1_code":"8",
    "gn:asciiname":"Karangente",
    "gn:country_code":"ID",
    "gn:dem":20,
    "gn:feature_class":"P",
    "gn:feature_code":"PPL",
    "gn:name":"Karangente",
    "gn:population":0,
    "gn:timezone":"Asia/Jakarta",
    "iso:country":"ID",
    "name:ind_x_preferred":[
        "Karangente"
    ],
    "wof:name":"Karangente",
    "wof:placetype":"locality"
},
  "geometry": {"coordinates":[114.3608,-8.2354],"type":"Point"}
}