{
  "type": "Feature",
  "properties": {
    "gn:admin1_code":"41.0",
    "gn:asciiname":"Orobua",
    "gn:country_code":"ID",
    "gn:dem":1259,
    "gn:feature_class":"P",
    "gn:feature_code":"PPL",
    "gn:name":"Orobua",
    "gn:population":0,
    "gn:timezone":"Asia/Makassar",
    "iso:country":"ID",
    "name:ind_x_preferred":[
        "Orobua"
    ],
    "name:und_x_variant":[
        "Oraboea",
        "Orabua"
    ],
    "wof:lang_x_official":[
        "ind"
    ],
    "wof:lang_x_spoken":[
        "ind",
        "eng"
    ],
    "wof:name":"Orobua",
    "wof:placetype":"locality"
},
  "geometry": {"coordinates":[119.4049,-2.9905],"type":"Point"}
}