{
  "type": "Feature",
  "properties": {
    "gn:admin1_code":"30.0",
    "gn:asciiname":"Cikancana",
    "gn:country_code":"ID",
    "gn:dem":558,
    "gn:feature_class":"P",
    "gn:feature_code":"PPL",
    "gn:name":"Cikancana",
    "gn:population":0,
    "gn:timezone":"Asia/Jakarta",
    "iso:country":"ID",
    "name:ind_x_preferred":[
        "Cikancana"
    ],
    "name:und_x_variant":[
        "Tjikantjana"
    ],
    "wof:name":"Cikancana",
    "wof:placetype":"locality"
},
  "geometry": {"coordinates":[107.08417,-6.89028],"type":"Point"}
}