{
  "type": "Feature",
  "properties": {
    "gn:admin1_code":"41",
    "gn:asciiname":"Salukaha",
    "gn:country_code":"ID",
    "gn:dem":27,
    "gn:feature_class":"P",
    "gn:feature_code":"PPL",
    "gn:name":"Salukaha",
    "gn:population":0,
    "gn:timezone":"Asia/Makassar",
    "iso:country":"ID",
    "name:ind_x_preferred":[
        "Salukaha"
    ],
    "name:und_x_variant":[
        "Salukakat"
    ],
    "wof:name":"Salukaha",
    "wof:placetype":"locality"
},
  "geometry": {"coordinates":[119.0869,-2.5631],"type":"Point"}
}