{
  "type": "Feature",
  "properties": {
    "gn:admin1_code":"7",
    "gn:asciiname":"Seren",
    "gn:country_code":"ID",
    "gn:dem":883,
    "gn:feature_class":"P",
    "gn:feature_code":"PPL",
    "gn:name":"Seren",
    "gn:population":0,
    "gn:timezone":"Asia/Jakarta",
    "iso:country":"ID",
    "name:ind_x_preferred":[
        "Seren"
    ],
    "wof:name":"Seren",
    "wof:placetype":"locality"
},
  "geometry": {"coordinates":[111.19667,-7.91167],"type":"Point"}
}