{
  "type": "Feature",
  "properties": {
    "gn:admin1_code":"38.0",
    "gn:asciiname":"Karangan",
    "gn:country_code":"ID",
    "gn:dem":45,
    "gn:feature_class":"P",
    "gn:feature_code":"PPL",
    "gn:name":"Karangan",
    "gn:population":0,
    "gn:timezone":"Asia/Makassar",
    "iso:country":"ID",
    "name:ceb_x_preferred":[
        "Karangan"
    ],
    "name:ind_x_preferred":[
        "Karangan"
    ],
    "name:nld_x_preferred":[
        "Karangan"
    ],
    "name:swe_x_preferred":[
        "Karangan"
    ],
    "wof:lang_x_official":[
        "ind"
    ],
    "wof:lang_x_spoken":[
        "ind",
        "eng"
    ],
    "wof:name":"Karangan",
    "wof:placetype":"locality"
},
  "geometry": {"coordinates":[120.26390000000001,-3.2663],"type":"Point"}
}