{
  "type": "Feature",
  "properties": {
    "gn:admin1_code":"38.0",
    "gn:asciiname":"Panga",
    "gn:country_code":"ID",
    "gn:dem":847,
    "gn:feature_class":"P",
    "gn:feature_code":"PPL",
    "gn:name":"Panga",
    "gn:population":0,
    "gn:timezone":"Asia/Makassar",
    "iso:country":"ID",
    "name:afr_x_preferred":[
        "Panga"
    ],
    "name:cat_x_preferred":[
        "Pterogymnus laniarius"
    ],
    "name:ceb_x_preferred":[
        "Pterogymnus laniarius"
    ],
    "name:eus_x_preferred":[
        "Hegoafrikako panga"
    ],
    "name:fra_x_preferred":[
        "Pterogymnus laniarius"
    ],
    "name:ind_x_preferred":[
        "Panga"
    ],
    "name:nld_x_preferred":[
        "Panga"
    ],
    "name:pol_x_preferred":[
        "Pangafer"
    ],
    "name:por_x_preferred":[
        "Panga"
    ],
    "name:slv_x_preferred":[
        "Panga"
    ],
    "name:spa_x_preferred":[
        "Pterogymnus laniarius"
    ],
    "name:swe_x_preferred":[
        "Pangablecka"
    ],
    "name:ukr_x_preferred":[
        "Pterogymnus laniarius"
    ],
    "name:war_x_preferred":[
        "Pterogymnus laniarius"
    ],
    "name:zho_x_preferred":[
        "\u7d05\u88f8\u7ffc\u9bdb"
    ],
    "wof:lang_x_official":[
        "ind"
    ],
    "wof:lang_x_spoken":[
        "ind",
        "eng"
    ],
    "wof:name":"Panga",
    "wof:placetype":"locality"
},
  "geometry": {"coordinates":[119.92449999999999,-2.9749],"type":"Point"}
}