{
  "type": "Feature",
  "properties": {
    "gn:admin1_code":"38.0",
    "gn:asciiname":"Panga",
    "gn:country_code":"ID",
    "gn:dem":847,
    "gn:feature_class":"P",
    "gn:feature_code":"PPL",
    "gn:name":"Panga",
    "gn:population":0,
    "gn:timezone":"Asia/Makassar",
    "iso:country":"ID",
    "name:ind_x_preferred":[
        "Panga"
    ],
    "wof:name":"Panga",
    "wof:placetype":"locality"
},
  "geometry": {"coordinates":[119.92449999999999,-2.9749],"type":"Point"}
}