{
  "type": "Feature",
  "properties": {
    "gn:admin1_code":"7.0",
    "gn:asciiname":"Karangtengah",
    "gn:country_code":"ID",
    "gn:dem":243,
    "gn:feature_class":"P",
    "gn:feature_code":"PPL",
    "gn:name":"Karangtengah",
    "gn:population":0,
    "gn:timezone":"Asia/Jakarta",
    "iso:country":"ID",
    "name:ind_x_preferred":[
        "Karangtengah"
    ],
    "wof:name":"Karangtengah",
    "wof:placetype":"locality"
},
  "geometry": {"coordinates":[109.12111000000002,-7.38056],"type":"Point"}
}