{
  "type": "Feature",
  "properties": {
    "gn:admin1_code":"7.0",
    "gn:asciiname":"Sikasur",
    "gn:country_code":"ID",
    "gn:dem":372,
    "gn:feature_class":"P",
    "gn:feature_code":"PPL",
    "gn:name":"Sikasur",
    "gn:population":0,
    "gn:timezone":"Asia/Jakarta",
    "iso:country":"ID",
    "name:ind_x_preferred":[
        "Sikasur"
    ],
    "wof:name":"Sikasur",
    "wof:placetype":"locality"
},
  "geometry": {"coordinates":[109.71083,-7.41083],"type":"Point"}
}