{
  "type": "Feature",
  "properties": {
    "gn:admin1_code":"30",
    "gn:asciiname":"Tanahbaru Satu",
    "gn:country_code":"ID",
    "gn:dem":227,
    "gn:feature_class":"P",
    "gn:feature_code":"PPL",
    "gn:name":"Tanahbaru Satu",
    "gn:population":0,
    "gn:timezone":"Asia/Jakarta",
    "iso:country":"ID",
    "name:ind_x_preferred":[
        "Tanahbaru Satu"
    ],
    "name:und_x_variant":[
        "Tanahbaru 1"
    ],
    "wof:lang_x_official":[
        "ind"
    ],
    "wof:lang_x_spoken":[
        "ind",
        "eng"
    ],
    "wof:name":"Tanahbaru Satu",
    "wof:placetype":"locality"
},
  "geometry": {"coordinates":[106.82250000000001,-6.585],"type":"Point"}
}