{
  "type": "Feature",
  "properties": {
    "gn:admin1_code":"26",
    "gn:asciiname":"Jumateguh Tiga",
    "gn:country_code":"ID",
    "gn:dem":758,
    "gn:feature_class":"P",
    "gn:feature_code":"PPL",
    "gn:name":"Jumateguh Tiga",
    "gn:population":0,
    "gn:timezone":"Asia/Jakarta",
    "iso:country":"ID",
    "name:ind_x_preferred":[
        "Jumateguh Tiga"
    ],
    "name:und_x_variant":[
        "Jumategun 3"
    ],
    "wof:name":"Jumateguh Tiga",
    "wof:placetype":"locality"
},
  "geometry": {"coordinates":[98.2239,2.7941],"type":"Point"}
}