{
  "type": "Feature",
  "properties": {
    "gn:admin1_code":"30",
    "gn:asciiname":"Cirawa Girang",
    "gn:country_code":"ID",
    "gn:dem":1104,
    "gn:feature_class":"P",
    "gn:feature_code":"PPL",
    "gn:name":"Cirawa Girang",
    "gn:population":0,
    "gn:timezone":"Asia/Jakarta",
    "iso:country":"ID",
    "name:ind_x_preferred":[
        "Cirawa Girang"
    ],
    "wof:name":"Cirawa Girang",
    "wof:placetype":"locality"
},
  "geometry": {"coordinates":[107.32832999999999,-6.97833],"type":"Point"}
}