{
  "type": "Feature",
  "properties": {
    "gn:admin1_code":"18",
    "gn:asciiname":"Lioboto",
    "gn:country_code":"ID",
    "gn:dem":484,
    "gn:feature_class":"P",
    "gn:feature_code":"PPL",
    "gn:name":"Lioboto",
    "gn:population":0,
    "gn:timezone":"Asia/Makassar",
    "iso:country":"ID",
    "name:ind_x_preferred":[
        "Lioboto"
    ],
    "wof:name":"Lioboto",
    "wof:placetype":"locality"
},
  "geometry": {"coordinates":[121.8447,-8.5319],"type":"Point"}
}