{
  "type": "Feature",
  "properties": {
    "gn:admin1_code":"8",
    "gn:asciiname":"Setalang",
    "gn:country_code":"ID",
    "gn:dem":385,
    "gn:feature_class":"P",
    "gn:feature_code":"PPL",
    "gn:name":"Setalang",
    "gn:population":0,
    "gn:timezone":"Asia/Jakarta",
    "iso:country":"ID",
    "name:ind_x_preferred":[
        "Setalang"
    ],
    "wof:name":"Setalang",
    "wof:placetype":"locality"
},
  "geometry": {"coordinates":[111.18971999999999,-7.49972],"type":"Point"}
}