{
  "type": "Feature",
  "properties": {
    "gn:admin1_code":"0.0",
    "gn:asciiname":"Aerjeruk",
    "gn:cc2":"ID",
    "gn:country_code":"ID",
    "gn:dem":12,
    "gn:feature_class":"P",
    "gn:feature_code":"PPL",
    "gn:name":"Aerjeruk",
    "gn:population":0,
    "gn:timezone":"Asia/Jakarta",
    "iso:country":"ID",
    "name:und_x_variant":[
        "Aerdjeruk",
        "Aerjeruk"
    ],
    "wof:name":"Aerjeruk",
    "wof:placetype":"locality"
},
  "geometry": {"coordinates":[105.58333,-6.85],"type":"Point"}
}