{
  "type": "Feature",
  "properties": {
    "gn:admin1_code":"35",
    "gn:asciiname":"Airnipah",
    "gn:country_code":"ID",
    "gn:dem":17,
    "gn:feature_class":"P",
    "gn:feature_code":"PPL",
    "gn:name":"Airnipah",
    "gn:population":0,
    "gn:timezone":"Asia/Jakarta",
    "iso:country":"ID",
    "name:ind_x_preferred":[
        "Airnipah"
    ],
    "wof:name":"Airnipah",
    "wof:placetype":"locality"
},
  "geometry": {"coordinates":[106.17127000000001,-1.91774],"type":"Point"}
}