{
  "type": "Feature",
  "properties": {
    "gn:admin1_code":"30",
    "gn:asciiname":"Gunungkerud",
    "gn:country_code":"ID",
    "gn:dem":1023,
    "gn:feature_class":"P",
    "gn:feature_code":"PPL",
    "gn:name":"Gunungkerud",
    "gn:population":0,
    "gn:timezone":"Asia/Jakarta",
    "iso:country":"ID",
    "wof:name":"Gunungkerud",
    "wof:placetype":"locality"
},
  "geometry": {"coordinates":[107.47944,-7.00778],"type":"Point"}
}