{
  "type": "Feature",
  "properties": {
    "gn:admin1_code":"18.0",
    "gn:asciiname":"Ladeloko",
    "gn:country_code":"ID",
    "gn:dem":273,
    "gn:feature_class":"P",
    "gn:feature_code":"PPL",
    "gn:name":"Ladeloko",
    "gn:population":0,
    "gn:timezone":"Asia/Makassar",
    "iso:country":"ID",
    "name:ind_x_preferred":[
        "Ladeloko"
    ],
    "wof:name":"Ladeloko",
    "wof:placetype":"locality"
},
  "geometry": {"coordinates":[119.178,-9.6137],"type":"Point"}
}