{
  "type": "Feature",
  "properties": {
    "gn:admin1_code":"30",
    "gn:asciiname":"Cilame",
    "gn:country_code":"ID",
    "gn:dem":587,
    "gn:feature_class":"P",
    "gn:feature_code":"PPL",
    "gn:name":"Cilame",
    "gn:population":0,
    "gn:timezone":"Asia/Jakarta",
    "iso:country":"ID",
    "name:ind_x_preferred":[
        "Cilame"
    ],
    "wof:name":"Cilame",
    "wof:placetype":"locality"
},
  "geometry": {"coordinates":[108.48721999999999,-6.95528],"type":"Point"}
}