{
  "type": "Feature",
  "properties": {
    "gn:admin1_code":"18.0",
    "gn:asciiname":"Ngaruwinu Atas",
    "gn:country_code":"ID",
    "gn:dem":83,
    "gn:feature_class":"P",
    "gn:feature_code":"PPL",
    "gn:name":"Ngaruwinu Atas",
    "gn:population":0,
    "gn:timezone":"Asia/Makassar",
    "iso:country":"ID",
    "name:ind_x_preferred":[
        "Ngaruwinu Atas"
    ],
    "wof:lang_x_official":[
        "ind"
    ],
    "wof:lang_x_spoken":[
        "ind",
        "eng"
    ],
    "wof:name":"Ngaruwinu Atas",
    "wof:placetype":"locality"
},
  "geometry": {"coordinates":[120.45269999999999,-10.2473],"type":"Point"}
}