{
  "type": "Feature",
  "properties": {
    "gn:admin1_code":"22.0",
    "gn:asciiname":"Rumbarumba",
    "gn:country_code":"ID",
    "gn:dem":20,
    "gn:feature_class":"P",
    "gn:feature_code":"PPL",
    "gn:name":"Rumbarumba",
    "gn:population":0,
    "gn:timezone":"Asia/Makassar",
    "iso:country":"ID",
    "name:ind_x_preferred":[
        "Rumbarumba"
    ],
    "name:und_x_variant":[
        "Roemba",
        "Roembaroemba"
    ],
    "wof:lang_x_official":[
        "ind"
    ],
    "wof:lang_x_spoken":[
        "ind",
        "eng"
    ],
    "wof:name":"Rumbarumba",
    "wof:placetype":"locality"
},
  "geometry": {"coordinates":[122.80589999999999,-4.4251],"type":"Point"}
}