{
  "type": "Feature",
  "properties": {
    "gn:admin1_code":"8.0",
    "gn:asciiname":"Tella",
    "gn:country_code":"ID",
    "gn:dem":76,
    "gn:feature_class":"P",
    "gn:feature_code":"PPL",
    "gn:name":"Tella",
    "gn:population":0,
    "gn:timezone":"Asia/Jakarta",
    "iso:country":"ID",
    "name:deu_x_preferred":[
        "Tella"
    ],
    "name:fra_x_preferred":[
        "Tella"
    ],
    "name:ind_x_preferred":[
        "Tella"
    ],
    "name:jpn_x_preferred":[
        "\u30c6\u30e9"
    ],
    "name:lit_x_preferred":[
        "Tela"
    ],
    "name:nld_x_preferred":[
        "Tella"
    ],
    "name:pol_x_preferred":[
        "Tella"
    ],
    "name:por_x_preferred":[
        "Tella"
    ],
    "name:spa_x_preferred":[
        "Tella"
    ],
    "wof:lang_x_official":[
        "ind"
    ],
    "wof:lang_x_spoken":[
        "ind",
        "eng"
    ],
    "wof:name":"Tella",
    "wof:placetype":"locality"
},
  "geometry": {"coordinates":[114.0787,-7.7574],"type":"Point"}
}