{
  "type": "Feature",
  "properties": {
    "gn:admin1_code":"8",
    "gn:asciiname":"Jarak",
    "gn:country_code":"ID",
    "gn:dem":76,
    "gn:feature_class":"P",
    "gn:feature_code":"PPL",
    "gn:name":"Jarak",
    "gn:population":0,
    "gn:timezone":"Asia/Jakarta",
    "iso:country":"ID",
    "name:ceb_x_preferred":[
        "Jarak"
    ],
    "name:deu_x_preferred":[
        "Jarak"
    ],
    "name:epo_x_preferred":[
        "Jarak"
    ],
    "name:fra_x_preferred":[
        "Jarak"
    ],
    "name:hrv_x_preferred":[
        "Jarak"
    ],
    "name:hun_x_preferred":[
        "Jarak"
    ],
    "name:ind_x_preferred":[
        "Jarak"
    ],
    "name:msa_x_preferred":[
        "Jarak"
    ],
    "name:rus_x_preferred":[
        "\u042f\u0440\u0430\u043a"
    ],
    "name:slv_x_preferred":[
        "Jarak"
    ],
    "name:srp_x_preferred":[
        "\u0408\u0430\u0440\u0430\u043a"
    ],
    "name:urd_x_preferred":[
        "\u062c\u0631\u06a9"
    ],
    "wof:name":"Jarak",
    "wof:placetype":"locality"
},
  "geometry": {"coordinates":[111.14888999999999,-7.37778],"type":"Point"}
}