{
  "type": "Feature",
  "properties": {
    "gn:admin1_code":"7.0",
    "gn:asciiname":"Pangkat",
    "gn:country_code":"ID",
    "gn:dem":628,
    "gn:feature_class":"P",
    "gn:feature_code":"PPL",
    "gn:name":"Pangkat",
    "gn:population":0,
    "gn:timezone":"Asia/Jakarta",
    "iso:country":"ID",
    "wof:name":"Pangkat",
    "wof:placetype":"locality"
},
  "geometry": {"coordinates":[110.3075,-7.44278],"type":"Point"}
}