{
  "type": "Feature",
  "properties": {
    "gn:admin1_code":"30",
    "gn:asciiname":"Sidepankarangasem",
    "gn:country_code":"ID",
    "gn:dem":22,
    "gn:feature_class":"P",
    "gn:feature_code":"PPL",
    "gn:name":"Sidepankarangasem",
    "gn:population":0,
    "gn:timezone":"Asia/Jakarta",
    "iso:country":"ID",
    "name:ind_x_preferred":[
        "Sidepankarangasem"
    ],
    "wof:name":"Sidepankarangasem",
    "wof:placetype":"locality"
},
  "geometry": {"coordinates":[112.9391,-7.7516],"type":"Point"}
}