{
  "type": "Feature",
  "properties": {
    "gn:admin1_code":"8",
    "gn:asciiname":"Gunung",
    "gn:country_code":"ID",
    "gn:dem":52,
    "gn:feature_class":"P",
    "gn:feature_code":"PPL",
    "gn:name":"Gunung",
    "gn:population":0,
    "gn:timezone":"Asia/Jakarta",
    "iso:country":"ID",
    "name:ceb_x_preferred":[
        "Gunung"
    ],
    "name:ind_x_preferred":[
        "Gunung"
    ],
    "name:nld_x_preferred":[
        "Gunung"
    ],
    "name:swe_x_preferred":[
        "Gunung"
    ],
    "wof:name":"Gunung",
    "wof:placetype":"locality"
},
  "geometry": {"coordinates":[113.0033,-7.0517],"type":"Point"}
}