{
  "type": "Feature",
  "properties": {
    "gn:admin1_code":"30",
    "gn:asciiname":"Lukut Kaler",
    "gn:country_code":"ID",
    "gn:dem":265,
    "gn:feature_class":"P",
    "gn:feature_code":"PPL",
    "gn:name":"Lukut Kaler",
    "gn:population":0,
    "gn:timezone":"Asia/Jakarta",
    "iso:country":"ID",
    "name:ind_x_preferred":[
        "Lukut Kaler"
    ],
    "wof:name":"Lukut Kaler",
    "wof:placetype":"locality"
},
  "geometry": {"coordinates":[106.54722,-6.57972],"type":"Point"}
}