{
  "type": "Feature",
  "properties": {
    "gn:admin1_code":"15.0",
    "gn:asciiname":"Talang Jungkung",
    "gn:country_code":"ID",
    "gn:dem":899,
    "gn:feature_class":"P",
    "gn:feature_code":"PPL",
    "gn:name":"Talang Jungkung",
    "gn:population":0,
    "gn:timezone":"Asia/Jakarta",
    "iso:country":"ID",
    "name:ind_x_preferred":[
        "Talang Jungkung"
    ],
    "wof:name":"Talang Jungkung",
    "wof:placetype":"locality"
},
  "geometry": {"coordinates":[103.94799999999999,-4.92743],"type":"Point"}
}