{
  "type": "Feature",
  "properties": {
    "gn:admin1_code":"30",
    "gn:asciiname":"Nagrak",
    "gn:country_code":"ID",
    "gn:dem":1061,
    "gn:feature_class":"P",
    "gn:feature_code":"PPL",
    "gn:name":"Nagrak",
    "gn:population":0,
    "gn:timezone":"Asia/Jakarta",
    "iso:country":"ID",
    "name:ind_x_preferred":[
        "Nagrak"
    ],
    "name:und_x_variant":[
        "Nagrak 5",
        "Nagrak Lima"
    ],
    "wof:lang_x_official":[
        "ind"
    ],
    "wof:lang_x_spoken":[
        "ind",
        "eng"
    ],
    "wof:name":"Nagrak",
    "wof:placetype":"locality"
},
  "geometry": {"coordinates":[107.32666999999999,-6.98361],"type":"Point"}
}