{
  "type": "Feature",
  "properties": {
    "gn:admin1_code":"22.0",
    "gn:asciiname":"Laloa",
    "gn:country_code":"ID",
    "gn:dem":79,
    "gn:feature_class":"P",
    "gn:feature_code":"PPL",
    "gn:name":"Laloa",
    "gn:population":0,
    "gn:timezone":"Asia/Makassar",
    "iso:country":"ID",
    "name:ind_x_preferred":[
        "Laloa"
    ],
    "wof:name":"Laloa",
    "wof:placetype":"locality"
},
  "geometry": {"coordinates":[122.0018,-4.8381],"type":"Point"}
}