{
  "type": "Feature",
  "properties": {
    "gn:admin1_code":"30",
    "gn:asciiname":"Kopeng",
    "gn:country_code":"ID",
    "gn:dem":316,
    "gn:feature_class":"P",
    "gn:feature_code":"PPL",
    "gn:name":"Kopeng",
    "gn:population":0,
    "gn:timezone":"Asia/Jakarta",
    "iso:country":"ID",
    "name:ind_x_preferred":[
        "Kopeng"
    ],
    "name:jav_x_preferred":[
        "Kop\u00e8ng"
    ],
    "name:nld_x_preferred":[
        "Kopeng"
    ],
    "wof:name":"Kopeng",
    "wof:placetype":"locality"
},
  "geometry": {"coordinates":[107.29056,-6.88111],"type":"Point"}
}