{
  "type": "Feature",
  "properties": {
    "gn:admin1_code":"26",
    "gn:asciiname":"Sisanggu",
    "gn:country_code":"ID",
    "gn:dem":953,
    "gn:feature_class":"P",
    "gn:feature_code":"PPL",
    "gn:name":"Sisanggu",
    "gn:population":0,
    "gn:timezone":"Asia/Jakarta",
    "iso:country":"ID",
    "name:ind_x_preferred":[
        "Sisanggu"
    ],
    "wof:lang_x_official":[
        "ind"
    ],
    "wof:lang_x_spoken":[
        "ind",
        "eng"
    ],
    "wof:name":"Sisanggu",
    "wof:placetype":"locality"
},
  "geometry": {"coordinates":[98.97750000000001,2.0222],"type":"Point"}
}