{
  "type": "Feature",
  "properties": {
    "gn:admin1_code":"30",
    "gn:asciiname":"Ciawitali Dua",
    "gn:country_code":"ID",
    "gn:dem":20,
    "gn:feature_class":"P",
    "gn:feature_code":"PPL",
    "gn:name":"Ciawitali Dua",
    "gn:population":0,
    "gn:timezone":"Asia/Jakarta",
    "iso:country":"ID",
    "name:ind_x_preferred":[
        "Ciawitali Dua"
    ],
    "wof:name":"Ciawitali Dua",
    "wof:placetype":"locality"
},
  "geometry": {"coordinates":[107.75082999999999,-6.36528],"type":"Point"}
}