{
  "type": "Feature",
  "properties": {
    "gn:admin1_code":"7.0",
    "gn:asciiname":"Mantingan",
    "gn:country_code":"ID",
    "gn:dem":311,
    "gn:feature_class":"P",
    "gn:feature_code":"PPL",
    "gn:name":"Mantingan",
    "gn:population":0,
    "gn:timezone":"Asia/Jakarta",
    "iso:country":"ID",
    "name:ind_x_preferred":[
        "Mantingan"
    ],
    "name:jav_x_preferred":[
        "Mantingan"
    ],
    "name:nld_x_preferred":[
        "Mantingan"
    ],
    "wof:lang_x_official":[
        "ind"
    ],
    "wof:lang_x_spoken":[
        "ind",
        "eng"
    ],
    "wof:name":"Mantingan",
    "wof:placetype":"locality"
},
  "geometry": {"coordinates":[110.30611,-7.63944],"type":"Point"}
}