{
  "type": "Feature",
  "properties": {
    "gn:admin1_code":"30",
    "gn:asciiname":"Kobakputat",
    "gn:country_code":"ID",
    "gn:dem":2,
    "gn:feature_class":"P",
    "gn:feature_code":"PPL",
    "gn:name":"Kobakputat",
    "gn:population":0,
    "gn:timezone":"Asia/Jakarta",
    "iso:country":"ID",
    "name:ind_x_preferred":[
        "Kobakputat"
    ],
    "wof:name":"Kobakputat",
    "wof:placetype":"locality"
},
  "geometry": {"coordinates":[107.26333,-6.03778],"type":"Point"}
}