{
  "type": "Feature",
  "properties": {
    "gn:admin1_code":"38.0",
    "gn:asciiname":"Potoa",
    "gn:country_code":"ID",
    "gn:dem":53,
    "gn:feature_class":"P",
    "gn:feature_code":"PPL",
    "gn:name":"Potoa",
    "gn:population":0,
    "gn:timezone":"Asia/Makassar",
    "iso:country":"ID",
    "name:ind_x_preferred":[
        "Potoa"
    ],
    "wof:name":"Potoa",
    "wof:placetype":"locality"
},
  "geometry": {"coordinates":[120.32729999999999,-3.6873],"type":"Point"}
}