{
  "type": "Feature",
  "properties": {
    "gn:admin1_code":"2",
    "gn:asciiname":"Banjar Siladan",
    "gn:country_code":"ID",
    "gn:dem":232,
    "gn:feature_class":"P",
    "gn:feature_code":"PPL",
    "gn:name":"Banjar Siladan",
    "gn:population":0,
    "gn:timezone":"Asia/Makassar",
    "iso:country":"ID",
    "name:ind_x_preferred":[
        "Banjar Siladan"
    ],
    "wof:name":"Banjar Siladan",
    "wof:placetype":"locality"
},
  "geometry": {"coordinates":[115.3146,-8.5052],"type":"Point"}
}