{
  "type": "Feature",
  "properties": {
    "gn:admin1_code":"30.0",
    "gn:asciiname":"Purwasedar Dua",
    "gn:country_code":"ID",
    "gn:dem":306,
    "gn:feature_class":"P",
    "gn:feature_code":"PPL",
    "gn:name":"Purwasedar Dua",
    "gn:population":0,
    "gn:timezone":"Asia/Jakarta",
    "iso:country":"ID",
    "name:ind_x_preferred":[
        "Purwasedar Dua"
    ],
    "wof:name":"Purwasedar Dua",
    "wof:placetype":"locality"
},
  "geometry": {"coordinates":[106.63030000000001,-7.2633],"type":"Point"}
}