{
  "type": "Feature",
  "properties": {
    "gn:admin1_code":"21.0",
    "gn:asciiname":"Omu",
    "gn:country_code":"ID",
    "gn:dem":150,
    "gn:feature_class":"P",
    "gn:feature_code":"PPL",
    "gn:name":"Omu",
    "gn:population":0,
    "gn:timezone":"Asia/Makassar",
    "iso:country":"ID",
    "name:ceb_x_preferred":[
        "Omu"
    ],
    "name:ind_x_preferred":[
        "Omu"
    ],
    "name:swe_x_preferred":[
        "Omu"
    ],
    "wof:lang_x_official":[
        "ind"
    ],
    "wof:lang_x_spoken":[
        "ind",
        "eng"
    ],
    "wof:name":"Omu",
    "wof:placetype":"locality"
},
  "geometry": {"coordinates":[119.94540000000001,-1.277],"type":"Point"}
}