{
  "type": "Feature",
  "properties": {
    "gn:admin1_code":"30",
    "gn:asciiname":"Cereme",
    "gn:country_code":"ID",
    "gn:dem":198,
    "gn:feature_class":"P",
    "gn:feature_code":"PPL",
    "gn:name":"Cereme",
    "gn:population":0,
    "gn:timezone":"Asia/Jakarta",
    "iso:country":"ID",
    "name:ind_x_preferred":[
        "Cereme"
    ],
    "wof:name":"Cereme",
    "wof:placetype":"locality"
},
  "geometry": {"coordinates":[106.73222,-6.57778],"type":"Point"}
}