{
  "type": "Feature",
  "properties": {
    "gn:admin1_code":"7",
    "gn:asciiname":"Peniten",
    "gn:country_code":"ID",
    "gn:dem":18,
    "gn:feature_class":"P",
    "gn:feature_code":"PPL",
    "gn:name":"Peniten",
    "gn:population":0,
    "gn:timezone":"Asia/Jakarta",
    "iso:country":"ID",
    "name:ind_x_preferred":[
        "Peniten"
    ],
    "wof:name":"Peniten",
    "wof:placetype":"locality"
},
  "geometry": {"coordinates":[110.0496,-6.9604],"type":"Point"}
}