{
  "type": "Feature",
  "properties": {
    "gn:admin1_code":"07",
    "gn:asciiname":"Kebowan",
    "gn:country_code":"ID",
    "gn:dem":641,
    "gn:feature_class":"P",
    "gn:feature_code":"PPL",
    "gn:name":"Kebowan",
    "gn:population":0,
    "gn:timezone":"Asia/Jakarta",
    "iso:country":"ID",
    "name:und_x_variant":[
        "Kebowan 1",
        "Kebowan Satu",
        "Kebowan"
    ],
    "wof:lang_x_official":[
        "ind"
    ],
    "wof:lang_x_spoken":[
        "ind",
        "eng"
    ],
    "wof:name":"Kebowan",
    "wof:placetype":"locality"
},
  "geometry": {"coordinates":[110.55110999999999,-7.38056],"type":"Point"}
}