{
  "type": "Feature",
  "properties": {
    "gn:admin1_code":"30.0",
    "gn:asciiname":"Cimomon",
    "gn:country_code":"ID",
    "gn:dem":80,
    "gn:feature_class":"P",
    "gn:feature_code":"PPL",
    "gn:name":"Cimomon",
    "gn:population":0,
    "gn:timezone":"Asia/Jakarta",
    "iso:country":"ID",
    "name:ind_x_preferred":[
        "Cimomon"
    ],
    "name:und_x_variant":[
        "Tjimomon"
    ],
    "wof:lang_x_official":[
        "ind"
    ],
    "wof:lang_x_spoken":[
        "ind",
        "eng"
    ],
    "wof:name":"Cimomon",
    "wof:placetype":"locality"
},
  "geometry": {"coordinates":[108.27209999999999,-7.7646],"type":"Point"}
}