{
  "type": "Feature",
  "properties": {
    "gn:admin1_code":"7.0",
    "gn:asciiname":"Prangkokan",
    "gn:country_code":"ID",
    "gn:dem":1063,
    "gn:feature_class":"P",
    "gn:feature_code":"PPL",
    "gn:name":"Prangkokan",
    "gn:population":0,
    "gn:timezone":"Asia/Jakarta",
    "iso:country":"ID",
    "wof:name":"Prangkokan",
    "wof:placetype":"locality"
},
  "geometry": {"coordinates":[110.11306,-7.32972],"type":"Point"}
}