{
  "type": "Feature",
  "properties": {
    "gn:admin1_code":"30.0",
    "gn:asciiname":"Bulakbenda",
    "gn:country_code":"ID",
    "gn:dem":11,
    "gn:feature_class":"P",
    "gn:feature_code":"PPL",
    "gn:name":"Bulakbenda",
    "gn:population":0,
    "gn:timezone":"Asia/Jakarta",
    "iso:country":"ID",
    "name:ind_x_preferred":[
        "Bulakbenda"
    ],
    "name:und_x_variant":[
        "Boelakbenda"
    ],
    "wof:name":"Bulakbenda",
    "wof:placetype":"locality"
},
  "geometry": {"coordinates":[108.4846,-7.7949],"type":"Point"}
}