{
  "type": "Feature",
  "properties": {
    "gn:admin1_code":"0.0",
    "gn:asciiname":"Simataniari",
    "gn:country_code":"ID",
    "gn:dem":1078,
    "gn:feature_class":"P",
    "gn:feature_code":"PPL",
    "gn:name":"Simataniari",
    "gn:population":0,
    "gn:timezone":"Asia/Jakarta",
    "iso:country":"ID",
    "wof:name":"Simataniari",
    "wof:placetype":"locality"
},
  "geometry": {"coordinates":[98.55,2.33333],"type":"Point"}
}