{
  "type": "Feature",
  "properties": {
    "gn:admin1_code":"30.0",
    "gn:asciiname":"Cicungging",
    "gn:country_code":"ID",
    "gn:dem":290,
    "gn:feature_class":"P",
    "gn:feature_code":"PPL",
    "gn:name":"Cicungging",
    "gn:population":0,
    "gn:timezone":"Asia/Jakarta",
    "iso:country":"ID",
    "name:ind_x_preferred":[
        "Cicungging"
    ],
    "name:und_x_variant":[
        "Tjitjoengging"
    ],
    "wof:name":"Cicungging",
    "wof:placetype":"locality"
},
  "geometry": {"coordinates":[108.42829999999999,-7.2255],"type":"Point"}
}