{
  "type": "Feature",
  "properties": {
    "gn:admin1_code":"30.0",
    "gn:asciiname":"Gadog",
    "gn:country_code":"ID",
    "gn:dem":27,
    "gn:feature_class":"P",
    "gn:feature_code":"PPLA4",
    "gn:name":"Gadog",
    "gn:population":0,
    "gn:timezone":"Asia/Jakarta",
    "iso:country":"ID",
    "name:ind_x_preferred":[
        "Gadog"
    ],
    "wof:name":"Gadog",
    "wof:placetype":"locality"
},
  "geometry": {"coordinates":[108.43810000000001,-7.7937],"type":"Point"}
}