{
  "type": "Feature",
  "properties": {
    "gn:admin1_code":"30",
    "gn:asciiname":"Rancabogo",
    "gn:country_code":"ID",
    "gn:dem":705,
    "gn:feature_class":"P",
    "gn:feature_code":"PPL",
    "gn:name":"Rancabogo",
    "gn:population":0,
    "gn:timezone":"Asia/Jakarta",
    "iso:country":"ID",
    "name:ind_x_preferred":[
        "Rancabogo"
    ],
    "wof:name":"Rancabogo",
    "wof:placetype":"locality"
},
  "geometry": {"coordinates":[107.51111000000002,-6.86861],"type":"Point"}
}