{
  "type": "Feature",
  "properties": {
    "gn:admin1_code":"33.0",
    "gn:asciiname":"Cipiit",
    "gn:country_code":"ID",
    "gn:dem":333,
    "gn:feature_class":"P",
    "gn:feature_code":"PPL",
    "gn:name":"Cipiit",
    "gn:population":0,
    "gn:timezone":"Asia/Jakarta",
    "iso:country":"ID",
    "name:ind_x_preferred":[
        "Cipiit"
    ],
    "wof:name":"Cipiit",
    "wof:placetype":"locality"
},
  "geometry": {"coordinates":[106.2282,-6.6146],"type":"Point"}
}