{
  "type": "Feature",
  "properties": {
    "gn:admin1_code":"8.0",
    "gn:asciiname":"Sompur",
    "gn:country_code":"ID",
    "gn:dem":47,
    "gn:feature_class":"P",
    "gn:feature_code":"PPL",
    "gn:name":"Sompur",
    "gn:population":0,
    "gn:timezone":"Asia/Jakarta",
    "iso:country":"ID",
    "name:ind_x_preferred":[
        "Sompur"
    ],
    "wof:name":"Sompur",
    "wof:placetype":"locality"
},
  "geometry": {"coordinates":[113.51000999999999,-7.13438],"type":"Point"}
}