{
  "type": "Feature",
  "properties": {
    "gn:admin1_code":"2",
    "gn:asciiname":"Bali Villas",
    "gn:country_code":"ID",
    "gn:dem":30,
    "gn:feature_class":"P",
    "gn:feature_code":"PPLS",
    "gn:name":"Bali Villas",
    "gn:population":0,
    "gn:timezone":"Asia/Makassar",
    "iso:country":"ID",
    "wof:name":"Bali Villas",
    "wof:placetype":"locality"
},
  "geometry": {"coordinates":[115.25449999999999,-8.63177],"type":"Point"}
}