{
  "type": "Feature",
  "properties": {
    "gn:admin1_code":"30.0",
    "gn:asciiname":"Cigaragol",
    "gn:country_code":"ID",
    "gn:dem":595,
    "gn:feature_class":"P",
    "gn:feature_code":"PPL",
    "gn:name":"Cigaragol",
    "gn:population":0,
    "gn:timezone":"Asia/Jakarta",
    "iso:country":"ID",
    "name:ind_x_preferred":[
        "Cigaragol"
    ],
    "name:und_x_variant":[
        "Tjigarogol"
    ],
    "wof:lang_x_official":[
        "ind"
    ],
    "wof:lang_x_spoken":[
        "ind",
        "eng"
    ],
    "wof:name":"Cigaragol",
    "wof:placetype":"locality"
},
  "geometry": {"coordinates":[108.38639999999999,-7.5188],"type":"Point"}
}