{
  "type": "Feature",
  "properties": {
    "gn:admin1_code":"8.0",
    "gn:asciiname":"Mamer",
    "gn:country_code":"ID",
    "gn:dem":4,
    "gn:feature_class":"P",
    "gn:feature_code":"PPL",
    "gn:name":"Mamer",
    "gn:population":0,
    "gn:timezone":"Asia/Jakarta",
    "iso:country":"ID",
    "name:als_x_preferred":[
        "Mamer"
    ],
    "name:bel_x_preferred":[
        "\u041c\u0430\u043c\u0435\u0440"
    ],
    "name:cat_x_preferred":[
        "Mamer"
    ],
    "name:ceb_x_preferred":[
        "Mamer"
    ],
    "name:ces_x_preferred":[
        "Mamer"
    ],
    "name:dan_x_preferred":[
        "Mamer"
    ],
    "name:deu_x_preferred":[
        "Mamer"
    ],
    "name:fas_x_preferred":[
        "\u0645\u0627\u0645\u0631"
    ],
    "name:fra_x_preferred":[
        "Mamer"
    ],
    "name:ind_x_preferred":[
        "Mamer"
    ],
    "name:ita_x_preferred":[
        "Mamer"
    ],
    "name:lit_x_preferred":[
        "Mameris"
    ],
    "name:ltz_x_preferred":[
        "Gemeng Mamer"
    ],
    "name:msa_x_preferred":[
        "Mamer"
    ],
    "name:nds_x_preferred":[
        "Gemeen Mamer"
    ],
    "name:nld_x_preferred":[
        "Mamer"
    ],
    "name:nor_x_preferred":[
        "Mamer"
    ],
    "name:pol_x_preferred":[
        "Mamer"
    ],
    "name:por_x_preferred":[
        "Mamer"
    ],
    "name:ron_x_preferred":[
        "Mamer"
    ],
    "name:rus_x_preferred":[
        "\u041c\u0430\u043c\u0435\u0440"
    ],
    "name:slk_x_preferred":[
        "Mamer"
    ],
    "name:swa_x_preferred":[
        "Mamer"
    ],
    "name:swe_x_preferred":[
        "Mamer"
    ],
    "name:ukr_x_preferred":[
        "\u041c\u0430\u043c\u0435\u0440"
    ],
    "name:zho_x_preferred":[
        "\u9a6c\u9ed8"
    ],
    "wof:lang_x_official":[
        "ind"
    ],
    "wof:lang_x_spoken":[
        "ind",
        "eng"
    ],
    "wof:name":"Mamer",
    "wof:placetype":"locality"
},
  "geometry": {"coordinates":[111.8172,-6.7978],"type":"Point"}
}