{
  "type": "Feature",
  "properties": {
    "gn:admin1_code":"8.0",
    "gn:asciiname":"Mamer",
    "gn:country_code":"ID",
    "gn:dem":4,
    "gn:feature_class":"P",
    "gn:feature_code":"PPL",
    "gn:name":"Mamer",
    "gn:population":0,
    "gn:timezone":"Asia/Jakarta",
    "iso:country":"ID",
    "name:ind_x_preferred":[
        "Mamer"
    ],
    "wof:name":"Mamer",
    "wof:placetype":"locality"
},
  "geometry": {"coordinates":[111.8172,-6.7978],"type":"Point"}
}