{
  "type": "Feature",
  "properties": {
    "gn:admin1_code":"18.0",
    "gn:asciiname":"Kampungtengah",
    "gn:country_code":"ID",
    "gn:dem":182,
    "gn:feature_class":"P",
    "gn:feature_code":"PPLA4",
    "gn:name":"Kampungtengah",
    "gn:population":0,
    "gn:timezone":"Asia/Makassar",
    "iso:country":"ID",
    "name:ind_x_preferred":[
        "Kampungtengah"
    ],
    "wof:name":"Kampungtengah",
    "wof:placetype":"locality"
},
  "geometry": {"coordinates":[124.1421,-9.9246],"type":"Point"}
}