{
  "type": "Feature",
  "properties": {
    "gn:admin1_code":"18.0",
    "gn:asciiname":"Fatututa",
    "gn:country_code":"ID",
    "gn:dem":588,
    "gn:feature_class":"P",
    "gn:feature_code":"PPL",
    "gn:name":"Fatututa",
    "gn:population":0,
    "gn:timezone":"Asia/Makassar",
    "iso:country":"ID",
    "name:ind_x_preferred":[
        "Fatututa"
    ],
    "wof:name":"Fatututa",
    "wof:placetype":"locality"
},
  "geometry": {"coordinates":[124.6151,-9.7658],"type":"Point"}
}