{
  "type": "Feature",
  "properties": {
    "gn:admin1_code":"0.0",
    "gn:asciiname":"Sayar",
    "gn:cc2":"ID",
    "gn:country_code":"ID",
    "gn:dem":206,
    "gn:feature_class":"P",
    "gn:feature_code":"PPL",
    "gn:name":"Sayar",
    "gn:population":0,
    "gn:timezone":"Asia/Jakarta",
    "iso:country":"ID",
    "name:deu_x_preferred":[
        "Sayar"
    ],
    "name:tur_x_preferred":[
        "Sayar"
    ],
    "name:und_x_variant":[
        "Sajar",
        "Sayar"
    ],
    "wof:lang_x_official":[
        "ind"
    ],
    "wof:lang_x_spoken":[
        "ind",
        "eng"
    ],
    "wof:name":"Sayar",
    "wof:placetype":"locality"
},
  "geometry": {"coordinates":[106.09999999999999,-6.15],"type":"Point"}
}