{
  "type": "Feature",
  "properties": {
    "gn:admin1_code":"35.0",
    "gn:asciiname":"Mula",
    "gn:country_code":"ID",
    "gn:dem":7,
    "gn:feature_class":"P",
    "gn:feature_code":"PPL",
    "gn:name":"Mula",
    "gn:population":0,
    "gn:timezone":"Asia/Jakarta",
    "iso:country":"ID",
    "name:ind_x_preferred":[
        "Mula"
    ],
    "name:und_x_variant":[
        "Moelia",
        "Mulia"
    ],
    "wof:name":"Mula",
    "wof:placetype":"locality"
},
  "geometry": {"coordinates":[106.26465,-2.36916],"type":"Point"}
}