{
  "type": "Feature",
  "properties": {
    "gn:admin1_code":"35.0",
    "gn:asciiname":"Mula",
    "gn:country_code":"ID",
    "gn:dem":7,
    "gn:feature_class":"P",
    "gn:feature_code":"PPL",
    "gn:name":"Mula",
    "gn:population":0,
    "gn:timezone":"Asia/Jakarta",
    "iso:country":"ID",
    "name:ara_x_preferred":[
        "\u0645\u0648\u0644\u0629"
    ],
    "name:arg_x_preferred":[
        "Mula"
    ],
    "name:cat_x_preferred":[
        "Mula"
    ],
    "name:ceb_x_preferred":[
        "Mula"
    ],
    "name:deu_x_preferred":[
        "Mula"
    ],
    "name:fra_x_preferred":[
        "Mula"
    ],
    "name:ind_x_preferred":[
        "Mula"
    ],
    "name:ita_x_preferred":[
        "Mula"
    ],
    "name:nds_x_preferred":[
        "Mula"
    ],
    "name:por_x_preferred":[
        "Mula"
    ],
    "name:spa_x_preferred":[
        "Mula"
    ],
    "name:swe_x_preferred":[
        "Mula"
    ],
    "name:tur_x_preferred":[
        "Mula"
    ],
    "name:und_x_variant":[
        "Moelia",
        "Mulia"
    ],
    "wof:lang_x_official":[
        "ind"
    ],
    "wof:lang_x_spoken":[
        "ind",
        "eng"
    ],
    "wof:name":"Mula",
    "wof:placetype":"locality"
},
  "geometry": {"coordinates":[106.26465,-2.36916],"type":"Point"}
}