{
  "type": "Feature",
  "properties": {
    "gn:admin1_code":"30",
    "gn:asciiname":"Bojonggadung",
    "gn:cc2":"ID",
    "gn:country_code":"ID",
    "gn:dem":8,
    "gn:feature_class":"P",
    "gn:feature_code":"PPL",
    "gn:name":"Bojonggadung",
    "gn:population":0,
    "gn:timezone":"Asia/Jakarta",
    "iso:country":"ID",
    "name:und_x_variant":[
        "Bodjonggadung 1",
        "Bodjonggadung",
        "Bodjonggadung Satu",
        "Bojonggadung"
    ],
    "wof:name":"Bojonggadung",
    "wof:placetype":"locality"
},
  "geometry": {"coordinates":[106.30306000000002,-6.07611],"type":"Point"}
}