{
  "type": "Feature",
  "properties": {
    "gn:admin1_code":"36.0",
    "gn:asciiname":"Wariek",
    "gn:country_code":"ID",
    "gn:dem":13,
    "gn:feature_class":"P",
    "gn:feature_code":"PPL",
    "gn:name":"Wariek",
    "gn:population":0,
    "gn:timezone":"Asia/Jayapura",
    "iso:country":"ID",
    "name:und_x_variant":[
        "Warik",
        "Wariek"
    ],
    "wof:name":"Wariek",
    "wof:placetype":"locality"
},
  "geometry": {"coordinates":[140.68743999999998,-8.33761],"type":"Point"}
}