{
  "type": "Feature",
  "properties": {
    "gn:admin1_code":"30.0",
    "gn:asciiname":"Sidikmulya",
    "gn:country_code":"ID",
    "gn:dem":155,
    "gn:feature_class":"P",
    "gn:feature_code":"PPL",
    "gn:name":"Sidikmulya",
    "gn:population":0,
    "gn:timezone":"Asia/Jakarta",
    "iso:country":"ID",
    "name:ind_x_preferred":[
        "Sidikmulya"
    ],
    "wof:name":"Sidikmulya",
    "wof:placetype":"locality"
},
  "geometry": {"coordinates":[108.4726,-7.617],"type":"Point"}
}