{
  "type": "Feature",
  "properties": {
    "gn:admin1_code":"7",
    "gn:asciiname":"Kasotengah",
    "gn:country_code":"ID",
    "gn:dem":177,
    "gn:feature_class":"P",
    "gn:feature_code":"PPL",
    "gn:name":"Kasotengah",
    "gn:population":0,
    "gn:timezone":"Asia/Jakarta",
    "iso:country":"ID",
    "name:ind_x_preferred":[
        "Kasotengah"
    ],
    "wof:name":"Kasotengah",
    "wof:placetype":"locality"
},
  "geometry": {"coordinates":[109.68989999999999,-7.0318],"type":"Point"}
}