{
  "type": "Feature",
  "properties": {
    "gn:admin1_code":"17.0",
    "gn:asciiname":"Lingkokteres",
    "gn:country_code":"ID",
    "gn:dem":157,
    "gn:feature_class":"P",
    "gn:feature_code":"PPL",
    "gn:name":"Lingkokteres",
    "gn:population":0,
    "gn:timezone":"Asia/Makassar",
    "iso:country":"ID",
    "name:ind_x_preferred":[
        "Lingkokteres"
    ],
    "wof:name":"Lingkokteres",
    "wof:placetype":"locality"
},
  "geometry": {"coordinates":[116.376,-8.735],"type":"Point"}
}