{
  "type": "Feature",
  "properties": {
    "gn:admin1_code":"17",
    "gn:asciiname":"Peseng Daya",
    "gn:country_code":"ID",
    "gn:dem":490,
    "gn:feature_class":"P",
    "gn:feature_code":"PPL",
    "gn:name":"Peseng Daya",
    "gn:population":0,
    "gn:timezone":"Asia/Makassar",
    "iso:country":"ID",
    "name:ind_x_preferred":[
        "Peseng Daya"
    ],
    "wof:name":"Peseng Daya",
    "wof:placetype":"locality"
},
  "geometry": {"coordinates":[116.3753,-8.5769],"type":"Point"}
}