{
  "type": "Feature",
  "properties": {
    "gn:admin1_code":"30.0",
    "gn:asciiname":"Lebakjaya",
    "gn:country_code":"ID",
    "gn:dem":857,
    "gn:feature_class":"P",
    "gn:feature_code":"PPL",
    "gn:name":"Lebakjaya",
    "gn:population":0,
    "gn:timezone":"Asia/Jakarta",
    "iso:country":"ID",
    "name:ind_x_preferred":[
        "Lebakjaya"
    ],
    "name:und_x_variant":[
        "Lebakdjaja"
    ],
    "wof:lang_x_official":[
        "ind"
    ],
    "wof:lang_x_spoken":[
        "ind",
        "eng"
    ],
    "wof:name":"Lebakjaya",
    "wof:placetype":"locality"
},
  "geometry": {"coordinates":[107.9431,-7.2326],"type":"Point"}
}