{
  "type": "Feature",
  "properties": {
    "gn:admin1_code":"30.0",
    "gn:asciiname":"Cipeundeuy",
    "gn:country_code":"ID",
    "gn:dem":463,
    "gn:feature_class":"P",
    "gn:feature_code":"PPL",
    "gn:name":"Cipeundeuy",
    "gn:population":0,
    "gn:timezone":"Asia/Jakarta",
    "iso:country":"ID",
    "name:ind_x_preferred":[
        "Cipeundeuy"
    ],
    "name:und_x_variant":[
        "Tjipendeuj",
        "Cipendeuy"
    ],
    "wof:lang_x_official":[
        "ind"
    ],
    "wof:lang_x_spoken":[
        "ind",
        "eng"
    ],
    "wof:name":"Cipeundeuy",
    "wof:placetype":"locality"
},
  "geometry": {"coordinates":[108.18028,-6.94778],"type":"Point"}
}