{
  "type": "Feature",
  "properties": {
    "gn:admin1_code":"07",
    "gn:asciiname":"Kemiri",
    "gn:country_code":"ID",
    "gn:dem":729,
    "gn:feature_class":"P",
    "gn:feature_code":"PPL",
    "gn:name":"Kemiri",
    "gn:population":0,
    "gn:timezone":"Asia/Jakarta",
    "iso:country":"ID",
    "wof:name":"Kemiri",
    "wof:placetype":"locality"
},
  "geometry": {"coordinates":[110.26361,-7.26972],"type":"Point"}
}