{
  "type": "Feature",
  "properties": {
    "gn:admin1_code":"15.0",
    "gn:asciiname":"Ganjaragung Satu",
    "gn:country_code":"ID",
    "gn:dem":56,
    "gn:feature_class":"P",
    "gn:feature_code":"PPL",
    "gn:name":"Ganjaragung Satu",
    "gn:population":0,
    "gn:timezone":"Asia/Jakarta",
    "iso:country":"ID",
    "name:ind_x_preferred":[
        "Ganjaragung Satu"
    ],
    "name:und_x_variant":[
        "Ganjaragung 1"
    ],
    "wof:lang_x_official":[
        "ind"
    ],
    "wof:lang_x_spoken":[
        "ind",
        "eng"
    ],
    "wof:name":"Ganjaragung Satu",
    "wof:placetype":"locality"
},
  "geometry": {"coordinates":[105.28852999999999,-5.12146],"type":"Point"}
}