{
  "type": "Feature",
  "properties": {
    "gn:country":"ID",
    "gn:fcode":"PPLA3",
    "gn:pop":0,
    "iso:country":"ID",
    "name:unk_x_variant":[
        "Rambipoedji"
    ],
    "qs:name":"Rambipuji",
    "qs:photos_9r":0,
    "qs:photos_sr":0,
    "qs:pop_sr":"0",
    "wof:lang_x_official":[
        "ind"
    ],
    "wof:lang_x_spoken":[
        "ind",
        "eng"
    ],
    "wof:name":"Rambipuji",
    "wof:placetype":"locality",
    "wof:population":0
},
  "geometry": {"coordinates":[113.6092,-8.209],"type":"Point"}
}