{
  "type": "Feature",
  "properties": {
    "gn:admin1_code":"30",
    "gn:asciiname":"Kebonitiwu",
    "gn:country_code":"ID",
    "gn:dem":671,
    "gn:feature_class":"P",
    "gn:feature_code":"PPL",
    "gn:name":"Kebonitiwu",
    "gn:population":0,
    "gn:timezone":"Asia/Jakarta",
    "iso:country":"ID",
    "wof:name":"Kebonitiwu",
    "wof:placetype":"locality"
},
  "geometry": {"coordinates":[107.73944,-7.03861],"type":"Point"}
}