{
  "type": "Feature",
  "properties": {
    "gn:admin1_code":"30",
    "gn:asciiname":"Cilangkap",
    "gn:cc2":"ID",
    "gn:country_code":"ID",
    "gn:dem":66,
    "gn:feature_class":"P",
    "gn:feature_code":"PPL",
    "gn:name":"Cilangkap",
    "gn:population":0,
    "gn:timezone":"Asia/Jakarta",
    "iso:country":"ID",
    "name:und_x_variant":[
        "Tjilangap 1",
        "Cilangap Satu",
        "Cilangkap"
    ],
    "wof:name":"Cilangkap",
    "wof:placetype":"locality"
},
  "geometry": {"coordinates":[106.55278,-6.36111],"type":"Point"}
}