{
  "type": "Feature",
  "properties": {
    "gn:admin1_code":"0.0",
    "gn:asciiname":"Mebetce",
    "gn:cc2":"ID",
    "gn:country_code":"ID",
    "gn:dem":33,
    "gn:feature_class":"P",
    "gn:feature_code":"PPL",
    "gn:name":"Mebetce",
    "gn:population":0,
    "gn:timezone":"Asia/Jayapura",
    "iso:country":"ID",
    "name:und_x_variant":[
        "Mibitje",
        "Mebettje",
        "Mebetche",
        "Mebetce"
    ],
    "wof:name":"Mebetce",
    "wof:placetype":"locality"
},
  "geometry": {"coordinates":[140.76667,-7.56667],"type":"Point"}
}