{
  "type": "Feature",
  "properties": {
    "gn:admin1_code":"37.0",
    "gn:asciiname":"Dusuntenang",
    "gn:country_code":"ID",
    "gn:dem":42,
    "gn:feature_class":"P",
    "gn:feature_code":"PPL",
    "gn:name":"Dusuntenang",
    "gn:population":0,
    "gn:timezone":"Asia/Jakarta",
    "iso:country":"ID",
    "name:ind_x_preferred":[
        "Dusuntenang"
    ],
    "wof:name":"Dusuntenang",
    "wof:placetype":"locality"
},
  "geometry": {"coordinates":[102.18691,-0.15898],"type":"Point"}
}