{
  "type": "Feature",
  "properties": {
    "gn:admin1_code":"0.0",
    "gn:asciiname":"Curukbadak",
    "gn:cc2":"ID",
    "gn:country_code":"ID",
    "gn:dem":6,
    "gn:feature_class":"P",
    "gn:feature_code":"PPL",
    "gn:name":"Curukbadak",
    "gn:population":0,
    "gn:timezone":"Asia/Jakarta",
    "iso:country":"ID",
    "name:und_x_variant":[
        "Tjurukbadak",
        "Curukbadak"
    ],
    "wof:name":"Curukbadak",
    "wof:placetype":"locality"
},
  "geometry": {"coordinates":[107.75,-6.31667],"type":"Point"}
}