{
  "type": "Feature",
  "properties": {
    "gn:admin1_code":"8",
    "gn:asciiname":"Lingkungan Tiga",
    "gn:country_code":"ID",
    "gn:dem":113,
    "gn:feature_class":"P",
    "gn:feature_code":"PPL",
    "gn:name":"Lingkungan Tiga",
    "gn:population":0,
    "gn:timezone":"Asia/Jakarta",
    "iso:country":"ID",
    "name:ind_x_preferred":[
        "Lingkungan Tiga"
    ],
    "wof:name":"Lingkungan Tiga",
    "wof:placetype":"locality"
},
  "geometry": {"coordinates":[111.4956,-7.8648],"type":"Point"}
}