{
  "type": "Feature",
  "properties": {
    "gn:admin1_code":"8",
    "gn:asciiname":"Mengen Selatan",
    "gn:country_code":"ID",
    "gn:dem":370,
    "gn:feature_class":"P",
    "gn:feature_code":"PPL",
    "gn:name":"Mengen Selatan",
    "gn:population":0,
    "gn:timezone":"Asia/Jakarta",
    "iso:country":"ID",
    "name:ind_x_preferred":[
        "Mengen Selatan"
    ],
    "wof:name":"Mengen Selatan",
    "wof:placetype":"locality"
},
  "geometry": {"coordinates":[113.8468,-8.0441],"type":"Point"}
}