{
  "type": "Feature",
  "properties": {
    "gn:admin1_code":"0.0",
    "gn:asciiname":"Alokonik",
    "gn:cc2":"ID",
    "gn:country_code":"ID",
    "gn:dem":2356,
    "gn:feature_class":"P",
    "gn:feature_code":"PPL",
    "gn:name":"Alokonik",
    "gn:population":0,
    "gn:timezone":"Asia/Jayapura",
    "iso:country":"ID",
    "name:und_x_variant":[
        "Alaknik",
        "Aloknik",
        "Alokonik"
    ],
    "wof:lang_x_official":[
        "ind"
    ],
    "wof:lang_x_spoken":[
        "ind",
        "eng"
    ],
    "wof:name":"Alokonik",
    "wof:placetype":"locality"
},
  "geometry": {"coordinates":[138.51667,-3.81667],"type":"Point"}
}