{
  "type": "Feature",
  "properties": {
    "gn:admin1_code":"17",
    "gn:asciiname":"Teluk",
    "gn:country_code":"ID",
    "gn:dem":422,
    "gn:feature_class":"P",
    "gn:feature_code":"PPL",
    "gn:name":"Teluk",
    "gn:population":0,
    "gn:timezone":"Asia/Makassar",
    "iso:country":"ID",
    "name:ind_x_preferred":[
        "Teluk"
    ],
    "wof:name":"Teluk",
    "wof:placetype":"locality"
},
  "geometry": {"coordinates":[116.4091,-8.5919],"type":"Point"}
}