{
  "type": "Feature",
  "properties": {
    "gn:admin1_code":"22",
    "gn:asciiname":"Puwehuko Dua",
    "gn:country_code":"ID",
    "gn:dem":30,
    "gn:feature_class":"P",
    "gn:feature_code":"PPL",
    "gn:name":"Puwehuko Dua",
    "gn:population":0,
    "gn:timezone":"Asia/Makassar",
    "iso:country":"ID",
    "name:ind_x_preferred":[
        "Puwehuko Dua"
    ],
    "name:und_x_variant":[
        "Puwehuko 2",
        "Puwehuko"
    ],
    "wof:name":"Puwehuko Dua",
    "wof:placetype":"locality"
},
  "geometry": {"coordinates":[122.2242,-4.0466],"type":"Point"}
}