{
  "type": "Feature",
  "properties": {
    "gn:admin1_code":"18.0",
    "gn:asciiname":"Lamaluwo",
    "gn:country_code":"ID",
    "gn:dem":656,
    "gn:feature_class":"P",
    "gn:feature_code":"PPLA4",
    "gn:name":"Lamaluwo",
    "gn:population":0,
    "gn:timezone":"Asia/Makassar",
    "iso:country":"ID",
    "name:ind_x_preferred":[
        "Lamaluwo"
    ],
    "wof:name":"Lamaluwo",
    "wof:placetype":"locality"
},
  "geometry": {"coordinates":[123.1542,-8.3435],"type":"Point"}
}