{
  "type": "Feature",
  "properties": {
    "gn:admin1_code":"30",
    "gn:asciiname":"Cigelendong",
    "gn:country_code":"ID",
    "gn:dem":898,
    "gn:feature_class":"P",
    "gn:feature_code":"PPL",
    "gn:name":"Cigelendong",
    "gn:population":0,
    "gn:timezone":"Asia/Jakarta",
    "iso:country":"ID",
    "name:ind_x_preferred":[
        "Cigelendong"
    ],
    "name:und_x_variant":[
        "Tjigalendang",
        "Cigalendang"
    ],
    "wof:name":"Cigelendong",
    "wof:placetype":"locality"
},
  "geometry": {"coordinates":[107.59278,-6.865],"type":"Point"}
}