{
  "type": "Feature",
  "properties": {
    "gn:admin1_code":"26",
    "gn:asciiname":"Afdeling Tiga Bangun",
    "gn:country_code":"ID",
    "gn:dem":260,
    "gn:feature_class":"P",
    "gn:feature_code":"PPL",
    "gn:name":"Afdeling Tiga Bangun",
    "gn:population":0,
    "gn:timezone":"Asia/Jakarta",
    "iso:country":"ID",
    "name:ind_x_preferred":[
        "Afdeling Tiga Bangun"
    ],
    "name:und_x_variant":[
        "Afdeling 3 Bangun"
    ],
    "wof:lang_x_official":[
        "ind"
    ],
    "wof:lang_x_spoken":[
        "ind",
        "eng"
    ],
    "wof:name":"Afdeling Tiga Bangun",
    "wof:placetype":"locality"
},
  "geometry": {"coordinates":[99.1328,2.975],"type":"Point"}
}