{
  "type": "Feature",
  "properties": {
    "gn:admin1_code":"18.0",
    "gn:asciiname":"Jore",
    "gn:country_code":"ID",
    "gn:dem":42,
    "gn:feature_class":"P",
    "gn:feature_code":"PPL",
    "gn:name":"Jore",
    "gn:population":0,
    "gn:timezone":"Asia/Makassar",
    "iso:country":"ID",
    "name:ind_x_preferred":[
        "Jore"
    ],
    "name:tam_x_preferred":[
        "\u0b9c\u0bcb\u0bb0\u0bcd"
    ],
    "wof:lang_x_official":[
        "ind"
    ],
    "wof:lang_x_spoken":[
        "ind",
        "eng"
    ],
    "wof:name":"Jore",
    "wof:placetype":"locality"
},
  "geometry": {"coordinates":[121.8591,-10.5147],"type":"Point"}
}