{
  "type": "Feature",
  "properties": {
    "gn:admin1_code":"1",
    "gn:asciiname":"Sehelap",
    "gn:country_code":"ID",
    "gn:dem":22,
    "gn:feature_class":"P",
    "gn:feature_code":"PPL",
    "gn:name":"Sehelap",
    "gn:population":0,
    "gn:timezone":"Asia/Jakarta",
    "iso:country":"ID",
    "name:ind_x_preferred":[
        "Sehelap"
    ],
    "wof:name":"Sehelap",
    "wof:placetype":"locality"
},
  "geometry": {"coordinates":[95.4038,5.4858],"type":"Point"}
}