{
  "type": "Feature",
  "properties": {
    "gn:admin1_code":"1.0",
    "gn:asciiname":"Madang",
    "gn:country_code":"ID",
    "gn:dem":25,
    "gn:feature_class":"P",
    "gn:feature_code":"PPL",
    "gn:name":"Madang",
    "gn:population":0,
    "gn:timezone":"Asia/Jakarta",
    "iso:country":"ID",
    "name:ceb_x_preferred":[
        "Madang"
    ],
    "name:deu_x_preferred":[
        "Madang"
    ],
    "name:fas_x_preferred":[
        "\u0645\u0627\u062f\u0627\u0646\u06af"
    ],
    "name:fin_x_preferred":[
        "Madang"
    ],
    "name:fra_x_preferred":[
        "Madang"
    ],
    "name:glg_x_preferred":[
        "Madang"
    ],
    "name:heb_x_preferred":[
        "\u05d4\u05d0\u05d9 \u05de\u05d3\u05d9\u05e8\u05d4"
    ],
    "name:heb_x_variant":[
        "\u05de\u05d3\u05e0\u05d2"
    ],
    "name:hin_x_preferred":[
        "\u092e\u0926\u093e\u0902\u0917"
    ],
    "name:hun_x_preferred":[
        "Madang"
    ],
    "name:ind_x_preferred":[
        "Madang"
    ],
    "name:ita_x_preferred":[
        "Madang"
    ],
    "name:jpn_x_preferred":[
        "\u30de\u30c0\u30f3"
    ],
    "name:kor_x_preferred":[
        "\ub9c8\ub2f9"
    ],
    "name:lit_x_preferred":[
        "Madangas"
    ],
    "name:nld_x_preferred":[
        "Madang"
    ],
    "name:pol_x_preferred":[
        "Madang"
    ],
    "name:por_x_preferred":[
        "Madang"
    ],
    "name:rus_x_preferred":[
        "\u041c\u0430\u0434\u0430\u043d\u0433"
    ],
    "name:spa_x_preferred":[
        "Madang"
    ],
    "name:swe_x_preferred":[
        "Madang"
    ],
    "name:tpi_x_preferred":[
        "Madang"
    ],
    "name:ukr_x_preferred":[
        "\u041c\u0430\u0434\u0430\u043d\u0433"
    ],
    "name:urd_x_preferred":[
        "\u0645\u0627\u062f\u0646\u06af"
    ],
    "name:vie_x_preferred":[
        "Madang"
    ],
    "wof:lang_x_official":[
        "ind"
    ],
    "wof:lang_x_spoken":[
        "ind",
        "eng"
    ],
    "wof:name":"Madang",
    "wof:placetype":"locality"
},
  "geometry": {"coordinates":[95.1576,5.6272],"type":"Point"}
}