{
  "type": "Feature",
  "properties": {
    "gn:admin1_code":"30",
    "gn:asciiname":"Sukamulya Dua",
    "gn:country_code":"ID",
    "gn:dem":102,
    "gn:feature_class":"P",
    "gn:feature_code":"PPL",
    "gn:name":"Sukamulya Dua",
    "gn:population":0,
    "gn:timezone":"Asia/Jakarta",
    "iso:country":"ID",
    "name:ind_x_preferred":[
        "Sukamulya Dua"
    ],
    "wof:name":"Sukamulya Dua",
    "wof:placetype":"locality"
},
  "geometry": {"coordinates":[108.26833000000001,-6.81083],"type":"Point"}
}