{
  "type": "Feature",
  "properties": {
    "gn:admin1_code":"30.0",
    "gn:asciiname":"Bunijaya",
    "gn:country_code":"ID",
    "gn:dem":326,
    "gn:feature_class":"P",
    "gn:feature_code":"PPL",
    "gn:name":"Bunijaya",
    "gn:population":0,
    "gn:timezone":"Asia/Jakarta",
    "iso:country":"ID",
    "name:ind_x_preferred":[
        "Bunijaya"
    ],
    "wof:name":"Bunijaya",
    "wof:placetype":"locality"
},
  "geometry": {"coordinates":[107.6904,-7.5609],"type":"Point"}
}