{
  "type": "Feature",
  "properties": {
    "gn:admin1_code":"8.0",
    "gn:asciiname":"Krajan Kedungsalam",
    "gn:country_code":"ID",
    "gn:dem":332,
    "gn:feature_class":"P",
    "gn:feature_code":"PPLA4",
    "gn:name":"Krajan Kedungsalam",
    "gn:population":0,
    "gn:timezone":"Asia/Jakarta",
    "iso:country":"ID",
    "name:ind_x_preferred":[
        "Krajan Kedungsalam"
    ],
    "wof:name":"Krajan Kedungsalam",
    "wof:placetype":"locality"
},
  "geometry": {"coordinates":[112.45010000000001,-8.3251],"type":"Point"}
}