{
  "type": "Feature",
  "properties": {
    "gn:gn_country":"ID",
    "gn:gn_fcode":"ADM3",
    "gn:gn_pop":0,
    "iso:country":"ID",
    "name:ind_x_preferred":[
        "Kecamatan Banjit"
    ],
    "name:unk_x_variant":[
        "Banjit"
    ],
    "qs_pg:aaroncc":"ID",
    "qs_pg:gn_country":"ID",
    "qs_pg:gn_fcode":"ADM3",
    "qs_pg:gn_pop":0,
    "qs_pg:name":"Kecamatan Banjit",
    "qs_pg:photos_9r":0,
    "qs_pg:photos_sr":0,
    "qs_pg:pop_sr":0,
    "qs_pg:qs_pg_placetype":"localadmin",
    "wof:lang_x_official":[
        "ind"
    ],
    "wof:lang_x_spoken":[
        "ind",
        "eng"
    ],
    "wof:name":"Kecamatan Banjit",
    "wof:placetype":"localadmin"
},
  "geometry": {"coordinates":[104.49602,-4.85499],"type":"Point"}
}