{
  "type": "Feature",
  "properties": {
    "gn:admin1_code":"30.0",
    "gn:asciiname":"Lebakteureup",
    "gn:country_code":"ID",
    "gn:dem":490,
    "gn:feature_class":"P",
    "gn:feature_code":"PPL",
    "gn:name":"Lebakteureup",
    "gn:population":0,
    "gn:timezone":"Asia/Jakarta",
    "iso:country":"ID",
    "name:ind_x_preferred":[
        "Lebakteureup"
    ],
    "wof:name":"Lebakteureup",
    "wof:placetype":"locality"
},
  "geometry": {"coordinates":[108.3656,-7.1503],"type":"Point"}
}