{
  "type": "Feature",
  "properties": {
    "gn:admin1_code":"36",
    "gn:asciiname":"Kobakma",
    "gn:country_code":"ID",
    "gn:dem":961,
    "gn:feature_class":"P",
    "gn:feature_code":"PPLA2",
    "gn:name":"Kobakma",
    "gn:population":0,
    "gn:timezone":"Asia/Jayapura",
    "iso:country":"ID",
    "name:ind_x_preferred":[
        "Kobakma"
    ],
    "wof:name":"Kobakma",
    "wof:placetype":"locality"
},
  "geometry": {"coordinates":[139.065,-3.66417],"type":"Point"}
}