{
  "type": "Feature",
  "properties": {
    "gn:admin1_code":"15",
    "gn:asciiname":"Negarasaka",
    "gn:country_code":"ID",
    "gn:dem":87,
    "gn:feature_class":"P",
    "gn:feature_code":"PPL",
    "gn:name":"Negarasaka",
    "gn:population":0,
    "gn:timezone":"Asia/Jakarta",
    "iso:country":"ID",
    "name:ind_x_preferred":[
        "Negarasaka"
    ],
    "wof:name":"Negarasaka",
    "wof:placetype":"locality"
},
  "geometry": {"coordinates":[105.16515,-5.23886],"type":"Point"}
}