{
  "type": "Feature",
  "properties": {
    "gn:admin1_code":"32.0",
    "gn:asciiname":"Negeriagungbaru",
    "gn:country_code":"ID",
    "gn:dem":149,
    "gn:feature_class":"P",
    "gn:feature_code":"PPL",
    "gn:name":"Negeriagungbaru",
    "gn:population":0,
    "gn:timezone":"Asia/Jakarta",
    "iso:country":"ID",
    "name:ind_x_preferred":[
        "Negeriagungbaru"
    ],
    "wof:name":"Negeriagungbaru",
    "wof:placetype":"locality"
},
  "geometry": {"coordinates":[103.98359000000001,-4.52497],"type":"Point"}
}