{
  "type": "Feature",
  "properties": {
    "gn:admin1_code":"26",
    "gn:asciiname":"Padangbongbongan",
    "gn:country_code":"ID",
    "gn:dem":50,
    "gn:feature_class":"P",
    "gn:feature_code":"PPL",
    "gn:name":"Padangbongbongan",
    "gn:population":0,
    "gn:timezone":"Asia/Jakarta",
    "iso:country":"ID",
    "name:ind_x_preferred":[
        "Padangbongbongan"
    ],
    "wof:name":"Padangbongbongan",
    "wof:placetype":"locality"
},
  "geometry": {"coordinates":[99.8348,1.4525],"type":"Point"}
}