{
  "type": "Feature",
  "properties": {
    "gn:admin1_code":"38",
    "gn:asciiname":"Monconge",
    "gn:country_code":"ID",
    "gn:dem":7,
    "gn:feature_class":"P",
    "gn:feature_code":"PPL",
    "gn:name":"Monconge",
    "gn:population":0,
    "gn:timezone":"Asia/Makassar",
    "iso:country":"ID",
    "name:ind_x_preferred":[
        "Monconge"
    ],
    "wof:name":"Monconge",
    "wof:placetype":"locality"
},
  "geometry": {"coordinates":[119.601,-4.5737],"type":"Point"}
}