{
  "type": "Feature",
  "properties": {
    "gn:admin1_code":"8.0",
    "gn:asciiname":"Mojo",
    "gn:country_code":"ID",
    "gn:dem":79,
    "gn:feature_class":"P",
    "gn:feature_code":"PPL",
    "gn:name":"Mojo",
    "gn:population":0,
    "gn:timezone":"Asia/Jakarta",
    "iso:country":"ID",
    "name:ceb_x_preferred":[
        "Mojo"
    ],
    "name:ces_x_preferred":[
        "Mojo"
    ],
    "name:deu_x_preferred":[
        "Mojo"
    ],
    "name:fra_x_preferred":[
        "Mojo"
    ],
    "name:hun_x_preferred":[
        "Mojo"
    ],
    "name:ind_x_preferred":[
        "Mojo"
    ],
    "name:ita_x_preferred":[
        "Mojo"
    ],
    "name:jpn_x_preferred":[
        "\u30e2\u30b8\u30e7"
    ],
    "name:msa_x_preferred":[
        "Mojo"
    ],
    "name:nld_x_preferred":[
        "Mojo"
    ],
    "name:pol_x_preferred":[
        "Mojo"
    ],
    "name:por_x_preferred":[
        "Mojo"
    ],
    "name:rus_x_preferred":[
        "Mojo"
    ],
    "name:spa_x_preferred":[
        "Mojo"
    ],
    "name:swe_x_preferred":[
        "Mojo"
    ],
    "wof:lang_x_official":[
        "ind"
    ],
    "wof:lang_x_spoken":[
        "ind",
        "eng"
    ],
    "wof:name":"Mojo",
    "wof:placetype":"locality"
},
  "geometry": {"coordinates":[111.5819,-7.4369],"type":"Point"}
}