{
  "type": "Feature",
  "properties": {
    "gn:admin1_code":"26",
    "gn:asciiname":"Pasar Sembilan",
    "gn:country_code":"ID",
    "gn:dem":111,
    "gn:feature_class":"P",
    "gn:feature_code":"PPL",
    "gn:name":"Pasar Sembilan",
    "gn:population":0,
    "gn:timezone":"Asia/Jakarta",
    "iso:country":"ID",
    "name:ind_x_preferred":[
        "Pasar Sembilan"
    ],
    "name:und_x_variant":[
        "Pasar 9"
    ],
    "wof:lang_x_official":[
        "ind"
    ],
    "wof:lang_x_spoken":[
        "ind",
        "eng"
    ],
    "wof:name":"Pasar Sembilan",
    "wof:placetype":"locality"
},
  "geometry": {"coordinates":[98.68600000000001,3.4258],"type":"Point"}
}