{
  "type": "Feature",
  "properties": {
    "gn:admin1_code":"7.0",
    "gn:asciiname":"Rabak",
    "gn:country_code":"ID",
    "gn:dem":98,
    "gn:feature_class":"P",
    "gn:feature_code":"PPL",
    "gn:name":"Rabak",
    "gn:population":0,
    "gn:timezone":"Asia/Jakarta",
    "iso:country":"ID",
    "name:ara_x_preferred":[
        "\u0631\u0628\u0643"
    ],
    "name:ceb_x_preferred":[
        "Rabak"
    ],
    "name:deu_x_preferred":[
        "Rabak"
    ],
    "name:epo_x_preferred":[
        "Rabak"
    ],
    "name:fas_x_preferred":[
        "\u0631\u0628\u06a9"
    ],
    "name:fra_x_preferred":[
        "Rabak"
    ],
    "name:ind_x_preferred":[
        "Rabak"
    ],
    "name:ita_x_preferred":[
        "Rabak"
    ],
    "name:jpn_x_preferred":[
        "\u30e9\u30d0\u30af"
    ],
    "name:kor_x_preferred":[
        "\ub77c\ubc14\ud06c"
    ],
    "name:lit_x_preferred":[
        "Rabakas"
    ],
    "name:nld_x_preferred":[
        "Rabak"
    ],
    "name:pol_x_preferred":[
        "Rabak"
    ],
    "name:ron_x_preferred":[
        "Rabak"
    ],
    "name:rus_x_preferred":[
        "\u0420\u0430\u0431\u0430\u043a"
    ],
    "name:tur_x_preferred":[
        "Rabak"
    ],
    "name:ukr_x_preferred":[
        "\u0420\u0430\u0431\u0430\u043a"
    ],
    "name:war_x_preferred":[
        "Rabak"
    ],
    "name:zho_x_preferred":[
        "\u62c9\u5df4\u514b"
    ],
    "wof:name":"Rabak",
    "wof:placetype":"locality"
},
  "geometry": {"coordinates":[109.46417,-7.4975],"type":"Point"}
}