{
  "type": "Feature",
  "properties": {
    "gn:admin1_code":"26",
    "gn:asciiname":"Bandar Khalipah Empat",
    "gn:country_code":"ID",
    "gn:dem":20,
    "gn:feature_class":"P",
    "gn:feature_code":"PPL",
    "gn:name":"Bandar Khalipah Empat",
    "gn:population":0,
    "gn:timezone":"Asia/Jakarta",
    "iso:country":"ID",
    "name:ind_x_preferred":[
        "Bandar Khalipah Empat"
    ],
    "name:und_x_variant":[
        "Bandarkhalipah 4"
    ],
    "wof:name":"Bandar Khalipah Empat",
    "wof:placetype":"locality"
},
  "geometry": {"coordinates":[98.74120000000001,3.6092],"type":"Point"}
}