{
  "type": "Feature",
  "properties": {
    "gn:admin1_code":"30.0",
    "gn:asciiname":"Jati",
    "gn:country_code":"ID",
    "gn:dem":710,
    "gn:feature_class":"P",
    "gn:feature_code":"PPL",
    "gn:name":"Jati",
    "gn:population":0,
    "gn:timezone":"Asia/Jakarta",
    "iso:country":"ID",
    "name:bih_x_preferred":[
        "\u091c\u093e\u0924\u093f"
    ],
    "name:ceb_x_preferred":[
        "Jati"
    ],
    "name:fra_x_preferred":[
        "Jati"
    ],
    "name:ind_x_preferred":[
        "Jati"
    ],
    "name:ita_x_preferred":[
        "Jati"
    ],
    "name:jav_x_preferred":[
        "Jati"
    ],
    "name:mal_x_preferred":[
        "\u0d1c\u0d3e\u0d24\u0d3f"
    ],
    "name:nld_x_preferred":[
        "Jati"
    ],
    "name:swe_x_preferred":[
        "Jati"
    ],
    "name:und_x_variant":[
        "Djati"
    ],
    "name:vie_x_preferred":[
        "Jati"
    ],
    "wof:name":"Jati",
    "wof:placetype":"locality"
},
  "geometry": {"coordinates":[107.9935,-7.4919],"type":"Point"}
}