{
  "type": "Feature",
  "properties": {
    "gn:admin1_code":"30.0",
    "gn:asciiname":"Jati",
    "gn:country_code":"ID",
    "gn:dem":710,
    "gn:feature_class":"P",
    "gn:feature_code":"PPL",
    "gn:name":"Jati",
    "gn:population":0,
    "gn:timezone":"Asia/Jakarta",
    "iso:country":"ID",
    "name:ind_x_preferred":[
        "Jati"
    ],
    "name:und_x_variant":[
        "Djati"
    ],
    "wof:name":"Jati",
    "wof:placetype":"locality"
},
  "geometry": {"coordinates":[107.9935,-7.4919],"type":"Point"}
}