{
  "type": "Feature",
  "properties": {
    "gn:admin1_code":"26",
    "gn:asciiname":"Marijanji Asih",
    "gn:country_code":"ID",
    "gn:dem":401,
    "gn:feature_class":"P",
    "gn:feature_code":"PPL",
    "gn:name":"Marijanji Asih",
    "gn:population":0,
    "gn:timezone":"Asia/Jakarta",
    "iso:country":"ID",
    "name:ind_x_preferred":[
        "Marijanji Asih"
    ],
    "name:und_x_variant":[
        "Merdjandjiasih"
    ],
    "wof:lang_x_official":[
        "ind"
    ],
    "wof:lang_x_spoken":[
        "ind",
        "eng"
    ],
    "wof:name":"Marijanji Asih",
    "wof:placetype":"locality"
},
  "geometry": {"coordinates":[99.13930000000001,2.8181],"type":"Point"}
}