{
  "type": "Feature",
  "properties": {
    "gn:country":"ID",
    "gn:fcode":"PPLA3",
    "gn:pop":0,
    "iso:country":"ID",
    "name:ban_x_preferred":[
        "Sedati"
    ],
    "name:ceb_x_preferred":[
        "Kecamatan Sedati"
    ],
    "name:deu_x_preferred":[
        "Sedati"
    ],
    "name:eng_x_preferred":[
        "Sedati"
    ],
    "name:fra_x_preferred":[
        "Sedati"
    ],
    "name:ind_x_preferred":[
        "Sedati"
    ],
    "name:jav_x_preferred":[
        "Sedati"
    ],
    "name:nan_x_preferred":[
        "Sedati"
    ],
    "name:nld_x_preferred":[
        "Sedati"
    ],
    "name:swe_x_preferred":[
        "Kecamatan Sedati"
    ],
    "qs:name":"Sedati",
    "qs:photos_9r":0,
    "qs:photos_sr":0,
    "qs:pop_sr":"0",
    "wd:wordcount":19,
    "wof:lang_x_official":[
        "ind"
    ],
    "wof:lang_x_spoken":[
        "ind",
        "eng"
    ],
    "wof:name":"Sedati",
    "wof:placetype":"locality",
    "wof:population":0
},
  "geometry": {"coordinates":[112.7675,-7.3952],"type":"Point"}
}