{
  "type": "Feature",
  "properties": {
    "gn:admin1_code":"33.0",
    "gn:asciiname":"Rancabaok",
    "gn:country_code":"ID",
    "gn:dem":126,
    "gn:feature_class":"P",
    "gn:feature_code":"PPL",
    "gn:name":"Rancabaok",
    "gn:population":0,
    "gn:timezone":"Asia/Jakarta",
    "iso:country":"ID",
    "name:ind_x_preferred":[
        "Rancabaok"
    ],
    "wof:name":"Rancabaok",
    "wof:placetype":"locality"
},
  "geometry": {"coordinates":[106.0685,-6.4179],"type":"Point"}
}