{
  "type": "Feature",
  "properties": {
    "gn:admin1_code":"30.0",
    "gn:asciiname":"Cilandak",
    "gn:country_code":"ID",
    "gn:dem":954,
    "gn:feature_class":"P",
    "gn:feature_code":"PPL",
    "gn:name":"Cilandak",
    "gn:population":0,
    "gn:timezone":"Asia/Jakarta",
    "iso:country":"ID",
    "name:ind_x_preferred":[
        "Cilandak"
    ],
    "wof:name":"Cilandak",
    "wof:placetype":"locality"
},
  "geometry": {"coordinates":[107.92659999999999,-7.2688],"type":"Point"}
}