{
  "type": "Feature",
  "properties": {
    "gn:admin1_code":"22.0",
    "gn:asciiname":"Ketalaposu",
    "gn:country_code":"ID",
    "gn:dem":8,
    "gn:feature_class":"P",
    "gn:feature_code":"PPL",
    "gn:name":"Ketalaposu",
    "gn:population":0,
    "gn:timezone":"Asia/Makassar",
    "iso:country":"ID",
    "name:ind_x_preferred":[
        "Ketalaposu"
    ],
    "wof:name":"Ketalaposu",
    "wof:placetype":"locality"
},
  "geometry": {"coordinates":[121.81359999999999,-5.2369],"type":"Point"}
}