{
  "type": "Feature",
  "properties": {
    "gn:admin1_code":"1",
    "gn:asciiname":"Uteunpupaleh",
    "gn:country_code":"ID",
    "gn:dem":16,
    "gn:feature_class":"P",
    "gn:feature_code":"PPL",
    "gn:name":"Uteunpupaleh",
    "gn:population":0,
    "gn:timezone":"Asia/Jakarta",
    "iso:country":"ID",
    "name:ind_x_preferred":[
        "Uteunpupaleh"
    ],
    "wof:name":"Uteunpupaleh",
    "wof:placetype":"locality"
},
  "geometry": {"coordinates":[96.5076,5.1529],"type":"Point"}
}