{
  "type": "Feature",
  "properties": {
    "gn:admin1_code":"07",
    "gn:asciiname":"Kajar",
    "gn:country_code":"ID",
    "gn:dem":152,
    "gn:feature_class":"P",
    "gn:feature_code":"PPL",
    "gn:name":"Kajar",
    "gn:population":0,
    "gn:timezone":"Asia/Jakarta",
    "iso:country":"ID",
    "name:und_x_variant":[
        "Kadjar",
        "Kajar"
    ],
    "wof:name":"Kajar",
    "wof:placetype":"locality"
},
  "geometry": {"coordinates":[110.73417000000001,-7.47306],"type":"Point"}
}