{
  "type": "Feature",
  "properties": {
    "gn:admin1_code":"26",
    "gn:asciiname":"Siharbo Dangkal",
    "gn:country_code":"ID",
    "gn:dem":440,
    "gn:feature_class":"P",
    "gn:feature_code":"PPL",
    "gn:name":"Siharbo Dangkal",
    "gn:population":0,
    "gn:timezone":"Asia/Jakarta",
    "iso:country":"ID",
    "name:ind_x_preferred":[
        "Siharbo Dangkal"
    ],
    "wof:name":"Siharbo Dangkal",
    "wof:placetype":"locality"
},
  "geometry": {"coordinates":[98.46720000000001,2.2166],"type":"Point"}
}