{
  "type": "Feature",
  "properties": {
    "gn:admin1_code":"38",
    "gn:asciiname":"Honebase",
    "gn:country_code":"ID",
    "gn:dem":22,
    "gn:feature_class":"P",
    "gn:feature_code":"PPL",
    "gn:name":"Honebase",
    "gn:population":0,
    "gn:timezone":"Asia/Makassar",
    "iso:country":"ID",
    "name:ind_x_preferred":[
        "Honebase"
    ],
    "wof:name":"Honebase",
    "wof:placetype":"locality"
},
  "geometry": {"coordinates":[119.64790000000001,-4.3513],"type":"Point"}
}