{
  "type": "Feature",
  "properties": {
    "gn:admin1_code":"32.0",
    "gn:asciiname":"Talangmumpa",
    "gn:country_code":"ID",
    "gn:dem":70,
    "gn:feature_class":"P",
    "gn:feature_code":"PPL",
    "gn:name":"Talangmumpa",
    "gn:population":0,
    "gn:timezone":"Asia/Jakarta",
    "iso:country":"ID",
    "name:ind_x_preferred":[
        "Talangmumpa"
    ],
    "wof:name":"Talangmumpa",
    "wof:placetype":"locality"
},
  "geometry": {"coordinates":[103.64060000000001,-3.1375],"type":"Point"}
}