{
  "type": "Feature",
  "properties": {
    "gn:admin1_code":"32.0",
    "gn:asciiname":"Tanjungjan",
    "gn:country_code":"ID",
    "gn:dem":14,
    "gn:feature_class":"P",
    "gn:feature_code":"PPL",
    "gn:name":"Tanjungjan",
    "gn:population":0,
    "gn:timezone":"Asia/Jakarta",
    "iso:country":"ID",
    "name:ind_x_preferred":[
        "Tanjungjan"
    ],
    "wof:name":"Tanjungjan",
    "wof:placetype":"locality"
},
  "geometry": {"coordinates":[103.6729,-2.8314],"type":"Point"}
}