{
  "type": "Feature",
  "properties": {
    "gn:admin1_code":"41",
    "gn:asciiname":"Minake",
    "gn:country_code":"ID",
    "gn:dem":982,
    "gn:feature_class":"P",
    "gn:feature_code":"PPL",
    "gn:name":"Minake",
    "gn:population":0,
    "gn:timezone":"Asia/Makassar",
    "iso:country":"ID",
    "name:ind_x_preferred":[
        "Minake"
    ],
    "wof:name":"Minake",
    "wof:placetype":"locality"
},
  "geometry": {"coordinates":[119.2942,-3.026],"type":"Point"}
}