{
  "type": "Feature",
  "properties": {
    "gn:admin1_code":"0.0",
    "gn:asciiname":"Muraukwa",
    "gn:cc2":"ID",
    "gn:country_code":"ID",
    "gn:dem":25,
    "gn:feature_class":"P",
    "gn:feature_code":"PPL",
    "gn:name":"Muraukwa",
    "gn:population":0,
    "gn:timezone":"Asia/Jayapura",
    "iso:country":"ID",
    "name:und_x_variant":[
        "Moeraukwa",
        "Muraukwa"
    ],
    "wof:name":"Muraukwa",
    "wof:placetype":"locality"
},
  "geometry": {"coordinates":[136.69999999999999,-4.83333],"type":"Point"}
}