{
  "type": "Feature",
  "properties": {
    "gn:admin1_code":"26",
    "gn:asciiname":"Kampung Baru Simatorkis",
    "gn:country_code":"ID",
    "gn:dem":552,
    "gn:feature_class":"P",
    "gn:feature_code":"PPL",
    "gn:name":"Kampung Baru Simatorkis",
    "gn:population":0,
    "gn:timezone":"Asia/Jakarta",
    "iso:country":"ID",
    "name:ind_x_preferred":[
        "Kampung Baru Simatorkis"
    ],
    "wof:name":"Kampung Baru Simatorkis",
    "wof:placetype":"locality"
},
  "geometry": {"coordinates":[99.1575,1.4369],"type":"Point"}
}