{
  "type": "Feature",
  "properties": {
    "gn:admin1_code":"38",
    "gn:asciiname":"Parigi",
    "gn:country_code":"ID",
    "gn:dem":994,
    "gn:feature_class":"P",
    "gn:feature_code":"PPL",
    "gn:name":"Parigi",
    "gn:population":0,
    "gn:timezone":"Asia/Makassar",
    "iso:country":"ID",
    "name:ceb_x_preferred":[
        "Parigi"
    ],
    "name:deu_x_preferred":[
        "Parigi"
    ],
    "name:fra_x_preferred":[
        "Parigi"
    ],
    "name:ind_x_preferred":[
        "Parigi"
    ],
    "name:ita_x_preferred":[
        "Parigi"
    ],
    "name:nld_x_preferred":[
        "Parigi"
    ],
    "name:srp_x_preferred":[
        "Parigi"
    ],
    "name:swe_x_preferred":[
        "Parigi"
    ],
    "wof:name":"Parigi",
    "wof:placetype":"locality"
},
  "geometry": {"coordinates":[119.8766,-3.1807],"type":"Point"}
}