{
  "type": "Feature",
  "properties": {
    "gn:admin1_code":"0.0",
    "gn:asciiname":"Perjiwa",
    "gn:cc2":"ID",
    "gn:country_code":"ID",
    "gn:dem":69,
    "gn:feature_class":"P",
    "gn:feature_code":"PPL",
    "gn:name":"Perjiwa",
    "gn:population":0,
    "gn:timezone":"Asia/Makassar",
    "iso:country":"ID",
    "name:und_x_variant":[
        "Perdjiwa",
        "Perjiwa"
    ],
    "wof:lang_x_official":[
        "ind"
    ],
    "wof:lang_x_spoken":[
        "ind",
        "eng"
    ],
    "wof:name":"Perjiwa",
    "wof:placetype":"locality"
},
  "geometry": {"coordinates":[117.01667,-0.41667],"type":"Point"}
}