{
  "type": "Feature",
  "properties": {
    "gn:admin1_code":"0.0",
    "gn:asciiname":"Banti",
    "gn:country_code":"ID",
    "gn:dem":1358,
    "gn:feature_class":"P",
    "gn:feature_code":"PPL",
    "gn:name":"Banti",
    "gn:population":0,
    "gn:timezone":"Asia/Makassar",
    "iso:country":"ID",
    "wof:name":"Banti",
    "wof:placetype":"locality"
},
  "geometry": {"coordinates":[119.83333,-3.46667],"type":"Point"}
}