{
  "type": "Feature",
  "properties": {
    "gn:admin1_code":"30.0",
    "gn:asciiname":"Cimapag Dua",
    "gn:country_code":"ID",
    "gn:dem":479,
    "gn:feature_class":"P",
    "gn:feature_code":"PPL",
    "gn:name":"Cimapag Dua",
    "gn:population":0,
    "gn:timezone":"Asia/Jakarta",
    "iso:country":"ID",
    "name:ind_x_preferred":[
        "Cimapag Dua"
    ],
    "wof:name":"Cimapag Dua",
    "wof:placetype":"locality"
},
  "geometry": {"coordinates":[106.8792,-7.1362],"type":"Point"}
}