{
  "type": "Feature",
  "properties": {
    "gn:admin1_code":"28.0",
    "gn:asciiname":"Naam",
    "gn:country_code":"ID",
    "gn:dem":13,
    "gn:feature_class":"P",
    "gn:feature_code":"PPL",
    "gn:name":"Naam",
    "gn:population":0,
    "gn:timezone":"Asia/Jayapura",
    "iso:country":"ID",
    "name:ind_x_preferred":[
        "Naam"
    ],
    "wof:name":"Naam",
    "wof:placetype":"locality"
},
  "geometry": {"coordinates":[132.81521000000001,-5.54295],"type":"Point"}
}