{
  "type": "Feature",
  "properties": {
    "gn:admin1_code":"7",
    "gn:asciiname":"Kabukan",
    "gn:country_code":"ID",
    "gn:dem":22,
    "gn:feature_class":"P",
    "gn:feature_code":"PPL",
    "gn:name":"Kabukan",
    "gn:population":0,
    "gn:timezone":"Asia/Jakarta",
    "iso:country":"ID",
    "name:ind_x_preferred":[
        "Kabukan"
    ],
    "wof:name":"Kabukan",
    "wof:placetype":"locality"
},
  "geometry": {"coordinates":[109.15730000000001,-6.9318],"type":"Point"}
}