{
  "type": "Feature",
  "properties": {
    "gn:admin1_code":"42",
    "gn:asciiname":"Long Puna",
    "gn:country_code":"ID",
    "gn:dem":995,
    "gn:feature_class":"P",
    "gn:feature_code":"PPL",
    "gn:name":"Long Puna",
    "gn:population":0,
    "gn:timezone":"Asia/Makassar",
    "iso:country":"ID",
    "name:msa_x_preferred":[
        "Long Puna"
    ],
    "wof:name":"Long Puna",
    "wof:placetype":"locality"
},
  "geometry": {"coordinates":[115.61341000000002,3.76304],"type":"Point"}
}