{
  "type": "Feature",
  "properties": {
    "gn:admin1_code":"1.0",
    "gn:asciiname":"Turucut",
    "gn:country_code":"ID",
    "gn:dem":477,
    "gn:feature_class":"P",
    "gn:feature_code":"PPL",
    "gn:name":"Turucut",
    "gn:population":0,
    "gn:timezone":"Asia/Jakarta",
    "iso:country":"ID",
    "name:ind_x_preferred":[
        "Turucut"
    ],
    "wof:name":"Turucut",
    "wof:placetype":"locality"
},
  "geometry": {"coordinates":[96.14163000000001,4.83738],"type":"Point"}
}