{
  "type": "Feature",
  "properties": {
    "gn:admin1_code":"8.0",
    "gn:asciiname":"Popoh",
    "gn:country_code":"ID",
    "gn:dem":23,
    "gn:feature_class":"P",
    "gn:feature_code":"PPL",
    "gn:name":"Popoh",
    "gn:population":0,
    "gn:timezone":"Asia/Jakarta",
    "iso:country":"ID",
    "name:und_x_variant":[
        "Popo",
        "Popoh"
    ],
    "wof:name":"Popoh",
    "wof:placetype":"locality"
},
  "geometry": {"coordinates":[111.8036,-8.2611],"type":"Point"}
}