{
  "type": "Feature",
  "properties": {
    "gn:admin1_code":"1",
    "gn:asciiname":"Seuneubok Padang",
    "gn:country_code":"ID",
    "gn:dem":13,
    "gn:feature_class":"P",
    "gn:feature_code":"PPL",
    "gn:name":"Seuneubok Padang",
    "gn:population":0,
    "gn:timezone":"Asia/Jakarta",
    "iso:country":"ID",
    "name:ind_x_preferred":[
        "Seuneubok Padang"
    ],
    "name:und_x_variant":[
        "Seuneubobakongpaja"
    ],
    "wof:lang_x_official":[
        "ind"
    ],
    "wof:lang_x_spoken":[
        "ind",
        "eng"
    ],
    "wof:name":"Seuneubok Padang",
    "wof:placetype":"locality"
},
  "geometry": {"coordinates":[95.77970000000001,4.4873],"type":"Point"}
}