{
  "type": "Feature",
  "properties": {
    "gn:admin1_code":"11",
    "gn:asciiname":"Mampal",
    "gn:country_code":"ID",
    "gn:dem":57,
    "gn:feature_class":"P",
    "gn:feature_code":"PPL",
    "gn:name":"Mampal",
    "gn:population":0,
    "gn:timezone":"Asia/Pontianak",
    "iso:country":"ID",
    "name:ind_x_preferred":[
        "Mampal"
    ],
    "wof:name":"Mampal",
    "wof:placetype":"locality"
},
  "geometry": {"coordinates":[110.5853,-0.70818],"type":"Point"}
}