{
  "type": "Feature",
  "properties": {
    "gn:admin1_code":"10.0",
    "gn:asciiname":"Krengseng",
    "gn:country_code":"ID",
    "gn:dem":47,
    "gn:feature_class":"P",
    "gn:feature_code":"PPL",
    "gn:name":"Krengseng",
    "gn:population":0,
    "gn:timezone":"Asia/Jakarta",
    "iso:country":"ID",
    "wof:name":"Krengseng",
    "wof:placetype":"locality"
},
  "geometry": {"coordinates":[110.12111000000002,-7.86611],"type":"Point"}
}