{
  "type": "Feature",
  "properties": {
    "gn:admin1_code":"38",
    "gn:asciiname":"Bolamalimponge",
    "gn:country_code":"ID",
    "gn:dem":12,
    "gn:feature_class":"P",
    "gn:feature_code":"PPL",
    "gn:name":"Bolamalimponge",
    "gn:population":0,
    "gn:timezone":"Asia/Makassar",
    "iso:country":"ID",
    "name:ind_x_preferred":[
        "Bolamalimponge"
    ],
    "wof:name":"Bolamalimponge",
    "wof:placetype":"locality"
},
  "geometry": {"coordinates":[120.0458,-4.1663],"type":"Point"}
}