{
  "type": "Feature",
  "properties": {
    "gn:country":"ID",
    "gn:fcode":"PPL",
    "gn:pop":0,
    "iso:country":"ID",
    "name:deu_x_preferred":[
        "Rajabasa"
    ],
    "name:eng_x_preferred":[
        "Raja Basa"
    ],
    "name:eng_x_variant":[
        "Rajabasa"
    ],
    "name:fra_x_preferred":[
        "Rajabasa"
    ],
    "name:ind_x_preferred":[
        "Rajabasa"
    ],
    "name:ind_x_variant":[
        "Raja Basa"
    ],
    "name:nld_x_preferred":[
        "Rajabasa"
    ],
    "name:por_x_preferred":[
        "Raja Basa"
    ],
    "name:sun_x_preferred":[
        "Rajabasa"
    ],
    "qs:name":"Rajabasa",
    "qs:name_adm0":"Indonesia",
    "qs:name_adm1":"Lampung",
    "qs:photos_9k":1,
    "qs:photos_9r":1,
    "qs:photos_all":2,
    "qs:photos_sr":0,
    "qs:placetype":"Town",
    "qs:pop_sr":"0",
    "wd:wordcount":89,
    "wof:lang_x_official":[
        "ind"
    ],
    "wof:lang_x_spoken":[
        "ind",
        "eng"
    ],
    "wof:name":"Rajabasa",
    "wof:placetype":"locality",
    "wof:population":0
},
  "geometry": {"coordinates":[105.59686000000001,-5.82],"type":"Point"}
}