{
  "type": "Feature",
  "properties": {
    "gn:admin1_code":"15.0",
    "gn:asciiname":"Pematangbo",
    "gn:country_code":"ID",
    "gn:dem":20,
    "gn:feature_class":"P",
    "gn:feature_code":"PPL",
    "gn:name":"Pematangbo",
    "gn:population":0,
    "gn:timezone":"Asia/Jakarta",
    "iso:country":"ID",
    "name:ind_x_preferred":[
        "Pematangbo"
    ],
    "name:und_x_variant":[
        "Pematang bom"
    ],
    "wof:name":"Pematangbo",
    "wof:placetype":"locality"
},
  "geometry": {"coordinates":[105.75388999999998,-5.646],"type":"Point"}
}