{
  "type": "Feature",
  "properties": {
    "gn:admin1_code":"30",
    "gn:asciiname":"Periuk",
    "gn:cc2":"ID",
    "gn:country_code":"ID",
    "gn:dem":7,
    "gn:feature_class":"P",
    "gn:feature_code":"PPL",
    "gn:name":"Periuk",
    "gn:population":0,
    "gn:timezone":"Asia/Jakarta",
    "iso:country":"ID",
    "name:und_x_variant":[
        "Pariuk Satu",
        "Pariuk 1",
        "Periuk"
    ],
    "wof:name":"Periuk",
    "wof:placetype":"locality"
},
  "geometry": {"coordinates":[106.31889,-6.07083],"type":"Point"}
}