{
  "type": "Feature",
  "properties": {
    "gn:admin1_code":"7",
    "gn:asciiname":"Jobot Lor",
    "gn:country_code":"ID",
    "gn:dem":211,
    "gn:feature_class":"P",
    "gn:feature_code":"PPL",
    "gn:name":"Jobot Lor",
    "gn:population":0,
    "gn:timezone":"Asia/Jakarta",
    "iso:country":"ID",
    "name:ind_x_preferred":[
        "Jobot Lor"
    ],
    "wof:name":"Jobot Lor",
    "wof:placetype":"locality"
},
  "geometry": {"coordinates":[111.09305999999999,-7.9475],"type":"Point"}
}