{
  "type": "Feature",
  "properties": {
    "gn:admin1_code":"18.0",
    "gn:asciiname":"Oebufu",
    "gn:country_code":"ID",
    "gn:dem":110,
    "gn:feature_class":"P",
    "gn:feature_code":"PPLA4",
    "gn:name":"Oebufu",
    "gn:population":0,
    "gn:timezone":"Asia/Makassar",
    "iso:country":"ID",
    "name:ind_x_preferred":[
        "Oebufu"
    ],
    "wof:name":"Oebufu",
    "wof:placetype":"locality"
},
  "geometry": {"coordinates":[123.621,-10.1786],"type":"Point"}
}