{
  "type": "Feature",
  "properties": {
    "gn:admin1_code":"18.0",
    "gn:asciiname":"Hoebeti",
    "gn:country_code":"ID",
    "gn:dem":556,
    "gn:feature_class":"P",
    "gn:feature_code":"PPL",
    "gn:name":"Hoebeti",
    "gn:population":0,
    "gn:timezone":"Asia/Makassar",
    "iso:country":"ID",
    "name:ind_x_preferred":[
        "Hoebeti"
    ],
    "wof:name":"Hoebeti",
    "wof:placetype":"locality"
},
  "geometry": {"coordinates":[124.59990000000001,-9.9638],"type":"Point"}
}