{
  "type": "Feature",
  "properties": {
    "gn:admin1_code":"36.0",
    "gn:asciiname":"Kwantisore",
    "gn:country_code":"ID",
    "gn:dem":18,
    "gn:feature_class":"P",
    "gn:feature_code":"PPLA3",
    "gn:name":"Kwantisore",
    "gn:population":0,
    "gn:timezone":"Asia/Jayapura",
    "iso:country":"ID",
    "name:ind_x_preferred":[
        "Kwantisore"
    ],
    "name:und_x_variant":[
        "Kwatisore"
    ],
    "wof:lang_x_official":[
        "ind"
    ],
    "wof:lang_x_spoken":[
        "ind",
        "eng"
    ],
    "wof:name":"Kwantisore",
    "wof:placetype":"locality"
},
  "geometry": {"coordinates":[134.90649999999999,-3.2651],"type":"Point"}
}