{
  "type": "Feature",
  "properties": {
    "gn:admin1_code":"14.0",
    "gn:asciiname":"Sebongkok",
    "gn:country_code":"ID",
    "gn:dem":5,
    "gn:feature_class":"P",
    "gn:feature_code":"PPL",
    "gn:name":"Sebongkok",
    "gn:population":0,
    "gn:timezone":"Asia/Makassar",
    "iso:country":"ID",
    "name:ind_x_preferred":[
        "Sebongkok"
    ],
    "wof:name":"Sebongkok",
    "wof:placetype":"locality"
},
  "geometry": {"coordinates":[117.5607,0.7385],"type":"Point"}
}