{
  "type": "Feature",
  "properties": {
    "gn:admin1_code":"38",
    "gn:asciiname":"Bontobonto",
    "gn:country_code":"ID",
    "gn:dem":3,
    "gn:feature_class":"P",
    "gn:feature_code":"PPL",
    "gn:name":"Bontobonto",
    "gn:population":0,
    "gn:timezone":"Asia/Makassar",
    "iso:country":"ID",
    "name:ind_x_preferred":[
        "Bontobonto"
    ],
    "wof:name":"Bontobonto",
    "wof:placetype":"locality"
},
  "geometry": {"coordinates":[119.5518,-4.9389],"type":"Point"}
}