{
  "type": "Feature",
  "properties": {
    "gn:admin1_code":"26",
    "gn:asciiname":"Luning",
    "gn:country_code":"ID",
    "gn:dem":238,
    "gn:feature_class":"P",
    "gn:feature_code":"PPL",
    "gn:name":"Luning",
    "gn:population":0,
    "gn:timezone":"Asia/Jakarta",
    "iso:country":"ID",
    "name:deu_x_preferred":[
        "L\u00fcning"
    ],
    "name:ind_x_preferred":[
        "Luning"
    ],
    "wof:lang_x_official":[
        "ind"
    ],
    "wof:lang_x_spoken":[
        "ind",
        "eng"
    ],
    "wof:name":"Luning",
    "wof:placetype":"locality"
},
  "geometry": {"coordinates":[98.56399999999999,3.4021],"type":"Point"}
}