{
  "type": "Feature",
  "properties": {
    "gn:admin1_code":"26",
    "gn:asciiname":"Garoga",
    "gn:country_code":"ID",
    "gn:dem":867,
    "gn:feature_class":"P",
    "gn:feature_code":"PPL",
    "gn:name":"Garoga",
    "gn:population":0,
    "gn:timezone":"Asia/Jakarta",
    "iso:country":"ID",
    "name:ind_x_preferred":[
        "Garoga"
    ],
    "wof:name":"Garoga",
    "wof:placetype":"locality"
},
  "geometry": {"coordinates":[99.30800000000001,1.6048],"type":"Point"}
}