{
  "type": "Feature",
  "properties": {
    "gn:admin1_code":"30.0",
    "gn:asciiname":"Cisaung",
    "gn:country_code":"ID",
    "gn:dem":441,
    "gn:feature_class":"P",
    "gn:feature_code":"PPL",
    "gn:name":"Cisaung",
    "gn:population":0,
    "gn:timezone":"Asia/Jakarta",
    "iso:country":"ID",
    "name:ind_x_preferred":[
        "Cisaung"
    ],
    "name:und_x_variant":[
        "Tjisaung",
        "Cisaung",
        "Tjisaoeng"
    ],
    "wof:lang_x_official":[
        "ind"
    ],
    "wof:lang_x_spoken":[
        "ind",
        "eng"
    ],
    "wof:name":"Cisaung",
    "wof:placetype":"locality"
},
  "geometry": {"coordinates":[108.1061,-7.4476],"type":"Point"}
}