{
  "type": "Feature",
  "properties": {
    "gn:admin1_code":"8",
    "gn:asciiname":"Kerjen Satu",
    "gn:country_code":"ID",
    "gn:dem":119,
    "gn:feature_class":"P",
    "gn:feature_code":"PPL",
    "gn:name":"Kerjen Satu",
    "gn:population":0,
    "gn:timezone":"Asia/Jakarta",
    "iso:country":"ID",
    "name:ind_x_preferred":[
        "Kerjen Satu"
    ],
    "wof:name":"Kerjen Satu",
    "wof:placetype":"locality"
},
  "geometry": {"coordinates":[112.0531,-8.0784],"type":"Point"}
}