{
  "type": "Feature",
  "properties": {
    "gn:admin1_code":"17",
    "gn:asciiname":"Batunyeret",
    "gn:country_code":"ID",
    "gn:dem":342,
    "gn:feature_class":"P",
    "gn:feature_code":"PPL",
    "gn:name":"Batunyeret",
    "gn:population":0,
    "gn:timezone":"Asia/Makassar",
    "iso:country":"ID",
    "name:ind_x_preferred":[
        "Batunyeret"
    ],
    "wof:name":"Batunyeret",
    "wof:placetype":"locality"
},
  "geometry": {"coordinates":[116.4062,-8.6617],"type":"Point"}
}