{
  "type": "Feature",
  "properties": {
    "gn:admin1_code":"1",
    "gn:asciiname":"Alai",
    "gn:country_code":"ID",
    "gn:dem":17,
    "gn:feature_class":"P",
    "gn:feature_code":"PPL",
    "gn:name":"Alai",
    "gn:population":0,
    "gn:timezone":"Asia/Jakarta",
    "iso:country":"ID",
    "name:ceb_x_preferred":[
        "Alai"
    ],
    "name:deu_x_preferred":[
        "Alai"
    ],
    "name:ind_x_preferred":[
        "Alai"
    ],
    "name:nld_x_preferred":[
        "Alai"
    ],
    "name:rus_x_preferred":[
        "\u0410\u043b\u0430\u0439"
    ],
    "name:spa_x_preferred":[
        "Alai"
    ],
    "name:swe_x_preferred":[
        "Alai"
    ],
    "name:ukr_x_preferred":[
        "\u0410\u043b\u0430\u0439"
    ],
    "wof:lang_x_official":[
        "ind"
    ],
    "wof:lang_x_spoken":[
        "ind",
        "eng"
    ],
    "wof:name":"Alai",
    "wof:placetype":"locality"
},
  "geometry": {"coordinates":[97.38379999999999,3.0963],"type":"Point"}
}