{
  "type": "Feature",
  "properties": {
    "gn:admin1_code":"30",
    "gn:asciiname":"Mundu",
    "gn:country_code":"ID",
    "gn:dem":11,
    "gn:feature_class":"P",
    "gn:feature_code":"PPL",
    "gn:name":"Mundu",
    "gn:population":0,
    "gn:timezone":"Asia/Jakarta",
    "iso:country":"ID",
    "name:fra_x_preferred":[
        "Mundu"
    ],
    "name:ind_x_preferred":[
        "Mundu"
    ],
    "name:mal_x_preferred":[
        "\u0d2e\u0d41\u0d23\u0d4d\u0d1f\u0d4d"
    ],
    "name:pol_x_preferred":[
        "Mundu"
    ],
    "wof:lang_x_official":[
        "ind"
    ],
    "wof:lang_x_spoken":[
        "ind",
        "eng"
    ],
    "wof:name":"Mundu",
    "wof:placetype":"locality"
},
  "geometry": {"coordinates":[108.3925,-6.46361],"type":"Point"}
}