{
  "type": "Feature",
  "properties": {
    "gn:admin1_code":"28",
    "gn:admin2_code":"8108",
    "gn:asciiname":"Tiakur",
    "gn:country_code":"ID",
    "gn:dem":21,
    "gn:feature_class":"P",
    "gn:feature_code":"PPLA2",
    "gn:name":"Tiakur",
    "gn:population":0,
    "gn:timezone":"Asia/Jayapura",
    "iso:country":"ID",
    "name:eng_x_preferred":[
        "Tiakur"
    ],
    "name:ind_x_preferred":[
        "Tiakur"
    ],
    "wof:name":"Tiakur",
    "wof:placetype":"locality"
},
  "geometry": {"coordinates":[127.795,-8.15],"type":"Point"}
}