{
  "type": "Feature",
  "properties": {
    "gn:admin1_code":"08",
    "gn:asciiname":"Sanglabang",
    "gn:country_code":"ID",
    "gn:dem":75,
    "gn:feature_class":"P",
    "gn:feature_code":"PPL",
    "gn:name":"Sanglabang",
    "gn:population":0,
    "gn:timezone":"Asia/Jakarta",
    "iso:country":"ID",
    "name:ind_x_preferred":[
        "Sanglabang"
    ],
    "wof:name":"Sanglabang",
    "wof:placetype":"locality"
},
  "geometry": {"coordinates":[112.99209999999999,-7.1493],"type":"Point"}
}