{
  "type": "Feature",
  "properties": {
    "gn:admin1_code":"33.0",
    "gn:asciiname":"Limusgantung Timur",
    "gn:country_code":"ID",
    "gn:dem":125,
    "gn:feature_class":"P",
    "gn:feature_code":"PPL",
    "gn:name":"Limusgantung Timur",
    "gn:population":0,
    "gn:timezone":"Asia/Jakarta",
    "iso:country":"ID",
    "name:ind_x_preferred":[
        "Limusgantung Timur"
    ],
    "wof:lang_x_official":[
        "ind"
    ],
    "wof:lang_x_spoken":[
        "ind",
        "eng"
    ],
    "wof:name":"Limusgantung Timur",
    "wof:placetype":"locality"
},
  "geometry": {"coordinates":[106.06100000000001,-6.4082],"type":"Point"}
}