{
  "type": "Feature",
  "properties": {
    "gn:admin1_code":"15.0",
    "gn:asciiname":"Balisandhar Utara",
    "gn:country_code":"ID",
    "gn:dem":181,
    "gn:feature_class":"P",
    "gn:feature_code":"PPL",
    "gn:name":"Balisandhar Utara",
    "gn:population":0,
    "gn:timezone":"Asia/Jakarta",
    "iso:country":"ID",
    "name:ind_x_preferred":[
        "Balisandhar Utara"
    ],
    "wof:name":"Balisandhar Utara",
    "wof:placetype":"locality"
},
  "geometry": {"coordinates":[104.4957,-4.75373],"type":"Point"}
}