{
  "type": "Feature",
  "properties": {
    "gn:admin1_code":"36.0",
    "gn:asciiname":"Jatan-Dafera",
    "gn:country_code":"ID",
    "gn:dem":6,
    "gn:feature_class":"P",
    "gn:feature_code":"PPL",
    "gn:name":"Jatan-Dafera",
    "gn:population":0,
    "gn:timezone":"Asia/Jayapura",
    "iso:country":"ID",
    "name:ind_x_preferred":[
        "Jatan-Dafera"
    ],
    "wof:name":"Jatan-Dafera",
    "wof:placetype":"locality"
},
  "geometry": {"coordinates":[139.22068000000002,-6.76059],"type":"Point"}
}