{
  "type": "Feature",
  "properties": {
    "gn:admin1_code":"30.0",
    "gn:asciiname":"Pangrumasan",
    "gn:country_code":"ID",
    "gn:dem":454,
    "gn:feature_class":"P",
    "gn:feature_code":"PPLA4",
    "gn:name":"Pangrumasan",
    "gn:population":0,
    "gn:timezone":"Asia/Jakarta",
    "iso:country":"ID",
    "name:ind_x_preferred":[
        "Pangrumasan"
    ],
    "name:und_x_variant":[
        "Pangroemasan"
    ],
    "wof:lang_x_official":[
        "ind"
    ],
    "wof:lang_x_spoken":[
        "ind",
        "eng"
    ],
    "wof:name":"Pangrumasan",
    "wof:placetype":"locality"
},
  "geometry": {"coordinates":[107.8973,-7.5661],"type":"Point"}
}