{
  "type": "Feature",
  "properties": {
    "gn:admin1_code":"18.0",
    "gn:asciiname":"Bangarai",
    "gn:country_code":"ID",
    "gn:dem":89,
    "gn:feature_class":"P",
    "gn:feature_code":"PPL",
    "gn:name":"Bangarai",
    "gn:population":0,
    "gn:timezone":"Asia/Makassar",
    "iso:country":"ID",
    "name:ind_x_preferred":[
        "Bangarai"
    ],
    "wof:name":"Bangarai",
    "wof:placetype":"locality"
},
  "geometry": {"coordinates":[121.5663,-10.6026],"type":"Point"}
}