{
  "type": "Feature",
  "properties": {
    "gn:admin1_code":"33.0",
    "gn:asciiname":"Cicatang Satu",
    "gn:country_code":"ID",
    "gn:dem":74,
    "gn:feature_class":"P",
    "gn:feature_code":"PPLA4",
    "gn:name":"Cicatang Satu",
    "gn:population":0,
    "gn:timezone":"Asia/Jakarta",
    "iso:country":"ID",
    "name:ind_x_preferred":[
        "Cicatang Satu"
    ],
    "name:und_x_variant":[
        "Citjatung",
        "Tjitjatang",
        "Cicatang"
    ],
    "wof:lang_x_official":[
        "ind"
    ],
    "wof:lang_x_spoken":[
        "ind",
        "eng"
    ],
    "wof:name":"Cicatang Satu",
    "wof:placetype":"locality"
},
  "geometry": {"coordinates":[106.10691,-6.86433],"type":"Point"}
}