{
  "type": "Feature",
  "properties": {
    "gn:admin1_code":"8.0",
    "gn:asciiname":"Banjarsari Dua",
    "gn:country_code":"ID",
    "gn:dem":411,
    "gn:feature_class":"P",
    "gn:feature_code":"PPL",
    "gn:name":"Banjarsari Dua",
    "gn:population":0,
    "gn:timezone":"Asia/Jakarta",
    "iso:country":"ID",
    "name:ind_x_preferred":[
        "Banjarsari Dua"
    ],
    "wof:name":"Banjarsari Dua",
    "wof:placetype":"locality"
},
  "geometry": {"coordinates":[112.65767,-8.12842],"type":"Point"}
}