{
  "type": "Feature",
  "properties": {
    "gn:admin1_code":"0.0",
    "gn:asciiname":"Kamasan",
    "gn:country_code":"ID",
    "gn:dem":25,
    "gn:feature_class":"P",
    "gn:feature_code":"PPL",
    "gn:name":"Kamasan",
    "gn:population":0,
    "gn:timezone":"Asia/Jakarta",
    "iso:country":"ID",
    "name:ind_x_preferred":[
        "Kamasan"
    ],
    "name:jav_x_preferred":[
        "Kamasan"
    ],
    "name:msa_x_preferred":[
        "Kamasan"
    ],
    "name:nld_x_preferred":[
        "Kamasan"
    ],
    "wof:name":"Kamasan",
    "wof:placetype":"locality"
},
  "geometry": {"coordinates":[105.88333,-6.11667],"type":"Point"}
}