{
  "type": "Feature",
  "properties": {
    "gn:admin1_code":"30",
    "gn:asciiname":"Pangauban",
    "gn:cc2":"ID",
    "gn:country_code":"ID",
    "gn:dem":975,
    "gn:feature_class":"P",
    "gn:feature_code":"PPL",
    "gn:name":"Pangauban",
    "gn:population":0,
    "gn:timezone":"Asia/Jakarta",
    "iso:country":"ID",
    "name:und_x_variant":[
        "Bangauban",
        "Pangauban"
    ],
    "wof:name":"Pangauban",
    "wof:placetype":"locality"
},
  "geometry": {"coordinates":[107.69777999999999,-7.12306],"type":"Point"}
}