{
  "type": "Feature",
  "properties": {
    "gn:admin1_code":"8.0",
    "gn:asciiname":"Gato",
    "gn:country_code":"ID",
    "gn:dem":115,
    "gn:feature_class":"P",
    "gn:feature_code":"PPL",
    "gn:name":"Gato",
    "gn:population":0,
    "gn:timezone":"Asia/Jakarta",
    "iso:country":"ID",
    "name:arg_x_preferred":[
        "Gato"
    ],
    "name:ceb_x_preferred":[
        "Gato"
    ],
    "name:deu_x_preferred":[
        "Gato"
    ],
    "name:glg_x_preferred":[
        "Gato"
    ],
    "name:ind_x_preferred":[
        "Gato"
    ],
    "name:ita_x_preferred":[
        "Gato"
    ],
    "name:jpn_x_preferred":[
        "\u30ac\u30c8\u30fc"
    ],
    "name:por_x_preferred":[
        "Gato"
    ],
    "name:rus_x_preferred":[
        "\u0413\u0430\u0442\u043e"
    ],
    "name:spa_x_preferred":[
        "Gato"
    ],
    "name:swe_x_preferred":[
        "Gato"
    ],
    "wof:lang_x_official":[
        "ind"
    ],
    "wof:lang_x_spoken":[
        "ind",
        "eng"
    ],
    "wof:name":"Gato",
    "wof:placetype":"locality"
},
  "geometry": {"coordinates":[111.6092,-6.9204],"type":"Point"}
}