{
  "type": "Feature",
  "properties": {
    "gn:admin1_code":"38",
    "gn:asciiname":"Kirukiru",
    "gn:country_code":"ID",
    "gn:dem":13,
    "gn:feature_class":"P",
    "gn:feature_code":"PPL",
    "gn:name":"Kirukiru",
    "gn:population":0,
    "gn:timezone":"Asia/Makassar",
    "iso:country":"ID",
    "name:ind_x_preferred":[
        "Kirukiru"
    ],
    "wof:name":"Kirukiru",
    "wof:placetype":"locality"
},
  "geometry": {"coordinates":[119.6369,-4.2563],"type":"Point"}
}