{
  "type": "Feature",
  "properties": {
    "gn:admin1_code":"30.0",
    "gn:asciiname":"Sindanghayu",
    "gn:country_code":"ID",
    "gn:dem":23,
    "gn:feature_class":"P",
    "gn:feature_code":"PPLA4",
    "gn:name":"Sindanghayu",
    "gn:population":0,
    "gn:timezone":"Asia/Jakarta",
    "iso:country":"ID",
    "name:ind_x_preferred":[
        "Sindanghayu"
    ],
    "name:und_x_variant":[
        "Sindangaju",
        "Sindangayu",
        "Sindangajoe"
    ],
    "wof:lang_x_official":[
        "ind"
    ],
    "wof:lang_x_spoken":[
        "ind",
        "eng"
    ],
    "wof:name":"Sindanghayu",
    "wof:placetype":"locality"
},
  "geometry": {"coordinates":[108.6356,-7.4716],"type":"Point"}
}