{
  "type": "Feature",
  "properties": {
    "gn:admin1_code":"30.0",
    "gn:asciiname":"Bojongpetir",
    "gn:country_code":"ID",
    "gn:dem":521,
    "gn:feature_class":"P",
    "gn:feature_code":"PPL",
    "gn:name":"Bojongpetir",
    "gn:population":0,
    "gn:timezone":"Asia/Jakarta",
    "iso:country":"ID",
    "name:ind_x_preferred":[
        "Bojongpetir"
    ],
    "name:und_x_variant":[
        "Bodjongpetir"
    ],
    "wof:lang_x_official":[
        "ind"
    ],
    "wof:lang_x_spoken":[
        "ind",
        "eng"
    ],
    "wof:name":"Bojongpetir",
    "wof:placetype":"locality"
},
  "geometry": {"coordinates":[108.0745,-7.3249],"type":"Point"}
}