{
  "type": "Feature",
  "properties": {
    "gn:admin1_code":"7.0",
    "gn:asciiname":"Pluberan",
    "gn:country_code":"ID",
    "gn:dem":384,
    "gn:feature_class":"P",
    "gn:feature_code":"PPL",
    "gn:name":"Pluberan",
    "gn:population":0,
    "gn:timezone":"Asia/Jakarta",
    "iso:country":"ID",
    "wof:name":"Pluberan",
    "wof:placetype":"locality"
},
  "geometry": {"coordinates":[110.32805999999999,-7.63056],"type":"Point"}
}