{
  "type": "Feature",
  "properties": {
    "gn:admin1_code":"1",
    "gn:asciiname":"Jeumoheuk",
    "gn:country_code":"ID",
    "gn:dem":13,
    "gn:feature_class":"P",
    "gn:feature_code":"PPL",
    "gn:name":"Jeumoheuk",
    "gn:population":0,
    "gn:timezone":"Asia/Jakarta",
    "iso:country":"ID",
    "name:ind_x_preferred":[
        "Jeumoheuk"
    ],
    "wof:name":"Jeumoheuk",
    "wof:placetype":"locality"
},
  "geometry": {"coordinates":[95.4349,4.825],"type":"Point"}
}