{
  "type": "Feature",
  "properties": {
    "gn:admin1_code":"30.0",
    "gn:asciiname":"Bojongkondang",
    "gn:country_code":"ID",
    "gn:dem":566,
    "gn:feature_class":"P",
    "gn:feature_code":"PPL",
    "gn:name":"Bojongkondang",
    "gn:population":0,
    "gn:timezone":"Asia/Jakarta",
    "iso:country":"ID",
    "name:ind_x_preferred":[
        "Bojongkondang"
    ],
    "name:und_x_variant":[
        "Bodjongkondang",
        "Bojongkondang"
    ],
    "wof:name":"Bojongkondang",
    "wof:placetype":"locality"
},
  "geometry": {"coordinates":[108.38209999999999,-7.4994],"type":"Point"}
}