{
  "type": "Feature",
  "properties": {
    "gn:admin1_code":"29.0",
    "gn:asciiname":"Pohea",
    "gn:country_code":"ID",
    "gn:dem":12,
    "gn:elevation":"162.0",
    "gn:feature_class":"P",
    "gn:feature_code":"PPL",
    "gn:name":"Pohea",
    "gn:population":0,
    "gn:timezone":"Asia/Jayapura",
    "iso:country":"ID",
    "name:ind_x_preferred":[
        "Pohea"
    ],
    "name:und_x_variant":[
        "Pohieja",
        "Pohi-eja"
    ],
    "wof:lang_x_official":[
        "ind"
    ],
    "wof:lang_x_spoken":[
        "ind",
        "eng"
    ],
    "wof:name":"Pohea",
    "wof:placetype":"locality"
},
  "geometry": {"coordinates":[125.9687,-2.00614],"type":"Point"}
}