{
  "type": "Feature",
  "properties": {
    "gn:admin1_code":"18.0",
    "gn:asciiname":"Bengubelan Dua",
    "gn:country_code":"ID",
    "gn:dem":20,
    "gn:feature_class":"P",
    "gn:feature_code":"PPL",
    "gn:name":"Bengubelan Dua",
    "gn:population":0,
    "gn:timezone":"Asia/Makassar",
    "iso:country":"ID",
    "name:ind_x_preferred":[
        "Bengubelan Dua"
    ],
    "wof:name":"Bengubelan Dua",
    "wof:placetype":"locality"
},
  "geometry": {"coordinates":[123.2389,-10.7483],"type":"Point"}
}