{
  "type": "Feature",
  "properties": {
    "gn:admin1_code":"2",
    "gn:asciiname":"Banjar Lampu",
    "gn:country_code":"ID",
    "gn:dem":1257,
    "gn:feature_class":"P",
    "gn:feature_code":"PPL",
    "gn:name":"Banjar Lampu",
    "gn:population":0,
    "gn:timezone":"Asia/Makassar",
    "iso:country":"ID",
    "name:ind_x_preferred":[
        "Banjar Lampu"
    ],
    "wof:name":"Banjar Lampu",
    "wof:placetype":"locality"
},
  "geometry": {"coordinates":[115.24339999999999,-8.224],"type":"Point"}
}