{
  "type": "Feature",
  "properties": {
    "gn:admin1_code":"30.0",
    "gn:asciiname":"Sagara",
    "gn:country_code":"ID",
    "gn:dem":350,
    "gn:feature_class":"P",
    "gn:feature_code":"PPLA4",
    "gn:name":"Sagara",
    "gn:population":0,
    "gn:timezone":"Asia/Jakarta",
    "iso:country":"ID",
    "name:ceb_x_preferred":[
        "Sagara"
    ],
    "name:deu_x_preferred":[
        "Sagara"
    ],
    "name:ind_x_preferred":[
        "Sagara"
    ],
    "name:nld_x_preferred":[
        "Sagara"
    ],
    "name:por_x_preferred":[
        "Sagara"
    ],
    "name:rus_x_preferred":[
        "\u0421\u0430\u0433\u0430\u0440\u0430"
    ],
    "name:spa_x_preferred":[
        "Sagara"
    ],
    "name:swe_x_preferred":[
        "Sagara"
    ],
    "wof:lang_x_official":[
        "ind"
    ],
    "wof:lang_x_spoken":[
        "ind",
        "eng"
    ],
    "wof:name":"Sagara",
    "wof:placetype":"locality"
},
  "geometry": {"coordinates":[108.6399,-7.1115],"type":"Point"}
}