{
  "type": "Feature",
  "properties": {
    "gn:admin1_code":"30.0",
    "gn:asciiname":"Bunirasa",
    "gn:country_code":"ID",
    "gn:dem":252,
    "gn:feature_class":"P",
    "gn:feature_code":"PPLA4",
    "gn:name":"Bunirasa",
    "gn:population":0,
    "gn:timezone":"Asia/Jakarta",
    "iso:country":"ID",
    "name:ind_x_preferred":[
        "Bunirasa"
    ],
    "name:und_x_variant":[
        "Boenirasa Dua"
    ],
    "wof:name":"Bunirasa",
    "wof:placetype":"locality"
},
  "geometry": {"coordinates":[108.3279,-7.3343],"type":"Point"}
}