{
  "type": "Feature",
  "properties": {
    "gn:admin1_code":"38.0",
    "gn:asciiname":"Pasanglambe",
    "gn:country_code":"ID",
    "gn:dem":734,
    "gn:feature_class":"P",
    "gn:feature_code":"PPL",
    "gn:name":"Pasanglambe",
    "gn:population":0,
    "gn:timezone":"Asia/Makassar",
    "iso:country":"ID",
    "name:ind_x_preferred":[
        "Pasanglambe"
    ],
    "wof:name":"Pasanglambe",
    "wof:placetype":"locality"
},
  "geometry": {"coordinates":[119.5192,-3.3714],"type":"Point"}
}