{
  "type": "Feature",
  "properties": {
    "gn:admin1_code":"36",
    "gn:asciiname":"Soejam",
    "gn:country_code":"ID",
    "gn:dem":267,
    "gn:feature_class":"P",
    "gn:feature_code":"PPL",
    "gn:name":"Soejam",
    "gn:population":0,
    "gn:timezone":"Asia/Jayapura",
    "iso:country":"ID",
    "wof:name":"Soejam",
    "wof:placetype":"locality"
},
  "geometry": {"coordinates":[132.32981000000001,-1.27448],"type":"Point"}
}