{
  "type": "Feature",
  "properties": {
    "gn:admin1_code":"33",
    "gn:asciiname":"Saungilir",
    "gn:country_code":"ID",
    "gn:dem":103,
    "gn:feature_class":"P",
    "gn:feature_code":"PPL",
    "gn:name":"Saungilir",
    "gn:population":0,
    "gn:timezone":"Asia/Jakarta",
    "iso:country":"ID",
    "name:ind_x_preferred":[
        "Saungilir"
    ],
    "wof:name":"Saungilir",
    "wof:placetype":"locality"
},
  "geometry": {"coordinates":[106.0361,-6.0863],"type":"Point"}
}