{
  "type": "Feature",
  "properties": {
    "gn:admin1_code":"8",
    "gn:asciiname":"Kulonkali",
    "gn:country_code":"ID",
    "gn:dem":758,
    "gn:feature_class":"P",
    "gn:feature_code":"PPL",
    "gn:name":"Kulonkali",
    "gn:population":0,
    "gn:timezone":"Asia/Jakarta",
    "iso:country":"ID",
    "name:ind_x_preferred":[
        "Kulonkali"
    ],
    "wof:name":"Kulonkali",
    "wof:placetype":"locality"
},
  "geometry": {"coordinates":[112.8039,-7.8365],"type":"Point"}
}