{
  "type": "Feature",
  "properties": {
    "gn:admin1_code":"14",
    "gn:asciiname":"Komplek Tentara Nasional Indonesia-Angkatan Udara",
    "gn:country_code":"ID",
    "gn:dem":9,
    "gn:feature_class":"P",
    "gn:feature_code":"PPL",
    "gn:name":"Komplek Tentara Nasional Indonesia-Angkatan Udara",
    "gn:population":0,
    "gn:timezone":"Asia/Makassar",
    "iso:country":"ID",
    "name:ind_x_preferred":[
        "Komplek Tentara Nasional Indonesia-Angkatan Udara"
    ],
    "wof:name":"Komplek Tentara Nasional Indonesia-Angkatan Udara",
    "wof:placetype":"locality"
},
  "geometry": {"coordinates":[116.91630000000001,-1.2608],"type":"Point"}
}