{
  "type": "Feature",
  "properties": {
    "gn:admin1_code":"30",
    "gn:asciiname":"Lemahneundeut Satu",
    "gn:country_code":"ID",
    "gn:dem":521,
    "gn:feature_class":"P",
    "gn:feature_code":"PPL",
    "gn:name":"Lemahneundeut Satu",
    "gn:population":0,
    "gn:timezone":"Asia/Jakarta",
    "iso:country":"ID",
    "name:ind_x_preferred":[
        "Lemahneundeut Satu"
    ],
    "name:und_x_variant":[
        "Lemahneundeut 1"
    ],
    "wof:name":"Lemahneundeut Satu",
    "wof:placetype":"locality"
},
  "geometry": {"coordinates":[106.85389000000001,-6.70528],"type":"Point"}
}