{
  "type": "Feature",
  "properties": {
    "gn:admin1_code":"7.0",
    "gn:asciiname":"Margorejo",
    "gn:country_code":"ID",
    "gn:dem":298,
    "gn:feature_class":"P",
    "gn:feature_code":"PPL",
    "gn:name":"Margorejo",
    "gn:population":0,
    "gn:timezone":"Asia/Jakarta",
    "iso:country":"ID",
    "wof:name":"Margorejo",
    "wof:placetype":"locality"
},
  "geometry": {"coordinates":[110.61167,-7.61194],"type":"Point"}
}