{
  "type": "Feature",
  "properties": {
    "gn:admin1_code":"18",
    "gn:asciiname":"Wehae",
    "gn:country_code":"ID",
    "gn:dem":543,
    "gn:feature_class":"P",
    "gn:feature_code":"PPL",
    "gn:name":"Wehae",
    "gn:population":0,
    "gn:timezone":"Asia/Makassar",
    "iso:country":"ID",
    "wof:name":"Wehae",
    "wof:placetype":"locality"
},
  "geometry": {"coordinates":[124.82138999999999,-9.39861],"type":"Point"}
}