{
  "type": "Feature",
  "properties": {
    "gn:admin1_code":"24.0",
    "gn:asciiname":"Padangairdingin",
    "gn:country_code":"ID",
    "gn:dem":333,
    "gn:feature_class":"P",
    "gn:feature_code":"PPL",
    "gn:name":"Padangairdingin",
    "gn:population":0,
    "gn:timezone":"Asia/Jakarta",
    "iso:country":"ID",
    "name:ind_x_preferred":[
        "Padangairdingin"
    ],
    "wof:name":"Padangairdingin",
    "wof:placetype":"locality"
},
  "geometry": {"coordinates":[101.31516000000001,-1.4708],"type":"Point"}
}