{
  "type": "Feature",
  "properties": {
    "gn:admin1_code":"7",
    "gn:asciiname":"Genjikan",
    "gn:country_code":"ID",
    "gn:dem":153,
    "gn:feature_class":"P",
    "gn:feature_code":"PPL",
    "gn:name":"Genjikan",
    "gn:population":0,
    "gn:timezone":"Asia/Jakarta",
    "iso:country":"ID",
    "name:ind_x_preferred":[
        "Genjikan"
    ],
    "wof:name":"Genjikan",
    "wof:placetype":"locality"
},
  "geometry": {"coordinates":[110.8546,-6.7276],"type":"Point"}
}