{
  "type": "Feature",
  "properties": {
    "gn:admin1_code":"30",
    "gn:asciiname":"Bojongsari",
    "gn:country_code":"ID",
    "gn:dem":936,
    "gn:feature_class":"P",
    "gn:feature_code":"PPL",
    "gn:name":"Bojongsari",
    "gn:population":0,
    "gn:timezone":"Asia/Jakarta",
    "iso:country":"ID",
    "name:ind_x_preferred":[
        "Bojongsari"
    ],
    "wof:name":"Bojongsari",
    "wof:placetype":"locality"
},
  "geometry": {"coordinates":[107.83710000000001,-7.2176],"type":"Point"}
}