{
  "type": "Feature",
  "properties": {
    "gn:admin1_code":"38.0",
    "gn:asciiname":"Wakka",
    "gn:country_code":"ID",
    "gn:dem":7,
    "gn:feature_class":"P",
    "gn:feature_code":"PPL",
    "gn:name":"Wakka",
    "gn:population":0,
    "gn:timezone":"Asia/Makassar",
    "iso:country":"ID",
    "name:ind_x_preferred":[
        "Wakka"
    ],
    "name:tha_x_preferred":[
        "\u0e27\u0e31\u0e01\u0e01\u0e49\u0e32"
    ],
    "name:und_x_variant":[
        "Waka"
    ],
    "wof:lang_x_official":[
        "ind"
    ],
    "wof:lang_x_spoken":[
        "ind",
        "eng"
    ],
    "wof:name":"Wakka",
    "wof:placetype":"locality"
},
  "geometry": {"coordinates":[119.4859,-3.7493],"type":"Point"}
}