{
  "type": "Feature",
  "properties": {
    "gn:admin1_code":"7.0",
    "gn:asciiname":"Ngrandu",
    "gn:country_code":"ID",
    "gn:dem":203,
    "gn:feature_class":"P",
    "gn:feature_code":"PPL",
    "gn:name":"Ngrandu",
    "gn:population":0,
    "gn:timezone":"Asia/Jakarta",
    "iso:country":"ID",
    "name:ind_x_preferred":[
        "Ngrandu"
    ],
    "wof:name":"Ngrandu",
    "wof:placetype":"locality"
},
  "geometry": {"coordinates":[111.1519,-6.9738],"type":"Point"}
}