{
  "type": "Feature",
  "properties": {
    "gn:admin1_code":"11",
    "gn:asciiname":"Papan",
    "gn:country_code":"ID",
    "gn:dem":49,
    "gn:feature_class":"P",
    "gn:feature_code":"PPL",
    "gn:name":"Papan",
    "gn:population":0,
    "gn:timezone":"Asia/Pontianak",
    "iso:country":"ID",
    "name:ind_x_preferred":[
        "Papan"
    ],
    "name:kir_x_preferred":[
        "\u041f\u0430\u043f\u0430\u043d"
    ],
    "name:uzb_x_preferred":[
        "Papan"
    ],
    "wof:lang_x_official":[
        "ind"
    ],
    "wof:lang_x_spoken":[
        "ind",
        "eng"
    ],
    "wof:name":"Papan",
    "wof:placetype":"locality"
},
  "geometry": {"coordinates":[109.27506,0.89572],"type":"Point"}
}