{
  "type": "Feature",
  "properties": {
    "gn:admin1_code":"26.0",
    "gn:asciiname":"Nibungangus",
    "gn:country_code":"ID",
    "gn:dem":3,
    "gn:feature_class":"P",
    "gn:feature_code":"PPL",
    "gn:name":"Nibungangus",
    "gn:population":0,
    "gn:timezone":"Asia/Jakarta",
    "iso:country":"ID",
    "name:ind_x_preferred":[
        "Nibungangus"
    ],
    "wof:name":"Nibungangus",
    "wof:placetype":"locality"
},
  "geometry": {"coordinates":[99.62520000000001,3.19],"type":"Point"}
}