{
  "type": "Feature",
  "properties": {
    "gn:admin1_code":"30.0",
    "gn:asciiname":"Cibogo Wetan",
    "gn:country_code":"ID",
    "gn:dem":554,
    "gn:feature_class":"P",
    "gn:feature_code":"PPL",
    "gn:name":"Cibogo Wetan",
    "gn:population":0,
    "gn:timezone":"Asia/Jakarta",
    "iso:country":"ID",
    "name:ind_x_preferred":[
        "Cibogo Wetan"
    ],
    "wof:name":"Cibogo Wetan",
    "wof:placetype":"locality"
},
  "geometry": {"coordinates":[106.81740000000001,-7.0758],"type":"Point"}
}