{
  "type": "Feature",
  "properties": {
    "gn:admin1_code":"7",
    "gn:asciiname":"Pesantren Timur",
    "gn:country_code":"ID",
    "gn:dem":8,
    "gn:feature_class":"P",
    "gn:feature_code":"PPL",
    "gn:name":"Pesantren Timur",
    "gn:population":0,
    "gn:timezone":"Asia/Jakarta",
    "iso:country":"ID",
    "name:ind_x_preferred":[
        "Pesantren Timur"
    ],
    "wof:name":"Pesantren Timur",
    "wof:placetype":"locality"
},
  "geometry": {"coordinates":[109.5068,-6.8393],"type":"Point"}
}