{
  "type": "Feature",
  "properties": {
    "gn:admin1_code":"15.0",
    "gn:asciiname":"Dadurejo",
    "gn:country_code":"ID",
    "gn:dem":24,
    "gn:feature_class":"P",
    "gn:feature_code":"PPL",
    "gn:name":"Dadurejo",
    "gn:population":0,
    "gn:timezone":"Asia/Jakarta",
    "iso:country":"ID",
    "name:ind_x_preferred":[
        "Dadurejo"
    ],
    "wof:name":"Dadurejo",
    "wof:placetype":"locality"
},
  "geometry": {"coordinates":[105.46644999999999,-5.31844],"type":"Point"}
}