{
  "type": "Feature",
  "properties": {
    "gn:admin1_code":"30",
    "gn:asciiname":"Muara Tengah",
    "gn:country_code":"ID",
    "gn:dem":372,
    "gn:feature_class":"P",
    "gn:feature_code":"PPL",
    "gn:name":"Muara Tengah",
    "gn:population":0,
    "gn:timezone":"Asia/Jakarta",
    "iso:country":"ID",
    "name:ind_x_preferred":[
        "Muara Tengah"
    ],
    "wof:name":"Muara Tengah",
    "wof:placetype":"locality"
},
  "geometry": {"coordinates":[106.83389,-6.63639],"type":"Point"}
}