{
  "type": "Feature",
  "properties": {
    "gn:admin1_code":"30.0",
    "gn:asciiname":"Ciharus",
    "gn:country_code":"ID",
    "gn:dem":803,
    "gn:feature_class":"P",
    "gn:feature_code":"PPL",
    "gn:name":"Ciharus",
    "gn:population":0,
    "gn:timezone":"Asia/Jakarta",
    "iso:country":"ID",
    "name:ind_x_preferred":[
        "Ciharus"
    ],
    "name:und_x_variant":[
        "Tjiharoes"
    ],
    "wof:name":"Ciharus",
    "wof:placetype":"locality"
},
  "geometry": {"coordinates":[107.9616,-7.2121],"type":"Point"}
}