{
  "type": "Feature",
  "properties": {
    "gn:admin1_code":"38",
    "gn:asciiname":"Kariangoraja",
    "gn:country_code":"ID",
    "gn:dem":146,
    "gn:feature_class":"P",
    "gn:feature_code":"PPL",
    "gn:name":"Kariangoraja",
    "gn:population":0,
    "gn:timezone":"Asia/Makassar",
    "iso:country":"ID",
    "name:ind_x_preferred":[
        "Kariangoraja"
    ],
    "wof:name":"Kariangoraja",
    "wof:placetype":"locality"
},
  "geometry": {"coordinates":[120.529,-5.962],"type":"Point"}
}