{
  "type": "Feature",
  "properties": {
    "gn:admin1_code":"26",
    "gn:asciiname":"Kotabayu",
    "gn:country_code":"ID",
    "gn:dem":32,
    "gn:feature_class":"P",
    "gn:feature_code":"PPL",
    "gn:name":"Kotabayu",
    "gn:population":0,
    "gn:timezone":"Asia/Jakarta",
    "iso:country":"ID",
    "name:ind_x_preferred":[
        "Kotabayu"
    ],
    "name:und_x_variant":[
        "Kotabaju"
    ],
    "wof:name":"Kotabayu",
    "wof:placetype":"locality"
},
  "geometry": {"coordinates":[99.0895,3.3839],"type":"Point"}
}