{
  "type": "Feature",
  "properties": {
    "gn:admin1_code":"7",
    "gn:asciiname":"Kenep",
    "gn:country_code":"ID",
    "gn:dem":8,
    "gn:feature_class":"P",
    "gn:feature_code":"PPL",
    "gn:name":"Kenep",
    "gn:population":0,
    "gn:timezone":"Asia/Jakarta",
    "iso:country":"ID",
    "name:ind_x_preferred":[
        "Kenep"
    ],
    "wof:name":"Kenep",
    "wof:placetype":"locality"
},
  "geometry": {"coordinates":[110.63200000000001,-6.889],"type":"Point"}
}