{
  "type": "Feature",
  "properties": {
    "gn:admin1_code":"18.0",
    "gn:asciiname":"Daiwote",
    "gn:country_code":"ID",
    "gn:dem":15,
    "gn:feature_class":"P",
    "gn:feature_code":"PPL",
    "gn:name":"Daiwote",
    "gn:population":0,
    "gn:timezone":"Asia/Makassar",
    "iso:country":"ID",
    "name:ind_x_preferred":[
        "Daiwote"
    ],
    "wof:name":"Daiwote",
    "wof:placetype":"locality"
},
  "geometry": {"coordinates":[121.5873,-10.6331],"type":"Point"}
}