{
  "type": "Feature",
  "properties": {
    "gn:admin1_code":"24.0",
    "gn:asciiname":"Batukambing",
    "gn:country_code":"ID",
    "gn:dem":239,
    "gn:feature_class":"P",
    "gn:feature_code":"PPL",
    "gn:name":"Batukambing",
    "gn:population":0,
    "gn:timezone":"Asia/Jakarta",
    "iso:country":"ID",
    "name:ind_x_preferred":[
        "Batukambing"
    ],
    "wof:name":"Batukambing",
    "wof:placetype":"locality"
},
  "geometry": {"coordinates":[100.157,0.5152],"type":"Point"}
}