{
  "type": "Feature",
  "properties": {
    "gn:admin1_code":"1",
    "gn:asciiname":"Pucuk Alu",
    "gn:country_code":"ID",
    "gn:dem":17,
    "gn:feature_class":"P",
    "gn:feature_code":"PPL",
    "gn:name":"Pucuk Alu",
    "gn:population":0,
    "gn:timezone":"Asia/Jakarta",
    "iso:country":"ID",
    "name:ind_x_preferred":[
        "Pucuk Alu"
    ],
    "wof:name":"Pucuk Alu",
    "wof:placetype":"locality"
},
  "geometry": {"coordinates":[97.4755,5.0412],"type":"Point"}
}