{
  "type": "Feature",
  "properties": {
    "gn:admin1_code":"18.0",
    "gn:asciiname":"Lite",
    "gn:country_code":"ID",
    "gn:dem":430,
    "gn:feature_class":"P",
    "gn:feature_code":"PPL",
    "gn:name":"Lite",
    "gn:population":0,
    "gn:timezone":"Asia/Makassar",
    "iso:country":"ID",
    "name:ceb_x_preferred":[
        "Lite"
    ],
    "name:deu_x_preferred":[
        "Lite"
    ],
    "name:ind_x_preferred":[
        "Lite"
    ],
    "name:swe_x_preferred":[
        "Lite"
    ],
    "wof:name":"Lite",
    "wof:placetype":"locality"
},
  "geometry": {"coordinates":[123.4391,-8.4249],"type":"Point"}
}