{
  "type": "Feature",
  "properties": {
    "gn:admin1_code":"18.0",
    "gn:asciiname":"Aeloga",
    "gn:country_code":"ID",
    "gn:dem":25,
    "gn:feature_class":"P",
    "gn:feature_code":"PPL",
    "gn:name":"Aeloga",
    "gn:population":0,
    "gn:timezone":"Asia/Makassar",
    "iso:country":"ID",
    "name:ind_x_preferred":[
        "Aeloga"
    ],
    "wof:name":"Aeloga",
    "wof:placetype":"locality"
},
  "geometry": {"coordinates":[121.70386000000001,-8.57407],"type":"Point"}
}