{
  "type": "Feature",
  "properties": {
    "gn:admin1_code":"40",
    "gn:asciiname":"Sabang Mawang Barat",
    "gn:country_code":"ID",
    "gn:dem":4,
    "gn:feature_class":"P",
    "gn:feature_code":"PPLA3",
    "gn:name":"Sabang Mawang Barat",
    "gn:population":0,
    "gn:timezone":"Asia/Pontianak",
    "iso:country":"ID",
    "name:ind_x_preferred":[
        "Sabang Mawang Barat"
    ],
    "wof:name":"Sabang Mawang Barat",
    "wof:placetype":"locality"
},
  "geometry": {"coordinates":[108.11333,3.63306],"type":"Point"}
}