{
  "type": "Feature",
  "properties": {
    "gn:admin1_code":"7.0",
    "gn:asciiname":"Dringo Kidul",
    "gn:country_code":"ID",
    "gn:dem":6,
    "gn:feature_class":"P",
    "gn:feature_code":"PPL",
    "gn:name":"Dringo Kidul",
    "gn:population":0,
    "gn:timezone":"Asia/Jakarta",
    "iso:country":"ID",
    "name:ind_x_preferred":[
        "Dringo Kidul"
    ],
    "wof:name":"Dringo Kidul",
    "wof:placetype":"locality"
},
  "geometry": {"coordinates":[111.09869999999999,-6.7567],"type":"Point"}
}