{
  "type": "Feature",
  "properties": {
    "gn:admin1_code":"15.0",
    "gn:asciiname":"Perpas",
    "gn:country_code":"ID",
    "gn:dem":6,
    "gn:feature_class":"P",
    "gn:feature_code":"PPL",
    "gn:name":"Perpas",
    "gn:population":0,
    "gn:timezone":"Asia/Jakarta",
    "iso:country":"ID",
    "name:ind_x_preferred":[
        "Perpas"
    ],
    "name:und_x_variant":[
        "Soekarame"
    ],
    "wof:name":"Perpas",
    "wof:placetype":"locality"
},
  "geometry": {"coordinates":[103.91959,-5.13497],"type":"Point"}
}