{
  "type": "Feature",
  "properties": {
    "gn:admin1_code":"1",
    "gn:asciiname":"Alur Buluh",
    "gn:country_code":"ID",
    "gn:dem":136,
    "gn:feature_class":"P",
    "gn:feature_code":"PPL",
    "gn:name":"Alur Buluh",
    "gn:population":0,
    "gn:timezone":"Asia/Jakarta",
    "iso:country":"ID",
    "name:ind_x_preferred":[
        "Alur Buluh"
    ],
    "wof:name":"Alur Buluh",
    "wof:placetype":"locality"
},
  "geometry": {"coordinates":[97.8519,3.4088],"type":"Point"}
}