{
  "type": "Feature",
  "properties": {
    "gn:admin1_code":"7",
    "gn:asciiname":"Segunting",
    "gn:country_code":"ID",
    "gn:dem":75,
    "gn:feature_class":"P",
    "gn:feature_code":"PPL",
    "gn:name":"Segunting",
    "gn:population":0,
    "gn:timezone":"Asia/Jakarta",
    "iso:country":"ID",
    "name:ind_x_preferred":[
        "Segunting"
    ],
    "wof:name":"Segunting",
    "wof:placetype":"locality"
},
  "geometry": {"coordinates":[109.7598,-6.9423],"type":"Point"}
}