{
  "type": "Feature",
  "properties": {
    "gn:admin1_code":"7",
    "gn:asciiname":"Potro",
    "gn:country_code":"ID",
    "gn:dem":19,
    "gn:feature_class":"P",
    "gn:feature_code":"PPL",
    "gn:name":"Potro",
    "gn:population":0,
    "gn:timezone":"Asia/Jakarta",
    "iso:country":"ID",
    "name:ind_x_preferred":[
        "Potro"
    ],
    "wof:name":"Potro",
    "wof:placetype":"locality"
},
  "geometry": {"coordinates":[109.68810999999999,-6.94104],"type":"Point"}
}