{
  "type": "Feature",
  "properties": {
    "gn:admin1_code":"0.0",
    "gn:asciiname":"Batanguru",
    "gn:cc2":"ID",
    "gn:country_code":"ID",
    "gn:dem":1168,
    "gn:feature_class":"P",
    "gn:feature_code":"PPL",
    "gn:name":"Batanguru",
    "gn:population":0,
    "gn:timezone":"Asia/Makassar",
    "iso:country":"ID",
    "name:und_x_variant":[
        "Batangoeroe",
        "Batanguru"
    ],
    "wof:lang_x_official":[
        "ind"
    ],
    "wof:lang_x_spoken":[
        "ind",
        "eng"
    ],
    "wof:name":"Batanguru",
    "wof:placetype":"locality"
},
  "geometry": {"coordinates":[119.36667,-3.15],"type":"Point"}
}