{
  "type": "Feature",
  "properties": {
    "gn:admin1_code":"8.0",
    "gn:asciiname":"Kenongo",
    "gn:country_code":"ID",
    "gn:dem":740,
    "gn:feature_class":"P",
    "gn:feature_code":"PPLA4",
    "gn:name":"Kenongo",
    "gn:population":0,
    "gn:timezone":"Asia/Jakarta",
    "iso:country":"ID",
    "name:ind_x_preferred":[
        "Kenongo"
    ],
    "wof:name":"Kenongo",
    "wof:placetype":"locality"
},
  "geometry": {"coordinates":[112.5393,-8.0089],"type":"Point"}
}