{
  "type": "Feature",
  "properties": {
    "gn:admin1_code":"8.0",
    "gn:asciiname":"Bedi",
    "gn:country_code":"ID",
    "gn:dem":127,
    "gn:feature_class":"P",
    "gn:feature_code":"PPL",
    "gn:name":"Bedi",
    "gn:population":0,
    "gn:timezone":"Asia/Jakarta",
    "iso:country":"ID",
    "name:ind_x_preferred":[
        "Bedi"
    ],
    "wof:name":"Bedi",
    "wof:placetype":"locality"
},
  "geometry": {"coordinates":[111.58710000000001,-8.2676],"type":"Point"}
}