{
  "type": "Feature",
  "properties": {
    "gn:admin1_code":"8.0",
    "gn:asciiname":"Bedi",
    "gn:country_code":"ID",
    "gn:dem":127,
    "gn:feature_class":"P",
    "gn:feature_code":"PPL",
    "gn:name":"Bedi",
    "gn:population":0,
    "gn:timezone":"Asia/Jakarta",
    "iso:country":"ID",
    "name:bpy_x_preferred":[
        "\u09ac\u09c7\u09a6\u09c0"
    ],
    "name:ceb_x_preferred":[
        "Bedi"
    ],
    "name:deu_x_preferred":[
        "Bedi"
    ],
    "name:hin_x_preferred":[
        "\u092c\u0947\u0926\u0940"
    ],
    "name:ind_x_preferred":[
        "Bedi"
    ],
    "name:ita_x_preferred":[
        "Bedi"
    ],
    "name:new_x_preferred":[
        "\u092c\u0947\u0926\u0940"
    ],
    "name:swe_x_preferred":[
        "Bedi"
    ],
    "name:tur_x_preferred":[
        "Bedi"
    ],
    "wof:lang_x_official":[
        "ind"
    ],
    "wof:lang_x_spoken":[
        "ind",
        "eng"
    ],
    "wof:name":"Bedi",
    "wof:placetype":"locality"
},
  "geometry": {"coordinates":[111.58710000000001,-8.2676],"type":"Point"}
}