{
  "type": "Feature",
  "properties": {
    "gn:admin1_code":"17",
    "gn:asciiname":"Tenandon",
    "gn:country_code":"ID",
    "gn:dem":88,
    "gn:feature_class":"P",
    "gn:feature_code":"PPL",
    "gn:name":"Tenandon",
    "gn:population":0,
    "gn:timezone":"Asia/Makassar",
    "iso:country":"ID",
    "name:ind_x_preferred":[
        "Tenandon"
    ],
    "wof:name":"Tenandon",
    "wof:placetype":"locality"
},
  "geometry": {"coordinates":[116.2388,-8.7565],"type":"Point"}
}