{
  "type": "Feature",
  "properties": {
    "gn:admin1_code":"33",
    "gn:asciiname":"Kubangkepuh",
    "gn:country_code":"ID",
    "gn:dem":157,
    "gn:feature_class":"P",
    "gn:feature_code":"PPL",
    "gn:name":"Kubangkepuh",
    "gn:population":0,
    "gn:timezone":"Asia/Jakarta",
    "iso:country":"ID",
    "name:ind_x_preferred":[
        "Kubangkepuh"
    ],
    "wof:name":"Kubangkepuh",
    "wof:placetype":"locality"
},
  "geometry": {"coordinates":[106.01090000000001,-6.0954],"type":"Point"}
}