{
  "type": "Feature",
  "properties": {
    "gn:admin1_code":"7.0",
    "gn:asciiname":"Margosari",
    "gn:country_code":"ID",
    "gn:dem":834,
    "gn:feature_class":"P",
    "gn:feature_code":"PPL",
    "gn:name":"Margosari",
    "gn:population":0,
    "gn:timezone":"Asia/Jakarta",
    "iso:country":"ID",
    "wof:name":"Margosari",
    "wof:placetype":"locality"
},
  "geometry": {"coordinates":[110.49861,-7.41806],"type":"Point"}
}