{
  "type": "Feature",
  "properties": {
    "gn:admin1_code":"8.0",
    "gn:asciiname":"Luwok Lor",
    "gn:country_code":"ID",
    "gn:dem":5,
    "gn:feature_class":"P",
    "gn:feature_code":"PPL",
    "gn:name":"Luwok Lor",
    "gn:population":0,
    "gn:timezone":"Asia/Jakarta",
    "iso:country":"ID",
    "name:ind_x_preferred":[
        "Luwok Lor"
    ],
    "wof:name":"Luwok Lor",
    "wof:placetype":"locality"
},
  "geometry": {"coordinates":[112.4695,-7.0501],"type":"Point"}
}