{
  "type": "Feature",
  "properties": {
    "gn:admin1_code":"10.0",
    "gn:asciiname":"Tosari",
    "gn:country_code":"ID",
    "gn:dem":177,
    "gn:feature_class":"P",
    "gn:feature_code":"PPL",
    "gn:name":"Tosari",
    "gn:population":0,
    "gn:timezone":"Asia/Jakarta",
    "iso:country":"ID",
    "wof:name":"Tosari",
    "wof:placetype":"locality"
},
  "geometry": {"coordinates":[110.23166999999999,-7.69361],"type":"Point"}
}