{
  "type": "Feature",
  "properties": {
    "gn:admin1_code":"2.0",
    "gn:asciiname":"Tauman",
    "gn:country_code":"ID",
    "gn:dem":272,
    "gn:feature_class":"P",
    "gn:feature_code":"PPL",
    "gn:name":"Tauman",
    "gn:population":0,
    "gn:timezone":"Asia/Makassar",
    "iso:country":"ID",
    "name:ind_x_preferred":[
        "Tauman"
    ],
    "wof:name":"Tauman",
    "wof:placetype":"locality"
},
  "geometry": {"coordinates":[115.1823,-8.4755],"type":"Point"}
}