{
  "type": "Feature",
  "properties": {
    "gn:admin1_code":"18",
    "gn:asciiname":"Timung",
    "gn:country_code":"ID",
    "gn:dem":838,
    "gn:feature_class":"P",
    "gn:feature_code":"PPL",
    "gn:name":"Timung",
    "gn:population":0,
    "gn:timezone":"Asia/Makassar",
    "iso:country":"ID",
    "name:ind_x_preferred":[
        "Timung"
    ],
    "wof:name":"Timung",
    "wof:placetype":"locality"
},
  "geometry": {"coordinates":[120.5029,-8.5796],"type":"Point"}
}