{
  "type": "Feature",
  "properties": {
    "gn:admin1_code":"38.0",
    "gn:asciiname":"Pebu",
    "gn:country_code":"ID",
    "gn:dem":862,
    "gn:feature_class":"P",
    "gn:feature_code":"PPL",
    "gn:name":"Pebu",
    "gn:population":0,
    "gn:timezone":"Asia/Makassar",
    "iso:country":"ID",
    "name:ind_x_preferred":[
        "Pebu"
    ],
    "wof:name":"Pebu",
    "wof:placetype":"locality"
},
  "geometry": {"coordinates":[119.8124,-3.3205],"type":"Point"}
}