{
  "type": "Feature",
  "properties": {
    "gn:admin1_code":"07",
    "gn:asciiname":"Kebonkliwon",
    "gn:country_code":"ID",
    "gn:dem":527,
    "gn:feature_class":"P",
    "gn:feature_code":"PPL",
    "gn:name":"Kebonkliwon",
    "gn:population":0,
    "gn:timezone":"Asia/Jakarta",
    "iso:country":"ID",
    "name:ind_x_preferred":[
        "Kebonkliwon"
    ],
    "name:und_x_variant":[
        "Kebonkliwan"
    ],
    "wof:name":"Kebonkliwon",
    "wof:placetype":"locality"
},
  "geometry": {"coordinates":[110.41249999999999,-7.1925],"type":"Point"}
}