{
  "type": "Feature",
  "properties": {
    "gn:admin1_code":"30",
    "gn:asciiname":"Cikoneng Satu",
    "gn:country_code":"ID",
    "gn:dem":1062,
    "gn:feature_class":"P",
    "gn:feature_code":"PPL",
    "gn:name":"Cikoneng Satu",
    "gn:population":0,
    "gn:timezone":"Asia/Jakarta",
    "iso:country":"ID",
    "name:ind_x_preferred":[
        "Cikoneng Satu"
    ],
    "name:und_x_variant":[
        "Tjikoneng 1"
    ],
    "wof:name":"Cikoneng Satu",
    "wof:placetype":"locality"
},
  "geometry": {"coordinates":[107.74361,-6.89722],"type":"Point"}
}