{
  "type": "Feature",
  "properties": {
    "gn:admin1_code":"28.0",
    "gn:asciiname":"Bukrane",
    "gn:country_code":"ID",
    "gn:dem":26,
    "gn:feature_class":"P",
    "gn:feature_code":"PPL",
    "gn:name":"Bukrane",
    "gn:population":0,
    "gn:timezone":"Asia/Jayapura",
    "iso:country":"ID",
    "name:und_x_variant":[
        "Boekrane",
        "Bukrane"
    ],
    "wof:name":"Bukrane",
    "wof:placetype":"locality"
},
  "geometry": {"coordinates":[131.16542999999999,-7.71643],"type":"Point"}
}