{
  "type": "Feature",
  "properties": {
    "gn:admin1_code":"1",
    "gn:asciiname":"Panton Rayeuk Satu",
    "gn:country_code":"ID",
    "gn:dem":89,
    "gn:feature_class":"P",
    "gn:feature_code":"PPL",
    "gn:name":"Panton Rayeuk Satu",
    "gn:population":0,
    "gn:timezone":"Asia/Jakarta",
    "iso:country":"ID",
    "name:ind_x_preferred":[
        "Panton Rayeuk Satu"
    ],
    "name:und_x_variant":[
        "Panton Rayeuk 1"
    ],
    "wof:name":"Panton Rayeuk Satu",
    "wof:placetype":"locality"
},
  "geometry": {"coordinates":[97.03919999999999,5.1187],"type":"Point"}
}