{
  "type": "Feature",
  "properties": {
    "gn:admin1_code":"0.0",
    "gn:asciiname":"Bufareh",
    "gn:cc2":"ID",
    "gn:country_code":"ID",
    "gn:dem":68,
    "gn:feature_class":"P",
    "gn:feature_code":"PPL",
    "gn:name":"Bufareh",
    "gn:population":0,
    "gn:timezone":"Asia/Jayapura",
    "iso:country":"ID",
    "name:und_x_variant":[
        "Boefareh",
        "Bufareh"
    ],
    "wof:lang_x_official":[
        "ind"
    ],
    "wof:lang_x_spoken":[
        "ind",
        "eng"
    ],
    "wof:name":"Bufareh",
    "wof:placetype":"locality"
},
  "geometry": {"coordinates":[138.86066,-2.26534],"type":"Point"}
}