{
  "type": "Feature",
  "properties": {
    "gn:admin1_code":"0.0",
    "gn:asciiname":"Tanahtumbuh",
    "gn:cc2":"ID",
    "gn:country_code":"ID",
    "gn:dem":76,
    "gn:feature_class":"P",
    "gn:feature_code":"PPL",
    "gn:name":"Tanahtumbuh",
    "gn:population":0,
    "gn:timezone":"Asia/Jakarta",
    "iso:country":"ID",
    "name:und_x_variant":[
        "Tanahtoemboeh",
        "Tenahtoemboeh",
        "Tanahtumbuh"
    ],
    "wof:name":"Tanahtumbuh",
    "wof:placetype":"locality"
},
  "geometry": {"coordinates":[101.87897,-1.46583],"type":"Point"}
}