{
  "type": "Feature",
  "properties": {
    "gn:admin1_code":"38",
    "gn:asciiname":"Panaikang",
    "gn:country_code":"ID",
    "gn:dem":22,
    "gn:feature_class":"P",
    "gn:feature_code":"PPL",
    "gn:name":"Panaikang",
    "gn:population":0,
    "gn:timezone":"Asia/Makassar",
    "iso:country":"ID",
    "name:ind_x_preferred":[
        "Panaikang"
    ],
    "wof:name":"Panaikang",
    "wof:placetype":"locality"
},
  "geometry": {"coordinates":[119.492,-5.378],"type":"Point"}
}