{
  "type": "Feature",
  "properties": {
    "gn:admin1_code":"18.0",
    "gn:asciiname":"Suman",
    "gn:country_code":"ID",
    "gn:dem":85,
    "gn:feature_class":"P",
    "gn:feature_code":"PPLA4",
    "gn:name":"Suman",
    "gn:population":0,
    "gn:timezone":"Asia/Makassar",
    "iso:country":"ID",
    "name:deu_x_preferred":[
        "Suman"
    ],
    "name:ind_x_preferred":[
        "Suman"
    ],
    "name:ukr_x_preferred":[
        "\u0421\u0443\u043c\u0430\u043d"
    ],
    "wof:lang_x_official":[
        "ind"
    ],
    "wof:lang_x_spoken":[
        "ind",
        "eng"
    ],
    "wof:name":"Suman",
    "wof:placetype":"locality"
},
  "geometry": {"coordinates":[124.3449,-10.0662],"type":"Point"}
}