{
  "type": "Feature",
  "properties": {
    "gn:admin1_code":"18.0",
    "gn:asciiname":"Natarmage",
    "gn:country_code":"ID",
    "gn:dem":320,
    "gn:feature_class":"P",
    "gn:feature_code":"PPLA4",
    "gn:name":"Natarmage",
    "gn:population":0,
    "gn:timezone":"Asia/Makassar",
    "iso:country":"ID",
    "name:ind_x_preferred":[
        "Natarmage"
    ],
    "wof:lang_x_official":[
        "ind"
    ],
    "wof:lang_x_spoken":[
        "ind",
        "eng"
    ],
    "wof:name":"Natarmage",
    "wof:placetype":"locality"
},
  "geometry": {"coordinates":[122.5667,-8.6031],"type":"Point"}
}