{
  "type": "Feature",
  "properties": {
    "gn:admin1_code":"7.0",
    "gn:asciiname":"Keseran Dua",
    "gn:country_code":"ID",
    "gn:dem":905,
    "gn:feature_class":"P",
    "gn:feature_code":"PPL",
    "gn:name":"Keseran Dua",
    "gn:population":0,
    "gn:timezone":"Asia/Jakarta",
    "iso:country":"ID",
    "name:ind_x_preferred":[
        "Keseran Dua"
    ],
    "name:und_x_variant":[
        "Kesaren Dua"
    ],
    "wof:lang_x_official":[
        "ind"
    ],
    "wof:lang_x_spoken":[
        "ind",
        "eng"
    ],
    "wof:name":"Keseran Dua",
    "wof:placetype":"locality"
},
  "geometry": {"coordinates":[109.11888999999999,-7.16389],"type":"Point"}
}