{
  "type": "Feature",
  "properties": {
    "gn:admin1_code":"30",
    "gn:asciiname":"Pangkalan Kulon",
    "gn:country_code":"ID",
    "gn:dem":5,
    "gn:feature_class":"P",
    "gn:feature_code":"PPL",
    "gn:name":"Pangkalan Kulon",
    "gn:population":0,
    "gn:timezone":"Asia/Jakarta",
    "iso:country":"ID",
    "name:ind_x_preferred":[
        "Pangkalan Kulon"
    ],
    "wof:name":"Pangkalan Kulon",
    "wof:placetype":"locality"
},
  "geometry": {"coordinates":[108.20111,-6.39639],"type":"Point"}
}