{
  "type": "Feature",
  "properties": {
    "gn:admin1_code":"7",
    "gn:asciiname":"Tapak Timur",
    "gn:country_code":"ID",
    "gn:dem":28,
    "gn:feature_class":"P",
    "gn:feature_code":"PPL",
    "gn:name":"Tapak Timur",
    "gn:population":0,
    "gn:timezone":"Asia/Jakarta",
    "iso:country":"ID",
    "name:ind_x_preferred":[
        "Tapak Timur"
    ],
    "wof:name":"Tapak Timur",
    "wof:placetype":"locality"
},
  "geometry": {"coordinates":[110.1176,-7.0088],"type":"Point"}
}