{
  "type": "Feature",
  "properties": {
    "gn:admin1_code":"1",
    "gn:asciiname":"Asan Krueng Kreh",
    "gn:country_code":"ID",
    "gn:dem":13,
    "gn:feature_class":"P",
    "gn:feature_code":"PPL",
    "gn:name":"Asan Krueng Kreh",
    "gn:population":0,
    "gn:timezone":"Asia/Jakarta",
    "iso:country":"ID",
    "name:ind_x_preferred":[
        "Asan Krueng Kreh"
    ],
    "wof:name":"Asan Krueng Kreh",
    "wof:placetype":"locality"
},
  "geometry": {"coordinates":[97.3099,5.0223],"type":"Point"}
}