{
  "type": "Feature",
  "properties": {
    "gn:admin1_code":"33",
    "gn:asciiname":"Sorokbuah",
    "gn:country_code":"ID",
    "gn:dem":77,
    "gn:feature_class":"P",
    "gn:feature_code":"PPL",
    "gn:name":"Sorokbuah",
    "gn:population":0,
    "gn:timezone":"Asia/Jakarta",
    "iso:country":"ID",
    "name:ind_x_preferred":[
        "Sorokbuah"
    ],
    "wof:name":"Sorokbuah",
    "wof:placetype":"locality"
},
  "geometry": {"coordinates":[106.2115,-6.2947],"type":"Point"}
}