{
  "type": "Feature",
  "properties": {
    "gn:admin1_code":"1.0",
    "gn:asciiname":"Sungairaya",
    "gn:country_code":"ID",
    "gn:dem":4,
    "gn:feature_class":"P",
    "gn:feature_code":"PPL",
    "gn:name":"Sungairaya",
    "gn:population":0,
    "gn:timezone":"Asia/Jakarta",
    "iso:country":"ID",
    "name:ind_x_preferred":[
        "Sungairaya"
    ],
    "name:und_x_variant":[
        "Keude Soeng\u00f2\u00eb Raja",
        "Sungairaja",
        "Soengoe Raja",
        "Soenga\u00efraja",
        "Raya"
    ],
    "wof:lang_x_official":[
        "ind"
    ],
    "wof:lang_x_spoken":[
        "ind",
        "eng"
    ],
    "wof:name":"Sungairaya",
    "wof:placetype":"locality"
},
  "geometry": {"coordinates":[97.91800000000001,4.6744],"type":"Point"}
}