{
  "type": "Feature",
  "properties": {
    "gn:admin1_code":"17",
    "gn:asciiname":"Sukadana",
    "gn:country_code":"ID",
    "gn:dem":138,
    "gn:feature_class":"P",
    "gn:feature_code":"PPL",
    "gn:name":"Sukadana",
    "gn:population":0,
    "gn:timezone":"Asia/Makassar",
    "iso:country":"ID",
    "name:ind_x_preferred":[
        "Sukadana"
    ],
    "wof:name":"Sukadana",
    "wof:placetype":"locality"
},
  "geometry": {"coordinates":[116.2089,-8.8448],"type":"Point"}
}