{
  "type": "Feature",
  "properties": {
    "gn:admin1_code":"0.0",
    "gn:asciiname":"Cinyiruan-hilir",
    "gn:cc2":"ID",
    "gn:country_code":"ID",
    "gn:dem":1263,
    "gn:feature_class":"P",
    "gn:feature_code":"PPL",
    "gn:name":"Cinyiruan-hilir",
    "gn:population":0,
    "gn:timezone":"Asia/Jakarta",
    "iso:country":"ID",
    "name:und_x_variant":[
        "Tjinjiruan-hilir",
        "Cinyiruan-hilir"
    ],
    "wof:name":"Cinyiruan-hilir",
    "wof:placetype":"locality"
},
  "geometry": {"coordinates":[107.55,-7.15],"type":"Point"}
}