{
  "type": "Feature",
  "properties": {
    "gn:admin1_code":"36.0",
    "gn:asciiname":"Jurmandi",
    "gn:country_code":"ID",
    "gn:dem":476,
    "gn:feature_class":"P",
    "gn:feature_code":"PPL",
    "gn:name":"Jurmandi",
    "gn:population":0,
    "gn:timezone":"Asia/Jayapura",
    "iso:country":"ID",
    "name:ind_x_preferred":[
        "Jurmandi"
    ],
    "name:und_x_variant":[
        "Jukmandi"
    ],
    "wof:name":"Jurmandi",
    "wof:placetype":"locality"
},
  "geometry": {"coordinates":[140.72769,-5.05817],"type":"Point"}
}