{
  "type": "Feature",
  "properties": {
    "gn:admin1_code":"18.0",
    "gn:asciiname":"Tama",
    "gn:country_code":"ID",
    "gn:dem":15,
    "gn:feature_class":"P",
    "gn:feature_code":"PPL",
    "gn:name":"Tama",
    "gn:population":0,
    "gn:timezone":"Asia/Makassar",
    "iso:country":"ID",
    "name:ara_x_preferred":[
        "\u062a\u0627\u0645\u0627"
    ],
    "name:bel_x_preferred":[
        "\u0422\u0430\u043c\u0430"
    ],
    "name:ceb_x_preferred":[
        "Tama"
    ],
    "name:ces_x_preferred":[
        "Tama"
    ],
    "name:deu_x_preferred":[
        "Tama"
    ],
    "name:fin_x_preferred":[
        "Tama"
    ],
    "name:fra_x_preferred":[
        "Tama"
    ],
    "name:hrv_x_preferred":[
        "Tama"
    ],
    "name:hye_x_preferred":[
        "\u054f\u0561\u0574\u0561"
    ],
    "name:ind_x_preferred":[
        "Tama"
    ],
    "name:ita_x_preferred":[
        "Tama"
    ],
    "name:lit_x_preferred":[
        "Tama"
    ],
    "name:nld_x_preferred":[
        "Tama"
    ],
    "name:pol_x_preferred":[
        "Tama"
    ],
    "name:por_x_preferred":[
        "Tama"
    ],
    "name:ron_x_preferred":[
        "Tama"
    ],
    "name:rus_x_preferred":[
        "\u0422\u0430\u043c\u0430"
    ],
    "name:spa_x_preferred":[
        "Tama"
    ],
    "name:srp_x_preferred":[
        "\u0422\u0435\u0458\u043c\u0430"
    ],
    "name:swe_x_preferred":[
        "Tama"
    ],
    "name:tgl_x_preferred":[
        "Tama"
    ],
    "name:tha_x_preferred":[
        "\u0e17\u0e32\u0e21\u0e30"
    ],
    "name:ukr_x_preferred":[
        "\u0422\u0430\u043c\u0430"
    ],
    "name:vie_x_preferred":[
        "Tama"
    ],
    "wof:lang_x_official":[
        "ind"
    ],
    "wof:lang_x_spoken":[
        "ind",
        "eng"
    ],
    "wof:name":"Tama",
    "wof:placetype":"locality"
},
  "geometry": {"coordinates":[119.6724,-9.3858],"type":"Point"}
}