{
  "type": "Feature",
  "properties": {
    "gn:admin1_code":"39",
    "gn:asciiname":"Fenfamin",
    "gn:country_code":"ID",
    "gn:dem":92,
    "gn:feature_class":"P",
    "gn:feature_code":"PPL",
    "gn:name":"Fenfamin",
    "gn:population":0,
    "gn:timezone":"Asia/Jayapura",
    "iso:country":"ID",
    "name:ind_x_preferred":[
        "Fenfamin"
    ],
    "wof:name":"Fenfamin",
    "wof:placetype":"locality"
},
  "geometry": {"coordinates":[131.5394,-0.8822],"type":"Point"}
}