{
  "type": "Feature",
  "properties": {
    "gn:admin1_code":"24",
    "gn:asciiname":"Laing",
    "gn:country_code":"ID",
    "gn:dem":430,
    "gn:feature_class":"P",
    "gn:feature_code":"PPL",
    "gn:name":"Laing",
    "gn:population":0,
    "gn:timezone":"Asia/Jakarta",
    "iso:country":"ID",
    "name:deu_x_preferred":[
        "Laing"
    ],
    "name:fin_x_preferred":[
        "Laing"
    ],
    "name:fra_x_preferred":[
        "Laing"
    ],
    "name:ind_x_preferred":[
        "Laing"
    ],
    "name:nds_x_preferred":[
        "Laing"
    ],
    "name:pol_x_preferred":[
        "Laing"
    ],
    "name:tgl_x_preferred":[
        "Laing"
    ],
    "wof:name":"Laing",
    "wof:placetype":"locality"
},
  "geometry": {"coordinates":[100.69387,-0.76096],"type":"Point"}
}