{
  "type": "Feature",
  "properties": {
    "gn:admin1_code":"7.0",
    "gn:asciiname":"Kubangkangkung",
    "gn:country_code":"ID",
    "gn:dem":13,
    "gn:feature_class":"P",
    "gn:feature_code":"PPL",
    "gn:name":"Kubangkangkung",
    "gn:population":0,
    "gn:timezone":"Asia/Jakarta",
    "iso:country":"ID",
    "name:ind_x_preferred":[
        "Kubangkangkung"
    ],
    "wof:name":"Kubangkangkung",
    "wof:placetype":"locality"
},
  "geometry": {"coordinates":[108.94889000000001,-7.62472],"type":"Point"}
}