{
  "type": "Feature",
  "properties": {
    "gn:admin1_code":"2",
    "gn:asciiname":"Banjar Batursari",
    "gn:country_code":"ID",
    "gn:dem":146,
    "gn:feature_class":"P",
    "gn:feature_code":"PPL",
    "gn:name":"Banjar Batursari",
    "gn:population":0,
    "gn:timezone":"Asia/Makassar",
    "iso:country":"ID",
    "name:ind_x_preferred":[
        "Banjar Batursari"
    ],
    "wof:name":"Banjar Batursari",
    "wof:placetype":"locality"
},
  "geometry": {"coordinates":[115.3095,-8.5318],"type":"Point"}
}