{
  "type": "Feature",
  "properties": {
    "gn:admin1_code":"32.0",
    "gn:asciiname":"Tanjungmulak",
    "gn:country_code":"ID",
    "gn:dem":174,
    "gn:feature_class":"P",
    "gn:feature_code":"PPL",
    "gn:name":"Tanjungmulak",
    "gn:population":0,
    "gn:timezone":"Asia/Jakarta",
    "iso:country":"ID",
    "name:und_x_variant":[
        "Tandjungmulak",
        "Tandjoengmoelak",
        "Tanjungmulak"
    ],
    "wof:lang_x_official":[
        "ind"
    ],
    "wof:lang_x_spoken":[
        "ind",
        "eng"
    ],
    "wof:name":"Tanjungmulak",
    "wof:placetype":"locality"
},
  "geometry": {"coordinates":[103.51881,-3.8956],"type":"Point"}
}