{
  "type": "Feature",
  "properties": {
    "gn:admin1_code":"30",
    "gn:asciiname":"Cibitung Hilir",
    "gn:country_code":"ID",
    "gn:dem":672,
    "gn:feature_class":"P",
    "gn:feature_code":"PPL",
    "gn:name":"Cibitung Hilir",
    "gn:population":0,
    "gn:timezone":"Asia/Jakarta",
    "iso:country":"ID",
    "name:ind_x_preferred":[
        "Cibitung Hilir"
    ],
    "wof:name":"Cibitung Hilir",
    "wof:placetype":"locality"
},
  "geometry": {"coordinates":[107.07111,-6.94222],"type":"Point"}
}