{
  "type": "Feature",
  "properties": {
    "gn:admin1_code":"38",
    "gn:asciiname":"Padali Baru",
    "gn:country_code":"ID",
    "gn:dem":27,
    "gn:feature_class":"P",
    "gn:feature_code":"PPL",
    "gn:name":"Padali Baru",
    "gn:population":0,
    "gn:timezone":"Asia/Makassar",
    "iso:country":"ID",
    "name:ind_x_preferred":[
        "Padali Baru"
    ],
    "wof:name":"Padali Baru",
    "wof:placetype":"locality"
},
  "geometry": {"coordinates":[119.8882,-4.1827],"type":"Point"}
}