{
  "type": "Feature",
  "properties": {
    "gn:admin1_code":"38",
    "gn:asciiname":"Buktoang",
    "gn:country_code":"ID",
    "gn:dem":571,
    "gn:feature_class":"P",
    "gn:feature_code":"PPL",
    "gn:name":"Buktoang",
    "gn:population":0,
    "gn:timezone":"Asia/Makassar",
    "iso:country":"ID",
    "name:ind_x_preferred":[
        "Buktoang"
    ],
    "wof:name":"Buktoang",
    "wof:placetype":"locality"
},
  "geometry": {"coordinates":[119.80070000000001,-4.9476],"type":"Point"}
}