{
  "type": "Feature",
  "properties": {
    "gn:admin1_code":"8.0",
    "gn:asciiname":"Lompenay",
    "gn:country_code":"ID",
    "gn:dem":20,
    "gn:feature_class":"P",
    "gn:feature_code":"PPL",
    "gn:name":"Lompenay",
    "gn:population":0,
    "gn:timezone":"Asia/Jakarta",
    "iso:country":"ID",
    "name:ind_x_preferred":[
        "Lompenay"
    ],
    "wof:name":"Lompenay",
    "wof:placetype":"locality"
},
  "geometry": {"coordinates":[113.4418,-7.174],"type":"Point"}
}