{
  "type": "Feature",
  "properties": {
    "gn:admin1_code":"1.0",
    "gn:asciiname":"Srapong",
    "gn:country_code":"ID",
    "gn:dem":8,
    "gn:feature_class":"P",
    "gn:feature_code":"PPL",
    "gn:name":"Srapong",
    "gn:population":0,
    "gn:timezone":"Asia/Jakarta",
    "iso:country":"ID",
    "name:ind_x_preferred":[
        "Srapong"
    ],
    "wof:name":"Srapong",
    "wof:placetype":"locality"
},
  "geometry": {"coordinates":[95.0771,5.6648],"type":"Point"}
}