{
  "type": "Feature",
  "properties": {
    "gn:admin1_code":"26",
    "gn:asciiname":"Rantopisang",
    "gn:country_code":"ID",
    "gn:dem":43,
    "gn:feature_class":"P",
    "gn:feature_code":"PPL",
    "gn:name":"Rantopisang",
    "gn:population":0,
    "gn:timezone":"Asia/Jakarta",
    "iso:country":"ID",
    "name:ind_x_preferred":[
        "Rantopisang"
    ],
    "wof:name":"Rantopisang",
    "wof:placetype":"locality"
},
  "geometry": {"coordinates":[99.1949,1.0935],"type":"Point"}
}