{
  "type": "Feature",
  "properties": {
    "gn:admin1_code":"18.0",
    "gn:asciiname":"Kuaeno",
    "gn:country_code":"ID",
    "gn:dem":452,
    "gn:feature_class":"P",
    "gn:feature_code":"PPLA4",
    "gn:name":"Kuaeno",
    "gn:population":0,
    "gn:timezone":"Asia/Makassar",
    "iso:country":"ID",
    "name:ind_x_preferred":[
        "Kuaeno"
    ],
    "wof:name":"Kuaeno",
    "wof:placetype":"locality"
},
  "geometry": {"coordinates":[124.58029999999999,-9.7084],"type":"Point"}
}