{
  "type": "Feature",
  "properties": {
    "gn:admin1_code":"18.0",
    "gn:asciiname":"Leweng",
    "gn:country_code":"ID",
    "gn:dem":452,
    "gn:feature_class":"P",
    "gn:feature_code":"PPL",
    "gn:name":"Leweng",
    "gn:population":0,
    "gn:timezone":"Asia/Makassar",
    "iso:country":"ID",
    "name:ind_x_preferred":[
        "Leweng"
    ],
    "wof:name":"Leweng",
    "wof:placetype":"locality"
},
  "geometry": {"coordinates":[120.2343,-8.6841],"type":"Point"}
}