{
  "type": "Feature",
  "properties": {
    "gn:admin1_code":"30.0",
    "gn:asciiname":"Koanyar",
    "gn:country_code":"ID",
    "gn:dem":270,
    "gn:feature_class":"P",
    "gn:feature_code":"PPL",
    "gn:name":"Koanyar",
    "gn:population":0,
    "gn:timezone":"Asia/Jakarta",
    "iso:country":"ID",
    "name:ind_x_preferred":[
        "Koanyar"
    ],
    "wof:lang_x_official":[
        "ind"
    ],
    "wof:lang_x_spoken":[
        "ind",
        "eng"
    ],
    "wof:name":"Koanyar",
    "wof:placetype":"locality"
},
  "geometry": {"coordinates":[113.8994,-7.9017],"type":"Point"}
}