{
  "type": "Feature",
  "properties": {
    "gn:admin1_code":"8.0",
    "gn:asciiname":"Tawing",
    "gn:country_code":"ID",
    "gn:dem":74,
    "gn:feature_class":"P",
    "gn:feature_code":"PPL",
    "gn:name":"Tawing",
    "gn:population":0,
    "gn:timezone":"Asia/Jakarta",
    "iso:country":"ID",
    "name:ind_x_preferred":[
        "Tawing"
    ],
    "wof:name":"Tawing",
    "wof:placetype":"locality"
},
  "geometry": {"coordinates":[111.85599999999999,-7.6279],"type":"Point"}
}