{
  "type": "Feature",
  "properties": {
    "gn:admin1_code":"7.0",
    "gn:asciiname":"Pentol",
    "gn:country_code":"ID",
    "gn:dem":20,
    "gn:feature_class":"P",
    "gn:feature_code":"PPL",
    "gn:name":"Pentol",
    "gn:population":0,
    "gn:timezone":"Asia/Jakarta",
    "iso:country":"ID",
    "name:ind_x_preferred":[
        "Pentol"
    ],
    "wof:name":"Pentol",
    "wof:placetype":"locality"
},
  "geometry": {"coordinates":[109.68971999999999,-7.685],"type":"Point"}
}