{
  "type": "Feature",
  "properties": {
    "gn:admin1_code":"30",
    "gn:asciiname":"Cigenteng",
    "gn:country_code":"ID",
    "gn:dem":1327,
    "gn:feature_class":"P",
    "gn:feature_code":"PPL",
    "gn:name":"Cigenteng",
    "gn:population":0,
    "gn:timezone":"Asia/Jakarta",
    "iso:country":"ID",
    "name:ind_x_preferred":[
        "Cigenteng"
    ],
    "name:und_x_variant":[
        "Tjigenteng"
    ],
    "wof:lang_x_official":[
        "ind"
    ],
    "wof:lang_x_spoken":[
        "ind",
        "eng"
    ],
    "wof:name":"Cigenteng",
    "wof:placetype":"locality"
},
  "geometry": {"coordinates":[107.46380000000001,-7.1311],"type":"Point"}
}