{
  "type": "Feature",
  "properties": {
    "gn:admin1_code":"26",
    "gn:asciiname":"Ujungtanduk",
    "gn:country_code":"ID",
    "gn:dem":924,
    "gn:feature_class":"P",
    "gn:feature_code":"PPL",
    "gn:name":"Ujungtanduk",
    "gn:population":0,
    "gn:timezone":"Asia/Jakarta",
    "iso:country":"ID",
    "name:ind_x_preferred":[
        "Ujungtanduk"
    ],
    "name:und_x_variant":[
        "Udjungtanduk"
    ],
    "wof:lang_x_official":[
        "ind"
    ],
    "wof:lang_x_spoken":[
        "ind",
        "eng"
    ],
    "wof:name":"Ujungtanduk",
    "wof:placetype":"locality"
},
  "geometry": {"coordinates":[99.1467,2.3626],"type":"Point"}
}