{
  "type": "Feature",
  "properties": {
    "gn:admin1_code":"18.0",
    "gn:asciiname":"Sambi",
    "gn:country_code":"ID",
    "gn:dem":191,
    "gn:feature_class":"P",
    "gn:feature_code":"PPL",
    "gn:name":"Sambi",
    "gn:population":0,
    "gn:timezone":"Asia/Makassar",
    "iso:country":"ID",
    "name:ind_x_preferred":[
        "Sambi"
    ],
    "wof:name":"Sambi",
    "wof:placetype":"locality"
},
  "geometry": {"coordinates":[120.6772,-8.8083],"type":"Point"}
}