{
  "type": "Feature",
  "properties": {
    "gn:admin1_code":"8.0",
    "gn:asciiname":"Sambirejo Barat",
    "gn:country_code":"ID",
    "gn:dem":42,
    "gn:feature_class":"P",
    "gn:feature_code":"PPL",
    "gn:name":"Sambirejo Barat",
    "gn:population":0,
    "gn:timezone":"Asia/Jakarta",
    "iso:country":"ID",
    "name:ind_x_preferred":[
        "Sambirejo Barat"
    ],
    "wof:name":"Sambirejo Barat",
    "wof:placetype":"locality"
},
  "geometry": {"coordinates":[112.29000000000001,-7.5666],"type":"Point"}
}