{
  "type": "Feature",
  "properties": {
    "gn:admin1_code":"17",
    "gn:asciiname":"Juranalas",
    "gn:country_code":"ID",
    "gn:dem":22,
    "gn:feature_class":"P",
    "gn:feature_code":"PPLA4",
    "gn:name":"Juranalas",
    "gn:population":0,
    "gn:timezone":"Asia/Makassar",
    "iso:country":"ID",
    "name:ind_x_preferred":[
        "Juranalas"
    ],
    "wof:name":"Juranalas",
    "wof:placetype":"locality"
},
  "geometry": {"coordinates":[116.99728,-8.52296],"type":"Point"}
}