{
  "type": "Feature",
  "properties": {
    "gn:admin1_code":"18",
    "gn:asciiname":"Keli",
    "gn:country_code":"ID",
    "gn:dem":167,
    "gn:feature_class":"P",
    "gn:feature_code":"PPL",
    "gn:name":"Keli",
    "gn:population":0,
    "gn:timezone":"Asia/Makassar",
    "iso:country":"ID",
    "name:ind_x_preferred":[
        "Keli"
    ],
    "wof:name":"Keli",
    "wof:placetype":"locality"
},
  "geometry": {"coordinates":[121.0335,-8.9487],"type":"Point"}
}