{
  "type": "Feature",
  "properties": {
    "gn:admin1_code":"30",
    "gn:asciiname":"Cileuksa",
    "gn:country_code":"ID",
    "gn:dem":524,
    "gn:feature_class":"P",
    "gn:feature_code":"PPL",
    "gn:name":"Cileuksa",
    "gn:population":0,
    "gn:timezone":"Asia/Jakarta",
    "iso:country":"ID",
    "name:ind_x_preferred":[
        "Cileuksa"
    ],
    "wof:name":"Cileuksa",
    "wof:placetype":"locality"
},
  "geometry": {"coordinates":[107.99083,-6.79722],"type":"Point"}
}