{
  "type": "Feature",
  "properties": {
    "gn:admin1_code":"07",
    "gn:asciiname":"Cemenggah",
    "gn:country_code":"ID",
    "gn:dem":468,
    "gn:feature_class":"P",
    "gn:feature_code":"PPL",
    "gn:name":"Cemenggah",
    "gn:population":0,
    "gn:timezone":"Asia/Jakarta",
    "iso:country":"ID",
    "name:ind_x_preferred":[
        "Cemenggah"
    ],
    "name:und_x_variant":[
        "Tjemanggah-lor",
        "Cemanggah-lor"
    ],
    "wof:lang_x_official":[
        "ind"
    ],
    "wof:lang_x_spoken":[
        "ind",
        "eng"
    ],
    "wof:name":"Cemenggah",
    "wof:placetype":"locality"
},
  "geometry": {"coordinates":[110.3617,-7.1143],"type":"Point"}
}