{
  "type": "Feature",
  "properties": {
    "gn:admin1_code":"30.0",
    "gn:asciiname":"Ciharashas Satu",
    "gn:country_code":"ID",
    "gn:dem":536,
    "gn:feature_class":"P",
    "gn:feature_code":"PPL",
    "gn:name":"Ciharashas Satu",
    "gn:population":0,
    "gn:timezone":"Asia/Jakarta",
    "iso:country":"ID",
    "name:ind_x_preferred":[
        "Ciharashas Satu"
    ],
    "wof:name":"Ciharashas Satu",
    "wof:placetype":"locality"
},
  "geometry": {"coordinates":[106.8916,-7.1103],"type":"Point"}
}