{
  "type": "Feature",
  "properties": {
    "gn:country":"ID",
    "gn:fcode":"ADM4",
    "gn:pop":0,
    "iso:country":"ID",
    "name:ind_x_preferred":[
        "Kelurahan Bendungan Hilir"
    ],
    "name:unk_x_variant":[
        "Bendungan Hilir"
    ],
    "qs:name":"Kelurahan Bendungan Hilir",
    "qs:photos_9r":0,
    "qs:photos_sr":0,
    "qs:pop_sr":"0",
    "wof:name":"Kelurahan Bendungan Hilir",
    "wof:placetype":"localadmin",
    "wof:population":0
},
  "geometry": {"coordinates":[106.80880000000001,-6.2087],"type":"Point"}
}