{
  "type": "Feature",
  "properties": {
    "gn:admin1_code":"30.0",
    "gn:asciiname":"Cidomas Dua",
    "gn:country_code":"ID",
    "gn:dem":804,
    "gn:feature_class":"P",
    "gn:feature_code":"PPL",
    "gn:name":"Cidomas Dua",
    "gn:population":0,
    "gn:timezone":"Asia/Jakarta",
    "iso:country":"ID",
    "name:ind_x_preferred":[
        "Cidomas Dua"
    ],
    "wof:name":"Cidomas Dua",
    "wof:placetype":"locality"
},
  "geometry": {"coordinates":[107.5442,-7.4294],"type":"Point"}
}