{
  "type": "Feature",
  "properties": {
    "gn:admin1_code":"36.0",
    "gn:asciiname":"Win",
    "gn:country_code":"ID",
    "gn:dem":21,
    "gn:feature_class":"P",
    "gn:feature_code":"PPL",
    "gn:name":"Win",
    "gn:population":0,
    "gn:timezone":"Asia/Jayapura",
    "iso:country":"ID",
    "name:fra_x_preferred":[
        "Win"
    ],
    "name:ind_x_preferred":[
        "Win"
    ],
    "name:pol_x_preferred":[
        "Win"
    ],
    "wof:lang_x_official":[
        "ind"
    ],
    "wof:lang_x_spoken":[
        "ind",
        "eng"
    ],
    "wof:name":"Win",
    "wof:placetype":"locality"
},
  "geometry": {"coordinates":[140.23658,-6.15993],"type":"Point"}
}