{
  "type": "Feature",
  "properties": {
    "gn:admin1_code":"29.0",
    "gn:asciiname":"Kailupa",
    "gn:country_code":"ID",
    "gn:dem":13,
    "gn:feature_class":"P",
    "gn:feature_code":"PPL",
    "gn:name":"Kailupa",
    "gn:population":0,
    "gn:timezone":"Asia/Jayapura",
    "iso:country":"ID",
    "name:und_x_variant":[
        "Kailoepa",
        "Kailupa"
    ],
    "wof:name":"Kailupa",
    "wof:placetype":"locality"
},
  "geometry": {"coordinates":[127.37236,0.7408],"type":"Point"}
}