{
  "type": "Feature",
  "properties": {
    "gn:admin1_code":"41",
    "gn:asciiname":"Lambalamba",
    "gn:country_code":"ID",
    "gn:dem":8,
    "gn:feature_class":"P",
    "gn:feature_code":"PPL",
    "gn:name":"Lambalamba",
    "gn:population":0,
    "gn:timezone":"Asia/Makassar",
    "iso:country":"ID",
    "name:ind_x_preferred":[
        "Lambalamba"
    ],
    "wof:name":"Lambalamba",
    "wof:placetype":"locality"
},
  "geometry": {"coordinates":[119.1467,-2.2015],"type":"Point"}
}