{
  "type": "Feature",
  "properties": {
    "gn:admin1_code":"1",
    "gn:asciiname":"Jamboiemirah",
    "gn:country_code":"ID",
    "gn:dem":538,
    "gn:feature_class":"P",
    "gn:feature_code":"PPL",
    "gn:name":"Jamboiemirah",
    "gn:population":0,
    "gn:timezone":"Asia/Jakarta",
    "iso:country":"ID",
    "name:ind_x_preferred":[
        "Jamboiemirah"
    ],
    "name:und_x_variant":[
        "Djamboiemirah"
    ],
    "wof:name":"Jamboiemirah",
    "wof:placetype":"locality"
},
  "geometry": {"coordinates":[96.86060000000001,3.823],"type":"Point"}
}