{
  "type": "Feature",
  "properties": {
    "gn:admin1_code":"22",
    "gn:asciiname":"Arnes",
    "gn:country_code":"ID",
    "gn:dem":46,
    "gn:feature_class":"P",
    "gn:feature_code":"PPL",
    "gn:name":"Arnes",
    "gn:population":0,
    "gn:timezone":"Asia/Makassar",
    "iso:country":"ID",
    "name:ind_x_preferred":[
        "Arnes"
    ],
    "name:und_x_variant":[
        "Ames"
    ],
    "wof:name":"Arnes",
    "wof:placetype":"locality"
},
  "geometry": {"coordinates":[122.0702,-3.9507],"type":"Point"}
}