{
  "type": "Feature",
  "properties": {
    "gn:admin1_code":"2.0",
    "gn:asciiname":"Songbintang",
    "gn:country_code":"ID",
    "gn:dem":110,
    "gn:feature_class":"P",
    "gn:feature_code":"PPL",
    "gn:name":"Songbintang",
    "gn:population":0,
    "gn:timezone":"Asia/Makassar",
    "iso:country":"ID",
    "name:ind_x_preferred":[
        "Songbintang"
    ],
    "wof:name":"Songbintang",
    "wof:placetype":"locality"
},
  "geometry": {"coordinates":[115.0943,-8.8287],"type":"Point"}
}