{
  "type": "Feature",
  "properties": {
    "gn:country":"ID",
    "gn:fcode":"PPL",
    "gn:pop":0,
    "iso:country":"ID",
    "name:unk_x_variant":[
        "Tjurug-wetan"
    ],
    "qs:name":"Curug Wetan",
    "qs:name_adm0":"Indonesia",
    "qs:name_adm1":"Banten",
    "qs:photos_9r":0,
    "qs:photos_sr":0,
    "qs:placetype":"Town",
    "qs:pop_sr":"0",
    "wof:name":"Curug Wetan",
    "wof:placetype":"locality",
    "wof:population":0
},
  "geometry": {"coordinates":[106.56610999999999,-6.2625],"type":"Point"}
}