{
  "type": "Feature",
  "properties": {
    "gn:admin1_code":"8",
    "gn:asciiname":"Gebangkerep",
    "gn:country_code":"ID",
    "gn:dem":48,
    "gn:feature_class":"P",
    "gn:feature_code":"PPL",
    "gn:name":"Gebangkerep",
    "gn:population":0,
    "gn:timezone":"Asia/Jakarta",
    "iso:country":"ID",
    "name:ind_x_preferred":[
        "Gebangkerep"
    ],
    "wof:name":"Gebangkerep",
    "wof:placetype":"locality"
},
  "geometry": {"coordinates":[112.0629,-7.6149],"type":"Point"}
}