{
  "type": "Feature",
  "properties": {
    "gn:admin1_code":"7",
    "gn:asciiname":"Sambong",
    "gn:country_code":"ID",
    "gn:dem":146,
    "gn:feature_class":"P",
    "gn:feature_code":"PPL",
    "gn:name":"Sambong",
    "gn:population":0,
    "gn:timezone":"Asia/Jakarta",
    "iso:country":"ID",
    "name:ind_x_preferred":[
        "Sambong"
    ],
    "wof:name":"Sambong",
    "wof:placetype":"locality"
},
  "geometry": {"coordinates":[110.88111000000001,-8.00389],"type":"Point"}
}