{
  "type": "Feature",
  "properties": {
    "gn:admin1_code":"33",
    "gn:asciiname":"Parung",
    "gn:country_code":"ID",
    "gn:dem":29,
    "gn:feature_class":"P",
    "gn:feature_code":"PPL",
    "gn:name":"Parung",
    "gn:population":0,
    "gn:timezone":"Asia/Jakarta",
    "iso:country":"ID",
    "name:azb_x_preferred":[
        "\u067e\u0627\u0631\u0648\u0646\u0642"
    ],
    "name:fas_x_preferred":[
        "\u067e\u0627\u0631\u0648\u0646\u06af"
    ],
    "name:fra_x_preferred":[
        "Parung"
    ],
    "name:ind_x_preferred":[
        "Parung"
    ],
    "name:jav_x_preferred":[
        "Parung"
    ],
    "name:mlg_x_preferred":[
        "Parung"
    ],
    "name:nor_x_preferred":[
        "Parung"
    ],
    "name:sun_x_preferred":[
        "Parung"
    ],
    "wof:lang_x_official":[
        "ind"
    ],
    "wof:lang_x_spoken":[
        "ind",
        "eng"
    ],
    "wof:name":"Parung",
    "wof:placetype":"locality"
},
  "geometry": {"coordinates":[106.2253,-6.4433],"type":"Point"}
}