{
  "type": "Feature",
  "properties": {
    "gn:admin1_code":"15.0",
    "gn:asciiname":"Badak",
    "gn:country_code":"ID",
    "gn:dem":15,
    "gn:feature_class":"P",
    "gn:feature_code":"PPL",
    "gn:name":"Badak",
    "gn:population":0,
    "gn:timezone":"Asia/Jakarta",
    "iso:country":"ID",
    "name:ind_x_preferred":[
        "Badak"
    ],
    "wof:name":"Badak",
    "wof:placetype":"locality"
},
  "geometry": {"coordinates":[104.82049000000001,-5.61674],"type":"Point"}
}