{
  "type": "Feature",
  "properties": {
    "gn:admin1_code":"18.0",
    "gn:asciiname":"Baki",
    "gn:country_code":"ID",
    "gn:dem":646,
    "gn:feature_class":"P",
    "gn:feature_code":"PPLA4",
    "gn:name":"Baki",
    "gn:population":0,
    "gn:timezone":"Asia/Makassar",
    "iso:country":"ID",
    "name:cat_x_preferred":[
        "Baki"
    ],
    "name:ceb_x_preferred":[
        "Baki"
    ],
    "name:deu_x_preferred":[
        "Baki"
    ],
    "name:fin_x_preferred":[
        "Baki"
    ],
    "name:fra_x_preferred":[
        "Baki"
    ],
    "name:hun_x_preferred":[
        "Baki"
    ],
    "name:ind_x_preferred":[
        "Baki"
    ],
    "name:ita_x_preferred":[
        "Baki"
    ],
    "name:mlg_x_preferred":[
        "Baki"
    ],
    "name:nld_x_preferred":[
        "Baki"
    ],
    "name:pol_x_preferred":[
        "Baki"
    ],
    "name:rus_x_preferred":[
        "\u0411\u0430\u043a\u0438"
    ],
    "name:swa_x_preferred":[
        "Baki"
    ],
    "name:swe_x_preferred":[
        "Baki"
    ],
    "name:tha_x_preferred":[
        "\u0e1a\u0e32\u0e01\u0e34"
    ],
    "name:tur_x_preferred":[
        "Baki"
    ],
    "wof:lang_x_official":[
        "ind"
    ],
    "wof:lang_x_spoken":[
        "ind",
        "eng"
    ],
    "wof:name":"Baki",
    "wof:placetype":"locality"
},
  "geometry": {"coordinates":[124.4743,-9.9293],"type":"Point"}
}