{
  "type": "Feature",
  "properties": {
    "gn:admin1_code":"8",
    "gn:asciiname":"Kauman",
    "gn:country_code":"ID",
    "gn:dem":195,
    "gn:feature_class":"P",
    "gn:feature_code":"PPL",
    "gn:name":"Kauman",
    "gn:population":0,
    "gn:timezone":"Asia/Jakarta",
    "iso:country":"ID",
    "name:ind_x_preferred":[
        "Kauman"
    ],
    "wof:name":"Kauman",
    "wof:placetype":"locality"
},
  "geometry": {"coordinates":[112.35850000000001,-8.1592],"type":"Point"}
}