{
  "type": "Feature",
  "properties": {
    "gn:admin1_code":"38.0",
    "gn:asciiname":"Madata",
    "gn:country_code":"ID",
    "gn:dem":763,
    "gn:feature_class":"P",
    "gn:feature_code":"PPL",
    "gn:name":"Madata",
    "gn:population":0,
    "gn:timezone":"Asia/Makassar",
    "iso:country":"ID",
    "name:ind_x_preferred":[
        "Madata"
    ],
    "wof:name":"Madata",
    "wof:placetype":"locality"
},
  "geometry": {"coordinates":[119.87909999999999,-3.4391],"type":"Point"}
}