{
  "type": "Feature",
  "properties": {
    "gn:admin1_code":"0.0",
    "gn:asciiname":"Nabi",
    "gn:cc2":"ID",
    "gn:country_code":"ID",
    "gn:dem":319,
    "gn:feature_class":"P",
    "gn:feature_code":"PPL",
    "gn:name":"Nabi",
    "gn:population":0,
    "gn:timezone":"Asia/Jayapura",
    "iso:country":"ID",
    "name:ceb_x_preferred":[
        "Nabi"
    ],
    "name:deu_x_preferred":[
        "Nabi"
    ],
    "name:epo_x_preferred":[
        "Nabi"
    ],
    "name:fra_x_preferred":[
        "Nabi"
    ],
    "name:kaz_x_preferred":[
        "\u041d\u04d9\u0431\u0438"
    ],
    "name:kor_x_preferred":[
        "\ub098\ube44"
    ],
    "name:nds_x_preferred":[
        "Nabi"
    ],
    "name:rus_x_preferred":[
        "\u041d\u0430\u0431\u0438"
    ],
    "name:swe_x_preferred":[
        "Nabi"
    ],
    "name:und_x_variant":[
        "Nahbi",
        "Nabire",
        "Nabi"
    ],
    "wof:lang_x_official":[
        "ind"
    ],
    "wof:lang_x_spoken":[
        "ind",
        "eng"
    ],
    "wof:name":"Nabi",
    "wof:placetype":"locality"
},
  "geometry": {"coordinates":[134.23333,-2.93333],"type":"Point"}
}