{
  "type": "Feature",
  "properties": {
    "gn:admin1_code":"28.0",
    "gn:asciiname":"Banda Neira",
    "gn:country_code":"ID",
    "gn:dem":18,
    "gn:feature_class":"P",
    "gn:feature_code":"PPL",
    "gn:name":"Banda Neira",
    "gn:population":0,
    "gn:timezone":"Asia/Jayapura",
    "iso:country":"ID",
    "name:eng_x_preferred":[
        "Banda Neira"
    ],
    "name:fra_x_preferred":[
        "Banda Neira"
    ],
    "name:ind_x_preferred":[
        "Bandaneira"
    ],
    "name:und_x_variant":[
        "Niara",
        "Bandanarra",
        "Bandanaira",
        "Banda Neira"
    ],
    "wof:name":"Banda Neira",
    "wof:placetype":"locality"
},
  "geometry": {"coordinates":[129.90346,-4.5262],"type":"Point"}
}