{
  "type": "Feature",
  "properties": {
    "gn:admin1_code":"07",
    "gn:asciiname":"Grogol",
    "gn:country_code":"ID",
    "gn:dem":513,
    "gn:feature_class":"P",
    "gn:feature_code":"PPL",
    "gn:name":"Grogol",
    "gn:population":0,
    "gn:timezone":"Asia/Jakarta",
    "iso:country":"ID",
    "name:ceb_x_preferred":[
        "Kelurahan Grogol"
    ],
    "name:fas_x_preferred":[
        "\u06af\u0631\u0648\u06af\u0648\u0644"
    ],
    "name:ind_x_preferred":[
        "Grogol"
    ],
    "name:mlg_x_preferred":[
        "Grogol"
    ],
    "name:msa_x_preferred":[
        "Grogol"
    ],
    "name:nld_x_preferred":[
        "Grogol"
    ],
    "name:sun_x_preferred":[
        "Grogol"
    ],
    "name:swe_x_preferred":[
        "Kelurahan Grogol"
    ],
    "name:und_x_variant":[
        "Grogol 2",
        "Grogol Dua",
        "Grogol"
    ],
    "wof:name":"Grogol",
    "wof:placetype":"locality"
},
  "geometry": {"coordinates":[110.29167,-7.41861],"type":"Point"}
}