{
  "type": "Feature",
  "properties": {
    "gn:admin1_code":"8",
    "gn:asciiname":"Kebonwaru",
    "gn:country_code":"ID",
    "gn:dem":736,
    "gn:feature_class":"P",
    "gn:feature_code":"PPL",
    "gn:name":"Kebonwaru",
    "gn:population":0,
    "gn:timezone":"Asia/Jakarta",
    "iso:country":"ID",
    "name:ind_x_preferred":[
        "Kebonwaru"
    ],
    "wof:name":"Kebonwaru",
    "wof:placetype":"locality"
},
  "geometry": {"coordinates":[111.36861,-8.05528],"type":"Point"}
}