{
  "type": "Feature",
  "properties": {
    "gn:admin1_code":"32.0",
    "gn:asciiname":"Pedang",
    "gn:country_code":"ID",
    "gn:dem":70,
    "gn:feature_class":"P",
    "gn:feature_code":"PPL",
    "gn:name":"Pedang",
    "gn:population":0,
    "gn:timezone":"Asia/Jakarta",
    "iso:country":"ID",
    "name:ceb_x_preferred":[
        "Pedang"
    ],
    "name:ind_x_preferred":[
        "Pedang"
    ],
    "name:msa_x_preferred":[
        "Pedang"
    ],
    "name:nep_x_preferred":[
        "\u092a\u0947\u0926\u093e\u0919"
    ],
    "name:new_x_preferred":[
        "\u092a\u0947\u0926\u093e\u0919"
    ],
    "name:pol_x_preferred":[
        "Pedang"
    ],
    "wof:name":"Pedang",
    "wof:placetype":"locality"
},
  "geometry": {"coordinates":[102.98,-3.2646],"type":"Point"}
}