{
  "type": "Feature",
  "properties": {
    "gn:admin1_code":"7",
    "gn:asciiname":"Pendem",
    "gn:country_code":"ID",
    "gn:dem":492,
    "gn:feature_class":"P",
    "gn:feature_code":"PPL",
    "gn:name":"Pendem",
    "gn:population":0,
    "gn:timezone":"Asia/Jakarta",
    "iso:country":"ID",
    "name:ceb_x_preferred":[
        "Pendem"
    ],
    "name:ind_x_preferred":[
        "Pendem"
    ],
    "name:nld_x_preferred":[
        "Pendem"
    ],
    "name:swe_x_preferred":[
        "Pendem"
    ],
    "wof:name":"Pendem",
    "wof:placetype":"locality"
},
  "geometry": {"coordinates":[111.09639,-7.56056],"type":"Point"}
}