{
  "type": "Feature",
  "properties": {
    "gn:admin1_code":"38",
    "gn:asciiname":"Daya",
    "gn:country_code":"ID",
    "gn:dem":15,
    "gn:feature_class":"P",
    "gn:feature_code":"PPL",
    "gn:name":"Daya",
    "gn:population":0,
    "gn:timezone":"Asia/Makassar",
    "iso:country":"ID",
    "name:ceb_x_preferred":[
        "Daya"
    ],
    "name:heb_x_preferred":[
        "\u05d3\u05d9\u05d4"
    ],
    "name:ind_x_preferred":[
        "Daya"
    ],
    "name:pol_x_preferred":[
        "Daya"
    ],
    "name:swe_x_preferred":[
        "Daya"
    ],
    "name:vie_x_preferred":[
        "Daya"
    ],
    "wof:lang_x_official":[
        "ind"
    ],
    "wof:lang_x_spoken":[
        "ind",
        "eng"
    ],
    "wof:name":"Daya",
    "wof:placetype":"locality"
},
  "geometry": {"coordinates":[119.5121,-5.111],"type":"Point"}
}