{
  "type": "Feature",
  "properties": {
    "gn:admin1_code":"08",
    "gn:asciiname":"Kandangan",
    "gn:country_code":"ID",
    "gn:dem":948,
    "gn:feature_class":"P",
    "gn:feature_code":"PPL",
    "gn:name":"Kandangan",
    "gn:population":0,
    "gn:timezone":"Asia/Jakarta",
    "iso:country":"ID",
    "name:ara_x_preferred":[
        "\u0643\u0646\u062f\u0627\u0646\u063a\u0627\u0646"
    ],
    "name:bjn_x_preferred":[
        "Kandangan"
    ],
    "name:ind_x_preferred":[
        "Kandangan"
    ],
    "name:jav_x_preferred":[
        "Kandangan"
    ],
    "name:msa_x_preferred":[
        "Kandangan"
    ],
    "name:nld_x_preferred":[
        "Kandangan"
    ],
    "wof:lang_x_official":[
        "ind"
    ],
    "wof:lang_x_spoken":[
        "ind",
        "eng"
    ],
    "wof:name":"Kandangan",
    "wof:placetype":"locality"
},
  "geometry": {"coordinates":[112.51430000000001,-7.8442],"type":"Point"}
}