{
  "type": "Feature",
  "properties": {
    "gn:admin1_code":"7",
    "gn:asciiname":"Pondoksimpur",
    "gn:country_code":"ID",
    "gn:dem":254,
    "gn:feature_class":"P",
    "gn:feature_code":"PPL",
    "gn:name":"Pondoksimpur",
    "gn:population":0,
    "gn:timezone":"Asia/Jakarta",
    "iso:country":"ID",
    "name:ind_x_preferred":[
        "Pondoksimpur"
    ],
    "wof:name":"Pondoksimpur",
    "wof:placetype":"locality"
},
  "geometry": {"coordinates":[110.50528,-7.16806],"type":"Point"}
}