{
  "type": "Feature",
  "properties": {
    "gn:admin1_code":"17",
    "gn:asciiname":"Pamali",
    "gn:country_code":"ID",
    "gn:dem":555,
    "gn:feature_class":"P",
    "gn:feature_code":"PPL",
    "gn:name":"Pamali",
    "gn:population":0,
    "gn:timezone":"Asia/Makassar",
    "iso:country":"ID",
    "name:ind_x_preferred":[
        "Pamali"
    ],
    "wof:name":"Pamali",
    "wof:placetype":"locality"
},
  "geometry": {"coordinates":[118.90989999999999,-8.5365],"type":"Point"}
}