{
  "type": "Feature",
  "properties": {
    "gn:admin1_code":"0.0",
    "gn:asciiname":"Ulongtuyuk",
    "gn:cc2":"ID",
    "gn:country_code":"ID",
    "gn:dem":52,
    "gn:feature_class":"P",
    "gn:feature_code":"PPL",
    "gn:name":"Ulongtuyuk",
    "gn:population":0,
    "gn:timezone":"Asia/Makassar",
    "iso:country":"ID",
    "name:ind_x_preferred":[
        "Utongtujuk"
    ],
    "name:und_x_variant":[
        "Oeloengtoejoek",
        "Long Toejoek",
        "Oelongtoejoek",
        "Ulongtujuk",
        "Ulongtuyuk"
    ],
    "wof:lang_x_official":[
        "ind"
    ],
    "wof:lang_x_spoken":[
        "ind",
        "eng"
    ],
    "wof:name":"Ulongtuyuk",
    "wof:placetype":"locality"
},
  "geometry": {"coordinates":[116.25,-1.33333],"type":"Point"}
}