{
  "type": "Feature",
  "properties": {
    "gn:admin1_code":"42",
    "gn:asciiname":"Long Lian",
    "gn:country_code":"ID",
    "gn:dem":26,
    "gn:feature_class":"P",
    "gn:feature_code":"PPL",
    "gn:name":"Long Lian",
    "gn:population":0,
    "gn:timezone":"Asia/Makassar",
    "iso:country":"ID",
    "name:ind_x_preferred":[
        "Long Lian"
    ],
    "wof:name":"Long Lian",
    "wof:placetype":"locality"
},
  "geometry": {"coordinates":[116.75941,2.66758],"type":"Point"}
}