{
  "type": "Feature",
  "properties": {
    "gn:admin1_code":"26.0",
    "gn:asciiname":"Sibuntuon Dua",
    "gn:country_code":"ID",
    "gn:dem":1199,
    "gn:feature_class":"P",
    "gn:feature_code":"PPL",
    "gn:name":"Sibuntuon Dua",
    "gn:population":0,
    "gn:timezone":"Asia/Jakarta",
    "iso:country":"ID",
    "name:ind_x_preferred":[
        "Sibuntuon Dua"
    ],
    "name:und_x_variant":[
        "Sibuntuon 2"
    ],
    "wof:lang_x_official":[
        "ind"
    ],
    "wof:lang_x_spoken":[
        "ind",
        "eng"
    ],
    "wof:name":"Sibuntuon Dua",
    "wof:placetype":"locality"
},
  "geometry": {"coordinates":[98.72280000000001,2.1439],"type":"Point"}
}