{
  "type": "Feature",
  "properties": {
    "gn:admin1_code":"36.0",
    "gn:asciiname":"Keruda",
    "gn:country_code":"ID",
    "gn:dem":1596,
    "gn:feature_class":"P",
    "gn:feature_code":"PPL",
    "gn:name":"Keruda",
    "gn:population":0,
    "gn:timezone":"Asia/Jayapura",
    "iso:country":"ID",
    "name:ind_x_preferred":[
        "Keruda"
    ],
    "name:und_x_variant":[
        "Kerauda"
    ],
    "wof:lang_x_official":[
        "ind"
    ],
    "wof:lang_x_spoken":[
        "ind",
        "eng"
    ],
    "wof:name":"Keruda",
    "wof:placetype":"locality"
},
  "geometry": {"coordinates":[136.06064000000001,-4.06853],"type":"Point"}
}