{
  "type": "Feature",
  "properties": {
    "gn:admin1_code":"17.0",
    "gn:asciiname":"Dorowila",
    "gn:country_code":"ID",
    "gn:dem":20,
    "gn:feature_class":"P",
    "gn:feature_code":"PPL",
    "gn:name":"Dorowila",
    "gn:population":0,
    "gn:timezone":"Asia/Makassar",
    "iso:country":"ID",
    "name:ind_x_preferred":[
        "Dorowila"
    ],
    "wof:name":"Dorowila",
    "wof:placetype":"locality"
},
  "geometry": {"coordinates":[118.61799999999999,-8.505],"type":"Point"}
}