{
  "type": "Feature",
  "properties": {
    "gn:country":"ID",
    "gn:fcode":"ADM3",
    "gn:pop":0,
    "iso:country":"ID",
    "name:ind_x_preferred":[
        "Kecamatan Pekalongan Timur"
    ],
    "name:unk_x_variant":[
        "Pekalongan Timur"
    ],
    "qs:name":"Kecamatan Pekalongan Timur",
    "qs:photos_9r":0,
    "qs:photos_sr":0,
    "qs:pop_sr":"0",
    "wd:wordcount":1175,
    "wof:name":"Kecamatan Pekalongan Timur",
    "wof:placetype":"localadmin",
    "wof:population":0
},
  "geometry": {"coordinates":[109.6884,-6.89321],"type":"Point"}
}