{
  "type": "Feature",
  "properties": {
    "gn:admin1_code":"18.0",
    "gn:asciiname":"Balijaha",
    "gn:country_code":"ID",
    "gn:dem":31,
    "gn:feature_class":"P",
    "gn:feature_code":"PPL",
    "gn:name":"Balijaha",
    "gn:population":0,
    "gn:timezone":"Asia/Makassar",
    "iso:country":"ID",
    "name:ind_x_preferred":[
        "Balijaha"
    ],
    "wof:name":"Balijaha",
    "wof:placetype":"locality"
},
  "geometry": {"coordinates":[119.0176,-9.6435],"type":"Point"}
}