{
  "type": "Feature",
  "properties": {
    "gn:admin1_code":"26",
    "gn:asciiname":"Sukanalo",
    "gn:country_code":"ID",
    "gn:dem":1206,
    "gn:feature_class":"P",
    "gn:feature_code":"PPL",
    "gn:name":"Sukanalo",
    "gn:population":0,
    "gn:timezone":"Asia/Jakarta",
    "iso:country":"ID",
    "name:ind_x_preferred":[
        "Sukanalo"
    ],
    "name:und_x_variant":[
        "Sukanalu"
    ],
    "wof:name":"Sukanalo",
    "wof:placetype":"locality"
},
  "geometry": {"coordinates":[98.5515,3.0903],"type":"Point"}
}