{
  "type": "Feature",
  "properties": {
    "gn:admin1_code":"38.0",
    "gn:asciiname":"Carika",
    "gn:country_code":"ID",
    "gn:dem":420,
    "gn:feature_class":"P",
    "gn:feature_code":"PPL",
    "gn:name":"Carika",
    "gn:population":0,
    "gn:timezone":"Asia/Makassar",
    "iso:country":"ID",
    "name:ind_x_preferred":[
        "Carika"
    ],
    "wof:name":"Carika",
    "wof:placetype":"locality"
},
  "geometry": {"coordinates":[120.1104,-4.5116],"type":"Point"}
}