{
  "type": "Feature",
  "properties": {
    "gn:admin1_code":"17",
    "gn:asciiname":"Selat",
    "gn:country_code":"ID",
    "gn:dem":156,
    "gn:feature_class":"P",
    "gn:feature_code":"PPLA4",
    "gn:name":"Selat",
    "gn:population":0,
    "gn:timezone":"Asia/Makassar",
    "iso:country":"ID",
    "name:ind_x_preferred":[
        "Selat"
    ],
    "wof:name":"Selat",
    "wof:placetype":"locality"
},
  "geometry": {"coordinates":[116.2101,-8.5816],"type":"Point"}
}