{
  "type": "Feature",
  "properties": {
    "gn:admin1_code":"8.0",
    "gn:asciiname":"Kresek",
    "gn:country_code":"ID",
    "gn:dem":14,
    "gn:feature_class":"P",
    "gn:feature_code":"PPL",
    "gn:name":"Kresek",
    "gn:population":0,
    "gn:timezone":"Asia/Jakarta",
    "iso:country":"ID",
    "name:ceb_x_preferred":[
        "Kresek"
    ],
    "name:fas_x_preferred":[
        "\u06a9\u0631\u0633\u06a9"
    ],
    "name:ind_x_preferred":[
        "Kresek"
    ],
    "name:jav_x_preferred":[
        "Kresek"
    ],
    "name:mlg_x_preferred":[
        "Kresek"
    ],
    "name:msa_x_preferred":[
        "Kresek"
    ],
    "name:nld_x_preferred":[
        "Kresek"
    ],
    "name:nor_x_preferred":[
        "Kresek"
    ],
    "wof:lang_x_official":[
        "ind"
    ],
    "wof:lang_x_spoken":[
        "ind",
        "eng"
    ],
    "wof:name":"Kresek",
    "wof:placetype":"locality"
},
  "geometry": {"coordinates":[112.99590000000001,-7.7138],"type":"Point"}
}