{
  "type": "Feature",
  "properties": {
    "gn:admin1_code":"07",
    "gn:asciiname":"Jatirejo Satu",
    "gn:cc2":"ID",
    "gn:country_code":"ID",
    "gn:dem":568,
    "gn:feature_class":"P",
    "gn:feature_code":"PPL",
    "gn:name":"Jatirejo Satu",
    "gn:population":0,
    "gn:timezone":"Asia/Jakarta",
    "iso:country":"ID",
    "name:und_x_variant":[
        "Djatiredjo 1",
        "Jatirejo Satu"
    ],
    "wof:name":"Jatirejo Satu",
    "wof:placetype":"locality"
},
  "geometry": {"coordinates":[110.57193999999998,-7.38167],"type":"Point"}
}