{
  "type": "Feature",
  "properties": {
    "gn:admin1_code":"28.0",
    "gn:asciiname":"Uta",
    "gn:cc2":"ID",
    "gn:country_code":"ID",
    "gn:dem":14,
    "gn:feature_class":"P",
    "gn:feature_code":"PPL",
    "gn:name":"Uta",
    "gn:population":0,
    "gn:timezone":"Asia/Jayapura",
    "iso:country":"ID",
    "name:lat_x_preferred":[
        "Uta"
    ],
    "name:nld_x_preferred":[
        "Uta"
    ],
    "name:por_x_preferred":[
        "Uta"
    ],
    "name:swe_x_preferred":[
        "Uta"
    ],
    "name:und_x_variant":[
        "Oeta"
    ],
    "wof:lang_x_official":[
        "ind"
    ],
    "wof:lang_x_spoken":[
        "ind",
        "eng"
    ],
    "wof:name":"Uta",
    "wof:placetype":"locality"
},
  "geometry": {"coordinates":[131.62890999999999,-4.44859],"type":"Point"}
}