{
  "type": "Feature",
  "properties": {
    "gn:admin1_code":"28.0",
    "gn:asciiname":"Uta",
    "gn:cc2":"ID",
    "gn:country_code":"ID",
    "gn:dem":14,
    "gn:feature_class":"P",
    "gn:feature_code":"PPL",
    "gn:name":"Uta",
    "gn:population":0,
    "gn:timezone":"Asia/Jayapura",
    "iso:country":"ID",
    "name:und_x_variant":[
        "Oeta"
    ],
    "wof:name":"Uta",
    "wof:placetype":"locality"
},
  "geometry": {"coordinates":[131.62891000000002,-4.44859],"type":"Point"}
}