{
  "type": "Feature",
  "properties": {
    "gn:admin1_code":"7",
    "gn:asciiname":"Dungringan",
    "gn:country_code":"ID",
    "gn:dem":81,
    "gn:feature_class":"P",
    "gn:feature_code":"PPL",
    "gn:name":"Dungringan",
    "gn:population":0,
    "gn:timezone":"Asia/Jakarta",
    "iso:country":"ID",
    "name:ind_x_preferred":[
        "Dungringan"
    ],
    "wof:name":"Dungringan",
    "wof:placetype":"locality"
},
  "geometry": {"coordinates":[111.03972,-7.34056],"type":"Point"}
}