{
  "type": "Feature",
  "properties": {
    "gn:admin1_code":"30.0",
    "gn:asciiname":"Pasirkubang",
    "gn:country_code":"ID",
    "gn:dem":541,
    "gn:feature_class":"P",
    "gn:feature_code":"PPL",
    "gn:name":"Pasirkubang",
    "gn:population":0,
    "gn:timezone":"Asia/Jakarta",
    "iso:country":"ID",
    "name:ind_x_preferred":[
        "Pasirkubang"
    ],
    "name:und_x_variant":[
        "Pasirkoebang"
    ],
    "wof:name":"Pasirkubang",
    "wof:placetype":"locality"
},
  "geometry": {"coordinates":[108.26649999999999,-7.4843],"type":"Point"}
}