{
  "type": "Feature",
  "properties": {
    "gn:admin1_code":"7",
    "gn:asciiname":"Siasemdukuh",
    "gn:country_code":"ID",
    "gn:dem":12,
    "gn:feature_class":"P",
    "gn:feature_code":"PPL",
    "gn:name":"Siasemdukuh",
    "gn:population":0,
    "gn:timezone":"Asia/Jakarta",
    "iso:country":"ID",
    "name:ind_x_preferred":[
        "Siasemdukuh"
    ],
    "wof:name":"Siasemdukuh",
    "wof:placetype":"locality"
},
  "geometry": {"coordinates":[108.9969,-6.8814],"type":"Point"}
}