{
  "type": "Feature",
  "properties": {
    "gn:admin1_code":"30",
    "gn:asciiname":"Buaran",
    "gn:country_code":"ID",
    "gn:dem":21,
    "gn:feature_class":"P",
    "gn:feature_code":"PPL",
    "gn:name":"Buaran",
    "gn:population":0,
    "gn:timezone":"Asia/Jakarta",
    "iso:country":"ID",
    "name:ind_x_preferred":[
        "Buaran"
    ],
    "wof:name":"Buaran",
    "wof:placetype":"locality"
},
  "geometry": {"coordinates":[106.98569999999999,-6.2292],"type":"Point"}
}