{
  "type": "Feature",
  "properties": {
    "gn:admin1_code":"18.0",
    "gn:asciiname":"Wolosabu",
    "gn:country_code":"ID",
    "gn:dem":219,
    "gn:feature_class":"P",
    "gn:feature_code":"PPL",
    "gn:name":"Wolosabu",
    "gn:population":0,
    "gn:timezone":"Asia/Makassar",
    "iso:country":"ID",
    "name:ind_x_preferred":[
        "Wolosabu"
    ],
    "wof:name":"Wolosabu",
    "wof:placetype":"locality"
},
  "geometry": {"coordinates":[121.2029,-8.8677],"type":"Point"}
}