{
  "type": "Feature",
  "properties": {
    "gn:admin1_code":"7",
    "gn:asciiname":"Depok",
    "gn:country_code":"ID",
    "gn:dem":732,
    "gn:feature_class":"P",
    "gn:feature_code":"PPL",
    "gn:name":"Depok",
    "gn:population":0,
    "gn:timezone":"Asia/Jakarta",
    "iso:country":"ID",
    "name:ind_x_preferred":[
        "Depok"
    ],
    "wof:name":"Depok",
    "wof:placetype":"locality"
},
  "geometry": {"coordinates":[110.15528,-7.2175],"type":"Point"}
}