{
  "type": "Feature",
  "properties": {
    "gn:admin1_code":"8.0",
    "gn:asciiname":"Banjarkejen",
    "gn:country_code":"ID",
    "gn:dem":50,
    "gn:feature_class":"P",
    "gn:feature_code":"PPL",
    "gn:name":"Banjarkejen",
    "gn:population":0,
    "gn:timezone":"Asia/Jakarta",
    "iso:country":"ID",
    "name:ind_x_preferred":[
        "Banjarkejen"
    ],
    "wof:name":"Banjarkejen",
    "wof:placetype":"locality"
},
  "geometry": {"coordinates":[112.7559,-7.6248],"type":"Point"}
}