{
  "type": "Feature",
  "properties": {
    "gn:admin1_code":"22",
    "gn:asciiname":"Pongkurumba",
    "gn:country_code":"ID",
    "gn:dem":277,
    "gn:feature_class":"P",
    "gn:feature_code":"PPL",
    "gn:name":"Pongkurumba",
    "gn:population":0,
    "gn:timezone":"Asia/Makassar",
    "iso:country":"ID",
    "name:ind_x_preferred":[
        "Pongkurumba"
    ],
    "name:und_x_variant":[
        "Pangkumba"
    ],
    "wof:lang_x_official":[
        "ind"
    ],
    "wof:lang_x_spoken":[
        "ind",
        "eng"
    ],
    "wof:name":"Pongkurumba",
    "wof:placetype":"locality"
},
  "geometry": {"coordinates":[121.5898,-4.7151],"type":"Point"}
}