{
  "type": "Feature",
  "properties": {
    "gn:admin1_code":"18.0",
    "gn:asciiname":"Tanamiting",
    "gn:country_code":"ID",
    "gn:dem":132,
    "gn:feature_class":"P",
    "gn:feature_code":"PPL",
    "gn:name":"Tanamiting",
    "gn:population":0,
    "gn:timezone":"Asia/Makassar",
    "iso:country":"ID",
    "name:ind_x_preferred":[
        "Tanamiting"
    ],
    "wof:name":"Tanamiting",
    "wof:placetype":"locality"
},
  "geometry": {"coordinates":[120.2022,-9.5241],"type":"Point"}
}