{
  "type": "Feature",
  "properties": {
    "gn:admin1_code":"1",
    "gn:asciiname":"Paya Pisangklat",
    "gn:country_code":"ID",
    "gn:dem":31,
    "gn:feature_class":"P",
    "gn:feature_code":"PPL",
    "gn:name":"Paya Pisangklat",
    "gn:population":0,
    "gn:timezone":"Asia/Jakarta",
    "iso:country":"ID",
    "name:ind_x_preferred":[
        "Paya Pisangklat"
    ],
    "wof:name":"Paya Pisangklat",
    "wof:placetype":"locality"
},
  "geometry": {"coordinates":[96.2932,5.1712],"type":"Point"}
}