{
  "type": "Feature",
  "properties": {
    "gn:admin1_code":"33.0",
    "gn:asciiname":"Waringinsari",
    "gn:country_code":"ID",
    "gn:dem":82,
    "gn:feature_class":"P",
    "gn:feature_code":"PPL",
    "gn:name":"Waringinsari",
    "gn:population":0,
    "gn:timezone":"Asia/Jakarta",
    "iso:country":"ID",
    "name:ind_x_preferred":[
        "Waringinsari"
    ],
    "wof:name":"Waringinsari",
    "wof:placetype":"locality"
},
  "geometry": {"coordinates":[105.938,-6.4256],"type":"Point"}
}