{
  "type": "Feature",
  "properties": {
    "gn:admin1_code":"7.0",
    "gn:asciiname":"Tidarunan",
    "gn:country_code":"ID",
    "gn:dem":343,
    "gn:feature_class":"P",
    "gn:feature_code":"PPL",
    "gn:name":"Tidarunan",
    "gn:population":0,
    "gn:timezone":"Asia/Jakarta",
    "iso:country":"ID",
    "wof:name":"Tidarunan",
    "wof:placetype":"locality"
},
  "geometry": {"coordinates":[110.23056,-7.49389],"type":"Point"}
}