{
  "type": "Feature",
  "properties": {
    "gn:admin1_code":"29.0",
    "gn:asciiname":"Sopi",
    "gn:country_code":"ID",
    "gn:dem":39,
    "gn:feature_class":"P",
    "gn:feature_code":"PPL",
    "gn:name":"Sopi",
    "gn:population":0,
    "gn:timezone":"Asia/Jayapura",
    "iso:country":"ID",
    "name:ind_x_preferred":[
        "Sopi"
    ],
    "wof:name":"Sopi",
    "wof:placetype":"locality"
},
  "geometry": {"coordinates":[128.52751000000001,2.57682],"type":"Point"}
}