{
  "type": "Feature",
  "properties": {
    "gn:admin1_code":"7",
    "gn:asciiname":"Patian",
    "gn:country_code":"ID",
    "gn:dem":22,
    "gn:feature_class":"P",
    "gn:feature_code":"PPL",
    "gn:name":"Patian",
    "gn:population":0,
    "gn:timezone":"Asia/Jakarta",
    "iso:country":"ID",
    "name:ind_x_preferred":[
        "Patian"
    ],
    "wof:name":"Patian",
    "wof:placetype":"locality"
},
  "geometry": {"coordinates":[110.90940000000001,-6.7914],"type":"Point"}
}