{
  "type": "Feature",
  "properties": {
    "gn:admin1_code":"1",
    "gn:asciiname":"Pekan Air Joman",
    "gn:country_code":"ID",
    "gn:dem":11,
    "gn:feature_class":"P",
    "gn:feature_code":"PPL",
    "gn:name":"Pekan Air Joman",
    "gn:population":0,
    "gn:timezone":"Asia/Jakarta",
    "iso:country":"ID",
    "name:ind_x_preferred":[
        "Pekan Air Joman"
    ],
    "wof:name":"Pekan Air Joman",
    "wof:placetype":"locality"
},
  "geometry": {"coordinates":[99.7317,2.9938],"type":"Point"}
}