{
  "type": "Feature",
  "properties": {
    "gn:admin1_code":"30.0",
    "gn:asciiname":"Belembeng",
    "gn:country_code":"ID",
    "gn:dem":42,
    "gn:feature_class":"P",
    "gn:feature_code":"PPL",
    "gn:name":"Belembeng",
    "gn:population":0,
    "gn:timezone":"Asia/Jakarta",
    "iso:country":"ID",
    "name:ind_x_preferred":[
        "Belembeng"
    ],
    "name:und_x_variant":[
        "Belengbeng"
    ],
    "wof:name":"Belembeng",
    "wof:placetype":"locality"
},
  "geometry": {"coordinates":[107.24379999999999,-7.4678],"type":"Point"}
}