{
  "type": "Feature",
  "properties": {
    "gn:admin1_code":"30.0",
    "gn:asciiname":"Cisanggar",
    "gn:country_code":"ID",
    "gn:dem":99,
    "gn:feature_class":"P",
    "gn:feature_code":"PPL",
    "gn:name":"Cisanggar",
    "gn:population":0,
    "gn:timezone":"Asia/Jakarta",
    "iso:country":"ID",
    "name:ind_x_preferred":[
        "Cisanggar"
    ],
    "name:und_x_variant":[
        "Tjisanggar",
        "Cisanggar"
    ],
    "wof:name":"Cisanggar",
    "wof:placetype":"locality"
},
  "geometry": {"coordinates":[107.9324,-7.6784],"type":"Point"}
}