{
  "type": "Feature",
  "properties": {
    "gn:admin1_code":"0.0",
    "gn:asciiname":"Kutakatinah",
    "gn:cc2":"ID",
    "gn:country_code":"ID",
    "gn:dem":207,
    "gn:feature_class":"P",
    "gn:feature_code":"PPL",
    "gn:name":"Kutakatinah",
    "gn:population":0,
    "gn:timezone":"Asia/Makassar",
    "iso:country":"ID",
    "name:und_x_variant":[
        "Koetakatinah",
        "Kutakatinah"
    ],
    "wof:name":"Kutakatinah",
    "wof:placetype":"locality"
},
  "geometry": {"coordinates":[120.65000000000001,-10.08333],"type":"Point"}
}