{
  "type": "Feature",
  "properties": {
    "gn:admin1_code":"26",
    "gn:asciiname":"Pondok Rawa",
    "gn:country_code":"ID",
    "gn:dem":15,
    "gn:feature_class":"P",
    "gn:feature_code":"PPL",
    "gn:name":"Pondok Rawa",
    "gn:population":0,
    "gn:timezone":"Asia/Jakarta",
    "iso:country":"ID",
    "name:ind_x_preferred":[
        "Pondok Rawa"
    ],
    "wof:name":"Pondok Rawa",
    "wof:placetype":"locality"
},
  "geometry": {"coordinates":[98.73739999999999,3.6372],"type":"Point"}
}