{
  "type": "Feature",
  "properties": {
    "gn:admin1_code":"33.0",
    "gn:asciiname":"Ciasem",
    "gn:country_code":"ID",
    "gn:dem":179,
    "gn:feature_class":"P",
    "gn:feature_code":"PPL",
    "gn:name":"Ciasem",
    "gn:population":0,
    "gn:timezone":"Asia/Jakarta",
    "iso:country":"ID",
    "name:ind_x_preferred":[
        "Ciasem"
    ],
    "wof:name":"Ciasem",
    "wof:placetype":"locality"
},
  "geometry": {"coordinates":[106.06950000000001,-6.2004],"type":"Point"}
}