{
  "type": "Feature",
  "properties": {
    "gn:admin1_code":"33.0",
    "gn:asciiname":"Pasirgadung",
    "gn:country_code":"ID",
    "gn:dem":96,
    "gn:feature_class":"P",
    "gn:feature_code":"PPL",
    "gn:name":"Pasirgadung",
    "gn:population":0,
    "gn:timezone":"Asia/Jakarta",
    "iso:country":"ID",
    "name:ind_x_preferred":[
        "Pasirgadung"
    ],
    "wof:name":"Pasirgadung",
    "wof:placetype":"locality"
},
  "geometry": {"coordinates":[106.09950000000001,-6.1287],"type":"Point"}
}