{
  "type": "Feature",
  "properties": {
    "gn:admin1_code":"8",
    "gn:asciiname":"Ledok",
    "gn:country_code":"ID",
    "gn:dem":997,
    "gn:feature_class":"P",
    "gn:feature_code":"PPL",
    "gn:name":"Ledok",
    "gn:population":0,
    "gn:timezone":"Asia/Jakarta",
    "iso:country":"ID",
    "name:ind_x_preferred":[
        "Ledok"
    ],
    "wof:name":"Ledok",
    "wof:placetype":"locality"
},
  "geometry": {"coordinates":[113.15560000000001,-7.9878],"type":"Point"}
}