{
  "type": "Feature",
  "properties": {
    "gn:admin1_code":"24",
    "gn:asciiname":"Sinurut",
    "gn:country_code":"ID",
    "gn:dem":565,
    "gn:feature_class":"P",
    "gn:feature_code":"PPL",
    "gn:name":"Sinurut",
    "gn:population":0,
    "gn:timezone":"Asia/Jakarta",
    "iso:country":"ID",
    "name:ind_x_preferred":[
        "Sinurut"
    ],
    "wof:name":"Sinurut",
    "wof:placetype":"locality"
},
  "geometry": {"coordinates":[99.9619,0.2402],"type":"Point"}
}