{
  "type": "Feature",
  "properties": {
    "gn:admin1_code":"30",
    "gn:asciiname":"Babakan Sukasari",
    "gn:country_code":"ID",
    "gn:dem":816,
    "gn:feature_class":"P",
    "gn:feature_code":"PPL",
    "gn:name":"Babakan Sukasari",
    "gn:population":0,
    "gn:timezone":"Asia/Jakarta",
    "iso:country":"ID",
    "name:ind_x_preferred":[
        "Babakan Sukasari"
    ],
    "wof:name":"Babakan Sukasari",
    "wof:placetype":"locality"
},
  "geometry": {"coordinates":[107.78722,-6.91389],"type":"Point"}
}