{
  "type": "Feature",
  "properties": {
    "gn:admin1_code":"30",
    "gn:asciiname":"Wanakaya",
    "gn:country_code":"ID",
    "gn:dem":7,
    "gn:feature_class":"P",
    "gn:feature_code":"PPL",
    "gn:name":"Wanakaya",
    "gn:population":0,
    "gn:timezone":"Asia/Jakarta",
    "iso:country":"ID",
    "name:ind_x_preferred":[
        "Wanakaya"
    ],
    "wof:name":"Wanakaya",
    "wof:placetype":"locality"
},
  "geometry": {"coordinates":[108.5373,-6.6656],"type":"Point"}
}