{
  "type": "Feature",
  "properties": {
    "gn:admin1_code":"7.0",
    "gn:asciiname":"Arjosari",
    "gn:country_code":"ID",
    "gn:dem":522,
    "gn:feature_class":"P",
    "gn:feature_code":"PPL",
    "gn:name":"Arjosari",
    "gn:population":0,
    "gn:timezone":"Asia/Jakarta",
    "iso:country":"ID",
    "wof:name":"Arjosari",
    "wof:placetype":"locality"
},
  "geometry": {"coordinates":[110.3725,-7.62833],"type":"Point"}
}