{
  "type": "Feature",
  "properties": {
    "gn:admin1_code":"0.0",
    "gn:asciiname":"Kualapesaguan",
    "gn:cc2":"ID",
    "gn:country_code":"ID",
    "gn:dem":7,
    "gn:feature_class":"P",
    "gn:feature_code":"PPL",
    "gn:name":"Kualapesaguan",
    "gn:population":0,
    "gn:timezone":"Asia/Pontianak",
    "iso:country":"ID",
    "name:und_x_variant":[
        "Koealapesagoean",
        "Koealdpesagoean",
        "Koewala Pesagoewan",
        "Kualapesaguan"
    ],
    "wof:name":"Kualapesaguan",
    "wof:placetype":"locality"
},
  "geometry": {"coordinates":[110.13333,-2.01667],"type":"Point"}
}