{
  "type": "Feature",
  "properties": {
    "gn:admin1_code":"8.0",
    "gn:asciiname":"Sonosekar",
    "gn:country_code":"ID",
    "gn:dem":492,
    "gn:feature_class":"P",
    "gn:feature_code":"PPL",
    "gn:name":"Sonosekar",
    "gn:population":0,
    "gn:timezone":"Asia/Jakarta",
    "iso:country":"ID",
    "name:ind_x_preferred":[
        "Sonosekar"
    ],
    "wof:name":"Sonosekar",
    "wof:placetype":"locality"
},
  "geometry": {"coordinates":[112.8575,-8.2462],"type":"Point"}
}