{
  "type": "Feature",
  "properties": {
    "gn:admin1_code":"18.0",
    "gn:asciiname":"Oeauba",
    "gn:country_code":"ID",
    "gn:dem":599,
    "gn:feature_class":"P",
    "gn:feature_code":"PPL",
    "gn:name":"Oeauba",
    "gn:population":0,
    "gn:timezone":"Asia/Makassar",
    "iso:country":"ID",
    "name:ind_x_preferred":[
        "Oeauba"
    ],
    "wof:name":"Oeauba",
    "wof:placetype":"locality"
},
  "geometry": {"coordinates":[124.3356,-9.9851],"type":"Point"}
}