{
  "type": "Feature",
  "properties": {
    "gn:admin1_code":"38",
    "gn:asciiname":"Mambo",
    "gn:country_code":"ID",
    "gn:dem":94,
    "gn:feature_class":"P",
    "gn:feature_code":"PPL",
    "gn:name":"Mambo",
    "gn:population":0,
    "gn:timezone":"Asia/Makassar",
    "iso:country":"ID",
    "name:bre_x_preferred":[
        "Mambo"
    ],
    "name:ceb_x_preferred":[
        "Mambo"
    ],
    "name:dan_x_preferred":[
        "Mambo"
    ],
    "name:deu_x_preferred":[
        "Mambo"
    ],
    "name:fin_x_preferred":[
        "Mambo"
    ],
    "name:fra_x_preferred":[
        "Mambo"
    ],
    "name:hun_x_preferred":[
        "Mamb\u00f3"
    ],
    "name:ind_x_preferred":[
        "Mambo"
    ],
    "name:ita_x_preferred":[
        "Mambo"
    ],
    "name:nld_x_preferred":[
        "Mambo"
    ],
    "name:pol_x_preferred":[
        "Mambo"
    ],
    "name:swe_x_preferred":[
        "Mambo"
    ],
    "name:tha_x_preferred":[
        "\u0e41\u0e21\u0e21\u0e42\u0e1a"
    ],
    "name:tur_x_preferred":[
        "Mambo"
    ],
    "wof:name":"Mambo",
    "wof:placetype":"locality"
},
  "geometry": {"coordinates":[120.3168,-2.5211],"type":"Point"}
}