{
  "type": "Feature",
  "properties": {
    "gn:admin1_code":"30.0",
    "gn:asciiname":"Cihayam",
    "gn:country_code":"ID",
    "gn:dem":554,
    "gn:feature_class":"P",
    "gn:feature_code":"PPLA4",
    "gn:name":"Cihayam",
    "gn:population":0,
    "gn:timezone":"Asia/Jakarta",
    "iso:country":"ID",
    "name:ind_x_preferred":[
        "Cihayam"
    ],
    "wof:lang_x_official":[
        "ind"
    ],
    "wof:lang_x_spoken":[
        "ind",
        "eng"
    ],
    "wof:name":"Cihayam",
    "wof:placetype":"locality"
},
  "geometry": {"coordinates":[108.01949999999999,-7.0079],"type":"Point"}
}