{
  "type": "Feature",
  "properties": {
    "gn:admin1_code":"33.0",
    "gn:asciiname":"Tetekole",
    "gn:country_code":"ID",
    "gn:dem":105,
    "gn:feature_class":"P",
    "gn:feature_code":"PPL",
    "gn:name":"Tetekole",
    "gn:population":0,
    "gn:timezone":"Asia/Jakarta",
    "iso:country":"ID",
    "name:ind_x_preferred":[
        "Tetekole"
    ],
    "name:und_x_variant":[
        "Tektekkole"
    ],
    "wof:lang_x_official":[
        "ind"
    ],
    "wof:lang_x_spoken":[
        "ind",
        "eng"
    ],
    "wof:name":"Tetekole",
    "wof:placetype":"locality"
},
  "geometry": {"coordinates":[105.9543,-6.4071],"type":"Point"}
}