{
  "type": "Feature",
  "properties": {
    "gn:admin1_code":"8",
    "gn:asciiname":"Pasinan",
    "gn:country_code":"ID",
    "gn:dem":29,
    "gn:feature_class":"P",
    "gn:feature_code":"PPL",
    "gn:name":"Pasinan",
    "gn:population":0,
    "gn:timezone":"Asia/Jakarta",
    "iso:country":"ID",
    "name:ind_x_preferred":[
        "Pasinan"
    ],
    "wof:name":"Pasinan",
    "wof:placetype":"locality"
},
  "geometry": {"coordinates":[112.0994,-7.1238],"type":"Point"}
}