{
  "type": "Feature",
  "properties": {
    "gn:admin1_code":"7",
    "gn:asciiname":"Kecubung",
    "gn:country_code":"ID",
    "gn:dem":157,
    "gn:feature_class":"P",
    "gn:feature_code":"PPL",
    "gn:name":"Kecubung",
    "gn:population":0,
    "gn:timezone":"Asia/Jakarta",
    "iso:country":"ID",
    "name:ind_x_preferred":[
        "Kecubung"
    ],
    "wof:name":"Kecubung",
    "wof:placetype":"locality"
},
  "geometry": {"coordinates":[109.8768,-6.9573],"type":"Point"}
}