{
  "type": "Feature",
  "properties": {
    "gn:admin1_code":"18.0",
    "gn:asciiname":"Neob",
    "gn:country_code":"ID",
    "gn:dem":242,
    "gn:feature_class":"P",
    "gn:feature_code":"PPLA4",
    "gn:name":"Neob",
    "gn:population":0,
    "gn:timezone":"Asia/Makassar",
    "iso:country":"ID",
    "name:ind_x_preferred":[
        "Neob"
    ],
    "wof:name":"Neob",
    "wof:placetype":"locality"
},
  "geometry": {"coordinates":[124.59780000000001,-9.6086],"type":"Point"}
}