{
  "type": "Feature",
  "properties": {
    "gn:admin1_code":"30",
    "gn:asciiname":"Satus Dua",
    "gn:country_code":"ID",
    "gn:dem":278,
    "gn:feature_class":"P",
    "gn:feature_code":"PPL",
    "gn:name":"Satus Dua",
    "gn:population":0,
    "gn:timezone":"Asia/Jakarta",
    "iso:country":"ID",
    "name:ind_x_preferred":[
        "Satus Dua"
    ],
    "wof:name":"Satus Dua",
    "wof:placetype":"locality"
},
  "geometry": {"coordinates":[107.07222,-6.51361],"type":"Point"}
}