{
  "type": "Feature",
  "properties": {
    "gn:admin1_code":"30.0",
    "gn:asciiname":"Kopeng",
    "gn:country_code":"ID",
    "gn:dem":538,
    "gn:feature_class":"P",
    "gn:feature_code":"PPL",
    "gn:name":"Kopeng",
    "gn:population":0,
    "gn:timezone":"Asia/Jakarta",
    "iso:country":"ID",
    "name:ind_x_preferred":[
        "Kopeng"
    ],
    "name:jav_x_preferred":[
        "Kop\u00e8ng"
    ],
    "name:nld_x_preferred":[
        "Kopeng"
    ],
    "wof:lang_x_official":[
        "ind"
    ],
    "wof:lang_x_spoken":[
        "ind",
        "eng"
    ],
    "wof:name":"Kopeng",
    "wof:placetype":"locality"
},
  "geometry": {"coordinates":[107.59180000000001,-7.4342],"type":"Point"}
}