{
  "type": "Feature",
  "properties": {
    "gn:admin1_code":"8",
    "gn:asciiname":"Borogragal Kidul",
    "gn:country_code":"ID",
    "gn:dem":846,
    "gn:feature_class":"P",
    "gn:feature_code":"PPL",
    "gn:name":"Borogragal Kidul",
    "gn:population":0,
    "gn:timezone":"Asia/Jakarta",
    "iso:country":"ID",
    "name:ind_x_preferred":[
        "Borogragal Kidul"
    ],
    "wof:name":"Borogragal Kidul",
    "wof:placetype":"locality"
},
  "geometry": {"coordinates":[112.5783,-7.8565],"type":"Point"}
}