{
  "type": "Feature",
  "properties": {
    "gn:admin1_code":"07",
    "gn:asciiname":"Jumbleng",
    "gn:country_code":"ID",
    "gn:dem":644,
    "gn:feature_class":"P",
    "gn:feature_code":"PPL",
    "gn:name":"Jumbleng",
    "gn:population":0,
    "gn:timezone":"Asia/Jakarta",
    "iso:country":"ID",
    "name:und_x_variant":[
        "Djumbleng 2",
        "Jumbleng Dua",
        "Jumbleng"
    ],
    "wof:lang_x_official":[
        "ind"
    ],
    "wof:lang_x_spoken":[
        "ind",
        "eng"
    ],
    "wof:name":"Jumbleng",
    "wof:placetype":"locality"
},
  "geometry": {"coordinates":[110.55472,-7.48528],"type":"Point"}
}