{
  "type": "Feature",
  "properties": {
    "gn:admin1_code":"24",
    "gn:asciiname":"Saibisamukop Dua",
    "gn:country_code":"ID",
    "gn:dem":34,
    "gn:feature_class":"P",
    "gn:feature_code":"PPL",
    "gn:name":"Saibisamukop Dua",
    "gn:population":0,
    "gn:timezone":"Asia/Jakarta",
    "iso:country":"ID",
    "name:ind_x_preferred":[
        "Saibisamukop 2"
    ],
    "name:ind_x_variant":[
        "Saibisamukop Dua"
    ],
    "wof:lang_x_official":[
        "ind"
    ],
    "wof:lang_x_spoken":[
        "ind",
        "eng"
    ],
    "wof:name":"Saibisamukop Dua",
    "wof:placetype":"locality"
},
  "geometry": {"coordinates":[99.04178,-1.35702],"type":"Point"}
}