{
  "type": "Feature",
  "properties": {
    "gn:admin1_code":"7.0",
    "gn:asciiname":"Retakemiri",
    "gn:country_code":"ID",
    "gn:dem":330,
    "gn:feature_class":"P",
    "gn:feature_code":"PPL",
    "gn:name":"Retakemiri",
    "gn:population":0,
    "gn:timezone":"Asia/Jakarta",
    "iso:country":"ID",
    "name:ind_x_preferred":[
        "Retakemiri"
    ],
    "wof:name":"Retakemiri",
    "wof:placetype":"locality"
},
  "geometry": {"coordinates":[109.48027999999999,-7.26611],"type":"Point"}
}