{
  "type": "Feature",
  "properties": {
    "gn:admin1_code":"30.0",
    "gn:asciiname":"Honjar",
    "gn:country_code":"ID",
    "gn:dem":449,
    "gn:feature_class":"P",
    "gn:feature_code":"PPL",
    "gn:name":"Honjar",
    "gn:population":0,
    "gn:timezone":"Asia/Jakarta",
    "iso:country":"ID",
    "name:ind_x_preferred":[
        "Honjar"
    ],
    "wof:name":"Honjar",
    "wof:placetype":"locality"
},
  "geometry": {"coordinates":[108.4615,-7.2021],"type":"Point"}
}