{
  "type": "Feature",
  "properties": {
    "gn:admin1_code":"7",
    "gn:asciiname":"Gerung",
    "gn:country_code":"ID",
    "gn:dem":25,
    "gn:feature_class":"P",
    "gn:feature_code":"PPL",
    "gn:name":"Gerung",
    "gn:population":0,
    "gn:timezone":"Asia/Jakarta",
    "iso:country":"ID",
    "name:ind_x_preferred":[
        "Gerung"
    ],
    "name:jav_x_preferred":[
        "Gerung"
    ],
    "name:msa_x_preferred":[
        "Gerung"
    ],
    "name:nld_x_preferred":[
        "Gerung"
    ],
    "name:ukr_x_preferred":[
        "\u0413\u0435\u0440\u0443\u043d\u0433"
    ],
    "wof:name":"Gerung",
    "wof:placetype":"locality"
},
  "geometry": {"coordinates":[110.7961,-6.7722],"type":"Point"}
}