{
  "type": "Feature",
  "properties": {
    "gn:admin1_code":"30",
    "gn:asciiname":"Langgar",
    "gn:country_code":"ID",
    "gn:dem":11,
    "gn:feature_class":"P",
    "gn:feature_code":"PPL",
    "gn:name":"Langgar",
    "gn:population":0,
    "gn:timezone":"Asia/Jakarta",
    "iso:country":"ID",
    "name:ind_x_preferred":[
        "Langgar"
    ],
    "wof:name":"Langgar",
    "wof:placetype":"locality"
},
  "geometry": {"coordinates":[108.40056,-6.46944],"type":"Point"}
}