{
  "type": "Feature",
  "properties": {
    "gn:admin1_code":"0.0",
    "gn:asciiname":"Ria",
    "gn:country_code":"ID",
    "gn:dem":275,
    "gn:feature_class":"P",
    "gn:feature_code":"PPL",
    "gn:name":"Ria",
    "gn:population":0,
    "gn:timezone":"Asia/Makassar",
    "iso:country":"ID",
    "name:ara_x_preferred":[
        "\u0648\u0627\u062f \u0645\u063a\u0645\u0648\u0631"
    ],
    "name:ast_x_preferred":[
        "R\u00eda"
    ],
    "name:aze_x_preferred":[
        "Ria"
    ],
    "name:bel_x_preferred":[
        "\u0420\u044b\u044f\u0441"
    ],
    "name:bre_x_preferred":[
        "Aber"
    ],
    "name:cat_x_preferred":[
        "Ria"
    ],
    "name:deu_x_preferred":[
        "Ria"
    ],
    "name:ell_x_preferred":[
        "\u0393\u03b1\u03bb\u03b9\u03ba\u03b9\u03b1\u03bd\u03ae \u03b1\u03ba\u03c4\u03ae"
    ],
    "name:epo_x_preferred":[
        "Rio"
    ],
    "name:est_x_preferred":[
        "Riasrannik"
    ],
    "name:eus_x_preferred":[
        "Itsasadar"
    ],
    "name:fra_x_preferred":[
        "Aber"
    ],
    "name:glg_x_preferred":[
        "R\u00eda"
    ],
    "name:hrv_x_preferred":[
        "Rijas"
    ],
    "name:hun_x_preferred":[
        "Ria"
    ],
    "name:ind_x_preferred":[
        "Ria"
    ],
    "name:ita_x_preferred":[
        "R\u00eda"
    ],
    "name:jpn_x_preferred":[
        "\u6eba\u308c\u8c37"
    ],
    "name:kat_x_preferred":[
        "\u10e0\u10d8\u10d0"
    ],
    "name:kbd_x_preferred":[
        "\u0420\u0438\u044d"
    ],
    "name:kor_x_preferred":[
        "\ub9ac\uc544\uc2a4\uc2dd \ud574\uc548"
    ],
    "name:lat_x_preferred":[
        "Ria"
    ],
    "name:nld_x_preferred":[
        "R\u00eda"
    ],
    "name:nor_x_preferred":[
        "Ria"
    ],
    "name:oci_x_preferred":[
        "Ria"
    ],
    "name:pol_x_preferred":[
        "Wybrze\u017ce riasowe"
    ],
    "name:por_x_preferred":[
        "Ria"
    ],
    "name:rus_x_preferred":[
        "\u0420\u0438\u0430"
    ],
    "name:slv_x_preferred":[
        "Rias"
    ],
    "name:spa_x_preferred":[
        "R\u00eda"
    ],
    "name:sqi_x_preferred":[
        "Riasi"
    ],
    "name:srp_x_preferred":[
        "\u0420\u0438\u0458\u0430\u0441"
    ],
    "name:swe_x_preferred":[
        "Ria"
    ],
    "name:tat_x_preferred":[
        "\u0420\u0438\u0430\u0441"
    ],
    "name:tur_x_preferred":[
        "Ria"
    ],
    "name:ukr_x_preferred":[
        "\u0420\u0456\u0430"
    ],
    "wof:lang_x_official":[
        "ind"
    ],
    "wof:lang_x_spoken":[
        "ind",
        "eng"
    ],
    "wof:name":"Ria",
    "wof:placetype":"locality"
},
  "geometry": {"coordinates":[120.98333,-8.45],"type":"Point"}
}