{
  "type": "Feature",
  "properties": {
    "gn:admin1_code":"10.0",
    "gn:asciiname":"Luwengombo",
    "gn:country_code":"ID",
    "gn:dem":202,
    "gn:feature_class":"P",
    "gn:feature_code":"PPL",
    "gn:name":"Luwengombo",
    "gn:population":0,
    "gn:timezone":"Asia/Jakarta",
    "iso:country":"ID",
    "name:ind_x_preferred":[
        "Luwengombo"
    ],
    "wof:name":"Luwengombo",
    "wof:placetype":"locality"
},
  "geometry": {"coordinates":[110.67667,-8.15444],"type":"Point"}
}