{
  "type": "Feature",
  "properties": {
    "gn:admin1_code":"18.0",
    "gn:asciiname":"Liangdalo Satu",
    "gn:country_code":"ID",
    "gn:dem":204,
    "gn:feature_class":"P",
    "gn:feature_code":"PPL",
    "gn:name":"Liangdalo Satu",
    "gn:population":0,
    "gn:timezone":"Asia/Makassar",
    "iso:country":"ID",
    "name:ind_x_preferred":[
        "Liangdalo Satu"
    ],
    "wof:name":"Liangdalo Satu",
    "wof:placetype":"locality"
},
  "geometry": {"coordinates":[120.61579999999999,-8.393],"type":"Point"}
}