{
  "type": "Feature",
  "properties": {
    "gn:admin1_code":"7.0",
    "gn:asciiname":"Narukan",
    "gn:country_code":"ID",
    "gn:dem":24,
    "gn:feature_class":"P",
    "gn:feature_code":"PPLA4",
    "gn:name":"Narukan",
    "gn:population":0,
    "gn:timezone":"Asia/Jakarta",
    "iso:country":"ID",
    "name:ind_x_preferred":[
        "Narukan"
    ],
    "wof:name":"Narukan",
    "wof:placetype":"locality"
},
  "geometry": {"coordinates":[111.5826,-6.6943],"type":"Point"}
}