{
  "type": "Feature",
  "properties": {
    "gn:admin1_code":"38",
    "gn:asciiname":"Limpunoang",
    "gn:country_code":"ID",
    "gn:dem":197,
    "gn:feature_class":"P",
    "gn:feature_code":"PPL",
    "gn:name":"Limpunoang",
    "gn:population":0,
    "gn:timezone":"Asia/Makassar",
    "iso:country":"ID",
    "name:ind_x_preferred":[
        "Limpunoang"
    ],
    "wof:name":"Limpunoang",
    "wof:placetype":"locality"
},
  "geometry": {"coordinates":[120.1763,-4.501],"type":"Point"}
}