{
  "type": "Feature",
  "properties": {
    "gn:admin1_code":"8.0",
    "gn:asciiname":"Buktana Timur",
    "gn:country_code":"ID",
    "gn:dem":90,
    "gn:feature_class":"P",
    "gn:feature_code":"PPL",
    "gn:name":"Buktana Timur",
    "gn:population":0,
    "gn:timezone":"Asia/Jakarta",
    "iso:country":"ID",
    "name:ind_x_preferred":[
        "Buktana Timur"
    ],
    "name:und_x_variant":[
        "Buktama Timur"
    ],
    "wof:name":"Buktana Timur",
    "wof:placetype":"locality"
},
  "geometry": {"coordinates":[113.37050000000001,-7.0518],"type":"Point"}
}