{
  "type": "Feature",
  "properties": {
    "gn:admin1_code":"10",
    "gn:asciiname":"Sladi",
    "gn:country_code":"ID",
    "gn:dem":230,
    "gn:feature_class":"P",
    "gn:feature_code":"PPL",
    "gn:name":"Sladi",
    "gn:population":0,
    "gn:timezone":"Asia/Jakarta",
    "iso:country":"ID",
    "wof:name":"Sladi",
    "wof:placetype":"locality"
},
  "geometry": {"coordinates":[110.72499999999999,-7.94806],"type":"Point"}
}