{
  "type": "Feature",
  "properties": {
    "gn:admin1_code":"42.0",
    "gn:asciiname":"Long Pujungan",
    "gn:country_code":"ID",
    "gn:dem":254,
    "gn:feature_class":"P",
    "gn:feature_code":"PPLA3",
    "gn:name":"Long Pujungan",
    "gn:population":0,
    "gn:timezone":"Asia/Makassar",
    "iso:country":"ID",
    "name:ind_x_preferred":[
        "Long Pujungan"
    ],
    "name:und_x_variant":[
        "Pudjungan",
        "Poedjoengan",
        "Longpoedjoegan",
        "Longpudjungan",
        "Longpujungan"
    ],
    "wof:lang_x_official":[
        "ind"
    ],
    "wof:lang_x_spoken":[
        "ind",
        "eng"
    ],
    "wof:name":"Long Pujungan",
    "wof:placetype":"locality"
},
  "geometry": {"coordinates":[115.79478,2.58769],"type":"Point"}
}