{
  "type": "Feature",
  "properties": {
    "gn:admin1_code":"7",
    "gn:asciiname":"Ngadirejo",
    "gn:country_code":"ID",
    "gn:dem":856,
    "gn:feature_class":"P",
    "gn:feature_code":"PPL",
    "gn:name":"Ngadirejo",
    "gn:population":0,
    "gn:timezone":"Asia/Jakarta",
    "iso:country":"ID",
    "name:ind_x_preferred":[
        "Ngadirejo"
    ],
    "wof:name":"Ngadirejo",
    "wof:placetype":"locality"
},
  "geometry": {"coordinates":[109.8704,-7.1029],"type":"Point"}
}