{
  "type": "Feature",
  "properties": {
    "gn:admin1_code":"22.0",
    "gn:asciiname":"Benteng",
    "gn:country_code":"ID",
    "gn:dem":19,
    "gn:feature_class":"P",
    "gn:feature_code":"PPL",
    "gn:name":"Benteng",
    "gn:population":0,
    "gn:timezone":"Asia/Makassar",
    "iso:country":"ID",
    "name:ind_x_preferred":[
        "Benteng"
    ],
    "wof:name":"Benteng",
    "wof:placetype":"locality"
},
  "geometry": {"coordinates":[122.67829999999999,-5.392],"type":"Point"}
}