{
  "type": "Feature",
  "properties": {
    "gn:admin1_code":"17.0",
    "gn:asciiname":"Mpuriwau",
    "gn:country_code":"ID",
    "gn:dem":17,
    "gn:feature_class":"P",
    "gn:feature_code":"PPL",
    "gn:name":"Mpuriwau",
    "gn:population":0,
    "gn:timezone":"Asia/Makassar",
    "iso:country":"ID",
    "name:ind_x_preferred":[
        "Mpuriwau"
    ],
    "wof:name":"Mpuriwau",
    "wof:placetype":"locality"
},
  "geometry": {"coordinates":[119.008,-8.5295],"type":"Point"}
}