{
  "type": "Feature",
  "properties": {
    "gn:admin1_code":"13.0",
    "gn:asciiname":"Liangnjaling",
    "gn:country_code":"ID",
    "gn:dem":118,
    "gn:feature_class":"P",
    "gn:feature_code":"PPL",
    "gn:name":"Liangnjaling",
    "gn:population":0,
    "gn:timezone":"Asia/Pontianak",
    "iso:country":"ID",
    "name:ind_x_preferred":[
        "Liangnjaling"
    ],
    "wof:name":"Liangnjaling",
    "wof:placetype":"locality"
},
  "geometry": {"coordinates":[114.97035,-0.42933],"type":"Point"}
}