{
  "type": "Feature",
  "properties": {
    "gn:admin1_code":"30.0",
    "gn:asciiname":"Saapan",
    "gn:country_code":"ID",
    "gn:dem":492,
    "gn:feature_class":"P",
    "gn:feature_code":"PPL",
    "gn:name":"Saapan",
    "gn:population":0,
    "gn:timezone":"Asia/Jakarta",
    "iso:country":"ID",
    "name:ind_x_preferred":[
        "Saapan"
    ],
    "name:und_x_variant":[
        "Sa\u2018apan"
    ],
    "wof:lang_x_official":[
        "ind"
    ],
    "wof:lang_x_spoken":[
        "ind",
        "eng"
    ],
    "wof:name":"Saapan",
    "wof:placetype":"locality"
},
  "geometry": {"coordinates":[108.00369999999999,-7.042],"type":"Point"}
}