{
  "type": "Feature",
  "properties": {
    "gn:admin1_code":"8.0",
    "gn:asciiname":"Plalangan",
    "gn:country_code":"ID",
    "gn:dem":187,
    "gn:feature_class":"P",
    "gn:feature_code":"PPL",
    "gn:name":"Plalangan",
    "gn:population":0,
    "gn:timezone":"Asia/Jakarta",
    "iso:country":"ID",
    "name:ind_x_preferred":[
        "Plalangan"
    ],
    "wof:name":"Plalangan",
    "wof:placetype":"locality"
},
  "geometry": {"coordinates":[113.9444,-7.8512],"type":"Point"}
}