{
  "type": "Feature",
  "properties": {
    "gn:admin1_code":"30",
    "gn:asciiname":"Cantel",
    "gn:country_code":"ID",
    "gn:dem":746,
    "gn:feature_class":"P",
    "gn:feature_code":"PPL",
    "gn:name":"Cantel",
    "gn:population":0,
    "gn:timezone":"Asia/Jakarta",
    "iso:country":"ID",
    "name:ceb_x_preferred":[
        "Cantel"
    ],
    "name:ind_x_preferred":[
        "Cantel"
    ],
    "name:swe_x_preferred":[
        "Cantel"
    ],
    "wof:lang_x_official":[
        "ind"
    ],
    "wof:lang_x_spoken":[
        "ind",
        "eng"
    ],
    "wof:name":"Cantel",
    "wof:placetype":"locality"
},
  "geometry": {"coordinates":[107.8428,-7.0077],"type":"Point"}
}