{
  "type": "Feature",
  "properties": {
    "gn:admin1_code":"17",
    "gn:asciiname":"Sumbek",
    "gn:country_code":"ID",
    "gn:dem":320,
    "gn:feature_class":"P",
    "gn:feature_code":"PPL",
    "gn:name":"Sumbek",
    "gn:population":0,
    "gn:timezone":"Asia/Makassar",
    "iso:country":"ID",
    "name:bih_x_preferred":[
        "\u0938\u0941\u092e\u094d\u092c\u0947\u0915"
    ],
    "name:ceb_x_preferred":[
        "Sumbek"
    ],
    "name:hin_x_preferred":[
        "\u0938\u0941\u092e\u094d\u092c\u0947\u0915"
    ],
    "name:ind_x_preferred":[
        "Sumbek"
    ],
    "name:mai_x_preferred":[
        "\u0938\u0941\u092e\u094d\u092c\u0947\u0915"
    ],
    "name:msa_x_preferred":[
        "Sumbek"
    ],
    "name:nep_x_preferred":[
        "\u0938\u0941\u092e\u094d\u092c\u0947\u0915"
    ],
    "name:new_x_preferred":[
        "\u0938\u0941\u092e\u094d\u092c\u0947\u0915"
    ],
    "name:nld_x_preferred":[
        "Sumbek"
    ],
    "name:pol_x_preferred":[
        "Sumbek"
    ],
    "wof:name":"Sumbek",
    "wof:placetype":"locality"
},
  "geometry": {"coordinates":[116.3175,-8.6453],"type":"Point"}
}