{
  "type": "Feature",
  "properties": {
    "gn:admin1_code":"30",
    "gn:asciiname":"Bunut",
    "gn:country_code":"ID",
    "gn:dem":486,
    "gn:feature_class":"P",
    "gn:feature_code":"PPL",
    "gn:name":"Bunut",
    "gn:population":0,
    "gn:timezone":"Asia/Jakarta",
    "iso:country":"ID",
    "name:ceb_x_preferred":[
        "Bunut"
    ],
    "name:ind_x_preferred":[
        "Bunut"
    ],
    "name:nld_x_preferred":[
        "Bunut"
    ],
    "name:swe_x_preferred":[
        "Bunut"
    ],
    "wof:lang_x_official":[
        "ind"
    ],
    "wof:lang_x_spoken":[
        "ind",
        "eng"
    ],
    "wof:name":"Bunut",
    "wof:placetype":"locality"
},
  "geometry": {"coordinates":[107.96944000000001,-6.83056],"type":"Point"}
}