{
  "type": "Feature",
  "properties": {
    "gn:admin1_code":"8.0",
    "gn:asciiname":"Sumberjambe",
    "gn:country_code":"ID",
    "gn:dem":229,
    "gn:feature_class":"P",
    "gn:feature_code":"PPL",
    "gn:name":"Sumberjambe",
    "gn:population":0,
    "gn:timezone":"Asia/Jakarta",
    "iso:country":"ID",
    "name:ind_x_preferred":[
        "Sumberjambe"
    ],
    "name:und_x_variant":[
        "Soemberdjambe"
    ],
    "wof:lang_x_official":[
        "ind"
    ],
    "wof:lang_x_spoken":[
        "ind",
        "eng"
    ],
    "wof:name":"Sumberjambe",
    "wof:placetype":"locality"
},
  "geometry": {"coordinates":[112.5496,-8.3482],"type":"Point"}
}