{
  "type": "Feature",
  "properties": {
    "gn:admin1_code":"7.0",
    "gn:asciiname":"Ropohbugel",
    "gn:country_code":"ID",
    "gn:dem":22,
    "gn:feature_class":"P",
    "gn:feature_code":"PPL",
    "gn:name":"Ropohbugel",
    "gn:population":0,
    "gn:timezone":"Asia/Jakarta",
    "iso:country":"ID",
    "name:ind_x_preferred":[
        "Ropohbugel"
    ],
    "wof:name":"Ropohbugel",
    "wof:placetype":"locality"
},
  "geometry": {"coordinates":[111.45399999999999,-6.7135],"type":"Point"}
}