{
  "type": "Feature",
  "properties": {
    "gn:admin1_code":"8.0",
    "gn:asciiname":"Taretah Laok",
    "gn:country_code":"ID",
    "gn:dem":114,
    "gn:feature_class":"P",
    "gn:feature_code":"PPL",
    "gn:name":"Taretah Laok",
    "gn:population":0,
    "gn:timezone":"Asia/Jakarta",
    "iso:country":"ID",
    "name:ind_x_preferred":[
        "Taretah Laok"
    ],
    "wof:name":"Taretah Laok",
    "wof:placetype":"locality"
},
  "geometry": {"coordinates":[113.51779999999999,-6.95],"type":"Point"}
}