{
  "type": "Feature",
  "properties": {
    "gn:admin1_code":"8.0",
    "gn:asciiname":"Maor",
    "gn:country_code":"ID",
    "gn:dem":92,
    "gn:feature_class":"P",
    "gn:feature_code":"PPL",
    "gn:name":"Maor",
    "gn:population":0,
    "gn:timezone":"Asia/Jakarta",
    "iso:country":"ID",
    "name:ces_x_preferred":[
        "Ma'or"
    ],
    "name:heb_x_preferred":[
        "\u05de\u05d0\u05d5\u05e8"
    ],
    "name:ind_x_preferred":[
        "Maor"
    ],
    "name:nno_x_preferred":[
        "Maor"
    ],
    "wof:lang_x_official":[
        "ind"
    ],
    "wof:lang_x_spoken":[
        "ind",
        "eng"
    ],
    "wof:name":"Maor",
    "wof:placetype":"locality"
},
  "geometry": {"coordinates":[113.8539,-6.9497],"type":"Point"}
}