{
  "type": "Feature",
  "properties": {
    "gn:admin1_code":"1",
    "gn:asciiname":"Tanjonglaling",
    "gn:country_code":"ID",
    "gn:dem":9,
    "gn:feature_class":"P",
    "gn:feature_code":"PPL",
    "gn:name":"Tanjonglaling",
    "gn:population":0,
    "gn:timezone":"Asia/Jakarta",
    "iso:country":"ID",
    "name:ind_x_preferred":[
        "Tanjonglaling"
    ],
    "name:und_x_variant":[
        "Tandjonglaling"
    ],
    "wof:name":"Tanjonglaling",
    "wof:placetype":"locality"
},
  "geometry": {"coordinates":[97.4328,5.1828],"type":"Point"}
}