{
  "type": "Feature",
  "properties": {
    "gn:admin1_code":"38",
    "gn:asciiname":"Buka",
    "gn:country_code":"ID",
    "gn:dem":1471,
    "gn:feature_class":"P",
    "gn:feature_code":"PPL",
    "gn:name":"Buka",
    "gn:population":0,
    "gn:timezone":"Asia/Makassar",
    "iso:country":"ID",
    "name:ind_x_preferred":[
        "Buka"
    ],
    "wof:name":"Buka",
    "wof:placetype":"locality"
},
  "geometry": {"coordinates":[119.7564,-3.1005],"type":"Point"}
}