{
  "type": "Feature",
  "properties": {
    "gn:admin1_code":"38",
    "gn:asciiname":"Buka",
    "gn:country_code":"ID",
    "gn:dem":1471,
    "gn:feature_class":"P",
    "gn:feature_code":"PPL",
    "gn:name":"Buka",
    "gn:population":0,
    "gn:timezone":"Asia/Makassar",
    "iso:country":"ID",
    "name:ceb_x_preferred":[
        "Buka"
    ],
    "name:deu_x_preferred":[
        "Buka"
    ],
    "name:ind_x_preferred":[
        "Buka"
    ],
    "name:nld_x_preferred":[
        "Buka"
    ],
    "name:pol_x_preferred":[
        "Buka"
    ],
    "name:rus_x_preferred":[
        "\u0411\u0443\u043a\u0430"
    ],
    "name:swe_x_preferred":[
        "Buka"
    ],
    "name:ukr_x_preferred":[
        "\u0411\u0443\u043a\u0430"
    ],
    "name:uzb_x_preferred":[
        "Bo\u02bbka"
    ],
    "wof:lang_x_official":[
        "ind"
    ],
    "wof:lang_x_spoken":[
        "ind",
        "eng"
    ],
    "wof:name":"Buka",
    "wof:placetype":"locality"
},
  "geometry": {"coordinates":[119.7564,-3.1005],"type":"Point"}
}