{
  "type": "Feature",
  "properties": {
    "gn:admin1_code":"30",
    "gn:asciiname":"Barunangka",
    "gn:country_code":"ID",
    "gn:dem":1028,
    "gn:feature_class":"P",
    "gn:feature_code":"PPL",
    "gn:name":"Barunangka",
    "gn:population":0,
    "gn:timezone":"Asia/Jakarta",
    "iso:country":"ID",
    "wof:name":"Barunangka",
    "wof:placetype":"locality"
},
  "geometry": {"coordinates":[107.58333,-7.10583],"type":"Point"}
}