{
  "type": "Feature",
  "properties": {
    "gn:admin1_code":"1",
    "gn:asciiname":"Sangir",
    "gn:country_code":"ID",
    "gn:dem":1025,
    "gn:feature_class":"P",
    "gn:feature_code":"PPL",
    "gn:name":"Sangir",
    "gn:population":0,
    "gn:timezone":"Asia/Jakarta",
    "iso:country":"ID",
    "name:eng_x_preferred":[
        "Sangir"
    ],
    "name:fra_x_preferred":[
        "Sangir"
    ],
    "name:ind_x_preferred":[
        "Sangir"
    ],
    "name:nld_x_preferred":[
        "Sangir"
    ],
    "name:und_x_variant":[
        "Sanger"
    ],
    "wof:lang_x_official":[
        "ind"
    ],
    "wof:lang_x_spoken":[
        "ind",
        "eng"
    ],
    "wof:name":"Sangir",
    "wof:placetype":"locality"
},
  "geometry": {"coordinates":[97.4079,3.9764],"type":"Point"}
}