{
  "type": "Feature",
  "properties": {
    "gn:admin1_code":"17",
    "gn:asciiname":"Daha",
    "gn:country_code":"ID",
    "gn:dem":64,
    "gn:feature_class":"P",
    "gn:feature_code":"PPL",
    "gn:name":"Daha",
    "gn:population":0,
    "gn:timezone":"Asia/Makassar",
    "iso:country":"ID",
    "name:ceb_x_preferred":[
        "Daha"
    ],
    "name:fra_x_preferred":[
        "Daha"
    ],
    "name:ind_x_preferred":[
        "Daha"
    ],
    "name:ita_x_preferred":[
        "Daha"
    ],
    "name:swe_x_preferred":[
        "Daha"
    ],
    "name:uzb_x_preferred":[
        "Daha"
    ],
    "wof:lang_x_official":[
        "ind"
    ],
    "wof:lang_x_spoken":[
        "ind",
        "eng"
    ],
    "wof:name":"Daha",
    "wof:placetype":"locality"
},
  "geometry": {"coordinates":[118.4393,-8.7479],"type":"Point"}
}