{
  "type": "Feature",
  "properties": {
    "gn:admin1_code":"18.0",
    "gn:asciiname":"Golo Menes",
    "gn:country_code":"ID",
    "gn:dem":633,
    "gn:feature_class":"P",
    "gn:feature_code":"PPLF",
    "gn:name":"Golo Menes",
    "gn:population":0,
    "gn:timezone":"Asia/Makassar",
    "iso:country":"ID",
    "wof:lang_x_official":[
        "ind"
    ],
    "wof:lang_x_spoken":[
        "ind",
        "eng"
    ],
    "wof:name":"Golo Menes",
    "wof:placetype":"locality"
},
  "geometry": {"coordinates":[120.05314,-8.61079],"type":"Point"}
}