{
  "type": "Feature",
  "properties": {
    "gn:admin1_code":"38",
    "gn:asciiname":"Ciduk",
    "gn:country_code":"ID",
    "gn:dem":12,
    "gn:feature_class":"P",
    "gn:feature_code":"PPL",
    "gn:name":"Ciduk",
    "gn:population":0,
    "gn:timezone":"Asia/Makassar",
    "iso:country":"ID",
    "name:ind_x_preferred":[
        "Ciduk"
    ],
    "wof:name":"Ciduk",
    "wof:placetype":"locality"
},
  "geometry": {"coordinates":[119.5955,-5.0598],"type":"Point"}
}