{
  "type": "Feature",
  "properties": {
    "gn:admin1_code":"7.0",
    "gn:asciiname":"Cisayun",
    "gn:country_code":"ID",
    "gn:dem":245,
    "gn:feature_class":"P",
    "gn:feature_code":"PPL",
    "gn:name":"Cisayun",
    "gn:population":0,
    "gn:timezone":"Asia/Jakarta",
    "iso:country":"ID",
    "name:ind_x_preferred":[
        "Cisayun"
    ],
    "wof:name":"Cisayun",
    "wof:placetype":"locality"
},
  "geometry": {"coordinates":[108.8497,-7.2932],"type":"Point"}
}