{
  "type": "Feature",
  "properties": {
    "gn:admin1_code":"26",
    "gn:asciiname":"Sigelgel",
    "gn:country_code":"ID",
    "gn:dem":886,
    "gn:feature_class":"P",
    "gn:feature_code":"PPL",
    "gn:name":"Sigelgel",
    "gn:population":0,
    "gn:timezone":"Asia/Jakarta",
    "iso:country":"ID",
    "name:ind_x_preferred":[
        "Sigelgel"
    ],
    "wof:name":"Sigelgel",
    "wof:placetype":"locality"
},
  "geometry": {"coordinates":[99.27531999999999,1.61655],"type":"Point"}
}