{
  "type": "Feature",
  "properties": {
    "gn:admin1_code":"7",
    "gn:asciiname":"Kebongunung",
    "gn:country_code":"ID",
    "gn:dem":467,
    "gn:feature_class":"P",
    "gn:feature_code":"PPL",
    "gn:name":"Kebongunung",
    "gn:population":0,
    "gn:timezone":"Asia/Jakarta",
    "iso:country":"ID",
    "name:ind_x_preferred":[
        "Kebongunung"
    ],
    "wof:name":"Kebongunung",
    "wof:placetype":"locality"
},
  "geometry": {"coordinates":[111.04194,-7.7075],"type":"Point"}
}