{
  "type": "Feature",
  "properties": {
    "gn:admin1_code":"30",
    "gn:asciiname":"Cibuntu",
    "gn:country_code":"ID",
    "gn:dem":399,
    "gn:feature_class":"P",
    "gn:feature_code":"PPL",
    "gn:name":"Cibuntu",
    "gn:population":0,
    "gn:timezone":"Asia/Jakarta",
    "iso:country":"ID",
    "name:ind_x_preferred":[
        "Cibuntu"
    ],
    "wof:name":"Cibuntu",
    "wof:placetype":"locality"
},
  "geometry": {"coordinates":[107.87806,-6.75722],"type":"Point"}
}