{
  "type": "Feature",
  "properties": {
    "gn:admin1_code":"18.0",
    "gn:asciiname":"Nekaen",
    "gn:country_code":"ID",
    "gn:dem":226,
    "gn:feature_class":"P",
    "gn:feature_code":"PPL",
    "gn:name":"Nekaen",
    "gn:population":0,
    "gn:timezone":"Asia/Makassar",
    "iso:country":"ID",
    "name:ind_x_preferred":[
        "Nekaen"
    ],
    "wof:name":"Nekaen",
    "wof:placetype":"locality"
},
  "geometry": {"coordinates":[123.9786,-9.9103],"type":"Point"}
}