{
  "type": "Feature",
  "properties": {
    "gn:admin1_code":"8.0",
    "gn:asciiname":"Kayuenak",
    "gn:country_code":"ID",
    "gn:dem":1026,
    "gn:feature_class":"P",
    "gn:feature_code":"PPL",
    "gn:name":"Kayuenak",
    "gn:population":0,
    "gn:timezone":"Asia/Jakarta",
    "iso:country":"ID",
    "name:ind_x_preferred":[
        "Kayuenak"
    ],
    "name:und_x_variant":[
        "Kajuenak"
    ],
    "wof:lang_x_official":[
        "ind"
    ],
    "wof:lang_x_spoken":[
        "ind",
        "eng"
    ],
    "wof:name":"Kayuenak",
    "wof:placetype":"locality"
},
  "geometry": {"coordinates":[113.054,-8.0355],"type":"Point"}
}