{
  "type": "Feature",
  "properties": {
    "gn:admin1_code":"30",
    "gn:asciiname":"Girihieum",
    "gn:cc2":"ID",
    "gn:country_code":"ID",
    "gn:dem":1160,
    "gn:feature_class":"P",
    "gn:feature_code":"PPL",
    "gn:name":"Girihieum",
    "gn:population":0,
    "gn:timezone":"Asia/Jakarta",
    "iso:country":"ID",
    "name:und_x_variant":[
        "Geurihieum",
        "Girihieum"
    ],
    "wof:lang_x_official":[
        "ind"
    ],
    "wof:lang_x_spoken":[
        "ind",
        "eng"
    ],
    "wof:name":"Girihieum",
    "wof:placetype":"locality"
},
  "geometry": {"coordinates":[107.68472,-7.13861],"type":"Point"}
}