{
  "type": "Feature",
  "properties": {
    "gn:admin1_code":"26",
    "gn:asciiname":"Hilihoya",
    "gn:country_code":"ID",
    "gn:dem":520,
    "gn:feature_class":"P",
    "gn:feature_code":"PPL",
    "gn:name":"Hilihoya",
    "gn:population":0,
    "gn:timezone":"Asia/Jakarta",
    "iso:country":"ID",
    "name:ind_x_preferred":[
        "Hilihoya"
    ],
    "name:und_x_variant":[
        "Hilihoja"
    ],
    "wof:name":"Hilihoya",
    "wof:placetype":"locality"
},
  "geometry": {"coordinates":[97.68470000000001,0.8223],"type":"Point"}
}