{
  "type": "Feature",
  "properties": {
    "gn:admin1_code":"10.0",
    "gn:asciiname":"Sidorejo",
    "gn:country_code":"ID",
    "gn:dem":207,
    "gn:feature_class":"P",
    "gn:feature_code":"PPL",
    "gn:name":"Sidorejo",
    "gn:population":0,
    "gn:timezone":"Asia/Jakarta",
    "iso:country":"ID",
    "wof:name":"Sidorejo",
    "wof:placetype":"locality"
},
  "geometry": {"coordinates":[110.45222,-7.73278],"type":"Point"}
}