{
  "type": "Feature",
  "properties": {
    "gn:admin1_code":"18",
    "gn:asciiname":"Nuamuri",
    "gn:country_code":"ID",
    "gn:dem":584,
    "gn:feature_class":"P",
    "gn:feature_code":"PPL",
    "gn:name":"Nuamuri",
    "gn:population":0,
    "gn:timezone":"Asia/Makassar",
    "iso:country":"ID",
    "name:ind_x_preferred":[
        "Nuamuri"
    ],
    "wof:name":"Nuamuri",
    "wof:placetype":"locality"
},
  "geometry": {"coordinates":[121.63200000000001,-8.7966],"type":"Point"}
}