{
  "type": "Feature",
  "properties": {
    "gn:admin1_code":"17",
    "gn:asciiname":"Mentaum",
    "gn:country_code":"ID",
    "gn:dem":347,
    "gn:feature_class":"P",
    "gn:feature_code":"PPL",
    "gn:name":"Mentaum",
    "gn:population":0,
    "gn:timezone":"Asia/Makassar",
    "iso:country":"ID",
    "name:ind_x_preferred":[
        "Mentaum"
    ],
    "wof:name":"Mentaum",
    "wof:placetype":"locality"
},
  "geometry": {"coordinates":[116.4314,-8.6283],"type":"Point"}
}