{
  "type": "Feature",
  "properties": {
    "gn:admin1_code":"18",
    "gn:asciiname":"Tawui",
    "gn:country_code":"ID",
    "gn:dem":30,
    "gn:feature_class":"P",
    "gn:feature_code":"PPLA4",
    "gn:name":"Tawui",
    "gn:population":0,
    "gn:timezone":"Asia/Makassar",
    "iso:country":"ID",
    "name:ind_x_preferred":[
        "Tawui"
    ],
    "wof:name":"Tawui",
    "wof:placetype":"locality"
},
  "geometry": {"coordinates":[120.07299999999999,-10.143],"type":"Point"}
}