{
  "type": "Feature",
  "properties": {
    "gn:admin1_code":"30",
    "gn:asciiname":"Jayasari",
    "gn:country_code":"ID",
    "gn:dem":296,
    "gn:feature_class":"P",
    "gn:feature_code":"PPL",
    "gn:name":"Jayasari",
    "gn:population":0,
    "gn:timezone":"Asia/Jakarta",
    "iso:country":"ID",
    "name:ind_x_preferred":[
        "Jayasari"
    ],
    "wof:name":"Jayasari",
    "wof:placetype":"locality"
},
  "geometry": {"coordinates":[106.80110999999999,-6.62417],"type":"Point"}
}