{
  "type": "Feature",
  "properties": {
    "gn:admin1_code":"7.0",
    "gn:asciiname":"Biru",
    "gn:country_code":"ID",
    "gn:dem":113,
    "gn:feature_class":"P",
    "gn:feature_code":"PPL",
    "gn:name":"Biru",
    "gn:population":0,
    "gn:timezone":"Asia/Jakarta",
    "iso:country":"ID",
    "name:ind_x_preferred":[
        "Biru"
    ],
    "name:ita_x_preferred":[
        "Biru"
    ],
    "name:nld_x_preferred":[
        "Biru"
    ],
    "wof:lang_x_official":[
        "ind"
    ],
    "wof:lang_x_spoken":[
        "ind",
        "eng"
    ],
    "wof:name":"Biru",
    "wof:placetype":"locality"
},
  "geometry": {"coordinates":[110.74527999999999,-7.62167],"type":"Point"}
}