{
  "type": "Feature",
  "properties": {
    "gn:admin1_code":"30",
    "gn:asciiname":"Cijarian Tengah",
    "gn:country_code":"ID",
    "gn:dem":713,
    "gn:feature_class":"P",
    "gn:feature_code":"PPL",
    "gn:name":"Cijarian Tengah",
    "gn:population":0,
    "gn:timezone":"Asia/Jakarta",
    "iso:country":"ID",
    "name:ind_x_preferred":[
        "Cijarian Tengah"
    ],
    "wof:name":"Cijarian Tengah",
    "wof:placetype":"locality"
},
  "geometry": {"coordinates":[106.92222,-6.88222],"type":"Point"}
}