{
  "type": "Feature",
  "properties": {
    "gn:admin1_code":"7.0",
    "gn:asciiname":"Larangan",
    "gn:country_code":"ID",
    "gn:dem":311,
    "gn:feature_class":"P",
    "gn:feature_code":"PPL",
    "gn:name":"Larangan",
    "gn:population":0,
    "gn:timezone":"Asia/Jakarta",
    "iso:country":"ID",
    "name:ind_x_preferred":[
        "Larangan"
    ],
    "name:jav_x_preferred":[
        "Larangan"
    ],
    "name:msa_x_preferred":[
        "Larangan"
    ],
    "name:sun_x_preferred":[
        "Larangan"
    ],
    "name:urd_x_preferred":[
        "\u0644\u0627\u0631\u0627\u0646\u06af\u0627\u0646"
    ],
    "wof:lang_x_official":[
        "ind"
    ],
    "wof:lang_x_spoken":[
        "ind",
        "eng"
    ],
    "wof:name":"Larangan",
    "wof:placetype":"locality"
},
  "geometry": {"coordinates":[109.69917,-7.37389],"type":"Point"}
}