{
  "type": "Feature",
  "properties": {
    "gn:admin1_code":"17.0",
    "gn:asciiname":"Murkomah",
    "gn:country_code":"ID",
    "gn:dem":84,
    "gn:feature_class":"P",
    "gn:feature_code":"PPL",
    "gn:name":"Murkomah",
    "gn:population":0,
    "gn:timezone":"Asia/Makassar",
    "iso:country":"ID",
    "name:ind_x_preferred":[
        "Murkomah"
    ],
    "wof:name":"Murkomah",
    "wof:placetype":"locality"
},
  "geometry": {"coordinates":[116.167,-8.3905],"type":"Point"}
}