{
  "type": "Feature",
  "properties": {
    "gn:admin1_code":"26",
    "gn:asciiname":"Banjarbiangku",
    "gn:country_code":"ID",
    "gn:dem":370,
    "gn:feature_class":"P",
    "gn:feature_code":"PPL",
    "gn:name":"Banjarbiangku",
    "gn:population":0,
    "gn:timezone":"Asia/Jakarta",
    "iso:country":"ID",
    "name:ind_x_preferred":[
        "Banjarbiangku"
    ],
    "wof:name":"Banjarbiangku",
    "wof:placetype":"locality"
},
  "geometry": {"coordinates":[99.3374,0.717],"type":"Point"}
}