{
  "type": "Feature",
  "properties": {
    "gn:admin1_code":"30.0",
    "gn:asciiname":"Bongas",
    "gn:country_code":"ID",
    "gn:dem":371,
    "gn:feature_class":"P",
    "gn:feature_code":"PPL",
    "gn:name":"Bongas",
    "gn:population":0,
    "gn:timezone":"Asia/Jakarta",
    "iso:country":"ID",
    "name:ind_x_preferred":[
        "Bongas"
    ],
    "wof:name":"Bongas",
    "wof:placetype":"locality"
},
  "geometry": {"coordinates":[108.15770000000001,-7.3645],"type":"Point"}
}