{
  "type": "Feature",
  "properties": {
    "gn:admin1_code":"30",
    "gn:asciiname":"Cijaru",
    "gn:country_code":"ID",
    "gn:dem":124,
    "gn:feature_class":"P",
    "gn:feature_code":"PPL",
    "gn:name":"Cijaru",
    "gn:population":0,
    "gn:timezone":"Asia/Jakarta",
    "iso:country":"ID",
    "wof:name":"Cijaru",
    "wof:placetype":"locality"
},
  "geometry": {"coordinates":[106.32805999999999,-6.44889],"type":"Point"}
}