{
  "type": "Feature",
  "properties": {
    "gn:country":"ID",
    "gn:fcode":"ADM4",
    "gn:pop":0,
    "iso:country":"ID",
    "name:ind_x_preferred":[
        "Desa Jatimakmur"
    ],
    "name:unk_x_variant":[
        "Jatimakmur"
    ],
    "qs:name":"Desa Jatimakmur",
    "qs:photos_9r":0,
    "qs:photos_sr":0,
    "qs:pop_sr":"0",
    "wof:name":"Desa Jatimakmur",
    "wof:placetype":"localadmin",
    "wof:population":0
},
  "geometry": {"coordinates":[106.92910000000001,-6.2828],"type":"Point"}
}