{
  "type": "Feature",
  "properties": {
    "gn:admin1_code":"38",
    "gn:asciiname":"Bungungkanunang",
    "gn:country_code":"ID",
    "gn:dem":168,
    "gn:feature_class":"P",
    "gn:feature_code":"PPL",
    "gn:name":"Bungungkanunang",
    "gn:population":0,
    "gn:timezone":"Asia/Makassar",
    "iso:country":"ID",
    "name:ind_x_preferred":[
        "Bungungkanunang"
    ],
    "wof:name":"Bungungkanunang",
    "wof:placetype":"locality"
},
  "geometry": {"coordinates":[119.80110000000001,-5.5776],"type":"Point"}
}