{
  "type": "Feature",
  "properties": {
    "gn:admin1_code":"22.0",
    "gn:asciiname":"Lapalinggu",
    "gn:country_code":"ID",
    "gn:dem":156,
    "gn:feature_class":"P",
    "gn:feature_code":"PPL",
    "gn:name":"Lapalinggu",
    "gn:population":0,
    "gn:timezone":"Asia/Makassar",
    "iso:country":"ID",
    "name:ind_x_preferred":[
        "Lapalinggu"
    ],
    "wof:name":"Lapalinggu",
    "wof:placetype":"locality"
},
  "geometry": {"coordinates":[123.566,-5.2819],"type":"Point"}
}