{
  "type": "Feature",
  "properties": {
    "gn:admin1_code":"8",
    "gn:asciiname":"Kedungbanyak",
    "gn:country_code":"ID",
    "gn:dem":203,
    "gn:feature_class":"P",
    "gn:feature_code":"PPL",
    "gn:name":"Kedungbanyak",
    "gn:population":0,
    "gn:timezone":"Asia/Jakarta",
    "iso:country":"ID",
    "name:ind_x_preferred":[
        "Kedungbanyak"
    ],
    "wof:name":"Kedungbanyak",
    "wof:placetype":"locality"
},
  "geometry": {"coordinates":[111.20972,-7.465],"type":"Point"}
}