{
  "type": "Feature",
  "properties": {
    "gn:admin1_code":"17",
    "gn:asciiname":"Kuangpati Dua",
    "gn:country_code":"ID",
    "gn:dem":410,
    "gn:feature_class":"P",
    "gn:feature_code":"PPL",
    "gn:name":"Kuangpati Dua",
    "gn:population":0,
    "gn:timezone":"Asia/Makassar",
    "iso:country":"ID",
    "name:ind_x_preferred":[
        "Kuangpati Dua"
    ],
    "wof:name":"Kuangpati Dua",
    "wof:placetype":"locality"
},
  "geometry": {"coordinates":[116.37390000000001,-8.5961],"type":"Point"}
}