{
  "type": "Feature",
  "properties": {
    "gn:admin1_code":"22.0",
    "gn:asciiname":"Puutabu",
    "gn:country_code":"ID",
    "gn:dem":39,
    "gn:feature_class":"P",
    "gn:feature_code":"PPL",
    "gn:name":"Puutabu",
    "gn:population":0,
    "gn:timezone":"Asia/Makassar",
    "iso:country":"ID",
    "name:ind_x_preferred":[
        "Puutabu"
    ],
    "wof:name":"Puutabu",
    "wof:placetype":"locality"
},
  "geometry": {"coordinates":[121.67789999999999,-4.1221],"type":"Point"}
}