{
  "type": "Feature",
  "properties": {
    "gn:admin1_code":"26",
    "gn:asciiname":"Hutagurgur Timur",
    "gn:country_code":"ID",
    "gn:dem":1180,
    "gn:feature_class":"P",
    "gn:feature_code":"PPL",
    "gn:name":"Hutagurgur Timur",
    "gn:population":0,
    "gn:timezone":"Asia/Jakarta",
    "iso:country":"ID",
    "name:ind_x_preferred":[
        "Hutagurgur Timur"
    ],
    "wof:name":"Hutagurgur Timur",
    "wof:placetype":"locality"
},
  "geometry": {"coordinates":[99.23269999999999,2.4155],"type":"Point"}
}