{
  "type": "Feature",
  "properties": {
    "gn:admin1_code":"38.0",
    "gn:asciiname":"Samba",
    "gn:country_code":"ID",
    "gn:dem":23,
    "gn:feature_class":"P",
    "gn:feature_code":"PPL",
    "gn:name":"Samba",
    "gn:population":0,
    "gn:timezone":"Asia/Makassar",
    "iso:country":"ID",
    "name:ind_x_preferred":[
        "Samba"
    ],
    "wof:name":"Samba",
    "wof:placetype":"locality"
},
  "geometry": {"coordinates":[120.38639999999999,-3.5529],"type":"Point"}
}