{
  "type": "Feature",
  "properties": {
    "gn:admin1_code":"28.0",
    "gn:asciiname":"Lala",
    "gn:country_code":"ID",
    "gn:dem":9,
    "gn:feature_class":"P",
    "gn:feature_code":"PPL",
    "gn:name":"Lala",
    "gn:population":0,
    "gn:timezone":"Asia/Jayapura",
    "iso:country":"ID",
    "name:ind_x_preferred":[
        "Lala"
    ],
    "wof:name":"Lala",
    "wof:placetype":"locality"
},
  "geometry": {"coordinates":[127.08566999999999,-3.20889],"type":"Point"}
}