{
  "type": "Feature",
  "properties": {
    "gn:admin1_code":"30",
    "gn:asciiname":"Neglasari",
    "gn:country_code":"ID",
    "gn:dem":472,
    "gn:feature_class":"P",
    "gn:feature_code":"PPL",
    "gn:name":"Neglasari",
    "gn:population":0,
    "gn:timezone":"Asia/Jakarta",
    "iso:country":"ID",
    "name:ind_x_preferred":[
        "Neglasari"
    ],
    "wof:name":"Neglasari",
    "wof:placetype":"locality"
},
  "geometry": {"coordinates":[106.925,-6.96139],"type":"Point"}
}