{
  "type": "Feature",
  "properties": {
    "gn:admin1_code":"8.0",
    "gn:asciiname":"Besaren",
    "gn:country_code":"ID",
    "gn:dem":107,
    "gn:feature_class":"P",
    "gn:feature_code":"PPL",
    "gn:name":"Besaren",
    "gn:population":0,
    "gn:timezone":"Asia/Jakarta",
    "iso:country":"ID",
    "name:ind_x_preferred":[
        "Besaren"
    ],
    "wof:name":"Besaren",
    "wof:placetype":"locality"
},
  "geometry": {"coordinates":[111.48690000000001,-7.8945],"type":"Point"}
}