{
  "type": "Feature",
  "properties": {
    "gn:admin1_code":"30",
    "gn:asciiname":"Paneureusan",
    "gn:country_code":"ID",
    "gn:dem":669,
    "gn:feature_class":"P",
    "gn:feature_code":"PPL",
    "gn:name":"Paneureusan",
    "gn:population":0,
    "gn:timezone":"Asia/Jakarta",
    "iso:country":"ID",
    "name:ind_x_preferred":[
        "Paneureusan"
    ],
    "wof:name":"Paneureusan",
    "wof:placetype":"locality"
},
  "geometry": {"coordinates":[107.75579999999999,-7.0086],"type":"Point"}
}