{
  "type": "Feature",
  "properties": {
    "gn:admin1_code":"38",
    "gn:asciiname":"Alekang",
    "gn:country_code":"ID",
    "gn:dem":491,
    "gn:feature_class":"P",
    "gn:feature_code":"PPL",
    "gn:name":"Alekang",
    "gn:population":0,
    "gn:timezone":"Asia/Makassar",
    "iso:country":"ID",
    "name:ind_x_preferred":[
        "Alekang"
    ],
    "wof:name":"Alekang",
    "wof:placetype":"locality"
},
  "geometry": {"coordinates":[119.9392,-5.0374],"type":"Point"}
}