{
  "type": "Feature",
  "properties": {
    "gn:admin1_code":"8.0",
    "gn:asciiname":"Ngrecak",
    "gn:country_code":"ID",
    "gn:dem":378,
    "gn:feature_class":"P",
    "gn:feature_code":"PPL",
    "gn:name":"Ngrecak",
    "gn:population":0,
    "gn:timezone":"Asia/Jakarta",
    "iso:country":"ID",
    "name:ind_x_preferred":[
        "Ngrecak"
    ],
    "wof:name":"Ngrecak",
    "wof:placetype":"locality"
},
  "geometry": {"coordinates":[111.64100000000001,-8.2129],"type":"Point"}
}