{
  "type": "Feature",
  "properties": {
    "gn:admin1_code":"30",
    "gn:asciiname":"Cisegok",
    "gn:country_code":"ID",
    "gn:dem":1152,
    "gn:feature_class":"P",
    "gn:feature_code":"PPL",
    "gn:name":"Cisegok",
    "gn:population":0,
    "gn:timezone":"Asia/Jakarta",
    "iso:country":"ID",
    "name:ind_x_preferred":[
        "Cisegok"
    ],
    "wof:name":"Cisegok",
    "wof:placetype":"locality"
},
  "geometry": {"coordinates":[107.4419,-7.0727],"type":"Point"}
}