{
  "type": "Feature",
  "properties": {
    "gn:admin1_code":"30",
    "gn:asciiname":"Ciawitali Lembur",
    "gn:country_code":"ID",
    "gn:dem":624,
    "gn:feature_class":"P",
    "gn:feature_code":"PPL",
    "gn:name":"Ciawitali Lembur",
    "gn:population":0,
    "gn:timezone":"Asia/Jakarta",
    "iso:country":"ID",
    "name:ind_x_preferred":[
        "Ciawitali Lembur"
    ],
    "name:und_x_variant":[
        "Tjiawitah 2",
        "Ciawitah Dua"
    ],
    "wof:name":"Ciawitali Lembur",
    "wof:placetype":"locality"
},
  "geometry": {"coordinates":[107.46083,-6.76806],"type":"Point"}
}