{
  "type": "Feature",
  "properties": {
    "gn:admin1_code":"21.0",
    "gn:asciiname":"Ogotion",
    "gn:country_code":"ID",
    "gn:dem":3,
    "gn:feature_class":"P",
    "gn:feature_code":"PPL",
    "gn:name":"Ogotion",
    "gn:population":0,
    "gn:timezone":"Asia/Makassar",
    "iso:country":"ID",
    "name:ind_x_preferred":[
        "Ogotion"
    ],
    "name:und_x_variant":[
        "Okotio"
    ],
    "wof:name":"Ogotion",
    "wof:placetype":"locality"
},
  "geometry": {"coordinates":[120.71680000000001,0.4891],"type":"Point"}
}