{
  "type": "Feature",
  "properties": {
    "gn:admin1_code":"18.0",
    "gn:asciiname":"Taebone",
    "gn:country_code":"ID",
    "gn:dem":343,
    "gn:feature_class":"P",
    "gn:feature_code":"PPL",
    "gn:name":"Taebone",
    "gn:population":0,
    "gn:timezone":"Asia/Makassar",
    "iso:country":"ID",
    "name:ind_x_preferred":[
        "Taebone"
    ],
    "wof:name":"Taebone",
    "wof:placetype":"locality"
},
  "geometry": {"coordinates":[124.6478,-9.6641],"type":"Point"}
}