{
  "type": "Feature",
  "properties": {
    "gn:admin1_code":"0.0",
    "gn:asciiname":"Batutiris",
    "gn:cc2":"ID",
    "gn:country_code":"ID",
    "gn:dem":44,
    "gn:feature_class":"P",
    "gn:feature_code":"PPL",
    "gn:name":"Batutiris",
    "gn:population":0,
    "gn:timezone":"Asia/Makassar",
    "iso:country":"ID",
    "name:und_x_variant":[
        "Batoetiris",
        "Batutiris"
    ],
    "wof:lang_x_official":[
        "ind"
    ],
    "wof:lang_x_spoken":[
        "ind",
        "eng"
    ],
    "wof:name":"Batutiris",
    "wof:placetype":"locality"
},
  "geometry": {"coordinates":[115.01667,-3.43333],"type":"Point"}
}