{
  "type": "Feature",
  "properties": {
    "gn:admin1_code":"29.0",
    "gn:asciiname":"Rica",
    "gn:country_code":"ID",
    "gn:dem":8,
    "gn:feature_class":"P",
    "gn:feature_code":"PPL",
    "gn:name":"Rica",
    "gn:population":0,
    "gn:timezone":"Asia/Jayapura",
    "iso:country":"ID",
    "name:deu_x_preferred":[
        "Rica"
    ],
    "name:fra_x_preferred":[
        "Rica"
    ],
    "name:ind_x_preferred":[
        "Rica"
    ],
    "name:ita_x_preferred":[
        "Rica"
    ],
    "wof:lang_x_official":[
        "ind"
    ],
    "wof:lang_x_spoken":[
        "ind",
        "eng"
    ],
    "wof:name":"Rica",
    "wof:placetype":"locality"
},
  "geometry": {"coordinates":[127.70950000000001,-1.33931],"type":"Point"}
}