{
  "type": "Feature",
  "properties": {
    "gn:admin1_code":"0.0",
    "gn:asciiname":"Warbumi",
    "gn:cc2":"ID",
    "gn:country_code":"ID",
    "gn:dem":46,
    "gn:feature_class":"P",
    "gn:feature_code":"PPL",
    "gn:name":"Warbumi",
    "gn:population":0,
    "gn:timezone":"Asia/Jayapura",
    "iso:country":"ID",
    "name:und_x_variant":[
        "Warboemi",
        "Warbumi"
    ],
    "wof:name":"Warbumi",
    "wof:placetype":"locality"
},
  "geometry": {"coordinates":[134.19999999999999,-1.23333],"type":"Point"}
}