{
  "type": "Feature",
  "properties": {
    "gn:admin1_code":"21",
    "gn:asciiname":"Janja",
    "gn:country_code":"ID",
    "gn:dem":32,
    "gn:feature_class":"P",
    "gn:feature_code":"PPL",
    "gn:name":"Janja",
    "gn:population":0,
    "gn:timezone":"Asia/Makassar",
    "iso:country":"ID",
    "name:bos_x_preferred":[
        "Janja"
    ],
    "name:ceb_x_preferred":[
        "Janja"
    ],
    "name:deu_x_preferred":[
        "Janja"
    ],
    "name:fra_x_preferred":[
        "Janja"
    ],
    "name:hrv_x_preferred":[
        "Janja"
    ],
    "name:ind_x_preferred":[
        "Janja"
    ],
    "name:lit_x_preferred":[
        "Jania"
    ],
    "name:nld_x_preferred":[
        "Janja"
    ],
    "name:pol_x_preferred":[
        "Janja"
    ],
    "name:rus_x_preferred":[
        "\u042f\u043d\u044f"
    ],
    "name:slv_x_preferred":[
        "Janja"
    ],
    "name:srp_x_preferred":[
        "\u0408\u0430\u045a\u0430"
    ],
    "name:swe_x_preferred":[
        "Janja"
    ],
    "name:urd_x_preferred":[
        "\u062c\u0646\u062c\u0627"
    ],
    "wof:name":"Janja",
    "wof:placetype":"locality"
},
  "geometry": {"coordinates":[120.87609999999999,0.8681],"type":"Point"}
}