{
  "type": "Feature",
  "properties": {
    "gn:admin1_code":"21",
    "gn:asciiname":"Janja",
    "gn:country_code":"ID",
    "gn:dem":32,
    "gn:feature_class":"P",
    "gn:feature_code":"PPL",
    "gn:name":"Janja",
    "gn:population":0,
    "gn:timezone":"Asia/Makassar",
    "iso:country":"ID",
    "name:ind_x_preferred":[
        "Janja"
    ],
    "wof:name":"Janja",
    "wof:placetype":"locality"
},
  "geometry": {"coordinates":[120.87609999999999,0.8681],"type":"Point"}
}