{
  "type": "Feature",
  "properties": {
    "gn:admin1_code":"8.0",
    "gn:asciiname":"Sadar",
    "gn:country_code":"ID",
    "gn:dem":102,
    "gn:feature_class":"P",
    "gn:feature_code":"PPLA4",
    "gn:name":"Sadar",
    "gn:population":0,
    "gn:timezone":"Asia/Jakarta",
    "iso:country":"ID",
    "name:ceb_x_preferred":[
        "Sadar"
    ],
    "name:deu_x_preferred":[
        "Sadar"
    ],
    "name:ind_x_preferred":[
        "Sadar"
    ],
    "name:spa_x_preferred":[
        "Sadar"
    ],
    "wof:lang_x_official":[
        "ind"
    ],
    "wof:lang_x_spoken":[
        "ind",
        "eng"
    ],
    "wof:name":"Sadar",
    "wof:placetype":"locality"
},
  "geometry": {"coordinates":[111.9522,-8.0906],"type":"Point"}
}