{
  "type": "Feature",
  "properties": {
    "gn:admin1_code":"41",
    "gn:asciiname":"Lanu",
    "gn:country_code":"ID",
    "gn:dem":25,
    "gn:feature_class":"P",
    "gn:feature_code":"PPL",
    "gn:name":"Lanu",
    "gn:population":0,
    "gn:timezone":"Asia/Makassar",
    "iso:country":"ID",
    "name:ceb_x_preferred":[
        "Lanoo"
    ],
    "name:fas_x_preferred":[
        "\u0644\u0627\u0646\u0648"
    ],
    "name:ind_x_preferred":[
        "Lanu"
    ],
    "name:swe_x_preferred":[
        "Lanoo"
    ],
    "name:urd_x_preferred":[
        "\u0644\u0627\u0646\u0648"
    ],
    "wof:lang_x_official":[
        "ind"
    ],
    "wof:lang_x_spoken":[
        "ind",
        "eng"
    ],
    "wof:name":"Lanu",
    "wof:placetype":"locality"
},
  "geometry": {"coordinates":[119.1311,-3.4346],"type":"Point"}
}