{
  "type": "Feature",
  "properties": {
    "gn:admin1_code":"34",
    "gn:asciiname":"Lamu",
    "gn:country_code":"ID",
    "gn:dem":10,
    "gn:feature_class":"P",
    "gn:feature_code":"PPL",
    "gn:name":"Lamu",
    "gn:population":0,
    "gn:timezone":"Asia/Makassar",
    "iso:country":"ID",
    "name:ara_x_preferred":[
        "\u0644\u0627\u0645\u0648"
    ],
    "name:azb_x_preferred":[
        "\u0644\u0627\u0645\u0628\u0648"
    ],
    "name:bel_x_preferred":[
        "\u041b\u0430\u043c\u0443"
    ],
    "name:cat_x_preferred":[
        "Lamu"
    ],
    "name:ceb_x_preferred":[
        "Lamu"
    ],
    "name:dan_x_preferred":[
        "Lamu"
    ],
    "name:epo_x_preferred":[
        "Lamu"
    ],
    "name:fas_x_preferred":[
        "\u0644\u0627\u0645\u0628\u0648"
    ],
    "name:fra_x_preferred":[
        "Lamu"
    ],
    "name:heb_x_preferred":[
        "\u05dc\u05d0\u05de\u05d5"
    ],
    "name:hin_x_preferred":[
        "\u0932\u093e\u092e\u0942"
    ],
    "name:hun_x_preferred":[
        "Lamu"
    ],
    "name:ind_x_preferred":[
        "Lamu"
    ],
    "name:ita_x_preferred":[
        "Lamu"
    ],
    "name:jpn_x_preferred":[
        "\u30e9\u30e0"
    ],
    "name:kat_x_preferred":[
        "\u10da\u10d0\u10db\u10e3"
    ],
    "name:lit_x_preferred":[
        "Lamu"
    ],
    "name:mal_x_preferred":[
        "\u0d32\u0d2e\u0d41"
    ],
    "name:nld_x_preferred":[
        "Lamu"
    ],
    "name:nor_x_preferred":[
        "Lamu"
    ],
    "name:pol_x_preferred":[
        "Lamu"
    ],
    "name:por_x_preferred":[
        "Lamu"
    ],
    "name:ron_x_preferred":[
        "Lamu"
    ],
    "name:rus_x_preferred":[
        "\u041b\u0430\u043c\u0443"
    ],
    "name:spa_x_preferred":[
        "Lamu"
    ],
    "name:srp_x_preferred":[
        "\u041b\u0430\u043c\u0443"
    ],
    "name:swa_x_preferred":[
        "Lamu"
    ],
    "name:swe_x_preferred":[
        "Lamu"
    ],
    "name:tgl_x_preferred":[
        "Lamu"
    ],
    "name:tur_x_preferred":[
        "Lamu"
    ],
    "name:vie_x_preferred":[
        "Lamu"
    ],
    "name:zho_x_preferred":[
        "\u62c9\u7a46\u9547"
    ],
    "wof:name":"Lamu",
    "wof:placetype":"locality"
},
  "geometry": {"coordinates":[122.9012,0.4933],"type":"Point"}
}