{
  "type": "Feature",
  "properties": {
    "gn:country":"ID",
    "gn:fcode":"PPLA3",
    "gn:pop":35285,
    "iso:country":"ID",
    "name:unk_x_variant":[
        "Soemberpoetjoeng"
    ],
    "qs:name":"Sumberpucung",
    "qs:photos_9r":0,
    "qs:photos_sr":0,
    "qs:pop_sr":"7",
    "wof:lang_x_official":[
        "ind"
    ],
    "wof:lang_x_spoken":[
        "ind",
        "eng"
    ],
    "wof:name":"Sumberpucung",
    "wof:placetype":"locality",
    "wof:population":35285
},
  "geometry": {"coordinates":[112.48291999999999,-8.15856],"type":"Point"}
}