{
  "type": "Feature",
  "properties": {
    "gn:admin1_code":"18",
    "gn:asciiname":"Raci",
    "gn:country_code":"ID",
    "gn:dem":611,
    "gn:feature_class":"P",
    "gn:feature_code":"PPL",
    "gn:name":"Raci",
    "gn:population":0,
    "gn:timezone":"Asia/Makassar",
    "iso:country":"ID",
    "name:ceb_x_preferred":[
        "Raci"
    ],
    "name:fra_x_preferred":[
        "Raci"
    ],
    "name:ind_x_preferred":[
        "Raci"
    ],
    "name:nld_x_preferred":[
        "Raci"
    ],
    "name:swe_x_preferred":[
        "Raci"
    ],
    "wof:lang_x_official":[
        "ind"
    ],
    "wof:lang_x_spoken":[
        "ind",
        "eng"
    ],
    "wof:name":"Raci",
    "wof:placetype":"locality"
},
  "geometry": {"coordinates":[120.4397,-8.4743],"type":"Point"}
}