{
  "type": "Feature",
  "properties": {
    "gn:admin1_code":"21",
    "gn:asciiname":"Kotanagaya",
    "gn:country_code":"ID",
    "gn:dem":37,
    "gn:feature_class":"P",
    "gn:feature_code":"PPL",
    "gn:name":"Kotanagaya",
    "gn:population":0,
    "gn:timezone":"Asia/Makassar",
    "iso:country":"ID",
    "name:ind_x_preferred":[
        "Kotanagaya"
    ],
    "wof:name":"Kotanagaya",
    "wof:placetype":"locality"
},
  "geometry": {"coordinates":[120.96639999999999,0.5367],"type":"Point"}
}