{
  "type": "Feature",
  "properties": {
    "gn:admin1_code":"26",
    "gn:asciiname":"Galangan",
    "gn:country_code":"ID",
    "gn:dem":109,
    "gn:feature_class":"P",
    "gn:feature_code":"PPL",
    "gn:name":"Galangan",
    "gn:population":0,
    "gn:timezone":"Asia/Jakarta",
    "iso:country":"ID",
    "name:ind_x_preferred":[
        "Galangan"
    ],
    "wof:name":"Galangan",
    "wof:placetype":"locality"
},
  "geometry": {"coordinates":[99.69273,1.2963],"type":"Point"}
}