{
  "type": "Feature",
  "properties": {
    "gn:admin1_code":"30.0",
    "gn:asciiname":"Bojongsalam",
    "gn:country_code":"ID",
    "gn:dem":739,
    "gn:feature_class":"P",
    "gn:feature_code":"PPL",
    "gn:name":"Bojongsalam",
    "gn:population":0,
    "gn:timezone":"Asia/Jakarta",
    "iso:country":"ID",
    "name:ind_x_preferred":[
        "Bojongsalam"
    ],
    "name:und_x_variant":[
        "Bodjongsalam"
    ],
    "wof:name":"Bojongsalam",
    "wof:placetype":"locality"
},
  "geometry": {"coordinates":[107.9509,-7.5563],"type":"Point"}
}