{
  "type": "Feature",
  "properties": {
    "gn:admin1_code":"30.0",
    "gn:asciiname":"Sukamaju",
    "gn:country_code":"ID",
    "gn:dem":74,
    "gn:feature_class":"P",
    "gn:feature_code":"PPLA4",
    "gn:name":"Sukamaju",
    "gn:population":0,
    "gn:timezone":"Asia/Jakarta",
    "iso:country":"ID",
    "name:ind_x_preferred":[
        "Sukamaju"
    ],
    "wof:name":"Sukamaju",
    "wof:placetype":"locality"
},
  "geometry": {"coordinates":[108.5177,-7.4342],"type":"Point"}
}