{
  "type": "Feature",
  "properties": {
    "gn:admin1_code":"7.0",
    "gn:asciiname":"Benco",
    "gn:country_code":"ID",
    "gn:dem":13,
    "gn:feature_class":"P",
    "gn:feature_code":"PPL",
    "gn:name":"Benco",
    "gn:population":0,
    "gn:timezone":"Asia/Jakarta",
    "iso:country":"ID",
    "name:ind_x_preferred":[
        "Benco"
    ],
    "wof:name":"Benco",
    "wof:placetype":"locality"
},
  "geometry": {"coordinates":[109.21528000000001,-7.66722],"type":"Point"}
}