{
  "type": "Feature",
  "properties": {
    "gn:admin1_code":"7",
    "gn:asciiname":"Ngelo Kidul",
    "gn:country_code":"ID",
    "gn:dem":540,
    "gn:feature_class":"P",
    "gn:feature_code":"PPL",
    "gn:name":"Ngelo Kidul",
    "gn:population":0,
    "gn:timezone":"Asia/Jakarta",
    "iso:country":"ID",
    "name:ind_x_preferred":[
        "Ngelo Kidul"
    ],
    "wof:name":"Ngelo Kidul",
    "wof:placetype":"locality"
},
  "geometry": {"coordinates":[111.05777999999999,-7.71778],"type":"Point"}
}