{
  "type": "Feature",
  "properties": {
    "gn:admin1_code":"1",
    "gn:asciiname":"Pinang Rugup",
    "gn:country_code":"ID",
    "gn:dem":932,
    "gn:feature_class":"P",
    "gn:feature_code":"PPL",
    "gn:name":"Pinang Rugup",
    "gn:population":0,
    "gn:timezone":"Asia/Jakarta",
    "iso:country":"ID",
    "name:ind_x_preferred":[
        "Pinang Rugup"
    ],
    "name:und_x_variant":[
        "Pinangreugeup"
    ],
    "wof:lang_x_official":[
        "ind"
    ],
    "wof:lang_x_spoken":[
        "ind",
        "eng"
    ],
    "wof:name":"Pinang Rugup",
    "wof:placetype":"locality"
},
  "geometry": {"coordinates":[97.3207,4.0624],"type":"Point"}
}