{
  "type": "Feature",
  "properties": {
    "gn:admin1_code":"30",
    "gn:asciiname":"Setro",
    "gn:country_code":"ID",
    "gn:dem":658,
    "gn:feature_class":"P",
    "gn:feature_code":"PPL",
    "gn:name":"Setro",
    "gn:population":0,
    "gn:timezone":"Asia/Jakarta",
    "iso:country":"ID",
    "name:ind_x_preferred":[
        "Setro"
    ],
    "wof:name":"Setro",
    "wof:placetype":"locality"
},
  "geometry": {"coordinates":[112.8865,-7.8176],"type":"Point"}
}