{
  "type": "Feature",
  "properties": {
    "gn:admin1_code":"7.0",
    "gn:asciiname":"Jonggol",
    "gn:country_code":"ID",
    "gn:dem":71,
    "gn:feature_class":"P",
    "gn:feature_code":"PPL",
    "gn:name":"Jonggol",
    "gn:population":0,
    "gn:timezone":"Asia/Jakarta",
    "iso:country":"ID",
    "name:ind_x_preferred":[
        "Jonggol"
    ],
    "name:jav_x_preferred":[
        "Jonggol"
    ],
    "name:sun_x_preferred":[
        "Jonggol"
    ],
    "wof:lang_x_official":[
        "ind"
    ],
    "wof:lang_x_spoken":[
        "ind",
        "eng"
    ],
    "wof:name":"Jonggol",
    "wof:placetype":"locality"
},
  "geometry": {"coordinates":[109.55249999999999,-7.55111],"type":"Point"}
}