{
  "type": "Feature",
  "properties": {
    "gn:admin1_code":"30",
    "gn:asciiname":"Sukmadilaya",
    "gn:country_code":"ID",
    "gn:dem":257,
    "gn:feature_class":"P",
    "gn:feature_code":"PPL",
    "gn:name":"Sukmadilaya",
    "gn:population":0,
    "gn:timezone":"Asia/Jakarta",
    "iso:country":"ID",
    "name:ind_x_preferred":[
        "Sukmadilaya"
    ],
    "wof:name":"Sukmadilaya",
    "wof:placetype":"locality"
},
  "geometry": {"coordinates":[108.501,-6.8073],"type":"Point"}
}