{
  "type": "Feature",
  "properties": {
    "gn:admin1_code":"18.0",
    "gn:asciiname":"Nadibao",
    "gn:country_code":"ID",
    "gn:dem":95,
    "gn:feature_class":"P",
    "gn:feature_code":"PPL",
    "gn:name":"Nadibao",
    "gn:population":0,
    "gn:timezone":"Asia/Makassar",
    "iso:country":"ID",
    "name:ind_x_preferred":[
        "Nadibao"
    ],
    "wof:name":"Nadibao",
    "wof:placetype":"locality"
},
  "geometry": {"coordinates":[122.7893,-8.1563],"type":"Point"}
}