{
  "type": "Feature",
  "properties": {
    "gn:admin1_code":"0.0",
    "gn:asciiname":"Lombo",
    "gn:country_code":"ID",
    "gn:dem":276,
    "gn:feature_class":"P",
    "gn:feature_code":"PPL",
    "gn:name":"Lombo",
    "gn:population":0,
    "gn:timezone":"Asia/Makassar",
    "iso:country":"ID",
    "name:ceb_x_preferred":[
        "Lombo"
    ],
    "name:glg_x_preferred":[
        "Lombo"
    ],
    "name:nld_x_preferred":[
        "Lombo"
    ],
    "name:por_x_preferred":[
        "Lombo"
    ],
    "name:swe_x_preferred":[
        "Lombo"
    ],
    "wof:lang_x_official":[
        "ind"
    ],
    "wof:lang_x_spoken":[
        "ind",
        "eng"
    ],
    "wof:name":"Lombo",
    "wof:placetype":"locality"
},
  "geometry": {"coordinates":[120.06667,-3.73333],"type":"Point"}
}