{
  "type": "Feature",
  "properties": {
    "gn:admin1_code":"18",
    "gn:asciiname":"Nuaderok",
    "gn:country_code":"ID",
    "gn:dem":209,
    "gn:feature_class":"P",
    "gn:feature_code":"PPL",
    "gn:name":"Nuaderok",
    "gn:population":0,
    "gn:timezone":"Asia/Makassar",
    "iso:country":"ID",
    "wof:name":"Nuaderok",
    "wof:placetype":"locality"
},
  "geometry": {"coordinates":[125.09999999999999,-9.01333],"type":"Point"}
}