{
  "type": "Feature",
  "properties": {
    "gn:admin1_code":"38",
    "gn:asciiname":"Bua",
    "gn:country_code":"ID",
    "gn:dem":143,
    "gn:feature_class":"P",
    "gn:feature_code":"PPL",
    "gn:name":"Bua",
    "gn:population":0,
    "gn:timezone":"Asia/Makassar",
    "iso:country":"ID",
    "name:ceb_x_preferred":[
        "Bua"
    ],
    "name:glg_x_preferred":[
        "Bua"
    ],
    "name:ind_x_preferred":[
        "Bua"
    ],
    "name:nld_x_preferred":[
        "Bua"
    ],
    "name:swe_x_preferred":[
        "Bua"
    ],
    "wof:lang_x_official":[
        "ind"
    ],
    "wof:lang_x_spoken":[
        "ind",
        "eng"
    ],
    "wof:name":"Bua",
    "wof:placetype":"locality"
},
  "geometry": {"coordinates":[119.7149,-4.5631],"type":"Point"}
}