{
  "type": "Feature",
  "properties": {
    "gn:admin1_code":"8.0",
    "gn:asciiname":"Butoh",
    "gn:country_code":"ID",
    "gn:dem":28,
    "gn:feature_class":"P",
    "gn:feature_code":"PPL",
    "gn:name":"Butoh",
    "gn:population":0,
    "gn:timezone":"Asia/Jakarta",
    "iso:country":"ID",
    "name:ind_x_preferred":[
        "Butoh"
    ],
    "wof:name":"Butoh",
    "wof:placetype":"locality"
},
  "geometry": {"coordinates":[112.12869999999999,-7.1303],"type":"Point"}
}