{
  "type": "Feature",
  "properties": {
    "gn:admin1_code":"0.0",
    "gn:asciiname":"Aer Mati",
    "gn:country_code":"ID",
    "gn:dem":521,
    "gn:feature_class":"P",
    "gn:feature_code":"PPL",
    "gn:name":"Aer Mati",
    "gn:population":0,
    "gn:timezone":"Asia/Jayapura",
    "iso:country":"ID",
    "wof:name":"Aer Mati",
    "wof:placetype":"locality"
},
  "geometry": {"coordinates":[138.66666999999998,-2.41667],"type":"Point"}
}