{
  "type": "Feature",
  "properties": {
    "gn:admin1_code":"7",
    "gn:asciiname":"Sumber",
    "gn:country_code":"ID",
    "gn:dem":561,
    "gn:feature_class":"P",
    "gn:feature_code":"PPL",
    "gn:name":"Sumber",
    "gn:population":0,
    "gn:timezone":"Asia/Jakarta",
    "iso:country":"ID",
    "name:ind_x_preferred":[
        "Sumber"
    ],
    "wof:name":"Sumber",
    "wof:placetype":"locality"
},
  "geometry": {"coordinates":[110.0442,-7.0802],"type":"Point"}
}