{
  "type": "Feature",
  "properties": {
    "gn:admin1_code":"08",
    "gn:asciiname":"Silo",
    "gn:country_code":"ID",
    "gn:dem":35,
    "gn:feature_class":"P",
    "gn:feature_code":"PPL",
    "gn:name":"Silo",
    "gn:population":0,
    "gn:timezone":"Asia/Jakarta",
    "iso:country":"ID",
    "name:ara_x_preferred":[
        "\u0635\u0648\u0645\u0639\u0629"
    ],
    "name:arg_x_preferred":[
        "C\u00eda"
    ],
    "name:bul_x_preferred":[
        "\u0421\u0438\u043b\u043e\u0437"
    ],
    "name:cat_x_preferred":[
        "Sitja"
    ],
    "name:ces_x_preferred":[
        "Silo"
    ],
    "name:dan_x_preferred":[
        "Silo"
    ],
    "name:deu_x_preferred":[
        "Silo"
    ],
    "name:ell_x_preferred":[
        "\u03a3\u03b9\u03bb\u03cc"
    ],
    "name:epo_x_preferred":[
        "Turstokejo"
    ],
    "name:eus_x_preferred":[
        "Silo"
    ],
    "name:fas_x_preferred":[
        "\u0633\u06cc\u0644\u0648"
    ],
    "name:fin_x_preferred":[
        "Varastosiilo"
    ],
    "name:fra_x_preferred":[
        "Silo"
    ],
    "name:glg_x_preferred":[
        "Silo"
    ],
    "name:hau_x_preferred":[
        "Runbu"
    ],
    "name:heb_x_preferred":[
        "\u05de\u05de\u05d2\u05d5\u05e8\u05d4"
    ],
    "name:hrv_x_preferred":[
        "Silos"
    ],
    "name:hun_x_preferred":[
        "Sil\u00f3"
    ],
    "name:ido_x_preferred":[
        "Silo"
    ],
    "name:ind_x_preferred":[
        "Silo"
    ],
    "name:ita_x_preferred":[
        "Silo"
    ],
    "name:jpn_x_preferred":[
        "\u30b5\u30a4\u30ed"
    ],
    "name:kor_x_preferred":[
        "\uc800\uc7a5\ud0d1"
    ],
    "name:lit_x_preferred":[
        "Silosin\u0117"
    ],
    "name:msa_x_preferred":[
        "Silo"
    ],
    "name:nld_x_preferred":[
        "Silo"
    ],
    "name:nno_x_preferred":[
        "Silo"
    ],
    "name:nor_x_preferred":[
        "Silo"
    ],
    "name:pol_x_preferred":[
        "Silos"
    ],
    "name:por_x_preferred":[
        "Silo"
    ],
    "name:rus_x_preferred":[
        "\u0421\u0438\u043b\u043e\u0441\u043d\u0430\u044f \u0431\u0430\u0448\u043d\u044f"
    ],
    "name:sco_x_preferred":[
        "Silo"
    ],
    "name:spa_x_preferred":[
        "Silo"
    ],
    "name:swe_x_preferred":[
        "Silo"
    ],
    "name:tam_x_preferred":[
        "\u0b95\u0bb3\u0b9e\u0bcd\u0b9a\u0bbf\u0baf\u0bae\u0bcd"
    ],
    "name:tur_x_preferred":[
        "Silo"
    ],
    "name:ukr_x_preferred":[
        "\u0421\u0438\u043b\u043e\u0441"
    ],
    "name:vec_x_preferred":[
        "Si\u0142o"
    ],
    "wof:lang_x_official":[
        "ind"
    ],
    "wof:lang_x_spoken":[
        "ind",
        "eng"
    ],
    "wof:name":"Silo",
    "wof:placetype":"locality"
},
  "geometry": {"coordinates":[112.64167,-7.17889],"type":"Point"}
}