{
  "type": "Feature",
  "properties": {
    "gn:admin1_code":"1",
    "gn:asciiname":"Bener Lukup Dua",
    "gn:country_code":"ID",
    "gn:dem":1440,
    "gn:feature_class":"P",
    "gn:feature_code":"PPL",
    "gn:name":"Bener Lukup Dua",
    "gn:population":0,
    "gn:timezone":"Asia/Jakarta",
    "iso:country":"ID",
    "name:ind_x_preferred":[
        "Bener Lukup Dua"
    ],
    "name:und_x_variant":[
        "Benerlukup 2"
    ],
    "wof:lang_x_official":[
        "ind"
    ],
    "wof:lang_x_spoken":[
        "ind",
        "eng"
    ],
    "wof:name":"Bener Lukup Dua",
    "wof:placetype":"locality"
},
  "geometry": {"coordinates":[96.9114,4.7712],"type":"Point"}
}