{
  "type": "Feature",
  "properties": {
    "gn:admin1_code":"22",
    "gn:asciiname":"Hukaea",
    "gn:country_code":"ID",
    "gn:dem":23,
    "gn:feature_class":"P",
    "gn:feature_code":"PPL",
    "gn:name":"Hukaea",
    "gn:population":0,
    "gn:timezone":"Asia/Makassar",
    "iso:country":"ID",
    "name:ind_x_preferred":[
        "Hukaea"
    ],
    "wof:name":"Hukaea",
    "wof:placetype":"locality"
},
  "geometry": {"coordinates":[121.9939,-4.6829],"type":"Point"}
}