{
  "type": "Feature",
  "properties": {
    "gn:admin1_code":"30.0",
    "gn:asciiname":"Bangodua",
    "gn:country_code":"ID",
    "gn:dem":11,
    "gn:feature_class":"P",
    "gn:feature_code":"PPL",
    "gn:name":"Bangodua",
    "gn:population":0,
    "gn:timezone":"Asia/Jakarta",
    "iso:country":"ID",
    "name:ind_x_preferred":[
        "Bangodua"
    ],
    "name:und_x_variant":[
        "Bangadoea",
        "Bangodoea"
    ],
    "wof:name":"Bangodua",
    "wof:placetype":"locality"
},
  "geometry": {"coordinates":[108.45667,-6.66278],"type":"Point"}
}