{
  "type": "Feature",
  "properties": {
    "gn:admin1_code":"8.0",
    "gn:asciiname":"Jadi",
    "gn:country_code":"ID",
    "gn:dem":219,
    "gn:feature_class":"P",
    "gn:feature_code":"PPLA4",
    "gn:name":"Jadi",
    "gn:population":0,
    "gn:timezone":"Asia/Jakarta",
    "iso:country":"ID",
    "name:ind_x_preferred":[
        "Jadi"
    ],
    "wof:name":"Jadi",
    "wof:placetype":"locality"
},
  "geometry": {"coordinates":[111.9918,-6.9603],"type":"Point"}
}