{
  "type": "Feature",
  "properties": {
    "gn:admin1_code":"17",
    "gn:asciiname":"Jati",
    "gn:country_code":"ID",
    "gn:dem":264,
    "gn:feature_class":"P",
    "gn:feature_code":"PPL",
    "gn:name":"Jati",
    "gn:population":0,
    "gn:timezone":"Asia/Makassar",
    "iso:country":"ID",
    "name:ind_x_preferred":[
        "Jati"
    ],
    "wof:name":"Jati",
    "wof:placetype":"locality"
},
  "geometry": {"coordinates":[116.3514,-8.7017],"type":"Point"}
}