{
  "type": "Feature",
  "properties": {
    "gn:admin1_code":"1.0",
    "gn:asciiname":"Tingkeum Mangang",
    "gn:country_code":"ID",
    "gn:dem":12,
    "gn:feature_class":"P",
    "gn:feature_code":"PPL",
    "gn:name":"Tingkeum Mangang",
    "gn:population":0,
    "gn:timezone":"Asia/Jakarta",
    "iso:country":"ID",
    "name:ind_x_preferred":[
        "Tingkeum Mangang"
    ],
    "name:und_x_variant":[
        "Mangang"
    ],
    "wof:name":"Tingkeum Mangang",
    "wof:placetype":"locality"
},
  "geometry": {"coordinates":[96.8325,5.2146],"type":"Point"}
}