{
  "type": "Feature",
  "properties": {
    "gn:admin1_code":"28.0",
    "gn:asciiname":"Wageren Migodo",
    "gn:country_code":"ID",
    "gn:dem":14,
    "gn:feature_class":"P",
    "gn:feature_code":"PPL",
    "gn:name":"Wageren Migodo",
    "gn:population":0,
    "gn:timezone":"Asia/Jayapura",
    "iso:country":"ID",
    "name:ind_x_preferred":[
        "Wageren Migodo"
    ],
    "name:und_x_variant":[
        "Wa G\u00e9r\u00e8n Migodo"
    ],
    "wof:lang_x_official":[
        "ind"
    ],
    "wof:lang_x_spoken":[
        "ind",
        "eng"
    ],
    "wof:name":"Wageren Migodo",
    "wof:placetype":"locality"
},
  "geometry": {"coordinates":[126.92152,-3.42183],"type":"Point"}
}