{
  "type": "Feature",
  "properties": {
    "gn:admin1_code":"38",
    "gn:asciiname":"Balleanging",
    "gn:country_code":"ID",
    "gn:dem":197,
    "gn:feature_class":"P",
    "gn:feature_code":"PPL",
    "gn:name":"Balleanging",
    "gn:population":0,
    "gn:timezone":"Asia/Makassar",
    "iso:country":"ID",
    "name:ind_x_preferred":[
        "Balleanging"
    ],
    "wof:name":"Balleanging",
    "wof:placetype":"locality"
},
  "geometry": {"coordinates":[120.15300000000001,-4.8971],"type":"Point"}
}