{
  "type": "Feature",
  "properties": {
    "gn:admin1_code":"21",
    "gn:asciiname":"Ueruru",
    "gn:country_code":"ID",
    "gn:dem":19,
    "gn:feature_class":"P",
    "gn:feature_code":"PPL",
    "gn:name":"Ueruru",
    "gn:population":0,
    "gn:timezone":"Asia/Makassar",
    "iso:country":"ID",
    "name:ind_x_preferred":[
        "Ueruru"
    ],
    "name:und_x_variant":[
        "Veruru"
    ],
    "wof:name":"Ueruru",
    "wof:placetype":"locality"
},
  "geometry": {"coordinates":[121.8197,-1.7173],"type":"Point"}
}