{
  "type": "Feature",
  "properties": {
    "gn:admin1_code":"30",
    "gn:asciiname":"Babakanwesel",
    "gn:country_code":"ID",
    "gn:dem":33,
    "gn:feature_class":"P",
    "gn:feature_code":"PPL",
    "gn:name":"Babakanwesel",
    "gn:population":0,
    "gn:timezone":"Asia/Jakarta",
    "iso:country":"ID",
    "name:ind_x_preferred":[
        "Babakanwesel"
    ],
    "wof:name":"Babakanwesel",
    "wof:placetype":"locality"
},
  "geometry": {"coordinates":[107.86278,-6.50889],"type":"Point"}
}