{
  "type": "Feature",
  "properties": {
    "gn:admin1_code":"41.0",
    "gn:asciiname":"Lupu",
    "gn:country_code":"ID",
    "gn:dem":102,
    "gn:feature_class":"P",
    "gn:feature_code":"PPL",
    "gn:name":"Lupu",
    "gn:population":0,
    "gn:timezone":"Asia/Makassar",
    "iso:country":"ID",
    "name:ceb_x_preferred":[
        "Lupu"
    ],
    "name:deu_x_preferred":[
        "Lupu"
    ],
    "name:fin_x_preferred":[
        "Lupu"
    ],
    "name:fra_x_preferred":[
        "Lupu"
    ],
    "name:ind_x_preferred":[
        "Lupu"
    ],
    "name:ita_x_preferred":[
        "Lupu"
    ],
    "name:nld_x_preferred":[
        "Lupu"
    ],
    "name:ron_x_preferred":[
        "Lupu"
    ],
    "name:rus_x_preferred":[
        "\u041b\u0443\u043f\u0443"
    ],
    "name:swe_x_preferred":[
        "Lupu"
    ],
    "name:ukr_x_preferred":[
        "\u041b\u0443\u043f\u0443"
    ],
    "wof:lang_x_official":[
        "ind"
    ],
    "wof:lang_x_spoken":[
        "ind",
        "eng"
    ],
    "wof:name":"Lupu",
    "wof:placetype":"locality"
},
  "geometry": {"coordinates":[119.364,-3.4018],"type":"Point"}
}