{
  "type": "Feature",
  "properties": {
    "gn:admin1_code":"38",
    "gn:asciiname":"Lummi",
    "gn:country_code":"ID",
    "gn:dem":49,
    "gn:feature_class":"P",
    "gn:feature_code":"PPL",
    "gn:name":"Lummi",
    "gn:population":0,
    "gn:timezone":"Asia/Makassar",
    "iso:country":"ID",
    "name:bos_x_preferred":[
        "Lummi"
    ],
    "name:deu_x_preferred":[
        "Lummi"
    ],
    "name:fra_x_preferred":[
        "Lummi"
    ],
    "name:hrv_x_preferred":[
        "Lummi"
    ],
    "wof:lang_x_official":[
        "ind"
    ],
    "wof:lang_x_spoken":[
        "ind",
        "eng"
    ],
    "wof:name":"Lummi",
    "wof:placetype":"locality"
},
  "geometry": {"coordinates":[120.15083,-2.75111],"type":"Point"}
}