{
  "type": "Feature",
  "properties": {
    "gn:admin1_code":"34",
    "gn:asciiname":"Batupotong",
    "gn:country_code":"ID",
    "gn:dem":7,
    "gn:feature_class":"P",
    "gn:feature_code":"PPL",
    "gn:name":"Batupotong",
    "gn:population":0,
    "gn:timezone":"Asia/Makassar",
    "iso:country":"ID",
    "name:ind_x_preferred":[
        "Batupotong"
    ],
    "wof:name":"Batupotong",
    "wof:placetype":"locality"
},
  "geometry": {"coordinates":[122.4498,0.5218],"type":"Point"}
}