{
  "type": "Feature",
  "properties": {
    "gn:admin1_code":"22.0",
    "gn:asciiname":"Buli",
    "gn:country_code":"ID",
    "gn:dem":12,
    "gn:feature_class":"P",
    "gn:feature_code":"PPL",
    "gn:name":"Buli",
    "gn:population":0,
    "gn:timezone":"Asia/Makassar",
    "iso:country":"ID",
    "name:ceb_x_preferred":[
        "Buli"
    ],
    "name:deu_x_preferred":[
        "Buli"
    ],
    "name:hrv_x_preferred":[
        "Buli"
    ],
    "name:ind_x_preferred":[
        "Buli"
    ],
    "name:nld_x_preferred":[
        "Buli"
    ],
    "name:rus_x_preferred":[
        "\u0411\u0443\u043b\u0438"
    ],
    "name:srp_x_preferred":[
        "\u0411\u0443\u043b\u0438"
    ],
    "name:swe_x_preferred":[
        "Buli"
    ],
    "name:tgl_x_preferred":[
        "Buli"
    ],
    "wof:name":"Buli",
    "wof:placetype":"locality"
},
  "geometry": {"coordinates":[122.85380000000001,-4.5852],"type":"Point"}
}