{
  "type": "Feature",
  "properties": {
    "gn:admin1_code":"38",
    "gn:asciiname":"Merara",
    "gn:country_code":"ID",
    "gn:dem":890,
    "gn:feature_class":"P",
    "gn:feature_code":"PPL",
    "gn:name":"Merara",
    "gn:population":0,
    "gn:timezone":"Asia/Makassar",
    "iso:country":"ID",
    "name:ind_x_preferred":[
        "Merara"
    ],
    "wof:name":"Merara",
    "wof:placetype":"locality"
},
  "geometry": {"coordinates":[119.767,-3.1504],"type":"Point"}
}