{
  "type": "Feature",
  "properties": {
    "gn:admin1_code":"30.0",
    "gn:asciiname":"Ciburulung",
    "gn:country_code":"ID",
    "gn:dem":338,
    "gn:feature_class":"P",
    "gn:feature_code":"PPL",
    "gn:name":"Ciburulung",
    "gn:population":0,
    "gn:timezone":"Asia/Jakarta",
    "iso:country":"ID",
    "name:ind_x_preferred":[
        "Ciburulung"
    ],
    "name:und_x_variant":[
        "Tjiburutung",
        "Ciburutung"
    ],
    "wof:name":"Ciburulung",
    "wof:placetype":"locality"
},
  "geometry": {"coordinates":[107.88222,-6.74222],"type":"Point"}
}