{
  "type": "Feature",
  "properties": {
    "gn:admin1_code":"30",
    "gn:asciiname":"Wideng",
    "gn:country_code":"ID",
    "gn:dem":22,
    "gn:feature_class":"P",
    "gn:feature_code":"PPL",
    "gn:name":"Wideng",
    "gn:population":0,
    "gn:timezone":"Asia/Jakarta",
    "iso:country":"ID",
    "name:ind_x_preferred":[
        "Wideng"
    ],
    "wof:name":"Wideng",
    "wof:placetype":"locality"
},
  "geometry": {"coordinates":[108.30138999999998,-6.59889],"type":"Point"}
}