{
  "type": "Feature",
  "properties": {
    "gn:admin1_code":"30",
    "gn:asciiname":"Remang",
    "gn:country_code":"ID",
    "gn:dem":6,
    "gn:feature_class":"P",
    "gn:feature_code":"PPL",
    "gn:name":"Remang",
    "gn:population":0,
    "gn:timezone":"Asia/Jakarta",
    "iso:country":"ID",
    "name:ind_x_preferred":[
        "Remang"
    ],
    "wof:name":"Remang",
    "wof:placetype":"locality"
},
  "geometry": {"coordinates":[108.01443999999999,-6.315],"type":"Point"}
}