{
  "type": "Feature",
  "properties": {
    "gn:admin1_code":"07",
    "gn:asciiname":"Gading",
    "gn:country_code":"ID",
    "gn:dem":591,
    "gn:feature_class":"P",
    "gn:feature_code":"PPL",
    "gn:name":"Gading",
    "gn:population":0,
    "gn:timezone":"Asia/Jakarta",
    "iso:country":"ID",
    "wof:name":"Gading",
    "wof:placetype":"locality"
},
  "geometry": {"coordinates":[110.55694,-7.42556],"type":"Point"}
}