{
  "type": "Feature",
  "properties": {
    "gn:admin1_code":"13.0",
    "gn:asciiname":"Kuala Kurun",
    "gn:country_code":"ID",
    "gn:dem":36,
    "gn:feature_class":"P",
    "gn:feature_code":"PPL",
    "gn:name":"Kuala Kurun",
    "gn:population":0,
    "gn:timezone":"Asia/Pontianak",
    "iso:country":"ID",
    "name:ind_x_preferred":[
        "Kuala Kurun"
    ],
    "name:und_x_variant":[
        "Koealakoeroean",
        "Koealakoeroen",
        "Kualakurun"
    ],
    "wof:lang_x_official":[
        "ind"
    ],
    "wof:lang_x_spoken":[
        "ind",
        "eng"
    ],
    "wof:name":"Kuala Kurun",
    "wof:placetype":"locality"
},
  "geometry": {"coordinates":[113.88333,-1.11667],"type":"Point"}
}