{
  "type": "Feature",
  "properties": {
    "gn:admin1_code":"15.0",
    "gn:asciiname":"Gunungkasih",
    "gn:country_code":"ID",
    "gn:dem":139,
    "gn:feature_class":"P",
    "gn:feature_code":"PPL",
    "gn:name":"Gunungkasih",
    "gn:population":0,
    "gn:timezone":"Asia/Jakarta",
    "iso:country":"ID",
    "name:ind_x_preferred":[
        "Gunungkasih"
    ],
    "wof:name":"Gunungkasih",
    "wof:placetype":"locality"
},
  "geometry": {"coordinates":[104.87743,-5.4017],"type":"Point"}
}