{
  "type": "Feature",
  "properties": {
    "gn:admin1_code":"15.0",
    "gn:asciiname":"Tanjungkemala",
    "gn:country_code":"ID",
    "gn:dem":38,
    "gn:feature_class":"P",
    "gn:feature_code":"PPL",
    "gn:name":"Tanjungkemala",
    "gn:population":0,
    "gn:timezone":"Asia/Jakarta",
    "iso:country":"ID",
    "name:ind_x_preferred":[
        "Tanjungkemala"
    ],
    "wof:name":"Tanjungkemala",
    "wof:placetype":"locality"
},
  "geometry": {"coordinates":[104.35836999999999,-5.58378],"type":"Point"}
}