{
  "type": "Feature",
  "properties": {
    "gn:admin1_code":"15.0",
    "gn:asciiname":"Curup",
    "gn:country_code":"ID",
    "gn:dem":216,
    "gn:feature_class":"P",
    "gn:feature_code":"PPL",
    "gn:name":"Curup",
    "gn:population":0,
    "gn:timezone":"Asia/Jakarta",
    "iso:country":"ID",
    "name:ind_x_preferred":[
        "Curup"
    ],
    "name:jav_x_preferred":[
        "Curup"
    ],
    "name:min_x_preferred":[
        "Curup"
    ],
    "name:msa_x_preferred":[
        "Curup"
    ],
    "name:pol_x_preferred":[
        "Curup"
    ],
    "wof:lang_x_official":[
        "ind"
    ],
    "wof:lang_x_spoken":[
        "ind",
        "eng"
    ],
    "wof:name":"Curup",
    "wof:placetype":"locality"
},
  "geometry": {"coordinates":[104.87444000000001,-5.50028],"type":"Point"}
}