{
  "type": "Feature",
  "properties": {
    "gn:admin1_code":"24",
    "gn:asciiname":"Kandanglawas",
    "gn:country_code":"ID",
    "gn:dem":218,
    "gn:feature_class":"P",
    "gn:feature_code":"PPL",
    "gn:name":"Kandanglawas",
    "gn:population":0,
    "gn:timezone":"Asia/Jakarta",
    "iso:country":"ID",
    "name:ind_x_preferred":[
        "Kandanglawas"
    ],
    "wof:name":"Kandanglawas",
    "wof:placetype":"locality"
},
  "geometry": {"coordinates":[100.75987000000001,-0.45243],"type":"Point"}
}