{
  "type": "Feature",
  "properties": {
    "gn:admin1_code":"30",
    "gn:asciiname":"Pasirmanggu",
    "gn:country_code":"ID",
    "gn:dem":1025,
    "gn:feature_class":"P",
    "gn:feature_code":"PPL",
    "gn:name":"Pasirmanggu",
    "gn:population":0,
    "gn:timezone":"Asia/Jakarta",
    "iso:country":"ID",
    "name:ind_x_preferred":[
        "Pasirmanggu"
    ],
    "wof:name":"Pasirmanggu",
    "wof:placetype":"locality"
},
  "geometry": {"coordinates":[107.50694,-6.76417],"type":"Point"}
}