{
  "type": "Feature",
  "properties": {
    "gn:admin1_code":"7.0",
    "gn:asciiname":"Ngangu",
    "gn:country_code":"ID",
    "gn:dem":112,
    "gn:feature_class":"P",
    "gn:feature_code":"PPL",
    "gn:name":"Ngangu",
    "gn:population":0,
    "gn:timezone":"Asia/Jakarta",
    "iso:country":"ID",
    "name:ind_x_preferred":[
        "Ngangu"
    ],
    "wof:name":"Ngangu",
    "wof:placetype":"locality"
},
  "geometry": {"coordinates":[111.4025,-6.9298],"type":"Point"}
}