{
  "type": "Feature",
  "properties": {
    "gn:admin1_code":"7",
    "gn:asciiname":"Tulaan",
    "gn:country_code":"ID",
    "gn:dem":246,
    "gn:feature_class":"P",
    "gn:feature_code":"PPL",
    "gn:name":"Tulaan",
    "gn:population":0,
    "gn:timezone":"Asia/Jakarta",
    "iso:country":"ID",
    "name:ind_x_preferred":[
        "Tulaan"
    ],
    "wof:name":"Tulaan",
    "wof:placetype":"locality"
},
  "geometry": {"coordinates":[111.02611,-7.85028],"type":"Point"}
}