{
  "type": "Feature",
  "properties": {
    "gn:admin1_code":"38",
    "gn:asciiname":"Saulaeng",
    "gn:country_code":"ID",
    "gn:dem":7,
    "gn:feature_class":"P",
    "gn:feature_code":"PPL",
    "gn:name":"Saulaeng",
    "gn:population":0,
    "gn:timezone":"Asia/Makassar",
    "iso:country":"ID",
    "name:ind_x_preferred":[
        "Saulaeng"
    ],
    "wof:name":"Saulaeng",
    "wof:placetype":"locality"
},
  "geometry": {"coordinates":[119.40479999999999,-5.4582],"type":"Point"}
}