{
  "type": "Feature",
  "properties": {
    "gn:country":"ID",
    "gn:fcode":"PPLA4",
    "gn:pop":0,
    "iso:country":"ID",
    "name:ind_x_preferred":[
        "Cicomre"
    ],
    "name:unk_x_variant":[
        "Tjitjombre"
    ],
    "qs:name":"Cicomre",
    "qs:photos_9r":0,
    "qs:photos_sr":0,
    "qs:pop_sr":"0",
    "wof:lang_x_official":[
        "ind"
    ],
    "wof:lang_x_spoken":[
        "ind",
        "eng"
    ],
    "wof:name":"Cicomre",
    "wof:placetype":"locality",
    "wof:population":0
},
  "geometry": {"coordinates":[107.9559,-7.5953],"type":"Point"}
}