{
  "type": "Feature",
  "properties": {
    "gn:admin1_code":"18",
    "gn:asciiname":"Marakisa",
    "gn:country_code":"ID",
    "gn:dem":113,
    "gn:feature_class":"P",
    "gn:feature_code":"PPL",
    "gn:name":"Marakisa",
    "gn:population":0,
    "gn:timezone":"Asia/Makassar",
    "iso:country":"ID",
    "name:ind_x_preferred":[
        "Marakisa"
    ],
    "wof:name":"Marakisa",
    "wof:placetype":"locality"
},
  "geometry": {"coordinates":[121.413,-8.7368],"type":"Point"}
}