{
  "type": "Feature",
  "properties": {
    "gn:admin1_code":"18",
    "gn:asciiname":"Golosepang",
    "gn:country_code":"ID",
    "gn:dem":22,
    "gn:feature_class":"P",
    "gn:feature_code":"PPL",
    "gn:name":"Golosepang",
    "gn:population":0,
    "gn:timezone":"Asia/Makassar",
    "iso:country":"ID",
    "name:ind_x_preferred":[
        "Golosepang"
    ],
    "wof:name":"Golosepang",
    "wof:placetype":"locality"
},
  "geometry": {"coordinates":[120.0904,-8.4727],"type":"Point"}
}