{
  "type": "Feature",
  "properties": {
    "gn:admin1_code":"33.0",
    "gn:asciiname":"Padawaras",
    "gn:country_code":"ID",
    "gn:dem":41,
    "gn:feature_class":"P",
    "gn:feature_code":"PPL",
    "gn:name":"Padawaras",
    "gn:population":0,
    "gn:timezone":"Asia/Jakarta",
    "iso:country":"ID",
    "name:ind_x_preferred":[
        "Padawaras"
    ],
    "wof:name":"Padawaras",
    "wof:placetype":"locality"
},
  "geometry": {"coordinates":[106.194,-6.5124],"type":"Point"}
}