{
  "type": "Feature",
  "properties": {
    "gn:admin1_code":"8.0",
    "gn:asciiname":"Ngetrep",
    "gn:country_code":"ID",
    "gn:dem":26,
    "gn:feature_class":"P",
    "gn:feature_code":"PPL",
    "gn:name":"Ngetrep",
    "gn:population":0,
    "gn:timezone":"Asia/Jakarta",
    "iso:country":"ID",
    "name:ind_x_preferred":[
        "Ngetrep"
    ],
    "wof:name":"Ngetrep",
    "wof:placetype":"locality"
},
  "geometry": {"coordinates":[112.61539999999999,-7.5494],"type":"Point"}
}