{
  "type": "Feature",
  "properties": {
    "gn:admin1_code":"26",
    "gn:asciiname":"Balimbing Tonga",
    "gn:country_code":"ID",
    "gn:dem":103,
    "gn:feature_class":"P",
    "gn:feature_code":"PPL",
    "gn:name":"Balimbing Tonga",
    "gn:population":0,
    "gn:timezone":"Asia/Jakarta",
    "iso:country":"ID",
    "name:ind_x_preferred":[
        "Balimbing Tonga"
    ],
    "wof:name":"Balimbing Tonga",
    "wof:placetype":"locality"
},
  "geometry": {"coordinates":[99.5317,1.39204],"type":"Point"}
}