{
  "type": "Feature",
  "properties": {
    "gn:admin1_code":"30.0",
    "gn:asciiname":"Parenca",
    "gn:country_code":"ID",
    "gn:dem":181,
    "gn:feature_class":"P",
    "gn:feature_code":"PPL",
    "gn:name":"Parenca",
    "gn:population":0,
    "gn:timezone":"Asia/Jakarta",
    "iso:country":"ID",
    "name:ind_x_preferred":[
        "Parenca"
    ],
    "wof:name":"Parenca",
    "wof:placetype":"locality"
},
  "geometry": {"coordinates":[108.5273,-7.026],"type":"Point"}
}