{
  "type": "Feature",
  "properties": {
    "gn:admin1_code":"24",
    "gn:asciiname":"Sarik",
    "gn:country_code":"ID",
    "gn:dem":1168,
    "gn:feature_class":"P",
    "gn:feature_code":"PPL",
    "gn:name":"Sarik",
    "gn:population":0,
    "gn:timezone":"Asia/Jakarta",
    "iso:country":"ID",
    "name:ind_x_preferred":[
        "Sarik"
    ],
    "name:srp_x_preferred":[
        "\u0421\u0430\u0440\u0438\u043a"
    ],
    "wof:name":"Sarik",
    "wof:placetype":"locality"
},
  "geometry": {"coordinates":[100.40522,-0.36906],"type":"Point"}
}