{
  "type": "Feature",
  "properties": {
    "gn:admin1_code":"8.0",
    "gn:asciiname":"Noko",
    "gn:country_code":"ID",
    "gn:dem":7,
    "gn:feature_class":"P",
    "gn:feature_code":"PPL",
    "gn:name":"Noko",
    "gn:population":0,
    "gn:timezone":"Asia/Jakarta",
    "iso:country":"ID",
    "name:ind_x_preferred":[
        "Noko"
    ],
    "name:spa_x_preferred":[
        "Noko"
    ],
    "wof:name":"Noko",
    "wof:placetype":"locality"
},
  "geometry": {"coordinates":[113.36579999999999,-7.7606],"type":"Point"}
}