{
  "type": "Feature",
  "properties": {
    "gn:admin1_code":"7",
    "gn:asciiname":"Suryopandan",
    "gn:country_code":"ID",
    "gn:dem":5,
    "gn:feature_class":"P",
    "gn:feature_code":"PPL",
    "gn:name":"Suryopandan",
    "gn:population":0,
    "gn:timezone":"Asia/Jakarta",
    "iso:country":"ID",
    "name:ind_x_preferred":[
        "Suryopandan"
    ],
    "wof:name":"Suryopandan",
    "wof:placetype":"locality"
},
  "geometry": {"coordinates":[110.69110000000001,-6.7298],"type":"Point"}
}