{
  "type": "Feature",
  "properties": {
    "gn:admin1_code":"30",
    "gn:asciiname":"Bondol",
    "gn:country_code":"ID",
    "gn:dem":1137,
    "gn:feature_class":"P",
    "gn:feature_code":"PPL",
    "gn:name":"Bondol",
    "gn:population":0,
    "gn:timezone":"Asia/Jakarta",
    "iso:country":"ID",
    "name:ind_x_preferred":[
        "Bondol"
    ],
    "wof:lang_x_official":[
        "ind"
    ],
    "wof:lang_x_spoken":[
        "ind",
        "eng"
    ],
    "wof:name":"Bondol",
    "wof:placetype":"locality"
},
  "geometry": {"coordinates":[107.01721999999999,-6.71306],"type":"Point"}
}