{
  "type": "Feature",
  "properties": {
    "gn:admin1_code":"30",
    "gn:asciiname":"Cijayanti Satu",
    "gn:country_code":"ID",
    "gn:dem":431,
    "gn:feature_class":"P",
    "gn:feature_code":"PPL",
    "gn:name":"Cijayanti Satu",
    "gn:population":0,
    "gn:timezone":"Asia/Jakarta",
    "iso:country":"ID",
    "name:ind_x_preferred":[
        "Cijayanti Satu"
    ],
    "wof:name":"Cijayanti Satu",
    "wof:placetype":"locality"
},
  "geometry": {"coordinates":[106.87888999999998,-6.61028],"type":"Point"}
}