{
  "type": "Feature",
  "properties": {
    "gn:admin1_code":"26.0",
    "gn:asciiname":"Tigapancur",
    "gn:country_code":"ID",
    "gn:dem":1057,
    "gn:feature_class":"P",
    "gn:feature_code":"PPL",
    "gn:name":"Tigapancur",
    "gn:population":0,
    "gn:timezone":"Asia/Jakarta",
    "iso:country":"ID",
    "name:ind_x_preferred":[
        "Tigapancur"
    ],
    "name:und_x_variant":[
        "Tigapantjur"
    ],
    "wof:name":"Tigapancur",
    "wof:placetype":"locality"
},
  "geometry": {"coordinates":[98.4157,3.1204],"type":"Point"}
}