{
  "type": "Feature",
  "properties": {
    "gn:admin1_code":"0.0",
    "gn:asciiname":"Muarasingoan",
    "gn:cc2":"ID",
    "gn:country_code":"ID",
    "gn:dem":17,
    "gn:feature_class":"P",
    "gn:feature_code":"PPL",
    "gn:name":"Muarasingoan",
    "gn:population":0,
    "gn:timezone":"Asia/Jakarta",
    "iso:country":"ID",
    "name:ind_x_preferred":[
        "Muara Singoan"
    ],
    "name:msa_x_preferred":[
        "Muara Singoan"
    ],
    "name:nld_x_preferred":[
        "Muara Singoan"
    ],
    "name:und_x_variant":[
        "Moearasingoah",
        "Moearasingoan",
        "Muarasingoan"
    ],
    "wof:lang_x_official":[
        "ind"
    ],
    "wof:lang_x_spoken":[
        "ind",
        "eng"
    ],
    "wof:name":"Muarasingoan",
    "wof:placetype":"locality"
},
  "geometry": {"coordinates":[103.26667,-1.65],"type":"Point"}
}