{
  "type": "Feature",
  "properties": {
    "gn:admin1_code":"8.0",
    "gn:asciiname":"Seweden Satu",
    "gn:country_code":"ID",
    "gn:dem":230,
    "gn:feature_class":"P",
    "gn:feature_code":"PPL",
    "gn:name":"Seweden Satu",
    "gn:population":0,
    "gn:timezone":"Asia/Jakarta",
    "iso:country":"ID",
    "name:ind_x_preferred":[
        "Seweden Satu"
    ],
    "wof:name":"Seweden Satu",
    "wof:placetype":"locality"
},
  "geometry": {"coordinates":[112.1456,-8.2593],"type":"Point"}
}