{
  "type": "Feature",
  "properties": {
    "gn:admin1_code":"30.0",
    "gn:asciiname":"Cisarua",
    "gn:country_code":"ID",
    "gn:dem":683,
    "gn:feature_class":"P",
    "gn:feature_code":"PPL",
    "gn:name":"Cisarua",
    "gn:population":0,
    "gn:timezone":"Asia/Jakarta",
    "iso:country":"ID",
    "name:fas_x_preferred":[
        "\u06a9\u06cc\u0633\u0627\u0631\u0648\u0627"
    ],
    "name:ind_x_preferred":[
        "Cisarua"
    ],
    "wof:lang_x_official":[
        "ind"
    ],
    "wof:lang_x_spoken":[
        "ind",
        "eng"
    ],
    "wof:name":"Cisarua",
    "wof:placetype":"locality"
},
  "geometry": {"coordinates":[106.6704,-7.17],"type":"Point"}
}