{
  "type": "Feature",
  "properties": {
    "gn:admin1_code":"7.0",
    "gn:asciiname":"Ngepos",
    "gn:country_code":"ID",
    "gn:dem":340,
    "gn:feature_class":"P",
    "gn:feature_code":"PPL",
    "gn:name":"Ngepos",
    "gn:population":0,
    "gn:timezone":"Asia/Jakarta",
    "iso:country":"ID",
    "wof:name":"Ngepos",
    "wof:placetype":"locality"
},
  "geometry": {"coordinates":[110.23833,-7.48528],"type":"Point"}
}