{
  "type": "Feature",
  "properties": {
    "gn:admin1_code":"38.0",
    "gn:asciiname":"Batuloso",
    "gn:country_code":"ID",
    "gn:dem":26,
    "gn:feature_class":"P",
    "gn:feature_code":"PPL",
    "gn:name":"Batuloso",
    "gn:population":0,
    "gn:timezone":"Asia/Makassar",
    "iso:country":"ID",
    "name:ind_x_preferred":[
        "Batuloso"
    ],
    "wof:name":"Batuloso",
    "wof:placetype":"locality"
},
  "geometry": {"coordinates":[119.5069,-3.4772],"type":"Point"}
}