{
  "type": "Feature",
  "properties": {
    "gn:admin1_code":"26.0",
    "gn:asciiname":"Sigiring-giring",
    "gn:country_code":"ID",
    "gn:dem":945,
    "gn:feature_class":"P",
    "gn:feature_code":"PPL",
    "gn:name":"Sigiring-giring",
    "gn:population":0,
    "gn:timezone":"Asia/Jakarta",
    "iso:country":"ID",
    "name:ind_x_preferred":[
        "Sigiring-giring"
    ],
    "wof:name":"Sigiring-giring",
    "wof:placetype":"locality"
},
  "geometry": {"coordinates":[98.8659,2.9119],"type":"Point"}
}