{
  "type": "Feature",
  "properties": {
    "gn:admin1_code":"3.0",
    "gn:asciiname":"Padanggadung",
    "gn:country_code":"ID",
    "gn:dem":14,
    "gn:feature_class":"P",
    "gn:feature_code":"PPL",
    "gn:name":"Padanggadung",
    "gn:population":0,
    "gn:timezone":"Asia/Jakarta",
    "iso:country":"ID",
    "name:ind_x_preferred":[
        "Padanggadung"
    ],
    "wof:name":"Padanggadung",
    "wof:placetype":"locality"
},
  "geometry": {"coordinates":[102.2546,-3.7397],"type":"Point"}
}