{
  "type": "Feature",
  "properties": {
    "gn:admin1_code":"18.0",
    "gn:asciiname":"Hohawungo",
    "gn:country_code":"ID",
    "gn:dem":92,
    "gn:feature_class":"P",
    "gn:feature_code":"PPLA4",
    "gn:name":"Hohawungo",
    "gn:population":0,
    "gn:timezone":"Asia/Makassar",
    "iso:country":"ID",
    "name:ind_x_preferred":[
        "Hohawungo"
    ],
    "wof:name":"Hohawungo",
    "wof:placetype":"locality"
},
  "geometry": {"coordinates":[119.02419999999999,-9.532],"type":"Point"}
}