{
  "type": "Feature",
  "properties": {
    "gn:admin1_code":"26",
    "gn:asciiname":"Pasar Empat Setengah",
    "gn:country_code":"ID",
    "gn:dem":10,
    "gn:feature_class":"P",
    "gn:feature_code":"PPL",
    "gn:name":"Pasar Empat Setengah",
    "gn:population":0,
    "gn:timezone":"Asia/Jakarta",
    "iso:country":"ID",
    "name:ind_x_preferred":[
        "Pasar Empat Setengah"
    ],
    "name:und_x_variant":[
        "Pasar 4 1/2"
    ],
    "wof:name":"Pasar Empat Setengah",
    "wof:placetype":"locality"
},
  "geometry": {"coordinates":[98.42959999999999,3.8341],"type":"Point"}
}