{
  "type": "Feature",
  "properties": {
    "gn:admin1_code":"07",
    "gn:asciiname":"Bawu Dua",
    "gn:cc2":"ID",
    "gn:country_code":"ID",
    "gn:dem":110,
    "gn:feature_class":"P",
    "gn:feature_code":"PPL",
    "gn:name":"Bawu Dua",
    "gn:population":0,
    "gn:timezone":"Asia/Jakarta",
    "iso:country":"ID",
    "name:und_x_variant":[
        "Bawu 2",
        "Bawu Dua"
    ],
    "wof:name":"Bawu Dua",
    "wof:placetype":"locality"
},
  "geometry": {"coordinates":[110.74028,-7.30694],"type":"Point"}
}