{
  "type": "Feature",
  "properties": {
    "gn:country":"ID",
    "gn:fcode":"ADM3",
    "gn:pop":0,
    "iso:country":"ID",
    "name:ind_x_preferred":[
        "Kecamatan Wanayasa"
    ],
    "name:unk_x_variant":[
        "Wanayasa"
    ],
    "qs:name":"Kecamatan Wanayasa",
    "qs:photos_9r":0,
    "qs:photos_sr":0,
    "qs:pop_sr":"0",
    "wd:wordcount":1319,
    "wof:name":"Kecamatan Wanayasa",
    "wof:placetype":"localadmin",
    "wof:population":0
},
  "geometry": {"coordinates":[107.56139,-6.65639],"type":"Point"}
}