{
  "type": "Feature",
  "properties": {
    "gn:admin1_code":"5.0",
    "gn:asciiname":"Telukkayuputih",
    "gn:country_code":"ID",
    "gn:dem":61,
    "gn:feature_class":"P",
    "gn:feature_code":"PPL",
    "gn:name":"Telukkayuputih",
    "gn:population":0,
    "gn:timezone":"Asia/Jakarta",
    "iso:country":"ID",
    "name:und_x_variant":[
        "Telukkajuputih",
        "Teloekkajoepoetih",
        "Teloekkajoepoet",
        "Telukkayuputih"
    ],
    "wof:lang_x_official":[
        "ind"
    ],
    "wof:lang_x_spoken":[
        "ind",
        "eng"
    ],
    "wof:name":"Telukkayuputih",
    "wof:placetype":"locality"
},
  "geometry": {"coordinates":[101.98584,-1.17318],"type":"Point"}
}