{
  "type": "Feature",
  "properties": {
    "gn:admin1_code":"30",
    "gn:asciiname":"Cileunyi Satu",
    "gn:cc2":"ID",
    "gn:country_code":"ID",
    "gn:dem":718,
    "gn:feature_class":"P",
    "gn:feature_code":"PPL",
    "gn:name":"Cileunyi Satu",
    "gn:population":0,
    "gn:timezone":"Asia/Jakarta",
    "iso:country":"ID",
    "name:und_x_variant":[
        "Tjileunji 1",
        "Cileunyi Satu"
    ],
    "wof:lang_x_official":[
        "ind"
    ],
    "wof:lang_x_spoken":[
        "ind",
        "eng"
    ],
    "wof:name":"Cileunyi Satu",
    "wof:placetype":"locality"
},
  "geometry": {"coordinates":[107.74639000000001,-6.93694],"type":"Point"}
}