{
  "type": "Feature",
  "properties": {
    "gn:admin1_code":"38.0",
    "gn:asciiname":"Batubatu",
    "gn:country_code":"ID",
    "gn:dem":112,
    "gn:feature_class":"P",
    "gn:feature_code":"PPL",
    "gn:name":"Batubatu",
    "gn:population":0,
    "gn:timezone":"Asia/Makassar",
    "iso:country":"ID",
    "name:ind_x_preferred":[
        "Batubatu"
    ],
    "wof:name":"Batubatu",
    "wof:placetype":"locality"
},
  "geometry": {"coordinates":[119.7206,-3.4789],"type":"Point"}
}