{
  "type": "Feature",
  "properties": {
    "gn:admin1_code":"15.0",
    "gn:asciiname":"Margodadi Lima",
    "gn:country_code":"ID",
    "gn:dem":26,
    "gn:feature_class":"P",
    "gn:feature_code":"PPL",
    "gn:name":"Margodadi Lima",
    "gn:population":0,
    "gn:timezone":"Asia/Jakarta",
    "iso:country":"ID",
    "name:ind_x_preferred":[
        "Margodadi Lima"
    ],
    "name:und_x_variant":[
        "Margodadi 5"
    ],
    "wof:lang_x_official":[
        "ind"
    ],
    "wof:lang_x_spoken":[
        "ind",
        "eng"
    ],
    "wof:name":"Margodadi Lima",
    "wof:placetype":"locality"
},
  "geometry": {"coordinates":[105.15900000000001,-5.57013],"type":"Point"}
}