{
  "type": "Feature",
  "properties": {
    "gn:admin1_code":"8.0",
    "gn:asciiname":"Angsana Barat",
    "gn:country_code":"ID",
    "gn:dem":125,
    "gn:feature_class":"P",
    "gn:feature_code":"PPL",
    "gn:name":"Angsana Barat",
    "gn:population":0,
    "gn:timezone":"Asia/Jakarta",
    "iso:country":"ID",
    "name:ind_x_preferred":[
        "Angsana Barat"
    ],
    "wof:name":"Angsana Barat",
    "wof:placetype":"locality"
},
  "geometry": {"coordinates":[113.53879999999999,-7.09],"type":"Point"}
}