{
  "type": "Feature",
  "properties": {
    "gn:admin1_code":"8.0",
    "gn:asciiname":"Sengonrejo",
    "gn:country_code":"ID",
    "gn:dem":684,
    "gn:feature_class":"P",
    "gn:feature_code":"PPL",
    "gn:name":"Sengonrejo",
    "gn:population":0,
    "gn:timezone":"Asia/Jakarta",
    "iso:country":"ID",
    "name:ind_x_preferred":[
        "Sengonrejo"
    ],
    "wof:name":"Sengonrejo",
    "wof:placetype":"locality"
},
  "geometry": {"coordinates":[112.5475,-8.0022],"type":"Point"}
}