{
  "type": "Feature",
  "properties": {
    "gn:admin1_code":"30.0",
    "gn:asciiname":"Lemburpasir",
    "gn:country_code":"ID",
    "gn:dem":661,
    "gn:feature_class":"P",
    "gn:feature_code":"PPL",
    "gn:name":"Lemburpasir",
    "gn:population":0,
    "gn:timezone":"Asia/Jakarta",
    "iso:country":"ID",
    "name:ind_x_preferred":[
        "Lemburpasir"
    ],
    "wof:name":"Lemburpasir",
    "wof:placetype":"locality"
},
  "geometry": {"coordinates":[106.8852,-7.0594],"type":"Point"}
}