{
  "type": "Feature",
  "properties": {
    "gn:admin1_code":"30.0",
    "gn:asciiname":"Kokocoran",
    "gn:country_code":"ID",
    "gn:dem":15,
    "gn:feature_class":"P",
    "gn:feature_code":"PPL",
    "gn:name":"Kokocoran",
    "gn:population":0,
    "gn:timezone":"Asia/Jakarta",
    "iso:country":"ID",
    "name:ind_x_preferred":[
        "Kokocoran"
    ],
    "wof:name":"Kokocoran",
    "wof:placetype":"locality"
},
  "geometry": {"coordinates":[106.7277,-7.4236],"type":"Point"}
}