{
  "type": "Feature",
  "properties": {
    "gn:admin1_code":"26",
    "gn:asciiname":"Sitiotio",
    "gn:country_code":"ID",
    "gn:dem":1219,
    "gn:feature_class":"P",
    "gn:feature_code":"PPL",
    "gn:name":"Sitiotio",
    "gn:population":0,
    "gn:timezone":"Asia/Jakarta",
    "iso:country":"ID",
    "name:ind_x_preferred":[
        "Sitiotio"
    ],
    "wof:name":"Sitiotio",
    "wof:placetype":"locality"
},
  "geometry": {"coordinates":[98.88630000000001,2.4724],"type":"Point"}
}