{
  "type": "Feature",
  "properties": {
    "gn:admin1_code":"36.0",
    "gn:asciiname":"Mamogo",
    "gn:country_code":"ID",
    "gn:dem":23,
    "gn:feature_class":"P",
    "gn:feature_code":"PPL",
    "gn:name":"Mamogo",
    "gn:population":0,
    "gn:timezone":"Asia/Jayapura",
    "iso:country":"ID",
    "name:ind_x_preferred":[
        "Mamogo"
    ],
    "wof:name":"Mamogo",
    "wof:placetype":"locality"
},
  "geometry": {"coordinates":[138.41480000000001,-4.98499],"type":"Point"}
}