{
  "type": "Feature",
  "properties": {
    "gn:admin1_code":"7",
    "gn:asciiname":"Andapan Selatan",
    "gn:country_code":"ID",
    "gn:dem":5,
    "gn:feature_class":"P",
    "gn:feature_code":"PPL",
    "gn:name":"Andapan Selatan",
    "gn:population":0,
    "gn:timezone":"Asia/Jakarta",
    "iso:country":"ID",
    "name:ind_x_preferred":[
        "Andapan Selatan"
    ],
    "wof:name":"Andapan Selatan",
    "wof:placetype":"locality"
},
  "geometry": {"coordinates":[110.55670000000001,-6.8633],"type":"Point"}
}