{
  "type": "Feature",
  "properties": {
    "gn:admin1_code":"18.0",
    "gn:asciiname":"Ringkas",
    "gn:country_code":"ID",
    "gn:dem":682,
    "gn:feature_class":"P",
    "gn:feature_code":"PPL",
    "gn:name":"Ringkas",
    "gn:population":0,
    "gn:timezone":"Asia/Makassar",
    "iso:country":"ID",
    "name:ind_x_preferred":[
        "Ringkas"
    ],
    "wof:name":"Ringkas",
    "wof:placetype":"locality"
},
  "geometry": {"coordinates":[120.5124,-8.4816],"type":"Point"}
}