{
  "type": "Feature",
  "properties": {
    "gn:admin1_code":"30",
    "gn:asciiname":"Kramattaipur",
    "gn:country_code":"ID",
    "gn:dem":315,
    "gn:feature_class":"P",
    "gn:feature_code":"PPL",
    "gn:name":"Kramattaipur",
    "gn:population":0,
    "gn:timezone":"Asia/Jakarta",
    "iso:country":"ID",
    "name:ind_x_preferred":[
        "Kramattaipur"
    ],
    "wof:name":"Kramattaipur",
    "wof:placetype":"locality"
},
  "geometry": {"coordinates":[107.19944,-6.80333],"type":"Point"}
}