{
  "type": "Feature",
  "properties": {
    "gn:admin1_code":"38",
    "gn:asciiname":"Mico Satu",
    "gn:country_code":"ID",
    "gn:dem":833,
    "gn:feature_class":"P",
    "gn:feature_code":"PPL",
    "gn:name":"Mico Satu",
    "gn:population":0,
    "gn:timezone":"Asia/Makassar",
    "iso:country":"ID",
    "name:ind_x_preferred":[
        "Mico Satu"
    ],
    "name:und_x_variant":[
        "Micol",
        "Mico 1"
    ],
    "wof:lang_x_official":[
        "ind"
    ],
    "wof:lang_x_spoken":[
        "ind",
        "eng"
    ],
    "wof:name":"Mico Satu",
    "wof:placetype":"locality"
},
  "geometry": {"coordinates":[119.9132,-4.6864],"type":"Point"}
}