{
  "type": "Feature",
  "properties": {
    "gn:admin1_code":"11.0",
    "gn:asciiname":"Nangah Jerahai",
    "gn:country_code":"ID",
    "gn:dem":91,
    "gn:feature_class":"P",
    "gn:feature_code":"PPL",
    "gn:name":"Nangah Jerahai",
    "gn:population":0,
    "gn:timezone":"Asia/Pontianak",
    "iso:country":"ID",
    "name:und_x_variant":[
        "Nangah Djalihai",
        "Nangah Djerahai",
        "Nangah Jerahai"
    ],
    "wof:name":"Nangah Jerahai",
    "wof:placetype":"locality"
},
  "geometry": {"coordinates":[112.91667,0.36667],"type":"Point"}
}