{
  "type": "Feature",
  "properties": {
    "gn:admin1_code":"30",
    "gn:asciiname":"Bojongkalong Dua",
    "gn:cc2":"ID",
    "gn:country_code":"ID",
    "gn:dem":666,
    "gn:feature_class":"P",
    "gn:feature_code":"PPL",
    "gn:name":"Bojongkalong Dua",
    "gn:population":0,
    "gn:timezone":"Asia/Jakarta",
    "iso:country":"ID",
    "name:und_x_variant":[
        "Bodjongkalong 2",
        "Bojongkalong Dua"
    ],
    "wof:name":"Bojongkalong Dua",
    "wof:placetype":"locality"
},
  "geometry": {"coordinates":[107.70389,-6.995],"type":"Point"}
}