{
  "type": "Feature",
  "properties": {
    "gn:admin1_code":"30.0",
    "gn:asciiname":"Papayan",
    "gn:country_code":"ID",
    "gn:dem":222,
    "gn:feature_class":"P",
    "gn:feature_code":"PPLA4",
    "gn:name":"Papayan",
    "gn:population":0,
    "gn:timezone":"Asia/Jakarta",
    "iso:country":"ID",
    "name:ind_x_preferred":[
        "Papayan"
    ],
    "name:und_x_variant":[
        "Papajan",
        "Papayan"
    ],
    "wof:lang_x_official":[
        "ind"
    ],
    "wof:lang_x_spoken":[
        "ind",
        "eng"
    ],
    "wof:name":"Papayan",
    "wof:placetype":"locality"
},
  "geometry": {"coordinates":[108.20229999999999,-7.4649],"type":"Point"}
}