{
  "type": "Feature",
  "properties": {
    "gn:admin1_code":"31.0",
    "gn:asciiname":"Dusun Tiga Kombot",
    "gn:country_code":"ID",
    "gn:dem":4,
    "gn:feature_class":"P",
    "gn:feature_code":"PPL",
    "gn:name":"Dusun Tiga Kombot",
    "gn:population":0,
    "gn:timezone":"Asia/Makassar",
    "iso:country":"ID",
    "name:ind_x_preferred":[
        "Dusun Tiga Kombot"
    ],
    "name:und_x_variant":[
        "Dusun 3 Kombot"
    ],
    "wof:lang_x_official":[
        "ind"
    ],
    "wof:lang_x_spoken":[
        "ind",
        "eng"
    ],
    "wof:name":"Dusun Tiga Kombot",
    "wof:placetype":"locality"
},
  "geometry": {"coordinates":[124.15600000000001,0.3967],"type":"Point"}
}