{
  "type": "Feature",
  "properties": {
    "gn:admin1_code":"0.0",
    "gn:asciiname":"Tanahslam",
    "gn:cc2":"ID",
    "gn:country_code":"ID",
    "gn:dem":4,
    "gn:feature_class":"P",
    "gn:feature_code":"PPL",
    "gn:name":"Tanahslam",
    "gn:population":0,
    "gn:timezone":"Asia/Pontianak",
    "iso:country":"ID",
    "name:und_x_variant":[
        "Tanahsiam",
        "Tannasiam",
        "Tanahslam"
    ],
    "wof:name":"Tanahslam",
    "wof:placetype":"locality"
},
  "geometry": {"coordinates":[109.21666999999999,1.63333],"type":"Point"}
}