{
  "type": "Feature",
  "properties": {
    "gn:admin1_code":"10",
    "gn:asciiname":"Janten",
    "gn:country_code":"ID",
    "gn:dem":110,
    "gn:feature_class":"P",
    "gn:feature_code":"PPL",
    "gn:name":"Janten",
    "gn:population":0,
    "gn:timezone":"Asia/Jakarta",
    "iso:country":"ID",
    "wof:name":"Janten",
    "wof:placetype":"locality"
},
  "geometry": {"coordinates":[110.34139,-7.79417],"type":"Point"}
}