{
  "type": "Feature",
  "properties": {
    "gn:admin1_code":"8.0",
    "gn:asciiname":"Billamabuk",
    "gn:country_code":"ID",
    "gn:dem":60,
    "gn:feature_class":"P",
    "gn:feature_code":"PPL",
    "gn:name":"Billamabuk",
    "gn:population":0,
    "gn:timezone":"Asia/Jakarta",
    "iso:country":"ID",
    "name:ind_x_preferred":[
        "Billamabuk"
    ],
    "wof:name":"Billamabuk",
    "wof:placetype":"locality"
},
  "geometry": {"coordinates":[113.6815,-6.9044],"type":"Point"}
}