{
  "type": "Feature",
  "properties": {
    "gn:admin1_code":"30",
    "gn:asciiname":"Ciawitali",
    "gn:country_code":"ID",
    "gn:dem":651,
    "gn:feature_class":"P",
    "gn:feature_code":"PPL",
    "gn:name":"Ciawitali",
    "gn:population":0,
    "gn:timezone":"Asia/Jakarta",
    "iso:country":"ID",
    "name:ind_x_preferred":[
        "Ciawitali"
    ],
    "wof:name":"Ciawitali",
    "wof:placetype":"locality"
},
  "geometry": {"coordinates":[107.08222000000001,-6.91444],"type":"Point"}
}