{
  "type": "Feature",
  "properties": {
    "gn:admin1_code":"28.0",
    "gn:asciiname":"Wawali",
    "gn:country_code":"ID",
    "gn:dem":16,
    "gn:feature_class":"P",
    "gn:feature_code":"PPL",
    "gn:name":"Wawali",
    "gn:population":0,
    "gn:timezone":"Asia/Jayapura",
    "iso:country":"ID",
    "name:ind_x_preferred":[
        "Wawali"
    ],
    "name:und_x_variant":[
        "Wa Wali"
    ],
    "wof:name":"Wawali",
    "wof:placetype":"locality"
},
  "geometry": {"coordinates":[126.34487,-3.68588],"type":"Point"}
}