{
  "type": "Feature",
  "properties": {
    "gn:admin1_code":"38",
    "gn:asciiname":"Pitti",
    "gn:country_code":"ID",
    "gn:dem":808,
    "gn:feature_class":"P",
    "gn:feature_code":"PPL",
    "gn:name":"Pitti",
    "gn:population":0,
    "gn:timezone":"Asia/Makassar",
    "iso:country":"ID",
    "name:hin_x_preferred":[
        "\u092a\u093f\u091f\u094d\u091f\u0940 \u0926\u094d\u0935\u0940\u092a\u093f\u0915\u093e"
    ],
    "name:ind_x_preferred":[
        "Pitti"
    ],
    "wof:lang_x_official":[
        "ind"
    ],
    "wof:lang_x_spoken":[
        "ind",
        "eng"
    ],
    "wof:name":"Pitti",
    "wof:placetype":"locality"
},
  "geometry": {"coordinates":[119.7954,-3.0973],"type":"Point"}
}