{
  "type": "Feature",
  "properties": {
    "gn:admin1_code":"26",
    "gn:asciiname":"Kalapane Dua",
    "gn:country_code":"ID",
    "gn:dem":16,
    "gn:feature_class":"P",
    "gn:feature_code":"PPL",
    "gn:name":"Kalapane Dua",
    "gn:population":0,
    "gn:timezone":"Asia/Jakarta",
    "iso:country":"ID",
    "name:ind_x_preferred":[
        "Kalapane Dua"
    ],
    "wof:name":"Kalapane Dua",
    "wof:placetype":"locality"
},
  "geometry": {"coordinates":[100.09533999999999,1.90237],"type":"Point"}
}