{
  "type": "Feature",
  "properties": {
    "gn:admin1_code":"0.0",
    "gn:asciiname":"Guis",
    "gn:cc2":"ID",
    "gn:country_code":"ID",
    "gn:dem":43,
    "gn:feature_class":"P",
    "gn:feature_code":"PPL",
    "gn:name":"Guis",
    "gn:population":0,
    "gn:timezone":"Asia/Jayapura",
    "iso:country":"ID",
    "name:und_x_variant":[
        "Goeis",
        "Goesis",
        "Guis"
    ],
    "wof:name":"Guis",
    "wof:placetype":"locality"
},
  "geometry": {"coordinates":[140.86667,-6.81667],"type":"Point"}
}