{
  "type": "Feature",
  "properties": {
    "gn:admin1_code":"7.0",
    "gn:asciiname":"Ciara",
    "gn:country_code":"ID",
    "gn:dem":46,
    "gn:feature_class":"P",
    "gn:feature_code":"PPL",
    "gn:name":"Ciara",
    "gn:population":0,
    "gn:timezone":"Asia/Jakarta",
    "iso:country":"ID",
    "name:ara_x_preferred":[
        "\u0633\u064a\u0627\u0631\u0627"
    ],
    "name:ast_x_preferred":[
        "Ciara"
    ],
    "name:azb_x_preferred":[
        "\u0633\u06cc\u200c\u06cc\u0631\u0627"
    ],
    "name:bul_x_preferred":[
        "\u0421\u0438\u0430\u0440\u0430"
    ],
    "name:cat_x_preferred":[
        "Ciara"
    ],
    "name:ces_x_preferred":[
        "Ciara"
    ],
    "name:deu_x_preferred":[
        "Ciara"
    ],
    "name:est_x_preferred":[
        "Ciara"
    ],
    "name:fas_x_preferred":[
        "\u0633\u06cc\u200c\u06cc\u0631\u0627"
    ],
    "name:fin_x_preferred":[
        "Ciara"
    ],
    "name:fra_x_preferred":[
        "Ciara"
    ],
    "name:fry_x_preferred":[
        "Ciara"
    ],
    "name:glg_x_preferred":[
        "Ciara"
    ],
    "name:heb_x_preferred":[
        "\u05e1\u05d9\u05d0\u05e8\u05d4"
    ],
    "name:hrv_x_preferred":[
        "Ciara"
    ],
    "name:hun_x_preferred":[
        "Ciara"
    ],
    "name:hye_x_preferred":[
        "\u054d\u056b\u0561\u0580\u0561"
    ],
    "name:ind_x_preferred":[
        "Ciara"
    ],
    "name:ita_x_preferred":[
        "Ciara"
    ],
    "name:jpn_x_preferred":[
        "\u30b7\u30a2\u30e9"
    ],
    "name:kor_x_preferred":[
        "\uc2dc\uc5d0\ub77c"
    ],
    "name:lav_x_preferred":[
        "Ciara"
    ],
    "name:mal_x_preferred":[
        "\u0d38\u0d3f\u0d2f\u0d31"
    ],
    "name:nld_x_preferred":[
        "Ciara"
    ],
    "name:nor_x_preferred":[
        "Ciara"
    ],
    "name:pol_x_preferred":[
        "Ciara"
    ],
    "name:por_x_preferred":[
        "Ciara"
    ],
    "name:ron_x_preferred":[
        "Ciara"
    ],
    "name:rus_x_preferred":[
        "\u0421\u0438\u0430\u0440\u0430"
    ],
    "name:spa_x_preferred":[
        "Ciara"
    ],
    "name:sqi_x_preferred":[
        "Ciara"
    ],
    "name:srp_x_preferred":[
        "Sijera"
    ],
    "name:swa_x_preferred":[
        "Ciara"
    ],
    "name:swe_x_preferred":[
        "Ciara"
    ],
    "name:tel_x_preferred":[
        "\u0c38\u0c3f\u0c2f\u0c30\u0c3e"
    ],
    "name:tha_x_preferred":[
        "\u0e0b\u0e34\u0e40\u0e2d\u0e23\u0e32"
    ],
    "name:tur_x_preferred":[
        "Ciara"
    ],
    "name:ukr_x_preferred":[
        "Ciara"
    ],
    "name:vie_x_preferred":[
        "Ciara"
    ],
    "name:zho_x_preferred":[
        "\u5e2d\u4e9e\u62c9"
    ],
    "wof:name":"Ciara",
    "wof:placetype":"locality"
},
  "geometry": {"coordinates":[109.04000000000001,-7.53],"type":"Point"}
}