{
  "type": "Feature",
  "properties": {
    "gn:admin1_code":"26",
    "gn:asciiname":"Lae Garut",
    "gn:country_code":"ID",
    "gn:dem":527,
    "gn:feature_class":"P",
    "gn:feature_code":"PPL",
    "gn:name":"Lae Garut",
    "gn:population":0,
    "gn:timezone":"Asia/Jakarta",
    "iso:country":"ID",
    "name:ind_x_preferred":[
        "Lae Garut"
    ],
    "wof:name":"Lae Garut",
    "wof:placetype":"locality"
},
  "geometry": {"coordinates":[98.1234,2.8736],"type":"Point"}
}