{
  "type": "Feature",
  "properties": {
    "gn:admin1_code":"38.0",
    "gn:asciiname":"Maddenra",
    "gn:country_code":"ID",
    "gn:dem":49,
    "gn:feature_class":"P",
    "gn:feature_code":"PPL",
    "gn:name":"Maddenra",
    "gn:population":0,
    "gn:timezone":"Asia/Makassar",
    "iso:country":"ID",
    "name:ind_x_preferred":[
        "Maddenra"
    ],
    "wof:name":"Maddenra",
    "wof:placetype":"locality"
},
  "geometry": {"coordinates":[119.79819999999999,-3.7679],"type":"Point"}
}