{
  "type": "Feature",
  "properties": {
    "gn:admin1_code":"30.0",
    "gn:asciiname":"Batara",
    "gn:country_code":"ID",
    "gn:dem":631,
    "gn:feature_class":"P",
    "gn:feature_code":"PPL",
    "gn:name":"Batara",
    "gn:population":0,
    "gn:timezone":"Asia/Jakarta",
    "iso:country":"ID",
    "name:ceb_x_preferred":[
        "Batara"
    ],
    "name:deu_x_preferred":[
        "Batara"
    ],
    "name:fra_x_preferred":[
        "Batara"
    ],
    "name:ind_x_preferred":[
        "Batara"
    ],
    "name:pol_x_preferred":[
        "Batara"
    ],
    "name:swe_x_preferred":[
        "Batara"
    ],
    "wof:name":"Batara",
    "wof:placetype":"locality"
},
  "geometry": {"coordinates":[108.0257,-7.3407],"type":"Point"}
}