{
  "type": "Feature",
  "properties": {
    "gn:admin1_code":"7",
    "gn:asciiname":"Ngablak",
    "gn:country_code":"ID",
    "gn:dem":5,
    "gn:feature_class":"P",
    "gn:feature_code":"PPL",
    "gn:name":"Ngablak",
    "gn:population":0,
    "gn:timezone":"Asia/Jakarta",
    "iso:country":"ID",
    "name:ind_x_preferred":[
        "Ngablak"
    ],
    "wof:name":"Ngablak",
    "wof:placetype":"locality"
},
  "geometry": {"coordinates":[110.4644,-6.9721],"type":"Point"}
}