{
  "type": "Feature",
  "properties": {
    "gn:admin1_code":"30.0",
    "gn:asciiname":"Cikole",
    "gn:country_code":"ID",
    "gn:dem":895,
    "gn:feature_class":"P",
    "gn:feature_code":"PPL",
    "gn:name":"Cikole",
    "gn:population":0,
    "gn:timezone":"Asia/Jakarta",
    "iso:country":"ID",
    "name:ind_x_preferred":[
        "Cikole"
    ],
    "name:und_x_variant":[
        "Tjikale-hilir",
        "Cikale-hilir",
        "Tjikole-hilir"
    ],
    "wof:name":"Cikole",
    "wof:placetype":"locality"
},
  "geometry": {"coordinates":[107.79389999999999,-7.4876],"type":"Point"}
}