{
  "type": "Feature",
  "properties": {
    "gn:admin1_code":"28.0",
    "gn:asciiname":"Kulaim",
    "gn:country_code":"ID",
    "gn:dem":10,
    "gn:feature_class":"P",
    "gn:feature_code":"PPL",
    "gn:name":"Kulaim",
    "gn:population":0,
    "gn:timezone":"Asia/Jayapura",
    "iso:country":"ID",
    "name:ind_x_preferred":[
        "Kulaim"
    ],
    "name:und_x_variant":[
        "Koelaim"
    ],
    "wof:name":"Kulaim",
    "wof:placetype":"locality"
},
  "geometry": {"coordinates":[134.76751999999999,-5.88608],"type":"Point"}
}