{
  "type": "Feature",
  "properties": {
    "gn:admin1_code":"8.0",
    "gn:asciiname":"Buret",
    "gn:country_code":"ID",
    "gn:dem":115,
    "gn:feature_class":"P",
    "gn:feature_code":"PPL",
    "gn:name":"Buret",
    "gn:population":0,
    "gn:timezone":"Asia/Jakarta",
    "iso:country":"ID",
    "name:ceb_x_preferred":[
        "Buret"
    ],
    "name:deu_x_preferred":[
        "Buret"
    ],
    "name:fra_x_preferred":[
        "Buret"
    ],
    "name:ind_x_preferred":[
        "Buret"
    ],
    "wof:lang_x_official":[
        "ind"
    ],
    "wof:lang_x_spoken":[
        "ind",
        "eng"
    ],
    "wof:name":"Buret",
    "wof:placetype":"locality"
},
  "geometry": {"coordinates":[111.6807,-8.0456],"type":"Point"}
}