{
  "type": "Feature",
  "properties": {
    "gn:admin1_code":"7",
    "gn:asciiname":"Tembelang",
    "gn:country_code":"ID",
    "gn:dem":1078,
    "gn:feature_class":"P",
    "gn:feature_code":"PPL",
    "gn:name":"Tembelang",
    "gn:population":0,
    "gn:timezone":"Asia/Jakarta",
    "iso:country":"ID",
    "name:ind_x_preferred":[
        "Tembelang"
    ],
    "wof:name":"Tembelang",
    "wof:placetype":"locality"
},
  "geometry": {"coordinates":[109.70417,-7.24944],"type":"Point"}
}