{
  "type": "Feature",
  "properties": {
    "gn:admin1_code":"2",
    "gn:asciiname":"Tengah",
    "gn:country_code":"ID",
    "gn:dem":13,
    "gn:feature_class":"P",
    "gn:feature_code":"PPL",
    "gn:name":"Tengah",
    "gn:population":0,
    "gn:timezone":"Asia/Makassar",
    "iso:country":"ID",
    "name:ind_x_preferred":[
        "Tengah"
    ],
    "wof:name":"Tengah",
    "wof:placetype":"locality"
},
  "geometry": {"coordinates":[114.62050000000001,-8.3593],"type":"Point"}
}