{
  "type": "Feature",
  "properties": {
    "gn:admin1_code":"7.0",
    "gn:asciiname":"Tohok",
    "gn:country_code":"ID",
    "gn:dem":215,
    "gn:feature_class":"P",
    "gn:feature_code":"PPL",
    "gn:name":"Tohok",
    "gn:population":0,
    "gn:timezone":"Asia/Jakarta",
    "iso:country":"ID",
    "name:ind_x_preferred":[
        "Tohok"
    ],
    "wof:name":"Tohok",
    "wof:placetype":"locality"
},
  "geometry": {"coordinates":[109.59444000000001,-7.38417],"type":"Point"}
}