{
  "type": "Feature",
  "properties": {
    "gn:admin1_code":"8",
    "gn:asciiname":"Pringgading",
    "gn:country_code":"ID",
    "gn:dem":531,
    "gn:feature_class":"P",
    "gn:feature_code":"PPL",
    "gn:name":"Pringgading",
    "gn:population":0,
    "gn:timezone":"Asia/Jakarta",
    "iso:country":"ID",
    "name:ind_x_preferred":[
        "Pringgading"
    ],
    "wof:name":"Pringgading",
    "wof:placetype":"locality"
},
  "geometry": {"coordinates":[114.3008,-8.141],"type":"Point"}
}