{
  "type": "Feature",
  "properties": {
    "gn:admin1_code":"15.0",
    "gn:asciiname":"Talangbontor",
    "gn:country_code":"ID",
    "gn:dem":151,
    "gn:feature_class":"P",
    "gn:feature_code":"PPL",
    "gn:name":"Talangbontor",
    "gn:population":0,
    "gn:timezone":"Asia/Jakarta",
    "iso:country":"ID",
    "name:ind_x_preferred":[
        "Talangbontor"
    ],
    "wof:name":"Talangbontor",
    "wof:placetype":"locality"
},
  "geometry": {"coordinates":[104.89962,-5.29586],"type":"Point"}
}