{
  "type": "Feature",
  "properties": {
    "gn:admin1_code":"7.0",
    "gn:asciiname":"Citemba",
    "gn:country_code":"ID",
    "gn:dem":19,
    "gn:feature_class":"P",
    "gn:feature_code":"PPL",
    "gn:name":"Citemba",
    "gn:population":0,
    "gn:timezone":"Asia/Jakarta",
    "iso:country":"ID",
    "name:ind_x_preferred":[
        "Citemba"
    ],
    "wof:name":"Citemba",
    "wof:placetype":"locality"
},
  "geometry": {"coordinates":[108.93639,-7.57889],"type":"Point"}
}