{
  "type": "Feature",
  "properties": {
    "gn:admin1_code":"8.0",
    "gn:asciiname":"Sukomulyo",
    "gn:country_code":"ID",
    "gn:dem":471,
    "gn:feature_class":"P",
    "gn:feature_code":"PPL",
    "gn:name":"Sukomulyo",
    "gn:population":0,
    "gn:timezone":"Asia/Jakarta",
    "iso:country":"ID",
    "name:ind_x_preferred":[
        "Sukomulyo"
    ],
    "wof:name":"Sukomulyo",
    "wof:placetype":"locality"
},
  "geometry": {"coordinates":[112.6718,-8.0392],"type":"Point"}
}