{
  "type": "Feature",
  "properties": {
    "gn:admin1_code":"7.0",
    "gn:asciiname":"Krajan",
    "gn:country_code":"ID",
    "gn:dem":494,
    "gn:feature_class":"P",
    "gn:feature_code":"PPL",
    "gn:name":"Krajan",
    "gn:population":0,
    "gn:timezone":"Asia/Jakarta",
    "iso:country":"ID",
    "wof:name":"Krajan",
    "wof:placetype":"locality"
},
  "geometry": {"coordinates":[110.59639,-7.37806],"type":"Point"}
}