{
  "type": "Feature",
  "properties": {
    "gn:admin1_code":"33.0",
    "gn:asciiname":"Kampungsawah",
    "gn:country_code":"ID",
    "gn:dem":186,
    "gn:feature_class":"P",
    "gn:feature_code":"PPL",
    "gn:name":"Kampungsawah",
    "gn:population":0,
    "gn:timezone":"Asia/Jakarta",
    "iso:country":"ID",
    "name:ind_x_preferred":[
        "Kampungsawah"
    ],
    "wof:name":"Kampungsawah",
    "wof:placetype":"locality"
},
  "geometry": {"coordinates":[106.01900000000001,-6.2099],"type":"Point"}
}