{
  "type": "Feature",
  "properties": {
    "gn:admin1_code":"38",
    "gn:asciiname":"Awa",
    "gn:country_code":"ID",
    "gn:dem":861,
    "gn:feature_class":"P",
    "gn:feature_code":"PPL",
    "gn:name":"Awa",
    "gn:population":0,
    "gn:timezone":"Asia/Makassar",
    "iso:country":"ID",
    "name:ind_x_preferred":[
        "Awa"
    ],
    "wof:name":"Awa",
    "wof:placetype":"locality"
},
  "geometry": {"coordinates":[119.80110000000001,-3.0549],"type":"Point"}
}