{
  "type": "Feature",
  "properties": {
    "gn:admin1_code":"26",
    "gn:asciiname":"Aek Bargot",
    "gn:country_code":"ID",
    "gn:dem":210,
    "gn:feature_class":"P",
    "gn:feature_code":"PPL",
    "gn:name":"Aek Bargot",
    "gn:population":0,
    "gn:timezone":"Asia/Jakarta",
    "iso:country":"ID",
    "name:ind_x_preferred":[
        "Aek Bargot"
    ],
    "wof:name":"Aek Bargot",
    "wof:placetype":"locality"
},
  "geometry": {"coordinates":[99.46254999999999,1.44694],"type":"Point"}
}