{
  "type": "Feature",
  "properties": {
    "gn:admin1_code":"8",
    "gn:asciiname":"Pelle Kidul",
    "gn:country_code":"ID",
    "gn:dem":758,
    "gn:feature_class":"P",
    "gn:feature_code":"PPL",
    "gn:name":"Pelle Kidul",
    "gn:population":0,
    "gn:timezone":"Asia/Jakarta",
    "iso:country":"ID",
    "name:ind_x_preferred":[
        "Pelle Kidul"
    ],
    "wof:name":"Pelle Kidul",
    "wof:placetype":"locality"
},
  "geometry": {"coordinates":[114.155,-7.9079],"type":"Point"}
}