{
  "type": "Feature",
  "properties": {
    "gn:admin1_code":"30.0",
    "gn:asciiname":"Winangga",
    "gn:country_code":"ID",
    "gn:dem":53,
    "gn:feature_class":"P",
    "gn:feature_code":"PPL",
    "gn:name":"Winangga",
    "gn:population":0,
    "gn:timezone":"Asia/Jakarta",
    "iso:country":"ID",
    "name:ind_x_preferred":[
        "Winangga"
    ],
    "wof:name":"Winangga",
    "wof:placetype":"locality"
},
  "geometry": {"coordinates":[108.32528000000001,-6.72278],"type":"Point"}
}