{
  "type": "Feature",
  "properties": {
    "gn:admin1_code":"38.0",
    "gn:asciiname":"Balombong",
    "gn:country_code":"ID",
    "gn:dem":570,
    "gn:feature_class":"P",
    "gn:feature_code":"PPL",
    "gn:name":"Balombong",
    "gn:population":0,
    "gn:timezone":"Asia/Makassar",
    "iso:country":"ID",
    "name:ind_x_preferred":[
        "Balombong"
    ],
    "wof:name":"Balombong",
    "wof:placetype":"locality"
},
  "geometry": {"coordinates":[119.8758,-3.3883],"type":"Point"}
}