{
  "type": "Feature",
  "properties": {
    "gn:admin1_code":"18.0",
    "gn:asciiname":"Hanijar",
    "gn:country_code":"ID",
    "gn:dem":205,
    "gn:feature_class":"P",
    "gn:feature_code":"PPL",
    "gn:name":"Hanijar",
    "gn:population":0,
    "gn:timezone":"Asia/Makassar",
    "iso:country":"ID",
    "name:ind_x_preferred":[
        "Hanijar"
    ],
    "wof:name":"Hanijar",
    "wof:placetype":"locality"
},
  "geometry": {"coordinates":[124.369,-8.292],"type":"Point"}
}