{
  "type": "Feature",
  "properties": {
    "gn:admin1_code":"30",
    "gn:asciiname":"Munjul Dua",
    "gn:country_code":"ID",
    "gn:dem":87,
    "gn:feature_class":"P",
    "gn:feature_code":"PPL",
    "gn:name":"Munjul Dua",
    "gn:population":0,
    "gn:timezone":"Asia/Jakarta",
    "iso:country":"ID",
    "name:ind_x_preferred":[
        "Munjul Dua"
    ],
    "wof:name":"Munjul Dua",
    "wof:placetype":"locality"
},
  "geometry": {"coordinates":[107.47638999999999,-6.5325],"type":"Point"}
}