{
  "type": "Feature",
  "properties": {
    "gn:admin1_code":"18.0",
    "gn:asciiname":"Lao",
    "gn:country_code":"ID",
    "gn:dem":1146,
    "gn:feature_class":"P",
    "gn:feature_code":"PPL",
    "gn:name":"Lao",
    "gn:population":0,
    "gn:timezone":"Asia/Makassar",
    "iso:country":"ID",
    "name:cat_x_preferred":[
        "Lao"
    ],
    "name:ceb_x_preferred":[
        "Lao"
    ],
    "name:cym_x_preferred":[
        "Lao"
    ],
    "name:fin_x_preferred":[
        "Lao"
    ],
    "name:fra_x_preferred":[
        "Lao"
    ],
    "name:hrv_x_preferred":[
        "Lao"
    ],
    "name:ind_x_preferred":[
        "Lao"
    ],
    "name:nld_x_preferred":[
        "Lao"
    ],
    "name:pol_x_preferred":[
        "Lao"
    ],
    "name:por_x_preferred":[
        "Lao"
    ],
    "name:spa_x_preferred":[
        "Lao"
    ],
    "name:swe_x_preferred":[
        "Lao"
    ],
    "name:uzb_x_preferred":[
        "Lao"
    ],
    "name:vie_x_preferred":[
        "Lao"
    ],
    "wof:lang_x_official":[
        "ind"
    ],
    "wof:lang_x_spoken":[
        "ind",
        "eng"
    ],
    "wof:name":"Lao",
    "wof:placetype":"locality"
},
  "geometry": {"coordinates":[120.44629999999999,-8.6066],"type":"Point"}
}