{
  "type": "Feature",
  "properties": {
    "gn:admin1_code":"18.0",
    "gn:asciiname":"Lao",
    "gn:country_code":"ID",
    "gn:dem":1146,
    "gn:feature_class":"P",
    "gn:feature_code":"PPL",
    "gn:name":"Lao",
    "gn:population":0,
    "gn:timezone":"Asia/Makassar",
    "iso:country":"ID",
    "name:ind_x_preferred":[
        "Lao"
    ],
    "wof:name":"Lao",
    "wof:placetype":"locality"
},
  "geometry": {"coordinates":[120.44629999999999,-8.6066],"type":"Point"}
}