{
  "type": "Feature",
  "properties": {
    "gn:admin1_code":"30.0",
    "gn:asciiname":"Cicareuh",
    "gn:country_code":"ID",
    "gn:dem":616,
    "gn:feature_class":"P",
    "gn:feature_code":"PPL",
    "gn:name":"Cicareuh",
    "gn:population":0,
    "gn:timezone":"Asia/Jakarta",
    "iso:country":"ID",
    "name:ind_x_preferred":[
        "Cicareuh"
    ],
    "wof:name":"Cicareuh",
    "wof:placetype":"locality"
},
  "geometry": {"coordinates":[107.9175,-7.4889],"type":"Point"}
}