{
  "type": "Feature",
  "properties": {
    "gn:admin1_code":"7.0",
    "gn:asciiname":"Cilakar",
    "gn:country_code":"ID",
    "gn:dem":74,
    "gn:feature_class":"P",
    "gn:feature_code":"PPL",
    "gn:name":"Cilakar",
    "gn:population":0,
    "gn:timezone":"Asia/Jakarta",
    "iso:country":"ID",
    "name:ind_x_preferred":[
        "Cilakar"
    ],
    "wof:name":"Cilakar",
    "wof:placetype":"locality"
},
  "geometry": {"coordinates":[108.93222,-7.23306],"type":"Point"}
}