{
  "type": "Feature",
  "properties": {
    "gn:admin1_code":"8.0",
    "gn:asciiname":"Klepu",
    "gn:country_code":"ID",
    "gn:dem":297,
    "gn:feature_class":"P",
    "gn:feature_code":"PPL",
    "gn:name":"Klepu",
    "gn:population":0,
    "gn:timezone":"Asia/Jakarta",
    "iso:country":"ID",
    "name:ind_x_preferred":[
        "Klepu"
    ],
    "wof:name":"Klepu",
    "wof:placetype":"locality"
},
  "geometry": {"coordinates":[111.13583,-8.24333],"type":"Point"}
}