{
  "type": "Feature",
  "properties": {
    "gn:admin1_code":"7",
    "gn:asciiname":"Liyangan",
    "gn:country_code":"ID",
    "gn:dem":159,
    "gn:feature_class":"P",
    "gn:feature_code":"PPL",
    "gn:name":"Liyangan",
    "gn:population":0,
    "gn:timezone":"Asia/Jakarta",
    "iso:country":"ID",
    "name:ind_x_preferred":[
        "Liyangan"
    ],
    "name:ind_x_variant":[
        "Candi Liyangan"
    ],
    "name:jav_x_preferred":[
        "Candhi Liyangan"
    ],
    "name:tat_x_preferred":[
        "\u041b\u0438\u044f\u043d\u0433\u0430\u043d"
    ],
    "wof:lang_x_official":[
        "ind"
    ],
    "wof:lang_x_spoken":[
        "ind",
        "eng"
    ],
    "wof:name":"Liyangan",
    "wof:placetype":"locality"
},
  "geometry": {"coordinates":[109.8734,-6.9757],"type":"Point"}
}