{
  "type": "Feature",
  "properties": {
    "gn:admin1_code":"07",
    "gn:asciiname":"Nglimut",
    "gn:country_code":"ID",
    "gn:dem":612,
    "gn:feature_class":"P",
    "gn:feature_code":"PPL",
    "gn:name":"Nglimut",
    "gn:population":0,
    "gn:timezone":"Asia/Jakarta",
    "iso:country":"ID",
    "name:ind_x_preferred":[
        "Nglimut"
    ],
    "wof:lang_x_official":[
        "ind"
    ],
    "wof:lang_x_spoken":[
        "ind",
        "eng"
    ],
    "wof:name":"Nglimut",
    "wof:placetype":"locality"
},
  "geometry": {"coordinates":[110.32556,-7.14056],"type":"Point"}
}