{
  "type": "Feature",
  "properties": {
    "gn:admin1_code":"7.0",
    "gn:asciiname":"Surodadi",
    "gn:country_code":"ID",
    "gn:dem":1256,
    "gn:feature_class":"P",
    "gn:feature_code":"PPL",
    "gn:name":"Surodadi",
    "gn:population":0,
    "gn:timezone":"Asia/Jakarta",
    "iso:country":"ID",
    "wof:name":"Surodadi",
    "wof:placetype":"locality"
},
  "geometry": {"coordinates":[110.48917,-7.47167],"type":"Point"}
}