{
  "type": "Feature",
  "properties": {
    "gn:admin1_code":"18.0",
    "gn:asciiname":"Tamara",
    "gn:country_code":"ID",
    "gn:dem":14,
    "gn:feature_class":"P",
    "gn:feature_code":"PPL",
    "gn:name":"Tamara",
    "gn:population":0,
    "gn:timezone":"Asia/Makassar",
    "iso:country":"ID",
    "name:ceb_x_preferred":[
        "Tamara"
    ],
    "name:ces_x_preferred":[
        "Tamara"
    ],
    "name:deu_x_preferred":[
        "Tamara"
    ],
    "name:est_x_preferred":[
        "Tamara"
    ],
    "name:fra_x_preferred":[
        "Tamara"
    ],
    "name:hun_x_preferred":[
        "Tamara"
    ],
    "name:ind_x_preferred":[
        "Tamara"
    ],
    "name:ita_x_preferred":[
        "Tamara"
    ],
    "name:jpn_x_preferred":[
        "\u30bf\u30de\u30e9"
    ],
    "name:mal_x_preferred":[
        "\u0d1f\u0d2e\u0d3e\u0d30"
    ],
    "name:pol_x_preferred":[
        "Tamara"
    ],
    "name:por_x_preferred":[
        "Tamara"
    ],
    "name:rus_x_preferred":[
        "\u0422\u0430\u043c\u0430\u0440\u0430"
    ],
    "name:spa_x_preferred":[
        "Tamara"
    ],
    "name:srp_x_preferred":[
        "\u0422\u0430\u043c\u0430\u0440\u0430"
    ],
    "name:swe_x_preferred":[
        "Tamara"
    ],
    "name:ukr_x_preferred":[
        "\u0422\u0430\u043c\u0430\u0440\u0430"
    ],
    "wof:name":"Tamara",
    "wof:placetype":"locality"
},
  "geometry": {"coordinates":[119.9537,-9.9678],"type":"Point"}
}