{
  "type": "Feature",
  "properties": {
    "gn:admin1_code":"0.0",
    "gn:asciiname":"Minas",
    "gn:country_code":"ID",
    "gn:dem":17,
    "gn:feature_class":"P",
    "gn:feature_code":"PPL",
    "gn:name":"Minas",
    "gn:population":0,
    "gn:timezone":"Asia/Jakarta",
    "iso:country":"ID",
    "name:ceb_x_preferred":[
        "Minas"
    ],
    "name:deu_x_preferred":[
        "Minas"
    ],
    "name:fra_x_preferred":[
        "Minas"
    ],
    "name:hye_x_preferred":[
        "\u0544\u056b\u0576\u0561\u057d"
    ],
    "name:ind_x_preferred":[
        "Minas"
    ],
    "name:nld_x_preferred":[
        "Minas"
    ],
    "name:por_x_preferred":[
        "Minas"
    ],
    "name:rus_x_preferred":[
        "\u041c\u0438\u043d\u0430\u0441"
    ],
    "name:sco_x_preferred":[
        "Minas"
    ],
    "name:srp_x_preferred":[
        "\u041c\u0438\u043d\u0430\u0441"
    ],
    "name:swe_x_preferred":[
        "Minas"
    ],
    "name:ukr_x_preferred":[
        "\u041c\u0456\u043d\u0430\u0441"
    ],
    "wof:lang_x_official":[
        "ind"
    ],
    "wof:lang_x_spoken":[
        "ind",
        "eng"
    ],
    "wof:name":"Minas",
    "wof:placetype":"locality"
},
  "geometry": {"coordinates":[101.48196,0.87211],"type":"Point"}
}