{
  "type": "Feature",
  "properties": {
    "gn:admin1_code":"7.0",
    "gn:asciiname":"Binuang",
    "gn:country_code":"ID",
    "gn:dem":386,
    "gn:feature_class":"P",
    "gn:feature_code":"PPL",
    "gn:name":"Binuang",
    "gn:population":0,
    "gn:timezone":"Asia/Jakarta",
    "iso:country":"ID",
    "name:ind_x_preferred":[
        "Binuang"
    ],
    "name:und_x_variant":[
        "Binoewang Satu"
    ],
    "wof:name":"Binuang",
    "wof:placetype":"locality"
},
  "geometry": {"coordinates":[108.7467,-7.2299],"type":"Point"}
}