{
  "type": "Feature",
  "properties": {
    "gn:admin1_code":"7",
    "gn:asciiname":"Trebing",
    "gn:country_code":"ID",
    "gn:dem":144,
    "gn:feature_class":"P",
    "gn:feature_code":"PPL",
    "gn:name":"Trebing",
    "gn:population":0,
    "gn:timezone":"Asia/Jakarta",
    "iso:country":"ID",
    "name:ind_x_preferred":[
        "Trebing"
    ],
    "wof:name":"Trebing",
    "wof:placetype":"locality"
},
  "geometry": {"coordinates":[110.76519999999999,-6.6651],"type":"Point"}
}