{
  "type": "Feature",
  "properties": {
    "gn:admin1_code":"37",
    "gn:asciiname":"Tanjungpulai",
    "gn:country_code":"ID",
    "gn:dem":9,
    "gn:feature_class":"P",
    "gn:feature_code":"PPL",
    "gn:name":"Tanjungpulai",
    "gn:population":0,
    "gn:timezone":"Asia/Jakarta",
    "iso:country":"ID",
    "name:ind_x_preferred":[
        "Tanjungpulai"
    ],
    "wof:name":"Tanjungpulai",
    "wof:placetype":"locality"
},
  "geometry": {"coordinates":[102.81483,0.257],"type":"Point"}
}