{
  "type": "Feature",
  "properties": {
    "gn:admin1_code":"30",
    "gn:asciiname":"Jarakkosta",
    "gn:country_code":"ID",
    "gn:dem":27,
    "gn:feature_class":"P",
    "gn:feature_code":"PPL",
    "gn:name":"Jarakkosta",
    "gn:population":0,
    "gn:timezone":"Asia/Jakarta",
    "iso:country":"ID",
    "name:ind_x_preferred":[
        "Jarakkosta"
    ],
    "name:und_x_variant":[
        "Jarakasta"
    ],
    "wof:name":"Jarakkosta",
    "wof:placetype":"locality"
},
  "geometry": {"coordinates":[107.10417,-6.29167],"type":"Point"}
}