{
  "type": "Feature",
  "properties": {
    "gn:admin1_code":"30",
    "gn:asciiname":"Keluwungbaya Dua",
    "gn:cc2":"ID",
    "gn:country_code":"ID",
    "gn:dem":10,
    "gn:feature_class":"P",
    "gn:feature_code":"PPL",
    "gn:name":"Keluwungbaya Dua",
    "gn:population":0,
    "gn:timezone":"Asia/Jakarta",
    "iso:country":"ID",
    "name:und_x_variant":[
        "Keluwungbaja 2",
        "Keluwungbaja Dua",
        "Keluwungbaya Dua"
    ],
    "wof:name":"Keluwungbaya Dua",
    "wof:placetype":"locality"
},
  "geometry": {"coordinates":[106.37,-6.07444],"type":"Point"}
}