{
  "type": "Feature",
  "properties": {
    "gn:admin1_code":"21",
    "gn:asciiname":"Ogogili",
    "gn:country_code":"ID",
    "gn:dem":13,
    "gn:feature_class":"P",
    "gn:feature_code":"PPL",
    "gn:name":"Ogogili",
    "gn:population":0,
    "gn:timezone":"Asia/Makassar",
    "iso:country":"ID",
    "name:ind_x_preferred":[
        "Ogogili"
    ],
    "wof:name":"Ogogili",
    "wof:placetype":"locality"
},
  "geometry": {"coordinates":[120.51439999999999,0.791],"type":"Point"}
}