{
  "type": "Feature",
  "properties": {
    "gn:admin1_code":"30",
    "gn:asciiname":"Kliwon",
    "gn:country_code":"ID",
    "gn:dem":228,
    "gn:feature_class":"P",
    "gn:feature_code":"PPL",
    "gn:name":"Kliwon",
    "gn:population":0,
    "gn:timezone":"Asia/Jakarta",
    "iso:country":"ID",
    "name:ind_x_preferred":[
        "Kliwon"
    ],
    "wof:name":"Kliwon",
    "wof:placetype":"locality"
},
  "geometry": {"coordinates":[108.5778,-6.9657],"type":"Point"}
}