{
  "type": "Feature",
  "properties": {
    "gn:admin1_code":"12.0",
    "gn:asciiname":"Tanbakarangan",
    "gn:country_code":"ID",
    "gn:dem":6,
    "gn:feature_class":"P",
    "gn:feature_code":"PPL",
    "gn:name":"Tanbakarangan",
    "gn:population":0,
    "gn:timezone":"Asia/Makassar",
    "iso:country":"ID",
    "name:ind_x_preferred":[
        "Tanbakarangan"
    ],
    "name:und_x_variant":[
        "Tambakkarangan"
    ],
    "wof:name":"Tanbakarangan",
    "wof:placetype":"locality"
},
  "geometry": {"coordinates":[114.6349,-3.5966],"type":"Point"}
}