{
  "type": "Feature",
  "properties": {
    "gn:admin1_code":"7.0",
    "gn:asciiname":"Pakebonan",
    "gn:country_code":"ID",
    "gn:dem":18,
    "gn:feature_class":"P",
    "gn:feature_code":"PPL",
    "gn:name":"Pakebonan",
    "gn:population":0,
    "gn:timezone":"Asia/Jakarta",
    "iso:country":"ID",
    "name:ind_x_preferred":[
        "Pakebonan"
    ],
    "wof:name":"Pakebonan",
    "wof:placetype":"locality"
},
  "geometry": {"coordinates":[109.20111,-7.53917],"type":"Point"}
}