{
  "type": "Feature",
  "properties": {
    "gn:admin1_code":"42.0",
    "gn:asciiname":"Siakkemuat",
    "gn:country_code":"ID",
    "gn:dem":276,
    "gn:feature_class":"P",
    "gn:feature_code":"PPL",
    "gn:name":"Siakkemuat",
    "gn:population":0,
    "gn:timezone":"Asia/Makassar",
    "iso:country":"ID",
    "name:und_x_variant":[
        "Kalipos",
        "Siakkemoeat",
        "Siakkemuat"
    ],
    "wof:lang_x_official":[
        "ind"
    ],
    "wof:lang_x_spoken":[
        "ind",
        "eng"
    ],
    "wof:name":"Siakkemuat",
    "wof:placetype":"locality"
},
  "geometry": {"coordinates":[116.13158,3.74324],"type":"Point"}
}