{
  "type": "Feature",
  "properties": {
    "iso:country":"ID",
    "qs:name":"Pemogan",
    "qs:name_adm0":"Indonesia",
    "qs:name_adm1":"Bali",
    "qs:photos":117,
    "qs:photos_1k":24,
    "qs:photos_9k":1,
    "qs:photos_9r":3,
    "qs:photos_all":117,
    "qs:photos_sr":3,
    "qs:placetype":"Town",
    "qs:pop_sr":"0",
    "wof:name":"Pemogan",
    "wof:placetype":"locality"
},
  "geometry": {"coordinates":[115.19425699999999,-8.72016],"type":"Point"}
}