{
  "type": "Feature",
  "properties": {
    "gn:admin1_code":"1.0",
    "gn:asciiname":"Babahawe",
    "gn:country_code":"ID",
    "gn:dem":4,
    "gn:feature_class":"P",
    "gn:feature_code":"PPL",
    "gn:name":"Babahawe",
    "gn:population":0,
    "gn:timezone":"Asia/Jakarta",
    "iso:country":"ID",
    "name:ind_x_preferred":[
        "Babahawe"
    ],
    "wof:name":"Babahawe",
    "wof:placetype":"locality"
},
  "geometry": {"coordinates":[95.3792,4.9583],"type":"Point"}
}