{
  "type": "Feature",
  "properties": {
    "gn:admin1_code":"30",
    "gn:asciiname":"Sakambang",
    "gn:country_code":"ID",
    "gn:dem":721,
    "gn:feature_class":"P",
    "gn:feature_code":"PPL",
    "gn:name":"Sakambang",
    "gn:population":0,
    "gn:timezone":"Asia/Jakarta",
    "iso:country":"ID",
    "name:ind_x_preferred":[
        "Sakambang"
    ],
    "wof:name":"Sakambang",
    "wof:placetype":"locality"
},
  "geometry": {"coordinates":[107.53610999999999,-6.70444],"type":"Point"}
}