{
  "type": "Feature",
  "properties": {
    "gn:admin1_code":"7",
    "gn:asciiname":"Seceleng Selatan",
    "gn:country_code":"ID",
    "gn:dem":6,
    "gn:feature_class":"P",
    "gn:feature_code":"PPL",
    "gn:name":"Seceleng Selatan",
    "gn:population":0,
    "gn:timezone":"Asia/Jakarta",
    "iso:country":"ID",
    "name:ind_x_preferred":[
        "Seceleng Selatan"
    ],
    "wof:name":"Seceleng Selatan",
    "wof:placetype":"locality"
},
  "geometry": {"coordinates":[109.58110000000001,-6.8645],"type":"Point"}
}