{
  "type": "Feature",
  "properties": {
    "gn:admin1_code":"18.0",
    "gn:asciiname":"Werabuk",
    "gn:country_code":"ID",
    "gn:dem":344,
    "gn:feature_class":"P",
    "gn:feature_code":"PPL",
    "gn:name":"Werabuk",
    "gn:population":0,
    "gn:timezone":"Asia/Makassar",
    "iso:country":"ID",
    "name:ind_x_preferred":[
        "Werabuk"
    ],
    "wof:name":"Werabuk",
    "wof:placetype":"locality"
},
  "geometry": {"coordinates":[119.3695,-9.4818],"type":"Point"}
}