{
  "type": "Feature",
  "properties": {
    "gn:admin1_code":"30",
    "gn:asciiname":"Cieter",
    "gn:country_code":"ID",
    "gn:dem":1316,
    "gn:feature_class":"P",
    "gn:feature_code":"PPL",
    "gn:name":"Cieter",
    "gn:population":0,
    "gn:timezone":"Asia/Jakarta",
    "iso:country":"ID",
    "name:ind_x_preferred":[
        "Cieter"
    ],
    "name:und_x_variant":[
        "Tjitundjang",
        "Citunjang"
    ],
    "wof:name":"Cieter",
    "wof:placetype":"locality"
},
  "geometry": {"coordinates":[107.41240000000001,-7.0693],"type":"Point"}
}