{
  "type": "Feature",
  "properties": {
    "gn:admin1_code":"38",
    "gn:asciiname":"Talle",
    "gn:country_code":"ID",
    "gn:dem":691,
    "gn:feature_class":"P",
    "gn:feature_code":"PPL",
    "gn:name":"Talle",
    "gn:population":0,
    "gn:timezone":"Asia/Makassar",
    "iso:country":"ID",
    "name:ind_x_preferred":[
        "Talle"
    ],
    "wof:name":"Talle",
    "wof:placetype":"locality"
},
  "geometry": {"coordinates":[120.0089,-5.444],"type":"Point"}
}