{
  "type": "Feature",
  "properties": {
    "gn:admin1_code":"26.0",
    "gn:asciiname":"Dolok Nauli",
    "gn:country_code":"ID",
    "gn:dem":1298,
    "gn:feature_class":"P",
    "gn:feature_code":"PPL",
    "gn:name":"Dolok Nauli",
    "gn:population":0,
    "gn:timezone":"Asia/Jakarta",
    "iso:country":"ID",
    "name:ind_x_preferred":[
        "Dolok Nauli"
    ],
    "wof:name":"Dolok Nauli",
    "wof:placetype":"locality"
},
  "geometry": {"coordinates":[98.74120000000001,2.6457],"type":"Point"}
}