{
  "type": "Feature",
  "properties": {
    "gn:admin1_code":"18.0",
    "gn:asciiname":"Honemaga",
    "gn:country_code":"ID",
    "gn:dem":54,
    "gn:feature_class":"P",
    "gn:feature_code":"PPL",
    "gn:name":"Honemaga",
    "gn:population":0,
    "gn:timezone":"Asia/Makassar",
    "iso:country":"ID",
    "name:ind_x_preferred":[
        "Honemaga"
    ],
    "wof:name":"Honemaga",
    "wof:placetype":"locality"
},
  "geometry": {"coordinates":[123.5497,-8.2508],"type":"Point"}
}