{
  "type": "Feature",
  "properties": {
    "gn:admin1_code":"8",
    "gn:asciiname":"Dusun Selatan",
    "gn:country_code":"ID",
    "gn:dem":177,
    "gn:feature_class":"P",
    "gn:feature_code":"PPL",
    "gn:name":"Dusun Selatan",
    "gn:population":0,
    "gn:timezone":"Asia/Jakarta",
    "iso:country":"ID",
    "name:ind_x_preferred":[
        "Dusun Selatan"
    ],
    "wof:name":"Dusun Selatan",
    "wof:placetype":"locality"
},
  "geometry": {"coordinates":[114.22320000000001,-7.8267],"type":"Point"}
}