{
  "type": "Feature",
  "properties": {
    "gn:admin1_code":"07",
    "gn:asciiname":"Dalaman",
    "gn:country_code":"ID",
    "gn:dem":583,
    "gn:feature_class":"P",
    "gn:feature_code":"PPL",
    "gn:name":"Dalaman",
    "gn:population":0,
    "gn:timezone":"Asia/Jakarta",
    "iso:country":"ID",
    "name:ara_x_preferred":[
        "\u062f\u0627\u0644\u0627\u0645\u0627\u0646"
    ],
    "name:azb_x_preferred":[
        "\u062f\u0627\u0644\u0627\u0645\u0627\u0646"
    ],
    "name:ceb_x_preferred":[
        "Dalaman"
    ],
    "name:deu_x_preferred":[
        "Dalaman"
    ],
    "name:epo_x_preferred":[
        "Dalaman"
    ],
    "name:fas_x_preferred":[
        "\u062f\u0627\u0644\u0627\u0645\u0627\u0646"
    ],
    "name:fra_x_preferred":[
        "Dalaman"
    ],
    "name:hye_x_preferred":[
        "\u0534\u0561\u056c\u0561\u0574\u0561\u0576"
    ],
    "name:kat_x_preferred":[
        "\u10d3\u10d0\u10da\u10d0\u10db\u10d0\u10dc\u10d8"
    ],
    "name:kaz_x_preferred":[
        "\u0414\u0430\u043b\u0430\u043c\u0430\u043d"
    ],
    "name:lav_x_preferred":[
        "Dalamana"
    ],
    "name:min_x_preferred":[
        "Dalaman"
    ],
    "name:mrj_x_preferred":[
        "\u0414\u0430\u043b\u0430\u043c\u0430\u043d"
    ],
    "name:msa_x_preferred":[
        "Dalaman"
    ],
    "name:nld_x_preferred":[
        "Dalaman"
    ],
    "name:nno_x_preferred":[
        "Dalaman"
    ],
    "name:nor_x_preferred":[
        "Dalaman"
    ],
    "name:pnb_x_preferred":[
        "\u0636\u0644\u0639 \u062f\u0627\u0644\u0627\u0645\u0627\u0646"
    ],
    "name:pol_x_preferred":[
        "Dalaman"
    ],
    "name:por_x_preferred":[
        "Dalaman"
    ],
    "name:rus_x_preferred":[
        "\u0414\u0430\u043b\u0430\u043c\u0430\u043d"
    ],
    "name:spa_x_preferred":[
        "Dalaman"
    ],
    "name:srp_x_preferred":[
        "\u0414\u0430\u043b\u0430\u043c\u0430\u043d"
    ],
    "name:swa_x_preferred":[
        "Dalaman"
    ],
    "name:swe_x_preferred":[
        "Dalaman"
    ],
    "name:tur_x_preferred":[
        "Dalaman"
    ],
    "name:ukr_x_preferred":[
        "\u0414\u0430\u043b\u0430\u043c\u0430\u043d"
    ],
    "name:und_x_variant":[
        "Daleman",
        "Dalaman"
    ],
    "name:urd_x_preferred":[
        "\u062f\u0627\u0644\u0627\u0645\u0627\u0646"
    ],
    "name:vie_x_preferred":[
        "Dalaman"
    ],
    "name:zho_x_preferred":[
        "\u9054\u62c9\u66fc"
    ],
    "wof:lang_x_official":[
        "ind"
    ],
    "wof:lang_x_spoken":[
        "ind",
        "eng"
    ],
    "wof:name":"Dalaman",
    "wof:placetype":"locality"
},
  "geometry": {"coordinates":[110.57528000000001,-7.40889],"type":"Point"}
}