{
  "type": "Feature",
  "properties": {
    "gn:admin1_code":"18",
    "gn:asciiname":"Golopau",
    "gn:country_code":"ID",
    "gn:dem":735,
    "gn:feature_class":"P",
    "gn:feature_code":"PPL",
    "gn:name":"Golopau",
    "gn:population":0,
    "gn:timezone":"Asia/Makassar",
    "iso:country":"ID",
    "name:ind_x_preferred":[
        "Golopau"
    ],
    "wof:name":"Golopau",
    "wof:placetype":"locality"
},
  "geometry": {"coordinates":[120.7189,-8.5005],"type":"Point"}
}