{
  "type": "Feature",
  "properties": {
    "gn:admin1_code":"30.0",
    "gn:asciiname":"Ciakar Dua",
    "gn:country_code":"ID",
    "gn:dem":672,
    "gn:feature_class":"P",
    "gn:feature_code":"PPL",
    "gn:name":"Ciakar Dua",
    "gn:population":0,
    "gn:timezone":"Asia/Jakarta",
    "iso:country":"ID",
    "name:ind_x_preferred":[
        "Ciakar Dua"
    ],
    "wof:name":"Ciakar Dua",
    "wof:placetype":"locality"
},
  "geometry": {"coordinates":[106.89,-7.0669],"type":"Point"}
}