{
  "type": "Feature",
  "properties": {
    "gn:admin1_code":"38",
    "gn:asciiname":"Tappale",
    "gn:country_code":"ID",
    "gn:dem":147,
    "gn:feature_class":"P",
    "gn:feature_code":"PPL",
    "gn:name":"Tappale",
    "gn:population":0,
    "gn:timezone":"Asia/Makassar",
    "iso:country":"ID",
    "name:ind_x_preferred":[
        "Tappale"
    ],
    "wof:name":"Tappale",
    "wof:placetype":"locality"
},
  "geometry": {"coordinates":[120.06059999999999,-4.8871],"type":"Point"}
}