{
  "type": "Feature",
  "properties": {
    "gn:admin1_code":"8",
    "gn:asciiname":"Jenangan",
    "gn:country_code":"ID",
    "gn:dem":248,
    "gn:feature_class":"P",
    "gn:feature_code":"PPL",
    "gn:name":"Jenangan",
    "gn:population":0,
    "gn:timezone":"Asia/Jakarta",
    "iso:country":"ID",
    "name:ind_x_preferred":[
        "Jenangan"
    ],
    "wof:name":"Jenangan",
    "wof:placetype":"locality"
},
  "geometry": {"coordinates":[111.33806,-7.80889],"type":"Point"}
}