{
  "type": "Feature",
  "properties": {
    "gn:admin1_code":"7.0",
    "gn:asciiname":"Kalipalet",
    "gn:country_code":"ID",
    "gn:dem":151,
    "gn:feature_class":"P",
    "gn:feature_code":"PPL",
    "gn:name":"Kalipalet",
    "gn:population":0,
    "gn:timezone":"Asia/Jakarta",
    "iso:country":"ID",
    "name:ind_x_preferred":[
        "Kalipalet"
    ],
    "wof:name":"Kalipalet",
    "wof:placetype":"locality"
},
  "geometry": {"coordinates":[109.5125,-7.31194],"type":"Point"}
}