{
  "type": "Feature",
  "properties": {
    "gn:admin1_code":"7.0",
    "gn:asciiname":"Jurangjero",
    "gn:country_code":"ID",
    "gn:dem":385,
    "gn:feature_class":"P",
    "gn:feature_code":"PPL",
    "gn:name":"Jurangjero",
    "gn:population":0,
    "gn:timezone":"Asia/Jakarta",
    "iso:country":"ID",
    "name:ind_x_preferred":[
        "Jurangjero"
    ],
    "wof:name":"Jurangjero",
    "wof:placetype":"locality"
},
  "geometry": {"coordinates":[109.38916999999999,-7.52917],"type":"Point"}
}