{
  "type": "Feature",
  "properties": {
    "gn:admin1_code":"15.0",
    "gn:asciiname":"Sinarbandung",
    "gn:country_code":"ID",
    "gn:dem":163,
    "gn:feature_class":"P",
    "gn:feature_code":"PPL",
    "gn:name":"Sinarbandung",
    "gn:population":0,
    "gn:timezone":"Asia/Jakarta",
    "iso:country":"ID",
    "name:ind_x_preferred":[
        "Sinarbandung"
    ],
    "wof:name":"Sinarbandung",
    "wof:placetype":"locality"
},
  "geometry": {"coordinates":[104.87833999999999,-5.25526],"type":"Point"}
}