{
  "type": "Feature",
  "properties": {
    "gn:admin1_code":"30",
    "gn:asciiname":"Pamayaran",
    "gn:cc2":"ID",
    "gn:country_code":"ID",
    "gn:dem":1081,
    "gn:feature_class":"P",
    "gn:feature_code":"PPL",
    "gn:name":"Pamayaran",
    "gn:population":0,
    "gn:timezone":"Asia/Jakarta",
    "iso:country":"ID",
    "name:und_x_variant":[
        "Pamajaran",
        "Pamayaran"
    ],
    "wof:lang_x_official":[
        "ind"
    ],
    "wof:lang_x_spoken":[
        "ind",
        "eng"
    ],
    "wof:name":"Pamayaran",
    "wof:placetype":"locality"
},
  "geometry": {"coordinates":[107.69472,-6.86694],"type":"Point"}
}