{
  "type": "Feature",
  "properties": {
    "gn:admin1_code":"8.0",
    "gn:asciiname":"Tulungrejo",
    "gn:country_code":"ID",
    "gn:dem":334,
    "gn:feature_class":"P",
    "gn:feature_code":"PPLA4",
    "gn:name":"Tulungrejo",
    "gn:population":0,
    "gn:timezone":"Asia/Jakarta",
    "iso:country":"ID",
    "name:ind_x_preferred":[
        "Tulungrejo"
    ],
    "name:und_x_variant":[
        "Toeloengredjo"
    ],
    "wof:lang_x_official":[
        "ind"
    ],
    "wof:lang_x_spoken":[
        "ind",
        "eng"
    ],
    "wof:name":"Tulungrejo",
    "wof:placetype":"locality"
},
  "geometry": {"coordinates":[112.3302,-8.2697],"type":"Point"}
}