{
  "type": "Feature",
  "properties": {
    "gn:admin1_code":"7",
    "gn:asciiname":"Sukoharjo",
    "gn:country_code":"ID",
    "gn:dem":20,
    "gn:feature_class":"P",
    "gn:feature_code":"PPL",
    "gn:name":"Sukoharjo",
    "gn:population":0,
    "gn:timezone":"Asia/Jakarta",
    "iso:country":"ID",
    "name:ind_x_preferred":[
        "Sukoharjo"
    ],
    "wof:name":"Sukoharjo",
    "wof:placetype":"locality"
},
  "geometry": {"coordinates":[109.91306000000002,-7.70167],"type":"Point"}
}