{
  "type": "Feature",
  "properties": {
    "gn:admin1_code":"30.0",
    "gn:asciiname":"Panyindangan",
    "gn:country_code":"ID",
    "gn:dem":510,
    "gn:feature_class":"P",
    "gn:feature_code":"PPL",
    "gn:name":"Panyindangan",
    "gn:population":0,
    "gn:timezone":"Asia/Jakarta",
    "iso:country":"ID",
    "name:ind_x_preferred":[
        "Panyindangan"
    ],
    "name:und_x_variant":[
        "Panjindangan"
    ],
    "wof:name":"Panyindangan",
    "wof:placetype":"locality"
},
  "geometry": {"coordinates":[107.88972,-6.83111],"type":"Point"}
}