{
  "type": "Feature",
  "properties": {
    "gn:admin1_code":"37.0",
    "gn:asciiname":"Bagankajuara",
    "gn:country_code":"ID",
    "gn:dem":25,
    "gn:feature_class":"P",
    "gn:feature_code":"PPL",
    "gn:name":"Bagankajuara",
    "gn:population":0,
    "gn:timezone":"Asia/Jakarta",
    "iso:country":"ID",
    "name:ind_x_preferred":[
        "Bagankajuara"
    ],
    "wof:name":"Bagankajuara",
    "wof:placetype":"locality"
},
  "geometry": {"coordinates":[102.92997,-0.14966],"type":"Point"}
}