{
  "type": "Feature",
  "properties": {
    "gn:admin1_code":"30.0",
    "gn:asciiname":"Jolokpari",
    "gn:country_code":"ID",
    "gn:dem":696,
    "gn:feature_class":"P",
    "gn:feature_code":"PPL",
    "gn:name":"Jolokpari",
    "gn:population":0,
    "gn:timezone":"Asia/Jakarta",
    "iso:country":"ID",
    "name:ind_x_preferred":[
        "Jolokpari"
    ],
    "wof:name":"Jolokpari",
    "wof:placetype":"locality"
},
  "geometry": {"coordinates":[107.9395,-7.1684],"type":"Point"}
}