{
  "type": "Feature",
  "properties": {
    "gn:admin1_code":"15.0",
    "gn:asciiname":"Baturaja",
    "gn:country_code":"ID",
    "gn:dem":37,
    "gn:feature_class":"P",
    "gn:feature_code":"PPL",
    "gn:name":"Baturaja",
    "gn:population":0,
    "gn:timezone":"Asia/Jakarta",
    "iso:country":"ID",
    "name:ind_x_preferred":[
        "Baturaja"
    ],
    "name:und_x_variant":[
        "Batoeradjo"
    ],
    "wof:name":"Baturaja",
    "wof:placetype":"locality"
},
  "geometry": {"coordinates":[105.14309,-5.73143],"type":"Point"}
}