{
  "type": "Feature",
  "properties": {
    "gn:admin1_code":"30",
    "gn:asciiname":"Cijengkol",
    "gn:country_code":"ID",
    "gn:dem":533,
    "gn:feature_class":"P",
    "gn:feature_code":"PPL",
    "gn:name":"Cijengkol",
    "gn:population":0,
    "gn:timezone":"Asia/Jakarta",
    "iso:country":"ID",
    "name:ind_x_preferred":[
        "Cijengkol"
    ],
    "name:und_x_variant":[
        "Tjidjengkol"
    ],
    "wof:name":"Cijengkol",
    "wof:placetype":"locality"
},
  "geometry": {"coordinates":[107.44028,-6.78889],"type":"Point"}
}