{
  "type": "Feature",
  "properties": {
    "gn:admin1_code":"37",
    "gn:asciiname":"Selatkering",
    "gn:country_code":"ID",
    "gn:dem":9,
    "gn:feature_class":"P",
    "gn:feature_code":"PPL",
    "gn:name":"Selatkering",
    "gn:population":0,
    "gn:timezone":"Asia/Jakarta",
    "iso:country":"ID",
    "name:ind_x_preferred":[
        "Selatkering"
    ],
    "wof:name":"Selatkering",
    "wof:placetype":"locality"
},
  "geometry": {"coordinates":[101.70474,2.05283],"type":"Point"}
}