{
  "type": "Feature",
  "properties": {
    "gn:admin1_code":"8.0",
    "gn:asciiname":"Guluk",
    "gn:country_code":"ID",
    "gn:dem":156,
    "gn:feature_class":"P",
    "gn:feature_code":"PPL",
    "gn:name":"Guluk",
    "gn:population":0,
    "gn:timezone":"Asia/Jakarta",
    "iso:country":"ID",
    "name:ind_x_preferred":[
        "Guluk"
    ],
    "wof:name":"Guluk",
    "wof:placetype":"locality"
},
  "geometry": {"coordinates":[114.04040000000001,-7.8226],"type":"Point"}
}