{
  "type": "Feature",
  "properties": {
    "gn:admin1_code":"18.0",
    "gn:asciiname":"Usaefbaki",
    "gn:country_code":"ID",
    "gn:dem":507,
    "gn:feature_class":"P",
    "gn:feature_code":"PPL",
    "gn:name":"Usaefbaki",
    "gn:population":0,
    "gn:timezone":"Asia/Makassar",
    "iso:country":"ID",
    "name:ind_x_preferred":[
        "Usaefbaki"
    ],
    "wof:name":"Usaefbaki",
    "wof:placetype":"locality"
},
  "geometry": {"coordinates":[124.3652,-9.5973],"type":"Point"}
}