{
  "type": "Feature",
  "properties": {
    "gn:admin1_code":"07",
    "gn:asciiname":"Senggrong Satu",
    "gn:cc2":"ID",
    "gn:country_code":"ID",
    "gn:dem":341,
    "gn:feature_class":"P",
    "gn:feature_code":"PPL",
    "gn:name":"Senggrong Satu",
    "gn:population":0,
    "gn:timezone":"Asia/Jakarta",
    "iso:country":"ID",
    "name:und_x_variant":[
        "Senggrong 1",
        "Senggrong Satu"
    ],
    "wof:name":"Senggrong Satu",
    "wof:placetype":"locality"
},
  "geometry": {"coordinates":[110.52528,-7.24583],"type":"Point"}
}