{
  "type": "Feature",
  "properties": {
    "gn:admin1_code":"34.0",
    "gn:asciiname":"Lantadutomula",
    "gn:country_code":"ID",
    "gn:dem":593,
    "gn:feature_class":"P",
    "gn:feature_code":"PPL",
    "gn:name":"Lantadutomula",
    "gn:population":0,
    "gn:timezone":"Asia/Makassar",
    "iso:country":"ID",
    "name:ind_x_preferred":[
        "Lantadutomula"
    ],
    "wof:name":"Lantadutomula",
    "wof:placetype":"locality"
},
  "geometry": {"coordinates":[123.2225,0.4223],"type":"Point"}
}