{
  "type": "Feature",
  "properties": {
    "gn:admin1_code":"18",
    "gn:asciiname":"Usapibaki",
    "gn:country_code":"ID",
    "gn:dem":453,
    "gn:feature_class":"P",
    "gn:feature_code":"PPL",
    "gn:name":"Usapibaki",
    "gn:population":0,
    "gn:timezone":"Asia/Makassar",
    "iso:country":"ID",
    "wof:name":"Usapibaki",
    "wof:placetype":"locality"
},
  "geometry": {"coordinates":[124.57611,-9.31583],"type":"Point"}
}