{
  "type": "Feature",
  "properties": {
    "gn:admin1_code":"38",
    "gn:asciiname":"Lengkese",
    "gn:country_code":"ID",
    "gn:dem":1148,
    "gn:feature_class":"P",
    "gn:feature_code":"PPL",
    "gn:name":"Lengkese",
    "gn:population":0,
    "gn:timezone":"Asia/Makassar",
    "iso:country":"ID",
    "name:ind_x_preferred":[
        "Lengkese"
    ],
    "wof:name":"Lengkese",
    "wof:placetype":"locality"
},
  "geometry": {"coordinates":[119.88509999999999,-5.3018],"type":"Point"}
}