{
  "type": "Feature",
  "properties": {
    "gn:country":"ID",
    "gn:fcode":"ADM4",
    "gn:pop":0,
    "iso:country":"ID",
    "name:ind_x_preferred":[
        "Kelurahan Kuningan Timur"
    ],
    "name:unk_x_variant":[
        "Kuningan Timur"
    ],
    "qs:name":"Kelurahan Kuningan Timur",
    "qs:photos_9r":0,
    "qs:photos_sr":0,
    "qs:pop_sr":"0",
    "wof:name":"Kelurahan Kuningan Timur",
    "wof:placetype":"localadmin",
    "wof:population":0
},
  "geometry": {"coordinates":[106.82980000000001,-6.2313],"type":"Point"}
}