{
  "type": "Feature",
  "properties": {
    "gn:admin1_code":"26",
    "gn:asciiname":"Hutadelleng",
    "gn:country_code":"ID",
    "gn:dem":978,
    "gn:feature_class":"P",
    "gn:feature_code":"PPL",
    "gn:name":"Hutadelleng",
    "gn:population":0,
    "gn:timezone":"Asia/Jakarta",
    "iso:country":"ID",
    "name:ind_x_preferred":[
        "Hutadelleng"
    ],
    "wof:name":"Hutadelleng",
    "wof:placetype":"locality"
},
  "geometry": {"coordinates":[98.28879999999999,2.8071],"type":"Point"}
}