{
  "type": "Feature",
  "properties": {
    "gn:admin1_code":"30",
    "gn:asciiname":"Joglo",
    "gn:country_code":"ID",
    "gn:dem":619,
    "gn:feature_class":"P",
    "gn:feature_code":"PPL",
    "gn:name":"Joglo",
    "gn:population":0,
    "gn:timezone":"Asia/Jakarta",
    "iso:country":"ID",
    "name:ind_x_preferred":[
        "Joglo"
    ],
    "name:jav_x_preferred":[
        "Omah Joglo"
    ],
    "name:nld_x_preferred":[
        "Joglo"
    ],
    "name:por_x_preferred":[
        "Joglo"
    ],
    "name:tha_x_preferred":[
        "\u0e08\u0e01\u0e42\u0e25"
    ],
    "wof:name":"Joglo",
    "wof:placetype":"locality"
},
  "geometry": {"coordinates":[106.99028,-6.92639],"type":"Point"}
}