{
  "type": "Feature",
  "properties": {
    "gn:admin1_code":"15.0",
    "gn:asciiname":"Karangkelapa",
    "gn:country_code":"ID",
    "gn:dem":12,
    "gn:feature_class":"P",
    "gn:feature_code":"PPL",
    "gn:name":"Karangkelapa",
    "gn:population":0,
    "gn:timezone":"Asia/Jakarta",
    "iso:country":"ID",
    "name:ind_x_preferred":[
        "Karangkelapa"
    ],
    "name:und_x_variant":[
        "Karangtiapare",
        "Karangklapar\u0115dik"
    ],
    "wof:lang_x_official":[
        "ind"
    ],
    "wof:lang_x_spoken":[
        "ind",
        "eng"
    ],
    "wof:name":"Karangkelapa",
    "wof:placetype":"locality"
},
  "geometry": {"coordinates":[104.80513000000001,-5.80431],"type":"Point"}
}