{
  "type": "Feature",
  "properties": {
    "gn:admin1_code":"4",
    "gn:asciiname":"Gedungtinggi",
    "gn:country_code":"ID",
    "gn:dem":9,
    "gn:feature_class":"P",
    "gn:feature_code":"PPL",
    "gn:name":"Gedungtinggi",
    "gn:population":0,
    "gn:timezone":"Asia/Jakarta",
    "iso:country":"ID",
    "name:ind_x_preferred":[
        "Gedungtinggi"
    ],
    "wof:name":"Gedungtinggi",
    "wof:placetype":"locality"
},
  "geometry": {"coordinates":[106.8476,-6.162],"type":"Point"}
}