{
  "type": "Feature",
  "properties": {
    "gn:country":"ID",
    "gn:fcode":"ADM4",
    "gn:pop":0,
    "iso:country":"ID",
    "name:ind_x_preferred":[
        "Desa Liliba"
    ],
    "name:unk_x_variant":[
        "Liliba"
    ],
    "qs:name":"Desa Liliba",
    "qs:photos_9r":0,
    "qs:photos_sr":0,
    "qs:pop_sr":"0",
    "wof:name":"Desa Liliba",
    "wof:placetype":"localadmin",
    "wof:population":0
},
  "geometry": {"coordinates":[123.63958,-10.1708],"type":"Point"}
}