{
  "type": "Feature",
  "properties": {
    "gn:admin1_code":"21.0",
    "gn:asciiname":"Katu",
    "gn:country_code":"ID",
    "gn:dem":1106,
    "gn:feature_class":"P",
    "gn:feature_code":"PPL",
    "gn:name":"Katu",
    "gn:population":0,
    "gn:timezone":"Asia/Makassar",
    "iso:country":"ID",
    "name:ceb_x_preferred":[
        "Katu"
    ],
    "name:deu_x_preferred":[
        "Katu"
    ],
    "name:fra_x_preferred":[
        "Katu"
    ],
    "name:hye_x_preferred":[
        "\u053f\u0561\u057f\u0578\u0582\u0576\u0565\u0580"
    ],
    "name:ind_x_preferred":[
        "Katu"
    ],
    "name:swe_x_preferred":[
        "Katu"
    ],
    "name:und_x_variant":[
        "Katoe"
    ],
    "wof:lang_x_official":[
        "ind"
    ],
    "wof:lang_x_spoken":[
        "ind",
        "eng"
    ],
    "wof:name":"Katu",
    "wof:placetype":"locality"
},
  "geometry": {"coordinates":[120.25539999999999,-1.5883],"type":"Point"}
}