{
  "type": "Feature",
  "properties": {
    "gn:admin1_code":"17",
    "gn:asciiname":"Aijati",
    "gn:country_code":"ID",
    "gn:dem":49,
    "gn:feature_class":"P",
    "gn:feature_code":"PPL",
    "gn:name":"Aijati",
    "gn:population":0,
    "gn:timezone":"Asia/Makassar",
    "iso:country":"ID",
    "name:ind_x_preferred":[
        "Aijati"
    ],
    "wof:name":"Aijati",
    "wof:placetype":"locality"
},
  "geometry": {"coordinates":[116.905,-8.5537],"type":"Point"}
}