{
  "type": "Feature",
  "properties": {
    "gn:admin1_code":"30",
    "gn:asciiname":"Pasir Dua",
    "gn:country_code":"ID",
    "gn:dem":31,
    "gn:feature_class":"P",
    "gn:feature_code":"PPL",
    "gn:name":"Pasir Dua",
    "gn:population":0,
    "gn:timezone":"Asia/Jakarta",
    "iso:country":"ID",
    "name:ind_x_preferred":[
        "Pasir Dua"
    ],
    "wof:name":"Pasir Dua",
    "wof:placetype":"locality"
},
  "geometry": {"coordinates":[107.20833,-6.35222],"type":"Point"}
}