{
  "type": "Feature",
  "properties": {
    "gn:admin1_code":"30",
    "gn:asciiname":"Perumahan Umum Nasional Bumitelukjambe",
    "gn:country_code":"ID",
    "gn:dem":19,
    "gn:feature_class":"P",
    "gn:feature_code":"PPL",
    "gn:name":"Perumahan Umum Nasional Bumitelukjambe",
    "gn:population":0,
    "gn:timezone":"Asia/Jakarta",
    "iso:country":"ID",
    "name:ind_x_preferred":[
        "Perumahan Umum Nasional Bumitelukjambe"
    ],
    "name:und_x_variant":[
        "Perumnas Bumitelukjambe"
    ],
    "wof:lang_x_official":[
        "ind"
    ],
    "wof:lang_x_spoken":[
        "ind",
        "eng"
    ],
    "wof:name":"Perumahan Umum Nasional Bumitelukjambe",
    "wof:placetype":"locality"
},
  "geometry": {"coordinates":[107.28222,-6.33694],"type":"Point"}
}