{
  "type": "Feature",
  "properties": {
    "gn:admin1_code":"33",
    "gn:asciiname":"Jatikemelaka",
    "gn:country_code":"ID",
    "gn:dem":39,
    "gn:feature_class":"P",
    "gn:feature_code":"PPL",
    "gn:name":"Jatikemelaka",
    "gn:population":0,
    "gn:timezone":"Asia/Jakarta",
    "iso:country":"ID",
    "name:ind_x_preferred":[
        "Jatikemelaka"
    ],
    "wof:name":"Jatikemelaka",
    "wof:placetype":"locality"
},
  "geometry": {"coordinates":[106.13339999999999,-6.1175],"type":"Point"}
}