{
  "type": "Feature",
  "properties": {
    "gn:admin1_code":"22",
    "gn:asciiname":"Tondowatu",
    "gn:country_code":"ID",
    "gn:dem":18,
    "gn:feature_class":"P",
    "gn:feature_code":"PPL",
    "gn:name":"Tondowatu",
    "gn:population":0,
    "gn:timezone":"Asia/Makassar",
    "iso:country":"ID",
    "name:ind_x_preferred":[
        "Tondowatu"
    ],
    "wof:name":"Tondowatu",
    "wof:placetype":"locality"
},
  "geometry": {"coordinates":[122.21769999999999,-3.6376],"type":"Point"}
}