{
  "type": "Feature",
  "properties": {
    "gn:admin1_code":"07",
    "gn:asciiname":"Ampelgading",
    "gn:country_code":"ID",
    "gn:dem":236,
    "gn:feature_class":"P",
    "gn:feature_code":"PPL",
    "gn:name":"Ampelgading",
    "gn:population":0,
    "gn:timezone":"Asia/Jakarta",
    "iso:country":"ID",
    "name:ind_x_preferred":[
        "Ampelgading"
    ],
    "name:und_x_variant":[
        "Amulgading"
    ],
    "wof:lang_x_official":[
        "ind"
    ],
    "wof:lang_x_spoken":[
        "ind",
        "eng"
    ],
    "wof:name":"Ampelgading",
    "wof:placetype":"locality"
},
  "geometry": {"coordinates":[110.38760000000001,-7.0602],"type":"Point"}
}