{
  "type": "Feature",
  "properties": {
    "gn:admin1_code":"1",
    "gn:asciiname":"Krueng Baro",
    "gn:country_code":"ID",
    "gn:dem":10,
    "gn:feature_class":"P",
    "gn:feature_code":"PPL",
    "gn:name":"Krueng Baro",
    "gn:population":0,
    "gn:timezone":"Asia/Jakarta",
    "iso:country":"ID",
    "name:ind_x_preferred":[
        "Krueng Baro"
    ],
    "wof:name":"Krueng Baro",
    "wof:placetype":"locality"
},
  "geometry": {"coordinates":[97.2225,5.1019],"type":"Point"}
}