{
  "type": "Feature",
  "properties": {
    "gn:admin1_code":"32.0",
    "gn:asciiname":"Talangpela",
    "gn:country_code":"ID",
    "gn:dem":1170,
    "gn:feature_class":"P",
    "gn:feature_code":"PPL",
    "gn:name":"Talangpela",
    "gn:population":0,
    "gn:timezone":"Asia/Jakarta",
    "iso:country":"ID",
    "name:ind_x_preferred":[
        "Talangpela"
    ],
    "wof:name":"Talangpela",
    "wof:placetype":"locality"
},
  "geometry": {"coordinates":[104.07066,-4.84102],"type":"Point"}
}