{
  "type": "Feature",
  "properties": {
    "gn:admin1_code":"38.0",
    "gn:asciiname":"Polong",
    "gn:country_code":"ID",
    "gn:dem":29,
    "gn:feature_class":"P",
    "gn:feature_code":"PPL",
    "gn:name":"Polong",
    "gn:population":0,
    "gn:timezone":"Asia/Makassar",
    "iso:country":"ID",
    "name:ind_x_preferred":[
        "Polong"
    ],
    "name:msa_x_preferred":[
        "Polong"
    ],
    "name:rus_x_preferred":[
        "\u041f\u043e\u043b\u043e\u043d"
    ],
    "wof:name":"Polong",
    "wof:placetype":"locality"
},
  "geometry": {"coordinates":[120.4528,-5.8533],"type":"Point"}
}