{
  "type": "Feature",
  "properties": {
    "gn:admin1_code":"7.0",
    "gn:asciiname":"Pateh",
    "gn:country_code":"ID",
    "gn:dem":463,
    "gn:feature_class":"P",
    "gn:feature_code":"PPL",
    "gn:name":"Pateh",
    "gn:population":0,
    "gn:timezone":"Asia/Jakarta",
    "iso:country":"ID",
    "name:fas_x_preferred":[
        "\u067e\u062a\u0647"
    ],
    "wof:lang_x_official":[
        "ind"
    ],
    "wof:lang_x_spoken":[
        "ind",
        "eng"
    ],
    "wof:name":"Pateh",
    "wof:placetype":"locality"
},
  "geometry": {"coordinates":[110.56056,-7.60194],"type":"Point"}
}