{
  "type": "Feature",
  "properties": {
    "gn:country":"ID",
    "gn:fcode":"PPL",
    "gn:pop":0,
    "iso:country":"ID",
    "name:ace_x_preferred":[
        "Tanjung Benoa"
    ],
    "name:aze_x_preferred":[
        "Benoa burnu"
    ],
    "name:ban_x_preferred":[
        "Tanjung Benoa"
    ],
    "name:ceb_x_preferred":[
        "Tanjung Benoa"
    ],
    "name:deu_x_preferred":[
        "Tanjung Benoa"
    ],
    "name:eng_x_preferred":[
        "Tanjung Benoa"
    ],
    "name:fra_x_preferred":[
        "Tanjung Benoa"
    ],
    "name:ind_x_preferred":[
        "Tanjungbenoa"
    ],
    "name:ind_x_variant":[
        "Tanjung Benoa"
    ],
    "name:ita_x_preferred":[
        "capo Benoa"
    ],
    "name:jav_x_preferred":[
        "Tanjung Benoa"
    ],
    "name:msa_x_preferred":[
        "Tanjung Benoa"
    ],
    "name:nld_x_preferred":[
        "Tanjung Benoa"
    ],
    "name:por_x_preferred":[
        "Tanjung Benoa"
    ],
    "name:rus_x_preferred":[
        "\u0422\u0430\u043d\u0436\u0443\u043d\u0433 \u0411\u0435\u043d\u043e\u0430"
    ],
    "name:rus_x_variant":[
        "\u0411\u0435\u043d\u043e\u0430"
    ],
    "name:spa_x_preferred":[
        "Tanjung Benoa"
    ],
    "name:swe_x_preferred":[
        "Tanjung Benoa"
    ],
    "name:ukr_x_preferred":[
        "\u0411\u0435\u043d\u043e\u0430"
    ],
    "name:unk_x_variant":[
        "Benoa"
    ],
    "name:zho_x_preferred":[
        "\u80af\u5fb7\u723e"
    ],
    "name:zho_x_variant":[
        "\u4e39\u620e\u8c9d\u8afe\u74e6"
    ],
    "qs:name":"Tanjung Benoa",
    "qs:name_adm0":"Indonesia",
    "qs:name_adm1":"Bali",
    "qs:photos":2241,
    "qs:photos_1k":454,
    "qs:photos_9k":10,
    "qs:photos_9r":9,
    "qs:photos_all":2241,
    "qs:photos_sr":16,
    "qs:placetype":"Town",
    "qs:pop_sr":"0",
    "wd:wordcount":87,
    "wof:lang_x_official":[
        "ind"
    ],
    "wof:lang_x_spoken":[
        "ind",
        "eng"
    ],
    "wof:name":"Tanjung Benoa",
    "wof:placetype":"locality",
    "wof:population":0
},
  "geometry": {"coordinates":[115.2184,-8.7548],"type":"Point"}
}