{
  "type": "Feature",
  "properties": {
    "gn:admin1_code":"38",
    "gn:asciiname":"Bontoa",
    "gn:country_code":"ID",
    "gn:dem":618,
    "gn:feature_class":"P",
    "gn:feature_code":"PPL",
    "gn:name":"Bontoa",
    "gn:population":0,
    "gn:timezone":"Asia/Makassar",
    "iso:country":"ID",
    "name:ind_x_preferred":[
        "Bontoa"
    ],
    "wof:name":"Bontoa",
    "wof:placetype":"locality"
},
  "geometry": {"coordinates":[120.0317,-5.4296],"type":"Point"}
}