{
  "type": "Feature",
  "properties": {
    "gn:admin1_code":"33",
    "gn:asciiname":"Malabar",
    "gn:country_code":"ID",
    "gn:dem":44,
    "gn:feature_class":"P",
    "gn:feature_code":"PPL",
    "gn:name":"Malabar",
    "gn:population":0,
    "gn:timezone":"Asia/Jakarta",
    "iso:country":"ID",
    "name:ast_x_preferred":[
        "Malabar"
    ],
    "name:cat_x_preferred":[
        "Malabar"
    ],
    "name:ceb_x_preferred":[
        "Malabar"
    ],
    "name:ces_x_preferred":[
        "Malabar"
    ],
    "name:deu_x_preferred":[
        "Malabar"
    ],
    "name:eus_x_preferred":[
        "Malabar"
    ],
    "name:fra_x_preferred":[
        "Malabar"
    ],
    "name:heb_x_preferred":[
        "\u05de\u05dc\u05d1\u05e8"
    ],
    "name:ind_x_preferred":[
        "Malabar"
    ],
    "name:jpn_x_preferred":[
        "\u30de\u30e9\u30d0\u30fc"
    ],
    "name:mal_x_preferred":[
        "\u0d2e\u0d32\u0d2c\u0d3e\u0d7c"
    ],
    "name:mlg_x_preferred":[
        "Malabar"
    ],
    "name:nds_x_preferred":[
        "Malabar"
    ],
    "name:nld_x_preferred":[
        "Malabar"
    ],
    "name:oci_x_preferred":[
        "Malabar"
    ],
    "name:pol_x_preferred":[
        "Malabar"
    ],
    "name:por_x_preferred":[
        "Malabar"
    ],
    "name:rus_x_preferred":[
        "\u041c\u0430\u043b\u0430\u0431\u0430\u0440"
    ],
    "name:slk_x_preferred":[
        "Malabar"
    ],
    "name:spa_x_preferred":[
        "Malabar"
    ],
    "name:swe_x_preferred":[
        "Malabar"
    ],
    "name:urd_x_preferred":[
        "\u0645\u0644\u0627\u0628\u0627\u0631"
    ],
    "wof:lang_x_official":[
        "ind"
    ],
    "wof:lang_x_spoken":[
        "ind",
        "eng"
    ],
    "wof:name":"Malabar",
    "wof:placetype":"locality"
},
  "geometry": {"coordinates":[106.22539999999999,-6.3272],"type":"Point"}
}