{
  "type": "Feature",
  "properties": {
    "gn:admin1_code":"7",
    "gn:asciiname":"Kangsi",
    "gn:country_code":"ID",
    "gn:dem":690,
    "gn:feature_class":"P",
    "gn:feature_code":"PPL",
    "gn:name":"Kangsi",
    "gn:population":0,
    "gn:timezone":"Asia/Jakarta",
    "iso:country":"ID",
    "name:ind_x_preferred":[
        "Kangsi"
    ],
    "wof:name":"Kangsi",
    "wof:placetype":"locality"
},
  "geometry": {"coordinates":[111.07528000000001,-7.69278],"type":"Point"}
}