{
  "type": "Feature",
  "properties": {
    "gn:admin1_code":"8",
    "gn:asciiname":"Semambung Kidul",
    "gn:country_code":"ID",
    "gn:dem":430,
    "gn:feature_class":"P",
    "gn:feature_code":"PPL",
    "gn:name":"Semambung Kidul",
    "gn:population":0,
    "gn:timezone":"Asia/Jakarta",
    "iso:country":"ID",
    "name:ind_x_preferred":[
        "Semambung Kidul"
    ],
    "wof:name":"Semambung Kidul",
    "wof:placetype":"locality"
},
  "geometry": {"coordinates":[112.7165,-7.7913],"type":"Point"}
}