{
  "type": "Feature",
  "properties": {
    "gn:admin1_code":"08",
    "gn:asciiname":"Mojokemuning",
    "gn:country_code":"ID",
    "gn:dem":17,
    "gn:feature_class":"P",
    "gn:feature_code":"PPL",
    "gn:name":"Mojokemuning",
    "gn:population":0,
    "gn:timezone":"Asia/Jakarta",
    "iso:country":"ID",
    "name:ind_x_preferred":[
        "Mojokemuning"
    ],
    "name:und_x_variant":[
        "Modjokemuning"
    ],
    "wof:name":"Mojokemuning",
    "wof:placetype":"locality"
},
  "geometry": {"coordinates":[112.587,-7.3993],"type":"Point"}
}