{
  "type": "Feature",
  "properties": {
    "gn:admin1_code":"33.0",
    "gn:asciiname":"Tenjoherang",
    "gn:country_code":"ID",
    "gn:dem":115,
    "gn:feature_class":"P",
    "gn:feature_code":"PPL",
    "gn:name":"Tenjoherang",
    "gn:population":0,
    "gn:timezone":"Asia/Jakarta",
    "iso:country":"ID",
    "name:ind_x_preferred":[
        "Tenjoherang"
    ],
    "wof:name":"Tenjoherang",
    "wof:placetype":"locality"
},
  "geometry": {"coordinates":[106.0295,-6.4094],"type":"Point"}
}