{
  "type": "Feature",
  "properties": {
    "gn:admin1_code":"7.0",
    "gn:asciiname":"Ngerang Kidul",
    "gn:country_code":"ID",
    "gn:dem":10,
    "gn:feature_class":"P",
    "gn:feature_code":"PPL",
    "gn:name":"Ngerang Kidul",
    "gn:population":0,
    "gn:timezone":"Asia/Jakarta",
    "iso:country":"ID",
    "name:ind_x_preferred":[
        "Ngerang Kidul"
    ],
    "wof:name":"Ngerang Kidul",
    "wof:placetype":"locality"
},
  "geometry": {"coordinates":[111.1691,-6.7178],"type":"Point"}
}