{
  "type": "Feature",
  "properties": {
    "gn:admin1_code":"8",
    "gn:asciiname":"Gayasan",
    "gn:country_code":"ID",
    "gn:dem":463,
    "gn:feature_class":"P",
    "gn:feature_code":"PPL",
    "gn:name":"Gayasan",
    "gn:population":0,
    "gn:timezone":"Asia/Jakarta",
    "iso:country":"ID",
    "name:ind_x_preferred":[
        "Gayasan"
    ],
    "wof:name":"Gayasan",
    "wof:placetype":"locality"
},
  "geometry": {"coordinates":[113.91070000000001,-8.103],"type":"Point"}
}