{
  "type": "Feature",
  "properties": {
    "gn:admin1_code":"30",
    "gn:asciiname":"Gangsekolah",
    "gn:country_code":"ID",
    "gn:dem":264,
    "gn:feature_class":"P",
    "gn:feature_code":"PPL",
    "gn:name":"Gangsekolah",
    "gn:population":0,
    "gn:timezone":"Asia/Jakarta",
    "iso:country":"ID",
    "name:ind_x_preferred":[
        "Gangsekolah"
    ],
    "wof:name":"Gangsekolah",
    "wof:placetype":"locality"
},
  "geometry": {"coordinates":[107.38889,-6.64056],"type":"Point"}
}