{
  "type": "Feature",
  "properties": {
    "gn:admin1_code":"7",
    "gn:asciiname":"Kalipuru",
    "gn:country_code":"ID",
    "gn:dem":560,
    "gn:feature_class":"P",
    "gn:feature_code":"PPL",
    "gn:name":"Kalipuru",
    "gn:population":0,
    "gn:timezone":"Asia/Jakarta",
    "iso:country":"ID",
    "name:ind_x_preferred":[
        "Kalipuru"
    ],
    "wof:name":"Kalipuru",
    "wof:placetype":"locality"
},
  "geometry": {"coordinates":[110.0663,-7.0772],"type":"Point"}
}