{
  "type": "Feature",
  "properties": {
    "gn:admin1_code":"26",
    "gn:asciiname":"Pongohon",
    "gn:country_code":"ID",
    "gn:dem":342,
    "gn:feature_class":"P",
    "gn:feature_code":"PPL",
    "gn:name":"Pongohon",
    "gn:population":0,
    "gn:timezone":"Asia/Jakarta",
    "iso:country":"ID",
    "name:ind_x_preferred":[
        "Pongohon"
    ],
    "wof:name":"Pongohon",
    "wof:placetype":"locality"
},
  "geometry": {"coordinates":[98.2484,2.4087],"type":"Point"}
}