{
  "type": "Feature",
  "properties": {
    "gn:admin1_code":"7.0",
    "gn:asciiname":"Delawak",
    "gn:country_code":"ID",
    "gn:dem":370,
    "gn:feature_class":"P",
    "gn:feature_code":"PPL",
    "gn:name":"Delawak",
    "gn:population":0,
    "gn:timezone":"Asia/Jakarta",
    "iso:country":"ID",
    "wof:name":"Delawak",
    "wof:placetype":"locality"
},
  "geometry": {"coordinates":[110.15000000000001,-7.61972],"type":"Point"}
}