{
  "type": "Feature",
  "properties": {
    "gn:admin1_code":"30.0",
    "gn:asciiname":"Muara",
    "gn:country_code":"ID",
    "gn:dem":2,
    "gn:feature_class":"P",
    "gn:feature_code":"PPL",
    "gn:name":"Muara",
    "gn:population":0,
    "gn:timezone":"Asia/Jakarta",
    "iso:country":"ID",
    "name:ind_x_preferred":[
        "Muara"
    ],
    "name:und_x_variant":[
        "Muaratjiparage",
        "Muaraciparage 2"
    ],
    "wof:name":"Muara",
    "wof:placetype":"locality"
},
  "geometry": {"coordinates":[107.49222,-6.15861],"type":"Point"}
}