{
  "type": "Feature",
  "properties": {
    "gn:admin1_code":"18.0",
    "gn:asciiname":"Pogowatu",
    "gn:country_code":"ID",
    "gn:dem":385,
    "gn:feature_class":"P",
    "gn:feature_code":"PPL",
    "gn:name":"Pogowatu",
    "gn:population":0,
    "gn:timezone":"Asia/Makassar",
    "iso:country":"ID",
    "name:ind_x_preferred":[
        "Pogowatu"
    ],
    "wof:name":"Pogowatu",
    "wof:placetype":"locality"
},
  "geometry": {"coordinates":[119.4913,-9.5359],"type":"Point"}
}