{
  "type": "Feature",
  "properties": {
    "gn:admin1_code":"7",
    "gn:asciiname":"Jetaan",
    "gn:country_code":"ID",
    "gn:dem":673,
    "gn:feature_class":"P",
    "gn:feature_code":"PPL",
    "gn:name":"Jetaan",
    "gn:population":0,
    "gn:timezone":"Asia/Jakarta",
    "iso:country":"ID",
    "name:ind_x_preferred":[
        "Jetaan"
    ],
    "wof:name":"Jetaan",
    "wof:placetype":"locality"
},
  "geometry": {"coordinates":[110.0454,-7.117],"type":"Point"}
}