{
  "type": "Feature",
  "properties": {
    "gn:admin1_code":"30",
    "gn:asciiname":"Tamiang",
    "gn:cc2":"ID",
    "gn:country_code":"ID",
    "gn:dem":11,
    "gn:feature_class":"P",
    "gn:feature_code":"PPL",
    "gn:name":"Tamiang",
    "gn:population":0,
    "gn:timezone":"Asia/Jakarta",
    "iso:country":"ID",
    "name:und_x_variant":[
        "Tamiang Satu",
        "Tamiang 2",
        "Tamiang 1",
        "Tamiang"
    ],
    "wof:name":"Tamiang",
    "wof:placetype":"locality"
},
  "geometry": {"coordinates":[106.40667000000001,-6.10778],"type":"Point"}
}