{
  "type": "Feature",
  "properties": {
    "gn:admin1_code":"7.0",
    "gn:asciiname":"Watukumpul",
    "gn:country_code":"ID",
    "gn:dem":78,
    "gn:feature_class":"P",
    "gn:feature_code":"PPL",
    "gn:name":"Watukumpul",
    "gn:population":0,
    "gn:timezone":"Asia/Jakarta",
    "iso:country":"ID",
    "name:ind_x_preferred":[
        "Watukumpul"
    ],
    "wof:name":"Watukumpul",
    "wof:placetype":"locality"
},
  "geometry": {"coordinates":[109.13667,-7.46472],"type":"Point"}
}