{
  "type": "Feature",
  "properties": {
    "gn:admin1_code":"0.0",
    "gn:asciiname":"Pamatonggunung",
    "gn:country_code":"ID",
    "gn:dem":490,
    "gn:feature_class":"P",
    "gn:feature_code":"PPL",
    "gn:name":"Pamatonggunung",
    "gn:population":0,
    "gn:timezone":"Asia/Jakarta",
    "iso:country":"ID",
    "name:ind_x_preferred":[
        "Pamatonggunung"
    ],
    "wof:name":"Pamatonggunung",
    "wof:placetype":"locality"
},
  "geometry": {"coordinates":[100.05288,0.05568],"type":"Point"}
}