{
  "type": "Feature",
  "properties": {
    "gn:admin1_code":"30",
    "gn:asciiname":"Legokbadak",
    "gn:country_code":"ID",
    "gn:dem":805,
    "gn:feature_class":"P",
    "gn:feature_code":"PPL",
    "gn:name":"Legokbadak",
    "gn:population":0,
    "gn:timezone":"Asia/Jakarta",
    "iso:country":"ID",
    "name:ind_x_preferred":[
        "Legokbadak"
    ],
    "name:und_x_variant":[
        "Lebakbadak"
    ],
    "wof:lang_x_official":[
        "ind"
    ],
    "wof:lang_x_spoken":[
        "ind",
        "eng"
    ],
    "wof:name":"Legokbadak",
    "wof:placetype":"locality"
},
  "geometry": {"coordinates":[107.69833,-6.895],"type":"Point"}
}