{
  "type": "Feature",
  "properties": {
    "gn:admin1_code":"7",
    "gn:asciiname":"Lebak",
    "gn:country_code":"ID",
    "gn:dem":49,
    "gn:feature_class":"P",
    "gn:feature_code":"PPL",
    "gn:name":"Lebak",
    "gn:population":0,
    "gn:timezone":"Asia/Jakarta",
    "iso:country":"ID",
    "name:ceb_x_preferred":[
        "Lebak"
    ],
    "name:fra_x_preferred":[
        "Lebak"
    ],
    "name:ind_x_preferred":[
        "Lebak"
    ],
    "name:ita_x_preferred":[
        "Lebak"
    ],
    "name:nld_x_preferred":[
        "Lebak"
    ],
    "name:sun_x_preferred":[
        "Lebak"
    ],
    "name:swe_x_preferred":[
        "Lebak"
    ],
    "wof:name":"Lebak",
    "wof:placetype":"locality"
},
  "geometry": {"coordinates":[110.97799999999999,-7.0117],"type":"Point"}
}