{
  "type": "Feature",
  "properties": {
    "gn:admin1_code":"7.0",
    "gn:asciiname":"Gemulung",
    "gn:country_code":"ID",
    "gn:dem":147,
    "gn:feature_class":"P",
    "gn:feature_code":"PPL",
    "gn:name":"Gemulung",
    "gn:population":0,
    "gn:timezone":"Asia/Jakarta",
    "iso:country":"ID",
    "wof:name":"Gemulung",
    "wof:placetype":"locality"
},
  "geometry": {"coordinates":[110.82277999999999,-7.38389],"type":"Point"}
}