{
  "type": "Feature",
  "properties": {
    "gn:admin1_code":"30.0",
    "gn:asciiname":"Wonosroyo",
    "gn:country_code":"ID",
    "gn:dem":308,
    "gn:feature_class":"P",
    "gn:feature_code":"PPL",
    "gn:name":"Wonosroyo",
    "gn:population":0,
    "gn:timezone":"Asia/Jakarta",
    "iso:country":"ID",
    "name:ind_x_preferred":[
        "Wonosroyo"
    ],
    "wof:name":"Wonosroyo",
    "wof:placetype":"locality"
},
  "geometry": {"coordinates":[113.8867,-7.936],"type":"Point"}
}