{
  "type": "Feature",
  "properties": {
    "gn:admin1_code":"7",
    "gn:asciiname":"Temukerep",
    "gn:country_code":"ID",
    "gn:dem":18,
    "gn:feature_class":"P",
    "gn:feature_code":"PPL",
    "gn:name":"Temukerep",
    "gn:population":0,
    "gn:timezone":"Asia/Jakarta",
    "iso:country":"ID",
    "name:ind_x_preferred":[
        "Temukerep"
    ],
    "wof:name":"Temukerep",
    "wof:placetype":"locality"
},
  "geometry": {"coordinates":[108.9477,-6.975],"type":"Point"}
}