{
  "type": "Feature",
  "properties": {
    "gn:admin1_code":"1",
    "gn:asciiname":"Pesabakti",
    "gn:country_code":"ID",
    "gn:dem":611,
    "gn:feature_class":"P",
    "gn:feature_code":"PPL",
    "gn:name":"Pesabakti",
    "gn:population":0,
    "gn:timezone":"Asia/Jakarta",
    "iso:country":"ID",
    "name:ind_x_preferred":[
        "Pesabakti"
    ],
    "name:und_x_variant":[
        "Desabakti"
    ],
    "wof:lang_x_official":[
        "ind"
    ],
    "wof:lang_x_spoken":[
        "ind",
        "eng"
    ],
    "wof:name":"Pesabakti",
    "wof:placetype":"locality"
},
  "geometry": {"coordinates":[96.69670000000001,4.8682],"type":"Point"}
}