{
  "type": "Feature",
  "properties": {
    "gn:admin1_code":"29.0",
    "gn:asciiname":"Fayaul",
    "gn:country_code":"ID",
    "gn:dem":20,
    "gn:feature_class":"P",
    "gn:feature_code":"PPL",
    "gn:name":"Fayaul",
    "gn:population":0,
    "gn:timezone":"Asia/Jayapura",
    "iso:country":"ID",
    "name:und_x_variant":[
        "Fajaoel",
        "Fajaul",
        "Fayaul"
    ],
    "wof:lang_x_official":[
        "ind"
    ],
    "wof:lang_x_spoken":[
        "ind",
        "eng"
    ],
    "wof:name":"Fayaul",
    "wof:placetype":"locality"
},
  "geometry": {"coordinates":[128.01202000000001,1.09704],"type":"Point"}
}