{
  "type": "Feature",
  "properties": {
    "gn:admin1_code":"38",
    "gn:asciiname":"Dara",
    "gn:country_code":"ID",
    "gn:dem":97,
    "gn:feature_class":"P",
    "gn:feature_code":"PPL",
    "gn:name":"Dara",
    "gn:population":0,
    "gn:timezone":"Asia/Makassar",
    "iso:country":"ID",
    "name:ces_x_preferred":[
        "Dara"
    ],
    "name:ind_x_preferred":[
        "Dara"
    ],
    "name:isl_x_preferred":[
        "Dara"
    ],
    "name:slv_x_preferred":[
        "Dara"
    ],
    "name:srp_x_preferred":[
        "\u0414\u0430\u0440\u0430"
    ],
    "wof:name":"Dara",
    "wof:placetype":"locality"
},
  "geometry": {"coordinates":[120.4537,-2.561],"type":"Point"}
}