{
  "type": "Feature",
  "properties": {
    "gn:admin1_code":"8",
    "gn:asciiname":"Tugu",
    "gn:country_code":"ID",
    "gn:dem":274,
    "gn:feature_class":"P",
    "gn:feature_code":"PPL",
    "gn:name":"Tugu",
    "gn:population":0,
    "gn:timezone":"Asia/Jakarta",
    "iso:country":"ID",
    "name:ceb_x_preferred":[
        "Tugu"
    ],
    "name:ind_x_preferred":[
        "Tugu"
    ],
    "name:nld_x_preferred":[
        "Tugu"
    ],
    "name:swe_x_preferred":[
        "Tugu"
    ],
    "wof:lang_x_official":[
        "ind"
    ],
    "wof:lang_x_spoken":[
        "ind",
        "eng"
    ],
    "wof:name":"Tugu",
    "wof:placetype":"locality"
},
  "geometry": {"coordinates":[113.1266,-7.8845],"type":"Point"}
}