{
  "type": "Feature",
  "properties": {
    "gn:admin1_code":"39",
    "gn:asciiname":"Itaro",
    "gn:country_code":"ID",
    "gn:dem":34,
    "gn:feature_class":"P",
    "gn:feature_code":"PPL",
    "gn:name":"Itaro",
    "gn:population":0,
    "gn:timezone":"Asia/Jayapura",
    "iso:country":"ID",
    "wof:name":"Itaro",
    "wof:placetype":"locality"
},
  "geometry": {"coordinates":[132.16553000000002,-1.49946],"type":"Point"}
}