{
  "type": "Feature",
  "properties": {
    "gn:admin1_code":"30",
    "gn:asciiname":"Lembangdua",
    "gn:country_code":"ID",
    "gn:dem":662,
    "gn:feature_class":"P",
    "gn:feature_code":"PPL",
    "gn:name":"Lembangdua",
    "gn:population":0,
    "gn:timezone":"Asia/Jakarta",
    "iso:country":"ID",
    "wof:name":"Lembangdua",
    "wof:placetype":"locality"
},
  "geometry": {"coordinates":[107.65083,-7.00278],"type":"Point"}
}