{
  "type": "Feature",
  "properties": {
    "gn:admin1_code":"30.0",
    "gn:asciiname":"Rancakole",
    "gn:cc2":"ID",
    "gn:country_code":"ID",
    "gn:dem":820,
    "gn:feature_class":"P",
    "gn:feature_code":"PPL",
    "gn:name":"Rancakole",
    "gn:population":0,
    "gn:timezone":"Asia/Jakarta",
    "iso:country":"ID",
    "name:und_x_variant":[
        "Rantjakole",
        "Rancakole"
    ],
    "wof:lang_x_official":[
        "ind"
    ],
    "wof:lang_x_spoken":[
        "ind",
        "eng"
    ],
    "wof:name":"Rancakole",
    "wof:placetype":"locality"
},
  "geometry": {"coordinates":[107.68111,-7.07556],"type":"Point"}
}