{
  "type": "Feature",
  "properties": {
    "gn:admin1_code":"42",
    "gn:asciiname":"Long Pala",
    "gn:country_code":"ID",
    "gn:dem":588,
    "gn:feature_class":"P",
    "gn:feature_code":"PPL",
    "gn:name":"Long Pala",
    "gn:population":0,
    "gn:timezone":"Asia/Makassar",
    "iso:country":"ID",
    "name:ind_x_preferred":[
        "Long Pala"
    ],
    "wof:name":"Long Pala",
    "wof:placetype":"locality"
},
  "geometry": {"coordinates":[116.10361,4.04709],"type":"Point"}
}