{
  "type": "Feature",
  "properties": {
    "gn:admin1_code":"2",
    "gn:asciiname":"Penataran",
    "gn:country_code":"ID",
    "gn:dem":528,
    "gn:feature_class":"P",
    "gn:feature_code":"PPL",
    "gn:name":"Penataran",
    "gn:population":0,
    "gn:timezone":"Asia/Makassar",
    "iso:country":"ID",
    "name:ind_x_preferred":[
        "Penataran"
    ],
    "wof:name":"Penataran",
    "wof:placetype":"locality"
},
  "geometry": {"coordinates":[114.95869999999999,-8.4242],"type":"Point"}
}