{
  "type": "Feature",
  "properties": {
    "gn:admin1_code":"2",
    "gn:asciiname":"Penataran",
    "gn:country_code":"ID",
    "gn:dem":528,
    "gn:feature_class":"P",
    "gn:feature_code":"PPL",
    "gn:name":"Penataran",
    "gn:population":0,
    "gn:timezone":"Asia/Makassar",
    "iso:country":"ID",
    "name:ara_x_preferred":[
        "\u0645\u0639\u0628\u062f \u0628\u064a\u0646\u0627\u062a\u0627\u0631\u0627\u0646"
    ],
    "name:eus_x_preferred":[
        "Penatarango tenplua"
    ],
    "name:ind_x_preferred":[
        "Penataran"
    ],
    "name:ind_x_variant":[
        "Candi Penataran"
    ],
    "name:jav_x_preferred":[
        "Candhi Penataran"
    ],
    "name:nld_x_preferred":[
        "Candi Panataran"
    ],
    "name:tam_x_preferred":[
        "\u0baa\u0bc6\u0ba9\u0ba4\u0bcd\u0ba4\u0bbe\u0bb0\u0bbe\u0ba9\u0bcd \u0b95\u0bcb\u0bb5\u0bbf\u0bb2\u0bcd"
    ],
    "name:tat_x_preferred":[
        "\u041f\u0435\u043d\u0430\u0442\u0430\u0440\u0430\u043d"
    ],
    "wof:name":"Penataran",
    "wof:placetype":"locality"
},
  "geometry": {"coordinates":[114.95869999999999,-8.4242],"type":"Point"}
}