{
  "type": "Feature",
  "properties": {
    "gn:country":"ID",
    "gn:fcode":"PPL",
    "gn:pop":23584,
    "iso:country":"ID",
    "name:unk_x_variant":[
        "Trutjuk"
    ],
    "qs:name":"Trucuk",
    "qs:name_adm0":"Indonesia",
    "qs:name_adm1":"Provinsi Jawa Tengah",
    "qs:photos_9r":0,
    "qs:photos_sr":0,
    "qs:placetype":"Town",
    "qs:pop_sr":"7",
    "wof:lang_x_official":[
        "ind"
    ],
    "wof:lang_x_spoken":[
        "ind",
        "eng"
    ],
    "wof:name":"Trucuk",
    "wof:placetype":"locality",
    "wof:population":23584
},
  "geometry": {"coordinates":[110.65889,-7.71833],"type":"Point"}
}