{
  "type": "Feature",
  "properties": {
    "gn:admin1_code":"18",
    "gn:asciiname":"Wanomangeda",
    "gn:country_code":"ID",
    "gn:dem":101,
    "gn:feature_class":"P",
    "gn:feature_code":"PPL",
    "gn:name":"Wanomangeda",
    "gn:population":0,
    "gn:timezone":"Asia/Makassar",
    "iso:country":"ID",
    "name:ind_x_preferred":[
        "Wanomangeda"
    ],
    "wof:name":"Wanomangeda",
    "wof:placetype":"locality"
},
  "geometry": {"coordinates":[119.24531,-9.44193],"type":"Point"}
}