{
  "type": "Feature",
  "properties": {
    "gn:admin1_code":"26",
    "gn:asciiname":"Pondok Aldeling Sembilan",
    "gn:country_code":"ID",
    "gn:dem":75,
    "gn:feature_class":"P",
    "gn:feature_code":"PPL",
    "gn:name":"Pondok Aldeling Sembilan",
    "gn:population":0,
    "gn:timezone":"Asia/Jakarta",
    "iso:country":"ID",
    "name:ind_x_preferred":[
        "Pondok Aldeling Sembilan"
    ],
    "name:und_x_variant":[
        "Pondok Aldeling IX"
    ],
    "wof:lang_x_official":[
        "ind"
    ],
    "wof:lang_x_spoken":[
        "ind",
        "eng"
    ],
    "wof:name":"Pondok Aldeling Sembilan",
    "wof:placetype":"locality"
},
  "geometry": {"coordinates":[98.21210000000001,3.8418],"type":"Point"}
}