{
  "type": "Feature",
  "properties": {
    "gn:admin1_code":"08",
    "gn:asciiname":"Samir",
    "gn:country_code":"ID",
    "gn:dem":6,
    "gn:feature_class":"P",
    "gn:feature_code":"PPL",
    "gn:name":"Samir",
    "gn:population":0,
    "gn:timezone":"Asia/Jakarta",
    "iso:country":"ID",
    "name:ara_x_preferred":[
        "\u0633\u0645\u064a\u0631"
    ],
    "name:aze_x_preferred":[
        "Samir"
    ],
    "name:ces_x_preferred":[
        "Samir"
    ],
    "name:deu_x_preferred":[
        "Samir"
    ],
    "name:fra_x_preferred":[
        "Samir"
    ],
    "name:hin_x_preferred":[
        "\u0938\u092e\u0940\u0930"
    ],
    "name:ind_x_preferred":[
        "Samir"
    ],
    "name:ita_x_preferred":[
        "Samir"
    ],
    "name:kor_x_preferred":[
        "\uc0ac\ubbf8\ub974"
    ],
    "name:nor_x_preferred":[
        "Samir"
    ],
    "name:slv_x_preferred":[
        "Samir"
    ],
    "name:swe_x_preferred":[
        "Samir"
    ],
    "name:ukr_x_preferred":[
        "\u0421\u0430\u043c\u0456\u0440"
    ],
    "wof:lang_x_official":[
        "ind"
    ],
    "wof:lang_x_spoken":[
        "ind",
        "eng"
    ],
    "wof:name":"Samir",
    "wof:placetype":"locality"
},
  "geometry": {"coordinates":[112.529,-7.1579],"type":"Point"}
}