{
  "type": "Feature",
  "properties": {
    "gn:admin1_code":"38.0",
    "gn:asciiname":"Nelulah",
    "gn:country_code":"ID",
    "gn:dem":1526,
    "gn:feature_class":"P",
    "gn:feature_code":"PPL",
    "gn:name":"Nelulah",
    "gn:population":0,
    "gn:timezone":"Asia/Makassar",
    "iso:country":"ID",
    "name:ind_x_preferred":[
        "Nelulah"
    ],
    "wof:name":"Nelulah",
    "wof:placetype":"locality"
},
  "geometry": {"coordinates":[119.8407,-2.9487],"type":"Point"}
}