{
  "type": "Feature",
  "properties": {
    "gn:admin1_code":"30",
    "gn:asciiname":"Cibarengkok",
    "gn:country_code":"ID",
    "gn:dem":838,
    "gn:feature_class":"P",
    "gn:feature_code":"PPL",
    "gn:name":"Cibarengkok",
    "gn:population":0,
    "gn:timezone":"Asia/Jakarta",
    "iso:country":"ID",
    "name:ind_x_preferred":[
        "Cibarengkok"
    ],
    "wof:name":"Cibarengkok",
    "wof:placetype":"locality"
},
  "geometry": {"coordinates":[107.03583,-6.88167],"type":"Point"}
}