{
  "type": "Feature",
  "properties": {
    "gn:admin1_code":"32.0",
    "gn:asciiname":"Talang Selalang",
    "gn:country_code":"ID",
    "gn:dem":50,
    "gn:feature_class":"P",
    "gn:feature_code":"PPL",
    "gn:name":"Talang Selalang",
    "gn:population":0,
    "gn:timezone":"Asia/Jakarta",
    "iso:country":"ID",
    "name:ind_x_preferred":[
        "Talang Selalang"
    ],
    "name:ind_x_variant":[
        "Talangselalang"
    ],
    "wof:name":"Talang Selalang",
    "wof:placetype":"locality"
},
  "geometry": {"coordinates":[104.24412,-3.75744],"type":"Point"}
}