{
  "type": "Feature",
  "properties": {
    "gn:admin1_code":"15.0",
    "gn:asciiname":"Talang Mesin",
    "gn:country_code":"ID",
    "gn:dem":868,
    "gn:feature_class":"P",
    "gn:feature_code":"PPL",
    "gn:name":"Talang Mesin",
    "gn:population":0,
    "gn:timezone":"Asia/Jakarta",
    "iso:country":"ID",
    "name:ind_x_preferred":[
        "Talang Mesin"
    ],
    "wof:name":"Talang Mesin",
    "wof:placetype":"locality"
},
  "geometry": {"coordinates":[104.41867000000001,-4.99972],"type":"Point"}
}