{
  "type": "Feature",
  "properties": {
    "gn:admin1_code":"26",
    "gn:asciiname":"Sidingkalang",
    "gn:country_code":"ID",
    "gn:dem":36,
    "gn:feature_class":"P",
    "gn:feature_code":"PPL",
    "gn:name":"Sidingkalang",
    "gn:population":0,
    "gn:timezone":"Asia/Jakarta",
    "iso:country":"ID",
    "name:ind_x_preferred":[
        "Sidingkalang"
    ],
    "wof:name":"Sidingkalang",
    "wof:placetype":"locality"
},
  "geometry": {"coordinates":[98.5752,1.9146],"type":"Point"}
}