{
  "type": "Feature",
  "properties": {
    "gn:admin1_code":"8.0",
    "gn:asciiname":"Slengok",
    "gn:country_code":"ID",
    "gn:dem":730,
    "gn:feature_class":"P",
    "gn:feature_code":"PPL",
    "gn:name":"Slengok",
    "gn:population":0,
    "gn:timezone":"Asia/Jakarta",
    "iso:country":"ID",
    "name:ind_x_preferred":[
        "Slengok"
    ],
    "wof:name":"Slengok",
    "wof:placetype":"locality"
},
  "geometry": {"coordinates":[111.6758,-7.8678],"type":"Point"}
}