{
  "type": "Feature",
  "properties": {
    "gn:admin1_code":"18.0",
    "gn:asciiname":"Pagesotobu",
    "gn:country_code":"ID",
    "gn:dem":534,
    "gn:feature_class":"P",
    "gn:feature_code":"PPL",
    "gn:name":"Pagesotobu",
    "gn:population":0,
    "gn:timezone":"Asia/Makassar",
    "iso:country":"ID",
    "name:ind_x_preferred":[
        "Pagesotobu"
    ],
    "wof:name":"Pagesotobu",
    "wof:placetype":"locality"
},
  "geometry": {"coordinates":[119.3955,-9.5392],"type":"Point"}
}