{
  "type": "Feature",
  "properties": {
    "gn:admin1_code":"2.0",
    "gn:asciiname":"Beluran",
    "gn:country_code":"ID",
    "gn:dem":48,
    "gn:feature_class":"P",
    "gn:feature_code":"PPL",
    "gn:name":"Beluran",
    "gn:population":0,
    "gn:timezone":"Asia/Makassar",
    "iso:country":"ID",
    "name:deu_x_preferred":[
        "Beluran"
    ],
    "name:fra_x_preferred":[
        "Beluran"
    ],
    "name:ind_x_preferred":[
        "Beluran"
    ],
    "name:msa_x_preferred":[
        "Beluran"
    ],
    "name:nor_x_preferred":[
        "Beluran"
    ],
    "name:vie_x_preferred":[
        "Beluran"
    ],
    "wof:name":"Beluran",
    "wof:placetype":"locality"
},
  "geometry": {"coordinates":[115.17019999999999,-8.6404],"type":"Point"}
}