{
  "type": "Feature",
  "properties": {
    "gn:admin1_code":"8.0",
    "gn:asciiname":"Pasarbaru",
    "gn:country_code":"ID",
    "gn:dem":41,
    "gn:feature_class":"P",
    "gn:feature_code":"PPLA4",
    "gn:name":"Pasarbaru",
    "gn:population":0,
    "gn:timezone":"Asia/Jakarta",
    "iso:country":"ID",
    "name:ind_x_preferred":[
        "Pasarbaru"
    ],
    "wof:name":"Pasarbaru",
    "wof:placetype":"locality"
},
  "geometry": {"coordinates":[115.3171,-6.8599],"type":"Point"}
}