{
  "type": "Feature",
  "properties": {
    "gn:admin1_code":"17",
    "gn:asciiname":"Roy",
    "gn:country_code":"ID",
    "gn:dem":17,
    "gn:feature_class":"P",
    "gn:feature_code":"PPL",
    "gn:name":"Roy",
    "gn:population":0,
    "gn:timezone":"Asia/Makassar",
    "iso:country":"ID",
    "name:deu_x_preferred":[
        "Roy"
    ],
    "name:fin_x_preferred":[
        "Roy"
    ],
    "name:ind_x_preferred":[
        "Roy"
    ],
    "name:nno_x_preferred":[
        "Roy"
    ],
    "name:nor_x_preferred":[
        "Roy"
    ],
    "name:swe_x_preferred":[
        "Roy"
    ],
    "wof:name":"Roy",
    "wof:placetype":"locality"
},
  "geometry": {"coordinates":[118.4389,-8.71],"type":"Point"}
}