{
  "type": "Feature",
  "properties": {
    "gn:admin1_code":"7.0",
    "gn:asciiname":"Pengasinan",
    "gn:country_code":"ID",
    "gn:dem":204,
    "gn:feature_class":"P",
    "gn:feature_code":"PPL",
    "gn:name":"Pengasinan",
    "gn:population":0,
    "gn:timezone":"Asia/Jakarta",
    "iso:country":"ID",
    "name:ind_x_preferred":[
        "Pengasinan"
    ],
    "wof:name":"Pengasinan",
    "wof:placetype":"locality"
},
  "geometry": {"coordinates":[108.97333,-7.38889],"type":"Point"}
}