{
  "type": "Feature",
  "properties": {
    "gn:admin1_code":"18.0",
    "gn:asciiname":"Ratung",
    "gn:country_code":"ID",
    "gn:dem":784,
    "gn:feature_class":"P",
    "gn:feature_code":"PPL",
    "gn:name":"Ratung",
    "gn:population":0,
    "gn:timezone":"Asia/Makassar",
    "iso:country":"ID",
    "name:ind_x_preferred":[
        "Ratung"
    ],
    "wof:name":"Ratung",
    "wof:placetype":"locality"
},
  "geometry": {"coordinates":[120.6191,-8.6792],"type":"Point"}
}