{
  "type": "Feature",
  "properties": {
    "iso:country":"ID",
    "name:eng_x_preferred":[
        "Cipete-besar"
    ],
    "name:eng_x_variant":[
        "Cipetepakojan",
        "Tjipete-besar"
    ],
    "name:und_x_variant":[
        "Pakojan"
    ],
    "name:unk_x_variant":[
        "Cipete-besar"
    ],
    "qs:gn_adm0_cc":"ID",
    "qs:gn_local":1625084,
    "qs:gn_nam_loc":"tangerang",
    "qs:gn_namadm1":"30",
    "qs:local_max":22,
    "qs:local_sum":40,
    "qs:localhoods":2,
    "qs:name":"Cipete-besar",
    "qs:name_adm0":"Indonesia",
    "qs:name_adm1":"Banten",
    "qs:name_adm2":"Kotamadya Tangerang",
    "qs:name_local":"Tangerang",
    "qs:photo_max":3,
    "qs:photo_sum":18,
    "qs:placetype":"Suburb",
    "qs:quad_count":12,
    "qs:woe_adm0":23424846,
    "qs:woe_adm1":28350158,
    "qs:woe_adm2":56000239,
    "qs:woe_lau":0,
    "qs:woe_local":1048536,
    "qs:woe_ver":"7.10.0",
    "wof:lang":[
        "eng"
    ],
    "wof:name":"Cipete-besar",
    "wof:placetype":"neighbourhood"
},
  "geometry": {"coordinates":[106.64428700000001,-6.215495],"type":"Point"}
}