{
  "type": "Feature",
  "properties": {
    "gn:admin1_code":"18.0",
    "gn:asciiname":"Roe",
    "gn:country_code":"ID",
    "gn:dem":525,
    "gn:feature_class":"P",
    "gn:feature_code":"PPL",
    "gn:name":"Roe",
    "gn:population":0,
    "gn:timezone":"Asia/Makassar",
    "iso:country":"ID",
    "name:ind_x_preferred":[
        "Roe"
    ],
    "wof:name":"Roe",
    "wof:placetype":"locality"
},
  "geometry": {"coordinates":[121.3282,-8.6181],"type":"Point"}
}