{
  "type": "Feature",
  "properties": {
    "gn:admin1_code":"7",
    "gn:asciiname":"Ngancar",
    "gn:country_code":"ID",
    "gn:dem":166,
    "gn:feature_class":"P",
    "gn:feature_code":"PPL",
    "gn:name":"Ngancar",
    "gn:population":0,
    "gn:timezone":"Asia/Jakarta",
    "iso:country":"ID",
    "name:ind_x_preferred":[
        "Ngancar"
    ],
    "wof:name":"Ngancar",
    "wof:placetype":"locality"
},
  "geometry": {"coordinates":[110.95778,-8.03528],"type":"Point"}
}