{
  "type": "Feature",
  "properties": {
    "gn:admin1_code":"26",
    "gn:asciiname":"Dau",
    "gn:country_code":"ID",
    "gn:dem":10,
    "gn:feature_class":"P",
    "gn:feature_code":"PPL",
    "gn:name":"Dau",
    "gn:population":0,
    "gn:timezone":"Asia/Jakarta",
    "iso:country":"ID",
    "name:cat_x_preferred":[
        "Dau"
    ],
    "name:ceb_x_preferred":[
        "Dau"
    ],
    "name:ind_x_preferred":[
        "Dau"
    ],
    "name:swe_x_preferred":[
        "Dau"
    ],
    "wof:lang_x_official":[
        "ind"
    ],
    "wof:lang_x_spoken":[
        "ind",
        "eng"
    ],
    "wof:name":"Dau",
    "wof:placetype":"locality"
},
  "geometry": {"coordinates":[97.20440000000001,1.377],"type":"Point"}
}