{
  "type": "Feature",
  "properties": {
    "gn:country":"ID",
    "gn:fcode":"PPL",
    "gn:pop":0,
    "iso:country":"ID",
    "name:ind_x_preferred":[
        "Camba"
    ],
    "name:ita_x_preferred":[
        "Camba"
    ],
    "name:jpn_x_preferred":[
        "\u30ab\u30f3\u30d0"
    ],
    "name:por_x_preferred":[
        "Camba"
    ],
    "name:spa_x_preferred":[
        "Camba"
    ],
    "name:unk_x_variant":[
        "Tjamba"
    ],
    "qs:name":"Camba",
    "qs:name_adm0":"Indonesia",
    "qs:name_adm1":"Sulawesi Barat",
    "qs:photos_9r":0,
    "qs:photos_sr":0,
    "qs:placetype":"Town",
    "qs:pop_sr":"0",
    "wof:lang_x_official":[
        "ind"
    ],
    "wof:lang_x_spoken":[
        "ind",
        "eng"
    ],
    "wof:name":"Camba",
    "wof:placetype":"locality",
    "wof:population":0
},
  "geometry": {"coordinates":[118.94840000000001,-3.5464],"type":"Point"}
}