{
  "type": "Feature",
  "properties": {
    "gn:admin1_code":"15.0",
    "gn:asciiname":"Umbulanasat",
    "gn:country_code":"ID",
    "gn:dem":138,
    "gn:feature_class":"P",
    "gn:feature_code":"PPL",
    "gn:name":"Umbulanasat",
    "gn:population":0,
    "gn:timezone":"Asia/Jakarta",
    "iso:country":"ID",
    "name:ind_x_preferred":[
        "Umbulanasat"
    ],
    "name:und_x_variant":[
        "Umbulan Asal",
        "Oemboelan Asat"
    ],
    "wof:name":"Umbulanasat",
    "wof:placetype":"locality"
},
  "geometry": {"coordinates":[103.87273,-5.10433],"type":"Point"}
}