{
  "type": "Feature",
  "properties": {
    "gn:admin1_code":"1",
    "gn:asciiname":"Putjuklomot",
    "gn:country_code":"ID",
    "gn:dem":2573,
    "gn:feature_class":"P",
    "gn:feature_code":"PPL",
    "gn:name":"Putjuklomot",
    "gn:population":0,
    "gn:timezone":"Asia/Jakarta",
    "iso:country":"ID",
    "name:ind_x_preferred":[
        "Putjuklomot"
    ],
    "wof:name":"Putjuklomot",
    "wof:placetype":"locality"
},
  "geometry": {"coordinates":[96.91030000000001,4.2861],"type":"Point"}
}