{
  "type": "Feature",
  "properties": {
    "gn:admin1_code":"30",
    "gn:asciiname":"Peusar Wetan",
    "gn:country_code":"ID",
    "gn:dem":46,
    "gn:feature_class":"P",
    "gn:feature_code":"PPL",
    "gn:name":"Peusar Wetan",
    "gn:population":0,
    "gn:timezone":"Asia/Jakarta",
    "iso:country":"ID",
    "name:ind_x_preferred":[
        "Peusar Wetan"
    ],
    "name:und_x_variant":[
        "Peusar 2",
        "Peusar Dua"
    ],
    "wof:name":"Peusar Wetan",
    "wof:placetype":"locality"
},
  "geometry": {"coordinates":[106.43889,-6.31889],"type":"Point"}
}