{
  "type": "Feature",
  "properties": {
    "gn:admin1_code":"2.0",
    "gn:asciiname":"Banjar Balersetra",
    "gn:country_code":"ID",
    "gn:dem":147,
    "gn:feature_class":"P",
    "gn:feature_code":"PPL",
    "gn:name":"Banjar Balersetra",
    "gn:population":0,
    "gn:timezone":"Asia/Makassar",
    "iso:country":"ID",
    "name:ind_x_preferred":[
        "Banjar Balersetra"
    ],
    "wof:name":"Banjar Balersetra",
    "wof:placetype":"locality"
},
  "geometry": {"coordinates":[114.82559999999999,-8.3861],"type":"Point"}
}