{
  "type": "Feature",
  "properties": {
    "gn:admin1_code":"13.0",
    "gn:asciiname":"Kumai",
    "gn:country_code":"ID",
    "gn:dem":6,
    "gn:feature_class":"P",
    "gn:feature_code":"PPL",
    "gn:name":"Kumai",
    "gn:population":0,
    "gn:timezone":"Asia/Pontianak",
    "iso:country":"ID",
    "name:bjn_x_preferred":[
        "Kumai"
    ],
    "name:ind_x_preferred":[
        "Kumai"
    ],
    "name:jav_x_preferred":[
        "Kumai"
    ],
    "name:msa_x_preferred":[
        "Kumai"
    ],
    "name:und_x_variant":[
        "Koealapemboeang",
        "Koemai",
        "Kualapembuang",
        "Kumai"
    ],
    "wof:name":"Kumai",
    "wof:placetype":"locality"
},
  "geometry": {"coordinates":[112.55134,-3.37524],"type":"Point"}
}