{
  "type": "Feature",
  "properties": {
    "gn:admin1_code":"8",
    "gn:asciiname":"Klanjan",
    "gn:country_code":"ID",
    "gn:dem":105,
    "gn:feature_class":"P",
    "gn:feature_code":"PPL",
    "gn:name":"Klanjan",
    "gn:population":0,
    "gn:timezone":"Asia/Jakarta",
    "iso:country":"ID",
    "name:ind_x_preferred":[
        "Klanjan"
    ],
    "wof:name":"Klanjan",
    "wof:placetype":"locality"
},
  "geometry": {"coordinates":[112.4314,-7.6072],"type":"Point"}
}