{
  "type": "Feature",
  "properties": {
    "gn:admin1_code":"30",
    "gn:asciiname":"Rancabali",
    "gn:country_code":"ID",
    "gn:dem":696,
    "gn:feature_class":"P",
    "gn:feature_code":"PPL",
    "gn:name":"Rancabali",
    "gn:population":0,
    "gn:timezone":"Asia/Jakarta",
    "iso:country":"ID",
    "name:ind_x_preferred":[
        "Rancabali"
    ],
    "wof:name":"Rancabali",
    "wof:placetype":"locality"
},
  "geometry": {"coordinates":[107.76560000000001,-7.0612],"type":"Point"}
}