{
  "type": "Feature",
  "properties": {
    "gn:admin1_code":"7.0",
    "gn:asciiname":"Karangpucung",
    "gn:country_code":"ID",
    "gn:dem":48,
    "gn:feature_class":"P",
    "gn:feature_code":"PPL",
    "gn:name":"Karangpucung",
    "gn:population":0,
    "gn:timezone":"Asia/Jakarta",
    "iso:country":"ID",
    "name:ind_x_preferred":[
        "Karangpucung"
    ],
    "wof:name":"Karangpucung",
    "wof:placetype":"locality"
},
  "geometry": {"coordinates":[109.17361,-7.45667],"type":"Point"}
}