{
  "type": "Feature",
  "properties": {
    "gn:admin1_code":"8",
    "gn:asciiname":"Curahlengkong Dua",
    "gn:country_code":"ID",
    "gn:dem":112,
    "gn:feature_class":"P",
    "gn:feature_code":"PPL",
    "gn:name":"Curahlengkong Dua",
    "gn:population":0,
    "gn:timezone":"Asia/Jakarta",
    "iso:country":"ID",
    "name:ind_x_preferred":[
        "Curahlengkong Dua"
    ],
    "wof:name":"Curahlengkong Dua",
    "wof:placetype":"locality"
},
  "geometry": {"coordinates":[113.2546,-8.055],"type":"Point"}
}