{
  "type": "Feature",
  "properties": {
    "gn:admin1_code":"38.0",
    "gn:asciiname":"Jawaro",
    "gn:country_code":"ID",
    "gn:dem":25,
    "gn:feature_class":"P",
    "gn:feature_code":"PPL",
    "gn:name":"Jawaro",
    "gn:population":0,
    "gn:timezone":"Asia/Makassar",
    "iso:country":"ID",
    "name:ind_x_preferred":[
        "Jawaro"
    ],
    "wof:name":"Jawaro",
    "wof:placetype":"locality"
},
  "geometry": {"coordinates":[120.3643,-3.4005],"type":"Point"}
}