{
  "type": "Feature",
  "properties": {
    "gn:admin1_code":"7",
    "gn:asciiname":"Majenang",
    "gn:country_code":"ID",
    "gn:dem":66,
    "gn:feature_class":"P",
    "gn:feature_code":"PPL",
    "gn:name":"Majenang",
    "gn:population":0,
    "gn:timezone":"Asia/Jakarta",
    "iso:country":"ID",
    "name:ind_x_preferred":[
        "Majenang"
    ],
    "wof:name":"Majenang",
    "wof:placetype":"locality"
},
  "geometry": {"coordinates":[110.91694,-7.17167],"type":"Point"}
}