{
  "type": "Feature",
  "properties": {
    "gn:admin1_code":"30",
    "gn:asciiname":"Capar Tiga",
    "gn:country_code":"ID",
    "gn:dem":176,
    "gn:feature_class":"P",
    "gn:feature_code":"PPL",
    "gn:name":"Capar Tiga",
    "gn:population":0,
    "gn:timezone":"Asia/Jakarta",
    "iso:country":"ID",
    "name:ind_x_preferred":[
        "Capar Tiga"
    ],
    "wof:name":"Capar Tiga",
    "wof:placetype":"locality"
},
  "geometry": {"coordinates":[108.45667,-6.77889],"type":"Point"}
}