{
  "type": "Feature",
  "properties": {
    "gn:admin1_code":"30",
    "gn:asciiname":"Nangoh",
    "gn:country_code":"ID",
    "gn:dem":668,
    "gn:feature_class":"P",
    "gn:feature_code":"PPL",
    "gn:name":"Nangoh",
    "gn:population":0,
    "gn:timezone":"Asia/Jakarta",
    "iso:country":"ID",
    "name:ind_x_preferred":[
        "Nangoh"
    ],
    "wof:name":"Nangoh",
    "wof:placetype":"locality"
},
  "geometry": {"coordinates":[107.02916999999999,-6.98028],"type":"Point"}
}