{
  "type": "Feature",
  "properties": {
    "gn:admin1_code":"21",
    "gn:asciiname":"Moengko Lama",
    "gn:country_code":"ID",
    "gn:dem":21,
    "gn:feature_class":"P",
    "gn:feature_code":"PPL",
    "gn:name":"Moengko Lama",
    "gn:population":0,
    "gn:timezone":"Asia/Makassar",
    "iso:country":"ID",
    "name:ind_x_preferred":[
        "Moengko Lama"
    ],
    "wof:name":"Moengko Lama",
    "wof:placetype":"locality"
},
  "geometry": {"coordinates":[120.72280000000001,-1.3934],"type":"Point"}
}