{
  "type": "Feature",
  "properties": {
    "gn:admin1_code":"30.0",
    "gn:asciiname":"Cibatu",
    "gn:country_code":"ID",
    "gn:dem":93,
    "gn:feature_class":"P",
    "gn:feature_code":"PPLA4",
    "gn:name":"Cibatu",
    "gn:population":0,
    "gn:timezone":"Asia/Jakarta",
    "iso:country":"ID",
    "name:ind_x_preferred":[
        "Cibatu"
    ],
    "name:und_x_variant":[
        "Tjibatu",
        "Cibatu",
        "Tjibatoe"
    ],
    "wof:name":"Cibatu",
    "wof:placetype":"locality"
},
  "geometry": {"coordinates":[108.2008,-7.6327],"type":"Point"}
}