{
  "type": "Feature",
  "properties": {
    "gn:admin1_code":"4",
    "gn:asciiname":"Alfa Indah",
    "gn:country_code":"ID",
    "gn:dem":12,
    "gn:feature_class":"P",
    "gn:feature_code":"PPL",
    "gn:name":"Alfa Indah",
    "gn:population":0,
    "gn:timezone":"Asia/Jakarta",
    "iso:country":"ID",
    "name:ind_x_preferred":[
        "Alfa Indah"
    ],
    "wof:name":"Alfa Indah",
    "wof:placetype":"locality"
},
  "geometry": {"coordinates":[106.75360000000001,-6.2227],"type":"Point"}
}