{
  "type": "Feature",
  "properties": {
    "gn:admin1_code":"1",
    "gn:asciiname":"Alumeuting",
    "gn:country_code":"ID",
    "gn:dem":10,
    "gn:feature_class":"P",
    "gn:feature_code":"PPL",
    "gn:name":"Alumeuting",
    "gn:population":0,
    "gn:timezone":"Asia/Jakarta",
    "iso:country":"ID",
    "name:ind_x_preferred":[
        "Alumeuting"
    ],
    "wof:name":"Alumeuting",
    "wof:placetype":"locality"
},
  "geometry": {"coordinates":[97.51600000000001,5.0931],"type":"Point"}
}