{
  "type": "Feature",
  "properties": {
    "gn:admin1_code":"07",
    "gn:asciiname":"Suroyudan",
    "gn:country_code":"ID",
    "gn:dem":551,
    "gn:feature_class":"P",
    "gn:feature_code":"PPL",
    "gn:name":"Suroyudan",
    "gn:population":0,
    "gn:timezone":"Asia/Jakarta",
    "iso:country":"ID",
    "name:und_x_variant":[
        "Soroyudan",
        "Sorojudan",
        "Suroyudan"
    ],
    "wof:lang_x_official":[
        "ind"
    ],
    "wof:lang_x_spoken":[
        "ind",
        "eng"
    ],
    "wof:name":"Suroyudan",
    "wof:placetype":"locality"
},
  "geometry": {"coordinates":[110.28944,-7.465],"type":"Point"}
}