{
  "type": "Feature",
  "properties": {
    "gn:admin1_code":"7.0",
    "gn:asciiname":"Sanggung",
    "gn:country_code":"ID",
    "gn:dem":139,
    "gn:feature_class":"P",
    "gn:feature_code":"PPL",
    "gn:name":"Sanggung",
    "gn:population":0,
    "gn:timezone":"Asia/Jakarta",
    "iso:country":"ID",
    "name:ind_x_preferred":[
        "Sanggung"
    ],
    "name:sin_x_preferred":[
        "\u0dc3\u0d82\u0d9c\u0dd4\u0d82"
    ],
    "name:tha_x_preferred":[
        "\u0e0b\u0e31\u0e07\u0e01\u0e38\u0e07"
    ],
    "wof:lang_x_official":[
        "ind"
    ],
    "wof:lang_x_spoken":[
        "ind",
        "eng"
    ],
    "wof:name":"Sanggung",
    "wof:placetype":"locality"
},
  "geometry": {"coordinates":[110.70972,-7.59389],"type":"Point"}
}