{
  "type": "Feature",
  "properties": {
    "gn:admin1_code":"07",
    "gn:asciiname":"Wringinpitu",
    "gn:country_code":"ID",
    "gn:dem":49,
    "gn:feature_class":"P",
    "gn:feature_code":"PPL",
    "gn:name":"Wringinpitu",
    "gn:population":0,
    "gn:timezone":"Asia/Jakarta",
    "iso:country":"ID",
    "wof:name":"Wringinpitu",
    "wof:placetype":"locality"
},
  "geometry": {"coordinates":[110.59721999999999,-7.11694],"type":"Point"}
}