{
  "type": "Feature",
  "properties": {
    "gn:admin1_code":"30",
    "gn:asciiname":"Leuwikeris",
    "gn:country_code":"ID",
    "gn:dem":41,
    "gn:feature_class":"P",
    "gn:feature_code":"PPL",
    "gn:name":"Leuwikeris",
    "gn:population":0,
    "gn:timezone":"Asia/Jakarta",
    "iso:country":"ID",
    "name:ind_x_preferred":[
        "Leuwikeris"
    ],
    "wof:name":"Leuwikeris",
    "wof:placetype":"locality"
},
  "geometry": {"coordinates":[108.68170000000001,-6.9276],"type":"Point"}
}