{
  "type": "Feature",
  "properties": {
    "gn:admin1_code":"7.0",
    "gn:asciiname":"Karang",
    "gn:country_code":"ID",
    "gn:dem":903,
    "gn:feature_class":"P",
    "gn:feature_code":"PPL",
    "gn:name":"Karang",
    "gn:population":0,
    "gn:timezone":"Asia/Jakarta",
    "iso:country":"ID",
    "wof:name":"Karang",
    "wof:placetype":"locality"
},
  "geometry": {"coordinates":[110.47861,-7.59361],"type":"Point"}
}