{
  "type": "Feature",
  "properties": {
    "gn:admin1_code":"30.0",
    "gn:asciiname":"Kertabumi",
    "gn:country_code":"ID",
    "gn:dem":120,
    "gn:feature_class":"P",
    "gn:feature_code":"PPLA4",
    "gn:name":"Kertabumi",
    "gn:population":0,
    "gn:timezone":"Asia/Jakarta",
    "iso:country":"ID",
    "name:ind_x_preferred":[
        "Kertabumi"
    ],
    "name:und_x_variant":[
        "Kertaboemi"
    ],
    "wof:name":"Kertabumi",
    "wof:placetype":"locality"
},
  "geometry": {"coordinates":[108.4384,-7.3347],"type":"Point"}
}