{
  "type": "Feature",
  "properties": {
    "gn:admin1_code":"8",
    "gn:asciiname":"Sonokembang",
    "gn:country_code":"ID",
    "gn:dem":444,
    "gn:feature_class":"P",
    "gn:feature_code":"PPL",
    "gn:name":"Sonokembang",
    "gn:population":0,
    "gn:timezone":"Asia/Jakarta",
    "iso:country":"ID",
    "name:ind_x_preferred":[
        "Sonokembang"
    ],
    "wof:name":"Sonokembang",
    "wof:placetype":"locality"
},
  "geometry": {"coordinates":[112.6558,-7.958],"type":"Point"}
}