{
  "type": "Feature",
  "properties": {
    "gn:admin1_code":"38.0",
    "gn:asciiname":"Banda",
    "gn:country_code":"ID",
    "gn:dem":893,
    "gn:feature_class":"P",
    "gn:feature_code":"PPL",
    "gn:name":"Banda",
    "gn:population":0,
    "gn:timezone":"Asia/Makassar",
    "iso:country":"ID",
    "name:ind_x_preferred":[
        "Banda"
    ],
    "wof:name":"Banda",
    "wof:placetype":"locality"
},
  "geometry": {"coordinates":[119.5891,-3.1072],"type":"Point"}
}