{
  "type": "Feature",
  "properties": {
    "gn:admin1_code":"1",
    "gn:asciiname":"Lang Nibong",
    "gn:country_code":"ID",
    "gn:dem":5,
    "gn:feature_class":"P",
    "gn:feature_code":"PPL",
    "gn:name":"Lang Nibong",
    "gn:population":0,
    "gn:timezone":"Asia/Jakarta",
    "iso:country":"ID",
    "name:ind_x_preferred":[
        "Lang Nibong"
    ],
    "wof:name":"Lang Nibong",
    "wof:placetype":"locality"
},
  "geometry": {"coordinates":[97.3751,5.1096],"type":"Point"}
}