{
  "type": "Feature",
  "properties": {
    "gn:admin1_code":"7",
    "gn:asciiname":"Ponowareng Dua",
    "gn:country_code":"ID",
    "gn:dem":12,
    "gn:feature_class":"P",
    "gn:feature_code":"PPL",
    "gn:name":"Ponowareng Dua",
    "gn:population":0,
    "gn:timezone":"Asia/Jakarta",
    "iso:country":"ID",
    "name:ind_x_preferred":[
        "Ponowareng Dua"
    ],
    "wof:name":"Ponowareng Dua",
    "wof:placetype":"locality"
},
  "geometry": {"coordinates":[109.8045,-6.9174],"type":"Point"}
}