{
  "type": "Feature",
  "properties": {
    "gn:admin1_code":"8",
    "gn:asciiname":"Dango",
    "gn:country_code":"ID",
    "gn:dem":783,
    "gn:feature_class":"P",
    "gn:feature_code":"PPL",
    "gn:name":"Dango",
    "gn:population":0,
    "gn:timezone":"Asia/Jakarta",
    "iso:country":"ID",
    "name:ind_x_preferred":[
        "Dango"
    ],
    "wof:name":"Dango",
    "wof:placetype":"locality"
},
  "geometry": {"coordinates":[111.26222,-7.72472],"type":"Point"}
}