{
  "type": "Feature",
  "properties": {
    "gn:admin1_code":"30",
    "gn:asciiname":"Rahong",
    "gn:country_code":"ID",
    "gn:dem":675,
    "gn:feature_class":"P",
    "gn:feature_code":"PPL",
    "gn:name":"Rahong",
    "gn:population":0,
    "gn:timezone":"Asia/Jakarta",
    "iso:country":"ID",
    "name:ind_x_preferred":[
        "Rahong"
    ],
    "wof:name":"Rahong",
    "wof:placetype":"locality"
},
  "geometry": {"coordinates":[107.33444,-6.90028],"type":"Point"}
}