{
  "type": "Feature",
  "properties": {
    "gn:admin1_code":"30.0",
    "gn:asciiname":"Sukamanah",
    "gn:country_code":"ID",
    "gn:dem":501,
    "gn:feature_class":"P",
    "gn:feature_code":"PPL",
    "gn:name":"Sukamanah",
    "gn:population":0,
    "gn:timezone":"Asia/Jakarta",
    "iso:country":"ID",
    "name:ind_x_preferred":[
        "Sukamanah"
    ],
    "wof:name":"Sukamanah",
    "wof:placetype":"locality"
},
  "geometry": {"coordinates":[106.95659999999999,-7.17],"type":"Point"}
}