{
  "type": "Feature",
  "properties": {
    "gn:admin1_code":"30",
    "gn:asciiname":"Rancbeet Kulon",
    "gn:country_code":"ID",
    "gn:dem":976,
    "gn:feature_class":"P",
    "gn:feature_code":"PPL",
    "gn:name":"Rancbeet Kulon",
    "gn:population":0,
    "gn:timezone":"Asia/Jakarta",
    "iso:country":"ID",
    "name:ind_x_preferred":[
        "Rancbeet Kulon"
    ],
    "wof:name":"Rancbeet Kulon",
    "wof:placetype":"locality"
},
  "geometry": {"coordinates":[107.8242,-7.2112],"type":"Point"}
}