{
  "type": "Feature",
  "properties": {
    "gn:admin1_code":"26",
    "gn:asciiname":"Batumandi",
    "gn:country_code":"ID",
    "gn:dem":37,
    "gn:feature_class":"P",
    "gn:feature_code":"PPL",
    "gn:name":"Batumandi",
    "gn:population":0,
    "gn:timezone":"Asia/Jakarta",
    "iso:country":"ID",
    "name:ind_x_preferred":[
        "Batumandi"
    ],
    "wof:name":"Batumandi",
    "wof:placetype":"locality"
},
  "geometry": {"coordinates":[98.3817,3.6449],"type":"Point"}
}