{
  "type": "Feature",
  "properties": {
    "gn:admin1_code":"30",
    "gn:asciiname":"Rawajati",
    "gn:country_code":"ID",
    "gn:dem":159,
    "gn:feature_class":"P",
    "gn:feature_code":"PPL",
    "gn:name":"Rawajati",
    "gn:population":0,
    "gn:timezone":"Asia/Jakarta",
    "iso:country":"ID",
    "name:ind_x_preferred":[
        "Rawajati"
    ],
    "wof:name":"Rawajati",
    "wof:placetype":"locality"
},
  "geometry": {"coordinates":[106.77388999999999,-6.51778],"type":"Point"}
}