{
  "type": "Feature",
  "properties": {
    "gn:admin1_code":"30.0",
    "gn:asciiname":"Gardu",
    "gn:country_code":"ID",
    "gn:dem":440,
    "gn:feature_class":"P",
    "gn:feature_code":"PPLA4",
    "gn:name":"Gardu",
    "gn:population":0,
    "gn:timezone":"Asia/Jakarta",
    "iso:country":"ID",
    "name:ind_x_preferred":[
        "Gardu"
    ],
    "name:nld_x_preferred":[
        "Gardu"
    ],
    "name:und_x_variant":[
        "Gardoe Dua"
    ],
    "wof:name":"Gardu",
    "wof:placetype":"locality"
},
  "geometry": {"coordinates":[108.3845,-7.0762],"type":"Point"}
}