{
  "type": "Feature",
  "properties": {
    "gn:admin1_code":"30.0",
    "gn:asciiname":"Jati Dua",
    "gn:country_code":"ID",
    "gn:dem":65,
    "gn:feature_class":"P",
    "gn:feature_code":"PPL",
    "gn:name":"Jati Dua",
    "gn:population":0,
    "gn:timezone":"Asia/Jakarta",
    "iso:country":"ID",
    "name:ind_x_preferred":[
        "Jati Dua"
    ],
    "name:und_x_variant":[
        "Babakan Jati",
        "Babakan Djati",
        "Jati 2"
    ],
    "wof:lang_x_official":[
        "ind"
    ],
    "wof:lang_x_spoken":[
        "ind",
        "eng"
    ],
    "wof:name":"Jati Dua",
    "wof:placetype":"locality"
},
  "geometry": {"coordinates":[107.21556,-6.47972],"type":"Point"}
}