{
  "type": "Feature",
  "properties": {
    "gn:admin1_code":"30.0",
    "gn:asciiname":"Cimapag Tiga",
    "gn:country_code":"ID",
    "gn:dem":30,
    "gn:feature_class":"P",
    "gn:feature_code":"PPL",
    "gn:name":"Cimapag Tiga",
    "gn:population":0,
    "gn:timezone":"Asia/Jakarta",
    "iso:country":"ID",
    "name:ind_x_preferred":[
        "Cimapag Tiga"
    ],
    "wof:name":"Cimapag Tiga",
    "wof:placetype":"locality"
},
  "geometry": {"coordinates":[106.8463,-7.4265],"type":"Point"}
}