{
  "type": "Feature",
  "properties": {
    "gn:admin1_code":"17.0",
    "gn:asciiname":"Padende",
    "gn:country_code":"ID",
    "gn:dem":789,
    "gn:feature_class":"P",
    "gn:feature_code":"PPL",
    "gn:name":"Padende",
    "gn:population":0,
    "gn:timezone":"Asia/Makassar",
    "iso:country":"ID",
    "name:ind_x_preferred":[
        "Padende"
    ],
    "wof:name":"Padende",
    "wof:placetype":"locality"
},
  "geometry": {"coordinates":[118.532,-8.4317],"type":"Point"}
}