{
  "type": "Feature",
  "properties": {
    "gn:admin1_code":"38",
    "gn:asciiname":"Kajuara",
    "gn:country_code":"ID",
    "gn:dem":56,
    "gn:feature_class":"P",
    "gn:feature_code":"PPL",
    "gn:name":"Kajuara",
    "gn:population":0,
    "gn:timezone":"Asia/Makassar",
    "iso:country":"ID",
    "name:ind_x_preferred":[
        "Kajuara"
    ],
    "wof:name":"Kajuara",
    "wof:placetype":"locality"
},
  "geometry": {"coordinates":[119.8978,-4.2846],"type":"Point"}
}