{
  "type": "Feature",
  "properties": {
    "gn:admin1_code":"30",
    "gn:asciiname":"Bangjaranpucung Dua",
    "gn:cc2":"ID",
    "gn:country_code":"ID",
    "gn:dem":111,
    "gn:feature_class":"P",
    "gn:feature_code":"PPL",
    "gn:name":"Bangjaranpucung Dua",
    "gn:population":0,
    "gn:timezone":"Asia/Jakarta",
    "iso:country":"ID",
    "name:und_x_variant":[
        "Bangdjaranputjung 2",
        "Bangdjaranputjung Dua",
        "Bangjaranpucung Dua"
    ],
    "wof:name":"Bangjaranpucung Dua",
    "wof:placetype":"locality"
},
  "geometry": {"coordinates":[106.87944,-6.43611],"type":"Point"}
}