{
  "type": "Feature",
  "properties": {
    "gn:admin1_code":"38.0",
    "gn:asciiname":"Melle",
    "gn:country_code":"ID",
    "gn:dem":51,
    "gn:feature_class":"P",
    "gn:feature_code":"PPL",
    "gn:name":"Melle",
    "gn:population":0,
    "gn:timezone":"Asia/Makassar",
    "iso:country":"ID",
    "name:bel_x_preferred":[
        "\u041c\u0435\u043b\u0435"
    ],
    "name:bre_x_preferred":[
        "Melle"
    ],
    "name:cat_x_preferred":[
        "Melle"
    ],
    "name:ceb_x_preferred":[
        "Melle"
    ],
    "name:deu_x_preferred":[
        "Melle"
    ],
    "name:epo_x_preferred":[
        "Melle"
    ],
    "name:est_x_preferred":[
        "Melle"
    ],
    "name:fra_x_preferred":[
        "Melle"
    ],
    "name:glg_x_preferred":[
        "Melle"
    ],
    "name:hun_x_preferred":[
        "Melle"
    ],
    "name:ind_x_preferred":[
        "Melle"
    ],
    "name:ita_x_preferred":[
        "Melle"
    ],
    "name:kaz_x_preferred":[
        "\u041c\u0435\u043b\u043b\u0435"
    ],
    "name:nds_x_preferred":[
        "Melle"
    ],
    "name:nld_x_preferred":[
        "Melle"
    ],
    "name:nor_x_preferred":[
        "Melle"
    ],
    "name:pol_x_preferred":[
        "Melle"
    ],
    "name:por_x_preferred":[
        "Melle"
    ],
    "name:ron_x_preferred":[
        "Melle"
    ],
    "name:rus_x_preferred":[
        "\u041c\u0435\u043b\u043b\u0435"
    ],
    "name:spa_x_preferred":[
        "Melle"
    ],
    "name:swe_x_preferred":[
        "Melle"
    ],
    "name:ukr_x_preferred":[
        "\u041c\u0435\u043b\u043b\u0435"
    ],
    "name:vol_x_preferred":[
        "Melle"
    ],
    "wof:name":"Melle",
    "wof:placetype":"locality"
},
  "geometry": {"coordinates":[120.294,-4.5853],"type":"Point"}
}