{
  "type": "Feature",
  "properties": {
    "gn:admin1_code":"38.0",
    "gn:asciiname":"Melle",
    "gn:country_code":"ID",
    "gn:dem":51,
    "gn:feature_class":"P",
    "gn:feature_code":"PPL",
    "gn:name":"Melle",
    "gn:population":0,
    "gn:timezone":"Asia/Makassar",
    "iso:country":"ID",
    "name:ind_x_preferred":[
        "Melle"
    ],
    "wof:name":"Melle",
    "wof:placetype":"locality"
},
  "geometry": {"coordinates":[120.294,-4.5853],"type":"Point"}
}