{
  "type": "Feature",
  "properties": {
    "gn:admin1_code":"33.0",
    "gn:asciiname":"Pasauran",
    "gn:country_code":"ID",
    "gn:dem":10,
    "gn:feature_class":"P",
    "gn:feature_code":"PPLA4",
    "gn:name":"Pasauran",
    "gn:population":0,
    "gn:timezone":"Asia/Jakarta",
    "iso:country":"ID",
    "name:ind_x_preferred":[
        "Pasauran"
    ],
    "name:und_x_variant":[
        "Pasaoeran",
        "Pasauran"
    ],
    "wof:lang_x_official":[
        "ind"
    ],
    "wof:lang_x_spoken":[
        "ind",
        "eng"
    ],
    "wof:name":"Pasauran",
    "wof:placetype":"locality"
},
  "geometry": {"coordinates":[105.8325,-6.2306],"type":"Point"}
}