{
  "type": "Feature",
  "properties": {
    "gn:admin1_code":"1.0",
    "gn:asciiname":"Baleq",
    "gn:country_code":"ID",
    "gn:dem":898,
    "gn:feature_class":"P",
    "gn:feature_code":"PPL",
    "gn:name":"Baleq",
    "gn:population":0,
    "gn:timezone":"Asia/Jakarta",
    "iso:country":"ID",
    "name:ind_x_preferred":[
        "Baleq"
    ],
    "name:und_x_variant":[
        "Bal\u00e9q",
        "Balek"
    ],
    "wof:name":"Baleq",
    "wof:placetype":"locality"
},
  "geometry": {"coordinates":[96.7281,4.7209],"type":"Point"}
}