{
  "type": "Feature",
  "properties": {
    "gn:admin1_code":"7.0",
    "gn:asciiname":"Watugede",
    "gn:country_code":"ID",
    "gn:dem":198,
    "gn:feature_class":"P",
    "gn:feature_code":"PPL",
    "gn:name":"Watugede",
    "gn:population":0,
    "gn:timezone":"Asia/Jakarta",
    "iso:country":"ID",
    "name:ind_x_preferred":[
        "Watugede"
    ],
    "wof:name":"Watugede",
    "wof:placetype":"locality"
},
  "geometry": {"coordinates":[109.75722,-7.61222],"type":"Point"}
}