{
  "type": "Feature",
  "properties": {
    "gn:admin1_code":"7",
    "gn:asciiname":"Gendero",
    "gn:country_code":"ID",
    "gn:dem":4,
    "gn:feature_class":"P",
    "gn:feature_code":"PPL",
    "gn:name":"Gendero",
    "gn:population":0,
    "gn:timezone":"Asia/Jakarta",
    "iso:country":"ID",
    "name:ind_x_preferred":[
        "Gendero"
    ],
    "wof:name":"Gendero",
    "wof:placetype":"locality"
},
  "geometry": {"coordinates":[110.54940000000001,-6.8288],"type":"Point"}
}