{
  "type": "Feature",
  "properties": {
    "gn:admin1_code":"37.0",
    "gn:asciiname":"Sotol",
    "gn:country_code":"ID",
    "gn:dem":16,
    "gn:feature_class":"P",
    "gn:feature_code":"PPL",
    "gn:name":"Sotol",
    "gn:population":0,
    "gn:timezone":"Asia/Jakarta",
    "iso:country":"ID",
    "name:eng_x_preferred":[
        "Setul"
    ],
    "name:ind_x_preferred":[
        "Sotol"
    ],
    "name:und_x_variant":[
        "Setoel"
    ],
    "wof:name":"Sotol",
    "wof:placetype":"locality"
},
  "geometry": {"coordinates":[101.6129,0.2121],"type":"Point"}
}