{
  "type": "Feature",
  "properties": {
    "gn:admin1_code":"8.0",
    "gn:asciiname":"Sumberyuyu",
    "gn:country_code":"ID",
    "gn:dem":128,
    "gn:feature_class":"P",
    "gn:feature_code":"PPL",
    "gn:name":"Sumberyuyu",
    "gn:population":0,
    "gn:timezone":"Asia/Jakarta",
    "iso:country":"ID",
    "name:ind_x_preferred":[
        "Sumberyuyu"
    ],
    "wof:name":"Sumberyuyu",
    "wof:placetype":"locality"
},
  "geometry": {"coordinates":[111.92449999999999,-7.734],"type":"Point"}
}