{
  "type": "Feature",
  "properties": {
    "gn:admin1_code":"26",
    "gn:asciiname":"Rahu",
    "gn:country_code":"ID",
    "gn:dem":1021,
    "gn:feature_class":"P",
    "gn:feature_code":"PPL",
    "gn:name":"Rahu",
    "gn:population":0,
    "gn:timezone":"Asia/Jakarta",
    "iso:country":"ID",
    "name:ind_x_preferred":[
        "Rahu"
    ],
    "wof:name":"Rahu",
    "wof:placetype":"locality"
},
  "geometry": {"coordinates":[98.3387,2.6424],"type":"Point"}
}