{
  "type": "Feature",
  "properties": {
    "gn:admin1_code":"28.0",
    "gn:asciiname":"Jursian",
    "gn:country_code":"ID",
    "gn:dem":0,
    "gn:feature_class":"P",
    "gn:feature_code":"PPL",
    "gn:name":"Jursian",
    "gn:population":0,
    "gn:timezone":"Asia/Jayapura",
    "iso:country":"ID",
    "name:und_x_variant":[
        "Djoersian",
        "Djursian",
        "Jursian"
    ],
    "wof:name":"Jursian",
    "wof:placetype":"locality"
},
  "geometry": {"coordinates":[134.80267000000001,-5.87611],"type":"Point"}
}