{
  "type": "Feature",
  "properties": {
    "gn:admin1_code":"8",
    "gn:asciiname":"Lawar",
    "gn:country_code":"ID",
    "gn:dem":285,
    "gn:feature_class":"P",
    "gn:feature_code":"PPL",
    "gn:name":"Lawar",
    "gn:population":0,
    "gn:timezone":"Asia/Jakarta",
    "iso:country":"ID",
    "name:bpy_x_preferred":[
        "\u09b2\u09be\u09f1\u09be\u09b0 \u098f\u09a8\u09aa\u09bf"
    ],
    "name:ceb_x_preferred":[
        "L\u0101war Kh\u0101s"
    ],
    "name:ind_x_preferred":[
        "Lawar"
    ],
    "name:ita_x_preferred":[
        "Lawar"
    ],
    "name:msa_x_preferred":[
        "Lawar"
    ],
    "name:nld_x_preferred":[
        "Lawar"
    ],
    "name:pol_x_preferred":[
        "Lawar"
    ],
    "name:por_x_preferred":[
        "Lawar"
    ],
    "name:swe_x_preferred":[
        "L\u0101war Kh\u0101s"
    ],
    "name:urd_x_preferred":[
        "\u0644\u0627\u0648\u0631"
    ],
    "name:vie_x_preferred":[
        "Lawar"
    ],
    "name:zho_x_preferred":[
        "\u62c9\u74e6\u5c14\u6069\u666e"
    ],
    "wof:lang_x_official":[
        "ind"
    ],
    "wof:lang_x_spoken":[
        "ind",
        "eng"
    ],
    "wof:name":"Lawar",
    "wof:placetype":"locality"
},
  "geometry": {"coordinates":[111.34721999999999,-7.63944],"type":"Point"}
}