{
  "type": "Feature",
  "properties": {
    "gn:admin1_code":"38",
    "gn:asciiname":"Butung Dua",
    "gn:country_code":"ID",
    "gn:dem":26,
    "gn:feature_class":"P",
    "gn:feature_code":"PPL",
    "gn:name":"Butung Dua",
    "gn:population":0,
    "gn:timezone":"Asia/Makassar",
    "iso:country":"ID",
    "name:ind_x_preferred":[
        "Butung Dua"
    ],
    "name:und_x_variant":[
        "Butung 2"
    ],
    "wof:name":"Butung Dua",
    "wof:placetype":"locality"
},
  "geometry": {"coordinates":[120.42829999999999,-5.4353],"type":"Point"}
}