{
  "type": "Feature",
  "properties": {
    "gn:admin1_code":"8",
    "gn:asciiname":"Wonosari Kidul",
    "gn:country_code":"ID",
    "gn:dem":5,
    "gn:feature_class":"P",
    "gn:feature_code":"PPL",
    "gn:name":"Wonosari Kidul",
    "gn:population":0,
    "gn:timezone":"Asia/Jakarta",
    "iso:country":"ID",
    "name:ind_x_preferred":[
        "Wonosari Kidul"
    ],
    "wof:name":"Wonosari Kidul",
    "wof:placetype":"locality"
},
  "geometry": {"coordinates":[114.37390000000001,-8.251],"type":"Point"}
}