{
  "type": "Feature",
  "properties": {
    "gn:admin1_code":"17",
    "gn:asciiname":"Karangasem",
    "gn:country_code":"ID",
    "gn:dem":235,
    "gn:feature_class":"P",
    "gn:feature_code":"PPL",
    "gn:name":"Karangasem",
    "gn:population":0,
    "gn:timezone":"Asia/Makassar",
    "iso:country":"ID",
    "name:ceb_x_preferred":[
        "Karangasem"
    ],
    "name:ind_x_preferred":[
        "Karangasem"
    ],
    "name:nld_x_preferred":[
        "Karangasem"
    ],
    "name:rus_x_preferred":[
        "\u041a\u0430\u0440\u0430\u043d\u0433\u0430\u0441\u0435\u043c"
    ],
    "name:swe_x_preferred":[
        "Karangasem"
    ],
    "wof:name":"Karangasem",
    "wof:placetype":"locality"
},
  "geometry": {"coordinates":[116.56610000000001,-8.5583],"type":"Point"}
}