{
  "type": "Feature",
  "properties": {
    "gn:admin1_code":"26",
    "gn:asciiname":"Afdeling Sembilan",
    "gn:country_code":"ID",
    "gn:dem":87,
    "gn:feature_class":"P",
    "gn:feature_code":"PPL",
    "gn:name":"Afdeling Sembilan",
    "gn:population":0,
    "gn:timezone":"Asia/Jakarta",
    "iso:country":"ID",
    "name:ind_x_preferred":[
        "Afdeling Sembilan"
    ],
    "name:und_x_variant":[
        "Afdeling 9"
    ],
    "wof:name":"Afdeling Sembilan",
    "wof:placetype":"locality"
},
  "geometry": {"coordinates":[99.1832,3.1803],"type":"Point"}
}