{
  "type": "Feature",
  "properties": {
    "gn:admin1_code":"18.0",
    "gn:asciiname":"Praikamalu",
    "gn:country_code":"ID",
    "gn:dem":21,
    "gn:feature_class":"P",
    "gn:feature_code":"PPL",
    "gn:name":"Praikamalu",
    "gn:population":0,
    "gn:timezone":"Asia/Makassar",
    "iso:country":"ID",
    "name:ind_x_preferred":[
        "Praikamalu"
    ],
    "wof:name":"Praikamalu",
    "wof:placetype":"locality"
},
  "geometry": {"coordinates":[120.2765,-9.6594],"type":"Point"}
}