{
  "type": "Feature",
  "properties": {
    "gn:admin1_code":"8.0",
    "gn:asciiname":"Kebonagung Kidul",
    "gn:country_code":"ID",
    "gn:dem":62,
    "gn:feature_class":"P",
    "gn:feature_code":"PPL",
    "gn:name":"Kebonagung Kidul",
    "gn:population":0,
    "gn:timezone":"Asia/Jakarta",
    "iso:country":"ID",
    "name:ind_x_preferred":[
        "Kebonagung Kidul"
    ],
    "wof:name":"Kebonagung Kidul",
    "wof:placetype":"locality"
},
  "geometry": {"coordinates":[113.20829999999999,-8.1194],"type":"Point"}
}