{
  "type": "Feature",
  "properties": {
    "gn:admin1_code":"15.0",
    "gn:asciiname":"Umbulan Wonogiri Dua",
    "gn:country_code":"ID",
    "gn:dem":62,
    "gn:feature_class":"P",
    "gn:feature_code":"PPL",
    "gn:name":"Umbulan Wonogiri Dua",
    "gn:population":0,
    "gn:timezone":"Asia/Jakarta",
    "iso:country":"ID",
    "name:ind_x_preferred":[
        "Umbulan Wonogiri Dua"
    ],
    "name:und_x_variant":[
        "Umbulan Wonogiri 2"
    ],
    "wof:name":"Umbulan Wonogiri Dua",
    "wof:placetype":"locality"
},
  "geometry": {"coordinates":[104.92147,-4.8472],"type":"Point"}
}