{
  "type": "Feature",
  "properties": {
    "gn:admin1_code":"33.0",
    "gn:asciiname":"Dungkuk",
    "gn:country_code":"ID",
    "gn:dem":345,
    "gn:feature_class":"P",
    "gn:feature_code":"PPL",
    "gn:name":"Dungkuk",
    "gn:population":0,
    "gn:timezone":"Asia/Jakarta",
    "iso:country":"ID",
    "name:ind_x_preferred":[
        "Dungkuk"
    ],
    "wof:name":"Dungkuk",
    "wof:placetype":"locality"
},
  "geometry": {"coordinates":[106.151,-6.6203],"type":"Point"}
}