{
  "type": "Feature",
  "properties": {
    "gn:admin1_code":"30.0",
    "gn:asciiname":"Ciberenuk",
    "gn:country_code":"ID",
    "gn:dem":203,
    "gn:feature_class":"P",
    "gn:feature_code":"PPL",
    "gn:name":"Ciberenuk",
    "gn:population":0,
    "gn:timezone":"Asia/Jakarta",
    "iso:country":"ID",
    "name:ind_x_preferred":[
        "Ciberenuk"
    ],
    "wof:name":"Ciberenuk",
    "wof:placetype":"locality"
},
  "geometry": {"coordinates":[106.60720000000001,-7.3051],"type":"Point"}
}