{
  "type": "Feature",
  "properties": {
    "gn:admin1_code":"30.0",
    "gn:asciiname":"Cipalembuan",
    "gn:country_code":"ID",
    "gn:dem":467,
    "gn:feature_class":"P",
    "gn:feature_code":"PPL",
    "gn:name":"Cipalembuan",
    "gn:population":0,
    "gn:timezone":"Asia/Jakarta",
    "iso:country":"ID",
    "name:ind_x_preferred":[
        "Cipalembuan"
    ],
    "name:und_x_variant":[
        "Tjipalemboean"
    ],
    "wof:name":"Cipalembuan",
    "wof:placetype":"locality"
},
  "geometry": {"coordinates":[108.0827,-7.3433],"type":"Point"}
}