{
  "type": "Feature",
  "properties": {
    "gn:admin1_code":"30",
    "gn:asciiname":"Asemuda",
    "gn:cc2":"ID",
    "gn:country_code":"ID",
    "gn:dem":18,
    "gn:feature_class":"P",
    "gn:feature_code":"PPL",
    "gn:name":"Asemuda",
    "gn:population":0,
    "gn:timezone":"Asia/Jakarta",
    "iso:country":"ID",
    "name:und_x_variant":[
        "Asemmuda",
        "Asemuda"
    ],
    "wof:name":"Asemuda",
    "wof:placetype":"locality"
},
  "geometry": {"coordinates":[106.395,-6.15806],"type":"Point"}
}