{
  "type": "Feature",
  "properties": {
    "gn:admin1_code":"18.0",
    "gn:asciiname":"Lusibua",
    "gn:country_code":"ID",
    "gn:dem":653,
    "gn:feature_class":"P",
    "gn:feature_code":"PPL",
    "gn:name":"Lusibua",
    "gn:population":0,
    "gn:timezone":"Asia/Makassar",
    "iso:country":"ID",
    "name:ind_x_preferred":[
        "Lusibua"
    ],
    "wof:name":"Lusibua",
    "wof:placetype":"locality"
},
  "geometry": {"coordinates":[123.5433,-8.506],"type":"Point"}
}