{
  "type": "Feature",
  "properties": {
    "gn:admin1_code":"7",
    "gn:asciiname":"Demangan",
    "gn:country_code":"ID",
    "gn:dem":22,
    "gn:feature_class":"P",
    "gn:feature_code":"PPL",
    "gn:name":"Demangan",
    "gn:population":0,
    "gn:timezone":"Asia/Jakarta",
    "iso:country":"ID",
    "name:ind_x_preferred":[
        "Demangan"
    ],
    "wof:name":"Demangan",
    "wof:placetype":"locality"
},
  "geometry": {"coordinates":[110.8344,-6.8097],"type":"Point"}
}