{
  "type": "Feature",
  "properties": {
    "gn:admin1_code":"30",
    "gn:asciiname":"Kepuhangga",
    "gn:country_code":"ID",
    "gn:dem":11,
    "gn:feature_class":"P",
    "gn:feature_code":"PPL",
    "gn:name":"Kepuhangga",
    "gn:population":0,
    "gn:timezone":"Asia/Jakarta",
    "iso:country":"ID",
    "name:ind_x_preferred":[
        "Kepuhangga"
    ],
    "wof:name":"Kepuhangga",
    "wof:placetype":"locality"
},
  "geometry": {"coordinates":[107.74306,-6.31833],"type":"Point"}
}