{
  "type": "Feature",
  "properties": {
    "gn:admin1_code":"26",
    "gn:asciiname":"Hutahariaranauli",
    "gn:country_code":"ID",
    "gn:dem":6,
    "gn:feature_class":"P",
    "gn:feature_code":"PPL",
    "gn:name":"Hutahariaranauli",
    "gn:population":0,
    "gn:timezone":"Asia/Jakarta",
    "iso:country":"ID",
    "name:ind_x_preferred":[
        "Hutahariaranauli"
    ],
    "wof:name":"Hutahariaranauli",
    "wof:placetype":"locality"
},
  "geometry": {"coordinates":[98.8219,1.7177],"type":"Point"}
}