{
  "type": "Feature",
  "properties": {
    "gn:admin1_code":"30",
    "gn:asciiname":"Kedongdong",
    "gn:country_code":"ID",
    "gn:dem":4,
    "gn:feature_class":"P",
    "gn:feature_code":"PPL",
    "gn:name":"Kedongdong",
    "gn:population":0,
    "gn:timezone":"Asia/Jakarta",
    "iso:country":"ID",
    "name:ind_x_preferred":[
        "Kedongdong"
    ],
    "wof:name":"Kedongdong",
    "wof:placetype":"locality"
},
  "geometry": {"coordinates":[107.11667,-6.01417],"type":"Point"}
}