{
  "type": "Feature",
  "properties": {
    "gn:admin1_code":"8.0",
    "gn:asciiname":"Gunungbutak",
    "gn:country_code":"ID",
    "gn:dem":54,
    "gn:feature_class":"P",
    "gn:feature_code":"PPL",
    "gn:name":"Gunungbutak",
    "gn:population":0,
    "gn:timezone":"Asia/Jakarta",
    "iso:country":"ID",
    "name:ind_x_preferred":[
        "Gunungbulak"
    ],
    "wof:name":"Gunungbutak",
    "wof:placetype":"locality"
},
  "geometry": {"coordinates":[113.7469,-8.4106],"type":"Point"}
}