{
  "type": "Feature",
  "properties": {
    "gn:admin1_code":"21.0",
    "gn:asciiname":"Pautu",
    "gn:country_code":"ID",
    "gn:dem":16,
    "gn:feature_class":"P",
    "gn:feature_code":"PPL",
    "gn:name":"Pautu",
    "gn:population":0,
    "gn:timezone":"Asia/Makassar",
    "iso:country":"ID",
    "name:ind_x_preferred":[
        "Pautu"
    ],
    "wof:name":"Pautu",
    "wof:placetype":"locality"
},
  "geometry": {"coordinates":[121.94889999999999,-0.4261],"type":"Point"}
}