{
  "type": "Feature",
  "properties": {
    "gn:admin1_code":"8.0",
    "gn:asciiname":"Bonditan",
    "gn:country_code":"ID",
    "gn:dem":558,
    "gn:feature_class":"P",
    "gn:feature_code":"PPL",
    "gn:name":"Bonditan",
    "gn:population":0,
    "gn:timezone":"Asia/Jakarta",
    "iso:country":"ID",
    "name:ind_x_preferred":[
        "Bonditan"
    ],
    "wof:name":"Bonditan",
    "wof:placetype":"locality"
},
  "geometry": {"coordinates":[111.8579,-7.7647],"type":"Point"}
}