{
  "type": "Feature",
  "properties": {
    "gn:admin1_code":"18",
    "gn:asciiname":"Lamba",
    "gn:country_code":"ID",
    "gn:dem":840,
    "gn:feature_class":"P",
    "gn:feature_code":"PPL",
    "gn:name":"Lamba",
    "gn:population":0,
    "gn:timezone":"Asia/Makassar",
    "iso:country":"ID",
    "name:ind_x_preferred":[
        "Lamba"
    ],
    "wof:name":"Lamba",
    "wof:placetype":"locality"
},
  "geometry": {"coordinates":[120.50190000000001,-8.5784],"type":"Point"}
}