{
  "type": "Feature",
  "properties": {
    "gn:admin1_code":"38",
    "gn:asciiname":"Bontokunyi",
    "gn:country_code":"ID",
    "gn:dem":167,
    "gn:feature_class":"P",
    "gn:feature_code":"PPL",
    "gn:name":"Bontokunyi",
    "gn:population":0,
    "gn:timezone":"Asia/Makassar",
    "iso:country":"ID",
    "name:ind_x_preferred":[
        "Bontokunyi"
    ],
    "wof:name":"Bontokunyi",
    "wof:placetype":"locality"
},
  "geometry": {"coordinates":[120.28789999999999,-5.2731],"type":"Point"}
}