{
  "type": "Feature",
  "properties": {
    "gn:admin1_code":"30",
    "gn:asciiname":"Pasirsatri",
    "gn:country_code":"ID",
    "gn:dem":674,
    "gn:feature_class":"P",
    "gn:feature_code":"PPL",
    "gn:name":"Pasirsatri",
    "gn:population":0,
    "gn:timezone":"Asia/Jakarta",
    "iso:country":"ID",
    "name:ind_x_preferred":[
        "Pasirsatri"
    ],
    "wof:name":"Pasirsatri",
    "wof:placetype":"locality"
},
  "geometry": {"coordinates":[107.05138999999998,-6.96722],"type":"Point"}
}