{
  "type": "Feature",
  "properties": {
    "gn:admin1_code":"4.0",
    "gn:asciiname":"Petojo Utara",
    "gn:country_code":"ID",
    "gn:dem":6,
    "gn:feature_class":"P",
    "gn:feature_code":"PPL",
    "gn:name":"Petojo Utara",
    "gn:population":0,
    "gn:timezone":"Asia/Jakarta",
    "iso:country":"ID",
    "name:ceb_x_preferred":[
        "Kelurahan Petojo Utara"
    ],
    "name:ind_x_preferred":[
        "Petojo Utara"
    ],
    "name:msa_x_preferred":[
        "Petojo Utara"
    ],
    "name:nld_x_preferred":[
        "Petojo Utara"
    ],
    "name:sun_x_preferred":[
        "Petojo Utara"
    ],
    "name:swe_x_preferred":[
        "Kelurahan Petojo Utara"
    ],
    "name:und_x_variant":[
        "Petodjo Utik",
        "Petodjo Sawah",
        "Petodjo",
        "Petodjo-oedik",
        "Petojo"
    ],
    "wof:lang_x_official":[
        "ind"
    ],
    "wof:lang_x_spoken":[
        "ind",
        "eng"
    ],
    "wof:name":"Petojo Utara",
    "wof:placetype":"locality"
},
  "geometry": {"coordinates":[106.8141,-6.1616],"type":"Point"}
}