{
  "type": "Feature",
  "properties": {
    "gn:admin1_code":"8",
    "gn:asciiname":"Gua",
    "gn:country_code":"ID",
    "gn:dem":83,
    "gn:feature_class":"P",
    "gn:feature_code":"PPL",
    "gn:name":"Gua",
    "gn:population":0,
    "gn:timezone":"Asia/Jakarta",
    "iso:country":"ID",
    "name:ceb_x_preferred":[
        "Gua"
    ],
    "name:ind_x_preferred":[
        "Gua"
    ],
    "name:pol_x_preferred":[
        "Gua"
    ],
    "name:scn_x_preferred":[
        "Gua"
    ],
    "name:spa_x_preferred":[
        "Gua"
    ],
    "name:swe_x_preferred":[
        "Gua"
    ],
    "wof:name":"Gua",
    "wof:placetype":"locality"
},
  "geometry": {"coordinates":[113.008,-7.1221],"type":"Point"}
}