{
  "type": "Feature",
  "properties": {
    "gn:admin1_code":"38.0",
    "gn:asciiname":"Batubatu",
    "gn:country_code":"ID",
    "gn:dem":23,
    "gn:feature_class":"P",
    "gn:feature_code":"PPL",
    "gn:name":"Batubatu",
    "gn:population":0,
    "gn:timezone":"Asia/Makassar",
    "iso:country":"ID",
    "name:ind_x_preferred":[
        "Batubatu"
    ],
    "name:und_x_variant":[
        "Batoebatoe"
    ],
    "wof:name":"Batubatu",
    "wof:placetype":"locality"
},
  "geometry": {"coordinates":[119.8914,-4.1436],"type":"Point"}
}