{
  "type": "Feature",
  "properties": {
    "gn:admin1_code":"7.0",
    "gn:asciiname":"Cingkrik",
    "gn:country_code":"ID",
    "gn:dem":145,
    "gn:feature_class":"P",
    "gn:feature_code":"PPL",
    "gn:name":"Cingkrik",
    "gn:population":0,
    "gn:timezone":"Asia/Jakarta",
    "iso:country":"ID",
    "name:ind_x_preferred":[
        "Cingkrik"
    ],
    "wof:name":"Cingkrik",
    "wof:placetype":"locality"
},
  "geometry": {"coordinates":[109.4525,-7.32528],"type":"Point"}
}