{
  "type": "Feature",
  "properties": {
    "gn:admin1_code":"15.0",
    "gn:asciiname":"Batujaya",
    "gn:country_code":"ID",
    "gn:dem":51,
    "gn:feature_class":"P",
    "gn:feature_code":"PPL",
    "gn:name":"Batujaya",
    "gn:population":0,
    "gn:timezone":"Asia/Jakarta",
    "iso:country":"ID",
    "name:ind_x_preferred":[
        "Batujaya"
    ],
    "wof:name":"Batujaya",
    "wof:placetype":"locality"
},
  "geometry": {"coordinates":[105.65434999999999,-5.41092],"type":"Point"}
}