{
  "type": "Feature",
  "properties": {
    "gn:admin1_code":"7",
    "gn:asciiname":"Lengsar",
    "gn:country_code":"ID",
    "gn:dem":943,
    "gn:feature_class":"P",
    "gn:feature_code":"PPL",
    "gn:name":"Lengsar",
    "gn:population":0,
    "gn:timezone":"Asia/Jakarta",
    "iso:country":"ID",
    "name:ind_x_preferred":[
        "Lengsar"
    ],
    "wof:name":"Lengsar",
    "wof:placetype":"locality"
},
  "geometry": {"coordinates":[109.57917,-7.22778],"type":"Point"}
}