{
  "type": "Feature",
  "properties": {
    "gn:admin1_code":"7",
    "gn:asciiname":"Bebel Lima",
    "gn:country_code":"ID",
    "gn:dem":9,
    "gn:feature_class":"P",
    "gn:feature_code":"PPL",
    "gn:name":"Bebel Lima",
    "gn:population":0,
    "gn:timezone":"Asia/Jakarta",
    "iso:country":"ID",
    "name:ind_x_preferred":[
        "Bebel Lima"
    ],
    "wof:name":"Bebel Lima",
    "wof:placetype":"locality"
},
  "geometry": {"coordinates":[109.62309999999999,-6.8803],"type":"Point"}
}