{
  "type": "Feature",
  "properties": {
    "gn:admin1_code":"18.0",
    "gn:asciiname":"Ngoraurang",
    "gn:country_code":"ID",
    "gn:dem":410,
    "gn:feature_class":"P",
    "gn:feature_code":"PPL",
    "gn:name":"Ngoraurang",
    "gn:population":0,
    "gn:timezone":"Asia/Makassar",
    "iso:country":"ID",
    "name:ind_x_preferred":[
        "Ngoraurang"
    ],
    "wof:name":"Ngoraurang",
    "wof:placetype":"locality"
},
  "geometry": {"coordinates":[119.5898,-9.5294],"type":"Point"}
}