{
  "type": "Feature",
  "properties": {
    "gn:admin1_code":"18.0",
    "gn:asciiname":"Waikacoda",
    "gn:country_code":"ID",
    "gn:dem":450,
    "gn:feature_class":"P",
    "gn:feature_code":"PPL",
    "gn:name":"Waikacoda",
    "gn:population":0,
    "gn:timezone":"Asia/Makassar",
    "iso:country":"ID",
    "name:ind_x_preferred":[
        "Waikacoda"
    ],
    "wof:name":"Waikacoda",
    "wof:placetype":"locality"
},
  "geometry": {"coordinates":[119.23009999999999,-9.5059],"type":"Point"}
}