{
  "type": "Feature",
  "properties": {
    "gn:admin1_code":"17.0",
    "gn:asciiname":"Mujur",
    "gn:country_code":"ID",
    "gn:dem":111,
    "gn:feature_class":"P",
    "gn:feature_code":"PPLA3",
    "gn:name":"Mujur",
    "gn:population":0,
    "gn:timezone":"Asia/Makassar",
    "iso:country":"ID",
    "name:ind_x_preferred":[
        "Mujur"
    ],
    "name:und_x_variant":[
        "Moedjoer",
        "Mudjur"
    ],
    "wof:name":"Mujur",
    "wof:placetype":"locality"
},
  "geometry": {"coordinates":[116.3548,-8.7617],"type":"Point"}
}