{
  "type": "Feature",
  "properties": {
    "gn:admin1_code":"30.0",
    "gn:asciiname":"Ciawang",
    "gn:country_code":"ID",
    "gn:dem":471,
    "gn:feature_class":"P",
    "gn:feature_code":"PPLA4",
    "gn:name":"Ciawang",
    "gn:population":0,
    "gn:timezone":"Asia/Jakarta",
    "iso:country":"ID",
    "name:ind_x_preferred":[
        "Ciawang"
    ],
    "name:und_x_variant":[
        "Tjiawang"
    ],
    "wof:lang_x_official":[
        "ind"
    ],
    "wof:lang_x_spoken":[
        "ind",
        "eng"
    ],
    "wof:name":"Ciawang",
    "wof:placetype":"locality"
},
  "geometry": {"coordinates":[108.1135,-7.3223],"type":"Point"}
}