{
  "type": "Feature",
  "properties": {
    "gn:admin1_code":"30.0",
    "gn:asciiname":"Jaga",
    "gn:country_code":"ID",
    "gn:dem":810,
    "gn:feature_class":"P",
    "gn:feature_code":"PPLA4",
    "gn:name":"Jaga",
    "gn:population":0,
    "gn:timezone":"Asia/Jakarta",
    "iso:country":"ID",
    "name:ind_x_preferred":[
        "Jaga"
    ],
    "name:und_x_variant":[
        "Djaga"
    ],
    "wof:name":"Jaga",
    "wof:placetype":"locality"
},
  "geometry": {"coordinates":[108.26900000000001,-7.0451],"type":"Point"}
}