{
  "type": "Feature",
  "properties": {
    "gn:admin1_code":"24",
    "gn:asciiname":"Bancahlumpur",
    "gn:country_code":"ID",
    "gn:dem":124,
    "gn:feature_class":"P",
    "gn:feature_code":"PPL",
    "gn:name":"Bancahlumpur",
    "gn:population":0,
    "gn:timezone":"Asia/Jakarta",
    "iso:country":"ID",
    "name:eng_x_preferred":[
        "Bantjahlumpur"
    ],
    "name:ind_x_preferred":[
        "Bancahlumpur"
    ],
    "wof:lang_x_official":[
        "ind"
    ],
    "wof:lang_x_spoken":[
        "ind",
        "eng"
    ],
    "wof:name":"Bancahlumpur",
    "wof:placetype":"locality"
},
  "geometry": {"coordinates":[100.62949999999999,0.1231],"type":"Point"}
}