{
  "type": "Feature",
  "properties": {
    "gn:admin1_code":"30.0",
    "gn:asciiname":"Candra",
    "gn:country_code":"ID",
    "gn:dem":251,
    "gn:feature_class":"P",
    "gn:feature_code":"PPL",
    "gn:name":"Candra",
    "gn:population":0,
    "gn:timezone":"Asia/Jakarta",
    "iso:country":"ID",
    "name:ind_x_preferred":[
        "Candra"
    ],
    "wof:name":"Candra",
    "wof:placetype":"locality"
},
  "geometry": {"coordinates":[107.90309999999999,-7.6727],"type":"Point"}
}