{
  "type": "Feature",
  "properties": {
    "gn:admin1_code":"30.0",
    "gn:asciiname":"Sindangjawa",
    "gn:country_code":"ID",
    "gn:dem":657,
    "gn:feature_class":"P",
    "gn:feature_code":"PPLA4",
    "gn:name":"Sindangjawa",
    "gn:population":0,
    "gn:timezone":"Asia/Jakarta",
    "iso:country":"ID",
    "name:ind_x_preferred":[
        "Sindangjawa"
    ],
    "name:und_x_variant":[
        "Sindangdjawa"
    ],
    "wof:name":"Sindangjawa",
    "wof:placetype":"locality"
},
  "geometry": {"coordinates":[108.45350000000001,-7.0301],"type":"Point"}
}