{
  "type": "Feature",
  "properties": {
    "gn:admin1_code":"30",
    "gn:asciiname":"Ciakar",
    "gn:cc2":"ID",
    "gn:country_code":"ID",
    "gn:dem":47,
    "gn:feature_class":"P",
    "gn:feature_code":"PPL",
    "gn:name":"Ciakar",
    "gn:population":0,
    "gn:timezone":"Asia/Jakarta",
    "iso:country":"ID",
    "name:und_x_variant":[
        "Tjiakar 3",
        "Ciakar Tiga",
        "Ciakar"
    ],
    "wof:lang_x_official":[
        "ind"
    ],
    "wof:lang_x_spoken":[
        "ind",
        "eng"
    ],
    "wof:name":"Ciakar",
    "wof:placetype":"locality"
},
  "geometry": {"coordinates":[106.60861,-6.30861],"type":"Point"}
}