{
  "type": "Feature",
  "properties": {
    "gn:admin1_code":"18.0",
    "gn:asciiname":"Taililu",
    "gn:country_code":"ID",
    "gn:dem":137,
    "gn:feature_class":"P",
    "gn:feature_code":"PPL",
    "gn:name":"Taililu",
    "gn:population":0,
    "gn:timezone":"Asia/Makassar",
    "iso:country":"ID",
    "name:ind_x_preferred":[
        "Taililu"
    ],
    "wof:name":"Taililu",
    "wof:placetype":"locality"
},
  "geometry": {"coordinates":[119.37179999999999,-9.737],"type":"Point"}
}