{
  "type": "Feature",
  "properties": {
    "gn:admin1_code":"38",
    "gn:asciiname":"Pelali",
    "gn:country_code":"ID",
    "gn:dem":892,
    "gn:feature_class":"P",
    "gn:feature_code":"PPL",
    "gn:name":"Pelali",
    "gn:population":0,
    "gn:timezone":"Asia/Makassar",
    "iso:country":"ID",
    "name:ind_x_preferred":[
        "Pelali"
    ],
    "name:und_x_variant":[
        "Pelati"
    ],
    "wof:name":"Pelali",
    "wof:placetype":"locality"
},
  "geometry": {"coordinates":[119.8522,-3.3202],"type":"Point"}
}