{
  "type": "Feature",
  "properties": {
    "gn:admin1_code":"30",
    "gn:asciiname":"Sadamalun",
    "gn:country_code":"ID",
    "gn:dem":17,
    "gn:feature_class":"P",
    "gn:feature_code":"PPL",
    "gn:name":"Sadamalun",
    "gn:population":0,
    "gn:timezone":"Asia/Jakarta",
    "iso:country":"ID",
    "name:ind_x_preferred":[
        "Sadamalun"
    ],
    "wof:name":"Sadamalun",
    "wof:placetype":"locality"
},
  "geometry": {"coordinates":[107.29472,-6.30861],"type":"Point"}
}