{
  "type": "Feature",
  "properties": {
    "gn:admin1_code":"8.0",
    "gn:asciiname":"Duluran Wetan",
    "gn:country_code":"ID",
    "gn:dem":167,
    "gn:feature_class":"P",
    "gn:feature_code":"PPL",
    "gn:name":"Duluran Wetan",
    "gn:population":0,
    "gn:timezone":"Asia/Jakarta",
    "iso:country":"ID",
    "name:ind_x_preferred":[
        "Duluran Wetan"
    ],
    "wof:name":"Duluran Wetan",
    "wof:placetype":"locality"
},
  "geometry": {"coordinates":[112.1972,-7.7841],"type":"Point"}
}