{
  "type": "Feature",
  "properties": {
    "gn:country":"ID",
    "gn:fcode":"PPL",
    "gn:pop":0,
    "iso:country":"ID",
    "name:ind_x_preferred":[
        "Sukasari"
    ],
    "qs:name":"Sukasari",
    "qs:name_adm0":"Indonesia",
    "qs:name_adm1":"Jawa Barat",
    "qs:photos_9k":1,
    "qs:photos_9r":1,
    "qs:photos_all":20,
    "qs:photos_sr":0,
    "qs:placetype":"Town",
    "qs:pop_sr":"0",
    "wd:wordcount":1319,
    "wof:lang_x_official":[
        "ind"
    ],
    "wof:lang_x_spoken":[
        "ind",
        "eng"
    ],
    "wof:name":"Sukasari",
    "wof:placetype":"locality",
    "wof:population":0
},
  "geometry": {"coordinates":[106.76972000000001,-6.85528],"type":"Point"}
}