{
  "type": "Feature",
  "properties": {
    "gn:country":"ID",
    "gn:fcode":"PPL",
    "gn:pop":29529,
    "iso:country":"ID",
    "name:ban_x_preferred":[
        "Kapanewon"
    ],
    "qs:name":"Srandakan",
    "qs:name_adm0":"Indonesia",
    "qs:name_adm1":"Daerah Istimewa Yogyakarta",
    "qs:photos_9k":1,
    "qs:photos_9r":1,
    "qs:photos_all":5,
    "qs:photos_sr":0,
    "qs:placetype":"Town",
    "qs:pop_sr":"7",
    "wd:wordcount":224,
    "wof:lang_x_official":[
        "ind"
    ],
    "wof:lang_x_spoken":[
        "ind",
        "eng"
    ],
    "wof:name":"Srandakan",
    "wof:placetype":"locality",
    "wof:population":29529
},
  "geometry": {"coordinates":[110.25055999999999,-7.93861],"type":"Point"}
}