{
  "type": "Feature",
  "properties": {
    "gn:admin1_code":"0.0",
    "gn:asciiname":"Freiwaer",
    "gn:cc2":"ID",
    "gn:country_code":"ID",
    "gn:dem":141,
    "gn:feature_class":"P",
    "gn:feature_code":"PPL",
    "gn:name":"Freiwaer",
    "gn:population":0,
    "gn:timezone":"Asia/Jayapura",
    "iso:country":"ID",
    "name:und_x_variant":[
        "Fraiwa\u00ebr",
        "Freiwater",
        "Freiwaer"
    ],
    "wof:name":"Freiwaer",
    "wof:placetype":"locality"
},
  "geometry": {"coordinates":[133.94999999999999,-3.51667],"type":"Point"}
}