{
  "type": "Feature",
  "properties": {
    "gn:country":"ID",
    "gn:fcode":"PPL",
    "gn:pop":0,
    "iso:country":"ID",
    "name:ind_x_preferred":[
        "Garum"
    ],
    "name:unk_x_variant":[
        "Garoem"
    ],
    "qs:name":"Garum",
    "qs:name_adm0":"Indonesia",
    "qs:name_adm1":"Jawa Timur",
    "qs:photos_9k":1,
    "qs:photos_9r":1,
    "qs:photos_all":1,
    "qs:photos_sr":0,
    "qs:placetype":"Town",
    "qs:pop_sr":"0",
    "wd:wordcount":1884,
    "wof:name":"Garum",
    "wof:placetype":"locality",
    "wof:population":0
},
  "geometry": {"coordinates":[112.2222,-8.0773],"type":"Point"}
}