{
  "type": "Feature",
  "properties": {
    "gn:admin1_code":"24",
    "gn:asciiname":"Pulutpulut",
    "gn:country_code":"ID",
    "gn:dem":230,
    "gn:feature_class":"P",
    "gn:feature_code":"PPL",
    "gn:name":"Pulutpulut",
    "gn:population":0,
    "gn:timezone":"Asia/Jakarta",
    "iso:country":"ID",
    "name:ind_x_preferred":[
        "Pulutpulut"
    ],
    "wof:name":"Pulutpulut",
    "wof:placetype":"locality"
},
  "geometry": {"coordinates":[100.59979,-1.18501],"type":"Point"}
}