{
  "type": "Feature",
  "properties": {
    "gn:admin1_code":"0.0",
    "gn:asciiname":"Panyungkatliang",
    "gn:cc2":"ID",
    "gn:country_code":"ID",
    "gn:dem":243,
    "gn:feature_class":"P",
    "gn:feature_code":"PPL",
    "gn:name":"Panyungkatliang",
    "gn:population":0,
    "gn:timezone":"Asia/Pontianak",
    "iso:country":"ID",
    "name:und_x_variant":[
        "Panjoengkatliang",
        "Panjungkatliang",
        "Panyungkatliang"
    ],
    "wof:name":"Panyungkatliang",
    "wof:placetype":"locality"
},
  "geometry": {"coordinates":[114.58333,-0.95],"type":"Point"}
}