{
  "type": "Feature",
  "properties": {
    "gn:admin1_code":"30.0",
    "gn:asciiname":"Cikaler",
    "gn:country_code":"ID",
    "gn:dem":471,
    "gn:feature_class":"P",
    "gn:feature_code":"PPL",
    "gn:name":"Cikaler",
    "gn:population":0,
    "gn:timezone":"Asia/Jakarta",
    "iso:country":"ID",
    "name:ind_x_preferred":[
        "Cikaler"
    ],
    "name:und_x_variant":[
        "Tjikaler",
        "Cikaler"
    ],
    "wof:lang_x_official":[
        "ind"
    ],
    "wof:lang_x_spoken":[
        "ind",
        "eng"
    ],
    "wof:name":"Cikaler",
    "wof:placetype":"locality"
},
  "geometry": {"coordinates":[106.7475,-7.1135],"type":"Point"}
}