{
  "type": "Feature",
  "properties": {
    "gn:admin1_code":"11",
    "gn:asciiname":"Maklanan",
    "gn:country_code":"ID",
    "gn:dem":8,
    "gn:feature_class":"P",
    "gn:feature_code":"PPL",
    "gn:name":"Maklanan",
    "gn:population":0,
    "gn:timezone":"Asia/Pontianak",
    "iso:country":"ID",
    "name:ind_x_preferred":[
        "Maklanan"
    ],
    "wof:name":"Maklanan",
    "wof:placetype":"locality"
},
  "geometry": {"coordinates":[108.96025,0.87155],"type":"Point"}
}