{
  "type": "Feature",
  "properties": {
    "gn:admin1_code":"38",
    "gn:asciiname":"Bure",
    "gn:country_code":"ID",
    "gn:dem":318,
    "gn:feature_class":"P",
    "gn:feature_code":"PPL",
    "gn:name":"Bure",
    "gn:population":0,
    "gn:timezone":"Asia/Makassar",
    "iso:country":"ID",
    "name:ind_x_preferred":[
        "Bure"
    ],
    "wof:name":"Bure",
    "wof:placetype":"locality"
},
  "geometry": {"coordinates":[120.0286,-2.7993],"type":"Point"}
}