{
  "type": "Feature",
  "properties": {
    "gn:admin1_code":"38",
    "gn:asciiname":"Bure",
    "gn:country_code":"ID",
    "gn:dem":318,
    "gn:feature_class":"P",
    "gn:feature_code":"PPL",
    "gn:name":"Bure",
    "gn:population":0,
    "gn:timezone":"Asia/Makassar",
    "iso:country":"ID",
    "name:als_x_preferred":[
        "Bure"
    ],
    "name:bre_x_preferred":[
        "Bure"
    ],
    "name:cat_x_preferred":[
        "Bure"
    ],
    "name:ceb_x_preferred":[
        "Bure"
    ],
    "name:ces_x_preferred":[
        "Bou\u0159e"
    ],
    "name:deu_x_preferred":[
        "Bure"
    ],
    "name:epo_x_preferred":[
        "Bure"
    ],
    "name:fra_x_preferred":[
        "Bure"
    ],
    "name:ind_x_preferred":[
        "Bure"
    ],
    "name:ita_x_preferred":[
        "Bure"
    ],
    "name:ltz_x_preferred":[
        "Bure"
    ],
    "name:nld_x_preferred":[
        "Bure"
    ],
    "name:oci_x_preferred":[
        "Bure"
    ],
    "name:pol_x_preferred":[
        "Bure"
    ],
    "name:por_x_preferred":[
        "Bure"
    ],
    "name:scn_x_preferred":[
        "Bure"
    ],
    "name:spa_x_preferred":[
        "Bure"
    ],
    "name:swe_x_preferred":[
        "Bure"
    ],
    "name:ukr_x_preferred":[
        "\u0411\u044e\u0440"
    ],
    "wof:lang_x_official":[
        "ind"
    ],
    "wof:lang_x_spoken":[
        "ind",
        "eng"
    ],
    "wof:name":"Bure",
    "wof:placetype":"locality"
},
  "geometry": {"coordinates":[120.0286,-2.7993],"type":"Point"}
}