{
  "type": "Feature",
  "properties": {
    "gn:admin1_code":"26",
    "gn:asciiname":"Kampung Bukit",
    "gn:country_code":"ID",
    "gn:dem":148,
    "gn:feature_class":"P",
    "gn:feature_code":"PPL",
    "gn:name":"Kampung Bukit",
    "gn:population":0,
    "gn:timezone":"Asia/Jakarta",
    "iso:country":"ID",
    "name:ind_x_preferred":[
        "Kampung Bukit"
    ],
    "wof:name":"Kampung Bukit",
    "wof:placetype":"locality"
},
  "geometry": {"coordinates":[99.2795,2.9548],"type":"Point"}
}