{
  "type": "Feature",
  "properties": {
    "gn:admin1_code":"32.0",
    "gn:asciiname":"Talang Najam",
    "gn:country_code":"ID",
    "gn:dem":545,
    "gn:feature_class":"P",
    "gn:feature_code":"PPL",
    "gn:name":"Talang Najam",
    "gn:population":0,
    "gn:timezone":"Asia/Jakarta",
    "iso:country":"ID",
    "name:ind_x_preferred":[
        "Talang Najam"
    ],
    "wof:name":"Talang Najam",
    "wof:placetype":"locality"
},
  "geometry": {"coordinates":[103.85877000000001,-4.75698],"type":"Point"}
}