{
  "type": "Feature",
  "properties": {
    "gn:admin1_code":"18.0",
    "gn:asciiname":"Liwunbangga",
    "gn:country_code":"ID",
    "gn:dem":39,
    "gn:feature_class":"P",
    "gn:feature_code":"PPL",
    "gn:name":"Liwunbangga",
    "gn:population":0,
    "gn:timezone":"Asia/Makassar",
    "iso:country":"ID",
    "name:ind_x_preferred":[
        "Liwunbangga"
    ],
    "wof:name":"Liwunbangga",
    "wof:placetype":"locality"
},
  "geometry": {"coordinates":[121.73952,-8.57331],"type":"Point"}
}