{
  "type": "Feature",
  "properties": {
    "gn:admin1_code":"18.0",
    "gn:asciiname":"Toesahan",
    "gn:country_code":"ID",
    "gn:dem":707,
    "gn:feature_class":"P",
    "gn:feature_code":"PPL",
    "gn:name":"Toesahan",
    "gn:population":0,
    "gn:timezone":"Asia/Makassar",
    "iso:country":"ID",
    "name:ind_x_preferred":[
        "Toesahan"
    ],
    "wof:name":"Toesahan",
    "wof:placetype":"locality"
},
  "geometry": {"coordinates":[124.51220000000001,-9.9708],"type":"Point"}
}