{
  "type": "Feature",
  "properties": {
    "gn:admin1_code":"2.0",
    "gn:asciiname":"Tamankerthanadhi",
    "gn:country_code":"ID",
    "gn:dem":19,
    "gn:feature_class":"P",
    "gn:feature_code":"PPL",
    "gn:name":"Tamankerthanadhi",
    "gn:population":0,
    "gn:timezone":"Asia/Makassar",
    "iso:country":"ID",
    "name:ind_x_preferred":[
        "Tamankerthanadhi"
    ],
    "wof:name":"Tamankerthanadhi",
    "wof:placetype":"locality"
},
  "geometry": {"coordinates":[115.1658,-8.6826],"type":"Point"}
}