{
  "type": "Feature",
  "properties": {
    "gn:admin1_code":"7.0",
    "gn:asciiname":"Sambiroto Kidul",
    "gn:country_code":"ID",
    "gn:dem":231,
    "gn:feature_class":"P",
    "gn:feature_code":"PPL",
    "gn:name":"Sambiroto Kidul",
    "gn:population":0,
    "gn:timezone":"Asia/Jakarta",
    "iso:country":"ID",
    "name:ind_x_preferred":[
        "Sambiroto Kidul"
    ],
    "wof:name":"Sambiroto Kidul",
    "wof:placetype":"locality"
},
  "geometry": {"coordinates":[110.81638999999998,-8.06528],"type":"Point"}
}