{
  "type": "Feature",
  "properties": {
    "gn:admin1_code":"26",
    "gn:asciiname":"Sialangoman Dua",
    "gn:country_code":"ID",
    "gn:dem":331,
    "gn:feature_class":"P",
    "gn:feature_code":"PPL",
    "gn:name":"Sialangoman Dua",
    "gn:population":0,
    "gn:timezone":"Asia/Jakarta",
    "iso:country":"ID",
    "name:ind_x_preferred":[
        "Sialangoman Dua"
    ],
    "name:und_x_variant":[
        "Sialangoman 2"
    ],
    "wof:lang_x_official":[
        "ind"
    ],
    "wof:lang_x_spoken":[
        "ind",
        "eng"
    ],
    "wof:name":"Sialangoman Dua",
    "wof:placetype":"locality"
},
  "geometry": {"coordinates":[99.2118,2.7809],"type":"Point"}
}