{
  "type": "Feature",
  "properties": {
    "gn:admin1_code":"15.0",
    "gn:asciiname":"Purbosembodo",
    "gn:country_code":"ID",
    "gn:dem":62,
    "gn:feature_class":"P",
    "gn:feature_code":"PPL",
    "gn:name":"Purbosembodo",
    "gn:population":0,
    "gn:timezone":"Asia/Jakarta",
    "iso:country":"ID",
    "name:ind_x_preferred":[
        "Purbosembodo"
    ],
    "name:und_x_variant":[
        "Purwosembodo"
    ],
    "wof:name":"Purbosembodo",
    "wof:placetype":"locality"
},
  "geometry": {"coordinates":[105.29679,-5.20208],"type":"Point"}
}