{
  "type": "Feature",
  "properties": {
    "gn:admin1_code":"18.0",
    "gn:asciiname":"Rinalolon",
    "gn:country_code":"ID",
    "gn:dem":112,
    "gn:feature_class":"P",
    "gn:feature_code":"PPL",
    "gn:name":"Rinalolon",
    "gn:population":0,
    "gn:timezone":"Asia/Makassar",
    "iso:country":"ID",
    "name:ind_x_preferred":[
        "Rinalolon"
    ],
    "wof:name":"Rinalolon",
    "wof:placetype":"locality"
},
  "geometry": {"coordinates":[122.90309999999999,-10.8791],"type":"Point"}
}