{
  "type": "Feature",
  "properties": {
    "gn:admin1_code":"5.0",
    "gn:asciiname":"Kemun Satu",
    "gn:country_code":"ID",
    "gn:dem":813,
    "gn:feature_class":"P",
    "gn:feature_code":"PPL",
    "gn:name":"Kemun Satu",
    "gn:population":0,
    "gn:timezone":"Asia/Jakarta",
    "iso:country":"ID",
    "name:ind_x_preferred":[
        "Kemun Satu"
    ],
    "name:und_x_variant":[
        "Kemun 1"
    ],
    "wof:lang_x_official":[
        "ind"
    ],
    "wof:lang_x_spoken":[
        "ind",
        "eng"
    ],
    "wof:name":"Kemun Satu",
    "wof:placetype":"locality"
},
  "geometry": {"coordinates":[101.4117,-2.0936],"type":"Point"}
}