{
  "type": "Feature",
  "properties": {
    "gn:admin1_code":"30.0",
    "gn:asciiname":"Nyalindung",
    "gn:country_code":"ID",
    "gn:dem":247,
    "gn:feature_class":"P",
    "gn:feature_code":"PPL",
    "gn:name":"Nyalindung",
    "gn:population":0,
    "gn:timezone":"Asia/Jakarta",
    "iso:country":"ID",
    "name:ind_x_preferred":[
        "Nyalindung"
    ],
    "wof:name":"Nyalindung",
    "wof:placetype":"locality"
},
  "geometry": {"coordinates":[108.4098,-7.2555],"type":"Point"}
}