{
  "type": "Feature",
  "properties": {
    "gn:admin1_code":"17.0",
    "gn:asciiname":"Dasantengak",
    "gn:country_code":"ID",
    "gn:dem":203,
    "gn:feature_class":"P",
    "gn:feature_code":"PPL",
    "gn:name":"Dasantengak",
    "gn:population":0,
    "gn:timezone":"Asia/Makassar",
    "iso:country":"ID",
    "name:ind_x_preferred":[
        "Dasantengak"
    ],
    "wof:name":"Dasantengak",
    "wof:placetype":"locality"
},
  "geometry": {"coordinates":[116.4576,-8.7109],"type":"Point"}
}