{
  "type": "Feature",
  "properties": {
    "gn:admin1_code":"7.0",
    "gn:asciiname":"Nglempong",
    "gn:country_code":"ID",
    "gn:dem":135,
    "gn:feature_class":"P",
    "gn:feature_code":"PPL",
    "gn:name":"Nglempong",
    "gn:population":0,
    "gn:timezone":"Asia/Jakarta",
    "iso:country":"ID",
    "wof:name":"Nglempong",
    "wof:placetype":"locality"
},
  "geometry": {"coordinates":[110.715,-7.60111],"type":"Point"}
}