{
  "type": "Feature",
  "properties": {
    "gn:admin1_code":"8.0",
    "gn:asciiname":"Plumbangan",
    "gn:country_code":"ID",
    "gn:dem":300,
    "gn:feature_class":"P",
    "gn:feature_code":"PPLA4",
    "gn:name":"Plumbangan",
    "gn:population":0,
    "gn:timezone":"Asia/Jakarta",
    "iso:country":"ID",
    "name:ind_x_preferred":[
        "Plumbangan"
    ],
    "wof:name":"Plumbangan",
    "wof:placetype":"locality"
},
  "geometry": {"coordinates":[112.3404,-8.0766],"type":"Point"}
}