{
  "type": "Feature",
  "properties": {
    "gn:admin1_code":"24",
    "gn:asciiname":"Kasai",
    "gn:country_code":"ID",
    "gn:dem":8,
    "gn:feature_class":"P",
    "gn:feature_code":"PPL",
    "gn:name":"Kasai",
    "gn:population":0,
    "gn:timezone":"Asia/Jakarta",
    "iso:country":"ID",
    "name:ara_x_preferred":[
        "\u0643\u0627\u0633\u0627\u064a"
    ],
    "name:ben_x_preferred":[
        "\u0995\u09be\u09b8\u09be\u0987"
    ],
    "name:cat_x_preferred":[
        "Kasai"
    ],
    "name:ceb_x_preferred":[
        "Kasai"
    ],
    "name:deu_x_preferred":[
        "Kasai"
    ],
    "name:epo_x_preferred":[
        "Kasai"
    ],
    "name:est_x_preferred":[
        "Kasai"
    ],
    "name:fra_x_preferred":[
        "Kasa\u00ef"
    ],
    "name:glg_x_preferred":[
        "Kasai"
    ],
    "name:hun_x_preferred":[
        "Kasai"
    ],
    "name:ind_x_preferred":[
        "Kasai"
    ],
    "name:ita_x_preferred":[
        "Kasai"
    ],
    "name:jpn_x_preferred":[
        "\u30ab\u30b5\u30a4"
    ],
    "name:kor_x_preferred":[
        "\uac00\uc0ac\uc774"
    ],
    "name:lav_x_preferred":[
        "Kasai"
    ],
    "name:nld_x_preferred":[
        "Kasa\u00ef"
    ],
    "name:nor_x_preferred":[
        "Kasai"
    ],
    "name:pol_x_preferred":[
        "Kasai"
    ],
    "name:por_x_preferred":[
        "Kasai"
    ],
    "name:ron_x_preferred":[
        "Kasai"
    ],
    "name:rus_x_preferred":[
        "\u041a\u0430\u0441\u0430\u0439"
    ],
    "name:slk_x_preferred":[
        "Kasai"
    ],
    "name:spa_x_preferred":[
        "Kasai"
    ],
    "name:swe_x_preferred":[
        "Kasai"
    ],
    "name:urd_x_preferred":[
        "\u06a9\u0627\u0633\u0627\u0626\u06cc"
    ],
    "wof:lang_x_official":[
        "ind"
    ],
    "wof:lang_x_spoken":[
        "ind",
        "eng"
    ],
    "wof:name":"Kasai",
    "wof:placetype":"locality"
},
  "geometry": {"coordinates":[100.28874,-0.77401],"type":"Point"}
}