{
  "type": "Feature",
  "properties": {
    "gn:admin1_code":"30",
    "gn:asciiname":"Ancol",
    "gn:country_code":"ID",
    "gn:dem":47,
    "gn:feature_class":"P",
    "gn:feature_code":"PPL",
    "gn:name":"Ancol",
    "gn:population":0,
    "gn:timezone":"Asia/Jakarta",
    "iso:country":"ID",
    "name:ceb_x_preferred":[
        "Kelurahan Ancol"
    ],
    "name:ind_x_preferred":[
        "Ancol"
    ],
    "name:msa_x_preferred":[
        "Ancol"
    ],
    "name:nld_x_preferred":[
        "Ancol"
    ],
    "name:sun_x_preferred":[
        "Ancol"
    ],
    "name:und_x_variant":[
        "Antjal",
        "Ancal"
    ],
    "wof:name":"Ancol",
    "wof:placetype":"locality"
},
  "geometry": {"coordinates":[106.41722,-6.30056],"type":"Point"}
}