{
  "type": "Feature",
  "properties": {
    "gn:admin1_code":"08",
    "gn:asciiname":"Jeruklegi",
    "gn:country_code":"ID",
    "gn:dem":17,
    "gn:feature_class":"P",
    "gn:feature_code":"PPL",
    "gn:name":"Jeruklegi",
    "gn:population":0,
    "gn:timezone":"Asia/Jakarta",
    "iso:country":"ID",
    "name:ind_x_preferred":[
        "Jeruklegi"
    ],
    "name:und_x_variant":[
        "Djeruklegi"
    ],
    "wof:name":"Jeruklegi",
    "wof:placetype":"locality"
},
  "geometry": {"coordinates":[112.5547,-7.402],"type":"Point"}
}