{
  "type": "Feature",
  "properties": {
    "gn:admin1_code":"38",
    "gn:asciiname":"Todala",
    "gn:country_code":"ID",
    "gn:dem":120,
    "gn:feature_class":"P",
    "gn:feature_code":"PPL",
    "gn:name":"Todala",
    "gn:population":0,
    "gn:timezone":"Asia/Makassar",
    "iso:country":"ID",
    "name:ind_x_preferred":[
        "Todala"
    ],
    "wof:name":"Todala",
    "wof:placetype":"locality"
},
  "geometry": {"coordinates":[120.49120000000001,-6.0365],"type":"Point"}
}