{
  "type": "Feature",
  "properties": {
    "gn:admin1_code":"1",
    "gn:asciiname":"Lamblang",
    "gn:country_code":"ID",
    "gn:dem":10,
    "gn:feature_class":"P",
    "gn:feature_code":"PPL",
    "gn:name":"Lamblang",
    "gn:population":0,
    "gn:timezone":"Asia/Jakarta",
    "iso:country":"ID",
    "name:ind_x_preferred":[
        "Lamblang"
    ],
    "wof:name":"Lamblang",
    "wof:placetype":"locality"
},
  "geometry": {"coordinates":[95.2731,5.5258],"type":"Point"}
}