{
  "type": "Feature",
  "properties": {
    "gn:admin1_code":"7",
    "gn:asciiname":"Morosari",
    "gn:country_code":"ID",
    "gn:dem":4,
    "gn:feature_class":"P",
    "gn:feature_code":"PPL",
    "gn:name":"Morosari",
    "gn:population":0,
    "gn:timezone":"Asia/Jakarta",
    "iso:country":"ID",
    "name:ind_x_preferred":[
        "Morosari"
    ],
    "wof:name":"Morosari",
    "wof:placetype":"locality"
},
  "geometry": {"coordinates":[110.4846,-6.9274],"type":"Point"}
}