{
  "type": "Feature",
  "properties": {
    "gn:admin1_code":"30.0",
    "gn:asciiname":"Lebaknangka",
    "gn:country_code":"ID",
    "gn:dem":710,
    "gn:feature_class":"P",
    "gn:feature_code":"PPL",
    "gn:name":"Lebaknangka",
    "gn:population":0,
    "gn:timezone":"Asia/Jakarta",
    "iso:country":"ID",
    "name:ind_x_preferred":[
        "Lebaknangka"
    ],
    "wof:name":"Lebaknangka",
    "wof:placetype":"locality"
},
  "geometry": {"coordinates":[106.4769,-6.8738],"type":"Point"}
}