{
  "type": "Feature",
  "properties": {
    "gn:admin1_code":"1",
    "gn:asciiname":"Beurawang",
    "gn:country_code":"ID",
    "gn:dem":30,
    "gn:feature_class":"P",
    "gn:feature_code":"PPL",
    "gn:name":"Beurawang",
    "gn:population":0,
    "gn:timezone":"Asia/Jakarta",
    "iso:country":"ID",
    "name:ind_x_preferred":[
        "Beurawang"
    ],
    "wof:name":"Beurawang",
    "wof:placetype":"locality"
},
  "geometry": {"coordinates":[95.8796,5.3733],"type":"Point"}
}