{
  "type": "Feature",
  "properties": {
    "gn:admin1_code":"7",
    "gn:asciiname":"Sidamulya",
    "gn:country_code":"ID",
    "gn:dem":399,
    "gn:feature_class":"P",
    "gn:feature_code":"PPL",
    "gn:name":"Sidamulya",
    "gn:population":0,
    "gn:timezone":"Asia/Jakarta",
    "iso:country":"ID",
    "name:ind_x_preferred":[
        "Sidamulya"
    ],
    "wof:name":"Sidamulya",
    "wof:placetype":"locality"
},
  "geometry": {"coordinates":[109.46639,-7.16278],"type":"Point"}
}