{
  "type": "Feature",
  "properties": {
    "gn:admin1_code":"8",
    "gn:asciiname":"Madubronto",
    "gn:country_code":"ID",
    "gn:dem":13,
    "gn:feature_class":"P",
    "gn:feature_code":"PPL",
    "gn:name":"Madubronto",
    "gn:population":0,
    "gn:timezone":"Asia/Jakarta",
    "iso:country":"ID",
    "name:ind_x_preferred":[
        "Madubronto"
    ],
    "wof:name":"Madubronto",
    "wof:placetype":"locality"
},
  "geometry": {"coordinates":[112.61360000000001,-7.3761],"type":"Point"}
}