{
  "type": "Feature",
  "properties": {
    "gn:admin1_code":"38",
    "gn:asciiname":"Bake",
    "gn:country_code":"ID",
    "gn:dem":21,
    "gn:feature_class":"P",
    "gn:feature_code":"PPL",
    "gn:name":"Bake",
    "gn:population":0,
    "gn:timezone":"Asia/Makassar",
    "iso:country":"ID",
    "name:ceb_x_preferred":[
        "Bake"
    ],
    "name:deu_x_preferred":[
        "Bake"
    ],
    "name:ind_x_preferred":[
        "Bake"
    ],
    "name:nds_x_preferred":[
        "Bake"
    ],
    "name:nld_x_preferred":[
        "Bake"
    ],
    "name:swe_x_preferred":[
        "Bake"
    ],
    "wof:lang_x_official":[
        "ind"
    ],
    "wof:lang_x_spoken":[
        "ind",
        "eng"
    ],
    "wof:name":"Bake",
    "wof:placetype":"locality"
},
  "geometry": {"coordinates":[119.9379,-4.3096],"type":"Point"}
}