{
  "type": "Feature",
  "properties": {
    "gn:admin1_code":"37",
    "gn:asciiname":"Komang",
    "gn:country_code":"ID",
    "gn:dem":17,
    "gn:feature_class":"P",
    "gn:feature_code":"PPL",
    "gn:name":"Komang",
    "gn:population":0,
    "gn:timezone":"Asia/Jakarta",
    "iso:country":"ID",
    "name:ind_x_preferred":[
        "Komang"
    ],
    "wof:name":"Komang",
    "wof:placetype":"locality"
},
  "geometry": {"coordinates":[101.81270000000001,0.4521],"type":"Point"}
}