{
  "type": "Feature",
  "properties": {
    "gn:admin1_code":"30",
    "gn:asciiname":"Kamuning",
    "gn:cc2":"ID",
    "gn:country_code":"ID",
    "gn:dem":16,
    "gn:feature_class":"P",
    "gn:feature_code":"PPL",
    "gn:name":"Kamuning",
    "gn:population":0,
    "gn:timezone":"Asia/Jakarta",
    "iso:country":"ID",
    "name:und_x_variant":[
        "Kamuning Satu",
        "Kamuning 1",
        "Kamuning"
    ],
    "wof:name":"Kamuning",
    "wof:placetype":"locality"
},
  "geometry": {"coordinates":[106.41722,-6.12722],"type":"Point"}
}