{
  "type": "Feature",
  "properties": {
    "gn:admin1_code":"26",
    "gn:asciiname":"Tobak Pandarian",
    "gn:country_code":"ID",
    "gn:dem":1013,
    "gn:feature_class":"P",
    "gn:feature_code":"PPL",
    "gn:name":"Tobak Pandarian",
    "gn:population":0,
    "gn:timezone":"Asia/Jakarta",
    "iso:country":"ID",
    "name:ind_x_preferred":[
        "Tobak Pandarian"
    ],
    "wof:name":"Tobak Pandarian",
    "wof:placetype":"locality"
},
  "geometry": {"coordinates":[98.9404,2.0445],"type":"Point"}
}