{
  "type": "Feature",
  "properties": {
    "gn:admin1_code":"2.0",
    "gn:asciiname":"Banjar Tegal",
    "gn:country_code":"ID",
    "gn:dem":46,
    "gn:feature_class":"P",
    "gn:feature_code":"PPLA4",
    "gn:name":"Banjar Tegal",
    "gn:population":0,
    "gn:timezone":"Asia/Makassar",
    "iso:country":"ID",
    "name:ind_x_preferred":[
        "Banjar Tegal"
    ],
    "wof:name":"Banjar Tegal",
    "wof:placetype":"locality"
},
  "geometry": {"coordinates":[115.0891,-8.1243],"type":"Point"}
}