{
  "type": "Feature",
  "properties": {
    "gn:admin1_code":"2",
    "gn:asciiname":"Banjar Taman Tengah",
    "gn:country_code":"ID",
    "gn:dem":404,
    "gn:feature_class":"P",
    "gn:feature_code":"PPL",
    "gn:name":"Banjar Taman Tengah",
    "gn:population":0,
    "gn:timezone":"Asia/Makassar",
    "iso:country":"ID",
    "name:ind_x_preferred":[
        "Banjar Taman Tengah"
    ],
    "wof:name":"Banjar Taman Tengah",
    "wof:placetype":"locality"
},
  "geometry": {"coordinates":[115.36790000000001,-8.4618],"type":"Point"}
}