{
  "type": "Feature",
  "properties": {
    "gn:admin1_code":"7",
    "gn:asciiname":"Bengkal",
    "gn:country_code":"ID",
    "gn:dem":5,
    "gn:feature_class":"P",
    "gn:feature_code":"PPL",
    "gn:name":"Bengkal",
    "gn:population":0,
    "gn:timezone":"Asia/Jakarta",
    "iso:country":"ID",
    "name:ind_x_preferred":[
        "Bengkal"
    ],
    "wof:name":"Bengkal",
    "wof:placetype":"locality"
},
  "geometry": {"coordinates":[110.72539999999999,-6.7981],"type":"Point"}
}