{
  "type": "Feature",
  "properties": {
    "gn:admin1_code":"21",
    "gn:asciiname":"Pantolo",
    "gn:country_code":"ID",
    "gn:dem":20,
    "gn:feature_class":"P",
    "gn:feature_code":"PPL",
    "gn:name":"Pantolo",
    "gn:population":0,
    "gn:timezone":"Asia/Makassar",
    "iso:country":"ID",
    "name:ind_x_preferred":[
        "Pantolo"
    ],
    "wof:name":"Pantolo",
    "wof:placetype":"locality"
},
  "geometry": {"coordinates":[120.09480000000001,-0.7116],"type":"Point"}
}