{
  "type": "Feature",
  "properties": {
    "gn:admin1_code":"30.0",
    "gn:asciiname":"Karedok",
    "gn:country_code":"ID",
    "gn:dem":81,
    "gn:feature_class":"P",
    "gn:feature_code":"PPL",
    "gn:name":"Karedok",
    "gn:population":0,
    "gn:timezone":"Asia/Jakarta",
    "iso:country":"ID",
    "name:epo_x_preferred":[
        "Karedok"
    ],
    "name:ind_x_preferred":[
        "Karedok"
    ],
    "name:jav_x_preferred":[
        "Kar\u00e9dhok"
    ],
    "name:sun_x_preferred":[
        "Kar\u00e9dok"
    ],
    "wof:lang_x_official":[
        "ind"
    ],
    "wof:lang_x_spoken":[
        "ind",
        "eng"
    ],
    "wof:name":"Karedok",
    "wof:placetype":"locality"
},
  "geometry": {"coordinates":[108.1075,-6.82083],"type":"Point"}
}