{
  "type": "Feature",
  "properties": {
    "gn:admin1_code":"30.0",
    "gn:asciiname":"Cigereleng",
    "gn:country_code":"ID",
    "gn:dem":346,
    "gn:feature_class":"P",
    "gn:feature_code":"PPL",
    "gn:name":"Cigereleng",
    "gn:population":0,
    "gn:timezone":"Asia/Jakarta",
    "iso:country":"ID",
    "name:ind_x_preferred":[
        "Cigereleng"
    ],
    "wof:name":"Cigereleng",
    "wof:placetype":"locality"
},
  "geometry": {"coordinates":[107.64360000000001,-7.5073],"type":"Point"}
}