{
  "type": "Feature",
  "properties": {
    "gn:admin1_code":"8",
    "gn:asciiname":"Sidodadi",
    "gn:country_code":"ID",
    "gn:dem":28,
    "gn:feature_class":"P",
    "gn:feature_code":"PPL",
    "gn:name":"Sidodadi",
    "gn:population":0,
    "gn:timezone":"Asia/Jakarta",
    "iso:country":"ID",
    "name:ind_x_preferred":[
        "Sidodadi"
    ],
    "wof:name":"Sidodadi",
    "wof:placetype":"locality"
},
  "geometry": {"coordinates":[113.4481,-8.2144],"type":"Point"}
}