{
  "type": "Feature",
  "properties": {
    "gn:admin1_code":"7.0",
    "gn:asciiname":"Melikan",
    "gn:country_code":"ID",
    "gn:dem":159,
    "gn:feature_class":"P",
    "gn:feature_code":"PPL",
    "gn:name":"Melikan",
    "gn:population":0,
    "gn:timezone":"Asia/Jakarta",
    "iso:country":"ID",
    "wof:name":"Melikan",
    "wof:placetype":"locality"
},
  "geometry": {"coordinates":[110.95083,-7.92111],"type":"Point"}
}