{
  "type": "Feature",
  "properties": {
    "gn:admin1_code":"30",
    "gn:asciiname":"Pamoyanan",
    "gn:country_code":"ID",
    "gn:dem":926,
    "gn:feature_class":"P",
    "gn:feature_code":"PPL",
    "gn:name":"Pamoyanan",
    "gn:population":0,
    "gn:timezone":"Asia/Jakarta",
    "iso:country":"ID",
    "name:ind_x_preferred":[
        "Pamoyanan"
    ],
    "name:und_x_variant":[
        "Pamojonan 1",
        "Pamoyonan Satu"
    ],
    "wof:lang_x_official":[
        "ind"
    ],
    "wof:lang_x_spoken":[
        "ind",
        "eng"
    ],
    "wof:name":"Pamoyanan",
    "wof:placetype":"locality"
},
  "geometry": {"coordinates":[107.55417,-6.84556],"type":"Point"}
}