{
  "type": "Feature",
  "properties": {
    "gn:admin1_code":"18.0",
    "gn:asciiname":"Praikapuli",
    "gn:country_code":"ID",
    "gn:dem":130,
    "gn:feature_class":"P",
    "gn:feature_code":"PPL",
    "gn:name":"Praikapuli",
    "gn:population":0,
    "gn:timezone":"Asia/Makassar",
    "iso:country":"ID",
    "name:ind_x_preferred":[
        "Praikapuli"
    ],
    "wof:name":"Praikapuli",
    "wof:placetype":"locality"
},
  "geometry": {"coordinates":[119.43859999999999,-9.7012],"type":"Point"}
}