{
  "type": "Feature",
  "properties": {
    "gn:admin1_code":"18",
    "gn:asciiname":"Toba",
    "gn:country_code":"ID",
    "gn:dem":959,
    "gn:feature_class":"P",
    "gn:feature_code":"PPL",
    "gn:name":"Toba",
    "gn:population":0,
    "gn:timezone":"Asia/Makassar",
    "iso:country":"ID",
    "name:ind_x_preferred":[
        "Toba"
    ],
    "wof:name":"Toba",
    "wof:placetype":"locality"
},
  "geometry": {"coordinates":[121.8004,-8.7967],"type":"Point"}
}