{
  "type": "Feature",
  "properties": {
    "gn:admin1_code":"8.0",
    "gn:asciiname":"Galang",
    "gn:country_code":"ID",
    "gn:dem":32,
    "gn:feature_class":"P",
    "gn:feature_code":"PPL",
    "gn:name":"Galang",
    "gn:population":0,
    "gn:timezone":"Asia/Jakarta",
    "iso:country":"ID",
    "name:ceb_x_preferred":[
        "Galang"
    ],
    "name:ind_x_preferred":[
        "Galang"
    ],
    "name:swe_x_preferred":[
        "Galang"
    ],
    "wof:lang_x_official":[
        "ind"
    ],
    "wof:lang_x_spoken":[
        "ind",
        "eng"
    ],
    "wof:name":"Galang",
    "wof:placetype":"locality"
},
  "geometry": {"coordinates":[111.32666999999999,-8.20028],"type":"Point"}
}