{
  "type": "Feature",
  "properties": {
    "gn:admin1_code":"15.0",
    "gn:asciiname":"Talang Kibang",
    "gn:country_code":"ID",
    "gn:dem":153,
    "gn:feature_class":"P",
    "gn:feature_code":"PPL",
    "gn:name":"Talang Kibang",
    "gn:population":0,
    "gn:timezone":"Asia/Jakarta",
    "iso:country":"ID",
    "name:ind_x_preferred":[
        "Talang Kibang"
    ],
    "wof:name":"Talang Kibang",
    "wof:placetype":"locality"
},
  "geometry": {"coordinates":[104.64727000000001,-4.8604],"type":"Point"}
}