{
  "type": "Feature",
  "properties": {
    "gn:admin1_code":"30",
    "gn:asciiname":"Krajan Tiga",
    "gn:country_code":"ID",
    "gn:dem":13,
    "gn:feature_class":"P",
    "gn:feature_code":"PPL",
    "gn:name":"Krajan Tiga",
    "gn:population":0,
    "gn:timezone":"Asia/Jakarta",
    "iso:country":"ID",
    "name:ind_x_preferred":[
        "Krajan Tiga"
    ],
    "name:und_x_variant":[
        "Krajan 3"
    ],
    "wof:name":"Krajan Tiga",
    "wof:placetype":"locality"
},
  "geometry": {"coordinates":[107.45139,-6.28722],"type":"Point"}
}