{
  "type": "Feature",
  "properties": {
    "gn:admin1_code":"0.0",
    "gn:asciiname":"Babo",
    "gn:country_code":"ID",
    "gn:dem":81,
    "gn:feature_class":"P",
    "gn:feature_code":"PPL",
    "gn:name":"Babo",
    "gn:population":0,
    "gn:timezone":"Asia/Jakarta",
    "iso:country":"ID",
    "name:ind_x_preferred":[
        "Babo"
    ],
    "wof:name":"Babo",
    "wof:placetype":"locality"
},
  "geometry": {"coordinates":[97.36642999999999,1.34848],"type":"Point"}
}