{
  "type": "Feature",
  "properties": {
    "gn:admin1_code":"28.0",
    "gn:asciiname":"Danar",
    "gn:country_code":"ID",
    "gn:dem":5,
    "gn:feature_class":"P",
    "gn:feature_code":"PPL",
    "gn:name":"Danar",
    "gn:population":0,
    "gn:timezone":"Asia/Jayapura",
    "iso:country":"ID",
    "name:ind_x_preferred":[
        "Danar"
    ],
    "wof:name":"Danar",
    "wof:placetype":"locality"
},
  "geometry": {"coordinates":[132.74877000000001,-5.94612],"type":"Point"}
}