{
  "type": "Feature",
  "properties": {
    "gn:admin1_code":"38",
    "gn:asciiname":"Amassangeng",
    "gn:country_code":"ID",
    "gn:dem":52,
    "gn:feature_class":"P",
    "gn:feature_code":"PPL",
    "gn:name":"Amassangeng",
    "gn:population":0,
    "gn:timezone":"Asia/Makassar",
    "iso:country":"ID",
    "name:ind_x_preferred":[
        "Amassangeng"
    ],
    "wof:name":"Amassangeng",
    "wof:placetype":"locality"
},
  "geometry": {"coordinates":[120.1178,-4.2952],"type":"Point"}
}