{
  "type": "Feature",
  "properties": {
    "gn:admin1_code":"1",
    "gn:asciiname":"Ujong Rimbacot",
    "gn:country_code":"ID",
    "gn:dem":34,
    "gn:feature_class":"P",
    "gn:feature_code":"PPL",
    "gn:name":"Ujong Rimbacot",
    "gn:population":0,
    "gn:timezone":"Asia/Jakarta",
    "iso:country":"ID",
    "name:ind_x_preferred":[
        "Ujong Rimbacot"
    ],
    "wof:name":"Ujong Rimbacot",
    "wof:placetype":"locality"
},
  "geometry": {"coordinates":[95.9776,5.2431],"type":"Point"}
}