{
  "type": "Feature",
  "properties": {
    "gn:admin1_code":"30.0",
    "gn:asciiname":"Legokwaru",
    "gn:country_code":"ID",
    "gn:dem":36,
    "gn:feature_class":"P",
    "gn:feature_code":"PPL",
    "gn:name":"Legokwaru",
    "gn:population":0,
    "gn:timezone":"Asia/Jakarta",
    "iso:country":"ID",
    "name:ind_x_preferred":[
        "Legokwaru"
    ],
    "wof:name":"Legokwaru",
    "wof:placetype":"locality"
},
  "geometry": {"coordinates":[107.0716,-7.3827],"type":"Point"}
}