{
  "type": "Feature",
  "properties": {
    "gn:admin1_code":"34.0",
    "gn:asciiname":"Hulato",
    "gn:country_code":"ID",
    "gn:dem":11,
    "gn:feature_class":"P",
    "gn:feature_code":"PPL",
    "gn:name":"Hulato",
    "gn:population":0,
    "gn:timezone":"Asia/Makassar",
    "iso:country":"ID",
    "name:ind_x_preferred":[
        "Hulato"
    ],
    "wof:name":"Hulato",
    "wof:placetype":"locality"
},
  "geometry": {"coordinates":[121.8295,0.4936],"type":"Point"}
}