{
  "type": "Feature",
  "properties": {
    "gn:admin1_code":"30",
    "gn:asciiname":"Cileuweung Dua",
    "gn:cc2":"ID",
    "gn:country_code":"ID",
    "gn:dem":800,
    "gn:feature_class":"P",
    "gn:feature_code":"PPL",
    "gn:name":"Cileuweung Dua",
    "gn:population":0,
    "gn:timezone":"Asia/Jakarta",
    "iso:country":"ID",
    "name:und_x_variant":[
        "Tjileuweung 2",
        "Cileuweung Dua"
    ],
    "wof:name":"Cileuweung Dua",
    "wof:placetype":"locality"
},
  "geometry": {"coordinates":[107.66694,-6.8825],"type":"Point"}
}