{
  "type": "Feature",
  "properties": {
    "gn:admin1_code":"0.0",
    "gn:asciiname":"Kaburuang",
    "gn:cc2":"ID",
    "gn:country_code":"ID",
    "gn:dem":50,
    "gn:feature_class":"P",
    "gn:feature_code":"PPL",
    "gn:name":"Kaburuang",
    "gn:population":0,
    "gn:timezone":"Asia/Makassar",
    "iso:country":"ID",
    "name:und_x_variant":[
        "Kaboeroeang",
        "Kampoeng Kaboeroeang",
        "Kabaroeng",
        "Kabaruang",
        "Kaburuan",
        "Kabaroeang",
        "Kaburuang"
    ],
    "wof:name":"Kaburuang",
    "wof:placetype":"locality"
},
  "geometry": {"coordinates":[126.78333000000001,3.83333],"type":"Point"}
}