{
  "type": "Feature",
  "properties": {
    "gn:admin1_code":"30",
    "gn:asciiname":"Ceger",
    "gn:country_code":"ID",
    "gn:dem":15,
    "gn:feature_class":"P",
    "gn:feature_code":"PPL",
    "gn:name":"Ceger",
    "gn:population":0,
    "gn:timezone":"Asia/Jakarta",
    "iso:country":"ID",
    "name:ind_x_preferred":[
        "Ceger"
    ],
    "name:und_x_variant":[
        "Tjeger 1",
        "Ceger Satu"
    ],
    "wof:name":"Ceger",
    "wof:placetype":"locality"
},
  "geometry": {"coordinates":[107.14667,-6.22778],"type":"Point"}
}