{
  "type": "Feature",
  "properties": {
    "gn:admin1_code":"8",
    "gn:asciiname":"Telengsari",
    "gn:country_code":"ID",
    "gn:dem":75,
    "gn:feature_class":"P",
    "gn:feature_code":"PPLA4",
    "gn:name":"Telengsari",
    "gn:population":0,
    "gn:timezone":"Asia/Jakarta",
    "iso:country":"ID",
    "name:ind_x_preferred":[
        "Telengsari"
    ],
    "wof:name":"Telengsari",
    "wof:placetype":"locality"
},
  "geometry": {"coordinates":[113.6917,-8.1814],"type":"Point"}
}