{
  "type": "Feature",
  "properties": {
    "gn:admin1_code":"30",
    "gn:asciiname":"Simbir",
    "gn:country_code":"ID",
    "gn:dem":485,
    "gn:feature_class":"P",
    "gn:feature_code":"PPL",
    "gn:name":"Simbir",
    "gn:population":0,
    "gn:timezone":"Asia/Jakarta",
    "iso:country":"ID",
    "name:ind_x_preferred":[
        "Simbir"
    ],
    "wof:name":"Simbir",
    "wof:placetype":"locality"
},
  "geometry": {"coordinates":[107.9425,-6.86972],"type":"Point"}
}