{
  "type": "Feature",
  "properties": {
    "gn:admin1_code":"30",
    "gn:asciiname":"Renged",
    "gn:cc2":"ID",
    "gn:country_code":"ID",
    "gn:dem":12,
    "gn:feature_class":"P",
    "gn:feature_code":"PPL",
    "gn:name":"Renged",
    "gn:population":0,
    "gn:timezone":"Asia/Jakarta",
    "iso:country":"ID",
    "name:und_x_variant":[
        "Renged 1",
        "Renged Satu",
        "Renged"
    ],
    "wof:name":"Renged",
    "wof:placetype":"locality"
},
  "geometry": {"coordinates":[106.38417,-6.13861],"type":"Point"}
}