{
  "type": "Feature",
  "properties": {
    "gn:admin1_code":"30",
    "gn:asciiname":"Cidaulat",
    "gn:country_code":"ID",
    "gn:dem":1380,
    "gn:feature_class":"P",
    "gn:feature_code":"PPL",
    "gn:name":"Cidaulat",
    "gn:population":0,
    "gn:timezone":"Asia/Jakarta",
    "iso:country":"ID",
    "name:ind_x_preferred":[
        "Cidaulat"
    ],
    "wof:name":"Cidaulat",
    "wof:placetype":"locality"
},
  "geometry": {"coordinates":[107.7627,-7.2153],"type":"Point"}
}