{
  "type": "Feature",
  "properties": {
    "gn:admin1_code":"1.0",
    "gn:asciiname":"Pasir Panjang",
    "gn:country_code":"ID",
    "gn:dem":69,
    "gn:feature_class":"P",
    "gn:feature_code":"PPLA3",
    "gn:name":"Pasir Panjang",
    "gn:population":0,
    "gn:timezone":"Asia/Jakarta",
    "iso:country":"ID",
    "name:ind_x_preferred":[
        "Pasir Panjang"
    ],
    "name:msa_x_preferred":[
        "Pasir Panjang"
    ],
    "name:ukr_x_preferred":[
        "\u041f\u0430\u0441\u0456\u0440-\u041f\u0430\u043d\u0434\u0436\u0430\u043d\u0433"
    ],
    "wof:name":"Pasir Panjang",
    "wof:placetype":"locality"
},
  "geometry": {"coordinates":[98.00057,2.67455],"type":"Point"}
}