{
  "type": "Feature",
  "properties": {
    "gn:admin1_code":"30.0",
    "gn:asciiname":"Ciparay",
    "gn:country_code":"ID",
    "gn:dem":790,
    "gn:feature_class":"P",
    "gn:feature_code":"PPL",
    "gn:name":"Ciparay",
    "gn:population":0,
    "gn:timezone":"Asia/Jakarta",
    "iso:country":"ID",
    "name:ind_x_preferred":[
        "Ciparay"
    ],
    "name:und_x_variant":[
        "Tjiparaj",
        "Ciparay"
    ],
    "wof:name":"Ciparay",
    "wof:placetype":"locality"
},
  "geometry": {"coordinates":[107.0985,-7.1509],"type":"Point"}
}