{
  "type": "Feature",
  "properties": {
    "gn:admin1_code":"28",
    "gn:asciiname":"Hatuwe",
    "gn:country_code":"ID",
    "gn:dem":7,
    "gn:feature_class":"P",
    "gn:feature_code":"PPL",
    "gn:name":"Hatuwe",
    "gn:population":0,
    "gn:timezone":"Asia/Jayapura",
    "iso:country":"ID",
    "name:ind_x_preferred":[
        "Hatuwe"
    ],
    "wof:name":"Hatuwe",
    "wof:placetype":"locality"
},
  "geometry": {"coordinates":[129.4956,-2.7949],"type":"Point"}
}