{
  "type": "Feature",
  "properties": {
    "gn:admin1_code":"07",
    "gn:asciiname":"Cinde",
    "gn:cc2":"ID",
    "gn:country_code":"ID",
    "gn:dem":272,
    "gn:feature_class":"P",
    "gn:feature_code":"PPL",
    "gn:name":"Cinde",
    "gn:population":0,
    "gn:timezone":"Asia/Jakarta",
    "iso:country":"ID",
    "name:und_x_variant":[
        "Tinde",
        "Tjinde",
        "Cinde"
    ],
    "wof:name":"Cinde",
    "wof:placetype":"locality"
},
  "geometry": {"coordinates":[110.70028000000001,-7.33167],"type":"Point"}
}