{
  "type": "Feature",
  "properties": {
    "gn:admin1_code":"8.0",
    "gn:asciiname":"Baraan",
    "gn:country_code":"ID",
    "gn:dem":626,
    "gn:feature_class":"P",
    "gn:feature_code":"PPL",
    "gn:name":"Baraan",
    "gn:population":0,
    "gn:timezone":"Asia/Jakarta",
    "iso:country":"ID",
    "name:ind_x_preferred":[
        "Baraan"
    ],
    "wof:name":"Baraan",
    "wof:placetype":"locality"
},
  "geometry": {"coordinates":[112.3742,-7.8041],"type":"Point"}
}