{
  "type": "Feature",
  "properties": {
    "gn:admin1_code":"1.0",
    "gn:asciiname":"Kampung Sawah",
    "gn:country_code":"ID",
    "gn:dem":1776,
    "gn:feature_class":"P",
    "gn:feature_code":"PPL",
    "gn:name":"Kampung Sawah",
    "gn:population":0,
    "gn:timezone":"Asia/Jakarta",
    "iso:country":"ID",
    "name:ind_x_preferred":[
        "Kampung Sawah"
    ],
    "wof:name":"Kampung Sawah",
    "wof:placetype":"locality"
},
  "geometry": {"coordinates":[97.39203999999999,3.44945],"type":"Point"}
}