{
  "type": "Feature",
  "properties": {
    "gn:admin1_code":"38",
    "gn:asciiname":"Barang",
    "gn:country_code":"ID",
    "gn:dem":11,
    "gn:feature_class":"P",
    "gn:feature_code":"PPL",
    "gn:name":"Barang",
    "gn:population":0,
    "gn:timezone":"Asia/Makassar",
    "iso:country":"ID",
    "name:ceb_x_preferred":[
        "Barang"
    ],
    "name:fas_x_preferred":[
        "\u0628\u0631\u0646\u06af"
    ],
    "name:ind_x_preferred":[
        "Barang"
    ],
    "name:nld_x_preferred":[
        "Barang"
    ],
    "name:swe_x_preferred":[
        "Barang"
    ],
    "wof:lang_x_official":[
        "ind"
    ],
    "wof:lang_x_spoken":[
        "ind",
        "eng"
    ],
    "wof:name":"Barang",
    "wof:placetype":"locality"
},
  "geometry": {"coordinates":[119.5954,-3.8577],"type":"Point"}
}