{
  "type": "Feature",
  "properties": {
    "gn:admin1_code":"7.0",
    "gn:asciiname":"Slungkep",
    "gn:country_code":"ID",
    "gn:dem":22,
    "gn:feature_class":"P",
    "gn:feature_code":"PPL",
    "gn:name":"Slungkep",
    "gn:population":0,
    "gn:timezone":"Asia/Jakarta",
    "iso:country":"ID",
    "name:ind_x_preferred":[
        "Slungkep"
    ],
    "name:und_x_variant":[
        "Sloengkep"
    ],
    "wof:lang_x_official":[
        "ind"
    ],
    "wof:lang_x_spoken":[
        "ind",
        "eng"
    ],
    "wof:name":"Slungkep",
    "wof:placetype":"locality"
},
  "geometry": {"coordinates":[110.9905,-6.9118],"type":"Point"}
}