{
  "type": "Feature",
  "properties": {
    "gn:admin1_code":"18.0",
    "gn:asciiname":"Wolobheto",
    "gn:country_code":"ID",
    "gn:dem":806,
    "gn:feature_class":"P",
    "gn:feature_code":"PPL",
    "gn:name":"Wolobheto",
    "gn:population":0,
    "gn:timezone":"Asia/Makassar",
    "iso:country":"ID",
    "name:ind_x_preferred":[
        "Wolobheto"
    ],
    "name:und_x_variant":[
        "Wolobeto"
    ],
    "wof:lang_x_official":[
        "ind"
    ],
    "wof:lang_x_spoken":[
        "ind",
        "eng"
    ],
    "wof:name":"Wolobheto",
    "wof:placetype":"locality"
},
  "geometry": {"coordinates":[122.0568,-8.6314],"type":"Point"}
}