{
  "type": "Feature",
  "properties": {
    "gn:admin1_code":"18",
    "gn:asciiname":"Rami",
    "gn:country_code":"ID",
    "gn:dem":507,
    "gn:feature_class":"P",
    "gn:feature_code":"PPL",
    "gn:name":"Rami",
    "gn:population":0,
    "gn:timezone":"Asia/Makassar",
    "iso:country":"ID",
    "name:ind_x_preferred":[
        "Rami"
    ],
    "wof:name":"Rami",
    "wof:placetype":"locality"
},
  "geometry": {"coordinates":[120.85420000000001,-8.5661],"type":"Point"}
}