{
  "type": "Feature",
  "properties": {
    "gn:admin1_code":"18",
    "gn:asciiname":"Rami",
    "gn:country_code":"ID",
    "gn:dem":507,
    "gn:feature_class":"P",
    "gn:feature_code":"PPL",
    "gn:name":"Rami",
    "gn:population":0,
    "gn:timezone":"Asia/Makassar",
    "iso:country":"ID",
    "name:ceb_x_preferred":[
        "Rami"
    ],
    "name:fin_x_preferred":[
        "Rami"
    ],
    "name:fra_x_preferred":[
        "Rami"
    ],
    "name:ind_x_preferred":[
        "Rami"
    ],
    "name:ita_x_preferred":[
        "Rami"
    ],
    "name:jpn_x_preferred":[
        "\u30e9\u30df\u30fc"
    ],
    "name:por_x_preferred":[
        "Rami"
    ],
    "name:rus_x_preferred":[
        "\u0420\u0430\u043c\u0438"
    ],
    "name:spa_x_preferred":[
        "Rami"
    ],
    "name:swe_x_preferred":[
        "Rami"
    ],
    "name:ukr_x_preferred":[
        "\u0420\u0430\u043c\u0456"
    ],
    "wof:name":"Rami",
    "wof:placetype":"locality"
},
  "geometry": {"coordinates":[120.85420000000001,-8.5661],"type":"Point"}
}