{
  "type": "Feature",
  "properties": {
    "gn:admin1_code":"36.0",
    "gn:asciiname":"Bilogai",
    "gn:country_code":"ID",
    "gn:dem":1624,
    "gn:feature_class":"P",
    "gn:feature_code":"PPLA3",
    "gn:name":"Bilogai",
    "gn:population":0,
    "gn:timezone":"Asia/Jayapura",
    "iso:country":"ID",
    "name:ind_x_preferred":[
        "Bilogai"
    ],
    "wof:lang_x_official":[
        "ind"
    ],
    "wof:lang_x_spoken":[
        "ind",
        "eng"
    ],
    "wof:name":"Bilogai",
    "wof:placetype":"locality"
},
  "geometry": {"coordinates":[136.66829999999999,-3.7181],"type":"Point"}
}