{
  "type": "Feature",
  "properties": {
    "gn:admin1_code":"18",
    "gn:asciiname":"Lena",
    "gn:country_code":"ID",
    "gn:dem":641,
    "gn:feature_class":"P",
    "gn:feature_code":"PPLA4",
    "gn:name":"Lena",
    "gn:population":0,
    "gn:timezone":"Asia/Makassar",
    "iso:country":"ID",
    "name:ind_x_preferred":[
        "Lena"
    ],
    "wof:name":"Lena",
    "wof:placetype":"locality"
},
  "geometry": {"coordinates":[121.301,-8.7613],"type":"Point"}
}