{
  "type": "Feature",
  "properties": {
    "gn:admin1_code":"33.0",
    "gn:asciiname":"Malangnengah",
    "gn:country_code":"ID",
    "gn:dem":143,
    "gn:feature_class":"P",
    "gn:feature_code":"PPL",
    "gn:name":"Malangnengah",
    "gn:population":0,
    "gn:timezone":"Asia/Jakarta",
    "iso:country":"ID",
    "name:ind_x_preferred":[
        "Malangnengah"
    ],
    "wof:name":"Malangnengah",
    "wof:placetype":"locality"
},
  "geometry": {"coordinates":[106.07792999999999,-6.80604],"type":"Point"}
}