{
  "type": "Feature",
  "properties": {
    "gn:admin1_code":"30.0",
    "gn:asciiname":"Cikupa",
    "gn:country_code":"ID",
    "gn:dem":977,
    "gn:feature_class":"P",
    "gn:feature_code":"PPL",
    "gn:name":"Cikupa",
    "gn:population":0,
    "gn:timezone":"Asia/Jakarta",
    "iso:country":"ID",
    "name:fas_x_preferred":[
        "\u0633\u06cc\u06a9\u0648\u067e\u0627"
    ],
    "name:fra_x_preferred":[
        "Cikupa"
    ],
    "name:ind_x_preferred":[
        "Cikupa"
    ],
    "name:jav_x_preferred":[
        "Cikupa"
    ],
    "name:mlg_x_preferred":[
        "Cikupa"
    ],
    "name:msa_x_preferred":[
        "Cikupa"
    ],
    "name:nld_x_preferred":[
        "Cikupa"
    ],
    "name:nor_x_preferred":[
        "Cikupa"
    ],
    "wof:lang_x_official":[
        "ind"
    ],
    "wof:lang_x_spoken":[
        "ind",
        "eng"
    ],
    "wof:name":"Cikupa",
    "wof:placetype":"locality"
},
  "geometry": {"coordinates":[108.1728,-7.0158],"type":"Point"}
}