{
  "type": "Feature",
  "properties": {
    "gn:admin1_code":"30",
    "gn:asciiname":"Limusnunggal Dua",
    "gn:cc2":"ID",
    "gn:country_code":"ID",
    "gn:dem":69,
    "gn:feature_class":"P",
    "gn:feature_code":"PPL",
    "gn:name":"Limusnunggal Dua",
    "gn:population":0,
    "gn:timezone":"Asia/Jakarta",
    "iso:country":"ID",
    "name:und_x_variant":[
        "Limusnunggal 2",
        "Limusnunggal Dua"
    ],
    "wof:name":"Limusnunggal Dua",
    "wof:placetype":"locality"
},
  "geometry": {"coordinates":[106.96861,-6.37639],"type":"Point"}
}