{
  "type": "Feature",
  "properties": {
    "gn:admin1_code":"30.0",
    "gn:asciiname":"Pasirtengah",
    "gn:country_code":"ID",
    "gn:dem":373,
    "gn:feature_class":"P",
    "gn:feature_code":"PPL",
    "gn:name":"Pasirtengah",
    "gn:population":0,
    "gn:timezone":"Asia/Jakarta",
    "iso:country":"ID",
    "name:ind_x_preferred":[
        "Pasirtengah"
    ],
    "wof:name":"Pasirtengah",
    "wof:placetype":"locality"
},
  "geometry": {"coordinates":[108.3454,-7.2614],"type":"Point"}
}