{
  "type": "Feature",
  "properties": {
    "gn:admin1_code":"33.0",
    "gn:asciiname":"Tanggok Barat",
    "gn:country_code":"ID",
    "gn:dem":114,
    "gn:feature_class":"P",
    "gn:feature_code":"PPL",
    "gn:name":"Tanggok Barat",
    "gn:population":0,
    "gn:timezone":"Asia/Jakarta",
    "iso:country":"ID",
    "name:ind_x_preferred":[
        "Tanggok Barat"
    ],
    "wof:name":"Tanggok Barat",
    "wof:placetype":"locality"
},
  "geometry": {"coordinates":[106.0942,-6.387],"type":"Point"}
}