{
  "type": "Feature",
  "properties": {
    "gn:admin1_code":"7.0",
    "gn:asciiname":"Jubug",
    "gn:country_code":"ID",
    "gn:dem":780,
    "gn:feature_class":"P",
    "gn:feature_code":"PPL",
    "gn:name":"Jubug",
    "gn:population":0,
    "gn:timezone":"Asia/Jakarta",
    "iso:country":"ID",
    "wof:name":"Jubug",
    "wof:placetype":"locality"
},
  "geometry": {"coordinates":[110.10611000000002,-7.2875],"type":"Point"}
}