{
  "type": "Feature",
  "properties": {
    "gn:admin1_code":"26",
    "gn:asciiname":"Pertumbukan",
    "gn:country_code":"ID",
    "gn:dem":338,
    "gn:feature_class":"P",
    "gn:feature_code":"PPL",
    "gn:name":"Pertumbukan",
    "gn:population":0,
    "gn:timezone":"Asia/Jakarta",
    "iso:country":"ID",
    "name:ind_x_preferred":[
        "Pertumbukan"
    ],
    "wof:name":"Pertumbukan",
    "wof:placetype":"locality"
},
  "geometry": {"coordinates":[98.6318,3.3275],"type":"Point"}
}