{
  "type": "Feature",
  "properties": {
    "gn:admin1_code":"26",
    "gn:asciiname":"Sitaka",
    "gn:country_code":"ID",
    "gn:dem":1062,
    "gn:feature_class":"P",
    "gn:feature_code":"PPL",
    "gn:name":"Sitaka",
    "gn:population":0,
    "gn:timezone":"Asia/Jakarta",
    "iso:country":"ID",
    "name:ind_x_preferred":[
        "Sitaka"
    ],
    "wof:name":"Sitaka",
    "wof:placetype":"locality"
},
  "geometry": {"coordinates":[98.9555,2.0028],"type":"Point"}
}