{
  "type": "Feature",
  "properties": {
    "gn:admin1_code":"7.0",
    "gn:asciiname":"Gandusari",
    "gn:country_code":"ID",
    "gn:dem":13,
    "gn:feature_class":"P",
    "gn:feature_code":"PPL",
    "gn:name":"Gandusari",
    "gn:population":0,
    "gn:timezone":"Asia/Jakarta",
    "iso:country":"ID",
    "name:ind_x_preferred":[
        "Gandusari"
    ],
    "wof:name":"Gandusari",
    "wof:placetype":"locality"
},
  "geometry": {"coordinates":[109.85083,-7.76722],"type":"Point"}
}