{
  "type": "Feature",
  "properties": {
    "gn:admin1_code":"30.0",
    "gn:asciiname":"Karangpucung",
    "gn:country_code":"ID",
    "gn:dem":58,
    "gn:feature_class":"P",
    "gn:feature_code":"PPL",
    "gn:name":"Karangpucung",
    "gn:population":0,
    "gn:timezone":"Asia/Jakarta",
    "iso:country":"ID",
    "name:ind_x_preferred":[
        "Karangpucung"
    ],
    "name:und_x_variant":[
        "Karangputjung",
        "Karangpoetjoeng",
        "Karangpucung"
    ],
    "wof:lang_x_official":[
        "ind"
    ],
    "wof:lang_x_spoken":[
        "ind",
        "eng"
    ],
    "wof:name":"Karangpucung",
    "wof:placetype":"locality"
},
  "geometry": {"coordinates":[108.4945,-7.355],"type":"Point"}
}