{
  "type": "Feature",
  "properties": {
    "gn:admin1_code":"30.0",
    "gn:asciiname":"Cipeujeuh",
    "gn:country_code":"ID",
    "gn:dem":539,
    "gn:feature_class":"P",
    "gn:feature_code":"PPL",
    "gn:name":"Cipeujeuh",
    "gn:population":0,
    "gn:timezone":"Asia/Jakarta",
    "iso:country":"ID",
    "name:ind_x_preferred":[
        "Cipeujeuh"
    ],
    "name:und_x_variant":[
        "Tjipeudjeuh 2"
    ],
    "wof:lang_x_official":[
        "ind"
    ],
    "wof:lang_x_spoken":[
        "ind",
        "eng"
    ],
    "wof:name":"Cipeujeuh",
    "wof:placetype":"locality"
},
  "geometry": {"coordinates":[108.011,-7.0505],"type":"Point"}
}