{
  "type": "Feature",
  "properties": {
    "gn:admin1_code":"30",
    "gn:asciiname":"Asem",
    "gn:country_code":"ID",
    "gn:dem":13,
    "gn:feature_class":"P",
    "gn:feature_code":"PPL",
    "gn:name":"Asem",
    "gn:population":0,
    "gn:timezone":"Asia/Jakarta",
    "iso:country":"ID",
    "wof:name":"Asem",
    "wof:placetype":"locality"
},
  "geometry": {"coordinates":[106.46278,-6.11333],"type":"Point"}
}