{
  "type": "Feature",
  "properties": {
    "gn:admin1_code":"18",
    "gn:asciiname":"Weli",
    "gn:country_code":"ID",
    "gn:dem":903,
    "gn:feature_class":"P",
    "gn:feature_code":"PPL",
    "gn:name":"Weli",
    "gn:population":0,
    "gn:timezone":"Asia/Makassar",
    "iso:country":"ID",
    "name:deu_x_preferred":[
        "Weli"
    ],
    "name:fra_x_preferred":[
        "Weli"
    ],
    "name:ind_x_preferred":[
        "Weli"
    ],
    "wof:name":"Weli",
    "wof:placetype":"locality"
},
  "geometry": {"coordinates":[120.63590000000001,-8.5589],"type":"Point"}
}