{
  "type": "Feature",
  "properties": {
    "gn:admin1_code":"30.0",
    "gn:asciiname":"Tugu",
    "gn:country_code":"ID",
    "gn:dem":353,
    "gn:feature_class":"P",
    "gn:feature_code":"PPLA4",
    "gn:name":"Tugu",
    "gn:population":0,
    "gn:timezone":"Asia/Jakarta",
    "iso:country":"ID",
    "name:ind_x_preferred":[
        "Tugu"
    ],
    "wof:name":"Tugu",
    "wof:placetype":"locality"
},
  "geometry": {"coordinates":[108.247,-7.2962],"type":"Point"}
}