{
  "type": "Feature",
  "properties": {
    "gn:admin1_code":"7.0",
    "gn:asciiname":"Cikubang",
    "gn:country_code":"ID",
    "gn:dem":196,
    "gn:feature_class":"P",
    "gn:feature_code":"PPL",
    "gn:name":"Cikubang",
    "gn:population":0,
    "gn:timezone":"Asia/Jakarta",
    "iso:country":"ID",
    "name:ind_x_preferred":[
        "Cikubang"
    ],
    "name:und_x_variant":[
        "Tjikoebang"
    ],
    "wof:name":"Cikubang",
    "wof:placetype":"locality"
},
  "geometry": {"coordinates":[108.5919,-7.2546],"type":"Point"}
}