{
  "type": "Feature",
  "properties": {
    "gn:admin1_code":"8.0",
    "gn:asciiname":"Tobalang Tiga",
    "gn:country_code":"ID",
    "gn:dem":128,
    "gn:feature_class":"P",
    "gn:feature_code":"PPL",
    "gn:name":"Tobalang Tiga",
    "gn:population":0,
    "gn:timezone":"Asia/Jakarta",
    "iso:country":"ID",
    "name:ind_x_preferred":[
        "Tobalang Tiga"
    ],
    "wof:name":"Tobalang Tiga",
    "wof:placetype":"locality"
},
  "geometry": {"coordinates":[113.55840000000001,-6.9362],"type":"Point"}
}