{
  "type": "Feature",
  "properties": {
    "gn:admin1_code":"8.0",
    "gn:asciiname":"Jaru",
    "gn:country_code":"ID",
    "gn:dem":89,
    "gn:feature_class":"P",
    "gn:feature_code":"PPL",
    "gn:name":"Jaru",
    "gn:population":0,
    "gn:timezone":"Asia/Jakarta",
    "iso:country":"ID",
    "name:bpy_x_preferred":[
        "\u099c\u09be\u09b0\u09c1"
    ],
    "name:deu_x_preferred":[
        "Jaru"
    ],
    "name:epo_x_preferred":[
        "Jaru"
    ],
    "name:eus_x_preferred":[
        "Jaru"
    ],
    "name:fra_x_preferred":[
        "Jaru"
    ],
    "name:ind_x_preferred":[
        "Jaru"
    ],
    "name:ita_x_preferred":[
        "Jaru"
    ],
    "name:kat_x_preferred":[
        "\u10df\u10d0\u10e0\u10e3"
    ],
    "name:kaz_x_preferred":[
        "\u0416\u0430\u0440\u0443"
    ],
    "name:mlg_x_preferred":[
        "Jaru"
    ],
    "name:nor_x_preferred":[
        "Jaru"
    ],
    "name:pol_x_preferred":[
        "Jaru"
    ],
    "name:por_x_preferred":[
        "Jaru"
    ],
    "name:ron_x_preferred":[
        "Jaru"
    ],
    "name:rus_x_preferred":[
        "\u0416\u0430\u0440\u0443"
    ],
    "name:urd_x_preferred":[
        "\u062c\u0691\u0648"
    ],
    "name:vol_x_preferred":[
        "Jaru"
    ],
    "name:war_x_preferred":[
        "Jaru"
    ],
    "name:zho_x_preferred":[
        "\u96c5\u9b6f"
    ],
    "wof:lang_x_official":[
        "ind"
    ],
    "wof:lang_x_spoken":[
        "ind",
        "eng"
    ],
    "wof:name":"Jaru",
    "wof:placetype":"locality"
},
  "geometry": {"coordinates":[111.953,-7.9804],"type":"Point"}
}