{
  "type": "Feature",
  "properties": {
    "gn:admin1_code":"34.0",
    "gn:asciiname":"Patali",
    "gn:country_code":"ID",
    "gn:dem":20,
    "gn:feature_class":"P",
    "gn:feature_code":"PPL",
    "gn:name":"Patali",
    "gn:population":0,
    "gn:timezone":"Asia/Makassar",
    "iso:country":"ID",
    "name:fas_x_preferred":[
        "\u067e\u0627\u062a\u0644\u06cc"
    ],
    "name:ind_x_preferred":[
        "Patali"
    ],
    "wof:name":"Patali",
    "wof:placetype":"locality"
},
  "geometry": {"coordinates":[123.0441,0.5829],"type":"Point"}
}