{
  "type": "Feature",
  "properties": {
    "gn:admin1_code":"8",
    "gn:asciiname":"Krajan Kulon",
    "gn:country_code":"ID",
    "gn:dem":45,
    "gn:feature_class":"P",
    "gn:feature_code":"PPL",
    "gn:name":"Krajan Kulon",
    "gn:population":0,
    "gn:timezone":"Asia/Jakarta",
    "iso:country":"ID",
    "name:ind_x_preferred":[
        "Krajan Kulon"
    ],
    "wof:name":"Krajan Kulon",
    "wof:placetype":"locality"
},
  "geometry": {"coordinates":[113.02030000000001,-7.7503],"type":"Point"}
}