{
  "type": "Feature",
  "properties": {
    "gn:admin1_code":"24.0",
    "gn:asciiname":"Kotatinggal",
    "gn:country_code":"ID",
    "gn:dem":710,
    "gn:feature_class":"P",
    "gn:feature_code":"PPL",
    "gn:name":"Kotatinggal",
    "gn:population":0,
    "gn:timezone":"Asia/Jakarta",
    "iso:country":"ID",
    "name:ind_x_preferred":[
        "Kotatinggal"
    ],
    "wof:name":"Kotatinggal",
    "wof:placetype":"locality"
},
  "geometry": {"coordinates":[100.71769999999999,-0.2892],"type":"Point"}
}