{
  "type": "Feature",
  "properties": {
    "gn:admin1_code":"26.0",
    "gn:asciiname":"Aekbaru",
    "gn:country_code":"ID",
    "gn:dem":390,
    "gn:feature_class":"P",
    "gn:feature_code":"PPL",
    "gn:name":"Aekbaru",
    "gn:population":0,
    "gn:timezone":"Asia/Jakarta",
    "iso:country":"ID",
    "name:ind_x_preferred":[
        "Aekbaru"
    ],
    "wof:name":"Aekbaru",
    "wof:placetype":"locality"
},
  "geometry": {"coordinates":[99.337,0.71805],"type":"Point"}
}