{
  "type": "Feature",
  "properties": {
    "gn:admin1_code":"40.0",
    "gn:asciiname":"Telukrampak",
    "gn:country_code":"ID",
    "gn:dem":5,
    "gn:feature_class":"P",
    "gn:feature_code":"PPL",
    "gn:name":"Telukrampak",
    "gn:population":0,
    "gn:timezone":"Asia/Jakarta",
    "iso:country":"ID",
    "name:und_x_variant":[
        "Teloekrampak",
        "Telukrampak",
        "Rampak"
    ],
    "wof:lang_x_official":[
        "ind"
    ],
    "wof:lang_x_spoken":[
        "ind",
        "eng"
    ],
    "wof:name":"Telukrampak",
    "wof:placetype":"locality"
},
  "geometry": {"coordinates":[103.35625,1.0084],"type":"Point"}
}