{
  "type": "Feature",
  "properties": {
    "gn:admin1_code":"30",
    "gn:asciiname":"Maja",
    "gn:country_code":"ID",
    "gn:dem":33,
    "gn:feature_class":"P",
    "gn:feature_code":"PPL",
    "gn:name":"Maja",
    "gn:population":0,
    "gn:timezone":"Asia/Jakarta",
    "iso:country":"ID",
    "name:bos_x_preferred":[
        "Maja"
    ],
    "name:ceb_x_preferred":[
        "Maja"
    ],
    "name:ces_x_preferred":[
        "Maja"
    ],
    "name:deu_x_preferred":[
        "Maja"
    ],
    "name:epo_x_preferred":[
        "Maja"
    ],
    "name:est_x_preferred":[
        "Maja"
    ],
    "name:fin_x_preferred":[
        "Maja"
    ],
    "name:fra_x_preferred":[
        "Maja"
    ],
    "name:fry_x_preferred":[
        "Maja"
    ],
    "name:hrv_x_preferred":[
        "Maja"
    ],
    "name:hun_x_preferred":[
        "Maja"
    ],
    "name:ind_x_preferred":[
        "Maja"
    ],
    "name:ita_x_preferred":[
        "Maja"
    ],
    "name:jpn_x_preferred":[
        "\u30de\u30fc\u30e4"
    ],
    "name:lit_x_preferred":[
        "Maja"
    ],
    "name:mkd_x_preferred":[
        "\u041c\u0430\u0458\u0430"
    ],
    "name:nld_x_preferred":[
        "Maja"
    ],
    "name:pol_x_preferred":[
        "Maja"
    ],
    "name:por_x_preferred":[
        "Maja"
    ],
    "name:slk_x_preferred":[
        "Maja"
    ],
    "name:slv_x_preferred":[
        "Maja"
    ],
    "name:srp_x_preferred":[
        "\u041c\u0430\u0458\u0430"
    ],
    "name:swe_x_preferred":[
        "Maja"
    ],
    "name:tur_x_preferred":[
        "Maja"
    ],
    "wof:lang_x_official":[
        "ind"
    ],
    "wof:lang_x_spoken":[
        "ind",
        "eng"
    ],
    "wof:name":"Maja",
    "wof:placetype":"locality"
},
  "geometry": {"coordinates":[106.27611,-6.23194],"type":"Point"}
}