{
  "type": "Feature",
  "properties": {
    "gn:admin1_code":"38",
    "gn:asciiname":"Tabanga",
    "gn:country_code":"ID",
    "gn:dem":39,
    "gn:feature_class":"P",
    "gn:feature_code":"PPL",
    "gn:name":"Tabanga",
    "gn:population":0,
    "gn:timezone":"Asia/Makassar",
    "iso:country":"ID",
    "name:ind_x_preferred":[
        "Tabanga"
    ],
    "wof:name":"Tabanga",
    "wof:placetype":"locality"
},
  "geometry": {"coordinates":[119.54470000000001,-5.2712],"type":"Point"}
}