{
  "type": "Feature",
  "properties": {
    "gn:admin1_code":"38.0",
    "gn:asciiname":"Karangan",
    "gn:country_code":"ID",
    "gn:dem":1113,
    "gn:feature_class":"P",
    "gn:feature_code":"PPL",
    "gn:name":"Karangan",
    "gn:population":0,
    "gn:timezone":"Asia/Makassar",
    "iso:country":"ID",
    "name:ind_x_preferred":[
        "Karangan"
    ],
    "wof:name":"Karangan",
    "wof:placetype":"locality"
},
  "geometry": {"coordinates":[120.06180000000001,-3.0142],"type":"Point"}
}