{
  "type": "Feature",
  "properties": {
    "gn:admin1_code":"30",
    "gn:asciiname":"Babakanwaru",
    "gn:country_code":"ID",
    "gn:dem":478,
    "gn:feature_class":"P",
    "gn:feature_code":"PPL",
    "gn:name":"Babakanwaru",
    "gn:population":0,
    "gn:timezone":"Asia/Jakarta",
    "iso:country":"ID",
    "name:ind_x_preferred":[
        "Babakanwaru"
    ],
    "wof:name":"Babakanwaru",
    "wof:placetype":"locality"
},
  "geometry": {"coordinates":[107.05444,-6.56417],"type":"Point"}
}