{
  "type": "Feature",
  "properties": {
    "gn:admin1_code":"8.0",
    "gn:asciiname":"Jirak",
    "gn:country_code":"ID",
    "gn:dem":204,
    "gn:feature_class":"P",
    "gn:feature_code":"PPL",
    "gn:name":"Jirak",
    "gn:population":0,
    "gn:timezone":"Asia/Jakarta",
    "iso:country":"ID",
    "name:ceb_x_preferred":[
        "Jirak"
    ],
    "name:deu_x_preferred":[
        "Jirak"
    ],
    "name:ind_x_preferred":[
        "Jirak"
    ],
    "name:swe_x_preferred":[
        "Jirak"
    ],
    "wof:lang_x_official":[
        "ind"
    ],
    "wof:lang_x_spoken":[
        "ind",
        "eng"
    ],
    "wof:name":"Jirak",
    "wof:placetype":"locality"
},
  "geometry": {"coordinates":[111.73050000000001,-8.2301],"type":"Point"}
}