{
  "type": "Feature",
  "properties": {
    "gn:admin1_code":"38",
    "gn:asciiname":"Galungberu",
    "gn:country_code":"ID",
    "gn:dem":183,
    "gn:feature_class":"P",
    "gn:feature_code":"PPL",
    "gn:name":"Galungberu",
    "gn:population":0,
    "gn:timezone":"Asia/Makassar",
    "iso:country":"ID",
    "name:ind_x_preferred":[
        "Galungberu"
    ],
    "wof:name":"Galungberu",
    "wof:placetype":"locality"
},
  "geometry": {"coordinates":[120.136,-5.2566],"type":"Point"}
}