{
  "type": "Feature",
  "properties": {
    "gn:admin1_code":"7.0",
    "gn:asciiname":"Kobar",
    "gn:country_code":"ID",
    "gn:dem":350,
    "gn:feature_class":"P",
    "gn:feature_code":"PPL",
    "gn:name":"Kobar",
    "gn:population":0,
    "gn:timezone":"Asia/Jakarta",
    "iso:country":"ID",
    "name:ara_x_preferred":[
        "\u0643\u0648\u0628\u0631"
    ],
    "name:cat_x_preferred":[
        "Kobar"
    ],
    "name:heb_x_preferred":[
        "\u05db\u05d5\u05d1\u05d0\u05e8"
    ],
    "name:nno_x_preferred":[
        "Kobar"
    ],
    "name:pol_x_preferred":[
        "Kubar"
    ],
    "wof:lang_x_official":[
        "ind"
    ],
    "wof:lang_x_spoken":[
        "ind",
        "eng"
    ],
    "wof:name":"Kobar",
    "wof:placetype":"locality"
},
  "geometry": {"coordinates":[110.12694,-7.60944],"type":"Point"}
}