{
  "type": "Feature",
  "properties": {
    "gn:admin1_code":"30.0",
    "gn:asciiname":"Cidahon Girang",
    "gn:country_code":"ID",
    "gn:dem":10,
    "gn:feature_class":"P",
    "gn:feature_code":"PPL",
    "gn:name":"Cidahon Girang",
    "gn:population":0,
    "gn:timezone":"Asia/Jakarta",
    "iso:country":"ID",
    "name:ind_x_preferred":[
        "Cidahon Girang"
    ],
    "wof:name":"Cidahon Girang",
    "wof:placetype":"locality"
},
  "geometry": {"coordinates":[106.47280000000001,-7.2135],"type":"Point"}
}