{
  "type": "Feature",
  "properties": {
    "gn:admin1_code":"7.0",
    "gn:asciiname":"Kleco",
    "gn:country_code":"ID",
    "gn:dem":365,
    "gn:feature_class":"P",
    "gn:feature_code":"PPL",
    "gn:name":"Kleco",
    "gn:population":0,
    "gn:timezone":"Asia/Jakarta",
    "iso:country":"ID",
    "wof:name":"Kleco",
    "wof:placetype":"locality"
},
  "geometry": {"coordinates":[110.59721999999999,-7.31778],"type":"Point"}
}