{
  "type": "Feature",
  "properties": {
    "gn:admin1_code":"30",
    "gn:asciiname":"Blendung",
    "gn:country_code":"ID",
    "gn:dem":4,
    "gn:feature_class":"P",
    "gn:feature_code":"PPL",
    "gn:name":"Blendung",
    "gn:population":0,
    "gn:timezone":"Asia/Jakarta",
    "iso:country":"ID",
    "name:ind_x_preferred":[
        "Blendung"
    ],
    "wof:name":"Blendung",
    "wof:placetype":"locality"
},
  "geometry": {"coordinates":[108.17,-6.33667],"type":"Point"}
}