{
  "type": "Feature",
  "properties": {
    "gn:admin1_code":"30",
    "gn:asciiname":"Cikunir",
    "gn:country_code":"ID",
    "gn:dem":676,
    "gn:feature_class":"P",
    "gn:feature_code":"PPL",
    "gn:name":"Cikunir",
    "gn:population":0,
    "gn:timezone":"Asia/Jakarta",
    "iso:country":"ID",
    "wof:name":"Cikunir",
    "wof:placetype":"locality"
},
  "geometry": {"coordinates":[106.72472,-6.77667],"type":"Point"}
}