{
  "type": "Feature",
  "properties": {
    "gn:admin1_code":"30",
    "gn:asciiname":"Karangmulya",
    "gn:country_code":"ID",
    "gn:dem":3,
    "gn:feature_class":"P",
    "gn:feature_code":"PPL",
    "gn:name":"Karangmulya",
    "gn:population":0,
    "gn:timezone":"Asia/Jakarta",
    "iso:country":"ID",
    "name:ind_x_preferred":[
        "Karangmulya"
    ],
    "wof:name":"Karangmulya",
    "wof:placetype":"locality"
},
  "geometry": {"coordinates":[108.1725,-6.39417],"type":"Point"}
}