{
  "type": "Feature",
  "properties": {
    "gn:admin1_code":"15.0",
    "gn:asciiname":"Bedeng Alang Alang",
    "gn:country_code":"ID",
    "gn:dem":124,
    "gn:feature_class":"P",
    "gn:feature_code":"PPL",
    "gn:name":"Bedeng Alang Alang",
    "gn:population":0,
    "gn:timezone":"Asia/Jakarta",
    "iso:country":"ID",
    "name:ind_x_preferred":[
        "Bedeng Alang Alang"
    ],
    "wof:name":"Bedeng Alang Alang",
    "wof:placetype":"locality"
},
  "geometry": {"coordinates":[104.54113,-4.60903],"type":"Point"}
}