{
  "type": "Feature",
  "properties": {
    "gn:admin1_code":"30",
    "gn:asciiname":"Kareo",
    "gn:country_code":"ID",
    "gn:dem":518,
    "gn:feature_class":"P",
    "gn:feature_code":"PPL",
    "gn:name":"Kareo",
    "gn:population":0,
    "gn:timezone":"Asia/Jakarta",
    "iso:country":"ID",
    "name:ind_x_preferred":[
        "Kareo"
    ],
    "wof:name":"Kareo",
    "wof:placetype":"locality"
},
  "geometry": {"coordinates":[107.12611,-6.80167],"type":"Point"}
}