{
  "type": "Feature",
  "properties": {
    "gn:admin1_code":"30",
    "gn:asciiname":"Cikentit",
    "gn:country_code":"ID",
    "gn:dem":688,
    "gn:feature_class":"P",
    "gn:feature_code":"PPL",
    "gn:name":"Cikentit",
    "gn:population":0,
    "gn:timezone":"Asia/Jakarta",
    "iso:country":"ID",
    "name:ind_x_preferred":[
        "Cikentit"
    ],
    "name:und_x_variant":[
        "Tjikentit"
    ],
    "wof:name":"Cikentit",
    "wof:placetype":"locality"
},
  "geometry": {"coordinates":[107.36083000000001,-6.88722],"type":"Point"}
}