{
  "type": "Feature",
  "properties": {
    "gn:admin1_code":"8.0",
    "gn:asciiname":"Kandangan",
    "gn:country_code":"ID",
    "gn:dem":534,
    "gn:feature_class":"P",
    "gn:feature_code":"PPL",
    "gn:name":"Kandangan",
    "gn:population":0,
    "gn:timezone":"Asia/Jakarta",
    "iso:country":"ID",
    "name:ind_x_preferred":[
        "Kandangan"
    ],
    "wof:name":"Kandangan",
    "wof:placetype":"locality"
},
  "geometry": {"coordinates":[111.83450000000001,-7.9414],"type":"Point"}
}