{
  "type": "Feature",
  "properties": {
    "gn:admin1_code":"08",
    "gn:asciiname":"Clumpit",
    "gn:country_code":"ID",
    "gn:dem":662,
    "gn:feature_class":"P",
    "gn:feature_code":"PPL",
    "gn:name":"Clumpit",
    "gn:population":0,
    "gn:timezone":"Asia/Jakarta",
    "iso:country":"ID",
    "name:ind_x_preferred":[
        "Clumpit"
    ],
    "name:und_x_variant":[
        "Gunungsari"
    ],
    "wof:lang_x_official":[
        "ind"
    ],
    "wof:lang_x_spoken":[
        "ind",
        "eng"
    ],
    "wof:name":"Clumpit",
    "wof:placetype":"locality"
},
  "geometry": {"coordinates":[112.6435,-7.8622],"type":"Point"}
}