{
  "type": "Feature",
  "properties": {
    "gn:admin1_code":"38",
    "gn:asciiname":"Lele",
    "gn:country_code":"ID",
    "gn:dem":200,
    "gn:feature_class":"P",
    "gn:feature_code":"PPL",
    "gn:name":"Lele",
    "gn:population":0,
    "gn:timezone":"Asia/Makassar",
    "iso:country":"ID",
    "name:ceb_x_preferred":[
        "Lele"
    ],
    "name:deu_x_preferred":[
        "Lele"
    ],
    "name:fra_x_preferred":[
        "Lele"
    ],
    "name:hye_x_preferred":[
        "\u053c\u0565\u056c\u0565"
    ],
    "name:ind_x_preferred":[
        "Lele"
    ],
    "name:ita_x_preferred":[
        "Lele"
    ],
    "name:nld_x_preferred":[
        "Lele"
    ],
    "name:swe_x_preferred":[
        "Lele"
    ],
    "wof:lang_x_official":[
        "ind"
    ],
    "wof:lang_x_spoken":[
        "ind",
        "eng"
    ],
    "wof:name":"Lele",
    "wof:placetype":"locality"
},
  "geometry": {"coordinates":[120.06364000000001,-5.509],"type":"Point"}
}