{
  "type": "Feature",
  "properties": {
    "gn:admin1_code":"15.0",
    "gn:asciiname":"Nabangsari",
    "gn:country_code":"ID",
    "gn:dem":108,
    "gn:feature_class":"P",
    "gn:feature_code":"PPL",
    "gn:name":"Nabangsari",
    "gn:population":0,
    "gn:timezone":"Asia/Jakarta",
    "iso:country":"ID",
    "name:ind_x_preferred":[
        "Nabangsari"
    ],
    "wof:name":"Nabangsari",
    "wof:placetype":"locality"
},
  "geometry": {"coordinates":[104.98626000000002,-5.46726],"type":"Point"}
}