{
  "type": "Feature",
  "properties": {
    "gn:admin1_code":"38.0",
    "gn:asciiname":"Kampungbaru",
    "gn:country_code":"ID",
    "gn:dem":21,
    "gn:feature_class":"P",
    "gn:feature_code":"PPL",
    "gn:name":"Kampungbaru",
    "gn:population":0,
    "gn:timezone":"Asia/Makassar",
    "iso:country":"ID",
    "name:ind_x_preferred":[
        "Kampungbaru"
    ],
    "wof:name":"Kampungbaru",
    "wof:placetype":"locality"
},
  "geometry": {"coordinates":[120.9132,-2.4746],"type":"Point"}
}