{
  "type": "Feature",
  "properties": {
    "gn:admin1_code":"10",
    "gn:asciiname":"Wonotoro",
    "gn:country_code":"ID",
    "gn:dem":199,
    "gn:feature_class":"P",
    "gn:feature_code":"PPL",
    "gn:name":"Wonotoro",
    "gn:population":0,
    "gn:timezone":"Asia/Jakarta",
    "iso:country":"ID",
    "wof:name":"Wonotoro",
    "wof:placetype":"locality"
},
  "geometry": {"coordinates":[110.69194,-7.92472],"type":"Point"}
}