{
  "type": "Feature",
  "properties": {
    "gn:admin1_code":"31",
    "gn:asciiname":"Lolah Satu",
    "gn:country_code":"ID",
    "gn:dem":318,
    "gn:feature_class":"P",
    "gn:feature_code":"PPL",
    "gn:name":"Lolah Satu",
    "gn:population":0,
    "gn:timezone":"Asia/Makassar",
    "iso:country":"ID",
    "name:ind_x_preferred":[
        "Lolah Satu"
    ],
    "wof:name":"Lolah Satu",
    "wof:placetype":"locality"
},
  "geometry": {"coordinates":[124.7259,1.351],"type":"Point"}
}