{
  "type": "Feature",
  "properties": {
    "gn:admin1_code":"38",
    "gn:asciiname":"Saruran",
    "gn:country_code":"ID",
    "gn:dem":591,
    "gn:feature_class":"P",
    "gn:feature_code":"PPL",
    "gn:name":"Saruran",
    "gn:population":0,
    "gn:timezone":"Asia/Makassar",
    "iso:country":"ID",
    "name:ceb_x_preferred":[
        "Sar\u016br\u0101n"
    ],
    "name:fas_x_preferred":[
        "\u0633\u0631\u0648\u0631\u0627\u0646"
    ],
    "name:ind_x_preferred":[
        "Saruran"
    ],
    "name:swe_x_preferred":[
        "Sar\u016br\u0101n"
    ],
    "wof:lang_x_official":[
        "ind"
    ],
    "wof:lang_x_spoken":[
        "ind",
        "eng"
    ],
    "wof:name":"Saruran",
    "wof:placetype":"locality"
},
  "geometry": {"coordinates":[119.7505,-3.2125],"type":"Point"}
}