{
  "type": "Feature",
  "properties": {
    "gn:admin1_code":"38",
    "gn:asciiname":"Abakae",
    "gn:country_code":"ID",
    "gn:dem":36,
    "gn:feature_class":"P",
    "gn:feature_code":"PPL",
    "gn:name":"Abakae",
    "gn:population":0,
    "gn:timezone":"Asia/Makassar",
    "iso:country":"ID",
    "name:ind_x_preferred":[
        "Abakae"
    ],
    "wof:name":"Abakae",
    "wof:placetype":"locality"
},
  "geometry": {"coordinates":[120.3197,-4.4517],"type":"Point"}
}