{
  "type": "Feature",
  "properties": {
    "gn:admin1_code":"8.0",
    "gn:asciiname":"Rokorok",
    "gn:country_code":"ID",
    "gn:dem":29,
    "gn:feature_class":"P",
    "gn:feature_code":"PPL",
    "gn:name":"Rokorok",
    "gn:population":0,
    "gn:timezone":"Asia/Jakarta",
    "iso:country":"ID",
    "name:ind_x_preferred":[
        "Rokorok"
    ],
    "wof:name":"Rokorok",
    "wof:placetype":"locality"
},
  "geometry": {"coordinates":[113.44499999999999,-7.1674],"type":"Point"}
}