{
  "type": "Feature",
  "properties": {
    "gn:admin1_code":"8",
    "gn:asciiname":"Gombangan",
    "gn:country_code":"ID",
    "gn:dem":645,
    "gn:feature_class":"P",
    "gn:feature_code":"PPL",
    "gn:name":"Gombangan",
    "gn:population":0,
    "gn:timezone":"Asia/Jakarta",
    "iso:country":"ID",
    "name:ind_x_preferred":[
        "Gombangan"
    ],
    "wof:name":"Gombangan",
    "wof:placetype":"locality"
},
  "geometry": {"coordinates":[111.33,-8.01222],"type":"Point"}
}