{
  "type": "Feature",
  "properties": {
    "gn:admin1_code":"33.0",
    "gn:asciiname":"Cicadas",
    "gn:country_code":"ID",
    "gn:dem":631,
    "gn:feature_class":"P",
    "gn:feature_code":"PPL",
    "gn:name":"Cicadas",
    "gn:population":0,
    "gn:timezone":"Asia/Jakarta",
    "iso:country":"ID",
    "name:und_x_variant":[
        "Tjidjangkoran",
        "Cijangkoran",
        "Cicadas"
    ],
    "wof:lang_x_official":[
        "ind"
    ],
    "wof:lang_x_spoken":[
        "ind",
        "eng"
    ],
    "wof:name":"Cicadas",
    "wof:placetype":"locality"
},
  "geometry": {"coordinates":[106.44540000000001,-6.8396],"type":"Point"}
}