{
  "type": "Feature",
  "properties": {
    "gn:admin1_code":"17",
    "gn:asciiname":"Batubelek",
    "gn:country_code":"ID",
    "gn:dem":116,
    "gn:feature_class":"P",
    "gn:feature_code":"PPL",
    "gn:name":"Batubelek",
    "gn:population":0,
    "gn:timezone":"Asia/Makassar",
    "iso:country":"ID",
    "name:ind_x_preferred":[
        "Batubelek"
    ],
    "wof:name":"Batubelek",
    "wof:placetype":"locality"
},
  "geometry": {"coordinates":[116.59610000000001,-8.5546],"type":"Point"}
}