{
  "type": "Feature",
  "properties": {
    "gn:admin1_code":"30.0",
    "gn:asciiname":"Cipeleting",
    "gn:country_code":"ID",
    "gn:dem":580,
    "gn:feature_class":"P",
    "gn:feature_code":"PPL",
    "gn:name":"Cipeleting",
    "gn:population":0,
    "gn:timezone":"Asia/Jakarta",
    "iso:country":"ID",
    "name:ind_x_preferred":[
        "Cipeleting"
    ],
    "wof:name":"Cipeleting",
    "wof:placetype":"locality"
},
  "geometry": {"coordinates":[106.6974,-7.1298],"type":"Point"}
}