{
  "type": "Feature",
  "properties": {
    "gn:admin1_code":"7.0",
    "gn:asciiname":"Tlilir",
    "gn:country_code":"ID",
    "gn:dem":1036,
    "gn:feature_class":"P",
    "gn:feature_code":"PPL",
    "gn:name":"Tlilir",
    "gn:population":0,
    "gn:timezone":"Asia/Jakarta",
    "iso:country":"ID",
    "wof:name":"Tlilir",
    "wof:placetype":"locality"
},
  "geometry": {"coordinates":[110.13139,-7.35778],"type":"Point"}
}