{
  "type": "Feature",
  "properties": {
    "gn:admin1_code":"29.0",
    "gn:asciiname":"Rumutua",
    "gn:country_code":"ID",
    "gn:dem":6,
    "gn:feature_class":"P",
    "gn:feature_code":"PPL",
    "gn:name":"Rumutua",
    "gn:population":0,
    "gn:timezone":"Asia/Jayapura",
    "iso:country":"ID",
    "name:und_x_variant":[
        "Roemtoea"
    ],
    "wof:name":"Rumutua",
    "wof:placetype":"locality"
},
  "geometry": {"coordinates":[127.38723,0.73722],"type":"Point"}
}