{
  "type": "Feature",
  "properties": {
    "gn:admin1_code":"18",
    "gn:asciiname":"Laihangar",
    "gn:country_code":"ID",
    "gn:dem":523,
    "gn:feature_class":"P",
    "gn:feature_code":"PPL",
    "gn:name":"Laihangar",
    "gn:population":0,
    "gn:timezone":"Asia/Makassar",
    "iso:country":"ID",
    "name:ind_x_preferred":[
        "Laihangar"
    ],
    "wof:name":"Laihangar",
    "wof:placetype":"locality"
},
  "geometry": {"coordinates":[120.1705,-10.0681],"type":"Point"}
}