{
  "type": "Feature",
  "properties": {
    "gn:admin1_code":"18.0",
    "gn:asciiname":"Pangkalo",
    "gn:country_code":"ID",
    "gn:dem":285,
    "gn:feature_class":"P",
    "gn:feature_code":"PPL",
    "gn:name":"Pangkalo",
    "gn:population":0,
    "gn:timezone":"Asia/Makassar",
    "iso:country":"ID",
    "name:ind_x_preferred":[
        "Pangkalo"
    ],
    "wof:name":"Pangkalo",
    "wof:placetype":"locality"
},
  "geometry": {"coordinates":[120.4902,-8.7933],"type":"Point"}
}