{
  "type": "Feature",
  "properties": {
    "gn:admin1_code":"21",
    "gn:asciiname":"Paisulamo",
    "gn:country_code":"ID",
    "gn:dem":3,
    "gn:feature_class":"P",
    "gn:feature_code":"PPL",
    "gn:name":"Paisulamo",
    "gn:population":0,
    "gn:timezone":"Asia/Makassar",
    "iso:country":"ID",
    "name:ind_x_preferred":[
        "Paisulamo"
    ],
    "name:und_x_variant":[
        "Palsulamu"
    ],
    "wof:name":"Paisulamo",
    "wof:placetype":"locality"
},
  "geometry": {"coordinates":[123.3428,-1.69],"type":"Point"}
}