{
  "type": "Feature",
  "properties": {
    "gn:admin1_code":"8.0",
    "gn:asciiname":"Serre",
    "gn:country_code":"ID",
    "gn:dem":185,
    "gn:feature_class":"P",
    "gn:feature_code":"PPL",
    "gn:name":"Serre",
    "gn:population":0,
    "gn:timezone":"Asia/Jakarta",
    "iso:country":"ID",
    "name:ind_x_preferred":[
        "Serre"
    ],
    "wof:name":"Serre",
    "wof:placetype":"locality"
},
  "geometry": {"coordinates":[113.6721,-6.9269],"type":"Point"}
}