{
  "type": "Feature",
  "properties": {
    "gn:admin1_code":"30",
    "gn:asciiname":"Babakankiara",
    "gn:country_code":"ID",
    "gn:dem":863,
    "gn:feature_class":"P",
    "gn:feature_code":"PPL",
    "gn:name":"Babakankiara",
    "gn:population":0,
    "gn:timezone":"Asia/Jakarta",
    "iso:country":"ID",
    "name:ind_x_preferred":[
        "Babakankiara"
    ],
    "wof:lang_x_official":[
        "ind"
    ],
    "wof:lang_x_spoken":[
        "ind",
        "eng"
    ],
    "wof:name":"Babakankiara",
    "wof:placetype":"locality"
},
  "geometry": {"coordinates":[107.06833,-6.70722],"type":"Point"}
}