{
  "type": "Feature",
  "properties": {
    "gn:admin1_code":"7",
    "gn:asciiname":"Rawa",
    "gn:country_code":"ID",
    "gn:dem":8,
    "gn:feature_class":"P",
    "gn:feature_code":"PPL",
    "gn:name":"Rawa",
    "gn:population":0,
    "gn:timezone":"Asia/Jakarta",
    "iso:country":"ID",
    "name:ceb_x_preferred":[
        "Rawa"
    ],
    "name:deu_x_preferred":[
        "Rawa"
    ],
    "name:fra_x_preferred":[
        "Rawa"
    ],
    "name:ind_x_preferred":[
        "Rawa"
    ],
    "name:ita_x_preferred":[
        "Rawa"
    ],
    "name:nld_x_preferred":[
        "Rawa"
    ],
    "name:pol_x_preferred":[
        "Rawa"
    ],
    "name:swe_x_preferred":[
        "Rawa"
    ],
    "name:tur_x_preferred":[
        "Rawa"
    ],
    "wof:name":"Rawa",
    "wof:placetype":"locality"
},
  "geometry": {"coordinates":[109.10550000000001,-6.8956],"type":"Point"}
}