{
  "type": "Feature",
  "properties": {
    "gn:admin1_code":"30",
    "gn:asciiname":"Telokdengklok",
    "gn:country_code":"ID",
    "gn:dem":778,
    "gn:feature_class":"P",
    "gn:feature_code":"PPL",
    "gn:name":"Telokdengklok",
    "gn:population":0,
    "gn:timezone":"Asia/Jakarta",
    "iso:country":"ID",
    "name:ind_x_preferred":[
        "Telokdengklok"
    ],
    "wof:name":"Telokdengklok",
    "wof:placetype":"locality"
},
  "geometry": {"coordinates":[107.71528000000001,-6.90389],"type":"Point"}
}