{
  "type": "Feature",
  "properties": {
    "gn:admin1_code":"18.0",
    "gn:asciiname":"Jagangara",
    "gn:country_code":"ID",
    "gn:dem":430,
    "gn:feature_class":"P",
    "gn:feature_code":"PPL",
    "gn:name":"Jagangara",
    "gn:population":0,
    "gn:timezone":"Asia/Makassar",
    "iso:country":"ID",
    "name:ind_x_preferred":[
        "Jagangara"
    ],
    "wof:name":"Jagangara",
    "wof:placetype":"locality"
},
  "geometry": {"coordinates":[119.4735,-9.6353],"type":"Point"}
}