{
  "type": "Feature",
  "properties": {
    "gn:admin1_code":"32.0",
    "gn:asciiname":"Talang Tiding Satu",
    "gn:country_code":"ID",
    "gn:dem":325,
    "gn:feature_class":"P",
    "gn:feature_code":"PPL",
    "gn:name":"Talang Tiding Satu",
    "gn:population":0,
    "gn:timezone":"Asia/Jakarta",
    "iso:country":"ID",
    "name:ind_x_preferred":[
        "Talang Tiding Satu"
    ],
    "name:und_x_variant":[
        "Talang Tiding 1"
    ],
    "wof:lang_x_official":[
        "ind"
    ],
    "wof:lang_x_spoken":[
        "ind",
        "eng"
    ],
    "wof:name":"Talang Tiding Satu",
    "wof:placetype":"locality"
},
  "geometry": {"coordinates":[104.14985,-4.66512],"type":"Point"}
}