{
  "type": "Feature",
  "properties": {
    "gn:admin1_code":"15.0",
    "gn:asciiname":"Banjaragung",
    "gn:country_code":"ID",
    "gn:dem":53,
    "gn:feature_class":"P",
    "gn:feature_code":"PPL",
    "gn:name":"Banjaragung",
    "gn:population":0,
    "gn:timezone":"Asia/Jakarta",
    "iso:country":"ID",
    "name:ind_x_preferred":[
        "Banjaragung"
    ],
    "wof:name":"Banjaragung",
    "wof:placetype":"locality"
},
  "geometry": {"coordinates":[105.54342,-5.27173],"type":"Point"}
}