{
  "type": "Feature",
  "properties": {
    "gn:admin1_code":"12.0",
    "gn:asciiname":"Kupangrunding",
    "gn:country_code":"ID",
    "gn:dem":49,
    "gn:feature_class":"P",
    "gn:feature_code":"PPL",
    "gn:name":"Kupangrunding",
    "gn:population":0,
    "gn:timezone":"Asia/Makassar",
    "iso:country":"ID",
    "name:ind_x_preferred":[
        "Kupangrunding"
    ],
    "name:und_x_variant":[
        "Koepangnoending",
        "Kupangnunding"
    ],
    "wof:name":"Kupangrunding",
    "wof:placetype":"locality"
},
  "geometry": {"coordinates":[115.5689,-1.9563],"type":"Point"}
}