{
  "type": "Feature",
  "properties": {
    "gn:admin1_code":"08",
    "gn:asciiname":"Trajeng Satu",
    "gn:cc2":"ID",
    "gn:country_code":"ID",
    "gn:dem":556,
    "gn:feature_class":"P",
    "gn:feature_code":"PPL",
    "gn:name":"Trajeng Satu",
    "gn:population":0,
    "gn:timezone":"Asia/Jakarta",
    "iso:country":"ID",
    "name:und_x_variant":[
        "Tradjeng 1",
        "Trajeng Satu"
    ],
    "wof:name":"Trajeng Satu",
    "wof:placetype":"locality"
},
  "geometry": {"coordinates":[112.73111000000002,-7.92167],"type":"Point"}
}