{
  "type": "Feature",
  "properties": {
    "gn:admin1_code":"8.0",
    "gn:asciiname":"Tanaden",
    "gn:country_code":"ID",
    "gn:dem":156,
    "gn:feature_class":"P",
    "gn:feature_code":"PPL",
    "gn:name":"Tanaden",
    "gn:population":0,
    "gn:timezone":"Asia/Jakarta",
    "iso:country":"ID",
    "name:ind_x_preferred":[
        "Tanaden"
    ],
    "wof:name":"Tanaden",
    "wof:placetype":"locality"
},
  "geometry": {"coordinates":[113.4243,-6.9935],"type":"Point"}
}