{
  "type": "Feature",
  "properties": {
    "gn:admin1_code":"18.0",
    "gn:asciiname":"Bansone",
    "gn:country_code":"ID",
    "gn:dem":1096,
    "gn:feature_class":"P",
    "gn:feature_code":"PPL",
    "gn:name":"Bansone",
    "gn:population":0,
    "gn:timezone":"Asia/Makassar",
    "iso:country":"ID",
    "name:ind_x_preferred":[
        "Bansone"
    ],
    "wof:name":"Bansone",
    "wof:placetype":"locality"
},
  "geometry": {"coordinates":[124.2882,-9.5778],"type":"Point"}
}