{
  "type": "Feature",
  "properties": {
    "gn:admin1_code":"30.0",
    "gn:asciiname":"Pasirkerud",
    "gn:country_code":"ID",
    "gn:dem":961,
    "gn:feature_class":"P",
    "gn:feature_code":"PPL",
    "gn:name":"Pasirkerud",
    "gn:population":0,
    "gn:timezone":"Asia/Jakarta",
    "iso:country":"ID",
    "name:ind_x_preferred":[
        "Pasirkerud"
    ],
    "wof:name":"Pasirkerud",
    "wof:placetype":"locality"
},
  "geometry": {"coordinates":[107.8749,-7.4099],"type":"Point"}
}