{
  "type": "Feature",
  "properties": {
    "gn:admin1_code":"18.0",
    "gn:asciiname":"Nekatuka",
    "gn:country_code":"ID",
    "gn:dem":246,
    "gn:feature_class":"P",
    "gn:feature_code":"PPL",
    "gn:name":"Nekatuka",
    "gn:population":0,
    "gn:timezone":"Asia/Makassar",
    "iso:country":"ID",
    "name:ind_x_preferred":[
        "Nekatuka"
    ],
    "wof:name":"Nekatuka",
    "wof:placetype":"locality"
},
  "geometry": {"coordinates":[123.7025,-10.2041],"type":"Point"}
}