{
  "type": "Feature",
  "properties": {
    "gn:admin1_code":"0.0",
    "gn:asciiname":"Lewobunga",
    "gn:cc2":"ID",
    "gn:country_code":"ID",
    "gn:dem":152,
    "gn:feature_class":"P",
    "gn:feature_code":"PPL",
    "gn:name":"Lewobunga",
    "gn:population":0,
    "gn:timezone":"Asia/Makassar",
    "iso:country":"ID",
    "name:und_x_variant":[
        "Lewoboenga",
        "Lewobunga"
    ],
    "wof:name":"Lewobunga",
    "wof:placetype":"locality"
},
  "geometry": {"coordinates":[122.96666999999999,-8.16667],"type":"Point"}
}