{
  "type": "Feature",
  "properties": {
    "gn:admin1_code":"07",
    "gn:asciiname":"Jlegong Lor",
    "gn:country_code":"ID",
    "gn:dem":534,
    "gn:feature_class":"P",
    "gn:feature_code":"PPL",
    "gn:name":"Jlegong Lor",
    "gn:population":0,
    "gn:timezone":"Asia/Jakarta",
    "iso:country":"ID",
    "name:und_x_variant":[
        "Dilegong",
        "Jlegong Lor"
    ],
    "wof:name":"Jlegong Lor",
    "wof:placetype":"locality"
},
  "geometry": {"coordinates":[110.295,-7.40056],"type":"Point"}
}