{
  "type": "Feature",
  "properties": {
    "gn:admin1_code":"8.0",
    "gn:asciiname":"Karanganyarkrajan",
    "gn:country_code":"ID",
    "gn:dem":305,
    "gn:feature_class":"P",
    "gn:feature_code":"PPL",
    "gn:name":"Karanganyarkrajan",
    "gn:population":0,
    "gn:timezone":"Asia/Jakarta",
    "iso:country":"ID",
    "name:ind_x_preferred":[
        "Karanganyarkrajan"
    ],
    "wof:name":"Karanganyarkrajan",
    "wof:placetype":"locality"
},
  "geometry": {"coordinates":[113.1341,-8.0904],"type":"Point"}
}