{
  "type": "Feature",
  "properties": {
    "gn:admin1_code":"32.0",
    "gn:asciiname":"Umbulan Radenlanang",
    "gn:country_code":"ID",
    "gn:dem":49,
    "gn:feature_class":"P",
    "gn:feature_code":"PPL",
    "gn:name":"Umbulan Radenlanang",
    "gn:population":0,
    "gn:timezone":"Asia/Jakarta",
    "iso:country":"ID",
    "name:ind_x_preferred":[
        "Umbulan Radenlanang"
    ],
    "name:und_x_variant":[
        "Umbulanradenlanang"
    ],
    "wof:name":"Umbulan Radenlanang",
    "wof:placetype":"locality"
},
  "geometry": {"coordinates":[104.80092,-4.25066],"type":"Point"}
}