{
  "type": "Feature",
  "properties": {
    "gn:admin1_code":"30",
    "gn:asciiname":"Genteng Dua",
    "gn:cc2":"ID",
    "gn:country_code":"ID",
    "gn:dem":638,
    "gn:feature_class":"P",
    "gn:feature_code":"PPL",
    "gn:name":"Genteng Dua",
    "gn:population":0,
    "gn:timezone":"Asia/Jakarta",
    "iso:country":"ID",
    "name:und_x_variant":[
        "Genteng 2",
        "Genteng Dua"
    ],
    "wof:name":"Genteng Dua",
    "wof:placetype":"locality"
},
  "geometry": {"coordinates":[107.435,-6.93389],"type":"Point"}
}