{
  "type": "Feature",
  "properties": {
    "gn:admin1_code":"24.0",
    "gn:asciiname":"Alahanpanjang",
    "gn:country_code":"ID",
    "gn:dem":1414,
    "gn:feature_class":"P",
    "gn:feature_code":"PPLA3",
    "gn:name":"Alahanpanjang",
    "gn:population":0,
    "gn:timezone":"Asia/Jakarta",
    "iso:country":"ID",
    "name:fas_x_preferred":[
        "\u0627\u0644\u0627\u0647\u0627\u0646 \u067e\u0646\u062c\u0627\u0646\u06af"
    ],
    "name:ind_x_preferred":[
        "Alahanpanjang"
    ],
    "name:ind_x_variant":[
        "Alahan Panjang"
    ],
    "name:min_x_preferred":[
        "Alahan Panjang"
    ],
    "name:und_x_variant":[
        "Alahanpandjang",
        "Alahanpandgan"
    ],
    "wof:lang_x_official":[
        "ind"
    ],
    "wof:lang_x_spoken":[
        "ind",
        "eng"
    ],
    "wof:name":"Alahanpanjang",
    "wof:placetype":"locality"
},
  "geometry": {"coordinates":[100.79353999999999,-1.07491],"type":"Point"}
}