{
  "type": "Feature",
  "properties": {
    "gn:admin1_code":"30",
    "gn:asciiname":"Ngawen",
    "gn:country_code":"ID",
    "gn:dem":640,
    "gn:feature_class":"P",
    "gn:feature_code":"PPL",
    "gn:name":"Ngawen",
    "gn:population":0,
    "gn:timezone":"Asia/Jakarta",
    "iso:country":"ID",
    "name:ind_x_preferred":[
        "Ngawen"
    ],
    "name:ind_x_variant":[
        "Candi Ngawen"
    ],
    "name:jav_x_preferred":[
        "Candhi Ngaw\u00e8n"
    ],
    "wof:name":"Ngawen",
    "wof:placetype":"locality"
},
  "geometry": {"coordinates":[106.95222,-6.92111],"type":"Point"}
}