{
  "type": "Feature",
  "properties": {
    "gn:admin1_code":"38",
    "gn:asciiname":"Tombolo",
    "gn:country_code":"ID",
    "gn:dem":81,
    "gn:feature_class":"P",
    "gn:feature_code":"PPL",
    "gn:name":"Tombolo",
    "gn:population":0,
    "gn:timezone":"Asia/Makassar",
    "iso:country":"ID",
    "name:ind_x_preferred":[
        "Tombolo"
    ],
    "wof:name":"Tombolo",
    "wof:placetype":"locality"
},
  "geometry": {"coordinates":[119.7022,-5.1269],"type":"Point"}
}