{
  "type": "Feature",
  "properties": {
    "gn:admin1_code":"38",
    "gn:asciiname":"Tombolo",
    "gn:country_code":"ID",
    "gn:dem":81,
    "gn:feature_class":"P",
    "gn:feature_code":"PPL",
    "gn:name":"Tombolo",
    "gn:population":0,
    "gn:timezone":"Asia/Makassar",
    "iso:country":"ID",
    "name:ara_x_preferred":[
        "\u062a\u0648\u0645\u0628\u0644\u0648"
    ],
    "name:aze_x_preferred":[
        "Tombolo"
    ],
    "name:cat_x_preferred":[
        "T\u00f3mbol"
    ],
    "name:ces_x_preferred":[
        "Tombolo"
    ],
    "name:deu_x_preferred":[
        "Tombolo"
    ],
    "name:est_x_preferred":[
        "Tombolo"
    ],
    "name:eus_x_preferred":[
        "Tonbolo"
    ],
    "name:fas_x_preferred":[
        "\u062a\u0648\u0645\u0628\u0648\u0644\u0648"
    ],
    "name:fra_x_preferred":[
        "Tombolo"
    ],
    "name:glg_x_preferred":[
        "T\u00f3mbolo"
    ],
    "name:glv_x_preferred":[
        "Tombolo"
    ],
    "name:heb_x_preferred":[
        "\u05d8\u05d5\u05de\u05d1\u05d5\u05dc\u05d5"
    ],
    "name:hin_x_preferred":[
        "\u0938\u0902\u092f\u094b\u091c\u0915 \u0930\u094b\u0927\u093f\u0915\u093e"
    ],
    "name:hun_x_preferred":[
        "Tombol\u00f3"
    ],
    "name:ind_x_preferred":[
        "Tombolo"
    ],
    "name:ita_x_preferred":[
        "Tombolo"
    ],
    "name:jpn_x_preferred":[
        "\u9678\u7e4b\u7802\u5dde"
    ],
    "name:kor_x_preferred":[
        "\uc721\uacc4\uc0ac\uc8fc"
    ],
    "name:lat_x_preferred":[
        "Tumulus"
    ],
    "name:nld_x_preferred":[
        "Tombolo"
    ],
    "name:nno_x_preferred":[
        "Tombolo"
    ],
    "name:pol_x_preferred":[
        "Tombolo"
    ],
    "name:por_x_preferred":[
        "T\u00f4mbolo"
    ],
    "name:rus_x_preferred":[
        "\u0422\u043e\u043c\u0431\u043e\u043b\u043e"
    ],
    "name:spa_x_preferred":[
        "T\u00f3mbolo"
    ],
    "name:swe_x_preferred":[
        "Tombolo"
    ],
    "name:tha_x_preferred":[
        "\u0e2a\u0e31\u0e19\u0e14\u0e2d\u0e19\u0e40\u0e0a\u0e37\u0e48\u0e2d\u0e21\u0e40\u0e01\u0e32\u0e30"
    ],
    "name:tur_x_preferred":[
        "Tombolo"
    ],
    "name:ukr_x_preferred":[
        "\u0422\u043e\u043c\u0431\u043e\u043b\u043e"
    ],
    "name:zho_x_preferred":[
        "\u9023\u5cf6\u6c99\u6d32"
    ],
    "wof:name":"Tombolo",
    "wof:placetype":"locality"
},
  "geometry": {"coordinates":[119.7022,-5.1269],"type":"Point"}
}