{
  "type": "Feature",
  "properties": {
    "gn:admin1_code":"07",
    "gn:asciiname":"Ngrapah",
    "gn:country_code":"ID",
    "gn:dem":169,
    "gn:feature_class":"P",
    "gn:feature_code":"PPL",
    "gn:name":"Ngrapah",
    "gn:population":0,
    "gn:timezone":"Asia/Jakarta",
    "iso:country":"ID",
    "name:ind_x_preferred":[
        "Ngrapah"
    ],
    "wof:name":"Ngrapah",
    "wof:placetype":"locality"
},
  "geometry": {"coordinates":[110.55249999999999,-7.16833],"type":"Point"}
}