{
  "type": "Feature",
  "properties": {
    "gn:admin1_code":"7.0",
    "gn:asciiname":"Bulak",
    "gn:country_code":"ID",
    "gn:dem":57,
    "gn:feature_class":"P",
    "gn:feature_code":"PPLA4",
    "gn:name":"Bulak",
    "gn:population":0,
    "gn:timezone":"Asia/Jakarta",
    "iso:country":"ID",
    "name:ind_x_preferred":[
        "Bulak"
    ],
    "wof:name":"Bulak",
    "wof:placetype":"locality"
},
  "geometry": {"coordinates":[111.2998,-6.7744],"type":"Point"}
}