{
  "type": "Feature",
  "properties": {
    "gn:admin1_code":"17.0",
    "gn:asciiname":"Karangpinang",
    "gn:country_code":"ID",
    "gn:dem":209,
    "gn:feature_class":"P",
    "gn:feature_code":"PPL",
    "gn:name":"Karangpinang",
    "gn:population":0,
    "gn:timezone":"Asia/Makassar",
    "iso:country":"ID",
    "name:ind_x_preferred":[
        "Karangpinang"
    ],
    "wof:name":"Karangpinang",
    "wof:placetype":"locality"
},
  "geometry": {"coordinates":[116.4226,-8.2655],"type":"Point"}
}