{
  "type": "Feature",
  "properties": {
    "gn:admin1_code":"18.0",
    "gn:asciiname":"Pondok Kilometer Dua Satu Kiri",
    "gn:country_code":"ID",
    "gn:dem":19,
    "gn:feature_class":"P",
    "gn:feature_code":"PPL",
    "gn:name":"Pondok Kilometer Dua Satu Kiri",
    "gn:population":0,
    "gn:timezone":"Asia/Makassar",
    "iso:country":"ID",
    "name:ind_x_preferred":[
        "Pondok Kilometer Dua Satu Kiri"
    ],
    "name:und_x_variant":[
        "Pondok Km 2 Satu Kiri"
    ],
    "wof:name":"Pondok Kilometer Dua Satu Kiri",
    "wof:placetype":"locality"
},
  "geometry": {"coordinates":[121.29819999999999,-8.5298],"type":"Point"}
}