{
  "type": "Feature",
  "properties": {
    "gn:admin1_code":"7",
    "gn:asciiname":"Jumbleng",
    "gn:country_code":"ID",
    "gn:dem":625,
    "gn:feature_class":"P",
    "gn:feature_code":"PPL",
    "gn:name":"Jumbleng",
    "gn:population":0,
    "gn:timezone":"Asia/Jakarta",
    "iso:country":"ID",
    "name:ind_x_preferred":[
        "Jumbleng"
    ],
    "wof:name":"Jumbleng",
    "wof:placetype":"locality"
},
  "geometry": {"coordinates":[111.22778,-7.78389],"type":"Point"}
}