{
  "type": "Feature",
  "properties": {
    "gn:admin1_code":"18.0",
    "gn:asciiname":"Paratabonde",
    "gn:country_code":"ID",
    "gn:dem":74,
    "gn:feature_class":"P",
    "gn:feature_code":"PPL",
    "gn:name":"Paratabonde",
    "gn:population":0,
    "gn:timezone":"Asia/Makassar",
    "iso:country":"ID",
    "name:ind_x_preferred":[
        "Paratabonde"
    ],
    "wof:name":"Paratabonde",
    "wof:placetype":"locality"
},
  "geometry": {"coordinates":[119.0981,-9.4521],"type":"Point"}
}