{
  "type": "Feature",
  "properties": {
    "gn:country":"ID",
    "iso:country":"ID",
    "qs:name":"Muarabinuangeun",
    "qs:name_adm0":"Indonesia",
    "qs:name_adm1":"Banten",
    "qs:photos":107,
    "qs:photos_1k":22,
    "qs:photos_9k":1,
    "qs:photos_9r":3,
    "qs:photos_all":107,
    "qs:photos_sr":3,
    "qs:placetype":"Town",
    "qs:pop_sr":"0",
    "wof:name":"Muarabinuangeun",
    "wof:placetype":"locality"
},
  "geometry": {"coordinates":[105.89292500000001,-6.831158],"type":"Point"}
}