{
  "type": "Feature",
  "properties": {
    "gn:admin1_code":"21.0",
    "gn:asciiname":"Watukilo",
    "gn:country_code":"ID",
    "gn:dem":432,
    "gn:feature_class":"P",
    "gn:feature_code":"PPL",
    "gn:name":"Watukilo",
    "gn:population":0,
    "gn:timezone":"Asia/Makassar",
    "iso:country":"ID",
    "name:ind_x_preferred":[
        "Watukilo"
    ],
    "name:und_x_variant":[
        "Watoekama",
        "Watukama"
    ],
    "wof:name":"Watukilo",
    "wof:placetype":"locality"
},
  "geometry": {"coordinates":[120.03740000000001,-1.6081],"type":"Point"}
}