{
  "type": "Feature",
  "properties": {
    "gn:admin1_code":"10.0",
    "gn:asciiname":"Jayan",
    "gn:country_code":"ID",
    "gn:dem":254,
    "gn:feature_class":"P",
    "gn:feature_code":"PPL",
    "gn:name":"Jayan",
    "gn:population":0,
    "gn:timezone":"Asia/Jakarta",
    "iso:country":"ID",
    "wof:name":"Jayan",
    "wof:placetype":"locality"
},
  "geometry": {"coordinates":[110.41861000000002,-7.715],"type":"Point"}
}