{
  "type": "Feature",
  "properties": {
    "gn:admin1_code":"8.0",
    "gn:asciiname":"Ploso Kidul",
    "gn:country_code":"ID",
    "gn:dem":174,
    "gn:feature_class":"P",
    "gn:feature_code":"PPL",
    "gn:name":"Ploso Kidul",
    "gn:population":0,
    "gn:timezone":"Asia/Jakarta",
    "iso:country":"ID",
    "name:ind_x_preferred":[
        "Ploso Kidul"
    ],
    "wof:name":"Ploso Kidul",
    "wof:placetype":"locality"
},
  "geometry": {"coordinates":[111.8801,-7.9866],"type":"Point"}
}