{
  "type": "Feature",
  "properties": {
    "gn:admin1_code":"18.0",
    "gn:asciiname":"Lewopao Atas",
    "gn:country_code":"ID",
    "gn:dem":246,
    "gn:feature_class":"P",
    "gn:feature_code":"PPL",
    "gn:name":"Lewopao Atas",
    "gn:population":0,
    "gn:timezone":"Asia/Makassar",
    "iso:country":"ID",
    "name:ind_x_preferred":[
        "Lewopao Atas"
    ],
    "wof:name":"Lewopao Atas",
    "wof:placetype":"locality"
},
  "geometry": {"coordinates":[123.2697,-8.374],"type":"Point"}
}