{
  "type": "Feature",
  "properties": {
    "gn:admin1_code":"10.0",
    "gn:asciiname":"Kaliduren",
    "gn:country_code":"ID",
    "gn:dem":511,
    "gn:feature_class":"P",
    "gn:feature_code":"PPL",
    "gn:name":"Kaliduren",
    "gn:population":0,
    "gn:timezone":"Asia/Jakarta",
    "iso:country":"ID",
    "wof:name":"Kaliduren",
    "wof:placetype":"locality"
},
  "geometry": {"coordinates":[110.14528,-7.70472],"type":"Point"}
}