{
  "type": "Feature",
  "properties": {
    "gn:admin1_code":"26",
    "gn:asciiname":"Saitnihuta Empat",
    "gn:country_code":"ID",
    "gn:dem":967,
    "gn:feature_class":"P",
    "gn:feature_code":"PPL",
    "gn:name":"Saitnihuta Empat",
    "gn:population":0,
    "gn:timezone":"Asia/Jakarta",
    "iso:country":"ID",
    "name:ind_x_preferred":[
        "Saitnihuta Empat"
    ],
    "name:und_x_variant":[
        "Saitnihuta 4"
    ],
    "wof:lang_x_official":[
        "ind"
    ],
    "wof:lang_x_spoken":[
        "ind",
        "eng"
    ],
    "wof:name":"Saitnihuta Empat",
    "wof:placetype":"locality"
},
  "geometry": {"coordinates":[99.04340000000001,2.338],"type":"Point"}
}