{
  "type": "Feature",
  "properties": {
    "gn:admin1_code":"38",
    "gn:asciiname":"Karerang",
    "gn:country_code":"ID",
    "gn:dem":881,
    "gn:feature_class":"P",
    "gn:feature_code":"PPL",
    "gn:name":"Karerang",
    "gn:population":0,
    "gn:timezone":"Asia/Makassar",
    "iso:country":"ID",
    "name:ind_x_preferred":[
        "Karerang"
    ],
    "wof:name":"Karerang",
    "wof:placetype":"locality"
},
  "geometry": {"coordinates":[119.8758,-3.1336],"type":"Point"}
}