{
  "type": "Feature",
  "properties": {
    "gn:admin1_code":"30.0",
    "gn:asciiname":"Sirnagalih",
    "gn:country_code":"ID",
    "gn:dem":1243,
    "gn:feature_class":"P",
    "gn:feature_code":"PPLA4",
    "gn:name":"Sirnagalih",
    "gn:population":0,
    "gn:timezone":"Asia/Jakarta",
    "iso:country":"ID",
    "name:ind_x_preferred":[
        "Sirnagalih"
    ],
    "wof:name":"Sirnagalih",
    "wof:placetype":"locality"
},
  "geometry": {"coordinates":[107.79989999999999,-7.3505],"type":"Point"}
}