{
  "type": "Feature",
  "properties": {
    "gn:admin1_code":"28.0",
    "gn:asciiname":"Humkaku",
    "gn:country_code":"ID",
    "gn:dem":951,
    "gn:feature_class":"P",
    "gn:feature_code":"PPL",
    "gn:name":"Humkaku",
    "gn:population":0,
    "gn:timezone":"Asia/Jayapura",
    "iso:country":"ID",
    "name:ind_x_preferred":[
        "Humkaku"
    ],
    "name:und_x_variant":[
        "Hoem \u2019Kakoe"
    ],
    "wof:lang_x_official":[
        "ind"
    ],
    "wof:lang_x_spoken":[
        "ind",
        "eng"
    ],
    "wof:name":"Humkaku",
    "wof:placetype":"locality"
},
  "geometry": {"coordinates":[126.85122,-3.65505],"type":"Point"}
}