{
  "type": "Feature",
  "properties": {
    "iso:country":"ID",
    "qs:name":"Uleelheueblang",
    "qs:name_adm0":"Indonesia",
    "qs:name_adm1":"Nanggroe Aceh Darussalam",
    "qs:photos":124,
    "qs:photos_1k":25,
    "qs:photos_9k":1,
    "qs:photos_9r":3,
    "qs:photos_all":124,
    "qs:photos_sr":3,
    "qs:placetype":"Town",
    "qs:pop_sr":"0",
    "wof:lang_x_official":[
        "ind"
    ],
    "wof:lang_x_spoken":[
        "ind",
        "eng"
    ],
    "wof:name":"Uleelheueblang",
    "wof:placetype":"locality"
},
  "geometry": {"coordinates":[95.29197600000001,5.562548],"type":"Point"}
}