{
  "type": "Feature",
  "properties": {
    "gn:admin1_code":"7",
    "gn:asciiname":"Maningkem",
    "gn:country_code":"ID",
    "gn:dem":220,
    "gn:feature_class":"P",
    "gn:feature_code":"PPL",
    "gn:name":"Maningkem",
    "gn:population":0,
    "gn:timezone":"Asia/Jakarta",
    "iso:country":"ID",
    "name:ind_x_preferred":[
        "Maningkem"
    ],
    "wof:name":"Maningkem",
    "wof:placetype":"locality"
},
  "geometry": {"coordinates":[109.31659999999999,-7.0867],"type":"Point"}
}