{
  "type": "Feature",
  "properties": {
    "gn:admin1_code":"38",
    "gn:asciiname":"Polewali",
    "gn:country_code":"ID",
    "gn:dem":20,
    "gn:feature_class":"P",
    "gn:feature_code":"PPL",
    "gn:name":"Polewali",
    "gn:population":0,
    "gn:timezone":"Asia/Makassar",
    "iso:country":"ID",
    "name:ind_x_preferred":[
        "Polewali"
    ],
    "wof:name":"Polewali",
    "wof:placetype":"locality"
},
  "geometry": {"coordinates":[120.3394,-4.7626],"type":"Point"}
}