{
  "type": "Feature",
  "properties": {
    "gn:admin1_code":"17",
    "gn:asciiname":"Karanglebah",
    "gn:country_code":"ID",
    "gn:dem":246,
    "gn:feature_class":"P",
    "gn:feature_code":"PPL",
    "gn:name":"Karanglebah",
    "gn:population":0,
    "gn:timezone":"Asia/Makassar",
    "iso:country":"ID",
    "name:ind_x_preferred":[
        "Karanglebah"
    ],
    "wof:name":"Karanglebah",
    "wof:placetype":"locality"
},
  "geometry": {"coordinates":[116.4576,-8.6843],"type":"Point"}
}