{
  "type": "Feature",
  "properties": {
    "gn:admin1_code":"31",
    "gn:asciiname":"Tamboasin",
    "gn:country_code":"ID",
    "gn:dem":53,
    "gn:feature_class":"P",
    "gn:feature_code":"PPL",
    "gn:name":"Tamboasin",
    "gn:population":0,
    "gn:timezone":"Asia/Makassar",
    "iso:country":"ID",
    "name:ind_x_preferred":[
        "Tamboasin"
    ],
    "wof:name":"Tamboasin",
    "wof:placetype":"locality"
},
  "geometry": {"coordinates":[125.0097,1.6975],"type":"Point"}
}