{
  "type": "Feature",
  "properties": {
    "gn:admin1_code":"8.0",
    "gn:asciiname":"Dengkeng",
    "gn:country_code":"ID",
    "gn:dem":449,
    "gn:feature_class":"P",
    "gn:feature_code":"PPL",
    "gn:name":"Dengkeng",
    "gn:population":0,
    "gn:timezone":"Asia/Jakarta",
    "iso:country":"ID",
    "name:ind_x_preferred":[
        "Dengkeng"
    ],
    "wof:name":"Dengkeng",
    "wof:placetype":"locality"
},
  "geometry": {"coordinates":[111.38249999999999,-8.205],"type":"Point"}
}