{
  "type": "Feature",
  "properties": {
    "gn:admin1_code":"15.0",
    "gn:asciiname":"Kertajaman",
    "gn:country_code":"ID",
    "gn:dem":92,
    "gn:feature_class":"P",
    "gn:feature_code":"PPL",
    "gn:name":"Kertajaman",
    "gn:population":0,
    "gn:timezone":"Asia/Jakarta",
    "iso:country":"ID",
    "name:ind_x_preferred":[
        "Kertajaman"
    ],
    "wof:name":"Kertajaman",
    "wof:placetype":"locality"
},
  "geometry": {"coordinates":[105.70253999999998,-5.78044],"type":"Point"}
}