{
  "type": "Feature",
  "properties": {
    "gn:admin1_code":"30",
    "gn:asciiname":"Sukabungah",
    "gn:country_code":"ID",
    "gn:dem":685,
    "gn:feature_class":"P",
    "gn:feature_code":"PPL",
    "gn:name":"Sukabungah",
    "gn:population":0,
    "gn:timezone":"Asia/Jakarta",
    "iso:country":"ID",
    "name:ind_x_preferred":[
        "Sukabungah"
    ],
    "wof:name":"Sukabungah",
    "wof:placetype":"locality"
},
  "geometry": {"coordinates":[107.46083,-6.72],"type":"Point"}
}