{
  "type": "Feature",
  "properties": {
    "gn:admin1_code":"7",
    "gn:asciiname":"Genengan",
    "gn:country_code":"ID",
    "gn:dem":1052,
    "gn:feature_class":"P",
    "gn:feature_code":"PPL",
    "gn:name":"Genengan",
    "gn:population":0,
    "gn:timezone":"Asia/Jakarta",
    "iso:country":"ID",
    "name:ind_x_preferred":[
        "Genengan"
    ],
    "wof:name":"Genengan",
    "wof:placetype":"locality"
},
  "geometry": {"coordinates":[111.12361,-7.71194],"type":"Point"}
}