{
  "type": "Feature",
  "properties": {
    "gn:admin1_code":"30.0",
    "gn:asciiname":"Pasirgaruk",
    "gn:country_code":"ID",
    "gn:dem":544,
    "gn:feature_class":"P",
    "gn:feature_code":"PPL",
    "gn:name":"Pasirgaruk",
    "gn:population":0,
    "gn:timezone":"Asia/Jakarta",
    "iso:country":"ID",
    "name:ind_x_preferred":[
        "Pasirgaruk"
    ],
    "wof:name":"Pasirgaruk",
    "wof:placetype":"locality"
},
  "geometry": {"coordinates":[108.4032,-7.1312],"type":"Point"}
}