{
  "type": "Feature",
  "properties": {
    "gn:admin1_code":"28.0",
    "gn:asciiname":"Kilun",
    "gn:country_code":"ID",
    "gn:dem":6,
    "gn:feature_class":"P",
    "gn:feature_code":"PPL",
    "gn:name":"Kilun",
    "gn:population":0,
    "gn:timezone":"Asia/Jayapura",
    "iso:country":"ID",
    "name:und_x_variant":[
        "Kiloen",
        "Kilun"
    ],
    "wof:name":"Kilun",
    "wof:placetype":"locality"
},
  "geometry": {"coordinates":[131.59351999999998,-6.72508],"type":"Point"}
}