{
  "type": "Feature",
  "properties": {
    "gn:admin1_code":"8.0",
    "gn:asciiname":"Saman",
    "gn:country_code":"ID",
    "gn:dem":482,
    "gn:feature_class":"P",
    "gn:feature_code":"PPL",
    "gn:name":"Saman",
    "gn:population":0,
    "gn:timezone":"Asia/Jakarta",
    "iso:country":"ID",
    "name:ceb_x_preferred":[
        "Saman"
    ],
    "name:fra_x_preferred":[
        "Saman"
    ],
    "name:ind_x_preferred":[
        "Saman"
    ],
    "name:kat_x_preferred":[
        "\u10e1\u10d0\u10db\u10d0\u10dc\u10d8"
    ],
    "name:nld_x_preferred":[
        "Saman"
    ],
    "name:pol_x_preferred":[
        "Saman"
    ],
    "name:rus_x_preferred":[
        "\u0421\u0430\u043c\u0430\u043d"
    ],
    "name:swe_x_preferred":[
        "Saman"
    ],
    "name:ukr_x_preferred":[
        "\u0421\u0430\u043c\u0430\u043d"
    ],
    "wof:name":"Saman",
    "wof:placetype":"locality"
},
  "geometry": {"coordinates":[111.26472,-8.14639],"type":"Point"}
}