{
  "type": "Feature",
  "properties": {
    "gn:admin1_code":"38",
    "gn:asciiname":"Moncongkeke",
    "gn:country_code":"ID",
    "gn:dem":37,
    "gn:feature_class":"P",
    "gn:feature_code":"PPL",
    "gn:name":"Moncongkeke",
    "gn:population":0,
    "gn:timezone":"Asia/Makassar",
    "iso:country":"ID",
    "name:ind_x_preferred":[
        "Moncongkeke"
    ],
    "wof:name":"Moncongkeke",
    "wof:placetype":"locality"
},
  "geometry": {"coordinates":[119.5874,-5.164],"type":"Point"}
}