{
  "type": "Feature",
  "properties": {
    "gn:admin1_code":"17",
    "gn:asciiname":"Tanahembang Lauk",
    "gn:country_code":"ID",
    "gn:dem":347,
    "gn:feature_class":"P",
    "gn:feature_code":"PPL",
    "gn:name":"Tanahembang Lauk",
    "gn:population":0,
    "gn:timezone":"Asia/Makassar",
    "iso:country":"ID",
    "name:ind_x_preferred":[
        "Tanahembang Lauk"
    ],
    "wof:name":"Tanahembang Lauk",
    "wof:placetype":"locality"
},
  "geometry": {"coordinates":[116.30840000000001,-8.5905],"type":"Point"}
}