{
  "type": "Feature",
  "properties": {
    "gn:admin1_code":"8.0",
    "gn:asciiname":"Jengkol",
    "gn:country_code":"ID",
    "gn:dem":791,
    "gn:feature_class":"P",
    "gn:feature_code":"PPL",
    "gn:name":"Jengkol",
    "gn:population":0,
    "gn:timezone":"Asia/Jakarta",
    "iso:country":"ID",
    "name:ind_x_preferred":[
        "Jengkol"
    ],
    "wof:name":"Jengkol",
    "wof:placetype":"locality"
},
  "geometry": {"coordinates":[111.77209999999999,-7.9626],"type":"Point"}
}