{
  "type": "Feature",
  "properties": {
    "gn:admin1_code":"26",
    "gn:asciiname":"Simpang Muara",
    "gn:country_code":"ID",
    "gn:dem":1545,
    "gn:feature_class":"P",
    "gn:feature_code":"PPL",
    "gn:name":"Simpang Muara",
    "gn:population":0,
    "gn:timezone":"Asia/Jakarta",
    "iso:country":"ID",
    "name:ind_x_preferred":[
        "Simpang Muara"
    ],
    "wof:name":"Simpang Muara",
    "wof:placetype":"locality"
},
  "geometry": {"coordinates":[98.9614,2.2995],"type":"Point"}
}