{
  "type": "Feature",
  "properties": {
    "gn:admin1_code":"33",
    "gn:asciiname":"Ranji",
    "gn:country_code":"ID",
    "gn:dem":36,
    "gn:feature_class":"P",
    "gn:feature_code":"PPL",
    "gn:name":"Ranji",
    "gn:population":0,
    "gn:timezone":"Asia/Jakarta",
    "iso:country":"ID",
    "name:ind_x_preferred":[
        "Ranji"
    ],
    "wof:name":"Ranji",
    "wof:placetype":"locality"
},
  "geometry": {"coordinates":[106.33759999999999,-6.2786],"type":"Point"}
}