{
  "type": "Feature",
  "properties": {
    "gn:admin1_code":"7.0",
    "gn:asciiname":"Kedungbanteng",
    "gn:country_code":"ID",
    "gn:dem":295,
    "gn:feature_class":"P",
    "gn:feature_code":"PPL",
    "gn:name":"Kedungbanteng",
    "gn:population":0,
    "gn:timezone":"Asia/Jakarta",
    "iso:country":"ID",
    "name:ind_x_preferred":[
        "Kedungbanteng"
    ],
    "wof:name":"Kedungbanteng",
    "wof:placetype":"locality"
},
  "geometry": {"coordinates":[109.03610999999999,-7.31167],"type":"Point"}
}