{
  "type": "Feature",
  "properties": {
    "gn:admin1_code":"30",
    "gn:asciiname":"Tanahmerah",
    "gn:country_code":"ID",
    "gn:dem":9,
    "gn:feature_class":"P",
    "gn:feature_code":"PPL",
    "gn:name":"Tanahmerah",
    "gn:population":0,
    "gn:timezone":"Asia/Jakarta",
    "iso:country":"ID",
    "name:ind_x_preferred":[
        "Tanahmerah"
    ],
    "wof:name":"Tanahmerah",
    "wof:placetype":"locality"
},
  "geometry": {"coordinates":[107.215,-6.26],"type":"Point"}
}