{
  "type": "Feature",
  "properties": {
    "gn:country":"ID",
    "gn:fcode":"ADMD",
    "gn:pop":0,
    "iso:country":"ID",
    "name:unk_x_variant":[
        "Daerah Tingkat II Lebak"
    ],
    "qs:name":"Kabupaten Lebak",
    "qs:photos_9r":0,
    "qs:photos_sr":0,
    "qs:pop_sr":"0",
    "wof:name":"Kabupaten Lebak",
    "wof:placetype":"localadmin",
    "wof:population":0
},
  "geometry": {"coordinates":[106.25,-6.66667],"type":"Point"}
}