{
  "type": "Feature",
  "properties": {
    "gn:admin1_code":"30.0",
    "gn:asciiname":"Sukalembah",
    "gn:country_code":"ID",
    "gn:dem":418,
    "gn:feature_class":"P",
    "gn:feature_code":"PPL",
    "gn:name":"Sukalembah",
    "gn:population":0,
    "gn:timezone":"Asia/Jakarta",
    "iso:country":"ID",
    "name:ind_x_preferred":[
        "Sukalembah"
    ],
    "name:und_x_variant":[
        "Soekalembak"
    ],
    "wof:name":"Sukalembah",
    "wof:placetype":"locality"
},
  "geometry": {"coordinates":[108.6416,-7.5742],"type":"Point"}
}