{
  "type": "Feature",
  "properties": {
    "gn:admin1_code":"30.0",
    "gn:asciiname":"Kemancing",
    "gn:country_code":"ID",
    "gn:dem":208,
    "gn:feature_class":"P",
    "gn:feature_code":"PPL",
    "gn:name":"Kemancing",
    "gn:population":0,
    "gn:timezone":"Asia/Jakarta",
    "iso:country":"ID",
    "name:ind_x_preferred":[
        "Kemancing"
    ],
    "name:und_x_variant":[
        "Kemantjing"
    ],
    "wof:name":"Kemancing",
    "wof:placetype":"locality"
},
  "geometry": {"coordinates":[108.5249,-7.0375],"type":"Point"}
}