{
  "type": "Feature",
  "properties": {
    "gn:admin1_code":"31.0",
    "gn:asciiname":"Bangomolunow",
    "gn:country_code":"ID",
    "gn:dem":21,
    "gn:feature_class":"P",
    "gn:feature_code":"PPL",
    "gn:name":"Bangomolunow",
    "gn:population":0,
    "gn:timezone":"Asia/Makassar",
    "iso:country":"ID",
    "name:ind_x_preferred":[
        "Bangomolunow"
    ],
    "wof:name":"Bangomolunow",
    "wof:placetype":"locality"
},
  "geometry": {"coordinates":[124.13979999999999,0.8565],"type":"Point"}
}