{
  "type": "Feature",
  "properties": {
    "gn:admin1_code":"7",
    "gn:asciiname":"Sidomukti",
    "gn:country_code":"ID",
    "gn:dem":853,
    "gn:feature_class":"P",
    "gn:feature_code":"PPL",
    "gn:name":"Sidomukti",
    "gn:population":0,
    "gn:timezone":"Asia/Jakarta",
    "iso:country":"ID",
    "name:ind_x_preferred":[
        "Sidomukti"
    ],
    "wof:name":"Sidomukti",
    "wof:placetype":"locality"
},
  "geometry": {"coordinates":[109.95722000000001,-7.38194],"type":"Point"}
}