{
  "type": "Feature",
  "properties": {
    "gn:admin1_code":"26.0",
    "gn:asciiname":"Sirombu",
    "gn:country_code":"ID",
    "gn:dem":9,
    "gn:feature_class":"P",
    "gn:feature_code":"PPL",
    "gn:name":"Sirombu",
    "gn:population":0,
    "gn:timezone":"Asia/Jakarta",
    "iso:country":"ID",
    "name:ind_x_preferred":[
        "Sirombu"
    ],
    "name:und_x_variant":[
        "Siromboe"
    ],
    "wof:name":"Sirombu",
    "wof:placetype":"locality"
},
  "geometry": {"coordinates":[97.4174,0.9514],"type":"Point"}
}