{
  "type": "Feature",
  "properties": {
    "gn:admin1_code":"8.0",
    "gn:asciiname":"Marwa",
    "gn:country_code":"ID",
    "gn:dem":1,
    "gn:feature_class":"P",
    "gn:feature_code":"PPL",
    "gn:name":"Marwa",
    "gn:population":0,
    "gn:timezone":"Asia/Jakarta",
    "iso:country":"ID",
    "name:ara_x_preferred":[
        "\u0645\u0631\u0648\u0649"
    ],
    "name:ceb_x_preferred":[
        "Marwa"
    ],
    "name:deu_x_preferred":[
        "Marwa"
    ],
    "name:ind_x_preferred":[
        "Marwa"
    ],
    "name:rus_x_preferred":[
        "\u041c\u0430\u0440\u0432\u0430"
    ],
    "name:swe_x_preferred":[
        "Marwa"
    ],
    "wof:lang_x_official":[
        "ind"
    ],
    "wof:lang_x_spoken":[
        "ind",
        "eng"
    ],
    "wof:name":"Marwa",
    "wof:placetype":"locality"
},
  "geometry": {"coordinates":[113.2497,-7.6805],"type":"Point"}
}