{
  "type": "Feature",
  "properties": {
    "gn:admin1_code":"30.0",
    "gn:asciiname":"Ciwahang",
    "gn:country_code":"ID",
    "gn:dem":680,
    "gn:feature_class":"P",
    "gn:feature_code":"PPL",
    "gn:name":"Ciwahang",
    "gn:population":0,
    "gn:timezone":"Asia/Jakarta",
    "iso:country":"ID",
    "name:ind_x_preferred":[
        "Ciwahang"
    ],
    "name:und_x_variant":[
        "Tjiwahang"
    ],
    "wof:name":"Ciwahang",
    "wof:placetype":"locality"
},
  "geometry": {"coordinates":[108.0967,-7.0622],"type":"Point"}
}