{
  "type": "Feature",
  "properties": {
    "gn:admin1_code":"18.0",
    "gn:asciiname":"Elopada",
    "gn:country_code":"ID",
    "gn:dem":482,
    "gn:feature_class":"P",
    "gn:feature_code":"PPLA3",
    "gn:name":"Elopada",
    "gn:population":0,
    "gn:timezone":"Asia/Makassar",
    "iso:country":"ID",
    "name:ind_x_preferred":[
        "Elopada"
    ],
    "name:und_x_variant":[
        "Ellopada",
        "Elopada"
    ],
    "wof:lang_x_official":[
        "ind"
    ],
    "wof:lang_x_spoken":[
        "ind",
        "eng"
    ],
    "wof:name":"Elopada",
    "wof:placetype":"locality"
},
  "geometry": {"coordinates":[119.3172,-9.5686],"type":"Point"}
}