{
  "type": "Feature",
  "properties": {
    "gn:admin1_code":"33.0",
    "gn:asciiname":"Limusgantung Barat",
    "gn:country_code":"ID",
    "gn:dem":120,
    "gn:feature_class":"P",
    "gn:feature_code":"PPL",
    "gn:name":"Limusgantung Barat",
    "gn:population":0,
    "gn:timezone":"Asia/Jakarta",
    "iso:country":"ID",
    "name:ind_x_preferred":[
        "Limusgantung Barat"
    ],
    "wof:name":"Limusgantung Barat",
    "wof:placetype":"locality"
},
  "geometry": {"coordinates":[106.06140000000001,-6.4093],"type":"Point"}
}