{
  "type": "Feature",
  "properties": {
    "gn:admin1_code":"15.0",
    "gn:asciiname":"Talangdikun",
    "gn:country_code":"ID",
    "gn:dem":829,
    "gn:feature_class":"P",
    "gn:feature_code":"PPL",
    "gn:name":"Talangdikun",
    "gn:population":0,
    "gn:timezone":"Asia/Jakarta",
    "iso:country":"ID",
    "name:ind_x_preferred":[
        "Talangdikun"
    ],
    "wof:name":"Talangdikun",
    "wof:placetype":"locality"
},
  "geometry": {"coordinates":[104.60929,-5.29755],"type":"Point"}
}