{
  "type": "Feature",
  "properties": {
    "gn:admin1_code":"10",
    "gn:asciiname":"Blambangan",
    "gn:country_code":"ID",
    "gn:dem":103,
    "gn:feature_class":"P",
    "gn:feature_code":"PPL",
    "gn:name":"Blambangan",
    "gn:population":0,
    "gn:timezone":"Asia/Jakarta",
    "iso:country":"ID",
    "wof:name":"Blambangan",
    "wof:placetype":"locality"
},
  "geometry": {"coordinates":[110.46639,-7.8075],"type":"Point"}
}