{
  "type": "Feature",
  "properties": {
    "gn:admin1_code":"38",
    "gn:asciiname":"Rea",
    "gn:country_code":"ID",
    "gn:dem":475,
    "gn:feature_class":"P",
    "gn:feature_code":"PPL",
    "gn:name":"Rea",
    "gn:population":0,
    "gn:timezone":"Asia/Makassar",
    "iso:country":"ID",
    "name:bre_x_preferred":[
        "Rea"
    ],
    "name:cat_x_preferred":[
        "Rea"
    ],
    "name:ceb_x_preferred":[
        "Rea"
    ],
    "name:ces_x_preferred":[
        "Rea"
    ],
    "name:eus_x_preferred":[
        "Rea"
    ],
    "name:fra_x_preferred":[
        "Rea"
    ],
    "name:glg_x_preferred":[
        "Rea"
    ],
    "name:hun_x_preferred":[
        "Rea"
    ],
    "name:ind_x_preferred":[
        "Rea"
    ],
    "name:nds_x_preferred":[
        "Rea"
    ],
    "name:nld_x_preferred":[
        "Rea"
    ],
    "name:pol_x_preferred":[
        "Rea"
    ],
    "name:por_x_preferred":[
        "Rea"
    ],
    "name:slv_x_preferred":[
        "Rea"
    ],
    "name:spa_x_preferred":[
        "Rea"
    ],
    "name:und_x_variant":[
        "Reo"
    ],
    "name:vol_x_preferred":[
        "Rea"
    ],
    "wof:lang_x_official":[
        "ind"
    ],
    "wof:lang_x_spoken":[
        "ind",
        "eng"
    ],
    "wof:name":"Rea",
    "wof:placetype":"locality"
},
  "geometry": {"coordinates":[119.7946,-4.6178],"type":"Point"}
}