{
  "type": "Feature",
  "properties": {
    "gn:admin1_code":"0.0",
    "gn:asciiname":"Terasterunjam",
    "gn:cc2":"ID",
    "gn:country_code":"ID",
    "gn:dem":28,
    "gn:feature_class":"P",
    "gn:feature_code":"PPL",
    "gn:name":"Terasterunjam",
    "gn:population":0,
    "gn:timezone":"Asia/Jakarta",
    "iso:country":"ID",
    "name:und_x_variant":[
        "Terasterundjam",
        "Terasteroendjam",
        "Terasterunjam"
    ],
    "wof:lang_x_official":[
        "ind"
    ],
    "wof:lang_x_spoken":[
        "ind",
        "eng"
    ],
    "wof:name":"Terasterunjam",
    "wof:placetype":"locality"
},
  "geometry": {"coordinates":[101.25,-2.58333],"type":"Point"}
}