{
  "type": "Feature",
  "properties": {
    "gn:admin1_code":"0.0",
    "gn:asciiname":"Bangsal",
    "gn:cc2":"ID",
    "gn:country_code":"ID",
    "gn:dem":31,
    "gn:feature_class":"P",
    "gn:feature_code":"PPL",
    "gn:name":"Bangsal",
    "gn:population":0,
    "gn:timezone":"Asia/Makassar",
    "iso:country":"ID",
    "name:und_x_variant":[
        "Bongsal",
        "Bangsal"
    ],
    "wof:name":"Bangsal",
    "wof:placetype":"locality"
},
  "geometry": {"coordinates":[116.98333,-1.08333],"type":"Point"}
}