{
  "type": "Feature",
  "properties": {
    "gn:admin1_code":"33.0",
    "gn:asciiname":"Warunggunung",
    "gn:country_code":"ID",
    "gn:dem":23,
    "gn:feature_class":"P",
    "gn:feature_code":"PPL",
    "gn:name":"Warunggunung",
    "gn:population":0,
    "gn:timezone":"Asia/Jakarta",
    "iso:country":"ID",
    "name:ind_x_preferred":[
        "Warunggunung"
    ],
    "wof:name":"Warunggunung",
    "wof:placetype":"locality"
},
  "geometry": {"coordinates":[106.17086999999999,-6.90707],"type":"Point"}
}