{
  "type": "Feature",
  "properties": {
    "gn:admin1_code":"2",
    "gn:asciiname":"Banjar Baleagung",
    "gn:country_code":"ID",
    "gn:dem":37,
    "gn:feature_class":"P",
    "gn:feature_code":"PPL",
    "gn:name":"Banjar Baleagung",
    "gn:population":0,
    "gn:timezone":"Asia/Makassar",
    "iso:country":"ID",
    "name:ind_x_preferred":[
        "Banjar Baleagung"
    ],
    "wof:name":"Banjar Baleagung",
    "wof:placetype":"locality"
},
  "geometry": {"coordinates":[115.1135,-8.623],"type":"Point"}
}