{
  "type": "Feature",
  "properties": {
    "gn:admin1_code":"8.0",
    "gn:asciiname":"Kenton",
    "gn:country_code":"ID",
    "gn:dem":78,
    "gn:feature_class":"P",
    "gn:feature_code":"PPL",
    "gn:name":"Kenton",
    "gn:population":0,
    "gn:timezone":"Asia/Jakarta",
    "iso:country":"ID",
    "name:cat_x_preferred":[
        "Kenton"
    ],
    "name:ceb_x_preferred":[
        "Kenton"
    ],
    "name:deu_x_preferred":[
        "Kenton"
    ],
    "name:fra_x_preferred":[
        "Kenton"
    ],
    "name:ind_x_preferred":[
        "Kenton"
    ],
    "name:ita_x_preferred":[
        "Kenton"
    ],
    "name:nld_x_preferred":[
        "Kenton"
    ],
    "name:pol_x_preferred":[
        "Kenton"
    ],
    "name:por_x_preferred":[
        "Kenton"
    ],
    "name:rus_x_preferred":[
        "\u041a\u0435\u043d\u0442\u043e\u043d"
    ],
    "name:sco_x_preferred":[
        "Kenton"
    ],
    "name:spa_x_preferred":[
        "Kenton"
    ],
    "name:srp_x_preferred":[
        "\u041a\u0435\u043d\u0442\u043e\u043d"
    ],
    "name:swe_x_preferred":[
        "Kenton"
    ],
    "name:ukr_x_preferred":[
        "\u041a\u0435\u043d\u0442\u043e\u043d"
    ],
    "name:vol_x_preferred":[
        "Kenton"
    ],
    "wof:name":"Kenton",
    "wof:placetype":"locality"
},
  "geometry": {"coordinates":[111.9828,-7.7854],"type":"Point"}
}