{
  "type": "Feature",
  "properties": {
    "gn:admin1_code":"1.0",
    "gn:asciiname":"Kulam",
    "gn:country_code":"ID",
    "gn:dem":7,
    "gn:feature_class":"P",
    "gn:feature_code":"PPL",
    "gn:name":"Kulam",
    "gn:population":0,
    "gn:timezone":"Asia/Jakarta",
    "iso:country":"ID",
    "name:ind_x_preferred":[
        "Kulam"
    ],
    "name:und_x_variant":[
        "Kulan"
    ],
    "wof:name":"Kulam",
    "wof:placetype":"locality"
},
  "geometry": {"coordinates":[95.8912,5.4487],"type":"Point"}
}