{
  "type": "Feature",
  "properties": {
    "gn:admin1_code":"18.0",
    "gn:asciiname":"Nefokeba",
    "gn:country_code":"ID",
    "gn:dem":360,
    "gn:feature_class":"P",
    "gn:feature_code":"PPL",
    "gn:name":"Nefokeba",
    "gn:population":0,
    "gn:timezone":"Asia/Makassar",
    "iso:country":"ID",
    "name:ind_x_preferred":[
        "Nefokeba"
    ],
    "wof:name":"Nefokeba",
    "wof:placetype":"locality"
},
  "geometry": {"coordinates":[123.6182,-10.3234],"type":"Point"}
}