{
  "type": "Feature",
  "properties": {
    "gn:admin1_code":"18.0",
    "gn:asciiname":"Koba",
    "gn:country_code":"ID",
    "gn:dem":78,
    "gn:feature_class":"P",
    "gn:feature_code":"PPL",
    "gn:name":"Koba",
    "gn:population":0,
    "gn:timezone":"Asia/Makassar",
    "iso:country":"ID",
    "name:ceb_x_preferred":[
        "Koba"
    ],
    "name:deu_x_preferred":[
        "Koba"
    ],
    "name:fra_x_preferred":[
        "Koba"
    ],
    "name:ind_x_preferred":[
        "Koba"
    ],
    "name:ita_x_preferred":[
        "Koba"
    ],
    "name:nld_x_preferred":[
        "Koba"
    ],
    "name:rus_x_preferred":[
        "\u041a\u043e\u0431\u0430"
    ],
    "name:srp_x_preferred":[
        "\u041a\u043e\u0431\u0430"
    ],
    "name:swe_x_preferred":[
        "Koba"
    ],
    "wof:name":"Koba",
    "wof:placetype":"locality"
},
  "geometry": {"coordinates":[119.0052,-9.5371],"type":"Point"}
}