{
  "type": "Feature",
  "properties": {
    "gn:admin1_code":"26",
    "gn:asciiname":"Lau Pengkerukan",
    "gn:country_code":"ID",
    "gn:dem":327,
    "gn:feature_class":"P",
    "gn:feature_code":"PPL",
    "gn:name":"Lau Pengkerukan",
    "gn:population":0,
    "gn:timezone":"Asia/Jakarta",
    "iso:country":"ID",
    "name:ind_x_preferred":[
        "Lau Pengkerukan"
    ],
    "wof:name":"Lau Pengkerukan",
    "wof:placetype":"locality"
},
  "geometry": {"coordinates":[98.1451,2.9734],"type":"Point"}
}