{
  "type": "Feature",
  "properties": {
    "gn:admin1_code":"18.0",
    "gn:asciiname":"Dua",
    "gn:country_code":"ID",
    "gn:dem":698,
    "gn:feature_class":"P",
    "gn:feature_code":"PPL",
    "gn:name":"Dua",
    "gn:population":0,
    "gn:timezone":"Asia/Makassar",
    "iso:country":"ID",
    "name:afr_x_preferred":[
        "Dua"
    ],
    "name:ara_x_preferred":[
        "\u062f\u0639\u0627\u0621"
    ],
    "name:asm_x_preferred":[
        "\u09a6\u09c1\u0986"
    ],
    "name:bak_x_preferred":[
        "\u0414\u043e\u0493\u0430"
    ],
    "name:ben_x_preferred":[
        "\u09a6\u09cb\u09af\u09bc\u09be"
    ],
    "name:ces_x_preferred":[
        "Du'\u00e1"
    ],
    "name:deu_x_preferred":[
        "Du\u02bf\u0101'"
    ],
    "name:fas_x_preferred":[
        "\u062f\u0639\u0627"
    ],
    "name:hin_x_preferred":[
        "\u0926\u0941\u0906"
    ],
    "name:ind_x_preferred":[
        "Dua"
    ],
    "name:msa_x_preferred":[
        "Doa"
    ],
    "name:rus_x_preferred":[
        "\u0414\u0443\u0430"
    ],
    "name:snd_x_preferred":[
        "\u062f\u0639\u0627"
    ],
    "name:sqi_x_preferred":[
        "Duaja"
    ],
    "name:tat_x_preferred":[
        "\u0414\u043e\u0433\u0430"
    ],
    "name:tgk_x_preferred":[
        "\u0414\u0443\u043e"
    ],
    "name:ukr_x_preferred":[
        "\u0414\u0443\u0430"
    ],
    "name:urd_x_preferred":[
        "\u062f\u0639\u0627"
    ],
    "name:uzb_x_preferred":[
        "Duo"
    ],
    "wof:lang_x_official":[
        "ind"
    ],
    "wof:lang_x_spoken":[
        "ind",
        "eng"
    ],
    "wof:name":"Dua",
    "wof:placetype":"locality"
},
  "geometry": {"coordinates":[123.5234,-8.4601],"type":"Point"}
}