{
  "type": "Feature",
  "properties": {
    "gn:admin1_code":"18.0",
    "gn:asciiname":"Dua",
    "gn:country_code":"ID",
    "gn:dem":698,
    "gn:feature_class":"P",
    "gn:feature_code":"PPL",
    "gn:name":"Dua",
    "gn:population":0,
    "gn:timezone":"Asia/Makassar",
    "iso:country":"ID",
    "name:ind_x_preferred":[
        "Dua"
    ],
    "wof:name":"Dua",
    "wof:placetype":"locality"
},
  "geometry": {"coordinates":[123.5234,-8.4601],"type":"Point"}
}