{
  "type": "Feature",
  "properties": {
    "gn:admin1_code":"30.0",
    "gn:asciiname":"Sukamantri",
    "gn:country_code":"ID",
    "gn:dem":374,
    "gn:feature_class":"P",
    "gn:feature_code":"PPL",
    "gn:name":"Sukamantri",
    "gn:population":0,
    "gn:timezone":"Asia/Jakarta",
    "iso:country":"ID",
    "name:ind_x_preferred":[
        "Sukamantri"
    ],
    "name:und_x_variant":[
        "Soekainantri",
        "Soekamantri"
    ],
    "wof:name":"Sukamantri",
    "wof:placetype":"locality"
},
  "geometry": {"coordinates":[107.88694,-6.76278],"type":"Point"}
}