{
  "type": "Feature",
  "properties": {
    "gn:admin1_code":"42.0",
    "gn:asciiname":"Salinbatu",
    "gn:country_code":"ID",
    "gn:dem":5,
    "gn:feature_class":"P",
    "gn:feature_code":"PPLA3",
    "gn:name":"Salinbatu",
    "gn:population":0,
    "gn:timezone":"Asia/Makassar",
    "iso:country":"ID",
    "name:ind_x_preferred":[
        "Salinbatu"
    ],
    "name:ind_x_variant":[
        "Salim Batu"
    ],
    "name:und_x_variant":[
        "Salimbatoe",
        "Salinbatoe",
        "Salimbatu"
    ],
    "wof:lang_x_official":[
        "ind"
    ],
    "wof:lang_x_spoken":[
        "ind",
        "eng"
    ],
    "wof:name":"Salinbatu",
    "wof:placetype":"locality"
},
  "geometry": {"coordinates":[117.34343,2.94051],"type":"Point"}
}