{
  "type": "Feature",
  "properties": {
    "gn:admin1_code":"30",
    "gn:asciiname":"Sekehonje",
    "gn:country_code":"ID",
    "gn:dem":782,
    "gn:feature_class":"P",
    "gn:feature_code":"PPL",
    "gn:name":"Sekehonje",
    "gn:population":0,
    "gn:timezone":"Asia/Jakarta",
    "iso:country":"ID",
    "name:ind_x_preferred":[
        "Sekehonje"
    ],
    "name:und_x_variant":[
        "Sekehondje"
    ],
    "wof:lang_x_official":[
        "ind"
    ],
    "wof:lang_x_spoken":[
        "ind",
        "eng"
    ],
    "wof:name":"Sekehonje",
    "wof:placetype":"locality"
},
  "geometry": {"coordinates":[107.72167,-6.91083],"type":"Point"}
}