{
  "type": "Feature",
  "properties": {
    "gn:admin1_code":"33.0",
    "gn:asciiname":"Karangropong",
    "gn:country_code":"ID",
    "gn:dem":469,
    "gn:feature_class":"P",
    "gn:feature_code":"PPL",
    "gn:name":"Karangropong",
    "gn:population":0,
    "gn:timezone":"Asia/Jakarta",
    "iso:country":"ID",
    "name:ind_x_preferred":[
        "Karangropong"
    ],
    "wof:name":"Karangropong",
    "wof:placetype":"locality"
},
  "geometry": {"coordinates":[106.4359,-6.8281],"type":"Point"}
}