{
  "type": "Feature",
  "properties": {
    "gn:admin1_code":"26",
    "gn:asciiname":"Sawahluta Dua",
    "gn:country_code":"ID",
    "gn:dem":33,
    "gn:feature_class":"P",
    "gn:feature_code":"PPL",
    "gn:name":"Sawahluta Dua",
    "gn:population":0,
    "gn:timezone":"Asia/Jakarta",
    "iso:country":"ID",
    "name:ind_x_preferred":[
        "Sawahluta Dua"
    ],
    "name:und_x_variant":[
        "Sawahluta 2"
    ],
    "wof:name":"Sawahluta Dua",
    "wof:placetype":"locality"
},
  "geometry": {"coordinates":[98.3776,2.0522],"type":"Point"}
}