{
  "type": "Feature",
  "properties": {
    "gn:admin1_code":"17",
    "gn:asciiname":"Mertagaok",
    "gn:country_code":"ID",
    "gn:dem":229,
    "gn:feature_class":"P",
    "gn:feature_code":"PPL",
    "gn:name":"Mertagaok",
    "gn:population":0,
    "gn:timezone":"Asia/Makassar",
    "iso:country":"ID",
    "name:ind_x_preferred":[
        "Mertagaok"
    ],
    "wof:name":"Mertagaok",
    "wof:placetype":"locality"
},
  "geometry": {"coordinates":[116.2881,-8.6619],"type":"Point"}
}