{
  "type": "Feature",
  "properties": {
    "gn:admin1_code":"26.0",
    "gn:asciiname":"Sitokir",
    "gn:country_code":"ID",
    "gn:dem":918,
    "gn:feature_class":"P",
    "gn:feature_code":"PPL",
    "gn:name":"Sitokir",
    "gn:population":0,
    "gn:timezone":"Asia/Jakarta",
    "iso:country":"ID",
    "name:ind_x_preferred":[
        "Sitokir"
    ],
    "name:und_x_variant":[
        "Sinabono"
    ],
    "wof:lang_x_official":[
        "ind"
    ],
    "wof:lang_x_spoken":[
        "ind",
        "eng"
    ],
    "wof:name":"Sitokir",
    "wof:placetype":"locality"
},
  "geometry": {"coordinates":[98.69240000000001,2.6929],"type":"Point"}
}