{
  "type": "Feature",
  "properties": {
    "gn:admin1_code":"17.0",
    "gn:asciiname":"Karangbugis",
    "gn:country_code":"ID",
    "gn:dem":16,
    "gn:feature_class":"P",
    "gn:feature_code":"PPLA4",
    "gn:name":"Karangbugis",
    "gn:population":0,
    "gn:timezone":"Asia/Makassar",
    "iso:country":"ID",
    "name:ind_x_preferred":[
        "Karangbugis"
    ],
    "name:und_x_variant":[
        "Boegis",
        "Bugis"
    ],
    "wof:lang_x_official":[
        "ind"
    ],
    "wof:lang_x_spoken":[
        "ind",
        "eng"
    ],
    "wof:name":"Karangbugis",
    "wof:placetype":"locality"
},
  "geometry": {"coordinates":[117.42189999999999,-8.4966],"type":"Point"}
}