{
  "type": "Feature",
  "properties": {
    "gn:country":"ID",
    "gn:fcode":"ADM4",
    "gn:pop":0,
    "iso:country":"ID",
    "name:ind_x_preferred":[
        "Kelurahan Bangka"
    ],
    "name:unk_x_variant":[
        "Bangka"
    ],
    "qs:name":"Kelurahan Bangka",
    "qs:photos_9r":0,
    "qs:photos_sr":0,
    "qs:pop_sr":"0",
    "wd:wordcount":131,
    "wof:name":"Kelurahan Bangka",
    "wof:placetype":"localadmin",
    "wof:population":0
},
  "geometry": {"coordinates":[106.8186,-6.2654],"type":"Point"}
}