{
  "type": "Feature",
  "properties": {
    "gn:country":"ID",
    "gn:fcode":"PPL",
    "gn:pop":0,
    "iso:country":"ID",
    "name:ind_x_preferred":[
        "Tropodo"
    ],
    "qs:name":"Tropodo",
    "qs:name_adm0":"Indonesia",
    "qs:name_adm1":"Jawa Timur",
    "qs:photos_9k":1,
    "qs:photos_9r":1,
    "qs:photos_all":3,
    "qs:photos_sr":0,
    "qs:placetype":"Town",
    "qs:pop_sr":"0",
    "wof:name":"Tropodo",
    "wof:placetype":"locality",
    "wof:population":0
},
  "geometry": {"coordinates":[112.57361,-7.4275],"type":"Point"}
}