{
  "type": "Feature",
  "properties": {
    "gn:admin1_code":"8.0",
    "gn:asciiname":"Bobo",
    "gn:country_code":"ID",
    "gn:dem":9,
    "gn:feature_class":"P",
    "gn:feature_code":"PPL",
    "gn:name":"Bobo",
    "gn:population":0,
    "gn:timezone":"Asia/Jakarta",
    "iso:country":"ID",
    "name:ceb_x_preferred":[
        "Bobo"
    ],
    "name:deu_x_preferred":[
        "Bobo"
    ],
    "name:fin_x_preferred":[
        "Bobo"
    ],
    "name:fra_x_preferred":[
        "Bobo"
    ],
    "name:hun_x_preferred":[
        "Bobo"
    ],
    "name:ind_x_preferred":[
        "Bobo"
    ],
    "name:ita_x_preferred":[
        "Bobo"
    ],
    "name:nld_x_preferred":[
        "Bobo"
    ],
    "name:pol_x_preferred":[
        "Bobo"
    ],
    "name:por_x_preferred":[
        "Bobo"
    ],
    "name:rus_x_preferred":[
        "\u0411\u043e\u0431\u043e"
    ],
    "name:spa_x_preferred":[
        "Bobo"
    ],
    "name:zho_x_preferred":[
        "Bobo"
    ],
    "wof:name":"Bobo",
    "wof:placetype":"locality"
},
  "geometry": {"coordinates":[115.6512,-7.0532],"type":"Point"}
}