{
  "type": "Feature",
  "properties": {
    "gn:admin1_code":"30",
    "gn:asciiname":"Espres",
    "gn:country_code":"ID",
    "gn:dem":10,
    "gn:feature_class":"P",
    "gn:feature_code":"PPL",
    "gn:name":"Espres",
    "gn:population":0,
    "gn:timezone":"Asia/Jakarta",
    "iso:country":"ID",
    "name:ind_x_preferred":[
        "Espres"
    ],
    "wof:name":"Espres",
    "wof:placetype":"locality"
},
  "geometry": {"coordinates":[107.76555999999999,-6.3225],"type":"Point"}
}