{
  "type": "Feature",
  "properties": {
    "gn:admin1_code":"30.0",
    "gn:asciiname":"Pasagi",
    "gn:country_code":"ID",
    "gn:dem":924,
    "gn:feature_class":"P",
    "gn:feature_code":"PPL",
    "gn:name":"Pasagi",
    "gn:population":0,
    "gn:timezone":"Asia/Jakarta",
    "iso:country":"ID",
    "name:ind_x_preferred":[
        "Pasagi"
    ],
    "wof:name":"Pasagi",
    "wof:placetype":"locality"
},
  "geometry": {"coordinates":[107.17700000000001,-7.0092],"type":"Point"}
}