{
  "type": "Feature",
  "properties": {
    "gn:admin1_code":"38.0",
    "gn:asciiname":"Dare",
    "gn:country_code":"ID",
    "gn:dem":17,
    "gn:feature_class":"P",
    "gn:feature_code":"PPL",
    "gn:name":"Dare",
    "gn:population":0,
    "gn:timezone":"Asia/Makassar",
    "iso:country":"ID",
    "name:ind_x_preferred":[
        "Dare"
    ],
    "wof:name":"Dare",
    "wof:placetype":"locality"
},
  "geometry": {"coordinates":[119.54349999999999,-3.72],"type":"Point"}
}