{
  "type": "Feature",
  "properties": {
    "gn:admin1_code":"34",
    "gn:asciiname":"Didingga",
    "gn:country_code":"ID",
    "gn:dem":15,
    "gn:feature_class":"P",
    "gn:feature_code":"PPL",
    "gn:name":"Didingga",
    "gn:population":0,
    "gn:timezone":"Asia/Makassar",
    "iso:country":"ID",
    "name:ind_x_preferred":[
        "Didingga"
    ],
    "wof:name":"Didingga",
    "wof:placetype":"locality"
},
  "geometry": {"coordinates":[122.21380000000001,0.9774],"type":"Point"}
}