{
  "type": "Feature",
  "properties": {
    "gn:admin1_code":"8.0",
    "gn:asciiname":"Flagen",
    "gn:country_code":"ID",
    "gn:dem":348,
    "gn:feature_class":"P",
    "gn:feature_code":"PPL",
    "gn:name":"Flagen",
    "gn:population":0,
    "gn:timezone":"Asia/Jakarta",
    "iso:country":"ID",
    "name:ind_x_preferred":[
        "Flagen"
    ],
    "wof:name":"Flagen",
    "wof:placetype":"locality"
},
  "geometry": {"coordinates":[111.512,-8.2934],"type":"Point"}
}