{
  "type": "Feature",
  "properties": {
    "gn:admin1_code":"8",
    "gn:asciiname":"Ngembes",
    "gn:country_code":"ID",
    "gn:dem":409,
    "gn:feature_class":"P",
    "gn:feature_code":"PPL",
    "gn:name":"Ngembes",
    "gn:population":0,
    "gn:timezone":"Asia/Jakarta",
    "iso:country":"ID",
    "name:ind_x_preferred":[
        "Ngembes"
    ],
    "wof:name":"Ngembes",
    "wof:placetype":"locality"
},
  "geometry": {"coordinates":[113.13639999999999,-7.9015],"type":"Point"}
}