{
  "type": "Feature",
  "properties": {
    "gn:admin1_code":"7.0",
    "gn:asciiname":"Bugelsari",
    "gn:country_code":"ID",
    "gn:dem":27,
    "gn:feature_class":"P",
    "gn:feature_code":"PPL",
    "gn:name":"Bugelsari",
    "gn:population":0,
    "gn:timezone":"Asia/Jakarta",
    "iso:country":"ID",
    "name:ind_x_preferred":[
        "Bugelsari"
    ],
    "wof:name":"Bugelsari",
    "wof:placetype":"locality"
},
  "geometry": {"coordinates":[108.77849999999999,-7.3065],"type":"Point"}
}