{
  "type": "Feature",
  "properties": {
    "gn:admin1_code":"18",
    "gn:asciiname":"Rembong",
    "gn:country_code":"ID",
    "gn:dem":610,
    "gn:feature_class":"P",
    "gn:feature_code":"PPL",
    "gn:name":"Rembong",
    "gn:population":0,
    "gn:timezone":"Asia/Makassar",
    "iso:country":"ID",
    "name:ind_x_preferred":[
        "Rembong"
    ],
    "wof:name":"Rembong",
    "wof:placetype":"locality"
},
  "geometry": {"coordinates":[120.36020000000001,-8.5342],"type":"Point"}
}