{
  "type": "Feature",
  "properties": {
    "gn:admin1_code":"7",
    "gn:asciiname":"Pengineban",
    "gn:country_code":"ID",
    "gn:dem":101,
    "gn:feature_class":"P",
    "gn:feature_code":"PPL",
    "gn:name":"Pengineban",
    "gn:population":0,
    "gn:timezone":"Asia/Jakarta",
    "iso:country":"ID",
    "name:ind_x_preferred":[
        "Pengineban"
    ],
    "wof:name":"Pengineban",
    "wof:placetype":"locality"
},
  "geometry": {"coordinates":[109.1275,-7.0366],"type":"Point"}
}