{
  "type": "Feature",
  "properties": {
    "gn:admin1_code":"8.0",
    "gn:asciiname":"Berek",
    "gn:country_code":"ID",
    "gn:dem":19,
    "gn:feature_class":"P",
    "gn:feature_code":"PPL",
    "gn:name":"Berek",
    "gn:population":0,
    "gn:timezone":"Asia/Jakarta",
    "iso:country":"ID",
    "name:bos_x_preferred":[
        "Berek"
    ],
    "name:ceb_x_preferred":[
        "Berek"
    ],
    "name:deu_x_preferred":[
        "Berek"
    ],
    "name:fra_x_preferred":[
        "Berek"
    ],
    "name:hrv_x_preferred":[
        "Berek"
    ],
    "name:hun_x_preferred":[
        "Berek"
    ],
    "name:ind_x_preferred":[
        "Berek"
    ],
    "name:slv_x_preferred":[
        "Berek"
    ],
    "name:srp_x_preferred":[
        "\u0411\u0435\u0440\u0435\u043a"
    ],
    "name:swe_x_preferred":[
        "Berek"
    ],
    "wof:name":"Berek",
    "wof:placetype":"locality"
},
  "geometry": {"coordinates":[111.98618999999999,-7.14719],"type":"Point"}
}