{
  "type": "Feature",
  "properties": {
    "gn:admin1_code":"7.0",
    "gn:asciiname":"Meletan",
    "gn:country_code":"ID",
    "gn:dem":113,
    "gn:feature_class":"P",
    "gn:feature_code":"PPL",
    "gn:name":"Meletan",
    "gn:population":0,
    "gn:timezone":"Asia/Jakarta",
    "iso:country":"ID",
    "wof:name":"Meletan",
    "wof:placetype":"locality"
},
  "geometry": {"coordinates":[110.81056,-7.51472],"type":"Point"}
}