{
  "type": "Feature",
  "properties": {
    "gn:admin1_code":"18",
    "gn:asciiname":"Wolomoni",
    "gn:country_code":"ID",
    "gn:dem":733,
    "gn:feature_class":"P",
    "gn:feature_code":"PPLA4",
    "gn:name":"Wolomoni",
    "gn:population":0,
    "gn:timezone":"Asia/Makassar",
    "iso:country":"ID",
    "name:ind_x_preferred":[
        "Wolomoni"
    ],
    "wof:name":"Wolomoni",
    "wof:placetype":"locality"
},
  "geometry": {"coordinates":[121.7445,-8.7433],"type":"Point"}
}