{
  "type": "Feature",
  "properties": {
    "gn:admin1_code":"8.0",
    "gn:asciiname":"Bedahan",
    "gn:country_code":"ID",
    "gn:dem":27,
    "gn:feature_class":"P",
    "gn:feature_code":"PPL",
    "gn:name":"Bedahan",
    "gn:population":0,
    "gn:timezone":"Asia/Jakarta",
    "iso:country":"ID",
    "name:ind_x_preferred":[
        "Bedahan"
    ],
    "wof:name":"Bedahan",
    "wof:placetype":"locality"
},
  "geometry": {"coordinates":[111.6786,-7.1335],"type":"Point"}
}