{
  "type": "Feature",
  "properties": {
    "gn:admin1_code":"0.0",
    "gn:asciiname":"Mohungo",
    "gn:cc2":"ID",
    "gn:country_code":"ID",
    "gn:dem":25,
    "gn:feature_class":"P",
    "gn:feature_code":"PPL",
    "gn:name":"Mohungo",
    "gn:population":0,
    "gn:timezone":"Asia/Makassar",
    "iso:country":"ID",
    "name:und_x_variant":[
        "Mohoengo",
        "Mohungo"
    ],
    "wof:name":"Mohungo",
    "wof:placetype":"locality"
},
  "geometry": {"coordinates":[122.34999999999999,0.55],"type":"Point"}
}