{
  "type": "Feature",
  "properties": {
    "gn:country":"ID",
    "gn:fcode":"PPL",
    "gn:pop":0,
    "iso:country":"ID",
    "name:ind_x_preferred":[
        "Takalala"
    ],
    "qs:name":"Takalala",
    "qs:name_adm0":"Indonesia",
    "qs:name_adm1":"Sulawesi Selatan",
    "qs:photos_9r":0,
    "qs:photos_sr":0,
    "qs:placetype":"Town",
    "qs:pop_sr":"0",
    "wof:name":"Takalala",
    "wof:placetype":"locality",
    "wof:population":0
},
  "geometry": {"coordinates":[119.95050000000001,-4.4533],"type":"Point"}
}