{
  "type": "Feature",
  "properties": {
    "gn:admin1_code":"7.0",
    "gn:asciiname":"Sarwodadi",
    "gn:country_code":"ID",
    "gn:dem":35,
    "gn:feature_class":"P",
    "gn:feature_code":"PPL",
    "gn:name":"Sarwodadi",
    "gn:population":0,
    "gn:timezone":"Asia/Jakarta",
    "iso:country":"ID",
    "name:ind_x_preferred":[
        "Sarwodadi"
    ],
    "wof:name":"Sarwodadi",
    "wof:placetype":"locality"
},
  "geometry": {"coordinates":[109.65778,-7.635],"type":"Point"}
}