{
  "type": "Feature",
  "properties": {
    "gn:admin1_code":"8",
    "gn:asciiname":"Purwojati",
    "gn:country_code":"ID",
    "gn:dem":140,
    "gn:feature_class":"P",
    "gn:feature_code":"PPL",
    "gn:name":"Purwojati",
    "gn:population":0,
    "gn:timezone":"Asia/Jakarta",
    "iso:country":"ID",
    "name:ind_x_preferred":[
        "Purwojati"
    ],
    "wof:name":"Purwojati",
    "wof:placetype":"locality"
},
  "geometry": {"coordinates":[111.55549999999999,-7.7294],"type":"Point"}
}