{
  "type": "Feature",
  "properties": {
    "gn:admin1_code":"7",
    "gn:asciiname":"Bengkelo",
    "gn:country_code":"ID",
    "gn:dem":18,
    "gn:feature_class":"P",
    "gn:feature_code":"PPL",
    "gn:name":"Bengkelo",
    "gn:population":0,
    "gn:timezone":"Asia/Jakarta",
    "iso:country":"ID",
    "name:ind_x_preferred":[
        "Bengkelo"
    ],
    "wof:name":"Bengkelo",
    "wof:placetype":"locality"
},
  "geometry": {"coordinates":[110.17700000000001,-6.9623],"type":"Point"}
}