{
  "type": "Feature",
  "properties": {
    "gn:admin1_code":"7.0",
    "gn:asciiname":"Jabung",
    "gn:country_code":"ID",
    "gn:dem":88,
    "gn:feature_class":"P",
    "gn:feature_code":"PPL",
    "gn:name":"Jabung",
    "gn:population":0,
    "gn:timezone":"Asia/Jakarta",
    "iso:country":"ID",
    "name:ind_x_preferred":[
        "Candi Jabung"
    ],
    "name:jav_x_preferred":[
        "Candhi Jabung"
    ],
    "wof:name":"Jabung",
    "wof:placetype":"locality"
},
  "geometry": {"coordinates":[110.88722,-7.46222],"type":"Point"}
}