{
  "type": "Feature",
  "properties": {
    "gn:admin1_code":"17.0",
    "gn:asciiname":"Dorotoi",
    "gn:country_code":"ID",
    "gn:dem":139,
    "gn:feature_class":"P",
    "gn:feature_code":"PPL",
    "gn:name":"Dorotoi",
    "gn:population":0,
    "gn:timezone":"Asia/Makassar",
    "iso:country":"ID",
    "name:ind_x_preferred":[
        "Dorotoi"
    ],
    "wof:name":"Dorotoi",
    "wof:placetype":"locality"
},
  "geometry": {"coordinates":[118.24809999999999,-8.5656],"type":"Point"}
}