{
  "type": "Feature",
  "properties": {
    "gn:admin1_code":"8",
    "gn:asciiname":"Kepanasan",
    "gn:country_code":"ID",
    "gn:dem":17,
    "gn:feature_class":"P",
    "gn:feature_code":"PPL",
    "gn:name":"Kepanasan",
    "gn:population":0,
    "gn:timezone":"Asia/Jakarta",
    "iso:country":"ID",
    "name:ind_x_preferred":[
        "Kepanasan"
    ],
    "wof:name":"Kepanasan",
    "wof:placetype":"locality"
},
  "geometry": {"coordinates":[112.12560000000001,-7.1195],"type":"Point"}
}