{
  "type": "Feature",
  "properties": {
    "gn:admin1_code":"7",
    "gn:asciiname":"Selento",
    "gn:country_code":"ID",
    "gn:dem":202,
    "gn:feature_class":"P",
    "gn:feature_code":"PPL",
    "gn:name":"Selento",
    "gn:population":0,
    "gn:timezone":"Asia/Jakarta",
    "iso:country":"ID",
    "name:ind_x_preferred":[
        "Selento"
    ],
    "wof:name":"Selento",
    "wof:placetype":"locality"
},
  "geometry": {"coordinates":[110.19361000000001,-7.14639],"type":"Point"}
}