{
  "type": "Feature",
  "properties": {
    "gn:admin1_code":"08",
    "gn:asciiname":"Kapurono",
    "gn:country_code":"ID",
    "gn:dem":635,
    "gn:feature_class":"P",
    "gn:feature_code":"PPL",
    "gn:name":"Kapurono",
    "gn:population":0,
    "gn:timezone":"Asia/Jakarta",
    "iso:country":"ID",
    "name:ind_x_preferred":[
        "Kapurono"
    ],
    "wof:name":"Kapurono",
    "wof:placetype":"locality"
},
  "geometry": {"coordinates":[112.5407,-8.0291],"type":"Point"}
}