{
  "type": "Feature",
  "properties": {
    "gn:admin1_code":"7.0",
    "gn:asciiname":"Randegan",
    "gn:country_code":"ID",
    "gn:dem":169,
    "gn:feature_class":"P",
    "gn:feature_code":"PPL",
    "gn:name":"Randegan",
    "gn:population":0,
    "gn:timezone":"Asia/Jakarta",
    "iso:country":"ID",
    "name:ind_x_preferred":[
        "Randegan"
    ],
    "wof:name":"Randegan",
    "wof:placetype":"locality"
},
  "geometry": {"coordinates":[109.26222,-7.37583],"type":"Point"}
}