{
  "type": "Feature",
  "properties": {
    "gn:admin1_code":"26",
    "gn:asciiname":"Gunung Seribu Pasar",
    "gn:country_code":"ID",
    "gn:dem":652,
    "gn:feature_class":"P",
    "gn:feature_code":"PPL",
    "gn:name":"Gunung Seribu Pasar",
    "gn:population":0,
    "gn:timezone":"Asia/Jakarta",
    "iso:country":"ID",
    "name:ind_x_preferred":[
        "Gunung Seribu Pasar"
    ],
    "wof:name":"Gunung Seribu Pasar",
    "wof:placetype":"locality"
},
  "geometry": {"coordinates":[98.70050000000001,3.114],"type":"Point"}
}