{
  "type": "Feature",
  "properties": {
    "gn:admin1_code":"38",
    "gn:asciiname":"Tombangbai",
    "gn:country_code":"ID",
    "gn:dem":1702,
    "gn:feature_class":"P",
    "gn:feature_code":"PPL",
    "gn:name":"Tombangbai",
    "gn:population":0,
    "gn:timezone":"Asia/Makassar",
    "iso:country":"ID",
    "name:ind_x_preferred":[
        "Tombangbai"
    ],
    "wof:name":"Tombangbai",
    "wof:placetype":"locality"
},
  "geometry": {"coordinates":[119.77200000000001,-3.2385],"type":"Point"}
}