{
  "type": "Feature",
  "properties": {
    "gn:admin1_code":"7.0",
    "gn:asciiname":"Karanganyar",
    "gn:country_code":"ID",
    "gn:dem":115,
    "gn:feature_class":"P",
    "gn:feature_code":"PPL",
    "gn:name":"Karanganyar",
    "gn:population":0,
    "gn:timezone":"Asia/Jakarta",
    "iso:country":"ID",
    "name:ceb_x_preferred":[
        "Karanganyar"
    ],
    "name:ind_x_preferred":[
        "Karanganyar"
    ],
    "name:jav_x_preferred":[
        "Karanganyar"
    ],
    "name:nld_x_preferred":[
        "Karanganyar"
    ],
    "name:swe_x_preferred":[
        "Karanganyar"
    ],
    "wof:name":"Karanganyar",
    "wof:placetype":"locality"
},
  "geometry": {"coordinates":[110.76917,-7.80139],"type":"Point"}
}