{
  "type": "Feature",
  "properties": {
    "gn:admin1_code":"7",
    "gn:asciiname":"Tembiring",
    "gn:country_code":"ID",
    "gn:dem":8,
    "gn:feature_class":"P",
    "gn:feature_code":"PPL",
    "gn:name":"Tembiring",
    "gn:population":0,
    "gn:timezone":"Asia/Jakarta",
    "iso:country":"ID",
    "name:ind_x_preferred":[
        "Tembiring"
    ],
    "wof:name":"Tembiring",
    "wof:placetype":"locality"
},
  "geometry": {"coordinates":[110.6396,-6.9015],"type":"Point"}
}