{
  "type": "Feature",
  "properties": {
    "gn:admin1_code":"30.0",
    "gn:asciiname":"Dado",
    "gn:country_code":"ID",
    "gn:dem":1011,
    "gn:feature_class":"P",
    "gn:feature_code":"PPL",
    "gn:name":"Dado",
    "gn:population":0,
    "gn:timezone":"Asia/Jakarta",
    "iso:country":"ID",
    "name:ceb_x_preferred":[
        "Dado"
    ],
    "name:deu_x_preferred":[
        "Dado"
    ],
    "name:fas_x_preferred":[
        "\u062f\u0627\u062f\u0648"
    ],
    "name:ind_x_preferred":[
        "Dado"
    ],
    "name:ita_x_preferred":[
        "Dado"
    ],
    "name:por_x_preferred":[
        "Dado"
    ],
    "name:spa_x_preferred":[
        "Dado"
    ],
    "name:swe_x_preferred":[
        "Dado"
    ],
    "wof:name":"Dado",
    "wof:placetype":"locality"
},
  "geometry": {"coordinates":[107.86969999999999,-7.4079],"type":"Point"}
}