{
  "type": "Feature",
  "properties": {
    "gn:admin1_code":"38",
    "gn:asciiname":"Gattareng",
    "gn:country_code":"ID",
    "gn:dem":78,
    "gn:feature_class":"P",
    "gn:feature_code":"PPL",
    "gn:name":"Gattareng",
    "gn:population":0,
    "gn:timezone":"Asia/Makassar",
    "iso:country":"ID",
    "name:ind_x_preferred":[
        "Gattareng"
    ],
    "wof:name":"Gattareng",
    "wof:placetype":"locality"
},
  "geometry": {"coordinates":[120.17910000000001,-5.008],"type":"Point"}
}