{
  "type": "Feature",
  "properties": {
    "gn:admin1_code":"22.0",
    "gn:asciiname":"Woipundi",
    "gn:country_code":"ID",
    "gn:dem":16,
    "gn:feature_class":"P",
    "gn:feature_code":"PPL",
    "gn:name":"Woipundi",
    "gn:population":0,
    "gn:timezone":"Asia/Makassar",
    "iso:country":"ID",
    "name:ind_x_preferred":[
        "Woipundi"
    ],
    "wof:name":"Woipundi",
    "wof:placetype":"locality"
},
  "geometry": {"coordinates":[121.2627,-3.8197],"type":"Point"}
}