{
  "type": "Feature",
  "properties": {
    "gn:admin1_code":"14",
    "gn:asciiname":"Tende",
    "gn:country_code":"ID",
    "gn:dem":113,
    "gn:feature_class":"P",
    "gn:feature_code":"PPL",
    "gn:name":"Tende",
    "gn:population":0,
    "gn:timezone":"Asia/Makassar",
    "iso:country":"ID",
    "name:ara_x_preferred":[
        "\u062a\u064a\u0646\u062f"
    ],
    "name:bug_x_preferred":[
        "Tende"
    ],
    "name:bul_x_preferred":[
        "\u0422\u0430\u043d\u0434"
    ],
    "name:cat_x_preferred":[
        "Tenda"
    ],
    "name:ceb_x_preferred":[
        "Tende"
    ],
    "name:deu_x_preferred":[
        "Tende"
    ],
    "name:epo_x_preferred":[
        "Tenda"
    ],
    "name:est_x_preferred":[
        "Tende'i vald"
    ],
    "name:eus_x_preferred":[
        "Tenda"
    ],
    "name:fas_x_preferred":[
        "\u062a\u0646\u062f"
    ],
    "name:fra_x_preferred":[
        "Tende"
    ],
    "name:hun_x_preferred":[
        "Tende"
    ],
    "name:hye_x_preferred":[
        "\u054f\u0561\u0576\u0564"
    ],
    "name:ind_x_preferred":[
        "Tende"
    ],
    "name:ita_x_preferred":[
        "Tenda"
    ],
    "name:jpn_x_preferred":[
        "\u30bf\u30f3\u30c9"
    ],
    "name:kat_x_preferred":[
        "\u10e2\u10d4\u10dc\u10d3\u10d8"
    ],
    "name:lat_x_preferred":[
        "Tenda"
    ],
    "name:lij_x_preferred":[
        "Tenda"
    ],
    "name:msa_x_preferred":[
        "Tende"
    ],
    "name:nld_x_preferred":[
        "Tende"
    ],
    "name:oci_x_preferred":[
        "Tenda"
    ],
    "name:pms_x_preferred":[
        "Tenda"
    ],
    "name:pol_x_preferred":[
        "Tende"
    ],
    "name:por_x_preferred":[
        "Tende"
    ],
    "name:ron_x_preferred":[
        "Tende"
    ],
    "name:rus_x_preferred":[
        "\u0422\u0430\u043d\u0434"
    ],
    "name:slk_x_preferred":[
        "Tende"
    ],
    "name:slv_x_preferred":[
        "Tende"
    ],
    "name:spa_x_preferred":[
        "Tende"
    ],
    "name:sqi_x_preferred":[
        "Tende"
    ],
    "name:swe_x_preferred":[
        "Tende"
    ],
    "name:tur_x_preferred":[
        "Tende"
    ],
    "name:ukr_x_preferred":[
        "\u0422\u0430\u043d\u0434"
    ],
    "name:vie_x_preferred":[
        "Tende"
    ],
    "name:vol_x_preferred":[
        "Tende"
    ],
    "name:war_x_preferred":[
        "Tende"
    ],
    "wof:lang_x_official":[
        "ind"
    ],
    "wof:lang_x_spoken":[
        "ind",
        "eng"
    ],
    "wof:name":"Tende",
    "wof:placetype":"locality"
},
  "geometry": {"coordinates":[115.75539999999999,-1.0094],"type":"Point"}
}