{
  "type": "Feature",
  "properties": {
    "gn:admin1_code":"8.0",
    "gn:asciiname":"Ngampir",
    "gn:country_code":"ID",
    "gn:dem":221,
    "gn:feature_class":"P",
    "gn:feature_code":"PPL",
    "gn:name":"Ngampir",
    "gn:population":0,
    "gn:timezone":"Asia/Jakarta",
    "iso:country":"ID",
    "name:ind_x_preferred":[
        "Ngampir"
    ],
    "wof:name":"Ngampir",
    "wof:placetype":"locality"
},
  "geometry": {"coordinates":[112.66849999999999,-7.6421],"type":"Point"}
}