{
  "type": "Feature",
  "properties": {
    "gn:admin1_code":"30",
    "gn:asciiname":"Situ",
    "gn:country_code":"ID",
    "gn:dem":370,
    "gn:feature_class":"P",
    "gn:feature_code":"PPL",
    "gn:name":"Situ",
    "gn:population":0,
    "gn:timezone":"Asia/Jakarta",
    "iso:country":"ID",
    "name:ceb_x_preferred":[
        "Situ"
    ],
    "name:ind_x_preferred":[
        "Situ"
    ],
    "name:swe_x_preferred":[
        "Situ"
    ],
    "wof:name":"Situ",
    "wof:placetype":"locality"
},
  "geometry": {"coordinates":[107.22917,-6.56917],"type":"Point"}
}