{
  "type": "Feature",
  "properties": {
    "gn:admin1_code":"08",
    "gn:asciiname":"Karangan",
    "gn:country_code":"ID",
    "gn:dem":702,
    "gn:feature_class":"P",
    "gn:feature_code":"PPL",
    "gn:name":"Karangan",
    "gn:population":0,
    "gn:timezone":"Asia/Jakarta",
    "iso:country":"ID",
    "name:ceb_x_preferred":[
        "Karangan"
    ],
    "name:ind_x_preferred":[
        "Karangan"
    ],
    "name:nld_x_preferred":[
        "Karangan"
    ],
    "name:swe_x_preferred":[
        "Karangan"
    ],
    "wof:name":"Karangan",
    "wof:placetype":"locality"
},
  "geometry": {"coordinates":[112.5822,-7.8781],"type":"Point"}
}