{
  "type": "Feature",
  "properties": {
    "gn:admin1_code":"18.0",
    "gn:asciiname":"Noebana",
    "gn:country_code":"ID",
    "gn:dem":435,
    "gn:feature_class":"P",
    "gn:feature_code":"PPLA4",
    "gn:name":"Noebana",
    "gn:population":0,
    "gn:timezone":"Asia/Makassar",
    "iso:country":"ID",
    "name:ind_x_preferred":[
        "Noebana"
    ],
    "wof:name":"Noebana",
    "wof:placetype":"locality"
},
  "geometry": {"coordinates":[124.6575,-9.7724],"type":"Point"}
}