{
  "type": "Feature",
  "properties": {
    "gn:admin1_code":"21.0",
    "gn:asciiname":"Tambu",
    "gn:country_code":"ID",
    "gn:dem":6,
    "gn:feature_class":"P",
    "gn:feature_code":"PPL",
    "gn:name":"Tambu",
    "gn:population":0,
    "gn:timezone":"Asia/Makassar",
    "iso:country":"ID",
    "name:ceb_x_preferred":[
        "Tambu"
    ],
    "name:fin_x_preferred":[
        "Tambu"
    ],
    "name:ind_x_preferred":[
        "Tambu"
    ],
    "name:nld_x_preferred":[
        "Tambu"
    ],
    "name:slk_x_preferred":[
        "Tambu"
    ],
    "name:slv_x_preferred":[
        "Tambu"
    ],
    "name:swe_x_preferred":[
        "Tambu"
    ],
    "wof:name":"Tambu",
    "wof:placetype":"locality"
},
  "geometry": {"coordinates":[120.52160000000001,-1.0394],"type":"Point"}
}