{
  "type": "Feature",
  "properties": {
    "gn:admin1_code":"29.0",
    "gn:asciiname":"Kawato",
    "gn:country_code":"ID",
    "gn:dem":5,
    "gn:feature_class":"P",
    "gn:feature_code":"PPL",
    "gn:name":"Kawato",
    "gn:population":0,
    "gn:timezone":"Asia/Jayapura",
    "iso:country":"ID",
    "name:ind_x_preferred":[
        "Kawato"
    ],
    "name:und_x_variant":[
        "Kawaloe",
        "Kawalu"
    ],
    "wof:name":"Kawato",
    "wof:placetype":"locality"
},
  "geometry": {"coordinates":[124.56359999999999,-1.9993],"type":"Point"}
}