{
  "type": "Feature",
  "properties": {
    "gn:admin1_code":"8.0",
    "gn:asciiname":"Klitih",
    "gn:country_code":"ID",
    "gn:dem":114,
    "gn:feature_class":"P",
    "gn:feature_code":"PPL",
    "gn:name":"Klitih",
    "gn:population":0,
    "gn:timezone":"Asia/Jakarta",
    "iso:country":"ID",
    "name:ind_x_preferred":[
        "Klitih"
    ],
    "wof:name":"Klitih",
    "wof:placetype":"locality"
},
  "geometry": {"coordinates":[114.24469999999999,-8.3498],"type":"Point"}
}