{
  "type": "Feature",
  "properties": {
    "gn:admin1_code":"30",
    "gn:asciiname":"Gunungsari Selatan",
    "gn:country_code":"ID",
    "gn:dem":47,
    "gn:feature_class":"P",
    "gn:feature_code":"PPL",
    "gn:name":"Gunungsari Selatan",
    "gn:population":0,
    "gn:timezone":"Asia/Jakarta",
    "iso:country":"ID",
    "name:ind_x_preferred":[
        "Gunungsari Selatan"
    ],
    "wof:name":"Gunungsari Selatan",
    "wof:placetype":"locality"
},
  "geometry": {"coordinates":[108.23083,-6.75444],"type":"Point"}
}