{
  "type": "Feature",
  "properties": {
    "gn:admin1_code":"8",
    "gn:asciiname":"Denok Wetan",
    "gn:country_code":"ID",
    "gn:dem":32,
    "gn:feature_class":"P",
    "gn:feature_code":"PPL",
    "gn:name":"Denok Wetan",
    "gn:population":0,
    "gn:timezone":"Asia/Jakarta",
    "iso:country":"ID",
    "name:ind_x_preferred":[
        "Denok Wetan"
    ],
    "wof:name":"Denok Wetan",
    "wof:placetype":"locality"
},
  "geometry": {"coordinates":[113.2693,-8.1507],"type":"Point"}
}