{
  "type": "Feature",
  "properties": {
    "gn:admin1_code":"37.0",
    "gn:asciiname":"Pondokkayuara",
    "gn:country_code":"ID",
    "gn:dem":26,
    "gn:feature_class":"P",
    "gn:feature_code":"PPL",
    "gn:name":"Pondokkayuara",
    "gn:population":0,
    "gn:timezone":"Asia/Jakarta",
    "iso:country":"ID",
    "name:ind_x_preferred":[
        "Pondokkayuara"
    ],
    "wof:name":"Pondokkayuara",
    "wof:placetype":"locality"
},
  "geometry": {"coordinates":[102.33651,-0.06096],"type":"Point"}
}