{
  "type": "Feature",
  "properties": {
    "gn:admin1_code":"18",
    "gn:asciiname":"Wololele B",
    "gn:country_code":"ID",
    "gn:dem":383,
    "gn:feature_class":"P",
    "gn:feature_code":"PPLA4",
    "gn:name":"Wololele B",
    "gn:population":0,
    "gn:timezone":"Asia/Makassar",
    "iso:country":"ID",
    "name:ind_x_preferred":[
        "Wololele B"
    ],
    "wof:lang_x_official":[
        "ind"
    ],
    "wof:lang_x_spoken":[
        "ind",
        "eng"
    ],
    "wof:name":"Wololele B",
    "wof:placetype":"locality"
},
  "geometry": {"coordinates":[121.8929,-8.7624],"type":"Point"}
}