{
  "type": "Feature",
  "properties": {
    "gn:admin1_code":"18.0",
    "gn:asciiname":"Niondoa",
    "gn:country_code":"ID",
    "gn:dem":353,
    "gn:feature_class":"P",
    "gn:feature_code":"PPL",
    "gn:name":"Niondoa",
    "gn:population":0,
    "gn:timezone":"Asia/Makassar",
    "iso:country":"ID",
    "name:ind_x_preferred":[
        "Niondoa"
    ],
    "wof:name":"Niondoa",
    "wof:placetype":"locality"
},
  "geometry": {"coordinates":[121.29510000000001,-8.881],"type":"Point"}
}