{
  "type": "Feature",
  "properties": {
    "gn:admin1_code":"38.0",
    "gn:asciiname":"Langae",
    "gn:country_code":"ID",
    "gn:dem":915,
    "gn:feature_class":"P",
    "gn:feature_code":"PPL",
    "gn:name":"Langae",
    "gn:population":0,
    "gn:timezone":"Asia/Makassar",
    "iso:country":"ID",
    "name:ind_x_preferred":[
        "Langae"
    ],
    "wof:name":"Langae",
    "wof:placetype":"locality"
},
  "geometry": {"coordinates":[119.92700000000001,-3.4388],"type":"Point"}
}