{
  "type": "Feature",
  "properties": {
    "gn:admin1_code":"35.0",
    "gn:asciiname":"Simpangtiga",
    "gn:country_code":"ID",
    "gn:dem":37,
    "gn:feature_class":"P",
    "gn:feature_code":"PPL",
    "gn:name":"Simpangtiga",
    "gn:population":0,
    "gn:timezone":"Asia/Jakarta",
    "iso:country":"ID",
    "name:ind_x_preferred":[
        "Simpangtiga"
    ],
    "wof:name":"Simpangtiga",
    "wof:placetype":"locality"
},
  "geometry": {"coordinates":[107.90491000000002,-2.84294],"type":"Point"}
}