{
  "type": "Feature",
  "properties": {
    "gn:admin1_code":"33",
    "gn:asciiname":"Kelapadua",
    "gn:country_code":"ID",
    "gn:dem":27,
    "gn:feature_class":"P",
    "gn:feature_code":"PPL",
    "gn:name":"Kelapadua",
    "gn:population":0,
    "gn:timezone":"Asia/Jakarta",
    "iso:country":"ID",
    "name:ind_x_preferred":[
        "Kelapadua"
    ],
    "wof:name":"Kelapadua",
    "wof:placetype":"locality"
},
  "geometry": {"coordinates":[106.14830000000001,-6.1066],"type":"Point"}
}