{
  "type": "Feature",
  "properties": {
    "gn:admin1_code":"8",
    "gn:asciiname":"Ingasbatok",
    "gn:country_code":"ID",
    "gn:dem":70,
    "gn:feature_class":"P",
    "gn:feature_code":"PPL",
    "gn:name":"Ingasbatok",
    "gn:population":0,
    "gn:timezone":"Asia/Jakarta",
    "iso:country":"ID",
    "name:ind_x_preferred":[
        "Ingasbatok"
    ],
    "wof:name":"Ingasbatok",
    "wof:placetype":"locality"
},
  "geometry": {"coordinates":[111.21306,-7.35944],"type":"Point"}
}