{
  "type": "Feature",
  "properties": {
    "gn:admin1_code":"33.0",
    "gn:asciiname":"Paja",
    "gn:country_code":"ID",
    "gn:dem":82,
    "gn:feature_class":"P",
    "gn:feature_code":"PPL",
    "gn:name":"Paja",
    "gn:population":0,
    "gn:timezone":"Asia/Jakarta",
    "iso:country":"ID",
    "name:fas_x_preferred":[
        "\u067e\u0627\u062c\u0627"
    ],
    "name:glk_x_preferred":[
        "\u067e\u0627\u062c\u0627"
    ],
    "name:ind_x_preferred":[
        "Paja"
    ],
    "name:mzn_x_preferred":[
        "\u067e\u0627\u062c\u0627"
    ],
    "wof:name":"Paja",
    "wof:placetype":"locality"
},
  "geometry": {"coordinates":[106.0321,-6.4938],"type":"Point"}
}