{
  "type": "Feature",
  "properties": {
    "gn:admin1_code":"18.0",
    "gn:asciiname":"Poreleng",
    "gn:country_code":"ID",
    "gn:dem":850,
    "gn:feature_class":"P",
    "gn:feature_code":"PPL",
    "gn:name":"Poreleng",
    "gn:population":0,
    "gn:timezone":"Asia/Makassar",
    "iso:country":"ID",
    "name:ind_x_preferred":[
        "Poreleng"
    ],
    "wof:name":"Poreleng",
    "wof:placetype":"locality"
},
  "geometry": {"coordinates":[124.6309,-8.2456],"type":"Point"}
}