{
  "type": "Feature",
  "properties": {
    "gn:admin1_code":"30.0",
    "gn:asciiname":"Parungjagong",
    "gn:country_code":"ID",
    "gn:dem":146,
    "gn:feature_class":"P",
    "gn:feature_code":"PPL",
    "gn:name":"Parungjagong",
    "gn:population":0,
    "gn:timezone":"Asia/Jakarta",
    "iso:country":"ID",
    "name:ind_x_preferred":[
        "Parungjagong"
    ],
    "name:und_x_variant":[
        "Paroengdjagong"
    ],
    "wof:lang_x_official":[
        "ind"
    ],
    "wof:lang_x_spoken":[
        "ind",
        "eng"
    ],
    "wof:name":"Parungjagong",
    "wof:placetype":"locality"
},
  "geometry": {"coordinates":[108.18899999999999,-7.5237],"type":"Point"}
}