{
  "type": "Feature",
  "properties": {
    "gn:admin1_code":"1",
    "gn:asciiname":"Batin Wih Pongas",
    "gn:country_code":"ID",
    "gn:dem":1353,
    "gn:feature_class":"P",
    "gn:feature_code":"PPL",
    "gn:name":"Batin Wih Pongas",
    "gn:population":0,
    "gn:timezone":"Asia/Jakarta",
    "iso:country":"ID",
    "name:ind_x_preferred":[
        "Batin Wih Pongas"
    ],
    "wof:name":"Batin Wih Pongas",
    "wof:placetype":"locality"
},
  "geometry": {"coordinates":[96.8723,4.7113],"type":"Point"}
}