{
  "type": "Feature",
  "properties": {
    "gn:admin1_code":"22.0",
    "gn:asciiname":"Andinira",
    "gn:country_code":"ID",
    "gn:dem":38,
    "gn:feature_class":"P",
    "gn:feature_code":"PPL",
    "gn:name":"Andinira",
    "gn:population":0,
    "gn:timezone":"Asia/Makassar",
    "iso:country":"ID",
    "name:ind_x_preferred":[
        "Andinira"
    ],
    "wof:name":"Andinira",
    "wof:placetype":"locality"
},
  "geometry": {"coordinates":[122.20869999999999,-4.105],"type":"Point"}
}