{
  "type": "Feature",
  "properties": {
    "gn:admin1_code":"41",
    "gn:asciiname":"Lumandang",
    "gn:country_code":"ID",
    "gn:dem":11,
    "gn:feature_class":"P",
    "gn:feature_code":"PPL",
    "gn:name":"Lumandang",
    "gn:population":0,
    "gn:timezone":"Asia/Makassar",
    "iso:country":"ID",
    "name:ind_x_preferred":[
        "Lumandang"
    ],
    "wof:name":"Lumandang",
    "wof:placetype":"locality"
},
  "geometry": {"coordinates":[118.8355,-2.6392],"type":"Point"}
}