{
  "type": "Feature",
  "properties": {
    "gn:admin1_code":"38",
    "gn:asciiname":"Birakeke",
    "gn:country_code":"ID",
    "gn:dem":61,
    "gn:feature_class":"P",
    "gn:feature_code":"PPL",
    "gn:name":"Birakeke",
    "gn:population":0,
    "gn:timezone":"Asia/Makassar",
    "iso:country":"ID",
    "name:ind_x_preferred":[
        "Birakeke"
    ],
    "wof:name":"Birakeke",
    "wof:placetype":"locality"
},
  "geometry": {"coordinates":[120.4577,-5.5854],"type":"Point"}
}