{
  "type": "Feature",
  "properties": {
    "gn:admin1_code":"22",
    "gn:asciiname":"Latawe",
    "gn:country_code":"ID",
    "gn:dem":7,
    "gn:feature_class":"P",
    "gn:feature_code":"PPL",
    "gn:name":"Latawe",
    "gn:population":0,
    "gn:timezone":"Asia/Makassar",
    "iso:country":"ID",
    "name:ind_x_preferred":[
        "Latawe"
    ],
    "wof:name":"Latawe",
    "wof:placetype":"locality"
},
  "geometry": {"coordinates":[122.6032,-4.6449],"type":"Point"}
}