{
  "type": "Feature",
  "properties": {
    "gn:admin1_code":"17.0",
    "gn:asciiname":"Muer",
    "gn:country_code":"ID",
    "gn:dem":88,
    "gn:feature_class":"P",
    "gn:feature_code":"PPLA4",
    "gn:name":"Muer",
    "gn:population":0,
    "gn:timezone":"Asia/Makassar",
    "iso:country":"ID",
    "name:ind_x_preferred":[
        "Muer"
    ],
    "name:und_x_variant":[
        "Moer",
        "Mur"
    ],
    "wof:lang_x_official":[
        "ind"
    ],
    "wof:lang_x_spoken":[
        "ind",
        "eng"
    ],
    "wof:name":"Muer",
    "wof:placetype":"locality"
},
  "geometry": {"coordinates":[117.73050000000001,-8.749],"type":"Point"}
}