{
  "type": "Feature",
  "properties": {
    "gn:admin1_code":"33.0",
    "gn:asciiname":"Malingping Selatan",
    "gn:country_code":"ID",
    "gn:dem":107,
    "gn:feature_class":"P",
    "gn:feature_code":"PPL",
    "gn:name":"Malingping Selatan",
    "gn:population":0,
    "gn:timezone":"Asia/Jakarta",
    "iso:country":"ID",
    "name:ind_x_preferred":[
        "Malingping Selatan"
    ],
    "wof:name":"Malingping Selatan",
    "wof:placetype":"locality"
},
  "geometry": {"coordinates":[106.0308,-6.4257],"type":"Point"}
}