{
  "type": "Feature",
  "properties": {
    "gn:admin1_code":"8.0",
    "gn:asciiname":"Kaliwadung Kidul",
    "gn:country_code":"ID",
    "gn:dem":245,
    "gn:feature_class":"P",
    "gn:feature_code":"PPL",
    "gn:name":"Kaliwadung Kidul",
    "gn:population":0,
    "gn:timezone":"Asia/Jakarta",
    "iso:country":"ID",
    "name:ind_x_preferred":[
        "Kaliwadung Kidul"
    ],
    "wof:name":"Kaliwadung Kidul",
    "wof:placetype":"locality"
},
  "geometry": {"coordinates":[114.1103,-8.3297],"type":"Point"}
}