{
  "type": "Feature",
  "properties": {
    "gn:admin1_code":"26",
    "gn:asciiname":"Negerijahe",
    "gn:country_code":"ID",
    "gn:dem":574,
    "gn:feature_class":"P",
    "gn:feature_code":"PPL",
    "gn:name":"Negerijahe",
    "gn:population":0,
    "gn:timezone":"Asia/Jakarta",
    "iso:country":"ID",
    "name:ind_x_preferred":[
        "Negerijahe"
    ],
    "name:und_x_variant":[
        "Negeridjahe"
    ],
    "wof:name":"Negerijahe",
    "wof:placetype":"locality"
},
  "geometry": {"coordinates":[98.2145,3.1444],"type":"Point"}
}