{
  "type": "Feature",
  "properties": {
    "gn:admin1_code":"18.0",
    "gn:asciiname":"Baopukang",
    "gn:country_code":"ID",
    "gn:dem":14,
    "gn:feature_class":"P",
    "gn:feature_code":"PPLA4",
    "gn:name":"Baopukang",
    "gn:population":0,
    "gn:timezone":"Asia/Makassar",
    "iso:country":"ID",
    "name:ind_x_preferred":[
        "Baopukang"
    ],
    "wof:name":"Baopukang",
    "wof:placetype":"locality"
},
  "geometry": {"coordinates":[123.51860000000001,-8.308],"type":"Point"}
}