{
  "type": "Feature",
  "properties": {
    "gn:admin1_code":"0.0",
    "gn:asciiname":"Kamanapi",
    "gn:cc2":"ID",
    "gn:country_code":"ID",
    "gn:dem":36,
    "gn:feature_class":"P",
    "gn:feature_code":"PPL",
    "gn:name":"Kamanapi",
    "gn:population":0,
    "gn:timezone":"Asia/Jayapura",
    "iso:country":"ID",
    "name:und_x_variant":[
        "Kamenapi",
        "Kamanapi"
    ],
    "wof:name":"Kamanapi",
    "wof:placetype":"locality"
},
  "geometry": {"coordinates":[136.05000000000001,-1.83333],"type":"Point"}
}