{
  "type": "Feature",
  "properties": {
    "gn:admin1_code":"8.0",
    "gn:asciiname":"Kabuaran Utara",
    "gn:country_code":"ID",
    "gn:dem":434,
    "gn:feature_class":"P",
    "gn:feature_code":"PPL",
    "gn:name":"Kabuaran Utara",
    "gn:population":0,
    "gn:timezone":"Asia/Jakarta",
    "iso:country":"ID",
    "name:ind_x_preferred":[
        "Kabuaran Utara"
    ],
    "wof:name":"Kabuaran Utara",
    "wof:placetype":"locality"
},
  "geometry": {"coordinates":[113.7714,-7.9754],"type":"Point"}
}