{
  "type": "Feature",
  "properties": {
    "gn:admin1_code":"30",
    "gn:asciiname":"Babakandadi",
    "gn:country_code":"ID",
    "gn:dem":686,
    "gn:feature_class":"P",
    "gn:feature_code":"PPL",
    "gn:name":"Babakandadi",
    "gn:population":0,
    "gn:timezone":"Asia/Jakarta",
    "iso:country":"ID",
    "name:ind_x_preferred":[
        "Babakandadi"
    ],
    "wof:name":"Babakandadi",
    "wof:placetype":"locality"
},
  "geometry": {"coordinates":[107.60056000000002,-6.67833],"type":"Point"}
}