{
  "type": "Feature",
  "properties": {
    "gn:admin1_code":"39.0",
    "gn:asciiname":"Saukorem",
    "gn:country_code":"ID",
    "gn:dem":19,
    "gn:feature_class":"P",
    "gn:feature_code":"PPLA3",
    "gn:name":"Saukorem",
    "gn:population":0,
    "gn:timezone":"Asia/Jayapura",
    "iso:country":"ID",
    "name:und_x_variant":[
        "Saoekorem",
        "Saokorem",
        "Saukorem"
    ],
    "wof:lang_x_official":[
        "ind"
    ],
    "wof:lang_x_spoken":[
        "ind",
        "eng"
    ],
    "wof:name":"Saukorem",
    "wof:placetype":"locality"
},
  "geometry": {"coordinates":[133.15270000000001,-0.565],"type":"Point"}
}