{
  "type": "Feature",
  "properties": {
    "gn:admin1_code":"30.0",
    "gn:asciiname":"Cicadas",
    "gn:country_code":"ID",
    "gn:dem":872,
    "gn:feature_class":"P",
    "gn:feature_code":"PPL",
    "gn:name":"Cicadas",
    "gn:population":0,
    "gn:timezone":"Asia/Jakarta",
    "iso:country":"ID",
    "name:ind_x_preferred":[
        "Cicadas"
    ],
    "wof:name":"Cicadas",
    "wof:placetype":"locality"
},
  "geometry": {"coordinates":[107.968,-7.2202],"type":"Point"}
}