{
  "type": "Feature",
  "properties": {
    "gn:admin1_code":"30.0",
    "gn:asciiname":"Cimalingping",
    "gn:country_code":"ID",
    "gn:dem":1318,
    "gn:feature_class":"P",
    "gn:feature_code":"PPL",
    "gn:name":"Cimalingping",
    "gn:population":0,
    "gn:timezone":"Asia/Jakarta",
    "iso:country":"ID",
    "name:ind_x_preferred":[
        "Cimalingping"
    ],
    "wof:name":"Cimalingping",
    "wof:placetype":"locality"
},
  "geometry": {"coordinates":[107.81740000000001,-7.3043],"type":"Point"}
}