{
  "type": "Feature",
  "properties": {
    "gn:admin1_code":"8.0",
    "gn:asciiname":"Lungurduwur",
    "gn:country_code":"ID",
    "gn:dem":224,
    "gn:feature_class":"P",
    "gn:feature_code":"PPL",
    "gn:name":"Lungurduwur",
    "gn:population":0,
    "gn:timezone":"Asia/Jakarta",
    "iso:country":"ID",
    "name:ind_x_preferred":[
        "Lungurduwur"
    ],
    "wof:name":"Lungurduwur",
    "wof:placetype":"locality"
},
  "geometry": {"coordinates":[111.9654,-8.2407],"type":"Point"}
}