{
  "type": "Feature",
  "properties": {
    "gn:admin1_code":"30.0",
    "gn:asciiname":"Cocongkok",
    "gn:country_code":"ID",
    "gn:dem":265,
    "gn:feature_class":"P",
    "gn:feature_code":"PPL",
    "gn:name":"Cocongkok",
    "gn:population":0,
    "gn:timezone":"Asia/Jakarta",
    "iso:country":"ID",
    "name:ind_x_preferred":[
        "Cocongkok"
    ],
    "wof:name":"Cocongkok",
    "wof:placetype":"locality"
},
  "geometry": {"coordinates":[108.253,-7.5431],"type":"Point"}
}