{
  "type": "Feature",
  "properties": {
    "gn:admin1_code":"7",
    "gn:asciiname":"Pejagatan",
    "gn:country_code":"ID",
    "gn:dem":21,
    "gn:feature_class":"P",
    "gn:feature_code":"PPL",
    "gn:name":"Pejagatan",
    "gn:population":0,
    "gn:timezone":"Asia/Jakarta",
    "iso:country":"ID",
    "name:ind_x_preferred":[
        "Pejagatan"
    ],
    "wof:name":"Pejagatan",
    "wof:placetype":"locality"
},
  "geometry": {"coordinates":[109.76694000000001,-7.71111],"type":"Point"}
}