{
  "type": "Feature",
  "properties": {
    "gn:admin1_code":"22.0",
    "gn:asciiname":"Wakalambe",
    "gn:country_code":"ID",
    "gn:dem":14,
    "gn:feature_class":"P",
    "gn:feature_code":"PPL",
    "gn:name":"Wakalambe",
    "gn:population":0,
    "gn:timezone":"Asia/Makassar",
    "iso:country":"ID",
    "name:ind_x_preferred":[
        "Wakalambe"
    ],
    "name:und_x_variant":[
        "Wakolambe"
    ],
    "wof:name":"Wakalambe",
    "wof:placetype":"locality"
},
  "geometry": {"coordinates":[122.7445,-5.2574],"type":"Point"}
}