{
  "type": "Feature",
  "properties": {
    "gn:admin1_code":"30.0",
    "gn:asciiname":"Tambir",
    "gn:country_code":"ID",
    "gn:dem":487,
    "gn:feature_class":"P",
    "gn:feature_code":"PPL",
    "gn:name":"Tambir",
    "gn:population":0,
    "gn:timezone":"Asia/Jakarta",
    "iso:country":"ID",
    "name:ind_x_preferred":[
        "Tambir"
    ],
    "wof:name":"Tambir",
    "wof:placetype":"locality"
},
  "geometry": {"coordinates":[108.1104,-7.3198],"type":"Point"}
}