{
  "type": "Feature",
  "properties": {
    "gn:admin1_code":"38",
    "gn:asciiname":"Calurenge",
    "gn:country_code":"ID",
    "gn:dem":101,
    "gn:feature_class":"P",
    "gn:feature_code":"PPL",
    "gn:name":"Calurenge",
    "gn:population":0,
    "gn:timezone":"Asia/Makassar",
    "iso:country":"ID",
    "name:ind_x_preferred":[
        "Calurenge"
    ],
    "wof:name":"Calurenge",
    "wof:placetype":"locality"
},
  "geometry": {"coordinates":[120.01900000000001,-4.7216],"type":"Point"}
}