{
  "type": "Feature",
  "properties": {
    "gn:admin1_code":"40.0",
    "gn:asciiname":"Teluksenang",
    "gn:country_code":"ID",
    "gn:dem":12,
    "gn:feature_class":"P",
    "gn:feature_code":"PPL",
    "gn:name":"Teluksenang",
    "gn:population":0,
    "gn:timezone":"Asia/Jakarta",
    "iso:country":"ID",
    "name:ind_x_preferred":[
        "Teluksenang"
    ],
    "wof:name":"Teluksenang",
    "wof:placetype":"locality"
},
  "geometry": {"coordinates":[103.32647,1.0953],"type":"Point"}
}