{
  "type": "Feature",
  "properties": {
    "gn:admin1_code":"18.0",
    "gn:asciiname":"Laipori Dua",
    "gn:country_code":"ID",
    "gn:dem":11,
    "gn:feature_class":"P",
    "gn:feature_code":"PPL",
    "gn:name":"Laipori Dua",
    "gn:population":0,
    "gn:timezone":"Asia/Makassar",
    "iso:country":"ID",
    "name:ind_x_preferred":[
        "Laipori Dua"
    ],
    "wof:name":"Laipori Dua",
    "wof:placetype":"locality"
},
  "geometry": {"coordinates":[120.4727,-9.644],"type":"Point"}
}