{
  "type": "Feature",
  "properties": {
    "gn:admin1_code":"1",
    "gn:asciiname":"Kuala Kemuning",
    "gn:country_code":"ID",
    "gn:dem":33,
    "gn:feature_class":"P",
    "gn:feature_code":"PPL",
    "gn:name":"Kuala Kemuning",
    "gn:population":0,
    "gn:timezone":"Asia/Jakarta",
    "iso:country":"ID",
    "name:ind_x_preferred":[
        "Kuala Kemuning"
    ],
    "wof:name":"Kuala Kemuning",
    "wof:placetype":"locality"
},
  "geometry": {"coordinates":[99.61490000000001,2.7846],"type":"Point"}
}