{
  "type": "Feature",
  "properties": {
    "gn:admin1_code":"10.0",
    "gn:asciiname":"Kalimenur",
    "gn:cc2":"ID",
    "gn:country_code":"ID",
    "gn:dem":30,
    "gn:feature_class":"P",
    "gn:feature_code":"PPL",
    "gn:name":"Kalimenur",
    "gn:population":0,
    "gn:timezone":"Asia/Jakarta",
    "iso:country":"ID",
    "name:und_x_variant":[
        "Kalimenoer",
        "Kalimenur"
    ],
    "wof:lang_x_official":[
        "ind"
    ],
    "wof:lang_x_spoken":[
        "ind",
        "eng"
    ],
    "wof:name":"Kalimenur",
    "wof:placetype":"locality"
},
  "geometry": {"coordinates":[110.20722000000001,-7.86972],"type":"Point"}
}