{
  "type": "Feature",
  "properties": {
    "gn:admin1_code":"15.0",
    "gn:asciiname":"Talang Kelapapuyuh",
    "gn:country_code":"ID",
    "gn:dem":144,
    "gn:feature_class":"P",
    "gn:feature_code":"PPL",
    "gn:name":"Talang Kelapapuyuh",
    "gn:population":0,
    "gn:timezone":"Asia/Jakarta",
    "iso:country":"ID",
    "name:ind_x_preferred":[
        "Talang Kelapapuyuh"
    ],
    "wof:name":"Talang Kelapapuyuh",
    "wof:placetype":"locality"
},
  "geometry": {"coordinates":[104.65089999999999,-4.79881],"type":"Point"}
}