{
  "type": "Feature",
  "properties": {
    "gn:admin1_code":"30",
    "gn:asciiname":"Ciganitri Hilir",
    "gn:country_code":"ID",
    "gn:dem":668,
    "gn:feature_class":"P",
    "gn:feature_code":"PPL",
    "gn:name":"Ciganitri Hilir",
    "gn:population":0,
    "gn:timezone":"Asia/Jakarta",
    "iso:country":"ID",
    "name:ind_x_preferred":[
        "Ciganitri Hilir"
    ],
    "name:und_x_variant":[
        "Tjiganitri 2",
        "Ciganitri Dua"
    ],
    "wof:name":"Ciganitri Hilir",
    "wof:placetype":"locality"
},
  "geometry": {"coordinates":[107.64778,-6.97722],"type":"Point"}
}