{
  "type": "Feature",
  "properties": {
    "gn:admin1_code":"29.0",
    "gn:asciiname":"Gosoma",
    "gn:country_code":"ID",
    "gn:dem":17,
    "gn:feature_class":"P",
    "gn:feature_code":"PPL",
    "gn:name":"Gosoma",
    "gn:population":0,
    "gn:timezone":"Asia/Jayapura",
    "iso:country":"ID",
    "wof:name":"Gosoma",
    "wof:placetype":"locality"
},
  "geometry": {"coordinates":[128.01187999999999,1.71023],"type":"Point"}
}