{
  "type": "Feature",
  "properties": {
    "gn:admin1_code":"18.0",
    "gn:asciiname":"Maratalado",
    "gn:country_code":"ID",
    "gn:dem":580,
    "gn:feature_class":"P",
    "gn:feature_code":"PPL",
    "gn:name":"Maratalado",
    "gn:population":0,
    "gn:timezone":"Asia/Makassar",
    "iso:country":"ID",
    "name:ind_x_preferred":[
        "Maratalado"
    ],
    "wof:name":"Maratalado",
    "wof:placetype":"locality"
},
  "geometry": {"coordinates":[119.3907,-9.5442],"type":"Point"}
}