{
  "type": "Feature",
  "properties": {
    "gn:admin1_code":"30",
    "gn:asciiname":"Sukaati",
    "gn:country_code":"ID",
    "gn:dem":1472,
    "gn:feature_class":"P",
    "gn:feature_code":"PPL",
    "gn:name":"Sukaati",
    "gn:population":0,
    "gn:timezone":"Asia/Jakarta",
    "iso:country":"ID",
    "wof:name":"Sukaati",
    "wof:placetype":"locality"
},
  "geometry": {"coordinates":[107.61221999999999,-7.23611],"type":"Point"}
}