{
  "type": "Feature",
  "properties": {
    "gn:admin1_code":"32.0",
    "gn:asciiname":"Tanjungsari",
    "gn:country_code":"ID",
    "gn:dem":169,
    "gn:feature_class":"P",
    "gn:feature_code":"PPL",
    "gn:name":"Tanjungsari",
    "gn:population":0,
    "gn:timezone":"Asia/Jakarta",
    "iso:country":"ID",
    "name:ind_x_preferred":[
        "Tanjungsari"
    ],
    "wof:name":"Tanjungsari",
    "wof:placetype":"locality"
},
  "geometry": {"coordinates":[103.83597,-4.06271],"type":"Point"}
}