{
  "type": "Feature",
  "properties": {
    "gn:admin1_code":"30",
    "gn:asciiname":"Warungkadu",
    "gn:country_code":"ID",
    "gn:dem":101,
    "gn:feature_class":"P",
    "gn:feature_code":"PPL",
    "gn:name":"Warungkadu",
    "gn:population":0,
    "gn:timezone":"Asia/Jakarta",
    "iso:country":"ID",
    "name:ind_x_preferred":[
        "Warungkadu"
    ],
    "wof:name":"Warungkadu",
    "wof:placetype":"locality"
},
  "geometry": {"coordinates":[107.46917000000001,-6.56111],"type":"Point"}
}