{
  "type": "Feature",
  "properties": {
    "gn:admin1_code":"1",
    "gn:asciiname":"Meunasah Cot Plieng",
    "gn:country_code":"ID",
    "gn:dem":7,
    "gn:feature_class":"P",
    "gn:feature_code":"PPL",
    "gn:name":"Meunasah Cot Plieng",
    "gn:population":0,
    "gn:timezone":"Asia/Jakarta",
    "iso:country":"ID",
    "name:ind_x_preferred":[
        "Meunasah Cot Plieng"
    ],
    "wof:name":"Meunasah Cot Plieng",
    "wof:placetype":"locality"
},
  "geometry": {"coordinates":[97.184,5.1158],"type":"Point"}
}