{
  "type": "Feature",
  "properties": {
    "gn:admin1_code":"07",
    "gn:asciiname":"Gompyong",
    "gn:country_code":"ID",
    "gn:dem":804,
    "gn:feature_class":"P",
    "gn:feature_code":"PPL",
    "gn:name":"Gompyong",
    "gn:population":0,
    "gn:timezone":"Asia/Jakarta",
    "iso:country":"ID",
    "name:und_x_variant":[
        "Gompjong",
        "Gompyong"
    ],
    "wof:name":"Gompyong",
    "wof:placetype":"locality"
},
  "geometry": {"coordinates":[110.53861000000001,-7.39472],"type":"Point"}
}