{
  "type": "Feature",
  "properties": {
    "gn:admin1_code":"0.0",
    "gn:asciiname":"Benuaosang",
    "gn:cc2":"ID",
    "gn:country_code":"ID",
    "gn:dem":21,
    "gn:feature_class":"P",
    "gn:feature_code":"PPL",
    "gn:name":"Benuaosang",
    "gn:population":0,
    "gn:timezone":"Asia/Pontianak",
    "iso:country":"ID",
    "name:und_x_variant":[
        "Banoeaosang",
        "Benuosang",
        "Benoeaosang",
        "Benuaosang"
    ],
    "wof:lang_x_official":[
        "ind"
    ],
    "wof:lang_x_spoken":[
        "ind",
        "eng"
    ],
    "wof:name":"Benuaosang",
    "wof:placetype":"locality"
},
  "geometry": {"coordinates":[112.26667,-2.68333],"type":"Point"}
}