{
  "type": "Feature",
  "properties": {
    "gn:admin1_code":"26",
    "gn:asciiname":"Laembantor",
    "gn:country_code":"ID",
    "gn:dem":342,
    "gn:feature_class":"P",
    "gn:feature_code":"PPL",
    "gn:name":"Laembantor",
    "gn:population":0,
    "gn:timezone":"Asia/Jakarta",
    "iso:country":"ID",
    "name:ind_x_preferred":[
        "Laembantor"
    ],
    "name:und_x_variant":[
        "Laembontar"
    ],
    "wof:lang_x_official":[
        "ind"
    ],
    "wof:lang_x_spoken":[
        "ind",
        "eng"
    ],
    "wof:name":"Laembantor",
    "wof:placetype":"locality"
},
  "geometry": {"coordinates":[98.1893,2.4635],"type":"Point"}
}