{
  "type": "Feature",
  "properties": {
    "gn:admin1_code":"30",
    "gn:asciiname":"Cisoga",
    "gn:country_code":"ID",
    "gn:dem":701,
    "gn:feature_class":"P",
    "gn:feature_code":"PPL",
    "gn:name":"Cisoga",
    "gn:population":0,
    "gn:timezone":"Asia/Jakarta",
    "iso:country":"ID",
    "name:ind_x_preferred":[
        "Cisoga"
    ],
    "wof:name":"Cisoga",
    "wof:placetype":"locality"
},
  "geometry": {"coordinates":[107.8236,-7.0037],"type":"Point"}
}