{
  "type": "Feature",
  "properties": {
    "gn:admin1_code":"30",
    "gn:asciiname":"Sukagalih",
    "gn:country_code":"ID",
    "gn:dem":95,
    "gn:feature_class":"P",
    "gn:feature_code":"PPL",
    "gn:name":"Sukagalih",
    "gn:population":0,
    "gn:timezone":"Asia/Jakarta",
    "iso:country":"ID",
    "wof:name":"Sukagalih",
    "wof:placetype":"locality"
},
  "geometry": {"coordinates":[106.54028,-6.43639],"type":"Point"}
}