{
  "type": "Feature",
  "properties": {
    "gn:admin1_code":"8.0",
    "gn:asciiname":"Suruh",
    "gn:country_code":"ID",
    "gn:dem":400,
    "gn:feature_class":"P",
    "gn:feature_code":"PPL",
    "gn:name":"Suruh",
    "gn:population":0,
    "gn:timezone":"Asia/Jakarta",
    "iso:country":"ID",
    "name:ara_x_preferred":[
        "\u0633\u0631\u0648\u062d"
    ],
    "name:fra_x_preferred":[
        "Suruh"
    ],
    "name:ind_x_preferred":[
        "Suruh"
    ],
    "name:pol_x_preferred":[
        "Suruh"
    ],
    "wof:lang_x_official":[
        "ind"
    ],
    "wof:lang_x_spoken":[
        "ind",
        "eng"
    ],
    "wof:name":"Suruh",
    "wof:placetype":"locality"
},
  "geometry": {"coordinates":[111.7597,-8.0058],"type":"Point"}
}