{
  "type": "Feature",
  "properties": {
    "gn:admin1_code":"7.0",
    "gn:asciiname":"Griyaprajamukti",
    "gn:country_code":"ID",
    "gn:dem":66,
    "gn:feature_class":"P",
    "gn:feature_code":"PPL",
    "gn:name":"Griyaprajamukti",
    "gn:population":0,
    "gn:timezone":"Asia/Jakarta",
    "iso:country":"ID",
    "name:ind_x_preferred":[
        "Griyaprajamukti"
    ],
    "wof:name":"Griyaprajamukti",
    "wof:placetype":"locality"
},
  "geometry": {"coordinates":[109.64917,-7.6575],"type":"Point"}
}