{
  "type": "Feature",
  "properties": {
    "gn:admin1_code":"30.0",
    "gn:asciiname":"Situsari",
    "gn:country_code":"ID",
    "gn:dem":488,
    "gn:feature_class":"P",
    "gn:feature_code":"PPL",
    "gn:name":"Situsari",
    "gn:population":0,
    "gn:timezone":"Asia/Jakarta",
    "iso:country":"ID",
    "name:ind_x_preferred":[
        "Situsari"
    ],
    "wof:name":"Situsari",
    "wof:placetype":"locality"
},
  "geometry": {"coordinates":[108.3318,-7.1684],"type":"Point"}
}