{
  "type": "Feature",
  "properties": {
    "gn:admin1_code":"8.0",
    "gn:asciiname":"Kecubung Utara",
    "gn:country_code":"ID",
    "gn:dem":59,
    "gn:feature_class":"P",
    "gn:feature_code":"PPL",
    "gn:name":"Kecubung Utara",
    "gn:population":0,
    "gn:timezone":"Asia/Jakarta",
    "iso:country":"ID",
    "name:ind_x_preferred":[
        "Kecubung Utara"
    ],
    "wof:name":"Kecubung Utara",
    "wof:placetype":"locality"
},
  "geometry": {"coordinates":[111.9345,-7.6501],"type":"Point"}
}