{
  "type": "Feature",
  "properties": {
    "gn:admin1_code":"38.0",
    "gn:asciiname":"Tanjung",
    "gn:country_code":"ID",
    "gn:dem":13,
    "gn:feature_class":"P",
    "gn:feature_code":"PPL",
    "gn:name":"Tanjung",
    "gn:population":0,
    "gn:timezone":"Asia/Makassar",
    "iso:country":"ID",
    "name:ind_x_preferred":[
        "Tanjung"
    ],
    "wof:name":"Tanjung",
    "wof:placetype":"locality"
},
  "geometry": {"coordinates":[119.34059999999999,-1.1707],"type":"Point"}
}