{
  "type": "Feature",
  "properties": {
    "gn:admin1_code":"7",
    "gn:asciiname":"Candidukuh",
    "gn:country_code":"ID",
    "gn:dem":30,
    "gn:feature_class":"P",
    "gn:feature_code":"PPL",
    "gn:name":"Candidukuh",
    "gn:population":0,
    "gn:timezone":"Asia/Jakarta",
    "iso:country":"ID",
    "name:ind_x_preferred":[
        "Candidukuh"
    ],
    "wof:name":"Candidukuh",
    "wof:placetype":"locality"
},
  "geometry": {"coordinates":[110.8659,-7.1153],"type":"Point"}
}