{
  "type": "Feature",
  "properties": {
    "gn:admin1_code":"1",
    "gn:asciiname":"Guha",
    "gn:country_code":"ID",
    "gn:dem":30,
    "gn:feature_class":"P",
    "gn:feature_code":"PPL",
    "gn:name":"Guha",
    "gn:population":0,
    "gn:timezone":"Asia/Jakarta",
    "iso:country":"ID",
    "name:deu_x_preferred":[
        "Guha"
    ],
    "name:ind_x_preferred":[
        "Guha"
    ],
    "wof:name":"Guha",
    "wof:placetype":"locality"
},
  "geometry": {"coordinates":[98.08929999999999,2.4733],"type":"Point"}
}