{
  "type": "Feature",
  "properties": {
    "gn:admin1_code":"30",
    "gn:asciiname":"Karangtengah",
    "gn:country_code":"ID",
    "gn:dem":16,
    "gn:feature_class":"P",
    "gn:feature_code":"PPL",
    "gn:name":"Karangtengah",
    "gn:population":0,
    "gn:timezone":"Asia/Jakarta",
    "iso:country":"ID",
    "name:fra_x_preferred":[
        "Karang Tengah"
    ],
    "name:ind_x_preferred":[
        "Karangtengah"
    ],
    "name:jav_x_preferred":[
        "Karangtengah"
    ],
    "name:msa_x_preferred":[
        "Karangtengah"
    ],
    "name:sun_x_preferred":[
        "Karangtengah"
    ],
    "wof:name":"Karangtengah",
    "wof:placetype":"locality"
},
  "geometry": {"coordinates":[107.34667,-6.28333],"type":"Point"}
}