{
  "type": "Feature",
  "properties": {
    "gn:admin1_code":"0.0",
    "gn:asciiname":"Soprayan",
    "gn:cc2":"ID",
    "gn:country_code":"ID",
    "gn:dem":549,
    "gn:feature_class":"P",
    "gn:feature_code":"PPL",
    "gn:name":"Soprayan",
    "gn:population":0,
    "gn:timezone":"Asia/Jakarta",
    "iso:country":"ID",
    "name:und_x_variant":[
        "Soprajan",
        "Soprayan"
    ],
    "wof:name":"Soprayan",
    "wof:placetype":"locality"
},
  "geometry": {"coordinates":[110.40000000000001,-7.63333],"type":"Point"}
}