{
  "type": "Feature",
  "properties": {
    "gn:admin1_code":"18.0",
    "gn:asciiname":"Watupatinjang",
    "gn:country_code":"ID",
    "gn:dem":986,
    "gn:feature_class":"P",
    "gn:feature_code":"PPL",
    "gn:name":"Watupatinjang",
    "gn:population":0,
    "gn:timezone":"Asia/Makassar",
    "iso:country":"ID",
    "name:ind_x_preferred":[
        "Watupatinjang"
    ],
    "wof:name":"Watupatinjang",
    "wof:placetype":"locality"
},
  "geometry": {"coordinates":[120.3169,-10.0526],"type":"Point"}
}