{
  "type": "Feature",
  "properties": {
    "gn:admin1_code":"7",
    "gn:asciiname":"Kedungwungu",
    "gn:country_code":"ID",
    "gn:dem":463,
    "gn:feature_class":"P",
    "gn:feature_code":"PPL",
    "gn:name":"Kedungwungu",
    "gn:population":0,
    "gn:timezone":"Asia/Jakarta",
    "iso:country":"ID",
    "name:ind_x_preferred":[
        "Kedungwungu"
    ],
    "wof:name":"Kedungwungu",
    "wof:placetype":"locality"
},
  "geometry": {"coordinates":[109.1772,-7.0788],"type":"Point"}
}