{
  "type": "Feature",
  "properties": {
    "gn:admin1_code":"8.0",
    "gn:asciiname":"Kembangan",
    "gn:country_code":"ID",
    "gn:dem":21,
    "gn:feature_class":"P",
    "gn:feature_code":"PPL",
    "gn:name":"Kembangan",
    "gn:population":0,
    "gn:timezone":"Asia/Jakarta",
    "iso:country":"ID",
    "name:ceb_x_preferred":[
        "Kembangan"
    ],
    "name:ind_x_preferred":[
        "Kembangan"
    ],
    "name:nld_x_preferred":[
        "Kembangan"
    ],
    "name:swe_x_preferred":[
        "Kembangan"
    ],
    "wof:lang_x_official":[
        "ind"
    ],
    "wof:lang_x_spoken":[
        "ind",
        "eng"
    ],
    "wof:name":"Kembangan",
    "wof:placetype":"locality"
},
  "geometry": {"coordinates":[112.5962,-7.5291],"type":"Point"}
}