{
  "type": "Feature",
  "properties": {
    "gn:admin1_code":"29.0",
    "gn:asciiname":"Soot",
    "gn:country_code":"ID",
    "gn:dem":16,
    "gn:feature_class":"P",
    "gn:feature_code":"PPL",
    "gn:name":"Soot",
    "gn:population":0,
    "gn:timezone":"Asia/Jayapura",
    "iso:country":"ID",
    "name:ara_x_preferred":[
        "\u0633\u0646\u0627\u062c"
    ],
    "name:arc_x_preferred":[
        "\u072b\u0718\u0721\u072a\u0710"
    ],
    "name:arg_x_preferred":[
        "Foll\u00edn"
    ],
    "name:aym_x_preferred":[
        "Qhisti"
    ],
    "name:bel_x_preferred":[
        "\u0421\u0430\u0436\u0430"
    ],
    "name:bul_x_preferred":[
        "\u0421\u0430\u0436\u0434\u0438"
    ],
    "name:cat_x_preferred":[
        "Sutge"
    ],
    "name:ces_x_preferred":[
        "Saze"
    ],
    "name:cos_x_preferred":[
        "Fumaticu"
    ],
    "name:dan_x_preferred":[
        "Sod"
    ],
    "name:ell_x_preferred":[
        "\u0391\u03b9\u03b8\u03ac\u03bb\u03b7"
    ],
    "name:eml_x_preferred":[
        "Cal\u00e9\u015bna"
    ],
    "name:epo_x_preferred":[
        "Fulgo"
    ],
    "name:eus_x_preferred":[
        "Kedar"
    ],
    "name:fas_x_preferred":[
        "\u062f\u0648\u062f\u0647"
    ],
    "name:fin_x_preferred":[
        "Noki"
    ],
    "name:fra_x_preferred":[
        "Suie"
    ],
    "name:heb_x_preferred":[
        "\u05e4\u05d9\u05d7"
    ],
    "name:hun_x_preferred":[
        "Korom"
    ],
    "name:hye_x_preferred":[
        "\u0544\u0578\u0582\u0580"
    ],
    "name:ido_x_preferred":[
        "Fuligino"
    ],
    "name:ind_x_preferred":[
        "Jelaga"
    ],
    "name:ita_x_preferred":[
        "Particolato carbonioso"
    ],
    "name:kan_x_preferred":[
        "\u0cb9\u0cca\u0c97\u0cc6\u0cae\u0cb8\u0cbf"
    ],
    "name:kor_x_preferred":[
        "\uadf8\uc744\uc74c"
    ],
    "name:lim_x_preferred":[
        "Root"
    ],
    "name:ltz_x_preferred":[
        "Rouscht"
    ],
    "name:msa_x_preferred":[
        "Jelaga"
    ],
    "name:nds_x_preferred":[
        "Sott"
    ],
    "name:nld_x_preferred":[
        "Roet"
    ],
    "name:nno_x_preferred":[
        "Sot"
    ],
    "name:nor_x_preferred":[
        "Sot"
    ],
    "name:oci_x_preferred":[
        "Suja"
    ],
    "name:pol_x_preferred":[
        "Sadza"
    ],
    "name:por_x_preferred":[
        "Fuligem"
    ],
    "name:rus_x_preferred":[
        "\u0421\u0430\u0436\u0430"
    ],
    "name:scn_x_preferred":[
        "Mascar\u00f2"
    ],
    "name:slv_x_preferred":[
        "Saje"
    ],
    "name:spa_x_preferred":[
        "Holl\u00edn"
    ],
    "name:swe_x_preferred":[
        "Sot"
    ],
    "name:ukr_x_preferred":[
        "\u0421\u0430\u0436\u0430"
    ],
    "name:und_x_variant":[
        "So\u00f6t"
    ],
    "name:vie_x_preferred":[
        "B\u1ed3 h\u00f3ng"
    ],
    "wof:name":"Soot",
    "wof:placetype":"locality"
},
  "geometry": {"coordinates":[127.93376000000001,0.8978],"type":"Point"}
}