{
  "type": "Feature",
  "properties": {
    "gn:admin1_code":"29.0",
    "gn:asciiname":"Soot",
    "gn:country_code":"ID",
    "gn:dem":16,
    "gn:feature_class":"P",
    "gn:feature_code":"PPL",
    "gn:name":"Soot",
    "gn:population":0,
    "gn:timezone":"Asia/Jayapura",
    "iso:country":"ID",
    "name:und_x_variant":[
        "So\u00f6t"
    ],
    "wof:name":"Soot",
    "wof:placetype":"locality"
},
  "geometry": {"coordinates":[127.93376000000001,0.8978],"type":"Point"}
}