{
  "type": "Feature",
  "properties": {
    "gn:admin1_code":"1",
    "gn:asciiname":"Matangrimei",
    "gn:country_code":"ID",
    "gn:dem":8,
    "gn:feature_class":"P",
    "gn:feature_code":"PPL",
    "gn:name":"Matangrimei",
    "gn:population":0,
    "gn:timezone":"Asia/Jakarta",
    "iso:country":"ID",
    "name:ind_x_preferred":[
        "Matangrimei"
    ],
    "wof:name":"Matangrimei",
    "wof:placetype":"locality"
},
  "geometry": {"coordinates":[97.30419999999999,4.9965],"type":"Point"}
}