{
  "type": "Feature",
  "properties": {
    "gn:admin1_code":"1",
    "gn:asciiname":"Ie Jereneh Dua",
    "gn:country_code":"ID",
    "gn:dem":14,
    "gn:feature_class":"P",
    "gn:feature_code":"PPL",
    "gn:name":"Ie Jereneh Dua",
    "gn:population":0,
    "gn:timezone":"Asia/Jakarta",
    "iso:country":"ID",
    "name:ind_x_preferred":[
        "Ie Jereneh Dua"
    ],
    "name:und_x_variant":[
        "Ie Jereneh 2"
    ],
    "wof:lang_x_official":[
        "ind"
    ],
    "wof:lang_x_spoken":[
        "ind",
        "eng"
    ],
    "wof:name":"Ie Jereneh Dua",
    "wof:placetype":"locality"
},
  "geometry": {"coordinates":[97.70820000000001,2.8789],"type":"Point"}
}