{
  "type": "Feature",
  "properties": {
    "gn:admin1_code":"8.0",
    "gn:asciiname":"Pudak Kidul",
    "gn:country_code":"ID",
    "gn:dem":1003,
    "gn:feature_class":"P",
    "gn:feature_code":"PPL",
    "gn:name":"Pudak Kidul",
    "gn:population":0,
    "gn:timezone":"Asia/Jakarta",
    "iso:country":"ID",
    "name:ind_x_preferred":[
        "Pudak Kidul"
    ],
    "wof:name":"Pudak Kidul",
    "wof:placetype":"locality"
},
  "geometry": {"coordinates":[111.7116,-7.8715],"type":"Point"}
}