{
  "type": "Feature",
  "properties": {
    "gn:admin1_code":"30",
    "gn:asciiname":"Gunungcupu Dua",
    "gn:cc2":"ID",
    "gn:country_code":"ID",
    "gn:dem":1510,
    "gn:feature_class":"P",
    "gn:feature_code":"PPL",
    "gn:name":"Gunungcupu Dua",
    "gn:population":0,
    "gn:timezone":"Asia/Jakarta",
    "iso:country":"ID",
    "name:und_x_variant":[
        "Gunungtjupu 2",
        "Gunungcupu Dua"
    ],
    "wof:name":"Gunungcupu Dua",
    "wof:placetype":"locality"
},
  "geometry": {"coordinates":[107.56861000000001,-7.22139],"type":"Point"}
}