{
  "type": "Feature",
  "properties": {
    "gn:admin1_code":"17",
    "gn:asciiname":"Kauhan",
    "gn:country_code":"ID",
    "gn:dem":32,
    "gn:feature_class":"P",
    "gn:feature_code":"PPL",
    "gn:name":"Kauhan",
    "gn:population":0,
    "gn:timezone":"Asia/Makassar",
    "iso:country":"ID",
    "name:ind_x_preferred":[
        "Kauhan"
    ],
    "wof:name":"Kauhan",
    "wof:placetype":"locality"
},
  "geometry": {"coordinates":[116.12869999999999,-8.5862],"type":"Point"}
}