{
  "type": "Feature",
  "properties": {
    "gn:admin1_code":"0.0",
    "gn:asciiname":"Mombum",
    "gn:cc2":"ID",
    "gn:country_code":"ID",
    "gn:dem":11,
    "gn:feature_class":"P",
    "gn:feature_code":"PPL",
    "gn:name":"Mombum",
    "gn:population":0,
    "gn:timezone":"Asia/Jayapura",
    "iso:country":"ID",
    "name:und_x_variant":[
        "Momo",
        "Momboem",
        "Mombum"
    ],
    "wof:name":"Mombum",
    "wof:placetype":"locality"
},
  "geometry": {"coordinates":[138.84999999999999,-8.38333],"type":"Point"}
}