{
  "type": "Feature",
  "properties": {
    "gn:admin1_code":"7.0",
    "gn:asciiname":"Tawangsari",
    "gn:country_code":"ID",
    "gn:dem":91,
    "gn:feature_class":"P",
    "gn:feature_code":"PPLA4",
    "gn:name":"Tawangsari",
    "gn:population":0,
    "gn:timezone":"Asia/Jakarta",
    "iso:country":"ID",
    "name:ind_x_preferred":[
        "Tawangsari"
    ],
    "wof:name":"Tawangsari",
    "wof:placetype":"locality"
},
  "geometry": {"coordinates":[111.34310000000001,-6.9744],"type":"Point"}
}