{
  "type": "Feature",
  "properties": {
    "gn:admin1_code":"7",
    "gn:asciiname":"Gringgingsari",
    "gn:country_code":"ID",
    "gn:dem":368,
    "gn:feature_class":"P",
    "gn:feature_code":"PPL",
    "gn:name":"Gringgingsari",
    "gn:population":0,
    "gn:timezone":"Asia/Jakarta",
    "iso:country":"ID",
    "name:ind_x_preferred":[
        "Gringgingsari"
    ],
    "wof:name":"Gringgingsari",
    "wof:placetype":"locality"
},
  "geometry": {"coordinates":[109.7563,-7.0454],"type":"Point"}
}