{
  "type": "Feature",
  "properties": {
    "gn:admin1_code":"30",
    "gn:asciiname":"Blok Dua",
    "gn:country_code":"ID",
    "gn:dem":9,
    "gn:feature_class":"P",
    "gn:feature_code":"PPL",
    "gn:name":"Blok Dua",
    "gn:population":0,
    "gn:timezone":"Asia/Jakarta",
    "iso:country":"ID",
    "name:ind_x_preferred":[
        "Blok Dua"
    ],
    "wof:name":"Blok Dua",
    "wof:placetype":"locality"
},
  "geometry": {"coordinates":[108.44083000000001,-6.43222],"type":"Point"}
}