{
  "type": "Feature",
  "properties": {
    "gn:admin1_code":"11",
    "gn:asciiname":"Telukpakedai",
    "gn:country_code":"ID",
    "gn:dem":0,
    "gn:feature_class":"P",
    "gn:feature_code":"PPL",
    "gn:name":"Telukpakedai",
    "gn:population":0,
    "gn:timezone":"Asia/Pontianak",
    "iso:country":"ID",
    "name:ind_x_preferred":[
        "Telukpakedai"
    ],
    "wof:lang_x_official":[
        "ind"
    ],
    "wof:lang_x_spoken":[
        "ind",
        "eng"
    ],
    "wof:name":"Telukpakedai",
    "wof:placetype":"locality"
},
  "geometry": {"coordinates":[109.14866000000001,-0.31153],"type":"Point"}
}