{
  "type": "Feature",
  "properties": {
    "gn:admin1_code":"30",
    "gn:asciiname":"Sukarame",
    "gn:country_code":"ID",
    "gn:dem":743,
    "gn:feature_class":"P",
    "gn:feature_code":"PPL",
    "gn:name":"Sukarame",
    "gn:population":0,
    "gn:timezone":"Asia/Jakarta",
    "iso:country":"ID",
    "wof:name":"Sukarame",
    "wof:placetype":"locality"
},
  "geometry": {"coordinates":[107.51833000000001,-7.03472],"type":"Point"}
}