{
  "type": "Feature",
  "properties": {
    "gn:admin1_code":"17",
    "gn:asciiname":"Turida Timur",
    "gn:country_code":"ID",
    "gn:dem":35,
    "gn:feature_class":"P",
    "gn:feature_code":"PPL",
    "gn:name":"Turida Timur",
    "gn:population":0,
    "gn:timezone":"Asia/Makassar",
    "iso:country":"ID",
    "name:ind_x_preferred":[
        "Turida Timur"
    ],
    "wof:name":"Turida Timur",
    "wof:placetype":"locality"
},
  "geometry": {"coordinates":[116.14579999999999,-8.6062],"type":"Point"}
}