{
  "type": "Feature",
  "properties": {
    "gn:admin1_code":"26",
    "gn:asciiname":"Dalam Suka",
    "gn:country_code":"ID",
    "gn:dem":116,
    "gn:feature_class":"P",
    "gn:feature_code":"PPL",
    "gn:name":"Dalam Suka",
    "gn:population":0,
    "gn:timezone":"Asia/Jakarta",
    "iso:country":"ID",
    "name:ind_x_preferred":[
        "Dalam Suka"
    ],
    "wof:name":"Dalam Suka",
    "wof:placetype":"locality"
},
  "geometry": {"coordinates":[98.5386,3.4746],"type":"Point"}
}