{
  "type": "Feature",
  "properties": {
    "gn:admin1_code":"7",
    "gn:asciiname":"Kedungnglonggong",
    "gn:country_code":"ID",
    "gn:dem":76,
    "gn:feature_class":"P",
    "gn:feature_code":"PPL",
    "gn:name":"Kedungnglonggong",
    "gn:population":0,
    "gn:timezone":"Asia/Jakarta",
    "iso:country":"ID",
    "name:ind_x_preferred":[
        "Kedungnglonggong"
    ],
    "wof:name":"Kedungnglonggong",
    "wof:placetype":"locality"
},
  "geometry": {"coordinates":[110.94222000000001,-7.20333],"type":"Point"}
}