{
  "type": "Feature",
  "properties": {
    "gn:admin1_code":"30",
    "gn:asciiname":"Cimanggu Tiga",
    "gn:country_code":"ID",
    "gn:dem":313,
    "gn:feature_class":"P",
    "gn:feature_code":"PPL",
    "gn:name":"Cimanggu Tiga",
    "gn:population":0,
    "gn:timezone":"Asia/Jakarta",
    "iso:country":"ID",
    "name:ind_x_preferred":[
        "Cimanggu Tiga"
    ],
    "name:und_x_variant":[
        "Cimanggu 3"
    ],
    "wof:name":"Cimanggu Tiga",
    "wof:placetype":"locality"
},
  "geometry": {"coordinates":[106.67361,-6.60806],"type":"Point"}
}