{
  "type": "Feature",
  "properties": {
    "gn:admin1_code":"42",
    "gn:asciiname":"Muara Seputuk",
    "gn:country_code":"ID",
    "gn:dem":21,
    "gn:feature_class":"P",
    "gn:feature_code":"PPL",
    "gn:name":"Muara Seputuk",
    "gn:population":0,
    "gn:timezone":"Asia/Makassar",
    "iso:country":"ID",
    "name:ind_x_preferred":[
        "Muara Seputuk"
    ],
    "wof:name":"Muara Seputuk",
    "wof:placetype":"locality"
},
  "geometry": {"coordinates":[116.76049999999999,3.58317],"type":"Point"}
}