{
  "type": "Feature",
  "properties": {
    "gn:admin1_code":"22.0",
    "gn:asciiname":"Tokai",
    "gn:country_code":"ID",
    "gn:dem":51,
    "gn:feature_class":"P",
    "gn:feature_code":"PPL",
    "gn:name":"Tokai",
    "gn:population":0,
    "gn:timezone":"Asia/Makassar",
    "iso:country":"ID",
    "name:ara_x_preferred":[
        "\u062a\u0648\u0643\u0627\u064a"
    ],
    "name:bul_x_preferred":[
        "\u0422\u043e\u043a\u0430\u0439"
    ],
    "name:deu_x_preferred":[
        "Tokai"
    ],
    "name:fra_x_preferred":[
        "Tokai"
    ],
    "name:ind_x_preferred":[
        "Tokai"
    ],
    "name:ita_x_preferred":[
        "Tokai"
    ],
    "name:kor_x_preferred":[
        "\ub3c4\uce74\uc774"
    ],
    "name:nld_x_preferred":[
        "Tokai"
    ],
    "name:por_x_preferred":[
        "Tokai"
    ],
    "name:ron_x_preferred":[
        "Tokai"
    ],
    "name:rus_x_preferred":[
        "\u0422\u043e\u043a\u0430\u0439"
    ],
    "name:swe_x_preferred":[
        "Tokai"
    ],
    "name:ukr_x_preferred":[
        "\u0422\u043e\u043a\u0430\u0439"
    ],
    "wof:name":"Tokai",
    "wof:placetype":"locality"
},
  "geometry": {"coordinates":[121.9068,-4.2195],"type":"Point"}
}