{
  "type": "Feature",
  "properties": {
    "gn:admin1_code":"38",
    "gn:asciiname":"Tattumpumpung",
    "gn:country_code":"ID",
    "gn:dem":384,
    "gn:feature_class":"P",
    "gn:feature_code":"PPL",
    "gn:name":"Tattumpumpung",
    "gn:population":0,
    "gn:timezone":"Asia/Makassar",
    "iso:country":"ID",
    "name:ind_x_preferred":[
        "Tattumpumpung"
    ],
    "wof:name":"Tattumpumpung",
    "wof:placetype":"locality"
},
  "geometry": {"coordinates":[119.8914,-4.8082],"type":"Point"}
}