{
  "type": "Feature",
  "properties": {
    "gn:admin1_code":"30",
    "gn:asciiname":"Tirtajaya Satu",
    "gn:country_code":"ID",
    "gn:dem":515,
    "gn:feature_class":"P",
    "gn:feature_code":"PPL",
    "gn:name":"Tirtajaya Satu",
    "gn:population":0,
    "gn:timezone":"Asia/Jakarta",
    "iso:country":"ID",
    "name:ind_x_preferred":[
        "Tirtajaya Satu"
    ],
    "wof:name":"Tirtajaya Satu",
    "wof:placetype":"locality"
},
  "geometry": {"coordinates":[108.31638999999998,-6.85694],"type":"Point"}
}