{
  "type": "Feature",
  "properties": {
    "gn:admin1_code":"5.0",
    "gn:asciiname":"Semurup",
    "gn:country_code":"ID",
    "gn:dem":808,
    "gn:feature_class":"P",
    "gn:feature_code":"PPLA3",
    "gn:name":"Semurup",
    "gn:population":0,
    "gn:timezone":"Asia/Jakarta",
    "iso:country":"ID",
    "name:und_x_variant":[
        "Sumurup"
    ],
    "wof:lang_x_official":[
        "ind"
    ],
    "wof:lang_x_spoken":[
        "ind",
        "eng"
    ],
    "wof:name":"Semurup",
    "wof:placetype":"locality"
},
  "geometry": {"coordinates":[101.369,-1.9917],"type":"Point"}
}