{
  "type": "Feature",
  "properties": {
    "gn:admin1_code":"38.0",
    "gn:asciiname":"Banua",
    "gn:country_code":"ID",
    "gn:dem":804,
    "gn:feature_class":"P",
    "gn:feature_code":"PPL",
    "gn:name":"Banua",
    "gn:population":0,
    "gn:timezone":"Asia/Makassar",
    "iso:country":"ID",
    "name:ind_x_preferred":[
        "Banua"
    ],
    "wof:name":"Banua",
    "wof:placetype":"locality"
},
  "geometry": {"coordinates":[119.97020999999999,-3.54552],"type":"Point"}
}