{
  "type": "Feature",
  "properties": {
    "gn:admin1_code":"38",
    "gn:asciiname":"Carumbaan",
    "gn:country_code":"ID",
    "gn:dem":674,
    "gn:feature_class":"P",
    "gn:feature_code":"PPL",
    "gn:name":"Carumbaan",
    "gn:population":0,
    "gn:timezone":"Asia/Makassar",
    "iso:country":"ID",
    "name:ind_x_preferred":[
        "Carumbaan"
    ],
    "wof:name":"Carumbaan",
    "wof:placetype":"locality"
},
  "geometry": {"coordinates":[120.01560000000001,-5.203],"type":"Point"}
}