{
  "type": "Feature",
  "properties": {
    "gn:admin1_code":"30.0",
    "gn:asciiname":"Cijeruk",
    "gn:country_code":"ID",
    "gn:dem":593,
    "gn:feature_class":"P",
    "gn:feature_code":"PPL",
    "gn:name":"Cijeruk",
    "gn:population":0,
    "gn:timezone":"Asia/Jakarta",
    "iso:country":"ID",
    "name:ind_x_preferred":[
        "Cijeruk"
    ],
    "name:und_x_variant":[
        "Tjidjeroek"
    ],
    "wof:lang_x_official":[
        "ind"
    ],
    "wof:lang_x_spoken":[
        "ind",
        "eng"
    ],
    "wof:name":"Cijeruk",
    "wof:placetype":"locality"
},
  "geometry": {"coordinates":[107.9093,-7.4827],"type":"Point"}
}