{
  "type": "Feature",
  "properties": {
    "gn:admin1_code":"30",
    "gn:asciiname":"Gambungpangkalan",
    "gn:country_code":"ID",
    "gn:dem":1210,
    "gn:feature_class":"P",
    "gn:feature_code":"PPL",
    "gn:name":"Gambungpangkalan",
    "gn:population":0,
    "gn:timezone":"Asia/Jakarta",
    "iso:country":"ID",
    "name:ind_x_preferred":[
        "Gambungpangkalan"
    ],
    "wof:name":"Gambungpangkalan",
    "wof:placetype":"locality"
},
  "geometry": {"coordinates":[107.4914,-7.1222],"type":"Point"}
}