{
  "type": "Feature",
  "properties": {
    "gn:admin1_code":"7.0",
    "gn:asciiname":"Jadin",
    "gn:country_code":"ID",
    "gn:dem":48,
    "gn:feature_class":"P",
    "gn:feature_code":"PPL",
    "gn:name":"Jadin",
    "gn:population":0,
    "gn:timezone":"Asia/Jakarta",
    "iso:country":"ID",
    "name:deu_x_preferred":[
        "Jadin"
    ],
    "name:fra_x_preferred":[
        "Jadin"
    ],
    "name:ind_x_preferred":[
        "Jadin"
    ],
    "name:swe_x_preferred":[
        "Jadin"
    ],
    "wof:name":"Jadin",
    "wof:placetype":"locality"
},
  "geometry": {"coordinates":[109.47499999999999,-7.63583],"type":"Point"}
}