{
  "type": "Feature",
  "properties": {
    "gn:admin1_code":"30",
    "gn:asciiname":"Setu Dua",
    "gn:country_code":"ID",
    "gn:dem":330,
    "gn:feature_class":"P",
    "gn:feature_code":"PPL",
    "gn:name":"Setu Dua",
    "gn:population":0,
    "gn:timezone":"Asia/Jakarta",
    "iso:country":"ID",
    "name:ind_x_preferred":[
        "Setu Dua"
    ],
    "name:und_x_variant":[
        "Setu 2"
    ],
    "wof:lang_x_official":[
        "ind"
    ],
    "wof:lang_x_spoken":[
        "ind",
        "eng"
    ],
    "wof:name":"Setu Dua",
    "wof:placetype":"locality"
},
  "geometry": {"coordinates":[106.65722,-6.61722],"type":"Point"}
}