{
  "type": "Feature",
  "properties": {
    "gn:admin1_code":"28.0",
    "gn:asciiname":"Aruidas",
    "gn:country_code":"ID",
    "gn:dem":33,
    "gn:feature_class":"P",
    "gn:feature_code":"PPL",
    "gn:name":"Aruidas",
    "gn:population":0,
    "gn:timezone":"Asia/Jayapura",
    "iso:country":"ID",
    "name:und_x_variant":[
        "Aroeidas",
        "Aruidas"
    ],
    "wof:name":"Aruidas",
    "wof:placetype":"locality"
},
  "geometry": {"coordinates":[131.5445,-7.7139],"type":"Point"}
}