{
  "type": "Feature",
  "properties": {
    "gn:admin1_code":"15.0",
    "gn:asciiname":"Umbulanpurusbundet",
    "gn:country_code":"ID",
    "gn:dem":20,
    "gn:feature_class":"P",
    "gn:feature_code":"PPL",
    "gn:name":"Umbulanpurusbundet",
    "gn:population":0,
    "gn:timezone":"Asia/Jakarta",
    "iso:country":"ID",
    "name:ind_x_preferred":[
        "Umbulanpurusbundet"
    ],
    "wof:lang_x_official":[
        "ind"
    ],
    "wof:lang_x_spoken":[
        "ind",
        "eng"
    ],
    "wof:name":"Umbulanpurusbundet",
    "wof:placetype":"locality"
},
  "geometry": {"coordinates":[105.24484,-4.86731],"type":"Point"}
}