{
  "type": "Feature",
  "properties": {
    "gn:admin1_code":"33.0",
    "gn:asciiname":"Cidahu",
    "gn:country_code":"ID",
    "gn:dem":166,
    "gn:feature_class":"P",
    "gn:feature_code":"PPL",
    "gn:name":"Cidahu",
    "gn:population":0,
    "gn:timezone":"Asia/Jakarta",
    "iso:country":"ID",
    "name:ind_x_preferred":[
        "Cidahu"
    ],
    "wof:name":"Cidahu",
    "wof:placetype":"locality"
},
  "geometry": {"coordinates":[106.14861000000001,-6.879],"type":"Point"}
}