{
  "type": "Feature",
  "properties": {
    "gn:admin1_code":"38",
    "gn:asciiname":"Pasimbungang",
    "gn:country_code":"ID",
    "gn:dem":365,
    "gn:feature_class":"P",
    "gn:feature_code":"PPL",
    "gn:name":"Pasimbungang",
    "gn:population":0,
    "gn:timezone":"Asia/Makassar",
    "iso:country":"ID",
    "name:ind_x_preferred":[
        "Pasimbungang"
    ],
    "wof:name":"Pasimbungang",
    "wof:placetype":"locality"
},
  "geometry": {"coordinates":[120.0954,-5.4382],"type":"Point"}
}