{
  "type": "Feature",
  "properties": {
    "gn:admin1_code":"8",
    "gn:asciiname":"Gerinting",
    "gn:country_code":"ID",
    "gn:dem":104,
    "gn:feature_class":"P",
    "gn:feature_code":"PPL",
    "gn:name":"Gerinting",
    "gn:population":0,
    "gn:timezone":"Asia/Jakarta",
    "iso:country":"ID",
    "name:ind_x_preferred":[
        "Gerinting"
    ],
    "wof:name":"Gerinting",
    "wof:placetype":"locality"
},
  "geometry": {"coordinates":[112.4537,-7.5894],"type":"Point"}
}