{
  "type": "Feature",
  "properties": {
    "gn:admin1_code":"8.0",
    "gn:asciiname":"Banjarejo",
    "gn:country_code":"ID",
    "gn:dem":675,
    "gn:feature_class":"P",
    "gn:feature_code":"PPL",
    "gn:name":"Banjarejo",
    "gn:population":0,
    "gn:timezone":"Asia/Jakarta",
    "iso:country":"ID",
    "name:ind_x_preferred":[
        "Banjarejo"
    ],
    "wof:name":"Banjarejo",
    "wof:placetype":"locality"
},
  "geometry": {"coordinates":[112.3766,-7.8921],"type":"Point"}
}