{
  "type": "Feature",
  "properties": {
    "gn:admin1_code":"18.0",
    "gn:asciiname":"Taimung",
    "gn:country_code":"ID",
    "gn:dem":403,
    "gn:feature_class":"P",
    "gn:feature_code":"PPL",
    "gn:name":"Taimung",
    "gn:population":0,
    "gn:timezone":"Asia/Makassar",
    "iso:country":"ID",
    "name:ind_x_preferred":[
        "Taimung"
    ],
    "name:tha_x_preferred":[
        "\u0e44\u0e17\u0e21\u0e38\u0e07"
    ],
    "wof:name":"Taimung",
    "wof:placetype":"locality"
},
  "geometry": {"coordinates":[119.4288,-9.6583],"type":"Point"}
}