{
  "type": "Feature",
  "properties": {
    "gn:admin1_code":"8",
    "gn:asciiname":"Mloko",
    "gn:country_code":"ID",
    "gn:dem":701,
    "gn:feature_class":"P",
    "gn:feature_code":"PPL",
    "gn:name":"Mloko",
    "gn:population":0,
    "gn:timezone":"Asia/Jakarta",
    "iso:country":"ID",
    "name:ind_x_preferred":[
        "Mloko"
    ],
    "wof:name":"Mloko",
    "wof:placetype":"locality"
},
  "geometry": {"coordinates":[111.1875,-8.02556],"type":"Point"}
}