{
  "type": "Feature",
  "properties": {
    "gn:admin1_code":"38",
    "gn:asciiname":"Totana",
    "gn:country_code":"ID",
    "gn:dem":1066,
    "gn:feature_class":"P",
    "gn:feature_code":"PPL",
    "gn:name":"Totana",
    "gn:population":0,
    "gn:timezone":"Asia/Makassar",
    "iso:country":"ID",
    "name:ara_x_preferred":[
        "\u062a\u0648\u062a\u0627\u0646\u0627"
    ],
    "name:arg_x_preferred":[
        "Totana"
    ],
    "name:azb_x_preferred":[
        "\u062a\u062a\u0627\u0646\u0627"
    ],
    "name:cat_x_preferred":[
        "Totana"
    ],
    "name:ceb_x_preferred":[
        "Totana"
    ],
    "name:deu_x_preferred":[
        "Totana"
    ],
    "name:eus_x_preferred":[
        "Totana"
    ],
    "name:fas_x_preferred":[
        "\u062a\u062a\u0627\u0646\u0627"
    ],
    "name:fra_x_preferred":[
        "Totana"
    ],
    "name:glg_x_preferred":[
        "Totana"
    ],
    "name:hun_x_preferred":[
        "Totana"
    ],
    "name:ind_x_preferred":[
        "Totana"
    ],
    "name:ita_x_preferred":[
        "Totana"
    ],
    "name:mlg_x_preferred":[
        "Totana"
    ],
    "name:msa_x_preferred":[
        "Totana"
    ],
    "name:nld_x_preferred":[
        "Totana"
    ],
    "name:oci_x_preferred":[
        "Totana"
    ],
    "name:pol_x_preferred":[
        "Totana"
    ],
    "name:por_x_preferred":[
        "Totana"
    ],
    "name:rus_x_preferred":[
        "\u0422\u043e\u0442\u0430\u043d\u0430"
    ],
    "name:spa_x_preferred":[
        "Totana"
    ],
    "name:srp_x_preferred":[
        "\u0422\u043e\u0442\u0430\u043d\u0430"
    ],
    "name:swe_x_preferred":[
        "Totana"
    ],
    "name:ukr_x_preferred":[
        "\u0422\u043e\u0442\u0430\u043d\u0430"
    ],
    "name:war_x_preferred":[
        "Totana"
    ],
    "name:zho_x_preferred":[
        "\u6258\u5854\u7eb3"
    ],
    "wof:name":"Totana",
    "wof:placetype":"locality"
},
  "geometry": {"coordinates":[119.8509,-3.2226],"type":"Point"}
}