{
  "type": "Feature",
  "properties": {
    "gn:admin1_code":"38",
    "gn:asciiname":"Totana",
    "gn:country_code":"ID",
    "gn:dem":1066,
    "gn:feature_class":"P",
    "gn:feature_code":"PPL",
    "gn:name":"Totana",
    "gn:population":0,
    "gn:timezone":"Asia/Makassar",
    "iso:country":"ID",
    "name:ind_x_preferred":[
        "Totana"
    ],
    "wof:name":"Totana",
    "wof:placetype":"locality"
},
  "geometry": {"coordinates":[119.8509,-3.2226],"type":"Point"}
}