{
  "type": "Feature",
  "properties": {
    "gn:admin1_code":"30",
    "gn:asciiname":"Larangan",
    "gn:cc2":"ID",
    "gn:country_code":"ID",
    "gn:dem":15,
    "gn:feature_class":"P",
    "gn:feature_code":"PPL",
    "gn:name":"Larangan",
    "gn:population":0,
    "gn:timezone":"Asia/Jakarta",
    "iso:country":"ID",
    "name:und_x_variant":[
        "Rarangan 1",
        "Rarangan Satu",
        "Larangan"
    ],
    "wof:name":"Larangan",
    "wof:placetype":"locality"
},
  "geometry": {"coordinates":[106.5125,-6.14083],"type":"Point"}
}