{
  "type": "Feature",
  "properties": {
    "gn:admin1_code":"7.0",
    "gn:asciiname":"Duglig",
    "gn:country_code":"ID",
    "gn:dem":542,
    "gn:feature_class":"P",
    "gn:feature_code":"PPL",
    "gn:name":"Duglig",
    "gn:population":0,
    "gn:timezone":"Asia/Jakarta",
    "iso:country":"ID",
    "name:ind_x_preferred":[
        "Duglig"
    ],
    "wof:name":"Duglig",
    "wof:placetype":"locality"
},
  "geometry": {"coordinates":[109.74194,-7.36083],"type":"Point"}
}