{
  "type": "Feature",
  "properties": {
    "gn:admin1_code":"8.0",
    "gn:asciiname":"Karahindah",
    "gn:country_code":"ID",
    "gn:dem":8,
    "gn:feature_class":"P",
    "gn:feature_code":"PPL",
    "gn:name":"Karahindah",
    "gn:population":0,
    "gn:timezone":"Asia/Jakarta",
    "iso:country":"ID",
    "name:ind_x_preferred":[
        "Karahindah"
    ],
    "wof:name":"Karahindah",
    "wof:placetype":"locality"
},
  "geometry": {"coordinates":[112.7179,-7.3129],"type":"Point"}
}