{
  "type": "Feature",
  "properties": {
    "gn:admin1_code":"37",
    "gn:asciiname":"Siakrayatimber",
    "gn:country_code":"ID",
    "gn:dem":1,
    "gn:feature_class":"P",
    "gn:feature_code":"PPL",
    "gn:name":"Siakrayatimber",
    "gn:population":0,
    "gn:timezone":"Asia/Jakarta",
    "iso:country":"ID",
    "name:ind_x_preferred":[
        "Siakrayatimber"
    ],
    "wof:name":"Siakrayatimber",
    "wof:placetype":"locality"
},
  "geometry": {"coordinates":[102.00644,0.80072],"type":"Point"}
}