{
  "type": "Feature",
  "properties": {
    "gn:admin1_code":"30",
    "gn:asciiname":"Situgede",
    "gn:country_code":"ID",
    "gn:dem":1180,
    "gn:feature_class":"P",
    "gn:feature_code":"PPL",
    "gn:name":"Situgede",
    "gn:population":0,
    "gn:timezone":"Asia/Jakarta",
    "iso:country":"ID",
    "name:ind_x_preferred":[
        "Situgede"
    ],
    "wof:name":"Situgede",
    "wof:placetype":"locality"
},
  "geometry": {"coordinates":[107.4645,-7.1156],"type":"Point"}
}