{
  "type": "Feature",
  "properties": {
    "gn:admin1_code":"17.0",
    "gn:asciiname":"Pasinggah",
    "gn:country_code":"ID",
    "gn:dem":44,
    "gn:feature_class":"P",
    "gn:feature_code":"PPL",
    "gn:name":"Pasinggah",
    "gn:population":0,
    "gn:timezone":"Asia/Makassar",
    "iso:country":"ID",
    "name:ind_x_preferred":[
        "Pasinggah"
    ],
    "wof:name":"Pasinggah",
    "wof:placetype":"locality"
},
  "geometry": {"coordinates":[117.71729999999999,-8.9059],"type":"Point"}
}