{
  "type": "Feature",
  "properties": {
    "gn:admin1_code":"7",
    "gn:asciiname":"Tinggring",
    "gn:country_code":"ID",
    "gn:dem":823,
    "gn:feature_class":"P",
    "gn:feature_code":"PPL",
    "gn:name":"Tinggring",
    "gn:population":0,
    "gn:timezone":"Asia/Jakarta",
    "iso:country":"ID",
    "name:ind_x_preferred":[
        "Tinggring"
    ],
    "wof:name":"Tinggring",
    "wof:placetype":"locality"
},
  "geometry": {"coordinates":[109.90306,-7.34139],"type":"Point"}
}