{
  "type": "Feature",
  "properties": {
    "gn:admin1_code":"8.0",
    "gn:asciiname":"Sekola'an",
    "gn:country_code":"ID",
    "gn:dem":15,
    "gn:feature_class":"P",
    "gn:feature_code":"PPL",
    "gn:name":"Sekola\u2019an",
    "gn:population":0,
    "gn:timezone":"Asia/Jakarta",
    "iso:country":"ID",
    "name:ind_x_preferred":[
        "Sekola\u2019an"
    ],
    "wof:name":"Sekola'an",
    "wof:placetype":"locality"
},
  "geometry": {"coordinates":[113.9442,-7.065],"type":"Point"}
}