{
  "type": "Feature",
  "properties": {
    "gn:admin1_code":"05",
    "gn:asciiname":"Rengascondong",
    "gn:country_code":"ID",
    "gn:dem":20,
    "gn:feature_class":"P",
    "gn:feature_code":"PPL",
    "gn:name":"Rengascondong",
    "gn:population":0,
    "gn:timezone":"Asia/Jakarta",
    "iso:country":"ID",
    "name:ind_x_preferred":[
        "Rengascondong"
    ],
    "wof:name":"Rengascondong",
    "wof:placetype":"locality"
},
  "geometry": {"coordinates":[103.2739,-1.68807],"type":"Point"}
}