{
  "type": "Feature",
  "properties": {
    "gn:admin1_code":"30",
    "gn:asciiname":"Pratistatamansakura",
    "gn:country_code":"ID",
    "gn:dem":710,
    "gn:feature_class":"P",
    "gn:feature_code":"PPL",
    "gn:name":"Pratistatamansakura",
    "gn:population":0,
    "gn:timezone":"Asia/Jakarta",
    "iso:country":"ID",
    "name:ind_x_preferred":[
        "Pratistatamansakura"
    ],
    "wof:name":"Pratistatamansakura",
    "wof:placetype":"locality"
},
  "geometry": {"coordinates":[107.58306,-6.92556],"type":"Point"}
}