{
  "type": "Feature",
  "properties": {
    "gn:admin1_code":"30.0",
    "gn:asciiname":"Cikopi",
    "gn:country_code":"ID",
    "gn:dem":648,
    "gn:feature_class":"P",
    "gn:feature_code":"PPL",
    "gn:name":"Cikopi",
    "gn:population":0,
    "gn:timezone":"Asia/Jakarta",
    "iso:country":"ID",
    "name:ind_x_preferred":[
        "Cikopi"
    ],
    "wof:name":"Cikopi",
    "wof:placetype":"locality"
},
  "geometry": {"coordinates":[106.753,-7.0704],"type":"Point"}
}