{
  "type": "Feature",
  "properties": {
    "gn:admin1_code":"33",
    "gn:asciiname":"Ramabaru",
    "gn:country_code":"ID",
    "gn:dem":19,
    "gn:feature_class":"P",
    "gn:feature_code":"PPL",
    "gn:name":"Ramabaru",
    "gn:population":0,
    "gn:timezone":"Asia/Jakarta",
    "iso:country":"ID",
    "name:ind_x_preferred":[
        "Ramabaru"
    ],
    "wof:name":"Ramabaru",
    "wof:placetype":"locality"
},
  "geometry": {"coordinates":[106.0491,-5.999],"type":"Point"}
}