{
  "type": "Feature",
  "properties": {
    "gn:admin1_code":"33.0",
    "gn:asciiname":"Kampungmasjid",
    "gn:country_code":"ID",
    "gn:dem":16,
    "gn:feature_class":"P",
    "gn:feature_code":"PPLA4",
    "gn:name":"Kampungmasjid",
    "gn:population":0,
    "gn:timezone":"Asia/Jakarta",
    "iso:country":"ID",
    "name:ind_x_preferred":[
        "Kampungmasjid"
    ],
    "wof:name":"Kampungmasjid",
    "wof:placetype":"locality"
},
  "geometry": {"coordinates":[105.8914,-6.5661],"type":"Point"}
}