{
  "type": "Feature",
  "properties": {
    "gn:admin1_code":"38",
    "gn:asciiname":"Luraya",
    "gn:country_code":"ID",
    "gn:dem":1207,
    "gn:feature_class":"P",
    "gn:feature_code":"PPL",
    "gn:name":"Luraya",
    "gn:population":0,
    "gn:timezone":"Asia/Makassar",
    "iso:country":"ID",
    "name:ind_x_preferred":[
        "Luraya"
    ],
    "wof:name":"Luraya",
    "wof:placetype":"locality"
},
  "geometry": {"coordinates":[119.9149,-5.0642],"type":"Point"}
}