{
  "type": "Feature",
  "properties": {
    "gn:admin1_code":"17",
    "gn:asciiname":"Bongkak",
    "gn:country_code":"ID",
    "gn:dem":95,
    "gn:feature_class":"P",
    "gn:feature_code":"PPL",
    "gn:name":"Bongkak",
    "gn:population":0,
    "gn:timezone":"Asia/Makassar",
    "iso:country":"ID",
    "name:ind_x_preferred":[
        "Bongkak"
    ],
    "wof:name":"Bongkak",
    "wof:placetype":"locality"
},
  "geometry": {"coordinates":[116.2632,-8.8089],"type":"Point"}
}