{
  "type": "Feature",
  "properties": {
    "gn:admin1_code":"2",
    "gn:asciiname":"Banjar Patolan",
    "gn:country_code":"ID",
    "gn:dem":55,
    "gn:feature_class":"P",
    "gn:feature_code":"PPL",
    "gn:name":"Banjar Patolan",
    "gn:population":0,
    "gn:timezone":"Asia/Makassar",
    "iso:country":"ID",
    "name:ind_x_preferred":[
        "Banjar Patolan"
    ],
    "wof:name":"Banjar Patolan",
    "wof:placetype":"locality"
},
  "geometry": {"coordinates":[115.31999999999999,-8.5847],"type":"Point"}
}