{
  "type": "Feature",
  "properties": {
    "gn:admin1_code":"17",
    "gn:asciiname":"Kandai Satu",
    "gn:country_code":"ID",
    "gn:dem":32,
    "gn:feature_class":"P",
    "gn:feature_code":"PPL",
    "gn:name":"Kandai Satu",
    "gn:population":0,
    "gn:timezone":"Asia/Makassar",
    "iso:country":"ID",
    "name:ind_x_preferred":[
        "Kandai Satu"
    ],
    "wof:name":"Kandai Satu",
    "wof:placetype":"locality"
},
  "geometry": {"coordinates":[118.4571,-8.5446],"type":"Point"}
}