{
  "type": "Feature",
  "properties": {
    "gn:admin1_code":"33.0",
    "gn:asciiname":"Cahayamekar",
    "gn:country_code":"ID",
    "gn:dem":80,
    "gn:feature_class":"P",
    "gn:feature_code":"PPLA4",
    "gn:name":"Cahayamekar",
    "gn:population":0,
    "gn:timezone":"Asia/Jakarta",
    "iso:country":"ID",
    "name:ind_x_preferred":[
        "Cahayamekar"
    ],
    "wof:lang_x_official":[
        "ind"
    ],
    "wof:lang_x_spoken":[
        "ind",
        "eng"
    ],
    "wof:name":"Cahayamekar",
    "wof:placetype":"locality"
},
  "geometry": {"coordinates":[106.03874,-6.51389],"type":"Point"}
}