{
  "type": "Feature",
  "properties": {
    "gn:admin1_code":"7",
    "gn:asciiname":"Gunung",
    "gn:country_code":"ID",
    "gn:dem":922,
    "gn:feature_class":"P",
    "gn:feature_code":"PPL",
    "gn:name":"Gunung",
    "gn:population":0,
    "gn:timezone":"Asia/Jakarta",
    "iso:country":"ID",
    "name:ceb_x_preferred":[
        "Gunung"
    ],
    "name:ind_x_preferred":[
        "Gunung"
    ],
    "name:nld_x_preferred":[
        "Gunung"
    ],
    "name:swe_x_preferred":[
        "Gunung"
    ],
    "wof:lang_x_official":[
        "ind"
    ],
    "wof:lang_x_spoken":[
        "ind",
        "eng"
    ],
    "wof:name":"Gunung",
    "wof:placetype":"locality"
},
  "geometry": {"coordinates":[109.60833,-7.19],"type":"Point"}
}