{
  "type": "Feature",
  "properties": {
    "gn:admin1_code":"7.0",
    "gn:asciiname":"Dangsak",
    "gn:country_code":"ID",
    "gn:dem":109,
    "gn:feature_class":"P",
    "gn:feature_code":"PPL",
    "gn:name":"Dangsak",
    "gn:population":0,
    "gn:timezone":"Asia/Jakarta",
    "iso:country":"ID",
    "name:ind_x_preferred":[
        "Dangsak"
    ],
    "wof:name":"Dangsak",
    "wof:placetype":"locality"
},
  "geometry": {"coordinates":[109.48222,-7.33528],"type":"Point"}
}