{
  "type": "Feature",
  "properties": {
    "gn:admin1_code":"7.0",
    "gn:asciiname":"Kluwung",
    "gn:country_code":"ID",
    "gn:dem":18,
    "gn:feature_class":"P",
    "gn:feature_code":"PPL",
    "gn:name":"Kluwung",
    "gn:population":0,
    "gn:timezone":"Asia/Jakarta",
    "iso:country":"ID",
    "name:ind_x_preferred":[
        "Kluwung"
    ],
    "wof:name":"Kluwung",
    "wof:placetype":"locality"
},
  "geometry": {"coordinates":[111.0201,-6.8565],"type":"Point"}
}