{
  "type": "Feature",
  "properties": {
    "gn:admin1_code":"2",
    "gn:asciiname":"Ipil",
    "gn:country_code":"ID",
    "gn:dem":158,
    "gn:feature_class":"P",
    "gn:feature_code":"PPL",
    "gn:name":"Ipil",
    "gn:population":0,
    "gn:timezone":"Asia/Makassar",
    "iso:country":"ID",
    "name:ceb_x_preferred":[
        "Ipil"
    ],
    "name:deu_x_preferred":[
        "Ipil"
    ],
    "name:ind_x_preferred":[
        "Ipil"
    ],
    "name:tgl_x_preferred":[
        "Ipil"
    ],
    "wof:name":"Ipil",
    "wof:placetype":"locality"
},
  "geometry": {"coordinates":[115.0684,-8.4935],"type":"Point"}
}