{
  "type": "Feature",
  "properties": {
    "gn:admin1_code":"21.0",
    "gn:asciiname":"Lumbumamara",
    "gn:country_code":"ID",
    "gn:dem":50,
    "gn:feature_class":"P",
    "gn:feature_code":"PPL",
    "gn:name":"Lumbumamara",
    "gn:population":0,
    "gn:timezone":"Asia/Makassar",
    "iso:country":"ID",
    "name:ind_x_preferred":[
        "Lumbumamara"
    ],
    "wof:name":"Lumbumamara",
    "wof:placetype":"locality"
},
  "geometry": {"coordinates":[119.679,-0.817],"type":"Point"}
}