{
  "type": "Feature",
  "properties": {
    "gn:admin1_code":"15.0",
    "gn:asciiname":"Labugombong",
    "gn:country_code":"ID",
    "gn:dem":726,
    "gn:feature_class":"P",
    "gn:feature_code":"PPL",
    "gn:name":"Labugombong",
    "gn:population":0,
    "gn:timezone":"Asia/Jakarta",
    "iso:country":"ID",
    "name:ind_x_preferred":[
        "Labugombong"
    ],
    "wof:name":"Labugombong",
    "wof:placetype":"locality"
},
  "geometry": {"coordinates":[104.54028,-5.33672],"type":"Point"}
}