{
  "type": "Feature",
  "properties": {
    "gn:admin1_code":"15.0",
    "gn:asciiname":"Sinar Ogan Satu",
    "gn:country_code":"ID",
    "gn:dem":593,
    "gn:feature_class":"P",
    "gn:feature_code":"PPL",
    "gn:name":"Sinar Ogan Satu",
    "gn:population":0,
    "gn:timezone":"Asia/Jakarta",
    "iso:country":"ID",
    "name:ind_x_preferred":[
        "Sinar Ogan Satu"
    ],
    "name:und_x_variant":[
        "Sinar Ogan I"
    ],
    "wof:name":"Sinar Ogan Satu",
    "wof:placetype":"locality"
},
  "geometry": {"coordinates":[104.52307999999999,-4.93791],"type":"Point"}
}