{
  "type": "Feature",
  "properties": {
    "gn:admin1_code":"18.0",
    "gn:asciiname":"Ledemo",
    "gn:country_code":"ID",
    "gn:dem":42,
    "gn:feature_class":"P",
    "gn:feature_code":"PPL",
    "gn:name":"Ledemo",
    "gn:population":0,
    "gn:timezone":"Asia/Makassar",
    "iso:country":"ID",
    "name:ind_x_preferred":[
        "Ledemo"
    ],
    "wof:name":"Ledemo",
    "wof:placetype":"locality"
},
  "geometry": {"coordinates":[121.7617,-10.5436],"type":"Point"}
}