{
  "type": "Feature",
  "properties": {
    "gn:admin1_code":"33",
    "gn:asciiname":"Pengulah",
    "gn:country_code":"ID",
    "gn:dem":16,
    "gn:feature_class":"P",
    "gn:feature_code":"PPL",
    "gn:name":"Pengulah",
    "gn:population":0,
    "gn:timezone":"Asia/Jakarta",
    "iso:country":"ID",
    "name:ind_x_preferred":[
        "Pengulah"
    ],
    "wof:name":"Pengulah",
    "wof:placetype":"locality"
},
  "geometry": {"coordinates":[106.218,-6.1218],"type":"Point"}
}