{
  "type": "Feature",
  "properties": {
    "gn:admin1_code":"7.0",
    "gn:asciiname":"Ciledug",
    "gn:country_code":"ID",
    "gn:dem":649,
    "gn:feature_class":"P",
    "gn:feature_code":"PPL",
    "gn:name":"Ciledug",
    "gn:population":0,
    "gn:timezone":"Asia/Jakarta",
    "iso:country":"ID",
    "name:ind_x_preferred":[
        "Ciledug"
    ],
    "wof:name":"Ciledug",
    "wof:placetype":"locality"
},
  "geometry": {"coordinates":[108.6755,-7.2169],"type":"Point"}
}