{
  "type": "Feature",
  "properties": {
    "gn:admin1_code":"7.0",
    "gn:asciiname":"Ciledug",
    "gn:country_code":"ID",
    "gn:dem":649,
    "gn:feature_class":"P",
    "gn:feature_code":"PPL",
    "gn:name":"Ciledug",
    "gn:population":0,
    "gn:timezone":"Asia/Jakarta",
    "iso:country":"ID",
    "name:fas_x_preferred":[
        "\u0633\u06cc\u0644\u062f\u0648\u06af"
    ],
    "name:ind_x_preferred":[
        "Ciledug"
    ],
    "name:jav_x_preferred":[
        "Ciledug"
    ],
    "name:msa_x_preferred":[
        "Ciledug"
    ],
    "name:sun_x_preferred":[
        "Ciledug"
    ],
    "name:zho_x_preferred":[
        "\u829d\u52d2\u90fd"
    ],
    "wof:name":"Ciledug",
    "wof:placetype":"locality"
},
  "geometry": {"coordinates":[108.6755,-7.2169],"type":"Point"}
}