{
  "type": "Feature",
  "properties": {
    "gn:admin1_code":"8",
    "gn:asciiname":"Jajangan Kulon",
    "gn:country_code":"ID",
    "gn:dem":421,
    "gn:feature_class":"P",
    "gn:feature_code":"PPL",
    "gn:name":"Jajangan Kulon",
    "gn:population":0,
    "gn:timezone":"Asia/Jakarta",
    "iso:country":"ID",
    "name:ind_x_preferred":[
        "Jajangan Kulon"
    ],
    "wof:name":"Jajangan Kulon",
    "wof:placetype":"locality"
},
  "geometry": {"coordinates":[114.18393,-8.22728],"type":"Point"}
}