{
  "type": "Feature",
  "properties": {
    "gn:country":"ID",
    "gn:fcode":"ADM3",
    "gn:pop":0,
    "iso:country":"ID",
    "name:ind_x_preferred":[
        "Kecamatan Gemuh"
    ],
    "name:unk_x_variant":[
        "Gemuh"
    ],
    "qs:name":"Kecamatan Gemuh",
    "qs:photos_9r":0,
    "qs:photos_sr":0,
    "qs:pop_sr":"0",
    "wd:wordcount":1175,
    "wof:name":"Kecamatan Gemuh",
    "wof:placetype":"localadmin",
    "wof:population":0
},
  "geometry": {"coordinates":[110.1146,-6.9883],"type":"Point"}
}