{
  "type": "Feature",
  "properties": {
    "gn:admin1_code":"2",
    "gn:asciiname":"Banjar Gelogor",
    "gn:country_code":"ID",
    "gn:dem":886,
    "gn:feature_class":"P",
    "gn:feature_code":"PPL",
    "gn:name":"Banjar Gelogor",
    "gn:population":0,
    "gn:timezone":"Asia/Makassar",
    "iso:country":"ID",
    "name:ind_x_preferred":[
        "Banjar Gelogor"
    ],
    "wof:name":"Banjar Gelogor",
    "wof:placetype":"locality"
},
  "geometry": {"coordinates":[115.2081,-8.3293],"type":"Point"}
}