{
  "type": "Feature",
  "properties": {
    "gn:admin1_code":"8",
    "gn:asciiname":"Curahbindo",
    "gn:country_code":"ID",
    "gn:dem":97,
    "gn:feature_class":"P",
    "gn:feature_code":"PPL",
    "gn:name":"Curahbindo",
    "gn:population":0,
    "gn:timezone":"Asia/Jakarta",
    "iso:country":"ID",
    "name:ind_x_preferred":[
        "Curahbindo"
    ],
    "wof:name":"Curahbindo",
    "wof:placetype":"locality"
},
  "geometry": {"coordinates":[113.2116,-7.8822],"type":"Point"}
}