{
  "type": "Feature",
  "properties": {
    "gn:admin1_code":"30",
    "gn:asciiname":"Tangenjarak",
    "gn:country_code":"ID",
    "gn:dem":0,
    "gn:feature_class":"P",
    "gn:feature_code":"PPL",
    "gn:name":"Tangenjarak",
    "gn:population":0,
    "gn:timezone":"Asia/Jakarta",
    "iso:country":"ID",
    "name:ind_x_preferred":[
        "Tangenjarak"
    ],
    "wof:name":"Tangenjarak",
    "wof:placetype":"locality"
},
  "geometry": {"coordinates":[107.33693999999998,-5.96833],"type":"Point"}
}