{
  "type": "Feature",
  "properties": {
    "gn:admin1_code":"30",
    "gn:asciiname":"Cisarua",
    "gn:cc2":"ID",
    "gn:country_code":"ID",
    "gn:dem":1410,
    "gn:feature_class":"P",
    "gn:feature_code":"PPL",
    "gn:name":"Cisarua",
    "gn:population":0,
    "gn:timezone":"Asia/Jakarta",
    "iso:country":"ID",
    "name:fas_x_preferred":[
        "\u06a9\u06cc\u0633\u0627\u0631\u0648\u0627"
    ],
    "name:und_x_variant":[
        "Tjisarua",
        "Cisarua"
    ],
    "wof:name":"Cisarua",
    "wof:placetype":"locality"
},
  "geometry": {"coordinates":[107.53667,-7.18778],"type":"Point"}
}