{
  "type": "Feature",
  "properties": {
    "gn:admin1_code":"30",
    "gn:asciiname":"Tonjong",
    "gn:country_code":"ID",
    "gn:dem":29,
    "gn:feature_class":"P",
    "gn:feature_code":"PPL",
    "gn:name":"Tonjong",
    "gn:population":0,
    "gn:timezone":"Asia/Jakarta",
    "iso:country":"ID",
    "name:ind_x_preferred":[
        "Tonjong"
    ],
    "wof:name":"Tonjong",
    "wof:placetype":"locality"
},
  "geometry": {"coordinates":[108.60980000000001,-6.829],"type":"Point"}
}