{
  "type": "Feature",
  "properties": {
    "gn:admin1_code":"18",
    "gn:asciiname":"Norang",
    "gn:country_code":"ID",
    "gn:dem":1126,
    "gn:feature_class":"P",
    "gn:feature_code":"PPL",
    "gn:name":"Norang",
    "gn:population":0,
    "gn:timezone":"Asia/Makassar",
    "iso:country":"ID",
    "name:ind_x_preferred":[
        "Norang"
    ],
    "wof:name":"Norang",
    "wof:placetype":"locality"
},
  "geometry": {"coordinates":[120.4966,-8.6028],"type":"Point"}
}