{
  "type": "Feature",
  "properties": {
    "gn:admin1_code":"12",
    "gn:asciiname":"Buntukarau",
    "gn:country_code":"ID",
    "gn:dem":41,
    "gn:feature_class":"P",
    "gn:feature_code":"PPL",
    "gn:name":"Buntukarau",
    "gn:population":0,
    "gn:timezone":"Asia/Makassar",
    "iso:country":"ID",
    "name:ind_x_preferred":[
        "Buntukarau"
    ],
    "wof:name":"Buntukarau",
    "wof:placetype":"locality"
},
  "geometry": {"coordinates":[115.5491,-2.2794],"type":"Point"}
}