{
  "type": "Feature",
  "properties": {
    "gn:admin1_code":"30.0",
    "gn:asciiname":"Ciwareng",
    "gn:country_code":"ID",
    "gn:dem":620,
    "gn:feature_class":"P",
    "gn:feature_code":"PPL",
    "gn:name":"Ciwareng",
    "gn:population":0,
    "gn:timezone":"Asia/Jakarta",
    "iso:country":"ID",
    "name:ind_x_preferred":[
        "Ciwareng"
    ],
    "name:und_x_variant":[
        "Tjiwareng"
    ],
    "wof:name":"Ciwareng",
    "wof:placetype":"locality"
},
  "geometry": {"coordinates":[107.95829999999999,-7.0612],"type":"Point"}
}