{
  "type": "Feature",
  "properties": {
    "gn:admin1_code":"30",
    "gn:asciiname":"Cikasarak",
    "gn:cc2":"ID",
    "gn:country_code":"ID",
    "gn:dem":724,
    "gn:feature_class":"P",
    "gn:feature_code":"PPL",
    "gn:name":"Cikasarak",
    "gn:population":0,
    "gn:timezone":"Asia/Jakarta",
    "iso:country":"ID",
    "name:und_x_variant":[
        "Tjikasarak",
        "Cikasarak"
    ],
    "wof:lang_x_official":[
        "ind"
    ],
    "wof:lang_x_spoken":[
        "ind",
        "eng"
    ],
    "wof:name":"Cikasarak",
    "wof:placetype":"locality"
},
  "geometry": {"coordinates":[107.52778000000001,-7.0225],"type":"Point"}
}