{
  "type": "Feature",
  "properties": {
    "gn:admin1_code":"24",
    "gn:asciiname":"Parit Satu",
    "gn:country_code":"ID",
    "gn:dem":132,
    "gn:feature_class":"P",
    "gn:feature_code":"PPL",
    "gn:name":"Parit Satu",
    "gn:population":0,
    "gn:timezone":"Asia/Jakarta",
    "iso:country":"ID",
    "name:ind_x_preferred":[
        "Parit Satu"
    ],
    "name:und_x_variant":[
        "Parit 1"
    ],
    "wof:name":"Parit Satu",
    "wof:placetype":"locality"
},
  "geometry": {"coordinates":[100.23539,-0.51712],"type":"Point"}
}