{
  "type": "Feature",
  "properties": {
    "gn:admin1_code":"24",
    "gn:asciiname":"Sijinjang",
    "gn:country_code":"ID",
    "gn:dem":44,
    "gn:feature_class":"P",
    "gn:feature_code":"PPL",
    "gn:name":"Sijinjang",
    "gn:population":0,
    "gn:timezone":"Asia/Jakarta",
    "iso:country":"ID",
    "name:ind_x_preferred":[
        "Sijinjang"
    ],
    "wof:name":"Sijinjang",
    "wof:placetype":"locality"
},
  "geometry": {"coordinates":[98.84781,-0.99172],"type":"Point"}
}