{
  "type": "Feature",
  "properties": {
    "gn:admin1_code":"38",
    "gn:asciiname":"Lokasi",
    "gn:country_code":"ID",
    "gn:dem":1315,
    "gn:feature_class":"P",
    "gn:feature_code":"PPL",
    "gn:name":"Lokasi",
    "gn:population":0,
    "gn:timezone":"Asia/Makassar",
    "iso:country":"ID",
    "name:ind_x_preferred":[
        "Lokasi"
    ],
    "wof:name":"Lokasi",
    "wof:placetype":"locality"
},
  "geometry": {"coordinates":[119.7908,-2.8913],"type":"Point"}
}