{
  "type": "Feature",
  "properties": {
    "gn:admin1_code":"18.0",
    "gn:asciiname":"Lanubewa",
    "gn:country_code":"ID",
    "gn:dem":590,
    "gn:feature_class":"P",
    "gn:feature_code":"PPL",
    "gn:name":"Lanubewa",
    "gn:population":0,
    "gn:timezone":"Asia/Makassar",
    "iso:country":"ID",
    "name:ind_x_preferred":[
        "Lanubewa"
    ],
    "wof:name":"Lanubewa",
    "wof:placetype":"locality"
},
  "geometry": {"coordinates":[122.01730000000001,-8.7139],"type":"Point"}
}