{
  "type": "Feature",
  "properties": {
    "gn:admin1_code":"37",
    "gn:asciiname":"Telukpelita",
    "gn:country_code":"ID",
    "gn:dem":11,
    "gn:feature_class":"P",
    "gn:feature_code":"PPL",
    "gn:name":"Telukpelita",
    "gn:population":0,
    "gn:timezone":"Asia/Jakarta",
    "iso:country":"ID",
    "name:ind_x_preferred":[
        "Telukpelita"
    ],
    "wof:name":"Telukpelita",
    "wof:placetype":"locality"
},
  "geometry": {"coordinates":[103.23239,0.49088],"type":"Point"}
}