{
  "type": "Feature",
  "properties": {
    "gn:admin1_code":"8.0",
    "gn:asciiname":"Tegalampel",
    "gn:country_code":"ID",
    "gn:dem":249,
    "gn:feature_class":"P",
    "gn:feature_code":"PPL",
    "gn:name":"Tegalampel",
    "gn:population":0,
    "gn:timezone":"Asia/Jakarta",
    "iso:country":"ID",
    "name:ind_x_preferred":[
        "Tegalampel"
    ],
    "wof:name":"Tegalampel",
    "wof:placetype":"locality"
},
  "geometry": {"coordinates":[113.84999999999999,-7.8878],"type":"Point"}
}