{
  "type": "Feature",
  "properties": {
    "gn:admin1_code":"18.0",
    "gn:asciiname":"Lite",
    "gn:country_code":"ID",
    "gn:dem":505,
    "gn:feature_class":"P",
    "gn:feature_code":"PPL",
    "gn:name":"Lite",
    "gn:population":0,
    "gn:timezone":"Asia/Makassar",
    "iso:country":"ID",
    "name:ceb_x_preferred":[
        "Lite"
    ],
    "name:deu_x_preferred":[
        "Lite"
    ],
    "name:ind_x_preferred":[
        "Lite"
    ],
    "name:swe_x_preferred":[
        "Lite"
    ],
    "wof:lang_x_official":[
        "ind"
    ],
    "wof:lang_x_spoken":[
        "ind",
        "eng"
    ],
    "wof:name":"Lite",
    "wof:placetype":"locality"
},
  "geometry": {"coordinates":[124.73480000000001,-9.6801],"type":"Point"}
}