{
  "type": "Feature",
  "properties": {
    "gn:admin1_code":"08",
    "gn:asciiname":"Lowokgempol",
    "gn:country_code":"ID",
    "gn:dem":337,
    "gn:feature_class":"P",
    "gn:feature_code":"PPL",
    "gn:name":"Lowokgempol",
    "gn:population":0,
    "gn:timezone":"Asia/Jakarta",
    "iso:country":"ID",
    "name:ind_x_preferred":[
        "Lowokgempol"
    ],
    "name:und_x_variant":[
        "Iowakumpol"
    ],
    "wof:name":"Lowokgempol",
    "wof:placetype":"locality"
},
  "geometry": {"coordinates":[112.5321,-8.1203],"type":"Point"}
}