{
  "type": "Feature",
  "properties": {
    "gn:admin1_code":"7.0",
    "gn:asciiname":"Ampel",
    "gn:country_code":"ID",
    "gn:dem":227,
    "gn:feature_class":"P",
    "gn:feature_code":"PPL",
    "gn:name":"Ampel",
    "gn:population":0,
    "gn:timezone":"Asia/Jakarta",
    "iso:country":"ID",
    "name:ind_x_preferred":[
        "Ampel"
    ],
    "name:nld_x_preferred":[
        "Ampel"
    ],
    "wof:lang_x_official":[
        "ind"
    ],
    "wof:lang_x_spoken":[
        "ind",
        "eng"
    ],
    "wof:name":"Ampel",
    "wof:placetype":"locality"
},
  "geometry": {"coordinates":[109.32722,-7.33],"type":"Point"}
}