{
  "type": "Feature",
  "properties": {
    "gn:admin1_code":"31",
    "gn:asciiname":"Keroit",
    "gn:country_code":"ID",
    "gn:dem":751,
    "gn:feature_class":"P",
    "gn:feature_code":"PPL",
    "gn:name":"Keroit",
    "gn:population":0,
    "gn:timezone":"Asia/Makassar",
    "iso:country":"ID",
    "name:ind_x_preferred":[
        "Keroit"
    ],
    "wof:name":"Keroit",
    "wof:placetype":"locality"
},
  "geometry": {"coordinates":[124.43770000000001,0.9955],"type":"Point"}
}