{
  "type": "Feature",
  "properties": {
    "gn:admin1_code":"7.0",
    "gn:asciiname":"Kujang",
    "gn:country_code":"ID",
    "gn:dem":439,
    "gn:feature_class":"P",
    "gn:feature_code":"PPLA4",
    "gn:name":"Kujang",
    "gn:population":0,
    "gn:timezone":"Asia/Jakarta",
    "iso:country":"ID",
    "name:ceb_x_preferred":[
        "Kujang"
    ],
    "name:ind_x_preferred":[
        "Kujang"
    ],
    "name:nld_x_preferred":[
        "Kujang"
    ],
    "name:swe_x_preferred":[
        "Kujang"
    ],
    "wof:lang_x_official":[
        "ind"
    ],
    "wof:lang_x_spoken":[
        "ind",
        "eng"
    ],
    "wof:name":"Kujang",
    "wof:placetype":"locality"
},
  "geometry": {"coordinates":[108.6022,-7.1957],"type":"Point"}
}