{
  "type": "Feature",
  "properties": {
    "gn:admin1_code":"31",
    "gn:asciiname":"Wawona",
    "gn:country_code":"ID",
    "gn:dem":176,
    "gn:feature_class":"P",
    "gn:feature_code":"PPL",
    "gn:name":"Wawona",
    "gn:population":0,
    "gn:timezone":"Asia/Makassar",
    "iso:country":"ID",
    "name:fra_x_preferred":[
        "Wawona"
    ],
    "name:ind_x_preferred":[
        "Wawona"
    ],
    "name:rus_x_preferred":[
        "\u0423\u0430\u0432\u043e\u043d\u0430"
    ],
    "wof:name":"Wawona",
    "wof:placetype":"locality"
},
  "geometry": {"coordinates":[124.5586,1.3103],"type":"Point"}
}