{
  "type": "Feature",
  "properties": {
    "gn:admin1_code":"30.0",
    "gn:asciiname":"Karti",
    "gn:country_code":"ID",
    "gn:dem":9,
    "gn:feature_class":"P",
    "gn:feature_code":"PPL",
    "gn:name":"Karti",
    "gn:population":0,
    "gn:timezone":"Asia/Jakarta",
    "iso:country":"ID",
    "name:ceb_x_preferred":[
        "Kart\u012b"
    ],
    "name:fas_x_preferred":[
        "\u06a9\u0631\u062a\u06cc"
    ],
    "name:ind_x_preferred":[
        "Karti"
    ],
    "name:msa_x_preferred":[
        "Karti"
    ],
    "name:swe_x_preferred":[
        "Kart\u012b"
    ],
    "wof:lang_x_official":[
        "ind"
    ],
    "wof:lang_x_spoken":[
        "ind",
        "eng"
    ],
    "wof:name":"Karti",
    "wof:placetype":"locality"
},
  "geometry": {"coordinates":[108.46306,-6.64833],"type":"Point"}
}