{
  "type": "Feature",
  "properties": {
    "gn:admin1_code":"8",
    "gn:asciiname":"Jaringan",
    "gn:country_code":"ID",
    "gn:dem":41,
    "gn:feature_class":"P",
    "gn:feature_code":"PPL",
    "gn:name":"Jaringan",
    "gn:population":0,
    "gn:timezone":"Asia/Jakarta",
    "iso:country":"ID",
    "name:ind_x_preferred":[
        "Jaringan"
    ],
    "wof:name":"Jaringan",
    "wof:placetype":"locality"
},
  "geometry": {"coordinates":[113.0013,-7.7519],"type":"Point"}
}