{
  "type": "Feature",
  "properties": {
    "gn:admin1_code":"8",
    "gn:asciiname":"Bagoran",
    "gn:country_code":"ID",
    "gn:dem":49,
    "gn:feature_class":"P",
    "gn:feature_code":"PPL",
    "gn:name":"Bagoran",
    "gn:population":0,
    "gn:timezone":"Asia/Jakarta",
    "iso:country":"ID",
    "name:ind_x_preferred":[
        "Bagoran"
    ],
    "name:por_x_preferred":[
        "Bagoran"
    ],
    "wof:name":"Bagoran",
    "wof:placetype":"locality"
},
  "geometry": {"coordinates":[112.0273,-7.5856],"type":"Point"}
}