{
  "type": "Feature",
  "properties": {
    "gn:admin1_code":"7.0",
    "gn:asciiname":"Teseh",
    "gn:country_code":"ID",
    "gn:dem":20,
    "gn:feature_class":"P",
    "gn:feature_code":"PPL",
    "gn:name":"Teseh",
    "gn:population":0,
    "gn:timezone":"Asia/Jakarta",
    "iso:country":"ID",
    "name:ind_x_preferred":[
        "Teseh"
    ],
    "wof:name":"Teseh",
    "wof:placetype":"locality"
},
  "geometry": {"coordinates":[111.244,-6.7478],"type":"Point"}
}