{
  "type": "Feature",
  "properties": {
    "gn:admin1_code":"38",
    "gn:asciiname":"Mong",
    "gn:country_code":"ID",
    "gn:dem":100,
    "gn:feature_class":"P",
    "gn:feature_code":"PPL",
    "gn:name":"Mong",
    "gn:population":0,
    "gn:timezone":"Asia/Makassar",
    "iso:country":"ID",
    "name:deu_x_preferred":[
        "Mong"
    ],
    "name:ind_x_preferred":[
        "Mong"
    ],
    "name:nor_x_preferred":[
        "Mong"
    ],
    "wof:lang_x_official":[
        "ind"
    ],
    "wof:lang_x_spoken":[
        "ind",
        "eng"
    ],
    "wof:name":"Mong",
    "wof:placetype":"locality"
},
  "geometry": {"coordinates":[120.0284,-4.458],"type":"Point"}
}