{
  "type": "Feature",
  "properties": {
    "gn:admin1_code":"33.0",
    "gn:asciiname":"Kaduranca",
    "gn:country_code":"ID",
    "gn:dem":182,
    "gn:feature_class":"P",
    "gn:feature_code":"PPLA4",
    "gn:name":"Kaduranca",
    "gn:population":0,
    "gn:timezone":"Asia/Jakarta",
    "iso:country":"ID",
    "name:ind_x_preferred":[
        "Kaduranca"
    ],
    "name:und_x_variant":[
        "Kadurantja",
        "Kaduranca"
    ],
    "wof:lang_x_official":[
        "ind"
    ],
    "wof:lang_x_spoken":[
        "ind",
        "eng"
    ],
    "wof:name":"Kaduranca",
    "wof:placetype":"locality"
},
  "geometry": {"coordinates":[105.9299,-6.361],"type":"Point"}
}