{
  "type": "Feature",
  "properties": {
    "gn:admin1_code":"30.0",
    "gn:asciiname":"Cijumungkung",
    "gn:country_code":"ID",
    "gn:dem":752,
    "gn:feature_class":"P",
    "gn:feature_code":"PPL",
    "gn:name":"Cijumungkung",
    "gn:population":0,
    "gn:timezone":"Asia/Jakarta",
    "iso:country":"ID",
    "name:ind_x_preferred":[
        "Cijumungkung"
    ],
    "name:und_x_variant":[
        "Tjidjoemoengkoeng"
    ],
    "wof:lang_x_official":[
        "ind"
    ],
    "wof:lang_x_spoken":[
        "ind",
        "eng"
    ],
    "wof:name":"Cijumungkung",
    "wof:placetype":"locality"
},
  "geometry": {"coordinates":[107.97580000000001,-7.1949],"type":"Point"}
}