{
  "type": "Feature",
  "properties": {
    "gn:admin1_code":"30.0",
    "gn:asciiname":"Salagedang",
    "gn:country_code":"ID",
    "gn:dem":628,
    "gn:feature_class":"P",
    "gn:feature_code":"PPL",
    "gn:name":"Salagedang",
    "gn:population":0,
    "gn:timezone":"Asia/Jakarta",
    "iso:country":"ID",
    "name:ind_x_preferred":[
        "Salagedang"
    ],
    "name:und_x_variant":[
        "Selagedang"
    ],
    "wof:lang_x_official":[
        "ind"
    ],
    "wof:lang_x_spoken":[
        "ind",
        "eng"
    ],
    "wof:name":"Salagedang",
    "wof:placetype":"locality"
},
  "geometry": {"coordinates":[107.9659,-7.1091],"type":"Point"}
}