{
  "type": "Feature",
  "properties": {
    "gn:admin1_code":"28.0",
    "gn:asciiname":"Wakonit",
    "gn:country_code":"ID",
    "gn:dem":23,
    "gn:feature_class":"P",
    "gn:feature_code":"PPL",
    "gn:name":"Wakonit",
    "gn:population":0,
    "gn:timezone":"Asia/Jayapura",
    "iso:country":"ID",
    "name:ind_x_preferred":[
        "Wakonit"
    ],
    "name:und_x_variant":[
        "Wa Konit"
    ],
    "wof:name":"Wakonit",
    "wof:placetype":"locality"
},
  "geometry": {"coordinates":[126.89749999999999,-3.40915],"type":"Point"}
}