{
  "type": "Feature",
  "properties": {
    "gn:admin1_code":"10",
    "gn:asciiname":"Depok",
    "gn:country_code":"ID",
    "gn:dem":163,
    "gn:feature_class":"P",
    "gn:feature_code":"PPL",
    "gn:name":"Depok",
    "gn:population":0,
    "gn:timezone":"Asia/Jakarta",
    "iso:country":"ID",
    "name:afr_x_preferred":[
        "Depok"
    ],
    "name:ara_x_preferred":[
        "\u062f\u064a\u0628\u0648\u0643"
    ],
    "name:ast_x_preferred":[
        "Depok"
    ],
    "name:azb_x_preferred":[
        "\u062f\u0626\u067e\u0648\u06a9"
    ],
    "name:bel_x_preferred":[
        "\u0414\u044d\u043f\u0430\u043a"
    ],
    "name:bul_x_preferred":[
        "\u0414\u0435\u043f\u043e\u043a"
    ],
    "name:ceb_x_preferred":[
        "Depok"
    ],
    "name:ces_x_preferred":[
        "Depok"
    ],
    "name:che_x_preferred":[
        "\u0414\u0435\u043f\u043e\u043a"
    ],
    "name:deu_x_preferred":[
        "Depok"
    ],
    "name:epo_x_preferred":[
        "Depok"
    ],
    "name:eus_x_preferred":[
        "Depok"
    ],
    "name:fas_x_preferred":[
        "\u062f\u067e\u0648\u06a9"
    ],
    "name:fin_x_preferred":[
        "Depok"
    ],
    "name:fra_x_preferred":[
        "Depok"
    ],
    "name:heb_x_preferred":[
        "\u05d3\u05e4\u05d5\u05e7"
    ],
    "name:hun_x_preferred":[
        "Depok"
    ],
    "name:ido_x_preferred":[
        "Depok"
    ],
    "name:ind_x_preferred":[
        "Kota Depok"
    ],
    "name:ita_x_preferred":[
        "Depok"
    ],
    "name:jav_x_preferred":[
        "Kutha Dh\u00e9pok"
    ],
    "name:jpn_x_preferred":[
        "\u30c7\u30dd\u30c3\u30af"
    ],
    "name:kal_x_preferred":[
        "Depok"
    ],
    "name:kat_x_preferred":[
        "\u10d3\u10d4\u10de\u10dd\u10d9\u10d8"
    ],
    "name:lit_x_preferred":[
        "Depokas"
    ],
    "name:mlg_x_preferred":[
        "Kota Depok"
    ],
    "name:mri_x_preferred":[
        "Depok"
    ],
    "name:msa_x_preferred":[
        "Depok"
    ],
    "name:nld_x_preferred":[
        "Depok"
    ],
    "name:nor_x_preferred":[
        "Depok"
    ],
    "name:pol_x_preferred":[
        "Depok"
    ],
    "name:por_x_preferred":[
        "Depok"
    ],
    "name:ron_x_preferred":[
        "Depok"
    ],
    "name:rus_x_preferred":[
        "\u0414\u0435\u043f\u043e\u043a"
    ],
    "name:sco_x_preferred":[
        "Depok"
    ],
    "name:spa_x_preferred":[
        "Depok"
    ],
    "name:srp_x_preferred":[
        "\u0414\u0435\u043f\u043e\u043a"
    ],
    "name:sun_x_preferred":[
        "Kota D\u00e9pok"
    ],
    "name:swa_x_preferred":[
        "Depok"
    ],
    "name:swe_x_preferred":[
        "Depok"
    ],
    "name:tam_x_preferred":[
        "\u0ba4\u0bc6\u0baa\u0bcd\u0baa\u0bca"
    ],
    "name:tgl_x_preferred":[
        "Depok"
    ],
    "name:tha_x_preferred":[
        "\u0e40\u0e14\u0e1b\u0e01"
    ],
    "name:tur_x_preferred":[
        "Depok"
    ],
    "name:ukr_x_preferred":[
        "\u0414\u0435\u043f\u043e\u043a"
    ],
    "name:urd_x_preferred":[
        "\u062f\u06cc\u067e\u0648\u06a9"
    ],
    "name:vie_x_preferred":[
        "Depok"
    ],
    "name:war_x_preferred":[
        "Depok"
    ],
    "wof:name":"Depok",
    "wof:placetype":"locality"
},
  "geometry": {"coordinates":[110.51639,-7.82806],"type":"Point"}
}