{
  "type": "Feature",
  "properties": {
    "gn:admin1_code":"1",
    "gn:asciiname":"Jamburreuloim",
    "gn:country_code":"ID",
    "gn:dem":1329,
    "gn:feature_class":"P",
    "gn:feature_code":"PPL",
    "gn:name":"Jamburreuloim",
    "gn:population":0,
    "gn:timezone":"Asia/Jakarta",
    "iso:country":"ID",
    "name:ind_x_preferred":[
        "Jamburreuloim"
    ],
    "name:und_x_variant":[
        "Djamburreuloim"
    ],
    "wof:name":"Jamburreuloim",
    "wof:placetype":"locality"
},
  "geometry": {"coordinates":[96.6473,4.4268],"type":"Point"}
}