{
  "type": "Feature",
  "properties": {
    "gn:admin1_code":"37",
    "gn:asciiname":"Mendut",
    "gn:country_code":"ID",
    "gn:dem":12,
    "gn:feature_class":"P",
    "gn:feature_code":"PPL",
    "gn:name":"Mendut",
    "gn:population":0,
    "gn:timezone":"Asia/Jakarta",
    "iso:country":"ID",
    "name:hin_x_preferred":[
        "\u092e\u0947\u0928\u094d\u0926\u0941\u0924"
    ],
    "name:ind_x_preferred":[
        "Mendut"
    ],
    "name:ind_x_variant":[
        "Candi Mendut"
    ],
    "name:jav_x_preferred":[
        "Candhi Mendut"
    ],
    "name:kat_x_preferred":[
        "\u10db\u10d4\u10dc\u10d3\u10e3\u10e2\u10d8"
    ],
    "name:msa_x_preferred":[
        "Candi Mendut"
    ],
    "name:nld_x_preferred":[
        "Candi Mendut"
    ],
    "name:sun_x_preferred":[
        "Candi Mendut"
    ],
    "wof:lang_x_official":[
        "ind"
    ],
    "wof:lang_x_spoken":[
        "ind",
        "eng"
    ],
    "wof:name":"Mendut",
    "wof:placetype":"locality"
},
  "geometry": {"coordinates":[101.43246000000001,1.62037],"type":"Point"}
}