{
  "type": "Feature",
  "properties": {
    "gn:admin1_code":"17.0",
    "gn:asciiname":"Paoqgading",
    "gn:country_code":"ID",
    "gn:dem":204,
    "gn:feature_class":"P",
    "gn:feature_code":"PPL",
    "gn:name":"Paoqgading",
    "gn:population":0,
    "gn:timezone":"Asia/Makassar",
    "iso:country":"ID",
    "name:ind_x_preferred":[
        "Paoqgading"
    ],
    "wof:name":"Paoqgading",
    "wof:placetype":"locality"
},
  "geometry": {"coordinates":[116.2966,-8.2841],"type":"Point"}
}