{
  "type": "Feature",
  "properties": {
    "gn:admin1_code":"8.0",
    "gn:asciiname":"Kuwung",
    "gn:country_code":"ID",
    "gn:dem":25,
    "gn:feature_class":"P",
    "gn:feature_code":"PPL",
    "gn:name":"Kuwung",
    "gn:population":0,
    "gn:timezone":"Asia/Jakarta",
    "iso:country":"ID",
    "name:ind_x_preferred":[
        "Kuwung"
    ],
    "wof:name":"Kuwung",
    "wof:placetype":"locality"
},
  "geometry": {"coordinates":[112.44629999999999,-7.4842],"type":"Point"}
}