{
  "type": "Feature",
  "properties": {
    "gn:admin1_code":"8.0",
    "gn:asciiname":"Krajan Tengah",
    "gn:country_code":"ID",
    "gn:dem":344,
    "gn:feature_class":"P",
    "gn:feature_code":"PPLA4",
    "gn:name":"Krajan Tengah",
    "gn:population":0,
    "gn:timezone":"Asia/Jakarta",
    "iso:country":"ID",
    "name:ind_x_preferred":[
        "Krajan Tengah"
    ],
    "wof:lang_x_official":[
        "ind"
    ],
    "wof:lang_x_spoken":[
        "ind",
        "eng"
    ],
    "wof:name":"Krajan Tengah",
    "wof:placetype":"locality"
},
  "geometry": {"coordinates":[114.0325,-8.3035],"type":"Point"}
}