{
  "type": "Feature",
  "properties": {
    "gn:admin1_code":"07",
    "gn:asciiname":"Kecandran",
    "gn:cc2":"ID",
    "gn:country_code":"ID",
    "gn:dem":589,
    "gn:feature_class":"P",
    "gn:feature_code":"PPL",
    "gn:name":"Kecandran",
    "gn:population":0,
    "gn:timezone":"Asia/Jakarta",
    "iso:country":"ID",
    "name:und_x_variant":[
        "Ketjandran",
        "Kecandran"
    ],
    "wof:name":"Kecandran",
    "wof:placetype":"locality"
},
  "geometry": {"coordinates":[110.47389,-7.34111],"type":"Point"}
}