{
  "type": "Feature",
  "properties": {
    "gn:country":"ID",
    "gn:fcode":"PPLA3",
    "gn:pop":0,
    "iso:country":"ID",
    "name:ace_x_preferred":[
        "Cikalong"
    ],
    "name:cat_x_preferred":[
        "Cikalong"
    ],
    "name:ceb_x_preferred":[
        "Cikalong"
    ],
    "name:ces_x_preferred":[
        "Cikalong"
    ],
    "name:dan_x_preferred":[
        "Cikalong"
    ],
    "name:deu_x_preferred":[
        "Cikalong"
    ],
    "name:eng_x_preferred":[
        "Cikalong"
    ],
    "name:eus_x_preferred":[
        "Cikalong"
    ],
    "name:fin_x_preferred":[
        "Cikalong"
    ],
    "name:hrv_x_preferred":[
        "Cikalong"
    ],
    "name:ind_x_preferred":[
        "Cikalong"
    ],
    "name:ita_x_preferred":[
        "Cikalong"
    ],
    "name:msa_x_preferred":[
        "Cikalong"
    ],
    "name:nld_x_preferred":[
        "Cikalong"
    ],
    "name:nno_x_preferred":[
        "Cikalong"
    ],
    "name:nob_x_preferred":[
        "Cikalong"
    ],
    "name:pol_x_preferred":[
        "Cikalong"
    ],
    "name:por_x_preferred":[
        "Cikalong"
    ],
    "name:ron_x_preferred":[
        "Cikalong"
    ],
    "name:sco_x_preferred":[
        "Cikalong"
    ],
    "name:slk_x_preferred":[
        "Cikalong"
    ],
    "name:slv_x_preferred":[
        "Cikalong"
    ],
    "name:spa_x_preferred":[
        "Cikalong"
    ],
    "name:sun_x_preferred":[
        "Cikalong"
    ],
    "name:swe_x_preferred":[
        "Cikalong"
    ],
    "name:tur_x_preferred":[
        "Cikalong"
    ],
    "name:unk_x_variant":[
        "Chikalong"
    ],
    "name:war_x_preferred":[
        "Cikalong"
    ],
    "qs:name":"Cikalong",
    "qs:photos_9r":0,
    "qs:photos_sr":0,
    "qs:pop_sr":"0",
    "wof:name":"Cikalong",
    "wof:placetype":"locality",
    "wof:population":0
},
  "geometry": {"coordinates":[108.17270000000001,-7.7623],"type":"Point"}
}