{
  "type": "Feature",
  "properties": {
    "gn:admin1_code":"7.0",
    "gn:asciiname":"Gajian",
    "gn:country_code":"ID",
    "gn:dem":115,
    "gn:feature_class":"P",
    "gn:feature_code":"PPL",
    "gn:name":"Gajian",
    "gn:population":0,
    "gn:timezone":"Asia/Jakarta",
    "iso:country":"ID",
    "wof:name":"Gajian",
    "wof:placetype":"locality"
},
  "geometry": {"coordinates":[110.92528,-7.29861],"type":"Point"}
}