{
  "type": "Feature",
  "properties": {
    "gn:country":"ID",
    "gn:fcode":"PPL",
    "gn:pop":0,
    "iso:country":"ID",
    "name:ind_x_preferred":[
        "Cibuburindah"
    ],
    "qs:name":"Cibuburindah",
    "qs:name_adm0":"Indonesia",
    "qs:name_adm1":"Jawa Barat",
    "qs:photos":2,
    "qs:photos_1k":1,
    "qs:photos_9k":1,
    "qs:photos_9r":1,
    "qs:photos_all":2,
    "qs:photos_sr":1,
    "qs:placetype":"Suburb",
    "qs:pop_sr":"0",
    "wof:name":"Cibuburindah",
    "wof:placetype":"neighbourhood",
    "wof:population":0
},
  "geometry": {"coordinates":[106.89,-6.3531],"type":"Point"}
}