{
  "type": "Feature",
  "properties": {
    "gn:admin1_code":"8.0",
    "gn:asciiname":"Mandugan Timur",
    "gn:country_code":"ID",
    "gn:dem":100,
    "gn:feature_class":"P",
    "gn:feature_code":"PPL",
    "gn:name":"Mandugan Timur",
    "gn:population":0,
    "gn:timezone":"Asia/Jakarta",
    "iso:country":"ID",
    "name:ind_x_preferred":[
        "Mandugan Timur"
    ],
    "wof:name":"Mandugan Timur",
    "wof:placetype":"locality"
},
  "geometry": {"coordinates":[113.4569,-6.9909],"type":"Point"}
}