{
  "type": "Feature",
  "properties": {
    "gn:admin1_code":"18",
    "gn:asciiname":"Builalu",
    "gn:country_code":"ID",
    "gn:dem":258,
    "gn:feature_class":"P",
    "gn:feature_code":"PPL",
    "gn:name":"Builalu",
    "gn:population":0,
    "gn:timezone":"Asia/Makassar",
    "iso:country":"ID",
    "wof:name":"Builalu",
    "wof:placetype":"locality"
},
  "geometry": {"coordinates":[125.15582999999999,-9.04167],"type":"Point"}
}