{
  "type": "Feature",
  "properties": {
    "gn:admin1_code":"2",
    "gn:asciiname":"Kerobokan",
    "gn:country_code":"ID",
    "gn:dem":10,
    "gn:feature_class":"P",
    "gn:feature_code":"PPL",
    "gn:name":"Kerobokan",
    "gn:population":0,
    "gn:timezone":"Asia/Makassar",
    "iso:country":"ID",
    "name:ceb_x_preferred":[
        "Kerobokan"
    ],
    "name:deu_x_preferred":[
        "Kerobokan"
    ],
    "name:ind_x_preferred":[
        "Kerobokan"
    ],
    "name:msa_x_preferred":[
        "Kerobokan"
    ],
    "name:nld_x_preferred":[
        "Kerobokan"
    ],
    "wof:lang_x_official":[
        "ind"
    ],
    "wof:lang_x_spoken":[
        "ind",
        "eng"
    ],
    "wof:name":"Kerobokan",
    "wof:placetype":"locality"
},
  "geometry": {"coordinates":[114.62130000000001,-8.3675],"type":"Point"}
}