{
  "type": "Feature",
  "properties": {
    "gn:admin1_code":"37",
    "gn:asciiname":"Paritpelita",
    "gn:country_code":"ID",
    "gn:dem":5,
    "gn:feature_class":"P",
    "gn:feature_code":"PPL",
    "gn:name":"Paritpelita",
    "gn:population":0,
    "gn:timezone":"Asia/Jakarta",
    "iso:country":"ID",
    "name:ind_x_preferred":[
        "Paritpelita"
    ],
    "wof:name":"Paritpelita",
    "wof:placetype":"locality"
},
  "geometry": {"coordinates":[103.04629,0.64288],"type":"Point"}
}