{
  "type": "Feature",
  "properties": {
    "gn:admin1_code":"36.0",
    "gn:asciiname":"Yawimu",
    "gn:country_code":"ID",
    "gn:dem":14,
    "gn:feature_class":"P",
    "gn:feature_code":"PPL",
    "gn:name":"Yawimu",
    "gn:population":0,
    "gn:timezone":"Asia/Jayapura",
    "iso:country":"ID",
    "name:und_x_variant":[
        "Jawimoe",
        "Jawimu",
        "Yawimu"
    ],
    "wof:name":"Yawimu",
    "wof:placetype":"locality"
},
  "geometry": {"coordinates":[139.67788000000002,-7.82871],"type":"Point"}
}