{
  "type": "Feature",
  "properties": {
    "gn:admin1_code":"18.0",
    "gn:asciiname":"Basmuti",
    "gn:country_code":"ID",
    "gn:dem":607,
    "gn:feature_class":"P",
    "gn:feature_code":"PPL",
    "gn:name":"Basmuti",
    "gn:population":0,
    "gn:timezone":"Asia/Makassar",
    "iso:country":"ID",
    "name:ind_x_preferred":[
        "Basmuti"
    ],
    "wof:name":"Basmuti",
    "wof:placetype":"locality"
},
  "geometry": {"coordinates":[124.0711,-9.6401],"type":"Point"}
}