{
  "type": "Feature",
  "properties": {
    "gn:admin1_code":"33.0",
    "gn:asciiname":"Kadusirung Hilir",
    "gn:country_code":"ID",
    "gn:dem":76,
    "gn:feature_class":"P",
    "gn:feature_code":"PPLA4",
    "gn:name":"Kadusirung Hilir",
    "gn:population":0,
    "gn:timezone":"Asia/Jakarta",
    "iso:country":"ID",
    "name:ind_x_preferred":[
        "Kadusirung Hilir"
    ],
    "name:und_x_variant":[
        "Kadoesaroeng-hilir"
    ],
    "wof:lang_x_official":[
        "ind"
    ],
    "wof:lang_x_spoken":[
        "ind",
        "eng"
    ],
    "wof:name":"Kadusirung Hilir",
    "wof:placetype":"locality"
},
  "geometry": {"coordinates":[105.935,-6.4296],"type":"Point"}
}