{
  "type": "Feature",
  "properties": {
    "gn:admin1_code":"31.0",
    "gn:asciiname":"Pusian",
    "gn:country_code":"ID",
    "gn:dem":135,
    "gn:feature_class":"P",
    "gn:feature_code":"PPL",
    "gn:name":"Pusian",
    "gn:population":0,
    "gn:timezone":"Asia/Makassar",
    "iso:country":"ID",
    "name:ind_x_preferred":[
        "Pusian"
    ],
    "name:und_x_variant":[
        "Poesian"
    ],
    "wof:name":"Pusian",
    "wof:placetype":"locality"
},
  "geometry": {"coordinates":[124.1606,0.6578],"type":"Point"}
}