{
  "type": "Feature",
  "properties": {
    "gn:admin1_code":"18.0",
    "gn:asciiname":"Dobana",
    "gn:country_code":"ID",
    "gn:dem":539,
    "gn:feature_class":"P",
    "gn:feature_code":"PPL",
    "gn:name":"Dobana",
    "gn:population":0,
    "gn:timezone":"Asia/Makassar",
    "iso:country":"ID",
    "name:ind_x_preferred":[
        "Dobana"
    ],
    "wof:name":"Dobana",
    "wof:placetype":"locality"
},
  "geometry": {"coordinates":[119.4208,-9.6058],"type":"Point"}
}