{
  "type": "Feature",
  "properties": {
    "gn:admin1_code":"38.0",
    "gn:asciiname":"Lipungan",
    "gn:country_code":"ID",
    "gn:dem":899,
    "gn:feature_class":"P",
    "gn:feature_code":"PPL",
    "gn:name":"Lipungan",
    "gn:population":0,
    "gn:timezone":"Asia/Makassar",
    "iso:country":"ID",
    "name:ind_x_preferred":[
        "Lipungan"
    ],
    "wof:name":"Lipungan",
    "wof:placetype":"locality"
},
  "geometry": {"coordinates":[119.7841,-2.9959],"type":"Point"}
}