{
  "type": "Feature",
  "properties": {
    "gn:admin1_code":"28.0",
    "gn:asciiname":"Ban Lafun",
    "gn:country_code":"ID",
    "gn:dem":437,
    "gn:feature_class":"P",
    "gn:feature_code":"PPL",
    "gn:name":"Ban Lafun",
    "gn:population":0,
    "gn:timezone":"Asia/Jayapura",
    "iso:country":"ID",
    "name:ind_x_preferred":[
        "Ban Lafun"
    ],
    "name:und_x_variant":[
        "Wa \u2019Nlapitlahin",
        "Ban Lafoen",
        "Ban Lafun"
    ],
    "wof:name":"Ban Lafun",
    "wof:placetype":"locality"
},
  "geometry": {"coordinates":[126.72427,-3.38961],"type":"Point"}
}