{
  "type": "Feature",
  "properties": {
    "gn:admin1_code":"30",
    "gn:asciiname":"Subur",
    "gn:country_code":"ID",
    "gn:dem":454,
    "gn:feature_class":"P",
    "gn:feature_code":"PPL",
    "gn:name":"Subur",
    "gn:population":0,
    "gn:timezone":"Asia/Jakarta",
    "iso:country":"ID",
    "name:ind_x_preferred":[
        "Subur"
    ],
    "wof:name":"Subur",
    "wof:placetype":"locality"
},
  "geometry": {"coordinates":[108.50239999999999,-6.9809],"type":"Point"}
}