{
  "type": "Feature",
  "properties": {
    "gn:admin1_code":"7.0",
    "gn:asciiname":"Kedungan Tiga",
    "gn:country_code":"ID",
    "gn:dem":296,
    "gn:feature_class":"P",
    "gn:feature_code":"PPL",
    "gn:name":"Kedungan Tiga",
    "gn:population":0,
    "gn:timezone":"Asia/Jakarta",
    "iso:country":"ID",
    "wof:name":"Kedungan Tiga",
    "wof:placetype":"locality"
},
  "geometry": {"coordinates":[110.22750000000001,-7.63778],"type":"Point"}
}