{
  "type": "Feature",
  "properties": {
    "gn:admin1_code":"8.0",
    "gn:asciiname":"Dukuh",
    "gn:country_code":"ID",
    "gn:dem":202,
    "gn:feature_class":"P",
    "gn:feature_code":"PPL",
    "gn:name":"Dukuh",
    "gn:population":0,
    "gn:timezone":"Asia/Jakarta",
    "iso:country":"ID",
    "name:ind_x_preferred":[
        "Dukuh"
    ],
    "wof:name":"Dukuh",
    "wof:placetype":"locality"
},
  "geometry": {"coordinates":[111.6212,-6.9582],"type":"Point"}
}