{
  "type": "Feature",
  "properties": {
    "gn:admin1_code":"07",
    "gn:asciiname":"Sidorejo-lor",
    "gn:cc2":"ID",
    "gn:country_code":"ID",
    "gn:dem":567,
    "gn:feature_class":"P",
    "gn:feature_code":"PPL",
    "gn:name":"Sidorejo-lor",
    "gn:population":0,
    "gn:timezone":"Asia/Jakarta",
    "iso:country":"ID",
    "name:und_x_variant":[
        "Sidoredjo-lor",
        "Sidorejo-lor"
    ],
    "wof:lang_x_official":[
        "ind"
    ],
    "wof:lang_x_spoken":[
        "ind",
        "eng"
    ],
    "wof:name":"Sidorejo-lor",
    "wof:placetype":"locality"
},
  "geometry": {"coordinates":[110.49056,-7.31278],"type":"Point"}
}