{
  "type": "Feature",
  "properties": {
    "gn:admin1_code":"38",
    "gn:asciiname":"Bontobaddo",
    "gn:country_code":"ID",
    "gn:dem":19,
    "gn:feature_class":"P",
    "gn:feature_code":"PPL",
    "gn:name":"Bontobaddo",
    "gn:population":0,
    "gn:timezone":"Asia/Makassar",
    "iso:country":"ID",
    "name:ind_x_preferred":[
        "Bontobaddo"
    ],
    "wof:name":"Bontobaddo",
    "wof:placetype":"locality"
},
  "geometry": {"coordinates":[119.4804,-5.2268],"type":"Point"}
}