{
  "type": "Feature",
  "properties": {
    "gn:admin1_code":"30.0",
    "gn:asciiname":"Cililitan",
    "gn:country_code":"ID",
    "gn:dem":824,
    "gn:feature_class":"P",
    "gn:feature_code":"PPL",
    "gn:name":"Cililitan",
    "gn:population":0,
    "gn:timezone":"Asia/Jakarta",
    "iso:country":"ID",
    "name:ind_x_preferred":[
        "Cililitan"
    ],
    "name:und_x_variant":[
        "Lilitan"
    ],
    "wof:name":"Cililitan",
    "wof:placetype":"locality"
},
  "geometry": {"coordinates":[108.2817,-7.1025],"type":"Point"}
}