{
  "type": "Feature",
  "properties": {
    "gn:admin1_code":"30.0",
    "gn:asciiname":"Bojonggenteng",
    "gn:country_code":"ID",
    "gn:dem":599,
    "gn:feature_class":"P",
    "gn:feature_code":"PPL",
    "gn:name":"Bojonggenteng",
    "gn:population":0,
    "gn:timezone":"Asia/Jakarta",
    "iso:country":"ID",
    "name:ind_x_preferred":[
        "Bojonggenteng"
    ],
    "name:und_x_variant":[
        "Bodjonggenteng",
        "Bojonggenteng"
    ],
    "wof:lang_x_official":[
        "ind"
    ],
    "wof:lang_x_spoken":[
        "ind",
        "eng"
    ],
    "wof:name":"Bojonggenteng",
    "wof:placetype":"locality"
},
  "geometry": {"coordinates":[106.5613,-7.1515],"type":"Point"}
}