{
  "type": "Feature",
  "properties": {
    "gn:admin1_code":"18.0",
    "gn:asciiname":"Weeraka",
    "gn:country_code":"ID",
    "gn:dem":520,
    "gn:feature_class":"P",
    "gn:feature_code":"PPL",
    "gn:name":"Weeraka",
    "gn:population":0,
    "gn:timezone":"Asia/Makassar",
    "iso:country":"ID",
    "name:ind_x_preferred":[
        "Weeraka"
    ],
    "wof:name":"Weeraka",
    "wof:placetype":"locality"
},
  "geometry": {"coordinates":[119.45489999999999,-9.5457],"type":"Point"}
}