{
  "type": "Feature",
  "properties": {
    "gn:admin1_code":"7",
    "gn:asciiname":"Wotgalar",
    "gn:country_code":"ID",
    "gn:dem":1401,
    "gn:feature_class":"P",
    "gn:feature_code":"PPL",
    "gn:name":"Wotgalar",
    "gn:population":0,
    "gn:timezone":"Asia/Jakarta",
    "iso:country":"ID",
    "name:ind_x_preferred":[
        "Wotgalar"
    ],
    "wof:name":"Wotgalar",
    "wof:placetype":"locality"
},
  "geometry": {"coordinates":[109.76027999999999,-7.20944],"type":"Point"}
}