{
  "type": "Feature",
  "properties": {
    "gn:admin1_code":"7.0",
    "gn:asciiname":"Grugul",
    "gn:country_code":"ID",
    "gn:dem":149,
    "gn:feature_class":"P",
    "gn:feature_code":"PPL",
    "gn:name":"Grugul",
    "gn:population":0,
    "gn:timezone":"Asia/Jakarta",
    "iso:country":"ID",
    "name:ind_x_preferred":[
        "Grugul"
    ],
    "wof:name":"Grugul",
    "wof:placetype":"locality"
},
  "geometry": {"coordinates":[109.48611,-7.29972],"type":"Point"}
}