{
  "type": "Feature",
  "properties": {
    "gn:admin1_code":"8.0",
    "gn:asciiname":"Tajjan Barat",
    "gn:country_code":"ID",
    "gn:dem":156,
    "gn:feature_class":"P",
    "gn:feature_code":"PPL",
    "gn:name":"Tajjan Barat",
    "gn:population":0,
    "gn:timezone":"Asia/Jakarta",
    "iso:country":"ID",
    "name:ind_x_preferred":[
        "Tajjan Barat"
    ],
    "wof:name":"Tajjan Barat",
    "wof:placetype":"locality"
},
  "geometry": {"coordinates":[113.3449,-6.9556],"type":"Point"}
}