{
  "type": "Feature",
  "properties": {
    "gn:admin1_code":"33.0",
    "gn:asciiname":"Kadupayung",
    "gn:country_code":"ID",
    "gn:dem":32,
    "gn:feature_class":"P",
    "gn:feature_code":"PPLA4",
    "gn:name":"Kadupayung",
    "gn:population":0,
    "gn:timezone":"Asia/Jakarta",
    "iso:country":"ID",
    "name:ind_x_preferred":[
        "Kadupayung"
    ],
    "wof:lang_x_official":[
        "ind"
    ],
    "wof:lang_x_spoken":[
        "ind",
        "eng"
    ],
    "wof:name":"Kadupayung",
    "wof:placetype":"locality"
},
  "geometry": {"coordinates":[105.8477,-6.3968],"type":"Point"}
}