{
  "type": "Feature",
  "properties": {
    "gn:admin1_code":"30.0",
    "gn:asciiname":"Peusar",
    "gn:country_code":"ID",
    "gn:dem":458,
    "gn:feature_class":"P",
    "gn:feature_code":"PPL",
    "gn:name":"Peusar",
    "gn:population":0,
    "gn:timezone":"Asia/Jakarta",
    "iso:country":"ID",
    "name:ind_x_preferred":[
        "Peusar"
    ],
    "name:und_x_variant":[
        "Peusa"
    ],
    "wof:name":"Peusar",
    "wof:placetype":"locality"
},
  "geometry": {"coordinates":[107.86388999999998,-6.68722],"type":"Point"}
}