{
  "type": "Feature",
  "properties": {
    "gn:admin1_code":"0.0",
    "gn:asciiname":"Sungairotan",
    "gn:cc2":"ID",
    "gn:country_code":"ID",
    "gn:dem":27,
    "gn:feature_class":"P",
    "gn:feature_code":"PPL",
    "gn:name":"Sungairotan",
    "gn:population":0,
    "gn:timezone":"Asia/Jakarta",
    "iso:country":"ID",
    "name:und_x_variant":[
        "Soengairoean",
        "Sungaireng",
        "Soengairotan",
        "Sungairuan",
        "Sungairotan"
    ],
    "wof:lang_x_official":[
        "ind"
    ],
    "wof:lang_x_spoken":[
        "ind",
        "eng"
    ],
    "wof:name":"Sungairotan",
    "wof:placetype":"locality"
},
  "geometry": {"coordinates":[102.84999999999999,-1.65],"type":"Point"}
}