{
  "type": "Feature",
  "properties": {
    "gn:admin1_code":"2",
    "gn:asciiname":"Banjar Bukitcatu",
    "gn:country_code":"ID",
    "gn:dem":1280,
    "gn:feature_class":"P",
    "gn:feature_code":"PPL",
    "gn:name":"Banjar Bukitcatu",
    "gn:population":0,
    "gn:timezone":"Asia/Makassar",
    "iso:country":"ID",
    "name:ind_x_preferred":[
        "Banjar Bukitcatu"
    ],
    "wof:name":"Banjar Bukitcatu",
    "wof:placetype":"locality"
},
  "geometry": {"coordinates":[115.16249999999999,-8.2839],"type":"Point"}
}