{
  "type": "Feature",
  "properties": {
    "gn:admin1_code":"17.0",
    "gn:asciiname":"Pamegatan",
    "gn:country_code":"ID",
    "gn:dem":232,
    "gn:feature_class":"P",
    "gn:feature_code":"PPL",
    "gn:name":"Pamegatan",
    "gn:population":0,
    "gn:timezone":"Asia/Makassar",
    "iso:country":"ID",
    "name:ind_x_preferred":[
        "Pamegatan"
    ],
    "wof:name":"Pamegatan",
    "wof:placetype":"locality"
},
  "geometry": {"coordinates":[116.08799999999999,-8.7985],"type":"Point"}
}