{
  "type": "Feature",
  "properties": {
    "gn:admin1_code":"8.0",
    "gn:asciiname":"Sumberwadung",
    "gn:country_code":"ID",
    "gn:dem":88,
    "gn:feature_class":"P",
    "gn:feature_code":"PPL",
    "gn:name":"Sumberwadung",
    "gn:population":0,
    "gn:timezone":"Asia/Jakarta",
    "iso:country":"ID",
    "name:ind_x_preferred":[
        "Sumberwadung"
    ],
    "wof:name":"Sumberwadung",
    "wof:placetype":"locality"
},
  "geometry": {"coordinates":[113.1845,-8.1202],"type":"Point"}
}