{
  "type": "Feature",
  "properties": {
    "gn:admin1_code":"22",
    "gn:asciiname":"Tobengge",
    "gn:country_code":"ID",
    "gn:dem":57,
    "gn:feature_class":"P",
    "gn:feature_code":"PPL",
    "gn:name":"Tobengge",
    "gn:population":0,
    "gn:timezone":"Asia/Makassar",
    "iso:country":"ID",
    "name:ind_x_preferred":[
        "Tobengge"
    ],
    "wof:name":"Tobengge",
    "wof:placetype":"locality"
},
  "geometry": {"coordinates":[122.08369999999999,-3.9878],"type":"Point"}
}