{
  "type": "Feature",
  "properties": {
    "gn:admin1_code":"30.0",
    "gn:asciiname":"Malati",
    "gn:country_code":"ID",
    "gn:dem":536,
    "gn:feature_class":"P",
    "gn:feature_code":"PPLA4",
    "gn:name":"Malati",
    "gn:population":0,
    "gn:timezone":"Asia/Jakarta",
    "iso:country":"ID",
    "name:ind_x_preferred":[
        "Malati"
    ],
    "wof:lang_x_official":[
        "ind"
    ],
    "wof:lang_x_spoken":[
        "ind",
        "eng"
    ],
    "wof:name":"Malati",
    "wof:placetype":"locality"
},
  "geometry": {"coordinates":[107.3218,-7.3611],"type":"Point"}
}