{
  "type": "Feature",
  "properties": {
    "gn:admin1_code":"1",
    "gn:asciiname":"Payajagat",
    "gn:country_code":"ID",
    "gn:dem":1252,
    "gn:feature_class":"P",
    "gn:feature_code":"PPL",
    "gn:name":"Payajagat",
    "gn:population":0,
    "gn:timezone":"Asia/Jakarta",
    "iso:country":"ID",
    "name:ind_x_preferred":[
        "Payajagat"
    ],
    "name:und_x_variant":[
        "Pajadjagat"
    ],
    "wof:name":"Payajagat",
    "wof:placetype":"locality"
},
  "geometry": {"coordinates":[96.8297,4.5635],"type":"Point"}
}