{
  "type": "Feature",
  "properties": {
    "gn:admin1_code":"28.0",
    "gn:asciiname":"Wawalu Baman Satu",
    "gn:country_code":"ID",
    "gn:dem":15,
    "gn:feature_class":"P",
    "gn:feature_code":"PPL",
    "gn:name":"Wawalu Baman Satu",
    "gn:population":0,
    "gn:timezone":"Asia/Jayapura",
    "iso:country":"ID",
    "name:ind_x_preferred":[
        "Wawalu Baman Satu"
    ],
    "name:und_x_variant":[
        "Wawalu Bamane I",
        "Wa Waloe Baman I"
    ],
    "wof:lang_x_official":[
        "ind"
    ],
    "wof:lang_x_spoken":[
        "ind",
        "eng"
    ],
    "wof:name":"Wawalu Baman Satu",
    "wof:placetype":"locality"
},
  "geometry": {"coordinates":[126.93335,-3.40335],"type":"Point"}
}