{
  "type": "Feature",
  "properties": {
    "gn:admin1_code":"18.0",
    "gn:asciiname":"Tibutana",
    "gn:country_code":"ID",
    "gn:dem":414,
    "gn:feature_class":"P",
    "gn:feature_code":"PPLA4",
    "gn:name":"Tibutana",
    "gn:population":0,
    "gn:timezone":"Asia/Makassar",
    "iso:country":"ID",
    "name:ind_x_preferred":[
        "Tibutana"
    ],
    "wof:lang_x_official":[
        "ind"
    ],
    "wof:lang_x_spoken":[
        "ind",
        "eng"
    ],
    "wof:name":"Tibutana",
    "wof:placetype":"locality"
},
  "geometry": {"coordinates":[119.4259,-9.6337],"type":"Point"}
}