{
  "type": "Feature",
  "properties": {
    "gn:admin1_code":"7.0",
    "gn:asciiname":"Watukarung",
    "gn:country_code":"ID",
    "gn:dem":274,
    "gn:feature_class":"P",
    "gn:feature_code":"PPL",
    "gn:name":"Watukarung",
    "gn:population":0,
    "gn:timezone":"Asia/Jakarta",
    "iso:country":"ID",
    "wof:name":"Watukarung",
    "wof:placetype":"locality"
},
  "geometry": {"coordinates":[110.18222,-7.52917],"type":"Point"}
}