{
  "type": "Feature",
  "properties": {
    "gn:admin1_code":"7",
    "gn:asciiname":"Tanubayan",
    "gn:country_code":"ID",
    "gn:dem":8,
    "gn:feature_class":"P",
    "gn:feature_code":"PPL",
    "gn:name":"Tanubayan",
    "gn:population":0,
    "gn:timezone":"Asia/Jakarta",
    "iso:country":"ID",
    "name:ind_x_preferred":[
        "Tanubayan"
    ],
    "wof:name":"Tanubayan",
    "wof:placetype":"locality"
},
  "geometry": {"coordinates":[110.6454,-6.8905],"type":"Point"}
}