{
  "type": "Feature",
  "properties": {
    "gn:admin1_code":"38.0",
    "gn:asciiname":"Tondokbangala",
    "gn:country_code":"ID",
    "gn:dem":1086,
    "gn:feature_class":"P",
    "gn:feature_code":"PPL",
    "gn:name":"Tondokbangala",
    "gn:population":0,
    "gn:timezone":"Asia/Makassar",
    "iso:country":"ID",
    "name:ind_x_preferred":[
        "Tondokbangala"
    ],
    "wof:name":"Tondokbangala",
    "wof:placetype":"locality"
},
  "geometry": {"coordinates":[120.0031,-3.1913],"type":"Point"}
}