{
  "type": "Feature",
  "properties": {
    "gn:admin1_code":"30",
    "gn:asciiname":"Cipambuan",
    "gn:country_code":"ID",
    "gn:dem":192,
    "gn:feature_class":"P",
    "gn:feature_code":"PPL",
    "gn:name":"Cipambuan",
    "gn:population":0,
    "gn:timezone":"Asia/Jakarta",
    "iso:country":"ID",
    "name:ind_x_preferred":[
        "Cipambuan"
    ],
    "wof:name":"Cipambuan",
    "wof:placetype":"locality"
},
  "geometry": {"coordinates":[106.84639,-6.55861],"type":"Point"}
}