{
  "type": "Feature",
  "properties": {
    "gn:admin1_code":"38",
    "gn:asciiname":"Cempaga",
    "gn:country_code":"ID",
    "gn:dem":23,
    "gn:feature_class":"P",
    "gn:feature_code":"PPL",
    "gn:name":"Cempaga",
    "gn:population":0,
    "gn:timezone":"Asia/Makassar",
    "iso:country":"ID",
    "name:ind_x_preferred":[
        "Cempaga"
    ],
    "wof:name":"Cempaga",
    "wof:placetype":"locality"
},
  "geometry": {"coordinates":[120.3443,-4.4974],"type":"Point"}
}