{
  "type": "Feature",
  "properties": {
    "gn:admin1_code":"30",
    "gn:asciiname":"Tanjakan",
    "gn:country_code":"ID",
    "gn:dem":790,
    "gn:feature_class":"P",
    "gn:feature_code":"PPL",
    "gn:name":"Tanjakan",
    "gn:population":0,
    "gn:timezone":"Asia/Jakarta",
    "iso:country":"ID",
    "name:ind_x_preferred":[
        "Tanjakan"
    ],
    "wof:name":"Tanjakan",
    "wof:placetype":"locality"
},
  "geometry": {"coordinates":[107.87090000000001,-7.2049],"type":"Point"}
}