{
  "type": "Feature",
  "properties": {
    "gn:admin1_code":"7.0",
    "gn:asciiname":"Cirahab",
    "gn:country_code":"ID",
    "gn:dem":51,
    "gn:feature_class":"P",
    "gn:feature_code":"PPL",
    "gn:name":"Cirahab",
    "gn:population":0,
    "gn:timezone":"Asia/Jakarta",
    "iso:country":"ID",
    "name:ind_x_preferred":[
        "Cirahab"
    ],
    "wof:name":"Cirahab",
    "wof:placetype":"locality"
},
  "geometry": {"coordinates":[109.03806000000002,-7.49083],"type":"Point"}
}