{
  "type": "Feature",
  "properties": {
    "gn:admin1_code":"30",
    "gn:asciiname":"Cimuntuk",
    "gn:country_code":"ID",
    "gn:dem":242,
    "gn:feature_class":"P",
    "gn:feature_code":"PPL",
    "gn:name":"Cimuntuk",
    "gn:population":0,
    "gn:timezone":"Asia/Jakarta",
    "iso:country":"ID",
    "name:ind_x_preferred":[
        "Cimuntuk"
    ],
    "wof:name":"Cimuntuk",
    "wof:placetype":"locality"
},
  "geometry": {"coordinates":[107.41028,-6.61278],"type":"Point"}
}