{
  "type": "Feature",
  "properties": {
    "gn:admin1_code":"30",
    "gn:asciiname":"Citiwu",
    "gn:country_code":"ID",
    "gn:dem":1270,
    "gn:feature_class":"P",
    "gn:feature_code":"PPL",
    "gn:name":"Citiwu",
    "gn:population":0,
    "gn:timezone":"Asia/Jakarta",
    "iso:country":"ID",
    "name:ind_x_preferred":[
        "Citiwu"
    ],
    "name:und_x_variant":[
        "Tjitiwu"
    ],
    "wof:lang_x_official":[
        "ind"
    ],
    "wof:lang_x_spoken":[
        "ind",
        "eng"
    ],
    "wof:name":"Citiwu",
    "wof:placetype":"locality"
},
  "geometry": {"coordinates":[107.44070000000001,-7.1183],"type":"Point"}
}