{
  "type": "Feature",
  "properties": {
    "gn:admin1_code":"37.0",
    "gn:asciiname":"Airhitam",
    "gn:country_code":"ID",
    "gn:dem":37,
    "gn:feature_class":"P",
    "gn:feature_code":"PPL",
    "gn:name":"Airhitam",
    "gn:population":0,
    "gn:timezone":"Asia/Jakarta",
    "iso:country":"ID",
    "name:ind_x_preferred":[
        "Airhitam"
    ],
    "wof:name":"Airhitam",
    "wof:placetype":"locality"
},
  "geometry": {"coordinates":[102.14583,-0.14336],"type":"Point"}
}