{
  "type": "Feature",
  "properties": {
    "gn:admin1_code":"7",
    "gn:asciiname":"Jetis",
    "gn:country_code":"ID",
    "gn:dem":294,
    "gn:feature_class":"P",
    "gn:feature_code":"PPL",
    "gn:name":"Jetis",
    "gn:population":0,
    "gn:timezone":"Asia/Jakarta",
    "iso:country":"ID",
    "name:ind_x_preferred":[
        "Jetis"
    ],
    "wof:name":"Jetis",
    "wof:placetype":"locality"
},
  "geometry": {"coordinates":[109.96861,-7.55056],"type":"Point"}
}