{
  "type": "Feature",
  "properties": {
    "gn:admin1_code":"28.0",
    "gn:asciiname":"Galela",
    "gn:country_code":"ID",
    "gn:dem":11,
    "gn:feature_class":"P",
    "gn:feature_code":"PPL",
    "gn:name":"Galela",
    "gn:population":0,
    "gn:timezone":"Asia/Jayapura",
    "iso:country":"ID",
    "name:ind_x_preferred":[
        "Galela"
    ],
    "name:und_x_variant":[
        "Gal\u00e9la"
    ],
    "wof:name":"Galela",
    "wof:placetype":"locality"
},
  "geometry": {"coordinates":[126.93282000000001,-3.14551],"type":"Point"}
}