{
  "type": "Feature",
  "properties": {
    "gn:admin1_code":"30",
    "gn:asciiname":"Depok",
    "gn:country_code":"ID",
    "gn:dem":1171,
    "gn:feature_class":"P",
    "gn:feature_code":"PPL",
    "gn:name":"Depok",
    "gn:population":0,
    "gn:timezone":"Asia/Jakarta",
    "iso:country":"ID",
    "wof:name":"Depok",
    "wof:placetype":"locality"
},
  "geometry": {"coordinates":[107.57832999999999,-7.12944],"type":"Point"}
}