{
  "type": "Feature",
  "properties": {
    "gn:admin1_code":"15.0",
    "gn:asciiname":"Umbulan Kuparan",
    "gn:country_code":"ID",
    "gn:dem":879,
    "gn:feature_class":"P",
    "gn:feature_code":"PPL",
    "gn:name":"Umbulan Kuparan",
    "gn:population":0,
    "gn:timezone":"Asia/Jakarta",
    "iso:country":"ID",
    "name:ind_x_preferred":[
        "Umbulan Kuparan"
    ],
    "wof:name":"Umbulan Kuparan",
    "wof:placetype":"locality"
},
  "geometry": {"coordinates":[104.09396,-4.97327],"type":"Point"}
}