{
  "type": "Feature",
  "properties": {
    "gn:admin1_code":"18.0",
    "gn:asciiname":"Kalara",
    "gn:country_code":"ID",
    "gn:dem":19,
    "gn:feature_class":"P",
    "gn:feature_code":"PPL",
    "gn:name":"Kalara",
    "gn:population":0,
    "gn:timezone":"Asia/Makassar",
    "iso:country":"ID",
    "name:ben_x_preferred":[
        "\u0995\u09cb\u09b2\u09a1\u09bc\u09be"
    ],
    "name:bpy_x_preferred":[
        "\u0995\u09be\u09b2\u09be\u09b0\u09be"
    ],
    "name:hif_x_preferred":[
        "Kalara"
    ],
    "name:ind_x_preferred":[
        "Kalara"
    ],
    "name:ita_x_preferred":[
        "Kalara"
    ],
    "name:msa_x_preferred":[
        "Kalara"
    ],
    "name:new_x_preferred":[
        "\u0915\u0932\u0930\u093e"
    ],
    "name:nld_x_preferred":[
        "Kalara"
    ],
    "name:por_x_preferred":[
        "Kalara"
    ],
    "name:vie_x_preferred":[
        "Kalara"
    ],
    "wof:lang_x_official":[
        "ind"
    ],
    "wof:lang_x_spoken":[
        "ind",
        "eng"
    ],
    "wof:name":"Kalara",
    "wof:placetype":"locality"
},
  "geometry": {"coordinates":[120.30629999999999,-9.685],"type":"Point"}
}