{
  "type": "Feature",
  "properties": {
    "gn:admin1_code":"18.0",
    "gn:asciiname":"Dizi",
    "gn:country_code":"ID",
    "gn:dem":1299,
    "gn:feature_class":"P",
    "gn:feature_code":"PPL",
    "gn:name":"Dizi",
    "gn:population":0,
    "gn:timezone":"Asia/Makassar",
    "iso:country":"ID",
    "name:deu_x_preferred":[
        "Dizi"
    ],
    "name:fra_x_preferred":[
        "Dizi"
    ],
    "name:ind_x_preferred":[
        "Dizi"
    ],
    "name:tur_x_preferred":[
        "Dizi"
    ],
    "wof:name":"Dizi",
    "wof:placetype":"locality"
},
  "geometry": {"coordinates":[121.0106,-8.8409],"type":"Point"}
}