{
  "type": "Feature",
  "properties": {
    "gn:admin1_code":"30",
    "gn:asciiname":"Tambunkelapa",
    "gn:country_code":"ID",
    "gn:dem":9,
    "gn:feature_class":"P",
    "gn:feature_code":"PPL",
    "gn:name":"Tambunkelapa",
    "gn:population":0,
    "gn:timezone":"Asia/Jakarta",
    "iso:country":"ID",
    "name:ind_x_preferred":[
        "Tambunkelapa"
    ],
    "name:und_x_variant":[
        "Tambunkalapa"
    ],
    "wof:name":"Tambunkelapa",
    "wof:placetype":"locality"
},
  "geometry": {"coordinates":[107.06610999999999,-6.20417],"type":"Point"}
}