{
  "type": "Feature",
  "properties": {
    "gn:admin1_code":"1",
    "gn:asciiname":"Tepin Kebu",
    "gn:country_code":"ID",
    "gn:dem":14,
    "gn:feature_class":"P",
    "gn:feature_code":"PPL",
    "gn:name":"Tepin Kebu",
    "gn:population":0,
    "gn:timezone":"Asia/Jakarta",
    "iso:country":"ID",
    "name:ind_x_preferred":[
        "Tepin Kebu"
    ],
    "wof:name":"Tepin Kebu",
    "wof:placetype":"locality"
},
  "geometry": {"coordinates":[97.3681,5.0061],"type":"Point"}
}