{
  "type": "Feature",
  "properties": {
    "gn:admin1_code":"1",
    "gn:asciiname":"Panjimulya Satu",
    "gn:country_code":"ID",
    "gn:dem":1516,
    "gn:feature_class":"P",
    "gn:feature_code":"PPL",
    "gn:name":"Panjimulya Satu",
    "gn:population":0,
    "gn:timezone":"Asia/Jakarta",
    "iso:country":"ID",
    "name:ind_x_preferred":[
        "Panjimulya Satu"
    ],
    "name:und_x_variant":[
        "Panji Mulya I"
    ],
    "wof:name":"Panjimulya Satu",
    "wof:placetype":"locality"
},
  "geometry": {"coordinates":[96.8807,4.7472],"type":"Point"}
}