{
  "type": "Feature",
  "properties": {
    "gn:admin1_code":"30.0",
    "gn:asciiname":"Lemburtugu",
    "gn:country_code":"ID",
    "gn:dem":1011,
    "gn:feature_class":"P",
    "gn:feature_code":"PPL",
    "gn:name":"Lemburtugu",
    "gn:population":0,
    "gn:timezone":"Asia/Jakarta",
    "iso:country":"ID",
    "name:ind_x_preferred":[
        "Lemburtugu"
    ],
    "wof:name":"Lemburtugu",
    "wof:placetype":"locality"
},
  "geometry": {"coordinates":[106.9978,-7.0482],"type":"Point"}
}