{
  "type": "Feature",
  "properties": {
    "gn:admin1_code":"8.0",
    "gn:asciiname":"Angsana Timur",
    "gn:country_code":"ID",
    "gn:dem":92,
    "gn:feature_class":"P",
    "gn:feature_code":"PPL",
    "gn:name":"Angsana Timur",
    "gn:population":0,
    "gn:timezone":"Asia/Jakarta",
    "iso:country":"ID",
    "name:ind_x_preferred":[
        "Angsana Timur"
    ],
    "wof:name":"Angsana Timur",
    "wof:placetype":"locality"
},
  "geometry": {"coordinates":[113.3552,-7.0485],"type":"Point"}
}