{
  "type": "Feature",
  "properties": {
    "gn:admin1_code":"37",
    "gn:asciiname":"Peredak",
    "gn:country_code":"ID",
    "gn:dem":11,
    "gn:feature_class":"P",
    "gn:feature_code":"PPL",
    "gn:name":"Peredak",
    "gn:population":0,
    "gn:timezone":"Asia/Jakarta",
    "iso:country":"ID",
    "name:ind_x_preferred":[
        "Peredak"
    ],
    "wof:name":"Peredak",
    "wof:placetype":"locality"
},
  "geometry": {"coordinates":[103.55445,-0.09615],"type":"Point"}
}