{
  "type": "Feature",
  "properties": {
    "gn:admin1_code":"30",
    "gn:asciiname":"Maudin",
    "gn:country_code":"ID",
    "gn:dem":48,
    "gn:feature_class":"P",
    "gn:feature_code":"PPL",
    "gn:name":"Maudin",
    "gn:population":0,
    "gn:timezone":"Asia/Jakarta",
    "iso:country":"ID",
    "name:ind_x_preferred":[
        "Maudin"
    ],
    "wof:name":"Maudin",
    "wof:placetype":"locality"
},
  "geometry": {"coordinates":[108.10444,-6.685],"type":"Point"}
}