{
  "type": "Feature",
  "properties": {
    "gn:admin1_code":"33",
    "gn:asciiname":"Kadikaran",
    "gn:country_code":"ID",
    "gn:dem":11,
    "gn:feature_class":"P",
    "gn:feature_code":"PPL",
    "gn:name":"Kadikaran",
    "gn:population":0,
    "gn:timezone":"Asia/Jakarta",
    "iso:country":"ID",
    "name:ind_x_preferred":[
        "Kadikaran"
    ],
    "wof:name":"Kadikaran",
    "wof:placetype":"locality"
},
  "geometry": {"coordinates":[106.2397,-6.1106],"type":"Point"}
}