{
  "type": "Feature",
  "properties": {
    "gn:admin1_code":"30",
    "gn:asciiname":"Kubang",
    "gn:country_code":"ID",
    "gn:dem":580,
    "gn:feature_class":"P",
    "gn:feature_code":"PPL",
    "gn:name":"Kubang",
    "gn:population":0,
    "gn:timezone":"Asia/Jakarta",
    "iso:country":"ID",
    "name:ind_x_preferred":[
        "Kubang"
    ],
    "wof:name":"Kubang",
    "wof:placetype":"locality"
},
  "geometry": {"coordinates":[108.15611,-6.96278],"type":"Point"}
}