{
  "type": "Feature",
  "properties": {
    "gn:admin1_code":"8.0",
    "gn:asciiname":"Dokpucung",
    "gn:country_code":"ID",
    "gn:dem":107,
    "gn:feature_class":"P",
    "gn:feature_code":"PPL",
    "gn:name":"Dokpucung",
    "gn:population":0,
    "gn:timezone":"Asia/Jakarta",
    "iso:country":"ID",
    "name:ind_x_preferred":[
        "Dokpucung"
    ],
    "wof:name":"Dokpucung",
    "wof:placetype":"locality"
},
  "geometry": {"coordinates":[110.96861,-8.21222],"type":"Point"}
}