{
  "type": "Feature",
  "properties": {
    "gn:admin1_code":"18",
    "gn:asciiname":"Pajo",
    "gn:country_code":"ID",
    "gn:dem":697,
    "gn:feature_class":"P",
    "gn:feature_code":"PPL",
    "gn:name":"Pajo",
    "gn:population":0,
    "gn:timezone":"Asia/Makassar",
    "iso:country":"ID",
    "name:ind_x_preferred":[
        "Pajo"
    ],
    "name:jav_x_preferred":[
        "Pajo"
    ],
    "name:msa_x_preferred":[
        "Pajo"
    ],
    "name:ukr_x_preferred":[
        "\u041f\u0430\u0434\u0436\u043e"
    ],
    "wof:lang_x_official":[
        "ind"
    ],
    "wof:lang_x_spoken":[
        "ind",
        "eng"
    ],
    "wof:name":"Pajo",
    "wof:placetype":"locality"
},
  "geometry": {"coordinates":[120.33159999999999,-8.5157],"type":"Point"}
}