{
  "type": "Feature",
  "properties": {
    "gn:admin1_code":"8",
    "gn:asciiname":"Renteng",
    "gn:country_code":"ID",
    "gn:dem":650,
    "gn:feature_class":"P",
    "gn:feature_code":"PPL",
    "gn:name":"Renteng",
    "gn:population":0,
    "gn:timezone":"Asia/Jakarta",
    "iso:country":"ID",
    "name:ind_x_preferred":[
        "Renteng"
    ],
    "wof:name":"Renteng",
    "wof:placetype":"locality"
},
  "geometry": {"coordinates":[113.0299,-8.1318],"type":"Point"}
}