{
  "type": "Feature",
  "properties": {
    "gn:admin1_code":"38",
    "gn:asciiname":"Lampang",
    "gn:country_code":"ID",
    "gn:dem":7,
    "gn:feature_class":"P",
    "gn:feature_code":"PPL",
    "gn:name":"Lampang",
    "gn:population":0,
    "gn:timezone":"Asia/Makassar",
    "iso:country":"ID",
    "name:azb_x_preferred":[
        "\u0644\u0627\u0645\u067e\u0627\u0646\u0642"
    ],
    "name:bod_x_preferred":[
        "\u0f63\u0f58\u0f0b\u0f54\u0f44\u0f0b\u0f0d"
    ],
    "name:ceb_x_preferred":[
        "Lampang"
    ],
    "name:ces_x_preferred":[
        "Lampang"
    ],
    "name:deu_x_preferred":[
        "Lampang"
    ],
    "name:fas_x_preferred":[
        "\u0644\u0627\u0645\u067e\u0627\u0646\u06af"
    ],
    "name:fin_x_preferred":[
        "Lampang"
    ],
    "name:fra_x_preferred":[
        "Lampang"
    ],
    "name:heb_x_preferred":[
        "\u05dc\u05de\u05e4\u05e0\u05d2"
    ],
    "name:hun_x_preferred":[
        "Lampang"
    ],
    "name:ind_x_preferred":[
        "Lampang"
    ],
    "name:ita_x_preferred":[
        "Lampang"
    ],
    "name:lit_x_preferred":[
        "Lampangas"
    ],
    "name:mal_x_preferred":[
        "\u0d32\u0d3e\u0d2e\u0d4d\u0d2a\u0d3e\u0d19\u0d4d"
    ],
    "name:mya_x_preferred":[
        "\u101c\u1019\u103a\u1015\u1014\u103a\u1038\u1019\u103c\u102d\u102f\u1037"
    ],
    "name:nld_x_preferred":[
        "Lampang"
    ],
    "name:pnb_x_preferred":[
        "\u0644\u0627\u0645\u067e\u0627\u0646\u06af"
    ],
    "name:pol_x_preferred":[
        "Lampang"
    ],
    "name:por_x_preferred":[
        "Lampang"
    ],
    "name:rus_x_preferred":[
        "\u041b\u0430\u043c\u043f\u0430\u043d\u0433"
    ],
    "name:spa_x_preferred":[
        "Lampang"
    ],
    "name:tha_x_preferred":[
        "\u0e40\u0e17\u0e28\u0e1a\u0e32\u0e25\u0e19\u0e04\u0e23\u0e25\u0e33\u0e1b\u0e32\u0e07"
    ],
    "name:urd_x_preferred":[
        "\u0644\u06cc\u0645\u067e\u06cc\u0646\u06af"
    ],
    "name:vie_x_preferred":[
        "Lampang"
    ],
    "name:war_x_preferred":[
        "Lampang"
    ],
    "wof:lang_x_official":[
        "ind"
    ],
    "wof:lang_x_spoken":[
        "ind",
        "eng"
    ],
    "wof:name":"Lampang",
    "wof:placetype":"locality"
},
  "geometry": {"coordinates":[119.40819999999999,-5.453],"type":"Point"}
}