{
  "type": "Feature",
  "properties": {
    "gn:admin1_code":"26",
    "gn:asciiname":"Sei Beras Sekata Pasar Lima",
    "gn:country_code":"ID",
    "gn:dem":39,
    "gn:feature_class":"P",
    "gn:feature_code":"PPL",
    "gn:name":"Sei Beras Sekata Pasar Lima",
    "gn:population":0,
    "gn:timezone":"Asia/Jakarta",
    "iso:country":"ID",
    "name:ind_x_preferred":[
        "Sei Beras Sekata Pasar Lima"
    ],
    "name:und_x_variant":[
        "Seiberassekatapasar 5"
    ],
    "wof:lang_x_official":[
        "ind"
    ],
    "wof:lang_x_spoken":[
        "ind",
        "eng"
    ],
    "wof:name":"Sei Beras Sekata Pasar Lima",
    "wof:placetype":"locality"
},
  "geometry": {"coordinates":[98.5994,3.5593],"type":"Point"}
}