{
  "type": "Feature",
  "properties": {
    "gn:admin1_code":"22.0",
    "gn:asciiname":"Kombungo",
    "gn:country_code":"ID",
    "gn:dem":49,
    "gn:feature_class":"P",
    "gn:feature_code":"PPL",
    "gn:name":"Kombungo",
    "gn:population":0,
    "gn:timezone":"Asia/Makassar",
    "iso:country":"ID",
    "name:ind_x_preferred":[
        "Kombungo"
    ],
    "wof:name":"Kombungo",
    "wof:placetype":"locality"
},
  "geometry": {"coordinates":[122.521,-5.1694],"type":"Point"}
}