{
  "type": "Feature",
  "properties": {
    "gn:admin1_code":"8",
    "gn:asciiname":"Kalianyar",
    "gn:country_code":"ID",
    "gn:dem":52,
    "gn:feature_class":"P",
    "gn:feature_code":"PPL",
    "gn:name":"Kalianyar",
    "gn:population":0,
    "gn:timezone":"Asia/Jakarta",
    "iso:country":"ID",
    "name:ind_x_preferred":[
        "Kalianyar"
    ],
    "wof:name":"Kalianyar",
    "wof:placetype":"locality"
},
  "geometry": {"coordinates":[112.06529999999999,-7.6443],"type":"Point"}
}