{
  "type": "Feature",
  "properties": {
    "gn:admin1_code":"7.0",
    "gn:asciiname":"Kalipan",
    "gn:country_code":"ID",
    "gn:dem":400,
    "gn:feature_class":"P",
    "gn:feature_code":"PPL",
    "gn:name":"Kalipan",
    "gn:population":0,
    "gn:timezone":"Asia/Jakarta",
    "iso:country":"ID",
    "wof:name":"Kalipan",
    "wof:placetype":"locality"
},
  "geometry": {"coordinates":[110.09528,-7.54333],"type":"Point"}
}