{
  "type": "Feature",
  "properties": {
    "gn:admin1_code":"8.0",
    "gn:asciiname":"Sentul",
    "gn:country_code":"ID",
    "gn:dem":22,
    "gn:feature_class":"P",
    "gn:feature_code":"PPLA4",
    "gn:name":"Sentul",
    "gn:population":0,
    "gn:timezone":"Asia/Jakarta",
    "iso:country":"ID",
    "name:ceb_x_preferred":[
        "Sentul"
    ],
    "name:ind_x_preferred":[
        "Setol"
    ],
    "name:ind_x_variant":[
        "Sentul"
    ],
    "name:nld_x_preferred":[
        "Sentul"
    ],
    "name:swe_x_preferred":[
        "Sentul"
    ],
    "name:und_x_variant":[
        "Sentoel",
        "Sentul"
    ],
    "wof:lang_x_official":[
        "ind"
    ],
    "wof:lang_x_spoken":[
        "ind",
        "eng"
    ],
    "wof:name":"Sentul",
    "wof:placetype":"locality"
},
  "geometry": {"coordinates":[112.43034,-6.88154],"type":"Point"}
}