{
  "type": "Feature",
  "properties": {
    "gn:admin1_code":"07",
    "gn:asciiname":"Rowosari",
    "gn:country_code":"ID",
    "gn:dem":467,
    "gn:feature_class":"P",
    "gn:feature_code":"PPL",
    "gn:name":"Rowosari",
    "gn:population":0,
    "gn:timezone":"Asia/Jakarta",
    "iso:country":"ID",
    "wof:name":"Rowosari",
    "wof:placetype":"locality"
},
  "geometry": {"coordinates":[110.44861000000002,-7.315],"type":"Point"}
}