{
  "type": "Feature",
  "properties": {
    "gn:admin1_code":"7.0",
    "gn:asciiname":"Sindang",
    "gn:country_code":"ID",
    "gn:dem":425,
    "gn:feature_class":"P",
    "gn:feature_code":"PPL",
    "gn:name":"Sindang",
    "gn:population":0,
    "gn:timezone":"Asia/Jakarta",
    "iso:country":"ID",
    "name:ind_x_preferred":[
        "Sindang"
    ],
    "wof:name":"Sindang",
    "wof:placetype":"locality"
},
  "geometry": {"coordinates":[109.05306000000002,-7.35444],"type":"Point"}
}