{
  "type": "Feature",
  "properties": {
    "gn:admin1_code":"5.0",
    "gn:asciiname":"Dusunmuarakutur",
    "gn:country_code":"ID",
    "gn:dem":75,
    "gn:feature_class":"P",
    "gn:feature_code":"PPL",
    "gn:name":"Dusunmuarakutur",
    "gn:population":0,
    "gn:timezone":"Asia/Jakarta",
    "iso:country":"ID",
    "name:ind_x_preferred":[
        "Dusunmuarakutur"
    ],
    "wof:name":"Dusunmuarakutur",
    "wof:placetype":"locality"
},
  "geometry": {"coordinates":[102.5943,-2.4881],"type":"Point"}
}