{
  "type": "Feature",
  "properties": {
    "gn:admin1_code":"15.0",
    "gn:asciiname":"Margokoyo",
    "gn:country_code":"ID",
    "gn:dem":83,
    "gn:feature_class":"P",
    "gn:feature_code":"PPL",
    "gn:name":"Margokoyo",
    "gn:population":0,
    "gn:timezone":"Asia/Jakarta",
    "iso:country":"ID",
    "name:ind_x_preferred":[
        "Margokoyo"
    ],
    "wof:name":"Margokoyo",
    "wof:placetype":"locality"
},
  "geometry": {"coordinates":[105.29868999999999,-5.30523],"type":"Point"}
}