{
  "type": "Feature",
  "properties": {
    "gn:admin1_code":"18.0",
    "gn:asciiname":"Kabandajawa",
    "gn:country_code":"ID",
    "gn:dem":204,
    "gn:feature_class":"P",
    "gn:feature_code":"PPL",
    "gn:name":"Kabandajawa",
    "gn:population":0,
    "gn:timezone":"Asia/Makassar",
    "iso:country":"ID",
    "name:ind_x_preferred":[
        "Kabandajawa"
    ],
    "wof:name":"Kabandajawa",
    "wof:placetype":"locality"
},
  "geometry": {"coordinates":[120.6327,-10.1511],"type":"Point"}
}