{
  "type": "Feature",
  "properties": {
    "gn:admin1_code":"0.0",
    "gn:asciiname":"Warudoyong",
    "gn:cc2":"ID",
    "gn:country_code":"ID",
    "gn:dem":28,
    "gn:feature_class":"P",
    "gn:feature_code":"PPL",
    "gn:name":"Warudoyong",
    "gn:population":0,
    "gn:timezone":"Asia/Jakarta",
    "iso:country":"ID",
    "name:und_x_variant":[
        "Waroedojong",
        "Warudojong",
        "Warudoyong"
    ],
    "wof:name":"Warudoyong",
    "wof:placetype":"locality"
},
  "geometry": {"coordinates":[106.90000000000001,-6.26667],"type":"Point"}
}