{
  "type": "Feature",
  "properties": {
    "gn:admin1_code":"38",
    "gn:asciiname":"Sarajoko",
    "gn:country_code":"ID",
    "gn:dem":323,
    "gn:feature_class":"P",
    "gn:feature_code":"PPL",
    "gn:name":"Sarajoko",
    "gn:population":0,
    "gn:timezone":"Asia/Makassar",
    "iso:country":"ID",
    "name:ind_x_preferred":[
        "Sarajoko"
    ],
    "wof:name":"Sarajoko",
    "wof:placetype":"locality"
},
  "geometry": {"coordinates":[120.1669,-5.3477],"type":"Point"}
}