{
  "type": "Feature",
  "properties": {
    "gn:admin1_code":"18.0",
    "gn:asciiname":"Laleramuq",
    "gn:country_code":"ID",
    "gn:dem":25,
    "gn:feature_class":"P",
    "gn:feature_code":"PPL",
    "gn:name":"Laleramuq",
    "gn:population":0,
    "gn:timezone":"Asia/Makassar",
    "iso:country":"ID",
    "name:ind_x_preferred":[
        "Laleramuq"
    ],
    "wof:name":"Laleramuq",
    "wof:placetype":"locality"
},
  "geometry": {"coordinates":[123.74850000000001,-8.1961],"type":"Point"}
}