{
  "type": "Feature",
  "properties": {
    "gn:admin1_code":"2",
    "gn:asciiname":"Banjar Tatiapi Kelod",
    "gn:country_code":"ID",
    "gn:dem":200,
    "gn:feature_class":"P",
    "gn:feature_code":"PPL",
    "gn:name":"Banjar Tatiapi Kelod",
    "gn:population":0,
    "gn:timezone":"Asia/Makassar",
    "iso:country":"ID",
    "name:ind_x_preferred":[
        "Banjar Tatiapi Kelod"
    ],
    "wof:name":"Banjar Tatiapi Kelod",
    "wof:placetype":"locality"
},
  "geometry": {"coordinates":[115.28660000000001,-8.5143],"type":"Point"}
}