{
  "type": "Feature",
  "properties": {
    "gn:admin1_code":"30",
    "gn:asciiname":"Cikoneng",
    "gn:country_code":"ID",
    "gn:dem":1028,
    "gn:feature_class":"P",
    "gn:feature_code":"PPL",
    "gn:name":"Cikoneng",
    "gn:population":0,
    "gn:timezone":"Asia/Jakarta",
    "iso:country":"ID",
    "name:ind_x_preferred":[
        "Cikoneng"
    ],
    "name:und_x_variant":[
        "Tjikoneng 1",
        "Cikoneng Satu"
    ],
    "wof:name":"Cikoneng",
    "wof:placetype":"locality"
},
  "geometry": {"coordinates":[107.4799,-7.0715],"type":"Point"}
}