{
  "type": "Feature",
  "properties": {
    "gn:admin1_code":"30.0",
    "gn:asciiname":"Sawahastana",
    "gn:country_code":"ID",
    "gn:dem":349,
    "gn:feature_class":"P",
    "gn:feature_code":"PPL",
    "gn:name":"Sawahastana",
    "gn:population":0,
    "gn:timezone":"Asia/Jakarta",
    "iso:country":"ID",
    "name:ind_x_preferred":[
        "Sawahastana"
    ],
    "wof:name":"Sawahastana",
    "wof:placetype":"locality"
},
  "geometry": {"coordinates":[107.0851,-7.2778],"type":"Point"}
}