{
  "type": "Feature",
  "properties": {
    "gn:admin1_code":"26",
    "gn:asciiname":"Tanjung Kuala",
    "gn:country_code":"ID",
    "gn:dem":448,
    "gn:feature_class":"P",
    "gn:feature_code":"PPL",
    "gn:name":"Tanjung Kuala",
    "gn:population":0,
    "gn:timezone":"Asia/Jakarta",
    "iso:country":"ID",
    "name:ind_x_preferred":[
        "Tanjung Kuala"
    ],
    "wof:name":"Tanjung Kuala",
    "wof:placetype":"locality"
},
  "geometry": {"coordinates":[98.2132,2.9408],"type":"Point"}
}