{
  "type": "Feature",
  "properties": {
    "gn:admin1_code":"41",
    "gn:asciiname":"Lelo",
    "gn:country_code":"ID",
    "gn:dem":10,
    "gn:feature_class":"P",
    "gn:feature_code":"PPL",
    "gn:name":"Lelo",
    "gn:population":0,
    "gn:timezone":"Asia/Makassar",
    "iso:country":"ID",
    "name:ceb_x_preferred":[
        "Lelo"
    ],
    "name:fra_x_preferred":[
        "Lelo"
    ],
    "name:ind_x_preferred":[
        "Lelo"
    ],
    "name:swe_x_preferred":[
        "Lelo"
    ],
    "wof:lang_x_official":[
        "ind"
    ],
    "wof:lang_x_spoken":[
        "ind",
        "eng"
    ],
    "wof:name":"Lelo",
    "wof:placetype":"locality"
},
  "geometry": {"coordinates":[119.05889999999999,-2.5145],"type":"Point"}
}