{
  "type": "Feature",
  "properties": {
    "gn:admin1_code":"17",
    "gn:asciiname":"Mendu",
    "gn:country_code":"ID",
    "gn:dem":66,
    "gn:feature_class":"P",
    "gn:feature_code":"PPL",
    "gn:name":"Mendu",
    "gn:population":0,
    "gn:timezone":"Asia/Makassar",
    "iso:country":"ID",
    "name:bpy_x_preferred":[
        "\u09ae\u09c7\u09a8\u09cd\u09a6\u09c1"
    ],
    "name:ind_x_preferred":[
        "Mendu"
    ],
    "name:ita_x_preferred":[
        "Mendu"
    ],
    "name:msa_x_preferred":[
        "Mendu"
    ],
    "name:new_x_preferred":[
        "\u092e\u0947\u0928\u094d\u0926\u0941"
    ],
    "name:nld_x_preferred":[
        "Mendu"
    ],
    "name:pol_x_preferred":[
        "Mendu"
    ],
    "name:por_x_preferred":[
        "Mendu"
    ],
    "name:urd_x_preferred":[
        "\u0645\u06cc\u0646\u0688\u0648"
    ],
    "name:vie_x_preferred":[
        "Mendu"
    ],
    "wof:name":"Mendu",
    "wof:placetype":"locality"
},
  "geometry": {"coordinates":[116.22020000000001,-8.7717],"type":"Point"}
}