{
  "type": "Feature",
  "properties": {
    "gn:admin1_code":"8.0",
    "gn:asciiname":"Balongsono",
    "gn:country_code":"ID",
    "gn:dem":29,
    "gn:feature_class":"P",
    "gn:feature_code":"PPL",
    "gn:name":"Balongsono",
    "gn:population":0,
    "gn:timezone":"Asia/Jakarta",
    "iso:country":"ID",
    "name:ind_x_preferred":[
        "Balongsono"
    ],
    "wof:name":"Balongsono",
    "wof:placetype":"locality"
},
  "geometry": {"coordinates":[112.3498,-7.5098],"type":"Point"}
}