{
  "type": "Feature",
  "properties": {
    "gn:admin1_code":"38",
    "gn:asciiname":"Bongkong",
    "gn:country_code":"ID",
    "gn:dem":77,
    "gn:feature_class":"P",
    "gn:feature_code":"PPL",
    "gn:name":"Bongkong",
    "gn:population":0,
    "gn:timezone":"Asia/Makassar",
    "iso:country":"ID",
    "name:ind_x_preferred":[
        "Bongkong"
    ],
    "wof:name":"Bongkong",
    "wof:placetype":"locality"
},
  "geometry": {"coordinates":[120.17829999999999,-5.1482],"type":"Point"}
}