{
  "type": "Feature",
  "properties": {
    "gn:admin1_code":"7",
    "gn:asciiname":"Blokbeji",
    "gn:country_code":"ID",
    "gn:dem":40,
    "gn:feature_class":"P",
    "gn:feature_code":"PPL",
    "gn:name":"Blokbeji",
    "gn:population":0,
    "gn:timezone":"Asia/Jakarta",
    "iso:country":"ID",
    "name:ind_x_preferred":[
        "Blokbeji"
    ],
    "wof:name":"Blokbeji",
    "wof:placetype":"locality"
},
  "geometry": {"coordinates":[109.0883,-6.9798],"type":"Point"}
}