{
  "type": "Feature",
  "properties": {
    "gn:admin1_code":"30",
    "gn:asciiname":"Jami",
    "gn:country_code":"ID",
    "gn:dem":781,
    "gn:feature_class":"P",
    "gn:feature_code":"PPL",
    "gn:name":"Jami",
    "gn:population":0,
    "gn:timezone":"Asia/Jakarta",
    "iso:country":"ID",
    "name:ind_x_preferred":[
        "Jami"
    ],
    "wof:name":"Jami",
    "wof:placetype":"locality"
},
  "geometry": {"coordinates":[107.01222,-6.89556],"type":"Point"}
}