{
  "type": "Feature",
  "properties": {
    "gn:admin1_code":"30",
    "gn:asciiname":"Tonggoh Tengah",
    "gn:country_code":"ID",
    "gn:dem":148,
    "gn:feature_class":"P",
    "gn:feature_code":"PPL",
    "gn:name":"Tonggoh Tengah",
    "gn:population":0,
    "gn:timezone":"Asia/Jakarta",
    "iso:country":"ID",
    "wof:name":"Tonggoh Tengah",
    "wof:placetype":"locality"
},
  "geometry": {"coordinates":[106.90278000000001,-6.49611],"type":"Point"}
}