{
  "type": "Feature",
  "properties": {
    "gn:admin1_code":"30.0",
    "gn:asciiname":"Pinangjajar",
    "gn:country_code":"ID",
    "gn:dem":388,
    "gn:feature_class":"P",
    "gn:feature_code":"PPL",
    "gn:name":"Pinangjajar",
    "gn:population":0,
    "gn:timezone":"Asia/Jakarta",
    "iso:country":"ID",
    "name:ind_x_preferred":[
        "Pinangjajar"
    ],
    "wof:name":"Pinangjajar",
    "wof:placetype":"locality"
},
  "geometry": {"coordinates":[106.62309999999999,-7.2236],"type":"Point"}
}