{
  "type": "Feature",
  "properties": {
    "gn:admin1_code":"21",
    "gn:asciiname":"Gunungsari",
    "gn:country_code":"ID",
    "gn:dem":50,
    "gn:feature_class":"P",
    "gn:feature_code":"PPL",
    "gn:name":"Gunungsari",
    "gn:population":0,
    "gn:timezone":"Asia/Makassar",
    "iso:country":"ID",
    "name:ind_x_preferred":[
        "Gunungsari"
    ],
    "wof:name":"Gunungsari",
    "wof:placetype":"locality"
},
  "geometry": {"coordinates":[119.9902,-0.3211],"type":"Point"}
}