{
  "type": "Feature",
  "properties": {
    "gn:admin1_code":"28.0",
    "gn:asciiname":"Hualohi",
    "gn:country_code":"ID",
    "gn:dem":40,
    "gn:feature_class":"P",
    "gn:feature_code":"PPL",
    "gn:name":"Hualohi",
    "gn:population":0,
    "gn:timezone":"Asia/Jayapura",
    "iso:country":"ID",
    "name:ind_x_preferred":[
        "Hualohi"
    ],
    "name:und_x_variant":[
        "Hualooi",
        "Hoealohi"
    ],
    "wof:name":"Hualohi",
    "wof:placetype":"locality"
},
  "geometry": {"coordinates":[128.68523999999999,-3.40416],"type":"Point"}
}