{
  "type": "Feature",
  "properties": {
    "gn:admin1_code":"8.0",
    "gn:asciiname":"Baturaja",
    "gn:country_code":"ID",
    "gn:dem":14,
    "gn:feature_class":"P",
    "gn:feature_code":"PPL",
    "gn:name":"Baturaja",
    "gn:population":0,
    "gn:timezone":"Asia/Jakarta",
    "iso:country":"ID",
    "name:dan_x_preferred":[
        "Baturaja"
    ],
    "name:fas_x_preferred":[
        "\u0628\u0627\u062a\u0648\u0631\u0627\u062c\u0627"
    ],
    "name:fra_x_preferred":[
        "Baturaja"
    ],
    "name:ind_x_preferred":[
        "Baturaja"
    ],
    "name:mlg_x_preferred":[
        "Baturaja"
    ],
    "name:nno_x_preferred":[
        "Baturaja"
    ],
    "name:nor_x_preferred":[
        "Baturaja"
    ],
    "wof:lang_x_official":[
        "ind"
    ],
    "wof:lang_x_spoken":[
        "ind",
        "eng"
    ],
    "wof:name":"Baturaja",
    "wof:placetype":"locality"
},
  "geometry": {"coordinates":[114.0429,-7.0055],"type":"Point"}
}