{
  "type": "Feature",
  "properties": {
    "gn:admin1_code":"8.0",
    "gn:asciiname":"Baturaja",
    "gn:country_code":"ID",
    "gn:dem":14,
    "gn:feature_class":"P",
    "gn:feature_code":"PPL",
    "gn:name":"Baturaja",
    "gn:population":0,
    "gn:timezone":"Asia/Jakarta",
    "iso:country":"ID",
    "name:ind_x_preferred":[
        "Baturaja"
    ],
    "wof:name":"Baturaja",
    "wof:placetype":"locality"
},
  "geometry": {"coordinates":[114.0429,-7.0055],"type":"Point"}
}