{
  "type": "Feature",
  "properties": {
    "gn:admin1_code":"30",
    "gn:asciiname":"Cibiana",
    "gn:cc2":"ID",
    "gn:country_code":"ID",
    "gn:dem":803,
    "gn:feature_class":"P",
    "gn:feature_code":"PPL",
    "gn:name":"Cibiana",
    "gn:population":0,
    "gn:timezone":"Asia/Jakarta",
    "iso:country":"ID",
    "name:und_x_variant":[
        "Tjibiana",
        "Cibiana"
    ],
    "wof:name":"Cibiana",
    "wof:placetype":"locality"
},
  "geometry": {"coordinates":[107.74639000000001,-7.09972],"type":"Point"}
}