{
  "type": "Feature",
  "properties": {
    "gn:admin1_code":"18.0",
    "gn:asciiname":"Diu",
    "gn:country_code":"ID",
    "gn:dem":10,
    "gn:feature_class":"P",
    "gn:feature_code":"PPL",
    "gn:name":"Diu",
    "gn:population":0,
    "gn:timezone":"Asia/Makassar",
    "iso:country":"ID",
    "name:ara_x_preferred":[
        "\u062f\u064a\u0648"
    ],
    "name:ceb_x_preferred":[
        "Diu"
    ],
    "name:deu_x_preferred":[
        "Diu"
    ],
    "name:fra_x_preferred":[
        "Diu"
    ],
    "name:heb_x_preferred":[
        "\u05d3\u05d9\u05d5"
    ],
    "name:hun_x_preferred":[
        "Diu"
    ],
    "name:hye_x_preferred":[
        "\u0534\u056b\u0578\u0582"
    ],
    "name:ind_x_preferred":[
        "Diu"
    ],
    "name:msa_x_preferred":[
        "Diu"
    ],
    "name:nld_x_preferred":[
        "Diu"
    ],
    "name:rus_x_preferred":[
        "\u0414\u0438\u0443"
    ],
    "name:spa_x_preferred":[
        "Diu"
    ],
    "name:swe_x_preferred":[
        "Diu"
    ],
    "wof:lang_x_official":[
        "ind"
    ],
    "wof:lang_x_spoken":[
        "ind",
        "eng"
    ],
    "wof:name":"Diu",
    "wof:placetype":"locality"
},
  "geometry": {"coordinates":[123.04949999999999,-10.8507],"type":"Point"}
}