{
  "type": "Feature",
  "properties": {
    "gn:admin1_code":"26",
    "gn:asciiname":"Paringgonan",
    "gn:country_code":"ID",
    "gn:dem":1015,
    "gn:feature_class":"P",
    "gn:feature_code":"PPL",
    "gn:name":"Paringgonan",
    "gn:population":0,
    "gn:timezone":"Asia/Jakarta",
    "iso:country":"ID",
    "name:ind_x_preferred":[
        "Paringgonan"
    ],
    "wof:name":"Paringgonan",
    "wof:placetype":"locality"
},
  "geometry": {"coordinates":[99.28856,1.55098],"type":"Point"}
}