{
  "type": "Feature",
  "properties": {
    "gn:admin1_code":"2.0",
    "gn:asciiname":"Bolangan",
    "gn:country_code":"ID",
    "gn:dem":572,
    "gn:feature_class":"P",
    "gn:feature_code":"PPL",
    "gn:name":"Bolangan",
    "gn:population":0,
    "gn:timezone":"Asia/Makassar",
    "iso:country":"ID",
    "name:ind_x_preferred":[
        "Bolangan"
    ],
    "wof:name":"Bolangan",
    "wof:placetype":"locality"
},
  "geometry": {"coordinates":[115.1514,-8.3822],"type":"Point"}
}