{
  "type": "Feature",
  "properties": {
    "gn:admin1_code":"7",
    "gn:asciiname":"Rowoaking",
    "gn:country_code":"ID",
    "gn:dem":24,
    "gn:feature_class":"P",
    "gn:feature_code":"PPL",
    "gn:name":"Rowoaking",
    "gn:population":0,
    "gn:timezone":"Asia/Jakarta",
    "iso:country":"ID",
    "name:ind_x_preferred":[
        "Rowoaking"
    ],
    "wof:name":"Rowoaking",
    "wof:placetype":"locality"
},
  "geometry": {"coordinates":[110.1267,-6.9815],"type":"Point"}
}