{
  "type": "Feature",
  "properties": {
    "gn:admin1_code":"26",
    "gn:asciiname":"Sidoharjo",
    "gn:country_code":"ID",
    "gn:dem":28,
    "gn:feature_class":"P",
    "gn:feature_code":"PPL",
    "gn:name":"Sidoharjo",
    "gn:population":0,
    "gn:timezone":"Asia/Jakarta",
    "iso:country":"ID",
    "name:ind_x_preferred":[
        "Sidoharjo"
    ],
    "wof:name":"Sidoharjo",
    "wof:placetype":"locality"
},
  "geometry": {"coordinates":[98.9058,3.4898],"type":"Point"}
}