{
  "type": "Feature",
  "properties": {
    "gn:admin1_code":"18.0",
    "gn:asciiname":"Sano",
    "gn:country_code":"ID",
    "gn:dem":949,
    "gn:feature_class":"P",
    "gn:feature_code":"PPL",
    "gn:name":"Sano",
    "gn:population":0,
    "gn:timezone":"Asia/Makassar",
    "iso:country":"ID",
    "name:ind_x_preferred":[
        "Sano"
    ],
    "wof:name":"Sano",
    "wof:placetype":"locality"
},
  "geometry": {"coordinates":[120.44240000000001,-8.6926],"type":"Point"}
}