{
  "type": "Feature",
  "properties": {
    "gn:admin1_code":"8.0",
    "gn:asciiname":"Trebung Onjur",
    "gn:country_code":"ID",
    "gn:dem":121,
    "gn:feature_class":"P",
    "gn:feature_code":"PPL",
    "gn:name":"Trebung Onjur",
    "gn:population":0,
    "gn:timezone":"Asia/Jakarta",
    "iso:country":"ID",
    "name:ind_x_preferred":[
        "Trebung Onjur"
    ],
    "wof:name":"Trebung Onjur",
    "wof:placetype":"locality"
},
  "geometry": {"coordinates":[113.5134,-6.9836],"type":"Point"}
}