{
  "type": "Feature",
  "properties": {
    "gn:admin1_code":"33",
    "gn:asciiname":"Sadiah Satu",
    "gn:country_code":"ID",
    "gn:dem":12,
    "gn:feature_class":"P",
    "gn:feature_code":"PPL",
    "gn:name":"Sadiah Satu",
    "gn:population":0,
    "gn:timezone":"Asia/Jakarta",
    "iso:country":"ID",
    "name:ind_x_preferred":[
        "Sadiah Satu"
    ],
    "wof:name":"Sadiah Satu",
    "wof:placetype":"locality"
},
  "geometry": {"coordinates":[106.1771,-6.0791],"type":"Point"}
}