{
  "type": "Feature",
  "properties": {
    "gn:admin1_code":"18.0",
    "gn:asciiname":"Dokarobo",
    "gn:country_code":"ID",
    "gn:dem":68,
    "gn:feature_class":"P",
    "gn:feature_code":"PPL",
    "gn:name":"Dokarobo",
    "gn:population":0,
    "gn:timezone":"Asia/Makassar",
    "iso:country":"ID",
    "name:ind_x_preferred":[
        "Dokarobo"
    ],
    "wof:name":"Dokarobo",
    "wof:placetype":"locality"
},
  "geometry": {"coordinates":[121.84910000000001,-10.6089],"type":"Point"}
}