{
  "type": "Feature",
  "properties": {
    "gn:admin1_code":"26.0",
    "gn:asciiname":"Bangun Pane",
    "gn:country_code":"ID",
    "gn:dem":987,
    "gn:feature_class":"P",
    "gn:feature_code":"PPL",
    "gn:name":"Bangun Pane",
    "gn:population":0,
    "gn:timezone":"Asia/Jakarta",
    "iso:country":"ID",
    "name:ind_x_preferred":[
        "Bangun Pane"
    ],
    "name:und_x_variant":[
        "Bangoen Panei"
    ],
    "wof:name":"Bangun Pane",
    "wof:placetype":"locality"
},
  "geometry": {"coordinates":[98.85169999999999,2.9023],"type":"Point"}
}