{
  "type": "Feature",
  "properties": {
    "gn:admin1_code":"1",
    "gn:asciiname":"Tanjung Muliya",
    "gn:country_code":"ID",
    "gn:dem":27,
    "gn:feature_class":"P",
    "gn:feature_code":"PPL",
    "gn:name":"Tanjung Muliya",
    "gn:population":0,
    "gn:timezone":"Asia/Jakarta",
    "iso:country":"ID",
    "name:ind_x_preferred":[
        "Tanjung Muliya"
    ],
    "wof:name":"Tanjung Muliya",
    "wof:placetype":"locality"
},
  "geometry": {"coordinates":[99.6069,2.94],"type":"Point"}
}