{
  "type": "Feature",
  "properties": {
    "gn:admin1_code":"30.0",
    "gn:asciiname":"Ciwedus",
    "gn:country_code":"ID",
    "gn:dem":317,
    "gn:feature_class":"P",
    "gn:feature_code":"PPL",
    "gn:name":"Ciwedus",
    "gn:population":0,
    "gn:timezone":"Asia/Jakarta",
    "iso:country":"ID",
    "name:ind_x_preferred":[
        "Ciwedus"
    ],
    "name:und_x_variant":[
        "Tjiwedoes"
    ],
    "wof:lang_x_official":[
        "ind"
    ],
    "wof:lang_x_spoken":[
        "ind",
        "eng"
    ],
    "wof:name":"Ciwedus",
    "wof:placetype":"locality"
},
  "geometry": {"coordinates":[108.26139999999999,-7.3304],"type":"Point"}
}