{
  "type": "Feature",
  "properties": {
    "gn:admin1_code":"5.0",
    "gn:asciiname":"Durianluncuk",
    "gn:country_code":"ID",
    "gn:dem":27,
    "gn:feature_class":"P",
    "gn:feature_code":"PPL",
    "gn:name":"Durianluncuk",
    "gn:population":0,
    "gn:timezone":"Asia/Jakarta",
    "iso:country":"ID",
    "name:ind_x_preferred":[
        "Durian Luncuk"
    ],
    "name:msa_x_preferred":[
        "Durian Luncuk"
    ],
    "name:nld_x_preferred":[
        "Durian Luncuk"
    ],
    "name:sun_x_preferred":[
        "Durian Luncuk"
    ],
    "name:und_x_variant":[
        "Durianlutjuk",
        "Durianluntjuk",
        "Doerianloentjoek",
        "Durianluncuk"
    ],
    "wof:name":"Durianluncuk",
    "wof:placetype":"locality"
},
  "geometry": {"coordinates":[102.994,-1.8796],"type":"Point"}
}