{
  "type": "Feature",
  "properties": {
    "gn:admin1_code":"26",
    "gn:asciiname":"Hutajulu",
    "gn:country_code":"ID",
    "gn:dem":876,
    "gn:feature_class":"P",
    "gn:feature_code":"PPL",
    "gn:name":"Hutajulu",
    "gn:population":0,
    "gn:timezone":"Asia/Jakarta",
    "iso:country":"ID",
    "name:ind_x_preferred":[
        "Hutajulu"
    ],
    "wof:name":"Hutajulu",
    "wof:placetype":"locality"
},
  "geometry": {"coordinates":[99.02591,1.90705],"type":"Point"}
}