{
  "type": "Feature",
  "properties": {
    "gn:admin1_code":"26",
    "gn:asciiname":"Pematang Ramlie",
    "gn:country_code":"ID",
    "gn:dem":6,
    "gn:feature_class":"P",
    "gn:feature_code":"PPL",
    "gn:name":"Pematang Ramlie",
    "gn:population":0,
    "gn:timezone":"Asia/Jakarta",
    "iso:country":"ID",
    "name:ind_x_preferred":[
        "Pematang Ramlie"
    ],
    "wof:name":"Pematang Ramlie",
    "wof:placetype":"locality"
},
  "geometry": {"coordinates":[99.6296,3.108],"type":"Point"}
}