{
  "type": "Feature",
  "properties": {
    "gn:admin1_code":"30.0",
    "gn:asciiname":"Golempang",
    "gn:country_code":"ID",
    "gn:dem":39,
    "gn:feature_class":"P",
    "gn:feature_code":"PPL",
    "gn:name":"Golempang",
    "gn:population":0,
    "gn:timezone":"Asia/Jakarta",
    "iso:country":"ID",
    "name:ind_x_preferred":[
        "Golempang"
    ],
    "wof:name":"Golempang",
    "wof:placetype":"locality"
},
  "geometry": {"coordinates":[108.6725,-7.5046],"type":"Point"}
}