{
  "type": "Feature",
  "properties": {
    "gn:admin1_code":"18.0",
    "gn:asciiname":"Kuanheum",
    "gn:country_code":"ID",
    "gn:dem":40,
    "gn:feature_class":"P",
    "gn:feature_code":"PPLA4",
    "gn:name":"Kuanheum",
    "gn:population":0,
    "gn:timezone":"Asia/Makassar",
    "iso:country":"ID",
    "name:ind_x_preferred":[
        "Kuanheum"
    ],
    "wof:name":"Kuanheum",
    "wof:placetype":"locality"
},
  "geometry": {"coordinates":[123.51090000000001,-10.2403],"type":"Point"}
}