{
  "type": "Feature",
  "properties": {
    "gn:admin1_code":"7",
    "gn:asciiname":"Sulur",
    "gn:country_code":"ID",
    "gn:dem":81,
    "gn:feature_class":"P",
    "gn:feature_code":"PPL",
    "gn:name":"Sulur",
    "gn:population":0,
    "gn:timezone":"Asia/Jakarta",
    "iso:country":"ID",
    "name:ceb_x_preferred":[
        "Sulur"
    ],
    "name:ind_x_preferred":[
        "Sulur"
    ],
    "name:ita_x_preferred":[
        "Sulur"
    ],
    "name:msa_x_preferred":[
        "Sulur"
    ],
    "name:nld_x_preferred":[
        "Sulur"
    ],
    "name:por_x_preferred":[
        "Sulur"
    ],
    "name:tam_x_preferred":[
        "\u0b9a\u0bc2\u0bb2\u0bc2\u0bb0\u0bcd"
    ],
    "name:vie_x_preferred":[
        "Sulur"
    ],
    "name:zho_x_preferred":[
        "\u82cf\u5362\u5c14"
    ],
    "wof:name":"Sulur",
    "wof:placetype":"locality"
},
  "geometry": {"coordinates":[111.12972000000001,-7.385],"type":"Point"}
}