{
  "type": "Feature",
  "properties": {
    "gn:admin1_code":"7.0",
    "gn:asciiname":"Simangli",
    "gn:country_code":"ID",
    "gn:dem":269,
    "gn:feature_class":"P",
    "gn:feature_code":"PPL",
    "gn:name":"Simangli",
    "gn:population":0,
    "gn:timezone":"Asia/Jakarta",
    "iso:country":"ID",
    "name:ind_x_preferred":[
        "Simangli"
    ],
    "wof:name":"Simangli",
    "wof:placetype":"locality"
},
  "geometry": {"coordinates":[109.55528,-7.34917],"type":"Point"}
}