{
  "type": "Feature",
  "properties": {
    "gn:admin1_code":"7",
    "gn:asciiname":"Kenteng",
    "gn:country_code":"ID",
    "gn:dem":862,
    "gn:feature_class":"P",
    "gn:feature_code":"PPL",
    "gn:name":"Kenteng",
    "gn:population":0,
    "gn:timezone":"Asia/Jakarta",
    "iso:country":"ID",
    "name:ind_x_preferred":[
        "Kenteng"
    ],
    "wof:name":"Kenteng",
    "wof:placetype":"locality"
},
  "geometry": {"coordinates":[110.35972,-7.23417],"type":"Point"}
}