{
  "type": "Feature",
  "properties": {
    "gn:admin1_code":"29.0",
    "gn:asciiname":"Gula",
    "gn:country_code":"ID",
    "gn:dem":8,
    "gn:feature_class":"P",
    "gn:feature_code":"PPL",
    "gn:name":"Gula",
    "gn:population":0,
    "gn:timezone":"Asia/Jayapura",
    "iso:country":"ID",
    "name:ara_x_preferred":[
        "\u063a\u0648\u0644\u0627"
    ],
    "name:ceb_x_preferred":[
        "Gula"
    ],
    "name:deu_x_preferred":[
        "Gula"
    ],
    "name:fra_x_preferred":[
        "Gula"
    ],
    "name:ind_x_preferred":[
        "Gulau"
    ],
    "name:ind_x_variant":[
        "Gula"
    ],
    "name:ita_x_preferred":[
        "Gula"
    ],
    "name:pol_x_preferred":[
        "Gula"
    ],
    "name:por_x_preferred":[
        "Gula"
    ],
    "name:slk_x_preferred":[
        "Gula"
    ],
    "name:swe_x_preferred":[
        "Gula"
    ],
    "name:und_x_variant":[
        "Goelaoe"
    ],
    "wof:lang_x_official":[
        "ind"
    ],
    "wof:lang_x_spoken":[
        "ind",
        "eng"
    ],
    "wof:name":"Gula",
    "wof:placetype":"locality"
},
  "geometry": {"coordinates":[125.95869,-2.12972],"type":"Point"}
}