{
  "type": "Feature",
  "properties": {
    "gn:admin1_code":"8.0",
    "gn:asciiname":"Tati",
    "gn:country_code":"ID",
    "gn:dem":132,
    "gn:feature_class":"P",
    "gn:feature_code":"PPL",
    "gn:name":"Tati",
    "gn:population":0,
    "gn:timezone":"Asia/Jakarta",
    "iso:country":"ID",
    "name:bpy_x_preferred":[
        "\u09a4\u09be\u09a4\u09bf"
    ],
    "name:ceb_x_preferred":[
        "Tati"
    ],
    "name:deu_x_preferred":[
        "Tati"
    ],
    "name:fin_x_preferred":[
        "Tati"
    ],
    "name:fra_x_preferred":[
        "Tati"
    ],
    "name:ind_x_preferred":[
        "Tati"
    ],
    "name:ita_x_preferred":[
        "Tati"
    ],
    "name:msa_x_preferred":[
        "Tati"
    ],
    "name:nld_x_preferred":[
        "Tati"
    ],
    "name:por_x_preferred":[
        "Tati"
    ],
    "name:swe_x_preferred":[
        "Tati"
    ],
    "wof:lang_x_official":[
        "ind"
    ],
    "wof:lang_x_spoken":[
        "ind",
        "eng"
    ],
    "wof:name":"Tati",
    "wof:placetype":"locality"
},
  "geometry": {"coordinates":[110.97944,-8.20667],"type":"Point"}
}