{
  "type": "Feature",
  "properties": {
    "gn:admin1_code":"26",
    "gn:asciiname":"Paluh Datar",
    "gn:country_code":"ID",
    "gn:dem":2,
    "gn:feature_class":"P",
    "gn:feature_code":"PPL",
    "gn:name":"Paluh Datar",
    "gn:population":0,
    "gn:timezone":"Asia/Jakarta",
    "iso:country":"ID",
    "name:ind_x_preferred":[
        "Paluh Datar"
    ],
    "wof:name":"Paluh Datar",
    "wof:placetype":"locality"
},
  "geometry": {"coordinates":[98.7685,3.7027],"type":"Point"}
}