{
  "type": "Feature",
  "properties": {
    "gn:admin1_code":"18.0",
    "gn:asciiname":"Weekatina",
    "gn:country_code":"ID",
    "gn:dem":437,
    "gn:feature_class":"P",
    "gn:feature_code":"PPL",
    "gn:name":"Weekatina",
    "gn:population":0,
    "gn:timezone":"Asia/Makassar",
    "iso:country":"ID",
    "name:ind_x_preferred":[
        "Weekatina"
    ],
    "wof:name":"Weekatina",
    "wof:placetype":"locality"
},
  "geometry": {"coordinates":[119.3085,-9.5053],"type":"Point"}
}