{
  "type": "Feature",
  "properties": {
    "gn:admin1_code":"30.0",
    "gn:asciiname":"Cipayung",
    "gn:country_code":"ID",
    "gn:dem":236,
    "gn:feature_class":"P",
    "gn:feature_code":"PPL",
    "gn:name":"Cipayung",
    "gn:population":0,
    "gn:timezone":"Asia/Jakarta",
    "iso:country":"ID",
    "name:ind_x_preferred":[
        "Cipayung"
    ],
    "wof:name":"Cipayung",
    "wof:placetype":"locality"
},
  "geometry": {"coordinates":[107.09869999999999,-7.2678],"type":"Point"}
}