{
  "type": "Feature",
  "properties": {
    "gn:admin1_code":"7.0",
    "gn:asciiname":"Taman Wetan",
    "gn:country_code":"ID",
    "gn:dem":68,
    "gn:feature_class":"P",
    "gn:feature_code":"PPL",
    "gn:name":"Taman Wetan",
    "gn:population":0,
    "gn:timezone":"Asia/Jakarta",
    "iso:country":"ID",
    "name:ind_x_preferred":[
        "Taman Wetan"
    ],
    "wof:name":"Taman Wetan",
    "wof:placetype":"locality"
},
  "geometry": {"coordinates":[111.3909,-7.164],"type":"Point"}
}