{
  "type": "Feature",
  "properties": {
    "gn:admin1_code":"18.0",
    "gn:asciiname":"Noli",
    "gn:country_code":"ID",
    "gn:dem":48,
    "gn:feature_class":"P",
    "gn:feature_code":"PPL",
    "gn:name":"Noli",
    "gn:population":0,
    "gn:timezone":"Asia/Makassar",
    "iso:country":"ID",
    "name:afr_x_preferred":[
        "Noli"
    ],
    "name:ara_x_preferred":[
        "\u0646\u0648\u0644\u064a"
    ],
    "name:ast_x_preferred":[
        "Noli"
    ],
    "name:azb_x_preferred":[
        "\u0646\u0648\u0644\u06cc"
    ],
    "name:bel_x_preferred":[
        "\u041d\u043e\u043b\u0456"
    ],
    "name:bul_x_preferred":[
        "\u041d\u043e\u043b\u0438"
    ],
    "name:cat_x_preferred":[
        "Noli"
    ],
    "name:ceb_x_preferred":[
        "Noli"
    ],
    "name:ces_x_preferred":[
        "Noli"
    ],
    "name:deu_x_preferred":[
        "Noli"
    ],
    "name:epo_x_preferred":[
        "Noli"
    ],
    "name:eus_x_preferred":[
        "Noli"
    ],
    "name:fas_x_preferred":[
        "\u0646\u0648\u0644\u06cc"
    ],
    "name:fra_x_preferred":[
        "Noli"
    ],
    "name:hun_x_preferred":[
        "Noli"
    ],
    "name:hye_x_preferred":[
        "\u0546\u0578\u056c\u056b"
    ],
    "name:ina_x_preferred":[
        "Noli"
    ],
    "name:ind_x_preferred":[
        "Noli"
    ],
    "name:ita_x_preferred":[
        "Noli"
    ],
    "name:jpn_x_preferred":[
        "\u30ce\u30fc\u30ea"
    ],
    "name:kaz_x_preferred":[
        "\u041d\u043e\u043b\u0438"
    ],
    "name:lat_x_preferred":[
        "Naulum"
    ],
    "name:lij_x_preferred":[
        "N\u00f6i"
    ],
    "name:lmo_x_preferred":[
        "Noli"
    ],
    "name:msa_x_preferred":[
        "Noli"
    ],
    "name:nap_x_preferred":[
        "Noli"
    ],
    "name:nld_x_preferred":[
        "Noli"
    ],
    "name:pms_x_preferred":[
        "Noli"
    ],
    "name:pol_x_preferred":[
        "Noli"
    ],
    "name:por_x_preferred":[
        "Noli"
    ],
    "name:ron_x_preferred":[
        "Noli"
    ],
    "name:rus_x_preferred":[
        "\u041d\u043e\u043b\u0438"
    ],
    "name:scn_x_preferred":[
        "Noli"
    ],
    "name:spa_x_preferred":[
        "Noli"
    ],
    "name:srp_x_preferred":[
        "\u041d\u043e\u043b\u0438"
    ],
    "name:swe_x_preferred":[
        "Noli"
    ],
    "name:ukr_x_preferred":[
        "\u041d\u043e\u043b\u0456"
    ],
    "name:uzb_x_preferred":[
        "Noli"
    ],
    "name:vec_x_preferred":[
        "Noli"
    ],
    "name:vie_x_preferred":[
        "Noli"
    ],
    "name:vol_x_preferred":[
        "Noli"
    ],
    "name:war_x_preferred":[
        "Noli"
    ],
    "wof:name":"Noli",
    "wof:placetype":"locality"
},
  "geometry": {"coordinates":[123.3507,-10.6213],"type":"Point"}
}