{
  "type": "Feature",
  "properties": {
    "gn:admin1_code":"18.0",
    "gn:asciiname":"Noli",
    "gn:country_code":"ID",
    "gn:dem":48,
    "gn:feature_class":"P",
    "gn:feature_code":"PPL",
    "gn:name":"Noli",
    "gn:population":0,
    "gn:timezone":"Asia/Makassar",
    "iso:country":"ID",
    "name:ind_x_preferred":[
        "Noli"
    ],
    "wof:name":"Noli",
    "wof:placetype":"locality"
},
  "geometry": {"coordinates":[123.3507,-10.6213],"type":"Point"}
}