{
  "type": "Feature",
  "properties": {
    "gn:admin1_code":"30",
    "gn:asciiname":"Rancasepuluh",
    "gn:country_code":"ID",
    "gn:dem":16,
    "gn:feature_class":"P",
    "gn:feature_code":"PPL",
    "gn:name":"Rancasepuluh",
    "gn:population":0,
    "gn:timezone":"Asia/Jakarta",
    "iso:country":"ID",
    "name:ind_x_preferred":[
        "Rancasepuluh"
    ],
    "wof:name":"Rancasepuluh",
    "wof:placetype":"locality"
},
  "geometry": {"coordinates":[107.24722,-6.29944],"type":"Point"}
}