{
  "type": "Feature",
  "properties": {
    "gn:admin1_code":"30.0",
    "gn:asciiname":"Sukaharja",
    "gn:country_code":"ID",
    "gn:dem":516,
    "gn:feature_class":"P",
    "gn:feature_code":"PPLA4",
    "gn:name":"Sukaharja",
    "gn:population":0,
    "gn:timezone":"Asia/Jakarta",
    "iso:country":"ID",
    "name:ind_x_preferred":[
        "Sukaharja"
    ],
    "wof:name":"Sukaharja",
    "wof:placetype":"locality"
},
  "geometry": {"coordinates":[108.4768,-7.1522],"type":"Point"}
}