{
  "type": "Feature",
  "properties": {
    "gn:admin1_code":"07",
    "gn:asciiname":"Karangsari",
    "gn:country_code":"ID",
    "gn:dem":338,
    "gn:feature_class":"P",
    "gn:feature_code":"PPL",
    "gn:name":"Karangsari",
    "gn:population":0,
    "gn:timezone":"Asia/Jakarta",
    "iso:country":"ID",
    "name:ind_x_preferred":[
        "Karangsari"
    ],
    "wof:name":"Karangsari",
    "wof:placetype":"locality"
},
  "geometry": {"coordinates":[110.3827,-7.1002],"type":"Point"}
}