{
  "type": "Feature",
  "properties": {
    "gn:admin1_code":"8",
    "gn:asciiname":"Kalirejopermai Satu",
    "gn:country_code":"ID",
    "gn:dem":50,
    "gn:feature_class":"P",
    "gn:feature_code":"PPL",
    "gn:name":"Kalirejopermai Satu",
    "gn:population":0,
    "gn:timezone":"Asia/Jakarta",
    "iso:country":"ID",
    "name:ind_x_preferred":[
        "Kalirejopermai Satu"
    ],
    "wof:name":"Kalirejopermai Satu",
    "wof:placetype":"locality"
},
  "geometry": {"coordinates":[114.3412,-8.2491],"type":"Point"}
}