{
  "type": "Feature",
  "properties": {
    "gn:admin1_code":"30",
    "gn:asciiname":"Margamulya",
    "gn:country_code":"ID",
    "gn:dem":1201,
    "gn:feature_class":"P",
    "gn:feature_code":"PPL",
    "gn:name":"Margamulya",
    "gn:population":0,
    "gn:timezone":"Asia/Jakarta",
    "iso:country":"ID",
    "name:ind_x_preferred":[
        "Margamulya"
    ],
    "wof:name":"Margamulya",
    "wof:placetype":"locality"
},
  "geometry": {"coordinates":[107.45699999999999,-7.1121],"type":"Point"}
}