{
  "type": "Feature",
  "properties": {
    "gn:admin1_code":"8",
    "gn:asciiname":"Pandantoyo",
    "gn:country_code":"ID",
    "gn:dem":44,
    "gn:feature_class":"P",
    "gn:feature_code":"PPL",
    "gn:name":"Pandantoyo",
    "gn:population":0,
    "gn:timezone":"Asia/Jakarta",
    "iso:country":"ID",
    "name:ind_x_preferred":[
        "Pandantoyo"
    ],
    "wof:name":"Pandantoyo",
    "wof:placetype":"locality"
},
  "geometry": {"coordinates":[112.0956,-7.5821],"type":"Point"}
}