{
  "type": "Feature",
  "properties": {
    "gn:admin1_code":"0.0",
    "gn:asciiname":"Sungaikelambu",
    "gn:cc2":"ID",
    "gn:country_code":"ID",
    "gn:dem":2,
    "gn:feature_class":"P",
    "gn:feature_code":"PPL",
    "gn:name":"Sungaikelambu",
    "gn:population":0,
    "gn:timezone":"Asia/Makassar",
    "iso:country":"ID",
    "name:und_x_variant":[
        "Soengaikelamboe",
        "Sungaikelambu"
    ],
    "wof:name":"Sungaikelambu",
    "wof:placetype":"locality"
},
  "geometry": {"coordinates":[117.31667,-0.63333],"type":"Point"}
}