{
  "type": "Feature",
  "properties": {
    "gn:admin1_code":"33.0",
    "gn:asciiname":"Susukan",
    "gn:country_code":"ID",
    "gn:dem":55,
    "gn:feature_class":"P",
    "gn:feature_code":"PPL",
    "gn:name":"Susukan",
    "gn:population":0,
    "gn:timezone":"Asia/Jakarta",
    "iso:country":"ID",
    "name:ind_x_preferred":[
        "Susukan"
    ],
    "wof:name":"Susukan",
    "wof:placetype":"locality"
},
  "geometry": {"coordinates":[105.83750000000001,-6.2798],"type":"Point"}
}