{
  "type": "Feature",
  "properties": {
    "gn:admin1_code":"8",
    "gn:asciiname":"Danglanjang Timur",
    "gn:country_code":"ID",
    "gn:dem":95,
    "gn:feature_class":"P",
    "gn:feature_code":"PPL",
    "gn:name":"Danglanjang Timur",
    "gn:population":0,
    "gn:timezone":"Asia/Jakarta",
    "iso:country":"ID",
    "name:ind_x_preferred":[
        "Danglanjang Timur"
    ],
    "wof:name":"Danglanjang Timur",
    "wof:placetype":"locality"
},
  "geometry": {"coordinates":[113.2073,-7.0615],"type":"Point"}
}