{
  "type": "Feature",
  "properties": {
    "gn:admin1_code":"30.0",
    "gn:asciiname":"Pakapasan Ilir",
    "gn:country_code":"ID",
    "gn:dem":312,
    "gn:feature_class":"P",
    "gn:feature_code":"PPLA4",
    "gn:name":"Pakapasan Ilir",
    "gn:population":0,
    "gn:timezone":"Asia/Jakarta",
    "iso:country":"ID",
    "name:ind_x_preferred":[
        "Pakapasan Ilir"
    ],
    "name:und_x_variant":[
        "Pakapasan-hilir"
    ],
    "wof:lang_x_official":[
        "ind"
    ],
    "wof:lang_x_spoken":[
        "ind",
        "eng"
    ],
    "wof:name":"Pakapasan Ilir",
    "wof:placetype":"locality"
},
  "geometry": {"coordinates":[108.47499999999999,-7.061],"type":"Point"}
}