{
  "type": "Feature",
  "properties": {
    "gn:admin1_code":"30",
    "gn:asciiname":"Pasirtalaga Satu",
    "gn:country_code":"ID",
    "gn:dem":17,
    "gn:feature_class":"P",
    "gn:feature_code":"PPL",
    "gn:name":"Pasirtalaga Satu",
    "gn:population":0,
    "gn:timezone":"Asia/Jakarta",
    "iso:country":"ID",
    "name:ind_x_preferred":[
        "Pasirtalaga Satu"
    ],
    "name:und_x_variant":[
        "Pasirtalaga 1"
    ],
    "wof:name":"Pasirtalaga Satu",
    "wof:placetype":"locality"
},
  "geometry": {"coordinates":[107.38417,-6.29472],"type":"Point"}
}