{
  "type": "Feature",
  "properties": {
    "gn:admin1_code":"7.0",
    "gn:asciiname":"Padas",
    "gn:country_code":"ID",
    "gn:dem":127,
    "gn:feature_class":"P",
    "gn:feature_code":"PPL",
    "gn:name":"Padas",
    "gn:population":0,
    "gn:timezone":"Asia/Jakarta",
    "iso:country":"ID",
    "wof:name":"Padas",
    "wof:placetype":"locality"
},
  "geometry": {"coordinates":[110.75388999999998,-7.83444],"type":"Point"}
}