{
  "type": "Feature",
  "properties": {
    "gn:admin1_code":"21",
    "gn:asciiname":"Tayadun",
    "gn:country_code":"ID",
    "gn:dem":19,
    "gn:feature_class":"P",
    "gn:feature_code":"PPL",
    "gn:name":"Tayadun",
    "gn:population":0,
    "gn:timezone":"Asia/Makassar",
    "iso:country":"ID",
    "name:ind_x_preferred":[
        "Tayadun"
    ],
    "wof:name":"Tayadun",
    "wof:placetype":"locality"
},
  "geometry": {"coordinates":[121.5637,1.055],"type":"Point"}
}