{
  "type": "Feature",
  "properties": {
    "gn:admin1_code":"18",
    "gn:asciiname":"Cenak",
    "gn:country_code":"ID",
    "gn:dem":651,
    "gn:feature_class":"P",
    "gn:feature_code":"PPL",
    "gn:name":"Cenak",
    "gn:population":0,
    "gn:timezone":"Asia/Makassar",
    "iso:country":"ID",
    "name:ind_x_preferred":[
        "Cenak"
    ],
    "wof:name":"Cenak",
    "wof:placetype":"locality"
},
  "geometry": {"coordinates":[120.68470000000001,-8.4983],"type":"Point"}
}