{
  "type": "Feature",
  "properties": {
    "gn:admin1_code":"7.0",
    "gn:asciiname":"Jurutengah",
    "gn:country_code":"ID",
    "gn:dem":19,
    "gn:feature_class":"P",
    "gn:feature_code":"PPL",
    "gn:name":"Jurutengah",
    "gn:population":0,
    "gn:timezone":"Asia/Jakarta",
    "iso:country":"ID",
    "name:ind_x_preferred":[
        "Jurutengah"
    ],
    "wof:name":"Jurutengah",
    "wof:placetype":"locality"
},
  "geometry": {"coordinates":[109.69556,-7.77306],"type":"Point"}
}