{
  "type": "Feature",
  "properties": {
    "gn:admin1_code":"15.0",
    "gn:asciiname":"Camkanan",
    "gn:country_code":"ID",
    "gn:dem":441,
    "gn:feature_class":"P",
    "gn:feature_code":"PPL",
    "gn:name":"Camkanan",
    "gn:population":0,
    "gn:timezone":"Asia/Jakarta",
    "iso:country":"ID",
    "name:ind_x_preferred":[
        "Camkanan"
    ],
    "wof:name":"Camkanan",
    "wof:placetype":"locality"
},
  "geometry": {"coordinates":[104.98378999999998,-5.54611],"type":"Point"}
}