{
  "type": "Feature",
  "properties": {
    "gn:admin1_code":"18.0",
    "gn:asciiname":"Oja",
    "gn:country_code":"ID",
    "gn:dem":530,
    "gn:feature_class":"P",
    "gn:feature_code":"PPL",
    "gn:name":"Oja",
    "gn:population":0,
    "gn:timezone":"Asia/Makassar",
    "iso:country":"ID",
    "name:ceb_x_preferred":[
        "Oja"
    ],
    "name:deu_x_preferred":[
        "Oja"
    ],
    "name:est_x_preferred":[
        "Oja"
    ],
    "name:fra_x_preferred":[
        "Oja"
    ],
    "name:ind_x_preferred":[
        "Oja"
    ],
    "name:lav_x_preferred":[
        "Oja"
    ],
    "name:nds_x_preferred":[
        "Oja"
    ],
    "name:pol_x_preferred":[
        "Oja"
    ],
    "name:por_x_preferred":[
        "Oja"
    ],
    "name:swe_x_preferred":[
        "Oja"
    ],
    "wof:lang_x_official":[
        "ind"
    ],
    "wof:lang_x_spoken":[
        "ind",
        "eng"
    ],
    "wof:name":"Oja",
    "wof:placetype":"locality"
},
  "geometry": {"coordinates":[121.20659999999999,-8.8445],"type":"Point"}
}