{
  "type": "Feature",
  "properties": {
    "gn:admin1_code":"22",
    "gn:asciiname":"Lalodambu",
    "gn:country_code":"ID",
    "gn:dem":44,
    "gn:feature_class":"P",
    "gn:feature_code":"PPL",
    "gn:name":"Lalodambu",
    "gn:population":0,
    "gn:timezone":"Asia/Makassar",
    "iso:country":"ID",
    "name:ind_x_preferred":[
        "Lalodambu"
    ],
    "wof:name":"Lalodambu",
    "wof:placetype":"locality"
},
  "geometry": {"coordinates":[122.49039999999999,-3.918],"type":"Point"}
}