{
  "type": "Feature",
  "properties": {
    "gn:admin1_code":"26.0",
    "gn:asciiname":"Sihepeng",
    "gn:country_code":"ID",
    "gn:dem":188,
    "gn:feature_class":"P",
    "gn:feature_code":"PPL",
    "gn:name":"Sihepeng",
    "gn:population":0,
    "gn:timezone":"Asia/Jakarta",
    "iso:country":"ID",
    "name:ind_x_preferred":[
        "Sihepeng"
    ],
    "wof:name":"Sihepeng",
    "wof:placetype":"locality"
},
  "geometry": {"coordinates":[99.45419,1.0924],"type":"Point"}
}