{
  "type": "Feature",
  "properties": {
    "gn:admin1_code":"18.0",
    "gn:asciiname":"Bea",
    "gn:country_code":"ID",
    "gn:dem":935,
    "gn:feature_class":"P",
    "gn:feature_code":"PPL",
    "gn:name":"Bea",
    "gn:population":0,
    "gn:timezone":"Asia/Makassar",
    "iso:country":"ID",
    "name:ind_x_preferred":[
        "Bea"
    ],
    "wof:name":"Bea",
    "wof:placetype":"locality"
},
  "geometry": {"coordinates":[121.00369999999999,-8.8676],"type":"Point"}
}