{
  "type": "Feature",
  "properties": {
    "gn:admin1_code":"7",
    "gn:asciiname":"Gendingan",
    "gn:country_code":"ID",
    "gn:dem":39,
    "gn:feature_class":"P",
    "gn:feature_code":"PPL",
    "gn:name":"Gendingan",
    "gn:population":0,
    "gn:timezone":"Asia/Jakarta",
    "iso:country":"ID",
    "name:ind_x_preferred":[
        "Gendingan"
    ],
    "wof:name":"Gendingan",
    "wof:placetype":"locality"
},
  "geometry": {"coordinates":[110.90778,-7.13306],"type":"Point"}
}