{
  "type": "Feature",
  "properties": {
    "gn:admin1_code":"21.0",
    "gn:asciiname":"Bolokut",
    "gn:country_code":"ID",
    "gn:dem":2,
    "gn:feature_class":"P",
    "gn:feature_code":"PPL",
    "gn:name":"Bolokut",
    "gn:population":0,
    "gn:timezone":"Asia/Makassar",
    "iso:country":"ID",
    "name:ind_x_preferred":[
        "Bolokut"
    ],
    "wof:name":"Bolokut",
    "wof:placetype":"locality"
},
  "geometry": {"coordinates":[123.8305,-2.0134],"type":"Point"}
}