{
  "type": "Feature",
  "properties": {
    "gn:admin1_code":"30.0",
    "gn:asciiname":"Kulina",
    "gn:country_code":"ID",
    "gn:dem":512,
    "gn:feature_class":"P",
    "gn:feature_code":"PPL",
    "gn:name":"Kulina",
    "gn:population":0,
    "gn:timezone":"Asia/Jakarta",
    "iso:country":"ID",
    "name:bos_x_preferred":[
        "Kulina"
    ],
    "name:ceb_x_preferred":[
        "Kulina"
    ],
    "name:deu_x_preferred":[
        "Kulina"
    ],
    "name:fra_x_preferred":[
        "Kulina"
    ],
    "name:hrv_x_preferred":[
        "Kulina"
    ],
    "name:ind_x_preferred":[
        "Kulina"
    ],
    "name:nld_x_preferred":[
        "Kulina"
    ],
    "name:rus_x_preferred":[
        "\u041a\u0443\u043b\u0438\u043d\u0430"
    ],
    "name:slv_x_preferred":[
        "Kulina"
    ],
    "name:srp_x_preferred":[
        "\u041a\u0443\u043b\u0438\u043d\u0430"
    ],
    "name:swe_x_preferred":[
        "Kulina"
    ],
    "wof:lang_x_official":[
        "ind"
    ],
    "wof:lang_x_spoken":[
        "ind",
        "eng"
    ],
    "wof:name":"Kulina",
    "wof:placetype":"locality"
},
  "geometry": {"coordinates":[107.22620000000001,-7.2885],"type":"Point"}
}