{
  "type": "Feature",
  "properties": {
    "gn:admin1_code":"30.0",
    "gn:asciiname":"Kulina",
    "gn:country_code":"ID",
    "gn:dem":512,
    "gn:feature_class":"P",
    "gn:feature_code":"PPL",
    "gn:name":"Kulina",
    "gn:population":0,
    "gn:timezone":"Asia/Jakarta",
    "iso:country":"ID",
    "name:ind_x_preferred":[
        "Kulina"
    ],
    "wof:name":"Kulina",
    "wof:placetype":"locality"
},
  "geometry": {"coordinates":[107.22620000000001,-7.2885],"type":"Point"}
}