{
  "type": "Feature",
  "properties": {
    "gn:admin1_code":"33",
    "gn:asciiname":"Ciputat",
    "gn:country_code":"ID",
    "gn:dem":30,
    "gn:feature_class":"P",
    "gn:feature_code":"PPL",
    "gn:name":"Ciputat",
    "gn:population":0,
    "gn:timezone":"Asia/Jakarta",
    "iso:country":"ID",
    "name:ara_x_preferred":[
        "\u0633\u064a\u0628\u0648\u062a\u0627\u062a"
    ],
    "name:azb_x_preferred":[
        "\u0633\u06cc\u067e\u0648\u062a\u0627\u062a"
    ],
    "name:ceb_x_preferred":[
        "Kecamatan Ciputat"
    ],
    "name:fas_x_preferred":[
        "\u0633\u06cc\u067e\u0648\u062a\u0627\u062a"
    ],
    "name:fra_x_preferred":[
        "Ciputat"
    ],
    "name:ind_x_preferred":[
        "Ciputat"
    ],
    "name:jav_x_preferred":[
        "Ciputat"
    ],
    "name:mlg_x_preferred":[
        "Ciputat"
    ],
    "name:msa_x_preferred":[
        "Ciputat"
    ],
    "name:nld_x_preferred":[
        "Ciputat"
    ],
    "name:nor_x_preferred":[
        "Ciputat"
    ],
    "name:por_x_preferred":[
        "Ciputat"
    ],
    "name:swe_x_preferred":[
        "Kecamatan Ciputat"
    ],
    "name:zho_x_preferred":[
        "\u829d\u5e03\u8fbe"
    ],
    "wof:name":"Ciputat",
    "wof:placetype":"locality"
},
  "geometry": {"coordinates":[106.23699999999999,-6.3261],"type":"Point"}
}