{
  "type": "Feature",
  "properties": {
    "gn:admin1_code":"30",
    "gn:asciiname":"Grahaharapan",
    "gn:country_code":"ID",
    "gn:dem":30,
    "gn:feature_class":"P",
    "gn:feature_code":"PPL",
    "gn:name":"Grahaharapan",
    "gn:population":0,
    "gn:timezone":"Asia/Jakarta",
    "iso:country":"ID",
    "name:ind_x_preferred":[
        "Grahaharapan"
    ],
    "wof:name":"Grahaharapan",
    "wof:placetype":"locality"
},
  "geometry": {"coordinates":[107.02694,-6.30139],"type":"Point"}
}