{
  "type": "Feature",
  "properties": {
    "gn:admin1_code":"7",
    "gn:asciiname":"Cranggang Barat",
    "gn:country_code":"ID",
    "gn:dem":251,
    "gn:feature_class":"P",
    "gn:feature_code":"PPL",
    "gn:name":"Cranggang Barat",
    "gn:population":0,
    "gn:timezone":"Asia/Jakarta",
    "iso:country":"ID",
    "name:ind_x_preferred":[
        "Cranggang Barat"
    ],
    "wof:name":"Cranggang Barat",
    "wof:placetype":"locality"
},
  "geometry": {"coordinates":[110.90170000000001,-6.7112],"type":"Point"}
}