{
  "type": "Feature",
  "properties": {
    "gn:admin1_code":"8.0",
    "gn:asciiname":"Sumberagung Krajan",
    "gn:country_code":"ID",
    "gn:dem":299,
    "gn:feature_class":"P",
    "gn:feature_code":"PPL",
    "gn:name":"Sumberagung Krajan",
    "gn:population":0,
    "gn:timezone":"Asia/Jakarta",
    "iso:country":"ID",
    "name:ind_x_preferred":[
        "Sumberagung Krajan"
    ],
    "name:und_x_variant":[
        "Soemberagoeng"
    ],
    "wof:lang_x_official":[
        "ind"
    ],
    "wof:lang_x_spoken":[
        "ind",
        "eng"
    ],
    "wof:name":"Sumberagung Krajan",
    "wof:placetype":"locality"
},
  "geometry": {"coordinates":[112.6738,-8.3469],"type":"Point"}
}