{
  "type": "Feature",
  "properties": {
    "gn:admin1_code":"2",
    "gn:asciiname":"Batulompeni",
    "gn:country_code":"ID",
    "gn:dem":111,
    "gn:feature_class":"P",
    "gn:feature_code":"PPL",
    "gn:name":"Batulompeni",
    "gn:population":0,
    "gn:timezone":"Asia/Makassar",
    "iso:country":"ID",
    "name:ind_x_preferred":[
        "Batulompeni"
    ],
    "wof:name":"Batulompeni",
    "wof:placetype":"locality"
},
  "geometry": {"coordinates":[115.4914,-8.217],"type":"Point"}
}