{
  "type": "Feature",
  "properties": {
    "gn:admin1_code":"26",
    "gn:asciiname":"Blok Pasar Lima",
    "gn:country_code":"ID",
    "gn:dem":78,
    "gn:feature_class":"P",
    "gn:feature_code":"PPL",
    "gn:name":"Blok Pasar Lima",
    "gn:population":0,
    "gn:timezone":"Asia/Jakarta",
    "iso:country":"ID",
    "name:ind_x_preferred":[
        "Blok Pasar Lima"
    ],
    "name:und_x_variant":[
        "Blokpasar 5"
    ],
    "wof:lang_x_official":[
        "ind"
    ],
    "wof:lang_x_spoken":[
        "ind",
        "eng"
    ],
    "wof:name":"Blok Pasar Lima",
    "wof:placetype":"locality"
},
  "geometry": {"coordinates":[98.71510000000001,3.4624],"type":"Point"}
}