{
  "type": "Feature",
  "properties": {
    "gn:admin1_code":"30",
    "gn:asciiname":"Cibitung",
    "gn:cc2":"ID",
    "gn:country_code":"ID",
    "gn:dem":1673,
    "gn:feature_class":"P",
    "gn:feature_code":"PPL",
    "gn:name":"Cibitung",
    "gn:population":0,
    "gn:timezone":"Asia/Jakarta",
    "iso:country":"ID",
    "name:und_x_variant":[
        "Tjibitung 1",
        "Cibitung Satu",
        "Cibitung"
    ],
    "wof:name":"Cibitung",
    "wof:placetype":"locality"
},
  "geometry": {"coordinates":[107.62888999999998,-7.18889],"type":"Point"}
}