{
  "type": "Feature",
  "properties": {
    "gn:admin1_code":"30.0",
    "gn:asciiname":"Cibeber Satu",
    "gn:country_code":"ID",
    "gn:dem":545,
    "gn:feature_class":"P",
    "gn:feature_code":"PPL",
    "gn:name":"Cibeber Satu",
    "gn:population":0,
    "gn:timezone":"Asia/Jakarta",
    "iso:country":"ID",
    "name:ind_x_preferred":[
        "Cibeber Satu"
    ],
    "wof:name":"Cibeber Satu",
    "wof:placetype":"locality"
},
  "geometry": {"coordinates":[106.77,-7.1658],"type":"Point"}
}