{
  "type": "Feature",
  "properties": {
    "gn:admin1_code":"33.0",
    "gn:asciiname":"Warungjogjog",
    "gn:country_code":"ID",
    "gn:dem":44,
    "gn:feature_class":"P",
    "gn:feature_code":"PPL",
    "gn:name":"Warungjogjog",
    "gn:population":0,
    "gn:timezone":"Asia/Jakarta",
    "iso:country":"ID",
    "name:ind_x_preferred":[
        "Warungjogjog"
    ],
    "wof:name":"Warungjogjog",
    "wof:placetype":"locality"
},
  "geometry": {"coordinates":[105.94329999999999,-6.7326],"type":"Point"}
}