{
  "type": "Feature",
  "properties": {
    "gn:admin1_code":"14",
    "gn:asciiname":"Keluanglolo",
    "gn:country_code":"ID",
    "gn:dem":11,
    "gn:feature_class":"P",
    "gn:feature_code":"PPL",
    "gn:name":"Keluanglolo",
    "gn:population":0,
    "gn:timezone":"Asia/Makassar",
    "iso:country":"ID",
    "name:ind_x_preferred":[
        "Keluanglolo"
    ],
    "wof:name":"Keluanglolo",
    "wof:placetype":"locality"
},
  "geometry": {"coordinates":[116.11620000000001,-1.8801],"type":"Point"}
}