{
  "type": "Feature",
  "properties": {
    "gn:admin1_code":"26",
    "gn:asciiname":"Pasar Tujuh",
    "gn:country_code":"ID",
    "gn:dem":107,
    "gn:feature_class":"P",
    "gn:feature_code":"PPL",
    "gn:name":"Pasar Tujuh",
    "gn:population":0,
    "gn:timezone":"Asia/Jakarta",
    "iso:country":"ID",
    "name:ind_x_preferred":[
        "Pasar Tujuh"
    ],
    "name:und_x_variant":[
        "Pasar 7"
    ],
    "wof:name":"Pasar Tujuh",
    "wof:placetype":"locality"
},
  "geometry": {"coordinates":[98.70829999999999,3.4268],"type":"Point"}
}