{
  "type": "Feature",
  "properties": {
    "gn:admin1_code":"7.0",
    "gn:asciiname":"Panyeretan Kidul",
    "gn:country_code":"ID",
    "gn:dem":9,
    "gn:feature_class":"P",
    "gn:feature_code":"PPL",
    "gn:name":"Panyeretan Kidul",
    "gn:population":0,
    "gn:timezone":"Asia/Jakarta",
    "iso:country":"ID",
    "name:ind_x_preferred":[
        "Panyeretan Kidul"
    ],
    "wof:name":"Panyeretan Kidul",
    "wof:placetype":"locality"
},
  "geometry": {"coordinates":[108.7419,-7.6037],"type":"Point"}
}