{
  "type": "Feature",
  "properties": {
    "gn:admin1_code":"21",
    "gn:asciiname":"Lawangke",
    "gn:country_code":"ID",
    "gn:dem":140,
    "gn:feature_class":"P",
    "gn:feature_code":"PPL",
    "gn:name":"Lawangke",
    "gn:population":0,
    "gn:timezone":"Asia/Makassar",
    "iso:country":"ID",
    "name:ind_x_preferred":[
        "Lawangke"
    ],
    "wof:name":"Lawangke",
    "wof:placetype":"locality"
},
  "geometry": {"coordinates":[121.28789999999999,-2.2882],"type":"Point"}
}