{
  "type": "Feature",
  "properties": {
    "gn:admin1_code":"7.0",
    "gn:asciiname":"Gendayakan",
    "gn:country_code":"ID",
    "gn:dem":284,
    "gn:feature_class":"P",
    "gn:feature_code":"PPL",
    "gn:name":"Gendayakan",
    "gn:population":0,
    "gn:timezone":"Asia/Jakarta",
    "iso:country":"ID",
    "name:ind_x_preferred":[
        "Gendayakan"
    ],
    "wof:name":"Gendayakan",
    "wof:placetype":"locality"
},
  "geometry": {"coordinates":[110.88667,-8.15444],"type":"Point"}
}