{
  "type": "Feature",
  "properties": {
    "gn:admin1_code":"30",
    "gn:asciiname":"Babakanjeruk",
    "gn:country_code":"ID",
    "gn:dem":764,
    "gn:feature_class":"P",
    "gn:feature_code":"PPL",
    "gn:name":"Babakanjeruk",
    "gn:population":0,
    "gn:timezone":"Asia/Jakarta",
    "iso:country":"ID",
    "name:ind_x_preferred":[
        "Babakanjeruk"
    ],
    "wof:name":"Babakanjeruk",
    "wof:placetype":"locality"
},
  "geometry": {"coordinates":[107.58556000000002,-6.89083],"type":"Point"}
}