{
  "type": "Feature",
  "properties": {
    "gn:admin1_code":"30.0",
    "gn:asciiname":"Kowari",
    "gn:country_code":"ID",
    "gn:dem":252,
    "gn:feature_class":"P",
    "gn:feature_code":"PPL",
    "gn:name":"Kowari",
    "gn:population":0,
    "gn:timezone":"Asia/Jakarta",
    "iso:country":"ID",
    "name:bre_x_preferred":[
        "Kowari"
    ],
    "name:cat_x_preferred":[
        "Kowari"
    ],
    "name:ceb_x_preferred":[
        "Dasyuroides byrnei"
    ],
    "name:ces_x_preferred":[
        "Vakorejsek \u010dty\u0159prst\u00fd"
    ],
    "name:deu_x_preferred":[
        "Doppelkamm-Beutelmaus"
    ],
    "name:eus_x_preferred":[
        "Dasyuroides byrnei"
    ],
    "name:fas_x_preferred":[
        "\u06a9\u0648\u0648\u0627\u0631\u06cc"
    ],
    "name:fin_x_preferred":[
        "Byrnesinpussihiiri"
    ],
    "name:fra_x_preferred":[
        "Dasyuroides byrnei"
    ],
    "name:heb_x_preferred":[
        "\u05e7\u05d5\u05d5\u05d0\u05e8\u05d9"
    ],
    "name:hun_x_preferred":[
        "Kovari"
    ],
    "name:ind_x_preferred":[
        "Kowari"
    ],
    "name:ita_x_preferred":[
        "Dasyuroides byrnei"
    ],
    "name:kor_x_preferred":[
        "\ucf54\uc640\ub9ac"
    ],
    "name:nld_x_preferred":[
        "Kamstaartbuidelrat"
    ],
    "name:pol_x_preferred":[
        "Kowari pustynny"
    ],
    "name:por_x_preferred":[
        "Dasyuroides byrnei"
    ],
    "name:ron_x_preferred":[
        "Kowari"
    ],
    "name:slk_x_preferred":[
        "Vakomy\u0161 kowari"
    ],
    "name:spa_x_preferred":[
        "Dasyuroides byrnei"
    ],
    "name:srp_x_preferred":[
        "\u041a\u043e\u0432\u0430\u0440\u0438"
    ],
    "name:swe_x_preferred":[
        "Byrnes pungmus"
    ],
    "name:ukr_x_preferred":[
        "\u041a\u043e\u0432\u0430\u0440\u0456"
    ],
    "name:vie_x_preferred":[
        "Dasyuroides byrnei"
    ],
    "name:war_x_preferred":[
        "Dasyuroides byrnei"
    ],
    "wof:lang_x_official":[
        "ind"
    ],
    "wof:lang_x_spoken":[
        "ind",
        "eng"
    ],
    "wof:name":"Kowari",
    "wof:placetype":"locality"
},
  "geometry": {"coordinates":[108.5138,-7.1619],"type":"Point"}
}