{
  "type": "Feature",
  "properties": {
    "gn:admin1_code":"30",
    "gn:asciiname":"Tenjonagara",
    "gn:cc2":"ID",
    "gn:country_code":"ID",
    "gn:dem":883,
    "gn:feature_class":"P",
    "gn:feature_code":"PPL",
    "gn:name":"Tenjonagara",
    "gn:population":0,
    "gn:timezone":"Asia/Jakarta",
    "iso:country":"ID",
    "name:und_x_variant":[
        "Tendjonagara",
        "Tenjonagara"
    ],
    "wof:lang_x_official":[
        "ind"
    ],
    "wof:lang_x_spoken":[
        "ind",
        "eng"
    ],
    "wof:name":"Tenjonagara",
    "wof:placetype":"locality"
},
  "geometry": {"coordinates":[107.69972,-7.10111],"type":"Point"}
}