{
  "type": "Feature",
  "properties": {
    "gn:admin1_code":"38",
    "gn:asciiname":"Raja",
    "gn:country_code":"ID",
    "gn:dem":174,
    "gn:feature_class":"P",
    "gn:feature_code":"PPL",
    "gn:name":"Raja",
    "gn:population":0,
    "gn:timezone":"Asia/Makassar",
    "iso:country":"ID",
    "name:ind_x_preferred":[
        "Raja"
    ],
    "wof:name":"Raja",
    "wof:placetype":"locality"
},
  "geometry": {"coordinates":[119.96429999999999,-4.7596],"type":"Point"}
}