{
  "type": "Feature",
  "properties": {
    "gn:admin1_code":"38",
    "gn:asciiname":"Raja",
    "gn:country_code":"ID",
    "gn:dem":174,
    "gn:feature_class":"P",
    "gn:feature_code":"PPL",
    "gn:name":"Raja",
    "gn:population":0,
    "gn:timezone":"Asia/Makassar",
    "iso:country":"ID",
    "name:ara_x_preferred":[
        "\u0631\u0627\u062c\u0627"
    ],
    "name:bul_x_preferred":[
        "\u0420\u0430\u0434\u0436\u0430"
    ],
    "name:cat_x_preferred":[
        "Raja"
    ],
    "name:ces_x_preferred":[
        "R\u00e1d\u017ea"
    ],
    "name:dan_x_preferred":[
        "Raja"
    ],
    "name:deu_x_preferred":[
        "Raja"
    ],
    "name:epo_x_preferred":[
        "Ra\u011do"
    ],
    "name:eus_x_preferred":[
        "Raj\u00e1"
    ],
    "name:fas_x_preferred":[
        "\u0631\u0627\u062c\u0627"
    ],
    "name:fin_x_preferred":[
        "Rad\u017ea"
    ],
    "name:fra_x_preferred":[
        "Raja"
    ],
    "name:glg_x_preferred":[
        "Rax\u00e1"
    ],
    "name:heb_x_preferred":[
        "\u05e8\u05d2'\u05d4"
    ],
    "name:hun_x_preferred":[
        "R\u00e1dzsa"
    ],
    "name:hye_x_preferred":[
        "\u054c\u0561\u057b\u0561"
    ],
    "name:ilo_x_preferred":[
        "Raha"
    ],
    "name:ind_x_preferred":[
        "Raja"
    ],
    "name:ita_x_preferred":[
        "Raja"
    ],
    "name:jpn_x_preferred":[
        "\u30e9\u30fc\u30b8\u30e3"
    ],
    "name:kat_x_preferred":[
        "\u10e0\u10d0\u10ef\u10d0"
    ],
    "name:msa_x_preferred":[
        "Raja"
    ],
    "name:nld_x_preferred":[
        "Radja"
    ],
    "name:nor_x_preferred":[
        "Raja"
    ],
    "name:oci_x_preferred":[
        "Raja"
    ],
    "name:pol_x_preferred":[
        "Rad\u017ca"
    ],
    "name:por_x_preferred":[
        "Raj\u00e1"
    ],
    "name:rus_x_preferred":[
        "\u0420\u0430\u0434\u0436\u0430"
    ],
    "name:spa_x_preferred":[
        "Raj\u00e1"
    ],
    "name:srp_x_preferred":[
        "\u0420\u0430\u045f\u0430"
    ],
    "name:swe_x_preferred":[
        "Indiska adelstitlar"
    ],
    "name:tat_x_preferred":[
        "Raca"
    ],
    "name:tgl_x_preferred":[
        "Raha"
    ],
    "name:ukr_x_preferred":[
        "\u0420\u0430\u0434\u0436\u0430"
    ],
    "name:urd_x_preferred":[
        "\u0631\u0627\u062c\u0627"
    ],
    "name:uzb_x_preferred":[
        "Roja"
    ],
    "wof:lang_x_official":[
        "ind"
    ],
    "wof:lang_x_spoken":[
        "ind",
        "eng"
    ],
    "wof:name":"Raja",
    "wof:placetype":"locality"
},
  "geometry": {"coordinates":[119.96429999999999,-4.7596],"type":"Point"}
}