{
  "type": "Feature",
  "properties": {
    "gn:admin1_code":"38.0",
    "gn:asciiname":"Rawangale",
    "gn:country_code":"ID",
    "gn:dem":131,
    "gn:feature_class":"P",
    "gn:feature_code":"PPL",
    "gn:name":"Rawangale",
    "gn:population":0,
    "gn:timezone":"Asia/Makassar",
    "iso:country":"ID",
    "name:ind_x_preferred":[
        "Rawangale"
    ],
    "wof:name":"Rawangale",
    "wof:placetype":"locality"
},
  "geometry": {"coordinates":[120.0052,-4.7175],"type":"Point"}
}