{
  "type": "Feature",
  "properties": {
    "gn:admin1_code":"34.0",
    "gn:asciiname":"Dangi",
    "gn:country_code":"ID",
    "gn:dem":10,
    "gn:feature_class":"P",
    "gn:feature_code":"PPL",
    "gn:name":"Dangi",
    "gn:population":0,
    "gn:timezone":"Asia/Makassar",
    "iso:country":"ID",
    "name:ind_x_preferred":[
        "Dangi"
    ],
    "name:msa_x_preferred":[
        "Dangi"
    ],
    "wof:name":"Dangi",
    "wof:placetype":"locality"
},
  "geometry": {"coordinates":[123.11879999999999,0.8857],"type":"Point"}
}