{
  "type": "Feature",
  "properties": {
    "gn:admin1_code":"10.0",
    "gn:asciiname":"Sriten",
    "gn:country_code":"ID",
    "gn:dem":404,
    "gn:feature_class":"P",
    "gn:feature_code":"PPL",
    "gn:name":"Sriten",
    "gn:population":0,
    "gn:timezone":"Asia/Jakarta",
    "iso:country":"ID",
    "name:ind_x_preferred":[
        "Sriten"
    ],
    "wof:name":"Sriten",
    "wof:placetype":"locality"
},
  "geometry": {"coordinates":[110.75583,-8.03833],"type":"Point"}
}