{
  "type": "Feature",
  "properties": {
    "gn:admin1_code":"24",
    "gn:asciiname":"Padangbungo",
    "gn:country_code":"ID",
    "gn:dem":18,
    "gn:feature_class":"P",
    "gn:feature_code":"PPL",
    "gn:name":"Padangbungo",
    "gn:population":0,
    "gn:timezone":"Asia/Jakarta",
    "iso:country":"ID",
    "name:ind_x_preferred":[
        "Padangbungo"
    ],
    "wof:name":"Padangbungo",
    "wof:placetype":"locality"
},
  "geometry": {"coordinates":[100.52485,-1.24384],"type":"Point"}
}