{
  "type": "Feature",
  "properties": {
    "gn:country":"ID",
    "gn:fcode":"PPL",
    "gn:pop":0,
    "iso:country":"ID",
    "name:ind_x_preferred":[
        "Kotapinang"
    ],
    "qs:name":"Kotapinang",
    "qs:name_adm0":"Indonesia",
    "qs:name_adm1":"Sumatera Utara",
    "qs:photos_9r":0,
    "qs:photos_sr":0,
    "qs:placetype":"Town",
    "qs:pop_sr":"0",
    "wof:lang_x_official":[
        "ind"
    ],
    "wof:lang_x_spoken":[
        "ind",
        "eng"
    ],
    "wof:name":"Kotapinang",
    "wof:placetype":"locality",
    "wof:population":0
},
  "geometry": {"coordinates":[98.3398,3.5144],"type":"Point"}
}