{
  "type": "Feature",
  "properties": {
    "gn:admin1_code":"18.0",
    "gn:asciiname":"Suleama",
    "gn:country_code":"ID",
    "gn:dem":78,
    "gn:feature_class":"P",
    "gn:feature_code":"PPL",
    "gn:name":"Suleama",
    "gn:population":0,
    "gn:timezone":"Asia/Makassar",
    "iso:country":"ID",
    "name:ind_x_preferred":[
        "Suleama"
    ],
    "wof:name":"Suleama",
    "wof:placetype":"locality"
},
  "geometry": {"coordinates":[122.91370000000001,-10.9005],"type":"Point"}
}