{
  "type": "Feature",
  "properties": {
    "gn:admin1_code":"30",
    "gn:asciiname":"Kampungsirna",
    "gn:country_code":"ID",
    "gn:dem":557,
    "gn:feature_class":"P",
    "gn:feature_code":"PPL",
    "gn:name":"Kampungsirna",
    "gn:population":0,
    "gn:timezone":"Asia/Jakarta",
    "iso:country":"ID",
    "name:ind_x_preferred":[
        "Kampungsirna"
    ],
    "wof:name":"Kampungsirna",
    "wof:placetype":"locality"
},
  "geometry": {"coordinates":[106.64556,-6.67333],"type":"Point"}
}