{
  "type": "Feature",
  "properties": {
    "gn:admin1_code":"8.0",
    "gn:asciiname":"Kalipare",
    "gn:country":"ID",
    "gn:country_code":"ID",
    "gn:dem":304,
    "gn:fcode":"PPLA3",
    "gn:feature_class":"P",
    "gn:feature_code":"PPLA4",
    "gn:name":"Kalipare",
    "gn:pop":0,
    "gn:population":0,
    "gn:timezone":"Asia/Jakarta",
    "iso:country":"ID",
    "name:ind_x_preferred":[
        "Kalipare"
    ],
    "qs:name":"Kalipare",
    "qs:photos_9r":0,
    "qs:photos_sr":0,
    "qs:pop_sr":"0",
    "wof:lang_x_official":[
        "ind"
    ],
    "wof:lang_x_spoken":[
        "ind",
        "eng"
    ],
    "wof:name":"Kalipare",
    "wof:placetype":"locality",
    "wof:population":0
},
  "geometry": {"coordinates":[112.4663,-8.2066],"type":"Point"}
}