{
  "type": "Feature",
  "properties": {
    "gn:admin1_code":"17.0",
    "gn:asciiname":"Pamulung",
    "gn:country_code":"ID",
    "gn:dem":29,
    "gn:feature_class":"P",
    "gn:feature_code":"PPL",
    "gn:name":"Pamulung",
    "gn:population":0,
    "gn:timezone":"Asia/Makassar",
    "iso:country":"ID",
    "name:ind_x_preferred":[
        "Pamulung"
    ],
    "wof:name":"Pamulung",
    "wof:placetype":"locality"
},
  "geometry": {"coordinates":[117.38590000000001,-8.4996],"type":"Point"}
}