{
  "type": "Feature",
  "properties": {
    "gn:admin1_code":"24.0",
    "gn:asciiname":"Barungbarungrendah",
    "gn:country_code":"ID",
    "gn:dem":807,
    "gn:feature_class":"P",
    "gn:feature_code":"PPL",
    "gn:name":"Barungbarungrendah",
    "gn:population":0,
    "gn:timezone":"Asia/Jakarta",
    "iso:country":"ID",
    "name:ind_x_preferred":[
        "Barungbarungrendah"
    ],
    "name:und_x_variant":[
        "Baroengbaroengrendah"
    ],
    "wof:lang_x_official":[
        "ind"
    ],
    "wof:lang_x_spoken":[
        "ind",
        "eng"
    ],
    "wof:name":"Barungbarungrendah",
    "wof:placetype":"locality"
},
  "geometry": {"coordinates":[100.93486,-1.14584],"type":"Point"}
}