{
  "type": "Feature",
  "properties": {
    "gn:admin1_code":"0.0",
    "gn:asciiname":"Kediri",
    "gn:country_code":"ID",
    "gn:dem":94,
    "gn:feature_class":"P",
    "gn:feature_code":"PPL",
    "gn:name":"Kediri",
    "gn:population":0,
    "gn:timezone":"Asia/Makassar",
    "iso:country":"ID",
    "name:ceb_x_preferred":[
        "Kediri"
    ],
    "name:deu_x_preferred":[
        "Kediri"
    ],
    "name:heb_x_preferred":[
        "\u05e7\u05d3\u05d9\u05e8\u05d9"
    ],
    "name:hun_x_preferred":[
        "Kediri"
    ],
    "name:ind_x_preferred":[
        "Kediri"
    ],
    "name:jav_x_preferred":[
        "Kadhiri"
    ],
    "name:kat_x_preferred":[
        "\u10d9\u10d4\u10d3\u10d8\u10e0\u10d8"
    ],
    "name:mal_x_preferred":[
        "\u0d15\u0d46\u0d26\u0d3f\u0d30\u0d3f"
    ],
    "name:mlg_x_preferred":[
        "Kediri"
    ],
    "name:nld_x_preferred":[
        "Kediri"
    ],
    "name:rus_x_preferred":[
        "\u041a\u0435\u0434\u0438\u0440\u0438"
    ],
    "name:swe_x_preferred":[
        "Kediri"
    ],
    "name:vie_x_preferred":[
        "Kediri"
    ],
    "wof:lang_x_official":[
        "ind"
    ],
    "wof:lang_x_spoken":[
        "ind",
        "eng"
    ],
    "wof:name":"Kediri",
    "wof:placetype":"locality"
},
  "geometry": {"coordinates":[115.13333,-8.56667],"type":"Point"}
}