{
  "type": "Feature",
  "properties": {
    "gn:admin1_code":"08",
    "gn:asciiname":"Klampissemolo",
    "gn:country_code":"ID",
    "gn:dem":4,
    "gn:feature_class":"P",
    "gn:feature_code":"PPL",
    "gn:name":"Klampissemolo",
    "gn:population":0,
    "gn:timezone":"Asia/Jakarta",
    "iso:country":"ID",
    "name:ind_x_preferred":[
        "Klampissemolo"
    ],
    "wof:name":"Klampissemolo",
    "wof:placetype":"locality"
},
  "geometry": {"coordinates":[112.77889999999999,-7.2949],"type":"Point"}
}