{
  "type": "Feature",
  "properties": {
    "gn:admin1_code":"38",
    "gn:asciiname":"Lalong Selatan",
    "gn:country_code":"ID",
    "gn:dem":40,
    "gn:feature_class":"P",
    "gn:feature_code":"PPL",
    "gn:name":"Lalong Selatan",
    "gn:population":0,
    "gn:timezone":"Asia/Makassar",
    "iso:country":"ID",
    "name:ind_x_preferred":[
        "Lalong Selatan"
    ],
    "wof:name":"Lalong Selatan",
    "wof:placetype":"locality"
},
  "geometry": {"coordinates":[120.1567,-2.8707],"type":"Point"}
}