{
  "type": "Feature",
  "properties": {
    "gn:admin1_code":"22.0",
    "gn:asciiname":"Nohunohu Dua",
    "gn:country_code":"ID",
    "gn:dem":34,
    "gn:feature_class":"P",
    "gn:feature_code":"PPL",
    "gn:name":"Nohunohu Dua",
    "gn:population":0,
    "gn:timezone":"Asia/Makassar",
    "iso:country":"ID",
    "name:ind_x_preferred":[
        "Nohunohu Dua"
    ],
    "name:und_x_variant":[
        "Nohunohu 2"
    ],
    "wof:name":"Nohunohu Dua",
    "wof:placetype":"locality"
},
  "geometry": {"coordinates":[122.1279,-3.8942],"type":"Point"}
}