{
  "type": "Feature",
  "properties": {
    "gn:admin1_code":"7.0",
    "gn:asciiname":"Cindaga",
    "gn:country_code":"ID",
    "gn:dem":19,
    "gn:feature_class":"P",
    "gn:feature_code":"PPL",
    "gn:name":"Cindaga",
    "gn:population":0,
    "gn:timezone":"Asia/Jakarta",
    "iso:country":"ID",
    "name:ind_x_preferred":[
        "Cindaga"
    ],
    "name:und_x_variant":[
        "Tjindaga"
    ],
    "wof:name":"Cindaga",
    "wof:placetype":"locality"
},
  "geometry": {"coordinates":[109.17667,-7.54583],"type":"Point"}
}