{
  "type": "Feature",
  "properties": {
    "gn:admin1_code":"07",
    "gn:asciiname":"Karangduren",
    "gn:country_code":"ID",
    "gn:dem":458,
    "gn:feature_class":"P",
    "gn:feature_code":"PPL",
    "gn:name":"Karangduren",
    "gn:population":0,
    "gn:timezone":"Asia/Jakarta",
    "iso:country":"ID",
    "wof:name":"Karangduren",
    "wof:placetype":"locality"
},
  "geometry": {"coordinates":[110.59166999999999,-7.52306],"type":"Point"}
}