{
  "type": "Feature",
  "properties": {
    "gn:country":"ID",
    "gn:fcode":"PPL",
    "gn:pop":0,
    "iso:country":"ID",
    "qs:name":"Karangmojo",
    "qs:name_adm0":"Indonesia",
    "qs:name_adm1":"Daerah Istimewa Yogyakarta",
    "qs:photos_9r":0,
    "qs:photos_sr":0,
    "qs:placetype":"Town",
    "qs:pop_sr":"0",
    "wof:lang_x_official":[
        "ind"
    ],
    "wof:lang_x_spoken":[
        "ind",
        "eng"
    ],
    "wof:name":"Karangmojo",
    "wof:placetype":"locality",
    "wof:population":0
},
  "geometry": {"coordinates":[110.64028,-7.92778],"type":"Point"}
}