{
  "type": "Feature",
  "properties": {
    "gn:admin1_code":"8.0",
    "gn:asciiname":"Grebegan",
    "gn:country_code":"ID",
    "gn:dem":90,
    "gn:feature_class":"P",
    "gn:feature_code":"PPL",
    "gn:name":"Grebegan",
    "gn:population":0,
    "gn:timezone":"Asia/Jakarta",
    "iso:country":"ID",
    "name:ind_x_preferred":[
        "Grebegan"
    ],
    "wof:name":"Grebegan",
    "wof:placetype":"locality"
},
  "geometry": {"coordinates":[111.8642,-7.3213],"type":"Point"}
}