{
  "type": "Feature",
  "properties": {
    "gn:admin1_code":"7.0",
    "gn:asciiname":"Ngluko",
    "gn:country_code":"ID",
    "gn:dem":223,
    "gn:feature_class":"P",
    "gn:feature_code":"PPL",
    "gn:name":"Ngluko",
    "gn:population":0,
    "gn:timezone":"Asia/Jakarta",
    "iso:country":"ID",
    "name:ind_x_preferred":[
        "Ngluko"
    ],
    "wof:name":"Ngluko",
    "wof:placetype":"locality"
},
  "geometry": {"coordinates":[110.83056000000001,-8.00778],"type":"Point"}
}