{
  "type": "Feature",
  "properties": {
    "gn:admin1_code":"8.0",
    "gn:asciiname":"Sosial",
    "gn:country_code":"ID",
    "gn:dem":11,
    "gn:feature_class":"P",
    "gn:feature_code":"PPL",
    "gn:name":"Sosial",
    "gn:population":0,
    "gn:timezone":"Asia/Jakarta",
    "iso:country":"ID",
    "name:ind_x_preferred":[
        "Sosial"
    ],
    "wof:name":"Sosial",
    "wof:placetype":"locality"
},
  "geometry": {"coordinates":[114.23309999999999,-8.569],"type":"Point"}
}