{
  "type": "Feature",
  "properties": {
    "gn:admin1_code":"8.0",
    "gn:asciiname":"Kalitalun Wetan",
    "gn:country_code":"ID",
    "gn:dem":301,
    "gn:feature_class":"P",
    "gn:feature_code":"PPL",
    "gn:name":"Kalitalun Wetan",
    "gn:population":0,
    "gn:timezone":"Asia/Jakarta",
    "iso:country":"ID",
    "name:ind_x_preferred":[
        "Kalitalun Wetan"
    ],
    "wof:name":"Kalitalun Wetan",
    "wof:placetype":"locality"
},
  "geometry": {"coordinates":[111.88679999999999,-8.2162],"type":"Point"}
}