{
  "type": "Feature",
  "properties": {
    "gn:admin1_code":"30.0",
    "gn:asciiname":"Races Satu",
    "gn:country_code":"ID",
    "gn:dem":592,
    "gn:feature_class":"P",
    "gn:feature_code":"PPL",
    "gn:name":"Races Satu",
    "gn:population":0,
    "gn:timezone":"Asia/Jakarta",
    "iso:country":"ID",
    "name:ind_x_preferred":[
        "Races Satu"
    ],
    "wof:name":"Races Satu",
    "wof:placetype":"locality"
},
  "geometry": {"coordinates":[113.99809999999999,-7.9541],"type":"Point"}
}