{
  "type": "Feature",
  "properties": {
    "gn:admin1_code":"18",
    "gn:asciiname":"Kole",
    "gn:country_code":"ID",
    "gn:dem":850,
    "gn:feature_class":"P",
    "gn:feature_code":"PPL",
    "gn:name":"Kole",
    "gn:population":0,
    "gn:timezone":"Asia/Makassar",
    "iso:country":"ID",
    "name:fra_x_preferred":[
        "Kole Weathers"
    ],
    "name:heb_x_preferred":[
        "\u05e7\u05d5\u05dc\u05d4"
    ],
    "name:hun_x_preferred":[
        "Kole"
    ],
    "name:ind_x_preferred":[
        "Kole"
    ],
    "name:ron_x_preferred":[
        "Kole"
    ],
    "name:spa_x_preferred":[
        "Kole"
    ],
    "wof:lang_x_official":[
        "ind"
    ],
    "wof:lang_x_spoken":[
        "ind",
        "eng"
    ],
    "wof:name":"Kole",
    "wof:placetype":"locality"
},
  "geometry": {"coordinates":[120.35639999999999,-8.6869],"type":"Point"}
}