{
  "type": "Feature",
  "properties": {
    "gn:admin1_code":"30",
    "gn:asciiname":"Babakan Tengah",
    "gn:country_code":"ID",
    "gn:dem":7,
    "gn:feature_class":"P",
    "gn:feature_code":"PPL",
    "gn:name":"Babakan Tengah",
    "gn:population":0,
    "gn:timezone":"Asia/Jakarta",
    "iso:country":"ID",
    "name:ind_x_preferred":[
        "Babakan Tengah"
    ],
    "wof:name":"Babakan Tengah",
    "wof:placetype":"locality"
},
  "geometry": {"coordinates":[107.31139,-6.0875],"type":"Point"}
}