{
  "type": "Feature",
  "properties": {
    "gn:admin1_code":"31.0",
    "gn:asciiname":"Solang",
    "gn:country_code":"ID",
    "gn:dem":55,
    "gn:feature_class":"P",
    "gn:feature_code":"PPL",
    "gn:name":"Solang",
    "gn:population":0,
    "gn:timezone":"Asia/Makassar",
    "iso:country":"ID",
    "name:ind_x_preferred":[
        "Solang"
    ],
    "wof:name":"Solang",
    "wof:placetype":"locality"
},
  "geometry": {"coordinates":[125.44240000000001,2.3199],"type":"Point"}
}