{
  "type": "Feature",
  "properties": {
    "gn:admin1_code":"41",
    "gn:asciiname":"Tambuku",
    "gn:country_code":"ID",
    "gn:dem":29,
    "gn:feature_class":"P",
    "gn:feature_code":"PPL",
    "gn:name":"Tambuku",
    "gn:population":0,
    "gn:timezone":"Asia/Makassar",
    "iso:country":"ID",
    "name:ind_x_preferred":[
        "Tambuku"
    ],
    "wof:name":"Tambuku",
    "wof:placetype":"locality"
},
  "geometry": {"coordinates":[119.4284,-2.2533],"type":"Point"}
}