{
  "type": "Feature",
  "properties": {
    "gn:admin1_code":"7.0",
    "gn:asciiname":"Kebonjeruk",
    "gn:country_code":"ID",
    "gn:dem":408,
    "gn:feature_class":"P",
    "gn:feature_code":"PPL",
    "gn:name":"Kebonjeruk",
    "gn:population":0,
    "gn:timezone":"Asia/Jakarta",
    "iso:country":"ID",
    "wof:name":"Kebonjeruk",
    "wof:placetype":"locality"
},
  "geometry": {"coordinates":[110.62306,-7.39278],"type":"Point"}
}