{
  "type": "Feature",
  "properties": {
    "gn:admin1_code":"2.0",
    "gn:asciiname":"Ped",
    "gn:country_code":"ID",
    "gn:dem":9,
    "gn:feature_class":"P",
    "gn:feature_code":"PPLA4",
    "gn:name":"Ped",
    "gn:population":0,
    "gn:timezone":"Asia/Makassar",
    "iso:country":"ID",
    "name:ara_x_preferred":[
        "\u0628\u0627\u062f\u0626\u0629"
    ],
    "name:ces_x_preferred":[
        "Ped"
    ],
    "name:ind_x_preferred":[
        "Ped"
    ],
    "wof:lang_x_official":[
        "ind"
    ],
    "wof:lang_x_spoken":[
        "ind",
        "eng"
    ],
    "wof:name":"Ped",
    "wof:placetype":"locality"
},
  "geometry": {"coordinates":[115.5064,-8.6739],"type":"Point"}
}