{
  "type": "Feature",
  "properties": {
    "gn:admin1_code":"08",
    "gn:asciiname":"Mendikeh",
    "gn:country_code":"ID",
    "gn:dem":49,
    "gn:feature_class":"P",
    "gn:feature_code":"PPL",
    "gn:name":"Mendikeh",
    "gn:population":0,
    "gn:timezone":"Asia/Jakarta",
    "iso:country":"ID",
    "name:ind_x_preferred":[
        "Mendikeh"
    ],
    "name:und_x_variant":[
        "Mendike"
    ],
    "wof:name":"Mendikeh",
    "wof:placetype":"locality"
},
  "geometry": {"coordinates":[112.85850000000001,-7.0225],"type":"Point"}
}