{
  "type": "Feature",
  "properties": {
    "gn:admin1_code":"1",
    "gn:asciiname":"Payadeumam Dua",
    "gn:country_code":"ID",
    "gn:dem":11,
    "gn:feature_class":"P",
    "gn:feature_code":"PPL",
    "gn:name":"Payadeumam Dua",
    "gn:population":0,
    "gn:timezone":"Asia/Jakarta",
    "iso:country":"ID",
    "name:ind_x_preferred":[
        "Payadeumam Dua"
    ],
    "name:und_x_variant":[
        "Pajademam 2",
        "Payadeumam 2"
    ],
    "wof:lang_x_official":[
        "ind"
    ],
    "wof:lang_x_spoken":[
        "ind",
        "eng"
    ],
    "wof:name":"Payadeumam Dua",
    "wof:placetype":"locality"
},
  "geometry": {"coordinates":[97.5074,5.0948],"type":"Point"}
}