{
  "type": "Feature",
  "properties": {
    "gn:admin1_code":"0.0",
    "gn:asciiname":"Jogoboyo",
    "gn:cc2":"ID",
    "gn:country_code":"ID",
    "gn:dem":7,
    "gn:feature_class":"P",
    "gn:feature_code":"PPL",
    "gn:name":"Jogoboyo",
    "gn:population":0,
    "gn:timezone":"Asia/Jakarta",
    "iso:country":"ID",
    "name:und_x_variant":[
        "Djagabaja",
        "Djogobojo",
        "Djagalaga",
        "Jogoboyo"
    ],
    "wof:lang_x_official":[
        "ind"
    ],
    "wof:lang_x_spoken":[
        "ind",
        "eng"
    ],
    "wof:name":"Jogoboyo",
    "wof:placetype":"locality"
},
  "geometry": {"coordinates":[110.01667,-7.88333],"type":"Point"}
}