{
  "type": "Feature",
  "properties": {
    "gn:admin1_code":"38.0",
    "gn:asciiname":"Rappokanrung",
    "gn:country_code":"ID",
    "gn:dem":349,
    "gn:feature_class":"P",
    "gn:feature_code":"PPL",
    "gn:name":"Rappokanrung",
    "gn:population":0,
    "gn:timezone":"Asia/Makassar",
    "iso:country":"ID",
    "name:ind_x_preferred":[
        "Rappokanrung"
    ],
    "name:und_x_variant":[
        "Lapakanro\u00eb",
        "Lapankroi"
    ],
    "wof:lang_x_official":[
        "ind"
    ],
    "wof:lang_x_spoken":[
        "ind",
        "eng"
    ],
    "wof:name":"Rappokanrung",
    "wof:placetype":"locality"
},
  "geometry": {"coordinates":[119.9044,-4.9406],"type":"Point"}
}