{
  "type": "Feature",
  "properties": {
    "gn:admin1_code":"2.0",
    "gn:asciiname":"Tibulakasasak",
    "gn:country_code":"ID",
    "gn:dem":219,
    "gn:feature_class":"P",
    "gn:feature_code":"PPLA4",
    "gn:name":"Tibulakasasak",
    "gn:population":0,
    "gn:timezone":"Asia/Makassar",
    "iso:country":"ID",
    "name:ind_x_preferred":[
        "Tibulakasasak"
    ],
    "wof:name":"Tibulakasasak",
    "wof:placetype":"locality"
},
  "geometry": {"coordinates":[115.6309,-8.4234],"type":"Point"}
}