{
  "type": "Feature",
  "properties": {
    "gn:admin1_code":"8.0",
    "gn:asciiname":"Putatmalang",
    "gn:country_code":"ID",
    "gn:dem":49,
    "gn:feature_class":"P",
    "gn:feature_code":"PPL",
    "gn:name":"Putatmalang",
    "gn:population":0,
    "gn:timezone":"Asia/Jakarta",
    "iso:country":"ID",
    "name:ind_x_preferred":[
        "Putatmalang"
    ],
    "wof:name":"Putatmalang",
    "wof:placetype":"locality"
},
  "geometry": {"coordinates":[111.997,-7.5981],"type":"Point"}
}