{
  "type": "Feature",
  "properties": {
    "gn:admin1_code":"41.0",
    "gn:asciiname":"Mama",
    "gn:country_code":"ID",
    "gn:dem":1225,
    "gn:feature_class":"P",
    "gn:feature_code":"PPL",
    "gn:name":"Mama",
    "gn:population":0,
    "gn:timezone":"Asia/Makassar",
    "iso:country":"ID",
    "name:ind_x_preferred":[
        "Mama"
    ],
    "wof:name":"Mama",
    "wof:placetype":"locality"
},
  "geometry": {"coordinates":[119.41500000000001,-2.9173],"type":"Point"}
}