{
  "type": "Feature",
  "properties": {
    "gn:admin1_code":"41.0",
    "gn:asciiname":"Mama",
    "gn:country_code":"ID",
    "gn:dem":1225,
    "gn:feature_class":"P",
    "gn:feature_code":"PPL",
    "gn:name":"Mama",
    "gn:population":0,
    "gn:timezone":"Asia/Makassar",
    "iso:country":"ID",
    "name:bel_x_preferred":[
        "\u041c\u0430\u043c\u0430"
    ],
    "name:cat_x_preferred":[
        "Mama"
    ],
    "name:ceb_x_preferred":[
        "Mama"
    ],
    "name:ces_x_preferred":[
        "Mama"
    ],
    "name:deu_x_preferred":[
        "Mama"
    ],
    "name:est_x_preferred":[
        "Mama"
    ],
    "name:eus_x_preferred":[
        "Mama"
    ],
    "name:fas_x_preferred":[
        "\u0645\u0627\u0645\u0627"
    ],
    "name:fra_x_preferred":[
        "Mama"
    ],
    "name:hun_x_preferred":[
        "Mama"
    ],
    "name:ind_x_preferred":[
        "Mama"
    ],
    "name:ita_x_preferred":[
        "Mama"
    ],
    "name:jpn_x_preferred":[
        "\u30de\u30de"
    ],
    "name:lit_x_preferred":[
        "Mama"
    ],
    "name:nld_x_preferred":[
        "Mama"
    ],
    "name:pol_x_preferred":[
        "Mama"
    ],
    "name:por_x_preferred":[
        "Mama"
    ],
    "name:ron_x_preferred":[
        "Mama"
    ],
    "name:rus_x_preferred":[
        "\u041c\u0430\u043c\u0430"
    ],
    "name:slk_x_preferred":[
        "Mama"
    ],
    "name:spa_x_preferred":[
        "Mama"
    ],
    "name:srp_x_preferred":[
        "\u041c\u0430\u043c\u0430"
    ],
    "name:swe_x_preferred":[
        "Mama"
    ],
    "name:tgl_x_preferred":[
        "Mama"
    ],
    "name:tur_x_preferred":[
        "Mama"
    ],
    "name:ukr_x_preferred":[
        "\u041c\u0430\u043c\u0430"
    ],
    "wof:name":"Mama",
    "wof:placetype":"locality"
},
  "geometry": {"coordinates":[119.41500000000001,-2.9173],"type":"Point"}
}