{
  "type": "Feature",
  "properties": {
    "gn:admin1_code":"8.0",
    "gn:asciiname":"Broto",
    "gn:country_code":"ID",
    "gn:dem":150,
    "gn:feature_class":"P",
    "gn:feature_code":"PPLA4",
    "gn:name":"Broto",
    "gn:population":0,
    "gn:timezone":"Asia/Jakarta",
    "iso:country":"ID",
    "name:arg_x_preferred":[
        "Broto"
    ],
    "name:ast_x_preferred":[
        "Broto"
    ],
    "name:cat_x_preferred":[
        "Broto"
    ],
    "name:ceb_x_preferred":[
        "Broto"
    ],
    "name:deu_x_preferred":[
        "Broto"
    ],
    "name:eus_x_preferred":[
        "Broto"
    ],
    "name:fra_x_preferred":[
        "Broto"
    ],
    "name:hun_x_preferred":[
        "Broto"
    ],
    "name:ind_x_preferred":[
        "Broto"
    ],
    "name:ita_x_preferred":[
        "Broto"
    ],
    "name:msa_x_preferred":[
        "Broto"
    ],
    "name:nld_x_preferred":[
        "Broto"
    ],
    "name:oci_x_preferred":[
        "Broto"
    ],
    "name:pol_x_preferred":[
        "Broto"
    ],
    "name:por_x_preferred":[
        "Broto"
    ],
    "name:rus_x_preferred":[
        "\u0411\u0440\u043e\u0442\u043e"
    ],
    "name:spa_x_preferred":[
        "Broto"
    ],
    "name:swe_x_preferred":[
        "Broto"
    ],
    "name:ukr_x_preferred":[
        "\u0411\u0440\u043e\u0442\u043e"
    ],
    "name:uzb_x_preferred":[
        "Broto"
    ],
    "name:vie_x_preferred":[
        "Broto"
    ],
    "name:war_x_preferred":[
        "Broto"
    ],
    "name:zho_x_preferred":[
        "\u5e03\u7f57\u6258"
    ],
    "wof:name":"Broto",
    "wof:placetype":"locality"
},
  "geometry": {"coordinates":[111.41,-8.021],"type":"Point"}
}