{
  "type": "Feature",
  "properties": {
    "gn:admin1_code":"30",
    "gn:asciiname":"Wesel",
    "gn:country_code":"ID",
    "gn:dem":7,
    "gn:feature_class":"P",
    "gn:feature_code":"PPL",
    "gn:name":"Wesel",
    "gn:population":0,
    "gn:timezone":"Asia/Jakarta",
    "iso:country":"ID",
    "name:ind_x_preferred":[
        "Wesel"
    ],
    "wof:name":"Wesel",
    "wof:placetype":"locality"
},
  "geometry": {"coordinates":[107.80249999999999,-6.24333],"type":"Point"}
}