{
  "type": "Feature",
  "properties": {
    "gn:admin1_code":"30",
    "gn:asciiname":"Wesel",
    "gn:country_code":"ID",
    "gn:dem":7,
    "gn:feature_class":"P",
    "gn:feature_code":"PPL",
    "gn:name":"Wesel",
    "gn:population":0,
    "gn:timezone":"Asia/Jakarta",
    "iso:country":"ID",
    "name:ara_x_preferred":[
        "\u0641\u064a\u0632\u0644"
    ],
    "name:azb_x_preferred":[
        "\u0648\u0632\u0644"
    ],
    "name:bel_x_preferred":[
        "\u0412\u0435\u0437\u0435\u043b\u044c"
    ],
    "name:bul_x_preferred":[
        "\u0412\u0435\u0437\u0435\u043b"
    ],
    "name:cat_x_preferred":[
        "Wesel"
    ],
    "name:ceb_x_preferred":[
        "Wesel"
    ],
    "name:ces_x_preferred":[
        "Wesel"
    ],
    "name:dan_x_preferred":[
        "Wesel"
    ],
    "name:deu_x_preferred":[
        "Wesel"
    ],
    "name:epo_x_preferred":[
        "Wesel"
    ],
    "name:est_x_preferred":[
        "Wesel"
    ],
    "name:eus_x_preferred":[
        "Wesel"
    ],
    "name:fas_x_preferred":[
        "\u0648\u0632\u0644"
    ],
    "name:fin_x_preferred":[
        "Wesel"
    ],
    "name:fra_x_preferred":[
        "Wesel"
    ],
    "name:hun_x_preferred":[
        "Wesel"
    ],
    "name:ind_x_preferred":[
        "Wesel"
    ],
    "name:ita_x_preferred":[
        "Wesel"
    ],
    "name:kaz_x_preferred":[
        "\u0412\u0435\u0437\u0435\u043b\u044c"
    ],
    "name:kir_x_preferred":[
        "\u0412\u0435\u0437\u0435\u043b\u044c"
    ],
    "name:lat_x_preferred":[
        "Vesalia"
    ],
    "name:lim_x_preferred":[
        "Wesel"
    ],
    "name:lit_x_preferred":[
        "V\u0117zelis"
    ],
    "name:mkd_x_preferred":[
        "\u0412\u0435\u0437\u0435\u043b"
    ],
    "name:msa_x_preferred":[
        "Wesel"
    ],
    "name:nds_x_preferred":[
        "Wesel"
    ],
    "name:nld_x_preferred":[
        "Wesel"
    ],
    "name:nno_x_preferred":[
        "Wesel"
    ],
    "name:nor_x_preferred":[
        "Wesel"
    ],
    "name:oci_x_preferred":[
        "Wesel"
    ],
    "name:pol_x_preferred":[
        "Wesel"
    ],
    "name:por_x_preferred":[
        "Wesel"
    ],
    "name:ron_x_preferred":[
        "Wesel"
    ],
    "name:rus_x_preferred":[
        "\u0412\u0435\u0437\u0435\u043b\u044c"
    ],
    "name:sco_x_preferred":[
        "Wesel"
    ],
    "name:spa_x_preferred":[
        "Wesel"
    ],
    "name:srp_x_preferred":[
        "\u0412\u0435\u0437\u0435\u043b"
    ],
    "name:swa_x_preferred":[
        "Wesel"
    ],
    "name:swe_x_preferred":[
        "Wesel"
    ],
    "name:tat_x_preferred":[
        "\u0412\u0435\u0437\u0435\u043b"
    ],
    "name:tur_x_preferred":[
        "Wesel"
    ],
    "name:ukr_x_preferred":[
        "\u0412\u0435\u0437\u0435\u043b\u044c"
    ],
    "name:uzb_x_preferred":[
        "Wesel"
    ],
    "name:vol_x_preferred":[
        "Wesel"
    ],
    "name:war_x_preferred":[
        "Wesel"
    ],
    "name:zho_x_preferred":[
        "\u97e6\u745f\u5c14"
    ],
    "wof:lang_x_official":[
        "ind"
    ],
    "wof:lang_x_spoken":[
        "ind",
        "eng"
    ],
    "wof:name":"Wesel",
    "wof:placetype":"locality"
},
  "geometry": {"coordinates":[107.80249999999999,-6.24333],"type":"Point"}
}