{
  "type": "Feature",
  "properties": {
    "gn:admin1_code":"33.0",
    "gn:asciiname":"Kadumadang",
    "gn:country_code":"ID",
    "gn:dem":271,
    "gn:feature_class":"P",
    "gn:feature_code":"PPL",
    "gn:name":"Kadumadang",
    "gn:population":0,
    "gn:timezone":"Asia/Jakarta",
    "iso:country":"ID",
    "name:ind_x_preferred":[
        "Kadumadang"
    ],
    "wof:name":"Kadumadang",
    "wof:placetype":"locality"
},
  "geometry": {"coordinates":[106.0437,-6.334],"type":"Point"}
}