{
  "type": "Feature",
  "properties": {
    "gn:admin1_code":"8.0",
    "gn:asciiname":"Kletek Kidul",
    "gn:country_code":"ID",
    "gn:dem":24,
    "gn:feature_class":"P",
    "gn:feature_code":"PPL",
    "gn:name":"Kletek Kidul",
    "gn:population":0,
    "gn:timezone":"Asia/Jakarta",
    "iso:country":"ID",
    "name:ind_x_preferred":[
        "Kletek Kidul"
    ],
    "wof:name":"Kletek Kidul",
    "wof:placetype":"locality"
},
  "geometry": {"coordinates":[112.94159999999999,-7.7289],"type":"Point"}
}