{
  "type": "Feature",
  "properties": {
    "gn:admin1_code":"26",
    "gn:asciiname":"Pantai Labu Pekan Empat",
    "gn:country_code":"ID",
    "gn:dem":3,
    "gn:feature_class":"P",
    "gn:feature_code":"PPL",
    "gn:name":"Pantai Labu Pekan Empat",
    "gn:population":0,
    "gn:timezone":"Asia/Jakarta",
    "iso:country":"ID",
    "name:ind_x_preferred":[
        "Pantai Labu Pekan Empat"
    ],
    "name:und_x_variant":[
        "Pantailabupekan 4"
    ],
    "wof:lang_x_official":[
        "ind"
    ],
    "wof:lang_x_spoken":[
        "ind",
        "eng"
    ],
    "wof:name":"Pantai Labu Pekan Empat",
    "wof:placetype":"locality"
},
  "geometry": {"coordinates":[98.90170000000001,3.6671],"type":"Point"}
}