{
  "type": "Feature",
  "properties": {
    "gn:admin1_code":"30.0",
    "gn:asciiname":"Cipaingeun Tonggoh",
    "gn:country_code":"ID",
    "gn:dem":407,
    "gn:feature_class":"P",
    "gn:feature_code":"PPL",
    "gn:name":"Cipaingeun Tonggoh",
    "gn:population":0,
    "gn:timezone":"Asia/Jakarta",
    "iso:country":"ID",
    "name:ind_x_preferred":[
        "Cipaingeun Tonggoh"
    ],
    "wof:lang_x_official":[
        "ind"
    ],
    "wof:lang_x_spoken":[
        "ind",
        "eng"
    ],
    "wof:name":"Cipaingeun Tonggoh",
    "wof:placetype":"locality"
},
  "geometry": {"coordinates":[108.0924,-7.4854],"type":"Point"}
}