{
  "type": "Feature",
  "properties": {
    "gn:admin1_code":"7",
    "gn:asciiname":"Kambang Wetan",
    "gn:country_code":"ID",
    "gn:dem":19,
    "gn:feature_class":"P",
    "gn:feature_code":"PPL",
    "gn:name":"Kambang Wetan",
    "gn:population":0,
    "gn:timezone":"Asia/Jakarta",
    "iso:country":"ID",
    "name:ind_x_preferred":[
        "Kambang Wetan"
    ],
    "wof:name":"Kambang Wetan",
    "wof:placetype":"locality"
},
  "geometry": {"coordinates":[109.64825999999999,-6.95607],"type":"Point"}
}