{
  "type": "Feature",
  "properties": {
    "gn:admin1_code":"38",
    "gn:asciiname":"Karamae",
    "gn:country_code":"ID",
    "gn:dem":2,
    "gn:feature_class":"P",
    "gn:feature_code":"PPL",
    "gn:name":"Karamae",
    "gn:population":0,
    "gn:timezone":"Asia/Makassar",
    "iso:country":"ID",
    "name:ind_x_preferred":[
        "Karamae"
    ],
    "wof:name":"Karamae",
    "wof:placetype":"locality"
},
  "geometry": {"coordinates":[120.3032,-4.9994],"type":"Point"}
}