{
  "type": "Feature",
  "properties": {
    "gn:admin1_code":"15.0",
    "gn:asciiname":"Kuningan",
    "gn:country_code":"ID",
    "gn:dem":867,
    "gn:feature_class":"P",
    "gn:feature_code":"PPL",
    "gn:name":"Kuningan",
    "gn:population":0,
    "gn:timezone":"Asia/Jakarta",
    "iso:country":"ID",
    "name:ind_x_preferred":[
        "Kuningan"
    ],
    "wof:name":"Kuningan",
    "wof:placetype":"locality"
},
  "geometry": {"coordinates":[104.11803,-5.01821],"type":"Point"}
}