{
  "type": "Feature",
  "properties": {
    "gn:admin1_code":"30.0",
    "gn:asciiname":"Pongpet",
    "gn:country_code":"ID",
    "gn:dem":194,
    "gn:feature_class":"P",
    "gn:feature_code":"PPL",
    "gn:name":"Pongpet",
    "gn:population":0,
    "gn:timezone":"Asia/Jakarta",
    "iso:country":"ID",
    "name:ind_x_preferred":[
        "Pongpet"
    ],
    "wof:name":"Pongpet",
    "wof:placetype":"locality"
},
  "geometry": {"coordinates":[108.1651,-7.7016],"type":"Point"}
}