{
  "type": "Feature",
  "properties": {
    "gn:admin1_code":"18.0",
    "gn:asciiname":"Golopurak",
    "gn:country_code":"ID",
    "gn:dem":402,
    "gn:feature_class":"P",
    "gn:feature_code":"PPL",
    "gn:name":"Golopurak",
    "gn:population":0,
    "gn:timezone":"Asia/Makassar",
    "iso:country":"ID",
    "name:ind_x_preferred":[
        "Golopurak"
    ],
    "wof:name":"Golopurak",
    "wof:placetype":"locality"
},
  "geometry": {"coordinates":[120.5043,-8.425],"type":"Point"}
}