{
  "type": "Feature",
  "properties": {
    "gn:admin1_code":"18.0",
    "gn:asciiname":"Larawatu",
    "gn:country_code":"ID",
    "gn:dem":118,
    "gn:feature_class":"P",
    "gn:feature_code":"PPL",
    "gn:name":"Larawatu",
    "gn:population":0,
    "gn:timezone":"Asia/Makassar",
    "iso:country":"ID",
    "name:ind_x_preferred":[
        "Larawatu"
    ],
    "wof:name":"Larawatu",
    "wof:placetype":"locality"
},
  "geometry": {"coordinates":[119.37039,-9.75401],"type":"Point"}
}