{
  "type": "Feature",
  "properties": {
    "gn:admin1_code":"08",
    "gn:asciiname":"Gemurung Kidul",
    "gn:cc2":"ID",
    "gn:country_code":"ID",
    "gn:dem":7,
    "gn:feature_class":"P",
    "gn:feature_code":"PPL",
    "gn:name":"Gemurung Kidul",
    "gn:population":0,
    "gn:timezone":"Asia/Jakarta",
    "iso:country":"ID",
    "name:ind_x_preferred":[
        "Gemurung Kidul"
    ],
    "name:und_x_variant":[
        "Gemurung"
    ],
    "wof:name":"Gemurung Kidul",
    "wof:placetype":"locality"
},
  "geometry": {"coordinates":[112.75139,-7.40056],"type":"Point"}
}