{
  "type": "Feature",
  "properties": {
    "gn:admin1_code":"33.0",
    "gn:asciiname":"Tenjolahang Timur",
    "gn:country_code":"ID",
    "gn:dem":46,
    "gn:feature_class":"P",
    "gn:feature_code":"PPLA4",
    "gn:name":"Tenjolahang Timur",
    "gn:population":0,
    "gn:timezone":"Asia/Jakarta",
    "iso:country":"ID",
    "name:ind_x_preferred":[
        "Tenjolahang Timur"
    ],
    "name:und_x_variant":[
        "Tendjolhang",
        "Tenjolahang"
    ],
    "wof:lang_x_official":[
        "ind"
    ],
    "wof:lang_x_spoken":[
        "ind",
        "eng"
    ],
    "wof:name":"Tenjolahang Timur",
    "wof:placetype":"locality"
},
  "geometry": {"coordinates":[105.8561,-6.3557],"type":"Point"}
}