{
  "type": "Feature",
  "properties": {
    "gn:admin1_code":"18.0",
    "gn:asciiname":"Mamfetin",
    "gn:country_code":"ID",
    "gn:dem":257,
    "gn:feature_class":"P",
    "gn:feature_code":"PPL",
    "gn:name":"Mamfetin",
    "gn:population":0,
    "gn:timezone":"Asia/Makassar",
    "iso:country":"ID",
    "name:ind_x_preferred":[
        "Mamfetin"
    ],
    "wof:name":"Mamfetin",
    "wof:placetype":"locality"
},
  "geometry": {"coordinates":[124.3964,-9.9611],"type":"Point"}
}