{
  "type": "Feature",
  "properties": {
    "gn:admin1_code":"30.0",
    "gn:asciiname":"Babakanrandu",
    "gn:country_code":"ID",
    "gn:dem":782,
    "gn:feature_class":"P",
    "gn:feature_code":"PPL",
    "gn:name":"Babakanrandu",
    "gn:population":0,
    "gn:timezone":"Asia/Jakarta",
    "iso:country":"ID",
    "name:ind_x_preferred":[
        "Babakanrandu"
    ],
    "wof:name":"Babakanrandu",
    "wof:placetype":"locality"
},
  "geometry": {"coordinates":[107.75749999999999,-7.5212],"type":"Point"}
}