{
  "type": "Feature",
  "properties": {
    "gn:admin1_code":"7",
    "gn:asciiname":"Pengungsen",
    "gn:country_code":"ID",
    "gn:dem":711,
    "gn:feature_class":"P",
    "gn:feature_code":"PPL",
    "gn:name":"Pengungsen",
    "gn:population":0,
    "gn:timezone":"Asia/Jakarta",
    "iso:country":"ID",
    "name:ind_x_preferred":[
        "Pengungsen"
    ],
    "wof:name":"Pengungsen",
    "wof:placetype":"locality"
},
  "geometry": {"coordinates":[109.44167,-7.19833],"type":"Point"}
}