{
  "type": "Feature",
  "properties": {
    "gn:admin1_code":"18.0",
    "gn:asciiname":"Tablolong Selatan",
    "gn:country_code":"ID",
    "gn:dem":7,
    "gn:feature_class":"P",
    "gn:feature_code":"PPL",
    "gn:name":"Tablolong Selatan",
    "gn:population":0,
    "gn:timezone":"Asia/Makassar",
    "iso:country":"ID",
    "name:ind_x_preferred":[
        "Tablolong Selatan"
    ],
    "name:und_x_variant":[
        "Tablolong",
        "Toblolong"
    ],
    "wof:name":"Tablolong Selatan",
    "wof:placetype":"locality"
},
  "geometry": {"coordinates":[123.47799999999999,-10.3154],"type":"Point"}
}