{
  "type": "Feature",
  "properties": {
    "gn:admin1_code":"07",
    "gn:asciiname":"Danguran",
    "gn:country_code":"ID",
    "gn:dem":209,
    "gn:feature_class":"P",
    "gn:feature_code":"PPL",
    "gn:name":"Danguran",
    "gn:population":0,
    "gn:timezone":"Asia/Jakarta",
    "iso:country":"ID",
    "wof:name":"Danguran",
    "wof:placetype":"locality"
},
  "geometry": {"coordinates":[110.61,-7.66806],"type":"Point"}
}