{
  "type": "Feature",
  "properties": {
    "gn:admin1_code":"30",
    "gn:asciiname":"Pisangsambo",
    "gn:country_code":"ID",
    "gn:dem":7,
    "gn:feature_class":"P",
    "gn:feature_code":"PPL",
    "gn:name":"Pisangsambo",
    "gn:population":0,
    "gn:timezone":"Asia/Jakarta",
    "iso:country":"ID",
    "name:ind_x_preferred":[
        "Pisangsambo"
    ],
    "name:und_x_variant":[
        "Pisangsambo 1",
        "Pisangsambo Satu"
    ],
    "wof:lang_x_official":[
        "ind"
    ],
    "wof:lang_x_spoken":[
        "ind",
        "eng"
    ],
    "wof:name":"Pisangsambo",
    "wof:placetype":"locality"
},
  "geometry": {"coordinates":[107.23222,-6.10472],"type":"Point"}
}