{
  "type": "Feature",
  "properties": {
    "gn:country":"ID",
    "gn:fcode":"PPL",
    "gn:pop":0,
    "iso:country":"ID",
    "name:deu_x_preferred":[
        "Benua"
    ],
    "name:ukr_x_preferred":[
        "Benua"
    ],
    "name:unk_x_variant":[
        "Benoea"
    ],
    "qs:name":"Benua",
    "qs:name_adm0":"Indonesia",
    "qs:name_adm1":"Sulawesi Tenggara",
    "qs:photos_9k":1,
    "qs:photos_9r":1,
    "qs:photos_all":1,
    "qs:photos_sr":0,
    "qs:placetype":"Town",
    "qs:pop_sr":"0",
    "wd:wordcount":13,
    "wof:lang_x_official":[
        "ind"
    ],
    "wof:lang_x_spoken":[
        "ind",
        "eng"
    ],
    "wof:name":"Benua",
    "wof:placetype":"locality",
    "wof:population":0
},
  "geometry": {"coordinates":[122.23333,-3.95],"type":"Point"}
}