{
  "type": "Feature",
  "properties": {
    "gn:admin1_code":"8.0",
    "gn:asciiname":"Plosokerep",
    "gn:country_code":"ID",
    "gn:dem":81,
    "gn:feature_class":"P",
    "gn:feature_code":"PPL",
    "gn:name":"Plosokerep",
    "gn:population":0,
    "gn:timezone":"Asia/Jakarta",
    "iso:country":"ID",
    "name:ind_x_preferred":[
        "Plosokerep"
    ],
    "wof:name":"Plosokerep",
    "wof:placetype":"locality"
},
  "geometry": {"coordinates":[111.9739,-7.8661],"type":"Point"}
}