{
  "type": "Feature",
  "properties": {
    "gn:admin1_code":"7.0",
    "gn:asciiname":"Bigaran Satu",
    "gn:country_code":"ID",
    "gn:dem":251,
    "gn:feature_class":"P",
    "gn:feature_code":"PPL",
    "gn:name":"Bigaran Satu",
    "gn:population":0,
    "gn:timezone":"Asia/Jakarta",
    "iso:country":"ID",
    "wof:name":"Bigaran Satu",
    "wof:placetype":"locality"
},
  "geometry": {"coordinates":[110.24278,-7.64639],"type":"Point"}
}