{
  "type": "Feature",
  "properties": {
    "gn:admin1_code":"17",
    "gn:asciiname":"Mantung",
    "gn:country_code":"ID",
    "gn:dem":81,
    "gn:feature_class":"P",
    "gn:feature_code":"PPL",
    "gn:name":"Mantung",
    "gn:population":0,
    "gn:timezone":"Asia/Makassar",
    "iso:country":"ID",
    "name:ind_x_preferred":[
        "Mantung"
    ],
    "wof:name":"Mantung",
    "wof:placetype":"locality"
},
  "geometry": {"coordinates":[116.23860000000001,-8.7512],"type":"Point"}
}