{
  "type": "Feature",
  "properties": {
    "gn:admin1_code":"33",
    "gn:asciiname":"Temugiring",
    "gn:country_code":"ID",
    "gn:dem":43,
    "gn:feature_class":"P",
    "gn:feature_code":"PPL",
    "gn:name":"Temugiring",
    "gn:population":0,
    "gn:timezone":"Asia/Jakarta",
    "iso:country":"ID",
    "name:ind_x_preferred":[
        "Temugiring"
    ],
    "wof:name":"Temugiring",
    "wof:placetype":"locality"
},
  "geometry": {"coordinates":[105.9983,-6.0358],"type":"Point"}
}