{
  "type": "Feature",
  "properties": {
    "gn:admin1_code":"18.0",
    "gn:asciiname":"Belek",
    "gn:country_code":"ID",
    "gn:dem":861,
    "gn:feature_class":"P",
    "gn:feature_code":"PPL",
    "gn:name":"Belek",
    "gn:population":0,
    "gn:timezone":"Asia/Makassar",
    "iso:country":"ID",
    "name:ind_x_preferred":[
        "Belek"
    ],
    "wof:name":"Belek",
    "wof:placetype":"locality"
},
  "geometry": {"coordinates":[123.45310000000001,-8.455],"type":"Point"}
}