{
  "type": "Feature",
  "properties": {
    "gn:admin1_code":"18.0",
    "gn:asciiname":"Belek",
    "gn:country_code":"ID",
    "gn:dem":861,
    "gn:feature_class":"P",
    "gn:feature_code":"PPL",
    "gn:name":"Belek",
    "gn:population":0,
    "gn:timezone":"Asia/Makassar",
    "iso:country":"ID",
    "name:bak_x_preferred":[
        "\u0411\u0435\u043b\u0435\u043a"
    ],
    "name:ceb_x_preferred":[
        "Belek"
    ],
    "name:deu_x_preferred":[
        "Belek"
    ],
    "name:epo_x_preferred":[
        "Belek"
    ],
    "name:est_x_preferred":[
        "Belek"
    ],
    "name:fas_x_preferred":[
        "\u0628\u0644\u0686"
    ],
    "name:fin_x_preferred":[
        "Belek"
    ],
    "name:fra_x_preferred":[
        "Belek"
    ],
    "name:hun_x_preferred":[
        "Belek"
    ],
    "name:hye_x_preferred":[
        "\u0532\u0565\u056c\u0565\u0584"
    ],
    "name:ind_x_preferred":[
        "Belek"
    ],
    "name:kaz_x_preferred":[
        "\u0411\u0435\u043b\u0435\u043a"
    ],
    "name:mkd_x_preferred":[
        "\u0411\u0435\u043b\u0435\u043a"
    ],
    "name:nld_x_preferred":[
        "Belek"
    ],
    "name:pol_x_preferred":[
        "Belek"
    ],
    "name:ron_x_preferred":[
        "Belek"
    ],
    "name:rus_x_preferred":[
        "\u0411\u0435\u043b\u0435\u043a"
    ],
    "name:tur_x_preferred":[
        "Belek"
    ],
    "name:ukr_x_preferred":[
        "\u0411\u0435\u043b\u0435\u043a"
    ],
    "name:urd_x_preferred":[
        "\u0628\u06cc\u0644\u06cc\u0686"
    ],
    "name:vie_x_preferred":[
        "Belek"
    ],
    "wof:name":"Belek",
    "wof:placetype":"locality"
},
  "geometry": {"coordinates":[123.45310000000001,-8.455],"type":"Point"}
}