{
  "type": "Feature",
  "properties": {
    "gn:admin1_code":"30",
    "gn:asciiname":"Katulampa",
    "gn:country_code":"ID",
    "gn:dem":849,
    "gn:feature_class":"P",
    "gn:feature_code":"PPL",
    "gn:name":"Katulampa",
    "gn:population":0,
    "gn:timezone":"Asia/Jakarta",
    "iso:country":"ID",
    "wof:name":"Katulampa",
    "wof:placetype":"locality"
},
  "geometry": {"coordinates":[107.73778,-7.09972],"type":"Point"}
}