{
  "type": "Feature",
  "properties": {
    "gn:admin1_code":"38",
    "gn:asciiname":"Lamoare",
    "gn:country_code":"ID",
    "gn:dem":438,
    "gn:feature_class":"P",
    "gn:feature_code":"PPL",
    "gn:name":"Lamoare",
    "gn:population":0,
    "gn:timezone":"Asia/Makassar",
    "iso:country":"ID",
    "name:ind_x_preferred":[
        "Lamoare"
    ],
    "wof:name":"Lamoare",
    "wof:placetype":"locality"
},
  "geometry": {"coordinates":[121.366,-2.5285],"type":"Point"}
}