{
  "type": "Feature",
  "properties": {
    "gn:admin1_code":"2.0",
    "gn:asciiname":"Banjar Samuh",
    "gn:country_code":"ID",
    "gn:dem":17,
    "gn:feature_class":"P",
    "gn:feature_code":"PPL",
    "gn:name":"Banjar Samuh",
    "gn:population":0,
    "gn:timezone":"Asia/Makassar",
    "iso:country":"ID",
    "name:ind_x_preferred":[
        "Banjar Samuh"
    ],
    "wof:name":"Banjar Samuh",
    "wof:placetype":"locality"
},
  "geometry": {"coordinates":[115.5771,-8.5061],"type":"Point"}
}