{
  "type": "Feature",
  "properties": {
    "gn:admin1_code":"33",
    "gn:asciiname":"Pasirjengkol",
    "gn:country_code":"ID",
    "gn:dem":38,
    "gn:feature_class":"P",
    "gn:feature_code":"PPL",
    "gn:name":"Pasirjengkol",
    "gn:population":0,
    "gn:timezone":"Asia/Jakarta",
    "iso:country":"ID",
    "name:ind_x_preferred":[
        "Pasirjengkol"
    ],
    "name:und_x_variant":[
        "Paisrdjengkol Dua",
        "Paisrdjengkol 2",
        "Paisrjengkol Dua"
    ],
    "wof:name":"Pasirjengkol",
    "wof:placetype":"locality"
},
  "geometry": {"coordinates":[106.2624,-6.3301],"type":"Point"}
}