{
  "type": "Feature",
  "properties": {
    "gn:admin1_code":"0.0",
    "gn:asciiname":"Tanjung Bundang",
    "gn:cc2":"ID",
    "gn:country_code":"ID",
    "gn:dem":92,
    "gn:feature_class":"P",
    "gn:feature_code":"PPL",
    "gn:name":"Tanjung Bundang",
    "gn:population":0,
    "gn:timezone":"Asia/Pontianak",
    "iso:country":"ID",
    "name:und_x_variant":[
        "Tandjoeng Boendang",
        "Tandjung Bundang",
        "Tanjung Bundang"
    ],
    "wof:name":"Tanjung Bundang",
    "wof:placetype":"locality"
},
  "geometry": {"coordinates":[114.63333,-0.31667],"type":"Point"}
}