{
  "type": "Feature",
  "properties": {
    "gn:admin1_code":"28.0",
    "gn:asciiname":"Kataloka",
    "gn:cc2":"ID",
    "gn:country_code":"ID",
    "gn:dem":16,
    "gn:feature_class":"P",
    "gn:feature_code":"PPL",
    "gn:name":"Kataloka",
    "gn:population":0,
    "gn:timezone":"Asia/Jayapura",
    "iso:country":"ID",
    "name:und_x_variant":[
        "Katloka"
    ],
    "wof:name":"Kataloka",
    "wof:placetype":"locality"
},
  "geometry": {"coordinates":[131.37717000000001,-3.98927],"type":"Point"}
}