{
  "type": "Feature",
  "properties": {
    "gn:admin1_code":"7",
    "gn:asciiname":"Pliring",
    "gn:country_code":"ID",
    "gn:dem":362,
    "gn:feature_class":"P",
    "gn:feature_code":"PPL",
    "gn:name":"Pliring",
    "gn:population":0,
    "gn:timezone":"Asia/Jakarta",
    "iso:country":"ID",
    "name:ind_x_preferred":[
        "Pliring"
    ],
    "wof:name":"Pliring",
    "wof:placetype":"locality"
},
  "geometry": {"coordinates":[110.92189999999999,-6.6914],"type":"Point"}
}