{
  "type": "Feature",
  "properties": {
    "gn:admin1_code":"30.0",
    "gn:asciiname":"Salamnunggal",
    "gn:country_code":"ID",
    "gn:dem":711,
    "gn:feature_class":"P",
    "gn:feature_code":"PPLA4",
    "gn:name":"Salamnunggal",
    "gn:population":0,
    "gn:timezone":"Asia/Jakarta",
    "iso:country":"ID",
    "name:ind_x_preferred":[
        "Salamnunggal"
    ],
    "name:und_x_variant":[
        "Salamnoenggal"
    ],
    "wof:lang_x_official":[
        "ind"
    ],
    "wof:lang_x_spoken":[
        "ind",
        "eng"
    ],
    "wof:name":"Salamnunggal",
    "wof:placetype":"locality"
},
  "geometry": {"coordinates":[107.898,-7.1064],"type":"Point"}
}