{
  "type": "Feature",
  "properties": {
    "gn:admin1_code":"7.0",
    "gn:asciiname":"Jatiteken",
    "gn:country_code":"ID",
    "gn:dem":693,
    "gn:feature_class":"P",
    "gn:feature_code":"PPL",
    "gn:name":"Jatiteken",
    "gn:population":0,
    "gn:timezone":"Asia/Jakarta",
    "iso:country":"ID",
    "name:ind_x_preferred":[
        "Jatiteken"
    ],
    "wof:name":"Jatiteken",
    "wof:placetype":"locality"
},
  "geometry": {"coordinates":[109.06556,-7.21222],"type":"Point"}
}