{
  "type": "Feature",
  "properties": {
    "gn:admin1_code":"30",
    "gn:asciiname":"Cinengkelan",
    "gn:country_code":"ID",
    "gn:dem":1219,
    "gn:feature_class":"P",
    "gn:feature_code":"PPL",
    "gn:name":"Cinengkelan",
    "gn:population":0,
    "gn:timezone":"Asia/Jakarta",
    "iso:country":"ID",
    "wof:name":"Cinengkelan",
    "wof:placetype":"locality"
},
  "geometry": {"coordinates":[107.69750000000001,-7.15306],"type":"Point"}
}