{
  "type": "Feature",
  "properties": {
    "gn:admin1_code":"36.0",
    "gn:asciiname":"Deomata",
    "gn:country_code":"ID",
    "gn:dem":1950,
    "gn:feature_class":"P",
    "gn:feature_code":"PPL",
    "gn:name":"Deomata",
    "gn:population":0,
    "gn:timezone":"Asia/Jayapura",
    "iso:country":"ID",
    "name:ind_x_preferred":[
        "Deomata"
    ],
    "wof:name":"Deomata",
    "wof:placetype":"locality"
},
  "geometry": {"coordinates":[140.50120000000001,-4.77098],"type":"Point"}
}