{
  "type": "Feature",
  "properties": {
    "gn:admin1_code":"0.0",
    "gn:asciiname":"Renfaan",
    "gn:cc2":"ID",
    "gn:country_code":"ID",
    "gn:dem":260,
    "gn:feature_class":"P",
    "gn:feature_code":"PPL",
    "gn:name":"Renfaan",
    "gn:population":0,
    "gn:timezone":"Asia/Jayapura",
    "iso:country":"ID",
    "name:und_x_variant":[
        "Renfan",
        "Renfaan"
    ],
    "wof:lang_x_official":[
        "ind"
    ],
    "wof:lang_x_spoken":[
        "ind",
        "eng"
    ],
    "wof:name":"Renfaan",
    "wof:placetype":"locality"
},
  "geometry": {"coordinates":[133.13333,-5.38333],"type":"Point"}
}