{
  "type": "Feature",
  "properties": {
    "gn:admin1_code":"30.0",
    "gn:asciiname":"Babakaninpres",
    "gn:country_code":"ID",
    "gn:dem":61,
    "gn:feature_class":"P",
    "gn:feature_code":"PPL",
    "gn:name":"Babakaninpres",
    "gn:population":0,
    "gn:timezone":"Asia/Jakarta",
    "iso:country":"ID",
    "name:ind_x_preferred":[
        "Babakaninpres"
    ],
    "wof:name":"Babakaninpres",
    "wof:placetype":"locality"
},
  "geometry": {"coordinates":[106.8184,-7.4112],"type":"Point"}
}