{
  "type": "Feature",
  "properties": {
    "gn:admin1_code":"30.0",
    "gn:asciiname":"Gunungbuleud",
    "gn:country_code":"ID",
    "gn:dem":983,
    "gn:feature_class":"P",
    "gn:feature_code":"PPL",
    "gn:name":"Gunungbuleud",
    "gn:population":0,
    "gn:timezone":"Asia/Jakarta",
    "iso:country":"ID",
    "name:ind_x_preferred":[
        "Gunungbuleud"
    ],
    "name:und_x_variant":[
        "Goenoengboeleud"
    ],
    "wof:lang_x_official":[
        "ind"
    ],
    "wof:lang_x_spoken":[
        "ind",
        "eng"
    ],
    "wof:name":"Gunungbuleud",
    "wof:placetype":"locality"
},
  "geometry": {"coordinates":[107.0454,-7.1066],"type":"Point"}
}