{
  "type": "Feature",
  "properties": {
    "gn:admin1_code":"10.0",
    "gn:asciiname":"Tambakromo",
    "gn:country_code":"ID",
    "gn:dem":502,
    "gn:feature_class":"P",
    "gn:feature_code":"PPL",
    "gn:name":"Tambakromo",
    "gn:population":0,
    "gn:timezone":"Asia/Jakarta",
    "iso:country":"ID",
    "wof:name":"Tambakromo",
    "wof:placetype":"locality"
},
  "geometry": {"coordinates":[110.75667,-7.94417],"type":"Point"}
}