{
  "type": "Feature",
  "properties": {
    "gn:admin1_code":"38.0",
    "gn:asciiname":"Batangpalli",
    "gn:country_code":"ID",
    "gn:dem":1029,
    "gn:feature_class":"P",
    "gn:feature_code":"PPL",
    "gn:name":"Batangpalli",
    "gn:population":0,
    "gn:timezone":"Asia/Makassar",
    "iso:country":"ID",
    "name:ind_x_preferred":[
        "Batangpalli"
    ],
    "wof:name":"Batangpalli",
    "wof:placetype":"locality"
},
  "geometry": {"coordinates":[119.9812,-2.875],"type":"Point"}
}