{
  "type": "Feature",
  "properties": {
    "gn:admin1_code":"18.0",
    "gn:asciiname":"Tammabakul",
    "gn:country_code":"ID",
    "gn:dem":464,
    "gn:feature_class":"P",
    "gn:feature_code":"PPL",
    "gn:name":"Tammabakul",
    "gn:population":0,
    "gn:timezone":"Asia/Makassar",
    "iso:country":"ID",
    "name:ind_x_preferred":[
        "Tammabakul"
    ],
    "wof:name":"Tammabakul",
    "wof:placetype":"locality"
},
  "geometry": {"coordinates":[119.5789,-9.5768],"type":"Point"}
}