{
  "type": "Feature",
  "properties": {
    "gn:admin1_code":"22",
    "gn:asciiname":"Panganjaya",
    "gn:country_code":"ID",
    "gn:dem":18,
    "gn:feature_class":"P",
    "gn:feature_code":"PPL",
    "gn:name":"Panganjaya",
    "gn:population":0,
    "gn:timezone":"Asia/Makassar",
    "iso:country":"ID",
    "name:ind_x_preferred":[
        "Panganjaya"
    ],
    "wof:name":"Panganjaya",
    "wof:placetype":"locality"
},
  "geometry": {"coordinates":[122.5797,-4.3852],"type":"Point"}
}