{
  "type": "Feature",
  "properties": {
    "gn:admin1_code":"31",
    "gn:asciiname":"Bunaken",
    "gn:country_code":"ID",
    "gn:dem":7,
    "gn:feature_class":"P",
    "gn:feature_code":"PPL",
    "gn:name":"Bunaken",
    "gn:population":0,
    "gn:timezone":"Asia/Makassar",
    "iso:country":"ID",
    "name:ara_x_preferred":[
        "\u0628\u0648\u0646\u0627\u0643\u0646"
    ],
    "name:aze_x_preferred":[
        "Bunaken"
    ],
    "name:bel_x_preferred":[
        "\u0411\u0443\u043d\u0430\u043a\u0435\u043d"
    ],
    "name:ceb_x_preferred":[
        "Pulau Bunaken"
    ],
    "name:deu_x_preferred":[
        "Bunaken"
    ],
    "name:fin_x_preferred":[
        "Bunaken"
    ],
    "name:ind_x_preferred":[
        "Pulau Bunaken"
    ],
    "name:jav_x_preferred":[
        "Pulo Bunaken"
    ],
    "name:jpn_x_preferred":[
        "\u30d6\u30ca\u30b1\u30f3\u5cf6"
    ],
    "name:nld_x_preferred":[
        "Bunaken"
    ],
    "name:pfl_x_preferred":[
        "Bunaken"
    ],
    "name:rus_x_preferred":[
        "\u0411\u0443\u043d\u0430\u043a\u0435\u043d"
    ],
    "name:sun_x_preferred":[
        "Pulo Bunaken"
    ],
    "name:swe_x_preferred":[
        "Bunaken"
    ],
    "name:zho_x_preferred":[
        "\u5e03\u7d0d\u80af\u5cf6"
    ],
    "wof:lang_x_official":[
        "ind"
    ],
    "wof:lang_x_spoken":[
        "ind",
        "eng"
    ],
    "wof:name":"Bunaken",
    "wof:placetype":"locality"
},
  "geometry": {"coordinates":[124.77778000000001,1.59806],"type":"Point"}
}