{
  "type": "Feature",
  "properties": {
    "gn:admin1_code":"30.0",
    "gn:asciiname":"Cienggang",
    "gn:country_code":"ID",
    "gn:dem":1139,
    "gn:feature_class":"P",
    "gn:feature_code":"PPL",
    "gn:name":"Cienggang",
    "gn:population":0,
    "gn:timezone":"Asia/Jakarta",
    "iso:country":"ID",
    "name:ind_x_preferred":[
        "Cienggang"
    ],
    "wof:name":"Cienggang",
    "wof:placetype":"locality"
},
  "geometry": {"coordinates":[107.7868,-7.2637],"type":"Point"}
}