{
  "type": "Feature",
  "properties": {
    "gn:admin1_code":"8",
    "gn:asciiname":"Bere Sawah",
    "gn:country_code":"ID",
    "gn:dem":438,
    "gn:feature_class":"P",
    "gn:feature_code":"PPL",
    "gn:name":"Bere Sawah",
    "gn:population":0,
    "gn:timezone":"Asia/Jakarta",
    "iso:country":"ID",
    "name:ind_x_preferred":[
        "Bere Sawah"
    ],
    "wof:name":"Bere Sawah",
    "wof:placetype":"locality"
},
  "geometry": {"coordinates":[113.7406,-7.8251],"type":"Point"}
}