{
  "type": "Feature",
  "properties": {
    "gn:admin1_code":"41.0",
    "gn:asciiname":"Minanga",
    "gn:country_code":"ID",
    "gn:dem":1332,
    "gn:feature_class":"P",
    "gn:feature_code":"PPL",
    "gn:name":"Minanga",
    "gn:population":0,
    "gn:timezone":"Asia/Makassar",
    "iso:country":"ID",
    "name:ind_x_preferred":[
        "Minanga"
    ],
    "wof:name":"Minanga",
    "wof:placetype":"locality"
},
  "geometry": {"coordinates":[119.43000000000001,-2.9994],"type":"Point"}
}