{
  "type": "Feature",
  "properties": {
    "gn:admin1_code":"33",
    "gn:asciiname":"Cidadaru",
    "gn:country_code":"ID",
    "gn:dem":121,
    "gn:feature_class":"P",
    "gn:feature_code":"PPL",
    "gn:name":"Cidadaru",
    "gn:population":0,
    "gn:timezone":"Asia/Jakarta",
    "iso:country":"ID",
    "name:ind_x_preferred":[
        "Cidadaru"
    ],
    "wof:name":"Cidadaru",
    "wof:placetype":"locality"
},
  "geometry": {"coordinates":[106.1371,-6.3581],"type":"Point"}
}