{
  "type": "Feature",
  "properties": {
    "gn:admin1_code":"7.0",
    "gn:asciiname":"Jiken",
    "gn:country_code":"ID",
    "gn:dem":122,
    "gn:feature_class":"P",
    "gn:feature_code":"PPL",
    "gn:name":"Jiken",
    "gn:population":0,
    "gn:timezone":"Asia/Jakarta",
    "iso:country":"ID",
    "name:ind_x_preferred":[
        "Jiken"
    ],
    "name:und_x_variant":[
        "Djiken"
    ],
    "wof:name":"Jiken",
    "wof:placetype":"locality"
},
  "geometry": {"coordinates":[111.5082,-7.0046],"type":"Point"}
}