{
  "type": "Feature",
  "properties": {
    "gn:admin1_code":"29.0",
    "gn:asciiname":"Karebreu",
    "gn:country_code":"ID",
    "gn:dem":38,
    "gn:feature_class":"P",
    "gn:feature_code":"PPL",
    "gn:name":"Karebreu",
    "gn:population":0,
    "gn:timezone":"Asia/Jayapura",
    "iso:country":"ID",
    "name:ind_x_preferred":[
        "Karebreu"
    ],
    "name:und_x_variant":[
        "Kar\u0115breoe"
    ],
    "wof:name":"Karebreu",
    "wof:placetype":"locality"
},
  "geometry": {"coordinates":[124.72251,-1.89914],"type":"Point"}
}