{
  "type": "Feature",
  "properties": {
    "gn:admin1_code":"7.0",
    "gn:asciiname":"Baran",
    "gn:country_code":"ID",
    "gn:dem":102,
    "gn:feature_class":"P",
    "gn:feature_code":"PPL",
    "gn:name":"Baran",
    "gn:population":0,
    "gn:timezone":"Asia/Jakarta",
    "iso:country":"ID",
    "name:deu_x_preferred":[
        "Baran"
    ],
    "name:fra_x_preferred":[
        "Baran"
    ],
    "name:ita_x_preferred":[
        "Baran"
    ],
    "name:nld_x_preferred":[
        "Baran"
    ],
    "name:pol_x_preferred":[
        "Baran"
    ],
    "name:rus_x_preferred":[
        "\u0411\u0430\u0440\u0430\u043d"
    ],
    "name:slk_x_preferred":[
        "Baran"
    ],
    "name:swe_x_preferred":[
        "Baran"
    ],
    "name:ukr_x_preferred":[
        "\u0411\u0430\u0440\u0430\u043d"
    ],
    "wof:lang_x_official":[
        "ind"
    ],
    "wof:lang_x_spoken":[
        "ind",
        "eng"
    ],
    "wof:name":"Baran",
    "wof:placetype":"locality"
},
  "geometry": {"coordinates":[110.85278,-7.67889],"type":"Point"}
}