{
  "type": "Feature",
  "properties": {
    "gn:admin1_code":"30.0",
    "gn:asciiname":"Cipanas",
    "gn:country_code":"ID",
    "gn:dem":331,
    "gn:feature_class":"P",
    "gn:feature_code":"PPL",
    "gn:name":"Cipanas",
    "gn:population":0,
    "gn:timezone":"Asia/Jakarta",
    "iso:country":"ID",
    "name:ara_x_preferred":[
        "\u0633\u064a\u0628\u0627\u0646\u0627\u0633"
    ],
    "name:ind_x_preferred":[
        "Cipanas"
    ],
    "name:und_x_variant":[
        "Tjipanas"
    ],
    "wof:name":"Cipanas",
    "wof:placetype":"locality"
},
  "geometry": {"coordinates":[107.99917000000001,-6.73472],"type":"Point"}
}