{
  "type": "Feature",
  "properties": {
    "gn:admin1_code":"18",
    "gn:asciiname":"Kalembumanu",
    "gn:country_code":"ID",
    "gn:dem":427,
    "gn:feature_class":"P",
    "gn:feature_code":"PPL",
    "gn:name":"Kalembumanu",
    "gn:population":0,
    "gn:timezone":"Asia/Makassar",
    "iso:country":"ID",
    "name:ind_x_preferred":[
        "Kalembumanu"
    ],
    "wof:name":"Kalembumanu",
    "wof:placetype":"locality"
},
  "geometry": {"coordinates":[119.15479999999999,-9.4952],"type":"Point"}
}