{
  "type": "Feature",
  "properties": {
    "gn:admin1_code":"8.0",
    "gn:asciiname":"Pagergunung",
    "gn:country_code":"ID",
    "gn:dem":357,
    "gn:feature_class":"P",
    "gn:feature_code":"PPL",
    "gn:name":"Pagergunung",
    "gn:population":0,
    "gn:timezone":"Asia/Jakarta",
    "iso:country":"ID",
    "name:ind_x_preferred":[
        "Pagergunung"
    ],
    "wof:name":"Pagergunung",
    "wof:placetype":"locality"
},
  "geometry": {"coordinates":[110.95611,-8.13583],"type":"Point"}
}