{
  "type": "Feature",
  "properties": {
    "gn:admin1_code":"8",
    "gn:asciiname":"Cotek",
    "gn:country_code":"ID",
    "gn:dem":53,
    "gn:feature_class":"P",
    "gn:feature_code":"PPL",
    "gn:name":"Cotek",
    "gn:population":0,
    "gn:timezone":"Asia/Jakarta",
    "iso:country":"ID",
    "name:ind_x_preferred":[
        "Cotek"
    ],
    "wof:name":"Cotek",
    "wof:placetype":"locality"
},
  "geometry": {"coordinates":[114.0561,-7.7303],"type":"Point"}
}