{
  "type": "Feature",
  "properties": {
    "gn:admin1_code":"7",
    "gn:asciiname":"Luwuk",
    "gn:country_code":"ID",
    "gn:dem":15,
    "gn:feature_class":"P",
    "gn:feature_code":"PPL",
    "gn:name":"Luwuk",
    "gn:population":0,
    "gn:timezone":"Asia/Jakarta",
    "iso:country":"ID",
    "name:ind_x_preferred":[
        "Luwuk"
    ],
    "wof:name":"Luwuk",
    "wof:placetype":"locality"
},
  "geometry": {"coordinates":[110.78,-6.9608],"type":"Point"}
}