{
  "type": "Feature",
  "properties": {
    "gn:admin1_code":"7",
    "gn:asciiname":"Luwuk",
    "gn:country_code":"ID",
    "gn:dem":15,
    "gn:feature_class":"P",
    "gn:feature_code":"PPL",
    "gn:name":"Luwuk",
    "gn:population":0,
    "gn:timezone":"Asia/Jakarta",
    "iso:country":"ID",
    "name:ara_x_preferred":[
        "\u0644\u0648 \u0648\u0648\u0643"
    ],
    "name:ceb_x_preferred":[
        "Luwuk"
    ],
    "name:deu_x_preferred":[
        "Luwuk"
    ],
    "name:fas_x_preferred":[
        "\u0644\u0648\u0648\u06a9"
    ],
    "name:fra_x_preferred":[
        "Luwuk"
    ],
    "name:heb_x_preferred":[
        "\u05dc\u05d5\u05d5\u05e7"
    ],
    "name:hun_x_preferred":[
        "Luwuk"
    ],
    "name:ind_x_preferred":[
        "Luwuk"
    ],
    "name:jav_x_preferred":[
        "Luwuk"
    ],
    "name:mlg_x_preferred":[
        "Luwuk"
    ],
    "name:msa_x_preferred":[
        "Luwuk"
    ],
    "name:nld_x_preferred":[
        "Luwuk"
    ],
    "name:pol_x_preferred":[
        "Luwuk"
    ],
    "name:spa_x_preferred":[
        "Luwuk"
    ],
    "name:zho_x_preferred":[
        "\u5362\u6b66\u514b"
    ],
    "wof:lang_x_official":[
        "ind"
    ],
    "wof:lang_x_spoken":[
        "ind",
        "eng"
    ],
    "wof:name":"Luwuk",
    "wof:placetype":"locality"
},
  "geometry": {"coordinates":[110.78,-6.9608],"type":"Point"}
}