{
  "type": "Feature",
  "properties": {
    "gn:admin1_code":"2",
    "gn:asciiname":"Banjar Dajanpeken",
    "gn:country_code":"ID",
    "gn:dem":115,
    "gn:feature_class":"P",
    "gn:feature_code":"PPL",
    "gn:name":"Banjar Dajanpeken",
    "gn:population":0,
    "gn:timezone":"Asia/Makassar",
    "iso:country":"ID",
    "name:ind_x_preferred":[
        "Banjar Dajanpeken"
    ],
    "wof:name":"Banjar Dajanpeken",
    "wof:placetype":"locality"
},
  "geometry": {"coordinates":[115.1639,-8.5622],"type":"Point"}
}