{
  "type": "Feature",
  "properties": {
    "gn:admin1_code":"33",
    "gn:asciiname":"Perumahan Tamankrakatau",
    "gn:country_code":"ID",
    "gn:dem":20,
    "gn:feature_class":"P",
    "gn:feature_code":"PPL",
    "gn:name":"Perumahan Tamankrakatau",
    "gn:population":0,
    "gn:timezone":"Asia/Jakarta",
    "iso:country":"ID",
    "name:ind_x_preferred":[
        "Perumahan Tamankrakatau"
    ],
    "name:und_x_variant":[
        "Perumahan Tamankrkatau"
    ],
    "wof:lang_x_official":[
        "ind"
    ],
    "wof:lang_x_spoken":[
        "ind",
        "eng"
    ],
    "wof:name":"Perumahan Tamankrakatau",
    "wof:placetype":"locality"
},
  "geometry": {"coordinates":[106.07640000000001,-6.0527],"type":"Point"}
}