{
  "type": "Feature",
  "properties": {
    "gn:admin1_code":"0.0",
    "gn:asciiname":"Gelung-kidul",
    "gn:cc2":"ID",
    "gn:country_code":"ID",
    "gn:dem":4,
    "gn:feature_class":"P",
    "gn:feature_code":"PPL",
    "gn:name":"Gelung-kidul",
    "gn:population":0,
    "gn:timezone":"Asia/Jakarta",
    "iso:country":"ID",
    "name:und_x_variant":[
        "Geloeng-kidoel",
        "Gelung-kidul"
    ],
    "wof:name":"Gelung-kidul",
    "wof:placetype":"locality"
},
  "geometry": {"coordinates":[113.98333,-7.65],"type":"Point"}
}