{
  "type": "Feature",
  "properties": {
    "gn:admin1_code":"22.0",
    "gn:asciiname":"Buku",
    "gn:country_code":"ID",
    "gn:dem":46,
    "gn:feature_class":"P",
    "gn:feature_code":"PPL",
    "gn:name":"Buku",
    "gn:population":0,
    "gn:timezone":"Asia/Makassar",
    "iso:country":"ID",
    "name:ceb_x_preferred":[
        "Buku"
    ],
    "name:ind_x_preferred":[
        "Buku"
    ],
    "name:swe_x_preferred":[
        "Buku"
    ],
    "wof:name":"Buku",
    "wof:placetype":"locality"
},
  "geometry": {"coordinates":[122.679,-5.6702],"type":"Point"}
}