{
  "type": "Feature",
  "properties": {
    "gn:admin1_code":"18.0",
    "gn:asciiname":"Seda",
    "gn:country_code":"ID",
    "gn:dem":355,
    "gn:feature_class":"P",
    "gn:feature_code":"PPLA4",
    "gn:name":"Seda",
    "gn:population":0,
    "gn:timezone":"Asia/Makassar",
    "iso:country":"ID",
    "name:ast_x_preferred":[
        "Seda"
    ],
    "name:cat_x_preferred":[
        "Seda"
    ],
    "name:ceb_x_preferred":[
        "Seda"
    ],
    "name:ces_x_preferred":[
        "Seda"
    ],
    "name:deu_x_preferred":[
        "Seda"
    ],
    "name:fra_x_preferred":[
        "Seda"
    ],
    "name:glg_x_preferred":[
        "Seda"
    ],
    "name:kaz_x_preferred":[
        "\u0421\u0435\u0434\u0430"
    ],
    "name:lav_x_preferred":[
        "Seda"
    ],
    "name:lit_x_preferred":[
        "Seda"
    ],
    "name:por_x_preferred":[
        "Seda"
    ],
    "name:rus_x_preferred":[
        "\u0421\u0435\u0434\u0430"
    ],
    "name:spa_x_preferred":[
        "Seda"
    ],
    "name:swe_x_preferred":[
        "Seda"
    ],
    "name:ukr_x_preferred":[
        "\u0421\u0435\u0434\u0430"
    ],
    "name:und_x_variant":[
        "Sedah"
    ],
    "wof:name":"Seda",
    "wof:placetype":"locality"
},
  "geometry": {"coordinates":[123.2157,-10.7694],"type":"Point"}
}