{
  "type": "Feature",
  "properties": {
    "gn:admin1_code":"18.0",
    "gn:asciiname":"Puuponda",
    "gn:country_code":"ID",
    "gn:dem":433,
    "gn:feature_class":"P",
    "gn:feature_code":"PPL",
    "gn:name":"Puuponda",
    "gn:population":0,
    "gn:timezone":"Asia/Makassar",
    "iso:country":"ID",
    "name:ind_x_preferred":[
        "Puuponda"
    ],
    "wof:name":"Puuponda",
    "wof:placetype":"locality"
},
  "geometry": {"coordinates":[119.1527,-9.503],"type":"Point"}
}