{
  "type": "Feature",
  "properties": {
    "gn:admin1_code":"17",
    "gn:asciiname":"Bukittinggi",
    "gn:country_code":"ID",
    "gn:dem":23,
    "gn:feature_class":"P",
    "gn:feature_code":"PPL",
    "gn:name":"Bukittinggi",
    "gn:population":0,
    "gn:timezone":"Asia/Makassar",
    "iso:country":"ID",
    "name:ind_x_preferred":[
        "Bukittinggi"
    ],
    "wof:name":"Bukittinggi",
    "wof:placetype":"locality"
},
  "geometry": {"coordinates":[117.4276,-8.5092],"type":"Point"}
}