{
  "type": "Feature",
  "properties": {
    "gn:admin1_code":"7",
    "gn:asciiname":"Benjaran",
    "gn:country_code":"ID",
    "gn:dem":666,
    "gn:feature_class":"P",
    "gn:feature_code":"PPL",
    "gn:name":"Benjaran",
    "gn:population":0,
    "gn:timezone":"Asia/Jakarta",
    "iso:country":"ID",
    "name:ind_x_preferred":[
        "Benjaran"
    ],
    "wof:name":"Benjaran",
    "wof:placetype":"locality"
},
  "geometry": {"coordinates":[109.20917,-7.13361],"type":"Point"}
}