{
  "type": "Feature",
  "properties": {
    "gn:admin1_code":"34",
    "gn:asciiname":"Dulango",
    "gn:country_code":"ID",
    "gn:dem":24,
    "gn:feature_class":"P",
    "gn:feature_code":"PPL",
    "gn:name":"Dulango",
    "gn:population":0,
    "gn:timezone":"Asia/Makassar",
    "iso:country":"ID",
    "name:ind_x_preferred":[
        "Dulango"
    ],
    "wof:name":"Dulango",
    "wof:placetype":"locality"
},
  "geometry": {"coordinates":[122.8877,0.6319],"type":"Point"}
}