{
  "type": "Feature",
  "properties": {
    "gn:admin1_code":"30.0",
    "gn:asciiname":"Gununggedongan Dua",
    "gn:country_code":"ID",
    "gn:dem":533,
    "gn:feature_class":"P",
    "gn:feature_code":"PPL",
    "gn:name":"Gununggedongan Dua",
    "gn:population":0,
    "gn:timezone":"Asia/Jakarta",
    "iso:country":"ID",
    "name:ind_x_preferred":[
        "Gununggedongan Dua"
    ],
    "wof:name":"Gununggedongan Dua",
    "wof:placetype":"locality"
},
  "geometry": {"coordinates":[106.8359,-7.0378],"type":"Point"}
}