{
  "type": "Feature",
  "properties": {
    "gn:admin1_code":"0.0",
    "gn:asciiname":"Asu",
    "gn:cc2":"ID",
    "gn:country_code":"ID",
    "gn:dem":2,
    "gn:feature_class":"P",
    "gn:feature_code":"PPL",
    "gn:name":"Asu",
    "gn:population":0,
    "gn:timezone":"Asia/Jayapura",
    "iso:country":"ID",
    "name:und_x_variant":[
        "Asoe",
        "Asu"
    ],
    "wof:name":"Asu",
    "wof:placetype":"locality"
},
  "geometry": {"coordinates":[132.81666999999999,-2.75],"type":"Point"}
}