{
  "type": "Feature",
  "properties": {
    "gn:admin1_code":"30",
    "gn:asciiname":"Pamalagan",
    "gn:country_code":"ID",
    "gn:dem":519,
    "gn:feature_class":"P",
    "gn:feature_code":"PPL",
    "gn:name":"Pamalagan",
    "gn:population":0,
    "gn:timezone":"Asia/Jakarta",
    "iso:country":"ID",
    "name:ind_x_preferred":[
        "Pamalagan"
    ],
    "wof:name":"Pamalagan",
    "wof:placetype":"locality"
},
  "geometry": {"coordinates":[106.80777999999999,-6.83111],"type":"Point"}
}