{
  "type": "Feature",
  "properties": {
    "gn:admin1_code":"8.0",
    "gn:asciiname":"Kebon",
    "gn:country_code":"ID",
    "gn:dem":432,
    "gn:feature_class":"P",
    "gn:feature_code":"PPL",
    "gn:name":"Kebon",
    "gn:population":0,
    "gn:timezone":"Asia/Jakarta",
    "iso:country":"ID",
    "name:ind_x_preferred":[
        "Kebon"
    ],
    "wof:name":"Kebon",
    "wof:placetype":"locality"
},
  "geometry": {"coordinates":[111.6533,-8.1357],"type":"Point"}
}