{
  "type": "Feature",
  "properties": {
    "gn:admin1_code":"18.0",
    "gn:asciiname":"Jambapaita",
    "gn:country_code":"ID",
    "gn:dem":31,
    "gn:feature_class":"P",
    "gn:feature_code":"PPL",
    "gn:name":"Jambapaita",
    "gn:population":0,
    "gn:timezone":"Asia/Makassar",
    "iso:country":"ID",
    "name:ind_x_preferred":[
        "Jambapaita"
    ],
    "wof:name":"Jambapaita",
    "wof:placetype":"locality"
},
  "geometry": {"coordinates":[119.70489999999999,-9.4133],"type":"Point"}
}