{
  "type": "Feature",
  "properties": {
    "gn:admin1_code":"18.0",
    "gn:asciiname":"Buni",
    "gn:country_code":"ID",
    "gn:dem":294,
    "gn:feature_class":"P",
    "gn:feature_code":"PPL",
    "gn:name":"Buni",
    "gn:population":0,
    "gn:timezone":"Asia/Makassar",
    "iso:country":"ID",
    "name:ind_x_preferred":[
        "Buni"
    ],
    "wof:name":"Buni",
    "wof:placetype":"locality"
},
  "geometry": {"coordinates":[124.55110000000001,-9.9581],"type":"Point"}
}