{
  "type": "Feature",
  "properties": {
    "gn:admin1_code":"30",
    "gn:asciiname":"Cipetir Girang",
    "gn:country_code":"ID",
    "gn:dem":793,
    "gn:feature_class":"P",
    "gn:feature_code":"PPL",
    "gn:name":"Cipetir Girang",
    "gn:population":0,
    "gn:timezone":"Asia/Jakarta",
    "iso:country":"ID",
    "name:ind_x_preferred":[
        "Cipetir Girang"
    ],
    "wof:name":"Cipetir Girang",
    "wof:placetype":"locality"
},
  "geometry": {"coordinates":[106.91861000000002,-6.86889],"type":"Point"}
}