{
  "type": "Feature",
  "properties": {
    "gn:admin1_code":"8",
    "gn:asciiname":"Purwoharjo",
    "gn:country_code":"ID",
    "gn:dem":463,
    "gn:feature_class":"P",
    "gn:feature_code":"PPL",
    "gn:name":"Purwoharjo",
    "gn:population":0,
    "gn:timezone":"Asia/Jakarta",
    "iso:country":"ID",
    "name:ind_x_preferred":[
        "Purwoharjo"
    ],
    "wof:name":"Purwoharjo",
    "wof:placetype":"locality"
},
  "geometry": {"coordinates":[112.9023,-8.2491],"type":"Point"}
}