{
  "type": "Feature",
  "properties": {
    "gn:admin1_code":"07",
    "gn:asciiname":"Suran",
    "gn:country_code":"ID",
    "gn:dem":294,
    "gn:feature_class":"P",
    "gn:feature_code":"PPL",
    "gn:name":"Suran",
    "gn:population":0,
    "gn:timezone":"Asia/Jakarta",
    "iso:country":"ID",
    "name:ceb_x_preferred":[
        "Suran"
    ],
    "name:fas_x_preferred":[
        "\u0633\u0648\u0631\u0627\u0646"
    ],
    "name:fra_x_preferred":[
        "Suran"
    ],
    "name:kor_x_preferred":[
        "\uc218\ub780"
    ],
    "name:swe_x_preferred":[
        "Suran"
    ],
    "wof:lang_x_official":[
        "ind"
    ],
    "wof:lang_x_spoken":[
        "ind",
        "eng"
    ],
    "wof:name":"Suran",
    "wof:placetype":"locality"
},
  "geometry": {"coordinates":[110.59472,-7.63278],"type":"Point"}
}