{
  "type": "Feature",
  "properties": {
    "gn:admin1_code":"8.0",
    "gn:asciiname":"Bicabi Satu",
    "gn:country_code":"ID",
    "gn:dem":67,
    "gn:feature_class":"P",
    "gn:feature_code":"PPL",
    "gn:name":"Bicabi Satu",
    "gn:population":0,
    "gn:timezone":"Asia/Jakarta",
    "iso:country":"ID",
    "name:ind_x_preferred":[
        "Bicabi Satu"
    ],
    "wof:name":"Bicabi Satu",
    "wof:placetype":"locality"
},
  "geometry": {"coordinates":[113.5415,-7.1195],"type":"Point"}
}