{
  "type": "Feature",
  "properties": {
    "gn:admin1_code":"26",
    "gn:asciiname":"Pasar Serapuh",
    "gn:country_code":"ID",
    "gn:dem":5,
    "gn:feature_class":"P",
    "gn:feature_code":"PPL",
    "gn:name":"Pasar Serapuh",
    "gn:population":0,
    "gn:timezone":"Asia/Jakarta",
    "iso:country":"ID",
    "name:ind_x_preferred":[
        "Pasar Serapuh"
    ],
    "wof:name":"Pasar Serapuh",
    "wof:placetype":"locality"
},
  "geometry": {"coordinates":[98.3455,3.9749],"type":"Point"}
}