{
  "type": "Feature",
  "properties": {
    "gn:admin1_code":"8.0",
    "gn:asciiname":"Wedegan Kidul",
    "gn:country_code":"ID",
    "gn:dem":69,
    "gn:feature_class":"P",
    "gn:feature_code":"PPL",
    "gn:name":"Wedegan Kidul",
    "gn:population":0,
    "gn:timezone":"Asia/Jakarta",
    "iso:country":"ID",
    "name:ind_x_preferred":[
        "Wedegan Kidul"
    ],
    "wof:name":"Wedegan Kidul",
    "wof:placetype":"locality"
},
  "geometry": {"coordinates":[112.04510000000001,-7.3233],"type":"Point"}
}