{
  "type": "Feature",
  "properties": {
    "gn:admin1_code":"30",
    "gn:asciiname":"Jublegan",
    "gn:cc2":"ID",
    "gn:country_code":"ID",
    "gn:dem":1440,
    "gn:feature_class":"P",
    "gn:feature_code":"PPL",
    "gn:name":"Jublegan",
    "gn:population":0,
    "gn:timezone":"Asia/Jakarta",
    "iso:country":"ID",
    "name:und_x_variant":[
        "Djublegan",
        "Jublegan"
    ],
    "wof:name":"Jublegan",
    "wof:placetype":"locality"
},
  "geometry": {"coordinates":[107.58111,-7.17944],"type":"Point"}
}