{
  "type": "Feature",
  "properties": {
    "gn:admin1_code":"38.0",
    "gn:asciiname":"Laiya",
    "gn:country_code":"ID",
    "gn:dem":825,
    "gn:feature_class":"P",
    "gn:feature_code":"PPL",
    "gn:name":"Laiya",
    "gn:population":0,
    "gn:timezone":"Asia/Makassar",
    "iso:country":"ID",
    "name:ind_x_preferred":[
        "Laiya"
    ],
    "wof:name":"Laiya",
    "wof:placetype":"locality"
},
  "geometry": {"coordinates":[119.9597,-2.9531],"type":"Point"}
}