{
  "type": "Feature",
  "properties": {
    "gn:admin1_code":"2",
    "gn:asciiname":"Giriloka",
    "gn:country_code":"ID",
    "gn:dem":1250,
    "gn:feature_class":"P",
    "gn:feature_code":"PPL",
    "gn:name":"Giriloka",
    "gn:population":0,
    "gn:timezone":"Asia/Makassar",
    "iso:country":"ID",
    "name:ind_x_preferred":[
        "Giriloka"
    ],
    "wof:name":"Giriloka",
    "wof:placetype":"locality"
},
  "geometry": {"coordinates":[115.0902,-8.2718],"type":"Point"}
}