{
  "type": "Feature",
  "properties": {
    "gn:admin1_code":"07",
    "gn:asciiname":"Cepoko",
    "gn:country_code":"ID",
    "gn:dem":238,
    "gn:feature_class":"P",
    "gn:feature_code":"PPL",
    "gn:name":"Cepoko",
    "gn:population":0,
    "gn:timezone":"Asia/Jakarta",
    "iso:country":"ID",
    "name:und_x_variant":[
        "Tjepoko",
        "Cepoko"
    ],
    "wof:name":"Cepoko",
    "wof:placetype":"locality"
},
  "geometry": {"coordinates":[110.72693999999998,-7.37556],"type":"Point"}
}