{
  "type": "Feature",
  "properties": {
    "gn:admin1_code":"30.0",
    "gn:asciiname":"Barusindang",
    "gn:country_code":"ID",
    "gn:dem":451,
    "gn:feature_class":"P",
    "gn:feature_code":"PPL",
    "gn:name":"Barusindang",
    "gn:population":0,
    "gn:timezone":"Asia/Jakarta",
    "iso:country":"ID",
    "name:ind_x_preferred":[
        "Barusindang"
    ],
    "name:und_x_variant":[
        "Baroesindang"
    ],
    "wof:lang_x_official":[
        "ind"
    ],
    "wof:lang_x_spoken":[
        "ind",
        "eng"
    ],
    "wof:name":"Barusindang",
    "wof:placetype":"locality"
},
  "geometry": {"coordinates":[108.0932,-7.3801],"type":"Point"}
}