{
  "type": "Feature",
  "properties": {
    "gn:admin1_code":"7.0",
    "gn:asciiname":"Penusupan",
    "gn:country_code":"ID",
    "gn:dem":366,
    "gn:feature_class":"P",
    "gn:feature_code":"PPL",
    "gn:name":"Penusupan",
    "gn:population":0,
    "gn:timezone":"Asia/Jakarta",
    "iso:country":"ID",
    "name:ind_x_preferred":[
        "Penusupan"
    ],
    "wof:name":"Penusupan",
    "wof:placetype":"locality"
},
  "geometry": {"coordinates":[109.60861,-7.50806],"type":"Point"}
}