{
  "type": "Feature",
  "properties": {
    "gn:admin1_code":"30",
    "gn:asciiname":"Babakan Perusahaan Jawatan Kereta Api",
    "gn:country_code":"ID",
    "gn:dem":37,
    "gn:feature_class":"P",
    "gn:feature_code":"PPL",
    "gn:name":"Babakan Perusahaan Jawatan Kereta Api",
    "gn:population":0,
    "gn:timezone":"Asia/Jakarta",
    "iso:country":"ID",
    "name:ind_x_preferred":[
        "Babakan Perusahaan Jawatan Kereta Api"
    ],
    "name:und_x_variant":[
        "Babakan PJKA"
    ],
    "wof:name":"Babakan Perusahaan Jawatan Kereta Api",
    "wof:placetype":"locality"
},
  "geometry": {"coordinates":[107.69138999999998,-6.42639],"type":"Point"}
}