{
  "type": "Feature",
  "properties": {
    "gn:admin1_code":"38",
    "gn:asciiname":"Kalimbua",
    "gn:country_code":"ID",
    "gn:dem":775,
    "gn:feature_class":"P",
    "gn:feature_code":"PPL",
    "gn:name":"Kalimbua",
    "gn:population":0,
    "gn:timezone":"Asia/Makassar",
    "iso:country":"ID",
    "name:ind_x_preferred":[
        "Kalimbua"
    ],
    "wof:name":"Kalimbua",
    "wof:placetype":"locality"
},
  "geometry": {"coordinates":[119.88930000000001,-3.4064],"type":"Point"}
}