{
  "type": "Feature",
  "properties": {
    "gn:admin1_code":"26",
    "gn:asciiname":"Pondok Tanjung Mulyo",
    "gn:country_code":"ID",
    "gn:dem":21,
    "gn:feature_class":"P",
    "gn:feature_code":"PPL",
    "gn:name":"Pondok Tanjung Mulyo",
    "gn:population":0,
    "gn:timezone":"Asia/Jakarta",
    "iso:country":"ID",
    "name:ind_x_preferred":[
        "Pondok Tanjung Mulyo"
    ],
    "wof:name":"Pondok Tanjung Mulyo",
    "wof:placetype":"locality"
},
  "geometry": {"coordinates":[99.5514,3.0208],"type":"Point"}
}