{
  "type": "Feature",
  "properties": {
    "gn:admin1_code":"26",
    "gn:asciiname":"Rukahan",
    "gn:country_code":"ID",
    "gn:dem":208,
    "gn:feature_class":"P",
    "gn:feature_code":"PPL",
    "gn:name":"Rukahan",
    "gn:population":0,
    "gn:timezone":"Asia/Jakarta",
    "iso:country":"ID",
    "name:ind_x_preferred":[
        "Rukahan"
    ],
    "wof:name":"Rukahan",
    "wof:placetype":"locality"
},
  "geometry": {"coordinates":[97.8165,3.515],"type":"Point"}
}