{
  "type": "Feature",
  "properties": {
    "gn:admin1_code":"7.0",
    "gn:asciiname":"Pitulasi",
    "gn:country_code":"ID",
    "gn:dem":28,
    "gn:feature_class":"P",
    "gn:feature_code":"PPL",
    "gn:name":"Pitulasi",
    "gn:population":0,
    "gn:timezone":"Asia/Jakarta",
    "iso:country":"ID",
    "name:ind_x_preferred":[
        "Pitulasi"
    ],
    "wof:name":"Pitulasi",
    "wof:placetype":"locality"
},
  "geometry": {"coordinates":[108.762,-7.3675],"type":"Point"}
}