{
  "type": "Feature",
  "properties": {
    "gn:admin1_code":"24.0",
    "gn:asciiname":"Ciranting",
    "gn:country_code":"ID",
    "gn:dem":220,
    "gn:feature_class":"P",
    "gn:feature_code":"PPL",
    "gn:name":"Ciranting",
    "gn:population":0,
    "gn:timezone":"Asia/Jakarta",
    "iso:country":"ID",
    "name:und_x_variant":[
        "Tjiranting",
        "Ciranting"
    ],
    "wof:name":"Ciranting",
    "wof:placetype":"locality"
},
  "geometry": {"coordinates":[100.06019999999999,0.5495],"type":"Point"}
}