{
  "type": "Feature",
  "properties": {
    "gn:admin1_code":"40.0",
    "gn:asciiname":"Labu",
    "gn:country_code":"ID",
    "gn:dem":4,
    "gn:feature_class":"P",
    "gn:feature_code":"PPL",
    "gn:name":"Labu",
    "gn:population":0,
    "gn:timezone":"Asia/Jakarta",
    "iso:country":"ID",
    "name:ceb_x_preferred":[
        "Labu"
    ],
    "name:deu_x_preferred":[
        "Labu"
    ],
    "name:msa_x_preferred":[
        "Labu"
    ],
    "name:swe_x_preferred":[
        "Labu"
    ],
    "name:und_x_variant":[
        "Laboe",
        "Labu",
        "Labuh"
    ],
    "wof:lang_x_official":[
        "ind"
    ],
    "wof:lang_x_spoken":[
        "ind",
        "eng"
    ],
    "wof:name":"Labu",
    "wof:placetype":"locality"
},
  "geometry": {"coordinates":[104.44361000000001,-0.58333],"type":"Point"}
}