{
  "type": "Feature",
  "properties": {
    "gn:admin1_code":"18",
    "gn:asciiname":"Puufeo",
    "gn:country_code":"ID",
    "gn:dem":578,
    "gn:feature_class":"P",
    "gn:feature_code":"PPL",
    "gn:name":"Puufeo",
    "gn:population":0,
    "gn:timezone":"Asia/Makassar",
    "iso:country":"ID",
    "name:ind_x_preferred":[
        "Puufeo"
    ],
    "wof:name":"Puufeo",
    "wof:placetype":"locality"
},
  "geometry": {"coordinates":[121.2577,-8.7588],"type":"Point"}
}