{
  "type": "Feature",
  "properties": {
    "gn:admin1_code":"07",
    "gn:asciiname":"Bedoyo",
    "gn:country_code":"ID",
    "gn:dem":688,
    "gn:feature_class":"P",
    "gn:feature_code":"PPL",
    "gn:name":"Bedoyo",
    "gn:population":0,
    "gn:timezone":"Asia/Jakarta",
    "iso:country":"ID",
    "name:und_x_variant":[
        "Bedojo",
        "Bedoyo"
    ],
    "wof:lang_x_official":[
        "ind"
    ],
    "wof:lang_x_spoken":[
        "ind",
        "eng"
    ],
    "wof:name":"Bedoyo",
    "wof:placetype":"locality"
},
  "geometry": {"coordinates":[110.32444,-7.39083],"type":"Point"}
}