{
  "type": "Feature",
  "properties": {
    "gn:admin1_code":"07",
    "gn:asciiname":"Gembyang",
    "gn:cc2":"ID",
    "gn:country_code":"ID",
    "gn:dem":609,
    "gn:feature_class":"P",
    "gn:feature_code":"PPL",
    "gn:name":"Gembyang",
    "gn:population":0,
    "gn:timezone":"Asia/Jakarta",
    "iso:country":"ID",
    "name:und_x_variant":[
        "Gembjang",
        "Gembyang"
    ],
    "wof:lang_x_official":[
        "ind"
    ],
    "wof:lang_x_spoken":[
        "ind",
        "eng"
    ],
    "wof:name":"Gembyang",
    "wof:placetype":"locality"
},
  "geometry": {"coordinates":[110.39722,-7.24528],"type":"Point"}
}