{
  "type": "Feature",
  "properties": {
    "gn:admin1_code":"7.0",
    "gn:asciiname":"Kurwok",
    "gn:country_code":"ID",
    "gn:dem":26,
    "gn:feature_class":"P",
    "gn:feature_code":"PPL",
    "gn:name":"Kurwok",
    "gn:population":0,
    "gn:timezone":"Asia/Jakarta",
    "iso:country":"ID",
    "name:ind_x_preferred":[
        "Kurwok"
    ],
    "wof:name":"Kurwok",
    "wof:placetype":"locality"
},
  "geometry": {"coordinates":[109.485,-7.59639],"type":"Point"}
}