{
  "type": "Feature",
  "properties": {
    "gn:admin1_code":"28.0",
    "gn:asciiname":"Haruku",
    "gn:country_code":"ID",
    "gn:dem":8,
    "gn:feature_class":"P",
    "gn:feature_code":"PPL",
    "gn:name":"Haruku",
    "gn:population":0,
    "gn:timezone":"Asia/Jayapura",
    "iso:country":"ID",
    "name:ind_x_preferred":[
        "Haruku"
    ],
    "name:und_x_variant":[
        "Samet Haroekoe",
        "Haroekoe",
        "Kampoeng Haroekoe",
        "Haruku"
    ],
    "wof:lang_x_official":[
        "ind"
    ],
    "wof:lang_x_spoken":[
        "ind",
        "eng"
    ],
    "wof:name":"Haruku",
    "wof:placetype":"locality"
},
  "geometry": {"coordinates":[128.41878,-3.60341],"type":"Point"}
}