{
  "type": "Feature",
  "properties": {
    "gn:admin1_code":"17",
    "gn:asciiname":"Mecanggah",
    "gn:country_code":"ID",
    "gn:dem":35,
    "gn:feature_class":"P",
    "gn:feature_code":"PPL",
    "gn:name":"Mecanggah",
    "gn:population":0,
    "gn:timezone":"Asia/Makassar",
    "iso:country":"ID",
    "name:ind_x_preferred":[
        "Mecanggah"
    ],
    "wof:name":"Mecanggah",
    "wof:placetype":"locality"
},
  "geometry": {"coordinates":[115.9633,-8.8144],"type":"Point"}
}