{
  "type": "Feature",
  "properties": {
    "gn:admin1_code":"30",
    "gn:asciiname":"Cikadu Kaler",
    "gn:country_code":"ID",
    "gn:dem":1008,
    "gn:feature_class":"P",
    "gn:feature_code":"PPL",
    "gn:name":"Cikadu Kaler",
    "gn:population":0,
    "gn:timezone":"Asia/Jakarta",
    "iso:country":"ID",
    "name:ind_x_preferred":[
        "Cikadu Kaler"
    ],
    "wof:name":"Cikadu Kaler",
    "wof:placetype":"locality"
},
  "geometry": {"coordinates":[107.33638999999999,-6.965],"type":"Point"}
}