{
  "type": "Feature",
  "properties": {
    "gn:admin1_code":"18",
    "gn:asciiname":"Karipi Satu",
    "gn:country_code":"ID",
    "gn:dem":578,
    "gn:feature_class":"P",
    "gn:feature_code":"PPL",
    "gn:name":"Karipi Satu",
    "gn:population":0,
    "gn:timezone":"Asia/Makassar",
    "iso:country":"ID",
    "name:ind_x_preferred":[
        "Karipi Satu"
    ],
    "name:und_x_variant":[
        "Karipi 1"
    ],
    "wof:lang_x_official":[
        "ind"
    ],
    "wof:lang_x_spoken":[
        "ind",
        "eng"
    ],
    "wof:name":"Karipi Satu",
    "wof:placetype":"locality"
},
  "geometry": {"coordinates":[120.01479999999999,-9.6951],"type":"Point"}
}