{
  "type": "Feature",
  "properties": {
    "gn:admin1_code":"38",
    "gn:asciiname":"Bontobosi",
    "gn:country_code":"ID",
    "gn:dem":62,
    "gn:feature_class":"P",
    "gn:feature_code":"PPL",
    "gn:name":"Bontobosi",
    "gn:population":0,
    "gn:timezone":"Asia/Makassar",
    "iso:country":"ID",
    "name:ind_x_preferred":[
        "Bontobosi"
    ],
    "wof:name":"Bontobosi",
    "wof:placetype":"locality"
},
  "geometry": {"coordinates":[119.9148,-5.5401],"type":"Point"}
}