{
  "type": "Feature",
  "properties": {
    "gn:admin1_code":"8",
    "gn:asciiname":"Genitri",
    "gn:country_code":"ID",
    "gn:dem":470,
    "gn:feature_class":"P",
    "gn:feature_code":"PPL",
    "gn:name":"Genitri",
    "gn:population":0,
    "gn:timezone":"Asia/Jakarta",
    "iso:country":"ID",
    "name:ind_x_preferred":[
        "Genitri"
    ],
    "wof:name":"Genitri",
    "wof:placetype":"locality"
},
  "geometry": {"coordinates":[112.6116,-7.9728],"type":"Point"}
}