{
  "type": "Feature",
  "properties": {
    "gn:admin1_code":"28.0",
    "gn:asciiname":"Wamrugu",
    "gn:country_code":"ID",
    "gn:dem":35,
    "gn:feature_class":"P",
    "gn:feature_code":"PPL",
    "gn:name":"Wamrugu",
    "gn:population":0,
    "gn:timezone":"Asia/Jayapura",
    "iso:country":"ID",
    "name:ind_x_preferred":[
        "Wamrugu"
    ],
    "name:und_x_variant":[
        "Wa \u2019Mroegoe"
    ],
    "wof:lang_x_official":[
        "ind"
    ],
    "wof:lang_x_spoken":[
        "ind",
        "eng"
    ],
    "wof:name":"Wamrugu",
    "wof:placetype":"locality"
},
  "geometry": {"coordinates":[126.48032000000001,-3.09054],"type":"Point"}
}