{
  "type": "Feature",
  "properties": {
    "gn:admin1_code":"8.0",
    "gn:asciiname":"Jatian",
    "gn:country_code":"ID",
    "gn:dem":327,
    "gn:feature_class":"P",
    "gn:feature_code":"PPLA4",
    "gn:name":"Jatian",
    "gn:population":0,
    "gn:timezone":"Asia/Jakarta",
    "iso:country":"ID",
    "name:ind_x_preferred":[
        "Jatian"
    ],
    "wof:name":"Jatian",
    "wof:placetype":"locality"
},
  "geometry": {"coordinates":[113.7953,-8.0196],"type":"Point"}
}