{
  "type": "Feature",
  "properties": {
    "gn:admin1_code":"7",
    "gn:asciiname":"Gambiran",
    "gn:country_code":"ID",
    "gn:dem":7,
    "gn:feature_class":"P",
    "gn:feature_code":"PPL",
    "gn:name":"Gambiran",
    "gn:population":0,
    "gn:timezone":"Asia/Jakarta",
    "iso:country":"ID",
    "name:ind_x_preferred":[
        "Gambiran"
    ],
    "wof:name":"Gambiran",
    "wof:placetype":"locality"
},
  "geometry": {"coordinates":[110.27760000000001,-6.9648],"type":"Point"}
}