{
  "type": "Feature",
  "properties": {
    "gn:admin1_code":"4.0",
    "gn:asciiname":"Puloharapanindah",
    "gn:cc2":"ID",
    "gn:country_code":"ID",
    "gn:dem":5,
    "gn:feature_class":"P",
    "gn:feature_code":"PPL",
    "gn:name":"Puloharapanindah",
    "gn:population":0,
    "gn:timezone":"Asia/Jakarta",
    "iso:country":"ID",
    "name:und_x_variant":[
        "Poelo",
        "Pulo",
        "Puloharapanindah"
    ],
    "wof:lang_x_official":[
        "ind"
    ],
    "wof:lang_x_spoken":[
        "ind",
        "eng"
    ],
    "wof:name":"Puloharapanindah",
    "wof:placetype":"locality"
},
  "geometry": {"coordinates":[106.7225,-6.13306],"type":"Point"}
}