{
  "type": "Feature",
  "properties": {
    "gn:admin1_code":"8.0",
    "gn:asciiname":"Klutuk",
    "gn:country_code":"ID",
    "gn:dem":62,
    "gn:feature_class":"P",
    "gn:feature_code":"PPL",
    "gn:name":"Klutuk",
    "gn:population":0,
    "gn:timezone":"Asia/Jakarta",
    "iso:country":"ID",
    "name:ind_x_preferred":[
        "Klutuk"
    ],
    "wof:name":"Klutuk",
    "wof:placetype":"locality"
},
  "geometry": {"coordinates":[112.15260000000001,-7.6303],"type":"Point"}
}