{
  "type": "Feature",
  "properties": {
    "gn:admin1_code":"8.0",
    "gn:asciiname":"Sugihan",
    "gn:country_code":"ID",
    "gn:dem":34,
    "gn:feature_class":"P",
    "gn:feature_code":"PPL",
    "gn:name":"Sugihan",
    "gn:population":0,
    "gn:timezone":"Asia/Jakarta",
    "iso:country":"ID",
    "name:ind_x_preferred":[
        "Sugihan"
    ],
    "wof:name":"Sugihan",
    "wof:placetype":"locality"
},
  "geometry": {"coordinates":[112.5057,-7.5114],"type":"Point"}
}