{
  "type": "Feature",
  "properties": {
    "gn:admin1_code":"30",
    "gn:asciiname":"Cikawari",
    "gn:country_code":"ID",
    "gn:dem":1184,
    "gn:feature_class":"P",
    "gn:feature_code":"PPL",
    "gn:name":"Cikawari",
    "gn:population":0,
    "gn:timezone":"Asia/Jakarta",
    "iso:country":"ID",
    "name:ind_x_preferred":[
        "Cikawari"
    ],
    "name:und_x_variant":[
        "Tjikiweri",
        "Cikiweri"
    ],
    "wof:lang_x_official":[
        "ind"
    ],
    "wof:lang_x_spoken":[
        "ind",
        "eng"
    ],
    "wof:name":"Cikawari",
    "wof:placetype":"locality"
},
  "geometry": {"coordinates":[107.53389,-6.78472],"type":"Point"}
}