{
  "type": "Feature",
  "properties": {
    "gn:admin1_code":"3.0",
    "gn:asciiname":"Padangguci",
    "gn:country_code":"ID",
    "gn:dem":43,
    "gn:feature_class":"P",
    "gn:feature_code":"PPLA3",
    "gn:name":"Padangguci",
    "gn:population":0,
    "gn:timezone":"Asia/Jakarta",
    "iso:country":"ID",
    "name:und_x_variant":[
        "Padanggoetji",
        "Padanggutji",
        "Padanggutyi",
        "Padangguci"
    ],
    "wof:lang_x_official":[
        "ind"
    ],
    "wof:lang_x_spoken":[
        "ind",
        "eng"
    ],
    "wof:name":"Padangguci",
    "wof:placetype":"locality"
},
  "geometry": {"coordinates":[103.14425,-4.58891],"type":"Point"}
}