{
  "type": "Feature",
  "properties": {
    "gn:admin1_code":"30.0",
    "gn:asciiname":"Nangerang",
    "gn:country_code":"ID",
    "gn:dem":455,
    "gn:feature_class":"P",
    "gn:feature_code":"PPL",
    "gn:name":"Nangerang",
    "gn:population":0,
    "gn:timezone":"Asia/Jakarta",
    "iso:country":"ID",
    "name:ind_x_preferred":[
        "Nangerang"
    ],
    "wof:name":"Nangerang",
    "wof:placetype":"locality"
},
  "geometry": {"coordinates":[108.31619999999999,-7.5147],"type":"Point"}
}