{
  "type": "Feature",
  "properties": {
    "gn:admin1_code":"30",
    "gn:asciiname":"Bojonglangkap",
    "gn:country_code":"ID",
    "gn:dem":659,
    "gn:feature_class":"P",
    "gn:feature_code":"PPL",
    "gn:name":"Bojonglangkap",
    "gn:population":0,
    "gn:timezone":"Asia/Jakarta",
    "iso:country":"ID",
    "name:ind_x_preferred":[
        "Bojonglangkap"
    ],
    "name:und_x_variant":[
        "Bodjongmasain",
        "Bojongmasain"
    ],
    "wof:lang_x_official":[
        "ind"
    ],
    "wof:lang_x_spoken":[
        "ind",
        "eng"
    ],
    "wof:name":"Bojonglangkap",
    "wof:placetype":"locality"
},
  "geometry": {"coordinates":[107.38889,-6.92583],"type":"Point"}
}