{
  "type": "Feature",
  "properties": {
    "gn:admin1_code":"38.0",
    "gn:asciiname":"Ujungmajina",
    "gn:country_code":"ID",
    "gn:dem":19,
    "gn:feature_class":"P",
    "gn:feature_code":"PPL",
    "gn:name":"Ujungmajina",
    "gn:population":0,
    "gn:timezone":"Asia/Makassar",
    "iso:country":"ID",
    "name:ind_x_preferred":[
        "Ujungmajina"
    ],
    "wof:name":"Ujungmajina",
    "wof:placetype":"locality"
},
  "geometry": {"coordinates":[119.8027,-3.924],"type":"Point"}
}