{
  "type": "Feature",
  "properties": {
    "gn:admin1_code":"14.0",
    "gn:asciiname":"Longboh",
    "gn:country_code":"ID",
    "gn:dem":417,
    "gn:feature_class":"P",
    "gn:feature_code":"PPL",
    "gn:name":"Longboh",
    "gn:population":0,
    "gn:timezone":"Asia/Makassar",
    "iso:country":"ID",
    "wof:name":"Longboh",
    "wof:placetype":"locality"
},
  "geometry": {"coordinates":[115.03333000000001,0.86667],"type":"Point"}
}