{
  "type": "Feature",
  "properties": {
    "gn:admin1_code":"30.0",
    "gn:asciiname":"Cisema Kidul",
    "gn:country_code":"ID",
    "gn:dem":609,
    "gn:feature_class":"P",
    "gn:feature_code":"PPL",
    "gn:name":"Cisema Kidul",
    "gn:population":0,
    "gn:timezone":"Asia/Jakarta",
    "iso:country":"ID",
    "name:ind_x_preferred":[
        "Cisema Kidul"
    ],
    "wof:name":"Cisema Kidul",
    "wof:placetype":"locality"
},
  "geometry": {"coordinates":[108.2047,-7.0876],"type":"Point"}
}