{
  "type": "Feature",
  "properties": {
    "gn:admin1_code":"30",
    "gn:asciiname":"Padasukaindah",
    "gn:country_code":"ID",
    "gn:dem":738,
    "gn:feature_class":"P",
    "gn:feature_code":"PPL",
    "gn:name":"Padasukaindah",
    "gn:population":0,
    "gn:timezone":"Asia/Jakarta",
    "iso:country":"ID",
    "name:ind_x_preferred":[
        "Padasukaindah"
    ],
    "wof:name":"Padasukaindah",
    "wof:placetype":"locality"
},
  "geometry": {"coordinates":[107.52443999999998,-6.87167],"type":"Point"}
}