{
  "type": "Feature",
  "properties": {
    "gn:admin1_code":"36.0",
    "gn:asciiname":"Orimbori",
    "gn:country_code":"ID",
    "gn:dem":9,
    "gn:feature_class":"P",
    "gn:feature_code":"PPL",
    "gn:name":"Orimbori",
    "gn:population":0,
    "gn:timezone":"Asia/Jayapura",
    "iso:country":"ID",
    "name:ind_x_preferred":[
        "Orimbori"
    ],
    "name:und_x_variant":[
        "Oerimbori",
        "Orimbori"
    ],
    "wof:name":"Orimbori",
    "wof:placetype":"locality"
},
  "geometry": {"coordinates":[135.49501000000001,-0.65256],"type":"Point"}
}