{
  "type": "Feature",
  "properties": {
    "gn:admin1_code":"37",
    "gn:asciiname":"Lubuktebakar",
    "gn:country_code":"ID",
    "gn:dem":10,
    "gn:feature_class":"P",
    "gn:feature_code":"PPL",
    "gn:name":"Lubuktebakar",
    "gn:population":0,
    "gn:timezone":"Asia/Jakarta",
    "iso:country":"ID",
    "name:eng_x_preferred":[
        "Lubuktebakar"
    ],
    "wof:name":"Lubuktebakar",
    "wof:placetype":"locality"
},
  "geometry": {"coordinates":[101.2315,0.7352],"type":"Point"}
}