{
  "type": "Feature",
  "properties": {
    "gn:admin1_code":"1",
    "gn:asciiname":"Blang Aceh",
    "gn:country_code":"ID",
    "gn:dem":32,
    "gn:feature_class":"P",
    "gn:feature_code":"PPL",
    "gn:name":"Blang Aceh",
    "gn:population":0,
    "gn:timezone":"Asia/Jakarta",
    "iso:country":"ID",
    "name:ind_x_preferred":[
        "Blang Aceh"
    ],
    "wof:name":"Blang Aceh",
    "wof:placetype":"locality"
},
  "geometry": {"coordinates":[97.2179,5.0022],"type":"Point"}
}