{
  "type": "Feature",
  "properties": {
    "gn:admin1_code":"30",
    "gn:asciiname":"Pariuk",
    "gn:country_code":"ID",
    "gn:dem":70,
    "gn:feature_class":"P",
    "gn:feature_code":"PPL",
    "gn:name":"Pariuk",
    "gn:population":0,
    "gn:timezone":"Asia/Jakarta",
    "iso:country":"ID",
    "name:ind_x_preferred":[
        "Pariuk"
    ],
    "wof:name":"Pariuk",
    "wof:placetype":"locality"
},
  "geometry": {"coordinates":[106.47539999999999,-6.4471],"type":"Point"}
}