{
  "type": "Feature",
  "properties": {
    "gn:admin1_code":"15.0",
    "gn:asciiname":"Pancasila",
    "gn:country_code":"ID",
    "gn:dem":77,
    "gn:feature_class":"P",
    "gn:feature_code":"PPL",
    "gn:name":"Pancasila",
    "gn:population":0,
    "gn:timezone":"Asia/Jakarta",
    "iso:country":"ID",
    "name:ind_x_preferred":[
        "Pancasila"
    ],
    "wof:name":"Pancasila",
    "wof:placetype":"locality"
},
  "geometry": {"coordinates":[105.22216,-5.23909],"type":"Point"}
}