{
  "type": "Feature",
  "properties": {
    "gn:admin1_code":"30.0",
    "gn:asciiname":"Kampungsawah 1",
    "gn:country_code":"ID",
    "gn:dem":8,
    "gn:feature_class":"P",
    "gn:feature_code":"PPL",
    "gn:name":"Kampungsawah 1",
    "gn:population":0,
    "gn:timezone":"Asia/Jakarta",
    "iso:country":"ID",
    "wof:name":"Kampungsawah 1",
    "wof:placetype":"locality"
},
  "geometry": {"coordinates":[107.27249999999999,-6.1025],"type":"Point"}
}