{
  "type": "Feature",
  "properties": {
    "gn:admin1_code":"30",
    "gn:asciiname":"Tambakbago",
    "gn:country_code":"ID",
    "gn:dem":3,
    "gn:feature_class":"P",
    "gn:feature_code":"PPL",
    "gn:name":"Tambakbago",
    "gn:population":0,
    "gn:timezone":"Asia/Jakarta",
    "iso:country":"ID",
    "name:ind_x_preferred":[
        "Tambakbago"
    ],
    "wof:name":"Tambakbago",
    "wof:placetype":"locality"
},
  "geometry": {"coordinates":[107.90472,-6.24417],"type":"Point"}
}