{
  "type": "Feature",
  "properties": {
    "gn:admin1_code":"7",
    "gn:asciiname":"Karangnongko",
    "gn:country_code":"ID",
    "gn:dem":838,
    "gn:feature_class":"P",
    "gn:feature_code":"PPL",
    "gn:name":"Karangnongko",
    "gn:population":0,
    "gn:timezone":"Asia/Jakarta",
    "iso:country":"ID",
    "name:ind_x_preferred":[
        "Karangnongko"
    ],
    "name:jav_x_preferred":[
        "Karangnangka"
    ],
    "name:nld_x_preferred":[
        "Karangnongko"
    ],
    "wof:lang_x_official":[
        "ind"
    ],
    "wof:lang_x_spoken":[
        "ind",
        "eng"
    ],
    "wof:name":"Karangnongko",
    "wof:placetype":"locality"
},
  "geometry": {"coordinates":[109.61778,-7.17139],"type":"Point"}
}