{
  "type": "Feature",
  "properties": {
    "gn:admin1_code":"18.0",
    "gn:asciiname":"Bijaeruki",
    "gn:country_code":"ID",
    "gn:dem":396,
    "gn:feature_class":"P",
    "gn:feature_code":"PPL",
    "gn:name":"Bijaeruki",
    "gn:population":0,
    "gn:timezone":"Asia/Makassar",
    "iso:country":"ID",
    "name:ind_x_preferred":[
        "Bijaeruki"
    ],
    "wof:name":"Bijaeruki",
    "wof:placetype":"locality"
},
  "geometry": {"coordinates":[123.843,-10.306],"type":"Point"}
}