{
  "type": "Feature",
  "properties": {
    "gn:admin1_code":"28.0",
    "gn:asciiname":"Dangar",
    "gn:country_code":"ID",
    "gn:dem":39,
    "gn:feature_class":"P",
    "gn:feature_code":"PPL",
    "gn:name":"Dangar",
    "gn:population":0,
    "gn:timezone":"Asia/Jayapura",
    "iso:country":"ID",
    "name:ceb_x_preferred":[
        "Dangar"
    ],
    "name:fra_x_preferred":[
        "Dangar"
    ],
    "name:ind_x_preferred":[
        "Dangar"
    ],
    "name:swe_x_preferred":[
        "Dangar"
    ],
    "wof:lang_x_official":[
        "ind"
    ],
    "wof:lang_x_spoken":[
        "ind",
        "eng"
    ],
    "wof:name":"Dangar",
    "wof:placetype":"locality"
},
  "geometry": {"coordinates":[133.04571999999999,-5.51745],"type":"Point"}
}