{
  "type": "Feature",
  "properties": {
    "gn:admin1_code":"30.0",
    "gn:asciiname":"Cibuluh",
    "gn:country_code":"ID",
    "gn:dem":630,
    "gn:feature_class":"P",
    "gn:feature_code":"PPL",
    "gn:name":"Cibuluh",
    "gn:population":0,
    "gn:timezone":"Asia/Jakarta",
    "iso:country":"ID",
    "name:ind_x_preferred":[
        "Cibuluh"
    ],
    "wof:name":"Cibuluh",
    "wof:placetype":"locality"
},
  "geometry": {"coordinates":[107.1082,-7.1728],"type":"Point"}
}