{
  "type": "Feature",
  "properties": {
    "gn:admin1_code":"30.0",
    "gn:asciiname":"Pamoyanan",
    "gn:country_code":"ID",
    "gn:dem":18,
    "gn:feature_class":"P",
    "gn:feature_code":"PPL",
    "gn:name":"Pamoyanan",
    "gn:population":0,
    "gn:timezone":"Asia/Jakarta",
    "iso:country":"ID",
    "name:ind_x_preferred":[
        "Pamoyanan"
    ],
    "wof:name":"Pamoyanan",
    "wof:placetype":"locality"
},
  "geometry": {"coordinates":[106.9468,-7.3865],"type":"Point"}
}