{
  "type": "Feature",
  "properties": {
    "gn:admin1_code":"18",
    "gn:asciiname":"Parengu",
    "gn:country_code":"ID",
    "gn:dem":24,
    "gn:feature_class":"P",
    "gn:feature_code":"PPL",
    "gn:name":"Parengu",
    "gn:population":0,
    "gn:timezone":"Asia/Makassar",
    "iso:country":"ID",
    "name:ind_x_preferred":[
        "Parengu"
    ],
    "wof:name":"Parengu",
    "wof:placetype":"locality"
},
  "geometry": {"coordinates":[120.068,-10.1408],"type":"Point"}
}