{
  "type": "Feature",
  "properties": {
    "gn:admin1_code":"30",
    "gn:asciiname":"Cisumur",
    "gn:country_code":"ID",
    "gn:dem":811,
    "gn:feature_class":"P",
    "gn:feature_code":"PPL",
    "gn:name":"Cisumur",
    "gn:population":0,
    "gn:timezone":"Asia/Jakarta",
    "iso:country":"ID",
    "name:ind_x_preferred":[
        "Cisumur"
    ],
    "wof:name":"Cisumur",
    "wof:placetype":"locality"
},
  "geometry": {"coordinates":[107.47528,-6.99917],"type":"Point"}
}