{
  "type": "Feature",
  "properties": {
    "gn:admin1_code":"37.0",
    "gn:asciiname":"Sungairayahulu",
    "gn:country_code":"ID",
    "gn:dem":43,
    "gn:feature_class":"P",
    "gn:feature_code":"PPL",
    "gn:name":"Sungairayahulu",
    "gn:population":0,
    "gn:timezone":"Asia/Jakarta",
    "iso:country":"ID",
    "name:ind_x_preferred":[
        "Sungairayahulu"
    ],
    "name:und_x_variant":[
        "Soengairaja-hoeloe",
        "Sungairaja-hulu",
        "Soengairajaoeloe"
    ],
    "wof:lang_x_official":[
        "ind"
    ],
    "wof:lang_x_spoken":[
        "ind",
        "eng"
    ],
    "wof:name":"Sungairayahulu",
    "wof:placetype":"locality"
},
  "geometry": {"coordinates":[102.44110000000001,-0.4547],"type":"Point"}
}