{
  "type": "Feature",
  "properties": {
    "gn:admin1_code":"18.0",
    "gn:asciiname":"Lalong",
    "gn:country_code":"ID",
    "gn:dem":176,
    "gn:feature_class":"P",
    "gn:feature_code":"PPL",
    "gn:name":"Lalong",
    "gn:population":0,
    "gn:timezone":"Asia/Makassar",
    "iso:country":"ID",
    "name:ind_x_preferred":[
        "Lalong"
    ],
    "name:spa_x_preferred":[
        "Lalong"
    ],
    "name:urd_x_preferred":[
        "\u0644\u0627\u0644\u0648\u0646\u06af"
    ],
    "wof:lang_x_official":[
        "ind"
    ],
    "wof:lang_x_spoken":[
        "ind",
        "eng"
    ],
    "wof:name":"Lalong",
    "wof:placetype":"locality"
},
  "geometry": {"coordinates":[120.17489999999999,-8.7199],"type":"Point"}
}