{
  "type": "Feature",
  "properties": {
    "gn:admin1_code":"8.0",
    "gn:asciiname":"Gunungnyamil",
    "gn:country_code":"ID",
    "gn:dem":231,
    "gn:feature_class":"P",
    "gn:feature_code":"PPL",
    "gn:name":"Gunungnyamil",
    "gn:population":0,
    "gn:timezone":"Asia/Jakarta",
    "iso:country":"ID",
    "name:ind_x_preferred":[
        "Gunungnyamil"
    ],
    "wof:name":"Gunungnyamil",
    "wof:placetype":"locality"
},
  "geometry": {"coordinates":[112.2137,-8.2628],"type":"Point"}
}