{
  "type": "Feature",
  "properties": {
    "gn:admin1_code":"1",
    "gn:asciiname":"Lawe Beringin Horas Satu",
    "gn:country_code":"ID",
    "gn:dem":128,
    "gn:feature_class":"P",
    "gn:feature_code":"PPL",
    "gn:name":"Lawe Beringin Horas Satu",
    "gn:population":0,
    "gn:timezone":"Asia/Jakarta",
    "iso:country":"ID",
    "name:ind_x_preferred":[
        "Lawe Beringin Horas Satu"
    ],
    "name:und_x_variant":[
        "Lawe Beringin Horas 1"
    ],
    "wof:name":"Lawe Beringin Horas Satu",
    "wof:placetype":"locality"
},
  "geometry": {"coordinates":[97.88760000000001,3.3841],"type":"Point"}
}