{
  "type": "Feature",
  "properties": {
    "gn:admin1_code":"30",
    "gn:asciiname":"Sumbon Dua",
    "gn:country_code":"ID",
    "gn:dem":18,
    "gn:feature_class":"P",
    "gn:feature_code":"PPL",
    "gn:name":"Sumbon Dua",
    "gn:population":0,
    "gn:timezone":"Asia/Jakarta",
    "iso:country":"ID",
    "name:ind_x_preferred":[
        "Sumbon Dua"
    ],
    "wof:name":"Sumbon Dua",
    "wof:placetype":"locality"
},
  "geometry": {"coordinates":[108.09778,-6.47083],"type":"Point"}
}