{
  "type": "Feature",
  "properties": {
    "gn:admin1_code":"30",
    "gn:asciiname":"Cantilan",
    "gn:country_code":"ID",
    "gn:dem":10,
    "gn:feature_class":"P",
    "gn:feature_code":"PPL",
    "gn:name":"Cantilan",
    "gn:population":0,
    "gn:timezone":"Asia/Jakarta",
    "iso:country":"ID",
    "name:ind_x_preferred":[
        "Cantilan"
    ],
    "wof:name":"Cantilan",
    "wof:placetype":"locality"
},
  "geometry": {"coordinates":[108.64870000000001,-6.814],"type":"Point"}
}