{
  "type": "Feature",
  "properties": {
    "gn:admin1_code":"8.0",
    "gn:asciiname":"Bistah",
    "gn:country_code":"ID",
    "gn:dem":34,
    "gn:feature_class":"P",
    "gn:feature_code":"PPL",
    "gn:name":"Bistah",
    "gn:population":0,
    "gn:timezone":"Asia/Jakarta",
    "iso:country":"ID",
    "name:ind_x_preferred":[
        "Bistah"
    ],
    "wof:name":"Bistah",
    "wof:placetype":"locality"
},
  "geometry": {"coordinates":[113.25749999999999,-7.1394],"type":"Point"}
}