{
  "type": "Feature",
  "properties": {
    "gn:admin1_code":"8.0",
    "gn:asciiname":"Glagahsari",
    "gn:country_code":"ID",
    "gn:dem":20,
    "gn:feature_class":"P",
    "gn:feature_code":"PPL",
    "gn:name":"Glagahsari",
    "gn:population":0,
    "gn:timezone":"Asia/Jakarta",
    "iso:country":"ID",
    "name:ind_x_preferred":[
        "Glagahsari"
    ],
    "wof:name":"Glagahsari",
    "wof:placetype":"locality"
},
  "geometry": {"coordinates":[111.98211000000001,-7.14882],"type":"Point"}
}