{
  "type": "Feature",
  "properties": {
    "gn:admin1_code":"30",
    "gn:asciiname":"Curug",
    "gn:country_code":"ID",
    "gn:dem":754,
    "gn:feature_class":"P",
    "gn:feature_code":"PPL",
    "gn:name":"Curug",
    "gn:population":0,
    "gn:timezone":"Asia/Jakarta",
    "iso:country":"ID",
    "name:ceb_x_preferred":[
        "Curug"
    ],
    "name:fra_x_preferred":[
        "Curug"
    ],
    "name:ind_x_preferred":[
        "Curug"
    ],
    "name:nld_x_preferred":[
        "Curug"
    ],
    "name:swe_x_preferred":[
        "Curug"
    ],
    "wof:lang_x_official":[
        "ind"
    ],
    "wof:lang_x_spoken":[
        "ind",
        "eng"
    ],
    "wof:name":"Curug",
    "wof:placetype":"locality"
},
  "geometry": {"coordinates":[107.59,-7.06639],"type":"Point"}
}