{
  "type": "Feature",
  "properties": {
    "gn:admin1_code":"18.0",
    "gn:asciiname":"As'ana",
    "gn:country_code":"ID",
    "gn:dem":463,
    "gn:feature_class":"P",
    "gn:feature_code":"PPL",
    "gn:name":"As\u2019ana",
    "gn:population":0,
    "gn:timezone":"Asia/Makassar",
    "iso:country":"ID",
    "name:ind_x_preferred":[
        "As\u2019ana"
    ],
    "wof:lang_x_official":[
        "ind"
    ],
    "wof:lang_x_spoken":[
        "ind",
        "eng"
    ],
    "wof:name":"As'ana",
    "wof:placetype":"locality"
},
  "geometry": {"coordinates":[123.9708,-10.0063],"type":"Point"}
}