{
  "type": "Feature",
  "properties": {
    "gn:admin1_code":"18.0",
    "gn:asciiname":"Mataloko",
    "gn:country_code":"ID",
    "gn:dem":1008,
    "gn:feature_class":"P",
    "gn:feature_code":"PPLA3",
    "gn:name":"Mataloko",
    "gn:population":0,
    "gn:timezone":"Asia/Makassar",
    "iso:country":"ID",
    "name:ind_x_preferred":[
        "Mataloko"
    ],
    "wof:lang_x_official":[
        "ind"
    ],
    "wof:lang_x_spoken":[
        "ind",
        "eng"
    ],
    "wof:name":"Mataloko",
    "wof:placetype":"locality"
},
  "geometry": {"coordinates":[121.063,-8.8206],"type":"Point"}
}