{
  "type": "Feature",
  "properties": {
    "gn:admin1_code":"15.0",
    "gn:asciiname":"Umbulan Raden Intan",
    "gn:country_code":"ID",
    "gn:dem":17,
    "gn:feature_class":"P",
    "gn:feature_code":"PPL",
    "gn:name":"Umbulan Raden Intan",
    "gn:population":0,
    "gn:timezone":"Asia/Jakarta",
    "iso:country":"ID",
    "name:ind_x_preferred":[
        "Umbulan Raden Intan"
    ],
    "name:ind_x_variant":[
        "Umbulansadenintan"
    ],
    "wof:name":"Umbulan Raden Intan",
    "wof:placetype":"locality"
},
  "geometry": {"coordinates":[105.33257,-4.29792],"type":"Point"}
}