{
  "type": "Feature",
  "properties": {
    "gn:admin1_code":"21.0",
    "gn:asciiname":"Bahumbelo",
    "gn:cc2":"ID",
    "gn:country_code":"ID",
    "gn:dem":3,
    "gn:feature_class":"P",
    "gn:feature_code":"PPL",
    "gn:name":"Bahumbelo",
    "gn:population":0,
    "gn:timezone":"Asia/Makassar",
    "iso:country":"ID",
    "name:und_x_variant":[
        "Bahu-mbelu",
        "Bahunbelo",
        "Bahoe-mbeloe",
        "Bahumbelo"
    ],
    "wof:lang_x_official":[
        "ind"
    ],
    "wof:lang_x_spoken":[
        "ind",
        "eng"
    ],
    "wof:name":"Bahumbelo",
    "wof:placetype":"locality"
},
  "geometry": {"coordinates":[121.6925,-2.19139],"type":"Point"}
}