{
  "type": "Feature",
  "properties": {
    "gn:admin1_code":"17",
    "gn:asciiname":"Rempeloka",
    "gn:country_code":"ID",
    "gn:dem":21,
    "gn:feature_class":"P",
    "gn:feature_code":"PPL",
    "gn:name":"Rempeloka",
    "gn:population":0,
    "gn:timezone":"Asia/Makassar",
    "iso:country":"ID",
    "name:ind_x_preferred":[
        "Rempeloka"
    ],
    "wof:name":"Rempeloka",
    "wof:placetype":"locality"
},
  "geometry": {"coordinates":[116.86060000000001,-8.6491],"type":"Point"}
}