{
  "type": "Feature",
  "properties": {
    "gn:admin1_code":"24",
    "gn:asciiname":"Ujungpadang",
    "gn:country_code":"ID",
    "gn:dem":232,
    "gn:feature_class":"P",
    "gn:feature_code":"PPL",
    "gn:name":"Ujungpadang",
    "gn:population":0,
    "gn:timezone":"Asia/Jakarta",
    "iso:country":"ID",
    "name:ind_x_preferred":[
        "Ujungpadang"
    ],
    "wof:name":"Ujungpadang",
    "wof:placetype":"locality"
},
  "geometry": {"coordinates":[100.10290000000001,0.3294],"type":"Point"}
}