{
  "type": "Feature",
  "properties": {
    "gn:admin1_code":"18",
    "gn:asciiname":"Kedimau",
    "gn:country_code":"ID",
    "gn:dem":397,
    "gn:feature_class":"P",
    "gn:feature_code":"PPL",
    "gn:name":"Kedimau",
    "gn:population":0,
    "gn:timezone":"Asia/Makassar",
    "iso:country":"ID",
    "name:ind_x_preferred":[
        "Kedimau"
    ],
    "wof:name":"Kedimau",
    "wof:placetype":"locality"
},
  "geometry": {"coordinates":[121.3018,-8.8595],"type":"Point"}
}