{
  "type": "Feature",
  "properties": {
    "gn:admin1_code":"33.0",
    "gn:asciiname":"Cicarucub",
    "gn:country_code":"ID",
    "gn:dem":740,
    "gn:feature_class":"P",
    "gn:feature_code":"PPLA4",
    "gn:name":"Cicarucub",
    "gn:population":0,
    "gn:timezone":"Asia/Jakarta",
    "iso:country":"ID",
    "name:ind_x_preferred":[
        "Cicarucub"
    ],
    "name:und_x_variant":[
        "Tjitjarutjup",
        "Cicarucup"
    ],
    "wof:lang_x_official":[
        "ind"
    ],
    "wof:lang_x_spoken":[
        "ind",
        "eng"
    ],
    "wof:name":"Cicarucub",
    "wof:placetype":"locality"
},
  "geometry": {"coordinates":[106.3567,-6.8227],"type":"Point"}
}