{
  "type": "Feature",
  "properties": {
    "gn:admin1_code":"33",
    "gn:asciiname":"Watestelu",
    "gn:country_code":"ID",
    "gn:dem":17,
    "gn:feature_class":"P",
    "gn:feature_code":"PPL",
    "gn:name":"Watestelu",
    "gn:population":0,
    "gn:timezone":"Asia/Jakarta",
    "iso:country":"ID",
    "name:ind_x_preferred":[
        "Watestelu"
    ],
    "wof:name":"Watestelu",
    "wof:placetype":"locality"
},
  "geometry": {"coordinates":[106.0534,-5.991],"type":"Point"}
}