{
  "type": "Feature",
  "properties": {
    "gn:admin1_code":"30",
    "gn:asciiname":"Cicadas Tiga",
    "gn:country_code":"ID",
    "gn:dem":241,
    "gn:feature_class":"P",
    "gn:feature_code":"PPL",
    "gn:name":"Cicadas Tiga",
    "gn:population":0,
    "gn:timezone":"Asia/Jakarta",
    "iso:country":"ID",
    "name:ind_x_preferred":[
        "Cicadas Tiga"
    ],
    "name:und_x_variant":[
        "Cicadas 3"
    ],
    "wof:name":"Cicadas Tiga",
    "wof:placetype":"locality"
},
  "geometry": {"coordinates":[106.68611,-6.58694],"type":"Point"}
}