{
  "type": "Feature",
  "properties": {
    "gn:admin1_code":"33.0",
    "gn:asciiname":"Cisekel",
    "gn:country_code":"ID",
    "gn:dem":398,
    "gn:feature_class":"P",
    "gn:feature_code":"PPL",
    "gn:name":"Cisekel",
    "gn:population":0,
    "gn:timezone":"Asia/Jakarta",
    "iso:country":"ID",
    "name:ind_x_preferred":[
        "Cisekel"
    ],
    "wof:name":"Cisekel",
    "wof:placetype":"locality"
},
  "geometry": {"coordinates":[106.1327,-6.6882],"type":"Point"}
}