{
  "type": "Feature",
  "properties": {
    "gn:admin1_code":"07",
    "gn:asciiname":"Sumberagung",
    "gn:country_code":"ID",
    "gn:dem":462,
    "gn:feature_class":"P",
    "gn:feature_code":"PPL",
    "gn:name":"Sumberagung",
    "gn:population":0,
    "gn:timezone":"Asia/Jakarta",
    "iso:country":"ID",
    "wof:name":"Sumberagung",
    "wof:placetype":"locality"
},
  "geometry": {"coordinates":[110.25388999999998,-7.39889],"type":"Point"}
}