{
  "type": "Feature",
  "properties": {
    "gn:country":"ID",
    "gn:fcode":"ADM4",
    "gn:pop":0,
    "iso:country":"ID",
    "name:ind_x_preferred":[
        "Desa Lingsar"
    ],
    "qs:name":"Desa Lingsar",
    "qs:photos_9r":0,
    "qs:photos_sr":0,
    "qs:pop_sr":"0",
    "wof:name":"Desa Lingsar",
    "wof:placetype":"localadmin",
    "wof:population":0
},
  "geometry": {"coordinates":[116.1705,-8.5787],"type":"Point"}
}