{
  "type": "Feature",
  "properties": {
    "gn:admin1_code":"8.0",
    "gn:asciiname":"Mentorkrajan",
    "gn:country_code":"ID",
    "gn:dem":26,
    "gn:feature_class":"P",
    "gn:feature_code":"PPL",
    "gn:name":"Mentorkrajan",
    "gn:population":0,
    "gn:timezone":"Asia/Jakarta",
    "iso:country":"ID",
    "name:ind_x_preferred":[
        "Mentorkrajan"
    ],
    "name:und_x_variant":[
        "Mentor"
    ],
    "wof:name":"Mentorkrajan",
    "wof:placetype":"locality"
},
  "geometry": {"coordinates":[113.15479999999999,-7.7661],"type":"Point"}
}