{
  "type": "Feature",
  "properties": {
    "gn:admin1_code":"17.0",
    "gn:asciiname":"Kekait Satu",
    "gn:country_code":"ID",
    "gn:dem":32,
    "gn:feature_class":"P",
    "gn:feature_code":"PPL",
    "gn:name":"Kekait Satu",
    "gn:population":0,
    "gn:timezone":"Asia/Makassar",
    "iso:country":"ID",
    "name:ind_x_preferred":[
        "Kekait Satu"
    ],
    "wof:name":"Kekait Satu",
    "wof:placetype":"locality"
},
  "geometry": {"coordinates":[116.1026,-8.5202],"type":"Point"}
}