{
  "type": "Feature",
  "properties": {
    "gn:admin1_code":"33.0",
    "gn:asciiname":"Kemancing",
    "gn:country_code":"ID",
    "gn:dem":83,
    "gn:feature_class":"P",
    "gn:feature_code":"PPLA4",
    "gn:name":"Kemancing",
    "gn:population":0,
    "gn:timezone":"Asia/Jakarta",
    "iso:country":"ID",
    "name:ind_x_preferred":[
        "Kemancing"
    ],
    "wof:lang_x_official":[
        "ind"
    ],
    "wof:lang_x_spoken":[
        "ind",
        "eng"
    ],
    "wof:name":"Kemancing",
    "wof:placetype":"locality"
},
  "geometry": {"coordinates":[106.2257,-6.5557],"type":"Point"}
}