{
  "type": "Feature",
  "properties": {
    "gn:admin1_code":"33.0",
    "gn:asciiname":"Paniis Tonggoh",
    "gn:country_code":"ID",
    "gn:dem":78,
    "gn:feature_class":"P",
    "gn:feature_code":"PPL",
    "gn:name":"Paniis Tonggoh",
    "gn:population":0,
    "gn:timezone":"Asia/Jakarta",
    "iso:country":"ID",
    "name:ind_x_preferred":[
        "Paniis Tonggoh"
    ],
    "wof:name":"Paniis Tonggoh",
    "wof:placetype":"locality"
},
  "geometry": {"coordinates":[105.8862,-6.3488],"type":"Point"}
}