{
  "type": "Feature",
  "properties": {
    "gn:country":"ID",
    "gn:fcode":"PPL",
    "gn:pop":0,
    "iso:country":"ID",
    "name:eng_x_preferred":[
        "Tanette"
    ],
    "name:ind_x_preferred":[
        "Tanette"
    ],
    "name:ind_x_variant":[
        "Kerajaan Tanette"
    ],
    "name:unk_x_variant":[
        "Tanete"
    ],
    "qs:name":"Tanette",
    "qs:name_adm0":"Indonesia",
    "qs:name_adm1":"Sulawesi Selatan",
    "qs:photos_9k":1,
    "qs:photos_9r":1,
    "qs:photos_all":1,
    "qs:photos_sr":0,
    "qs:placetype":"Town",
    "qs:pop_sr":"0",
    "wd:wordcount":159,
    "wof:lang_x_official":[
        "ind"
    ],
    "wof:lang_x_spoken":[
        "ind",
        "eng"
    ],
    "wof:name":"Tanette",
    "wof:placetype":"locality",
    "wof:population":0
},
  "geometry": {"coordinates":[120.1371,-5.3306],"type":"Point"}
}