{
  "type": "Feature",
  "properties": {
    "gn:admin1_code":"31.0",
    "gn:asciiname":"Tarianglama",
    "gn:country_code":"ID",
    "gn:dem":9,
    "gn:feature_class":"P",
    "gn:feature_code":"PPL",
    "gn:name":"Tarianglama",
    "gn:population":0,
    "gn:timezone":"Asia/Makassar",
    "iso:country":"ID",
    "name:ind_x_preferred":[
        "Tarianglama"
    ],
    "name:und_x_variant":[
        "Tariang"
    ],
    "wof:name":"Tarianglama",
    "wof:placetype":"locality"
},
  "geometry": {"coordinates":[125.41160000000001,3.7189],"type":"Point"}
}