{
  "type": "Feature",
  "properties": {
    "gn:admin1_code":"2",
    "gn:asciiname":"Banjar Batuh",
    "gn:country_code":"ID",
    "gn:dem":171,
    "gn:feature_class":"P",
    "gn:feature_code":"PPL",
    "gn:name":"Banjar Batuh",
    "gn:population":0,
    "gn:timezone":"Asia/Makassar",
    "iso:country":"ID",
    "name:ind_x_preferred":[
        "Banjar Batuh"
    ],
    "wof:name":"Banjar Batuh",
    "wof:placetype":"locality"
},
  "geometry": {"coordinates":[115.24160000000001,-8.5288],"type":"Point"}
}