{
  "type": "Feature",
  "properties": {
    "gn:admin1_code":"33.0",
    "gn:asciiname":"Cibatukuda",
    "gn:country_code":"ID",
    "gn:dem":105,
    "gn:feature_class":"P",
    "gn:feature_code":"PPL",
    "gn:name":"Cibatukuda",
    "gn:population":0,
    "gn:timezone":"Asia/Jakarta",
    "iso:country":"ID",
    "name:ind_x_preferred":[
        "Cibatukuda"
    ],
    "wof:name":"Cibatukuda",
    "wof:placetype":"locality"
},
  "geometry": {"coordinates":[105.9581,-6.4037],"type":"Point"}
}