{
  "type": "Feature",
  "properties": {
    "gn:admin1_code":"08",
    "gn:asciiname":"Kalisongo Satu",
    "gn:cc2":"ID",
    "gn:country_code":"ID",
    "gn:dem":498,
    "gn:feature_class":"P",
    "gn:feature_code":"PPL",
    "gn:name":"Kalisongo Satu",
    "gn:population":0,
    "gn:timezone":"Asia/Jakarta",
    "iso:country":"ID",
    "name:und_x_variant":[
        "Kalisongo 1",
        "Kalisongo Satu"
    ],
    "wof:lang_x_official":[
        "ind"
    ],
    "wof:lang_x_spoken":[
        "ind",
        "eng"
    ],
    "wof:name":"Kalisongo Satu",
    "wof:placetype":"locality"
},
  "geometry": {"coordinates":[112.59721999999999,-7.96917],"type":"Point"}
}