{
  "type": "Feature",
  "properties": {
    "gn:admin1_code":"0.0",
    "gn:asciiname":"Sungaibilut",
    "gn:country_code":"ID",
    "gn:dem":146,
    "gn:feature_class":"P",
    "gn:feature_code":"PPL",
    "gn:name":"Sungaibilut",
    "gn:population":0,
    "gn:timezone":"Asia/Jakarta",
    "iso:country":"ID",
    "name:ind_x_preferred":[
        "Sungaibilut"
    ],
    "wof:name":"Sungaibilut",
    "wof:placetype":"locality"
},
  "geometry": {"coordinates":[100.21991,0.6869],"type":"Point"}
}