{
  "type": "Feature",
  "properties": {
    "gn:admin1_code":"7",
    "gn:asciiname":"Tanggung",
    "gn:country_code":"ID",
    "gn:dem":451,
    "gn:feature_class":"P",
    "gn:feature_code":"PPL",
    "gn:name":"Tanggung",
    "gn:population":0,
    "gn:timezone":"Asia/Jakarta",
    "iso:country":"ID",
    "name:ind_x_preferred":[
        "Tanggung"
    ],
    "wof:name":"Tanggung",
    "wof:placetype":"locality"
},
  "geometry": {"coordinates":[111.11139,-7.53222],"type":"Point"}
}