{
  "type": "Feature",
  "properties": {
    "gn:admin1_code":"8.0",
    "gn:asciiname":"Lebaksari",
    "gn:country_code":"ID",
    "gn:dem":428,
    "gn:feature_class":"P",
    "gn:feature_code":"PPL",
    "gn:name":"Lebaksari",
    "gn:population":0,
    "gn:timezone":"Asia/Jakarta",
    "iso:country":"ID",
    "name:ind_x_preferred":[
        "Lebaksari"
    ],
    "wof:name":"Lebaksari",
    "wof:placetype":"locality"
},
  "geometry": {"coordinates":[112.43519999999999,-7.6612],"type":"Point"}
}