{
  "type": "Feature",
  "properties": {
    "gn:admin1_code":"2",
    "gn:asciiname":"Banjar Cagnan",
    "gn:country_code":"ID",
    "gn:dem":268,
    "gn:feature_class":"P",
    "gn:feature_code":"PPL",
    "gn:name":"Banjar Cagnan",
    "gn:population":0,
    "gn:timezone":"Asia/Makassar",
    "iso:country":"ID",
    "name:ind_x_preferred":[
        "Banjar Cagnan"
    ],
    "wof:name":"Banjar Cagnan",
    "wof:placetype":"locality"
},
  "geometry": {"coordinates":[115.2974,-8.4952],"type":"Point"}
}