{
  "type": "Feature",
  "properties": {
    "gn:admin1_code":"30.0",
    "gn:asciiname":"Balemoyan",
    "gn:country_code":"ID",
    "gn:dem":898,
    "gn:feature_class":"P",
    "gn:feature_code":"PPLA4",
    "gn:name":"Balemoyan",
    "gn:population":0,
    "gn:timezone":"Asia/Jakarta",
    "iso:country":"ID",
    "name:ind_x_preferred":[
        "Balemoyan"
    ],
    "wof:name":"Balemoyan",
    "wof:placetype":"locality"
},
  "geometry": {"coordinates":[107.9452,-7.3174],"type":"Point"}
}