{
  "type": "Feature",
  "properties": {
    "gn:admin1_code":"15.0",
    "gn:asciiname":"Pematangawi",
    "gn:country_code":"ID",
    "gn:dem":28,
    "gn:feature_class":"P",
    "gn:feature_code":"PPL",
    "gn:name":"Pematangawi",
    "gn:population":0,
    "gn:timezone":"Asia/Jakarta",
    "iso:country":"ID",
    "name:ind_x_preferred":[
        "Pematangawi"
    ],
    "wof:name":"Pematangawi",
    "wof:placetype":"locality"
},
  "geometry": {"coordinates":[105.16025999999999,-5.65813],"type":"Point"}
}