{
  "type": "Feature",
  "properties": {
    "gn:admin1_code":"7",
    "gn:asciiname":"Kendalduwur Tengah",
    "gn:country_code":"ID",
    "gn:dem":13,
    "gn:feature_class":"P",
    "gn:feature_code":"PPL",
    "gn:name":"Kendalduwur Tengah",
    "gn:population":0,
    "gn:timezone":"Asia/Jakarta",
    "iso:country":"ID",
    "name:ind_x_preferred":[
        "Kendalduwur Tengah"
    ],
    "wof:name":"Kendalduwur Tengah",
    "wof:placetype":"locality"
},
  "geometry": {"coordinates":[109.5384,-6.8921],"type":"Point"}
}