{
  "type": "Feature",
  "properties": {
    "gn:admin1_code":"30",
    "gn:asciiname":"Sekepeer",
    "gn:country_code":"ID",
    "gn:dem":748,
    "gn:feature_class":"P",
    "gn:feature_code":"PPL",
    "gn:name":"Sekepeer",
    "gn:population":0,
    "gn:timezone":"Asia/Jakarta",
    "iso:country":"ID",
    "name:ind_x_preferred":[
        "Sekepeer"
    ],
    "wof:name":"Sekepeer",
    "wof:placetype":"locality"
},
  "geometry": {"coordinates":[107.68583,-6.89722],"type":"Point"}
}