{
  "type": "Feature",
  "properties": {
    "gn:admin1_code":"33",
    "gn:asciiname":"Bandung Tengah",
    "gn:country_code":"ID",
    "gn:dem":56,
    "gn:feature_class":"P",
    "gn:feature_code":"PPL",
    "gn:name":"Bandung Tengah",
    "gn:population":0,
    "gn:timezone":"Asia/Jakarta",
    "iso:country":"ID",
    "name:ind_x_preferred":[
        "Bandung Tengah"
    ],
    "name:und_x_variant":[
        "Bandung 2",
        "Bandung Dua"
    ],
    "wof:lang_x_official":[
        "ind"
    ],
    "wof:lang_x_spoken":[
        "ind",
        "eng"
    ],
    "wof:name":"Bandung Tengah",
    "wof:placetype":"locality"
},
  "geometry": {"coordinates":[106.36409999999999,-6.3605],"type":"Point"}
}