{
  "type": "Feature",
  "properties": {
    "gn:admin1_code":"7.0",
    "gn:asciiname":"Gombong",
    "gn:country_code":"ID",
    "gn:dem":579,
    "gn:feature_class":"P",
    "gn:feature_code":"PPL",
    "gn:name":"Gombong",
    "gn:population":0,
    "gn:timezone":"Asia/Jakarta",
    "iso:country":"ID",
    "name:ara_x_preferred":[
        "\u063a\u0645\u0628\u0648\u0646\u063a"
    ],
    "name:ceb_x_preferred":[
        "Gombong"
    ],
    "name:ind_x_preferred":[
        "Gombong"
    ],
    "name:jav_x_preferred":[
        "Gombong"
    ],
    "name:mlg_x_preferred":[
        "Gombong"
    ],
    "name:nld_x_preferred":[
        "Gombong"
    ],
    "wof:lang_x_official":[
        "ind"
    ],
    "wof:lang_x_spoken":[
        "ind",
        "eng"
    ],
    "wof:name":"Gombong",
    "wof:placetype":"locality"
},
  "geometry": {"coordinates":[110.13972,-7.62556],"type":"Point"}
}