{
  "type": "Feature",
  "properties": {
    "gn:admin1_code":"7.0",
    "gn:asciiname":"Lebakwangi",
    "gn:country_code":"ID",
    "gn:dem":816,
    "gn:feature_class":"P",
    "gn:feature_code":"PPL",
    "gn:name":"Lebakwangi",
    "gn:population":0,
    "gn:timezone":"Asia/Jakarta",
    "iso:country":"ID",
    "name:ind_x_preferred":[
        "Lebakwangi"
    ],
    "wof:name":"Lebakwangi",
    "wof:placetype":"locality"
},
  "geometry": {"coordinates":[108.73,-7.161],"type":"Point"}
}