{
  "type": "Feature",
  "properties": {
    "gn:admin1_code":"30",
    "gn:asciiname":"Sukamelang",
    "gn:country_code":"ID",
    "gn:dem":12,
    "gn:feature_class":"P",
    "gn:feature_code":"PPL",
    "gn:name":"Sukamelang",
    "gn:population":0,
    "gn:timezone":"Asia/Jakarta",
    "iso:country":"ID",
    "name:ind_x_preferred":[
        "Sukamelang"
    ],
    "wof:name":"Sukamelang",
    "wof:placetype":"locality"
},
  "geometry": {"coordinates":[108.29583,-6.40944],"type":"Point"}
}