{
  "type": "Feature",
  "properties": {
    "gn:admin1_code":"30.0",
    "gn:asciiname":"Kamasan",
    "gn:country_code":"ID",
    "gn:dem":675,
    "gn:feature_class":"P",
    "gn:feature_code":"PPL",
    "gn:name":"Kamasan",
    "gn:population":0,
    "gn:timezone":"Asia/Jakarta",
    "iso:country":"ID",
    "wof:name":"Kamasan",
    "wof:placetype":"locality"
},
  "geometry": {"coordinates":[107.58333,-7.04806],"type":"Point"}
}