{
  "type": "Feature",
  "properties": {
    "gn:admin1_code":"8.0",
    "gn:asciiname":"Laok Lorong Dua",
    "gn:country_code":"ID",
    "gn:dem":21,
    "gn:feature_class":"P",
    "gn:feature_code":"PPL",
    "gn:name":"Laok Lorong Dua",
    "gn:population":0,
    "gn:timezone":"Asia/Jakarta",
    "iso:country":"ID",
    "name:ind_x_preferred":[
        "Laok Lorong Dua"
    ],
    "wof:name":"Laok Lorong Dua",
    "wof:placetype":"locality"
},
  "geometry": {"coordinates":[113.5801,-6.8951],"type":"Point"}
}