{
  "type": "Feature",
  "properties": {
    "gn:admin1_code":"38",
    "gn:asciiname":"Polewali",
    "gn:country_code":"ID",
    "gn:dem":13,
    "gn:feature_class":"P",
    "gn:feature_code":"PPL",
    "gn:name":"Polewali",
    "gn:population":0,
    "gn:timezone":"Asia/Makassar",
    "iso:country":"ID",
    "name:ceb_x_preferred":[
        "Polewali"
    ],
    "name:ind_x_preferred":[
        "Polewali"
    ],
    "name:jav_x_preferred":[
        "Polewali"
    ],
    "name:mlg_x_preferred":[
        "Polewali"
    ],
    "name:nld_x_preferred":[
        "Polewali"
    ],
    "name:pol_x_preferred":[
        "Polewali"
    ],
    "name:zho_x_preferred":[
        "\u6ce2\u91cc\u54c7\u5229"
    ],
    "wof:name":"Polewali",
    "wof:placetype":"locality"
},
  "geometry": {"coordinates":[119.57129999999999,-3.7554],"type":"Point"}
}