{
  "type": "Feature",
  "properties": {
    "gn:admin1_code":"8",
    "gn:asciiname":"Made",
    "gn:country_code":"ID",
    "gn:dem":417,
    "gn:feature_class":"P",
    "gn:feature_code":"PPL",
    "gn:name":"Made",
    "gn:population":0,
    "gn:timezone":"Asia/Jakarta",
    "iso:country":"ID",
    "name:ind_x_preferred":[
        "Made"
    ],
    "wof:name":"Made",
    "wof:placetype":"locality"
},
  "geometry": {"coordinates":[111.6129,-7.7425],"type":"Point"}
}