{
  "type": "Feature",
  "properties": {
    "gn:admin1_code":"8",
    "gn:asciiname":"Made",
    "gn:country_code":"ID",
    "gn:dem":417,
    "gn:feature_class":"P",
    "gn:feature_code":"PPL",
    "gn:name":"Made",
    "gn:population":0,
    "gn:timezone":"Asia/Jakarta",
    "iso:country":"ID",
    "name:ceb_x_preferred":[
        "Made"
    ],
    "name:deu_x_preferred":[
        "Made"
    ],
    "name:fra_x_preferred":[
        "Made"
    ],
    "name:fry_x_preferred":[
        "Miedl\u00e2n"
    ],
    "name:ind_x_preferred":[
        "Made"
    ],
    "name:ita_x_preferred":[
        "Made"
    ],
    "name:kor_x_preferred":[
        "Made"
    ],
    "name:kur_x_preferred":[
        "Made"
    ],
    "name:nld_x_preferred":[
        "Made"
    ],
    "name:por_x_preferred":[
        "Made"
    ],
    "name:swe_x_preferred":[
        "Made"
    ],
    "wof:lang_x_official":[
        "ind"
    ],
    "wof:lang_x_spoken":[
        "ind",
        "eng"
    ],
    "wof:name":"Made",
    "wof:placetype":"locality"
},
  "geometry": {"coordinates":[111.6129,-7.7425],"type":"Point"}
}