{
  "type": "Feature",
  "properties": {
    "gn:admin1_code":"8.0",
    "gn:asciiname":"Kiduljaten",
    "gn:country_code":"ID",
    "gn:dem":126,
    "gn:feature_class":"P",
    "gn:feature_code":"PPL",
    "gn:name":"Kiduljaten",
    "gn:population":0,
    "gn:timezone":"Asia/Jakarta",
    "iso:country":"ID",
    "name:ind_x_preferred":[
        "Kiduljaten"
    ],
    "wof:name":"Kiduljaten",
    "wof:placetype":"locality"
},
  "geometry": {"coordinates":[111.68940000000001,-8.1028],"type":"Point"}
}