{
  "type": "Feature",
  "properties": {
    "gn:admin1_code":"30",
    "gn:asciiname":"Blokwage",
    "gn:country_code":"ID",
    "gn:dem":143,
    "gn:feature_class":"P",
    "gn:feature_code":"PPL",
    "gn:name":"Blokwage",
    "gn:population":0,
    "gn:timezone":"Asia/Jakarta",
    "iso:country":"ID",
    "name:ind_x_preferred":[
        "Blokwage"
    ],
    "wof:name":"Blokwage",
    "wof:placetype":"locality"
},
  "geometry": {"coordinates":[108.31861000000001,-6.795],"type":"Point"}
}