{
  "type": "Feature",
  "properties": {
    "gn:admin1_code":"38",
    "gn:asciiname":"Pamanjengang",
    "gn:country_code":"ID",
    "gn:dem":142,
    "gn:feature_class":"P",
    "gn:feature_code":"PPL",
    "gn:name":"Pamanjengang",
    "gn:population":0,
    "gn:timezone":"Asia/Makassar",
    "iso:country":"ID",
    "name:ind_x_preferred":[
        "Pamanjengang"
    ],
    "wof:name":"Pamanjengang",
    "wof:placetype":"locality"
},
  "geometry": {"coordinates":[119.68170000000001,-5.2265],"type":"Point"}
}