{
  "type": "Feature",
  "properties": {
    "gn:admin1_code":"8.0",
    "gn:asciiname":"Puhti Dua",
    "gn:country_code":"ID",
    "gn:dem":69,
    "gn:feature_class":"P",
    "gn:feature_code":"PPL",
    "gn:name":"Puhti Dua",
    "gn:population":0,
    "gn:timezone":"Asia/Jakarta",
    "iso:country":"ID",
    "name:ind_x_preferred":[
        "Puhti Dua"
    ],
    "wof:name":"Puhti Dua",
    "wof:placetype":"locality"
},
  "geometry": {"coordinates":[111.6002,-7.4803],"type":"Point"}
}