{
  "type": "Feature",
  "properties": {
    "gn:admin1_code":"26",
    "gn:asciiname":"Tapianbagasan",
    "gn:country_code":"ID",
    "gn:dem":1021,
    "gn:feature_class":"P",
    "gn:feature_code":"PPL",
    "gn:name":"Tapianbagasan",
    "gn:population":0,
    "gn:timezone":"Asia/Jakarta",
    "iso:country":"ID",
    "name:ind_x_preferred":[
        "Tapianbagasan"
    ],
    "wof:name":"Tapianbagasan",
    "wof:placetype":"locality"
},
  "geometry": {"coordinates":[99.07680000000001,2.4925],"type":"Point"}
}