{
  "type": "Feature",
  "properties": {
    "gn:admin1_code":"7",
    "gn:asciiname":"Bulusari",
    "gn:country_code":"ID",
    "gn:dem":251,
    "gn:feature_class":"P",
    "gn:feature_code":"PPL",
    "gn:name":"Bulusari",
    "gn:population":0,
    "gn:timezone":"Asia/Jakarta",
    "iso:country":"ID",
    "name:ind_x_preferred":[
        "Bulusari"
    ],
    "wof:name":"Bulusari",
    "wof:placetype":"locality"
},
  "geometry": {"coordinates":[111.31083,-7.84972],"type":"Point"}
}