{
  "type": "Feature",
  "properties": {
    "gn:admin1_code":"26",
    "gn:asciiname":"Simpang Tiga Pekan",
    "gn:country_code":"ID",
    "gn:dem":16,
    "gn:feature_class":"P",
    "gn:feature_code":"PPL",
    "gn:name":"Simpang Tiga Pekan",
    "gn:population":0,
    "gn:timezone":"Asia/Jakarta",
    "iso:country":"ID",
    "name:ind_x_preferred":[
        "Simpang Tiga Pekan"
    ],
    "wof:name":"Simpang Tiga Pekan",
    "wof:placetype":"locality"
},
  "geometry": {"coordinates":[98.9597,3.5663],"type":"Point"}
}