{
  "type": "Feature",
  "properties": {
    "gn:admin1_code":"18.0",
    "gn:asciiname":"Noekele Tengah",
    "gn:country_code":"ID",
    "gn:dem":77,
    "gn:feature_class":"P",
    "gn:feature_code":"PPL",
    "gn:name":"Noekele Tengah",
    "gn:population":0,
    "gn:timezone":"Asia/Makassar",
    "iso:country":"ID",
    "name:ind_x_preferred":[
        "Noekele Tengah"
    ],
    "wof:name":"Noekele Tengah",
    "wof:placetype":"locality"
},
  "geometry": {"coordinates":[123.8463,-10.1675],"type":"Point"}
}