{
  "type": "Feature",
  "properties": {
    "gn:admin1_code":"30",
    "gn:asciiname":"Cikamuning Kulon",
    "gn:country_code":"ID",
    "gn:dem":633,
    "gn:feature_class":"P",
    "gn:feature_code":"PPL",
    "gn:name":"Cikamuning Kulon",
    "gn:population":0,
    "gn:timezone":"Asia/Jakarta",
    "iso:country":"ID",
    "name:ind_x_preferred":[
        "Cikamuning Kulon"
    ],
    "wof:name":"Cikamuning Kulon",
    "wof:placetype":"locality"
},
  "geometry": {"coordinates":[107.47556000000002,-6.81889],"type":"Point"}
}