{
  "type": "Feature",
  "properties": {
    "gn:admin1_code":"1",
    "gn:asciiname":"Cotmantuk",
    "gn:country_code":"ID",
    "gn:dem":6,
    "gn:feature_class":"P",
    "gn:feature_code":"PPL",
    "gn:name":"Cotmantuk",
    "gn:population":0,
    "gn:timezone":"Asia/Jakarta",
    "iso:country":"ID",
    "name:ind_x_preferred":[
        "Cotmantuk"
    ],
    "wof:name":"Cotmantuk",
    "wof:placetype":"locality"
},
  "geometry": {"coordinates":[96.3266,3.964],"type":"Point"}
}