{
  "type": "Feature",
  "properties": {
    "gn:admin1_code":"2",
    "gn:asciiname":"Banjar Karangsuung Kelod",
    "gn:country_code":"ID",
    "gn:dem":580,
    "gn:feature_class":"P",
    "gn:feature_code":"PPL",
    "gn:name":"Banjar Karangsuung Kelod",
    "gn:population":0,
    "gn:timezone":"Asia/Makassar",
    "iso:country":"ID",
    "name:ind_x_preferred":[
        "Banjar Karangsuung Kelod"
    ],
    "wof:name":"Banjar Karangsuung Kelod",
    "wof:placetype":"locality"
},
  "geometry": {"coordinates":[115.4037,-8.4176],"type":"Point"}
}