{
  "type": "Feature",
  "properties": {
    "gn:admin1_code":"7",
    "gn:asciiname":"Penjor",
    "gn:country_code":"ID",
    "gn:dem":9,
    "gn:feature_class":"P",
    "gn:feature_code":"PPL",
    "gn:name":"Penjor",
    "gn:population":0,
    "gn:timezone":"Asia/Jakarta",
    "iso:country":"ID",
    "name:ind_x_preferred":[
        "Penjor"
    ],
    "wof:name":"Penjor",
    "wof:placetype":"locality"
},
  "geometry": {"coordinates":[110.54000000000001,-6.9757],"type":"Point"}
}