{
  "type": "Feature",
  "properties": {
    "gn:admin1_code":"30",
    "gn:asciiname":"Segaran",
    "gn:country_code":"ID",
    "gn:dem":10,
    "gn:feature_class":"P",
    "gn:feature_code":"PPL",
    "gn:name":"Segaran",
    "gn:population":0,
    "gn:timezone":"Asia/Jakarta",
    "iso:country":"ID",
    "name:ind_x_preferred":[
        "Segaran"
    ],
    "name:und_x_variant":[
        "Segaran 1",
        "Segaran Satu"
    ],
    "wof:name":"Segaran",
    "wof:placetype":"locality"
},
  "geometry": {"coordinates":[107.14749999999999,-6.07028],"type":"Point"}
}