{
  "type": "Feature",
  "properties": {
    "gn:admin1_code":"07",
    "gn:asciiname":"Srimulyo Timur",
    "gn:country_code":"ID",
    "gn:dem":459,
    "gn:feature_class":"P",
    "gn:feature_code":"PPL",
    "gn:name":"Srimulyo Timur",
    "gn:population":0,
    "gn:timezone":"Asia/Jakarta",
    "iso:country":"ID",
    "wof:name":"Srimulyo Timur",
    "wof:placetype":"locality"
},
  "geometry": {"coordinates":[110.60722,-7.51806],"type":"Point"}
}