{
  "type": "Feature",
  "properties": {
    "gn:admin1_code":"18",
    "gn:asciiname":"Auhun",
    "gn:country_code":"ID",
    "gn:dem":785,
    "gn:feature_class":"P",
    "gn:feature_code":"PPL",
    "gn:name":"Auhun",
    "gn:population":0,
    "gn:timezone":"Asia/Makassar",
    "iso:country":"ID",
    "wof:name":"Auhun",
    "wof:placetype":"locality"
},
  "geometry": {"coordinates":[124.92361,-9.25583],"type":"Point"}
}