{
  "type": "Feature",
  "properties": {
    "gn:admin1_code":"8.0",
    "gn:asciiname":"Kalisepanjang",
    "gn:country_code":"ID",
    "gn:dem":334,
    "gn:feature_class":"P",
    "gn:feature_code":"PPL",
    "gn:name":"Kalisepanjang",
    "gn:population":0,
    "gn:timezone":"Asia/Jakarta",
    "iso:country":"ID",
    "name:ind_x_preferred":[
        "Kalisepanjang"
    ],
    "wof:name":"Kalisepanjang",
    "wof:placetype":"locality"
},
  "geometry": {"coordinates":[114.07769999999999,-8.299],"type":"Point"}
}