{
  "type": "Feature",
  "properties": {
    "gn:admin1_code":"2",
    "gn:asciiname":"Banjar Kusia",
    "gn:country_code":"ID",
    "gn:dem":358,
    "gn:feature_class":"P",
    "gn:feature_code":"PPL",
    "gn:name":"Banjar Kusia",
    "gn:population":0,
    "gn:timezone":"Asia/Makassar",
    "iso:country":"ID",
    "name:ind_x_preferred":[
        "Banjar Kusia"
    ],
    "wof:name":"Banjar Kusia",
    "wof:placetype":"locality"
},
  "geometry": {"coordinates":[115.17829999999999,-8.1556],"type":"Point"}
}