{
  "type": "Feature",
  "properties": {
    "gn:admin1_code":"7.0",
    "gn:asciiname":"Somoleterkrajan",
    "gn:country_code":"ID",
    "gn:dem":294,
    "gn:feature_class":"P",
    "gn:feature_code":"PPL",
    "gn:name":"Somoleterkrajan",
    "gn:population":0,
    "gn:timezone":"Asia/Jakarta",
    "iso:country":"ID",
    "name:ind_x_preferred":[
        "Somoleterkrajan"
    ],
    "name:und_x_variant":[
        "Sumoleter"
    ],
    "wof:lang_x_official":[
        "ind"
    ],
    "wof:lang_x_spoken":[
        "ind",
        "eng"
    ],
    "wof:name":"Somoleterkrajan",
    "wof:placetype":"locality"
},
  "geometry": {"coordinates":[109.97417,-7.57583],"type":"Point"}
}