{
  "type": "Feature",
  "properties": {
    "gn:country":"ID",
    "gn:fcode":"PPL",
    "gn:pop":0,
    "iso:country":"ID",
    "name:ceb_x_preferred":[
        "Kraton"
    ],
    "name:deu_x_preferred":[
        "Kraton"
    ],
    "name:ind_x_preferred":[
        "Kraton"
    ],
    "name:nds_x_preferred":[
        "Kraton"
    ],
    "name:nld_x_preferred":[
        "Kraton"
    ],
    "name:slk_x_preferred":[
        "Krat\u00f3n"
    ],
    "name:swe_x_preferred":[
        "Kraton"
    ],
    "name:ukr_x_preferred":[
        "\u041a\u0440\u0430\u0442\u043e\u043d"
    ],
    "qs:name":"Kraton",
    "qs:name_adm0":"Indonesia",
    "qs:name_adm1":"Jawa Timur",
    "qs:photos_9r":0,
    "qs:photos_sr":0,
    "qs:placetype":"Town",
    "qs:pop_sr":"0",
    "wd:wordcount":51,
    "wof:lang_x_official":[
        "ind"
    ],
    "wof:lang_x_spoken":[
        "ind",
        "eng"
    ],
    "wof:name":"Kraton",
    "wof:placetype":"locality",
    "wof:population":0
},
  "geometry": {"coordinates":[112.8785,-7.6271],"type":"Point"}
}