{
  "type": "Feature",
  "properties": {
    "gn:admin1_code":"30.0",
    "gn:asciiname":"Cibatu Kulon",
    "gn:country_code":"ID",
    "gn:dem":477,
    "gn:feature_class":"P",
    "gn:feature_code":"PPL",
    "gn:name":"Cibatu Kulon",
    "gn:population":0,
    "gn:timezone":"Asia/Jakarta",
    "iso:country":"ID",
    "name:ind_x_preferred":[
        "Cibatu Kulon"
    ],
    "wof:name":"Cibatu Kulon",
    "wof:placetype":"locality"
},
  "geometry": {"coordinates":[106.5455,-7.1735],"type":"Point"}
}