{
  "type": "Feature",
  "properties": {
    "gn:admin1_code":"30",
    "gn:asciiname":"Cisalak",
    "gn:country_code":"ID",
    "gn:dem":388,
    "gn:feature_class":"P",
    "gn:feature_code":"PPL",
    "gn:name":"Cisalak",
    "gn:population":0,
    "gn:timezone":"Asia/Jakarta",
    "iso:country":"ID",
    "name:ind_x_preferred":[
        "Cisalak"
    ],
    "wof:name":"Cisalak",
    "wof:placetype":"locality"
},
  "geometry": {"coordinates":[108.22306,-6.97139],"type":"Point"}
}