{
  "type": "Feature",
  "properties": {
    "gn:admin1_code":"40.0",
    "gn:asciiname":"Sungai Kolak",
    "gn:country_code":"ID",
    "gn:dem":26,
    "gn:feature_class":"P",
    "gn:feature_code":"PPL",
    "gn:name":"Sungai Kolak",
    "gn:population":0,
    "gn:timezone":"Asia/Jakarta",
    "iso:country":"ID",
    "name:und_x_variant":[
        "Soengeikolar",
        "Sungei Kolar",
        "Soengai Kolak",
        "Sungei Kolak",
        "Sungai Kolak"
    ],
    "wof:lang_x_official":[
        "ind"
    ],
    "wof:lang_x_spoken":[
        "ind",
        "eng"
    ],
    "wof:name":"Sungai Kolak",
    "wof:placetype":"locality"
},
  "geometry": {"coordinates":[104.59999999999999,0.85],"type":"Point"}
}