{
  "type": "Feature",
  "properties": {
    "gn:admin1_code":"38",
    "gn:asciiname":"Limbua",
    "gn:country_code":"ID",
    "gn:dem":396,
    "gn:feature_class":"P",
    "gn:feature_code":"PPL",
    "gn:name":"Limbua",
    "gn:population":0,
    "gn:timezone":"Asia/Makassar",
    "iso:country":"ID",
    "name:ind_x_preferred":[
        "Limbua"
    ],
    "wof:name":"Limbua",
    "wof:placetype":"locality"
},
  "geometry": {"coordinates":[119.7788,-5.2812],"type":"Point"}
}