{
  "type": "Feature",
  "properties": {
    "gn:admin1_code":"2.0",
    "gn:asciiname":"Bungankapa",
    "gn:country_code":"ID",
    "gn:dem":350,
    "gn:feature_class":"P",
    "gn:feature_code":"PPL",
    "gn:name":"Bungankapa",
    "gn:population":0,
    "gn:timezone":"Asia/Makassar",
    "iso:country":"ID",
    "name:ind_x_preferred":[
        "Bungankapa"
    ],
    "wof:name":"Bungankapa",
    "wof:placetype":"locality"
},
  "geometry": {"coordinates":[115.1559,-8.447],"type":"Point"}
}