{
  "type": "Feature",
  "properties": {
    "gn:admin1_code":"8.0",
    "gn:asciiname":"Sukomoro Utara",
    "gn:country_code":"ID",
    "gn:dem":216,
    "gn:feature_class":"P",
    "gn:feature_code":"PPL",
    "gn:name":"Sukomoro Utara",
    "gn:population":0,
    "gn:timezone":"Asia/Jakarta",
    "iso:country":"ID",
    "name:ind_x_preferred":[
        "Sukomoro Utara"
    ],
    "name:und_x_variant":[
        "Sukomoro"
    ],
    "wof:lang_x_official":[
        "ind"
    ],
    "wof:lang_x_spoken":[
        "ind",
        "eng"
    ],
    "wof:name":"Sukomoro Utara",
    "wof:placetype":"locality"
},
  "geometry": {"coordinates":[111.37166999999999,-7.63056],"type":"Point"}
}