{
  "type": "Feature",
  "properties": {
    "gn:admin1_code":"8.0",
    "gn:asciiname":"Gudang",
    "gn:country_code":"ID",
    "gn:dem":311,
    "gn:feature_class":"P",
    "gn:feature_code":"PPL",
    "gn:name":"Gudang",
    "gn:population":0,
    "gn:timezone":"Asia/Jakarta",
    "iso:country":"ID",
    "name:ind_x_preferred":[
        "Gudang"
    ],
    "wof:name":"Gudang",
    "wof:placetype":"locality"
},
  "geometry": {"coordinates":[114.0936,-8.3028],"type":"Point"}
}