{
  "type": "Feature",
  "properties": {
    "gn:admin1_code":"30",
    "gn:asciiname":"Durenseribuponcol",
    "gn:country_code":"ID",
    "gn:dem":116,
    "gn:feature_class":"P",
    "gn:feature_code":"PPL",
    "gn:name":"Durenseribuponcol",
    "gn:population":0,
    "gn:timezone":"Asia/Jakarta",
    "iso:country":"ID",
    "wof:name":"Durenseribuponcol",
    "wof:placetype":"locality"
},
  "geometry": {"coordinates":[106.74361,-6.44167],"type":"Point"}
}