{
  "type": "Feature",
  "properties": {
    "gn:admin1_code":"14.0",
    "gn:asciiname":"Labuhankelambu",
    "gn:country_code":"ID",
    "gn:dem":6,
    "gn:feature_class":"P",
    "gn:feature_code":"PPL",
    "gn:name":"Labuhankelambu",
    "gn:population":0,
    "gn:timezone":"Asia/Makassar",
    "iso:country":"ID",
    "name:ind_x_preferred":[
        "Labuhankelambu"
    ],
    "wof:name":"Labuhankelambu",
    "wof:placetype":"locality"
},
  "geometry": {"coordinates":[117.9716,0.7754],"type":"Point"}
}