{
  "type": "Feature",
  "properties": {
    "gn:admin1_code":"7.0",
    "gn:asciiname":"Siteki",
    "gn:country_code":"ID",
    "gn:dem":196,
    "gn:feature_class":"P",
    "gn:feature_code":"PPL",
    "gn:name":"Siteki",
    "gn:population":0,
    "gn:timezone":"Asia/Jakarta",
    "iso:country":"ID",
    "name:afr_x_preferred":[
        "Siteki"
    ],
    "name:ben_x_preferred":[
        "\u09b8\u09bf\u099f\u09c7\u0995\u09bf"
    ],
    "name:ceb_x_preferred":[
        "Siteki"
    ],
    "name:deu_x_preferred":[
        "Siteki"
    ],
    "name:fas_x_preferred":[
        "\u0633\u06cc\u062a\u06af\u06cc"
    ],
    "name:fra_x_preferred":[
        "Siteki"
    ],
    "name:frr_x_preferred":[
        "Siteki"
    ],
    "name:heb_x_preferred":[
        "\u05e1\u05d9\u05d8\u05e7\u05d9"
    ],
    "name:hin_x_preferred":[
        "\u0938\u093e\u0907\u091f\u0915\u0940"
    ],
    "name:hrv_x_preferred":[
        "Siteki"
    ],
    "name:hun_x_preferred":[
        "Siteki"
    ],
    "name:ind_x_preferred":[
        "Siteki"
    ],
    "name:ita_x_preferred":[
        "Siteki"
    ],
    "name:jpn_x_preferred":[
        "\u30b7\u30c6\u30ad"
    ],
    "name:kor_x_preferred":[
        "\uc2dc\ud14c\ud0a4"
    ],
    "name:lit_x_preferred":[
        "Sitekis"
    ],
    "name:nld_x_preferred":[
        "Siteki"
    ],
    "name:pol_x_preferred":[
        "Siteki"
    ],
    "name:por_x_preferred":[
        "Siteki"
    ],
    "name:ron_x_preferred":[
        "Siteki"
    ],
    "name:rus_x_preferred":[
        "\u0421\u0438\u0442\u0435\u043a\u0438"
    ],
    "name:spa_x_preferred":[
        "Siteki"
    ],
    "name:ssw_x_preferred":[
        "Siteki"
    ],
    "name:swe_x_preferred":[
        "Siteki"
    ],
    "name:tur_x_preferred":[
        "Siteki"
    ],
    "name:ukr_x_preferred":[
        "\u0421\u0456\u0442\u0435\u043a\u0456"
    ],
    "name:urd_x_preferred":[
        "\u0633\u06cc\u06a9\u06cc\u06a9\u06cc"
    ],
    "name:xmf_x_preferred":[
        "\u10e1\u10d8\u10e2\u10d4\u10d9\u10d8"
    ],
    "name:zho_x_preferred":[
        "\u932b\u6cf0\u57fa"
    ],
    "wof:lang_x_official":[
        "ind"
    ],
    "wof:lang_x_spoken":[
        "ind",
        "eng"
    ],
    "wof:name":"Siteki",
    "wof:placetype":"locality"
},
  "geometry": {"coordinates":[109.59639,-7.45444],"type":"Point"}
}