{
  "type": "Feature",
  "properties": {
    "gn:admin1_code":"7.0",
    "gn:asciiname":"Siteki",
    "gn:country_code":"ID",
    "gn:dem":196,
    "gn:feature_class":"P",
    "gn:feature_code":"PPL",
    "gn:name":"Siteki",
    "gn:population":0,
    "gn:timezone":"Asia/Jakarta",
    "iso:country":"ID",
    "name:afr_x_preferred":[
        "Siteki"
    ],
    "name:ceb_x_preferred":[
        "Siteki"
    ],
    "name:deu_x_preferred":[
        "Siteki"
    ],
    "name:fra_x_preferred":[
        "Siteki"
    ],
    "name:frr_x_preferred":[
        "Siteki"
    ],
    "name:hrv_x_preferred":[
        "Siteki"
    ],
    "name:ind_x_preferred":[
        "Siteki"
    ],
    "name:ita_x_preferred":[
        "Siteki"
    ],
    "name:jpn_x_preferred":[
        "\u30b7\u30c6\u30ad"
    ],
    "name:lit_x_preferred":[
        "Sitekis"
    ],
    "name:nld_x_preferred":[
        "Siteki"
    ],
    "name:pol_x_preferred":[
        "Siteki"
    ],
    "name:por_x_preferred":[
        "Siteki"
    ],
    "name:ron_x_preferred":[
        "Siteki"
    ],
    "name:rus_x_preferred":[
        "\u0421\u0438\u0442\u0435\u043a\u0438"
    ],
    "name:spa_x_preferred":[
        "Siteki"
    ],
    "name:ssw_x_preferred":[
        "Siteki"
    ],
    "name:swe_x_preferred":[
        "Siteki"
    ],
    "name:tur_x_preferred":[
        "Siteki"
    ],
    "name:urd_x_preferred":[
        "\u0633\u06cc\u06a9\u06cc\u06a9\u06cc"
    ],
    "name:xmf_x_preferred":[
        "\u10e1\u10d8\u10e2\u10d4\u10d9\u10d8"
    ],
    "name:zho_x_preferred":[
        "\u932b\u6cf0\u57fa"
    ],
    "wof:name":"Siteki",
    "wof:placetype":"locality"
},
  "geometry": {"coordinates":[109.59639,-7.45444],"type":"Point"}
}