{
  "type": "Feature",
  "properties": {
    "gn:admin1_code":"15.0",
    "gn:asciiname":"Umbulan Gunungcahya",
    "gn:country_code":"ID",
    "gn:dem":41,
    "gn:feature_class":"P",
    "gn:feature_code":"PPL",
    "gn:name":"Umbulan Gunungcahya",
    "gn:population":0,
    "gn:timezone":"Asia/Jakarta",
    "iso:country":"ID",
    "name:ind_x_preferred":[
        "Umbulan Gunungcahya"
    ],
    "name:ind_x_variant":[
        "Umbulangunungcahya"
    ],
    "wof:name":"Umbulan Gunungcahya",
    "wof:placetype":"locality"
},
  "geometry": {"coordinates":[105.2559,-4.3427],"type":"Point"}
}