{
  "type": "Feature",
  "properties": {
    "gn:admin1_code":"1",
    "gn:asciiname":"Selemak",
    "gn:country_code":"ID",
    "gn:dem":164,
    "gn:feature_class":"P",
    "gn:feature_code":"PPL",
    "gn:name":"Selemak",
    "gn:population":0,
    "gn:timezone":"Asia/Jakarta",
    "iso:country":"ID",
    "name:ind_x_preferred":[
        "Selemak"
    ],
    "wof:name":"Selemak",
    "wof:placetype":"locality"
},
  "geometry": {"coordinates":[97.5097,4.4881],"type":"Point"}
}