{
  "type": "Feature",
  "properties": {
    "gn:admin1_code":"26",
    "gn:asciiname":"Sitampurung Satu",
    "gn:country_code":"ID",
    "gn:dem":1304,
    "gn:feature_class":"P",
    "gn:feature_code":"PPL",
    "gn:name":"Sitampurung Satu",
    "gn:population":0,
    "gn:timezone":"Asia/Jakarta",
    "iso:country":"ID",
    "name:ind_x_preferred":[
        "Sitampurung Satu"
    ],
    "name:und_x_variant":[
        "Sitampurung 1"
    ],
    "wof:name":"Sitampurung Satu",
    "wof:placetype":"locality"
},
  "geometry": {"coordinates":[98.9432,2.2213],"type":"Point"}
}