{
  "type": "Feature",
  "properties": {
    "gn:admin1_code":"1",
    "gn:asciiname":"Blangbalig",
    "gn:country_code":"ID",
    "gn:dem":940,
    "gn:feature_class":"P",
    "gn:feature_code":"PPL",
    "gn:name":"Blangbalig",
    "gn:population":0,
    "gn:timezone":"Asia/Jakarta",
    "iso:country":"ID",
    "name:ind_x_preferred":[
        "Blangbalig"
    ],
    "wof:name":"Blangbalig",
    "wof:placetype":"locality"
},
  "geometry": {"coordinates":[96.733,4.7138],"type":"Point"}
}