{
  "type": "Feature",
  "properties": {
    "gn:admin1_code":"10",
    "gn:asciiname":"Sribitan",
    "gn:country_code":"ID",
    "gn:dem":107,
    "gn:feature_class":"P",
    "gn:feature_code":"PPL",
    "gn:name":"Sribitan",
    "gn:population":0,
    "gn:timezone":"Asia/Jakarta",
    "iso:country":"ID",
    "wof:name":"Sribitan",
    "wof:placetype":"locality"
},
  "geometry": {"coordinates":[110.30110999999999,-7.83917],"type":"Point"}
}