{
  "type": "Feature",
  "properties": {
    "gn:admin1_code":"33",
    "gn:asciiname":"Sigedug",
    "gn:country_code":"ID",
    "gn:dem":108,
    "gn:feature_class":"P",
    "gn:feature_code":"PPL",
    "gn:name":"Sigedug",
    "gn:population":0,
    "gn:timezone":"Asia/Jakarta",
    "iso:country":"ID",
    "name:ind_x_preferred":[
        "Sigedug"
    ],
    "wof:name":"Sigedug",
    "wof:placetype":"locality"
},
  "geometry": {"coordinates":[106.0562,-6.1118],"type":"Point"}
}