{
  "type": "Feature",
  "properties": {
    "gn:admin1_code":"26",
    "gn:asciiname":"Polet",
    "gn:country_code":"ID",
    "gn:dem":487,
    "gn:feature_class":"P",
    "gn:feature_code":"PPL",
    "gn:name":"Polet",
    "gn:population":0,
    "gn:timezone":"Asia/Jakarta",
    "iso:country":"ID",
    "name:fra_x_preferred":[
        "Polet"
    ],
    "name:ind_x_preferred":[
        "Polet"
    ],
    "name:nld_x_preferred":[
        "Polet"
    ],
    "wof:name":"Polet",
    "wof:placetype":"locality"
},
  "geometry": {"coordinates":[98.2282,2.6617],"type":"Point"}
}