{
  "type": "Feature",
  "properties": {
    "gn:admin1_code":"30.0",
    "gn:asciiname":"Lengkongbarang",
    "gn:country_code":"ID",
    "gn:dem":282,
    "gn:feature_class":"P",
    "gn:feature_code":"PPLA4",
    "gn:name":"Lengkongbarang",
    "gn:population":0,
    "gn:timezone":"Asia/Jakarta",
    "iso:country":"ID",
    "name:ind_x_preferred":[
        "Lengkongbarang"
    ],
    "wof:name":"Lengkongbarang",
    "wof:placetype":"locality"
},
  "geometry": {"coordinates":[108.2814,-7.5712],"type":"Point"}
}