{
  "type": "Feature",
  "properties": {
    "gn:admin1_code":"30",
    "gn:asciiname":"Pasirseureuh",
    "gn:country_code":"ID",
    "gn:dem":324,
    "gn:feature_class":"P",
    "gn:feature_code":"PPL",
    "gn:name":"Pasirseureuh",
    "gn:population":0,
    "gn:timezone":"Asia/Jakarta",
    "iso:country":"ID",
    "name:ind_x_preferred":[
        "Pasirseureuh"
    ],
    "wof:name":"Pasirseureuh",
    "wof:placetype":"locality"
},
  "geometry": {"coordinates":[107.29443999999999,-6.68083],"type":"Point"}
}