{
  "type": "Feature",
  "properties": {
    "gn:admin1_code":"30",
    "gn:asciiname":"Cidepong Dua",
    "gn:country_code":"ID",
    "gn:dem":593,
    "gn:feature_class":"P",
    "gn:feature_code":"PPL",
    "gn:name":"Cidepong Dua",
    "gn:population":0,
    "gn:timezone":"Asia/Jakarta",
    "iso:country":"ID",
    "name:ind_x_preferred":[
        "Cidepong Dua"
    ],
    "name:und_x_variant":[
        "Tjidepong",
        "Cidepong"
    ],
    "wof:name":"Cidepong Dua",
    "wof:placetype":"locality"
},
  "geometry": {"coordinates":[107.41916999999999,-6.78306],"type":"Point"}
}