{
  "type": "Feature",
  "properties": {
    "gn:admin1_code":"42",
    "gn:asciiname":"Temalang",
    "gn:country_code":"ID",
    "gn:dem":178,
    "gn:feature_class":"P",
    "gn:feature_code":"PPL",
    "gn:name":"Temalang",
    "gn:population":0,
    "gn:timezone":"Asia/Makassar",
    "iso:country":"ID",
    "name:ind_x_preferred":[
        "Temalang"
    ],
    "name:ind_x_variant":[
        "Kampoeng Sawen Kiri"
    ],
    "wof:name":"Temalang",
    "wof:placetype":"locality"
},
  "geometry": {"coordinates":[116.18308,3.7796],"type":"Point"}
}