{
  "type": "Feature",
  "properties": {
    "gn:admin1_code":"2.0",
    "gn:asciiname":"Angas",
    "gn:country_code":"ID",
    "gn:dem":227,
    "gn:feature_class":"P",
    "gn:feature_code":"PPL",
    "gn:name":"Angas",
    "gn:population":0,
    "gn:timezone":"Asia/Makassar",
    "iso:country":"ID",
    "name:deu_x_preferred":[
        "Angas"
    ],
    "name:fra_x_preferred":[
        "Angas"
    ],
    "name:ind_x_preferred":[
        "Angas"
    ],
    "wof:lang_x_official":[
        "ind"
    ],
    "wof:lang_x_spoken":[
        "ind",
        "eng"
    ],
    "wof:name":"Angas",
    "wof:placetype":"locality"
},
  "geometry": {"coordinates":[115.5159,-8.7218],"type":"Point"}
}