{
  "type": "Feature",
  "properties": {
    "gn:admin1_code":"36.0",
    "gn:asciiname":"Sarire",
    "gn:country_code":"ID",
    "gn:dem":8,
    "gn:feature_class":"P",
    "gn:feature_code":"PPL",
    "gn:name":"Sarire",
    "gn:population":0,
    "gn:timezone":"Asia/Jayapura",
    "iso:country":"ID",
    "name:ind_x_preferred":[
        "Sarire"
    ],
    "wof:name":"Sarire",
    "wof:placetype":"locality"
},
  "geometry": {"coordinates":[140.50247999999999,-8.60469],"type":"Point"}
}