{
  "type": "Feature",
  "properties": {
    "gn:admin1_code":"30.0",
    "gn:asciiname":"Baruwan",
    "gn:country_code":"ID",
    "gn:dem":138,
    "gn:feature_class":"P",
    "gn:feature_code":"PPL",
    "gn:name":"Baruwan",
    "gn:population":0,
    "gn:timezone":"Asia/Jakarta",
    "iso:country":"ID",
    "name:ind_x_preferred":[
        "Baruwan"
    ],
    "wof:name":"Baruwan",
    "wof:placetype":"locality"
},
  "geometry": {"coordinates":[106.66200000000001,-7.3588],"type":"Point"}
}