{
  "type": "Feature",
  "properties": {
    "gn:admin1_code":"30",
    "gn:asciiname":"Griyamas",
    "gn:country_code":"ID",
    "gn:dem":773,
    "gn:feature_class":"P",
    "gn:feature_code":"PPL",
    "gn:name":"Griyamas",
    "gn:population":0,
    "gn:timezone":"Asia/Jakarta",
    "iso:country":"ID",
    "name:ind_x_preferred":[
        "Griyamas"
    ],
    "wof:name":"Griyamas",
    "wof:placetype":"locality"
},
  "geometry": {"coordinates":[107.57639,-6.88694],"type":"Point"}
}