{
  "type": "Feature",
  "properties": {
    "gn:admin1_code":"17",
    "gn:asciiname":"Rupe",
    "gn:country_code":"ID",
    "gn:dem":36,
    "gn:feature_class":"P",
    "gn:feature_code":"PPLA4",
    "gn:name":"Rupe",
    "gn:population":0,
    "gn:timezone":"Asia/Makassar",
    "iso:country":"ID",
    "name:ind_x_preferred":[
        "Rupe"
    ],
    "wof:name":"Rupe",
    "wof:placetype":"locality"
},
  "geometry": {"coordinates":[118.83839999999999,-8.6953],"type":"Point"}
}