{
  "type": "Feature",
  "properties": {
    "gn:admin1_code":"7.0",
    "gn:asciiname":"Timang Kulon",
    "gn:country_code":"ID",
    "gn:dem":142,
    "gn:feature_class":"P",
    "gn:feature_code":"PPL",
    "gn:name":"Timang Kulon",
    "gn:population":0,
    "gn:timezone":"Asia/Jakarta",
    "iso:country":"ID",
    "wof:name":"Timang Kulon",
    "wof:placetype":"locality"
},
  "geometry": {"coordinates":[110.93917,-7.7775],"type":"Point"}
}