{
  "type": "Feature",
  "properties": {
    "gn:admin1_code":"30",
    "gn:asciiname":"Rancabentang",
    "gn:country_code":"ID",
    "gn:dem":341,
    "gn:feature_class":"P",
    "gn:feature_code":"PPL",
    "gn:name":"Rancabentang",
    "gn:population":0,
    "gn:timezone":"Asia/Jakarta",
    "iso:country":"ID",
    "name:ind_x_preferred":[
        "Rancabentang"
    ],
    "name:und_x_variant":[
        "Rantjabaeud",
        "Rancabaeud"
    ],
    "wof:lang_x_official":[
        "ind"
    ],
    "wof:lang_x_spoken":[
        "ind",
        "eng"
    ],
    "wof:name":"Rancabentang",
    "wof:placetype":"locality"
},
  "geometry": {"coordinates":[107.35778000000001,-6.82333],"type":"Point"}
}