{
  "type": "Feature",
  "properties": {
    "gn:admin1_code":"17.0",
    "gn:asciiname":"Pisang",
    "gn:country_code":"ID",
    "gn:dem":27,
    "gn:feature_class":"P",
    "gn:feature_code":"PPLA4",
    "gn:name":"Pisang",
    "gn:population":0,
    "gn:timezone":"Asia/Makassar",
    "iso:country":"ID",
    "name:ceb_x_preferred":[
        "Pisang"
    ],
    "name:deu_x_preferred":[
        "Pisang"
    ],
    "name:fra_x_preferred":[
        "Pisang"
    ],
    "name:ind_x_preferred":[
        "Pisang"
    ],
    "name:mai_x_preferred":[
        "\u092a\u093f\u0938\u093e\u0919"
    ],
    "name:msa_x_preferred":[
        "Pisang"
    ],
    "name:nep_x_preferred":[
        "\u092a\u093f\u0938\u093e\u0919"
    ],
    "name:new_x_preferred":[
        "\u092a\u093f\u0938\u093e\u0919"
    ],
    "name:pol_x_preferred":[
        "Pisang"
    ],
    "name:rus_x_preferred":[
        "\u041f\u0438\u0441\u0430\u043d\u0433"
    ],
    "wof:name":"Pisang",
    "wof:placetype":"locality"
},
  "geometry": {"coordinates":[118.7574,-8.47],"type":"Point"}
}