{
  "type": "Feature",
  "properties": {
    "gn:admin1_code":"30.0",
    "gn:asciiname":"Taritih",
    "gn:country_code":"ID",
    "gn:dem":360,
    "gn:feature_class":"P",
    "gn:feature_code":"PPL",
    "gn:name":"Taritih",
    "gn:population":0,
    "gn:timezone":"Asia/Jakarta",
    "iso:country":"ID",
    "name:ind_x_preferred":[
        "Taritih"
    ],
    "wof:name":"Taritih",
    "wof:placetype":"locality"
},
  "geometry": {"coordinates":[108.12269999999999,-7.4585],"type":"Point"}
}