{
  "type": "Feature",
  "properties": {
    "gn:admin1_code":"22",
    "gn:asciiname":"Linonggasai",
    "gn:country_code":"ID",
    "gn:dem":28,
    "gn:feature_class":"P",
    "gn:feature_code":"PPL",
    "gn:name":"Linonggasai",
    "gn:population":0,
    "gn:timezone":"Asia/Makassar",
    "iso:country":"ID",
    "name:ind_x_preferred":[
        "Linonggasai"
    ],
    "name:und_x_variant":[
        "Linonggasi"
    ],
    "wof:name":"Linonggasai",
    "wof:placetype":"locality"
},
  "geometry": {"coordinates":[122.1356,-3.964],"type":"Point"}
}