{
  "type": "Feature",
  "properties": {
    "gn:admin1_code":"7.0",
    "gn:asciiname":"Saminan",
    "gn:country_code":"ID",
    "gn:dem":157,
    "gn:feature_class":"P",
    "gn:feature_code":"PPL",
    "gn:name":"Saminan",
    "gn:population":0,
    "gn:timezone":"Asia/Jakarta",
    "iso:country":"ID",
    "wof:name":"Saminan",
    "wof:placetype":"locality"
},
  "geometry": {"coordinates":[110.70583000000001,-7.51222],"type":"Point"}
}