{
  "type": "Feature",
  "properties": {
    "gn:admin1_code":"30",
    "gn:asciiname":"Sindanglaya",
    "gn:country_code":"ID",
    "gn:dem":646,
    "gn:feature_class":"P",
    "gn:feature_code":"PPL",
    "gn:name":"Sindanglaya",
    "gn:population":0,
    "gn:timezone":"Asia/Jakarta",
    "iso:country":"ID",
    "name:ind_x_preferred":[
        "Sindanglaya"
    ],
    "wof:name":"Sindanglaya",
    "wof:placetype":"locality"
},
  "geometry": {"coordinates":[107.07028,-6.86389],"type":"Point"}
}