{
  "type": "Feature",
  "properties": {
    "gn:admin1_code":"15.0",
    "gn:asciiname":"Umbulancapangkanan",
    "gn:country_code":"ID",
    "gn:dem":35,
    "gn:feature_class":"P",
    "gn:feature_code":"PPL",
    "gn:name":"Umbulancapangkanan",
    "gn:population":0,
    "gn:timezone":"Asia/Jakarta",
    "iso:country":"ID",
    "name:ind_x_preferred":[
        "Umbulancapangkanan"
    ],
    "wof:name":"Umbulancapangkanan",
    "wof:placetype":"locality"
},
  "geometry": {"coordinates":[105.11485,-4.76526],"type":"Point"}
}