{
  "type": "Feature",
  "properties": {
    "gn:admin1_code":"8",
    "gn:asciiname":"Kedungbanteng Tengah",
    "gn:country_code":"ID",
    "gn:dem":44,
    "gn:feature_class":"P",
    "gn:feature_code":"PPL",
    "gn:name":"Kedungbanteng Tengah",
    "gn:population":0,
    "gn:timezone":"Asia/Jakarta",
    "iso:country":"ID",
    "name:ind_x_preferred":[
        "Kedungbanteng Tengah"
    ],
    "wof:name":"Kedungbanteng Tengah",
    "wof:placetype":"locality"
},
  "geometry": {"coordinates":[112.7839,-7.6439],"type":"Point"}
}