{
  "type": "Feature",
  "properties": {
    "gn:admin1_code":"8",
    "gn:asciiname":"Semanding",
    "gn:country_code":"ID",
    "gn:dem":11,
    "gn:feature_class":"P",
    "gn:feature_code":"PPL",
    "gn:name":"Semanding",
    "gn:population":0,
    "gn:timezone":"Asia/Jakarta",
    "iso:country":"ID",
    "name:ind_x_preferred":[
        "Semanding"
    ],
    "wof:name":"Semanding",
    "wof:placetype":"locality"
},
  "geometry": {"coordinates":[112.4216,-7.1711],"type":"Point"}
}