{
  "type": "Feature",
  "properties": {
    "gn:admin1_code":"30.0",
    "gn:asciiname":"Cikeupeul",
    "gn:country_code":"ID",
    "gn:dem":553,
    "gn:feature_class":"P",
    "gn:feature_code":"PPL",
    "gn:name":"Cikeupeul",
    "gn:population":0,
    "gn:timezone":"Asia/Jakarta",
    "iso:country":"ID",
    "name:ind_x_preferred":[
        "Cikeupeul"
    ],
    "name:und_x_variant":[
        "Tjikeupeul"
    ],
    "wof:lang_x_official":[
        "ind"
    ],
    "wof:lang_x_spoken":[
        "ind",
        "eng"
    ],
    "wof:name":"Cikeupeul",
    "wof:placetype":"locality"
},
  "geometry": {"coordinates":[108.05370000000001,-7.3258],"type":"Point"}
}