{
  "type": "Feature",
  "properties": {
    "gn:admin1_code":"8.0",
    "gn:asciiname":"Gedangsewu",
    "gn:country_code":"ID",
    "gn:dem":88,
    "gn:feature_class":"P",
    "gn:feature_code":"PPL",
    "gn:name":"Gedangsewu",
    "gn:population":0,
    "gn:timezone":"Asia/Jakarta",
    "iso:country":"ID",
    "name:ind_x_preferred":[
        "Gedangsewu"
    ],
    "wof:name":"Gedangsewu",
    "wof:placetype":"locality"
},
  "geometry": {"coordinates":[111.88209999999999,-8.1445],"type":"Point"}
}