{
  "type": "Feature",
  "properties": {
    "gn:admin1_code":"22.0",
    "gn:asciiname":"Napa",
    "gn:country_code":"ID",
    "gn:dem":14,
    "gn:feature_class":"P",
    "gn:feature_code":"PPL",
    "gn:name":"Napa",
    "gn:population":0,
    "gn:timezone":"Asia/Makassar",
    "iso:country":"ID",
    "name:bul_x_preferred":[
        "\u041d\u0430\u043f\u0430"
    ],
    "name:cat_x_preferred":[
        "Napa"
    ],
    "name:ceb_x_preferred":[
        "Napa"
    ],
    "name:fin_x_preferred":[
        "Napa"
    ],
    "name:fra_x_preferred":[
        "Napa"
    ],
    "name:heb_x_preferred":[
        "\u05e0\u05d0\u05e4\u05d4"
    ],
    "name:hrv_x_preferred":[
        "Napa"
    ],
    "name:hun_x_preferred":[
        "Napa"
    ],
    "name:ind_x_preferred":[
        "Napa"
    ],
    "name:ita_x_preferred":[
        "Napa"
    ],
    "name:nld_x_preferred":[
        "Napa"
    ],
    "name:pol_x_preferred":[
        "Napa"
    ],
    "name:por_x_preferred":[
        "Napa"
    ],
    "name:rus_x_preferred":[
        "\u041d\u0430\u043f\u0430"
    ],
    "name:srp_x_preferred":[
        "\u041d\u0430\u043f\u0430"
    ],
    "name:swe_x_preferred":[
        "Napa"
    ],
    "name:ukr_x_preferred":[
        "\u041d\u0430\u043f\u0430"
    ],
    "wof:lang_x_official":[
        "ind"
    ],
    "wof:lang_x_spoken":[
        "ind",
        "eng"
    ],
    "wof:name":"Napa",
    "wof:placetype":"locality"
},
  "geometry": {"coordinates":[122.44110000000001,-5.0797],"type":"Point"}
}