{
  "type": "Feature",
  "properties": {
    "gn:admin1_code":"22.0",
    "gn:asciiname":"Napa",
    "gn:country_code":"ID",
    "gn:dem":14,
    "gn:feature_class":"P",
    "gn:feature_code":"PPL",
    "gn:name":"Napa",
    "gn:population":0,
    "gn:timezone":"Asia/Makassar",
    "iso:country":"ID",
    "name:ind_x_preferred":[
        "Napa"
    ],
    "wof:name":"Napa",
    "wof:placetype":"locality"
},
  "geometry": {"coordinates":[122.44110000000001,-5.0797],"type":"Point"}
}