{
  "type": "Feature",
  "properties": {
    "gn:admin1_code":"1",
    "gn:asciiname":"Kareung Puteh",
    "gn:country_code":"ID",
    "gn:dem":32,
    "gn:feature_class":"P",
    "gn:feature_code":"PPL",
    "gn:name":"Kareung Puteh",
    "gn:population":0,
    "gn:timezone":"Asia/Jakarta",
    "iso:country":"ID",
    "name:ind_x_preferred":[
        "Kareung Puteh"
    ],
    "wof:name":"Kareung Puteh",
    "wof:placetype":"locality"
},
  "geometry": {"coordinates":[96.5376,3.9698],"type":"Point"}
}