{
  "type": "Feature",
  "properties": {
    "gn:admin1_code":"30",
    "gn:asciiname":"Sidamukti",
    "gn:country_code":"ID",
    "gn:dem":1396,
    "gn:feature_class":"P",
    "gn:feature_code":"PPL",
    "gn:name":"Sidamukti",
    "gn:population":0,
    "gn:timezone":"Asia/Jakarta",
    "iso:country":"ID",
    "wof:name":"Sidamukti",
    "wof:placetype":"locality"
},
  "geometry": {"coordinates":[107.57083,-7.17861],"type":"Point"}
}