{
  "type": "Feature",
  "properties": {
    "gn:admin1_code":"7",
    "gn:asciiname":"Siberuk",
    "gn:country_code":"ID",
    "gn:dem":632,
    "gn:feature_class":"P",
    "gn:feature_code":"PPL",
    "gn:name":"Siberuk",
    "gn:population":0,
    "gn:timezone":"Asia/Jakarta",
    "iso:country":"ID",
    "name:ind_x_preferred":[
        "Siberuk"
    ],
    "wof:name":"Siberuk",
    "wof:placetype":"locality"
},
  "geometry": {"coordinates":[110.87690000000001,-6.6719],"type":"Point"}
}