{
  "type": "Feature",
  "properties": {
    "gn:admin1_code":"7",
    "gn:asciiname":"Rondongungak",
    "gn:country_code":"ID",
    "gn:dem":236,
    "gn:feature_class":"P",
    "gn:feature_code":"PPL",
    "gn:name":"Rondongungak",
    "gn:population":0,
    "gn:timezone":"Asia/Jakarta",
    "iso:country":"ID",
    "name:ind_x_preferred":[
        "Rondongungak"
    ],
    "wof:name":"Rondongungak",
    "wof:placetype":"locality"
},
  "geometry": {"coordinates":[109.6799,-7.0458],"type":"Point"}
}