{
  "type": "Feature",
  "properties": {
    "gn:admin1_code":"33.0",
    "gn:asciiname":"Sampangjaha",
    "gn:country_code":"ID",
    "gn:dem":119,
    "gn:feature_class":"P",
    "gn:feature_code":"PPL",
    "gn:name":"Sampangjaha",
    "gn:population":0,
    "gn:timezone":"Asia/Jakarta",
    "iso:country":"ID",
    "name:ind_x_preferred":[
        "Sampangjaha"
    ],
    "wof:name":"Sampangjaha",
    "wof:placetype":"locality"
},
  "geometry": {"coordinates":[105.8946,-6.6442],"type":"Point"}
}