{
  "type": "Feature",
  "properties": {
    "gn:admin1_code":"1",
    "gn:asciiname":"Tanjung Selamat",
    "gn:country_code":"ID",
    "gn:dem":14,
    "gn:feature_class":"P",
    "gn:feature_code":"PPL",
    "gn:name":"Tanjung Selamat",
    "gn:population":0,
    "gn:timezone":"Asia/Jakarta",
    "iso:country":"ID",
    "name:ind_x_preferred":[
        "Tanjung Selamat"
    ],
    "wof:name":"Tanjung Selamat",
    "wof:placetype":"locality"
},
  "geometry": {"coordinates":[97.48009999999999,4.9725],"type":"Point"}
}