{
  "type": "Feature",
  "properties": {
    "gn:admin1_code":"2",
    "gn:asciiname":"Angkahgede",
    "gn:country_code":"ID",
    "gn:dem":281,
    "gn:feature_class":"P",
    "gn:feature_code":"PPLA4",
    "gn:name":"Angkahgede",
    "gn:population":0,
    "gn:timezone":"Asia/Makassar",
    "iso:country":"ID",
    "name:ind_x_preferred":[
        "Angkahgede"
    ],
    "wof:lang_x_official":[
        "ind"
    ],
    "wof:lang_x_spoken":[
        "ind",
        "eng"
    ],
    "wof:name":"Angkahgede",
    "wof:placetype":"locality"
},
  "geometry": {"coordinates":[115.0159,-8.4635],"type":"Point"}
}