{
  "type": "Feature",
  "properties": {
    "gn:admin1_code":"30",
    "gn:asciiname":"Samoja",
    "gn:country_code":"ID",
    "gn:dem":524,
    "gn:feature_class":"P",
    "gn:feature_code":"PPL",
    "gn:name":"Samoja",
    "gn:population":0,
    "gn:timezone":"Asia/Jakarta",
    "iso:country":"ID",
    "name:ind_x_preferred":[
        "Samoja"
    ],
    "wof:name":"Samoja",
    "wof:placetype":"locality"
},
  "geometry": {"coordinates":[107.10361,-6.86361],"type":"Point"}
}