{
  "type": "Feature",
  "properties": {
    "gn:admin1_code":"32.0",
    "gn:asciiname":"Baru",
    "gn:country_code":"ID",
    "gn:dem":752,
    "gn:feature_class":"P",
    "gn:feature_code":"PPL",
    "gn:name":"Baru",
    "gn:population":0,
    "gn:timezone":"Asia/Jakarta",
    "iso:country":"ID",
    "name:ind_x_preferred":[
        "Baru"
    ],
    "wof:name":"Baru",
    "wof:placetype":"locality"
},
  "geometry": {"coordinates":[103.2574,-3.997],"type":"Point"}
}