{
  "type": "Feature",
  "properties": {
    "gn:admin1_code":"26",
    "gn:asciiname":"Lumban Sandaran",
    "gn:country_code":"ID",
    "gn:dem":1432,
    "gn:feature_class":"P",
    "gn:feature_code":"PPL",
    "gn:name":"Lumban Sandaran",
    "gn:population":0,
    "gn:timezone":"Asia/Jakarta",
    "iso:country":"ID",
    "name:ind_x_preferred":[
        "Lumban Sandaran"
    ],
    "wof:lang_x_official":[
        "ind"
    ],
    "wof:lang_x_spoken":[
        "ind",
        "eng"
    ],
    "wof:name":"Lumban Sandaran",
    "wof:placetype":"locality"
},
  "geometry": {"coordinates":[98.7568,2.2842],"type":"Point"}
}