{
  "type": "Feature",
  "properties": {
    "gn:admin1_code":"8",
    "gn:asciiname":"Mojodungkol",
    "gn:country_code":"ID",
    "gn:dem":156,
    "gn:feature_class":"P",
    "gn:feature_code":"PPL",
    "gn:name":"Mojodungkol",
    "gn:population":0,
    "gn:timezone":"Asia/Jakarta",
    "iso:country":"ID",
    "name:ind_x_preferred":[
        "Mojodungkol"
    ],
    "wof:name":"Mojodungkol",
    "wof:placetype":"locality"
},
  "geometry": {"coordinates":[113.7317,-7.7947],"type":"Point"}
}