{
  "type": "Feature",
  "properties": {
    "gn:admin1_code":"2.0",
    "gn:asciiname":"Batumulapan Kauh",
    "gn:country_code":"ID",
    "gn:dem":33,
    "gn:feature_class":"P",
    "gn:feature_code":"PPL",
    "gn:name":"Batumulapan Kauh",
    "gn:population":0,
    "gn:timezone":"Asia/Makassar",
    "iso:country":"ID",
    "name:ind_x_preferred":[
        "Batumulapan Kauh"
    ],
    "wof:name":"Batumulapan Kauh",
    "wof:placetype":"locality"
},
  "geometry": {"coordinates":[115.57080000000001,-8.6851],"type":"Point"}
}