{
  "type": "Feature",
  "properties": {
    "gn:admin1_code":"2.0",
    "gn:asciiname":"Banjar Mundukwaru",
    "gn:country_code":"ID",
    "gn:dem":223,
    "gn:feature_class":"P",
    "gn:feature_code":"PPL",
    "gn:name":"Banjar Mundukwaru",
    "gn:population":0,
    "gn:timezone":"Asia/Makassar",
    "iso:country":"ID",
    "name:ind_x_preferred":[
        "Banjar Mundukwaru"
    ],
    "wof:name":"Banjar Mundukwaru",
    "wof:placetype":"locality"
},
  "geometry": {"coordinates":[114.6452,-8.3063],"type":"Point"}
}