{
  "type": "Feature",
  "properties": {
    "gn:admin1_code":"3.0",
    "gn:asciiname":"Bukitkabu",
    "gn:country_code":"ID",
    "gn:dem":315,
    "gn:feature_class":"P",
    "gn:feature_code":"PPL",
    "gn:name":"Bukitkabu",
    "gn:population":0,
    "gn:timezone":"Asia/Jakarta",
    "iso:country":"ID",
    "name:und_x_variant":[
        "Boekitkahoe",
        "Boekitkaboe",
        "Bukitkabu"
    ],
    "wof:name":"Bukitkabu",
    "wof:placetype":"locality"
},
  "geometry": {"coordinates":[102.4632,-3.8061],"type":"Point"}
}