{
  "type": "Feature",
  "properties": {
    "gn:admin1_code":"30",
    "gn:asciiname":"Warudoyong",
    "gn:country_code":"ID",
    "gn:dem":543,
    "gn:feature_class":"P",
    "gn:feature_code":"PPL",
    "gn:name":"Warudoyong",
    "gn:population":0,
    "gn:timezone":"Asia/Jakarta",
    "iso:country":"ID",
    "name:ind_x_preferred":[
        "Warudoyong"
    ],
    "wof:name":"Warudoyong",
    "wof:placetype":"locality"
},
  "geometry": {"coordinates":[106.92111,-6.9325],"type":"Point"}
}