{
  "type": "Feature",
  "properties": {
    "gn:admin1_code":"18.0",
    "gn:asciiname":"Nelaoh",
    "gn:country_code":"ID",
    "gn:dem":472,
    "gn:feature_class":"P",
    "gn:feature_code":"PPL",
    "gn:name":"Nelaoh",
    "gn:population":0,
    "gn:timezone":"Asia/Makassar",
    "iso:country":"ID",
    "name:ind_x_preferred":[
        "Nelaoh"
    ],
    "wof:name":"Nelaoh",
    "wof:placetype":"locality"
},
  "geometry": {"coordinates":[124.3749,-9.77047],"type":"Point"}
}