{
  "type": "Feature",
  "properties": {
    "gn:admin1_code":"8.0",
    "gn:asciiname":"Sasakkudung",
    "gn:country_code":"ID",
    "gn:dem":381,
    "gn:feature_class":"P",
    "gn:feature_code":"PPL",
    "gn:name":"Sasakkudung",
    "gn:population":0,
    "gn:timezone":"Asia/Jakarta",
    "iso:country":"ID",
    "name:ind_x_preferred":[
        "Sasakkudung"
    ],
    "wof:name":"Sasakkudung",
    "wof:placetype":"locality"
},
  "geometry": {"coordinates":[114.1542,-8.2576],"type":"Point"}
}