{
  "type": "Feature",
  "properties": {
    "gn:admin1_code":"8",
    "gn:asciiname":"Crewe",
    "gn:country_code":"ID",
    "gn:dem":42,
    "gn:feature_class":"P",
    "gn:feature_code":"PPL",
    "gn:name":"Crewe",
    "gn:population":0,
    "gn:timezone":"Asia/Jakarta",
    "iso:country":"ID",
    "name:azb_x_preferred":[
        "\u06a9\u0631\u0648"
    ],
    "name:bul_x_preferred":[
        "\u041a\u0440\u044e"
    ],
    "name:ceb_x_preferred":[
        "Crewe"
    ],
    "name:cym_x_preferred":[
        "Crewe"
    ],
    "name:dan_x_preferred":[
        "Crewe"
    ],
    "name:deu_x_preferred":[
        "Crewe"
    ],
    "name:fas_x_preferred":[
        "\u06a9\u0631\u0648"
    ],
    "name:fra_x_preferred":[
        "Crewe"
    ],
    "name:gle_x_preferred":[
        "Crewe"
    ],
    "name:hun_x_preferred":[
        "Crewe"
    ],
    "name:ind_x_preferred":[
        "Crewe"
    ],
    "name:ita_x_preferred":[
        "Crewe"
    ],
    "name:jpn_x_preferred":[
        "\u30af\u30eb\u30fc"
    ],
    "name:kor_x_preferred":[
        "\ud06c\ub8e8"
    ],
    "name:lit_x_preferred":[
        "Kru"
    ],
    "name:nld_x_preferred":[
        "Crewe"
    ],
    "name:nno_x_preferred":[
        "Crewe"
    ],
    "name:nor_x_preferred":[
        "Crewe"
    ],
    "name:pol_x_preferred":[
        "Crewe"
    ],
    "name:por_x_preferred":[
        "Crewe"
    ],
    "name:ron_x_preferred":[
        "Crewe"
    ],
    "name:rus_x_preferred":[
        "\u041a\u0440\u0443"
    ],
    "name:sco_x_preferred":[
        "Crewe"
    ],
    "name:spa_x_preferred":[
        "Crewe"
    ],
    "name:srp_x_preferred":[
        "\u041a\u0440\u0443"
    ],
    "name:swe_x_preferred":[
        "Crewe"
    ],
    "name:tat_x_preferred":[
        "\u041a\u0440\u0443"
    ],
    "name:tur_x_preferred":[
        "Crewe"
    ],
    "name:ukr_x_preferred":[
        "\u041a\u0440\u0443"
    ],
    "name:vol_x_preferred":[
        "Crewe"
    ],
    "wof:lang_x_official":[
        "ind"
    ],
    "wof:lang_x_spoken":[
        "ind",
        "eng"
    ],
    "wof:name":"Crewe",
    "wof:placetype":"locality"
},
  "geometry": {"coordinates":[112.40049999999999,-7.291],"type":"Point"}
}