{
  "type": "Feature",
  "properties": {
    "gn:admin1_code":"8",
    "gn:asciiname":"Crewe",
    "gn:country_code":"ID",
    "gn:dem":42,
    "gn:feature_class":"P",
    "gn:feature_code":"PPL",
    "gn:name":"Crewe",
    "gn:population":0,
    "gn:timezone":"Asia/Jakarta",
    "iso:country":"ID",
    "name:ind_x_preferred":[
        "Crewe"
    ],
    "wof:name":"Crewe",
    "wof:placetype":"locality"
},
  "geometry": {"coordinates":[112.40049999999999,-7.291],"type":"Point"}
}