{
  "type": "Feature",
  "properties": {
    "gn:admin1_code":"1",
    "gn:asciiname":"Paro",
    "gn:country_code":"ID",
    "gn:dem":25,
    "gn:feature_class":"P",
    "gn:feature_code":"PPL",
    "gn:name":"Paro",
    "gn:population":0,
    "gn:timezone":"Asia/Jakarta",
    "iso:country":"ID",
    "name:ceb_x_preferred":[
        "Paro"
    ],
    "name:deu_x_preferred":[
        "Paro"
    ],
    "name:heb_x_preferred":[
        "\u05e4\u05d0\u05e8\u05d5"
    ],
    "name:hun_x_preferred":[
        "Paro"
    ],
    "name:ind_x_preferred":[
        "Paro"
    ],
    "name:ita_x_preferred":[
        "Paro"
    ],
    "name:nld_x_preferred":[
        "Paro"
    ],
    "name:rus_x_preferred":[
        "\u041f\u0430\u0440\u043e"
    ],
    "name:spa_x_preferred":[
        "Paro"
    ],
    "name:srp_x_preferred":[
        "\u041f\u0430\u0440\u043e"
    ],
    "name:swe_x_preferred":[
        "Paro"
    ],
    "name:vie_x_preferred":[
        "Paro"
    ],
    "wof:lang_x_official":[
        "ind"
    ],
    "wof:lang_x_spoken":[
        "ind",
        "eng"
    ],
    "wof:name":"Paro",
    "wof:placetype":"locality"
},
  "geometry": {"coordinates":[95.24639999999999,5.3158],"type":"Point"}
}