{
  "type": "Feature",
  "properties": {
    "gn:admin1_code":"8",
    "gn:asciiname":"Sarpao",
    "gn:country_code":"ID",
    "gn:dem":6,
    "gn:feature_class":"P",
    "gn:feature_code":"PPL",
    "gn:name":"Sarpao",
    "gn:population":0,
    "gn:timezone":"Asia/Jakarta",
    "iso:country":"ID",
    "name:ind_x_preferred":[
        "Sarpao"
    ],
    "wof:name":"Sarpao",
    "wof:placetype":"locality"
},
  "geometry": {"coordinates":[113.24550000000001,-7.191],"type":"Point"}
}