{
  "type": "Feature",
  "properties": {
    "gn:admin1_code":"37.0",
    "gn:asciiname":"Rantaukelapas",
    "gn:country_code":"ID",
    "gn:dem":14,
    "gn:feature_class":"P",
    "gn:feature_code":"PPL",
    "gn:name":"Rantaukelapas",
    "gn:population":0,
    "gn:timezone":"Asia/Jakarta",
    "iso:country":"ID",
    "name:eng_x_preferred":[
        "Rantaukelapas"
    ],
    "wof:name":"Rantaukelapas",
    "wof:placetype":"locality"
},
  "geometry": {"coordinates":[101.61969999999999,0.2859],"type":"Point"}
}