{
  "type": "Feature",
  "properties": {
    "gn:admin1_code":"18",
    "gn:asciiname":"Leke",
    "gn:country_code":"ID",
    "gn:dem":213,
    "gn:feature_class":"P",
    "gn:feature_code":"PPL",
    "gn:name":"Leke",
    "gn:population":0,
    "gn:timezone":"Asia/Makassar",
    "iso:country":"ID",
    "name:bre_x_preferred":[
        "Leke"
    ],
    "name:ceb_x_preferred":[
        "Leke"
    ],
    "name:fas_x_preferred":[
        "\u0644\u06a9"
    ],
    "name:fra_x_preferred":[
        "Leke"
    ],
    "name:ind_x_preferred":[
        "Leke"
    ],
    "name:nld_x_preferred":[
        "Leke"
    ],
    "name:por_x_preferred":[
        "Leke"
    ],
    "name:swe_x_preferred":[
        "Leke"
    ],
    "name:vls_x_preferred":[
        "Leke"
    ],
    "wof:lang_x_official":[
        "ind"
    ],
    "wof:lang_x_spoken":[
        "ind",
        "eng"
    ],
    "wof:name":"Leke",
    "wof:placetype":"locality"
},
  "geometry": {"coordinates":[121.7846,-8.8733],"type":"Point"}
}