{
  "type": "Feature",
  "properties": {
    "gn:admin1_code":"17",
    "gn:asciiname":"Sukaraja",
    "gn:country_code":"ID",
    "gn:dem":269,
    "gn:feature_class":"P",
    "gn:feature_code":"PPL",
    "gn:name":"Sukaraja",
    "gn:population":0,
    "gn:timezone":"Asia/Makassar",
    "iso:country":"ID",
    "name:ind_x_preferred":[
        "Sukaraja"
    ],
    "wof:name":"Sukaraja",
    "wof:placetype":"locality"
},
  "geometry": {"coordinates":[116.54040000000001,-8.5622],"type":"Point"}
}