{
  "type": "Feature",
  "properties": {
    "gn:admin1_code":"28.0",
    "gn:asciiname":"Letinger",
    "gn:country_code":"ID",
    "gn:dem":4,
    "gn:feature_class":"P",
    "gn:feature_code":"PPL",
    "gn:name":"Letinger",
    "gn:population":0,
    "gn:timezone":"Asia/Jayapura",
    "iso:country":"ID",
    "name:ind_x_preferred":[
        "Watoaru"
    ],
    "name:und_x_variant":[
        "Watoeroe",
        "Waturu"
    ],
    "wof:name":"Letinger",
    "wof:placetype":"locality"
},
  "geometry": {"coordinates":[131.66374999999999,-7.51661],"type":"Point"}
}