{
  "type": "Feature",
  "properties": {
    "gn:admin1_code":"30.0",
    "gn:asciiname":"Bandung",
    "gn:country_code":"ID",
    "gn:dem":387,
    "gn:feature_class":"P",
    "gn:feature_code":"PPLA4",
    "gn:name":"Bandung",
    "gn:population":0,
    "gn:timezone":"Asia/Jakarta",
    "iso:country":"ID",
    "name:ind_x_preferred":[
        "Bandung"
    ],
    "name:und_x_variant":[
        "Bandoeng"
    ],
    "wof:name":"Bandung",
    "wof:placetype":"locality"
},
  "geometry": {"coordinates":[108.2607,-7.3993],"type":"Point"}
}