{
  "type": "Feature",
  "properties": {
    "gn:admin1_code":"2.0",
    "gn:asciiname":"Darmawinangun Kangin",
    "gn:country_code":"ID",
    "gn:dem":32,
    "gn:feature_class":"P",
    "gn:feature_code":"PPL",
    "gn:name":"Darmawinangun Kangin",
    "gn:population":0,
    "gn:timezone":"Asia/Makassar",
    "iso:country":"ID",
    "name:ind_x_preferred":[
        "Darmawinangun Kangin"
    ],
    "wof:name":"Darmawinangun Kangin",
    "wof:placetype":"locality"
},
  "geometry": {"coordinates":[115.51349999999999,-8.2135],"type":"Point"}
}