{
  "type": "Feature",
  "properties": {
    "gn:admin1_code":"30.0",
    "gn:asciiname":"Awipari Tengah",
    "gn:country_code":"ID",
    "gn:dem":326,
    "gn:feature_class":"P",
    "gn:feature_code":"PPLA4",
    "gn:name":"Awipari Tengah",
    "gn:population":0,
    "gn:timezone":"Asia/Jakarta",
    "iso:country":"ID",
    "name:ind_x_preferred":[
        "Awipari Tengah"
    ],
    "name:und_x_variant":[
        "Awipari"
    ],
    "wof:lang_x_official":[
        "ind"
    ],
    "wof:lang_x_spoken":[
        "ind",
        "eng"
    ],
    "wof:name":"Awipari Tengah",
    "wof:placetype":"locality"
},
  "geometry": {"coordinates":[108.2719,-7.3511],"type":"Point"}
}