{
  "type": "Feature",
  "properties": {
    "gn:admin1_code":"40.0",
    "gn:asciiname":"Teluk Air",
    "gn:country_code":"ID",
    "gn:dem":8,
    "gn:feature_class":"P",
    "gn:feature_code":"PPL",
    "gn:name":"Teluk Air",
    "gn:population":0,
    "gn:timezone":"Asia/Jakarta",
    "iso:country":"ID",
    "name:ind_x_preferred":[
        "Teluk Air"
    ],
    "wof:name":"Teluk Air",
    "wof:placetype":"locality"
},
  "geometry": {"coordinates":[103.44125,0.99337],"type":"Point"}
}