{
  "type": "Feature",
  "properties": {
    "gn:admin1_code":"30",
    "gn:asciiname":"Cimuncang",
    "gn:country_code":"ID",
    "gn:dem":775,
    "gn:feature_class":"P",
    "gn:feature_code":"PPL",
    "gn:name":"Cimuncang",
    "gn:population":0,
    "gn:timezone":"Asia/Jakarta",
    "iso:country":"ID",
    "name:ind_x_preferred":[
        "Cimuncang"
    ],
    "name:und_x_variant":[
        "Tjimuntjang"
    ],
    "wof:name":"Cimuncang",
    "wof:placetype":"locality"
},
  "geometry": {"coordinates":[107.3925,-6.88778],"type":"Point"}
}