{
  "type": "Feature",
  "properties": {
    "gn:admin1_code":"07",
    "gn:asciiname":"Jeruk",
    "gn:country_code":"ID",
    "gn:dem":1249,
    "gn:feature_class":"P",
    "gn:feature_code":"PPL",
    "gn:name":"Jeruk",
    "gn:population":0,
    "gn:timezone":"Asia/Jakarta",
    "iso:country":"ID",
    "name:und_x_variant":[
        "Jetuk",
        "Djetuk",
        "Jeruk"
    ],
    "wof:name":"Jeruk",
    "wof:placetype":"locality"
},
  "geometry": {"coordinates":[110.49083,-7.48083],"type":"Point"}
}