{
  "type": "Feature",
  "properties": {
    "gn:admin1_code":"2",
    "gn:asciiname":"Banjar Yehmalet",
    "gn:country_code":"ID",
    "gn:dem":13,
    "gn:feature_class":"P",
    "gn:feature_code":"PPL",
    "gn:name":"Banjar Yehmalet",
    "gn:population":0,
    "gn:timezone":"Asia/Makassar",
    "iso:country":"ID",
    "name:ind_x_preferred":[
        "Banjar Yehmalet"
    ],
    "wof:name":"Banjar Yehmalet",
    "wof:placetype":"locality"
},
  "geometry": {"coordinates":[115.48439999999999,-8.5456],"type":"Point"}
}