{
  "type": "Feature",
  "properties": {
    "gn:admin1_code":"2",
    "gn:asciiname":"Banjar Antapdajansema",
    "gn:country_code":"ID",
    "gn:dem":71,
    "gn:feature_class":"P",
    "gn:feature_code":"PPL",
    "gn:name":"Banjar Antapdajansema",
    "gn:population":0,
    "gn:timezone":"Asia/Makassar",
    "iso:country":"ID",
    "name:ind_x_preferred":[
        "Banjar Antapdajansema"
    ],
    "wof:name":"Banjar Antapdajansema",
    "wof:placetype":"locality"
},
  "geometry": {"coordinates":[115.0129,-8.523],"type":"Point"}
}