{
  "type": "Feature",
  "properties": {
    "gn:admin1_code":"8.0",
    "gn:asciiname":"Baratdauh",
    "gn:country_code":"ID",
    "gn:dem":164,
    "gn:feature_class":"P",
    "gn:feature_code":"PPL",
    "gn:name":"Baratdauh",
    "gn:population":0,
    "gn:timezone":"Asia/Jakarta",
    "iso:country":"ID",
    "name:ind_x_preferred":[
        "Baratdauh"
    ],
    "wof:name":"Baratdauh",
    "wof:placetype":"locality"
},
  "geometry": {"coordinates":[113.2376,-6.9488],"type":"Point"}
}