{
  "type": "Feature",
  "properties": {
    "gn:admin1_code":"18.0",
    "gn:asciiname":"Raca",
    "gn:country_code":"ID",
    "gn:dem":15,
    "gn:feature_class":"P",
    "gn:feature_code":"PPL",
    "gn:name":"Raca",
    "gn:population":0,
    "gn:timezone":"Asia/Makassar",
    "iso:country":"ID",
    "name:ceb_x_preferred":[
        "Raca"
    ],
    "name:deu_x_preferred":[
        "Raca"
    ],
    "name:hsb_x_preferred":[
        "Raca"
    ],
    "name:ind_x_preferred":[
        "Raca"
    ],
    "name:ita_x_preferred":[
        "Raca"
    ],
    "name:nld_x_preferred":[
        "Raca"
    ],
    "name:spa_x_preferred":[
        "Raca"
    ],
    "name:sqi_x_preferred":[
        "Ra\u00e7a"
    ],
    "name:swe_x_preferred":[
        "Raca"
    ],
    "wof:lang_x_official":[
        "ind"
    ],
    "wof:lang_x_spoken":[
        "ind",
        "eng"
    ],
    "wof:name":"Raca",
    "wof:placetype":"locality"
},
  "geometry": {"coordinates":[120.4902,-8.3117],"type":"Point"}
}