{
  "type": "Feature",
  "properties": {
    "gn:admin1_code":"40.0",
    "gn:asciiname":"Selatbeliat",
    "gn:country_code":"ID",
    "gn:dem":16,
    "gn:feature_class":"P",
    "gn:feature_code":"PPL",
    "gn:name":"Selatbeliat",
    "gn:population":0,
    "gn:timezone":"Asia/Jakarta",
    "iso:country":"ID",
    "name:ind_x_preferred":[
        "Selatbeliat"
    ],
    "name:ind_x_variant":[
        "Bliah"
    ],
    "name:und_x_variant":[
        "Selatbliat"
    ],
    "wof:name":"Selatbeliat",
    "wof:placetype":"locality"
},
  "geometry": {"coordinates":[103.3771,0.89438],"type":"Point"}
}