{
  "type": "Feature",
  "properties": {
    "gn:admin1_code":"7.0",
    "gn:asciiname":"Manikmoyo",
    "gn:country_code":"ID",
    "gn:dem":551,
    "gn:feature_class":"P",
    "gn:feature_code":"PPL",
    "gn:name":"Manikmoyo",
    "gn:population":0,
    "gn:timezone":"Asia/Jakarta",
    "iso:country":"ID",
    "name:ind_x_preferred":[
        "Manikmoyo"
    ],
    "name:und_x_variant":[
        "Manemoyoh"
    ],
    "wof:name":"Manikmoyo",
    "wof:placetype":"locality"
},
  "geometry": {"coordinates":[110.36320000000001,-7.124],"type":"Point"}
}