{
  "type": "Feature",
  "properties": {
    "gn:admin1_code":"36.0",
    "gn:asciiname":"Bata",
    "gn:country_code":"ID",
    "gn:dem":1883,
    "gn:feature_class":"P",
    "gn:feature_code":"PPL",
    "gn:name":"Bata",
    "gn:population":0,
    "gn:timezone":"Asia/Jayapura",
    "iso:country":"ID",
    "name:ind_x_preferred":[
        "Bata"
    ],
    "wof:name":"Bata",
    "wof:placetype":"locality"
},
  "geometry": {"coordinates":[135.53880000000001,-3.8922],"type":"Point"}
}