{
  "type": "Feature",
  "properties": {
    "gn:admin1_code":"8",
    "gn:asciiname":"Sungailedok",
    "gn:country_code":"ID",
    "gn:dem":553,
    "gn:feature_class":"P",
    "gn:feature_code":"PPL",
    "gn:name":"Sungailedok",
    "gn:population":0,
    "gn:timezone":"Asia/Jakarta",
    "iso:country":"ID",
    "name:ind_x_preferred":[
        "Sungailedok"
    ],
    "wof:name":"Sungailedok",
    "wof:placetype":"locality"
},
  "geometry": {"coordinates":[113.9208,-8.0103],"type":"Point"}
}