{
  "type": "Feature",
  "properties": {
    "gn:admin1_code":"30.0",
    "gn:asciiname":"Campaka",
    "gn:country_code":"ID",
    "gn:dem":664,
    "gn:feature_class":"P",
    "gn:feature_code":"PPL",
    "gn:name":"Campaka",
    "gn:population":0,
    "gn:timezone":"Asia/Jakarta",
    "iso:country":"ID",
    "name:ind_x_preferred":[
        "Campaka"
    ],
    "wof:name":"Campaka",
    "wof:placetype":"locality"
},
  "geometry": {"coordinates":[107.9876,-7.4965],"type":"Point"}
}