{
  "type": "Feature",
  "properties": {
    "gn:admin1_code":"0.0",
    "gn:asciiname":"Riam",
    "gn:country_code":"ID",
    "gn:dem":121,
    "gn:feature_class":"P",
    "gn:feature_code":"PPL",
    "gn:name":"Riam",
    "gn:population":0,
    "gn:timezone":"Asia/Pontianak",
    "iso:country":"ID",
    "wof:name":"Riam",
    "wof:placetype":"locality"
},
  "geometry": {"coordinates":[111.90000000000001,-1.83333],"type":"Point"}
}