{
  "type": "Feature",
  "properties": {
    "gn:country":"ID",
    "gn:fcode":"ADM4",
    "gn:pop":0,
    "iso:country":"ID",
    "name:ind_x_preferred":[
        "Kelurahan Gotong Royong"
    ],
    "name:unk_x_variant":[
        "Gotong Royong"
    ],
    "qs:name":"Kelurahan Gotong Royong",
    "qs:photos_9r":0,
    "qs:photos_sr":0,
    "qs:pop_sr":"0",
    "wd:wordcount":5558,
    "wof:name":"Kelurahan Gotong Royong",
    "wof:placetype":"localadmin",
    "wof:population":0
},
  "geometry": {"coordinates":[105.25433,-5.42455],"type":"Point"}
}