{
  "type": "Feature",
  "properties": {
    "gn:admin1_code":"18.0",
    "gn:asciiname":"Tanggukai",
    "gn:country_code":"ID",
    "gn:dem":556,
    "gn:feature_class":"P",
    "gn:feature_code":"PPL",
    "gn:name":"Tanggukai",
    "gn:population":0,
    "gn:timezone":"Asia/Makassar",
    "iso:country":"ID",
    "name:ind_x_preferred":[
        "Tanggukai"
    ],
    "wof:name":"Tanggukai",
    "wof:placetype":"locality"
},
  "geometry": {"coordinates":[119.4123,-9.5208],"type":"Point"}
}