{
  "type": "Feature",
  "properties": {
    "gn:admin1_code":"7.0",
    "gn:asciiname":"Sindangheula",
    "gn:country_code":"ID",
    "gn:dem":118,
    "gn:feature_class":"P",
    "gn:feature_code":"PPLA4",
    "gn:name":"Sindangheula",
    "gn:population":0,
    "gn:timezone":"Asia/Jakarta",
    "iso:country":"ID",
    "name:ind_x_preferred":[
        "Sindangheula"
    ],
    "wof:name":"Sindangheula",
    "wof:placetype":"locality"
},
  "geometry": {"coordinates":[108.81059999999999,-7.0879],"type":"Point"}
}