{
  "type": "Feature",
  "properties": {
    "gn:admin1_code":"1",
    "gn:asciiname":"Sinjheu",
    "gn:country_code":"ID",
    "gn:dem":30,
    "gn:feature_class":"P",
    "gn:feature_code":"PPL",
    "gn:name":"Sinjheu",
    "gn:population":0,
    "gn:timezone":"Asia/Jakarta",
    "iso:country":"ID",
    "name:ind_x_preferred":[
        "Sinjheu"
    ],
    "wof:name":"Sinjheu",
    "wof:placetype":"locality"
},
  "geometry": {"coordinates":[95.4498,5.4089],"type":"Point"}
}