{
  "type": "Feature",
  "properties": {
    "gn:admin1_code":"7.0",
    "gn:asciiname":"Silunjarjaya",
    "gn:country_code":"ID",
    "gn:dem":136,
    "gn:feature_class":"P",
    "gn:feature_code":"PPL",
    "gn:name":"Silunjarjaya",
    "gn:population":0,
    "gn:timezone":"Asia/Jakarta",
    "iso:country":"ID",
    "name:ind_x_preferred":[
        "Silunjarjaya"
    ],
    "wof:name":"Silunjarjaya",
    "wof:placetype":"locality"
},
  "geometry": {"coordinates":[109.1225,-7.43167],"type":"Point"}
}