{
  "type": "Feature",
  "properties": {
    "gn:admin1_code":"7",
    "gn:asciiname":"Gayam",
    "gn:country_code":"ID",
    "gn:dem":229,
    "gn:feature_class":"P",
    "gn:feature_code":"PPL",
    "gn:name":"Gayam",
    "gn:population":0,
    "gn:timezone":"Asia/Jakarta",
    "iso:country":"ID",
    "name:ind_x_preferred":[
        "Gayam"
    ],
    "wof:name":"Gayam",
    "wof:placetype":"locality"
},
  "geometry": {"coordinates":[111.08499999999999,-7.90194],"type":"Point"}
}