{
  "type": "Feature",
  "properties": {
    "gn:admin1_code":"7.0",
    "gn:asciiname":"Panjatan",
    "gn:country_code":"ID",
    "gn:dem":244,
    "gn:feature_class":"P",
    "gn:feature_code":"PPL",
    "gn:name":"Panjatan",
    "gn:population":0,
    "gn:timezone":"Asia/Jakarta",
    "iso:country":"ID",
    "name:ind_x_preferred":[
        "Panjatan"
    ],
    "wof:name":"Panjatan",
    "wof:placetype":"locality"
},
  "geometry": {"coordinates":[109.59166999999999,-7.52972],"type":"Point"}
}