{
  "type": "Feature",
  "properties": {
    "gn:admin1_code":"30",
    "gn:asciiname":"Jatimekar",
    "gn:country_code":"ID",
    "gn:dem":89,
    "gn:feature_class":"P",
    "gn:feature_code":"PPL",
    "gn:name":"Jatimekar",
    "gn:population":0,
    "gn:timezone":"Asia/Jakarta",
    "iso:country":"ID",
    "name:ind_x_preferred":[
        "Jatimekar"
    ],
    "wof:name":"Jatimekar",
    "wof:placetype":"locality"
},
  "geometry": {"coordinates":[107.43416999999999,-6.52944],"type":"Point"}
}