{
  "type": "Feature",
  "properties": {
    "gn:admin1_code":"18.0",
    "gn:asciiname":"Kongarusa",
    "gn:country_code":"ID",
    "gn:dem":105,
    "gn:feature_class":"P",
    "gn:feature_code":"PPL",
    "gn:name":"Kongarusa",
    "gn:population":0,
    "gn:timezone":"Asia/Makassar",
    "iso:country":"ID",
    "name:ind_x_preferred":[
        "Kongarusa"
    ],
    "wof:name":"Kongarusa",
    "wof:placetype":"locality"
},
  "geometry": {"coordinates":[122.0123,-8.7844],"type":"Point"}
}