{
  "type": "Feature",
  "properties": {
    "gn:admin1_code":"7.0",
    "gn:asciiname":"Nglobener",
    "gn:country_code":"ID",
    "gn:dem":104,
    "gn:feature_class":"P",
    "gn:feature_code":"PPL",
    "gn:name":"Nglobener",
    "gn:population":0,
    "gn:timezone":"Asia/Jakarta",
    "iso:country":"ID",
    "name:ind_x_preferred":[
        "Nglobener"
    ],
    "wof:name":"Nglobener",
    "wof:placetype":"locality"
},
  "geometry": {"coordinates":[111.4632,-6.9702],"type":"Point"}
}