{
  "type": "Feature",
  "properties": {
    "gn:admin1_code":"18.0",
    "gn:asciiname":"Hila",
    "gn:country_code":"ID",
    "gn:dem":542,
    "gn:feature_class":"P",
    "gn:feature_code":"PPLA4",
    "gn:name":"Hila",
    "gn:population":0,
    "gn:timezone":"Asia/Makassar",
    "iso:country":"ID",
    "name:deu_x_preferred":[
        "Hila"
    ],
    "name:fin_x_preferred":[
        "Hila"
    ],
    "name:fra_x_preferred":[
        "Hila"
    ],
    "name:ind_x_preferred":[
        "Hila"
    ],
    "wof:lang_x_official":[
        "ind"
    ],
    "wof:lang_x_spoken":[
        "ind",
        "eng"
    ],
    "wof:name":"Hila",
    "wof:placetype":"locality"
},
  "geometry": {"coordinates":[122.613,-8.5628],"type":"Point"}
}