{
  "type": "Feature",
  "properties": {
    "gn:admin1_code":"8",
    "gn:asciiname":"Ngamban",
    "gn:country_code":"ID",
    "gn:dem":315,
    "gn:feature_class":"P",
    "gn:feature_code":"PPL",
    "gn:name":"Ngamban",
    "gn:population":0,
    "gn:timezone":"Asia/Jakarta",
    "iso:country":"ID",
    "name:ind_x_preferred":[
        "Ngamban"
    ],
    "wof:name":"Ngamban",
    "wof:placetype":"locality"
},
  "geometry": {"coordinates":[111.30806,-7.58361],"type":"Point"}
}