{
  "type": "Feature",
  "properties": {
    "gn:admin1_code":"18.0",
    "gn:asciiname":"Watobolak",
    "gn:country_code":"ID",
    "gn:dem":27,
    "gn:feature_class":"P",
    "gn:feature_code":"PPL",
    "gn:name":"Watobolak",
    "gn:population":0,
    "gn:timezone":"Asia/Makassar",
    "iso:country":"ID",
    "name:ind_x_preferred":[
        "Watobolak"
    ],
    "wof:name":"Watobolak",
    "wof:placetype":"locality"
},
  "geometry": {"coordinates":[122.7824,-8.2317],"type":"Point"}
}