{
  "type": "Feature",
  "properties": {
    "gn:admin1_code":"1",
    "gn:asciiname":"Lhok Dalam",
    "gn:country_code":"ID",
    "gn:dem":3,
    "gn:feature_class":"P",
    "gn:feature_code":"PPL",
    "gn:name":"Lhok Dalam",
    "gn:population":0,
    "gn:timezone":"Asia/Jakarta",
    "iso:country":"ID",
    "name:ind_x_preferred":[
        "Lhok Dalam"
    ],
    "wof:name":"Lhok Dalam",
    "wof:placetype":"locality"
},
  "geometry": {"coordinates":[97.8913,4.8018],"type":"Point"}
}