{
  "type": "Feature",
  "properties": {
    "gn:admin1_code":"15.0",
    "gn:asciiname":"Umbulan Jarusaka",
    "gn:country_code":"ID",
    "gn:dem":99,
    "gn:feature_class":"P",
    "gn:feature_code":"PPL",
    "gn:name":"Umbulan Jarusaka",
    "gn:population":0,
    "gn:timezone":"Asia/Jakarta",
    "iso:country":"ID",
    "name:ind_x_preferred":[
        "Umbulanjurusaka"
    ],
    "name:ind_x_variant":[
        "Umbulan Jarusaka"
    ],
    "name:und_x_variant":[
        "Oemboelan Djaroesaka"
    ],
    "wof:name":"Umbulan Jarusaka",
    "wof:placetype":"locality"
},
  "geometry": {"coordinates":[104.8036,-5.0048],"type":"Point"}
}