{
  "type": "Feature",
  "properties": {
    "gn:admin1_code":"18.0",
    "gn:asciiname":"Lapadang",
    "gn:country_code":"ID",
    "gn:dem":694,
    "gn:feature_class":"P",
    "gn:feature_code":"PPL",
    "gn:name":"Lapadang",
    "gn:population":0,
    "gn:timezone":"Asia/Makassar",
    "iso:country":"ID",
    "name:ind_x_preferred":[
        "Lapadang"
    ],
    "wof:name":"Lapadang",
    "wof:placetype":"locality"
},
  "geometry": {"coordinates":[120.47709999999999,-10.0596],"type":"Point"}
}