{
  "type": "Feature",
  "properties": {
    "gn:admin1_code":"12.0",
    "gn:asciiname":"Tabudarat",
    "gn:country_code":"ID",
    "gn:dem":11,
    "gn:feature_class":"P",
    "gn:feature_code":"PPL",
    "gn:name":"Tabudarat",
    "gn:population":0,
    "gn:timezone":"Asia/Makassar",
    "iso:country":"ID",
    "name:ind_x_preferred":[
        "Tabudarat"
    ],
    "wof:name":"Tabudarat",
    "wof:placetype":"locality"
},
  "geometry": {"coordinates":[115.32555000000001,-2.65499],"type":"Point"}
}