{
  "type": "Feature",
  "properties": {
    "gn:admin1_code":"8.0",
    "gn:asciiname":"Garan Atas",
    "gn:country_code":"ID",
    "gn:dem":486,
    "gn:feature_class":"P",
    "gn:feature_code":"PPL",
    "gn:name":"Garan Atas",
    "gn:population":0,
    "gn:timezone":"Asia/Jakarta",
    "iso:country":"ID",
    "name:ind_x_preferred":[
        "Garan Atas"
    ],
    "wof:name":"Garan Atas",
    "wof:placetype":"locality"
},
  "geometry": {"coordinates":[113.9166,-8.275],"type":"Point"}
}