{
  "type": "Feature",
  "properties": {
    "gn:admin1_code":"30",
    "gn:asciiname":"Cikalong",
    "gn:country_code":"ID",
    "gn:dem":391,
    "gn:feature_class":"P",
    "gn:feature_code":"PPL",
    "gn:name":"Cikalong",
    "gn:population":0,
    "gn:timezone":"Asia/Jakarta",
    "iso:country":"ID",
    "name:ind_x_preferred":[
        "Cikalong"
    ],
    "wof:name":"Cikalong",
    "wof:placetype":"locality"
},
  "geometry": {"coordinates":[107.89806000000002,-6.76389],"type":"Point"}
}