{
  "type": "Feature",
  "properties": {
    "gn:admin1_code":"8.0",
    "gn:asciiname":"Tambakan",
    "gn:country_code":"ID",
    "gn:dem":335,
    "gn:feature_class":"P",
    "gn:feature_code":"PPLA4",
    "gn:name":"Tambakan",
    "gn:population":0,
    "gn:timezone":"Asia/Jakarta",
    "iso:country":"ID",
    "name:ind_x_preferred":[
        "Tambakan"
    ],
    "wof:name":"Tambakan",
    "wof:placetype":"locality"
},
  "geometry": {"coordinates":[112.298,-8.0566],"type":"Point"}
}