{
  "type": "Feature",
  "properties": {
    "gn:admin1_code":"18.0",
    "gn:asciiname":"Buti",
    "gn:country_code":"ID",
    "gn:dem":777,
    "gn:feature_class":"P",
    "gn:feature_code":"PPL",
    "gn:name":"Buti",
    "gn:population":0,
    "gn:timezone":"Asia/Makassar",
    "iso:country":"ID",
    "name:azb_x_preferred":[
        "\u0628\u0648\u062a\u06cc"
    ],
    "name:bcl_x_preferred":[
        "Buti"
    ],
    "name:bel_x_preferred":[
        "\u0411\u0443\u0446\u0456"
    ],
    "name:bul_x_preferred":[
        "\u0411\u0443\u0442\u0438"
    ],
    "name:cat_x_preferred":[
        "Buti"
    ],
    "name:ceb_x_preferred":[
        "Buti"
    ],
    "name:cos_x_preferred":[
        "Buti"
    ],
    "name:deu_x_preferred":[
        "Buti"
    ],
    "name:epo_x_preferred":[
        "Buti"
    ],
    "name:eus_x_preferred":[
        "Buti"
    ],
    "name:fas_x_preferred":[
        "\u0628\u0648\u062a\u06cc"
    ],
    "name:fra_x_preferred":[
        "Buti"
    ],
    "name:hun_x_preferred":[
        "Buti"
    ],
    "name:hye_x_preferred":[
        "\u0532\u0578\u0582\u057f\u056b"
    ],
    "name:ind_x_preferred":[
        "Buti"
    ],
    "name:ita_x_preferred":[
        "Buti"
    ],
    "name:jpn_x_preferred":[
        "\u30d6\u30fc\u30c6\u30a3"
    ],
    "name:kaz_x_preferred":[
        "\u0411\u0443\u0442\u0438"
    ],
    "name:lat_x_preferred":[
        "Buiti Castrum"
    ],
    "name:lmo_x_preferred":[
        "Buti"
    ],
    "name:msa_x_preferred":[
        "Buti"
    ],
    "name:nap_x_preferred":[
        "Buti"
    ],
    "name:nld_x_preferred":[
        "Buti"
    ],
    "name:pms_x_preferred":[
        "Buti"
    ],
    "name:pol_x_preferred":[
        "Buti"
    ],
    "name:por_x_preferred":[
        "Buti"
    ],
    "name:ron_x_preferred":[
        "Buti"
    ],
    "name:rus_x_preferred":[
        "\u0411\u0443\u0442\u0438"
    ],
    "name:scn_x_preferred":[
        "Buti"
    ],
    "name:spa_x_preferred":[
        "Buti"
    ],
    "name:srp_x_preferred":[
        "\u0411\u0443\u0442\u0438"
    ],
    "name:tgl_x_preferred":[
        "Buti"
    ],
    "name:ukr_x_preferred":[
        "\u0411\u0443\u0442\u0456"
    ],
    "name:uzb_x_preferred":[
        "Buti"
    ],
    "name:vie_x_preferred":[
        "Buti"
    ],
    "name:vol_x_preferred":[
        "Buti"
    ],
    "name:war_x_preferred":[
        "Buti"
    ],
    "wof:lang_x_official":[
        "ind"
    ],
    "wof:lang_x_spoken":[
        "ind",
        "eng"
    ],
    "wof:name":"Buti",
    "wof:placetype":"locality"
},
  "geometry": {"coordinates":[124.4332,-9.9979],"type":"Point"}
}