{
  "type": "Feature",
  "properties": {
    "gn:admin1_code":"8",
    "gn:asciiname":"Wates",
    "gn:country_code":"ID",
    "gn:dem":361,
    "gn:feature_class":"P",
    "gn:feature_code":"PPL",
    "gn:name":"Wates",
    "gn:population":0,
    "gn:timezone":"Asia/Jakarta",
    "iso:country":"ID",
    "name:ind_x_preferred":[
        "Wates"
    ],
    "wof:name":"Wates",
    "wof:placetype":"locality"
},
  "geometry": {"coordinates":[111.6271,-7.9495],"type":"Point"}
}