{
  "type": "Feature",
  "properties": {
    "gn:admin1_code":"8",
    "gn:asciiname":"Jarakah",
    "gn:country_code":"ID",
    "gn:dem":382,
    "gn:feature_class":"P",
    "gn:feature_code":"PPL",
    "gn:name":"Jarakah",
    "gn:population":0,
    "gn:timezone":"Asia/Jakarta",
    "iso:country":"ID",
    "name:ind_x_preferred":[
        "Jarakah"
    ],
    "wof:name":"Jarakah",
    "wof:placetype":"locality"
},
  "geometry": {"coordinates":[111.32472,-7.70194],"type":"Point"}
}