{
  "type": "Feature",
  "properties": {
    "gn:admin1_code":"17",
    "gn:asciiname":"Dapur",
    "gn:country_code":"ID",
    "gn:dem":67,
    "gn:feature_class":"P",
    "gn:feature_code":"PPL",
    "gn:name":"Dapur",
    "gn:population":0,
    "gn:timezone":"Asia/Makassar",
    "iso:country":"ID",
    "name:ind_x_preferred":[
        "Dapur"
    ],
    "wof:name":"Dapur",
    "wof:placetype":"locality"
},
  "geometry": {"coordinates":[116.1742,-8.62],"type":"Point"}
}