{
  "type": "Feature",
  "properties": {
    "gn:admin1_code":"39.0",
    "gn:asciiname":"Saonek",
    "gn:country_code":"ID",
    "gn:dem":68,
    "gn:feature_class":"P",
    "gn:feature_code":"PPLA3",
    "gn:name":"Saonek",
    "gn:population":0,
    "gn:timezone":"Asia/Jayapura",
    "iso:country":"ID",
    "name:ind_x_preferred":[
        "Saonek"
    ],
    "wof:name":"Saonek",
    "wof:placetype":"locality"
},
  "geometry": {"coordinates":[130.7559,-0.4379],"type":"Point"}
}