{
  "type": "Feature",
  "properties": {
    "gn:admin1_code":"7",
    "gn:asciiname":"Cokrah",
    "gn:country_code":"ID",
    "gn:dem":7,
    "gn:feature_class":"P",
    "gn:feature_code":"PPL",
    "gn:name":"Cokrah",
    "gn:population":0,
    "gn:timezone":"Asia/Jakarta",
    "iso:country":"ID",
    "name:ind_x_preferred":[
        "Cokrah"
    ],
    "wof:name":"Cokrah",
    "wof:placetype":"locality"
},
  "geometry": {"coordinates":[109.616,-6.8945],"type":"Point"}
}