{
  "type": "Feature",
  "properties": {
    "gn:admin1_code":"2",
    "gn:asciiname":"Banjar Ceniguhun",
    "gn:country_code":"ID",
    "gn:dem":1036,
    "gn:feature_class":"P",
    "gn:feature_code":"PPL",
    "gn:name":"Banjar Ceniguhun",
    "gn:population":0,
    "gn:timezone":"Asia/Makassar",
    "iso:country":"ID",
    "name:ind_x_preferred":[
        "Banjar Ceniguhun"
    ],
    "wof:name":"Banjar Ceniguhun",
    "wof:placetype":"locality"
},
  "geometry": {"coordinates":[115.2954,-8.1776],"type":"Point"}
}