{
  "type": "Feature",
  "properties": {
    "gn:admin1_code":"30",
    "gn:asciiname":"Gempol",
    "gn:country_code":"ID",
    "gn:dem":693,
    "gn:feature_class":"P",
    "gn:feature_code":"PPL",
    "gn:name":"Gempol",
    "gn:population":0,
    "gn:timezone":"Asia/Jakarta",
    "iso:country":"ID",
    "name:ind_x_preferred":[
        "Gempol"
    ],
    "wof:name":"Gempol",
    "wof:placetype":"locality"
},
  "geometry": {"coordinates":[107.55722,-6.93111],"type":"Point"}
}