{
  "type": "Feature",
  "properties": {
    "gn:admin1_code":"30",
    "gn:asciiname":"Jerokaso",
    "gn:country_code":"ID",
    "gn:dem":660,
    "gn:feature_class":"P",
    "gn:feature_code":"PPL",
    "gn:name":"Jerokaso",
    "gn:population":0,
    "gn:timezone":"Asia/Jakarta",
    "iso:country":"ID",
    "name:ind_x_preferred":[
        "Jerokaso"
    ],
    "wof:name":"Jerokaso",
    "wof:placetype":"locality"
},
  "geometry": {"coordinates":[108.31417,-6.89361],"type":"Point"}
}