{
  "type": "Feature",
  "properties": {
    "gn:admin1_code":"7",
    "gn:asciiname":"Corot",
    "gn:country_code":"ID",
    "gn:dem":84,
    "gn:feature_class":"P",
    "gn:feature_code":"PPL",
    "gn:name":"Corot",
    "gn:population":0,
    "gn:timezone":"Asia/Jakarta",
    "iso:country":"ID",
    "name:deu_x_preferred":[
        "Corot"
    ],
    "name:fra_x_preferred":[
        "Corot"
    ],
    "name:hun_x_preferred":[
        "Corot"
    ],
    "name:ind_x_preferred":[
        "Corot"
    ],
    "name:ita_x_preferred":[
        "Corot"
    ],
    "name:ltz_x_preferred":[
        "Corot"
    ],
    "name:nld_x_preferred":[
        "Corot"
    ],
    "name:pol_x_preferred":[
        "Corot"
    ],
    "name:por_x_preferred":[
        "Corot"
    ],
    "name:ron_x_preferred":[
        "Corot"
    ],
    "name:rus_x_preferred":[
        "\u041a\u043e\u0440\u043e"
    ],
    "name:spa_x_preferred":[
        "Corot"
    ],
    "name:ukr_x_preferred":[
        "\u041a\u043e\u0440\u043e"
    ],
    "wof:name":"Corot",
    "wof:placetype":"locality"
},
  "geometry": {"coordinates":[111.01027999999999,-7.35667],"type":"Point"}
}