{
  "type": "Feature",
  "properties": {
    "gn:admin1_code":"12",
    "gn:asciiname":"Pondokbutuh",
    "gn:country_code":"ID",
    "gn:dem":12,
    "gn:feature_class":"P",
    "gn:feature_code":"PPL",
    "gn:name":"Pondokbutuh",
    "gn:population":0,
    "gn:timezone":"Asia/Makassar",
    "iso:country":"ID",
    "name:ind_x_preferred":[
        "Pondokbutuh"
    ],
    "wof:name":"Pondokbutuh",
    "wof:placetype":"locality"
},
  "geometry": {"coordinates":[115.97069999999999,-3.4822],"type":"Point"}
}