{
  "type": "Feature",
  "properties": {
    "gn:admin1_code":"33",
    "gn:asciiname":"Lebakpelah",
    "gn:country_code":"ID",
    "gn:dem":110,
    "gn:feature_class":"P",
    "gn:feature_code":"PPL",
    "gn:name":"Lebakpelah",
    "gn:population":0,
    "gn:timezone":"Asia/Jakarta",
    "iso:country":"ID",
    "name:ind_x_preferred":[
        "Lebakpelah"
    ],
    "wof:name":"Lebakpelah",
    "wof:placetype":"locality"
},
  "geometry": {"coordinates":[105.9588,-6.0825],"type":"Point"}
}