{
  "type": "Feature",
  "properties": {
    "gn:admin1_code":"30.0",
    "gn:asciiname":"Parakanterus Dua",
    "gn:country_code":"ID",
    "gn:dem":26,
    "gn:feature_class":"P",
    "gn:feature_code":"PPL",
    "gn:name":"Parakanterus Dua",
    "gn:population":0,
    "gn:timezone":"Asia/Jakarta",
    "iso:country":"ID",
    "name:ind_x_preferred":[
        "Parakanterus Dua"
    ],
    "name:und_x_variant":[
        "Parakanterus"
    ],
    "wof:name":"Parakanterus Dua",
    "wof:placetype":"locality"
},
  "geometry": {"coordinates":[107.35861,-6.40167],"type":"Point"}
}