{
  "type": "Feature",
  "properties": {
    "gn:admin1_code":"8.0",
    "gn:asciiname":"Wanglu Kulon",
    "gn:country_code":"ID",
    "gn:dem":48,
    "gn:feature_class":"P",
    "gn:feature_code":"PPLA4",
    "gn:name":"Wanglu Kulon",
    "gn:population":0,
    "gn:timezone":"Asia/Jakarta",
    "iso:country":"ID",
    "name:ind_x_preferred":[
        "Wanglu Kulon"
    ],
    "wof:lang_x_official":[
        "ind"
    ],
    "wof:lang_x_spoken":[
        "ind",
        "eng"
    ],
    "wof:name":"Wanglu Kulon",
    "wof:placetype":"locality"
},
  "geometry": {"coordinates":[111.73139999999999,-7.0197],"type":"Point"}
}