{
  "type": "Feature",
  "properties": {
    "gn:admin1_code":"10.0",
    "gn:asciiname":"Karang",
    "gn:country_code":"ID",
    "gn:dem":319,
    "gn:feature_class":"P",
    "gn:feature_code":"PPL",
    "gn:name":"Karang",
    "gn:population":0,
    "gn:timezone":"Asia/Jakarta",
    "iso:country":"ID",
    "name:ind_x_preferred":[
        "Karang"
    ],
    "wof:name":"Karang",
    "wof:placetype":"locality"
},
  "geometry": {"coordinates":[110.70833,-8.085],"type":"Point"}
}