{
  "type": "Feature",
  "properties": {
    "gn:admin1_code":"24.0",
    "gn:asciiname":"Dusunlimausundai",
    "gn:country_code":"ID",
    "gn:dem":72,
    "gn:feature_class":"P",
    "gn:feature_code":"PPL",
    "gn:name":"Dusunlimausundai",
    "gn:population":0,
    "gn:timezone":"Asia/Jakarta",
    "iso:country":"ID",
    "name:ind_x_preferred":[
        "Dusunlimausundai"
    ],
    "wof:name":"Dusunlimausundai",
    "wof:placetype":"locality"
},
  "geometry": {"coordinates":[101.8586,-1.1299],"type":"Point"}
}