{
  "type": "Feature",
  "properties": {
    "gn:admin1_code":"26",
    "gn:asciiname":"Rambungsialangtengah",
    "gn:country_code":"ID",
    "gn:dem":34,
    "gn:feature_class":"P",
    "gn:feature_code":"PPL",
    "gn:name":"Rambungsialangtengah",
    "gn:population":0,
    "gn:timezone":"Asia/Jakarta",
    "iso:country":"ID",
    "name:ind_x_preferred":[
        "Rambungsialangtengah"
    ],
    "wof:name":"Rambungsialangtengah",
    "wof:placetype":"locality"
},
  "geometry": {"coordinates":[99.0106,3.4373],"type":"Point"}
}