{
  "type": "Feature",
  "properties": {
    "gn:admin1_code":"26",
    "gn:asciiname":"Pondok Afdeling Sepuluh",
    "gn:country_code":"ID",
    "gn:dem":33,
    "gn:feature_class":"P",
    "gn:feature_code":"PPL",
    "gn:name":"Pondok Afdeling Sepuluh",
    "gn:population":0,
    "gn:timezone":"Asia/Jakarta",
    "iso:country":"ID",
    "name:ind_x_preferred":[
        "Pondok Afdeling Sepuluh"
    ],
    "name:und_x_variant":[
        "Pondok Afdeling X"
    ],
    "wof:lang_x_official":[
        "ind"
    ],
    "wof:lang_x_spoken":[
        "ind",
        "eng"
    ],
    "wof:name":"Pondok Afdeling Sepuluh",
    "wof:placetype":"locality"
},
  "geometry": {"coordinates":[98.2268,3.8741],"type":"Point"}
}