{
  "type": "Feature",
  "properties": {
    "gn:admin1_code":"08",
    "gn:asciiname":"Gedog Kulon",
    "gn:country_code":"ID",
    "gn:dem":368,
    "gn:feature_class":"P",
    "gn:feature_code":"PPL",
    "gn:name":"Gedog Kulon",
    "gn:population":0,
    "gn:timezone":"Asia/Jakarta",
    "iso:country":"ID",
    "name:ind_x_preferred":[
        "Gedog Kulon"
    ],
    "name:und_x_variant":[
        "Gedakkulon"
    ],
    "wof:lang_x_official":[
        "ind"
    ],
    "wof:lang_x_spoken":[
        "ind",
        "eng"
    ],
    "wof:name":"Gedog Kulon",
    "wof:placetype":"locality"
},
  "geometry": {"coordinates":[112.68562,-8.20098],"type":"Point"}
}