{
  "type": "Feature",
  "properties": {
    "gn:admin1_code":"7.0",
    "gn:asciiname":"Kaduwangi",
    "gn:country_code":"ID",
    "gn:dem":560,
    "gn:feature_class":"P",
    "gn:feature_code":"PPL",
    "gn:name":"Kaduwangi",
    "gn:population":0,
    "gn:timezone":"Asia/Jakarta",
    "iso:country":"ID",
    "name:ind_x_preferred":[
        "Kaduwangi"
    ],
    "wof:name":"Kaduwangi",
    "wof:placetype":"locality"
},
  "geometry": {"coordinates":[108.7152,-7.2159],"type":"Point"}
}