{
  "type": "Feature",
  "properties": {
    "gn:admin1_code":"7.0",
    "gn:asciiname":"Panjul Kulon",
    "gn:country_code":"ID",
    "gn:dem":89,
    "gn:feature_class":"P",
    "gn:feature_code":"PPL",
    "gn:name":"Panjul Kulon",
    "gn:population":0,
    "gn:timezone":"Asia/Jakarta",
    "iso:country":"ID",
    "name:ind_x_preferred":[
        "Panjul Kulon"
    ],
    "wof:name":"Panjul Kulon",
    "wof:placetype":"locality"
},
  "geometry": {"coordinates":[109.68222,-7.52333],"type":"Point"}
}