{
  "type": "Feature",
  "properties": {
    "gn:country":"ID",
    "gn:fcode":"PPL",
    "gn:pop":0,
    "iso:country":"ID",
    "name:ind_x_preferred":[
        "Kaligondang"
    ],
    "qs:name":"Kaligondang",
    "qs:name_adm0":"Indonesia",
    "qs:name_adm1":"Provinsi Jawa Tengah",
    "qs:photos_9k":2,
    "qs:photos_9r":5,
    "qs:photos_all":342,
    "qs:photos_sr":0,
    "qs:placetype":"Town",
    "qs:pop_sr":"0",
    "wof:lang_x_official":[
        "ind"
    ],
    "wof:lang_x_spoken":[
        "ind",
        "eng"
    ],
    "wof:name":"Kaligondang",
    "wof:placetype":"locality",
    "wof:population":0
},
  "geometry": {"coordinates":[109.40472,-7.37972],"type":"Point"}
}