{
  "type": "Feature",
  "properties": {
    "gn:admin1_code":"30",
    "gn:asciiname":"Laksanakarya",
    "gn:country_code":"ID",
    "gn:dem":40,
    "gn:feature_class":"P",
    "gn:feature_code":"PPL",
    "gn:name":"Laksanakarya",
    "gn:population":0,
    "gn:timezone":"Asia/Jakarta",
    "iso:country":"ID",
    "name:ind_x_preferred":[
        "Laksanakarya"
    ],
    "wof:name":"Laksanakarya",
    "wof:placetype":"locality"
},
  "geometry": {"coordinates":[108.15582999999999,-6.63],"type":"Point"}
}