{
  "type": "Feature",
  "properties": {
    "gn:admin1_code":"42",
    "gn:asciiname":"Rumah Nasab",
    "gn:country_code":"ID",
    "gn:dem":955,
    "gn:feature_class":"P",
    "gn:feature_code":"PPL",
    "gn:name":"Rumah Nasab",
    "gn:population":0,
    "gn:timezone":"Asia/Makassar",
    "iso:country":"ID",
    "name:msa_x_preferred":[
        "Rumah Nasab"
    ],
    "wof:lang_x_official":[
        "ind"
    ],
    "wof:lang_x_spoken":[
        "ind",
        "eng"
    ],
    "wof:name":"Rumah Nasab",
    "wof:placetype":"locality"
},
  "geometry": {"coordinates":[115.64713,3.9194],"type":"Point"}
}