{
  "type": "Feature",
  "properties": {
    "gn:admin1_code":"8.0",
    "gn:asciiname":"Bayur",
    "gn:country_code":"ID",
    "gn:dem":491,
    "gn:feature_class":"P",
    "gn:feature_code":"PPL",
    "gn:name":"Bayur",
    "gn:population":0,
    "gn:timezone":"Asia/Jakarta",
    "iso:country":"ID",
    "name:ind_x_preferred":[
        "Bayur"
    ],
    "name:ind_x_variant":[
        "Bayua"
    ],
    "name:min_x_preferred":[
        "Bayua"
    ],
    "name:msa_x_preferred":[
        "Bayua"
    ],
    "name:nld_x_preferred":[
        "Nagari Bayua"
    ],
    "wof:name":"Bayur",
    "wof:placetype":"locality"
},
  "geometry": {"coordinates":[113.7581,-7.8864],"type":"Point"}
}