{
  "type": "Feature",
  "properties": {
    "gn:admin1_code":"30",
    "gn:asciiname":"Cipicung Satu",
    "gn:country_code":"ID",
    "gn:dem":74,
    "gn:feature_class":"P",
    "gn:feature_code":"PPL",
    "gn:name":"Cipicung Satu",
    "gn:population":0,
    "gn:timezone":"Asia/Jakarta",
    "iso:country":"ID",
    "name:ind_x_preferred":[
        "Cipicung Satu"
    ],
    "name:und_x_variant":[
        "Tjipitjung Satu",
        "Tjipitjung 1"
    ],
    "wof:lang_x_official":[
        "ind"
    ],
    "wof:lang_x_spoken":[
        "ind",
        "eng"
    ],
    "wof:name":"Cipicung Satu",
    "wof:placetype":"locality"
},
  "geometry": {"coordinates":[107.00111,-6.40778],"type":"Point"}
}