{
  "type": "Feature",
  "properties": {
    "gn:admin1_code":"21",
    "gn:asciiname":"Sisera",
    "gn:country_code":"ID",
    "gn:dem":138,
    "gn:feature_class":"P",
    "gn:feature_code":"PPL",
    "gn:name":"Sisera",
    "gn:population":0,
    "gn:timezone":"Asia/Makassar",
    "iso:country":"ID",
    "name:ind_x_preferred":[
        "Sisera"
    ],
    "wof:name":"Sisera",
    "wof:placetype":"locality"
},
  "geometry": {"coordinates":[119.8515,-0.6307],"type":"Point"}
}