{
  "type": "Feature",
  "properties": {
    "gn:admin1_code":"21",
    "gn:asciiname":"Sisera",
    "gn:country_code":"ID",
    "gn:dem":138,
    "gn:feature_class":"P",
    "gn:feature_code":"PPL",
    "gn:name":"Sisera",
    "gn:population":0,
    "gn:timezone":"Asia/Makassar",
    "iso:country":"ID",
    "name:ara_x_preferred":[
        "\u0633\u064a\u0633\u0631\u0627"
    ],
    "name:bre_x_preferred":[
        "Sisera"
    ],
    "name:deu_x_preferred":[
        "Sisera"
    ],
    "name:epo_x_preferred":[
        "Sisera"
    ],
    "name:fas_x_preferred":[
        "\u0633\u06cc\u0633\u0631\u0627"
    ],
    "name:fra_x_preferred":[
        "Sis\u00e9ra"
    ],
    "name:heb_x_preferred":[
        "\u05e1\u05d9\u05e1\u05e8\u05d0"
    ],
    "name:ind_x_preferred":[
        "Sisera"
    ],
    "name:ita_x_preferred":[
        "Sisara"
    ],
    "name:pol_x_preferred":[
        "Sisera"
    ],
    "name:por_x_preferred":[
        "S\u00edsera"
    ],
    "name:ron_x_preferred":[
        "Sisera"
    ],
    "name:rus_x_preferred":[
        "\u0421\u0438\u0441\u0430\u0440\u0430"
    ],
    "name:spa_x_preferred":[
        "S\u00edsara"
    ],
    "name:tam_x_preferred":[
        "\u0b9a\u0bc0\u0b9a\u0bb0\u0bbe"
    ],
    "name:ukr_x_preferred":[
        "\u0421\u0456\u0441\u0435\u0440\u0430"
    ],
    "wof:lang_x_official":[
        "ind"
    ],
    "wof:lang_x_spoken":[
        "ind",
        "eng"
    ],
    "wof:name":"Sisera",
    "wof:placetype":"locality"
},
  "geometry": {"coordinates":[119.8515,-0.6307],"type":"Point"}
}