{
  "type": "Feature",
  "properties": {
    "gn:admin1_code":"18.0",
    "gn:asciiname":"Fatuoni",
    "gn:country_code":"ID",
    "gn:dem":307,
    "gn:feature_class":"P",
    "gn:feature_code":"PPL",
    "gn:name":"Fatuoni",
    "gn:population":0,
    "gn:timezone":"Asia/Makassar",
    "iso:country":"ID",
    "name:ind_x_preferred":[
        "Fatuoni"
    ],
    "wof:name":"Fatuoni",
    "wof:placetype":"locality"
},
  "geometry": {"coordinates":[124.5455,-9.6719],"type":"Point"}
}