{
  "type": "Feature",
  "properties": {
    "gn:admin1_code":"08",
    "gn:asciiname":"Pesantren",
    "gn:country_code":"ID",
    "gn:dem":922,
    "gn:feature_class":"P",
    "gn:feature_code":"PPL",
    "gn:name":"Pesantren",
    "gn:population":0,
    "gn:timezone":"Asia/Jakarta",
    "iso:country":"ID",
    "name:ind_x_preferred":[
        "Pesantren"
    ],
    "name:und_x_variant":[
        "Pesantren 1",
        "Pesantren Satu"
    ],
    "wof:name":"Pesantren",
    "wof:placetype":"locality"
},
  "geometry": {"coordinates":[112.5158,-7.8672],"type":"Point"}
}