{
  "type": "Feature",
  "properties": {
    "gn:admin1_code":"7.0",
    "gn:asciiname":"Nilorejo",
    "gn:country_code":"ID",
    "gn:dem":105,
    "gn:feature_class":"P",
    "gn:feature_code":"PPL",
    "gn:name":"Nilorejo",
    "gn:population":0,
    "gn:timezone":"Asia/Jakarta",
    "iso:country":"ID",
    "wof:name":"Nilorejo",
    "wof:placetype":"locality"
},
  "geometry": {"coordinates":[110.90111,-7.56278],"type":"Point"}
}