{
  "type": "Feature",
  "properties": {
    "gn:admin1_code":"15.0",
    "gn:asciiname":"Karang Jawa",
    "gn:country_code":"ID",
    "gn:dem":65,
    "gn:feature_class":"P",
    "gn:feature_code":"PPL",
    "gn:name":"Karang Jawa",
    "gn:population":0,
    "gn:timezone":"Asia/Jakarta",
    "iso:country":"ID",
    "name:ind_x_preferred":[
        "Karang Jawa"
    ],
    "wof:name":"Karang Jawa",
    "wof:placetype":"locality"
},
  "geometry": {"coordinates":[104.97443,-4.95916],"type":"Point"}
}