{
  "type": "Feature",
  "properties": {
    "gn:admin1_code":"8",
    "gn:asciiname":"Boro",
    "gn:country_code":"ID",
    "gn:dem":14,
    "gn:feature_class":"P",
    "gn:feature_code":"PPL",
    "gn:name":"Boro",
    "gn:population":0,
    "gn:timezone":"Asia/Jakarta",
    "iso:country":"ID",
    "name:ceb_x_preferred":[
        "Boro"
    ],
    "name:deu_x_preferred":[
        "Boro"
    ],
    "name:fin_x_preferred":[
        "Boro"
    ],
    "name:fra_x_preferred":[
        "Boro"
    ],
    "name:ind_x_preferred":[
        "Boro"
    ],
    "name:ita_x_preferred":[
        "Boro"
    ],
    "name:nld_x_preferred":[
        "Boro"
    ],
    "name:slk_x_preferred":[
        "Boro"
    ],
    "name:swe_x_preferred":[
        "Boro"
    ],
    "wof:lang_x_official":[
        "ind"
    ],
    "wof:lang_x_spoken":[
        "ind",
        "eng"
    ],
    "wof:name":"Boro",
    "wof:placetype":"locality"
},
  "geometry": {"coordinates":[112.06100000000001,-7.0691],"type":"Point"}
}