{
  "type": "Feature",
  "properties": {
    "gn:admin1_code":"7.0",
    "gn:asciiname":"Ngasem Kulon",
    "gn:country_code":"ID",
    "gn:dem":232,
    "gn:feature_class":"P",
    "gn:feature_code":"PPL",
    "gn:name":"Ngasem Kulon",
    "gn:population":0,
    "gn:timezone":"Asia/Jakarta",
    "iso:country":"ID",
    "wof:name":"Ngasem Kulon",
    "wof:placetype":"locality"
},
  "geometry": {"coordinates":[110.97778,-7.77861],"type":"Point"}
}