{
  "type": "Feature",
  "properties": {
    "gn:admin1_code":"7",
    "gn:asciiname":"Brakas",
    "gn:country_code":"ID",
    "gn:dem":20,
    "gn:feature_class":"P",
    "gn:feature_code":"PPL",
    "gn:name":"Brakas",
    "gn:population":0,
    "gn:timezone":"Asia/Jakarta",
    "iso:country":"ID",
    "name:ind_x_preferred":[
        "Brakas"
    ],
    "wof:name":"Brakas",
    "wof:placetype":"locality"
},
  "geometry": {"coordinates":[110.7711,-6.9797],"type":"Point"}
}