{
  "type": "Feature",
  "properties": {
    "gn:admin1_code":"18.0",
    "gn:asciiname":"Lailata",
    "gn:country_code":"ID",
    "gn:dem":218,
    "gn:feature_class":"P",
    "gn:feature_code":"PPL",
    "gn:name":"Lailata",
    "gn:population":0,
    "gn:timezone":"Asia/Makassar",
    "iso:country":"ID",
    "name:ind_x_preferred":[
        "Lailata"
    ],
    "wof:name":"Lailata",
    "wof:placetype":"locality"
},
  "geometry": {"coordinates":[121.8772,-10.5361],"type":"Point"}
}