{
  "type": "Feature",
  "properties": {
    "gn:admin1_code":"7",
    "gn:asciiname":"Pegadungan",
    "gn:country_code":"ID",
    "gn:dem":5,
    "gn:feature_class":"P",
    "gn:feature_code":"PPL",
    "gn:name":"Pegadungan",
    "gn:population":0,
    "gn:timezone":"Asia/Jakarta",
    "iso:country":"ID",
    "name:ind_x_preferred":[
        "Pegadungan"
    ],
    "name:msa_x_preferred":[
        "Pegadungan"
    ],
    "name:nld_x_preferred":[
        "Pegadungan"
    ],
    "name:sun_x_preferred":[
        "Pegadungan"
    ],
    "wof:lang_x_official":[
        "ind"
    ],
    "wof:lang_x_spoken":[
        "ind",
        "eng"
    ],
    "wof:name":"Pegadungan",
    "wof:placetype":"locality"
},
  "geometry": {"coordinates":[109.1357,-6.8623],"type":"Point"}
}