{
  "type": "Feature",
  "properties": {
    "gn:admin1_code":"18.0",
    "gn:asciiname":"Eduk",
    "gn:country_code":"ID",
    "gn:dem":798,
    "gn:feature_class":"P",
    "gn:feature_code":"PPL",
    "gn:name":"Eduk",
    "gn:population":0,
    "gn:timezone":"Asia/Makassar",
    "iso:country":"ID",
    "name:ind_x_preferred":[
        "Eduk"
    ],
    "wof:name":"Eduk",
    "wof:placetype":"locality"
},
  "geometry": {"coordinates":[120.69880000000001,-8.6886],"type":"Point"}
}