{
  "type": "Feature",
  "properties": {
    "gn:admin1_code":"7",
    "gn:asciiname":"Karanganyar Lor",
    "gn:country_code":"ID",
    "gn:dem":41,
    "gn:feature_class":"P",
    "gn:feature_code":"PPL",
    "gn:name":"Karanganyar Lor",
    "gn:population":0,
    "gn:timezone":"Asia/Jakarta",
    "iso:country":"ID",
    "name:ind_x_preferred":[
        "Karanganyar Lor"
    ],
    "wof:name":"Karanganyar Lor",
    "wof:placetype":"locality"
},
  "geometry": {"coordinates":[109.69540000000001,-6.97638],"type":"Point"}
}