{
  "type": "Feature",
  "properties": {
    "gn:admin1_code":"18.0",
    "gn:asciiname":"Puukabo",
    "gn:country_code":"ID",
    "gn:dem":162,
    "gn:feature_class":"P",
    "gn:feature_code":"PPL",
    "gn:name":"Puukabo",
    "gn:population":0,
    "gn:timezone":"Asia/Makassar",
    "iso:country":"ID",
    "name:ind_x_preferred":[
        "Puukabo"
    ],
    "wof:name":"Puukabo",
    "wof:placetype":"locality"
},
  "geometry": {"coordinates":[119.3942,-9.7084],"type":"Point"}
}