{
  "type": "Feature",
  "properties": {
    "gn:admin1_code":"33.0",
    "gn:asciiname":"Cengkok",
    "gn:country_code":"ID",
    "gn:dem":248,
    "gn:feature_class":"P",
    "gn:feature_code":"PPL",
    "gn:name":"Cengkok",
    "gn:population":0,
    "gn:timezone":"Asia/Jakarta",
    "iso:country":"ID",
    "name:cat_x_preferred":[
        "Cengkok"
    ],
    "name:ind_x_preferred":[
        "Cengkok"
    ],
    "wof:name":"Cengkok",
    "wof:placetype":"locality"
},
  "geometry": {"coordinates":[105.68940000000001,-6.672],"type":"Point"}
}