{
  "type": "Feature",
  "properties": {
    "gn:admin1_code":"38",
    "gn:asciiname":"Baloro",
    "gn:country_code":"ID",
    "gn:dem":61,
    "gn:feature_class":"P",
    "gn:feature_code":"PPL",
    "gn:name":"Baloro",
    "gn:population":0,
    "gn:timezone":"Asia/Makassar",
    "iso:country":"ID",
    "name:ind_x_preferred":[
        "Baloro"
    ],
    "wof:name":"Baloro",
    "wof:placetype":"locality"
},
  "geometry": {"coordinates":[119.64490000000001,-5.1434],"type":"Point"}
}