{
  "type": "Feature",
  "properties": {
    "gn:admin1_code":"38",
    "gn:asciiname":"Togo",
    "gn:country_code":"ID",
    "gn:dem":259,
    "gn:feature_class":"P",
    "gn:feature_code":"PPL",
    "gn:name":"Togo",
    "gn:population":0,
    "gn:timezone":"Asia/Makassar",
    "iso:country":"ID",
    "name:ind_x_preferred":[
        "Togo"
    ],
    "wof:name":"Togo",
    "wof:placetype":"locality"
},
  "geometry": {"coordinates":[121.2629,-2.6056],"type":"Point"}
}