{
  "type": "Feature",
  "properties": {
    "gn:admin1_code":"07",
    "gn:asciiname":"Pendem",
    "gn:country_code":"ID",
    "gn:dem":144,
    "gn:feature_class":"P",
    "gn:feature_code":"PPL",
    "gn:name":"Pendem",
    "gn:population":0,
    "gn:timezone":"Asia/Jakarta",
    "iso:country":"ID",
    "name:ceb_x_preferred":[
        "Pendem"
    ],
    "name:nld_x_preferred":[
        "Pendem"
    ],
    "name:swe_x_preferred":[
        "Pendem"
    ],
    "wof:lang_x_official":[
        "ind"
    ],
    "wof:lang_x_spoken":[
        "ind",
        "eng"
    ],
    "wof:name":"Pendem",
    "wof:placetype":"locality"
},
  "geometry": {"coordinates":[110.65028,-7.69861],"type":"Point"}
}