{
  "type": "Feature",
  "properties": {
    "gn:admin1_code":"21.0",
    "gn:asciiname":"Tobesule",
    "gn:country_code":"ID",
    "gn:dem":131,
    "gn:feature_class":"P",
    "gn:feature_code":"PPL",
    "gn:name":"Tobesule",
    "gn:population":0,
    "gn:timezone":"Asia/Makassar",
    "iso:country":"ID",
    "name:ind_x_preferred":[
        "Tobesule"
    ],
    "wof:name":"Tobesule",
    "wof:placetype":"locality"
},
  "geometry": {"coordinates":[119.8349,-0.5192],"type":"Point"}
}