{
  "type": "Feature",
  "properties": {
    "gn:admin1_code":"8",
    "gn:asciiname":"Tegalrejo",
    "gn:country_code":"ID",
    "gn:dem":92,
    "gn:feature_class":"P",
    "gn:feature_code":"PPL",
    "gn:name":"Tegalrejo",
    "gn:population":0,
    "gn:timezone":"Asia/Jakarta",
    "iso:country":"ID",
    "name:ind_x_preferred":[
        "Tegalrejo"
    ],
    "wof:name":"Tegalrejo",
    "wof:placetype":"locality"
},
  "geometry": {"coordinates":[113.7026,-8.1649],"type":"Point"}
}