{
  "type": "Feature",
  "properties": {
    "gn:admin1_code":"18.0",
    "gn:asciiname":"Palelo",
    "gn:country_code":"ID",
    "gn:dem":787,
    "gn:feature_class":"P",
    "gn:feature_code":"PPL",
    "gn:name":"Palelo",
    "gn:population":0,
    "gn:timezone":"Asia/Makassar",
    "iso:country":"ID",
    "name:ind_x_preferred":[
        "Palelo"
    ],
    "name:und_x_variant":[
        "Paleno"
    ],
    "wof:name":"Palelo",
    "wof:placetype":"locality"
},
  "geometry": {"coordinates":[124.2431,-9.8614],"type":"Point"}
}