{
  "type": "Feature",
  "properties": {
    "gn:admin1_code":"1",
    "gn:asciiname":"Pinangbelayar",
    "gn:country_code":"ID",
    "gn:dem":14,
    "gn:feature_class":"P",
    "gn:feature_code":"PPL",
    "gn:name":"Pinangbelayar",
    "gn:population":0,
    "gn:timezone":"Asia/Jakarta",
    "iso:country":"ID",
    "name:ind_x_preferred":[
        "Pinangbelayar"
    ],
    "name:und_x_variant":[
        "Pinangbelajar"
    ],
    "wof:name":"Pinangbelayar",
    "wof:placetype":"locality"
},
  "geometry": {"coordinates":[97.8152,2.573],"type":"Point"}
}