{
  "type": "Feature",
  "properties": {
    "gn:admin1_code":"26",
    "gn:asciiname":"Pondok karangjati",
    "gn:country_code":"ID",
    "gn:dem":73,
    "gn:feature_class":"P",
    "gn:feature_code":"PPL",
    "gn:name":"Pondok karangjati",
    "gn:population":0,
    "gn:timezone":"Asia/Jakarta",
    "iso:country":"ID",
    "name:ind_x_preferred":[
        "Pondok karangjati"
    ],
    "wof:name":"Pondok karangjati",
    "wof:placetype":"locality"
},
  "geometry": {"coordinates":[98.3188,3.5298],"type":"Point"}
}