{
  "type": "Feature",
  "properties": {
    "gn:admin1_code":"30.0",
    "gn:asciiname":"Dago",
    "gn:country_code":"ID",
    "gn:dem":594,
    "gn:feature_class":"P",
    "gn:feature_code":"PPL",
    "gn:name":"Dago",
    "gn:population":0,
    "gn:timezone":"Asia/Jakarta",
    "iso:country":"ID",
    "name:ind_x_preferred":[
        "Dago"
    ],
    "wof:name":"Dago",
    "wof:placetype":"locality"
},
  "geometry": {"coordinates":[107.1601,-7.3068],"type":"Point"}
}