{
  "type": "Feature",
  "properties": {
    "gn:admin1_code":"30.0",
    "gn:asciiname":"Dago",
    "gn:country_code":"ID",
    "gn:dem":594,
    "gn:feature_class":"P",
    "gn:feature_code":"PPL",
    "gn:name":"Dago",
    "gn:population":0,
    "gn:timezone":"Asia/Jakarta",
    "iso:country":"ID",
    "name:ceb_x_preferred":[
        "Dago"
    ],
    "name:deu_x_preferred":[
        "Dag\u00f6"
    ],
    "name:fra_x_preferred":[
        "Dago"
    ],
    "name:ind_x_preferred":[
        "Dago"
    ],
    "name:ita_x_preferred":[
        "Dago"
    ],
    "name:nld_x_preferred":[
        "Dago"
    ],
    "name:swe_x_preferred":[
        "Dago"
    ],
    "wof:lang_x_official":[
        "ind"
    ],
    "wof:lang_x_spoken":[
        "ind",
        "eng"
    ],
    "wof:name":"Dago",
    "wof:placetype":"locality"
},
  "geometry": {"coordinates":[107.1601,-7.3068],"type":"Point"}
}