{
  "type": "Feature",
  "properties": {
    "gn:admin1_code":"30",
    "gn:asciiname":"Babakan Kaler",
    "gn:country_code":"ID",
    "gn:dem":1213,
    "gn:feature_class":"P",
    "gn:feature_code":"PPL",
    "gn:name":"Babakan Kaler",
    "gn:population":0,
    "gn:timezone":"Asia/Jakarta",
    "iso:country":"ID",
    "name:ind_x_preferred":[
        "Babakan Kaler"
    ],
    "wof:name":"Babakan Kaler",
    "wof:placetype":"locality"
},
  "geometry": {"coordinates":[108.36,-6.90694],"type":"Point"}
}