{
  "type": "Feature",
  "properties": {
    "gn:admin1_code":"31",
    "gn:asciiname":"Walepineleng",
    "gn:country_code":"ID",
    "gn:dem":164,
    "gn:feature_class":"P",
    "gn:feature_code":"PPL",
    "gn:name":"Walepineleng",
    "gn:population":0,
    "gn:timezone":"Asia/Makassar",
    "iso:country":"ID",
    "name:ind_x_preferred":[
        "Walepineleng"
    ],
    "wof:name":"Walepineleng",
    "wof:placetype":"locality"
},
  "geometry": {"coordinates":[124.84099999999999,1.4247],"type":"Point"}
}