{
  "type": "Feature",
  "properties": {
    "gn:admin1_code":"30",
    "gn:asciiname":"Leles",
    "gn:country_code":"ID",
    "gn:dem":632,
    "gn:feature_class":"P",
    "gn:feature_code":"PPL",
    "gn:name":"Leles",
    "gn:population":0,
    "gn:timezone":"Asia/Jakarta",
    "iso:country":"ID",
    "name:ind_x_preferred":[
        "Leles"
    ],
    "wof:name":"Leles",
    "wof:placetype":"locality"
},
  "geometry": {"coordinates":[108.46972,-6.9375],"type":"Point"}
}