{
  "type": "Feature",
  "properties": {
    "gn:admin1_code":"30",
    "gn:asciiname":"Emong",
    "gn:country_code":"ID",
    "gn:dem":698,
    "gn:feature_class":"P",
    "gn:feature_code":"PPL",
    "gn:name":"Emong",
    "gn:population":0,
    "gn:timezone":"Asia/Jakarta",
    "iso:country":"ID",
    "name:ind_x_preferred":[
        "Emong"
    ],
    "wof:name":"Emong",
    "wof:placetype":"locality"
},
  "geometry": {"coordinates":[107.61806,-6.92556],"type":"Point"}
}