{
  "type": "Feature",
  "properties": {
    "gn:admin1_code":"30.0",
    "gn:asciiname":"Bedeng",
    "gn:country_code":"ID",
    "gn:dem":515,
    "gn:feature_class":"P",
    "gn:feature_code":"PPL",
    "gn:name":"Bedeng",
    "gn:population":0,
    "gn:timezone":"Asia/Jakarta",
    "iso:country":"ID",
    "name:ind_x_preferred":[
        "Bedeng"
    ],
    "wof:name":"Bedeng",
    "wof:placetype":"locality"
},
  "geometry": {"coordinates":[108.15819999999999,-7.1184],"type":"Point"}
}