{
  "type": "Feature",
  "properties": {
    "gn:country":"ID",
    "gn:fcode":"PPL",
    "gn:pop":0,
    "iso:country":"ID",
    "name:ind_x_preferred":[
        "Ciawigebang"
    ],
    "name:unk_x_variant":[
        "Tjiawigebang"
    ],
    "qs:name":"Ciawigebang",
    "qs:name_adm0":"Indonesia",
    "qs:name_adm1":"Jawa Barat",
    "qs:photos_9r":0,
    "qs:photos_sr":0,
    "qs:placetype":"Town",
    "qs:pop_sr":"0",
    "wd:wordcount":1319,
    "wof:lang_x_official":[
        "ind"
    ],
    "wof:lang_x_spoken":[
        "ind",
        "eng"
    ],
    "wof:name":"Ciawigebang",
    "wof:placetype":"locality",
    "wof:population":0
},
  "geometry": {"coordinates":[108.5834,-6.9718],"type":"Point"}
}