{
  "type": "Feature",
  "properties": {
    "gn:admin1_code":"07",
    "gn:asciiname":"Mruwah",
    "gn:country_code":"ID",
    "gn:dem":676,
    "gn:feature_class":"P",
    "gn:feature_code":"PPL",
    "gn:name":"Mruwah",
    "gn:population":0,
    "gn:timezone":"Asia/Jakarta",
    "iso:country":"ID",
    "name:und_x_variant":[
        "Mruah",
        "Mruwah"
    ],
    "wof:name":"Mruwah",
    "wof:placetype":"locality"
},
  "geometry": {"coordinates":[110.25833,-7.29167],"type":"Point"}
}