{
  "type": "Feature",
  "properties": {
    "gn:admin1_code":"7",
    "gn:asciiname":"Pencil",
    "gn:country_code":"ID",
    "gn:dem":456,
    "gn:feature_class":"P",
    "gn:feature_code":"PPL",
    "gn:name":"Pencil",
    "gn:population":0,
    "gn:timezone":"Asia/Jakarta",
    "iso:country":"ID",
    "name:ind_x_preferred":[
        "Pencil"
    ],
    "wof:name":"Pencil",
    "wof:placetype":"locality"
},
  "geometry": {"coordinates":[111.04277999999999,-7.72889],"type":"Point"}
}