{
  "type": "Feature",
  "properties": {
    "gn:admin1_code":"7.0",
    "gn:asciiname":"Karangmangu",
    "gn:country_code":"ID",
    "gn:dem":484,
    "gn:feature_class":"P",
    "gn:feature_code":"PPL",
    "gn:name":"Karangmangu",
    "gn:population":0,
    "gn:timezone":"Asia/Jakarta",
    "iso:country":"ID",
    "name:ind_x_preferred":[
        "Karangmangu"
    ],
    "name:und_x_variant":[
        "Karangmanggoe",
        "Karangmangoe",
        "Karangmanggu"
    ],
    "wof:lang_x_official":[
        "ind"
    ],
    "wof:lang_x_spoken":[
        "ind",
        "eng"
    ],
    "wof:name":"Karangmangu",
    "wof:placetype":"locality"
},
  "geometry": {"coordinates":[109.22917,-7.33056],"type":"Point"}
}