{
  "type": "Feature",
  "properties": {
    "gn:admin1_code":"8.0",
    "gn:asciiname":"Tawang",
    "gn:country_code":"ID",
    "gn:dem":491,
    "gn:feature_class":"P",
    "gn:feature_code":"PPL",
    "gn:name":"Tawang",
    "gn:population":0,
    "gn:timezone":"Asia/Jakarta",
    "iso:country":"ID",
    "name:ind_x_preferred":[
        "Tawang"
    ],
    "wof:name":"Tawang",
    "wof:placetype":"locality"
},
  "geometry": {"coordinates":[111.86150000000001,-7.7584],"type":"Point"}
}