{
  "type": "Feature",
  "properties": {
    "gn:admin1_code":"37.0",
    "gn:asciiname":"Paritunak Satu",
    "gn:country_code":"ID",
    "gn:dem":4,
    "gn:feature_class":"P",
    "gn:feature_code":"PPL",
    "gn:name":"Paritunak Satu",
    "gn:population":0,
    "gn:timezone":"Asia/Jakarta",
    "iso:country":"ID",
    "name:ind_x_preferred":[
        "Paritunak Satu"
    ],
    "name:und_x_variant":[
        "Paritunak 1"
    ],
    "wof:name":"Paritunak Satu",
    "wof:placetype":"locality"
},
  "geometry": {"coordinates":[103.0656,-0.2634],"type":"Point"}
}