{
  "type": "Feature",
  "properties": {
    "gn:admin1_code":"8",
    "gn:asciiname":"Pojok",
    "gn:country_code":"ID",
    "gn:dem":637,
    "gn:feature_class":"P",
    "gn:feature_code":"PPL",
    "gn:name":"Pojok",
    "gn:population":0,
    "gn:timezone":"Asia/Jakarta",
    "iso:country":"ID",
    "name:ind_x_preferred":[
        "Pojok"
    ],
    "wof:name":"Pojok",
    "wof:placetype":"locality"
},
  "geometry": {"coordinates":[111.66079999999999,-7.9724],"type":"Point"}
}