{
  "type": "Feature",
  "properties": {
    "gn:admin1_code":"8.0",
    "gn:asciiname":"Sambiringik Kidul",
    "gn:country_code":"ID",
    "gn:dem":14,
    "gn:feature_class":"P",
    "gn:feature_code":"PPL",
    "gn:name":"Sambiringik Kidul",
    "gn:population":0,
    "gn:timezone":"Asia/Jakarta",
    "iso:country":"ID",
    "name:ind_x_preferred":[
        "Sambiringik Kidul"
    ],
    "wof:name":"Sambiringik Kidul",
    "wof:placetype":"locality"
},
  "geometry": {"coordinates":[113.5314,-8.372],"type":"Point"}
}