{
  "type": "Feature",
  "properties": {
    "gn:admin1_code":"30",
    "gn:asciiname":"Cinaya",
    "gn:country_code":"ID",
    "gn:dem":679,
    "gn:feature_class":"P",
    "gn:feature_code":"PPL",
    "gn:name":"Cinaya",
    "gn:population":0,
    "gn:timezone":"Asia/Jakarta",
    "iso:country":"ID",
    "name:ind_x_preferred":[
        "Cinaya"
    ],
    "wof:name":"Cinaya",
    "wof:placetype":"locality"
},
  "geometry": {"coordinates":[107.47499999999999,-6.7175],"type":"Point"}
}