{
  "type": "Feature",
  "properties": {
    "gn:admin1_code":"15.0",
    "gn:asciiname":"Maja",
    "gn:country_code":"ID",
    "gn:dem":26,
    "gn:feature_class":"P",
    "gn:feature_code":"PPL",
    "gn:name":"Maja",
    "gn:population":0,
    "gn:timezone":"Asia/Jakarta",
    "iso:country":"ID",
    "name:ind_x_preferred":[
        "Maya"
    ],
    "name:ind_x_variant":[
        "Madjo"
    ],
    "name:und_x_variant":[
        "Madja",
        "Maja",
        "Madj\u014f"
    ],
    "wof:name":"Maja",
    "wof:placetype":"locality"
},
  "geometry": {"coordinates":[105.15652,-5.68058],"type":"Point"}
}