{
  "type": "Feature",
  "properties": {
    "gn:admin1_code":"17",
    "gn:asciiname":"Lingkokgodak",
    "gn:country_code":"ID",
    "gn:dem":483,
    "gn:feature_class":"P",
    "gn:feature_code":"PPL",
    "gn:name":"Lingkokgodak",
    "gn:population":0,
    "gn:timezone":"Asia/Makassar",
    "iso:country":"ID",
    "name:ind_x_preferred":[
        "Lingkokgodak"
    ],
    "wof:name":"Lingkokgodak",
    "wof:placetype":"locality"
},
  "geometry": {"coordinates":[116.3762,-8.5836],"type":"Point"}
}