{
  "type": "Feature",
  "properties": {
    "gn:admin1_code":"30",
    "gn:asciiname":"Cirangrang Barat",
    "gn:country_code":"ID",
    "gn:dem":684,
    "gn:feature_class":"P",
    "gn:feature_code":"PPL",
    "gn:name":"Cirangrang Barat",
    "gn:population":0,
    "gn:timezone":"Asia/Jakarta",
    "iso:country":"ID",
    "name:ind_x_preferred":[
        "Cirangrang Barat"
    ],
    "wof:name":"Cirangrang Barat",
    "wof:placetype":"locality"
},
  "geometry": {"coordinates":[107.58278,-6.95167],"type":"Point"}
}