{
  "type": "Feature",
  "properties": {
    "gn:admin1_code":"8.0",
    "gn:asciiname":"Pandean",
    "gn:country_code":"ID",
    "gn:dem":17,
    "gn:feature_class":"P",
    "gn:feature_code":"PPL",
    "gn:name":"Pandean",
    "gn:population":0,
    "gn:timezone":"Asia/Jakarta",
    "iso:country":"ID",
    "name:ind_x_preferred":[
        "Pandean"
    ],
    "wof:name":"Pandean",
    "wof:placetype":"locality"
},
  "geometry": {"coordinates":[112.81789999999999,-7.6095],"type":"Point"}
}