{
  "type": "Feature",
  "properties": {
    "gn:admin1_code":"8.0",
    "gn:asciiname":"Watulempit",
    "gn:country_code":"ID",
    "gn:dem":442,
    "gn:feature_class":"P",
    "gn:feature_code":"PPL",
    "gn:name":"Watulempit",
    "gn:population":0,
    "gn:timezone":"Asia/Jakarta",
    "iso:country":"ID",
    "name:ind_x_preferred":[
        "Watulempit"
    ],
    "wof:name":"Watulempit",
    "wof:placetype":"locality"
},
  "geometry": {"coordinates":[113.9641,-8.3276],"type":"Point"}
}