{
  "type": "Feature",
  "properties": {
    "gn:admin1_code":"26",
    "gn:asciiname":"Buluhlaga",
    "gn:country_code":"ID",
    "gn:dem":346,
    "gn:feature_class":"P",
    "gn:feature_code":"PPL",
    "gn:name":"Buluhlaga",
    "gn:population":0,
    "gn:timezone":"Asia/Jakarta",
    "iso:country":"ID",
    "name:ind_x_preferred":[
        "Buluhlaga"
    ],
    "wof:name":"Buluhlaga",
    "wof:placetype":"locality"
},
  "geometry": {"coordinates":[98.66759999999999,3.2536],"type":"Point"}
}