{
  "type": "Feature",
  "properties": {
    "gn:admin1_code":"30",
    "gn:asciiname":"Sipelem",
    "gn:country_code":"ID",
    "gn:dem":34,
    "gn:feature_class":"P",
    "gn:feature_code":"PPL",
    "gn:name":"Sipelem",
    "gn:population":0,
    "gn:timezone":"Asia/Jakarta",
    "iso:country":"ID",
    "name:ind_x_preferred":[
        "Sipelem"
    ],
    "wof:name":"Sipelem",
    "wof:placetype":"locality"
},
  "geometry": {"coordinates":[108.5335,-6.7588],"type":"Point"}
}