{
  "type": "Feature",
  "properties": {
    "gn:admin1_code":"18",
    "gn:asciiname":"Lalian",
    "gn:country_code":"ID",
    "gn:dem":416,
    "gn:feature_class":"P",
    "gn:feature_code":"PPL",
    "gn:name":"Lalian",
    "gn:population":0,
    "gn:timezone":"Asia/Makassar",
    "iso:country":"ID",
    "name:ceb_x_preferred":[
        "L\u0101li\u0101n"
    ],
    "name:fas_x_preferred":[
        "\u0644\u0627\u0644\u06cc\u0627\u0646"
    ],
    "name:fra_x_preferred":[
        "Lalian"
    ],
    "name:pol_x_preferred":[
        "Lalian"
    ],
    "name:por_x_preferred":[
        "Lalian"
    ],
    "name:urd_x_preferred":[
        "\u0644\u0627\u0644\u06cc\u0627\u06ba"
    ],
    "wof:name":"Lalian",
    "wof:placetype":"locality"
},
  "geometry": {"coordinates":[124.89749999999999,-9.17361],"type":"Point"}
}