{
  "type": "Feature",
  "properties": {
    "gn:admin1_code":"7.0",
    "gn:asciiname":"Sibopong",
    "gn:country_code":"ID",
    "gn:dem":90,
    "gn:feature_class":"P",
    "gn:feature_code":"PPL",
    "gn:name":"Sibopong",
    "gn:population":0,
    "gn:timezone":"Asia/Jakarta",
    "iso:country":"ID",
    "name:ind_x_preferred":[
        "Sibopong"
    ],
    "wof:name":"Sibopong",
    "wof:placetype":"locality"
},
  "geometry": {"coordinates":[109.63083,-7.54111],"type":"Point"}
}