{
  "type": "Feature",
  "properties": {
    "gn:admin1_code":"8",
    "gn:asciiname":"Sekebo",
    "gn:country_code":"ID",
    "gn:dem":782,
    "gn:feature_class":"P",
    "gn:feature_code":"PPL",
    "gn:name":"Sekebo",
    "gn:population":0,
    "gn:timezone":"Asia/Jakarta",
    "iso:country":"ID",
    "name:ind_x_preferred":[
        "Sekebo"
    ],
    "wof:name":"Sekebo",
    "wof:placetype":"locality"
},
  "geometry": {"coordinates":[111.69670000000001,-7.932],"type":"Point"}
}