{
  "type": "Feature",
  "properties": {
    "gn:admin1_code":"30",
    "gn:asciiname":"Padasuka",
    "gn:country_code":"ID",
    "gn:dem":891,
    "gn:feature_class":"P",
    "gn:feature_code":"PPL",
    "gn:name":"Padasuka",
    "gn:population":0,
    "gn:timezone":"Asia/Jakarta",
    "iso:country":"ID",
    "name:ind_x_preferred":[
        "Padasuka"
    ],
    "wof:name":"Padasuka",
    "wof:placetype":"locality"
},
  "geometry": {"coordinates":[107.78528,-6.88972],"type":"Point"}
}