{
  "type": "Feature",
  "properties": {
    "gn:admin1_code":"30.0",
    "gn:asciiname":"Cipunagara",
    "gn:country_code":"ID",
    "gn:dem":28,
    "gn:feature_class":"P",
    "gn:feature_code":"PPL",
    "gn:name":"Cipunagara",
    "gn:population":0,
    "gn:timezone":"Asia/Jakarta",
    "iso:country":"ID",
    "name:ind_x_preferred":[
        "Cipunagara"
    ],
    "name:und_x_variant":[
        "Tjipunegara",
        "Tjipoenegara",
        "Tjipunagara",
        "Cipunegara"
    ],
    "wof:lang_x_official":[
        "ind"
    ],
    "wof:lang_x_spoken":[
        "ind",
        "eng"
    ],
    "wof:name":"Cipunagara",
    "wof:placetype":"locality"
},
  "geometry": {"coordinates":[107.88028,-6.46361],"type":"Point"}
}