{
  "type": "Feature",
  "properties": {
    "gn:admin1_code":"8.0",
    "gn:asciiname":"Trenggulunan",
    "gn:country_code":"ID",
    "gn:dem":179,
    "gn:feature_class":"P",
    "gn:feature_code":"PPL",
    "gn:name":"Trenggulunan",
    "gn:population":0,
    "gn:timezone":"Asia/Jakarta",
    "iso:country":"ID",
    "name:ind_x_preferred":[
        "Trenggulunan"
    ],
    "wof:name":"Trenggulunan",
    "wof:placetype":"locality"
},
  "geometry": {"coordinates":[111.81399999999999,-7.4048],"type":"Point"}
}