{
  "type": "Feature",
  "properties": {
    "gn:admin1_code":"30",
    "gn:asciiname":"Cibojong",
    "gn:country_code":"ID",
    "gn:dem":630,
    "gn:feature_class":"P",
    "gn:feature_code":"PPL",
    "gn:name":"Cibojong",
    "gn:population":0,
    "gn:timezone":"Asia/Jakarta",
    "iso:country":"ID",
    "name:ind_x_preferred":[
        "Cibojong"
    ],
    "wof:lang_x_official":[
        "ind"
    ],
    "wof:lang_x_spoken":[
        "ind",
        "eng"
    ],
    "wof:name":"Cibojong",
    "wof:placetype":"locality"
},
  "geometry": {"coordinates":[106.64749999999999,-6.80389],"type":"Point"}
}