{
  "type": "Feature",
  "properties": {
    "gn:admin1_code":"08",
    "gn:asciiname":"Ploso",
    "gn:country_code":"ID",
    "gn:dem":14,
    "gn:feature_class":"P",
    "gn:feature_code":"PPL",
    "gn:name":"Ploso",
    "gn:population":0,
    "gn:timezone":"Asia/Jakarta",
    "iso:country":"ID",
    "name:ind_x_preferred":[
        "Ploso"
    ],
    "wof:name":"Ploso",
    "wof:placetype":"locality"
},
  "geometry": {"coordinates":[112.6422,-7.433],"type":"Point"}
}