{
  "type": "Feature",
  "properties": {
    "gn:admin1_code":"18.0",
    "gn:asciiname":"Netenain",
    "gn:country_code":"ID",
    "gn:dem":88,
    "gn:feature_class":"P",
    "gn:feature_code":"PPLA4",
    "gn:name":"Netenain",
    "gn:population":0,
    "gn:timezone":"Asia/Makassar",
    "iso:country":"ID",
    "name:ind_x_preferred":[
        "Netenain"
    ],
    "wof:name":"Netenain",
    "wof:placetype":"locality"
},
  "geometry": {"coordinates":[122.9564,-10.765],"type":"Point"}
}