{
  "type": "Feature",
  "properties": {
    "gn:admin1_code":"30.0",
    "gn:asciiname":"Pasirsereh",
    "gn:country_code":"ID",
    "gn:dem":364,
    "gn:feature_class":"P",
    "gn:feature_code":"PPL",
    "gn:name":"Pasirsereh",
    "gn:population":0,
    "gn:timezone":"Asia/Jakarta",
    "iso:country":"ID",
    "name:ind_x_preferred":[
        "Pasirsereh"
    ],
    "wof:name":"Pasirsereh",
    "wof:placetype":"locality"
},
  "geometry": {"coordinates":[108.23860000000001,-7.4304],"type":"Point"}
}