{
  "type": "Feature",
  "properties": {
    "gn:admin1_code":"7",
    "gn:asciiname":"Kedungdowo",
    "gn:country_code":"ID",
    "gn:dem":437,
    "gn:feature_class":"P",
    "gn:feature_code":"PPL",
    "gn:name":"Kedungdowo",
    "gn:population":0,
    "gn:timezone":"Asia/Jakarta",
    "iso:country":"ID",
    "name:ind_x_preferred":[
        "Kedungdowo"
    ],
    "wof:name":"Kedungdowo",
    "wof:placetype":"locality"
},
  "geometry": {"coordinates":[111.0475,-7.63444],"type":"Point"}
}