{
  "type": "Feature",
  "properties": {
    "gn:admin1_code":"30",
    "gn:asciiname":"Bantargintung Dua",
    "gn:country_code":"ID",
    "gn:dem":51,
    "gn:feature_class":"P",
    "gn:feature_code":"PPL",
    "gn:name":"Bantargintung Dua",
    "gn:population":0,
    "gn:timezone":"Asia/Jakarta",
    "iso:country":"ID",
    "name:ind_x_preferred":[
        "Bantargintung Dua"
    ],
    "wof:name":"Bantargintung Dua",
    "wof:placetype":"locality"
},
  "geometry": {"coordinates":[108.11388999999998,-6.78528],"type":"Point"}
}