{
  "type": "Feature",
  "properties": {
    "gn:admin1_code":"7",
    "gn:asciiname":"Gondopolo",
    "gn:country_code":"ID",
    "gn:dem":569,
    "gn:feature_class":"P",
    "gn:feature_code":"PPL",
    "gn:name":"Gondopolo",
    "gn:population":0,
    "gn:timezone":"Asia/Jakarta",
    "iso:country":"ID",
    "name:ind_x_preferred":[
        "Gondopolo"
    ],
    "wof:name":"Gondopolo",
    "wof:placetype":"locality"
},
  "geometry": {"coordinates":[111.20028000000001,-7.80972],"type":"Point"}
}