{
  "type": "Feature",
  "properties": {
    "gn:admin1_code":"30.0",
    "gn:asciiname":"Lemahputih",
    "gn:country_code":"ID",
    "gn:dem":967,
    "gn:feature_class":"P",
    "gn:feature_code":"PPLA3",
    "gn:name":"Lemahputih",
    "gn:population":0,
    "gn:timezone":"Asia/Jakarta",
    "iso:country":"ID",
    "name:ind_x_preferred":[
        "Lemahputih"
    ],
    "name:und_x_variant":[
        "Lemahpoetih",
        "Lemahputih"
    ],
    "wof:lang_x_official":[
        "ind"
    ],
    "wof:lang_x_spoken":[
        "ind",
        "eng"
    ],
    "wof:name":"Lemahputih",
    "wof:placetype":"locality"
},
  "geometry": {"coordinates":[108.1698,-7.0099],"type":"Point"}
}