{
  "type": "Feature",
  "properties": {
    "gn:admin1_code":"38",
    "gn:asciiname":"Serre Satu",
    "gn:country_code":"ID",
    "gn:dem":119,
    "gn:feature_class":"P",
    "gn:feature_code":"PPL",
    "gn:name":"Serre Satu",
    "gn:population":0,
    "gn:timezone":"Asia/Makassar",
    "iso:country":"ID",
    "name:ind_x_preferred":[
        "Serre Satu"
    ],
    "name:und_x_variant":[
        "Serre 1"
    ],
    "wof:name":"Serre Satu",
    "wof:placetype":"locality"
},
  "geometry": {"coordinates":[120.203,-5.2017],"type":"Point"}
}