{
  "type": "Feature",
  "properties": {
    "gn:admin1_code":"26",
    "gn:asciiname":"Uratan",
    "gn:country_code":"ID",
    "gn:dem":11,
    "gn:feature_class":"P",
    "gn:feature_code":"PPL",
    "gn:name":"Uratan",
    "gn:population":0,
    "gn:timezone":"Asia/Jakarta",
    "iso:country":"ID",
    "name:ind_x_preferred":[
        "Uratan"
    ],
    "wof:name":"Uratan",
    "wof:placetype":"locality"
},
  "geometry": {"coordinates":[98.40000000000001,2.0255],"type":"Point"}
}