{
  "type": "Feature",
  "properties": {
    "gn:admin1_code":"30",
    "gn:asciiname":"Kalibaru",
    "gn:country_code":"ID",
    "gn:dem":7,
    "gn:feature_class":"P",
    "gn:feature_code":"PPL",
    "gn:name":"Kalibaru",
    "gn:population":0,
    "gn:timezone":"Asia/Jakarta",
    "iso:country":"ID",
    "name:ind_x_preferred":[
        "Kalibaru"
    ],
    "wof:name":"Kalibaru",
    "wof:placetype":"locality"
},
  "geometry": {"coordinates":[107.06889,-6.11056],"type":"Point"}
}