{
  "type": "Feature",
  "properties": {
    "gn:admin1_code":"2",
    "gn:asciiname":"Banjar Kabetan Kelod",
    "gn:country_code":"ID",
    "gn:dem":238,
    "gn:feature_class":"P",
    "gn:feature_code":"PPL",
    "gn:name":"Banjar Kabetan Kelod",
    "gn:population":0,
    "gn:timezone":"Asia/Makassar",
    "iso:country":"ID",
    "name:ind_x_preferred":[
        "Banjar Kabetan Kelod"
    ],
    "wof:name":"Banjar Kabetan Kelod",
    "wof:placetype":"locality"
},
  "geometry": {"coordinates":[115.3283,-8.504],"type":"Point"}
}