{
  "type": "Feature",
  "properties": {
    "gn:admin1_code":"36.0",
    "gn:asciiname":"Sowau",
    "gn:country_code":"ID",
    "gn:dem":21,
    "gn:feature_class":"P",
    "gn:feature_code":"PPL",
    "gn:name":"Sowau",
    "gn:population":0,
    "gn:timezone":"Asia/Jayapura",
    "iso:country":"ID",
    "name:und_x_variant":[
        "Sowaoe",
        "Sawaoe",
        "Sowau"
    ],
    "wof:name":"Sowau",
    "wof:placetype":"locality"
},
  "geometry": {"coordinates":[140.98623999999995,-8.04025],"type":"Point"}
}