{
  "type": "Feature",
  "properties": {
    "gn:admin1_code":"18",
    "gn:asciiname":"Pemo",
    "gn:country_code":"ID",
    "gn:dem":385,
    "gn:feature_class":"P",
    "gn:feature_code":"PPL",
    "gn:name":"Pemo",
    "gn:population":0,
    "gn:timezone":"Asia/Makassar",
    "iso:country":"ID",
    "name:ind_x_preferred":[
        "Pemo"
    ],
    "wof:name":"Pemo",
    "wof:placetype":"locality"
},
  "geometry": {"coordinates":[121.63930000000001,-8.7334],"type":"Point"}
}