{
  "type": "Feature",
  "properties": {
    "gn:admin1_code":"30.0",
    "gn:asciiname":"Jajaway",
    "gn:country_code":"ID",
    "gn:dem":345,
    "gn:feature_class":"P",
    "gn:feature_code":"PPL",
    "gn:name":"Jajaway",
    "gn:population":0,
    "gn:timezone":"Asia/Jakarta",
    "iso:country":"ID",
    "name:ind_x_preferred":[
        "Jajaway"
    ],
    "wof:name":"Jajaway",
    "wof:placetype":"locality"
},
  "geometry": {"coordinates":[106.75579999999999,-7.2495],"type":"Point"}
}