{
  "type": "Feature",
  "properties": {
    "gn:admin1_code":"0.0",
    "gn:asciiname":"Kandri",
    "gn:country_code":"ID",
    "gn:dem":107,
    "gn:feature_class":"P",
    "gn:feature_code":"PPL",
    "gn:name":"Kandri",
    "gn:population":0,
    "gn:timezone":"Asia/Jakarta",
    "iso:country":"ID",
    "name:ben_x_preferred":[
        "\u0995\u09be\u09a8\u09cd\u09a6\u09cd\u09b0\u09bf"
    ],
    "name:bpy_x_preferred":[
        "\u0995\u09be\u09a8\u09cd\u09a6\u09cd\u09b0\u09bf"
    ],
    "name:ceb_x_preferred":[
        "Kandri"
    ],
    "name:ind_x_preferred":[
        "Kandri"
    ],
    "name:ita_x_preferred":[
        "Kandri"
    ],
    "name:msa_x_preferred":[
        "Kandri"
    ],
    "name:new_x_preferred":[
        "\u0915\u0928\u094d\u0926\u094d\u0930\u0940"
    ],
    "name:nld_x_preferred":[
        "Kandri"
    ],
    "name:por_x_preferred":[
        "Kandri"
    ],
    "name:urd_x_preferred":[
        "\u06a9\u0627\u0646\u062f\u0631\u06cc"
    ],
    "name:vie_x_preferred":[
        "Kandri"
    ],
    "name:zho_x_preferred":[
        "\u574e\u5fb7\u91cc"
    ],
    "wof:lang_x_official":[
        "ind"
    ],
    "wof:lang_x_spoken":[
        "ind",
        "eng"
    ],
    "wof:name":"Kandri",
    "wof:placetype":"locality"
},
  "geometry": {"coordinates":[110.68333,-7.78333],"type":"Point"}
}