{
  "type": "Feature",
  "properties": {
    "gn:admin1_code":"26.0",
    "gn:asciiname":"Simaniorang",
    "gn:country_code":"ID",
    "gn:dem":1004,
    "gn:feature_class":"P",
    "gn:feature_code":"PPL",
    "gn:name":"Simaniorang",
    "gn:population":0,
    "gn:timezone":"Asia/Jakarta",
    "iso:country":"ID",
    "name:ind_x_preferred":[
        "Simaniorang"
    ],
    "wof:name":"Simaniorang",
    "wof:placetype":"locality"
},
  "geometry": {"coordinates":[98.64579999999999,2.574],"type":"Point"}
}