{
  "type": "Feature",
  "properties": {
    "gn:admin1_code":"33.0",
    "gn:asciiname":"Kalapanunggal",
    "gn:country_code":"ID",
    "gn:dem":97,
    "gn:feature_class":"P",
    "gn:feature_code":"PPL",
    "gn:name":"Kalapanunggal",
    "gn:population":0,
    "gn:timezone":"Asia/Jakarta",
    "iso:country":"ID",
    "name:ind_x_preferred":[
        "Kalapanunggal"
    ],
    "wof:name":"Kalapanunggal",
    "wof:placetype":"locality"
},
  "geometry": {"coordinates":[105.96720000000001,-6.4357],"type":"Point"}
}