{
  "type": "Feature",
  "properties": {
    "gn:admin1_code":"7.0",
    "gn:asciiname":"Ngangkrik",
    "gn:country_code":"ID",
    "gn:dem":233,
    "gn:feature_class":"P",
    "gn:feature_code":"PPL",
    "gn:name":"Ngangkrik",
    "gn:population":0,
    "gn:timezone":"Asia/Jakarta",
    "iso:country":"ID",
    "wof:name":"Ngangkrik",
    "wof:placetype":"locality"
},
  "geometry": {"coordinates":[110.33833,-7.70111],"type":"Point"}
}