{
  "type": "Feature",
  "properties": {
    "gn:admin1_code":"30",
    "gn:asciiname":"Cileuweung",
    "gn:country_code":"ID",
    "gn:dem":267,
    "gn:feature_class":"P",
    "gn:feature_code":"PPL",
    "gn:name":"Cileuweung",
    "gn:population":0,
    "gn:timezone":"Asia/Jakarta",
    "iso:country":"ID",
    "name:ind_x_preferred":[
        "Cileuweung"
    ],
    "wof:name":"Cileuweung",
    "wof:placetype":"locality"
},
  "geometry": {"coordinates":[108.38361,-6.79361],"type":"Point"}
}