{
  "type": "Feature",
  "properties": {
    "gn:admin1_code":"30",
    "gn:asciiname":"Grenjeng",
    "gn:country_code":"ID",
    "gn:dem":24,
    "gn:feature_class":"P",
    "gn:feature_code":"PPL",
    "gn:name":"Grenjeng",
    "gn:population":0,
    "gn:timezone":"Asia/Jakarta",
    "iso:country":"ID",
    "name:ind_x_preferred":[
        "Grenjeng"
    ],
    "wof:name":"Grenjeng",
    "wof:placetype":"locality"
},
  "geometry": {"coordinates":[108.5342,-6.7506],"type":"Point"}
}