{
  "type": "Feature",
  "properties": {
    "gn:admin1_code":"15.0",
    "gn:asciiname":"Candipuro Dua",
    "gn:country_code":"ID",
    "gn:dem":25,
    "gn:feature_class":"P",
    "gn:feature_code":"PPL",
    "gn:name":"Candipuro Dua",
    "gn:population":0,
    "gn:timezone":"Asia/Jakarta",
    "iso:country":"ID",
    "name:ind_x_preferred":[
        "Candipuro Dua"
    ],
    "name:und_x_variant":[
        "Candipuro 2"
    ],
    "wof:name":"Candipuro Dua",
    "wof:placetype":"locality"
},
  "geometry": {"coordinates":[105.58902999999999,-5.54381],"type":"Point"}
}