{
  "type": "Feature",
  "properties": {
    "gn:admin1_code":"28.0",
    "gn:asciiname":"Raliusawelit",
    "gn:country_code":"ID",
    "gn:dem":18,
    "gn:feature_class":"P",
    "gn:feature_code":"PPL",
    "gn:name":"Raliusawelit",
    "gn:population":0,
    "gn:timezone":"Asia/Jayapura",
    "iso:country":"ID",
    "name:ind_x_preferred":[
        "Raliusawelit"
    ],
    "name:und_x_variant":[
        "Ralioe Sawelit"
    ],
    "wof:lang_x_official":[
        "ind"
    ],
    "wof:lang_x_spoken":[
        "ind",
        "eng"
    ],
    "wof:name":"Raliusawelit",
    "wof:placetype":"locality"
},
  "geometry": {"coordinates":[128.64437000000001,-2.84985],"type":"Point"}
}