{
  "type": "Feature",
  "properties": {
    "gn:admin1_code":"18.0",
    "gn:asciiname":"Majameti",
    "gn:country_code":"ID",
    "gn:dem":34,
    "gn:feature_class":"P",
    "gn:feature_code":"PPL",
    "gn:name":"Majameti",
    "gn:population":0,
    "gn:timezone":"Asia/Makassar",
    "iso:country":"ID",
    "name:ind_x_preferred":[
        "Majameti"
    ],
    "wof:name":"Majameti",
    "wof:placetype":"locality"
},
  "geometry": {"coordinates":[121.702,-8.59272],"type":"Point"}
}