{
  "type": "Feature",
  "properties": {
    "gn:admin1_code":"08",
    "gn:asciiname":"Kebanyer-barat",
    "gn:cc2":"ID",
    "gn:country_code":"ID",
    "gn:dem":16,
    "gn:feature_class":"P",
    "gn:feature_code":"PPL",
    "gn:name":"Kebanyer-barat",
    "gn:population":0,
    "gn:timezone":"Asia/Jakarta",
    "iso:country":"ID",
    "name:und_x_variant":[
        "Kebanjer-barat",
        "Kebanyer-barat"
    ],
    "wof:name":"Kebanyer-barat",
    "wof:placetype":"locality"
},
  "geometry": {"coordinates":[112.84944,-7.16361],"type":"Point"}
}