{
  "type": "Feature",
  "properties": {
    "gn:admin1_code":"30.0",
    "gn:asciiname":"Warungpeuteuy",
    "gn:country_code":"ID",
    "gn:dem":740,
    "gn:feature_class":"P",
    "gn:feature_code":"PPL",
    "gn:name":"Warungpeuteuy",
    "gn:population":0,
    "gn:timezone":"Asia/Jakarta",
    "iso:country":"ID",
    "name:ind_x_preferred":[
        "Warungpeuteuy"
    ],
    "name:und_x_variant":[
        "Warungpeuteuj",
        "Warungpeuteuy",
        "Waroengpeuteuj"
    ],
    "wof:lang_x_official":[
        "ind"
    ],
    "wof:lang_x_spoken":[
        "ind",
        "eng"
    ],
    "wof:name":"Warungpeuteuy",
    "wof:placetype":"locality"
},
  "geometry": {"coordinates":[107.9008,-7.1564],"type":"Point"}
}