{
  "type": "Feature",
  "properties": {
    "gn:admin1_code":"30.0",
    "gn:asciiname":"Kupel",
    "gn:country_code":"ID",
    "gn:dem":999,
    "gn:feature_class":"P",
    "gn:feature_code":"PPLA4",
    "gn:name":"Kupel",
    "gn:population":0,
    "gn:timezone":"Asia/Jakarta",
    "iso:country":"ID",
    "name:ind_x_preferred":[
        "Kupel"
    ],
    "wof:lang_x_official":[
        "ind"
    ],
    "wof:lang_x_spoken":[
        "ind",
        "eng"
    ],
    "wof:name":"Kupel",
    "wof:placetype":"locality"
},
  "geometry": {"coordinates":[107.1737,-7.076],"type":"Point"}
}