{
  "type": "Feature",
  "properties": {
    "gn:admin1_code":"8.0",
    "gn:asciiname":"Mojosewu",
    "gn:country_code":"ID",
    "gn:dem":35,
    "gn:feature_class":"P",
    "gn:feature_code":"PPL",
    "gn:name":"Mojosewu",
    "gn:population":0,
    "gn:timezone":"Asia/Jakarta",
    "iso:country":"ID",
    "name:ind_x_preferred":[
        "Mojosewu"
    ],
    "wof:name":"Mojosewu",
    "wof:placetype":"locality"
},
  "geometry": {"coordinates":[112.2051,-7.1282],"type":"Point"}
}