{
  "type": "Feature",
  "properties": {
    "gn:admin1_code":"8.0",
    "gn:asciiname":"Prajekan Kidul",
    "gn:country_code":"ID",
    "gn:dem":87,
    "gn:feature_class":"P",
    "gn:feature_code":"PPL",
    "gn:name":"Prajekan Kidul",
    "gn:population":0,
    "gn:timezone":"Asia/Jakarta",
    "iso:country":"ID",
    "name:ind_x_preferred":[
        "Prajekan Kidul"
    ],
    "wof:name":"Prajekan Kidul",
    "wof:placetype":"locality"
},
  "geometry": {"coordinates":[113.9789,-7.7974],"type":"Point"}
}