{
  "type": "Feature",
  "properties": {
    "gn:admin1_code":"38.0",
    "gn:asciiname":"Palli",
    "gn:country_code":"ID",
    "gn:dem":659,
    "gn:feature_class":"P",
    "gn:feature_code":"PPL",
    "gn:name":"Palli",
    "gn:population":0,
    "gn:timezone":"Asia/Makassar",
    "iso:country":"ID",
    "name:deu_x_preferred":[
        "Palli"
    ],
    "name:fin_x_preferred":[
        "Palli"
    ],
    "name:ind_x_preferred":[
        "Palli"
    ],
    "name:ita_x_preferred":[
        "Palli"
    ],
    "name:swe_x_preferred":[
        "Palli"
    ],
    "name:vol_x_preferred":[
        "Palli"
    ],
    "wof:name":"Palli",
    "wof:placetype":"locality"
},
  "geometry": {"coordinates":[119.98229000000001,-3.60431],"type":"Point"}
}