{
  "type": "Feature",
  "properties": {
    "gn:admin1_code":"28.0",
    "gn:asciiname":"Wakarleli",
    "gn:country_code":"ID",
    "gn:dem":21,
    "gn:feature_class":"P",
    "gn:feature_code":"PPL",
    "gn:name":"Wakarleli",
    "gn:population":0,
    "gn:timezone":"Asia/Jayapura",
    "iso:country":"ID",
    "name:und_x_variant":[
        "Wakarlili",
        "Wakarleli"
    ],
    "wof:name":"Wakarleli",
    "wof:placetype":"locality"
},
  "geometry": {"coordinates":[127.80535999999999,-8.1899],"type":"Point"}
}