{
  "type": "Feature",
  "properties": {
    "gn:admin1_code":"18.0",
    "gn:asciiname":"Tuapara",
    "gn:country_code":"ID",
    "gn:dem":152,
    "gn:feature_class":"P",
    "gn:feature_code":"PPL",
    "gn:name":"Tuapara",
    "gn:population":0,
    "gn:timezone":"Asia/Makassar",
    "iso:country":"ID",
    "name:ind_x_preferred":[
        "Tuapara"
    ],
    "wof:name":"Tuapara",
    "wof:placetype":"locality"
},
  "geometry": {"coordinates":[123.8758,-10.1733],"type":"Point"}
}