{
  "type": "Feature",
  "properties": {
    "gn:admin1_code":"18.0",
    "gn:asciiname":"Lempe",
    "gn:country_code":"ID",
    "gn:dem":528,
    "gn:feature_class":"P",
    "gn:feature_code":"PPL",
    "gn:name":"Lempe",
    "gn:population":0,
    "gn:timezone":"Asia/Makassar",
    "iso:country":"ID",
    "name:ceb_x_preferred":[
        "Lempe"
    ],
    "name:chv_x_preferred":[
        "\u041b\u0435\u043c\u043f\u0435"
    ],
    "name:deu_x_preferred":[
        "Lempe"
    ],
    "name:ind_x_preferred":[
        "Lempe"
    ],
    "name:rus_x_preferred":[
        "\u041b\u0435\u043c\u043f\u0435"
    ],
    "wof:lang_x_official":[
        "ind"
    ],
    "wof:lang_x_spoken":[
        "ind",
        "eng"
    ],
    "wof:name":"Lempe",
    "wof:placetype":"locality"
},
  "geometry": {"coordinates":[120.04340000000001,-8.7003],"type":"Point"}
}