{
  "type": "Feature",
  "properties": {
    "gn:admin1_code":"38.0",
    "gn:asciiname":"Larewa",
    "gn:country_code":"ID",
    "gn:dem":60,
    "gn:feature_class":"P",
    "gn:feature_code":"PPL",
    "gn:name":"Larewa",
    "gn:population":0,
    "gn:timezone":"Asia/Makassar",
    "iso:country":"ID",
    "name:ind_x_preferred":[
        "Larewa"
    ],
    "wof:name":"Larewa",
    "wof:placetype":"locality"
},
  "geometry": {"coordinates":[120.2821,-3.447],"type":"Point"}
}