{
  "type": "Feature",
  "properties": {
    "gn:admin1_code":"2",
    "gn:asciiname":"Mertasari",
    "gn:country_code":"ID",
    "gn:dem":34,
    "gn:feature_class":"P",
    "gn:feature_code":"PPL",
    "gn:name":"Mertasari",
    "gn:population":0,
    "gn:timezone":"Asia/Makassar",
    "iso:country":"ID",
    "name:ind_x_preferred":[
        "Mertasari"
    ],
    "wof:name":"Mertasari",
    "wof:placetype":"locality"
},
  "geometry": {"coordinates":[114.8391,-8.2085],"type":"Point"}
}