{
  "type": "Feature",
  "properties": {
    "gn:admin1_code":"8.0",
    "gn:asciiname":"Sanggan",
    "gn:country_code":"ID",
    "gn:dem":23,
    "gn:feature_class":"P",
    "gn:feature_code":"PPL",
    "gn:name":"Sanggan",
    "gn:population":0,
    "gn:timezone":"Asia/Jakarta",
    "iso:country":"ID",
    "name:ara_x_preferred":[
        "\u0633\u0627\u0646\u062c\u0627\u0646"
    ],
    "name:ben_x_preferred":[
        "\u09b8\u09be\u0982\u0997\u09be\u09a8"
    ],
    "name:deu_x_preferred":[
        "Sanggan He"
    ],
    "name:ell_x_preferred":[
        "\u03a3\u03b1\u03bd\u03b3\u03ba\u03ac\u03bd"
    ],
    "name:fas_x_preferred":[
        "\u0633\u0627\u0646\u06af\u0627\u0646"
    ],
    "name:fra_x_preferred":[
        "Sanggan"
    ],
    "name:heb_x_preferred":[
        "\u05e1\u05d0\u05e0\u05d2\u05d2\u05df"
    ],
    "name:hin_x_preferred":[
        "\u0938\u0902\u0917\u0928"
    ],
    "name:hun_x_preferred":[
        "Sanggan"
    ],
    "name:ind_x_preferred":[
        "Sanggan"
    ],
    "name:ita_x_preferred":[
        "Sanggan"
    ],
    "name:jpn_x_preferred":[
        "\u6851\u4e7e\u6cb3"
    ],
    "name:kor_x_preferred":[
        "\uc0c1\uac04"
    ],
    "name:nld_x_preferred":[
        "Sanggan"
    ],
    "name:pol_x_preferred":[
        "Sanggan"
    ],
    "name:por_x_preferred":[
        "Sanggan"
    ],
    "name:rus_x_preferred":[
        "\u0432\u043e\u0434\u043e\u0445\u0440\u0430\u043d\u0438\u043b\u0438\u0449\u0435 \u0413\u0443\u0430\u043d\u044c\u0442\u0438\u043d"
    ],
    "name:spa_x_preferred":[
        "Sanggan"
    ],
    "name:swe_x_preferred":[
        "Sanggan He"
    ],
    "name:tur_x_preferred":[
        "Sanggan"
    ],
    "name:ukr_x_preferred":[
        "\u0421\u0435\u043d\u0433\u0430\u043d\u043d"
    ],
    "name:urd_x_preferred":[
        "\u0633\u0627\u0646\u06af\u0627\u0646"
    ],
    "name:vie_x_preferred":[
        "S\u00f4ng Tang Can"
    ],
    "name:zho_cn_x_preferred":[
        "\u6851\u5e72\u6cb3"
    ],
    "name:zho_tw_x_preferred":[
        "\u6851\u4e7e\u6cb3"
    ],
    "wof:lang_x_official":[
        "ind"
    ],
    "wof:lang_x_spoken":[
        "ind",
        "eng"
    ],
    "wof:name":"Sanggan",
    "wof:placetype":"locality"
},
  "geometry": {"coordinates":[113.3058,-7.2048],"type":"Point"}
}