{
  "type": "Feature",
  "properties": {
    "gn:admin1_code":"38",
    "gn:asciiname":"Pangkalan",
    "gn:country_code":"ID",
    "gn:dem":11,
    "gn:feature_class":"P",
    "gn:feature_code":"PPL",
    "gn:name":"Pangkalan",
    "gn:population":0,
    "gn:timezone":"Asia/Makassar",
    "iso:country":"ID",
    "name:ceb_x_preferred":[
        "Pangkalan"
    ],
    "name:ind_x_preferred":[
        "Pangkalan"
    ],
    "name:nld_x_preferred":[
        "Pangkalan"
    ],
    "name:swe_x_preferred":[
        "Pangkalan"
    ],
    "wof:lang_x_official":[
        "ind"
    ],
    "wof:lang_x_spoken":[
        "ind",
        "eng"
    ],
    "wof:name":"Pangkalan",
    "wof:placetype":"locality"
},
  "geometry": {"coordinates":[119.4498,-5.4661],"type":"Point"}
}