{
  "type": "Feature",
  "properties": {
    "gn:admin1_code":"30",
    "gn:asciiname":"Sasaktiga",
    "gn:country_code":"ID",
    "gn:dem":19,
    "gn:feature_class":"P",
    "gn:feature_code":"PPL",
    "gn:name":"Sasaktiga",
    "gn:population":0,
    "gn:timezone":"Asia/Jakarta",
    "iso:country":"ID",
    "name:ind_x_preferred":[
        "Sasaktiga"
    ],
    "name:und_x_variant":[
        "Sasaktiga 1",
        "Sasaktiga Satu"
    ],
    "wof:lang_x_official":[
        "ind"
    ],
    "wof:lang_x_spoken":[
        "ind",
        "eng"
    ],
    "wof:name":"Sasaktiga",
    "wof:placetype":"locality"
},
  "geometry": {"coordinates":[107.06917,-6.24111],"type":"Point"}
}