{
  "type": "Feature",
  "properties": {
    "gn:admin1_code":"7",
    "gn:asciiname":"Buling Lor",
    "gn:country_code":"ID",
    "gn:dem":789,
    "gn:feature_class":"P",
    "gn:feature_code":"PPL",
    "gn:name":"Buling Lor",
    "gn:population":0,
    "gn:timezone":"Asia/Jakarta",
    "iso:country":"ID",
    "name:ind_x_preferred":[
        "Buling Lor"
    ],
    "wof:name":"Buling Lor",
    "wof:placetype":"locality"
},
  "geometry": {"coordinates":[111.22056000000001,-7.76222],"type":"Point"}
}