{
  "type": "Feature",
  "properties": {
    "gn:admin1_code":"30",
    "gn:asciiname":"Sukamulya",
    "gn:country_code":"ID",
    "gn:dem":1039,
    "gn:feature_class":"P",
    "gn:feature_code":"PPL",
    "gn:name":"Sukamulya",
    "gn:population":0,
    "gn:timezone":"Asia/Jakarta",
    "iso:country":"ID",
    "name:ind_x_preferred":[
        "Sukamulya"
    ],
    "wof:name":"Sukamulya",
    "wof:placetype":"locality"
},
  "geometry": {"coordinates":[107.8086,-7.2192],"type":"Point"}
}