{
  "type": "Feature",
  "properties": {
    "gn:admin1_code":"7",
    "gn:asciiname":"Trukan",
    "gn:country_code":"ID",
    "gn:dem":61,
    "gn:feature_class":"P",
    "gn:feature_code":"PPL",
    "gn:name":"Trukan",
    "gn:population":0,
    "gn:timezone":"Asia/Jakarta",
    "iso:country":"ID",
    "name:ind_x_preferred":[
        "Trukan"
    ],
    "wof:name":"Trukan",
    "wof:placetype":"locality"
},
  "geometry": {"coordinates":[109.99333,-7.72722],"type":"Point"}
}