{
  "type": "Feature",
  "properties": {
    "gn:admin1_code":"33.0",
    "gn:asciiname":"Pasirhaur",
    "gn:country_code":"ID",
    "gn:dem":77,
    "gn:feature_class":"P",
    "gn:feature_code":"PPLA4",
    "gn:name":"Pasirhaur",
    "gn:population":0,
    "gn:timezone":"Asia/Jakarta",
    "iso:country":"ID",
    "name:ind_x_preferred":[
        "Pasirhaur"
    ],
    "wof:name":"Pasirhaur",
    "wof:placetype":"locality"
},
  "geometry": {"coordinates":[106.01673999999998,-6.77673],"type":"Point"}
}