{
  "type": "Feature",
  "properties": {
    "gn:admin1_code":"07",
    "gn:asciiname":"Pijenan",
    "gn:country_code":"ID",
    "gn:dem":375,
    "gn:feature_class":"P",
    "gn:feature_code":"PPL",
    "gn:name":"Pijenan",
    "gn:population":0,
    "gn:timezone":"Asia/Jakarta",
    "iso:country":"ID",
    "wof:name":"Pijenan",
    "wof:placetype":"locality"
},
  "geometry": {"coordinates":[110.51056,-7.66361],"type":"Point"}
}