{
  "type": "Feature",
  "properties": {
    "gn:admin1_code":"41",
    "gn:asciiname":"Lampa",
    "gn:country_code":"ID",
    "gn:dem":13,
    "gn:feature_class":"P",
    "gn:feature_code":"PPL",
    "gn:name":"Lampa",
    "gn:population":0,
    "gn:timezone":"Asia/Makassar",
    "iso:country":"ID",
    "name:bel_x_preferred":[
        "\u041b\u044f\u043c\u043f\u0430"
    ],
    "name:bul_x_preferred":[
        "\u041b\u0430\u043c\u043f\u0430"
    ],
    "name:ceb_x_preferred":[
        "Lampa"
    ],
    "name:ces_x_preferred":[
        "Lampa"
    ],
    "name:deu_x_preferred":[
        "Lampa"
    ],
    "name:fra_x_preferred":[
        "Lampa"
    ],
    "name:ind_x_preferred":[
        "Lampa"
    ],
    "name:ita_x_preferred":[
        "Lampa"
    ],
    "name:jpn_x_preferred":[
        "\u30e9\u30f3\u30d1"
    ],
    "name:nld_x_preferred":[
        "Lampa"
    ],
    "name:pol_x_preferred":[
        "Lampa"
    ],
    "name:por_x_preferred":[
        "Lampa"
    ],
    "name:rus_x_preferred":[
        "\u041b\u0430\u043c\u043f\u0430"
    ],
    "name:slk_x_preferred":[
        "Lampa"
    ],
    "name:spa_x_preferred":[
        "Lampa"
    ],
    "name:srp_x_preferred":[
        "\u041b\u0430\u043c\u043f\u0430"
    ],
    "name:swe_x_preferred":[
        "Lampa"
    ],
    "name:ukr_x_preferred":[
        "\u041b\u0430\u043c\u043f\u0430"
    ],
    "wof:lang_x_official":[
        "ind"
    ],
    "wof:lang_x_spoken":[
        "ind",
        "eng"
    ],
    "wof:name":"Lampa",
    "wof:placetype":"locality"
},
  "geometry": {"coordinates":[119.18089999999999,-3.4041],"type":"Point"}
}