{
  "type": "Feature",
  "properties": {
    "gn:admin1_code":"41",
    "gn:asciiname":"Lampa",
    "gn:country_code":"ID",
    "gn:dem":13,
    "gn:feature_class":"P",
    "gn:feature_code":"PPL",
    "gn:name":"Lampa",
    "gn:population":0,
    "gn:timezone":"Asia/Makassar",
    "iso:country":"ID",
    "name:ind_x_preferred":[
        "Lampa"
    ],
    "wof:name":"Lampa",
    "wof:placetype":"locality"
},
  "geometry": {"coordinates":[119.18089999999999,-3.4041],"type":"Point"}
}