{
  "type": "Feature",
  "properties": {
    "gn:admin1_code":"8.0",
    "gn:asciiname":"Ngantakulung",
    "gn:country_code":"ID",
    "gn:dem":64,
    "gn:feature_class":"P",
    "gn:feature_code":"PPL",
    "gn:name":"Ngantakulung",
    "gn:population":0,
    "gn:timezone":"Asia/Jakarta",
    "iso:country":"ID",
    "name:ind_x_preferred":[
        "Ngantakulung"
    ],
    "name:und_x_variant":[
        "Ngantakngulung"
    ],
    "wof:name":"Ngantakulung",
    "wof:placetype":"locality"
},
  "geometry": {"coordinates":[111.23888999999998,-8.25083],"type":"Point"}
}