{
  "type": "Feature",
  "properties": {
    "gn:admin1_code":"18.0",
    "gn:asciiname":"Perseja",
    "gn:country_code":"ID",
    "gn:dem":41,
    "gn:feature_class":"P",
    "gn:feature_code":"PPL",
    "gn:name":"Perseja",
    "gn:population":0,
    "gn:timezone":"Asia/Makassar",
    "iso:country":"ID",
    "name:ind_x_preferred":[
        "Perseja"
    ],
    "wof:name":"Perseja",
    "wof:placetype":"locality"
},
  "geometry": {"coordinates":[122.9212,-8.2093],"type":"Point"}
}