{
  "type": "Feature",
  "properties": {
    "gn:admin1_code":"37",
    "gn:asciiname":"Lubukkemodan",
    "gn:country_code":"ID",
    "gn:dem":7,
    "gn:feature_class":"P",
    "gn:feature_code":"PPL",
    "gn:name":"Lubukkemodan",
    "gn:population":0,
    "gn:timezone":"Asia/Jakarta",
    "iso:country":"ID",
    "name:ind_x_preferred":[
        "Lubukkemodan"
    ],
    "wof:name":"Lubukkemodan",
    "wof:placetype":"locality"
},
  "geometry": {"coordinates":[101.3078,1.0328],"type":"Point"}
}