{
  "type": "Feature",
  "properties": {
    "gn:admin1_code":"22.0",
    "gn:asciiname":"Lakansai",
    "gn:country_code":"ID",
    "gn:dem":30,
    "gn:feature_class":"P",
    "gn:feature_code":"PPL",
    "gn:name":"Lakansai",
    "gn:population":0,
    "gn:timezone":"Asia/Makassar",
    "iso:country":"ID",
    "name:ind_x_preferred":[
        "Lakansai"
    ],
    "wof:name":"Lakansai",
    "wof:placetype":"locality"
},
  "geometry": {"coordinates":[123.1567,-4.5276],"type":"Point"}
}