{
  "type": "Feature",
  "properties": {
    "gn:admin1_code":"7.0",
    "gn:asciiname":"Sukoyoso",
    "gn:country_code":"ID",
    "gn:dem":1174,
    "gn:feature_class":"P",
    "gn:feature_code":"PPL",
    "gn:name":"Sukoyoso",
    "gn:population":0,
    "gn:timezone":"Asia/Jakarta",
    "iso:country":"ID",
    "name:und_x_variant":[
        "Sokojoso",
        "Sokoyoso",
        "Sukoyoso"
    ],
    "wof:lang_x_official":[
        "ind"
    ],
    "wof:lang_x_spoken":[
        "ind",
        "eng"
    ],
    "wof:name":"Sukoyoso",
    "wof:placetype":"locality"
},
  "geometry": {"coordinates":[110.06083,-7.44861],"type":"Point"}
}