{
  "type": "Feature",
  "properties": {
    "gn:admin1_code":"30",
    "gn:asciiname":"Cibening Tiga",
    "gn:country_code":"ID",
    "gn:dem":19,
    "gn:feature_class":"P",
    "gn:feature_code":"PPL",
    "gn:name":"Cibening Tiga",
    "gn:population":0,
    "gn:timezone":"Asia/Jakarta",
    "iso:country":"ID",
    "wof:name":"Cibening Tiga",
    "wof:placetype":"locality"
},
  "geometry": {"coordinates":[106.94750000000001,-6.255],"type":"Point"}
}