{
  "type": "Feature",
  "properties": {
    "gn:admin1_code":"8",
    "gn:asciiname":"Tamansari",
    "gn:country_code":"ID",
    "gn:dem":163,
    "gn:feature_class":"P",
    "gn:feature_code":"PPL",
    "gn:name":"Tamansari",
    "gn:population":0,
    "gn:timezone":"Asia/Jakarta",
    "iso:country":"ID",
    "name:ind_x_preferred":[
        "Tamansari"
    ],
    "wof:name":"Tamansari",
    "wof:placetype":"locality"
},
  "geometry": {"coordinates":[114.3109,-8.2334],"type":"Point"}
}