{
  "type": "Feature",
  "properties": {
    "gn:admin1_code":"30",
    "gn:asciiname":"Serang",
    "gn:country_code":"ID",
    "gn:dem":442,
    "gn:feature_class":"P",
    "gn:feature_code":"PPL",
    "gn:name":"Serang",
    "gn:population":0,
    "gn:timezone":"Asia/Jakarta",
    "iso:country":"ID",
    "name:ace_x_preferred":[
        "Serang"
    ],
    "name:ara_x_preferred":[
        "\u0633\u064a\u0631\u0627\u0646\u063a"
    ],
    "name:bel_x_preferred":[
        "\u0421\u0435\u0440\u0430\u043d\u0433"
    ],
    "name:cat_x_preferred":[
        "Serang"
    ],
    "name:ceb_x_preferred":[
        "Serang"
    ],
    "name:che_x_preferred":[
        "\u0421\u0435\u0440\u0430\u043d\u0433"
    ],
    "name:deu_x_preferred":[
        "Serang"
    ],
    "name:epo_x_preferred":[
        "Serang"
    ],
    "name:eus_x_preferred":[
        "Serang"
    ],
    "name:fas_x_preferred":[
        "\u0633\u0631\u0627\u0646\u06af"
    ],
    "name:fij_x_preferred":[
        "Serang"
    ],
    "name:fin_x_preferred":[
        "Serang"
    ],
    "name:fra_x_preferred":[
        "Serang"
    ],
    "name:gor_x_preferred":[
        "Kota Serang"
    ],
    "name:heb_x_preferred":[
        "\u05e1\u05e8\u05e0\u05d2"
    ],
    "name:hun_x_preferred":[
        "Serang"
    ],
    "name:ind_x_preferred":[
        "Serang"
    ],
    "name:ind_x_variant":[
        "Kota Serang"
    ],
    "name:ita_x_preferred":[
        "Serang"
    ],
    "name:jav_x_preferred":[
        "Kutha Serang"
    ],
    "name:jpn_x_preferred":[
        "\u30bb\u30e9\u30f3"
    ],
    "name:kal_x_preferred":[
        "Serang"
    ],
    "name:kat_x_preferred":[
        "\u10e1\u10d4\u10e0\u10d0\u10dc\u10d2\u10d8"
    ],
    "name:lit_x_preferred":[
        "Serangas"
    ],
    "name:mal_x_preferred":[
        "\u0d38\u0d46\u0d30\u0d3e\u0d19\u0d4d"
    ],
    "name:mlg_x_preferred":[
        "Kota Serang"
    ],
    "name:mri_x_preferred":[
        "Serang"
    ],
    "name:msa_x_preferred":[
        "Kota Serang"
    ],
    "name:nld_x_preferred":[
        "Serang"
    ],
    "name:nor_x_preferred":[
        "Serang"
    ],
    "name:pnb_x_preferred":[
        "\u0633\u06cc\u0631\u0627\u0646\u06af"
    ],
    "name:pol_x_preferred":[
        "Serang"
    ],
    "name:por_x_preferred":[
        "Serang"
    ],
    "name:ron_x_preferred":[
        "Serang"
    ],
    "name:rus_x_preferred":[
        "\u0421\u0435\u0440\u0430\u043d\u0433"
    ],
    "name:spa_x_preferred":[
        "Serang"
    ],
    "name:sun_x_preferred":[
        "Kota S\u00e9rang"
    ],
    "name:swa_x_preferred":[
        "Serang"
    ],
    "name:swe_x_preferred":[
        "Serang"
    ],
    "name:tha_x_preferred":[
        "\u0e40\u0e0b\u0e23\u0e31\u0e07"
    ],
    "name:tur_x_preferred":[
        "Serang"
    ],
    "name:ukr_x_preferred":[
        "\u0421\u0435\u0440\u0430\u043d\u0433"
    ],
    "name:urd_x_preferred":[
        "\u0633\u06cc\u0631\u0627\u0646\u06af"
    ],
    "name:war_x_preferred":[
        "Serang"
    ],
    "wof:lang_x_official":[
        "ind"
    ],
    "wof:lang_x_spoken":[
        "ind",
        "eng"
    ],
    "wof:name":"Serang",
    "wof:placetype":"locality"
},
  "geometry": {"coordinates":[106.79139000000001,-6.88778],"type":"Point"}
}