{
  "type": "Feature",
  "properties": {
    "gn:admin1_code":"26",
    "gn:asciiname":"Siopat-opat",
    "gn:country_code":"ID",
    "gn:dem":252,
    "gn:feature_class":"P",
    "gn:feature_code":"PPL",
    "gn:name":"Siopat-opat",
    "gn:population":0,
    "gn:timezone":"Asia/Jakarta",
    "iso:country":"ID",
    "name:ind_x_preferred":[
        "Siopat-opat"
    ],
    "wof:name":"Siopat-opat",
    "wof:placetype":"locality"
},
  "geometry": {"coordinates":[99.17243000000001,1.35155],"type":"Point"}
}