{
  "type": "Feature",
  "properties": {
    "gn:admin1_code":"1.0",
    "gn:asciiname":"Ujongtankaji",
    "gn:country_code":"ID",
    "gn:dem":1021,
    "gn:feature_class":"P",
    "gn:feature_code":"PPL",
    "gn:name":"Ujongtankaji",
    "gn:population":0,
    "gn:timezone":"Asia/Jakarta",
    "iso:country":"ID",
    "name:ind_x_preferred":[
        "Ujongtankaji"
    ],
    "name:und_x_variant":[
        "Oedjongtankajdji",
        "Udjungtankajdji",
        "Udjongtankajdji",
        "Ujungtankayji"
    ],
    "wof:lang_x_official":[
        "ind"
    ],
    "wof:lang_x_spoken":[
        "ind",
        "eng"
    ],
    "wof:name":"Ujongtankaji",
    "wof:placetype":"locality"
},
  "geometry": {"coordinates":[97.2038,3.5319],"type":"Point"}
}