{
  "type": "Feature",
  "properties": {
    "gn:admin1_code":"08",
    "gn:asciiname":"Penjalinan",
    "gn:country_code":"ID",
    "gn:dem":363,
    "gn:feature_class":"P",
    "gn:feature_code":"PPL",
    "gn:name":"Penjalinan",
    "gn:population":0,
    "gn:timezone":"Asia/Jakarta",
    "iso:country":"ID",
    "name:ind_x_preferred":[
        "Penjalinan"
    ],
    "name:und_x_variant":[
        "Pendjalinan"
    ],
    "wof:lang_x_official":[
        "ind"
    ],
    "wof:lang_x_spoken":[
        "ind",
        "eng"
    ],
    "wof:name":"Penjalinan",
    "wof:placetype":"locality"
},
  "geometry": {"coordinates":[112.6182,-8.1685],"type":"Point"}
}