{
  "type": "Feature",
  "properties": {
    "gn:admin1_code":"26.0",
    "gn:asciiname":"Sosor Gande",
    "gn:country_code":"ID",
    "gn:dem":1529,
    "gn:feature_class":"P",
    "gn:feature_code":"PPL",
    "gn:name":"Sosor Gande",
    "gn:population":0,
    "gn:timezone":"Asia/Jakarta",
    "iso:country":"ID",
    "name:ind_x_preferred":[
        "Sosor Gande"
    ],
    "wof:name":"Sosor Gande",
    "wof:placetype":"locality"
},
  "geometry": {"coordinates":[98.7834,2.5949],"type":"Point"}
}