{
  "type": "Feature",
  "properties": {
    "gn:admin1_code":"30.0",
    "gn:asciiname":"Penclut",
    "gn:country_code":"ID",
    "gn:dem":937,
    "gn:feature_class":"P",
    "gn:feature_code":"PPL",
    "gn:name":"Penclut",
    "gn:population":0,
    "gn:timezone":"Asia/Jakarta",
    "iso:country":"ID",
    "name:ind_x_preferred":[
        "Penclut"
    ],
    "wof:name":"Penclut",
    "wof:placetype":"locality"
},
  "geometry": {"coordinates":[107.9263,-7.3068],"type":"Point"}
}