{
  "type": "Feature",
  "properties": {
    "gn:admin1_code":"08",
    "gn:asciiname":"Sadah Laok",
    "gn:country_code":"ID",
    "gn:dem":92,
    "gn:feature_class":"P",
    "gn:feature_code":"PPL",
    "gn:name":"Sadah Laok",
    "gn:population":0,
    "gn:timezone":"Asia/Jakarta",
    "iso:country":"ID",
    "name:ind_x_preferred":[
        "Sadah Laok"
    ],
    "name:und_x_variant":[
        "Sadah"
    ],
    "wof:name":"Sadah Laok",
    "wof:placetype":"locality"
},
  "geometry": {"coordinates":[112.9136,-7.0603],"type":"Point"}
}