{
  "type": "Feature",
  "properties": {
    "gn:admin1_code":"7",
    "gn:asciiname":"Karangdoro",
    "gn:country_code":"ID",
    "gn:dem":51,
    "gn:feature_class":"P",
    "gn:feature_code":"PPL",
    "gn:name":"Karangdoro",
    "gn:population":0,
    "gn:timezone":"Asia/Jakarta",
    "iso:country":"ID",
    "name:ind_x_preferred":[
        "Karangdoro"
    ],
    "wof:name":"Karangdoro",
    "wof:placetype":"locality"
},
  "geometry": {"coordinates":[110.7586,-6.7319],"type":"Point"}
}