{
  "type": "Feature",
  "properties": {
    "gn:admin1_code":"7",
    "gn:asciiname":"Kendil",
    "gn:country_code":"ID",
    "gn:dem":389,
    "gn:feature_class":"P",
    "gn:feature_code":"PPL",
    "gn:name":"Kendil",
    "gn:population":0,
    "gn:timezone":"Asia/Jakarta",
    "iso:country":"ID",
    "name:ind_x_preferred":[
        "Kendil"
    ],
    "wof:name":"Kendil",
    "wof:placetype":"locality"
},
  "geometry": {"coordinates":[111.03055999999999,-7.65667],"type":"Point"}
}