{
  "type": "Feature",
  "properties": {
    "gn:admin1_code":"17",
    "gn:asciiname":"Ladon",
    "gn:country_code":"ID",
    "gn:dem":151,
    "gn:feature_class":"P",
    "gn:feature_code":"PPL",
    "gn:name":"Ladon",
    "gn:population":0,
    "gn:timezone":"Asia/Makassar",
    "iso:country":"ID",
    "name:als_x_preferred":[
        "Ladon"
    ],
    "name:ben_x_preferred":[
        "\u09b2\u09be\u09a6\u09a8"
    ],
    "name:bre_x_preferred":[
        "Ladon"
    ],
    "name:cat_x_preferred":[
        "Lad\u00f3"
    ],
    "name:deu_x_preferred":[
        "Ladon"
    ],
    "name:fra_x_preferred":[
        "Ladon"
    ],
    "name:hye_x_preferred":[
        "\u053c\u0561\u0564\u0578\u0576"
    ],
    "name:ind_x_preferred":[
        "Ladon"
    ],
    "name:nld_x_preferred":[
        "Ladon"
    ],
    "name:oci_x_preferred":[
        "Ladon"
    ],
    "name:pol_x_preferred":[
        "Ladon"
    ],
    "name:por_x_preferred":[
        "Lad\u00e3o"
    ],
    "name:rus_x_preferred":[
        "\u041b\u0430\u0434\u043e\u043d"
    ],
    "name:slk_x_preferred":[
        "Lad\u00f3n"
    ],
    "name:spa_x_preferred":[
        "Lad\u00f3n"
    ],
    "name:ukr_x_preferred":[
        "\u041b\u0430\u0434\u043e\u043d"
    ],
    "wof:lang_x_official":[
        "ind"
    ],
    "wof:lang_x_spoken":[
        "ind",
        "eng"
    ],
    "wof:name":"Ladon",
    "wof:placetype":"locality"
},
  "geometry": {"coordinates":[116.5647,-8.5794],"type":"Point"}
}