{
  "type": "Feature",
  "properties": {
    "gn:admin1_code":"26",
    "gn:asciiname":"Runding",
    "gn:country_code":"ID",
    "gn:dem":288,
    "gn:feature_class":"P",
    "gn:feature_code":"PPL",
    "gn:name":"Runding",
    "gn:population":0,
    "gn:timezone":"Asia/Jakarta",
    "iso:country":"ID",
    "name:ceb_x_preferred":[
        "Runding"
    ],
    "name:deu_x_preferred":[
        "Runding"
    ],
    "name:epo_x_preferred":[
        "Runding"
    ],
    "name:eus_x_preferred":[
        "Runding"
    ],
    "name:fas_x_preferred":[
        "\u0631\u0648\u0646\u062f\u06cc\u0646\u06af"
    ],
    "name:fra_x_preferred":[
        "Runding"
    ],
    "name:hun_x_preferred":[
        "Runding"
    ],
    "name:hye_x_preferred":[
        "\u054c\u0578\u0582\u0576\u0564\u056b\u0576\u0563"
    ],
    "name:ind_x_preferred":[
        "Runding"
    ],
    "name:ita_x_preferred":[
        "Runding"
    ],
    "name:kaz_x_preferred":[
        "\u0420\u0443\u043d\u0434\u0438\u043d\u0433"
    ],
    "name:kir_x_preferred":[
        "\u0420\u0443\u043d\u0434\u0438\u043d\u0433"
    ],
    "name:lmo_x_preferred":[
        "Runding"
    ],
    "name:msa_x_preferred":[
        "Runding"
    ],
    "name:nld_x_preferred":[
        "Runding"
    ],
    "name:pol_x_preferred":[
        "Runding"
    ],
    "name:por_x_preferred":[
        "Runding"
    ],
    "name:ron_x_preferred":[
        "Runding"
    ],
    "name:rus_x_preferred":[
        "\u0420\u0443\u043d\u0434\u0438\u043d\u0433"
    ],
    "name:spa_x_preferred":[
        "Runding"
    ],
    "name:srp_x_preferred":[
        "\u0420\u0443\u043d\u0434\u0438\u043d\u0433"
    ],
    "name:ukr_x_preferred":[
        "\u0420\u0443\u043d\u0434\u0456\u043d\u0433"
    ],
    "name:uzb_x_preferred":[
        "Runding"
    ],
    "name:vie_x_preferred":[
        "Runding"
    ],
    "name:vol_x_preferred":[
        "Runding"
    ],
    "name:war_x_preferred":[
        "Runding"
    ],
    "wof:lang_x_official":[
        "ind"
    ],
    "wof:lang_x_spoken":[
        "ind",
        "eng"
    ],
    "wof:name":"Runding",
    "wof:placetype":"locality"
},
  "geometry": {"coordinates":[99.50149999999999,0.8492],"type":"Point"}
}