{
  "type": "Feature",
  "properties": {
    "gn:admin1_code":"26",
    "gn:asciiname":"Runding",
    "gn:country_code":"ID",
    "gn:dem":288,
    "gn:feature_class":"P",
    "gn:feature_code":"PPL",
    "gn:name":"Runding",
    "gn:population":0,
    "gn:timezone":"Asia/Jakarta",
    "iso:country":"ID",
    "name:ind_x_preferred":[
        "Runding"
    ],
    "wof:name":"Runding",
    "wof:placetype":"locality"
},
  "geometry": {"coordinates":[99.50149999999999,0.8492],"type":"Point"}
}