{
  "type": "Feature",
  "properties": {
    "gn:admin1_code":"7.0",
    "gn:asciiname":"Distrikan",
    "gn:country_code":"ID",
    "gn:dem":586,
    "gn:feature_class":"P",
    "gn:feature_code":"PPL",
    "gn:name":"Distrikan",
    "gn:population":0,
    "gn:timezone":"Asia/Jakarta",
    "iso:country":"ID",
    "wof:name":"Distrikan",
    "wof:placetype":"locality"
},
  "geometry": {"coordinates":[110.17833,-7.31528],"type":"Point"}
}