{
  "type": "Feature",
  "properties": {
    "gn:admin1_code":"11.0",
    "gn:asciiname":"Sei Raya",
    "gn:country_code":"ID",
    "gn:dem":24,
    "gn:feature_class":"P",
    "gn:feature_code":"PPL",
    "gn:name":"Sei Raya",
    "gn:population":0,
    "gn:timezone":"Asia/Pontianak",
    "iso:country":"ID",
    "name:ind_x_preferred":[
        "Sei Raya"
    ],
    "wof:name":"Sei Raya",
    "wof:placetype":"locality"
},
  "geometry": {"coordinates":[110.33523999999998,0.14806],"type":"Point"}
}