{
  "type": "Feature",
  "properties": {
    "gn:admin1_code":"15.0",
    "gn:asciiname":"Umbulalirahman",
    "gn:country_code":"ID",
    "gn:dem":620,
    "gn:feature_class":"P",
    "gn:feature_code":"PPL",
    "gn:name":"Umbulalirahman",
    "gn:population":0,
    "gn:timezone":"Asia/Jakarta",
    "iso:country":"ID",
    "name:ind_x_preferred":[
        "Umbulalirahman"
    ],
    "wof:name":"Umbulalirahman",
    "wof:placetype":"locality"
},
  "geometry": {"coordinates":[104.64879000000001,-5.09538],"type":"Point"}
}