{
  "type": "Feature",
  "properties": {
    "gn:admin1_code":"26",
    "gn:asciiname":"Hutatambunan",
    "gn:country_code":"ID",
    "gn:dem":1205,
    "gn:feature_class":"P",
    "gn:feature_code":"PPL",
    "gn:name":"Hutatambunan",
    "gn:population":0,
    "gn:timezone":"Asia/Jakarta",
    "iso:country":"ID",
    "name:ind_x_preferred":[
        "Hutatambunan"
    ],
    "wof:name":"Hutatambunan",
    "wof:placetype":"locality"
},
  "geometry": {"coordinates":[99.15179999999999,2.0078],"type":"Point"}
}