{
  "type": "Feature",
  "properties": {
    "gn:admin1_code":"38",
    "gn:asciiname":"Buakangpaliang",
    "gn:country_code":"ID",
    "gn:dem":1437,
    "gn:feature_class":"P",
    "gn:feature_code":"PPL",
    "gn:name":"Buakangpaliang",
    "gn:population":0,
    "gn:timezone":"Asia/Makassar",
    "iso:country":"ID",
    "name:ind_x_preferred":[
        "Buakangpaliang"
    ],
    "wof:name":"Buakangpaliang",
    "wof:placetype":"locality"
},
  "geometry": {"coordinates":[119.931,-5.4258],"type":"Point"}
}