{
  "type": "Feature",
  "properties": {
    "gn:admin1_code":"38",
    "gn:asciiname":"Sidayu",
    "gn:country_code":"ID",
    "gn:dem":8,
    "gn:feature_class":"P",
    "gn:feature_code":"PPL",
    "gn:name":"Sidayu",
    "gn:population":0,
    "gn:timezone":"Asia/Makassar",
    "iso:country":"ID",
    "name:ind_x_preferred":[
        "Sidayu"
    ],
    "wof:name":"Sidayu",
    "wof:placetype":"locality"
},
  "geometry": {"coordinates":[119.3806,-5.3703],"type":"Point"}
}