{
  "type": "Feature",
  "properties": {
    "gn:admin1_code":"26.0",
    "gn:asciiname":"Sagala",
    "gn:country_code":"ID",
    "gn:dem":1069,
    "gn:feature_class":"P",
    "gn:feature_code":"PPL",
    "gn:name":"Sagala",
    "gn:population":0,
    "gn:timezone":"Asia/Jakarta",
    "iso:country":"ID",
    "name:ind_x_preferred":[
        "Sagala"
    ],
    "name:ita_x_preferred":[
        "Sagala"
    ],
    "name:kor_x_preferred":[
        "\uc0ac\uac08\ub77c"
    ],
    "name:por_x_preferred":[
        "Sagala"
    ],
    "name:tam_x_preferred":[
        "\u0b9a\u0b95\u0bb2\u0bbe"
    ],
    "name:uzb_x_preferred":[
        "Shakala"
    ],
    "name:zho_x_preferred":[
        "\u5962\u7faf\u7f57"
    ],
    "wof:lang_x_official":[
        "ind"
    ],
    "wof:lang_x_spoken":[
        "ind",
        "eng"
    ],
    "wof:name":"Sagala",
    "wof:placetype":"locality"
},
  "geometry": {"coordinates":[98.6313,2.6111],"type":"Point"}
}