{
  "type": "Feature",
  "properties": {
    "gn:admin1_code":"26.0",
    "gn:asciiname":"Sagala",
    "gn:country_code":"ID",
    "gn:dem":1069,
    "gn:feature_class":"P",
    "gn:feature_code":"PPL",
    "gn:name":"Sagala",
    "gn:population":0,
    "gn:timezone":"Asia/Jakarta",
    "iso:country":"ID",
    "name:ind_x_preferred":[
        "Sagala"
    ],
    "wof:name":"Sagala",
    "wof:placetype":"locality"
},
  "geometry": {"coordinates":[98.6313,2.6111],"type":"Point"}
}