{
  "type": "Feature",
  "properties": {
    "gn:admin1_code":"7",
    "gn:asciiname":"Peganjuran",
    "gn:country_code":"ID",
    "gn:dem":14,
    "gn:feature_class":"P",
    "gn:feature_code":"PPL",
    "gn:name":"Peganjuran",
    "gn:population":0,
    "gn:timezone":"Asia/Jakarta",
    "iso:country":"ID",
    "name:ind_x_preferred":[
        "Peganjuran"
    ],
    "wof:name":"Peganjuran",
    "wof:placetype":"locality"
},
  "geometry": {"coordinates":[110.0598,-6.9401],"type":"Point"}
}