{
  "type": "Feature",
  "properties": {
    "gn:admin1_code":"38",
    "gn:asciiname":"Buluseppie",
    "gn:country_code":"ID",
    "gn:dem":241,
    "gn:feature_class":"P",
    "gn:feature_code":"PPL",
    "gn:name":"Buluseppie",
    "gn:population":0,
    "gn:timezone":"Asia/Makassar",
    "iso:country":"ID",
    "name:ind_x_preferred":[
        "Buluseppie"
    ],
    "name:und_x_variant":[
        "Buhuseppie"
    ],
    "wof:lang_x_official":[
        "ind"
    ],
    "wof:lang_x_spoken":[
        "ind",
        "eng"
    ],
    "wof:name":"Buluseppie",
    "wof:placetype":"locality"
},
  "geometry": {"coordinates":[119.9725,-4.7869],"type":"Point"}
}