{
  "type": "Feature",
  "properties": {
    "gn:admin1_code":"17",
    "gn:asciiname":"Gubuktengak Timuk",
    "gn:country_code":"ID",
    "gn:dem":318,
    "gn:feature_class":"P",
    "gn:feature_code":"PPL",
    "gn:name":"Gubuktengak Timuk",
    "gn:population":0,
    "gn:timezone":"Asia/Makassar",
    "iso:country":"ID",
    "name:ind_x_preferred":[
        "Gubuktengak Timuk"
    ],
    "wof:name":"Gubuktengak Timuk",
    "wof:placetype":"locality"
},
  "geometry": {"coordinates":[116.4442,-8.6196],"type":"Point"}
}