{
  "type": "Feature",
  "properties": {
    "gn:admin1_code":"30.0",
    "gn:asciiname":"Cisaronge",
    "gn:country_code":"ID",
    "gn:dem":281,
    "gn:feature_class":"P",
    "gn:feature_code":"PPL",
    "gn:name":"Cisaronge",
    "gn:population":0,
    "gn:timezone":"Asia/Jakarta",
    "iso:country":"ID",
    "name:ind_x_preferred":[
        "Cisaronge"
    ],
    "wof:name":"Cisaronge",
    "wof:placetype":"locality"
},
  "geometry": {"coordinates":[108.1285,-7.5537],"type":"Point"}
}