{
  "type": "Feature",
  "properties": {
    "gn:admin1_code":"18.0",
    "gn:asciiname":"Elo",
    "gn:country_code":"ID",
    "gn:dem":539,
    "gn:feature_class":"P",
    "gn:feature_code":"PPL",
    "gn:name":"Elo",
    "gn:population":0,
    "gn:timezone":"Asia/Makassar",
    "iso:country":"ID",
    "name:ceb_x_preferred":[
        "Elo"
    ],
    "name:dan_x_preferred":[
        "Elo"
    ],
    "name:fin_x_preferred":[
        "Elo"
    ],
    "name:glg_x_preferred":[
        "Elo"
    ],
    "name:ind_x_preferred":[
        "Elo"
    ],
    "name:lit_x_preferred":[
        "Elo"
    ],
    "name:pol_x_preferred":[
        "Elo"
    ],
    "name:por_x_preferred":[
        "Elo"
    ],
    "name:ron_x_preferred":[
        "Elo"
    ],
    "name:spa_x_preferred":[
        "Elo"
    ],
    "name:vep_x_preferred":[
        "Elo"
    ],
    "name:vie_x_preferred":[
        "Elo"
    ],
    "wof:lang_x_official":[
        "ind"
    ],
    "wof:lang_x_spoken":[
        "ind",
        "eng"
    ],
    "wof:name":"Elo",
    "wof:placetype":"locality"
},
  "geometry": {"coordinates":[124.3982,-10.052],"type":"Point"}
}