{
  "type": "Feature",
  "properties": {
    "gn:admin1_code":"7",
    "gn:asciiname":"Sokorejo",
    "gn:country_code":"ID",
    "gn:dem":11,
    "gn:feature_class":"P",
    "gn:feature_code":"PPL",
    "gn:name":"Sokorejo",
    "gn:population":0,
    "gn:timezone":"Asia/Jakarta",
    "iso:country":"ID",
    "name:ind_x_preferred":[
        "Sokorejo"
    ],
    "wof:name":"Sokorejo",
    "wof:placetype":"locality"
},
  "geometry": {"coordinates":[109.69262999999999,-6.90904],"type":"Point"}
}