{
  "type": "Feature",
  "properties": {
    "gn:admin1_code":"30",
    "gn:asciiname":"Sekemandung",
    "gn:country_code":"ID",
    "gn:dem":770,
    "gn:feature_class":"P",
    "gn:feature_code":"PPL",
    "gn:name":"Sekemandung",
    "gn:population":0,
    "gn:timezone":"Asia/Jakarta",
    "iso:country":"ID",
    "name:ind_x_preferred":[
        "Sekemandung"
    ],
    "name:und_x_variant":[
        "Sekemendung 1",
        "Sekemendung Satu"
    ],
    "wof:lang_x_official":[
        "ind"
    ],
    "wof:lang_x_spoken":[
        "ind",
        "eng"
    ],
    "wof:name":"Sekemandung",
    "wof:placetype":"locality"
},
  "geometry": {"coordinates":[107.69499999999999,-6.895],"type":"Point"}
}