{
  "type": "Feature",
  "properties": {
    "gn:admin1_code":"30",
    "gn:asciiname":"Sungaisasak",
    "gn:country_code":"ID",
    "gn:dem":4,
    "gn:feature_class":"P",
    "gn:feature_code":"PPL",
    "gn:name":"Sungaisasak",
    "gn:population":0,
    "gn:timezone":"Asia/Jakarta",
    "iso:country":"ID",
    "name:ind_x_preferred":[
        "Sungaisasak"
    ],
    "wof:name":"Sungaisasak",
    "wof:placetype":"locality"
},
  "geometry": {"coordinates":[107.17139,-6.00278],"type":"Point"}
}