{
  "type": "Feature",
  "properties": {
    "gn:admin1_code":"26",
    "gn:asciiname":"Tebingtinggi",
    "gn:country_code":"ID",
    "gn:dem":3,
    "gn:feature_class":"P",
    "gn:feature_code":"PPL",
    "gn:name":"Tebingtinggi",
    "gn:population":0,
    "gn:timezone":"Asia/Jakarta",
    "iso:country":"ID",
    "name:heb_x_preferred":[
        "\u05d8\u05d1\u05d9\u05e0\u05d2\u05d8\u05d9\u05e0\u05d2\u05d9"
    ],
    "name:hun_x_preferred":[
        "Tebingtinggi"
    ],
    "name:ind_x_preferred":[
        "Tebingtinggi"
    ],
    "wof:lang_x_official":[
        "ind"
    ],
    "wof:lang_x_spoken":[
        "ind",
        "eng"
    ],
    "wof:name":"Tebingtinggi",
    "wof:placetype":"locality"
},
  "geometry": {"coordinates":[99.227,3.4874],"type":"Point"}
}