{
  "type": "Feature",
  "properties": {
    "gn:admin1_code":"18.0",
    "gn:asciiname":"Heak",
    "gn:country_code":"ID",
    "gn:dem":343,
    "gn:feature_class":"P",
    "gn:feature_code":"PPL",
    "gn:name":"Heak",
    "gn:population":0,
    "gn:timezone":"Asia/Makassar",
    "iso:country":"ID",
    "name:ind_x_preferred":[
        "Heak"
    ],
    "wof:name":"Heak",
    "wof:placetype":"locality"
},
  "geometry": {"coordinates":[120.2115,-8.6738],"type":"Point"}
}