{
  "type": "Feature",
  "properties": {
    "gn:admin1_code":"1.0",
    "gn:asciiname":"Peukankuala",
    "gn:country_code":"ID",
    "gn:dem":7,
    "gn:feature_class":"P",
    "gn:feature_code":"PPL",
    "gn:name":"Peukankuala",
    "gn:population":0,
    "gn:timezone":"Asia/Jakarta",
    "iso:country":"ID",
    "name:ind_x_preferred":[
        "Peukankuala"
    ],
    "name:und_x_variant":[
        "Peukankoeala",
        "Pekankuala"
    ],
    "wof:lang_x_official":[
        "ind"
    ],
    "wof:lang_x_spoken":[
        "ind",
        "eng"
    ],
    "wof:name":"Peukankuala",
    "wof:placetype":"locality"
},
  "geometry": {"coordinates":[96.2311,4.0771],"type":"Point"}
}