{
  "type": "Feature",
  "properties": {
    "gn:admin1_code":"33.0",
    "gn:asciiname":"Kadukincir",
    "gn:country_code":"ID",
    "gn:dem":199,
    "gn:feature_class":"P",
    "gn:feature_code":"PPL",
    "gn:name":"Kadukincir",
    "gn:population":0,
    "gn:timezone":"Asia/Jakarta",
    "iso:country":"ID",
    "name:ind_x_preferred":[
        "Kadukincir"
    ],
    "wof:name":"Kadukincir",
    "wof:placetype":"locality"
},
  "geometry": {"coordinates":[105.926,-6.3477],"type":"Point"}
}