{
  "type": "Feature",
  "properties": {
    "gn:admin1_code":"07",
    "gn:asciiname":"Nyomplong",
    "gn:country_code":"ID",
    "gn:dem":366,
    "gn:feature_class":"P",
    "gn:feature_code":"PPL",
    "gn:name":"Nyomplong",
    "gn:population":0,
    "gn:timezone":"Asia/Jakarta",
    "iso:country":"ID",
    "wof:name":"Nyomplong",
    "wof:placetype":"locality"
},
  "geometry": {"coordinates":[110.62111000000002,-7.50972],"type":"Point"}
}