{
  "type": "Feature",
  "properties": {
    "gn:admin1_code":"7.0",
    "gn:asciiname":"Nguwur",
    "gn:country_code":"ID",
    "gn:dem":149,
    "gn:feature_class":"P",
    "gn:feature_code":"PPL",
    "gn:name":"Nguwur",
    "gn:population":0,
    "gn:timezone":"Asia/Jakarta",
    "iso:country":"ID",
    "wof:name":"Nguwur",
    "wof:placetype":"locality"
},
  "geometry": {"coordinates":[110.91083,-7.99861],"type":"Point"}
}