{
  "type": "Feature",
  "properties": {
    "gn:admin1_code":"33.0",
    "gn:asciiname":"Kadutundun",
    "gn:country_code":"ID",
    "gn:dem":225,
    "gn:feature_class":"P",
    "gn:feature_code":"PPL",
    "gn:name":"Kadutundun",
    "gn:population":0,
    "gn:timezone":"Asia/Jakarta",
    "iso:country":"ID",
    "name:ind_x_preferred":[
        "Kadutundun"
    ],
    "wof:name":"Kadutundun",
    "wof:placetype":"locality"
},
  "geometry": {"coordinates":[105.88509999999999,-6.3096],"type":"Point"}
}