{
  "type": "Feature",
  "properties": {
    "gn:admin1_code":"18.0",
    "gn:asciiname":"Dabba",
    "gn:country_code":"ID",
    "gn:dem":22,
    "gn:feature_class":"P",
    "gn:feature_code":"PPL",
    "gn:name":"Dabba",
    "gn:population":0,
    "gn:timezone":"Asia/Makassar",
    "iso:country":"ID",
    "name:ceb_x_preferred":[
        "Dabba"
    ],
    "name:deu_x_preferred":[
        "Dabba"
    ],
    "name:ind_x_preferred":[
        "Dabba"
    ],
    "wof:name":"Dabba",
    "wof:placetype":"locality"
},
  "geometry": {"coordinates":[121.8647,-10.6017],"type":"Point"}
}