{
  "type": "Feature",
  "properties": {
    "gn:admin1_code":"1",
    "gn:asciiname":"Meunasa Rambar",
    "gn:country_code":"ID",
    "gn:dem":13,
    "gn:feature_class":"P",
    "gn:feature_code":"PPL",
    "gn:name":"Meunasa Rambar",
    "gn:population":0,
    "gn:timezone":"Asia/Jakarta",
    "iso:country":"ID",
    "name:ind_x_preferred":[
        "Meunasa Rambar"
    ],
    "wof:name":"Meunasa Rambar",
    "wof:placetype":"locality"
},
  "geometry": {"coordinates":[96.1938,4.2537],"type":"Point"}
}