{
  "type": "Feature",
  "properties": {
    "gn:admin1_code":"30",
    "gn:asciiname":"Pasanggrahan",
    "gn:country_code":"ID",
    "gn:dem":1177,
    "gn:feature_class":"P",
    "gn:feature_code":"PPL",
    "gn:name":"Pasanggrahan",
    "gn:population":0,
    "gn:timezone":"Asia/Jakarta",
    "iso:country":"ID",
    "name:ind_x_preferred":[
        "Pasanggrahan"
    ],
    "wof:name":"Pasanggrahan",
    "wof:placetype":"locality"
},
  "geometry": {"coordinates":[107.795,-6.83694],"type":"Point"}
}