{
  "type": "Feature",
  "properties": {
    "gn:admin1_code":"24",
    "gn:asciiname":"Batupinggai",
    "gn:country_code":"ID",
    "gn:dem":767,
    "gn:feature_class":"P",
    "gn:feature_code":"PPL",
    "gn:name":"Batupinggai",
    "gn:population":0,
    "gn:timezone":"Asia/Jakarta",
    "iso:country":"ID",
    "name:ind_x_preferred":[
        "Batupinggai"
    ],
    "wof:name":"Batupinggai",
    "wof:placetype":"locality"
},
  "geometry": {"coordinates":[100.69324,-0.90651],"type":"Point"}
}