{
  "type": "Feature",
  "properties": {
    "gn:admin1_code":"8.0",
    "gn:asciiname":"Tulungrejo",
    "gn:country_code":"ID",
    "gn:dem":104,
    "gn:feature_class":"P",
    "gn:feature_code":"PPL",
    "gn:name":"Tulungrejo",
    "gn:population":0,
    "gn:timezone":"Asia/Jakarta",
    "iso:country":"ID",
    "name:ind_x_preferred":[
        "Tulungrejo"
    ],
    "wof:name":"Tulungrejo",
    "wof:placetype":"locality"
},
  "geometry": {"coordinates":[111.706,-7.4936],"type":"Point"}
}