{
  "type": "Feature",
  "properties": {
    "gn:admin1_code":"7.0",
    "gn:asciiname":"Bojongsari",
    "gn:country_code":"ID",
    "gn:dem":107,
    "gn:feature_class":"P",
    "gn:feature_code":"PPL",
    "gn:name":"Bojongsari",
    "gn:population":0,
    "gn:timezone":"Asia/Jakarta",
    "iso:country":"ID",
    "name:ind_x_preferred":[
        "Bojongsari"
    ],
    "wof:name":"Bojongsari",
    "wof:placetype":"locality"
},
  "geometry": {"coordinates":[109.35611000000002,-7.3525],"type":"Point"}
}