{
  "type": "Feature",
  "properties": {
    "gn:admin1_code":"30.0",
    "gn:asciiname":"Girimukti",
    "gn:country_code":"ID",
    "gn:dem":839,
    "gn:feature_class":"P",
    "gn:feature_code":"PPL",
    "gn:name":"Girimukti",
    "gn:population":0,
    "gn:timezone":"Asia/Jakarta",
    "iso:country":"ID",
    "name:ind_x_preferred":[
        "Girimukti"
    ],
    "wof:name":"Girimukti",
    "wof:placetype":"locality"
},
  "geometry": {"coordinates":[107.9743,-7.4846],"type":"Point"}
}