{
  "type": "Feature",
  "properties": {
    "gn:admin1_code":"31",
    "gn:asciiname":"Matani Tiga",
    "gn:country_code":"ID",
    "gn:dem":760,
    "gn:feature_class":"P",
    "gn:feature_code":"PPL",
    "gn:name":"Matani Tiga",
    "gn:population":0,
    "gn:timezone":"Asia/Makassar",
    "iso:country":"ID",
    "name:ind_x_preferred":[
        "Matani Tiga"
    ],
    "name:und_x_variant":[
        "Matani 3"
    ],
    "wof:name":"Matani Tiga",
    "wof:placetype":"locality"
},
  "geometry": {"coordinates":[124.8361,1.3132],"type":"Point"}
}