{
  "type": "Feature",
  "properties": {
    "gn:admin1_code":"7.0",
    "gn:asciiname":"Tegowanon",
    "gn:country_code":"ID",
    "gn:dem":398,
    "gn:feature_class":"P",
    "gn:feature_code":"PPL",
    "gn:name":"Tegowanon",
    "gn:population":0,
    "gn:timezone":"Asia/Jakarta",
    "iso:country":"ID",
    "wof:name":"Tegowanon",
    "wof:placetype":"locality"
},
  "geometry": {"coordinates":[110.22917,-7.42889],"type":"Point"}
}