{
  "type": "Feature",
  "properties": {
    "gn:admin1_code":"7.0",
    "gn:asciiname":"Poglan A",
    "gn:country_code":"ID",
    "gn:dem":1417,
    "gn:feature_class":"P",
    "gn:feature_code":"PPL",
    "gn:name":"Poglan A",
    "gn:population":0,
    "gn:timezone":"Asia/Jakarta",
    "iso:country":"ID",
    "name:und_x_variant":[
        "Pogalan",
        "Poglan A"
    ],
    "wof:name":"Poglan A",
    "wof:placetype":"locality"
},
  "geometry": {"coordinates":[110.39610999999999,-7.43528],"type":"Point"}
}