{
  "type": "Feature",
  "properties": {
    "gn:admin1_code":"33.0",
    "gn:asciiname":"Sukacai",
    "gn:country_code":"ID",
    "gn:dem":125,
    "gn:feature_class":"P",
    "gn:feature_code":"PPL",
    "gn:name":"Sukacai",
    "gn:population":0,
    "gn:timezone":"Asia/Jakarta",
    "iso:country":"ID",
    "name:ind_x_preferred":[
        "Sukacai"
    ],
    "wof:name":"Sukacai",
    "wof:placetype":"locality"
},
  "geometry": {"coordinates":[105.9521,-6.2162],"type":"Point"}
}