{
  "type": "Feature",
  "properties": {
    "gn:admin1_code":"30",
    "gn:asciiname":"Cijawa",
    "gn:country_code":"ID",
    "gn:dem":714,
    "gn:feature_class":"P",
    "gn:feature_code":"PPL",
    "gn:name":"Cijawa",
    "gn:population":0,
    "gn:timezone":"Asia/Jakarta",
    "iso:country":"ID",
    "name:ind_x_preferred":[
        "Cijawa"
    ],
    "name:und_x_variant":[
        "Tjidjawal",
        "Cijawal"
    ],
    "wof:name":"Cijawa",
    "wof:placetype":"locality"
},
  "geometry": {"coordinates":[107.32889,-6.90278],"type":"Point"}
}