{
  "type": "Feature",
  "properties": {
    "gn:admin1_code":"30",
    "gn:asciiname":"Babakan Ciandeu",
    "gn:country_code":"ID",
    "gn:dem":121,
    "gn:feature_class":"P",
    "gn:feature_code":"PPL",
    "gn:name":"Babakan Ciandeu",
    "gn:population":0,
    "gn:timezone":"Asia/Jakarta",
    "iso:country":"ID",
    "name:ind_x_preferred":[
        "Babakan Ciandeu"
    ],
    "wof:name":"Babakan Ciandeu",
    "wof:placetype":"locality"
},
  "geometry": {"coordinates":[108.20389,-6.86583],"type":"Point"}
}