{
  "type": "Feature",
  "properties": {
    "gn:admin1_code":"30",
    "gn:asciiname":"Kesan",
    "gn:country_code":"ID",
    "gn:dem":20,
    "gn:feature_class":"P",
    "gn:feature_code":"PPL",
    "gn:name":"Kesan",
    "gn:population":0,
    "gn:timezone":"Asia/Jakarta",
    "iso:country":"ID",
    "name:ceb_x_preferred":[
        "Kasan"
    ],
    "name:fas_x_preferred":[
        "\u06a9\u0633\u0646"
    ],
    "name:ind_x_preferred":[
        "Kesan"
    ],
    "name:msa_x_preferred":[
        "Kesan"
    ],
    "name:swe_x_preferred":[
        "Kasan"
    ],
    "name:und_x_variant":[
        "Kesan 1"
    ],
    "wof:lang_x_official":[
        "ind"
    ],
    "wof:lang_x_spoken":[
        "ind",
        "eng"
    ],
    "wof:name":"Kesan",
    "wof:placetype":"locality"
},
  "geometry": {"coordinates":[107.935,-6.39306],"type":"Point"}
}