{
  "type": "Feature",
  "properties": {
    "gn:admin1_code":"18.0",
    "gn:asciiname":"Kiusnafa",
    "gn:country_code":"ID",
    "gn:dem":583,
    "gn:feature_class":"P",
    "gn:feature_code":"PPL",
    "gn:name":"Kiusnafa",
    "gn:population":0,
    "gn:timezone":"Asia/Makassar",
    "iso:country":"ID",
    "name:ind_x_preferred":[
        "Kiusnafa"
    ],
    "wof:name":"Kiusnafa",
    "wof:placetype":"locality"
},
  "geometry": {"coordinates":[124.4517,-9.80865],"type":"Point"}
}