{
  "type": "Feature",
  "properties": {
    "gn:admin1_code":"26",
    "gn:asciiname":"Keluluran",
    "gn:country_code":"ID",
    "gn:dem":346,
    "gn:feature_class":"P",
    "gn:feature_code":"PPL",
    "gn:name":"Keluluran",
    "gn:population":0,
    "gn:timezone":"Asia/Jakarta",
    "iso:country":"ID",
    "name:ind_x_preferred":[
        "Keluluran"
    ],
    "wof:name":"Keluluran",
    "wof:placetype":"locality"
},
  "geometry": {"coordinates":[98.2086,3.2898],"type":"Point"}
}