{
  "type": "Feature",
  "properties": {
    "gn:admin1_code":"7",
    "gn:asciiname":"Surobayan",
    "gn:country_code":"ID",
    "gn:dem":36,
    "gn:feature_class":"P",
    "gn:feature_code":"PPL",
    "gn:name":"Surobayan",
    "gn:population":0,
    "gn:timezone":"Asia/Jakarta",
    "iso:country":"ID",
    "name:ind_x_preferred":[
        "Surobayan"
    ],
    "wof:name":"Surobayan",
    "wof:placetype":"locality"
},
  "geometry": {"coordinates":[109.98444000000001,-7.76417],"type":"Point"}
}