{
  "type": "Feature",
  "properties": {
    "gn:admin1_code":"37",
    "gn:asciiname":"Sungaitohor Satu",
    "gn:country_code":"ID",
    "gn:dem":13,
    "gn:feature_class":"P",
    "gn:feature_code":"PPL",
    "gn:name":"Sungaitohor Satu",
    "gn:population":0,
    "gn:timezone":"Asia/Jakarta",
    "iso:country":"ID",
    "name:ind_x_preferred":[
        "Sungaitohor Satu"
    ],
    "name:und_x_variant":[
        "Sungaitohor 1",
        "SungaitohorKanan"
    ],
    "wof:lang_x_official":[
        "ind"
    ],
    "wof:lang_x_spoken":[
        "ind",
        "eng"
    ],
    "wof:name":"Sungaitohor Satu",
    "wof:placetype":"locality"
},
  "geometry": {"coordinates":[102.93049999999999,0.8841],"type":"Point"}
}