{
  "type": "Feature",
  "properties": {
    "gn:admin1_code":"7",
    "gn:asciiname":"Bungkus",
    "gn:country_code":"ID",
    "gn:dem":135,
    "gn:feature_class":"P",
    "gn:feature_code":"PPL",
    "gn:name":"Bungkus",
    "gn:population":0,
    "gn:timezone":"Asia/Jakarta",
    "iso:country":"ID",
    "name:ind_x_preferred":[
        "Bungkus"
    ],
    "wof:name":"Bungkus",
    "wof:placetype":"locality"
},
  "geometry": {"coordinates":[111.10639,-7.25667],"type":"Point"}
}