{
  "type": "Feature",
  "properties": {
    "gn:admin1_code":"13.0",
    "gn:asciiname":"Paring",
    "gn:country_code":"ID",
    "gn:dem":76,
    "gn:feature_class":"P",
    "gn:feature_code":"PPL",
    "gn:name":"Paring",
    "gn:population":0,
    "gn:timezone":"Asia/Pontianak",
    "iso:country":"ID",
    "name:deu_x_preferred":[
        "Paring"
    ],
    "name:ind_x_preferred":[
        "Paring"
    ],
    "wof:name":"Paring",
    "wof:placetype":"locality"
},
  "geometry": {"coordinates":[115.1675,-1.22497],"type":"Point"}
}