{
  "type": "Feature",
  "properties": {
    "gn:admin1_code":"26",
    "gn:asciiname":"Perlis",
    "gn:country_code":"ID",
    "gn:dem":5,
    "gn:feature_class":"P",
    "gn:feature_code":"PPL",
    "gn:name":"Perlis",
    "gn:population":0,
    "gn:timezone":"Asia/Jakarta",
    "iso:country":"ID",
    "name:ind_x_preferred":[
        "Perlis"
    ],
    "wof:name":"Perlis",
    "wof:placetype":"locality"
},
  "geometry": {"coordinates":[98.2881,4.0354],"type":"Point"}
}