{
  "type": "Feature",
  "properties": {
    "gn:admin1_code":"26",
    "gn:asciiname":"Perlis",
    "gn:country_code":"ID",
    "gn:dem":5,
    "gn:feature_class":"P",
    "gn:feature_code":"PPL",
    "gn:name":"Perlis",
    "gn:population":0,
    "gn:timezone":"Asia/Jakarta",
    "iso:country":"ID",
    "name:ace_x_preferred":[
        "Perlis"
    ],
    "name:ara_x_preferred":[
        "\u0628\u0631\u0644\u064a\u0633"
    ],
    "name:aze_x_preferred":[
        "Perlis"
    ],
    "name:bjn_x_preferred":[
        "Perlis"
    ],
    "name:bul_x_preferred":[
        "\u041f\u0435\u0440\u043b\u0438\u0441"
    ],
    "name:cat_x_preferred":[
        "Perlis"
    ],
    "name:cdo_x_preferred":[
        "Perlis"
    ],
    "name:ceb_x_preferred":[
        "Perlis"
    ],
    "name:ces_x_preferred":[
        "Perlis"
    ],
    "name:dan_x_preferred":[
        "Perlis"
    ],
    "name:deu_x_preferred":[
        "Perlis"
    ],
    "name:diq_x_preferred":[
        "Perlis"
    ],
    "name:epo_x_preferred":[
        "Perliso"
    ],
    "name:eus_x_preferred":[
        "Perlis"
    ],
    "name:fas_x_preferred":[
        "\u067e\u0631\u0644\u06cc\u0633"
    ],
    "name:fin_x_preferred":[
        "Perlis"
    ],
    "name:fra_x_preferred":[
        "Perlis"
    ],
    "name:hak_x_preferred":[
        "Perlis"
    ],
    "name:heb_x_preferred":[
        "\u05e4\u05e8\u05dc\u05d9\u05e1"
    ],
    "name:hin_x_preferred":[
        "\u092a\u0947\u0930\u0932\u093f\u0938"
    ],
    "name:hun_x_preferred":[
        "Perlis"
    ],
    "name:ind_x_preferred":[
        "Perlis"
    ],
    "name:ipk_x_preferred":[
        "Perlis"
    ],
    "name:ita_x_preferred":[
        "Perlis"
    ],
    "name:jpn_x_preferred":[
        "\u30d7\u30eb\u30ea\u30b9\u5dde"
    ],
    "name:kat_x_preferred":[
        "\u10de\u10d4\u10e0\u10da\u10d8\u10e1\u10d8"
    ],
    "name:kor_x_preferred":[
        "\ud504\ub97c\ub9ac\uc2a4\uc8fc"
    ],
    "name:mar_x_preferred":[
        "\u092a\u0930\u094d\u0932\u093f\u0938"
    ],
    "name:mkd_x_preferred":[
        "\u041f\u0435\u0440\u043b\u0438\u0441"
    ],
    "name:msa_x_preferred":[
        "Perlis"
    ],
    "name:nld_x_preferred":[
        "Perlis"
    ],
    "name:nor_x_preferred":[
        "Perlis"
    ],
    "name:pms_x_preferred":[
        "Perlis"
    ],
    "name:pol_x_preferred":[
        "Perlis"
    ],
    "name:por_x_preferred":[
        "Perlis"
    ],
    "name:rus_x_preferred":[
        "\u041f\u0435\u0440\u043b\u0438\u0441"
    ],
    "name:spa_x_preferred":[
        "Perlis"
    ],
    "name:swe_x_preferred":[
        "Perlis"
    ],
    "name:tam_x_preferred":[
        "\u0baa\u0bc6\u0bb0\u0bcd\u0bb2\u0bbf\u0bb8\u0bcd"
    ],
    "name:tha_x_preferred":[
        "\u0e23\u0e31\u0e10\u0e1b\u0e30\u0e25\u0e34\u0e2a"
    ],
    "name:tur_x_preferred":[
        "Perlis"
    ],
    "name:ukr_x_preferred":[
        "\u041f\u0435\u0440\u043b\u0456\u0441"
    ],
    "name:urd_x_preferred":[
        "\u067e\u0631\u0644\u0633"
    ],
    "name:vie_x_preferred":[
        "Perlis"
    ],
    "name:war_x_preferred":[
        "Perlis"
    ],
    "name:zho_x_preferred":[
        "\u73bb\u7483\u5e02"
    ],
    "wof:lang_x_official":[
        "ind"
    ],
    "wof:lang_x_spoken":[
        "ind",
        "eng"
    ],
    "wof:name":"Perlis",
    "wof:placetype":"locality"
},
  "geometry": {"coordinates":[98.2881,4.0354],"type":"Point"}
}