{
  "type": "Feature",
  "properties": {
    "gn:admin1_code":"2",
    "gn:asciiname":"Banjar Kecicang Islam",
    "gn:country_code":"ID",
    "gn:dem":180,
    "gn:feature_class":"P",
    "gn:feature_code":"PPL",
    "gn:name":"Banjar Kecicang Islam",
    "gn:population":0,
    "gn:timezone":"Asia/Makassar",
    "iso:country":"ID",
    "name:ind_x_preferred":[
        "Banjar Kecicang Islam"
    ],
    "wof:name":"Banjar Kecicang Islam",
    "wof:placetype":"locality"
},
  "geometry": {"coordinates":[115.5849,-8.45],"type":"Point"}
}