{
  "type": "Feature",
  "properties": {
    "gn:admin1_code":"29.0",
    "gn:asciiname":"Yaro",
    "gn:country_code":"ID",
    "gn:dem":-9999,
    "gn:feature_class":"P",
    "gn:feature_code":"PPL",
    "gn:name":"Yaro",
    "gn:population":0,
    "gn:timezone":"Asia/Jayapura",
    "iso:country":"ID",
    "name:azb_x_preferred":[
        "\u06cc\u0627\u0631\u0648"
    ],
    "name:ceb_x_preferred":[
        "Yaro"
    ],
    "name:fas_x_preferred":[
        "\u06cc\u0627\u0631\u0648"
    ],
    "name:fra_x_preferred":[
        "Yaro"
    ],
    "name:swe_x_preferred":[
        "Yaro"
    ],
    "name:und_x_variant":[
        "Jaro",
        "Yaro"
    ],
    "wof:lang_x_official":[
        "ind"
    ],
    "wof:lang_x_spoken":[
        "ind",
        "eng"
    ],
    "wof:name":"Yaro",
    "wof:placetype":"locality"
},
  "geometry": {"coordinates":[128.00436999999999,1.59415],"type":"Point"}
}