{
  "type": "Feature",
  "properties": {
    "gn:admin1_code":"21.0",
    "gn:asciiname":"Paisumosoni",
    "gn:country_code":"ID",
    "gn:dem":10,
    "gn:feature_class":"P",
    "gn:feature_code":"PPL",
    "gn:name":"Paisumosoni",
    "gn:population":0,
    "gn:timezone":"Asia/Makassar",
    "iso:country":"ID",
    "name:ind_x_preferred":[
        "Paisumosoni"
    ],
    "wof:name":"Paisumosoni",
    "wof:placetype":"locality"
},
  "geometry": {"coordinates":[123.5022,-1.5028],"type":"Point"}
}