{
  "type": "Feature",
  "properties": {
    "gn:admin1_code":"1",
    "gn:asciiname":"Drlemangko",
    "gn:country_code":"ID",
    "gn:dem":15,
    "gn:feature_class":"P",
    "gn:feature_code":"PPL",
    "gn:name":"Drlemangko",
    "gn:population":0,
    "gn:timezone":"Asia/Jakarta",
    "iso:country":"ID",
    "name:ind_x_preferred":[
        "Drlemangko"
    ],
    "wof:name":"Drlemangko",
    "wof:placetype":"locality"
},
  "geometry": {"coordinates":[96.0706,4.4021],"type":"Point"}
}