{
  "type": "Feature",
  "properties": {
    "gn:admin1_code":"30.0",
    "gn:asciiname":"Cijati",
    "gn:country_code":"ID",
    "gn:dem":727,
    "gn:feature_class":"P",
    "gn:feature_code":"PPL",
    "gn:name":"Cijati",
    "gn:population":0,
    "gn:timezone":"Asia/Jakarta",
    "iso:country":"ID",
    "name:ind_x_preferred":[
        "Cijati"
    ],
    "wof:name":"Cijati",
    "wof:placetype":"locality"
},
  "geometry": {"coordinates":[108.0737,-7.0692],"type":"Point"}
}