{
  "type": "Feature",
  "properties": {
    "gn:admin1_code":"8.0",
    "gn:asciiname":"Jerukdurga",
    "gn:country_code":"ID",
    "gn:dem":115,
    "gn:feature_class":"P",
    "gn:feature_code":"PPL",
    "gn:name":"Jerukdurga",
    "gn:population":0,
    "gn:timezone":"Asia/Jakarta",
    "iso:country":"ID",
    "name:ind_x_preferred":[
        "Jerukdurga"
    ],
    "wof:name":"Jerukdurga",
    "wof:placetype":"locality"
},
  "geometry": {"coordinates":[113.645,-7.0416],"type":"Point"}
}