{
  "type": "Feature",
  "properties": {
    "gn:admin1_code":"7",
    "gn:asciiname":"Panggung Karangsari",
    "gn:country_code":"ID",
    "gn:dem":3,
    "gn:feature_class":"P",
    "gn:feature_code":"PPL",
    "gn:name":"Panggung Karangsari",
    "gn:population":0,
    "gn:timezone":"Asia/Jakarta",
    "iso:country":"ID",
    "name:ind_x_preferred":[
        "Panggung Karangsari"
    ],
    "wof:name":"Panggung Karangsari",
    "wof:placetype":"locality"
},
  "geometry": {"coordinates":[109.1555,-6.8516],"type":"Point"}
}