{
  "type": "Feature",
  "properties": {
    "gn:admin1_code":"1",
    "gn:asciiname":"Matang Cot Paseh",
    "gn:country_code":"ID",
    "gn:dem":13,
    "gn:feature_class":"P",
    "gn:feature_code":"PPL",
    "gn:name":"Matang Cot Paseh",
    "gn:population":0,
    "gn:timezone":"Asia/Jakarta",
    "iso:country":"ID",
    "name:ind_x_preferred":[
        "Matang Cot Paseh"
    ],
    "name:und_x_variant":[
        "Matangpanjang-meunasahtjotpase"
    ],
    "wof:lang_x_official":[
        "ind"
    ],
    "wof:lang_x_spoken":[
        "ind",
        "eng"
    ],
    "wof:name":"Matang Cot Paseh",
    "wof:placetype":"locality"
},
  "geometry": {"coordinates":[96.7799,5.2044],"type":"Point"}
}