{
  "type": "Feature",
  "properties": {
    "gn:admin1_code":"31.0",
    "gn:asciiname":"Kopandakan",
    "gn:country_code":"ID",
    "gn:dem":193,
    "gn:feature_class":"P",
    "gn:feature_code":"PPL",
    "gn:name":"Kopandakan",
    "gn:population":0,
    "gn:timezone":"Asia/Makassar",
    "iso:country":"ID",
    "name:ind_x_preferred":[
        "Kopandakan"
    ],
    "name:ind_x_variant":[
        "Koponda"
    ],
    "name:und_x_variant":[
        "Kopondakan"
    ],
    "wof:lang_x_official":[
        "ind"
    ],
    "wof:lang_x_spoken":[
        "ind",
        "eng"
    ],
    "wof:name":"Kopandakan",
    "wof:placetype":"locality"
},
  "geometry": {"coordinates":[124.28489999999999,0.7071],"type":"Point"}
}