{
  "type": "Feature",
  "properties": {
    "gn:admin1_code":"37",
    "gn:asciiname":"Sukodadi",
    "gn:country_code":"ID",
    "gn:dem":6,
    "gn:feature_class":"P",
    "gn:feature_code":"PPL",
    "gn:name":"Sukodadi",
    "gn:population":0,
    "gn:timezone":"Asia/Jakarta",
    "iso:country":"ID",
    "name:ind_x_preferred":[
        "Sukodadi"
    ],
    "wof:name":"Sukodadi",
    "wof:placetype":"locality"
},
  "geometry": {"coordinates":[100.98961,2.28311],"type":"Point"}
}