{
  "type": "Feature",
  "properties": {
    "gn:admin1_code":"8.0",
    "gn:asciiname":"Bebekan Utara",
    "gn:country_code":"ID",
    "gn:dem":34,
    "gn:feature_class":"P",
    "gn:feature_code":"PPL",
    "gn:name":"Bebekan Utara",
    "gn:population":0,
    "gn:timezone":"Asia/Jakarta",
    "iso:country":"ID",
    "name:ind_x_preferred":[
        "Bebekan Utara"
    ],
    "wof:name":"Bebekan Utara",
    "wof:placetype":"locality"
},
  "geometry": {"coordinates":[112.2987,-7.4277],"type":"Point"}
}