{
  "type": "Feature",
  "properties": {
    "gn:admin1_code":"8.0",
    "gn:asciiname":"Bunis Timur",
    "gn:country_code":"ID",
    "gn:dem":35,
    "gn:feature_class":"P",
    "gn:feature_code":"PPL",
    "gn:name":"Bunis Timur",
    "gn:population":0,
    "gn:timezone":"Asia/Jakarta",
    "iso:country":"ID",
    "name:ind_x_preferred":[
        "Bunis Timur"
    ],
    "wof:name":"Bunis Timur",
    "wof:placetype":"locality"
},
  "geometry": {"coordinates":[114.01139999999999,-7.1013],"type":"Point"}
}