{
  "type": "Feature",
  "properties": {
    "gn:admin1_code":"30",
    "gn:asciiname":"Bongkar Dua",
    "gn:cc2":"ID",
    "gn:country_code":"ID",
    "gn:dem":1260,
    "gn:feature_class":"P",
    "gn:feature_code":"PPL",
    "gn:name":"Bongkar Dua",
    "gn:population":0,
    "gn:timezone":"Asia/Jakarta",
    "iso:country":"ID",
    "name:und_x_variant":[
        "Bongkar 2",
        "Bongkor 2",
        "Bongkar Dua"
    ],
    "wof:name":"Bongkar Dua",
    "wof:placetype":"locality"
},
  "geometry": {"coordinates":[107.63306,-6.82639],"type":"Point"}
}