{
  "type": "Feature",
  "properties": {
    "gn:admin1_code":"30.0",
    "gn:asciiname":"Sampalanjambe",
    "gn:country_code":"ID",
    "gn:dem":161,
    "gn:feature_class":"P",
    "gn:feature_code":"PPL",
    "gn:name":"Sampalanjambe",
    "gn:population":0,
    "gn:timezone":"Asia/Jakarta",
    "iso:country":"ID",
    "name:ind_x_preferred":[
        "Sampalanjambe"
    ],
    "wof:name":"Sampalanjambe",
    "wof:placetype":"locality"
},
  "geometry": {"coordinates":[108.22320000000001,-7.6506],"type":"Point"}
}