{
  "type": "Feature",
  "properties": {
    "gn:admin1_code":"0.0",
    "gn:asciiname":"Puusule",
    "gn:cc2":"ID",
    "gn:country_code":"ID",
    "gn:dem":6,
    "gn:feature_class":"P",
    "gn:feature_code":"PPL",
    "gn:name":"Puusule",
    "gn:population":0,
    "gn:timezone":"Asia/Makassar",
    "iso:country":"ID",
    "name:und_x_variant":[
        "Poeoesoele",
        "Puusule"
    ],
    "wof:name":"Puusule",
    "wof:placetype":"locality"
},
  "geometry": {"coordinates":[122.13333,-3.48333],"type":"Point"}
}