{
  "type": "Feature",
  "properties": {
    "gn:admin1_code":"10",
    "gn:asciiname":"Ngasem",
    "gn:country_code":"ID",
    "gn:dem":216,
    "gn:feature_class":"P",
    "gn:feature_code":"PPL",
    "gn:name":"Ngasem",
    "gn:population":0,
    "gn:timezone":"Asia/Jakarta",
    "iso:country":"ID",
    "wof:name":"Ngasem",
    "wof:placetype":"locality"
},
  "geometry": {"coordinates":[110.45361,-7.84972],"type":"Point"}
}