{
  "type": "Feature",
  "properties": {
    "gn:admin1_code":"7",
    "gn:asciiname":"Jali",
    "gn:country_code":"ID",
    "gn:dem":8,
    "gn:feature_class":"P",
    "gn:feature_code":"PPL",
    "gn:name":"Jali",
    "gn:population":0,
    "gn:timezone":"Asia/Jakarta",
    "iso:country":"ID",
    "name:ara_x_preferred":[
        "\u062c\u0627\u0644\u064a"
    ],
    "name:deu_x_preferred":[
        "Jali"
    ],
    "name:epo_x_preferred":[
        "Jalio"
    ],
    "name:fra_x_preferred":[
        "Jali"
    ],
    "name:ind_x_preferred":[
        "Jali"
    ],
    "name:ita_x_preferred":[
        "Jali"
    ],
    "name:nld_x_preferred":[
        "Jali"
    ],
    "name:por_x_preferred":[
        "Jali"
    ],
    "wof:lang_x_official":[
        "ind"
    ],
    "wof:lang_x_spoken":[
        "ind",
        "eng"
    ],
    "wof:name":"Jali",
    "wof:placetype":"locality"
},
  "geometry": {"coordinates":[109.62733,-6.90145],"type":"Point"}
}