{
  "type": "Feature",
  "properties": {
    "gn:admin1_code":"30.0",
    "gn:asciiname":"Taringgul",
    "gn:country_code":"ID",
    "gn:dem":770,
    "gn:feature_class":"P",
    "gn:feature_code":"PPL",
    "gn:name":"Taringgul",
    "gn:population":0,
    "gn:timezone":"Asia/Jakarta",
    "iso:country":"ID",
    "name:ind_x_preferred":[
        "Taringgul"
    ],
    "wof:name":"Taringgul",
    "wof:placetype":"locality"
},
  "geometry": {"coordinates":[106.9922,-7.1232],"type":"Point"}
}