{
  "type": "Feature",
  "properties": {
    "gn:admin1_code":"8",
    "gn:asciiname":"Dawuhan",
    "gn:country_code":"ID",
    "gn:dem":158,
    "gn:feature_class":"P",
    "gn:feature_code":"PPLA4",
    "gn:name":"Dawuhan",
    "gn:population":0,
    "gn:timezone":"Asia/Jakarta",
    "iso:country":"ID",
    "name:ind_x_preferred":[
        "Dawuhan"
    ],
    "wof:name":"Dawuhan",
    "wof:placetype":"locality"
},
  "geometry": {"coordinates":[112.13120000000001,-8.168],"type":"Point"}
}