{
  "type": "Feature",
  "properties": {
    "gn:admin1_code":"33.0",
    "gn:asciiname":"Kadukoneng",
    "gn:country_code":"ID",
    "gn:dem":413,
    "gn:feature_class":"P",
    "gn:feature_code":"PPLA4",
    "gn:name":"Kadukoneng",
    "gn:population":0,
    "gn:timezone":"Asia/Jakarta",
    "iso:country":"ID",
    "name:ind_x_preferred":[
        "Kadukoneng"
    ],
    "wof:lang_x_official":[
        "ind"
    ],
    "wof:lang_x_spoken":[
        "ind",
        "eng"
    ],
    "wof:name":"Kadukoneng",
    "wof:placetype":"locality"
},
  "geometry": {"coordinates":[105.96810000000001,-6.265],"type":"Point"}
}