{
  "type": "Feature",
  "properties": {
    "gn:admin1_code":"30",
    "gn:asciiname":"Rong",
    "gn:country_code":"ID",
    "gn:dem":14,
    "gn:feature_class":"P",
    "gn:feature_code":"PPL",
    "gn:name":"Rong",
    "gn:population":0,
    "gn:timezone":"Asia/Jakarta",
    "iso:country":"ID",
    "name:ara_x_preferred":[
        "\u0631\u0648\u0646\u063a"
    ],
    "name:ben_x_preferred":[
        "\u09b0\u0982"
    ],
    "name:deu_x_preferred":[
        "Rong River"
    ],
    "name:deu_x_variant":[
        "Rong"
    ],
    "name:ell_x_preferred":[
        "\u03a1\u03bf\u03bd\u03b3\u03ba"
    ],
    "name:fas_x_preferred":[
        "\u0631\u0648\u0646\u06af"
    ],
    "name:fra_x_preferred":[
        "Rong"
    ],
    "name:heb_x_preferred":[
        "\u05e8\u05d5\u05e0\u05d2"
    ],
    "name:hin_x_preferred":[
        "\u0930\u094b\u0902\u0917\u094b"
    ],
    "name:hun_x_preferred":[
        "Rong"
    ],
    "name:ind_x_preferred":[
        "Rong"
    ],
    "name:ita_x_preferred":[
        "Rong"
    ],
    "name:jpn_x_preferred":[
        "\u6804\u5ddd"
    ],
    "name:kor_x_preferred":[
        "\ub871"
    ],
    "name:nld_x_preferred":[
        "Rong"
    ],
    "name:nor_x_preferred":[
        "Rong"
    ],
    "name:pol_x_preferred":[
        "Rong"
    ],
    "name:por_x_preferred":[
        "Rong"
    ],
    "name:rus_x_preferred":[
        "\u0440\u0435\u043a\u0430 \u0416\u0443\u043d\u0446\u0437\u044f\u043d"
    ],
    "name:spa_x_preferred":[
        "Rong"
    ],
    "name:swe_x_preferred":[
        "Rong"
    ],
    "name:tur_x_preferred":[
        "Rong"
    ],
    "name:ukr_x_preferred":[
        "\u0420\u043e\u043d\u0433"
    ],
    "name:urd_x_preferred":[
        "\u0631\u0648\u0646\u06af"
    ],
    "name:vie_x_preferred":[
        "S\u00f4ng Dung Giang"
    ],
    "name:zho_cn_x_preferred":[
        "\u6995\u6c5f"
    ],
    "name:zho_tw_x_preferred":[
        "\u6995\u6c5f"
    ],
    "wof:lang_x_official":[
        "ind"
    ],
    "wof:lang_x_spoken":[
        "ind",
        "eng"
    ],
    "wof:name":"Rong",
    "wof:placetype":"locality"
},
  "geometry": {"coordinates":[108.07778,-6.44611],"type":"Point"}
}