{
  "type": "Feature",
  "properties": {
    "gn:admin1_code":"38.0",
    "gn:asciiname":"Polotendo",
    "gn:country_code":"ID",
    "gn:dem":29,
    "gn:feature_class":"P",
    "gn:feature_code":"PPL",
    "gn:name":"Polotendo",
    "gn:population":0,
    "gn:timezone":"Asia/Makassar",
    "iso:country":"ID",
    "name:ind_x_preferred":[
        "Polotendo"
    ],
    "wof:name":"Polotendo",
    "wof:placetype":"locality"
},
  "geometry": {"coordinates":[120.30710000000001,-3.3361],"type":"Point"}
}