{
  "type": "Feature",
  "properties": {
    "gn:admin1_code":"41",
    "gn:asciiname":"Botteng",
    "gn:country_code":"ID",
    "gn:dem":477,
    "gn:feature_class":"P",
    "gn:feature_code":"PPL",
    "gn:name":"Botteng",
    "gn:population":0,
    "gn:timezone":"Asia/Makassar",
    "iso:country":"ID",
    "name:ind_x_preferred":[
        "Botteng"
    ],
    "wof:name":"Botteng",
    "wof:placetype":"locality"
},
  "geometry": {"coordinates":[119.1786,-3.076],"type":"Point"}
}