{
  "type": "Feature",
  "properties": {
    "gn:admin1_code":"30",
    "gn:asciiname":"Cilodong",
    "gn:country_code":"ID",
    "gn:dem":31,
    "gn:feature_class":"P",
    "gn:feature_code":"PPL",
    "gn:name":"Cilodong",
    "gn:population":0,
    "gn:timezone":"Asia/Jakarta",
    "iso:country":"ID",
    "name:ind_x_preferred":[
        "Cilodong"
    ],
    "wof:name":"Cilodong",
    "wof:placetype":"locality"
},
  "geometry": {"coordinates":[107.14361,-6.43194],"type":"Point"}
}