{
  "type": "Feature",
  "properties": {
    "gn:admin1_code":"8.0",
    "gn:asciiname":"Probungan Daja",
    "gn:country_code":"ID",
    "gn:dem":103,
    "gn:feature_class":"P",
    "gn:feature_code":"PPL",
    "gn:name":"Probungan Daja",
    "gn:population":0,
    "gn:timezone":"Asia/Jakarta",
    "iso:country":"ID",
    "name:ind_x_preferred":[
        "Probungan Daja"
    ],
    "wof:name":"Probungan Daja",
    "wof:placetype":"locality"
},
  "geometry": {"coordinates":[113.325,-7.0043],"type":"Point"}
}