{
  "type": "Feature",
  "properties": {
    "gn:admin1_code":"18.0",
    "gn:asciiname":"Letekamugilana",
    "gn:country_code":"ID",
    "gn:dem":467,
    "gn:feature_class":"P",
    "gn:feature_code":"PPL",
    "gn:name":"Letekamugilana",
    "gn:population":0,
    "gn:timezone":"Asia/Makassar",
    "iso:country":"ID",
    "name:ind_x_preferred":[
        "Letekamugilana"
    ],
    "wof:name":"Letekamugilana",
    "wof:placetype":"locality"
},
  "geometry": {"coordinates":[119.43429999999999,-9.649],"type":"Point"}
}