{
  "type": "Feature",
  "properties": {
    "gn:admin1_code":"0.0",
    "gn:asciiname":"Tapas",
    "gn:country_code":"ID",
    "gn:dem":17,
    "gn:feature_class":"P",
    "gn:feature_code":"PPL",
    "gn:name":"Tapas",
    "gn:population":0,
    "gn:timezone":"Asia/Jayapura",
    "iso:country":"ID",
    "name:ara_x_preferred":[
        "\u062a\u0627\u0628\u0627\u0633"
    ],
    "name:ast_x_preferred":[
        "Tapa"
    ],
    "name:aze_x_preferred":[
        "Tapas"
    ],
    "name:bul_x_preferred":[
        "\u0422\u0430\u043f\u0430\u0441"
    ],
    "name:cat_x_preferred":[
        "Tapa"
    ],
    "name:ces_x_preferred":[
        "Tapas"
    ],
    "name:dan_x_preferred":[
        "Tapas"
    ],
    "name:deu_x_preferred":[
        "Tapa"
    ],
    "name:epo_x_preferred":[
        "Tapo"
    ],
    "name:eus_x_preferred":[
        "Tapa"
    ],
    "name:fas_x_preferred":[
        "\u062a\u0627\u067e\u0627\u0633"
    ],
    "name:fin_x_preferred":[
        "Tapas"
    ],
    "name:fra_x_preferred":[
        "Tapas"
    ],
    "name:glg_x_preferred":[
        "Tapa"
    ],
    "name:heb_x_preferred":[
        "\u05d8\u05d0\u05e4\u05e1"
    ],
    "name:hun_x_preferred":[
        "Tapas"
    ],
    "name:hye_x_preferred":[
        "\u054f\u0561\u057a\u0561\u057d"
    ],
    "name:ita_x_preferred":[
        "Tapas"
    ],
    "name:jpn_x_preferred":[
        "\u30bf\u30d1\u30b9"
    ],
    "name:kor_x_preferred":[
        "\ud0c0\ud30c\uc2a4"
    ],
    "name:lat_x_preferred":[
        "Operculum"
    ],
    "name:nld_x_preferred":[
        "Tapa"
    ],
    "name:nno_x_preferred":[
        "Tapas"
    ],
    "name:nor_x_preferred":[
        "Tapas"
    ],
    "name:pol_x_preferred":[
        "Tapas"
    ],
    "name:por_x_preferred":[
        "Tapa"
    ],
    "name:rus_x_preferred":[
        "\u0422\u0430\u043f\u0430\u0441"
    ],
    "name:spa_x_preferred":[
        "Tapa"
    ],
    "name:swe_x_preferred":[
        "Tapas"
    ],
    "name:tgl_x_preferred":[
        "Tapas"
    ],
    "name:ukr_x_preferred":[
        "\u0422\u0430\u043f\u0438"
    ],
    "name:vie_x_preferred":[
        "Tapas"
    ],
    "name:zho_x_preferred":[
        "\u5854\u5e15\u65af"
    ],
    "wof:name":"Tapas",
    "wof:placetype":"locality"
},
  "geometry": {"coordinates":[132.40000000000001,-2.25],"type":"Point"}
}