{
  "type": "Feature",
  "properties": {
    "gn:admin1_code":"7",
    "gn:asciiname":"Curah",
    "gn:country_code":"ID",
    "gn:dem":47,
    "gn:feature_class":"P",
    "gn:feature_code":"PPL",
    "gn:name":"Curah",
    "gn:population":0,
    "gn:timezone":"Asia/Jakarta",
    "iso:country":"ID",
    "name:ind_x_preferred":[
        "Curah"
    ],
    "wof:name":"Curah",
    "wof:placetype":"locality"
},
  "geometry": {"coordinates":[109.1413,-6.9887],"type":"Point"}
}