{
  "type": "Feature",
  "properties": {
    "gn:admin1_code":"38.0",
    "gn:asciiname":"Banba",
    "gn:country_code":"ID",
    "gn:dem":73,
    "gn:feature_class":"P",
    "gn:feature_code":"PPL",
    "gn:name":"Banba",
    "gn:population":0,
    "gn:timezone":"Asia/Makassar",
    "iso:country":"ID",
    "name:deu_x_preferred":[
        "Banba"
    ],
    "name:fin_x_preferred":[
        "Banbha"
    ],
    "name:fra_x_preferred":[
        "Banba"
    ],
    "name:gle_x_preferred":[
        "Banbha"
    ],
    "name:ind_x_preferred":[
        "Banba"
    ],
    "name:ita_x_preferred":[
        "Banba"
    ],
    "name:jpn_x_preferred":[
        "\u30d0\u30f3\u30d0"
    ],
    "name:nld_x_preferred":[
        "Banba"
    ],
    "name:pol_x_preferred":[
        "Banba"
    ],
    "name:por_x_preferred":[
        "Banba"
    ],
    "wof:lang_x_official":[
        "ind"
    ],
    "wof:lang_x_spoken":[
        "ind",
        "eng"
    ],
    "wof:name":"Banba",
    "wof:placetype":"locality"
},
  "geometry": {"coordinates":[119.77376,-3.55712],"type":"Point"}
}