{
  "type": "Feature",
  "properties": {
    "gn:admin1_code":"30",
    "gn:asciiname":"Legokpanjang",
    "gn:country_code":"ID",
    "gn:dem":27,
    "gn:feature_class":"P",
    "gn:feature_code":"PPL",
    "gn:name":"Legokpanjang",
    "gn:population":0,
    "gn:timezone":"Asia/Jakarta",
    "iso:country":"ID",
    "name:ind_x_preferred":[
        "Legokpanjang"
    ],
    "wof:name":"Legokpanjang",
    "wof:placetype":"locality"
},
  "geometry": {"coordinates":[107.38056,-6.41889],"type":"Point"}
}