{
  "type": "Feature",
  "properties": {
    "gn:admin1_code":"7.0",
    "gn:asciiname":"Cempaka",
    "gn:country_code":"ID",
    "gn:dem":1056,
    "gn:feature_class":"P",
    "gn:feature_code":"PPL",
    "gn:name":"Cempaka",
    "gn:population":0,
    "gn:timezone":"Asia/Jakarta",
    "iso:country":"ID",
    "name:ind_x_preferred":[
        "Cempaka"
    ],
    "wof:name":"Cempaka",
    "wof:placetype":"locality"
},
  "geometry": {"coordinates":[109.79806000000001,-7.26694],"type":"Point"}
}