{
  "type": "Feature",
  "properties": {
    "gn:admin1_code":"29.0",
    "gn:asciiname":"Tawakale",
    "gn:country_code":"ID",
    "gn:dem":13,
    "gn:feature_class":"P",
    "gn:feature_code":"PPL",
    "gn:name":"Tawakale",
    "gn:population":0,
    "gn:timezone":"Asia/Jayapura",
    "iso:country":"ID",
    "name:ind_x_preferred":[
        "Tawakale"
    ],
    "wof:name":"Tawakale",
    "wof:placetype":"locality"
},
  "geometry": {"coordinates":[128.64453999999998,2.34869],"type":"Point"}
}