{
  "type": "Feature",
  "properties": {
    "gn:admin1_code":"30.0",
    "gn:asciiname":"Cimuncang",
    "gn:country_code":"ID",
    "gn:dem":542,
    "gn:feature_class":"P",
    "gn:feature_code":"PPL",
    "gn:name":"Cimuncang",
    "gn:population":0,
    "gn:timezone":"Asia/Jakarta",
    "iso:country":"ID",
    "name:ind_x_preferred":[
        "Cimuncang"
    ],
    "name:und_x_variant":[
        "Tjimoentjang 3"
    ],
    "wof:lang_x_official":[
        "ind"
    ],
    "wof:lang_x_spoken":[
        "ind",
        "eng"
    ],
    "wof:name":"Cimuncang",
    "wof:placetype":"locality"
},
  "geometry": {"coordinates":[107.98180000000001,-7.0633],"type":"Point"}
}