{
  "type": "Feature",
  "properties": {
    "gn:admin1_code":"7.0",
    "gn:asciiname":"Entak",
    "gn:country_code":"ID",
    "gn:dem":15,
    "gn:feature_class":"P",
    "gn:feature_code":"PPL",
    "gn:name":"Entak",
    "gn:population":0,
    "gn:timezone":"Asia/Jakarta",
    "iso:country":"ID",
    "name:ind_x_preferred":[
        "Entak"
    ],
    "wof:name":"Entak",
    "wof:placetype":"locality"
},
  "geometry": {"coordinates":[109.56722000000001,-7.655],"type":"Point"}
}