{
  "type": "Feature",
  "properties": {
    "gn:admin1_code":"18.0",
    "gn:asciiname":"Besnakeh",
    "gn:country_code":"ID",
    "gn:dem":931,
    "gn:feature_class":"P",
    "gn:feature_code":"PPLA4",
    "gn:name":"Besnakeh",
    "gn:population":0,
    "gn:timezone":"Asia/Makassar",
    "iso:country":"ID",
    "name:ind_x_preferred":[
        "Besnakeh"
    ],
    "wof:lang_x_official":[
        "ind"
    ],
    "wof:lang_x_spoken":[
        "ind",
        "eng"
    ],
    "wof:name":"Besnakeh",
    "wof:placetype":"locality"
},
  "geometry": {"coordinates":[124.27330000000001,-9.6825],"type":"Point"}
}