{
  "type": "Feature",
  "properties": {
    "gn:admin1_code":"2",
    "gn:asciiname":"Banjar Tegalkepuh",
    "gn:country_code":"ID",
    "gn:dem":54,
    "gn:feature_class":"P",
    "gn:feature_code":"PPL",
    "gn:name":"Banjar Tegalkepuh",
    "gn:population":0,
    "gn:timezone":"Asia/Makassar",
    "iso:country":"ID",
    "name:ind_x_preferred":[
        "Banjar Tegalkepuh"
    ],
    "wof:name":"Banjar Tegalkepuh",
    "wof:placetype":"locality"
},
  "geometry": {"coordinates":[115.13800000000001,-8.6075],"type":"Point"}
}