{
  "type": "Feature",
  "properties": {
    "gn:country":"ID",
    "gn:fcode":"PPLA3",
    "gn:pop":0,
    "iso:country":"ID",
    "name:ara_x_preferred":[
        "\u062c\u064a\u0628\u0627\u0631\u0627"
    ],
    "name:fra_x_preferred":[
        "Jepara"
    ],
    "name:ind_x_preferred":[
        "Jepara"
    ],
    "name:jav_x_preferred":[
        "Jepara"
    ],
    "name:por_x_preferred":[
        "Jepara"
    ],
    "name:ron_x_preferred":[
        "Jepara"
    ],
    "name:unk_x_variant":[
        "Djepara"
    ],
    "name:vie_x_preferred":[
        "Jepara"
    ],
    "qs:name":"Jepara",
    "qs:photos_9r":0,
    "qs:photos_sr":0,
    "qs:pop_sr":"5",
    "wd:wordcount":495,
    "wof:lang_x_official":[
        "ind"
    ],
    "wof:lang_x_spoken":[
        "ind",
        "eng"
    ],
    "wof:name":"Jepara",
    "wof:placetype":"locality",
    "wof:population":0
},
  "geometry": {"coordinates":[105.70441,-5.16948],"type":"Point"}
}