{
  "type": "Feature",
  "properties": {
    "gn:admin1_code":"8",
    "gn:asciiname":"Sarirejo Dua",
    "gn:country_code":"ID",
    "gn:dem":75,
    "gn:feature_class":"P",
    "gn:feature_code":"PPL",
    "gn:name":"Sarirejo Dua",
    "gn:population":0,
    "gn:timezone":"Asia/Jakarta",
    "iso:country":"ID",
    "name:ind_x_preferred":[
        "Sarirejo Dua"
    ],
    "wof:name":"Sarirejo Dua",
    "wof:placetype":"locality"
},
  "geometry": {"coordinates":[113.2009,-8.1533],"type":"Point"}
}