{
  "type": "Feature",
  "properties": {
    "gn:admin1_code":"15.0",
    "gn:asciiname":"Ulokpandan",
    "gn:country_code":"ID",
    "gn:dem":9,
    "gn:feature_class":"P",
    "gn:feature_code":"PPL",
    "gn:name":"Ulokpandan",
    "gn:population":0,
    "gn:timezone":"Asia/Jakarta",
    "iso:country":"ID",
    "name:ind_x_preferred":[
        "Lhokpandan"
    ],
    "name:und_x_variant":[
        "Oelokpandan",
        "Ulakpandan",
        "Oelakpandan",
        "Ulokpandan"
    ],
    "wof:name":"Ulokpandan",
    "wof:placetype":"locality"
},
  "geometry": {"coordinates":[103.91303000000001,-5.12542],"type":"Point"}
}