{
  "type": "Feature",
  "properties": {
    "gn:admin1_code":"30",
    "gn:asciiname":"Jongor",
    "gn:cc2":"ID",
    "gn:country_code":"ID",
    "gn:dem":678,
    "gn:feature_class":"P",
    "gn:feature_code":"PPL",
    "gn:name":"Jongor",
    "gn:population":0,
    "gn:timezone":"Asia/Jakarta",
    "iso:country":"ID",
    "name:und_x_variant":[
        "Djoger",
        "Joger",
        "Jongor"
    ],
    "wof:name":"Jongor",
    "wof:placetype":"locality"
},
  "geometry": {"coordinates":[107.71028,-7.03278],"type":"Point"}
}