{
  "type": "Feature",
  "properties": {
    "gn:admin1_code":"1.0",
    "gn:asciiname":"Umepanu",
    "gn:country_code":"ID",
    "gn:dem":992,
    "gn:feature_class":"P",
    "gn:feature_code":"PPL",
    "gn:name":"Umepanu",
    "gn:population":0,
    "gn:timezone":"Asia/Jakarta",
    "iso:country":"ID",
    "name:ind_x_preferred":[
        "Umepanu"
    ],
    "name:und_x_variant":[
        "Umeupandeu"
    ],
    "wof:name":"Umepanu",
    "wof:placetype":"locality"
},
  "geometry": {"coordinates":[97.17700000000001,4.0528],"type":"Point"}
}