{
  "type": "Feature",
  "properties": {
    "gn:admin1_code":"10.0",
    "gn:asciiname":"Joholanang",
    "gn:country_code":"ID",
    "gn:dem":293,
    "gn:feature_class":"P",
    "gn:feature_code":"PPL",
    "gn:name":"Joholanang",
    "gn:population":0,
    "gn:timezone":"Asia/Jakarta",
    "iso:country":"ID",
    "wof:name":"Joholanang",
    "wof:placetype":"locality"
},
  "geometry": {"coordinates":[110.48027999999999,-7.69056],"type":"Point"}
}