{
  "type": "Feature",
  "properties": {
    "gn:admin1_code":"26",
    "gn:asciiname":"Batu Tiga",
    "gn:country_code":"ID",
    "gn:dem":26,
    "gn:feature_class":"P",
    "gn:feature_code":"PPL",
    "gn:name":"Batu Tiga",
    "gn:population":0,
    "gn:timezone":"Asia/Jakarta",
    "iso:country":"ID",
    "name:ind_x_preferred":[
        "Batu Tiga"
    ],
    "name:msa_x_preferred":[
        "Batu Tiga"
    ],
    "name:und_x_variant":[
        "Batu III"
    ],
    "name:zho_x_preferred":[
        "\u5cc7\u90fd\u77e5\u7532"
    ],
    "wof:lang_x_official":[
        "ind"
    ],
    "wof:lang_x_spoken":[
        "ind",
        "eng"
    ],
    "wof:name":"Batu Tiga",
    "wof:placetype":"locality"
},
  "geometry": {"coordinates":[99.1365,3.3107],"type":"Point"}
}