{
  "type": "Feature",
  "properties": {
    "gn:admin1_code":"7",
    "gn:asciiname":"Gedong",
    "gn:country_code":"ID",
    "gn:dem":527,
    "gn:feature_class":"P",
    "gn:feature_code":"PPL",
    "gn:name":"Gedong",
    "gn:population":0,
    "gn:timezone":"Asia/Jakarta",
    "iso:country":"ID",
    "name:ind_x_preferred":[
        "Gedong"
    ],
    "wof:name":"Gedong",
    "wof:placetype":"locality"
},
  "geometry": {"coordinates":[111.25388999999998,-7.78722],"type":"Point"}
}