{
  "type": "Feature",
  "properties": {
    "gn:admin1_code":"7.0",
    "gn:asciiname":"Pete",
    "gn:country_code":"ID",
    "gn:dem":488,
    "gn:feature_class":"P",
    "gn:feature_code":"PPL",
    "gn:name":"Pete",
    "gn:population":0,
    "gn:timezone":"Asia/Jakarta",
    "iso:country":"ID",
    "name:ceb_x_preferred":[
        "Pete"
    ],
    "name:fra_x_preferred":[
        "Pete"
    ],
    "name:hun_x_preferred":[
        "Pete"
    ],
    "name:ind_x_preferred":[
        "Pete"
    ],
    "name:jpn_x_preferred":[
        "\u30d4\u30fc\u30c8"
    ],
    "name:nld_x_preferred":[
        "Pete"
    ],
    "name:spa_x_preferred":[
        "Pete"
    ],
    "name:swe_x_preferred":[
        "Pete"
    ],
    "wof:lang_x_official":[
        "ind"
    ],
    "wof:lang_x_spoken":[
        "ind",
        "eng"
    ],
    "wof:name":"Pete",
    "wof:placetype":"locality"
},
  "geometry": {"coordinates":[109.72583,-7.45472],"type":"Point"}
}