{
  "type": "Feature",
  "properties": {
    "gn:admin1_code":"30.0",
    "gn:asciiname":"Cihikeugede",
    "gn:country_code":"ID",
    "gn:dem":920,
    "gn:feature_class":"P",
    "gn:feature_code":"PPL",
    "gn:name":"Cihikeugede",
    "gn:population":0,
    "gn:timezone":"Asia/Jakarta",
    "iso:country":"ID",
    "name:ind_x_preferred":[
        "Cihikeugede"
    ],
    "wof:name":"Cihikeugede",
    "wof:placetype":"locality"
},
  "geometry": {"coordinates":[107.60769999999999,-7.4021],"type":"Point"}
}