{
  "type": "Feature",
  "properties": {
    "gn:admin1_code":"30",
    "gn:asciiname":"Bangreung",
    "gn:country_code":"ID",
    "gn:dem":934,
    "gn:feature_class":"P",
    "gn:feature_code":"PPL",
    "gn:name":"Bangreung",
    "gn:population":0,
    "gn:timezone":"Asia/Jakarta",
    "iso:country":"ID",
    "wof:name":"Bangreung",
    "wof:placetype":"locality"
},
  "geometry": {"coordinates":[107.57832999999999,-7.09417],"type":"Point"}
}