{
  "type": "Feature",
  "properties": {
    "gn:admin1_code":"30.0",
    "gn:asciiname":"Kadudua",
    "gn:country_code":"ID",
    "gn:dem":109,
    "gn:feature_class":"P",
    "gn:feature_code":"PPL",
    "gn:name":"Kadudua",
    "gn:population":0,
    "gn:timezone":"Asia/Jakarta",
    "iso:country":"ID",
    "name:ind_x_preferred":[
        "Kadudua"
    ],
    "name:und_x_variant":[
        "Kadoedoea"
    ],
    "wof:name":"Kadudua",
    "wof:placetype":"locality"
},
  "geometry": {"coordinates":[108.48139999999999,-7.6683],"type":"Point"}
}