{
  "type": "Feature",
  "properties": {
    "gn:admin1_code":"07",
    "gn:asciiname":"Wates",
    "gn:country_code":"ID",
    "gn:dem":27,
    "gn:feature_class":"P",
    "gn:feature_code":"PPL",
    "gn:name":"Wates",
    "gn:population":0,
    "gn:timezone":"Asia/Jakarta",
    "iso:country":"ID",
    "name:ceb_x_preferred":[
        "Wates"
    ],
    "name:ind_x_preferred":[
        "Wates"
    ],
    "name:nld_x_preferred":[
        "Wates"
    ],
    "name:swe_x_preferred":[
        "Wates"
    ],
    "wof:lang_x_official":[
        "ind"
    ],
    "wof:lang_x_spoken":[
        "ind",
        "eng"
    ],
    "wof:name":"Wates",
    "wof:placetype":"locality"
},
  "geometry": {"coordinates":[110.48833,-7.03361],"type":"Point"}
}