{
  "type": "Feature",
  "properties": {
    "gn:admin1_code":"30",
    "gn:asciiname":"Astapada",
    "gn:country_code":"ID",
    "gn:dem":19,
    "gn:feature_class":"P",
    "gn:feature_code":"PPL",
    "gn:name":"Astapada",
    "gn:population":0,
    "gn:timezone":"Asia/Jakarta",
    "iso:country":"ID",
    "name:ind_x_preferred":[
        "Astapada"
    ],
    "wof:name":"Astapada",
    "wof:placetype":"locality"
},
  "geometry": {"coordinates":[108.51519999999999,-6.7177],"type":"Point"}
}