{
  "type": "Feature",
  "properties": {
    "gn:admin1_code":"30.0",
    "gn:asciiname":"Balandongan",
    "gn:country_code":"ID",
    "gn:dem":716,
    "gn:feature_class":"P",
    "gn:feature_code":"PPL",
    "gn:name":"Balandongan",
    "gn:population":0,
    "gn:timezone":"Asia/Jakarta",
    "iso:country":"ID",
    "name:ind_x_preferred":[
        "Balandongan"
    ],
    "name:und_x_variant":[
        "Blandongan"
    ],
    "wof:lang_x_official":[
        "ind"
    ],
    "wof:lang_x_spoken":[
        "ind",
        "eng"
    ],
    "wof:name":"Balandongan",
    "wof:placetype":"locality"
},
  "geometry": {"coordinates":[107.9426,-7.1933],"type":"Point"}
}