{
  "type": "Feature",
  "properties": {
    "gn:admin1_code":"37",
    "gn:asciiname":"Buluhjala",
    "gn:country_code":"ID",
    "gn:dem":14,
    "gn:feature_class":"P",
    "gn:feature_code":"PPL",
    "gn:name":"Buluhjala",
    "gn:population":0,
    "gn:timezone":"Asia/Jakarta",
    "iso:country":"ID",
    "name:eng_x_preferred":[
        "Buluhdjala"
    ],
    "name:ind_x_preferred":[
        "Buluhjala"
    ],
    "wof:name":"Buluhjala",
    "wof:placetype":"locality"
},
  "geometry": {"coordinates":[101.869,0.6073],"type":"Point"}
}