{
  "type": "Feature",
  "properties": {
    "gn:admin1_code":"26",
    "gn:asciiname":"Aeknabirong",
    "gn:country_code":"ID",
    "gn:dem":448,
    "gn:feature_class":"P",
    "gn:feature_code":"PPL",
    "gn:name":"Aeknabirong",
    "gn:population":0,
    "gn:timezone":"Asia/Jakarta",
    "iso:country":"ID",
    "name:ind_x_preferred":[
        "Aeknabirong"
    ],
    "wof:name":"Aeknabirong",
    "wof:placetype":"locality"
},
  "geometry": {"coordinates":[98.78400000000001,1.8993],"type":"Point"}
}