{
  "type": "Feature",
  "properties": {
    "gn:admin1_code":"1",
    "gn:asciiname":"Meunasah Pulodulang",
    "gn:country_code":"ID",
    "gn:dem":6,
    "gn:feature_class":"P",
    "gn:feature_code":"PPL",
    "gn:name":"Meunasah Pulodulang",
    "gn:population":0,
    "gn:timezone":"Asia/Jakarta",
    "iso:country":"ID",
    "name:ind_x_preferred":[
        "Meunasah Pulodulang"
    ],
    "wof:name":"Meunasah Pulodulang",
    "wof:placetype":"locality"
},
  "geometry": {"coordinates":[97.312,5.0622],"type":"Point"}
}