{
  "type": "Feature",
  "properties": {
    "gn:admin1_code":"30",
    "gn:asciiname":"Puncakresort",
    "gn:country_code":"ID",
    "gn:dem":950,
    "gn:feature_class":"P",
    "gn:feature_code":"PPL",
    "gn:name":"Puncakresort",
    "gn:population":0,
    "gn:timezone":"Asia/Jakarta",
    "iso:country":"ID",
    "name:ind_x_preferred":[
        "Puncakresort"
    ],
    "wof:name":"Puncakresort",
    "wof:placetype":"locality"
},
  "geometry": {"coordinates":[107.04861,-6.70556],"type":"Point"}
}