{
  "type": "Feature",
  "properties": {
    "gn:admin1_code":"7.0",
    "gn:asciiname":"Punggul",
    "gn:country_code":"ID",
    "gn:dem":107,
    "gn:feature_class":"P",
    "gn:feature_code":"PPL",
    "gn:name":"Punggul",
    "gn:population":0,
    "gn:timezone":"Asia/Jakarta",
    "iso:country":"ID",
    "name:ind_x_preferred":[
        "Punggul"
    ],
    "wof:name":"Punggul",
    "wof:placetype":"locality"
},
  "geometry": {"coordinates":[111.32769999999999,-6.8525],"type":"Point"}
}