{
  "type": "Feature",
  "properties": {
    "gn:admin1_code":"1",
    "gn:asciiname":"Tampieng",
    "gn:country_code":"ID",
    "gn:dem":26,
    "gn:feature_class":"P",
    "gn:feature_code":"PPL",
    "gn:name":"Tampieng",
    "gn:population":0,
    "gn:timezone":"Asia/Jakarta",
    "iso:country":"ID",
    "name:ind_x_preferred":[
        "Tampieng"
    ],
    "wof:name":"Tampieng",
    "wof:placetype":"locality"
},
  "geometry": {"coordinates":[96.20350000000001,4.3795],"type":"Point"}
}