{
  "type": "Feature",
  "properties": {
    "gn:admin1_code":"8.0",
    "gn:asciiname":"Pragelan",
    "gn:country_code":"ID",
    "gn:dem":193,
    "gn:feature_class":"P",
    "gn:feature_code":"PPL",
    "gn:name":"Pragelan",
    "gn:population":0,
    "gn:timezone":"Asia/Jakarta",
    "iso:country":"ID",
    "name:ind_x_preferred":[
        "Pragelan"
    ],
    "wof:name":"Pragelan",
    "wof:placetype":"locality"
},
  "geometry": {"coordinates":[111.7919,-7.3977],"type":"Point"}
}