{
  "type": "Feature",
  "properties": {
    "gn:admin1_code":"8",
    "gn:asciiname":"Krai",
    "gn:country_code":"ID",
    "gn:dem":617,
    "gn:feature_class":"P",
    "gn:feature_code":"PPL",
    "gn:name":"Krai",
    "gn:population":0,
    "gn:timezone":"Asia/Jakarta",
    "iso:country":"ID",
    "name:afr_x_preferred":[
        "Krai"
    ],
    "name:ben_x_preferred":[
        "\u0995\u09cd\u09b0\u09be\u0987"
    ],
    "name:ell_x_preferred":[
        "\u039a\u03c1\u03ac\u03b9"
    ],
    "name:epo_x_preferred":[
        "Regiono"
    ],
    "name:eus_x_preferred":[
        "Krai"
    ],
    "name:glg_x_preferred":[
        "Krai"
    ],
    "name:ind_x_preferred":[
        "Krai"
    ],
    "name:lij_x_preferred":[
        "Krai"
    ],
    "name:mar_x_preferred":[
        "\u0915\u094d\u0930\u093e\u092f"
    ],
    "name:por_x_preferred":[
        "Krai"
    ],
    "name:ron_x_preferred":[
        "Krain\u0103"
    ],
    "name:spa_x_preferred":[
        "Krai"
    ],
    "name:tur_x_preferred":[
        "Kray"
    ],
    "name:vie_x_preferred":[
        "Krai"
    ],
    "wof:lang_x_official":[
        "ind"
    ],
    "wof:lang_x_spoken":[
        "ind",
        "eng"
    ],
    "wof:name":"Krai",
    "wof:placetype":"locality"
},
  "geometry": {"coordinates":[112.6855,-7.7946],"type":"Point"}
}