{
  "type": "Feature",
  "properties": {
    "gn:admin1_code":"8",
    "gn:asciiname":"Krai",
    "gn:country_code":"ID",
    "gn:dem":617,
    "gn:feature_class":"P",
    "gn:feature_code":"PPL",
    "gn:name":"Krai",
    "gn:population":0,
    "gn:timezone":"Asia/Jakarta",
    "iso:country":"ID",
    "name:ind_x_preferred":[
        "Krai"
    ],
    "wof:name":"Krai",
    "wof:placetype":"locality"
},
  "geometry": {"coordinates":[112.6855,-7.7946],"type":"Point"}
}