{
  "type": "Feature",
  "properties": {
    "gn:admin1_code":"38.0",
    "gn:asciiname":"Seppon",
    "gn:country_code":"ID",
    "gn:dem":398,
    "gn:feature_class":"P",
    "gn:feature_code":"PPL",
    "gn:name":"Seppon",
    "gn:population":0,
    "gn:timezone":"Asia/Makassar",
    "iso:country":"ID",
    "name:ind_x_preferred":[
        "Seppon"
    ],
    "wof:name":"Seppon",
    "wof:placetype":"locality"
},
  "geometry": {"coordinates":[119.7056,-3.3733],"type":"Point"}
}