{
  "type": "Feature",
  "properties": {
    "gn:admin1_code":"30",
    "gn:asciiname":"Babakan",
    "gn:country_code":"ID",
    "gn:dem":414,
    "gn:feature_class":"P",
    "gn:feature_code":"PPL",
    "gn:name":"Babakan",
    "gn:population":0,
    "gn:timezone":"Asia/Jakarta",
    "iso:country":"ID",
    "name:ind_x_preferred":[
        "Babakan"
    ],
    "wof:name":"Babakan",
    "wof:placetype":"locality"
},
  "geometry": {"coordinates":[108.27249999999999,-6.96583],"type":"Point"}
}