{
  "type": "Feature",
  "properties": {
    "gn:admin1_code":"30.0",
    "gn:asciiname":"Citikur",
    "gn:country_code":"ID",
    "gn:dem":225,
    "gn:feature_class":"P",
    "gn:feature_code":"PPL",
    "gn:name":"Citikur",
    "gn:population":0,
    "gn:timezone":"Asia/Jakarta",
    "iso:country":"ID",
    "name:ind_x_preferred":[
        "Citikur"
    ],
    "name:und_x_variant":[
        "Tjitikoer"
    ],
    "wof:lang_x_official":[
        "ind"
    ],
    "wof:lang_x_spoken":[
        "ind",
        "eng"
    ],
    "wof:name":"Citikur",
    "wof:placetype":"locality"
},
  "geometry": {"coordinates":[108.6125,-7.0932],"type":"Point"}
}