{
  "type": "Feature",
  "properties": {
    "gn:admin1_code":"30",
    "gn:asciiname":"Sumurbandung",
    "gn:country_code":"ID",
    "gn:dem":46,
    "gn:feature_class":"P",
    "gn:feature_code":"PPL",
    "gn:name":"Sumurbandung",
    "gn:population":0,
    "gn:timezone":"Asia/Jakarta",
    "iso:country":"ID",
    "name:ind_x_preferred":[
        "Sumurbandung"
    ],
    "wof:name":"Sumurbandung",
    "wof:placetype":"locality"
},
  "geometry": {"coordinates":[108.10778000000001,-6.71333],"type":"Point"}
}