{
  "type": "Feature",
  "properties": {
    "gn:admin1_code":"22",
    "gn:asciiname":"Laudu",
    "gn:country_code":"ID",
    "gn:dem":76,
    "gn:feature_class":"P",
    "gn:feature_code":"PPL",
    "gn:name":"Laudu",
    "gn:population":0,
    "gn:timezone":"Asia/Makassar",
    "iso:country":"ID",
    "name:ind_x_preferred":[
        "Laudu"
    ],
    "wof:name":"Laudu",
    "wof:placetype":"locality"
},
  "geometry": {"coordinates":[122.5337,-4.9084],"type":"Point"}
}