{
  "type": "Feature",
  "properties": {
    "gn:admin1_code":"30.0",
    "gn:asciiname":"Cimanglid",
    "gn:country_code":"ID",
    "gn:dem":683,
    "gn:feature_class":"P",
    "gn:feature_code":"PPL",
    "gn:name":"Cimanglid",
    "gn:population":0,
    "gn:timezone":"Asia/Jakarta",
    "iso:country":"ID",
    "name:ind_x_preferred":[
        "Cimanglid"
    ],
    "name:und_x_variant":[
        "Tjimanglid Tiga"
    ],
    "wof:lang_x_official":[
        "ind"
    ],
    "wof:lang_x_spoken":[
        "ind",
        "eng"
    ],
    "wof:name":"Cimanglid",
    "wof:placetype":"locality"
},
  "geometry": {"coordinates":[108.23860000000001,-7.0965],"type":"Point"}
}