{
  "type": "Feature",
  "properties": {
    "gn:admin1_code":"18",
    "gn:asciiname":"Tuke",
    "gn:country_code":"ID",
    "gn:dem":1082,
    "gn:feature_class":"P",
    "gn:feature_code":"PPL",
    "gn:name":"Tuke",
    "gn:population":0,
    "gn:timezone":"Asia/Makassar",
    "iso:country":"ID",
    "name:deu_x_preferred":[
        "Tuke"
    ],
    "name:fra_x_preferred":[
        "Tuke"
    ],
    "name:ind_x_preferred":[
        "Tuke"
    ],
    "name:rus_x_preferred":[
        "\u0422\u044e\u043a"
    ],
    "wof:name":"Tuke",
    "wof:placetype":"locality"
},
  "geometry": {"coordinates":[120.44670000000001,-8.5966],"type":"Point"}
}