{
  "type": "Feature",
  "properties": {
    "gn:admin1_code":"8.0",
    "gn:asciiname":"Ngagli",
    "gn:country_code":"ID",
    "gn:dem":434,
    "gn:feature_class":"P",
    "gn:feature_code":"PPL",
    "gn:name":"Ngagli",
    "gn:population":0,
    "gn:timezone":"Asia/Jakarta",
    "iso:country":"ID",
    "name:ind_x_preferred":[
        "Ngagli"
    ],
    "wof:name":"Ngagli",
    "wof:placetype":"locality"
},
  "geometry": {"coordinates":[111.02361000000001,-8.10139],"type":"Point"}
}