{
  "type": "Feature",
  "properties": {
    "gn:admin1_code":"30",
    "gn:asciiname":"Sipalasa",
    "gn:country_code":"ID",
    "gn:dem":5,
    "gn:feature_class":"P",
    "gn:feature_code":"PPL",
    "gn:name":"Sipalasa",
    "gn:population":0,
    "gn:timezone":"Asia/Jakarta",
    "iso:country":"ID",
    "name:ind_x_preferred":[
        "Sipalasa"
    ],
    "wof:name":"Sipalasa",
    "wof:placetype":"locality"
},
  "geometry": {"coordinates":[108.53449999999999,-6.6514],"type":"Point"}
}