{
  "type": "Feature",
  "properties": {
    "gn:country":"ID",
    "gn:fcode":"PPL",
    "gn:pop":0,
    "iso:country":"ID",
    "name:ind_x_preferred":[
        "Pucangsewu"
    ],
    "qs:name":"Pucangsewu",
    "qs:name_adm0":"Indonesia",
    "qs:name_adm1":"Jawa Timur",
    "qs:photos_9r":0,
    "qs:photos_sr":0,
    "qs:placetype":"Town",
    "qs:pop_sr":"0",
    "wof:name":"Pucangsewu",
    "wof:placetype":"locality",
    "wof:population":0
},
  "geometry": {"coordinates":[112.7521,-7.2872],"type":"Point"}
}