{
  "type": "Feature",
  "properties": {
    "gn:admin1_code":"18",
    "gn:asciiname":"Wololele A",
    "gn:country_code":"ID",
    "gn:dem":906,
    "gn:feature_class":"P",
    "gn:feature_code":"PPLA4",
    "gn:name":"Wololele A",
    "gn:population":0,
    "gn:timezone":"Asia/Makassar",
    "iso:country":"ID",
    "name:ind_x_preferred":[
        "Wololele A"
    ],
    "wof:name":"Wololele A",
    "wof:placetype":"locality"
},
  "geometry": {"coordinates":[121.9151,-8.7567],"type":"Point"}
}