{
  "type": "Feature",
  "properties": {
    "gn:admin1_code":"30",
    "gn:asciiname":"Bojongkihiang Dua",
    "gn:cc2":"ID",
    "gn:country_code":"ID",
    "gn:dem":870,
    "gn:feature_class":"P",
    "gn:feature_code":"PPL",
    "gn:name":"Bojongkihiang Dua",
    "gn:population":0,
    "gn:timezone":"Asia/Jakarta",
    "iso:country":"ID",
    "name:und_x_variant":[
        "Bodjongkihiang 2",
        "Bojongkihiang Dua"
    ],
    "wof:lang_x_official":[
        "ind"
    ],
    "wof:lang_x_spoken":[
        "ind",
        "eng"
    ],
    "wof:name":"Bojongkihiang Dua",
    "wof:placetype":"locality"
},
  "geometry": {"coordinates":[107.65555999999999,-6.87361],"type":"Point"}
}