{
  "type": "Feature",
  "properties": {
    "gn:admin1_code":"18.0",
    "gn:asciiname":"Kiuola",
    "gn:country_code":"ID",
    "gn:dem":363,
    "gn:feature_class":"P",
    "gn:feature_code":"PPLA4",
    "gn:name":"Kiuola",
    "gn:population":0,
    "gn:timezone":"Asia/Makassar",
    "iso:country":"ID",
    "name:ind_x_preferred":[
        "Kiuola"
    ],
    "wof:lang_x_official":[
        "ind"
    ],
    "wof:lang_x_spoken":[
        "ind",
        "eng"
    ],
    "wof:name":"Kiuola",
    "wof:placetype":"locality"
},
  "geometry": {"coordinates":[124.458,-9.5889],"type":"Point"}
}