{
  "type": "Feature",
  "properties": {
    "gn:admin1_code":"33",
    "gn:asciiname":"Bangbayang",
    "gn:country_code":"ID",
    "gn:dem":110,
    "gn:feature_class":"P",
    "gn:feature_code":"PPL",
    "gn:name":"Bangbayang",
    "gn:population":0,
    "gn:timezone":"Asia/Jakarta",
    "iso:country":"ID",
    "name:ind_x_preferred":[
        "Bangbayang"
    ],
    "wof:name":"Bangbayang",
    "wof:placetype":"locality"
},
  "geometry": {"coordinates":[105.95440000000001,-6.079],"type":"Point"}
}