{
  "type": "Feature",
  "properties": {
    "gn:admin1_code":"8",
    "gn:asciiname":"Junglorong",
    "gn:country_code":"ID",
    "gn:dem":28,
    "gn:feature_class":"P",
    "gn:feature_code":"PPL",
    "gn:name":"Junglorong",
    "gn:population":0,
    "gn:timezone":"Asia/Jakarta",
    "iso:country":"ID",
    "name:ind_x_preferred":[
        "Junglorong"
    ],
    "wof:name":"Junglorong",
    "wof:placetype":"locality"
},
  "geometry": {"coordinates":[113.23820000000001,-7.1148],"type":"Point"}
}