{
  "type": "Feature",
  "properties": {
    "gn:admin1_code":"31.0",
    "gn:asciiname":"Melebuhe",
    "gn:country_code":"ID",
    "gn:dem":25,
    "gn:feature_class":"P",
    "gn:feature_code":"PPL",
    "gn:name":"Melebuhe",
    "gn:population":0,
    "gn:timezone":"Asia/Makassar",
    "iso:country":"ID",
    "name:ind_x_preferred":[
        "Melebuhe"
    ],
    "wof:name":"Melebuhe",
    "wof:placetype":"locality"
},
  "geometry": {"coordinates":[125.4695,3.6146],"type":"Point"}
}