{
  "type": "Feature",
  "properties": {
    "gn:admin1_code":"30",
    "gn:asciiname":"Gununggombong",
    "gn:country_code":"ID",
    "gn:dem":976,
    "gn:feature_class":"P",
    "gn:feature_code":"PPL",
    "gn:name":"Gununggombong",
    "gn:population":0,
    "gn:timezone":"Asia/Jakarta",
    "iso:country":"ID",
    "name:ind_x_preferred":[
        "Gununggombong"
    ],
    "name:und_x_variant":[
        "Gununggambeng"
    ],
    "wof:name":"Gununggombong",
    "wof:placetype":"locality"
},
  "geometry": {"coordinates":[107.33138999999998,-6.99639],"type":"Point"}
}