{
  "type": "Feature",
  "properties": {
    "gn:admin1_code":"0.0",
    "gn:asciiname":"Tobobatu",
    "gn:cc2":"ID",
    "gn:country_code":"ID",
    "gn:dem":172,
    "gn:feature_class":"P",
    "gn:feature_code":"PPL",
    "gn:name":"Tobobatu",
    "gn:population":0,
    "gn:timezone":"Asia/Jayapura",
    "iso:country":"ID",
    "name:und_x_variant":[
        "Tobobatoe",
        "Tobobatu"
    ],
    "wof:name":"Tobobatu",
    "wof:placetype":"locality"
},
  "geometry": {"coordinates":[127.55,0.63333],"type":"Point"}
}