{
  "type": "Feature",
  "properties": {
    "gn:admin1_code":"28.0",
    "gn:asciiname":"Hatumeten",
    "gn:country_code":"ID",
    "gn:dem":46,
    "gn:feature_class":"P",
    "gn:feature_code":"PPL",
    "gn:name":"Hatumeten",
    "gn:population":0,
    "gn:timezone":"Asia/Jayapura",
    "iso:country":"ID",
    "name:ind_x_preferred":[
        "Hatumeten"
    ],
    "name:und_x_variant":[
        "Hatoemeten"
    ],
    "wof:name":"Hatumeten",
    "wof:placetype":"locality"
},
  "geometry": {"coordinates":[129.5864,-3.3073],"type":"Point"}
}