{
  "type": "Feature",
  "properties": {
    "gn:admin1_code":"15.0",
    "gn:asciiname":"Bedudu",
    "gn:country_code":"ID",
    "gn:dem":814,
    "gn:feature_class":"P",
    "gn:feature_code":"PPL",
    "gn:name":"Bedudu",
    "gn:population":0,
    "gn:timezone":"Asia/Jakarta",
    "iso:country":"ID",
    "name:ind_x_preferred":[
        "Bedudu"
    ],
    "name:und_x_variant":[
        "B\u0115doedoe"
    ],
    "wof:lang_x_official":[
        "ind"
    ],
    "wof:lang_x_spoken":[
        "ind",
        "eng"
    ],
    "wof:name":"Bedudu",
    "wof:placetype":"locality"
},
  "geometry": {"coordinates":[104.19602,-5.01605],"type":"Point"}
}