{
  "type": "Feature",
  "properties": {
    "gn:admin1_code":"17.0",
    "gn:asciiname":"Mbuju",
    "gn:country_code":"ID",
    "gn:dem":11,
    "gn:feature_class":"P",
    "gn:feature_code":"PPL",
    "gn:name":"Mbuju",
    "gn:population":0,
    "gn:timezone":"Asia/Makassar",
    "iso:country":"ID",
    "name:ind_x_preferred":[
        "Mbuju"
    ],
    "wof:name":"Mbuju",
    "wof:placetype":"locality"
},
  "geometry": {"coordinates":[118.33629999999999,-8.3673],"type":"Point"}
}