{
  "type": "Feature",
  "properties": {
    "gn:admin1_code":"7",
    "gn:asciiname":"Lompong",
    "gn:country_code":"ID",
    "gn:dem":1243,
    "gn:feature_class":"P",
    "gn:feature_code":"PPL",
    "gn:name":"Lompong",
    "gn:population":0,
    "gn:timezone":"Asia/Jakarta",
    "iso:country":"ID",
    "name:ind_x_preferred":[
        "Lompong"
    ],
    "wof:name":"Lompong",
    "wof:placetype":"locality"
},
  "geometry": {"coordinates":[109.28972,-7.22528],"type":"Point"}
}