{
  "type": "Feature",
  "properties": {
    "gn:admin1_code":"26",
    "gn:asciiname":"Baturancang",
    "gn:country_code":"ID",
    "gn:dem":425,
    "gn:feature_class":"P",
    "gn:feature_code":"PPL",
    "gn:name":"Baturancang",
    "gn:population":0,
    "gn:timezone":"Asia/Jakarta",
    "iso:country":"ID",
    "name:ind_x_preferred":[
        "Baturancang"
    ],
    "wof:name":"Baturancang",
    "wof:placetype":"locality"
},
  "geometry": {"coordinates":[99.49542,1.57936],"type":"Point"}
}