{
  "type": "Feature",
  "properties": {
    "gn:admin1_code":"21",
    "gn:asciiname":"Poboya",
    "gn:country_code":"ID",
    "gn:dem":170,
    "gn:feature_class":"P",
    "gn:feature_code":"PPL",
    "gn:name":"Poboya",
    "gn:population":0,
    "gn:timezone":"Asia/Makassar",
    "iso:country":"ID",
    "name:ind_x_preferred":[
        "Poboya"
    ],
    "wof:name":"Poboya",
    "wof:placetype":"locality"
},
  "geometry": {"coordinates":[119.9169,-0.8827],"type":"Point"}
}