{
  "type": "Feature",
  "properties": {
    "gn:admin1_code":"26.0",
    "gn:asciiname":"Purba Sianjur",
    "gn:country_code":"ID",
    "gn:dem":474,
    "gn:feature_class":"P",
    "gn:feature_code":"PPL",
    "gn:name":"Purba Sianjur",
    "gn:population":0,
    "gn:timezone":"Asia/Jakarta",
    "iso:country":"ID",
    "name:ind_x_preferred":[
        "Purba Sianjur"
    ],
    "wof:name":"Purba Sianjur",
    "wof:placetype":"locality"
},
  "geometry": {"coordinates":[98.5031,2.1518],"type":"Point"}
}