{
  "type": "Feature",
  "properties": {
    "gn:admin1_code":"7.0",
    "gn:asciiname":"Gender",
    "gn:country_code":"ID",
    "gn:dem":491,
    "gn:feature_class":"P",
    "gn:feature_code":"PPL",
    "gn:name":"Gender",
    "gn:population":0,
    "gn:timezone":"Asia/Jakarta",
    "iso:country":"ID",
    "name:ind_x_preferred":[
        "Gender"
    ],
    "wof:name":"Gender",
    "wof:placetype":"locality"
},
  "geometry": {"coordinates":[109.71861,-7.46722],"type":"Point"}
}