{
  "type": "Feature",
  "properties": {
    "gn:admin1_code":"0.0",
    "gn:asciiname":"Matindok",
    "gn:cc2":"ID",
    "gn:country_code":"ID",
    "gn:dem":2,
    "gn:feature_class":"P",
    "gn:feature_code":"PPL",
    "gn:name":"Matindok",
    "gn:population":0,
    "gn:timezone":"Asia/Makassar",
    "iso:country":"ID",
    "name:und_x_variant":[
        "Matindo",
        "Matindok"
    ],
    "wof:lang_x_official":[
        "ind"
    ],
    "wof:lang_x_spoken":[
        "ind",
        "eng"
    ],
    "wof:name":"Matindok",
    "wof:placetype":"locality"
},
  "geometry": {"coordinates":[122.46666999999999,-1.35],"type":"Point"}
}