{
  "type": "Feature",
  "properties": {
    "gn:admin1_code":"08",
    "gn:asciiname":"Sumbergondo",
    "gn:country_code":"ID",
    "gn:dem":1048,
    "gn:feature_class":"P",
    "gn:feature_code":"PPL",
    "gn:name":"Sumbergondo",
    "gn:population":0,
    "gn:timezone":"Asia/Jakarta",
    "iso:country":"ID",
    "wof:name":"Sumbergondo",
    "wof:placetype":"locality"
},
  "geometry": {"coordinates":[112.53389,-7.83139],"type":"Point"}
}