{
  "type": "Feature",
  "properties": {
    "gn:admin1_code":"33",
    "gn:asciiname":"Kadubinglu",
    "gn:country_code":"ID",
    "gn:dem":61,
    "gn:feature_class":"P",
    "gn:feature_code":"PPL",
    "gn:name":"Kadubinglu",
    "gn:population":0,
    "gn:timezone":"Asia/Jakarta",
    "iso:country":"ID",
    "name:ind_x_preferred":[
        "Kadubinglu"
    ],
    "wof:name":"Kadubinglu",
    "wof:placetype":"locality"
},
  "geometry": {"coordinates":[106.12616,-6.403],"type":"Point"}
}