{
  "type": "Feature",
  "properties": {
    "gn:admin1_code":"7",
    "gn:asciiname":"Kerekan",
    "gn:country_code":"ID",
    "gn:dem":80,
    "gn:feature_class":"P",
    "gn:feature_code":"PPL",
    "gn:name":"Kerekan",
    "gn:population":0,
    "gn:timezone":"Asia/Jakarta",
    "iso:country":"ID",
    "name:ind_x_preferred":[
        "Kerekan"
    ],
    "wof:name":"Kerekan",
    "wof:placetype":"locality"
},
  "geometry": {"coordinates":[111.05444,-7.33667],"type":"Point"}
}