{
  "type": "Feature",
  "properties": {
    "gn:admin1_code":"30.0",
    "gn:asciiname":"Pasirangin",
    "gn:country_code":"ID",
    "gn:dem":593,
    "gn:feature_class":"P",
    "gn:feature_code":"PPL",
    "gn:name":"Pasirangin",
    "gn:population":0,
    "gn:timezone":"Asia/Jakarta",
    "iso:country":"ID",
    "name:ind_x_preferred":[
        "Pasirangin"
    ],
    "name:und_x_variant":[
        "Pasirangin 1"
    ],
    "wof:name":"Pasirangin",
    "wof:placetype":"locality"
},
  "geometry": {"coordinates":[107.9327,-7.5109],"type":"Point"}
}