{
  "type": "Feature",
  "properties": {
    "gn:admin1_code":"30.0",
    "gn:asciiname":"Cijelag",
    "gn:country_code":"ID",
    "gn:dem":40,
    "gn:feature_class":"P",
    "gn:feature_code":"PPL",
    "gn:name":"Cijelag",
    "gn:population":0,
    "gn:timezone":"Asia/Jakarta",
    "iso:country":"ID",
    "name:ind_x_preferred":[
        "Cijelag"
    ],
    "name:und_x_variant":[
        "Tjidjelag"
    ],
    "wof:lang_x_official":[
        "ind"
    ],
    "wof:lang_x_spoken":[
        "ind",
        "eng"
    ],
    "wof:name":"Cijelag",
    "wof:placetype":"locality"
},
  "geometry": {"coordinates":[108.12444000000001,-6.76667],"type":"Point"}
}