{
  "type": "Feature",
  "properties": {
    "gn:admin1_code":"7.0",
    "gn:asciiname":"Harjosari",
    "gn:country_code":"ID",
    "gn:dem":426,
    "gn:feature_class":"P",
    "gn:feature_code":"PPL",
    "gn:name":"Harjosari",
    "gn:population":0,
    "gn:timezone":"Asia/Jakarta",
    "iso:country":"ID",
    "wof:name":"Harjosari",
    "wof:placetype":"locality"
},
  "geometry": {"coordinates":[110.22111,-7.39639],"type":"Point"}
}