{
  "type": "Feature",
  "properties": {
    "gn:admin1_code":"10.0",
    "gn:asciiname":"Gebang",
    "gn:country_code":"ID",
    "gn:dem":237,
    "gn:feature_class":"P",
    "gn:feature_code":"PPL",
    "gn:name":"Gebang",
    "gn:population":0,
    "gn:timezone":"Asia/Jakarta",
    "iso:country":"ID",
    "name:bih_x_preferred":[
        "\u0917\u0947\u092c\u093e\u0902\u0917"
    ],
    "name:ind_x_preferred":[
        "Gebang"
    ],
    "name:ind_x_variant":[
        "Candi Gebang"
    ],
    "name:jav_x_preferred":[
        "Candhi Gebang"
    ],
    "name:tat_x_preferred":[
        "\u0413\u0435\u0431\u0430\u043d\u0433"
    ],
    "wof:name":"Gebang",
    "wof:placetype":"locality"
},
  "geometry": {"coordinates":[110.63972,-8.05722],"type":"Point"}
}