{
  "type": "Feature",
  "properties": {
    "gn:admin1_code":"21",
    "gn:asciiname":"Kumbung",
    "gn:country_code":"ID",
    "gn:dem":10,
    "gn:feature_class":"P",
    "gn:feature_code":"PPL",
    "gn:name":"Kumbung",
    "gn:population":0,
    "gn:timezone":"Asia/Makassar",
    "iso:country":"ID",
    "name:ind_x_preferred":[
        "Kumbung"
    ],
    "wof:name":"Kumbung",
    "wof:placetype":"locality"
},
  "geometry": {"coordinates":[120.7081,0.8649],"type":"Point"}
}