{
  "type": "Feature",
  "properties": {
    "gn:admin1_code":"26",
    "gn:asciiname":"Pasirbara",
    "gn:country_code":"ID",
    "gn:dem":78,
    "gn:feature_class":"P",
    "gn:feature_code":"PPL",
    "gn:name":"Pasirbara",
    "gn:population":0,
    "gn:timezone":"Asia/Jakarta",
    "iso:country":"ID",
    "name:ind_x_preferred":[
        "Pasirbara"
    ],
    "wof:name":"Pasirbara",
    "wof:placetype":"locality"
},
  "geometry": {"coordinates":[99.77439,1.61715],"type":"Point"}
}