{
  "type": "Feature",
  "properties": {
    "gn:admin1_code":"7.0",
    "gn:asciiname":"Banjaran",
    "gn:country_code":"ID",
    "gn:dem":666,
    "gn:feature_class":"P",
    "gn:feature_code":"PPL",
    "gn:name":"Banjaran",
    "gn:population":0,
    "gn:timezone":"Asia/Jakarta",
    "iso:country":"ID",
    "name:fas_x_preferred":[
        "\u0628\u0627\u0646\u062c\u0627\u0631\u0627\u0646"
    ],
    "name:mlg_x_preferred":[
        "Banjaran"
    ],
    "name:new_x_preferred":[
        "\u092c\u0902\u091c\u093e\u0930\u0928"
    ],
    "wof:lang_x_official":[
        "ind"
    ],
    "wof:lang_x_spoken":[
        "ind",
        "eng"
    ],
    "wof:name":"Banjaran",
    "wof:placetype":"locality"
},
  "geometry": {"coordinates":[110.14333000000001,-7.45861],"type":"Point"}
}