{
  "type": "Feature",
  "properties": {
    "gn:admin1_code":"7.0",
    "gn:asciiname":"Banjaran",
    "gn:country_code":"ID",
    "gn:dem":666,
    "gn:feature_class":"P",
    "gn:feature_code":"PPL",
    "gn:name":"Banjaran",
    "gn:population":0,
    "gn:timezone":"Asia/Jakarta",
    "iso:country":"ID",
    "wof:name":"Banjaran",
    "wof:placetype":"locality"
},
  "geometry": {"coordinates":[110.14333000000001,-7.45861],"type":"Point"}
}