{
  "type": "Feature",
  "properties": {
    "gn:admin1_code":"41.0",
    "gn:asciiname":"Tubulutang",
    "gn:country_code":"ID",
    "gn:dem":56,
    "gn:feature_class":"P",
    "gn:feature_code":"PPL",
    "gn:name":"Tubulutang",
    "gn:population":0,
    "gn:timezone":"Asia/Makassar",
    "iso:country":"ID",
    "name:ind_x_preferred":[
        "Tubulutang"
    ],
    "wof:name":"Tubulutang",
    "wof:placetype":"locality"
},
  "geometry": {"coordinates":[118.9905,-3.4046],"type":"Point"}
}