{
  "type": "Feature",
  "properties": {
    "gn:admin1_code":"26.0",
    "gn:asciiname":"Hutatano",
    "gn:country_code":"ID",
    "gn:dem":1388,
    "gn:feature_class":"P",
    "gn:feature_code":"PPL",
    "gn:name":"Hutatano",
    "gn:population":0,
    "gn:timezone":"Asia/Jakarta",
    "iso:country":"ID",
    "name:ind_x_preferred":[
        "Hutatano"
    ],
    "name:und_x_variant":[
        "Hoetatanah"
    ],
    "wof:lang_x_official":[
        "ind"
    ],
    "wof:lang_x_spoken":[
        "ind",
        "eng"
    ],
    "wof:name":"Hutatano",
    "wof:placetype":"locality"
},
  "geometry": {"coordinates":[98.619,2.9101],"type":"Point"}
}