{
  "type": "Feature",
  "properties": {
    "gn:admin1_code":"31.0",
    "gn:asciiname":"Batubulan",
    "gn:country_code":"ID",
    "gn:dem":81,
    "gn:feature_class":"P",
    "gn:feature_code":"PPL",
    "gn:name":"Batubulan",
    "gn:population":0,
    "gn:timezone":"Asia/Makassar",
    "iso:country":"ID",
    "name:ind_x_preferred":[
        "Batubulan"
    ],
    "wof:name":"Batubulan",
    "wof:placetype":"locality"
},
  "geometry": {"coordinates":[125.4055,2.8105],"type":"Point"}
}