{
  "type": "Feature",
  "properties": {
    "gn:country":"ID",
    "gn:fcode":"ADM4",
    "gn:pop":0,
    "iso:country":"ID",
    "name:ind_x_preferred":[
        "Desa Jungutbatu"
    ],
    "name:unk_x_variant":[
        "Jungutbatu"
    ],
    "qs:name":"Desa Jungutbatu",
    "qs:photos_9r":0,
    "qs:photos_sr":0,
    "qs:pop_sr":"0",
    "wof:name":"Desa Jungutbatu",
    "wof:placetype":"localadmin",
    "wof:population":0
},
  "geometry": {"coordinates":[115.45310000000001,-8.6787],"type":"Point"}
}