{
  "type": "Feature",
  "properties": {
    "gn:admin1_code":"8",
    "gn:asciiname":"Kendal",
    "gn:country_code":"ID",
    "gn:dem":56,
    "gn:feature_class":"P",
    "gn:feature_code":"PPL",
    "gn:name":"Kendal",
    "gn:population":0,
    "gn:timezone":"Asia/Jakarta",
    "iso:country":"ID",
    "name:azb_x_preferred":[
        "\u06a9\u0646\u062f\u0627\u0644"
    ],
    "name:bul_x_preferred":[
        "\u041a\u0435\u043d\u0434\u0430\u043b"
    ],
    "name:cat_x_preferred":[
        "Kendal"
    ],
    "name:ceb_x_preferred":[
        "Kendal"
    ],
    "name:cym_x_preferred":[
        "Kendal"
    ],
    "name:dan_x_preferred":[
        "Kendal"
    ],
    "name:deu_x_preferred":[
        "Kendal"
    ],
    "name:epo_x_preferred":[
        "Kendal"
    ],
    "name:fas_x_preferred":[
        "\u06a9\u0646\u062f\u0627\u0644"
    ],
    "name:fra_x_preferred":[
        "Kendal"
    ],
    "name:gle_x_preferred":[
        "Kendal"
    ],
    "name:ind_x_preferred":[
        "Kendal"
    ],
    "name:ita_x_preferred":[
        "Kendal"
    ],
    "name:jpn_x_preferred":[
        "\u30b1\u30f3\u30c0\u30eb"
    ],
    "name:nld_x_preferred":[
        "Kendal"
    ],
    "name:nno_x_preferred":[
        "Kendal"
    ],
    "name:nor_x_preferred":[
        "Kendal"
    ],
    "name:pol_x_preferred":[
        "Kendal"
    ],
    "name:por_x_preferred":[
        "Kendal"
    ],
    "name:ron_x_preferred":[
        "Kendal"
    ],
    "name:spa_x_preferred":[
        "Kendal"
    ],
    "name:swe_x_preferred":[
        "Kendal"
    ],
    "name:vol_x_preferred":[
        "Kendal"
    ],
    "name:zho_x_preferred":[
        "\u80af\u5fb7\u723e"
    ],
    "wof:lang_x_official":[
        "ind"
    ],
    "wof:lang_x_spoken":[
        "ind",
        "eng"
    ],
    "wof:name":"Kendal",
    "wof:placetype":"locality"
},
  "geometry": {"coordinates":[113.0257,-7.6837],"type":"Point"}
}