{
  "type": "Feature",
  "properties": {
    "gn:admin1_code":"15.0",
    "gn:asciiname":"Besuki",
    "gn:country_code":"ID",
    "gn:dem":183,
    "gn:feature_class":"P",
    "gn:feature_code":"PPL",
    "gn:name":"Besuki",
    "gn:population":0,
    "gn:timezone":"Asia/Jakarta",
    "iso:country":"ID",
    "name:ind_x_preferred":[
        "Besuki"
    ],
    "name:jav_x_preferred":[
        "Besuki"
    ],
    "name:min_x_preferred":[
        "Besuki"
    ],
    "name:swe_x_preferred":[
        "Besuki"
    ],
    "wof:lang_x_official":[
        "ind"
    ],
    "wof:lang_x_spoken":[
        "ind",
        "eng"
    ],
    "wof:name":"Besuki",
    "wof:placetype":"locality"
},
  "geometry": {"coordinates":[104.53124,-4.737],"type":"Point"}
}