{
  "type": "Feature",
  "properties": {
    "gn:admin1_code":"26",
    "gn:asciiname":"Buntukriahan",
    "gn:country_code":"ID",
    "gn:dem":273,
    "gn:feature_class":"P",
    "gn:feature_code":"PPL",
    "gn:name":"Buntukriahan",
    "gn:population":0,
    "gn:timezone":"Asia/Jakarta",
    "iso:country":"ID",
    "name:ind_x_preferred":[
        "Buntukriahan"
    ],
    "wof:name":"Buntukriahan",
    "wof:placetype":"locality"
},
  "geometry": {"coordinates":[98.7633,3.2313],"type":"Point"}
}