{
  "type": "Feature",
  "properties": {
    "gn:country":"ID",
    "gn:fcode":"PPL",
    "gn:pop":0,
    "iso:country":"ID",
    "name:unk_x_variant":[
        "Kalisuren 2"
    ],
    "qs:name":"Kalisuren Dua",
    "qs:name_adm0":"Indonesia",
    "qs:name_adm1":"Jawa Barat",
    "qs:photos_9k":1,
    "qs:photos_9r":1,
    "qs:photos_all":2,
    "qs:photos_sr":0,
    "qs:placetype":"Town",
    "qs:pop_sr":"0",
    "wof:name":"Kalisuren Dua",
    "wof:placetype":"locality",
    "wof:population":0
},
  "geometry": {"coordinates":[106.7375,-6.45222],"type":"Point"}
}