{
  "type": "Feature",
  "properties": {
    "gn:admin1_code":"30.0",
    "gn:asciiname":"Cigadung",
    "gn:country_code":"ID",
    "gn:dem":617,
    "gn:feature_class":"P",
    "gn:feature_code":"PPL",
    "gn:name":"Cigadung",
    "gn:population":0,
    "gn:timezone":"Asia/Jakarta",
    "iso:country":"ID",
    "name:ind_x_preferred":[
        "Cigadung"
    ],
    "wof:name":"Cigadung",
    "wof:placetype":"locality"
},
  "geometry": {"coordinates":[107.9573,-7.1002],"type":"Point"}
}