{
  "type": "Feature",
  "properties": {
    "gn:admin1_code":"8.0",
    "gn:asciiname":"Melian",
    "gn:country_code":"ID",
    "gn:dem":215,
    "gn:feature_class":"P",
    "gn:feature_code":"PPL",
    "gn:name":"Melian",
    "gn:population":0,
    "gn:timezone":"Asia/Jakarta",
    "iso:country":"ID",
    "name:ind_x_preferred":[
        "Melian"
    ],
    "wof:name":"Melian",
    "wof:placetype":"locality"
},
  "geometry": {"coordinates":[111.0175,-8.22083],"type":"Point"}
}