{
  "type": "Feature",
  "properties": {
    "gn:admin1_code":"30",
    "gn:asciiname":"Jambu Wetan",
    "gn:country_code":"ID",
    "gn:dem":35,
    "gn:feature_class":"P",
    "gn:feature_code":"PPL",
    "gn:name":"Jambu Wetan",
    "gn:population":0,
    "gn:timezone":"Asia/Jakarta",
    "iso:country":"ID",
    "name:ind_x_preferred":[
        "Jambu Wetan"
    ],
    "wof:name":"Jambu Wetan",
    "wof:placetype":"locality"
},
  "geometry": {"coordinates":[107.91667,-6.50944],"type":"Point"}
}