{
  "type": "Feature",
  "properties": {
    "gn:admin1_code":"33",
    "gn:asciiname":"Nagreg",
    "gn:country_code":"ID",
    "gn:dem":112,
    "gn:feature_class":"P",
    "gn:feature_code":"PPL",
    "gn:name":"Nagreg",
    "gn:population":0,
    "gn:timezone":"Asia/Jakarta",
    "iso:country":"ID",
    "name:ind_x_preferred":[
        "Nagreg"
    ],
    "wof:name":"Nagreg",
    "wof:placetype":"locality"
},
  "geometry": {"coordinates":[106.1506,-6.357],"type":"Point"}
}