{
  "type": "Feature",
  "properties": {
    "gn:admin1_code":"18.0",
    "gn:asciiname":"Noemuti",
    "gn:country_code":"ID",
    "gn:dem":334,
    "gn:feature_class":"P",
    "gn:feature_code":"PPLA3",
    "gn:name":"Noemuti",
    "gn:population":0,
    "gn:timezone":"Asia/Makassar",
    "iso:country":"ID",
    "name:und_x_variant":[
        "No\u00ebmoeti",
        "Noemuti"
    ],
    "wof:name":"Noemuti",
    "wof:placetype":"locality"
},
  "geometry": {"coordinates":[124.495,-9.568],"type":"Point"}
}