{
  "type": "Feature",
  "properties": {
    "gn:admin1_code":"18.0",
    "gn:asciiname":"Bubuk",
    "gn:country_code":"ID",
    "gn:dem":513,
    "gn:feature_class":"P",
    "gn:feature_code":"PPL",
    "gn:name":"Bubuk",
    "gn:population":0,
    "gn:timezone":"Asia/Makassar",
    "iso:country":"ID",
    "name:ind_x_preferred":[
        "Bubuk"
    ],
    "wof:name":"Bubuk",
    "wof:placetype":"locality"
},
  "geometry": {"coordinates":[122.6619,-8.4885],"type":"Point"}
}