{
  "type": "Feature",
  "properties": {
    "gn:admin1_code":"30.0",
    "gn:asciiname":"Bantar",
    "gn:country_code":"ID",
    "gn:dem":386,
    "gn:feature_class":"P",
    "gn:feature_code":"PPLA4",
    "gn:name":"Bantar",
    "gn:population":0,
    "gn:timezone":"Asia/Jakarta",
    "iso:country":"ID",
    "name:ind_x_preferred":[
        "Bantar"
    ],
    "wof:lang_x_official":[
        "ind"
    ],
    "wof:lang_x_spoken":[
        "ind",
        "eng"
    ],
    "wof:name":"Bantar",
    "wof:placetype":"locality"
},
  "geometry": {"coordinates":[108.1897,-7.3231],"type":"Point"}
}