{
  "type": "Feature",
  "properties": {
    "gn:admin1_code":"18.0",
    "gn:asciiname":"Bileon",
    "gn:country_code":"ID",
    "gn:dem":499,
    "gn:feature_class":"P",
    "gn:feature_code":"PPLA4",
    "gn:name":"Bileon",
    "gn:population":0,
    "gn:timezone":"Asia/Makassar",
    "iso:country":"ID",
    "name:ind_x_preferred":[
        "Bileon"
    ],
    "wof:name":"Bileon",
    "wof:placetype":"locality"
},
  "geometry": {"coordinates":[124.5364,-9.7853],"type":"Point"}
}