{
  "type": "Feature",
  "properties": {
    "gn:admin1_code":"26",
    "gn:asciiname":"Tandukanraga",
    "gn:country_code":"ID",
    "gn:dem":36,
    "gn:feature_class":"P",
    "gn:feature_code":"PPL",
    "gn:name":"Tandukanraga",
    "gn:population":0,
    "gn:timezone":"Asia/Jakarta",
    "iso:country":"ID",
    "name:ind_x_preferred":[
        "Tandukanraga"
    ],
    "wof:name":"Tandukanraga",
    "wof:placetype":"locality"
},
  "geometry": {"coordinates":[98.76000000000001,3.4815],"type":"Point"}
}