{
  "type": "Feature",
  "properties": {
    "gn:admin1_code":"7.0",
    "gn:asciiname":"Tukul",
    "gn:country_code":"ID",
    "gn:dem":189,
    "gn:feature_class":"P",
    "gn:feature_code":"PPL",
    "gn:name":"Tukul",
    "gn:population":0,
    "gn:timezone":"Asia/Jakarta",
    "iso:country":"ID",
    "name:ita_x_preferred":[
        "Tucul"
    ],
    "wof:name":"Tukul",
    "wof:placetype":"locality"
},
  "geometry": {"coordinates":[110.95778,-7.91917],"type":"Point"}
}