{
  "type": "Feature",
  "properties": {
    "gn:admin1_code":"30",
    "gn:asciiname":"Dangdeur",
    "gn:country_code":"ID",
    "gn:dem":803,
    "gn:feature_class":"P",
    "gn:feature_code":"PPL",
    "gn:name":"Dangdeur",
    "gn:population":0,
    "gn:timezone":"Asia/Jakarta",
    "iso:country":"ID",
    "name:ind_x_preferred":[
        "Dangdeur"
    ],
    "wof:name":"Dangdeur",
    "wof:placetype":"locality"
},
  "geometry": {"coordinates":[107.11750000000001,-6.73806],"type":"Point"}
}