{
  "type": "Feature",
  "properties": {
    "gn:admin1_code":"30",
    "gn:asciiname":"Cikupa",
    "gn:country_code":"ID",
    "gn:dem":885,
    "gn:feature_class":"P",
    "gn:feature_code":"PPL",
    "gn:name":"Cikupa",
    "gn:population":0,
    "gn:timezone":"Asia/Jakarta",
    "iso:country":"ID",
    "name:ind_x_preferred":[
        "Cikupa"
    ],
    "wof:name":"Cikupa",
    "wof:placetype":"locality"
},
  "geometry": {"coordinates":[107.52110999999999,-6.83667],"type":"Point"}
}