{
  "type": "Feature",
  "properties": {
    "gn:admin1_code":"38.0",
    "gn:asciiname":"Pakeng",
    "gn:country_code":"ID",
    "gn:dem":22,
    "gn:feature_class":"P",
    "gn:feature_code":"PPL",
    "gn:name":"Pakeng",
    "gn:population":0,
    "gn:timezone":"Asia/Makassar",
    "iso:country":"ID",
    "name:ind_x_preferred":[
        "Pakeng"
    ],
    "wof:name":"Pakeng",
    "wof:placetype":"locality"
},
  "geometry": {"coordinates":[119.57250000000001,-3.5529],"type":"Point"}
}