{
  "type": "Feature",
  "properties": {
    "gn:admin1_code":"18.0",
    "gn:asciiname":"Talnusak",
    "gn:country_code":"ID",
    "gn:dem":10,
    "gn:feature_class":"P",
    "gn:feature_code":"PPL",
    "gn:name":"Talnusak",
    "gn:population":0,
    "gn:timezone":"Asia/Makassar",
    "iso:country":"ID",
    "name:ind_x_preferred":[
        "Talnusak"
    ],
    "wof:name":"Talnusak",
    "wof:placetype":"locality"
},
  "geometry": {"coordinates":[123.51730000000001,-10.3215],"type":"Point"}
}