{
  "type": "Feature",
  "properties": {
    "gn:admin1_code":"8.0",
    "gn:asciiname":"Perreng",
    "gn:country_code":"ID",
    "gn:dem":8,
    "gn:feature_class":"P",
    "gn:feature_code":"PPLA4",
    "gn:name":"Perreng",
    "gn:population":0,
    "gn:timezone":"Asia/Jakarta",
    "iso:country":"ID",
    "name:ind_x_preferred":[
        "Perreng"
    ],
    "wof:name":"Perreng",
    "wof:placetype":"locality"
},
  "geometry": {"coordinates":[113.9689,-6.8762],"type":"Point"}
}