{
  "type": "Feature",
  "properties": {
    "gn:admin1_code":"30.0",
    "gn:asciiname":"Cibingbin",
    "gn:country_code":"ID",
    "gn:dem":79,
    "gn:feature_class":"P",
    "gn:feature_code":"PPLA3",
    "gn:name":"Cibingbin",
    "gn:population":0,
    "gn:timezone":"Asia/Jakarta",
    "iso:country":"ID",
    "name:ind_x_preferred":[
        "Cibingbin"
    ],
    "name:und_x_variant":[
        "Tjibingbin",
        "Cibingbin"
    ],
    "wof:name":"Cibingbin",
    "wof:placetype":"locality"
},
  "geometry": {"coordinates":[108.7619,-7.0611],"type":"Point"}
}