{
  "type": "Feature",
  "properties": {
    "gn:admin1_code":"1",
    "gn:asciiname":"Seuneubok Rambong",
    "gn:country_code":"ID",
    "gn:dem":3,
    "gn:feature_class":"P",
    "gn:feature_code":"PPL",
    "gn:name":"Seuneubok Rambong",
    "gn:population":0,
    "gn:timezone":"Asia/Jakarta",
    "iso:country":"ID",
    "name:ind_x_preferred":[
        "Seuneubok Rambong"
    ],
    "wof:name":"Seuneubok Rambong",
    "wof:placetype":"locality"
},
  "geometry": {"coordinates":[97.78619999999999,4.945],"type":"Point"}
}