{
  "type": "Feature",
  "properties": {
    "gn:admin1_code":"18.0",
    "gn:asciiname":"Oeyek",
    "gn:country_code":"ID",
    "gn:dem":720,
    "gn:feature_class":"P",
    "gn:feature_code":"PPL",
    "gn:name":"Oeyek",
    "gn:population":0,
    "gn:timezone":"Asia/Makassar",
    "iso:country":"ID",
    "name:ind_x_preferred":[
        "Oeyek"
    ],
    "wof:name":"Oeyek",
    "wof:placetype":"locality"
},
  "geometry": {"coordinates":[124.6024,-9.8506],"type":"Point"}
}