{
  "type": "Feature",
  "properties": {
    "gn:admin1_code":"8.0",
    "gn:asciiname":"Komes",
    "gn:country_code":"ID",
    "gn:dem":169,
    "gn:feature_class":"P",
    "gn:feature_code":"PPL",
    "gn:name":"Komes",
    "gn:population":0,
    "gn:timezone":"Asia/Jakarta",
    "iso:country":"ID",
    "name:ind_x_preferred":[
        "Komes"
    ],
    "name:pol_x_preferred":[
        "Komesowie"
    ],
    "wof:lang_x_official":[
        "ind"
    ],
    "wof:lang_x_spoken":[
        "ind",
        "eng"
    ],
    "wof:name":"Komes",
    "wof:placetype":"locality"
},
  "geometry": {"coordinates":[113.3703,-7.1003],"type":"Point"}
}