{
  "type": "Feature",
  "properties": {
    "gn:admin1_code":"15.0",
    "gn:asciiname":"Umbulan Bawangko",
    "gn:country_code":"ID",
    "gn:dem":20,
    "gn:feature_class":"P",
    "gn:feature_code":"PPL",
    "gn:name":"Umbulan Bawangko",
    "gn:population":0,
    "gn:timezone":"Asia/Jakarta",
    "iso:country":"ID",
    "name:ind_x_preferred":[
        "Umbulan Bawangko"
    ],
    "name:ind_x_variant":[
        "Umbulanbawangko"
    ],
    "wof:name":"Umbulan Bawangko",
    "wof:placetype":"locality"
},
  "geometry": {"coordinates":[105.26863,-4.38413],"type":"Point"}
}