{
  "type": "Feature",
  "properties": {
    "gn:admin1_code":"30",
    "gn:asciiname":"Babakan",
    "gn:country_code":"ID",
    "gn:dem":49,
    "gn:feature_class":"P",
    "gn:feature_code":"PPL",
    "gn:name":"Babakan",
    "gn:population":0,
    "gn:timezone":"Asia/Jakarta",
    "iso:country":"ID",
    "name:aze_x_preferred":[
        "Bab\u0259kan"
    ],
    "name:ceb_x_preferred":[
        "B\u0101bak\u0101n"
    ],
    "name:fas_x_preferred":[
        "\u0628\u0627\u0628\u06a9\u0627\u0646"
    ],
    "name:ind_x_preferred":[
        "Babakan"
    ],
    "name:msa_x_preferred":[
        "Babakan"
    ],
    "name:swe_x_preferred":[
        "B\u0101bak\u0101n"
    ],
    "wof:lang_x_official":[
        "ind"
    ],
    "wof:lang_x_spoken":[
        "ind",
        "eng"
    ],
    "wof:name":"Babakan",
    "wof:placetype":"locality"
},
  "geometry": {"coordinates":[107.38500000000001,-6.39861],"type":"Point"}
}