{
  "type": "Feature",
  "properties": {
    "gn:admin1_code":"30.0",
    "gn:asciiname":"Cipogor",
    "gn:country_code":"ID",
    "gn:dem":728,
    "gn:feature_class":"P",
    "gn:feature_code":"PPL",
    "gn:name":"Cipogor",
    "gn:population":0,
    "gn:timezone":"Asia/Jakarta",
    "iso:country":"ID",
    "name:ind_x_preferred":[
        "Cipogor"
    ],
    "name:und_x_variant":[
        "Tjipogor",
        "Cipogor"
    ],
    "wof:name":"Cipogor",
    "wof:placetype":"locality"
},
  "geometry": {"coordinates":[107.29170000000001,-7.339],"type":"Point"}
}