{
  "type": "Feature",
  "properties": {
    "gn:admin1_code":"17",
    "gn:asciiname":"Bunlesong",
    "gn:country_code":"ID",
    "gn:dem":204,
    "gn:feature_class":"P",
    "gn:feature_code":"PPL",
    "gn:name":"Bunlesong",
    "gn:population":0,
    "gn:timezone":"Asia/Makassar",
    "iso:country":"ID",
    "name:ind_x_preferred":[
        "Bunlesong"
    ],
    "wof:name":"Bunlesong",
    "wof:placetype":"locality"
},
  "geometry": {"coordinates":[116.2527,-8.8587],"type":"Point"}
}