{
  "type": "Feature",
  "properties": {
    "gn:admin1_code":"30.0",
    "gn:asciiname":"Paburuan",
    "gn:country_code":"ID",
    "gn:dem":443,
    "gn:feature_class":"P",
    "gn:feature_code":"PPL",
    "gn:name":"Paburuan",
    "gn:population":0,
    "gn:timezone":"Asia/Jakarta",
    "iso:country":"ID",
    "name:ind_x_preferred":[
        "Paburuan"
    ],
    "name:und_x_variant":[
        "Paboewaran"
    ],
    "wof:lang_x_official":[
        "ind"
    ],
    "wof:lang_x_spoken":[
        "ind",
        "eng"
    ],
    "wof:name":"Paburuan",
    "wof:placetype":"locality"
},
  "geometry": {"coordinates":[108.3126,-7.2613],"type":"Point"}
}