{
  "type": "Feature",
  "properties": {
    "gn:admin1_code":"1",
    "gn:asciiname":"Cot Blang",
    "gn:country_code":"ID",
    "gn:dem":5,
    "gn:feature_class":"P",
    "gn:feature_code":"PPL",
    "gn:name":"Cot Blang",
    "gn:population":0,
    "gn:timezone":"Asia/Jakarta",
    "iso:country":"ID",
    "name:ind_x_preferred":[
        "Cot Blang"
    ],
    "wof:name":"Cot Blang",
    "wof:placetype":"locality"
},
  "geometry": {"coordinates":[97.3503,5.1234],"type":"Point"}
}