{
  "type": "Feature",
  "properties": {
    "gn:admin1_code":"34.0",
    "gn:asciiname":"Yilantala",
    "gn:country_code":"ID",
    "gn:dem":26,
    "gn:feature_class":"P",
    "gn:feature_code":"PPL",
    "gn:name":"Yilantala",
    "gn:population":0,
    "gn:timezone":"Asia/Makassar",
    "iso:country":"ID",
    "name:ind_x_preferred":[
        "Yilantala"
    ],
    "wof:name":"Yilantala",
    "wof:placetype":"locality"
},
  "geometry": {"coordinates":[123.1347,0.5318],"type":"Point"}
}