{
  "type": "Feature",
  "properties": {
    "gn:admin1_code":"22.0",
    "gn:asciiname":"Eelahaji",
    "gn:country_code":"ID",
    "gn:dem":18,
    "gn:feature_class":"P",
    "gn:feature_code":"PPL",
    "gn:name":"Eelahaji",
    "gn:population":0,
    "gn:timezone":"Asia/Makassar",
    "iso:country":"ID",
    "name:ind_x_preferred":[
        "Eelahaji"
    ],
    "wof:name":"Eelahaji",
    "wof:placetype":"locality"
},
  "geometry": {"coordinates":[123.1773,-4.7603],"type":"Point"}
}