{
  "type": "Feature",
  "properties": {
    "gn:admin1_code":"38.0",
    "gn:asciiname":"Loka",
    "gn:country_code":"ID",
    "gn:dem":465,
    "gn:feature_class":"P",
    "gn:feature_code":"PPL",
    "gn:name":"Loka",
    "gn:population":0,
    "gn:timezone":"Asia/Makassar",
    "iso:country":"ID",
    "name:ind_x_preferred":[
        "Loka"
    ],
    "wof:name":"Loka",
    "wof:placetype":"locality"
},
  "geometry": {"coordinates":[119.6872,-3.5341],"type":"Point"}
}