{
  "type": "Feature",
  "properties": {
    "gn:admin1_code":"7.0",
    "gn:asciiname":"Sono",
    "gn:country_code":"ID",
    "gn:dem":72,
    "gn:feature_class":"P",
    "gn:feature_code":"PPL",
    "gn:name":"Sono",
    "gn:population":0,
    "gn:timezone":"Asia/Jakarta",
    "iso:country":"ID",
    "name:ceb_x_preferred":[
        "Sono"
    ],
    "name:deu_x_preferred":[
        "Sono"
    ],
    "name:glg_x_preferred":[
        "Sono"
    ],
    "name:ind_x_preferred":[
        "Sono"
    ],
    "name:ita_x_preferred":[
        "Sono"
    ],
    "name:nld_x_preferred":[
        "Sono"
    ],
    "name:por_x_preferred":[
        "Sono"
    ],
    "name:rus_x_preferred":[
        "\u0421\u043e\u043d\u043e"
    ],
    "name:slk_x_preferred":[
        "Sono"
    ],
    "name:srp_x_preferred":[
        "\u0428\u043e\u043d\u043e"
    ],
    "name:swe_x_preferred":[
        "Sono"
    ],
    "name:vec_x_preferred":[
        "Sono"
    ],
    "wof:lang_x_official":[
        "ind"
    ],
    "wof:lang_x_spoken":[
        "ind",
        "eng"
    ],
    "wof:name":"Sono",
    "wof:placetype":"locality"
},
  "geometry": {"coordinates":[111.0647,-7.0407],"type":"Point"}
}