{
  "type": "Feature",
  "properties": {
    "gn:admin1_code":"41.0",
    "gn:asciiname":"Barung",
    "gn:country_code":"ID",
    "gn:dem":1224,
    "gn:feature_class":"P",
    "gn:feature_code":"PPL",
    "gn:name":"Barung",
    "gn:population":0,
    "gn:timezone":"Asia/Makassar",
    "iso:country":"ID",
    "name:ind_x_preferred":[
        "Barung"
    ],
    "name:und_x_variant":[
        "Barong",
        "Baroeng"
    ],
    "wof:lang_x_official":[
        "ind"
    ],
    "wof:lang_x_spoken":[
        "ind",
        "eng"
    ],
    "wof:name":"Barung",
    "wof:placetype":"locality"
},
  "geometry": {"coordinates":[119.4153,-2.9109],"type":"Point"}
}