{
  "type": "Feature",
  "properties": {
    "gn:country":"ID",
    "gn:fcode":"PPL",
    "gn:pop":0,
    "iso:country":"ID",
    "name:ind_x_preferred":[
        "Kandangjati Kulon"
    ],
    "qs:name":"Kandangjati Kulon",
    "qs:name_adm0":"Indonesia",
    "qs:name_adm1":"Jawa Timur",
    "qs:photos_9r":0,
    "qs:photos_sr":0,
    "qs:placetype":"Town",
    "qs:pop_sr":"0",
    "wof:name":"Kandangjati Kulon",
    "wof:placetype":"locality",
    "wof:population":0
},
  "geometry": {"coordinates":[113.4389,-7.76218],"type":"Point"}
}