{
  "type": "Feature",
  "properties": {
    "gn:admin1_code":"18.0",
    "gn:asciiname":"Langeramutu",
    "gn:country_code":"ID",
    "gn:dem":184,
    "gn:feature_class":"P",
    "gn:feature_code":"PPL",
    "gn:name":"Langeramutu",
    "gn:population":0,
    "gn:timezone":"Asia/Makassar",
    "iso:country":"ID",
    "name:ind_x_preferred":[
        "Langeramutu"
    ],
    "wof:name":"Langeramutu",
    "wof:placetype":"locality"
},
  "geometry": {"coordinates":[119.27589999999999,-9.7138],"type":"Point"}
}