{
  "type": "Feature",
  "properties": {
    "gn:admin1_code":"30",
    "gn:asciiname":"Kiara",
    "gn:country_code":"ID",
    "gn:dem":691,
    "gn:feature_class":"P",
    "gn:feature_code":"PPL",
    "gn:name":"Kiara",
    "gn:population":0,
    "gn:timezone":"Asia/Jakarta",
    "iso:country":"ID",
    "name:ceb_x_preferred":[
        "Kiara"
    ],
    "name:ces_x_preferred":[
        "Kiara"
    ],
    "name:ind_x_preferred":[
        "Kiara"
    ],
    "name:nld_x_preferred":[
        "Kiara"
    ],
    "name:por_x_preferred":[
        "Kiara"
    ],
    "name:spa_x_preferred":[
        "Kiara"
    ],
    "name:swe_x_preferred":[
        "Kiara"
    ],
    "wof:name":"Kiara",
    "wof:placetype":"locality"
},
  "geometry": {"coordinates":[107.54944,-6.92917],"type":"Point"}
}