{
  "type": "Feature",
  "properties": {
    "gn:admin1_code":"34.0",
    "gn:asciiname":"Rumbia",
    "gn:country_code":"ID",
    "gn:dem":33,
    "gn:feature_class":"P",
    "gn:feature_code":"PPL",
    "gn:name":"Rumbia",
    "gn:population":0,
    "gn:timezone":"Asia/Makassar",
    "iso:country":"ID",
    "name:ind_x_preferred":[
        "Rumbia"
    ],
    "wof:name":"Rumbia",
    "wof:placetype":"locality"
},
  "geometry": {"coordinates":[123.07340000000001,0.6003],"type":"Point"}
}