{
  "type": "Feature",
  "properties": {
    "gn:admin1_code":"22.0",
    "gn:asciiname":"Lalowaru",
    "gn:country_code":"ID",
    "gn:dem":7,
    "gn:feature_class":"P",
    "gn:feature_code":"PPL",
    "gn:name":"Lalowaru",
    "gn:population":0,
    "gn:timezone":"Asia/Makassar",
    "iso:country":"ID",
    "name:ind_x_preferred":[
        "Lalowaru"
    ],
    "wof:name":"Lalowaru",
    "wof:placetype":"locality"
},
  "geometry": {"coordinates":[122.2341,-3.6636],"type":"Point"}
}