{
  "type": "Feature",
  "properties": {
    "gn:country":"ID",
    "gn:fcode":"PPL",
    "gn:pop":0,
    "iso:country":"ID",
    "name:ban_x_preferred":[
        "Purwantoro"
    ],
    "name:deu_x_preferred":[
        "Purwantoro"
    ],
    "name:eng_x_preferred":[
        "Purwantoro"
    ],
    "name:fra_x_preferred":[
        "Purwantoro"
    ],
    "name:ind_x_preferred":[
        "Purwantoro"
    ],
    "name:jav_x_preferred":[
        "Purwantara"
    ],
    "name:nan_x_preferred":[
        "Purwantoro"
    ],
    "name:nld_x_preferred":[
        "Purwantoro"
    ],
    "name:unk_x_variant":[
        "Purwantara"
    ],
    "qs:name":"Purwantoro",
    "qs:name_adm0":"Indonesia",
    "qs:name_adm1":"Provinsi Jawa Tengah",
    "qs:photos_9k":1,
    "qs:photos_9r":1,
    "qs:photos_all":1,
    "qs:photos_sr":0,
    "qs:placetype":"Town",
    "qs:pop_sr":"4",
    "wd:wordcount":32,
    "wof:lang_x_official":[
        "ind"
    ],
    "wof:lang_x_spoken":[
        "ind",
        "eng"
    ],
    "wof:name":"Purwantoro",
    "wof:placetype":"locality",
    "wof:population":0
},
  "geometry": {"coordinates":[111.25972,-7.8475],"type":"Point"}
}