{
  "type": "Feature",
  "properties": {
    "gn:admin1_code":"26",
    "gn:asciiname":"Damakurat Bewah",
    "gn:country_code":"ID",
    "gn:dem":109,
    "gn:feature_class":"P",
    "gn:feature_code":"PPL",
    "gn:name":"Damakurat Bewah",
    "gn:population":0,
    "gn:timezone":"Asia/Jakarta",
    "iso:country":"ID",
    "name:ind_x_preferred":[
        "Damakurat Bewah"
    ],
    "name:und_x_variant":[
        "Damakurat"
    ],
    "wof:lang_x_official":[
        "ind"
    ],
    "wof:lang_x_spoken":[
        "ind",
        "eng"
    ],
    "wof:name":"Damakurat Bewah",
    "wof:placetype":"locality"
},
  "geometry": {"coordinates":[98.9838,3.2187],"type":"Point"}
}