{
  "type": "Feature",
  "properties": {
    "gn:admin1_code":"32.0",
    "gn:asciiname":"Talang Sungaibuluh",
    "gn:country_code":"ID",
    "gn:dem":21,
    "gn:feature_class":"P",
    "gn:feature_code":"PPL",
    "gn:name":"Talang Sungaibuluh",
    "gn:population":0,
    "gn:timezone":"Asia/Jakarta",
    "iso:country":"ID",
    "name:ind_x_preferred":[
        "Talang Sungaibuluh"
    ],
    "wof:name":"Talang Sungaibuluh",
    "wof:placetype":"locality"
},
  "geometry": {"coordinates":[105.59372,-3.80071],"type":"Point"}
}