{
  "type": "Feature",
  "properties": {
    "gn:admin1_code":"7",
    "gn:asciiname":"Dayu",
    "gn:country_code":"ID",
    "gn:dem":489,
    "gn:feature_class":"P",
    "gn:feature_code":"PPL",
    "gn:name":"Dayu",
    "gn:population":0,
    "gn:timezone":"Asia/Jakarta",
    "iso:country":"ID",
    "name:ind_x_preferred":[
        "Dayu"
    ],
    "wof:name":"Dayu",
    "wof:placetype":"locality"
},
  "geometry": {"coordinates":[111.145,-7.52639],"type":"Point"}
}