{
  "type": "Feature",
  "properties": {
    "gn:admin1_code":"38",
    "gn:asciiname":"Belalang",
    "gn:country_code":"ID",
    "gn:dem":820,
    "gn:feature_class":"P",
    "gn:feature_code":"PPL",
    "gn:name":"Belalang",
    "gn:population":0,
    "gn:timezone":"Asia/Makassar",
    "iso:country":"ID",
    "name:ind_x_preferred":[
        "Belalang"
    ],
    "wof:name":"Belalang",
    "wof:placetype":"locality"
},
  "geometry": {"coordinates":[119.9121,-3.4432],"type":"Point"}
}