{
  "type": "Feature",
  "properties": {
    "gn:admin1_code":"30",
    "gn:asciiname":"Cimayang Karim",
    "gn:country_code":"ID",
    "gn:dem":335,
    "gn:feature_class":"P",
    "gn:feature_code":"PPL",
    "gn:name":"Cimayang Karim",
    "gn:population":0,
    "gn:timezone":"Asia/Jakarta",
    "iso:country":"ID",
    "name:ind_x_preferred":[
        "Cimayang Karim"
    ],
    "wof:name":"Cimayang Karim",
    "wof:placetype":"locality"
},
  "geometry": {"coordinates":[106.66889,-6.61556],"type":"Point"}
}