{
  "type": "Feature",
  "properties": {
    "gn:admin1_code":"7.0",
    "gn:asciiname":"Ningalan",
    "gn:country_code":"ID",
    "gn:dem":64,
    "gn:feature_class":"P",
    "gn:feature_code":"PPL",
    "gn:name":"Ningalan",
    "gn:population":0,
    "gn:timezone":"Asia/Jakarta",
    "iso:country":"ID",
    "name:ind_x_preferred":[
        "Ningalan"
    ],
    "wof:name":"Ningalan",
    "wof:placetype":"locality"
},
  "geometry": {"coordinates":[111.48690000000001,-7.1356],"type":"Point"}
}