{
  "type": "Feature",
  "properties": {
    "gn:admin1_code":"30.0",
    "gn:asciiname":"Tegal",
    "gn:country_code":"ID",
    "gn:dem":41,
    "gn:feature_class":"P",
    "gn:feature_code":"PPL",
    "gn:name":"Tegal",
    "gn:population":0,
    "gn:timezone":"Asia/Jakarta",
    "iso:country":"ID",
    "name:ceb_x_preferred":[
        "Tegal"
    ],
    "name:ind_x_preferred":[
        "Tegal"
    ],
    "name:jav_x_preferred":[
        "Tegal"
    ],
    "name:nld_x_preferred":[
        "Tegal"
    ],
    "name:sun_x_preferred":[
        "Tegal"
    ],
    "name:swe_x_preferred":[
        "Tegal"
    ],
    "wof:lang_x_official":[
        "ind"
    ],
    "wof:lang_x_spoken":[
        "ind",
        "eng"
    ],
    "wof:name":"Tegal",
    "wof:placetype":"locality"
},
  "geometry": {"coordinates":[106.64333000000001,-6.295],"type":"Point"}
}