{
  "type": "Feature",
  "properties": {
    "gn:admin1_code":"28.0",
    "gn:asciiname":"Akoon",
    "gn:country_code":"ID",
    "gn:dem":20,
    "gn:feature_class":"P",
    "gn:feature_code":"PPL",
    "gn:name":"Akoon",
    "gn:population":0,
    "gn:timezone":"Asia/Jayapura",
    "iso:country":"ID",
    "name:ind_x_preferred":[
        "Akoon"
    ],
    "wof:name":"Akoon",
    "wof:placetype":"locality"
},
  "geometry": {"coordinates":[128.80993999999998,-3.67363],"type":"Point"}
}