{
  "type": "Feature",
  "properties": {
    "gn:admin1_code":"30.0",
    "gn:asciiname":"Cigalugur",
    "gn:country_code":"ID",
    "gn:dem":908,
    "gn:feature_class":"P",
    "gn:feature_code":"PPL",
    "gn:name":"Cigalugur",
    "gn:population":0,
    "gn:timezone":"Asia/Jakarta",
    "iso:country":"ID",
    "name:ind_x_preferred":[
        "Cigalugur"
    ],
    "name:und_x_variant":[
        "Tjigaloegoer"
    ],
    "wof:name":"Cigalugur",
    "wof:placetype":"locality"
},
  "geometry": {"coordinates":[107.9418,-7.3756],"type":"Point"}
}