{
  "type": "Feature",
  "properties": {
    "gn:admin1_code":"30",
    "gn:asciiname":"Gumuruh",
    "gn:cc2":"ID",
    "gn:country_code":"ID",
    "gn:dem":709,
    "gn:feature_class":"P",
    "gn:feature_code":"PPL",
    "gn:name":"Gumuruh",
    "gn:population":0,
    "gn:timezone":"Asia/Jakarta",
    "iso:country":"ID",
    "name:und_x_variant":[
        "Gumurun",
        "Gumuruh"
    ],
    "wof:name":"Gumuruh",
    "wof:placetype":"locality"
},
  "geometry": {"coordinates":[107.55472,-7.05667],"type":"Point"}
}