{
  "type": "Feature",
  "properties": {
    "gn:admin1_code":"30.0",
    "gn:asciiname":"Ciroyom Dua",
    "gn:country_code":"ID",
    "gn:dem":721,
    "gn:feature_class":"P",
    "gn:feature_code":"PPL",
    "gn:name":"Ciroyom Dua",
    "gn:population":0,
    "gn:timezone":"Asia/Jakarta",
    "iso:country":"ID",
    "name:ind_x_preferred":[
        "Ciroyom Dua"
    ],
    "name:und_x_variant":[
        "Tjirojom 2"
    ],
    "wof:name":"Ciroyom Dua",
    "wof:placetype":"locality"
},
  "geometry": {"coordinates":[107.05289999999999,-7.1694],"type":"Point"}
}