{
  "type": "Feature",
  "properties": {
    "gn:admin1_code":"33",
    "gn:asciiname":"Jurang",
    "gn:country_code":"ID",
    "gn:dem":351,
    "gn:feature_class":"P",
    "gn:feature_code":"PPL",
    "gn:name":"Jurang",
    "gn:population":0,
    "gn:timezone":"Asia/Jakarta",
    "iso:country":"ID",
    "name:ind_x_preferred":[
        "Jurang"
    ],
    "wof:name":"Jurang",
    "wof:placetype":"locality"
},
  "geometry": {"coordinates":[106.0389,-5.9443],"type":"Point"}
}