{
  "type": "Feature",
  "properties": {
    "gn:admin1_code":"26",
    "gn:asciiname":"Desa Pancaarga",
    "gn:country_code":"ID",
    "gn:dem":4,
    "gn:feature_class":"P",
    "gn:feature_code":"PPL",
    "gn:name":"Desa Pancaarga",
    "gn:population":0,
    "gn:timezone":"Asia/Jakarta",
    "iso:country":"ID",
    "name:ind_x_preferred":[
        "Desa Pancaarga"
    ],
    "wof:name":"Desa Pancaarga",
    "wof:placetype":"locality"
},
  "geometry": {"coordinates":[99.65560000000001,3.1132],"type":"Point"}
}