{
  "type": "Feature",
  "properties": {
    "gn:admin1_code":"18.0",
    "gn:asciiname":"Pudiputejo",
    "gn:country_code":"ID",
    "gn:dem":220,
    "gn:feature_class":"P",
    "gn:feature_code":"PPL",
    "gn:name":"Pudiputejo",
    "gn:population":0,
    "gn:timezone":"Asia/Makassar",
    "iso:country":"ID",
    "name:ind_x_preferred":[
        "Pudiputejo"
    ],
    "wof:name":"Pudiputejo",
    "wof:placetype":"locality"
},
  "geometry": {"coordinates":[121.87130000000001,-10.5348],"type":"Point"}
}