{
  "type": "Feature",
  "properties": {
    "gn:country":"ID",
    "gn:fcode":"PPL",
    "gn:pop":0,
    "iso:country":"ID",
    "name:ind_x_preferred":[
        "Lowokwaru"
    ],
    "name:unk_x_variant":[
        "Lowokwaroe"
    ],
    "qs:name":"Lowokwaru",
    "qs:name_adm0":"Indonesia",
    "qs:name_adm1":"Jawa Timur",
    "qs:photos_9k":1,
    "qs:photos_9r":1,
    "qs:photos_all":2,
    "qs:photos_sr":0,
    "qs:placetype":"Town",
    "qs:pop_sr":"0",
    "wd:wordcount":1363,
    "wof:lang_x_official":[
        "ind"
    ],
    "wof:lang_x_spoken":[
        "ind",
        "eng"
    ],
    "wof:name":"Lowokwaru",
    "wof:placetype":"locality",
    "wof:population":0
},
  "geometry": {"coordinates":[112.63420000000001,-7.9595],"type":"Point"}
}