{
  "type": "Feature",
  "properties": {
    "gn:admin1_code":"24",
    "gn:asciiname":"Lakutujuh",
    "gn:country_code":"ID",
    "gn:dem":212,
    "gn:feature_class":"P",
    "gn:feature_code":"PPL",
    "gn:name":"Lakutujuh",
    "gn:population":0,
    "gn:timezone":"Asia/Jakarta",
    "iso:country":"ID",
    "name:ind_x_preferred":[
        "Lakutujuh"
    ],
    "wof:name":"Lakutujuh",
    "wof:placetype":"locality"
},
  "geometry": {"coordinates":[100.88905,-0.63467],"type":"Point"}
}