{
  "type": "Feature",
  "properties": {
    "gn:admin1_code":"07",
    "gn:asciiname":"Kalileuseung",
    "gn:country_code":"ID",
    "gn:dem":896,
    "gn:feature_class":"P",
    "gn:feature_code":"PPL",
    "gn:name":"Kalileuseung",
    "gn:population":0,
    "gn:timezone":"Asia/Jakarta",
    "iso:country":"ID",
    "name:ind_x_preferred":[
        "Kalileuseung"
    ],
    "name:und_x_variant":[
        "Kalilingseng"
    ],
    "wof:name":"Kalileuseung",
    "wof:placetype":"locality"
},
  "geometry": {"coordinates":[110.30972,-7.20417],"type":"Point"}
}