{
  "type": "Feature",
  "properties": {
    "gn:admin1_code":"18.0",
    "gn:asciiname":"Degit",
    "gn:country_code":"ID",
    "gn:dem":17,
    "gn:feature_class":"P",
    "gn:feature_code":"PPL",
    "gn:name":"Degit",
    "gn:population":0,
    "gn:timezone":"Asia/Makassar",
    "iso:country":"ID",
    "name:ind_x_preferred":[
        "Degit"
    ],
    "wof:name":"Degit",
    "wof:placetype":"locality"
},
  "geometry": {"coordinates":[122.12390000000001,-8.7264],"type":"Point"}
}