{
  "type": "Feature",
  "properties": {
    "gn:admin1_code":"8",
    "gn:asciiname":"Wonotengah",
    "gn:country_code":"ID",
    "gn:dem":51,
    "gn:feature_class":"P",
    "gn:feature_code":"PPL",
    "gn:name":"Wonotengah",
    "gn:population":0,
    "gn:timezone":"Asia/Jakarta",
    "iso:country":"ID",
    "name:ind_x_preferred":[
        "Wonotengah"
    ],
    "wof:name":"Wonotengah",
    "wof:placetype":"locality"
},
  "geometry": {"coordinates":[112.113,-7.6596],"type":"Point"}
}