{
  "type": "Feature",
  "properties": {
    "gn:admin1_code":"7.0",
    "gn:asciiname":"Maluan",
    "gn:country_code":"ID",
    "gn:dem":223,
    "gn:feature_class":"P",
    "gn:feature_code":"PPL",
    "gn:name":"Maluan",
    "gn:population":0,
    "gn:timezone":"Asia/Jakarta",
    "iso:country":"ID",
    "wof:name":"Maluan",
    "wof:placetype":"locality"
},
  "geometry": {"coordinates":[110.66139,-7.5425],"type":"Point"}
}