{
  "type": "Feature",
  "properties": {
    "gn:admin1_code":"30.0",
    "gn:asciiname":"Balakasap Kaler",
    "gn:country_code":"ID",
    "gn:dem":675,
    "gn:feature_class":"P",
    "gn:feature_code":"PPL",
    "gn:name":"Balakasap Kaler",
    "gn:population":0,
    "gn:timezone":"Asia/Jakarta",
    "iso:country":"ID",
    "name:ind_x_preferred":[
        "Balakasap Kaler"
    ],
    "name:und_x_variant":[
        "Balakasap"
    ],
    "wof:name":"Balakasap Kaler",
    "wof:placetype":"locality"
},
  "geometry": {"coordinates":[107.51389,-6.93889],"type":"Point"}
}