{
  "type": "Feature",
  "properties": {
    "gn:admin1_code":"7.0",
    "gn:asciiname":"Banyusari",
    "gn:country_code":"ID",
    "gn:dem":511,
    "gn:feature_class":"P",
    "gn:feature_code":"PPL",
    "gn:name":"Banyusari",
    "gn:population":0,
    "gn:timezone":"Asia/Jakarta",
    "iso:country":"ID",
    "wof:name":"Banyusari",
    "wof:placetype":"locality"
},
  "geometry": {"coordinates":[110.27916999999999,-7.45056],"type":"Point"}
}