{
  "type": "Feature",
  "properties": {
    "gn:admin1_code":"38",
    "gn:asciiname":"Ceppaga",
    "gn:country_code":"ID",
    "gn:dem":300,
    "gn:feature_class":"P",
    "gn:feature_code":"PPL",
    "gn:name":"Ceppaga",
    "gn:population":0,
    "gn:timezone":"Asia/Makassar",
    "iso:country":"ID",
    "name:ind_x_preferred":[
        "Ceppaga"
    ],
    "wof:name":"Ceppaga",
    "wof:placetype":"locality"
},
  "geometry": {"coordinates":[120.0675,-5.0927],"type":"Point"}
}