{
  "type": "Feature",
  "properties": {
    "gn:admin1_code":"08",
    "gn:asciiname":"Mindi",
    "gn:country_code":"ID",
    "gn:dem":569,
    "gn:feature_class":"P",
    "gn:feature_code":"PPL",
    "gn:name":"Mindi",
    "gn:population":0,
    "gn:timezone":"Asia/Jakarta",
    "iso:country":"ID",
    "name:ind_x_preferred":[
        "Mindi"
    ],
    "name:und_x_variant":[
        "Petungmindi"
    ],
    "wof:name":"Mindi",
    "wof:placetype":"locality"
},
  "geometry": {"coordinates":[112.75060000000001,-7.9281],"type":"Point"}
}