{
  "type": "Feature",
  "properties": {
    "gn:admin1_code":"17",
    "gn:asciiname":"Manggecolu",
    "gn:country_code":"ID",
    "gn:dem":7,
    "gn:feature_class":"P",
    "gn:feature_code":"PPL",
    "gn:name":"Manggecolu",
    "gn:population":0,
    "gn:timezone":"Asia/Makassar",
    "iso:country":"ID",
    "name:ind_x_preferred":[
        "Manggecolu"
    ],
    "wof:name":"Manggecolu",
    "wof:placetype":"locality"
},
  "geometry": {"coordinates":[118.69305,-8.55646],"type":"Point"}
}