{
  "type": "Feature",
  "properties": {
    "gn:admin1_code":"8.0",
    "gn:asciiname":"Kalimenur",
    "gn:country_code":"ID",
    "gn:dem":242,
    "gn:feature_class":"P",
    "gn:feature_code":"PPL",
    "gn:name":"Kalimenur",
    "gn:population":0,
    "gn:timezone":"Asia/Jakarta",
    "iso:country":"ID",
    "name:ind_x_preferred":[
        "Kalimenur"
    ],
    "wof:name":"Kalimenur",
    "wof:placetype":"locality"
},
  "geometry": {"coordinates":[111.9576,-8.2462],"type":"Point"}
}