{
  "type": "Feature",
  "properties": {
    "gn:admin1_code":"17",
    "gn:asciiname":"Sebasangsektor",
    "gn:country_code":"ID",
    "gn:dem":77,
    "gn:feature_class":"P",
    "gn:feature_code":"PPL",
    "gn:name":"Sebasangsektor",
    "gn:population":0,
    "gn:timezone":"Asia/Makassar",
    "iso:country":"ID",
    "name:ind_x_preferred":[
        "Sebasangsektor"
    ],
    "wof:name":"Sebasangsektor",
    "wof:placetype":"locality"
},
  "geometry": {"coordinates":[117.4455,-8.637],"type":"Point"}
}