{
  "type": "Feature",
  "properties": {
    "gn:admin1_code":"26.0",
    "gn:asciiname":"Paropo",
    "gn:country_code":"ID",
    "gn:dem":918,
    "gn:feature_class":"P",
    "gn:feature_code":"PPL",
    "gn:name":"Paropo",
    "gn:population":0,
    "gn:timezone":"Asia/Jakarta",
    "iso:country":"ID",
    "name:ind_x_preferred":[
        "Paropo"
    ],
    "wof:name":"Paropo",
    "wof:placetype":"locality"
},
  "geometry": {"coordinates":[98.5211,2.8663],"type":"Point"}
}