{
  "type": "Feature",
  "properties": {
    "gn:admin1_code":"8",
    "gn:asciiname":"Damar Kulon",
    "gn:country_code":"ID",
    "gn:dem":441,
    "gn:feature_class":"P",
    "gn:feature_code":"PPL",
    "gn:name":"Damar Kulon",
    "gn:population":0,
    "gn:timezone":"Asia/Jakarta",
    "iso:country":"ID",
    "name:ind_x_preferred":[
        "Damar Kulon"
    ],
    "wof:name":"Damar Kulon",
    "wof:placetype":"locality"
},
  "geometry": {"coordinates":[112.70910000000001,-7.7728],"type":"Point"}
}