{
  "type": "Feature",
  "properties": {
    "gn:admin1_code":"36.0",
    "gn:asciiname":"Maniwuri",
    "gn:country_code":"ID",
    "gn:dem":20,
    "gn:feature_class":"P",
    "gn:feature_code":"PPL",
    "gn:name":"Maniwuri",
    "gn:population":0,
    "gn:timezone":"Asia/Jayapura",
    "iso:country":"ID",
    "name:ind_x_preferred":[
        "Maniwuri"
    ],
    "name:und_x_variant":[
        "Maniwori"
    ],
    "wof:name":"Maniwuri",
    "wof:placetype":"locality"
},
  "geometry": {"coordinates":[135.91540000000001,-2.8834],"type":"Point"}
}