{
  "type": "Feature",
  "properties": {
    "gn:country":"ID",
    "gn:fcode":"PPL",
    "gn:pop":0,
    "iso:country":"ID",
    "name:ind_x_preferred":[
        "Jatiluhur"
    ],
    "name:unk_x_variant":[
        "Djatiluhur"
    ],
    "qs:name":"Jati Luhur",
    "qs:name_adm0":"Indonesia",
    "qs:name_adm1":"Jawa Barat",
    "qs:photos_9r":0,
    "qs:photos_sr":0,
    "qs:placetype":"Town",
    "qs:pop_sr":"0",
    "wof:lang_x_official":[
        "ind"
    ],
    "wof:lang_x_spoken":[
        "ind",
        "eng"
    ],
    "wof:name":"Jati Luhur",
    "wof:placetype":"locality",
    "wof:population":0
},
  "geometry": {"coordinates":[107.4175,-6.53028],"type":"Point"}
}