{
  "type": "Feature",
  "properties": {
    "gn:admin1_code":"30",
    "gn:asciiname":"Cisaar",
    "gn:country_code":"ID",
    "gn:dem":238,
    "gn:feature_class":"P",
    "gn:feature_code":"PPL",
    "gn:name":"Cisaar",
    "gn:population":0,
    "gn:timezone":"Asia/Jakarta",
    "iso:country":"ID",
    "name:ind_x_preferred":[
        "Cisaar"
    ],
    "wof:name":"Cisaar",
    "wof:placetype":"locality"
},
  "geometry": {"coordinates":[107.32639,-6.77167],"type":"Point"}
}