{
  "type": "Feature",
  "properties": {
    "gn:admin1_code":"1",
    "gn:asciiname":"Blang Bidok",
    "gn:country_code":"ID",
    "gn:dem":18,
    "gn:feature_class":"P",
    "gn:feature_code":"PPL",
    "gn:name":"Blang Bidok",
    "gn:population":0,
    "gn:timezone":"Asia/Jakarta",
    "iso:country":"ID",
    "name:ind_x_preferred":[
        "Blang Bidok"
    ],
    "wof:name":"Blang Bidok",
    "wof:placetype":"locality"
},
  "geometry": {"coordinates":[97.2724,5.0492],"type":"Point"}
}