{
  "type": "Feature",
  "properties": {
    "gn:admin1_code":"38",
    "gn:asciiname":"Kambalu",
    "gn:country_code":"ID",
    "gn:dem":64,
    "gn:feature_class":"P",
    "gn:feature_code":"PPL",
    "gn:name":"Kambalu",
    "gn:population":0,
    "gn:timezone":"Asia/Makassar",
    "iso:country":"ID",
    "name:ind_x_preferred":[
        "Kambalu"
    ],
    "wof:name":"Kambalu",
    "wof:placetype":"locality"
},
  "geometry": {"coordinates":[120.2897,-3.4534],"type":"Point"}
}