{
  "type": "Feature",
  "properties": {
    "gn:admin1_code":"29.0",
    "gn:asciiname":"Tolong",
    "gn:country_code":"ID",
    "gn:dem":10,
    "gn:feature_class":"P",
    "gn:feature_code":"PPL",
    "gn:name":"Tolong",
    "gn:population":0,
    "gn:timezone":"Asia/Jayapura",
    "iso:country":"ID",
    "name:ind_x_preferred":[
        "Tolong"
    ],
    "name:und_x_variant":[
        "Totong",
        "Tolong"
    ],
    "wof:name":"Tolong",
    "wof:placetype":"locality"
},
  "geometry": {"coordinates":[124.44868999999998,-1.66479],"type":"Point"}
}