{
  "type": "Feature",
  "properties": {
    "gn:admin1_code":"31.0",
    "gn:asciiname":"Lolayan",
    "gn:country_code":"ID",
    "gn:dem":216,
    "gn:feature_class":"P",
    "gn:feature_code":"PPLA3",
    "gn:name":"Lolayan",
    "gn:population":0,
    "gn:timezone":"Asia/Makassar",
    "iso:country":"ID",
    "name:ind_x_preferred":[
        "Lolayan"
    ],
    "wof:name":"Lolayan",
    "wof:placetype":"locality"
},
  "geometry": {"coordinates":[124.3074,0.646],"type":"Point"}
}