{
  "type": "Feature",
  "properties": {
    "gn:admin1_code":"0.0",
    "gn:asciiname":"Ambat",
    "gn:country_code":"ID",
    "gn:dem":-9999,
    "gn:feature_class":"P",
    "gn:feature_code":"PPL",
    "gn:name":"Ambat",
    "gn:population":0,
    "gn:timezone":"Asia/Makassar",
    "iso:country":"ID",
    "name:rus_x_preferred":[
        "\u0410\u043c\u0431\u0430\u0442"
    ],
    "wof:name":"Ambat",
    "wof:placetype":"locality"
},
  "geometry": {"coordinates":[115.65000000000001,-8.33333],"type":"Point"}
}