{
  "type": "Feature",
  "properties": {
    "gn:admin1_code":"8",
    "gn:asciiname":"Sirnoboyo",
    "gn:country_code":"ID",
    "gn:dem":15,
    "gn:feature_class":"P",
    "gn:feature_code":"PPL",
    "gn:name":"Sirnoboyo",
    "gn:population":0,
    "gn:timezone":"Asia/Jakarta",
    "iso:country":"ID",
    "name:ind_x_preferred":[
        "Sirnoboyo"
    ],
    "wof:name":"Sirnoboyo",
    "wof:placetype":"locality"
},
  "geometry": {"coordinates":[112.48650000000001,-7.2527],"type":"Point"}
}