{
  "type": "Feature",
  "properties": {
    "gn:admin1_code":"07",
    "gn:asciiname":"Sumber",
    "gn:country_code":"ID",
    "gn:dem":126,
    "gn:feature_class":"P",
    "gn:feature_code":"PPL",
    "gn:name":"Sumber",
    "gn:population":0,
    "gn:timezone":"Asia/Jakarta",
    "iso:country":"ID",
    "name:fas_x_preferred":[
        "\u0633\u0648\u0645\u0628\u0631"
    ],
    "name:ind_x_preferred":[
        "Sumber"
    ],
    "name:jav_x_preferred":[
        "Sumber"
    ],
    "name:mlg_x_preferred":[
        "Sumber"
    ],
    "name:sun_x_preferred":[
        "Sumber"
    ],
    "wof:lang_x_official":[
        "ind"
    ],
    "wof:lang_x_spoken":[
        "ind",
        "eng"
    ],
    "wof:name":"Sumber",
    "wof:placetype":"locality"
},
  "geometry": {"coordinates":[110.51528,-7.10417],"type":"Point"}
}