{
  "type": "Feature",
  "properties": {
    "gn:country":"ID",
    "gn:fcode":"ADM3",
    "gn:pop":0,
    "iso:country":"ID",
    "name:ind_x_preferred":[
        "Kecamatan Purwodadi"
    ],
    "name:unk_x_variant":[
        "Purwodadi"
    ],
    "qs:name":"Kecamatan Purwodadi",
    "qs:photos_9r":0,
    "qs:photos_sr":0,
    "qs:pop_sr":"0",
    "wd:wordcount":137,
    "wof:name":"Kecamatan Purwodadi",
    "wof:placetype":"localadmin",
    "wof:population":0
},
  "geometry": {"coordinates":[109.98917,-7.81972],"type":"Point"}
}