{
  "type": "Feature",
  "properties": {
    "gn:admin1_code":"18.0",
    "gn:asciiname":"Kolongbaru",
    "gn:country_code":"ID",
    "gn:dem":522,
    "gn:feature_class":"P",
    "gn:feature_code":"PPL",
    "gn:name":"Kolongbaru",
    "gn:population":0,
    "gn:timezone":"Asia/Makassar",
    "iso:country":"ID",
    "name:ind_x_preferred":[
        "Kolongbaru"
    ],
    "wof:name":"Kolongbaru",
    "wof:placetype":"locality"
},
  "geometry": {"coordinates":[120.24630000000001,-8.669],"type":"Point"}
}