{
  "type": "Feature",
  "properties": {
    "gn:admin1_code":"41",
    "gn:asciiname":"Tandialo",
    "gn:country_code":"ID",
    "gn:dem":969,
    "gn:feature_class":"P",
    "gn:feature_code":"PPL",
    "gn:name":"Tandialo",
    "gn:population":0,
    "gn:timezone":"Asia/Makassar",
    "iso:country":"ID",
    "name:ind_x_preferred":[
        "Tandialo"
    ],
    "wof:lang_x_official":[
        "ind"
    ],
    "wof:lang_x_spoken":[
        "ind",
        "eng"
    ],
    "wof:name":"Tandialo",
    "wof:placetype":"locality"
},
  "geometry": {"coordinates":[119.2801,-3.1173],"type":"Point"}
}