{
  "type": "Feature",
  "properties": {
    "gn:admin1_code":"2",
    "gn:asciiname":"Anyar",
    "gn:country_code":"ID",
    "gn:dem":201,
    "gn:feature_class":"P",
    "gn:feature_code":"PPL",
    "gn:name":"Anyar",
    "gn:population":0,
    "gn:timezone":"Asia/Makassar",
    "iso:country":"ID",
    "name:ind_x_preferred":[
        "Anyar"
    ],
    "wof:name":"Anyar",
    "wof:placetype":"locality"
},
  "geometry": {"coordinates":[114.9224,-8.2279],"type":"Point"}
}