{
  "type": "Feature",
  "properties": {
    "gn:admin1_code":"30.0",
    "gn:asciiname":"Cijalu",
    "gn:country_code":"ID",
    "gn:dem":454,
    "gn:feature_class":"P",
    "gn:feature_code":"PPL",
    "gn:name":"Cijalu",
    "gn:population":0,
    "gn:timezone":"Asia/Jakarta",
    "iso:country":"ID",
    "name:ind_x_preferred":[
        "Cijalu"
    ],
    "name:und_x_variant":[
        "Tjijaloe"
    ],
    "wof:name":"Cijalu",
    "wof:placetype":"locality"
},
  "geometry": {"coordinates":[108.3737,-7.5437],"type":"Point"}
}