{
  "type": "Feature",
  "properties": {
    "gn:admin1_code":"30",
    "gn:asciiname":"Babakankertajaya",
    "gn:country_code":"ID",
    "gn:dem":667,
    "gn:feature_class":"P",
    "gn:feature_code":"PPL",
    "gn:name":"Babakankertajaya",
    "gn:population":0,
    "gn:timezone":"Asia/Jakarta",
    "iso:country":"ID",
    "name:ind_x_preferred":[
        "Babakankertajaya"
    ],
    "wof:name":"Babakankertajaya",
    "wof:placetype":"locality"
},
  "geometry": {"coordinates":[107.48972000000001,-6.85444],"type":"Point"}
}