{
  "type": "Feature",
  "properties": {
    "gn:admin1_code":"7.0",
    "gn:asciiname":"Watusudah",
    "gn:country_code":"ID",
    "gn:dem":50,
    "gn:feature_class":"P",
    "gn:feature_code":"PPL",
    "gn:name":"Watusudah",
    "gn:population":0,
    "gn:timezone":"Asia/Jakarta",
    "iso:country":"ID",
    "name:ind_x_preferred":[
        "Watusudah"
    ],
    "wof:name":"Watusudah",
    "wof:placetype":"locality"
},
  "geometry": {"coordinates":[109.48333,-7.57722],"type":"Point"}
}