{
  "type": "Feature",
  "properties": {
    "gn:admin1_code":"17",
    "gn:asciiname":"Dasankuburjaran",
    "gn:country_code":"ID",
    "gn:dem":189,
    "gn:feature_class":"P",
    "gn:feature_code":"PPL",
    "gn:name":"Dasankuburjaran",
    "gn:population":0,
    "gn:timezone":"Asia/Makassar",
    "iso:country":"ID",
    "name:ind_x_preferred":[
        "Dasankuburjaran"
    ],
    "wof:name":"Dasankuburjaran",
    "wof:placetype":"locality"
},
  "geometry": {"coordinates":[116.2394,-8.6218],"type":"Point"}
}