{
  "type": "Feature",
  "properties": {
    "gn:admin1_code":"18.0",
    "gn:asciiname":"Sombai",
    "gn:country_code":"ID",
    "gn:dem":526,
    "gn:feature_class":"P",
    "gn:feature_code":"PPL",
    "gn:name":"Sombai",
    "gn:population":0,
    "gn:timezone":"Asia/Makassar",
    "iso:country":"ID",
    "name:fra_x_preferred":[
        "Sombai"
    ],
    "name:ind_x_preferred":[
        "Sombai"
    ],
    "name:khm_x_preferred":[
        "\u179f\u17c6\u17bb\u1794\u17c3"
    ],
    "wof:lang_x_official":[
        "ind"
    ],
    "wof:lang_x_spoken":[
        "ind",
        "eng"
    ],
    "wof:name":"Sombai",
    "wof:placetype":"locality"
},
  "geometry": {"coordinates":[124.6313,-9.8422],"type":"Point"}
}