{
  "type": "Feature",
  "properties": {
    "gn:admin1_code":"21",
    "gn:asciiname":"Bayu",
    "gn:country_code":"ID",
    "gn:dem":8,
    "gn:feature_class":"P",
    "gn:feature_code":"PPL",
    "gn:name":"Bayu",
    "gn:population":0,
    "gn:timezone":"Asia/Makassar",
    "iso:country":"ID",
    "name:ind_x_preferred":[
        "Bayu"
    ],
    "wof:name":"Bayu",
    "wof:placetype":"locality"
},
  "geometry": {"coordinates":[122.9837,-0.8996],"type":"Point"}
}