{
  "type": "Feature",
  "properties": {
    "gn:admin1_code":"30",
    "gn:asciiname":"Pakuwon",
    "gn:country_code":"ID",
    "gn:dem":17,
    "gn:feature_class":"P",
    "gn:feature_code":"PPL",
    "gn:name":"Pakuwon",
    "gn:population":0,
    "gn:timezone":"Asia/Jakarta",
    "iso:country":"ID",
    "name:ind_x_preferred":[
        "Pakuwon"
    ],
    "wof:name":"Pakuwon",
    "wof:placetype":"locality"
},
  "geometry": {"coordinates":[108.74039999999999,-6.9151],"type":"Point"}
}