{
  "type": "Feature",
  "properties": {
    "gn:admin1_code":"17.0",
    "gn:asciiname":"Pawangkunyit",
    "gn:country_code":"ID",
    "gn:dem":210,
    "gn:feature_class":"P",
    "gn:feature_code":"PPL",
    "gn:name":"Pawangkunyit",
    "gn:population":0,
    "gn:timezone":"Asia/Makassar",
    "iso:country":"ID",
    "name:ind_x_preferred":[
        "Pawangkunyit"
    ],
    "wof:name":"Pawangkunyit",
    "wof:placetype":"locality"
},
  "geometry": {"coordinates":[116.33620000000001,-8.2616],"type":"Point"}
}