{
  "type": "Feature",
  "properties": {
    "gn:admin1_code":"26",
    "gn:asciiname":"Pondok Blok Enam Belas",
    "gn:country_code":"ID",
    "gn:dem":132,
    "gn:feature_class":"P",
    "gn:feature_code":"PPL",
    "gn:name":"Pondok Blok Enam Belas",
    "gn:population":0,
    "gn:timezone":"Asia/Jakarta",
    "iso:country":"ID",
    "name:ind_x_preferred":[
        "Pondok Blok Enam Belas"
    ],
    "name:und_x_variant":[
        "Pondok Blok 16"
    ],
    "wof:lang_x_official":[
        "ind"
    ],
    "wof:lang_x_spoken":[
        "ind",
        "eng"
    ],
    "wof:name":"Pondok Blok Enam Belas",
    "wof:placetype":"locality"
},
  "geometry": {"coordinates":[99.1447,3.1368],"type":"Point"}
}