{
  "type": "Feature",
  "properties": {
    "gn:admin1_code":"32.0",
    "gn:asciiname":"Talang Hitam",
    "gn:country_code":"ID",
    "gn:dem":268,
    "gn:feature_class":"P",
    "gn:feature_code":"PPL",
    "gn:name":"Talang Hitam",
    "gn:population":0,
    "gn:timezone":"Asia/Jakarta",
    "iso:country":"ID",
    "name:ind_x_preferred":[
        "Talang Hitam"
    ],
    "name:und_x_variant":[
        "Talanghitam"
    ],
    "wof:lang_x_official":[
        "ind"
    ],
    "wof:lang_x_spoken":[
        "ind",
        "eng"
    ],
    "wof:name":"Talang Hitam",
    "wof:placetype":"locality"
},
  "geometry": {"coordinates":[103.94707,-4.12385],"type":"Point"}
}