{
  "type": "Feature",
  "properties": {
    "gn:admin1_code":"26",
    "gn:asciiname":"Simotung",
    "gn:country_code":"ID",
    "gn:dem":952,
    "gn:feature_class":"P",
    "gn:feature_code":"PPL",
    "gn:name":"Simotung",
    "gn:population":0,
    "gn:timezone":"Asia/Jakarta",
    "iso:country":"ID",
    "name:ind_x_preferred":[
        "Simotung"
    ],
    "wof:name":"Simotung",
    "wof:placetype":"locality"
},
  "geometry": {"coordinates":[98.9693,2.0226],"type":"Point"}
}