{
  "type": "Feature",
  "properties": {
    "gn:admin1_code":"7.0",
    "gn:asciiname":"Plaosan",
    "gn:country_code":"ID",
    "gn:dem":275,
    "gn:feature_class":"P",
    "gn:feature_code":"PPL",
    "gn:name":"Plaosan",
    "gn:population":0,
    "gn:timezone":"Asia/Jakarta",
    "iso:country":"ID",
    "name:afr_x_preferred":[
        "Candi Plaosan"
    ],
    "name:ind_x_preferred":[
        "Candi Plaosan"
    ],
    "name:jav_x_preferred":[
        "Candhi Plaosan"
    ],
    "wof:lang_x_official":[
        "ind"
    ],
    "wof:lang_x_spoken":[
        "ind",
        "eng"
    ],
    "wof:name":"Plaosan",
    "wof:placetype":"locality"
},
  "geometry": {"coordinates":[110.2225,-7.55917],"type":"Point"}
}