{
  "type": "Feature",
  "properties": {
    "gn:admin1_code":"15.0",
    "gn:asciiname":"Bujungtenuk",
    "gn:country_code":"ID",
    "gn:dem":9,
    "gn:feature_class":"P",
    "gn:feature_code":"PPL",
    "gn:name":"Bujungtenuk",
    "gn:population":0,
    "gn:timezone":"Asia/Jakarta",
    "iso:country":"ID",
    "name:ind_x_preferred":[
        "Bujungtenuk"
    ],
    "name:ind_x_variant":[
        "Umbulanbujungteruk",
        "Oemboelan Boedjoengt\u0115noek"
    ],
    "wof:lang_x_official":[
        "ind"
    ],
    "wof:lang_x_spoken":[
        "ind",
        "eng"
    ],
    "wof:name":"Bujungtenuk",
    "wof:placetype":"locality"
},
  "geometry": {"coordinates":[105.23614000000001,-4.50563],"type":"Point"}
}