{
  "type": "Feature",
  "properties": {
    "gn:admin1_code":"30.0",
    "gn:asciiname":"Cilengkeng",
    "gn:country_code":"ID",
    "gn:dem":813,
    "gn:feature_class":"P",
    "gn:feature_code":"PPL",
    "gn:name":"Cilengkeng",
    "gn:population":0,
    "gn:timezone":"Asia/Jakarta",
    "iso:country":"ID",
    "name:ind_x_preferred":[
        "Cilengkeng"
    ],
    "name:und_x_variant":[
        "Tjilengkeng",
        "Cilengkeng"
    ],
    "wof:name":"Cilengkeng",
    "wof:placetype":"locality"
},
  "geometry": {"coordinates":[107.88809999999999,-7.4054],"type":"Point"}
}