{
  "type": "Feature",
  "properties": {
    "gn:admin1_code":"30",
    "gn:asciiname":"Leuweunggede",
    "gn:country_code":"ID",
    "gn:dem":712,
    "gn:feature_class":"P",
    "gn:feature_code":"PPL",
    "gn:name":"Leuweunggede",
    "gn:population":0,
    "gn:timezone":"Asia/Jakarta",
    "iso:country":"ID",
    "name:ind_x_preferred":[
        "Leuweunggede"
    ],
    "wof:name":"Leuweunggede",
    "wof:placetype":"locality"
},
  "geometry": {"coordinates":[107.55722,-6.91056],"type":"Point"}
}