{
  "type": "Feature",
  "properties": {
    "gn:admin1_code":"1",
    "gn:asciiname":"Ujong Tanoh",
    "gn:country_code":"ID",
    "gn:dem":12,
    "gn:feature_class":"P",
    "gn:feature_code":"PPL",
    "gn:name":"Ujong Tanoh",
    "gn:population":0,
    "gn:timezone":"Asia/Jakarta",
    "iso:country":"ID",
    "name:ind_x_preferred":[
        "Ujong Tanoh"
    ],
    "wof:name":"Ujong Tanoh",
    "wof:placetype":"locality"
},
  "geometry": {"coordinates":[95.9224,4.3641],"type":"Point"}
}