{
  "type": "Feature",
  "properties": {
    "gn:admin1_code":"7.0",
    "gn:asciiname":"Karangsari",
    "gn:country_code":"ID",
    "gn:dem":877,
    "gn:feature_class":"P",
    "gn:feature_code":"PPL",
    "gn:name":"Karangsari",
    "gn:population":0,
    "gn:timezone":"Asia/Jakarta",
    "iso:country":"ID",
    "wof:name":"Karangsari",
    "wof:placetype":"locality"
},
  "geometry": {"coordinates":[110.07861,-7.2775],"type":"Point"}
}