{
  "type": "Feature",
  "properties": {
    "gn:admin1_code":"7",
    "gn:asciiname":"Subak",
    "gn:country_code":"ID",
    "gn:dem":39,
    "gn:feature_class":"P",
    "gn:feature_code":"PPL",
    "gn:name":"Subak",
    "gn:population":0,
    "gn:timezone":"Asia/Jakarta",
    "iso:country":"ID",
    "name:deu_x_preferred":[
        "Subak"
    ],
    "name:hun_x_preferred":[
        "Szubak"
    ],
    "name:ind_x_preferred":[
        "Subak"
    ],
    "name:ita_x_preferred":[
        "Subak"
    ],
    "name:kor_x_preferred":[
        "\uc218\ubc15"
    ],
    "name:nld_x_preferred":[
        "Subak"
    ],
    "name:pol_x_preferred":[
        "Yusul"
    ],
    "name:vie_x_preferred":[
        "Subak"
    ],
    "wof:name":"Subak",
    "wof:placetype":"locality"
},
  "geometry": {"coordinates":[109.5835,-7.0209],"type":"Point"}
}