{
  "type": "Feature",
  "properties": {
    "gn:admin1_code":"30",
    "gn:asciiname":"Cangkuang",
    "gn:country_code":"ID",
    "gn:dem":13,
    "gn:feature_class":"P",
    "gn:feature_code":"PPL",
    "gn:name":"Cangkuang",
    "gn:population":0,
    "gn:timezone":"Asia/Jakarta",
    "iso:country":"ID",
    "name:ben_x_preferred":[
        "\u0995\u09cd\u09af\u09be\u0982\u0995\u09c1\u09af\u09bc\u09be\u0982"
    ],
    "name:deu_x_preferred":[
        "Candi Cangkuang"
    ],
    "name:ind_x_preferred":[
        "Cangkuang"
    ],
    "name:ind_x_variant":[
        "Candi Cangkuang"
    ],
    "name:jav_x_preferred":[
        "Candhi Cangkuang"
    ],
    "name:sun_x_preferred":[
        "Candi Cangkuang"
    ],
    "name:tat_x_preferred":[
        "\u0427\u0430\u043d\u0433\u043a\u0443\u0430\u043d\u0433"
    ],
    "wof:lang_x_official":[
        "ind"
    ],
    "wof:lang_x_spoken":[
        "ind",
        "eng"
    ],
    "wof:name":"Cangkuang",
    "wof:placetype":"locality"
},
  "geometry": {"coordinates":[108.7076,-6.8739],"type":"Point"}
}