{
  "type": "Feature",
  "properties": {
    "gn:admin1_code":"30.0",
    "gn:asciiname":"Senen",
    "gn:country_code":"ID",
    "gn:dem":52,
    "gn:feature_class":"P",
    "gn:feature_code":"PPL",
    "gn:name":"Senen",
    "gn:population":0,
    "gn:timezone":"Asia/Jakarta",
    "iso:country":"ID",
    "name:ceb_x_preferred":[
        "Kecamatan Senen"
    ],
    "name:ind_x_preferred":[
        "Senen"
    ],
    "name:jav_x_preferred":[
        "Sen\u00e8n"
    ],
    "name:nld_x_preferred":[
        "Senen"
    ],
    "name:pol_x_preferred":[
        "Senen"
    ],
    "name:sun_x_preferred":[
        "Sen\u00e9n"
    ],
    "name:swe_x_preferred":[
        "Kecamatan Senen"
    ],
    "wof:lang_x_official":[
        "ind"
    ],
    "wof:lang_x_spoken":[
        "ind",
        "eng"
    ],
    "wof:name":"Senen",
    "wof:placetype":"locality"
},
  "geometry": {"coordinates":[108.32917,-6.72611],"type":"Point"}
}