{
  "type": "Feature",
  "properties": {
    "gn:admin1_code":"8.0",
    "gn:asciiname":"Tegalkalong",
    "gn:country_code":"ID",
    "gn:dem":52,
    "gn:feature_class":"P",
    "gn:feature_code":"PPL",
    "gn:name":"Tegalkalong",
    "gn:population":0,
    "gn:timezone":"Asia/Jakarta",
    "iso:country":"ID",
    "name:ind_x_preferred":[
        "Tegalkalong"
    ],
    "wof:name":"Tegalkalong",
    "wof:placetype":"locality"
},
  "geometry": {"coordinates":[113.6161,-8.2903],"type":"Point"}
}