{
  "type": "Feature",
  "properties": {
    "gn:admin1_code":"22.0",
    "gn:asciiname":"Kanowela",
    "gn:country_code":"ID",
    "gn:dem":66,
    "gn:feature_class":"P",
    "gn:feature_code":"PPL",
    "gn:name":"Kanowela",
    "gn:population":0,
    "gn:timezone":"Asia/Makassar",
    "iso:country":"ID",
    "name:ind_x_preferred":[
        "Kanowela"
    ],
    "wof:name":"Kanowela",
    "wof:placetype":"locality"
},
  "geometry": {"coordinates":[122.5202,-4.8957],"type":"Point"}
}