{
  "type": "Feature",
  "properties": {
    "gn:admin1_code":"30",
    "gn:asciiname":"Ciremaigiri",
    "gn:country_code":"ID",
    "gn:dem":11,
    "gn:feature_class":"P",
    "gn:feature_code":"PPL",
    "gn:name":"Ciremaigiri",
    "gn:population":0,
    "gn:timezone":"Asia/Jakarta",
    "iso:country":"ID",
    "name:ind_x_preferred":[
        "Ciremaigiri"
    ],
    "wof:name":"Ciremaigiri",
    "wof:placetype":"locality"
},
  "geometry": {"coordinates":[108.5536,-6.7502],"type":"Point"}
}