{
  "type": "Feature",
  "properties": {
    "gn:admin1_code":"11",
    "gn:asciiname":"Kubupadi",
    "gn:country_code":"ID",
    "gn:dem":9,
    "gn:feature_class":"P",
    "gn:feature_code":"PPL",
    "gn:name":"Kubupadi",
    "gn:population":0,
    "gn:timezone":"Asia/Pontianak",
    "iso:country":"ID",
    "name:ind_x_preferred":[
        "Kubupadi"
    ],
    "wof:name":"Kubupadi",
    "wof:placetype":"locality"
},
  "geometry": {"coordinates":[109.42547,0.12666],"type":"Point"}
}