{
  "type": "Feature",
  "properties": {
    "gn:admin1_code":"07",
    "gn:asciiname":"Ngepas",
    "gn:country_code":"ID",
    "gn:dem":460,
    "gn:feature_class":"P",
    "gn:feature_code":"PPL",
    "gn:name":"Ngepas",
    "gn:population":0,
    "gn:timezone":"Asia/Jakarta",
    "iso:country":"ID",
    "wof:name":"Ngepas",
    "wof:placetype":"locality"
},
  "geometry": {"coordinates":[110.59278,-7.51917],"type":"Point"}
}