{
  "type": "Feature",
  "properties": {
    "gn:admin1_code":"7.0",
    "gn:asciiname":"Manon",
    "gn:country_code":"ID",
    "gn:dem":180,
    "gn:feature_class":"P",
    "gn:feature_code":"PPL",
    "gn:name":"Manon",
    "gn:population":0,
    "gn:timezone":"Asia/Jakarta",
    "iso:country":"ID",
    "wof:name":"Manon",
    "wof:placetype":"locality"
},
  "geometry": {"coordinates":[110.78139,-7.32361],"type":"Point"}
}