{
  "type": "Feature",
  "properties": {
    "gn:admin1_code":"7.0",
    "gn:asciiname":"Manon",
    "gn:country_code":"ID",
    "gn:dem":180,
    "gn:feature_class":"P",
    "gn:feature_code":"PPL",
    "gn:name":"Manon",
    "gn:population":0,
    "gn:timezone":"Asia/Jakarta",
    "iso:country":"ID",
    "name:cat_x_preferred":[
        "Manon"
    ],
    "name:ces_x_preferred":[
        "Manon"
    ],
    "name:deu_x_preferred":[
        "Manon"
    ],
    "name:ell_x_preferred":[
        "\u039c\u03b1\u03bd\u03cc\u03bd"
    ],
    "name:est_x_preferred":[
        "Manon"
    ],
    "name:fra_x_preferred":[
        "Manon"
    ],
    "name:hrv_x_preferred":[
        "Manon"
    ],
    "name:hun_x_preferred":[
        "Manon"
    ],
    "name:hye_x_preferred":[
        "\u0544\u0561\u0576\u0578\u0576"
    ],
    "name:ita_x_preferred":[
        "Manon"
    ],
    "name:jpn_x_preferred":[
        "\u30de\u30ce\u30f3"
    ],
    "name:nld_x_preferred":[
        "Manon"
    ],
    "name:pol_x_preferred":[
        "Manon"
    ],
    "name:por_x_preferred":[
        "Manon"
    ],
    "name:rus_x_preferred":[
        "\u041c\u0430\u043d\u043e\u043d"
    ],
    "name:slv_x_preferred":[
        "Manon"
    ],
    "name:spa_x_preferred":[
        "Manon"
    ],
    "name:swe_x_preferred":[
        "Manon"
    ],
    "name:ukr_x_preferred":[
        "\u041c\u0430\u043d\u043e\u043d"
    ],
    "name:vie_x_preferred":[
        "Manon"
    ],
    "wof:lang_x_official":[
        "ind"
    ],
    "wof:lang_x_spoken":[
        "ind",
        "eng"
    ],
    "wof:name":"Manon",
    "wof:placetype":"locality"
},
  "geometry": {"coordinates":[110.78139,-7.32361],"type":"Point"}
}