{
  "type": "Feature",
  "properties": {
    "gn:admin1_code":"22",
    "gn:asciiname":"Lambandia",
    "gn:country_code":"ID",
    "gn:dem":59,
    "gn:feature_class":"P",
    "gn:feature_code":"PPL",
    "gn:name":"Lambandia",
    "gn:population":0,
    "gn:timezone":"Asia/Makassar",
    "iso:country":"ID",
    "name:ind_x_preferred":[
        "Lambandia"
    ],
    "wof:name":"Lambandia",
    "wof:placetype":"locality"
},
  "geometry": {"coordinates":[121.9117,-4.2618],"type":"Point"}
}