{
  "type": "Feature",
  "properties": {
    "gn:admin1_code":"7.0",
    "gn:asciiname":"Dongdong",
    "gn:country_code":"ID",
    "gn:dem":312,
    "gn:feature_class":"P",
    "gn:feature_code":"PPL",
    "gn:name":"Dongdong",
    "gn:population":0,
    "gn:timezone":"Asia/Jakarta",
    "iso:country":"ID",
    "name:ind_x_preferred":[
        "Dongdong"
    ],
    "wof:name":"Dongdong",
    "wof:placetype":"locality"
},
  "geometry": {"coordinates":[110.78583,-8.09083],"type":"Point"}
}