{
  "type": "Feature",
  "properties": {
    "gn:admin1_code":"30.0",
    "gn:asciiname":"Padalarang",
    "gn:cc2":"ID",
    "gn:country_code":"ID",
    "gn:dem":691,
    "gn:feature_class":"P",
    "gn:feature_code":"PPL",
    "gn:name":"Padalarang",
    "gn:population":0,
    "gn:timezone":"Asia/Jakarta",
    "iso:country":"ID",
    "name:ind_x_preferred":[
        "Padalarang"
    ],
    "name:und_x_variant":[
        "Chipadalarang"
    ],
    "wof:lang_x_official":[
        "ind"
    ],
    "wof:lang_x_spoken":[
        "ind",
        "eng"
    ],
    "wof:name":"Padalarang",
    "wof:placetype":"locality"
},
  "geometry": {"coordinates":[107.48472,-6.8425],"type":"Point"}
}