{
  "type": "Feature",
  "properties": {
    "gn:admin1_code":"2",
    "gn:asciiname":"Banjar Bebalang",
    "gn:country_code":"ID",
    "gn:dem":373,
    "gn:feature_class":"P",
    "gn:feature_code":"PPLA4",
    "gn:name":"Banjar Bebalang",
    "gn:population":0,
    "gn:timezone":"Asia/Makassar",
    "iso:country":"ID",
    "name:ind_x_preferred":[
        "Banjar Bebalang"
    ],
    "wof:lang_x_official":[
        "ind"
    ],
    "wof:lang_x_spoken":[
        "ind",
        "eng"
    ],
    "wof:name":"Banjar Bebalang",
    "wof:placetype":"locality"
},
  "geometry": {"coordinates":[115.35299999999999,-8.4718],"type":"Point"}
}