{
  "type": "Feature",
  "properties": {
    "gn:admin1_code":"10",
    "gn:asciiname":"Purbayan",
    "gn:country_code":"ID",
    "gn:dem":84,
    "gn:feature_class":"P",
    "gn:feature_code":"PPL",
    "gn:name":"Purbayan",
    "gn:population":0,
    "gn:timezone":"Asia/Jakarta",
    "iso:country":"ID",
    "wof:name":"Purbayan",
    "wof:placetype":"locality"
},
  "geometry": {"coordinates":[110.405,-7.83278],"type":"Point"}
}