{
  "type": "Feature",
  "properties": {
    "gn:admin1_code":"30",
    "gn:asciiname":"Jangari",
    "gn:country_code":"ID",
    "gn:dem":231,
    "gn:feature_class":"P",
    "gn:feature_code":"PPL",
    "gn:name":"Jangari",
    "gn:population":0,
    "gn:timezone":"Asia/Jakarta",
    "iso:country":"ID",
    "name:ind_x_preferred":[
        "Jangari"
    ],
    "wof:name":"Jangari",
    "wof:placetype":"locality"
},
  "geometry": {"coordinates":[107.26111000000002,-6.75111],"type":"Point"}
}